Workbook

Sheet CORNEJO ESTELA
B2: CORNEJO DONATO DE CORDOVA ESTELA PILAR
A4: FECHA | B4: DOCUMENTO | C4: PERIODO | D4: CONCEPTO | E4: POR COBRAR | F4: PAGADO | G4: SALDO POR COBRAR
A5: 42736 | B5: SALDO AL 2016 | G5: 1045.3
A6: 42740 | B6: 12074 | C6: A CUENTA 2016 | F6: 8 | G6: =+G5+E6-F6 -> 1037.3
A7: 42804 | B7: 12414 | C7: A CUENTA 2016 | F7: 66.9 | G7: =+G6+E7-F7 -> 970.4
A8: 42787 | B8: 12339 | C8: A CUENTA 2016 | F8: 50.3 | G8: =+G7+E8-F8 -> 920.1
A9: 42763 | B9: TARJETA | C9: A CUENTA 2016 | F9: 80 | G9: =+G8+E9-F9 -> 840.1
A10: 42794 | B10: TARJETA | C10: A CUENTA 2016 | F10: 197 | G10: =+G9+E10-F10 -> 643.1
A11: 42802 | B11: TARJETA | C11: A CUENTA 2016 | F11: 43.1 | G11: =+G10+E11-F11 -> 600
A12: 42804 | B12: 12413 | C12: A CUENTA 2016 | F12: 600 | G12: =+G11+E12-F12 -> 0
A13: 42766 | B13: POR COBRAR | C13: ENERO | D13: LUZ | E13: 22 | G13: =+G12+E13-F13 -> 22
D14: AGUA | E14: 2.8 | G14: =+G13+E14-F14 -> 24.8
D15: G. ADM | E15: 60 | G15: =+G14+E15-F15 -> 84.8
D16: P. SOCIAL | E16: 2 | G16: =+G15+E16-F16 -> 86.8
D17: DEPOSITO | E17: 55 | G17: =+G16+E17-F17 -> 141.8
D18: P.S. FALLEC. | E18: 10 | G18: =+G17+E18-F18 -> 151.8
A19: 42763 | B19: TARJETA | C19: ENERO | D19: G. ADM | F19: 56 | G19: =+G18+E19-F19 -> 95.8
A20: 42804 | B20: 12413 | C20: ENERO | D20: DEPOSITO | F20: 55 | G20: =+G19+E20-F20 -> 40.8
A21: 42787 | B21: 12339 | C21: ENERO | D21: LUZ | F21: 22 | G21: =+G20+E21-F21 -> 18.8
A22: 42787 | B22: 12339 | C22: ENERO | D22: AGUA | F22: 2.8 | G22: =+G21+E22-F22 -> 16
A23: 42787 | B23: 12339 | C23: ENERO | D23: P.S. FALLEC. | F23: 10 | G23: =+G22+E23-F23 -> 6
A24: 42769 | B24: 12910 | C24: ENERO | D24: P. SOCIAL | F24: 2 | G24: =+G23+E24-F24 -> 4
A25: 42773 | B25: 12926 | C25: ENERO | D25: G. ADM | F25: 4 | G25: =+G24+E25-F25 -> 1.0658141e-14
A26: 42794 | B26: POR COBRAR | C26: FEBRERO | D26: LUZ | E26: 21.8 | G26: =+G25+E26-F26 -> 21.8
D27: AGUA | E27: 2 | G27: =+G26+E27-F27 -> 23.8
D28: G. ADM | E28: 56 | G28: =+G27+E28-F28 -> 79.8
D29: P. SOCIAL | E29: 2 | G29: =+G28+E29-F29 -> 81.8
D30: DEPOSITO | E30: 55 | G30: =+G29+E30-F30 -> 136.8
A31: 42794 | B31: TARJETA | C31: FEBRERO | D31: DEPOSITO | F31: 2 | G31: =+G30+E31-F31 -> 134.8
A32: 42794 | B32: TARJETA | C32: FEBRERO | D32: G. ADM | F32: 56 | G32: =+G31+E32-F32 -> 78.8
A33: 42794 | B33: TARJETA | C33: FEBRERO | D33: P. SOCIAL | F33: 2 | G33: =+G32+E33-F33 -> 76.8
A34: 42825 | B34: TARJETA | C34: FEBRERO | D34: DEPOSITO | F34: 20.9 | G34: =+G33+E34-F34 -> 55.9
A35: 42804 | B35: 12413 | C35: FEBRERO | D35: DEPOSITO | F35: 32.1 | G35: =+G34+E35-F35 -> 23.8
A36: 42818 | B36: 12464 | C36: FEBRERO | D36: LUZ | F36: 21.8 | G36: =+G35+E36-F36 -> 2
A37: 42818 | B37: 12464 | C37: FEBRERO | D37: AGUA | F37: 2 | G37: =+G36+E37-F37 -> 1.0658141e-14
A38: 42825 | B38: POR COBRAR | C38: MARZO | D38: LUZ | E38: 20.5 | G38: =+G37+E38-F38 -> 20.5
D39: AGUA | E39: 2 | G39: =+G38+E39-F39 -> 22.5
D40: G. ADM | E40: 60 | G40: =+G39+E40-F40 -> 82.5
D41: P. SOCIAL | E41: 2 | G41: =+G40+E41-F41 -> 84.5
D42: DEPOSITO | E42: 55 | F42: 0 | G42: =+G41+E42-F42 -> 139.5
A43: 42824 | B43: TARJETA | C43: MARZO | D43: G. ADM | F43: 60 | G43: =+G42+E43-F43 -> 79.5
A44: 42824 | B44: TARJETA | C44: MARZO | D44: P. SOCIAL | F44: 2 | G44: =+G43+E44-F44 -> 77.5
A45: 42885 | B45: 13001 | C45: MARZO | D45: LUZ | F45: 20.5 | G45: =+G44+E45-F45 -> 57
A46: 42885 | B46: 13001 | C46: MARZO | D46: AGUA | F46: 2 | G46: =+G45+E46-F46 -> 55
A47: 42885 | B47: 13001 | C47: MARZO | D47: DEPOSITO | F47: 55 | G47: =+G46+E47-F47 -> 0
A48: 42855 | B48: POR COBRAR | C48: ABRIL | D48: LUZ | E48: 21.6 | G48: =+G47+E48-F48 -> 21.6
D49: AGUA | E49: 2 | G49: =+G48+E49-F49 -> 23.6
D50: G. ADM | E50: 60 | G50: =+G49+E50-F50 -> 83.6
D51: P. SOCIAL | E51: 2 | G51: =+G50+E51-F51 -> 85.6
D52: DEPOSITO | E52: 55 | G52: =+G51+E52-F52 -> 140.6
A53: 42824 | B53: TARJETA | C53: ABRIL | D53: G. ADM | F53: 60 | G53: =+G52+E53-F53 -> 80.6
A54: 42824 | B54: TARJETA | C54: ABRIL | D54: P. SOCIAL | F54: 2 | G54: =+G53+E54-F54 -> 78.6
A55: 42885 | B55: 13001 | C55: ABRIL | D55: LUZ | F55: 21.6 | G55: =+G54+E55-F55 -> 57
A56: 42885 | B56: 13001 | C56: ABRIL | D56: AGUA | F56: 2 | G56: =+G55+E56-F56 -> 55
A57: 42885 | B57: 13001 | C57: ABRIL | D57: DEPOSITO | F57: 55 | G57: =+G56+E57-F57 -> 0
A58: 42886 | B58: POR COBRAR | C58: MAYO | D58: LUZ | E58: 26.9 | G58: =+G57+E58-F58 -> 26.9
D59: AGUA | E59: 2 | G59: =+G58+E59-F59 -> 28.9
D60: G. ADM | E60: 60 | G60: =+G59+E60-F60 -> 88.9
D61: P. SOCIAL | E61: 2 | G61: =+G60+E61-F61 -> 90.9
D62: DEPOSITO | E62: 55 | G62: =+G61+E62-F62 -> 145.9
A63: 42886 | B63: TARJETA | C63: MAYO | D63: G. ADM | F63: 60 | G63: =+G62+E63-F63 -> 85.9
A64: 42886 | B64: TARJETA | C64: MAYO | D64: P. SOCIAL | F64: 2 | G64: =+G63+E64-F64 -> 83.9
A65: 42950 | B65: 13395 | C65: MAYO | D65: LUZ | F65: 26.9 | G65: =+G64+E65-F65 -> 57
A66: 42950 | B66: 13395 | C66: MAYO | D66: AGUA | F66: 2 | G66: =+G65+E66-F66 -> 55
A67: 42950 | B67: 13395 | C67: MAYO | D67: DEPOSITO | F67: 55 | G67: =+G66+E67-F67 -> 0
A68: 42916 | B68: POR COBRAR | C68: JUNIO | D68: LUZ | E68: 26.1 | G68: =+G67+E68-F68 -> 26.1
D69: AGUA | E69: 2 | G69: =+G68+E69-F69 -> 28.1
D70: G. ADM | E70: 60 | G70: =+G69+E70-F70 -> 88.1
D71: P. SOCIAL | E71: 2 | G71: =+G70+E71-F71 -> 90.1
D72: DEPOSITO | E72: 55 | G72: =+G71+E72-F72 -> 145.1
A73: 42913 | B73: TARJETA | C73: JUNIO | D73: G. ADM | F73: 50 | G73: =+G72+E73-F73 -> 95.1
A74: 42950 | B74: 13395 | C74: JUNIO | D74: G. ADM | F74: 10 | G74: =+G73+E74-F74 -> 85.1
A75: 42950 | B75: 13395 | C75: JUNIO | D75: P. SOCIAL | F75: 2 | G75: =+G74+E75-F75 -> 83.1
A76: 42950 | B76: 13395 | C76: JUNIO | D76: LUZ | F76: 26.1 | G76: =+G75+E76-F76 -> 57
A77: 42950 | B77: 13395 | C77: JUNIO | D77: AGUA | F77: 2 | G77: =+G76+E77-F77 -> 55
A78: 42950 | B78: 13395 | C78: JUNIO | D78: DEPOSITO | F78: 55 | G78: =+G77+E78-F78 -> 0
A79: 42947 | B79: POR COBRAR | C79: JULIO | D79: LUZ | E79: 24.9 | G79: =+G78+E79-F79 -> 24.9
D80: AGUA | E80: 2 | G80: =+G79+E80-F80 -> 26.9
D81: G. ADM | E81: 60 | G81: =+G80+E81-F81 -> 86.9
D82: P. SOCIAL | E82: 2 | G82: =+G81+E82-F82 -> 88.9
D83: DEPOSITO | E83: 55 | G83: =+G82+E83-F83 -> 143.9
A84: 42947 | B84: TARJETA | C84: JULIO | D84: G. ADM | F84: 60 | G84: =+G83+E84-F84 -> 83.9
A85: 42947 | B85: TARJETA | C85: JULIO | D85: P. SOCIAL | F85: 2 | G85: =+G84+E85-F85 -> 81.9
A86: 42971 | B86: 13479 | C86: JULIO | D86: LUZ | F86: 24.9 | G86: =+G85+E86-F86 -> 57
A87: 42971 | B87: 13479 | C87: JULIO | D87: AGUA | F87: 2 | G87: =+G86+E87-F87 -> 55
A88: 42950 | B88: 13395 | C88: JULIO | D88: DEPOSITO | F88: 55 | G88: =+G87+E88-F88 -> 0
A89: 42978 | B89: POR COBRAR | C89: AGOSTO | D89: LUZ | E89: 24.9 | G89: =+G88+E89-F89 -> 24.9
D90: AGUA | E90: 2 | G90: =+G89+E90-F90 -> 26.9
D91: G. ADM | E91: 60 | G91: =+G90+E91-F91 -> 86.9
D92: P. SOCIAL | E92: 2 | G92: =+G91+E92-F92 -> 88.9
D93: DEPOSITO | E93: 55 | G93: =+G92+E93-F93 -> 143.9
A94: 42978 | B94: TARJETA | C94: AGOSTO | D94: G. ADM | F94: 60 | G94: =+G93+E94-F94 -> 83.9
A95: 42978 | B95: TARJETA | C95: AGOSTO | D95: P. SOCIAL | F95: 2 | G95: =+G94+E95-F95 -> 81.9
A96: 43021 | B96: 13826 | C96: AGOSTO | D96: LUZ | F96: 24.9 | G96: =+G95+E96-F96 -> 57
A97: 43021 | B97: 13826 | C97: AGOSTO | D97: AGUA | F97: 2 | G97: =+G96+E97-F97 -> 55
A98: 43021 | B98: 13826 | C98: AGOSTO | D98: DEPOSITO | F98: 55 | G98: =+G97+E98-F98 -> 0
A99: 43008 | B99: POR COBRAR | C99: SEPTIEMBRE | D99: LUZ | E99: 21.3 | G99: =+G98+E99-F99 -> 21.3
D100: AGUA | E100: 2 | G100: =+G99+E100-F100 -> 23.3
D101: G. ADM | E101: 60 | G101: =+G100+E101-F101 -> 83.3
D102: P. SOCIAL | E102: 2 | G102: =+G101+E102-F102 -> 85.3
...

Sheet CRUZ LUIS
B2: CRUZ JARAMILLO LUIS
A4: FECHA | B4: DOCUMENTO | C4: PERIODO | D4: CONCEPTO | E4: POR COBRAR | F4: PAGADO | G4: SALDO POR COBRAR
A5: 42736 | B5: SALDO AL 2016 | G5: 152.2
A6: 42739 | B6: 12061 | C6: A CUENTA 2016 | F6: 73.5 | G6: =+G5+E6-F6 -> 78.7
A7: 42763 | B7: 12173 | C7: A CUENTA 2016 | F7: 78.7 | G7: =+G6+E7-F7 -> 0
A8: 42766 | B8: POR COBRAR | C8: ENERO | D8: LUZ | E8: 79.2 | G8: =+G7+E8-F8 -> 79.2
D9: AGUA | E9: 2.8 | G9: =+G8+E9-F9 -> 82
D10: G. ADM | E10: 60 | G10: =+G9+E10-F10 -> 142
D11: P. SOCIAL | E11: 2 | G11: =+G10+E11-F11 -> 144
A12: 42765 | B12: TARJETA | C12: ENERO | D12: G. ADM | F12: 60 | G12: =+G11+E12-F12 -> 84
A13: 42765 | B13: TARJETA | C13: ENERO | D13: P. SOCIAL | F13: 2 | G13: =+G12+E13-F13 -> 82
A14: 42784 | B14: 12990 | C14: ENERO | D14: LUZ | F14: 79.2 | G14: =+G13+E14-F14 -> 2.8
A15: 42784 | B15: 12990 | C15: ENERO | D15: AGUA | F15: 2.8 | G15: =+G14+E15-F15 -> 0
A16: 42794 | B16: POR COBRAR | C16: FEBRERO | D16: LUZ | E16: 76 | G16: =+G15+E16-F16 -> 76
D17: AGUA | E17: 2 | G17: =+G16+E17-F17 -> 78
D18: G. ADM | E18: 56 | G18: =+G17+E18-F18 -> 134
D19: P. SOCIAL | E19: 2 | G19: =+G18+E19-F19 -> 136
D20: P.S. FALLEC. | E20: 10 | G20: =+G19+E20-F20 -> 146
A21: 42783 | B21: 12974 | C21: FEBRERO | D21: P.S. FALLEC. | F21: 10 | G21: =+G20+E21-F21 -> 136
A22: 42794 | B22: TARJETA | C22: FEBRERO | D22: G. ADM | F22: 56 | G22: =+G21+E22-F22 -> 80
A23: 42794 | B23: TARJETA | C23: FEBRERO | D23: P. SOCIAL | F23: 2 | G23: =+G22+E23-F23 -> 78
A24: 42818 | B24: 12456 | C24: FEBRERO | D24: LUZ | F24: 76 | G24: =+G23+E24-F24 -> 2
A25: 42818 | B25: 12456 | C25: FEBRERO | D25: AGUA | F25: 2 | G25: =+G24+E25-F25 -> 0
A26: 42825 | B26: POR COBRAR | C26: MARZO | D26: LUZ | E26: 72.7 | G26: =+G25+E26-F26 -> 72.7
D27: AGUA | E27: 2 | G27: =+G26+E27-F27 -> 74.7
D28: G. ADM | E28: 60 | G28: =+G27+E28-F28 -> 134.7
D29: P. SOCIAL | E29: 2 | G29: =+G28+E29-F29 -> 136.7
A30: 42824 | B30: TARJETA | C30: MARZO | D30: G. ADM | F30: 60 | G30: =+G29+E30-F30 -> 76.7
A31: 42824 | B31: TARJETA | C31: MARZO | D31: P. SOCIAL | F31: 2 | G31: =+G30+E31-F31 -> 74.7
A32: 42845 | B32: 12664 | C32: MARZO | D32: AGUA | F32: 2 | G32: =+G31+E32-F32 -> 72.7
A33: 42845 | B33: 12664 | C33: MARZO | D33: LUZ | F33: 72.7 | G33: =+G32+E33-F33 -> 0
A34: 42855 | B34: POR COBRAR | C34: ABRIL | D34: LUZ | E34: 74.3 | G34: =+G33+E34-F34 -> 74.3
D35: AGUA | E35: 2 | G35: =+G34+E35-F35 -> 76.3
D36: G. ADM | E36: 60 | G36: =+G35+E36-F36 -> 136.3
D37: P. SOCIAL | E37: 2 | G37: =+G36+E37-F37 -> 138.3
A38: 42855 | B38: TARJETA | C38: ABRIL | D38: G. ADM | F38: 60 | G38: =+G37+E38-F38 -> 78.3
A39: 42855 | B39: TARJETA | C39: ABRIL | D39: P. SOCIAL | F39: 2 | G39: =+G38+E39-F39 -> 76.3
A40: 42878 | B40: 12803 | C40: ABRIL | D40: LUZ | F40: 74.3 | G40: =+G39+E40-F40 -> 2
A41: 42878 | B41: 12803 | C41: ABRIL | D41: AGUA | F41: 2 | G41: =+G40+E41-F41 -> 1.4210855e-14
A42: 42886 | B42: POR COBRAR | C42: MAYO | D42: LUZ | E42: 69.4 | G42: =+G41+E42-F42 -> 69.4
D43: AGUA | E43: 2 | G43: =+G42+E43-F43 -> 71.4
D44: G. ADM | E44: 60 | G44: =+G43+E44-F44 -> 131.4
D45: P. SOCIAL | E45: 2 | G45: =+G44+E45-F45 -> 133.4
A46: 42885 | B46: TARJETA | C46: MAYO | D46: G. ADM | F46: 60 | G46: =+G45+E46-F46 -> 73.4
A47: 42885 | B47: TARJETA | C47: MAYO | D47: P. SOCIAL | F47: 2 | G47: =+G46+E47-F47 -> 71.4
A48: 42908 | B48: 13128 | C48: MAYO | D48: LUZ | F48: 69.4 | G48: =+G47+E48-F48 -> 2
A49: 42908 | B49: 13128 | C49: MAYO | D49: AGUA | F49: 2 | G49: =+G48+E49-F49 -> 2.8421709e-14
A50: 42916 | B50: POR COBRAR | C50: JUNIO | D50: LUZ | E50: 67.8 | G50: =+G49+E50-F50 -> 67.8
D51: AGUA | E51: 2 | G51: =+G50+E51-F51 -> 69.8
D52: G. ADM | E52: 60 | G52: =+G51+E52-F52 -> 129.8
D53: P. SOCIAL | E53: 2 | G53: =+G52+E53-F53 -> 131.8
A54: 42916 | B54: TARJETA | C54: JUNIO | D54: G. ADM | F54: 60 | G54: =+G53+E54-F54 -> 71.8
A55: 42916 | B55: TARJETA | C55: JUNIO | D55: P. SOCIAL | F55: 2 | G55: =+G54+E55-F55 -> 69.8
A56: 42936 | B56: 13224 | C56: JUMIO | D56: LUZ | F56: 67.8 | G56: =+G55+E56-F56 -> 2
A57: 42936 | B57: 13224 | C57: JUNIO | D57: AGUA | F57: 2 | G57: =+G56+E57-F57 -> 1.4210855e-14
A58: 42947 | B58: POR COBRAR | C58: JULIO | D58: LUZ | E58: 61.5 | G58: =+G57+E58-F58 -> 61.5
D59: AGUA | E59: 2 | G59: =+G58+E59-F59 -> 63.5
D60: G. ADM | E60: 60 | G60: =+G59+E60-F60 -> 123.5
D61: P. SOCIAL | E61: 2 | G61: =+G60+E61-F61 -> 125.5
A62: 42947 | B62: TARJETA | C62: JULIO | D62: G. ADM | F62: 60 | G62: =+G61+E62-F62 -> 65.5
A63: 42947 | B63: TARJETA | C63: JULIO | D63: P. SOCIAL | F63: 2 | G63: =+G62+E63-F63 -> 63.5
A64: 42972 | B64: 13487 | C64: JULIO | D64: LUZ | F64: 61.5 | G64: =+G63+E64-F64 -> 2
A65: 42972 | B65: 13487 | C65: JULIO | D65: AGUA | F65: 2 | G65: =+G64+E65-F65 -> 1.4210855e-14
A66: 42978 | B66: POR COBRAR | C66: AGOSTO | D66: LUZ | E66: 61.5 | G66: =+G65+E66-F66 -> 61.5
D67: AGUA | E67: 2 | G67: =+G66+E67-F67 -> 63.5
D68: G. ADM | E68: 60 | G68: =+G67+E68-F68 -> 123.5
D69: P. SOCIAL | E69: 2 | G69: =+G68+E69-F69 -> 125.5
A70: 42978 | B70: TARJETA | C70: AGOSTO | D70: G. ADM | F70: 60 | G70: =+G69+E70-F70 -> 65.5
A71: 42978 | B71: TARJETA | C71: AGOSTO | D71: P. SOCIAL | F71: 2 | G71: =+G70+E71-F71 -> 63.5
A72: 42997 | B72: 13608 | C72: AGOSTO | D72: LUZ | F72: 61.5 | G72: =+G71+E72-F72 -> 2
A73: 42997 | B73: 13608 | C73: AGOSTO | D73: AGUA | F73: 2 | G73: =+G72+E73-F73 -> 1.4210855e-14
A74: 43008 | B74: POR COBRAR | C74: SEPTIEMBRE | D74: LUZ | E74: 71.6 | G74: =+G73+E74-F74 -> 71.6
D75: AGUA | E75: 1.3 | G75: =+G74+E75-F75 -> 72.9
D76: G. ADM | E76: 60 | G76: =+G75+E76-F76 -> 132.9
D77: P. SOCIAL | E77: 2 | G77: =+G76+E77-F77 -> 134.9
A78: 43008 | B78: TARJETA | C78: SEPTIEMBRE | D78: G. ADM | F78: 60 | G78: =+G77+E78-F78 -> 74.9
A79: 43008 | B79: TARJETA | C79: SEPTIEMBRE | D79: P. SOCIAL | F79: 2 | G79: =+G78+E79-F79 -> 72.9
A80: 43031 | B80: 13856 | C80: SEPTIEMBRE | D80: LUZ | F80: 71.6 | G80: =+G79+E80-F80 -> 1.3
A81: 43031 | B81: 13856 | C81: SEPTIEMBRE | D81: AGUA | F81: 1.3 | G81: =+G80+E81-F81 -> 1.1324275e-14
A82: 43039 | B82: POR COBRAR | C82: OCTUBRE | D82: LUZ | E82: 71.2 | G82: =+G81+E82-F82 -> 71.2
D83: AGUA | E83: 2.7 | G83: =+G82+E83-F83 -> 73.9
D84: G. ADM | E84: 60 | G84: =+G83+E84-F84 -> 133.9
D85: P. SOCIAL | E85: 2 | G85: =+G84+E85-F85 -> 135.9
A86: 43039 | B86: TARJETA | C86: OCTUBRE | D86: G. ADM | F86: 60 | G86: =+G85+E86-F86 -> 75.9
A87: 43039 | B87: TARJETA | C87: OCTUBRE | D87: P. SOCIAL | F87: 2 | G87: =+G86+E87-F87 -> 73.9
A88: 43062 | B88: 14003 | C88: OCTUBRE | D88: LUZ | F88: 71.2 | G88: =+G87+E88-F88 -> 2.7
A89: 43062 | B89: 14003 | C89: OCTUBRE | D89: AGUA | F89: 2.7 | G89: =+G88+E89-F89 -> 3.1086245e-14
A90: 43069 | B90: POR COBRAR | C90: NOVIEMBRE | D90: LUZ | E90: 76 | G90: =+G89+E90-F90 -> 76
D91: AGUA | E91: 2 | G91: =+G90+E91-F91 -> 78
D92: G. ADM | E92: 60 | G92: =+G91+E92-F92 -> 138
D93: P. SOCIAL | E93: 2 | G93: =+G92+E93-F93 -> 140
A94: 43087 | B94: 14234 | C94: NOVIEMBRE | D94: LUZ | F94: 76 | G94: =+G93+E94-F94 -> 64
A95: 43087 | B95: 14234 | C95: NOVIEMBRE | D95: AGUA | F95: 2 | G95: =+G94+E95-F95 -> 62
A96: 43069 | B96: TARJETA | C96: NOVIEMBRE | D96: G. ADM | F96: 60 | G96: =+G95+E96-F96 -> 2
A97: 43069 | B97: TARJETA | C97: NOVIEMBRE | D97: P. SOCIAL | F97: 2 | G97: =+G96+E97-F97 -> 2.8421709e-14
A98: 43100 | B98: POR COBRAR | C98: DICIEMBRE | D98: LUZ | E98: 82.7 | G98: =+G97+E98-F98 -> 82.7
D99: AGUA | E99: 2 | G99: =+G98+E99-F99 -> 84.7
D100: G. ADM | E100: 60 | G100: =+G99+E100-F100 -> 144.7
D101: P. SOCIAL | E101: 2 | G101: =+G100+E101-F101 -> 146.7
A102: 43099 | B102: TARJETA | C102: DICIEMBRE | D102: G. ADM | F102: 60 | G102: =+G101+E102-F102 -> 86.7
...

Sheet CUCHO SAUL
B2: CUCHO DE LA CRUZ SAUL
A4: FECHA | B4: DOCUMENTO | C4: PERIODO | D4: CONCEPTO | E4: POR COBRAR | F4: PAGADO | G4: SALDO POR COBRAR
A5: 42736 | B5: SALDO AL 2016 | G5: 217
A6: 42786 | B6: 12241 | C6: A CUENTA 2016 | F6: 217 | G6: =+G5+E6-F6 -> 0
A7: 42766 | B7: POR COBRAR | C7: ENERO | D7: LUZ | E7: 107.1 | G7: =+G6+E7-F7 -> 107.1
D8: AGUA | E8: 2.8 | G8: =+G7+E8-F8 -> 109.9
D9: G. ADM | E9: 60 | G9: =+G8+E9-F9 -> 169.9
D10: P. SOCIAL | E10: 2 | G10: =+G9+E10-F10 -> 171.9
A11: 42765 | B11: TARJETA | C11: ENERO | D11: G. ADM | F11: 60 | G11: =+G10+E11-F11 -> 111.9
A12: 42765 | B12: TARJETA | C12: ENERO | D12: P. SOCIAL | F12: 2 | G12: =+G11+E12-F12 -> 109.9
A13: 42786 | B13: 12241 | C13: ENERO | D13: AGUA | F13: 2.8 | G13: =+G12+E13-F13 -> 107.1
A14: 42786 | B14: 12241 | C14: ENERO | D14: LUZ | F14: 107.1 | G14: =+G13+E14-F14 -> 0
A15: 42794 | B15: POR COBRAR | C15: FEBRERO | D15: LUZ | E15: 110.2 | G15: =+G14+E15-F15 -> 110.2
D16: AGUA | E16: 2 | G16: =+G15+E16-F16 -> 112.2
D17: G. ADM | E17: 56 | G17: =+G16+E17-F17 -> 168.2
D18: P. SOCIAL | E18: 2 | G18: =+G17+E18-F18 -> 170.2
A19: 42794 | B19: TARJETA | C19: ENERO | D19: G. ADM | F19: 56 | G19: =+G18+E19-F19 -> 114.2
A20: 42794 | B20: TARJETA | C20: ENERO | D20: P. SOCIAL | F20: 2 | G20: =+G19+E20-F20 -> 112.2
A21: 42828 | B21: 12626 | C21: FEBRERO | D21: AGUA | F21: 2 | G21: =+G20+E21-F21 -> 110.2
A22: 42828 | B22: 12626 | C22: FEBRERO | D22: LUZ | F22: 110.2 | G22: =+G21+E22-F22 -> 0
A23: 42825 | B23: POR COBRAR | C23: MARZO | D23: LUZ | E23: 105.7 | G23: =+G22+E23-F23 -> 105.7
D24: AGUA | E24: 2 | G24: =+G23+E24-F24 -> 107.7
D25: G. ADM | E25: 60 | G25: =+G24+E25-F25 -> 167.7
D26: P. SOCIAL | E26: 2 | G26: =+G25+E26-F26 -> 169.7
D27: MULTA | E27: 85 | G27: =+G26+E27-F27 -> 254.7
A28: 42824 | B28: TARJETA | C28: MARZO | D28: G. ADM | F28: 105.7 | G28: =+G27+E28-F28 -> 149
A29: 42885 | B29: 12885 | C29: MARZO | D29: LUZ | F29: 50 | G29: =+G28+E29-F29 -> 99
A30: 42885 | B30: 12885 | C30: MARZO | D30: AGUA | F30: 2 | G30: =+G29+E30-F30 -> 97
A31: 42948 | B31: 13298 | C31: MARZO | D31: G. ADM | F31: 10 | G31: =+G30+E31-F31 -> 87
A32: 42948 | B32: 13298 | C32: MARZO | D32: P. SOCIAL | F32: 2 | G32: =+G31+E32-F32 -> 85
A33: 42948 | B33: 13298 | C33: MARZO | D33: MULTA | F33: 85 | G33: =+G32+E33-F33 -> 0
A34: 42855 | B34: POR COBRAR | C34: ABRIL | D34: LUZ | E34: 107.6 | G34: =+G33+E34-F34 -> 107.6
D35: AGUA | E35: 2 | G35: =+G34+E35-F35 -> 109.6
D36: G. ADM | E36: 60 | G36: =+G35+E36-F36 -> 169.6
D37: P. SOCIAL | E37: 2 | G37: =+G36+E37-F37 -> 171.6
A38: 42855 | B38: TARJETA | C38: ABRIL | D38: G. ADM | F38: 60 | G38: =+G37+E38-F38 -> 111.6
A39: 42855 | B39: TARJETA | C39: ABRIL | D39: P. SOCIAL | F39: 2 | G39: =+G38+E39-F39 -> 109.6
A40: 42885 | B40: 12885 | C40: ABRIL | D40: LUZ | F40: 107.6 | G40: =+G39+E40-F40 -> 2
A41: 42885 | B41: 12885 | C41: ABRIL | D41: AGUA | F41: 2 | G41: =+G40+E41-F41 -> 0
A42: 42886 | B42: POR COBRAR | C42: MAYO | D42: LUZ | E42: 100.1 | G42: =+G41+E42-F42 -> 100.1
D43: AGUA | E43: 2 | G43: =+G42+E43-F43 -> 102.1
D44: G. ADM | E44: 60 | G44: =+G43+E44-F44 -> 162.1
D45: P. SOCIAL | E45: 2 | G45: =+G44+E45-F45 -> 164.1
A46: 42886 | B46: TARJETA | C46: MAYO | D46: G. ADM | F46: 60 | G46: =+G45+E46-F46 -> 104.1
A47: 42886 | B47: TARJETA | C47: MAYO | D47: P. SOCIAL | F47: 2 | G47: =+G46+E47-F47 -> 102.1
A48: 42916 | B48: 13171 | C48: MAYO | D48: LUZ | F48: 100.1 | G48: =+G47+E48-F48 -> 2
A49: 42916 | B49: 13171 | C49: MAYO | D49: AGUA | F49: 2 | G49: =+G48+E49-F49 -> 0
A50: 42916 | B50: POR COBRAR | C50: JUNIO | D50: LUZ | E50: 97.9 | G50: =+G49+E50-F50 -> 97.9
D51: AGUA | E51: 2 | G51: =+G50+E51-F51 -> 99.9
D52: G. ADM | E52: 60 | G52: =+G51+E52-F52 -> 159.9
D53: P. SOCIAL | E53: 2 | G53: =+G52+E53-F53 -> 161.9
A54: 42916 | B54: TARJETA | C54: JUNIO | D54: G. ADM | F54: 60 | G54: =+G53+E54-F54 -> 101.9
A55: 42916 | B55: TARJETA | C55: JUNIO | D55: P. SOCIAL | F55: 2 | G55: =+G54+E55-F55 -> 99.9
A56: 42948 | B56: 13298 | C56: JUNIO | D56: LUZ | F56: 97.9 | G56: =+G55+E56-F56 -> 2
A57: 42948 | B57: 13298 | C57: JUNIO | D57: AGUA | F57: 2 | G57: =+G56+E57-F57 -> 0
A58: 42947 | B58: POR COBRAR | C58: JULIO | D58: LUZ | E58: 87.8 | G58: =+G57+E58-F58 -> 87.8
D59: AGUA | E59: 2 | G59: =+G58+E59-F59 -> 89.8
D60: G. ADM | E60: 60 | G60: =+G59+E60-F60 -> 149.8
D61: P. SOCIAL | E61: 2 | G61: =+G60+E61-F61 -> 151.8
D62: P. SOCIAL X FALL. | E62: 10 | G62: =+G61+E62-F62 -> 161.8
A63: 42947 | B63: TARJETA | C63: JULIO | D63: G. ADM | F63: 60 | G63: =+G62+E63-F63 -> 101.8
A64: 42947 | B64: TARJETA | C64: JULIO | D64: P. SOCIAL | F64: 2 | G64: =+G63+E64-F64 -> 99.8
A65: 42948 | B65: 13298 | C65: JULIO | D65: P. SOCIAL X FALL. | F65: 10 | G65: =+G64+E65-F65 -> 89.8
A66: 42996 | B66: 13597 | C66: JULIO | D66: LUZ | F66: 87.8 | G66: =+G65+E66-F66 -> 2
A67: 42996 | B67: 13597 | C67: JULIO | D67: AGUA | F67: 2 | G67: =+G66+E67-F67 -> 1.4210855e-14
A68: 42978 | B68: POR COBRAR | C68: AGOSTO | D68: LUZ | E68: 87.8 | G68: =+G67+E68-F68 -> 87.8
D69: AGUA | E69: 2 | G69: =+G68+E69-F69 -> 89.8
D70: G. ADM | E70: 60 | G70: =+G69+E70-F70 -> 149.8
D71: P. SOCIAL | E71: 2 | G71: =+G70+E71-F71 -> 151.8
A72: 42978 | B72: TARJETA | C72: AGOSTO | D72: G. ADM | F72: 60 | G72: =+G71+E72-F72 -> 91.8
A73: 42978 | B73: TARJETA | C73: AGOSTO | D73: P. SOCIAL | F73: 2 | G73: =+G72+E73-F73 -> 89.8
A74: 42996 | B74: 13597 | C74: JULIO | D74: LUZ | F74: 87.8 | G74: =+G73+E74-F74 -> 2
A75: 42996 | B75: 13597 | C75: JULIO | D75: AGUA | F75: 2 | G75: =+G74+E75-F75 -> 1.4210855e-14
A76: 43008 | B76: POR COBRAR | C76: SEPTIEMBRE | D76: LUZ | E76: 100.6 | G76: =+G75+E76-F76 -> 100.6
D77: AGUA | E77: 2 | G77: =+G76+E77-F77 -> 102.6
D78: G. ADM | E78: 60 | G78: =+G77+E78-F78 -> 162.6
D79: P. SOCIAL | E79: 2 | G79: =+G78+E79-F79 -> 164.6
A80: 43008 | B80: TARJETA | C80: SEPTIEMBRE | D80: G. ADM | F80: 60 | G80: =+G79+E80-F80 -> 104.6
A81: 43008 | B81: TARJETA | C81: SEPTIEMBRE | D81: P. SOCIAL | F81: 2 | G81: =+G80+E81-F81 -> 102.6
A82: 43038 | B82: 13901 | C82: SEPTIEMBRE | D82: LUZ | F82: 100.6 | G82: =+G81+E82-F82 -> 2
A83: 43038 | B83: 13901 | C83: SEPTIEMBRE | D83: AGUA | F83: 2 | G83: =+G82+E83-F83 -> 2.8421709e-14
A84: 43039 | B84: POR COBRAR | C84: OCTUBRE | D84: LUZ | E84: 100 | G84: =+G83+E84-F84 -> 100
D85: AGUA | E85: 2 | G85: =+G84+E85-F85 -> 102
D86: G. ADM | E86: 60 | G86: =+G85+E86-F86 -> 162
D87: P. SOCIAL | E87: 2 | G87: =+G86+E87-F87 -> 164
A88: 43039 | B88: TARJETA | C88: OCTUBRE | D88: G. ADM | F88: 60 | G88: =+G87+E88-F88 -> 104
A89: 43039 | B89: TARJETA | C89: OCTUBRE | D89: P. SOCIAL | F89: 2 | G89: =+G88+E89-F89 -> 102
A90: 43067 | B90: 14123 | C90: OCTUBRE | D90: LUZ | F90: 100 | G90: =+G89+E90-F90 -> 2
A91: 43067 | B91: 14123 | C91: OCTUBRE | D91: AGUA | F91: 2 | G91: =+G90+E91-F91 -> 2.8421709e-14
A92: 43069 | B92: POR COBRAR | C92: NOVIEMBRE | D92: LUZ | E92: 106.8 | G92: =+G91+E92-F92 -> 106.8
D93: AGUA | E93: 2 | G93: =+G92+E93-F93 -> 108.8
D94: G. ADM | E94: 60 | G94: =+G93+E94-F94 -> 168.8
D95: P. SOCIAL | E95: 2 | G95: =+G94+E95-F95 -> 170.8
A96: 43095 | B96: 14348 | C96: NOVIEMBRE | D96: LUZ | F96: 106.8 | G96: =+G95+E96-F96 -> 64
A97: 43095 | B97: 14348 | C97: NOVIEMBRE | D97: AGUA | F97: 2 | G97: =+G96+E97-F97 -> 62
A98: 43069 | B98: TARJETA | C98: NOVIEMBRE | D98: G. ADM | F98: 40 | G98: =+G97+E98-F98 -> 22
A99: 43155 | B99: 14729 | C99: NOVIEMBRE | D99: G. ADM | F99: 20 | G99: =+G98+E99-F99 -> 2
A100: 43155 | B100: 14729 | C100: NOVIEMBRE | D100: P. SOCIAL | F100: 2 | G100: =+G99+E100-F100 -> 1.4210855e-14
A101: 43100 | B101: POR COBRAR | C101: DICIEMBRE | D101: LUZ | E101: 116.2 | G101: =+G100+E101-F101 -> 116.2
D102: AGUA | E102: 2 | G102: =+G101+E102-F102 -> 118.2
...

Sheet CUEVAS ENRIQUE
B2: CUEVAS MAYO ENRIQUE
A4: FECHA | B4: DOCUMENTO | C4: PERIODO | D4: CONCEPTO | E4: POR COBRAR | F4: PAGADO | G4: SALDO POR COBRAR
A5: 42736 | B5: SALDO AL 2016 | G5: 288.7
A6: 42768 | B6: 12193 | C6: A CUENTA 2016 | F6: 282.7 | G6: =+G5+E6-F6 -> 6
A7: 42768 | B7: 12194 | C7: A CUENTA 2016 | F7: 6 | G7: =+G6+E7-F7 -> 0
A8: 42766 | B8: POR COBRAR | C8: ENERO | D8: LUZ | E8: 120.6 | G8: =+G7+E8-F8 -> 120.6
D9: AGUA | E9: 2.8 | G9: =+G8+E9-F9 -> 123.4
D10: G. ADM | E10: 60 | G10: =+G9+E10-F10 -> 183.4
D11: P. SOCIAL | E11: 2 | G11: =+G10+E11-F11 -> 185.4
A12: 42768 | B12: 12193 | C12: ENERO | D12: G. ADM | F12: 60 | G12: =+G11+E12-F12 -> 125.4
A13: 42768 | B13: 12193 | C13: ENERO | D13: P. SOCIAL | F13: 2 | G13: =+G12+E13-F13 -> 123.4
A14: 42822 | B14: 12584 | C14: ENERO | D14: AGUA | F14: 2.8 | G14: =+G13+E14-F14 -> 120.6
A15: 42822 | B15: 12584 | C15: ENERO | D15: LUZ | F15: 120.6 | G15: =+G14+E15-F15 -> 0
A16: 42794 | B16: POR COBRAR | C16: FEBRERO | D16: LUZ | E16: 123.2 | G16: =+G15+E16-F16 -> 123.2
D17: AGUA | E17: 2 | G17: =+G16+E17-F17 -> 125.2
D18: G. ADM | E18: 56 | G18: =+G17+E18-F18 -> 181.2
D19: P. SOCIAL | E19: 2 | G19: =+G18+E19-F19 -> 183.2
A20: 42822 | B20: 12579 | C20: FEBRERO | D20: G. ADM | F20: 56 | G20: =+G19+E20-F20 -> 127.2
A21: 42822 | B21: 12579 | C21: FEBRERO | D21: P. SOCIAL | F21: 2 | G21: =+G20+E21-F21 -> 125.2
A22: 42822 | B22: 12579 | C22: FEBRERO | D22: AGUA | F22: 2 | G22: =+G21+E22-F22 -> 123.2
A23: 42822 | B23: 12579 | C23: FEBRERO | D23: LUZ | F23: 123.2 | G23: =+G22+E23-F23 -> 0
A24: 42825 | B24: POR COBRAR | C24: MARZO | D24: LUZ | E24: 117.7 | G24: =+G23+E24-F24 -> 117.7
D25: AGUA | E25: 2 | G25: =+G24+E25-F25 -> 119.7
D26: G. ADM | E26: 60 | G26: =+G25+E26-F26 -> 179.7
D27: P. SOCIAL | E27: 2 | G27: =+G26+E27-F27 -> 181.7
A28: 42854 | B28: 12708 | C28: MARZO | D28: LUZ | F28: 2 | G28: =+G27+E28-F28 -> 179.7
A29: 42854 | B29: 12708 | C29: MARZO | D29: AGUA | F29: 117.7 | G29: =+G28+E29-F29 -> 62
A30: 42854 | B30: 12708 | C30: MARZO | D30: P. SOCIAL | F30: 2 | G30: =+G29+E30-F30 -> 60
A31: 42854 | B31: 12708 | C31: MARZO | D31: G. ADM | F31: 60 | G31: =+G30+E31-F31 -> 0
A32: 42855 | B32: POR COBRAR | C32: ABRIL | D32: LUZ | E32: 120.6 | G32: =+G31+E32-F32 -> 120.6
D33: AGUA | E33: 2 | G33: =+G32+E33-F33 -> 122.6
D34: G. ADM | E34: 60 | G34: =+G33+E34-F34 -> 182.6
D35: P. SOCIAL | E35: 2 | G35: =+G34+E35-F35 -> 184.6
A36: 42885 | B36: 12867 | C36: ABRIL | D36: G. ADM | F36: 60 | G36: =+G35+E36-F36 -> 124.6
A37: 42885 | B37: 12867 | C37: ABRIL | D37: P. SOCIAL | F37: 2 | G37: =+G36+E37-F37 -> 122.6
A38: 42885 | B38: 12867 | C38: ABRIL | D38: LUZ | F38: 120.6 | G38: =+G37+E38-F38 -> 2
A39: 42885 | B39: 12867 | C39: ABRIL | D39: AGUA | F39: 2 | G39: =+G38+E39-F39 -> 0
A40: 42886 | B40: POR COBRAR | C40: MAYO | D40: LUZ | E40: 109.2 | G40: =+G39+E40-F40 -> 109.2
D41: AGUA | E41: 2 | G41: =+G40+E41-F41 -> 111.2
D42: G. ADM | E42: 60 | G42: =+G41+E42-F42 -> 171.2
D43: P. SOCIAL | E43: 2 | G43: =+G42+E43-F43 -> 173.2
A44: 42885 | B44: 12867 | C44: MAYO | D44: G. ADM | F44: 60 | G44: =+G43+E44-F44 -> 113.2
A45: 42885 | B45: 12867 | C45: MAYO | D45: P. SOCIAL | F45: 2 | G45: =+G44+E45-F45 -> 111.2
A46: 42909 | B46: 13143 | C46: MAYO | D46: AGUA | F46: 2 | G46: =+G45+E46-F46 -> 109.2
A47: 42909 | B47: 13143 | C47: MAYO | D47: LUZ | F47: 109.2 | G47: =+G46+E47-F47 -> 0
A48: 42916 | B48: POR COBRAR | C48: JUNIO | D48: LUZ | E48: 106.6 | G48: =+G47+E48-F48 -> 106.6
D49: AGUA | E49: 2 | G49: =+G48+E49-F49 -> 108.6
D50: G. ADM | E50: 60 | G50: =+G49+E50-F50 -> 168.6
D51: P. SOCIAL | E51: 2 | G51: =+G50+E51-F51 -> 170.6
A52: 42952 | B52: 13423 | C52: JUNIO | D52: G. ADM | F52: 60 | G52: =+G51+E52-F52 -> 110.6
A53: 42952 | B53: 13423 | C53: JUNIO | D53: P. SOCIAL | F53: 2 | G53: =+G52+E53-F53 -> 108.6
A54: 42952 | B54: 13423 | C54: JUNIO | D54: LUZ | F54: 106.6 | G54: =+G53+E54-F54 -> 2
A55: 42952 | B55: 13423 | C55: JUNIO | D55: AGUA | F55: 2 | G55: =+G54+E55-F55 -> 0
A56: 42947 | B56: POR COBRAR | C56: JULIO | D56: LUZ | E56: 100.8 | G56: =+G55+E56-F56 -> 100.8
D57: AGUA | E57: 2 | G57: =+G56+E57-F57 -> 102.8
D58: G. ADM | E58: 60 | G58: =+G57+E58-F58 -> 162.8
D59: P. SOCIAL | E59: 2 | G59: =+G58+E59-F59 -> 164.8
A60: 42952 | B60: 13423 | C60: JULIO | D60: G. ADM | F60: 60 | G60: =+G59+E60-F60 -> 104.8
A61: 42952 | B61: 13423 | C61: JULIO | D61: P. SOCIAL | F61: 2 | G61: =+G60+E61-F61 -> 102.8
A62: 42975 | B62: 13512 | C62: JULIO | D62: LUZ | F62: 100.8 | G62: =+G61+E62-F62 -> 2
A63: 42975 | B63: 13512 | C63: JULIO | D63: AGUA | F63: 2 | G63: =+G62+E63-F63 -> 1.4210855e-14
A64: 42978 | B64: POR COBRAR | C64: AGOSTO | D64: LUZ | E64: 100.8 | G64: =+G63+E64-F64 -> 100.8
D65: AGUA | E65: 2 | G65: =+G64+E65-F65 -> 102.8
D66: G. ADM | E66: 60 | G66: =+G65+E66-F66 -> 162.8
D67: P. SOCIAL | E67: 2 | G67: =+G66+E67-F67 -> 164.8
D68: MULTA | E68: 85 | G68: =+G67+E68-F68 -> 249.8
A69: 42975 | B69: 13512 | C69: AGOSTO | D69: G. ADM | F69: 60 | G69: =+G68+E69-F69 -> 189.8
A70: 42975 | B70: 13512 | C70: AGOSTO | D70: P. SOCIAL | F70: 2 | G70: =+G69+E70-F70 -> 187.8
A71: 42987 | B71: 13561 | C71: AGOSTO | D71: LUZ | F71: 100.8 | G71: =+G70+E71-F71 -> 87
A72: 42987 | B72: 13561 | C72: AGOSTO | D72: AGUA | F72: 2 | G72: =+G71+E72-F72 -> 85
A73: 43029 | B73: 13846 | C73: AGOSTO | D73: MULTA | F73: 85 | G73: =+G72+E73-F73 -> 0
A74: 43008 | B74: POR COBRAR | C74: SEPTIEMBRE | D74: LUZ | E74: 48.4 | G74: =+G73+E74-F74 -> 48.4
D75: AGUA | E75: 1.3 | G75: =+G74+E75-F75 -> 49.7
D76: G. ADM | E76: 60 | G76: =+G75+E76-F76 -> 109.7
D77: P. SOCIAL | E77: 2 | G77: =+G76+E77-F77 -> 111.7
A78: 42998 | B78: 13634 | C78: SEPTIEMBRE | D78: G. ADM | F78: 60 | G78: =+G77+E78-F78 -> 51.7
A79: 42998 | B79: 13634 | C79: SEPTIEMBRE | D79: P. SOCIAL | F79: 2 | G79: =+G78+E79-F79 -> 49.7
A80: 43029 | B80: 13845 | C80: SEPTIEMBRE | D80: AGUA | F80: 1.3 | G80: =+G79+E80-F80 -> 48.4
A81: 43029 | B81: 13845 | C81: SEPTIEMBRE | D81: LUZ | F81: 48.4 | G81: =+G80+E81-F81 -> 0
A82: 43039 | B82: POR COBRAR | C82: OCTUBRE | D82: LUZ | E82: 48.1 | G82: =+G81+E82-F82 -> 48.1
D83: AGUA | E83: 2 | G83: =+G82+E83-F83 -> 50.1
D84: G. ADM | E84: 60 | G84: =+G83+E84-F84 -> 110.1
D85: P. SOCIAL | E85: 2 | G85: =+G84+E85-F85 -> 112.1
A86: 43063 | B86: 14029 | C86: OCTUBRE | D86: LUZ | F86: 48.1 | G86: =+G85+E86-F86 -> 64
A87: 43063 | B87: 14029 | C87: OCTUBRE | D87: AGUA | F87: 2 | G87: =+G86+E87-F87 -> 62
A88: 43064 | B88: 14088 | C88: OCTUBRE | D88: G. ADM | F88: 60 | G88: =+G87+E88-F88 -> 2
A89: 43064 | B89: 14088 | C89: OCTUBRE | D89: P. SOCIAL | F89: 2 | G89: =+G88+E89-F89 -> -7.1054274e-15
A90: 43069 | B90: POR COBRAR | C90: NOVIEMBRE | D90: LUZ | E90: 51.3 | G90: =+G89+E90-F90 -> 51.3
D91: AGUA | E91: 2 | G91: =+G90+E91-F91 -> 53.3
D92: G. ADM | E92: 60 | G92: =+G91+E92-F92 -> 113.3
D93: P. SOCIAL | E93: 2 | G93: =+G92+E93-F93 -> 115.3
A94: 43088 | B94: 14310 | C94: NOVIEMBRE | D94: LUZ | F94: 51.3 | G94: =+G93+E94-F94 -> 64
A95: 43088 | B95: 14310 | C95: NOVIEMBRE | D95: AGUA | F95: 2 | G95: =+G94+E95-F95 -> 62
A96: 43088 | B96: 14311 | C96: NOVIEMBRE | D96: G. ADM | F96: 60 | G96: =+G95+E96-F96 -> 2
A97: 43088 | B97: 14311 | C97: NOVIEMBRE | D97: P. SOCIAL | F97: 2 | G97: =+G96+E97-F97 -> -1.4210855e-14
A98: 43100 | B98: POR COBRAR | C98: DICIEMBRE | D98: LUZ | E98: 55.9 | G98: =+G97+E98-F98 -> 55.9
D99: AGUA | E99: 2 | G99: =+G98+E99-F99 -> 57.9
D100: G. ADM | E100: 60 | G100: =+G99+E100-F100 -> 117.9
D101: P. SOCIAL | E101: 2 | G101: =+G100+E101-F101 -> 119.9
A102: 43088 | B102: 14311 | C102: DICIEMBRE | D102: G. ADM | F102: 60 | G102: =+G101+E102-F102 -> 59.9
...

Sheet CULE HAYDEE
B2: CULE CARRASCO HAYDEE MONICA
A4: FECHA | B4: DOCUMENTO | C4: PERIODO | D4: CONCEPTO | E4: POR COBRAR | F4: PAGADO | G4: SALDO POR COBRAR
A5: 42736 | B5: SALDO AL 2016 | G5: 495.1
A6: 42736 | B6: AGUA R. | E6: 9 | G6: =+G5+E6-F6 -> 504.1
A7: 42763 | B7: TARJETA | C7: A CUENTA DEL 2016 | F7: 60 | G7: =+G6+E7-F7 -> 444.1
A8: 42794 | B8: TARJETA | C8: A CUENTA DEL 2016 | F8: 445 | G8: =+G7+E8-F8 -> -0.9
A9: 42766 | B9: POR COBRAR | C9: ENERO | D9: LUZ | E9: 113.5 | G9: =+G8+E9-F9 -> 112.6
D10: AGUA | E10: 50 | G10: =+G9+E10-F10 -> 162.6
D11: G. ADM | E11: 60 | G11: =+G10+E11-F11 -> 222.6
D12: P. SOCIAL | E12: 2 | G12: =+G11+E12-F12 -> 224.6
D13: PS X FALLEC | E13: 10 | G13: =+G12+E13-F13 -> 234.6
A14: 42763 | B14: TARJETA | C14: ENERO | D14: G. ADM | F14: 24 | G14: =+G13+E14-F14 -> 210.6
A15: 42763 | B15: TARJETA | C15: ENERO | D15: LUZ | F15: 36 | G15: =+G14+E15-F15 -> 174.6
A16: 42809 | B16: 12421 | C16: ENERO | D16: G. ADM | F16: 35.1 | G16: =+G15+E16-F16 -> 139.5
A17: 42809 | B17: 12421 | C17: ENERO | D17: P. SOCIAL | F17: 2 | G17: =+G16+E17-F17 -> 137.5
A18: 42809 | B18: 12421 | C18: ENERO | D18: LUZ | F18: 77.5 | G18: =+G17+E18-F18 -> 60
A19: 42809 | B19: 12421 | C19: ENERO | D19: AGUA | F19: 50 | G19: =+G18+E19-F19 -> 10
A20: 42809 | B20: 12421 | C20: ENERO | D20: PS X FALLEC | F20: 10 | G20: =+G19+E20-F20 -> 2.8421709e-14
A21: 42794 | B21: POR COBRAR | C21: FEBRERO | D21: LUZ | E21: 118 | G21: =+G20+E21-F21 -> 118
D22: AGUA | E22: 35 | G22: =+G21+E22-F22 -> 153
D23: G. ADM | E23: 56 | G23: =+G22+E23-F23 -> 209
D24: P. SOCIAL | E24: 2 | G24: =+G23+E24-F24 -> 211
A25: 42794 | B25: TARJETA | C25: FEBRERO | D25: G. ADM | F25: 18 | G25: =+G24+E25-F25 -> 193
A26: 42794 | B26: TARJETA | C26: FEBRERO | D26: LUZ | F26: 27 | G26: =+G25+E26-F26 -> 166
A27: 42809 | B27: 12421 | C27: FEBRERO | D27: G. ADM | F27: 38 | G27: =+G26+E27-F27 -> 128
A28: 42809 | B28: 12421 | C28: FEBRERO | D28: P. SOCIAL | F28: 2 | G28: =+G27+E28-F28 -> 126
A29: 42822 | B29: 12600 | C29: FEBRERO | D29: LUZ | F29: 91 | G29: =+G28+E29-F29 -> 35
A30: 42822 | B30: 12600 | C30: FEBRERO | D30: AGUA | F30: 35 | G30: =+G29+E30-F30 -> 0
A31: 42825 | B31: POR COBRAR | C31: MARZO | D31: LUZ | E31: 116.2 | G31: =+G30+E31-F31 -> 116.2
D32: AGUA | E32: 36 | G32: =+G31+E32-F32 -> 152.2
D33: G. ADM | E33: 60 | G33: =+G32+E33-F33 -> 212.2
D34: P. SOCIAL | E34: 2 | G34: =+G33+E34-F34 -> 214.2
A35: 42823 | B35: TARJETA | C35: MARZO | D35: G. ADM | F35: 26 | G35: =+G34+E35-F35 -> 188.2
A36: 42823 | B36: TARJETA | C36: MARZO | D36: LUZ | F36: 104 | G36: =+G35+E36-F36 -> 84.2
A37: 42898 | B37: 13094 | C37: MARZO | D37: LUZ | F37: 12.2 | G37: =+G36+E37-F37 -> 72
A38: 42898 | B38: 13094 | C38: MARZO | D38: AGUA | F38: 36 | G38: =+G37+E38-F38 -> 36
A39: 42950 | B39: 13410 | C39: MARZO | D39: G. ADM | F39: 2 | G39: =+G38+E39-F39 -> 34
A40: 42950 | B40: 13410 | C40: MARZO | D40: P. SOCIAL | F40: 34 | G40: =+G39+E40-F40 -> 0
A41: 42855 | B41: POR COBRAR | C41: ABRIL | D41: LUZ | E41: 115 | G41: =+G40+E41-F41 -> 115
D42: AGUA | E42: 36.8 | G42: =+G41+E42-F42 -> 151.8
D43: G. ADM | E43: 60 | G43: =+G42+E43-F43 -> 211.8
D44: P. SOCIAL | E44: 2 | G44: =+G43+E44-F44 -> 213.8
A45: 42854 | B45: TARJETA | C45: ABRIL | D45: G. ADM | F45: 60 | G45: =+G44+E45-F45 -> 153.8
A46: 42854 | B46: TARJETA | C46: ABRIL | D46: P. SOCIAL | F46: 2 | G46: =+G45+E46-F46 -> 151.8
A47: 42854 | B47: TARJETA | C47: ABRIL | D47: LUZ | F47: 90 | G47: =+G46+E47-F47 -> 61.8
A48: 42898 | B48: 13094 | C48: ABRIL | D48: LUZ | F48: 25 | G48: =+G47+E48-F48 -> 36.8
A49: 42898 | B49: 13094 | C49: ABRIL | D49: AGUA | F49: 36.8 | G49: =+G48+E49-F49 -> 0
A50: 42886 | B50: POR COBRAR | C50: MAYO | D50: LUZ | E50: 97.2 | G50: =+G49+E50-F50 -> 97.2
D51: AGUA | E51: 35.1 | G51: =+G50+E51-F51 -> 132.3
D52: G. ADM | E52: 60 | G52: =+G51+E52-F52 -> 192.3
D53: P. SOCIAL | E53: 2 | G53: =+G52+E53-F53 -> 194.3
A54: 42884 | B54: TARJETA | C54: MAYO | D54: G. ADM | F54: 60 | G54: =+G53+E54-F54 -> 134.3
A55: 42884 | B55: TARJETA | C55: MAYO | D55: P. SOCIAL | F55: 2 | G55: =+G54+E55-F55 -> 132.3
A56: 42884 | B56: TARJETA | C56: MAYO | D56: LUZ | F56: 60 | G56: =+G55+E56-F56 -> 72.3
A57: 42950 | B57: 13410 | C57: MAYO | D57: LUZ | F57: 37.2 | G57: =+G56+E57-F57 -> 35.1
A58: 42950 | B58: 13410 | C58: MAYO | D58: AGUA | F58: 35.1 | G58: =+G57+E58-F58 -> 0
A59: 42916 | B59: POR COBRAR | C59: JUNIO | D59: LUZ | E59: 80.5 | G59: =+G58+E59-F59 -> 80.5
D60: AGUA | E60: 35.5 | G60: =+G59+E60-F60 -> 116
D61: G. ADM | E61: 60 | G61: =+G60+E61-F61 -> 176
D62: P. SOCIAL | E62: 2 | G62: =+G61+E62-F62 -> 178
A63: 42916 | B63: TARJETA | C63: JUNIO | D63: G. ADM | F63: 60 | G63: =+G62+E63-F63 -> 118
A64: 42916 | B64: TARJETA | C64: JUNIO | D64: P. SOCIAL | F64: 2 | G64: =+G63+E64-F64 -> 116
A65: 42916 | B65: TARJETA | C65: JUNIO | D65: LUZ | F65: 80.5 | G65: =+G64+E65-F65 -> 35.5
A66: 42916 | B66: TARJETA | C66: JUNIO | D66: AGUA | F66: 19.5 | G66: =+G65+E66-F66 -> 16
A67: 42950 | B67: 13410 | C67: JUNIO | D67: AGUA | F67: 16 | G67: =+G66+E67-F67 -> 0
A68: 42947 | B68: POR COBRAR | C68: JULIO | D68: LUZ | E68: 93.8 | G68: =+G67+E68-F68 -> 93.8
D69: AGUA | E69: 35 | G69: =+G68+E69-F69 -> 128.8
D70: G. ADM | E70: 60 | G70: =+G69+E70-F70 -> 188.8
D71: P. SOCIAL | E71: 2 | G71: =+G70+E71-F71 -> 190.8
A72: 42928 | B72: TARJETA | C72: JULIO | D72: G. ADM | F72: 60 | G72: =+G71+E72-F72 -> 130.8
A73: 42928 | B73: TARJETA | C73: JULIO | D73: P. SOCIAL | F73: 2 | G73: =+G72+E73-F73 -> 128.8
A74: 42947 | B74: TARJETA | C74: JULIO | D74: LUZ | F74: 80 | G74: =+G73+E74-F74 -> 48.8
A75: 43008 | B75: TARJETA | C75: JULIO | D75: LUZ | F75: 13.8 | G75: =+G74+E75-F75 -> 35
A76: 43008 | B76: TARJETA | C76: JULIO | D76: AGUA | F76: 35 | G76: =+G75+E76-F76 -> 0
A77: 42978 | B77: POR COBRAR | C77: AGOSTO | D77: LUZ | E77: 93.8 | G77: =+G76+E77-F77 -> 93.8
D78: AGUA | E78: 35 | G78: =+G77+E78-F78 -> 128.8
D79: G. ADM | E79: 60 | G79: =+G78+E79-F79 -> 188.8
D80: P. SOCIAL | E80: 2 | G80: =+G79+E80-F80 -> 190.8
A81: 42978 | B81: TARJETA | C81: AGOSTO | D81: G. ADM | F81: 60 | G81: =+G80+E81-F81 -> 130.8
A82: 42978 | B82: TARJETA | C82: AGOSTO | D82: P. SOCIAL | F82: 2 | G82: =+G81+E82-F82 -> 128.8
A83: 43008 | B83: TARJETA | C83: AGOSTO | D83: LUZ | F83: 31.2 | G83: =+G82+E83-F83 -> 97.6
A84: 43039 | B84: TARJETA | C84: AGOSTO | D84: LUZ | F84: 62.6 | G84: =+G83+E84-F84 -> 35
A85: 43039 | B85: TARJETA | C85: AGOSTO | D85: AGUA | F85: 35 | G85: =+G84+E85-F85 -> 0
A86: 43008 | B86: POR COBRAR | C86: SEPTIEMBRE | D86: LUZ | E86: 79.3 | G86: =+G85+E86-F86 -> 79.3
D87: AGUA | E87: 35.1 | G87: =+G86+E87-F87 -> 114.4
D88: G. ADM | E88: 60 | G88: =+G87+E88-F88 -> 174.4
D89: P. SOCIAL | E89: 2 | G89: =+G88+E89-F89 -> 176.4
A90: 43008 | B90: TARJETA | C90: SEPTIEMBRE | D90: G. ADM | F90: 60 | G90: =+G89+E90-F90 -> 116.4
A91: 43008 | B91: TARJETA | C91: SEPTIEMBRE | D91: P. SOCIAL | F91: 2 | G91: =+G90+E91-F91 -> 114.4
A92: 43039 | B92: TARJETA | C92: SEPTIEMBRE | D92: LUZ | F92: 40.4 | G92: =+G91+E92-F92 -> 74
A93: 43068 | B93: 14211 | C93: SEPTIEMBRE | D93: LUZ | F93: 38.9 | G93: =+G92+E93-F93 -> 35.1
A94: 43068 | B94: 14211 | C94: SEPTIEMBRE | D94: AGUA | F94: 35.1 | G94: =+G93+E94-F94 -> 0
A95: 43039 | B95: POR COBRAR | C95: OCTUBRE | D95: LUZ | E95: 78.9 | G95: =+G94+E95-F95 -> 78.9
D96: AGUA | E96: 35.1 | G96: =+G95+E96-F96 -> 114
D97: G. ADM | E97: 60 | G97: =+G96+E97-F97 -> 174
D98: P. SOCIAL | E98: 2 | G98: =+G97+E98-F98 -> 176
A99: 43039 | B99: TARJETA | C99: OCTUBRE | D99: G. ADM | F99: 60 | G99: =+G98+E99-F99 -> 116
A100: 43039 | B100: TARJETA | C100: OCTUBRE | D100: P. SOCIAL | F100: 2 | G100: =+G99+E100-F100 -> 114
A101: 43068 | B101: 14211 | C101: OCTUBRE | D101: LUZ | F101: 78.9 | G101: =+G100+E101-F101 -> 35.1
A102: 43068 | B102: 14211 | C102: OCTUBRE | D102: AGUA | F102: 35.1 | G102: =+G101+E102-F102 -> 0
...

Sheet CUSI SONIA
B2: CUSI LAURA SONIA
A4: FECHA | B4: DOCUMENTO | C4: PERIODO | D4: CONCEPTO | E4: POR COBRAR | F4: PAGADO | G4: SALDO POR COBRAR
A5: 42736 | B5: SALDO AL 2016 | G5: 31.9
A6: 42762 | B6: 12170 | C6: A CUENTA 2016 | F6: 31.9 | G6: =+G5+E6-F6 -> 0
A7: 42766 | B7: POR COBRAR | C7: ENERO | D7: LUZ | E7: 28.5 | G7: =+G6+E7-F7 -> 28.5
D8: AGUA | E8: 3 | G8: =+G7+E8-F8 -> 31.5
D9: G. ADM | E9: 60 | G9: =+G8+E9-F9 -> 91.5
D10: P. SOCIAL | E10: 2 | G10: =+G9+E10-F10 -> 93.5
A11: 42765 | B11: TARJETA | C11: ENERO | D11: G. ADM | F11: 60 | G11: =+G10+E11-F11 -> 33.5
A12: 42765 | B12: TARJETA | C12: ENERO | D12: P. SOCIAL | F12: 2 | G12: =+G11+E12-F12 -> 31.5
A13: 42783 | B13: 12981 | C13: ENERO | D13: LUZ | F13: 28.5 | G13: =+G12+E13-F13 -> 3
A14: 42783 | B14: 12981 | C14: ENERO | D14: AGUA | F14: 3 | G14: =+G13+E14-F14 -> 0
A15: 42794 | B15: POR COBRAR | C15: FEBRERO | D15: LUZ | E15: 28.5 | G15: =+G14+E15-F15 -> 28.5
D16: AGUA | E16: 2 | G16: =+G15+E16-F16 -> 30.5
D17: G. ADM | E17: 56 | G17: =+G16+E17-F17 -> 86.5
D18: P. SOCIAL | E18: 2 | G18: =+G17+E18-F18 -> 88.5
D19: MULTA | E19: 85 | G19: =+G18+E19-F19 -> 173.5
A20: 42789 | B20: 12361 | C20: FEBRERO | D20: MULTA | F20: 85 | G20: =+G19+E20-F20 -> 88.5
A21: 42794 | B21: TARJETA | C21: FEBRERO | D21: G. ADM | F21: 56 | G21: =+G20+E21-F21 -> 32.5
A22: 42794 | B22: TARJETA | C22: FEBRERO | D22: P. SOCIAL | F22: 2 | G22: =+G21+E22-F22 -> 30.5
A23: 42821 | B23: 12522 | C23: FEBRERO | D23: LUZ | F23: 28.5 | G23: =+G22+E23-F23 -> 2
A24: 42821 | B24: 12522 | C24: FEBRERO | D24: AGUA | F24: 2 | G24: =+G23+E24-F24 -> 0
A25: 42825 | B25: POR COBRAR | C25: MARZO | D25: LUZ | E25: 26.9 | G25: =+G24+E25-F25 -> 26.9
D26: AGUA | E26: 2 | G26: =+G25+E26-F26 -> 28.9
D27: G. ADM | E27: 60 | G27: =+G26+E27-F27 -> 88.9
D28: P. SOCIAL | E28: 2 | G28: =+G27+E28-F28 -> 90.9
A29: 42824 | B29: TARJETA | C29: MARZO | D29: G. ADM | F29: 60 | G29: =+G28+E29-F29 -> 30.9
A30: 42824 | B30: TARJETA | C30: MARZO | D30: P. SOCIAL | F30: 2 | G30: =+G29+E30-F30 -> 28.9
A31: 42845 | B31: 12665 | C31: MARZO | D31: LUZ | F31: 26.9 | G31: =+G30+E31-F31 -> 2
A32: 42845 | B32: 12665 | C32: MARZO | D32: AGUA | F32: 2 | G32: =+G31+E32-F32 -> 7.1054274e-15
A33: 42855 | B33: POR COBRAR | C33: ABRIL | D33: LUZ | E33: 28.1 | G33: =+G32+E33-F33 -> 28.1
D34: AGUA | E34: 2 | G34: =+G33+E34-F34 -> 30.1
D35: G. ADM | E35: 60 | G35: =+G34+E35-F35 -> 90.1
D36: P. SOCIAL | E36: 2 | G36: =+G35+E36-F36 -> 92.1
A37: 42854 | B37: TARJETA | C37: ABRIL | D37: G. ADM | F37: 60 | G37: =+G36+E37-F37 -> 32.1
A38: 42854 | B38: TARJETA | C38: ABRIL | D38: P. SOCIAL | F38: 2 | G38: =+G37+E38-F38 -> 30.1
A39: 42874 | B39: 12777 | C39: ABRIL | D39: LUZ | F39: 28.1 | G39: =+G38+E39-F39 -> 2
A40: 42874 | B40: 12777 | C40: ABRIL | D40: AGUA | F40: 2 | G40: =+G39+E40-F40 -> 7.1054274e-15
A41: 42886 | B41: POR COBRAR | C41: MAYO | D41: LUZ | E41: 26.9 | G41: =+G40+E41-F41 -> 26.9
D42: AGUA | E42: 2 | G42: =+G41+E42-F42 -> 28.9
D43: G. ADM | E43: 60 | G43: =+G42+E43-F43 -> 88.9
D44: P. SOCIAL | E44: 2 | G44: =+G43+E44-F44 -> 90.9
A45: 42885 | B45: TARJETA | C45: MAYO | D45: G. ADM | F45: 60 | G45: =+G44+E45-F45 -> 30.9
A46: 42885 | B46: TARJETA | C46: MAYO | D46: P. SOCIAL | F46: 2 | G46: =+G45+E46-F46 -> 28.9
A47: 42907 | B47: 13119 | C47: MAYO | D47: LUZ | F47: 26.9 | G47: =+G46+E47-F47 -> 2
A48: 42907 | B48: 13119 | C48: MAYO | D48: AGUA | F48: 2 | G48: =+G47+E48-F48 -> 7.1054274e-15
A49: 42916 | B49: POR COBRAR | C49: JUNIO | D49: LUZ | E49: 26.1 | G49: =+G48+E49-F49 -> 26.1
D50: AGUA | E50: 2 | G50: =+G49+E50-F50 -> 28.1
D51: G. ADM | E51: 60 | G51: =+G50+E51-F51 -> 88.1
D52: P. SOCIAL | E52: 2 | G52: =+G51+E52-F52 -> 90.1
A53: 42916 | B53: TARJETA | C53: JUNIO | D53: G. ADM | F53: 60 | G53: =+G52+E53-F53 -> 30.1
A54: 42916 | B54: TARJETA | C54: JUNIO | D54: P. SOCIAL | F54: 2 | G54: =+G53+E54-F54 -> 28.1
A55: 42936 | B55: 13226 | C55: JUNIO | D55: LUZ | F55: 26.1 | G55: =+G54+E55-F55 -> 2
A56: 42936 | B56: 13226 | C56: JUNIO | D56: AGUA | F56: 2 | G56: =+G55+E56-F56 -> 7.1054274e-15
A57: 42947 | B57: POR COBRAR | C57: JULIO | D57: LUZ | E57: 24.9 | G57: =+G56+E57-F57 -> 24.9
D58: AGUA | E58: 2 | G58: =+G57+E58-F58 -> 26.9
D59: G. ADM | E59: 60 | G59: =+G58+E59-F59 -> 86.9
D60: P. SOCIAL | E60: 2 | G60: =+G59+E60-F60 -> 88.9
A61: 42945 | B61: TARJETA | C61: JULIO | D61: G. ADM | F61: 60 | G61: =+G60+E61-F61 -> 28.9
A62: 42945 | B62: TARJETA | C62: JULIO | D62: P. SOCIAL | F62: 2 | G62: =+G61+E62-F62 -> 26.9
A63: 42969 | B63: 13449 | C63: JULIO | D63: LUZ | F63: 24.9 | G63: =+G62+E63-F63 -> 2
A64: 42969 | B64: 13449 | C64: JULIO | D64: AGUA | F64: 2 | G64: =+G63+E64-F64 -> 7.1054274e-15
A65: 42978 | B65: POR COBRAR | C65: AGOSTO | D65: LUZ | E65: 24.9 | G65: =+G64+E65-F65 -> 24.9
D66: AGUA | E66: 2 | G66: =+G65+E66-F66 -> 26.9
D67: G. ADM | E67: 60 | G67: =+G66+E67-F67 -> 86.9
D68: P. SOCIAL | E68: 2 | G68: =+G67+E68-F68 -> 88.9
A69: 42978 | B69: TARJETA | C69: AGOSTO | D69: G. ADM | F69: 60 | G69: =+G68+E69-F69 -> 28.9
A70: 42978 | B70: TARJETA | C70: AGOSTO | D70: P. SOCIAL | F70: 2 | G70: =+G69+E70-F70 -> 26.9
A71: 42997 | B71: 13611 | C71: AGOSTO | D71: LUZ | F71: 24.9 | G71: =+G70+E71-F71 -> 2
A72: 42997 | B72: 13611 | C72: AGOSTO | D72: AGUA | F72: 2 | G72: =+G71+E72-F72 -> 7.1054274e-15
A73: 43008 | B73: POR COBRAR | C73: SEPTIEMBRE | D73: LUZ | E73: 21.2 | G73: =+G72+E73-F73 -> 21.2
D74: AGUA | E74: 1.3 | G74: =+G73+E74-F74 -> 22.5
D75: G. ADM | E75: 60 | G75: =+G74+E75-F75 -> 82.5
D76: P. SOCIAL | E76: 2 | G76: =+G75+E76-F76 -> 84.5
A77: 42823 | D77: MULTA | E77: 85 | G77: =+G76+E77-F77 -> 169.5
A78: 42951 | D78: MULTA | E78: 85 | G78: =+G77+E78-F78 -> 254.5
A79: 43008 | B79: TARJETA | C79: SEPTIEMBRE | D79: G. ADM | F79: 60 | G79: =+G78+E79-F79 -> 194.5
A80: 43008 | B80: TARJETA | C80: SEPTIEMBRE | D80: P. SOCIAL | F80: 2 | G80: =+G79+E80-F80 -> 192.5
A81: 43028 | B81: 13838 | C81: SEPTIEMBRE | D81: LUZ | F81: 21.2 | G81: =+G80+E81-F81 -> 171.3
A82: 43028 | B82: 13838 | C82: SEPTIEMBRE | D82: AGUA | F82: 1.3 | G82: =+G81+E82-F82 -> 170
A83: 42972 | B83: 6330 | C83: 42951 | D83: MULTA | F83: 85 | G83: =+G82+E83-F83 -> 85
A84: 43049 | B84: 13953 | C84: 42823 | D84: MULTA | F84: 85 | G84: =+G83+E84-F84 -> 0
A85: 43039 | B85: POR COBRAR | C85: OCTUBRE | D85: LUZ | E85: 21.3 | G85: =+G84+E85-F85 -> 21.3
D86: AGUA | E86: 2 | G86: =+G85+E86-F86 -> 23.3
D87: G. ADM | E87: 60 | G87: =+G86+E87-F87 -> 83.3
D88: P. SOCIAL | E88: 2 | G88: =+G87+E88-F88 -> 85.3
A89: 43039 | B89: TARJETA | C89: OCTUBRE | D89: G. ADM | F89: 60 | G89: =+G88+E89-F89 -> 25.3
A90: 43039 | B90: TARJETA | C90: OCTUBRE | D90: P. SOCIAL | F90: 2 | G90: =+G89+E90-F90 -> 23.3
A91: 43060 | B91: 10209 | C91: OCTUBRE | D91: AGUA | F91: 2 | G91: =+G90+E91-F91 -> 21.3
A92: 43060 | B92: 10209 | C92: OCTUBRE | D92: LUZ | F92: 21.3 | G92: =+G91+E92-F92 -> 0
A93: 43069 | B93: POR COBRAR | C93: NOVIEMBRE | D93: LUZ | E93: 22.6 | G93: =+G92+E93-F93 -> 22.6
D94: AGUA | E94: 2 | G94: =+G93+E94-F94 -> 24.6
D95: G. ADM | E95: 60 | G95: =+G94+E95-F95 -> 84.6
D96: P. SOCIAL | E96: 2 | G96: =+G95+E96-F96 -> 86.6
A97: 43088 | B97: 14321 | C97: NOVIEMBRE | D97: LUZ | F97: 22.6 | G97: =+G96+E97-F97 -> 64
A98: 43088 | B98: 14321 | C98: NOVIEMBRE | D98: AGUA | F98: 2 | G98: =+G97+E98-F98 -> 62
A99: 43069 | B99: TARJETA | C99: NOVIEMBRE | D99: G. ADM | F99: 60 | G99: =+G98+E99-F99 -> 2
A100: 43069 | B100: TARJETA | C100: NOVIEMBRE | D100: P. SOCIAL | F100: 2 | G100: =+G99+E100-F100 -> -7.1054274e-15
A101: 43100 | B101: POR COBRAR | C101: DICIEMBRE | D101: LUZ | E101: 24.6 | G101: =+G100+E101-F101 -> 24.6
D102: AGUA | E102: 2 | G102: =+G101+E102-F102 -> 26.6
...

Sheet CUYA ALBERTO
B2: CUYA SANCHEZ ALBERTO
A4: FECHA | B4: DOCUMENTO | C4: PERIODO | D4: CONCEPTO | E4: POR COBRAR | F4: PAGADO | G4: SALDO POR COBRAR
A5: 42736 | B5: SALDO AL 2016 | G5: 376.1
A6: 42786 | B6: 12277 | C6: A CUENTA 2016 | F6: 65.1 | G6: =+G5+E6-F6 -> 311
A7: 42786 | B7: 12311 | C7: A CUENTA 2016 | F7: 311 | G7: =+G6+E7-F7 -> 0
A8: 42766 | B8: POR COBRAR | C8: ENERO | D8: LUZ | E8: 61 | G8: =+G7+E8-F8 -> 61
D9: AGUA | E9: 2.8 | G9: =+G8+E9-F9 -> 63.8
D10: G. ADM | E10: 60 | G10: =+G9+E10-F10 -> 123.8
D11: P. SOCIAL | E11: 2 | G11: =+G10+E11-F11 -> 125.8
A12: 42786 | B12: 12277 | C12: ENERO | D12: LUZ | F12: 61 | G12: =+G11+E12-F12 -> 64.8
A13: 42786 | B13: 12277 | C13: ENERO | D13: AGUA | F13: 2.8 | G13: =+G12+E13-F13 -> 62
A14: 42786 | B14: 12311 | C14: ENERO | D14: G. ADM | F14: 60 | G14: =+G13+E14-F14 -> 2
A15: 42786 | B15: 12311 | C15: ENERO | D15: P. SOCIAL | F15: 2 | G15: =+G14+E15-F15 -> 0
A16: 42794 | B16: POR COBRAR | C16: FEBRERO | D16: LUZ | E16: 61.4 | G16: =+G15+E16-F16 -> 61.4
D17: AGUA | E17: 2 | G17: =+G16+E17-F17 -> 63.4
D18: G. ADM | E18: 56 | G18: =+G17+E18-F18 -> 119.4
D19: P. SOCIAL | E19: 2 | G19: =+G18+E19-F19 -> 121.4
A20: 42822 | B20: 12605 | C20: FEBRERO | D20: G. ADM | F20: 56 | G20: =+G19+E20-F20 -> 65.4
A21: 42822 | B21: 12605 | C21: FEBRERO | D21: P. SOCIAL | F21: 2 | G21: =+G20+E21-F21 -> 63.4
A22: 42822 | B22: 12605 | C22: FEBRERO | D22: LUZ | F22: 61.4 | G22: =+G21+E22-F22 -> 2
A23: 42822 | B23: 12605 | C23: FEBRERO | D23: AGUA | F23: 2 | G23: =+G22+E23-F23 -> 7.1054274e-15
A24: 42825 | B24: POR COBRAR | C24: MARZO | D24: LUZ | E24: 58.1 | G24: =+G23+E24-F24 -> 58.1
D25: AGUA | E25: 2 | G25: =+G24+E25-F25 -> 60.1
D26: G. ADM | E26: 60 | G26: =+G25+E26-F26 -> 120.1
D27: P. SOCIAL | E27: 2 | G27: =+G26+E27-F27 -> 122.1
D28: MULTA | E28: 85 | G28: =+G27+E28-F28 -> 207.1
A29: 42885 | B29: 12878 | C29: MARZO | D29: LUZ | F29: 58.1 | G29: =+G28+E29-F29 -> 149
A30: 42885 | B30: 12878 | C30: MARZO | D30: AGUA | F30: 2 | G30: =+G29+E30-F30 -> 147
A31: 42893 | B31: 13082 | C31: MARZO | D31: G. ADM | F31: 60 | G31: =+G30+E31-F31 -> 87
A32: 42893 | B32: 13082 | C32: MARZO | D32: P. SOCIAL | F32: 2 | G32: =+G31+E32-F32 -> 85
A33: 42949 | B33: 13370 | C33: MARZO | D33: MULTA | F33: 85 | G33: =+G32+E33-F33 -> 0
A34: 42855 | B34: POR COBRAR | C34: ABRIL | D34: LUZ | E34: 60.4 | G34: =+G33+E34-F34 -> 60.4
D35: AGUA | E35: 2 | G35: =+G34+E35-F35 -> 62.4
D36: G. ADM | E36: 60 | G36: =+G35+E36-F36 -> 122.4
D37: P. SOCIAL | E37: 2 | G37: =+G36+E37-F37 -> 124.4
A38: 42885 | B38: 12878 | C38: ABRIL | D38: LUZ | F38: 60.4 | G38: =+G37+E38-F38 -> 64
A39: 42885 | B39: 12878 | C39: ABRIL | D39: AGUA | F39: 2 | G39: =+G38+E39-F39 -> 62
A40: 42893 | B40: 13082 | C40: ABRIL | D40: G. ADM | F40: 60 | G40: =+G39+E40-F40 -> 2
A41: 42893 | B41: 13082 | C41: ABRIL | D41: P. SOCIAL | F41: 2 | G41: =+G40+E41-F41 -> 0
A42: 42886 | B42: POR COBRAR | C42: MAYO | D42: LUZ | E42: 57.7 | G42: =+G41+E42-F42 -> 57.7
D43: AGUA | E43: 2 | G43: =+G42+E43-F43 -> 59.7
D44: G. ADM | E44: 60 | G44: =+G43+E44-F44 -> 119.7
D45: P. SOCIAL | E45: 2 | G45: =+G44+E45-F45 -> 121.7
A46: 42923 | B46: 13188 | C46: MAYO | D46: G. ADM | F46: 60 | G46: =+G45+E46-F46 -> 61.7
A47: 42923 | B47: 13188 | C47: MAYO | D47: P. SOCIAL | F47: 2 | G47: =+G46+E47-F47 -> 59.7
A48: 42949 | B48: 13370 | C48: MAYO | D48: LUZ | F48: 57.7 | G48: =+G47+E48-F48 -> 2
A49: 42949 | B49: 13370 | C49: MAYO | D49: AGUA | F49: 2 | G49: =+G48+E49-F49 -> 0
A50: 42916 | B50: POR COBRAR | C50: JUNIO | D50: LUZ | E50: 56.1 | G50: =+G49+E50-F50 -> 56.1
D51: AGUA | E51: 2 | G51: =+G50+E51-F51 -> 58.1
D52: G. ADM | E52: 60 | G52: =+G51+E52-F52 -> 118.1
D53: P. SOCIAL | E53: 2 | G53: =+G52+E53-F53 -> 120.1
A54: 42923 | B54: 13188 | C54: JUNIO | D54: G. ADM | F54: 60 | G54: =+G53+E54-F54 -> 60.1
A55: 42923 | B55: 13188 | C55: JUNIO | D55: P. SOCIAL | F55: 2 | G55: =+G54+E55-F55 -> 58.1
A56: 42949 | B56: 13370 | C56: JUNIO | D56: AGUA | F56: 2 | G56: =+G55+E56-F56 -> 56.1
A57: 42949 | B57: 13370 | C57: JUNIO | D57: LUZ | F57: 56.1 | G57: =+G56+E57-F57 -> 0
A58: 42947 | B58: POR COBRAR | C58: JULIO | D58: LUZ | E58: 53.2 | G58: =+G57+E58-F58 -> 53.2
D59: AGUA | E59: 2 | G59: =+G58+E59-F59 -> 55.2
D60: G. ADM | E60: 60 | G60: =+G59+E60-F60 -> 115.2
D61: P. SOCIAL | E61: 2 | G61: =+G60+E61-F61 -> 117.2
A62: 42950 | B62: 13394 | C62: JULIO | D62: G. ADM | F62: 60 | G62: =+G61+E62-F62 -> 57.2
A63: 42950 | B63: 13394 | C63: JULIO | D63: P. SOCIAL | F63: 2 | G63: =+G62+E63-F63 -> 55.2
A64: 42997 | B64: 13617 | C64: JULIO | D64: LUZ | F64: 53.2 | G64: =+G63+E64-F64 -> 2
A65: 42997 | B65: 13617 | C65: JULIO | D65: AGUA | F65: 2 | G65: =+G64+E65-F65 -> 0
A66: 42978 | B66: POR COBRAR | C66: AGOSTO | D66: LUZ | E66: 53.2 | G66: =+G65+E66-F66 -> 53.2
D67: AGUA | E67: 2 | G67: =+G66+E67-F67 -> 55.2
D68: G. ADM | E68: 60 | G68: =+G67+E68-F68 -> 115.2
D69: P. SOCIAL | E69: 2 | G69: =+G68+E69-F69 -> 117.2
A70: 42950 | B70: 13394 | C70: AGOSTO | D70: G. ADM | F70: 60 | G70: =+G69+E70-F70 -> 57.2
A71: 42950 | B71: 13394 | C71: AGOSTO | D71: P. SOCIAL | F71: 2 | G71: =+G70+E71-F71 -> 55.2
A72: 42997 | B72: 13617 | C72: AGOSTO | D72: LUZ | F72: 53.2 | G72: =+G71+E72-F72 -> 2
A73: 42997 | B73: 13617 | C73: AGOSTO | D73: AGUA | F73: 2 | G73: =+G72+E73-F73 -> 0
A74: 43008 | B74: POR COBRAR | C74: SEPTIEMBRE | D74: LUZ | E74: 71.6 | G74: =+G73+E74-F74 -> 71.6
D75: AGUA | E75: 2 | G75: =+G74+E75-F75 -> 73.6
D76: G. ADM | E76: 60 | G76: =+G75+E76-F76 -> 133.6
D77: P. SOCIAL | E77: 2 | G77: =+G76+E77-F77 -> 135.6
A78: 42950 | B78: 13394 | C78: SEPTIEMBRE | D78: G. ADM | F78: 60 | G78: =+G77+E78-F78 -> 75.6
A79: 42950 | B79: 13394 | C79: SEPTIEMBRE | D79: P. SOCIAL | F79: 2 | G79: =+G78+E79-F79 -> 73.6
A80: 43062 | B80: 14025 | C80: SEPTIEMBRE | D80: LUZ | F80: 71.6 | G80: =+G79+E80-F80 -> 2
A81: 43062 | B81: 14025 | C81: SEPTIEMBRE | D81: AGUA | F81: 2 | G81: =+G80+E81-F81 -> 0
A82: 43039 | B82: POR COBRAR | C82: OCTUBRE | D82: LUZ | E82: 71.2 | G82: =+G81+E82-F82 -> 71.2
D83: AGUA | E83: 2 | G83: =+G82+E83-F83 -> 73.2
D84: G. ADM | E84: 60 | G84: =+G83+E84-F84 -> 133.2
D85: P. SOCIAL | E85: 2 | G85: =+G84+E85-F85 -> 135.2
A86: 43062 | B86: 14025 | C86: OCTUBRE | D86: G. ADM | F86: 60 | G86: =+G85+E86-F86 -> 75.2
A87: 43062 | B87: 14025 | C87: OCTUBRE | D87: P. SOCIAL | F87: 2 | G87: =+G86+E87-F87 -> 73.2
A88: 43062 | B88: 14025 | C88: OCTUBRE | D88: AGUA | F88: 2 | G88: =+G87+E88-F88 -> 71.2
A89: 43062 | B89: 14025 | C89: OCTUBRE | D89: LUZ | F89: 71.2 | G89: =+G88+E89-F89 -> 0
A90: 43069 | B90: POR COBRAR | C90: NOVIEMBRE | D90: LUZ | E90: 76 | G90: =+G89+E90-F90 -> 76
D91: AGUA | E91: 2 | G91: =+G90+E91-F91 -> 78
D92: G. ADM | E92: 60 | G92: =+G91+E92-F92 -> 138
D93: P. SOCIAL | E93: 2 | G93: =+G92+E93-F93 -> 140
A94: 43108 | B94: 14408 | C94: NOVIEMBRE | D94: LUZ | F94: 76 | G94: =+G93+E94-F94 -> 64
A95: 43108 | B95: 14408 | C95: NOVIEMBRE | D95: AGUA | F95: 2 | G95: =+G94+E95-F95 -> 62
A96: 43108 | B96: 14408 | C96: NOVIEMBRE | D96: G. ADM | F96: 60 | G96: =+G95+E96-F96 -> 2
A97: 43108 | B97: 14408 | C97: NOVIEMBRE | D97: P. SOCIAL | F97: 2 | G97: =+G96+E97-F97 -> 0
A98: 43100 | B98: POR COBRAR | C98: DICIEMBRE | D98: LUZ | E98: 82.7 | G98: =+G97+E98-F98 -> 82.7
D99: AGUA | E99: 2 | G99: =+G98+E99-F99 -> 84.7
D100: G. ADM | E100: 60 | G100: =+G99+E100-F100 -> 144.7
D101: P. SOCIAL | E101: 2 | G101: =+G100+E101-F101 -> 146.7
A102: 43108 | B102: 14408 | C102: DICIEMBRE | D102: G. ADM | F102: 60 | G102: =+G101+E102-F102 -> 86.7
...

Sheet DAVILA MARISOL
B2: DAVILA CAHUANA MARISOL
A4: FECHA | B4: DOCUMENTO | C4: PERIODO | D4: CONCEPTO | E4: POR COBRAR | F4: PAGADO
A5: 42736 | B5: SALDO AL 2016 | G5: 1069.6
A6: 42753 | B6: 12116 | C6: A CUENTA 2016 | F6: 124 | G6: =+G5+E6-F6 -> 945.6
A7: 42753 | B7: 12117 | C7: A CUENTA 2016 | F7: 59 | G7: =+G6+E7-F7 -> 886.6
A8: 42786 | B8: 12257 | C8: A CUENTA 2016 | F8: 607 | G8: =+G7+E8-F8 -> 279.6
A9: 42823 | B9: 12622 | C9: CANCELACION DEL 2016 | F9: 279.6 | G9: =+G8+E9-F9 -> 0
A10: 42766 | B10: POR COBRAR | C10: ENERO | D10: LUZ | E10: 261.9 | G10: =+G9+E10-F10 -> 261.9
D11: AGUA | E11: 2.8 | G11: =+G10+E11-F11 -> 264.7
D12: G. ADM | E12: 60 | G12: =+G11+E12-F12 -> 324.7
D13: P. SOCIAL | E13: 2 | G13: =+G12+E13-F13 -> 326.7
A14: 42786 | B14: 12263 | C14: ENERO | D14: LUZ | F14: 261.9 | G14: =+G13+E14-F14 -> 64.8
A15: 42786 | B15: 12263 | C15: ENERO | D15: AGUA | F15: 2.8 | G15: =+G14+E15-F15 -> 62
A16: 42787 | B16: 12338 | C16: ENERO | D16: G. ADM | F16: 60 | G16: =+G15+E16-F16 -> 2
A17: 42787 | B17: 12338 | C17: ENERO | D17: P. SOCIAL | F17: 2 | G17: =+G16+E17-F17 -> 1.4210855e-14
A18: 42794 | B18: POR COBRAR | C18: FEBRERO | D18: LUZ | E18: 270.2 | G18: =+G17+E18-F18 -> 270.2
D19: AGUA | E19: 2 | G19: =+G18+E19-F19 -> 272.2
D20: G. ADM | E20: 56 | G20: =+G19+E20-F20 -> 328.2
D21: P. SOCIAL | E21: 2 | G21: =+G20+E21-F21 -> 330.2
A22: 42821 | B22: 12514 | C22: FEBRERO | D22: LUZ | F22: 270.2 | G22: =+G21+E22-F22 -> 60
A23: 42821 | B23: 12514 | C23: FEBRERO | D23: AGUA | F23: 2 | G23: =+G22+E23-F23 -> 58
A24: 42822 | B24: 12612 | C24: FEBRERO | D24: G. ADM | F24: 56 | G24: =+G23+E24-F24 -> 2
A25: 42822 | B25: 12612 | C25: FEBRERO | D25: P. SOCIAL | F25: 2 | G25: =+G24+E25-F25 -> 0
A26: 42825 | B26: POR COBRAR | C26: MARZO | D26: LUZ | E26: 259.4 | G26: =+G25+E26-F26 -> 259.4
D27: AGUA | E27: 2 | G27: =+G26+E27-F27 -> 261.4
D28: G. ADM | E28: 60 | G28: =+G27+E28-F28 -> 321.4
D29: P. SOCIAL | E29: 2 | G29: =+G28+E29-F29 -> 323.4
A30: 42842 | B30: 12647 | C30: MARZO | D30: G. ADM | F30: 60 | G30: =+G29+E30-F30 -> 263.4
A31: 42842 | B31: 12647 | C31: MARZO | D31: P. SOCIAL | F31: 2 | G31: =+G30+E31-F31 -> 261.4
A32: 42885 | B32: 12896 | C32: MARZO | D32: LUZ | F32: 259.4 | G32: =+G31+E32-F32 -> 2
A33: 42885 | B33: 12896 | C33: MARZO | D33: AGUA | F33: 2 | G33: =+G32+E33-F33 -> 0
A34: 42855 | B34: POR COBRAR | C34: ABRIL | D34: LUZ | E34: 263.6 | G34: =+G33+E34-F34 -> 263.6
D35: AGUA | E35: 2 | G35: =+G34+E35-F35 -> 265.6
D36: G. ADM | E36: 60 | G36: =+G35+E36-F36 -> 325.6
D37: P. SOCIAL | E37: 2 | G37: =+G36+E37-F37 -> 327.6
A38: 42885 | B38: 12896 | C38: ABRIL | D38: LUZ | F38: 263.6 | G38: =+G37+E38-F38 -> 64
A39: 42885 | B39: 12896 | C39: ABRIL | D39: AGUA | F39: 2 | G39: =+G38+E39-F39 -> 62
A40: 42935 | B40: 13220 | C40: ABRIL | D40: G. ADM | F40: 60 | G40: =+G39+E40-F40 -> 2
A41: 42935 | B41: 13220 | C41: ABRIL | D41: P. SOCIAL | F41: 2 | G41: =+G40+E41-F41 -> 0
A42: 42886 | B42: POR COBRAR | C42: MAYO | D42: LUZ | E42: 244.8 | G42: =+G41+E42-F42 -> 244.8
D43: AGUA | E43: 2 | G43: =+G42+E43-F43 -> 246.8
D44: G. ADM | E44: 60 | G44: =+G43+E44-F44 -> 306.8
D45: P. SOCIAL | E45: 2 | G45: =+G44+E45-F45 -> 308.8
A46: 42935 | B46: 13220 | C46: MAYO | D46: G. ADM | F46: 60 | G46: =+G45+E46-F46 -> 248.8
A47: 42935 | B47: 13220 | C47: MAYO | D47: P. SOCIAL | F47: 2 | G47: =+G46+E47-F47 -> 246.8
A48: 42949 | B48: 13373 | C48: MAYO | D48: LUZ | F48: 244.8 | G48: =+G47+E48-F48 -> 2
A49: 42949 | B49: 13373 | C49: MAYO | D49: AGUA | F49: 2 | G49: =+G48+E49-F49 -> 0
A50: 42916 | B50: POR COBRAR | C50: JUNIO | D50: LUZ | E50: 239.6 | G50: =+G49+E50-F50 -> 239.6
D51: AGUA | E51: 2 | G51: =+G50+E51-F51 -> 241.6
D52: G. ADM | E52: 60 | G52: =+G51+E52-F52 -> 301.6
D53: P. SOCIAL | E53: 2 | G53: =+G52+E53-F53 -> 303.6
A54: 42935 | B54: 13220 | C54: JUNIO | D54: G. ADM | F54: 60 | G54: =+G53+E54-F54 -> 243.6
A55: 42935 | B55: 13220 | C55: JUNIO | D55: P. SOCIAL | F55: 2 | G55: =+G54+E55-F55 -> 241.6
A56: 42949 | B56: 13373 | C56: JUNIO | D56: LUZ | F56: 239.6 | G56: =+G55+E56-F56 -> 2
A57: 42949 | B57: 13373 | C57: JUNIO | D57: AGUA | F57: 2 | G57: =+G56+E57-F57 -> 2.8421709e-14
A58: 42947 | B58: POR COBRAR | C58: JULIO | D58: LUZ | E58: 213.9 | G58: =+G57+E58-F58 -> 213.9
D59: AGUA | E59: 2 | G59: =+G58+E59-F59 -> 215.9
D60: G. ADM | E60: 60 | G60: =+G59+E60-F60 -> 275.9
D61: P. SOCIAL | E61: 2 | G61: =+G60+E61-F61 -> 277.9
A62: 42949 | B62: 13360 | C62: JULIO | D62: G. ADM | F62: 60 | G62: =+G61+E62-F62 -> 217.9
A63: 42949 | B63: 13360 | C63: JULIO | D63: P. SOCIAL | F63: 2 | G63: =+G62+E63-F63 -> 215.9
A64: 42998 | B64: 13622 | C64: JULIO | D64: LUZ | F64: 213.9 | G64: =+G63+E64-F64 -> 2
A65: 42998 | B65: 13622 | C65: JULIO | D65: AGUA | F65: 2 | G65: =+G64+E65-F65 -> 2.8421709e-14
A66: 42978 | B66: POR COBRAR | C66: AGOSTO | D66: LUZ | E66: 213.9 | G66: =+G65+E66-F66 -> 213.9
D67: AGUA | E67: 2 | G67: =+G66+E67-F67 -> 215.9
D68: G. ADM | E68: 60 | G68: =+G67+E68-F68 -> 275.9
D69: P. SOCIAL | E69: 2 | G69: =+G68+E69-F69 -> 277.9
A70: 42997 | B70: 13621 | C70: AGOSTO | D70: G. ADM | F70: 60 | G70: =+G69+E70-F70 -> 217.9
A71: 42997 | B71: 13621 | C71: AGOSTO | D71: P. SOCIAL | F71: 2 | G71: =+G70+E71-F71 -> 215.9
A72: 43012 | B72: 13793 | C72: AGOSTO | D72: LUZ | F72: 213.9 | G72: =+G71+E72-F72 -> 2
A73: 43012 | B73: 13793 | C73: AGOSTO | D73: AGUA | F73: 2 | G73: =+G72+E73-F73 -> 2.8421709e-14
A74: 43008 | B74: POR COBRAR | C74: SEPTIEMBRE | D74: LUZ | E74: 276.6 | G74: =+G73+E74-F74 -> 276.6
D75: AGUA | E75: 2 | G75: =+G74+E75-F75 -> 278.6
D76: G. ADM | E76: 60 | G76: =+G75+E76-F76 -> 338.6
D77: P. SOCIAL | E77: 2 | G77: =+G76+E77-F77 -> 340.6
A78: 43056 | B78: 13990 | C78: SEPTIEMBRE | D78: G. ADM | F78: 60 | G78: =+G77+E78-F78 -> 280.6
A79: 43056 | B79: 13990 | C79: SEPTIEMBRE | D79: P. SOCIAL | F79: 2 | G79: =+G78+E79-F79 -> 278.6
A80: 43067 | B80: 14146 | C80: SEPTIEMBRE | D80: LUZ | F80: 276.6 | G80: =+G79+E80-F80 -> 2
A81: 43067 | B81: 14146 | C81: SEPTIEMBRE | D81: AGUA | F81: 2 | G81: =+G80+E81-F81 -> 0
A82: 43039 | B82: POR COBRAR | C82: OCTUBRE | D82: LUZ | E82: 278 | G82: =+G81+E82-F82 -> 278
D83: AGUA | E83: 2 | G83: =+G82+E83-F83 -> 280
D84: G. ADM | E84: 60 | G84: =+G83+E84-F84 -> 340
D85: P. SOCIAL | E85: 2 | G85: =+G84+E85-F85 -> 342
A86: 42977 | B86: ACT. SANTA ROSA | D86: PARRILLA | E86: 50 | G86: =+G85+E86-F86 -> 392
A87: 43056 | B87: 13990 | C87: OCTUBRE | D87: G. ADM | F87: 60 | G87: =+G86+E87-F87 -> 332
A88: 43056 | B88: 13990 | C88: OCTUBRE | D88: P. SOCIAL | F88: 2 | G88: =+G87+E88-F88 -> 330
A89: 43068 | B89: 14170 | C89: OCTUBRE | D89: LUZ | F89: 278 | G89: =+G88+E89-F89 -> 52
A90: 43068 | B90: 14170 | C90: OCTUBRE | D90: AGUA | F90: 2 | G90: =+G89+E90-F90 -> 50
A91: 43119 | B91: 7413 | C91: OCTUBRE | D91: PARRILLA | F91: 50 | G91: =+G90+E91-F91 -> 0
A92: 43069 | B92: POR COBRAR | C92: NOVIEMBRE | D92: LUZ | E92: 293.7 | G92: =+G91+E92-F92 -> 293.7
D93: AGUA | E93: 2 | G93: =+G92+E93-F93 -> 295.7
D94: G. ADM | E94: 60 | G94: =+G93+E94-F94 -> 355.7
D95: P. SOCIAL | E95: 2 | G95: =+G94+E95-F95 -> 357.7
D96: P. S X FALL. FLORES EMMA | E96: 10 | G96: =+G95+E96-F96 -> 367.7
A97: 43066 | B97: 14119 | C97: NOVIEMBRE | D97: P. S X FALL. FLORES EMMA | F97: 10 | G97: =+G96+E97-F97 -> 357.7
A98: 43088 | B98: 14315 | C98: NOVIEMBRE | D98: LUZ | F98: 293.7 | G98: =+G97+E98-F98 -> 64
A99: 43088 | B99: 14315 | C99: NOVIEMBRE | D99: AGUA | F99: 2 | G99: =+G98+E99-F99 -> 62
A100: 43119 | B100: 14533 | C100: NOVIEMBRE | D100: G. ADM | F100: 60 | G100: =+G99+E100-F100 -> 2
A101: 43119 | B101: 14533 | C101: NOVIEMBRE | D101: P. SOCIAL | F101: 2 | G101: =+G100+E101-F101 -> 0
A102: 43100 | B102: POR COBRAR | C102: DICIEMBRE | D102: LUZ | E102: 319.5 | G102: =+G101+E102-F102 -> 319.5
...

Sheet DELA CRUZ JOSE
B2: DELA CRUZ ESTEBAN JOSE
A4: FECHA | B4: DOCUMENTO | C4: PERIODO | D4: CONCEPTO | E4: POR COBRAR | F4: PAGADO | G4: SALDO POR COBRAR
A5: 42736 | B5: SALDO AL 2016 | G5: 5499.5
A6: 42777 | B6: 12941 | C6: A CUENTA 2016 | F6: 96.6 | G6: =+G5+E6-F6 -> 5402.9
A7: 42763 | B7: TARJETA | C7: A CUENTA 2016 | F7: 190 | G7: =+G6+E7-F7 -> 5212.9
A8: 42793 | B8: TARJETA | C8: A CUENTA 2016 | F8: 180 | G8: =+G7+E8-F8 -> 5032.9
A9: 42825 | B9: TARJETA | C9: A CUENTA 2016 | F9: 210 | G9: =+G8+E9-F9 -> 4822.9
A10: 42854 | B10: TARJETA | C10: A CUENTA 2016 | F10: 220 | G10: =+G9+E10-F10 -> 4602.9
A11: 42885 | B11: TARJETA | C11: A CUENTA 2016 | F11: 300 | G11: =+G10+E11-F11 -> 4302.9
A12: 42914 | B12: TARJETA | C12: A CUENTA 2016 | F12: 180 | G12: =+G11+E12-F12 -> 4122.9
A13: 42947 | B13: TARJETA | C13: A CUENTA 2016 | F13: 300 | G13: =+G12+E13-F13 -> 3822.9
A14: 42978 | B14: TARJETA | C14: A CUENTA 2016 | F14: 110 | G14: =+G13+E14-F14 -> 3712.9
A15: 43008 | B15: TARJETA | C15: A CUENTA 2016 | F15: 160 | G15: =+G14+E15-F15 -> 3552.9
A16: 43039 | B16: TARJETA | C16: A CUENTA 2016 | F16: 300 | G16: =+G15+E16-F16 -> 3252.9
A17: 43067 | B17: 14135 | C17: A CUENTA 2016 | F17: 210 | G17: =+G16+E17-F17 -> 3042.9
A18: 43069 | B18: TARJETA | C18: A CUENTA 2016 | F18: 114 | G18: =+G17+E18-F18 -> 2928.9
A19: 43099 | B19: TARJETA | C19: A CUENTA 2016 | F19: 290 | G19: =+G18+E19-F19 -> 2638.9
A20: 43131 | B20: TARJETA | C20: A CUENTA 2016 | F20: 190 | G20: =+G19+E20-F20 -> 2448.9
A21: 43159 | B21: TARJETA | C21: A CUENTA 2016 | F21: 90 | G21: =+G20+E21-F21 -> 2358.9
A22: 43190 | B22: TARJETA | C22: A CUENTA 2016 | F22: 60 | G22: =+G21+E22-F22 -> 2298.9
A23: 43220 | B23: TARJETA | C23: A CUENTA 2016 | F23: 70 | G23: =+G22+E23-F23 -> 2228.9
A24: 43251 | B24: TARJETA | C24: A CUENTA 2016 | F24: 30 | G24: =+G23+E24-F24 -> 2198.9
A25: 44139 | B25: 20607 | C25: A CUENTA 2016 | F25: 110.7 | G25: =+G24+E25-F25 -> 2088.2
A26: 44161 | B26: CARTA -124-2020 | C26: EXONERACION | F26: 1517.2 | G26: =+G25+E26-F26 -> 571
A27: 44233 | B27: 21528 | C27: CANCELACION | F27: 571 | G27: =+G26+E27-F27 -> 0
A28: 42766 | B28: POR COBRAR | C28: ENERO | D28: LUZ | E28: 60.3 | G28: =+G27+E28-F28 -> 60.3
D29: AGUA | E29: 31.9 | G29: =+G28+E29-F29 -> 92.2
D30: G. ADM | E30: 60 | G30: =+G29+E30-F30 -> 152.2
D31: P. SOCIAL | E31: 2 | G31: =+G30+E31-F31 -> 154.2
A32: 42765 | B32: TARJETA | C32: ENERO | D32: G. ADM | F32: 60 | G32: =+G31+E32-F32 -> 94.2
A33: 42765 | B33: TARJETA | C33: ENERO | D33: P. SOCIAL | F33: 2 | G33: =+G32+E33-F33 -> 92.2
A34: 42816 | B34: 12441 | C34: ENERO | D34: LUZ | F34: 60.3 | G34: =+G33+E34-F34 -> 31.9
A35: 42816 | B35: 12441 | C35: ENERO | D35: AGUA | F35: 31.9 | G35: =+G34+E35-F35 -> 0
A36: 42794 | B36: POR COBRAR | C36: FEBRERO | D36: LUZ | E36: 61.6 | G36: =+G35+E36-F36 -> 61.6
D37: AGUA | E37: 22 | G37: =+G36+E37-F37 -> 83.6
D38: G. ADM | E38: 56 | G38: =+G37+E38-F38 -> 139.6
D39: P. SOCIAL | E39: 2 | G39: =+G38+E39-F39 -> 141.6
A40: 42793 | B40: TARJETA | C40: FEBRERO | D40: G. ADM | F40: 36 | G40: =+G39+E40-F40 -> 105.6
A41: 42846 | B41: 12681 | C41: FEBRERO | D41: LUZ | F41: 61.6 | G41: =+G40+E41-F41 -> 44
A42: 42846 | B42: 12681 | C42: FEBRERO | D42: AGUA | F42: 22 | G42: =+G41+E42-F42 -> 22
A43: 44233 | B43: 20607 | C43: FEBRERO | D43: G. ADM | F43: 20 | G43: =+G42+E43-F43 -> 2
A44: 44233 | B44: 20607 | C44: FEBRERO | D44: P. SOCIAL | F44: 2 | G44: =+G43+E44-F44 -> -7.1054274e-15
A45: 42825 | B45: POR COBRAR | C45: MARZO | D45: LUZ | E45: 58.9 | G45: =+G44+E45-F45 -> 58.9
D46: AGUA | E46: 23.2 | G46: =+G45+E46-F46 -> 82.1
D47: G. ADM | E47: 60 | G47: =+G46+E47-F47 -> 142.1
D48: P. SOCIAL | E48: 2 | G48: =+G47+E48-F48 -> 144.1
A49: 42825 | B49: TARJETA | C49: MARZO | D49: G. ADM | F49: 60 | G49: =+G48+E49-F49 -> 84.1
A50: 42825 | B50: TARJETA | C50: MARZO | D50: P. SOCIAL | F50: 2 | G50: =+G49+E50-F50 -> 82.1
A51: 42880 | B51: 12817 | C51: MARZO | D51: LUZ | F51: 58.9 | G51: =+G50+E51-F51 -> 23.2
A52: 42880 | B52: 12817 | C52: MARZO | D52: AGUA | F52: 23.2 | G52: =+G51+E52-F52 -> 0
A53: 42855 | B53: POR COBRAR | C53: ABRIL | D53: LUZ | E53: 60.3 | G53: =+G52+E53-F53 -> 60.3
D54: AGUA | E54: 23 | G54: =+G53+E54-F54 -> 83.3
D55: G. ADM | E55: 60 | G55: =+G54+E55-F55 -> 143.3
D56: P. SOCIAL | E56: 2 | G56: =+G55+E56-F56 -> 145.3
A57: 42854 | B57: TARJETA | C57: ABRIL | D57: G. ADM | F57: 60 | G57: =+G56+E57-F57 -> 85.3
A58: 42854 | B58: TARJETA | C58: ABRIL | D58: P. SOCIAL | F58: 2 | G58: =+G57+E58-F58 -> 83.3
A59: 42880 | B59: 12817 | C59: ABRIL | D59: LUZ | F59: 60.3 | G59: =+G58+E59-F59 -> 23
A60: 42880 | B60: 12817 | C60: ABRIL | D60: AGUA | F60: 23 | G60: =+G59+E60-F60 -> 0
A61: 42886 | B61: POR COBRAR | C61: MAYO | D61: LUZ | E61: 56.6 | G61: =+G60+E61-F61 -> 56.6
D62: AGUA | E62: 22.3 | G62: =+G61+E62-F62 -> 78.9
D63: G. ADM | E63: 60 | G63: =+G62+E63-F63 -> 138.9
D64: P. SOCIAL | E64: 2 | G64: =+G63+E64-F64 -> 140.9
A65: 42886 | B65: TARJETA | C65: MAYO | D65: G. ADM | F65: 60 | G65: =+G64+E65-F65 -> 80.9
A66: 42886 | B66: TARJETA | C66: MAYO | D66: P. SOCIAL | F66: 2 | G66: =+G65+E66-F66 -> 78.9
A67: 42917 | B67: 13175 | C67: MAYO | D67: LUZ | F67: 56.6 | G67: =+G66+E67-F67 -> 22.3
A68: 42917 | B68: 13175 | C68: MAYO | D68: AGUA | F68: 22.3 | G68: =+G67+E68-F68 -> 0
A69: 42916 | B69: POR COBRAR | C69: JUNIO | D69: LUZ | E69: 55.2 | G69: =+G68+E69-F69 -> 55.2
D70: AGUA | E70: 22.5 | G70: =+G69+E70-F70 -> 77.7
D71: G. ADM | E71: 60 | G71: =+G70+E71-F71 -> 137.7
D72: P. SOCIAL | E72: 2 | G72: =+G71+E72-F72 -> 139.7
A73: 42916 | B73: TARJETA | C73: JUNIO | D73: G. ADM | F73: 60 | G73: =+G72+E73-F73 -> 79.7
A74: 42916 | B74: TARJETA | C74: JUNIO | D74: P. SOCIAL | F74: 2 | G74: =+G73+E74-F74 -> 77.7
A75: 42954 | B75: 13425 | C75: JUNIO | D75: LUZ | F75: 55.2 | G75: =+G74+E75-F75 -> 22.5
A76: 42954 | B76: 13425 | C76: JUNIO | D76: AGUA | F76: 22.5 | G76: =+G75+E76-F76 -> 0
A77: 42947 | B77: POR COBRAR | C77: JULIO | D77: LUZ | E77: 50.4 | G77: =+G76+E77-F77 -> 50.4
D78: AGUA | E78: 23 | G78: =+G77+E78-F78 -> 73.4
D79: G. ADM | E79: 60 | G79: =+G78+E79-F79 -> 133.4
D80: P. SOCIAL | E80: 2 | G80: =+G79+E80-F80 -> 135.4
A81: 42947 | B81: TARJETA | C81: JULIO | D81: G. ADM | F81: 60 | G81: =+G80+E81-F81 -> 75.4
A82: 42947 | B82: TARJETA | C82: JULIO | D82: P. SOCIAL | F82: 2 | G82: =+G81+E82-F82 -> 73.4
A83: 42975 | B83: 13509 | C83: JULIO | D83: LUZ | F83: 50.4 | G83: =+G82+E83-F83 -> 23
A84: 42975 | B84: 13509 | C84: JULIO | D84: AGUA | F84: 23 | G84: =+G83+E84-F84 -> 0
A85: 42978 | B85: POR COBRAR | C85: AGOSTO | D85: LUZ | E85: 50.4 | G85: =+G84+E85-F85 -> 50.4
D86: AGUA | E86: 23 | G86: =+G85+E86-F86 -> 73.4
D87: G. ADM | E87: 60 | G87: =+G86+E87-F87 -> 133.4
D88: P. SOCIAL | E88: 2 | G88: =+G87+E88-F88 -> 135.4
A89: 42978 | B89: TARJETA | C89: AGOSTO | D89: G. ADM | F89: 36 | G89: =+G88+E89-F89 -> 99.4
A90: 43005 | B90: 13685 | C90: AGOSTO | D90: LUZ | F90: 50.4 | G90: =+G89+E90-F90 -> 49
A91: 43005 | B91: 13685 | C91: AGOSTO | D91: AGUA | F91: 23 | G91: =+G90+E91-F91 -> 26
A92: 44043 | B92: TARJETA | C92: AGOSTO | D92: G. ADM | F92: 7.9 | G92: =+G91+E92-F92 -> 18.1
A93: 44233 | B93: 21528 | C93: AGOSTO | D93: G. ADM | F93: 16.1 | G93: =+G92+E93-F93 -> 2
A94: 44233 | B94: 21528 | C94: AGOSTO | D94: P. SOCIAL | F94: 2 | G94: =+G93+E94-F94 -> 7.1054274e-15
A95: 43008 | B95: POR COBRAR | C95: SEPTIEMBRE | D95: LUZ | E95: 50.3 | G95: =+G94+E95-F95 -> 50.3
D96: AGUA | E96: 22.4 | G96: =+G95+E96-F96 -> 72.7
D97: G. ADM | E97: 60 | G97: =+G96+E97-F97 -> 132.7
D98: P. SOCIAL | E98: 2 | G98: =+G97+E98-F98 -> 134.7
A99: 42788 | D99: MULTA | E99: 85 | G99: =+G98+E99-F99 -> 219.7
A100: 42823 | D100: MULTA | E100: 85 | G100: =+G99+E100-F100 -> 304.7
A101: 42951 | D101: MULTA | E101: 85 | G101: =+G100+E101-F101 -> 389.7
A102: 43008 | B102: TARJETA | C102: SEPTIEMBRE | D102: G. ADM | F102: 34 | G102: =+G101+E102-F102 -> 355.7
...

Sheet ESPEJO ROSA
B2: ESPEJO URBANO ROSA FLORENCIA
A4: FECHA | B4: DOCUMENTO | C4: PERIODO | D4: CONCEPTO | E4: POR COBRAR | F4: PAGADO | G4: SALDO POR COBRAR
A5: 42736 | B5: SALDO AL 2016 | G5: 123.6
G6: =+G5+E6-F6 -> 123.6
A7: 42822 | B7: 12588 | C7: CANCELACION | F7: 123.6 | G7: =+G6+E7-F7 -> 0
A8: 42766 | B8: POR COBRAR | C8: ENERO | D8: LUZ | E8: 50.4 | G8: =+G7+E8-F8 -> 50.4
D9: AGUA | E9: 2.8 | G9: =+G8+E9-F9 -> 53.2
D10: G. ADM | E10: 60 | G10: =+G9+E10-F10 -> 113.2
D11: P. SOCIAL | E11: 2 | G11: =+G10+E11-F11 -> 115.2
A12: 42765 | B12: TARJETA | C12: ENERO | D12: G. ADM | F12: 60 | G12: =+G11+E12-F12 -> 55.2
A13: 42765 | B13: TARJETA | C13: ENERO | D13: P. SOCIAL | F13: 2 | G13: =+G12+E13-F13 -> 53.2
A14: 42822 | B14: 12588 | C14: ENERO | D14: AGUA | F14: 2.8 | G14: =+G13+E14-F14 -> 50.4
A15: 42822 | B15: 12588 | C15: ENERO | D15: LUZ | F15: 50.4 | G15: =+G14+E15-F15 -> 0
A16: 42794 | B16: POR COBRAR | C16: FEBRERO | D16: LUZ | E16: 50.3 | G16: =+G15+E16-F16 -> 50.3
D17: AGUA | E17: 2 | G17: =+G16+E17-F17 -> 52.3
D18: G. ADM | E18: 56 | G18: =+G17+E18-F18 -> 108.3
D19: P. SOCIAL | E19: 2 | G19: =+G18+E19-F19 -> 110.3
A20: 42794 | B20: TARJETA | C20: FEBRERO | D20: G. ADM | F20: 56 | G20: =+G19+E20-F20 -> 54.3
A21: 42794 | B21: TARJETA | C21: FEBRERO | D21: P. SOCIAL | F21: 2 | G21: =+G20+E21-F21 -> 52.3
A22: 42822 | B22: 12588 | C22: FEBRERO | D22: LUZ | F22: 50.3 | G22: =+G21+E22-F22 -> 2
A23: 42822 | B23: 12588 | C23: FEBRERO | D23: AGUA | F23: 2 | G23: =+G22+E23-F23 -> 0
A24: 42825 | B24: POR COBRAR | C24: MARZO | D24: LUZ | E24: 47.4 | G24: =+G23+E24-F24 -> 47.4
D25: AGUA | E25: 2 | G25: =+G24+E25-F25 -> 49.4
D26: G. ADM | E26: 60 | G26: =+G25+E26-F26 -> 109.4
D27: P. SOCIAL | E27: 2 | G27: =+G26+E27-F27 -> 111.4
A28: 42824 | B28: TARJETA | C28: MARZO | D28: G. ADM | F28: 60 | G28: =+G27+E28-F28 -> 51.4
A29: 42824 | B29: TARJETA | C29: MARZO | D29: P. SOCIAL | F29: 2 | G29: =+G28+E29-F29 -> 49.4
A30: 42885 | B30: 12872 | C30: MARZO | D30: LUZ | F30: 47.4 | G30: =+G29+E30-F30 -> 2
A31: 42885 | B31: 12872 | C31: MARZO | D31: AGUA | F31: 2 | G31: =+G30+E31-F31 -> 7.1054274e-15
A32: 42855 | B32: POR COBRAR | C32: ABRIL | D32: LUZ | E32: 49.7 | G32: =+G31+E32-F32 -> 49.7
D33: AGUA | E33: 2 | G33: =+G32+E33-F33 -> 51.7
D34: G. ADM | E34: 60 | G34: =+G33+E34-F34 -> 111.7
D35: P. SOCIAL | E35: 2 | G35: =+G34+E35-F35 -> 113.7
A36: 42855 | B36: TARJETA | C36: ABRIL | D36: G. ADM | F36: 60 | G36: =+G35+E36-F36 -> 53.7
A37: 42855 | B37: TARJETA | C37: ABRIL | D37: P. SOCIAL | F37: 2 | G37: =+G36+E37-F37 -> 51.7
A38: 42885 | B38: 12872 | C38: ABRIL | D38: LUZ | F38: 49.7 | G38: =+G37+E38-F38 -> 2
A39: 42885 | B39: 12872 | C39: ABRIL | D39: AGUA | F39: 2 | G39: =+G38+E39-F39 -> 1.4210855e-14
A40: 42886 | B40: POR COBRAR | C40: MAYO | D40: LUZ | E40: 47.8 | G40: =+G39+E40-F40 -> 47.8
D41: AGUA | E41: 2 | G41: =+G40+E41-F41 -> 49.8
D42: G. ADM | E42: 60 | G42: =+G41+E42-F42 -> 109.8
D43: P. SOCIAL | E43: 2 | G43: =+G42+E43-F43 -> 111.8
A44: 42885 | B44: TARJETA | C44: MAYO | D44: G. ADM | F44: 60 | G44: =+G43+E44-F44 -> 51.8
A45: 42885 | B45: TARJETA | C45: MAYO | D45: P. SOCIAL | F45: 2 | G45: =+G44+E45-F45 -> 49.8
A46: 42949 | B46: 13383 | C46: MAYO | D46: LUZ | F46: 47.8 | G46: =+G45+E46-F46 -> 2
A47: 42949 | B47: 13383 | C47: MAYO | D47: AGUA | F47: 2 | G47: =+G46+E47-F47 -> 1.4210855e-14
A48: 42916 | B48: POR COBRAR | C48: JUNIO | D48: LUZ | E48: 46.4 | G48: =+G47+E48-F48 -> 46.4
D49: AGUA | E49: 2 | G49: =+G48+E49-F49 -> 48.4
D50: G. ADM | E50: 60 | G50: =+G49+E50-F50 -> 108.4
D51: P. SOCIAL | E51: 2 | G51: =+G50+E51-F51 -> 110.4
A52: 42916 | B52: TARJETA | C52: JUNIO | D52: G. ADM | F52: 60 | G52: =+G51+E52-F52 -> 50.4
A53: 42916 | B53: TARJETA | C53: JUNIO | D53: P. SOCIAL | F53: 2 | G53: =+G52+E53-F53 -> 48.4
A54: 42949 | B54: 13383 | C54: JUNIO | D54: LUZ | F54: 46.4 | G54: =+G53+E54-F54 -> 2
A55: 42949 | B55: 13383 | C55: JUNIO | D55: AGUA | F55: 2 | G55: =+G54+E55-F55 -> 7.1054274e-15
A56: 42947 | B56: POR COBRAR | C56: JULIO | D56: LUZ | E56: 44.7 | G56: =+G55+E56-F56 -> 44.7
D57: AGUA | E57: 2 | G57: =+G56+E57-F57 -> 46.7
D58: G. ADM | E58: 60 | G58: =+G57+E58-F58 -> 106.7
D59: P. SOCIAL | E59: 2 | G59: =+G58+E59-F59 -> 108.7
A60: 42946 | B60: TARJETA | C60: JULO | D60: G. ADM | F60: 60 | G60: =+G59+E60-F60 -> 48.7
A61: 42946 | B61: TARJETA | C61: JULIO | D61: P. SOCIAL | F61: 2 | G61: =+G60+E61-F61 -> 46.7
A62: 43066 | B62: 14117 | C62: JULIO | D62: LUZ | F62: 44.7 | G62: =+G61+E62-F62 -> 2
A63: 43066 | B63: 14117 | C63: JULIO | D63: AGUA | F63: 2 | G63: =+G62+E63-F63 -> 1.4210855e-14
A64: 42978 | B64: POR COBRAR | C64: AGOSTO | D64: LUZ | E64: 44.7 | G64: =+G63+E64-F64 -> 44.7
D65: AGUA | E65: 2 | G65: =+G64+E65-F65 -> 46.7
D66: G. ADM | E66: 60 | G66: =+G65+E66-F66 -> 106.7
D67: P. SOCIAL | E67: 2 | G67: =+G66+E67-F67 -> 108.7
A68: 42978 | B68: TARJETA | C68: AGOSTO | D68: G. ADM | F68: 60 | G68: =+G67+E68-F68 -> 48.7
A69: 42978 | B69: TARJETA | C69: AGOSTO | D69: P. SOCIAL | F69: 2 | G69: =+G68+E69-F69 -> 46.7
A70: 43066 | B70: 14117 | C70: AGOSTO | D70: LUZ | F70: 44.7 | G70: =+G69+E70-F70 -> 2
A71: 43066 | B71: 14117 | C71: AGOSTO | D71: AGUA | F71: 2 | G71: =+G70+E71-F71 -> 1.4210855e-14
A72: 43008 | B72: POR COBRAR | C72: SEPTIEMBRE | D72: LUZ | E72: 38.7 | G72: =+G71+E72-F72 -> 38.7
D73: AGUA | E73: 2 | G73: =+G72+E73-F73 -> 40.7
D74: G. ADM | E74: 60 | G74: =+G73+E74-F74 -> 100.7
D75: P. SOCIAL | E75: 2 | G75: =+G74+E75-F75 -> 102.7
A76: 43008 | B76: TARJETA | C76: SEPTIEMBRE | D76: G. ADM | F76: 60 | G76: =+G75+E76-F76 -> 42.7
A77: 43008 | B77: TARJETA | C77: SEPTIEMBRE | D77: P. SOCIAL | F77: 2 | G77: =+G76+E77-F77 -> 40.7
A78: 43066 | B78: 14117 | C78: SEPTIEMBRE | D78: LUZ | F78: 38.7 | G78: =+G77+E78-F78 -> 2
A79: 43066 | B79: 14117 | C79: SEPTIEMBRE | D79: AGUA | F79: 2 | G79: =+G78+E79-F79 -> 1.4210855e-14
A80: 43039 | B80: POR COBRAR | C80: OCTUBRE | D80: LUZ | E80: 38.5 | G80: =+G79+E80-F80 -> 38.5
D81: AGUA | E81: 2 | G81: =+G80+E81-F81 -> 40.5
D82: G. ADM | E82: 60 | G82: =+G81+E82-F82 -> 100.5
D83: P. SOCIAL | E83: 2 | G83: =+G82+E83-F83 -> 102.5
A84: 43039 | B84: TARJETA | C84: OCTUBRE | D84: G. ADM | F84: 60 | G84: =+G83+E84-F84 -> 42.5
A85: 43039 | B85: TARJETA | C85: OCTUBRE | D85: P. SOCIAL | F85: 2 | G85: =+G84+E85-F85 -> 40.5
A86: 43064 | B86: 14095 | C86: OCTUBRE | D86: LUZ | F86: 38.5 | G86: =+G85+E86-F86 -> 2
A87: 43064 | B87: 14095 | C87: OCTUBRE | D87: AGUA | F87: 2 | G87: =+G86+E87-F87 -> 1.4210855e-14
A88: 43069 | B88: POR COBRAR | C88: NOVIEMBRE | D88: LUZ | E88: 41.4 | G88: =+G87+E88-F88 -> 41.4
D89: AGUA | E89: 2 | G89: =+G88+E89-F89 -> 43.4
D90: G. ADM | E90: 60 | G90: =+G89+E90-F90 -> 103.4
D91: P. SOCIAL | E91: 2 | G91: =+G90+E91-F91 -> 105.4
A92: 43104 | B92: 14391 | C92: NOVIEMBRE | D92: LUZ | F92: 41.4 | G92: =+G91+E92-F92 -> 64
A93: 43104 | B93: 14391 | C93: NOVIEMBRE | D93: AGUA | F93: 2 | G93: =+G92+E93-F93 -> 62
A94: 43069 | B94: TARJETA | C94: NOVIEMBRE | D94: G. ADM | F94: 60 | G94: =+G93+E94-F94 -> 2
A95: 43069 | B95: TARJETA | C95: NOVIEMBRE | D95: P. SOCIAL | F95: 2 | G95: =+G94+E95-F95 -> 0
A96: 43100 | B96: POR COBRAR | C96: DICIEMBRE | D96: LUZ | E96: 62.6 | G96: =+G95+E96-F96 -> 62.6
D97: AGUA | E97: 2 | G97: =+G96+E97-F97 -> 64.6
D98: G. ADM | E98: 60 | G98: =+G97+E98-F98 -> 124.6
D99: P. SOCIAL | E99: 2 | G99: =+G98+E99-F99 -> 126.6
A100: 43099 | B100: TARJETA | C100: DICIEMBRE | D100: G. ADM | F100: 60 | G100: =+G99+E100-F100 -> 66.6
A101: 43099 | B101: TARJETA | C101: DICIEMBRE | D101: P. SOCIAL | F101: 2 | G101: =+G100+E101-F101 -> 64.6
A102: 43118 | B102: 14474 | C102: DICIEMBRE | D102: LUZ | F102: 62.6 | G102: =+G101+E102-F102 -> 2
...

Sheet ESTELA ELVIA
B2: ESTELA SUAREZ ELVIA
A4: FECHA | B4: DOCUMENTO | C4: PERIODO | D4: CONCEPTO | E4: POR COBRAR | F4: PAGADO | G4: SALDO POR COBRAR
A5: 42736 | B5: SALDO AL 2016 | G5: 253.8
A6: 42752 | B6: 12115 | C6: A CUENTA 2016 | F6: 181.8 | G6: =+G5+E6-F6 -> 72
A7: 42786 | B7: 12268 | C7: A CUENTA 2016 | F7: 10.8 | G7: =+G6+E7-F7 -> 61.2
A8: 42817 | B8: 12451 | C8: A CUENTA 2016 | F8: 8 | G8: =+G7+E8-F8 -> 53.2
A9: 42845 | B9: 12669 | C9: A CUENTA 2016 | F9: 8 | G9: =+G8+E9-F9 -> 45.2
A10: 42871 | B10: 12759 | C10: A CUENTA 2016 | F10: 8 | G10: =+G9+E10-F10 -> 37.2
A11: 42906 | B11: 13117 | C11: A CUENTA 2016 | F11: 8 | G11: =+G10+E11-F11 -> 29.2
A12: 42941 | B12: 13254 | C12: A CUENTA 2016 | F12: 8 | G12: =+G11+E12-F12 -> 21.2
A13: 42969 | B13: 13450 | C13: A CUENTA 2016 | F13: 8 | G13: =+G12+E13-F13 -> 13.2
A14: 42997 | B14: 13620 | C14: CANCELACION 2016 | F14: 13.2 | G14: =+G13+E14-F14 -> 0
A15: 42766 | B15: POR COBRAR | C15: ENERO | D15: LUZ | E15: 75.2 | G15: =+G14+E15-F15 -> 75.2
D16: AGUA | E16: 32.2 | G16: =+G15+E16-F16 -> 107.4
D17: G. ADM | E17: 60 | G17: =+G16+E17-F17 -> 167.4
D18: P. SOCIAL | E18: 2 | G18: =+G17+E18-F18 -> 169.4
A19: 42786 | B19: 12268 | C19: ENERO | D19: LUZ | F19: 75.2 | G19: =+G18+E19-F19 -> 94.2
A20: 42787 | B20: 12342 | C20: ENERO | D20: AGUA | F20: 32.2 | G20: =+G19+E20-F20 -> 62
A21: 42787 | B21: 12342 | C21: ENERO | D21: G. ADM | F21: 60 | G21: =+G20+E21-F21 -> 2
A22: 42787 | B22: 12342 | C22: ENERO | D22: P. SOCIAL | F22: 2 | G22: =+G21+E22-F22 -> 0
A23: 42794 | B23: POR COBRAR | C23: FEBRERO | D23: LUZ | E23: 77.1 | G23: =+G22+E23-F23 -> 77.1
D24: AGUA | E24: 24.5 | G24: =+G23+E24-F24 -> 101.6
D25: G. ADM | E25: 56 | G25: =+G24+E25-F25 -> 157.6
D26: P. SOCIAL | E26: 2 | G26: =+G25+E26-F26 -> 159.6
A27: 42817 | B27: 12451 | C27: FEBRERO | D27: G. ADM | F27: 56 | G27: =+G26+E27-F27 -> 103.6
A28: 42817 | B28: 12451 | C28: FEBRERO | D28: P. SOCIAL | F28: 2 | G28: =+G27+E28-F28 -> 101.6
A29: 42817 | B29: 12451 | C29: FEBRERO | D29: LUZ | F29: 77.1 | G29: =+G28+E29-F29 -> 24.5
A30: 42807 | B30: 12451 | C30: FEBRERO | D30: AGUA | F30: 24.5 | G30: =+G29+E30-F30 -> 0
A31: 42825 | B31: POR COBRAR | C31: MARZO | D31: LUZ | E31: 73.8 | G31: =+G30+E31-F31 -> 73.8
D32: AGUA | E32: 25.5 | G32: =+G31+E32-F32 -> 99.3
D33: G. ADM | E33: 60 | G33: =+G32+E33-F33 -> 159.3
D34: P. SOCIAL | E34: 2 | G34: =+G33+E34-F34 -> 161.3
A35: 42845 | B35: 12669 | C35: MARZO | D35: G. ADM | F35: 60 | G35: =+G34+E35-F35 -> 101.3
A36: 42845 | B36: 12669 | C36: MARZO | D36: P. SOCIAL | F36: 2 | G36: =+G35+E36-F36 -> 99.3
A37: 42845 | B37: 12669 | C37: MARZO | D37: LUZ | F37: 73.8 | G37: =+G36+E37-F37 -> 25.5
A38: 42845 | B38: 12669 | C38: MARZO | D38: AGUA | F38: 25.5 | G38: =+G37+E38-F38 -> 0
A39: 42855 | B39: POR COBRAR | C39: ABRIL | D39: LUZ | E39: 75.4 | G39: =+G38+E39-F39 -> 75.4
D40: AGUA | E40: 22.8 | G40: =+G39+E40-F40 -> 98.2
D41: G. ADM | E41: 60 | G41: =+G40+E41-F41 -> 158.2
D42: P. SOCIAL | E42: 2 | G42: =+G41+E42-F42 -> 160.2
A43: 42871 | B43: 12759 | C43: ABRIL | D43: G. ADM | F43: 60 | G43: =+G42+E43-F43 -> 100.2
A44: 42871 | B44: 12759 | C44: ABRIL | D44: P. SOCIAL | F44: 2 | G44: =+G43+E44-F44 -> 98.2
A45: 42871 | B45: 12759 | C45: ABRIL | D45: LUZ | F45: 75.4 | G45: =+G44+E45-F45 -> 22.8
A46: 42871 | B46: 12759 | C46: ABRIL | D46: AGUA | F46: 22.8 | G46: =+G45+E46-F46 -> 0
A47: 42886 | B47: POR COBRAR | C47: MAYO | D47: LUZ | E47: 70.4 | G47: =+G46+E47-F47 -> 70.4
D48: AGUA | E48: 24.5 | G48: =+G47+E48-F48 -> 94.9
D49: G. ADM | E49: 60 | G49: =+G48+E49-F49 -> 154.9
D50: P. SOCIAL | E50: 2 | G50: =+G49+E50-F50 -> 156.9
A51: 42906 | B51: 13117 | C51: MAYO | D51: LUZ | F51: 70.4 | G51: =+G50+E51-F51 -> 86.5
A52: 42906 | B52: 13117 | C52: MAYO | D52: AGUA | F52: 24.5 | G52: =+G51+E52-F52 -> 62
A53: 42906 | B53: 13117 | C53: MAYO | D53: G. ADM | F53: 60 | G53: =+G52+E53-F53 -> 2
A54: 42906 | B54: 13117 | C54: MAYO | D54: P. SOCIAL | F54: 2 | G54: =+G53+E54-F54 -> 0
A55: 42916 | B55: POR COBRAR | C55: JUNIO | D55: LUZ | E55: 68.8 | G55: =+G54+E55-F55 -> 68.8
D56: AGUA | E56: 24.5 | G56: =+G55+E56-F56 -> 93.3
D57: G. ADM | E57: 60 | G57: =+G56+E57-F57 -> 153.3
D58: P. SOCIAL | E58: 2 | G58: =+G57+E58-F58 -> 155.3
A59: 42941 | B59: 13254 | C59: JUNIO | D59: G. ADM | F59: 2 | G59: =+G58+E59-F59 -> 153.3
A60: 42941 | B60: 13254 | C60: JUNIO | D60: P. SOCIAL | F60: 60 | G60: =+G59+E60-F60 -> 93.3
A61: 42941 | B61: 13254 | C61: JUNIO | D61: LUZ | F61: 68.8 | G61: =+G60+E61-F61 -> 24.5
A62: 42941 | B62: 13254 | C62: JUNIO | D62: AGUA | F62: 24.5 | G62: =+G61+E62-F62 -> 0
A63: 42947 | B63: POR COBRAR | C63: JULIO | D63: LUZ | E63: 62.3 | G63: =+G62+E63-F63 -> 62.3
D64: AGUA | E64: 25 | G64: =+G63+E64-F64 -> 87.3
D65: G. ADM | E65: 60 | G65: =+G64+E65-F65 -> 147.3
D66: P. SOCIAL | E66: 2 | G66: =+G65+E66-F66 -> 149.3
A67: 42949 | B67: 13346 | C67: JULIO | D67: G. ADM | F67: 60 | G67: =+G66+E67-F67 -> 89.3
A68: 42949 | B68: 13346 | C68: JULIO | D68: P. SOCIAL | F68: 2 | G68: =+G67+E68-F68 -> 87.3
A69: 42969 | B69: 13450 | C69: JULIO | D69: LUZ | F69: 62.3 | G69: =+G68+E69-F69 -> 25
A70: 42969 | B70: 13450 | C70: JULIO | D70: AGUA | F70: 25 | G70: =+G69+E70-F70 -> 0
A71: 42978 | B71: POR COBRAR | C71: AGOSTO | D71: LUZ | E71: 62.3 | G71: =+G70+E71-F71 -> 62.3
D72: AGUA | E72: 25 | G72: =+G71+E72-F72 -> 87.3
D73: G. ADM | E73: 60 | G73: =+G72+E73-F73 -> 147.3
D74: P. SOCIAL | E74: 2 | G74: =+G73+E74-F74 -> 149.3
A75: 42997 | B75: 13620 | C75: AGOSTO | D75: G. ADM | F75: 60 | G75: =+G74+E75-F75 -> 89.3
A76: 42997 | B76: 13620 | C76: AGOSTO | D76: P. SOCIAL | F76: 2 | G76: =+G75+E76-F76 -> 87.3
A77: 42997 | B77: 13620 | C77: AGOSTO | D77: LUZ | F77: 62.3 | G77: =+G76+E77-F77 -> 25
A78: 42997 | B78: 13620 | C78: AGOSTO | D78: AGUA | F78: 25 | G78: =+G77+E78-F78 -> 0
A79: 43008 | B79: POR COBRAR | C79: SEPTIEMBRE | D79: LUZ | E79: 62.5 | G79: =+G78+E79-F79 -> 62.5
D80: AGUA | E80: 24.5 | G80: =+G79+E80-F80 -> 87
D81: G. ADM | E81: 60 | G81: =+G80+E81-F81 -> 147
D82: P. SOCIAL | E82: 2 | G82: =+G81+E82-F82 -> 149
A83: 43027 | B83: 13834 | C83: SEPTIEMBRE | D83: G. ADM | F83: 60 | G83: =+G82+E83-F83 -> 89
A84: 43027 | B84: 13834 | C84: SEPTIEMBRE | D84: P. SOCIAL | F84: 2 | G84: =+G83+E84-F84 -> 87
A85: 43027 | B85: 13834 | C85: SEPTIEMBRE | D85: LUZ | F85: 62.5 | G85: =+G84+E85-F85 -> 24.5
A86: 43027 | B86: 13834 | C86: SEPTIEMBRE | D86: AGUA | F86: 24.5 | G86: =+G85+E86-F86 -> 0
A87: 43039 | B87: POR COBRAR | C87: OCTUBRE | D87: LUZ | E87: 62.5 | G87: =+G86+E87-F87 -> 62.5
D88: AGUA | E88: 24.5 | G88: =+G87+E88-F88 -> 87
D89: G. ADM | E89: 60 | G89: =+G88+E89-F89 -> 147
D90: P. SOCIAL | E90: 2 | G90: =+G89+E90-F90 -> 149
A91: 43054 | B91: 13983 | C91: OCTUBRE | D91: G. ADM | F91: 60 | G91: =+G90+E91-F91 -> 89
A92: 43054 | B92: 13983 | C92: OCTUBRE | D92: P. SOCIAL | F92: 2 | G92: =+G91+E92-F92 -> 87
A93: 43063 | B93: 14039 | C93: OCTUBRE | D93: LUZ | F93: 62.5 | G93: =+G92+E93-F93 -> 24.5
A94: 43063 | B94: 14039 | C94: OCTUBRE | D94: AGUA | F94: 24.5 | G94: =+G93+E94-F94 -> 0
A95: 43069 | B95: POR COBRAR | C95: NOVIEMBRE | D95: LUZ | E95: 66.8 | G95: =+G94+E95-F95 -> 66.8
D96: AGUA | E96: 24.5 | G96: =+G95+E96-F96 -> 91.3
D97: G. ADM | E97: 60 | G97: =+G96+E97-F97 -> 151.3
D98: P. SOCIAL | E98: 2 | G98: =+G97+E98-F98 -> 153.3
A99: 43087 | B99: 14280 | C99: NOVIEMBRE | D99: LUZ | F99: 66.8 | G99: =+G98+E99-F99 -> 86.5
A100: 43087 | B100: 14280 | C100: NOVIEMBRE | D100: AGUA | F100: 24.5 | G100: =+G99+E100-F100 -> 62
A101: 43090 | B101: 14341 | C101: NOVIEMBRE | D101: G. ADM | F101: 60 | G101: =+G100+E101-F101 -> 2
A102: 43090 | B102: 14341 | C102: NOVIEMBRE | D102: P. SOCIAL | F102: 2 | G102: =+G101+E102-F102 -> 1.4210855e-14
...

Sheet ESTRADA  OSCAR
I1: ESTRADA OSORIO DONATO
B2: ESTRADA CHACON OSCAR ALFREDO
A4: FECHA | B4: DOCUMENTO | C4: PERIODO | D4: CONCEPTO | E4: POR COBRAR | F4: PAGADO | G4: SALDO POR COBRAR
A5: 42736 | B5: SALDO AL 2016 | G5: 1186.4
A6: 42736 | B6: MULTA POZO | E6: 100 | G6: =+G5+E6-F6 -> 1286.4
A7: 42756 | B7: 12131 | C7: A CUENTA2016 | F7: 101.9 | G7: =+G6+E7-F7 -> 1184.5
A8: 42781 | B8: 12955 | C8: A CUENTA2016 | F8: 100.5 | G8: =+G7+E8-F8 -> 1084
A9: 43176 | B9: 14832 | C9: A CUENTA2016 | F9: 600 | G9: =+G8+E9-F9 -> 484
A10: 43193 | B10: 15078 | C10: A CUENTA2016 | F10: 281 | G10: =+G9+E10-F10 -> 203
A11: 43220 | B11: 15279 | C11: CANCELACION TOTAL 2016 | F11: 203 | G11: =+G10+E11-F11 -> 0
A12: 42766 | B12: POR COBRAR | C12: ENERO | D12: LUZ | E12: 39.1 | G12: =+G11+E12-F12 -> 39.1
D13: AGUA | E13: 66.5 | G13: =+G12+E13-F13 -> 105.6
D14: G. ADM | E14: 60 | G14: =+G13+E14-F14 -> 165.6
D15: P. SOCIAL | E15: 2 | G15: =+G14+E15-F15 -> 167.6
A16: 42765 | B16: TARJETA | C16: ENERO | D16: G. ADM | F16: 60 | G16: =+G15+E16-F16 -> 107.6
A17: 42765 | B17: TARJETA | C17: ENERO | D17: P. SOCIAL | F17: 2 | G17: =+G16+E17-F17 -> 105.6
A18: 42817 | B18: 12454 | C18: ENERO | D18: LUZ | F18: 39.1 | G18: =+G17+E18-F18 -> 66.5
A19: 42817 | B19: 12454 | C19: ENERO | D19: AGUA | F19: 66.5 | G19: =+G18+E19-F19 -> 0
A20: 42794 | B20: POR COBRAR | C20: FEBRERO | D20: LUZ | E20: 61.6 | G20: =+G19+E20-F20 -> 61.6
D21: AGUA | E21: 60 | G21: =+G20+E21-F21 -> 121.6
D22: G. ADM | E22: 56 | G22: =+G21+E22-F22 -> 177.6
D23: P. SOCIAL | E23: 2 | G23: =+G22+E23-F23 -> 179.6
A24: 42791 | B24: TARJETA | C24: FEBRERO | D24: G. ADM | F24: 50 | G24: =+G23+E24-F24 -> 129.6
A25: 42795 | B25: 12385 | C25: FEBRERO | D25: G. ADM | F25: 6 | G25: =+G24+E25-F25 -> 123.6
A26: 42767 | B26: 12385 | C26: FEBRERO | D26: P. SOCIAL | F26: 2 | G26: =+G25+E26-F26 -> 121.6
A27: 42817 | B27: 12454 | C27: FEBRERO | D27: LUZ | F27: 61.6 | G27: =+G26+E27-F27 -> 60
A28: 42817 | B28: 12454 | C28: FEBRERO | D28: AGUA | F28: 60 | G28: =+G27+E28-F28 -> 0
A29: 42825 | B29: POR COBRAR | C29: MARZO | D29: LUZ | E29: 58.9 | G29: =+G28+E29-F29 -> 58.9
D30: AGUA | E30: 48.9 | G30: =+G29+E30-F30 -> 107.8
D31: G. ADM | E31: 60 | G31: =+G30+E31-F31 -> 167.8
D32: P. SOCIAL | E32: 2 | G32: =+G31+E32-F32 -> 169.8
A33: 42825 | B33: TARJETA | C33: MARZO | D33: G. ADM | F33: 60 | G33: =+G32+E33-F33 -> 109.8
A34: 42825 | B34: TARJETA | C34: MARZO | D34: P. SOCIAL | F34: 2 | G34: =+G33+E34-F34 -> 107.8
A35: 42885 | B35: 12861 | C35: MARZO | D35: LUZ | F35: 58.9 | G35: =+G34+E35-F35 -> 48.9
A36: 42885 | B36: 12861 | C36: MARZO | D36: AGUA | F36: 48.9 | G36: =+G35+E36-F36 -> 0
A37: 42855 | B37: POR COBRAR | C37: ABRIL | D37: LUZ | E37: 60.3 | G37: =+G36+E37-F37 -> 60.3
D38: AGUA | E38: 48 | G38: =+G37+E38-F38 -> 108.3
D39: G. ADM | E39: 60 | G39: =+G38+E39-F39 -> 168.3
D40: P. SOCIAL | E40: 2 | G40: =+G39+E40-F40 -> 170.3
A41: 42855 | B41: TARJETA | C41: ABRIL | D41: G. ADM | F41: 60 | G41: =+G40+E41-F41 -> 110.3
A42: 42855 | B42: TARJETA | C42: ABRIL | D42: P. SOCIAL | F42: 2 | G42: =+G41+E42-F42 -> 108.3
A43: 43220 | B43: 15279 | C43: ABRIL | D43: LUZ | F43: 60.3 | G43: =+G42+E43-F43 -> 48
A44: 43220 | B44: 15279 | C44: ABRIL | D44: AGUA | F44: 48 | G44: =+G43+E44-F44 -> 0
A45: 42886 | B45: POR COBRAR | C45: MAYO | D45: LUZ | E45: 56.6 | G45: =+G44+E45-F45 -> 56.6
D46: AGUA | E46: 47 | G46: =+G45+E46-F46 -> 103.6
D47: G. ADM | E47: 60 | G47: =+G46+E47-F47 -> 163.6
D48: P. SOCIAL | E48: 2 | G48: =+G47+E48-F48 -> 165.6
A49: 42886 | B49: TARJETA | C49: MAYO | D49: G. ADM | F49: 60 | G49: =+G48+E49-F49 -> 105.6
A50: 42886 | B50: TARJETA | C50: MAYO | D50: P. SOCIAL | F50: 2 | G50: =+G49+E50-F50 -> 103.6
A51: 43220 | B51: 15279 | C51: MAYO | D51: LUZ | F51: 56.6 | G51: =+G50+E51-F51 -> 47
A52: 43220 | B52: 15279 | C52: MAYO | D52: AGUA | F52: 47 | G52: =+G51+E52-F52 -> 0
A53: 42916 | B53: POR COBRAR | C53: JUNIO | D53: LUZ | E53: 35.8 | G53: =+G52+E53-F53 -> 35.8
D54: AGUA | E54: 47 | G54: =+G53+E54-F54 -> 82.8
D55: G. ADM | E55: 60 | G55: =+G54+E55-F55 -> 142.8
D56: P. SOCIAL | E56: 2 | G56: =+G55+E56-F56 -> 144.8
A57: 42916 | B57: TARJETA | C57: JUNIO | D57: G. ADM | F57: 32 | G57: =+G56+E57-F57 -> 112.8
A58: 43220 | B58: 15279 | C58: JUNIO | D58: LUZ | F58: 35.8 | G58: =+G57+E58-F58 -> 77
A59: 43220 | B59: 15279 | C59: JUNIO | D59: AGUA | F59: 47 | G59: =+G58+E59-F59 -> 30
A60: 43220 | B60: 15279 | C60: JUNIO | D60: G. ADM | F60: 28 | G60: =+G59+E60-F60 -> 2
A61: 43220 | B61: 15279 | C61: JUNIO | D61: P. SOCIAL | F61: 2 | G61: =+G60+E61-F61 -> 1.4210855e-14
A62: 42947 | B62: POR COBRAR | C62: JULIO | D62: LUZ | E62: 50.4 | G62: =+G61+E62-F62 -> 50.4
D63: AGUA | E63: 47 | G63: =+G62+E63-F63 -> 97.4
D64: G. ADM | E64: 60 | G64: =+G63+E64-F64 -> 157.4
D65: P. SOCIAL | E65: 2 | G65: =+G64+E65-F65 -> 159.4
A66: 42945 | B66: TARJETA | C66: JULIO | D66: G. ADM | F66: 26 | G66: =+G65+E66-F66 -> 133.4
A67: 43220 | B67: 15279 | C67: JULIO | D67: G. ADM | F67: 34 | G67: =+G66+E67-F67 -> 99.4
A68: 43220 | B68: 15279 | C68: JULIO | D68: P. SOCIAL | F68: 2 | G68: =+G67+E68-F68 -> 97.4
A69: 43220 | B69: 15279 | C69: JULIO | D69: AGUA | F69: 47 | G69: =+G68+E69-F69 -> 50.4
A70: 43220 | B70: 15279 | C70: JULIO | D70: LUZ | F70: 50.4 | G70: =+G69+E70-F70 -> 0
A71: 42978 | B71: POR COBRAR | C71: AGOSTO | D71: LUZ | E71: 50.4 | G71: =+G70+E71-F71 -> 50.4
D72: AGUA | E72: 47 | G72: =+G71+E72-F72 -> 97.4
D73: G. ADM | E73: 60 | G73: =+G72+E73-F73 -> 157.4
D74: P. SOCIAL | E74: 2 | G74: =+G73+E74-F74 -> 159.4
A75: 42978 | B75: TARJETA | C75: AGOSTO | D75: G. ADM | F75: 22 | G75: =+G74+E75-F75 -> 137.4
A76: 43220 | B76: 15279 | C76: AGOSTO | D76: G. ADM | F76: 38 | G76: =+G75+E76-F76 -> 99.4
A77: 43220 | B77: 15279 | C77: AGOSTO | D77: P. SOCIAL | F77: 2 | G77: =+G76+E77-F77 -> 97.4
A78: 43220 | B78: 15279 | C78: AGOSTO | D78: LUZ | F78: 50.4 | G78: =+G77+E78-F78 -> 47
A79: 43220 | B79: 15279 | C79: AGOSTO | D79: AGUA | F79: 47 | G79: =+G78+E79-F79 -> 0
A80: 43008 | B80: POR COBRAR | C80: SEPTIEMBRE | D80: LUZ | E80: 40.6 | G80: =+G79+E80-F80 -> 40.6
D81: AGUA | E81: 47 | G81: =+G80+E81-F81 -> 87.6
D82: G. ADM | E82: 60 | G82: =+G81+E82-F82 -> 147.6
D83: P. SOCIAL | E83: 2 | G83: =+G82+E83-F83 -> 149.6
A84: 42788 | D84: MULTA | E84: 85 | G84: =+G83+E84-F84 -> 234.6
A85: 42823 | D85: MULTA | E85: 85 | G85: =+G84+E85-F85 -> 319.6
A86: 42951 | D86: MULTA | E86: 85 | G86: =+G85+E86-F86 -> 404.6
A87: 43008 | B87: TARJETA | C87: SEPTIEMBRE | D87: G. ADM | F87: 30 | G87: =+G86+E87-F87 -> 374.6
A88: 43220 | B88: 15279 | C88: SEPTIEMBRE | D88: LUZ | F88: 40.6 | G88: =+G87+E88-F88 -> 334
A89: 43220 | B89: 15279 | C89: SEPTIEMBRE | D89: AGUA | F89: 47 | G89: =+G88+E89-F89 -> 287
A90: 43220 | B90: 15279 | C90: SEPTIEMBRE | D90: G. ADM | F90: 30 | G90: =+G89+E90-F90 -> 257
A91: 43220 | B91: 15279 | C91: SEPTIEMBRE | D91: P. SOCIAL | F91: 2 | G91: =+G90+E91-F91 -> 255
A92: 43220 | B92: 15279 | C92: SEPTIEMBRE | D92: MULTA | F92: 85 | G92: =+G91+E92-F92 -> 170
A93: 43220 | B93: 15279 | C93: SEPTIEMBRE | D93: MULTA | F93: 85 | G93: =+G92+E93-F93 -> 85
A94: 43220 | B94: 15279 | C94: SEPTIEMBRE | D94: MULTA | F94: 85 | G94: =+G93+E94-F94 -> 0
A95: 43039 | B95: POR COBRAR | C95: OCTUBRE | D95: LUZ | E95: 40.4 | G95: =+G94+E95-F95 -> 40.4
D96: AGUA | E96: 47 | G96: =+G95+E96-F96 -> 87.4
D97: G. ADM | E97: 60 | G97: =+G96+E97-F97 -> 147.4
D98: P. SOCIAL | E98: 2 | G98: =+G97+E98-F98 -> 149.4
A99: 42977 | B99: ACT. SANTA ROSA | D99: CUOTA | E99: 10 | G99: =+G98+E99-F99 -> 159.4
A100: 43039 | B100: TARJETA | C100: OCTUBRE | D100: G. ADM | F100: 34 | G100: =+G99+E100-F100 -> 125.4
A101: 43220 | B101: 15279 | C101: OCTUBRE | D101: G. ADM | F101: 26 | G101: =+G100+E101-F101 -> 99.4
...

Sheet FALCON HECTOR 
B2: FALCON CHIARA HECTOR
A4: FECHA | B4: DOCUMENTO | C4: PERIODO | D4: CONCEPTO | E4: POR COBRAR | F4: PAGADO | G4: SALDO POR COBRAR
A5: 42736 | B5: SALDO AL 2016 | G5: 80.3
A6: 42786 | B6: 12286 | C6: A CUENTA 2016 | F6: 80.3 | G6: =+G5+E6-F6 -> 0
A7: 42766 | B7: POR COBRAR | C7: ENERO | D7: LUZ | E7: 99.3 | G7: =+G6+E7-F7 -> 99.3
D8: AGUA | E8: 2.8 | G8: =+G7+E8-F8 -> 102.1
D9: G. ADM | E9: 60 | G9: =+G8+E9-F9 -> 162.1
D10: P. SOCIAL | E10: 2 | G10: =+G9+E10-F10 -> 164.1
D11: DEPOSITO | E11: 70 | G11: =+G10+E11-F11 -> 234.1
A12: 42756 | B12: 12132 | C12: ENERO | D12: G. ADM | F12: 60 | G12: =+G11+E12-F12 -> 174.1
A13: 42756 | B13: 12132 | C13: ENERO | D13: P. SOCIAL | F13: 2 | G13: =+G12+E13-F13 -> 172.1
A14: 42786 | B14: 12286 | C14: ENERO | D14: LUZ | F14: 99.3 | G14: =+G13+E14-F14 -> 72.8
A15: 42786 | B15: 12286 | C15: ENERO | D15: AGUA | F15: 2.8 | G15: =+G14+E15-F15 -> 70
A16: 42822 | B16: 12602 | C16: ENERO | D16: DEPOSITO | F16: 70 | G16: =+G15+E16-F16 -> 0
A17: 42794 | B17: POR COBRAR | C17: FEBRERO | D17: LUZ | E17: 101.1 | G17: =+G16+E17-F17 -> 101.1
D18: AGUA | E18: 2 | G18: =+G17+E18-F18 -> 103.1
D19: G. ADM | E19: 60 | G19: =+G18+E19-F19 -> 163.1
D20: P. SOCIAL | E20: 2 | G20: =+G19+E20-F20 -> 165.1
D21: DEPOSITO | E21: 70 | G21: =+G20+E21-F21 -> 235.1
A22: 42782 | B22: 12959 | C22: FEBRERO | D22: G. ADM | F22: 60 | G22: =+G21+E22-F22 -> 175.1
A23: 42782 | B23: 12959 | C23: FEBRERO | D23: P. SOCIAL | F23: 2 | G23: =+G22+E23-F23 -> 173.1
A24: 42822 | B24: 12602 | C24: FEBRERO | D24: LUZ | F24: 101.1 | G24: =+G23+E24-F24 -> 72
A25: 42822 | B25: 12602 | C25: FEBRERO | D25: AGUA | F25: 2 | G25: =+G24+E25-F25 -> 70
A26: 42822 | B26: 12602 | C26: FEBRERO | D26: DEPOSITO | F26: 70 | G26: =+G25+E26-F26 -> 0
A27: 42825 | B27: POR COBRAR | C27: MARZO | D27: LUZ | E27: 86.8 | G27: =+G26+E27-F27 -> 86.8
D28: AGUA | E28: 2 | G28: =+G27+E28-F28 -> 88.8
D29: G. ADM | E29: 60 | G29: =+G28+E29-F29 -> 148.8
D30: P. SOCIAL | E30: 2 | G30: =+G29+E30-F30 -> 150.8
D31: CAMBIO DE GIRO | E31: 300 | G31: =+G30+E31-F31 -> 450.8
D32: DEPOSITO | E32: 70 | G32: =+G31+E32-F32 -> 520.8
A33: 42804 | B33: 12412 | C33: MARZO | D33: CAMBIO DE GIRO | F33: 300 | G33: =+G32+E33-F33 -> 220.8
A34: 42821 | B34: 12491 | C34: MARZO | D34: G. ADM | F34: 60 | G34: =+G33+E34-F34 -> 160.8
A35: 42821 | B35: 12491 | C35: MARZO | D35: P. SOCIAL | F35: 2 | G35: =+G34+E35-F35 -> 158.8
A36: 42885 | B36: 12868 | C36: MARZO | D36: LUZ | F36: 86.8 | G36: =+G35+E36-F36 -> 72
A37: 42885 | B37: 12868 | C37: MARZO | D37: AGUA | F37: 2 | G37: =+G36+E37-F37 -> 70
A38: 42885 | B38: 12868 | C38: MARZO | D38: DEPOSITO | F38: 70 | G38: =+G37+E38-F38 -> 0
A39: 42855 | B39: POR COBRAR | C39: ABRIL | D39: LUZ | E39: 89.4 | G39: =+G38+E39-F39 -> 89.4
D40: AGUA | E40: 2 | G40: =+G39+E40-F40 -> 91.4
D41: G. ADM | E41: 60 | G41: =+G40+E41-F41 -> 151.4
D42: P. SOCIAL | E42: 2 | G42: =+G41+E42-F42 -> 153.4
D43: DEPOSITO | E43: 70 | G43: =+G42+E43-F43 -> 223.4
A44: 42877 | B44: 12800 | C44: ABRIL | D44: G. ADM | F44: 60 | G44: =+G43+E44-F44 -> 163.4
A45: 42877 | B45: 12800 | C45: ABRIL | D45: P. SOCIAL | F45: 2 | G45: =+G44+E45-F45 -> 161.4
A46: 42885 | B46: 12868 | C46: ABRIL | D46: LUZ | F46: 89.4 | G46: =+G45+E46-F46 -> 72
A47: 42885 | B47: 12868 | C47: ABRIL | D47: AGUA | F47: 2 | G47: =+G46+E47-F47 -> 70
A48: 42885 | B48: 12868 | C48: ABRIL | D48: DEPOSITO | F48: 70 | G48: =+G47+E48-F48 -> 0
A49: 42886 | B49: POR COBRAR | C49: MAYO | D49: LUZ | E49: 49.8 | G49: =+G48+E49-F49 -> 49.8
D50: AGUA | E50: 2 | G50: =+G49+E50-F50 -> 51.8
D51: G. ADM | E51: 60 | G51: =+G50+E51-F51 -> 111.8
D52: P. SOCIAL | E52: 2 | G52: =+G51+E52-F52 -> 113.8
D53: DEPOSITO | E53: 70 | G53: =+G52+E53-F53 -> 183.8
A54: 42928 | B54: 13201 | C54: MAYO | D54: G. ADM | F54: 60 | G54: =+G53+E54-F54 -> 123.8
A55: 42928 | B55: 13201 | C55: MAYO | D55: P. SOCIAL | F55: 2 | G55: =+G54+E55-F55 -> 121.8
A56: 42949 | B56: 13367 | C56: MAYO | D56: LUZ | F56: 49.8 | G56: =+G55+E56-F56 -> 72
A57: 42949 | B57: 13367 | C57: MAYO | D57: AGUA | F57: 2 | G57: =+G56+E57-F57 -> 70
A58: 42949 | B58: 13367 | C58: MAYO | D58: DEPOSITO | F58: 70 | G58: =+G57+E58-F58 -> 0
A59: 42916 | B59: POR COBRAR | C59: JUNIO | D59: LUZ | E59: 48.3 | G59: =+G58+E59-F59 -> 48.3
D60: AGUA | E60: 2 | G60: =+G59+E60-F60 -> 50.3
D61: G. ADM | E61: 60 | G61: =+G60+E61-F61 -> 110.3
D62: P. SOCIAL | E62: 2 | G62: =+G61+E62-F62 -> 112.3
D63: DEPOSITO | E63: 70 | G63: =+G62+E63-F63 -> 182.3
A64: 42928 | B64: 13201 | C64: JUNIO | D64: G. ADM | F64: 60 | G64: =+G63+E64-F64 -> 122.3
A65: 42928 | B65: 13201 | C65: JUNIO | D65: P. SOCIAL | F65: 2 | G65: =+G64+E65-F65 -> 120.3
A66: 42949 | B66: 13367 | C66: JUNIO | D66: LUZ | F66: 48.3 | G66: =+G65+E66-F66 -> 72
A67: 42949 | B67: 13367 | C67: JUNIO | D67: AGUA | F67: 2 | G67: =+G66+E67-F67 -> 70
A68: 42949 | B68: 13367 | C68: JUNIO | D68: DEPOSITO | F68: 70 | G68: =+G67+E68-F68 -> 0
A69: 42947 | B69: POR COBRAR | C69: JULIO | D69: LUZ | E69: 49 | G69: =+G68+E69-F69 -> 49
D70: AGUA | E70: 2 | G70: =+G69+E70-F70 -> 51
D71: G. ADM | E71: 60 | G71: =+G70+E71-F71 -> 111
D72: P. SOCIAL | E72: 2 | G72: =+G71+E72-F72 -> 113
D73: DEPOSITO | E73: 70 | G73: =+G72+E73-F73 -> 183
A74: 42928 | B74: 13201 | C74: JULIO | D74: G. ADM | F74: 60 | G74: =+G73+E74-F74 -> 123
A75: 42928 | B75: 13201 | C75: JULIO | D75: P. SOCIAL | F75: 2 | G75: =+G74+E75-F75 -> 121
A76: 42997 | B76: 13614 | C76: JULIO | D76: LUZ | F76: 49 | G76: =+G75+E76-F76 -> 72
A77: 42997 | B77: 13614 | C77: JULIO | D77: LUZ | F77: 2 | G77: =+G76+E77-F77 -> 70
A78: 43062 | B78: 14022 | C78: JULIO | D78: DEPOSITO | F78: 70 | G78: =+G77+E78-F78 -> 0
A79: 42978 | B79: POR COBRAR | C79: AGOSTO | D79: LUZ | E79: 49 | G79: =+G78+E79-F79 -> 49
D80: AGUA | E80: 2 | G80: =+G79+E80-F80 -> 51
D81: G. ADM | E81: 60 | G81: =+G80+E81-F81 -> 111
D82: P. SOCIAL | E82: 2 | G82: =+G81+E82-F82 -> 113
D83: DEPOSITO | E83: 70 | G83: =+G82+E83-F83 -> 183
A84: 42961 | B84: 13433 | C84: AGOSTO | D84: G. ADM | F84: 60 | G84: =+G83+E84-F84 -> 123
A85: 42961 | B85: 13433 | C85: AGOSTO | D85: P. SOCIAL | F85: 2 | G85: =+G84+E85-F85 -> 121
A86: 42997 | B86: 13614 | C86: AGOSTO | D86: LUZ | F86: 49 | G86: =+G85+E86-F86 -> 72
A87: 42997 | B87: 13614 | C87: AGOSTO | D87: AGUA | F87: 2 | G87: =+G86+E87-F87 -> 70
A88: 43062 | B88: 14022 | C88: AGOSTO | D88: DEPOSITO | F88: 70 | G88: =+G87+E88-F88 -> 0
A89: 43008 | B89: POR COBRAR | C89: SEPTIEMBRE | D89: LUZ | E89: 23.2 | G89: =+G88+E89-F89 -> 23.2
D90: AGUA | E90: 2 | G90: =+G89+E90-F90 -> 25.2
D91: G. ADM | E91: 60 | G91: =+G90+E91-F91 -> 85.2
D92: P. SOCIAL | E92: 2 | G92: =+G91+E92-F92 -> 87.2
D93: DEPOSITO | E93: 70 | G93: =+G92+E93-F93 -> 157.2
A94: 43062 | B94: 14019 | C94: SEPTIEMBRE | D94: G. ADM | F94: 60 | G94: =+G93+E94-F94 -> 97.2
A95: 43062 | B95: 14019 | C95: SEPTIEMBRE | D95: P. SOCIAL | F95: 2 | G95: =+G94+E95-F95 -> 95.2
A96: 43062 | B96: 14022 | C96: SEPTIEMBRE | D96: LUZ | F96: 23.2 | G96: =+G95+E96-F96 -> 72
A97: 43062 | B97: 14022 | C97: SEPTIEMBRE | D97: AGUA | F97: 2 | G97: =+G96+E97-F97 -> 70
A98: 43062 | B98: 14022 | C98: SEPTIEMBRE | D98: DEPOSITO | F98: 70 | G98: =+G97+E98-F98 -> 0
A99: 43039 | B99: POR COBRAR | C99: OCTUBRE | D99: LUZ | E99: 23.1 | G99: =+G98+E99-F99 -> 23.1
D100: AGUA | E100: 2 | G100: =+G99+E100-F100 -> 25.1
D101: G. ADM | E101: 60 | G101: =+G100+E101-F101 -> 85.1
D102: P. SOCIAL | E102: 2 | G102: =+G101+E102-F102 -> 87.1
...

Sheet FLORES FLORES IRENE
B2: FLORES FLORES IRENE BERTILIA
A4: FECHA | B4: DOCUMENTO | C4: PERIODO | D4: CONCEPTO | E4: POR COBRAR | F4: PAGADO | G4: SALDO POR COBRAR
A5: 42736 | B5: SALDO AL 2016 | G5: 99.5
A6: 42765 | B6: 12179 | C6: A CUENTA 2016 | F6: 99.5 | G6: =+G5+E6-F6 -> 0
A7: 42766 | B7: POR COBRAR | C7: ENERO | D7: LUZ | E7: 180 | G7: =+G6+E7-F7 -> 180
D8: AGUA | E8: 39 | G8: =+G7+E8-F8 -> 219
D9: G. ADM | E9: 60 | G9: =+G8+E9-F9 -> 279
D10: P. SOCIAL | E10: 2 | G10: =+G9+E10-F10 -> 281
A11: 42765 | B11: TARJETA | C11: ENERO | D11: LUZ | F11: 169 | G11: =+G10+E11-F11 -> 112
A12: 42765 | B12: TARJETA | C12: ENERO | D12: G. ADM | F12: 60 | G12: =+G11+E12-F12 -> 52
A13: 42765 | B13: TARJETA | C13: ENERO | D13: P. SOCIAL | F13: 2 | G13: =+G12+E13-F13 -> 50
A14: 42786 | B14: 12235 | C14: ENERO | D14: LUZ | F14: 11 | G14: =+G13+E14-F14 -> 39
A15: 42786 | B15: 12235 | C15: ENERO | D15: AGUA | F15: 39 | G15: =+G14+E15-F15 -> 0
A16: 42794 | B16: POR COBRAR | C16: FEBRERO | D16: LUZ | E16: 197.5 | G16: =+G15+E16-F16 -> 197.5
D17: AGUA | E17: 25 | G17: =+G16+E17-F17 -> 222.5
D18: G. ADM | E18: 56 | G18: =+G17+E18-F18 -> 278.5
D19: P. SOCIAL | E19: 2 | G19: =+G18+E19-F19 -> 280.5
A20: 42794 | B20: TARJETA | C20: FEBRERO | D20: G. ADM | F20: 56 | G20: =+G19+E20-F20 -> 224.5
A21: 42794 | B21: TARJETA | C21: FEBRERO | D21: P. SOCIAL | F21: 2 | G21: =+G20+E21-F21 -> 222.5
A22: 42794 | B22: TARJETA | C22: FEBRERO | D22: LUZ | F22: 168 | G22: =+G21+E22-F22 -> 54.5
A23: 42821 | B23: 12529 | C23: FEBRERO | D23: LUZ | F23: 29.5 | G23: =+G22+E23-F23 -> 25
A24: 42821 | B24: 12529 | C24: FEBRERO | D24: AGUA | F24: 25 | G24: =+G23+E24-F24 -> 0
A25: 42825 | B25: POR COBRAR | C25: MARZO | D25: LUZ | E25: 169.6 | G25: =+G24+E25-F25 -> 169.6
D26: AGUA | E26: 27 | G26: =+G25+E26-F26 -> 196.6
D27: G. ADM | E27: 60 | G27: =+G26+E27-F27 -> 256.6
D28: P. SOCIAL | E28: 2 | G28: =+G27+E28-F28 -> 258.6
A29: 42824 | B29: TARJETA | C29: MARZO | D29: G. ADM | F29: 60 | G29: =+G28+E29-F29 -> 198.6
A30: 42824 | B30: TARJETA | C30: MARZO | D30: P. SOCIAL | F30: 2 | G30: =+G29+E30-F30 -> 196.6
A31: 42824 | B31: TARJETA | C31: MARZO | D31: LUZ | F31: 169.6 | G31: =+G30+E31-F31 -> 27
A32: 42824 | B32: TARJETA | C32: MARZO | D32: AGUA | F32: 10.4 | G32: =+G31+E32-F32 -> 16.6
A33: 42886 | B33: 13006 | C33: MARZO | D33: AGUA | F33: 16.6 | G33: =+G32+E33-F33 -> 2.8421709e-14
A34: 42855 | B34: POR COBRAR | C34: ABRIL | D34: LUZ | E34: 156 | G34: =+G33+E34-F34 -> 156
D35: AGUA | E35: 25.5 | G35: =+G34+E35-F35 -> 181.5
D36: G. ADM | E36: 60 | G36: =+G35+E36-F36 -> 241.5
D37: P. SOCIAL | E37: 2 | G37: =+G36+E37-F37 -> 243.5
A38: 42854 | B38: TARJETA | C38: ABRIL | D38: G. ADM | F38: 60 | G38: =+G37+E38-F38 -> 183.5
A39: 42854 | B39: TARJETA | C39: ABRIL | D39: P. SOCIAL | F39: 2 | G39: =+G38+E39-F39 -> 181.5
A40: 42854 | B40: TARJETA | C40: ABRIL | D40: LUZ | F40: 156 | G40: =+G39+E40-F40 -> 25.5
A41: 42854 | B41: TARJETA | C41: ABRIL | D41: AGUA | F41: 1.5 | G41: =+G40+E41-F41 -> 24
A42: 42886 | B42: 13006 | C42: ABRIL | D42: AGUA | F42: 24 | G42: =+G41+E42-F42 -> 2.8421709e-14
A43: 42886 | B43: POR COBRAR | C43: MAYO | D43: LUZ | E43: 144.7 | G43: =+G42+E43-F43 -> 144.7
D44: AGUA | E44: 35.3 | G44: =+G43+E44-F44 -> 180
D45: G. ADM | E45: 60 | G45: =+G44+E45-F45 -> 240
D46: P. SOCIAL | E46: 2 | G46: =+G45+E46-F46 -> 242
A47: 42885 | B47: TARJETA | C47: MAYO | D47: LUZ | F47: 144.7 | G47: =+G46+E47-F47 -> 97.3
A48: 42885 | B48: TARJETA | C48: MAYO | D48: AGUA | F48: 35.3 | G48: =+G47+E48-F48 -> 62
A49: 42885 | B49: TARJETA | C49: MAYO | D49: P. SOCIAL | F49: 2 | G49: =+G48+E49-F49 -> 60
A50: 42885 | B50: TARJETA | C50: MAYO | D50: G. ADM | F50: 60 | G50: =+G49+E50-F50 -> 0
A51: 42916 | B51: POR COBRAR | C51: JUNIO | D51: LUZ | E51: 141.6 | G51: =+G50+E51-F51 -> 141.6
D52: AGUA | E52: 38.4 | G52: =+G51+E52-F52 -> 180
D53: G. ADM | E53: 60 | G53: =+G52+E53-F53 -> 240
D54: P. SOCIAL | E54: 2 | G54: =+G53+E54-F54 -> 242
A55: 42916 | B55: TARJETA | C55: JUNIO | D55: LUZ | F55: 141.6 | G55: =+G54+E55-F55 -> 100.4
A56: 42916 | B56: TARJETA | C56: JUNIO | D56: AGUA | F56: 38.4 | G56: =+G55+E56-F56 -> 62
A57: 42916 | B57: TARJETA | C57: JUNIO | D57: P. SOCIAL | F57: 2 | G57: =+G56+E57-F57 -> 60
A58: 42916 | B58: TARJETA | C58: JUNIO | D58: G. ADM | F58: 60 | G58: =+G57+E58-F58 -> 0
A59: 42947 | B59: POR COBRAR | C59: JULIO | D59: LUZ | E59: 155 | G59: =+G58+E59-F59 -> 155
D60: AGUA | E60: 25 | G60: =+G59+E60-F60 -> 180
D61: G. ADM | E61: 60 | G61: =+G60+E61-F61 -> 240
D62: P. SOCIAL | E62: 2 | G62: =+G61+E62-F62 -> 242
A63: 42947 | B63: TARJETA | C63: JULIO | D63: G. ADM | F63: 2 | G63: =+G62+E63-F63 -> 240
A64: 42947 | B64: TARJETA | C64: JULIO | D64: P. SOCIAL | F64: 60 | G64: =+G63+E64-F64 -> 180
A65: 42947 | B65: TARJETA | C65: JULIO | D65: LUZ | F65: 155 | G65: =+G64+E65-F65 -> 25
A66: 42947 | B66: TARJETA | C66: JULIO | D66: AGUA | F66: 25 | G66: =+G65+E66-F66 -> 0
A67: 42978 | B67: POR COBRAR | C67: AGOSTO | D67: LUZ | E67: 155 | G67: =+G66+E67-F67 -> 155
D68: AGUA | E68: 25 | G68: =+G67+E68-F68 -> 180
D69: G. ADM | E69: 60 | G69: =+G68+E69-F69 -> 240
D70: P. SOCIAL | E70: 2 | G70: =+G69+E70-F70 -> 242
A71: 42978 | B71: TARJETA | C71: AGOSTO | D71: G. ADM | F71: 60 | G71: =+G70+E71-F71 -> 182
A72: 42978 | B72: TARJETA | C72: AGOSTO | D72: P. SOCIAL | F72: 2 | G72: =+G71+E72-F72 -> 180
A73: 42978 | B73: TARJETA | C73: AGOSTO | D73: LUZ | F73: 155 | G73: =+G72+E73-F73 -> 25
A74: 42978 | B74: TARJETA | C74: AGOSTO | D74: AGUA | F74: 25 | G74: =+G73+E74-F74 -> 0
A75: 43008 | B75: POR COBRAR | C75: SEPTIEMBRE | D75: LUZ | E75: 130.5 | G75: =+G74+E75-F75 -> 130.5
D76: AGUA | E76: 25 | G76: =+G75+E76-F76 -> 155.5
D77: G. ADM | E77: 60 | G77: =+G76+E77-F77 -> 215.5
D78: P. SOCIAL | E78: 2 | G78: =+G77+E78-F78 -> 217.5
A79: 43008 | B79: TARJETA | C79: SEPTIEMBRE | D79: G. ADM | F79: 60 | G79: =+G78+E79-F79 -> 157.5
A80: 43008 | B80: TARJETA | C80: SEPTIEMBRE | D80: P. SOCIAL | F80: 2 | G80: =+G79+E80-F80 -> 155.5
A81: 43008 | B81: TARJETA | C81: SEPTIEMBRE | D81: LUZ | F81: 130.5 | G81: =+G80+E81-F81 -> 25
A82: 43008 | B82: TARJETA | C82: SEPTIEMBRE | D82: AGUA | F82: 25 | G82: =+G81+E82-F82 -> 0
A83: 43039 | B83: POR COBRAR | C83: OCTUBRE | D83: LUZ | E83: 129.9 | G83: =+G82+E83-F83 -> 129.9
D84: AGUA | E84: 25 | G84: =+G83+E84-F84 -> 154.9
D85: G. ADM | E85: 60 | G85: =+G84+E85-F85 -> 214.9
D86: P. SOCIAL | E86: 2 | G86: =+G85+E86-F86 -> 216.9
A87: 43039 | B87: TARJETA | C87: OCTUBRE | D87: G. ADM | F87: 60 | G87: =+G86+E87-F87 -> 156.9
A88: 43039 | B88: TARJETA | C88: OCTUBRE | D88: P. SOCIAL | F88: 2 | G88: =+G87+E88-F88 -> 154.9
A89: 43008 | B89: TARJETA | C89: OCTUBRE | D89: LUZ | F89: 24.5 | G89: =+G88+E89-F89 -> 130.4
A90: 43039 | B90: TARJETA | C90: OCTUBRE | D90: LUZ | F90: 105.4 | G90: =+G89+E90-F90 -> 25
A91: 43039 | B91: TARJETA | C91: OCTUBRE | D91: AGUA | F91: 25 | G91: =+G90+E91-F91 -> 0
A92: 43069 | B92: POR COBRAR | C92: NOVIEMBRE | D92: LUZ | E92: 138.7 | G92: =+G91+E92-F92 -> 138.7
D93: AGUA | E93: 25 | G93: =+G92+E93-F93 -> 163.7
D94: G. ADM | E94: 60 | G94: =+G93+E94-F94 -> 223.7
D95: P. SOCIAL | E95: 2 | G95: =+G94+E95-F95 -> 225.7
A96: 43039 | B96: TARJETA | C96: NOVIEMBRE | D96: LUZ | F96: 49.6 | G96: =+G95+E96-F96 -> 176.1
A97: 43069 | B97: TARJETA | C97: NOVIEMBRE | D97: LUZ | F97: 89.1 | G97: =+G96+E97-F97 -> 87
A98: 43434 | B98: TARJETA | C98: NOVIEMBRE | D98: AGUA | F98: 24.9 | G98: =+G97+E98-F98 -> 62.1
A99: 43088 | B99: 14316 | C99: NOVIEMBRE | D99: AGUA | F99: 0.1 | G99: =+G98+E99-F99 -> 62
A100: 43069 | B100: TARJETA | C100: NOVIEMBRE | D100: G. ADM | F100: 38 | G100: =+G99+E100-F100 -> 24
A101: 43088 | B101: 14316 | C101: NOVIEMBRE | D101: G. ADM | F101: 22 | G101: =+G100+E101-F101 -> 2
A102: 43088 | B102: 14316 | C102: NOVIEMBRE | D102: P. SOCIAL | F102: 2 | G102: =+G101+E102-F102 -> 0
...

Sheet FLORES FLORES UMBELINA
B2: FLORES FLORES UMBELINA DORA
A4: FECHA | B4: DOCUMENTO | C4: PERIODO | D4: CONCEPTO | E4: POR COBRAR | F4: PAGADO | G4: SALDO POR COBRAR
A5: 42736 | B5: SALDO AL 2016 | G5: 680.2
A6: 42781 | B6: 12957 | C6: A CUENTA 2016 | F6: 291.7 | G6: =+G5+E6-F6 -> 388.5
A7: 43227 | B7: 15305 | C7: CANCELACION TOTAL 2016 | F7: 388.5 | G7: =+G6+E7-F7 -> 0
A8: 42766 | B8: POR COBRAR | C8: ENERO | D8: LUZ | E8: 91.4 | G8: =+G7+E8-F8 -> 91.4
D9: AGUA | E9: 39 | G9: =+G8+E9-F9 -> 130.4
D10: G. ADM | E10: 60 | G10: =+G9+E10-F10 -> 190.4
D11: P. SOCIAL | E11: 2 | G11: =+G10+E11-F11 -> 192.4
A12: 42765 | B12: TARJETA | C12: ENERO | D12: G. ADM | F12: 60 | G12: =+G11+E12-F12 -> 132.4
A13: 42765 | B13: TARJETA | C13: ENERO | D13: P. SOCIAL | F13: 2 | G13: =+G12+E13-F13 -> 130.4
A14: 42787 | B14: 12341 | C14: ENERO | D14: LUZ | F14: 91.4 | G14: =+G13+E14-F14 -> 39
A15: 42787 | B15: 12341 | C15: ENERO | D15: AGUA | F15: 39 | G15: =+G14+E15-F15 -> 0
A16: 42794 | B16: POR COBRAR | C16: FEBRERO | D16: LUZ | E16: 87 | G16: =+G15+E16-F16 -> 87
D17: AGUA | E17: 27.3 | G17: =+G16+E17-F17 -> 114.3
D18: G. ADM | E18: 56 | G18: =+G17+E18-F18 -> 170.3
D19: P. SOCIAL | E19: 2 | G19: =+G18+E19-F19 -> 172.3
A20: 42791 | B20: TARJETA | C20: FEBRERO | D20: G. ADM | F20: 50 | G20: =+G19+E20-F20 -> 122.3
A21: 42795 | B21: 12386 | C21: FEBRERO | D21: G. ADM | F21: 6 | G21: =+G20+E21-F21 -> 116.3
A22: 42795 | B22: 12386 | C22: FEBRERO | D22: P. SOCIAL | F22: 2 | G22: =+G21+E22-F22 -> 114.3
A23: 42884 | B23: 12850 | C23: FEBRERO | D23: LUZ | F23: 87 | G23: =+G22+E23-F23 -> 27.3
A24: 42884 | B24: 12850 | C24: FEBRERO | D24: AGUA | F24: 27.3 | G24: =+G23+E24-F24 -> 0
A25: 42825 | B25: POR COBRAR | C25: MARZO | D25: LUZ | E25: 83.4 | G25: =+G24+E25-F25 -> 83.4
D26: AGUA | E26: 28.4 | G26: =+G25+E26-F26 -> 111.8
D27: G. ADM | E27: 60 | G27: =+G26+E27-F27 -> 171.8
D28: P. SOCIAL | E28: 2 | G28: =+G27+E28-F28 -> 173.8
A29: 42825 | B29: TARJETA | C29: MARZO | D29: G. ADM | F29: 60 | G29: =+G28+E29-F29 -> 113.8
A30: 42884 | B30: 12850 | C30: MARZO | D30: LUZ | F30: 83.4 | G30: =+G29+E30-F30 -> 30.4
A31: 42884 | B31: 12850 | C31: MARZO | D31: AGUA | F31: 28.4 | G31: =+G30+E31-F31 -> 2
A32: 42949 | B32: 13335 | C32: MARZO | D32: P. SOCIAL | F32: 2 | G32: =+G31+E32-F32 -> 7.1054274e-15
A33: 42855 | B33: POR COBRAR | C33: ABRIL | D33: LUZ | E33: 85 | G33: =+G32+E33-F33 -> 85
D34: AGUA | E34: 27.9 | G34: =+G33+E34-F34 -> 112.9
D35: G. ADM | E35: 60 | G35: =+G34+E35-F35 -> 172.9
D36: P. SOCIAL | E36: 2 | G36: =+G35+E36-F36 -> 174.9
A37: 42854 | B37: TARJETA | C37: ABRIL | D37: G. ADM | F37: 60 | G37: =+G36+E37-F37 -> 114.9
A38: 42854 | B38: TARJETA | C38: ABRIL | D38: P. SOCIAL | F38: 2 | G38: =+G37+E38-F38 -> 112.9
A39: 42949 | B39: 13335 | C39: ABRIL | D39: LUZ | F39: 85 | G39: =+G38+E39-F39 -> 27.9
A40: 42949 | B40: 13335 | C40: ABRIL | D40: AGUA | F40: 27.9 | G40: =+G39+E40-F40 -> 0
A41: 42886 | B41: POR COBRAR | C41: MAYO | D41: LUZ | E41: 79.3 | G41: =+G40+E41-F41 -> 79.3
D42: AGUA | E42: 27.3 | G42: =+G41+E42-F42 -> 106.6
D43: G. ADM | E43: 60 | G43: =+G42+E43-F43 -> 166.6
D44: P. SOCIAL | E44: 2 | G44: =+G43+E44-F44 -> 168.6
A45: 42886 | B45: TARJETA | C45: MAYO | D45: G. ADM | F45: 60 | G45: =+G44+E45-F45 -> 108.6
A46: 42886 | B46: TARJETA | C46: MAYO | D46: P. SOCIAL | F46: 2 | G46: =+G45+E46-F46 -> 106.6
A47: 42949 | B47: 13335 | C47: MAYO | D47: LUZ | F47: 79.3 | G47: =+G46+E47-F47 -> 27.3
A48: 42949 | B48: 13335 | C48: MAYO | D48: AGUA | F48: 27.3 | G48: =+G47+E48-F48 -> 0
A49: 42916 | B49: POR COBRAR | C49: JUNIO | D49: LUZ | E49: 77.6 | G49: =+G48+E49-F49 -> 77.6
D50: AGUA | E50: 27.3 | G50: =+G49+E50-F50 -> 104.9
D51: G. ADM | E51: 60 | G51: =+G50+E51-F51 -> 164.9
D52: P. SOCIAL | E52: 2 | G52: =+G51+E52-F52 -> 166.9
A53: 42916 | B53: TARJETA | C53: JUNIO | D53: G. ADM | F53: 60 | G53: =+G52+E53-F53 -> 106.9
A54: 42916 | B54: TARJETA | C54: JUNIO | D54: P. SOCIAL | F54: 2 | G54: =+G53+E54-F54 -> 104.9
A55: 42949 | B55: 13335 | C55: JUNIO | D55: LUZ | F55: 77.6 | G55: =+G54+E55-F55 -> 27.3
A56: 42949 | B56: 13335 | C56: JUNIO | D56: AGUA | F56: 27.3 | G56: =+G55+E56-F56 -> 0
A57: 42947 | B57: POR COBRAR | C57: JULIO | D57: LUZ | E57: 70 | G57: =+G56+E57-F57 -> 70
D58: AGUA | E58: 27.5 | G58: =+G57+E58-F58 -> 97.5
D59: G. ADM | E59: 60 | G59: =+G58+E59-F59 -> 157.5
D60: P. SOCIAL | E60: 2 | G60: =+G59+E60-F60 -> 159.5
A61: 42945 | B61: TARJETA | C61: JULIO | D61: G. ADM | F61: 52 | G61: =+G60+E61-F61 -> 107.5
A62: 43005 | B62: 13687 | C62: JULIO | D62: LUZ | F62: 70 | G62: =+G61+E62-F62 -> 37.5
A63: 43005 | B63: 13687 | C63: JULIO | D63: AGUA | F63: 27.5 | G63: =+G62+E63-F63 -> 10
A64: 43063 | B64: 14043 | C64: JULIO | D64: G. ADM | F64: 8 | G64: =+G63+E64-F64 -> 2
A65: 43063 | B65: 14043 | C65: JULIO | D65: P. SOCIAL | F65: 2 | G65: =+G64+E65-F65 -> 0
A66: 42978 | B66: POR COBRAR | C66: AGOSTO | D66: LUZ | E66: 70 | G66: =+G65+E66-F66 -> 70
D67: AGUA | E67: 27.5 | G67: =+G66+E67-F67 -> 97.5
D68: G. ADM | E68: 60 | G68: =+G67+E68-F68 -> 157.5
D69: P. SOCIAL | E69: 2 | G69: =+G68+E69-F69 -> 159.5
A70: 42978 | B70: TARJETA | C70: AGOSTO | D70: G. ADM | F70: 54 | G70: =+G69+E70-F70 -> 105.5
A71: 43005 | B71: 13687 | C71: AGOSTO | D71: LUZ | F71: 70 | G71: =+G70+E71-F71 -> 35.5
A72: 43005 | B72: 13687 | C72: AGOSTO | D72: AGUA | F72: 27.5 | G72: =+G71+E72-F72 -> 8
A73: 43063 | B73: 14043 | C73: AGOSTO | D73: G. ADM | F73: 6 | G73: =+G72+E73-F73 -> 2
A74: 43063 | B74: 14043 | C74: AGOSTO | D74: P. SOCIAL | F74: 2 | G74: =+G73+E74-F74 -> 0
A75: 43008 | B75: POR COBRAR | C75: SEPTIEMBRE | D75: LUZ | E75: 66.7 | G75: =+G74+E75-F75 -> 66.7
D76: AGUA | E76: 27.3 | G76: =+G75+E76-F76 -> 94
D77: G. ADM | E77: 60 | G77: =+G76+E77-F77 -> 154
D78: P. SOCIAL | E78: 2 | G78: =+G77+E78-F78 -> 156
A79: 43008 | B79: TARJETA | C79: SEPTIEMBRE | D79: G. ADM | F79: 60 | G79: =+G78+E79-F79 -> 96
A80: 43008 | B80: TARJETA | C80: SEPTIEMBRE | D80: P. SOCIAL | F80: 2 | G80: =+G79+E80-F80 -> 94
A81: 43063 | B81: 14043 | C81: SEPTIEMBRE | D81: LUZ | F81: 66.7 | G81: =+G80+E81-F81 -> 27.3
A82: 43063 | B82: 14043 | C82: SEPTIEMBRE | D82: AGUA | F82: 27.3 | G82: =+G81+E82-F82 -> 0
A83: 43039 | B83: POR COBRAR | C83: OCTUBRE | D83: LUZ | E83: 66.4 | G83: =+G82+E83-F83 -> 66.4
D84: AGUA | E84: 27.3 | G84: =+G83+E84-F84 -> 93.7
D85: G. ADM | E85: 60 | G85: =+G84+E85-F85 -> 153.7
D86: P. SOCIAL | E86: 2 | G86: =+G85+E86-F86 -> 155.7
A87: 42977 | B87: ACT. SANTA ROSA | D87: CUOTA | E87: 10 | G87: =+G86+E87-F87 -> 165.7
A88: 43195 | B88: 7449 | C88: OCTUBRE | D88: CUOTA | F88: 10 | G88: =+G87+E88-F88 -> 155.7
A89: 43039 | B89: TARJETA | C89: OCTUBRE | D89: G. ADM | F89: 60 | G89: =+G88+E89-F89 -> 95.7
A90: 43039 | B90: TARJETA | C90: OCTUBRE | D90: P. SOCIAL | F90: 2 | G90: =+G89+E90-F90 -> 93.7
A91: 43063 | B91: 14043 | C91: OCTUBRE | D91: LUZ | F91: 66.4 | G91: =+G90+E91-F91 -> 27.3
A92: 43063 | B92: 14043 | C92: OCTUBRE | D92: AGUA | F92: 27.3 | G92: =+G91+E92-F92 -> 0
A93: 43069 | B93: POR COBRAR | C93: NOVIEMBRE | D93: LUZ | E93: 70.9 | G93: =+G92+E93-F93 -> 70.9
D94: AGUA | E94: 27.3 | G94: =+G93+E94-F94 -> 98.2
D95: G. ADM | E95: 60 | G95: =+G94+E95-F95 -> 158.2
D96: P. SOCIAL | E96: 2 | G96: =+G95+E96-F96 -> 160.2
A97: 43195 | B97: 15085 | C97: NOVIEMBRE | D97: P. SOCIAL | F97: 2 | G97: =+G96+E97-F97 -> 158.2
A98: 43087 | B98: 14276 | C98: NOVIEMBRE | D98: LUZ | F98: 70.9 | G98: =+G97+E98-F98 -> 87.3
A99: 43087 | B99: 14276 | C99: NOVIEMBRE | D99: AGUA | F99: 27.3 | G99: =+G98+E99-F99 -> 60
A100: 43069 | B100: TARJETA | C100: NOVIEMBRE | D100: G. ADM | F100: 40 | G100: =+G99+E100-F100 -> 20
A101: 43195 | B101: 15085 | C101: NOVIEMBRE | D101: G. ADM | F101: 20 | G101: =+G100+E101-F101 -> 0
A102: 43100 | B102: POR COBRAR | C102: DICIEMBRE | D102: LUZ | E102: 77.1 | G102: =+G101+E102-F102 -> 77.1
...

Sheet FLORES FRANCISCA
B2: FLORES YATO FRANCISCA DOLORES
A4: FECHA | B4: DOCUMENTO | C4: PERIODO | D4: CONCEPTO | E4: POR COBRAR | F4: PAGADO | G4: SALDO POR COBRAR
A5: 42736 | B5: SALDO AL 2016 | G5: 594.3
A6: 42747 | B6: 12102 | C6: A CUENTA 2016 | F6: 59 | G6: =+G5+E6-F6 -> 535.3
A7: 42776 | B7: 12940 | C7: A CUENTA 2016 | F7: 535.3 | G7: =+G6+E7-F7 -> 0
A8: 42766 | B8: POR COBRAR | C8: ENERO | D8: LUZ | E8: 204.6 | G8: =+G7+E8-F8 -> 204.6
D9: AGUA | E9: 2.8 | G9: =+G8+E9-F9 -> 207.4
D10: G. ADM | E10: 60 | G10: =+G9+E10-F10 -> 267.4
D11: P. SOCIAL | E11: 2 | G11: =+G10+E11-F11 -> 269.4
D12: POZO SEPTICO | E12: 50 | G12: =+G11+E12-F12 -> 319.4
A13: 42776 | B13: 12940 | C13: ENERO | D13: G. ADM | F13: 60 | G13: =+G12+E13-F13 -> 259.4
A14: 42776 | B14: 12940 | C14: ENERO | D14: P. SOCIAL | F14: 2 | G14: =+G13+E14-F14 -> 257.4
A15: 42779 | B15: 12942 | C15: ENERO | D15: POZO SEPTICO | F15: 50 | G15: =+G14+E15-F15 -> 207.4
A16: 42787 | B16: 12329 | C16: ENERO | D16: AGUA | F16: 2.8 | G16: =+G15+E16-F16 -> 204.6
A17: 42787 | B17: 12329 | C17: ENERO | D17: LUZ | F17: 204.6 | G17: =+G16+E17-F17 -> 0
A18: 42794 | B18: POR COBRAR | C18: FEBRERO | D18: LUZ | E18: 196.2 | G18: =+G17+E18-F18 -> 196.2
D19: AGUA | E19: 2 | G19: =+G18+E19-F19 -> 198.2
D20: G. ADM | E20: 56 | G20: =+G19+E20-F20 -> 254.2
D21: P. SOCIAL | E21: 2 | G21: =+G20+E21-F21 -> 256.2
A22: 42821 | B22: 12513 | C22: FEBRERO | D22: G. ADM | F22: 56 | G22: =+G21+E22-F22 -> 200.2
A23: 42821 | B23: 12513 | C23: FEBRERO | D23: P. SOCIAL | F23: 2 | G23: =+G22+E23-F23 -> 198.2
A24: 42821 | B24: 12513 | C24: FEBRERO | D24: LUZ | F24: 196.2 | G24: =+G23+E24-F24 -> 2
A25: 42821 | B25: 12513 | C25: FEBRERO | D25: AGUA | F25: 2 | G25: =+G24+E25-F25 -> 0
A26: 42825 | B26: POR COBRAR | C26: MARZO | D26: LUZ | E26: 188 | G26: =+G25+E26-F26 -> 188
D27: AGUA | E27: 2 | G27: =+G26+E27-F27 -> 190
D28: G. ADM | E28: 60 | G28: =+G27+E28-F28 -> 250
D29: P. SOCIAL | E29: 2 | G29: =+G28+E29-F29 -> 252
A30: 42891 | B30: 13048 | C30: MARZO | D30: LUZ | F30: 188 | G30: =+G29+E30-F30 -> 64
A31: 42891 | B31: 13048 | C31: MARZO | D31: AGUA | F31: 2 | G31: =+G30+E31-F31 -> 62
A32: 42949 | B32: 13357 | C32: MARZO | D32: G. ADM | F32: 60 | G32: =+G31+E32-F32 -> 2
A33: 42949 | B33: 13357 | C33: MARZO | D33: P. SOCIAL | F33: 2 | G33: =+G32+E33-F33 -> 0
A34: 42855 | B34: POR COBRAR | C34: ABRIL | D34: LUZ | E34: 191.6 | G34: =+G33+E34-F34 -> 191.6
D35: AGUA | E35: 2 | G35: =+G34+E35-F35 -> 193.6
D36: G. ADM | E36: 60 | G36: =+G35+E36-F36 -> 253.6
D37: P. SOCIAL | E37: 2 | G37: =+G36+E37-F37 -> 255.6
A38: 42891 | B38: 13048 | C38: ABRIL | D38: LUZ | F38: 191.6 | G38: =+G37+E38-F38 -> 64
A39: 42891 | B39: 13048 | C39: ABRIL | D39: AGUA | F39: 2 | G39: =+G38+E39-F39 -> 62
A40: 42949 | B40: 13357 | C40: ABRIL | D40: P. SOCIAL | F40: 2 | G40: =+G39+E40-F40 -> 60
A41: 42949 | B41: 13357 | C41: ABRIL | D41: G. ADM | F41: 60 | G41: =+G40+E41-F41 -> 0
A42: 42886 | B42: POR COBRAR | C42: MAYO | D42: LUZ | E42: 158.7 | G42: =+G41+E42-F42 -> 158.7
D43: AGUA | E43: 2 | G43: =+G42+E43-F43 -> 160.7
D44: G. ADM | E44: 60 | G44: =+G43+E44-F44 -> 220.7
D45: P. SOCIAL | E45: 2 | G45: =+G44+E45-F45 -> 222.7
A46: 42949 | B46: 13357 | C46: MAYO | D46: G. ADM | F46: 60 | G46: =+G45+E46-F46 -> 162.7
A47: 42949 | B47: 13357 | C47: MAYO | D47: P. SOCIAL | F47: 2 | G47: =+G46+E47-F47 -> 160.7
A48: 42949 | B48: 13357 | C48: MAYO | D48: LUZ | F48: 158.7 | G48: =+G47+E48-F48 -> 2
A49: 42949 | B49: 13357 | C49: MAYO | D49: AGUA | F49: 2 | G49: =+G48+E49-F49 -> 0
A50: 42916 | B50: POR COBRAR | C50: JUNIO | D50: LUZ | E50: 155.1 | G50: =+G49+E50-F50 -> 155.1
D51: AGUA | E51: 2 | G51: =+G50+E51-F51 -> 157.1
D52: G. ADM | E52: 60 | G52: =+G51+E52-F52 -> 217.1
D53: P. SOCIAL | E53: 2 | G53: =+G52+E53-F53 -> 219.1
A54: 42949 | B54: 13357 | C54: JUNIO | D54: G. ADM | F54: 60 | G54: =+G53+E54-F54 -> 159.1
A55: 42949 | B55: 13357 | C55: JUNIO | D55: P. SOCIAL | F55: 2 | G55: =+G54+E55-F55 -> 157.1
A56: 42949 | B56: 13357 | C56: JUNIO | D56: LUZ | F56: 155.1 | G56: =+G55+E56-F56 -> 2
A57: 42949 | B57: 13357 | C57: JUNIO | D57: AGUA | F57: 2 | G57: =+G56+E57-F57 -> 0
A58: 42947 | B58: POR COBRAR | C58: JULIO | D58: LUZ | E58: 139.9 | G58: =+G57+E58-F58 -> 139.9
D59: AGUA | E59: 2 | G59: =+G58+E59-F59 -> 141.9
D60: G. ADM | E60: 60 | G60: =+G59+E60-F60 -> 201.9
D61: P. SOCIAL | E61: 2 | G61: =+G60+E61-F61 -> 203.9
A62: 42949 | B62: 13357 | C62: JULIO | D62: G. ADM | F62: 60 | G62: =+G61+E62-F62 -> 143.9
A63: 42949 | B63: 13357 | C63: JULIO | D63: P. SOCIAL | F63: 2 | G63: =+G62+E63-F63 -> 141.9
A64: 43068 | B64: 14179 | C64: JULIO | D64: LUZ | F64: 139.9 | G64: =+G63+E64-F64 -> 2
A65: 43068 | B65: 14179 | C65: JULIO | D65: AGUA | F65: 2 | G65: =+G64+E65-F65 -> 0
A66: 42978 | B66: POR COBRAR | C66: AGOSTO | D66: LUZ | E66: 139.9 | G66: =+G65+E66-F66 -> 139.9
D67: AGUA | E67: 2 | G67: =+G66+E67-F67 -> 141.9
D68: G. ADM | E68: 60 | G68: =+G67+E68-F68 -> 201.9
D69: P. SOCIAL | E69: 2 | G69: =+G68+E69-F69 -> 203.9
A70: 43068 | B70: 14179 | C70: AGOSTO | D70: LUZ | F70: 139.9 | G70: =+G69+E70-F70 -> 64
A71: 43068 | B71: 14179 | C71: AGOSTO | D71: AGUA | F71: 2 | G71: =+G70+E71-F71 -> 62
A72: 43068 | B72: 14179 | C72: AGOSTO | D72: G. ADM | F72: 60 | G72: =+G71+E72-F72 -> 2
A73: 43068 | B73: 14179 | C73: AGOSTO | D73: P. SOCIAL | F73: 2 | G73: =+G72+E73-F73 -> 0
A74: 43008 | B74: POR COBRAR | C74: SEPTIEMBRE | D74: LUZ | E74: 85.1 | G74: =+G73+E74-F74 -> 85.1
D75: AGUA | E75: 2 | G75: =+G74+E75-F75 -> 87.1
D76: G. ADM | E76: 60 | G76: =+G75+E76-F76 -> 147.1
D77: P. SOCIAL | E77: 2 | G77: =+G76+E77-F77 -> 149.1
A78: 43068 | B78: 14179 | C78: SEPTIEMBRE | D78: G. ADM | F78: 60 | G78: =+G77+E78-F78 -> 89.1
A79: 43068 | B79: 14179 | C79: SEPTIEMBRE | D79: P. SOCIAL | F79: 2 | G79: =+G78+E79-F79 -> 87.1
A80: 43068 | B80: 14179 | C80: SEPTIEMBRE | D80: LUZ | F80: 85.1 | G80: =+G79+E80-F80 -> 2
A81: 43068 | B81: 14179 | C81: SEPTIEMBRE | D81: AGUA | F81: 2 | G81: =+G80+E81-F81 -> 0
A82: 43039 | B82: POR COBRAR | C82: OCTUBRE | D82: LUZ | E82: 84.7 | G82: =+G81+E82-F82 -> 84.7
D83: AGUA | E83: 2 | G83: =+G82+E83-F83 -> 86.7
D84: G. ADM | E84: 60 | G84: =+G83+E84-F84 -> 146.7
D85: P. SOCIAL | E85: 2 | G85: =+G84+E85-F85 -> 148.7
A86: 43063 | B86: 14060 | C86: OCTUBRE | D86: LUZ | F86: 84.7 | G86: =+G85+E86-F86 -> 64
A87: 43063 | B87: 14060 | C87: OCTUBRE | D87: AGUA | F87: 2 | G87: =+G86+E87-F87 -> 62
A88: 43068 | B88: 14179 | C88: OCTUBRE | D88: G. ADM | F88: 60 | G88: =+G87+E88-F88 -> 2
A89: 43068 | B89: 14179 | C89: OCTUBRE | D89: P. SOCIAL | F89: 2 | G89: =+G88+E89-F89 -> -1.4210855e-14
A90: 43069 | B90: POR COBRAR | C90: NOVIEMBRE | D90: LUZ | E90: 90.4 | G90: =+G89+E90-F90 -> 90.4
D91: AGUA | E91: 2 | G91: =+G90+E91-F91 -> 92.4
D92: G. ADM | E92: 60 | G92: =+G91+E92-F92 -> 152.4
D93: P. SOCIAL | E93: 2 | G93: =+G92+E93-F93 -> 154.4
A94: 43185 | B94: 14994 | C94: NOVIEMBRE | D94: LUZ | F94: 90.4 | G94: =+G93+E94-F94 -> 64
A95: 43185 | B95: 14994 | C95: NOVIEMBRE | D95: AGUA | F95: 2 | G95: =+G94+E95-F95 -> 62
A96: 43185 | B96: 14994 | C96: NOVIEMBRE | D96: G. ADM | F96: 60 | G96: =+G95+E96-F96 -> 2
A97: 43185 | B97: 14994 | C97: NOVIEMBRE | D97: P. SOCIAL | F97: 2 | G97: =+G96+E97-F97 -> -2.8421709e-14
A98: 43100 | B98: POR COBRAR | C98: DICIEMBRE | D98: LUZ | E98: 98.3 | G98: =+G97+E98-F98 -> 98.3
D99: AGUA | E99: 2 | G99: =+G98+E99-F99 -> 100.3
D100: G. ADM | E100: 60 | G100: =+G99+E100-F100 -> 160.3
D101: P. SOCIAL | E101: 2 | G101: =+G100+E101-F101 -> 162.3
A102: 43118 | B102: 14450 | C102: DICIEMBRE | D102: LUZ | F102: 98.3 | G102: =+G101+E102-F102 -> 64
...

Sheet GAVILAN NORMA
B2: GAVILAN MOSQUERA NORMA
A4: FECHA | B4: DOCUMENTO | C4: PERIODO | D4: CONCEPTO | E4: POR COBRAR | F4: PAGADO | G4: SALDO POR COBRAR
A5: 42736 | B5: SALDO AL 2016 | G5: 12814.9
A6: 42766 | B6: 12185 | C6: A CUENTA 2016 | F6: 80 | G6: =+G5+E6-F6 -> 12734.9
A7: 42766 | B7: 12181 | C7: A CUENTA 2016 | F7: 353.8 | G7: =+G6+E7-F7 -> 12381.1
A8: 43031 | B8: 13870 | C8: A CUENTA 2016 | F8: 130 | G8: =+G7+E8-F8 -> 12251.1
A9: 43045 | B9: 13935 | C9: A CUENTA 2016 | F9: 130 | G9: =+G8+E9-F9 -> 12121.1
A10: 43815 | B10: 19316 | C10: A CUENTA 2016 | F10: 4624.5 | G10: =+G9+E10-F10 -> 7496.6
A11: 44761 | B11: R 25100 | C11: A CUENTA 2016 | F11: 4000 | G11: =+G10+E11-F11 -> 3496.6
A12: 44761 | B12: R 25101 | C12: A CUENTA 2016 | F12: 1900 | G12: =+G11+E12-F12 -> 1596.6
A13: 44820 | B13: R 25517 | C13: A CUENTA 2016 | F13: 1500 | G13: =+G12+E13-F13 -> 96.6
A14: 45162 | B14: R 27368 | C14: A CUENTA 2016 | F14: 94.5 | G14: =+G13+E14-F14 -> 2.1
A15: 45419 | B15: 28803 | C15: A CUENTA 2016 | F15: 2.1 | G15: =+G14+E15-F15 -> 3.6370906e-13
A16: 42766 | B16: POR COBRAR | C16: ENERO | D16: LUZ | E16: 204.6 | G16: =+G15+E16-F16 -> 204.6
D17: AGUA | E17: 35.6 | G17: =+G16+E17-F17 -> 240.2
D18: G. ADM | E18: 60 | G18: =+G17+E18-F18 -> 300.2
D19: P. SOCIAL | E19: 2 | G19: =+G18+E19-F19 -> 302.2
A20: 42766 | B20: 12185 | C20: ENERO | D20: G. ADM | F20: 60 | G20: =+G19+E20-F20 -> 242.2
A21: 42766 | B21: 12185 | C21: ENERO | D21: P. SOCIAL | F21: 2 | G21: =+G20+E21-F21 -> 240.2
A22: 42819 | B22: 12483 | C22: ENERO | D22: LUZ | F22: 204.6 | G22: =+G21+E22-F22 -> 35.6
A23: 42819 | B23: 12483 | C23: ENERO | D23: AGUA | F23: 35.6 | G23: =+G22+E23-F23 -> 3.907985e-13
A24: 42794 | B24: POR COBRAR | C24: FEBRERO | D24: LUZ | E24: 174.3 | G24: =+G23+E24-F24 -> 174.3
D25: AGUA | E25: 25 | G25: =+G24+E25-F25 -> 199.3
D26: G. ADM | E26: 56 | G26: =+G25+E26-F26 -> 255.3
D27: P. SOCIAL | E27: 2 | G27: =+G26+E27-F27 -> 257.3
A28: 42819 | B28: 12483 | C28: FEBRERO | D28: LUZ | F28: 174.3 | G28: =+G27+E28-F28 -> 83
A29: 42819 | B29: 12483 | C29: FEBRERO | D29: AGUA | F29: 25 | G29: =+G28+E29-F29 -> 58
A30: 42819 | B30: 12483 | C30: FEBRERO | D30: G. ADM | F30: 56 | G30: =+G29+E30-F30 -> 2
A31: 42819 | B31: 12483 | C31: FEBRERO | D31: P. SOCIAL | F31: 2 | G31: =+G30+E31-F31 -> 3.9790393e-13
A32: 42825 | B32: POR COBRAR | C32: MARZO | D32: LUZ | E32: 149.4 | G32: =+G31+E32-F32 -> 149.4
D33: AGUA | E33: 25.7 | G33: =+G32+E33-F33 -> 175.1
D34: G. ADM | E34: 60 | G34: =+G33+E34-F34 -> 235.1
D35: P. SOCIAL | E35: 2 | G35: =+G34+E35-F35 -> 237.1
A36: 42846 | B36: 12674 | C36: MARZO | D36: G. ADM | F36: 60 | G36: =+G35+E36-F36 -> 177.1
A37: 42846 | B37: 12674 | C37: MARZO | D37: P. SOCIAL | F37: 2 | G37: =+G36+E37-F37 -> 175.1
A38: 42846 | B38: 12674 | C38: MARZO | D38: LUZ | F38: 149.4 | G38: =+G37+E38-F38 -> 25.7
A39: 42846 | B39: 12674 | C39: MARZO | D39: AGUA | F39: 25.7 | G39: =+G38+E39-F39 -> 3.8724579e-13
A40: 42855 | B40: POR COBRAR | C40: ABRIL | D40: LUZ | E40: 170 | G40: =+G39+E40-F40 -> 170
D41: AGUA | E41: 25.4 | G41: =+G40+E41-F41 -> 195.4
D42: G. ADM | E42: 60 | G42: =+G41+E42-F42 -> 255.4
D43: P. SOCIAL | E43: 2 | G43: =+G42+E43-F43 -> 257.4
A44: 42885 | B44: 12888 | C44: ABRIL | D44: G. ADM | F44: 60 | G44: =+G43+E44-F44 -> 197.4
A45: 42885 | B45: 12888 | C45: ABRIL | D45: P. SOCIAL | F45: 2 | G45: =+G44+E45-F45 -> 195.4
A46: 42885 | B46: 12888 | C46: ABRIL | D46: LUZ | F46: 170 | G46: =+G45+E46-F46 -> 25.4
A47: 42885 | B47: 12888 | C47: ABRIL | D47: AGUA | F47: 25.4 | G47: =+G46+E47-F47 -> 4.3343107e-13
A48: 42886 | B48: POR COBRAR | C48: MAYO | D48: LUZ | E48: 130.8 | G48: =+G47+E48-F48 -> 130.8
D49: AGUA | E49: 24.8 | G49: =+G48+E49-F49 -> 155.6
D50: G. ADM | E50: 60 | G50: =+G49+E50-F50 -> 215.6
D51: P. SOCIAL | E51: 2 | G51: =+G50+E51-F51 -> 217.6
A52: 42885 | B52: 12888 | C52: MAYO | D52: G. ADM | F52: 60 | G52: =+G51+E52-F52 -> 157.6
A53: 42885 | B53: 12888 | C53: MAYO | D53: P. SOCIAL | F53: 2 | G53: =+G52+E53-F53 -> 155.6
A54: 42913 | B54: 13161 | C54: MAYO | D54: LUZ | F54: 130.8 | G54: =+G53+E54-F54 -> 24.8
A55: 42913 | B55: 13161 | C55: MAYO | D55: AGUA | F55: 24.8 | G55: =+G54+E55-F55 -> 4.3698378e-13
A56: 42916 | B56: POR COBRAR | C56: JUNIO | D56: LUZ | E56: 128 | G56: =+G55+E56-F56 -> 128
D57: AGUA | E57: 25.1 | G57: =+G56+E57-F57 -> 153.1
D58: G. ADM | E58: 60 | G58: =+G57+E58-F58 -> 213.1
D59: P. SOCIAL | E59: 2 | G59: =+G58+E59-F59 -> 215.1
A60: 42913 | B60: 13162 | C60: JUNIO | D60: G. ADM | F60: 60 | G60: =+G59+E60-F60 -> 155.1
A61: 42913 | B61: 13162 | C61: JUNIO | D61: P. SOCIAL | F61: 2 | G61: =+G60+E61-F61 -> 153.1
A62: 42956 | B62: 13429 | C62: JUNIO | D62: LUZ | F62: 128 | G62: =+G61+E62-F62 -> 25.1
A63: 42956 | B63: 13429 | C63: JUNIO | D63: AGUA | F63: 25.1 | G63: =+G62+E63-F63 -> 4.1922021e-13
A64: 42947 | B64: POR COBRAR | C64: JULIO | D64: LUZ | E64: 114.2 | G64: =+G63+E64-F64 -> 114.2
D65: AGUA | E65: 25 | G65: =+G64+E65-F65 -> 139.2
D66: G. ADM | E66: 60 | G66: =+G65+E66-F66 -> 199.2
D67: P. SOCIAL | E67: 2 | G67: =+G66+E67-F67 -> 201.2
A68: 42956 | B68: 13429 | C68: JULIO | D68: G. ADM | F68: 60 | G68: =+G67+E68-F68 -> 141.2
A69: 42956 | B69: 13429 | C69: JULIO | D69: P. SOCIAL | F69: 2 | G69: =+G68+E69-F69 -> 139.2
A70: 42971 | B70: 13480 | C70: JULIO | D70: LUZ | F70: 114.2 | G70: =+G69+E70-F70 -> 25
A71: 42971 | B71: 13480 | C71: JULIO | D71: AGUA | F71: 25 | G71: =+G70+E71-F71 -> 4.1211479e-13
A72: 42978 | B72: POR COBRAR | C72: AGOSTO | D72: LUZ | E72: 114.2 | G72: =+G71+E72-F72 -> 114.2
D73: AGUA | E73: 25 | G73: =+G72+E73-F73 -> 139.2
D74: G. ADM | E74: 60 | G74: =+G73+E74-F74 -> 199.2 | J74: DEUDA 2013
D75: P. SOCIAL | E75: 2 | G75: =+G74+E75-F75 -> 201.2 | I75: 2017 | J75: AGOSTO | K75: MULTA
D76: MULTA | E76: 85 | G76: =+G75+E76-F76 -> 286.2 | J76: SEPTIEMBRE | K76: MULTA
A77: 42996 | B77: 13585 | C77: AGOSTO | D77: G. ADM | F77: 114.2 | G77: =+G76+E77-F77 -> 172 | K77: MULTA
A78: 42996 | B78: 13585 | C78: AGOSTO | D78: P. SOCIAL | F78: 25 | G78: =+G77+E78-F78 -> 147
A79: 42996 | B79: 13585 | C79: AGOSTO | D79: LUZ | F79: 60 | G79: =+G78+E79-F79 -> 87
A80: 42996 | B80: 13585 | C80: AGOSTO | D80: AGUA | F80: 2 | G80: =+G79+E80-F80 -> 85
B81: EXONERACION | D81: MULTA | F81: 42.5 | G81: =+G80+E81-F81 -> 42.5
A82: 45462 | B82: 29053 | C82: AGOSTO | D82: MULTA | F82: 42.5 | G82: =+G81+E82-F82 -> 3.9790393e-13
A83: 43008 | B83: POR COBRAR | C83: SEPTIEMBRE | D83: LUZ | E83: 119.9 | G83: =+G82+E83-F83 -> 119.9
D84: AGUA | E84: 16.4 | G84: =+G83+E84-F84 -> 136.3
D85: G. ADM | E85: 60 | G85: =+G84+E85-F85 -> 196.3
D86: P. SOCIAL | E86: 2 | G86: =+G85+E86-F86 -> 198.3
A87: 42788 | D87: MULTA | E87: 85 | G87: =+G86+E87-F87 -> 283.3
A88: 42823 | D88: MULTA | E88: 85 | G88: =+G87+E88-F88 -> 368.3
A89: 43031 | B89: 13869 | C89: SEPTIEMBRE | D89: G. ADM | F89: 60 | G89: =+G88+E89-F89 -> 308.3
A90: 43031 | B90: 13869 | C90: SEPTIEMBRE | D90: P. SOCIAL | F90: 2 | G90: =+G89+E90-F90 -> 306.3
A91: 43031 | B91: 13869 | C91: SEPTIEMBRE | D91: LUZ | F91: 119.9 | G91: =+G90+E91-F91 -> 186.4
A92: 43031 | B92: 13869 | C92: SEPTIEMBRE | D92: AGUA | F92: 16.4 | G92: =+G91+E92-F92 -> 170
B93: EXONERACION | D93: MULTA | F93: 42.5 | G93: =+G92+E93-F93 -> 127.5
A94: 45462 | B94: 29053 | C94: SEPTIEMBRE | D94: MULTA | F94: 42.5 | G94: =+G93+E94-F94 -> 85
B95: EXONERACION | D95: MULTA | F95: 42.5 | G95: =+G94+E95-F95 -> 42.5
A96: 45462 | B96: 29053 | C96: SEPTIEMBRE | D96: MULTA | F96: 42.5 | G96: =+G95+E96-F96 -> 3.9790393e-13
A97: 43039 | B97: POR COBRAR | C97: OCTUBRE | D97: LUZ | E97: 119.3 | G97: =+G96+E97-F97 -> 119.3
D98: AGUA | E98: 24.9 | G98: =+G97+E98-F98 -> 144.2
D99: G. ADM | E99: 60 | G99: =+G98+E99-F99 -> 204.2
D100: P. SOCIAL | E100: 2 | G100: =+G99+E100-F100 -> 206.2
A101: 43063 | B101: 14052 | C101: OCTUBRE | D101: LUZ | F101: 119.3 | G101: =+G100+E101-F101 -> 86.9
A102: 43063 | B102: 14052 | C102: OCTUBRE | D102: AGUA | F102: 24.9 | G102: =+G101+E102-F102 -> 62
...

Sheet GELDRES MIGUEL
B2: GELDRES REVILLA MIGUEL
A4: FECHA | B4: DOCUMENTO | C4: PERIODO | D4: CONCEPTO | E4: POR COBRAR | F4: PAGADO | G4: SALDO POR COBRAR
A5: 42736 | B5: SALDO AL 2016 | G5: 270.2
A6: 42753 | B6: 12119 | C6: A CUENTA 2016 | F6: 175.2 | G6: =+G5+E6-F6 -> 95
A7: 42786 | B7: 12301 | C7: A CUENTA 2016 | F7: 15 | G7: =+G6+E7-F7 -> 80
A8: 42845 | B8: 12668 | C8: A CUENTA 2016 | F8: 80 | G8: =+G7+E8-F8 -> 0
A9: 42766 | B9: POR COBRAR | C9: ENERO | D9: LUZ | E9: 116 | G9: =+G8+E9-F9 -> 116
D10: AGUA | E10: 57 | G10: =+G9+E10-F10 -> 173
D11: G. ADM | E11: 60 | G11: =+G10+E11-F11 -> 233
D12: P. SOCIAL | E12: 2 | G12: =+G11+E12-F12 -> 235
A13: 42765 | B13: TARJETA | C13: ENERO | D13: G. ADM | F13: 60 | G13: =+G12+E13-F13 -> 175
A14: 42765 | B14: TARJETA | C14: ENERO | D14: P. SOCIAL | F14: 2 | G14: =+G13+E14-F14 -> 173
A15: 42786 | B15: 12301 | C15: ENERO | D15: LUZ | F15: 116 | G15: =+G14+E15-F15 -> 57
A16: 42786 | B16: 12301 | C16: ENERO | D16: AGUA | F16: 57 | G16: =+G15+E16-F16 -> 0
A17: 42794 | B17: POR COBRAR | C17: FEBRERO | D17: LUZ | E17: 119.1 | G17: =+G16+E17-F17 -> 119.1
D18: AGUA | E18: 36 | G18: =+G17+E18-F18 -> 155.1
D19: G. ADM | E19: 56 | G19: =+G18+E19-F19 -> 211.1
D20: P. SOCIAL | E20: 2 | G20: =+G19+E20-F20 -> 213.1
A21: 42793 | B21: TARJETA | C21: FEBRERO | D21: G. ADM | F21: 56 | G21: =+G20+E21-F21 -> 157.1
A22: 42793 | B22: TARJETA | C22: FEBRERO | D22: P. SOCIAL | F22: 2 | G22: =+G21+E22-F22 -> 155.1
A23: 42821 | B23: 12572 | C23: FEBRERO | D23: LUZ | F23: 119.1 | G23: =+G22+E23-F23 -> 36
A24: 42821 | B24: 12572 | C24: FEBRERO | D24: AGUA | F24: 36 | G24: =+G23+E24-F24 -> 0
A25: 42825 | B25: POR COBRAR | C25: MARZO | D25: LUZ | E25: 114.2 | G25: =+G24+E25-F25 -> 114.2
D26: AGUA | E26: 37.8 | G26: =+G25+E26-F26 -> 152
D27: G. ADM | E27: 60 | G27: =+G26+E27-F27 -> 212
D28: P. SOCIAL | E28: 2 | G28: =+G27+E28-F28 -> 214
A29: 42824 | B29: TARJETA | C29: MARZO | D29: G. ADM | F29: 60 | G29: =+G28+E29-F29 -> 154
A30: 42824 | B30: TARJETA | C30: MARZO | D30: P. SOCIAL | F30: 2 | G30: =+G29+E30-F30 -> 152
A31: 42845 | B31: 12667 | C31: MARZO | D31: LUZ | F31: 114.2 | G31: =+G30+E31-F31 -> 37.8
A32: 42845 | B32: 12667 | C32: MARZO | D32: AGUA | F32: 37.8 | G32: =+G31+E32-F32 -> 0
A33: 42855 | B33: POR COBRAR | C33: ABRIL | D33: LUZ | E33: 116.2 | G33: =+G32+E33-F33 -> 116.2
D34: AGUA | E34: 37 | G34: =+G33+E34-F34 -> 153.2
D35: G. ADM | E35: 60 | G35: =+G34+E35-F35 -> 213.2
D36: P. SOCIAL | E36: 2 | G36: =+G35+E36-F36 -> 215.2
A37: 42854 | B37: TARJETA | C37: ABRIL | D37: G. ADM | F37: 60 | G37: =+G36+E37-F37 -> 155.2
A38: 42854 | B38: TARJETA | C38: ABRIL | D38: P. SOCIAL | F38: 2 | G38: =+G37+E38-F38 -> 153.2
A39: 42881 | B39: 12822 | C39: ABRIL | D39: LUZ | F39: 116.2 | G39: =+G38+E39-F39 -> 37
A40: 42881 | B40: 12822 | C40: ABRIL | D40: AGUA | F40: 37 | G40: =+G39+E40-F40 -> 0
A41: 42886 | B41: POR COBRAR | C41: MAYO | D41: LUZ | E41: 108 | G41: =+G40+E41-F41 -> 108
D42: AGUA | E42: 36.3 | G42: =+G41+E42-F42 -> 144.3
D43: G. ADM | E43: 60 | G43: =+G42+E43-F43 -> 204.3
D44: P. SOCIAL | E44: 2 | G44: =+G43+E44-F44 -> 206.3
A45: 42885 | B45: TARJETA | C45: MAYO | D45: G. ADM | F45: 60 | G45: =+G44+E45-F45 -> 146.3
A46: 42885 | B46: TARJETA | C46: MAYO | D46: P. SOCIAL | F46: 2 | G46: =+G45+E46-F46 -> 144.3
A47: 42908 | B47: 13134 | C47: MAYO | D47: LUZ | F47: 108 | G47: =+G46+E47-F47 -> 36.3
A48: 42908 | B48: 13134 | C48: MAYO | D48: AGUA | F48: 36.3 | G48: =+G47+E48-F48 -> 0
A49: 42916 | B49: POR COBRAR | C49: JUNIO | D49: LUZ | E49: 105.7 | G49: =+G48+E49-F49 -> 105.7
D50: AGUA | E50: 36.3 | G50: =+G49+E50-F50 -> 142
D51: G. ADM | E51: 60 | G51: =+G50+E51-F51 -> 202
D52: P. SOCIAL | E52: 2 | G52: =+G51+E52-F52 -> 204
A53: 42916 | B53: TARJETA | C53: JUNIO | D53: G. ADM | F53: 60 | G53: =+G52+E53-F53 -> 144
A54: 42916 | B54: TARJETA | C54: JUNIO | D54: P. SOCIAL | F54: 2 | G54: =+G53+E54-F54 -> 142
A55: 42935 | B55: 13218 | C55: JUNIO | D55: LUZ | F55: 105.7 | G55: =+G54+E55-F55 -> 36.3
A56: 42935 | B56: 13218 | C56: JUNIO | D56: AGUA | F56: 36.3 | G56: =+G55+E56-F56 -> 0
A57: 42947 | B57: POR COBRAR | C57: JULIO | D57: LUZ | E57: 47.3 | G57: =+G56+E57-F57 -> 47.3
D58: AGUA | E58: 18 | G58: =+G57+E58-F58 -> 65.3
D59: G. ADM | E59: 60 | G59: =+G58+E59-F59 -> 125.3
D60: P. SOCIAL | E60: 2 | G60: =+G59+E60-F60 -> 127.3
A61: 42947 | B61: TARJETA | C61: JULIO | D61: G. ADM | F61: 60 | G61: =+G60+E61-F61 -> 67.3
A62: 42947 | B62: TARJETA | C62: JULIO | D62: P. SOCIAL | F62: 2 | G62: =+G61+E62-F62 -> 65.3
A63: 43061 | B63: 10227 | C63: JULIO | D63: LUZ | F63: 47.3 | G63: =+G62+E63-F63 -> 18
A64: 43061 | B64: 10227 | C64: JULIO | D64: AGUA | F64: 18 | G64: =+G63+E64-F64 -> 0
A65: 42978 | B65: POR COBRAR | C65: AGOSTO | D65: LUZ | E65: 48 | G65: =+G64+E65-F65 -> 48
D66: AGUA | E66: 2 | G66: =+G65+E66-F66 -> 50
D67: G. ADM | E67: 60 | G67: =+G66+E67-F67 -> 110
D68: P. SOCIAL | E68: 2 | G68: =+G67+E68-F68 -> 112
D69: MULTA | E69: 85 | G69: =+G68+E69-F69 -> 197
A70: 43053 | B70: 13973 | C70: AGOSTO | D70: G. ADM | F70: 60 | G70: =+G69+E70-F70 -> 137
A71: 43053 | B71: 13973 | C71: AGOSTO | D71: P. SOCIAL | F71: 2 | G71: =+G70+E71-F71 -> 135
A72: 43061 | B72: 10227 | C72: AGOSTO | D72: LUZ | F72: 48 | G72: =+G71+E72-F72 -> 87
A73: 43061 | B73: 10227 | C73: AGOSTO | D73: AGUA | F73: 2 | G73: =+G72+E73-F73 -> 85
A74: 43067 | B74: EXONERACION | C74: AGOSTO | D74: MULTA | F74: 85 | G74: =+G73+E74-F74 -> 0
A75: 43008 | B75: POR COBRAR | C75: SEPTIEMBRE | D75: LUZ | E75: 23.6 | G75: =+G74+E75-F75 -> 23.6
D76: AGUA | E76: 9 | G76: =+G75+E76-F76 -> 32.6
D77: G. ADM | E77: 60 | G77: =+G76+E77-F77 -> 92.6
D78: P. SOCIAL | E78: 2 | G78: =+G77+E78-F78 -> 94.6
A79: 42788 | D79: MULTA | E79: 85 | G79: =+G78+E79-F79 -> 179.6
A80: 42823 | D80: MULTA | E80: 85 | G80: =+G79+E80-F80 -> 264.6
A81: 43053 | B81: 13973 | C81: SEPTIEMBRE | D81: G. ADM | F81: 60 | G81: =+G80+E81-F81 -> 204.6
A82: 43053 | B82: 13973 | C82: SEPTIEMBRE | D82: P. SOCIAL | F82: 2 | G82: =+G81+E82-F82 -> 202.6
A83: 43061 | B83: 10227 | C83: SEPTIEMBRE | D83: LUZ | F83: 23.6 | G83: =+G82+E83-F83 -> 179
A84: 43061 | B84: 10227 | C84: SEPTIEMBRE | D84: AGUA | F84: 9 | G84: =+G83+E84-F84 -> 170
A85: 43067 | B85: EXONERACION | C85: 42788 | D85: MULTA | F85: 85 | G85: =+G84+E85-F85 -> 85
A86: 43067 | B86: EXONERACION | C86: 42823 | D86: MULTA | F86: 85 | G86: =+G85+E86-F86 -> 0
A87: 43039 | B87: POR COBRAR | C87: OCTUBRE | D87: LUZ | E87: 116.4 | G87: =+G86+E87-F87 -> 116.4
D88: AGUA | E88: 36.3 | G88: =+G87+E88-F88 -> 152.7
D89: G. ADM | E89: 60 | G89: =+G88+E89-F89 -> 212.7
D90: P. SOCIAL | E90: 2 | G90: =+G89+E90-F90 -> 214.7
A91: 42977 | B91: ACT. SANTA ROSA | D91: CUOTA | E91: 10 | G91: =+G90+E91-F91 -> 224.7
A92: 43039 | B92: TARJETA | C92: OCTUBRE | D92: G. ADM | F92: 60 | G92: =+G91+E92-F92 -> 164.7
A93: 43039 | B93: TARJETA | C93: OCTUBRE | D93: P. SOCIAL | F93: 2 | G93: =+G92+E93-F93 -> 162.7
A94: 43066 | B94: 14100 | C94: OCTUBRE | D94: LUZ | F94: 116.4 | G94: =+G93+E94-F94 -> 46.3
A95: 43066 | B95: 14100 | C95: OCTUBRE | D95: AGUA | F95: 36.3 | G95: =+G94+E95-F95 -> 10
A96: 43147 | B96: 7425 | C96: OCTUBRE | D96: CUOTA | F96: 10 | G96: =+G95+E96-F96 -> -1.4210855e-14
A97: 43069 | B97: POR COBRAR | C97: NOVIEMBRE | D97: LUZ | E97: 116 | G97: =+G96+E97-F97 -> 116
D98: AGUA | E98: 36.3 | G98: =+G97+E98-F98 -> 152.3
D99: G. ADM | E99: 60 | G99: =+G98+E99-F99 -> 212.3
D100: P. SOCIAL | E100: 2 | G100: =+G99+E100-F100 -> 214.3
A101: 43104 | B101: 14389 | C101: NOVIEMBRE | D101: LUZ | F101: 116 | G101: =+G100+E101-F101 -> 98.3
A102: 43104 | B102: 14389 | C102: NOVIEMBRE | D102: AGUA | F102: 36.3 | G102: =+G101+E102-F102 -> 62
...

Sheet GUTIERREZ CASTILLO JORGE
B2: GUTIERREZ CASTILLO JORGE
A4: FECHA | B4: DOCUMENTO | C4: PERIODO | D4: CONCEPTO | E4: POR COBRAR | F4: PAGADO | G4: SALDO POR COBRAR
A5: 42736 | B5: SALDO AL 2016 | G5: 162.7
A6: 42786 | B6: 12253 | C6: CANCELACION | F6: 162.7 | G6: =+G5+E6-F6 -> 0
A7: 42766 | B7: POR COBRAR | C7: ENERO | D7: LUZ | E7: 79.4 | G7: =+G6+E7-F7 -> 79.4
D8: AGUA | E8: 2.8 | G8: =+G7+E8-F8 -> 82.2
D9: G. ADM | E9: 60 | G9: =+G8+E9-F9 -> 142.2
D10: P. SOCIAL | E10: 2 | G10: =+G9+E10-F10 -> 144.2
A11: 42765 | B11: TARJETA | C11: ENERO | D11: G. ADM | F11: 58 | G11: =+G10+E11-F11 -> 86.2
A12: 42783 | B12: 12987 | C12: ENERO | D12: G. ADM | F12: 2 | G12: =+G11+E12-F12 -> 84.2
A13: 42783 | B13: 12987 | C13: ENERO | D13: P. SOCIAL | F13: 2 | G13: =+G12+E13-F13 -> 82.2
A14: 42786 | B14: 12253 | C14: ENERO | D14: AGUA | F14: 2.8 | G14: =+G13+E14-F14 -> 79.4
A15: 42786 | B15: 12253 | C15: ENERO | D15: LUZ | F15: 79.4 | G15: =+G14+E15-F15 -> 0
A16: 42794 | B16: POR COBRAR | C16: FEBRERO | D16: LUZ | E16: 81.5 | G16: =+G15+E16-F16 -> 81.5
D17: AGUA | E17: 2 | G17: =+G16+E17-F17 -> 83.5
D18: G. ADM | E18: 56 | G18: =+G17+E18-F18 -> 139.5
D19: P. SOCIAL | E19: 2 | G19: =+G18+E19-F19 -> 141.5
A20: 42794 | B20: TARJETA | C20: FEBRERO | D20: G. ADM | F20: 56 | G20: =+G19+E20-F20 -> 85.5
A21: 42794 | B21: TARJETA | C21: FEBRERO | D21: P. SOCIAL | F21: 2 | G21: =+G20+E21-F21 -> 83.5
A22: 42822 | B22: 12614 | C22: FEBRERO | D22: LUZ | F22: 81.5 | G22: =+G21+E22-F22 -> 2
A23: 42822 | B23: 12614 | C23: FEBRERO | D23: AGUA | F23: 2 | G23: =+G22+E23-F23 -> 0
A24: 42825 | B24: POR COBRAR | C24: MARZO | D24: LUZ | E24: 78 | G24: =+G23+E24-F24 -> 78
D25: AGUA | E25: 2 | G25: =+G24+E25-F25 -> 80
D26: G. ADM | E26: 60 | G26: =+G25+E26-F26 -> 140
D27: P. SOCIAL | E27: 2 | G27: =+G26+E27-F27 -> 142
A28: 42824 | B28: TARJETA | C28: MARZO | D28: G. ADM | F28: 60 | G28: =+G27+E28-F28 -> 82
A29: 42824 | B29: TARJETA | C29: MARZO | D29: P. SOCIAL | F29: 2 | G29: =+G28+E29-F29 -> 80
A30: 42888 | B30: 13038 | C30: MARZO | D30: LUZ | F30: 78 | G30: =+G29+E30-F30 -> 2
A31: 42888 | B31: 13038 | C31: MARZO | D31: AGUA | F31: 2 | G31: =+G30+E31-F31 -> 0
A32: 42855 | B32: POR COBRAR | C32: ABRIL | D32: LUZ | E32: 79.7 | G32: =+G31+E32-F32 -> 79.7
D33: AGUA | E33: 2 | G33: =+G32+E33-F33 -> 81.7
D34: G. ADM | E34: 60 | G34: =+G33+E34-F34 -> 141.7
D35: P. SOCIAL | E35: 2 | G35: =+G34+E35-F35 -> 143.7
A36: 42855 | B36: TARJETA | C36: ABRIL | D36: G. ADM | F36: 60 | G36: =+G35+E36-F36 -> 83.7
A37: 42855 | B37: TARJETA | C37: ABRIL | D37: P. SOCIAL | F37: 2 | G37: =+G36+E37-F37 -> 81.7
A38: 42888 | B38: 13038 | C38: ABRIL | D38: AGUA | F38: 2 | G38: =+G37+E38-F38 -> 79.7
A39: 42888 | B39: 13038 | C39: ABRIL | D39: LUZ | F39: 79.7 | G39: =+G38+E39-F39 -> 0
A40: 42886 | B40: POR COBRAR | C40: MAYO | D40: LUZ | E40: 74.4 | G40: =+G39+E40-F40 -> 74.4
D41: AGUA | E41: 2 | G41: =+G40+E41-F41 -> 76.4
D42: G. ADM | E42: 60 | G42: =+G41+E42-F42 -> 136.4
D43: P. SOCIAL | E43: 2 | G43: =+G42+E43-F43 -> 138.4
A44: 42886 | B44: TARJETA | C44: MAYO | D44: G. ADM | F44: 60 | G44: =+G43+E44-F44 -> 78.4
A45: 42886 | B45: TARJETA | C45: MAYO | D45: P. SOCIAL | F45: 2 | G45: =+G44+E45-F45 -> 76.4
A46: 42949 | B46: 13374 | C46: MAYO | D46: LUZ | F46: 74.4 | G46: =+G45+E46-F46 -> 2
A47: 42949 | B47: 13374 | C47: MAYO | D47: AGUA | F47: 2 | G47: =+G46+E47-F47 -> 0
A48: 42916 | B48: POR COBRAR | C48: JUNIO | D48: LUZ | E48: 72.702 | G48: =+G47+E48-F48 -> 72.702
D49: AGUA | E49: 2 | G49: =+G48+E49-F49 -> 74.702
D50: G. ADM | E50: 60 | G50: =+G49+E50-F50 -> 134.702
D51: P. SOCIAL | E51: 2 | G51: =+G50+E51-F51 -> 136.702
A52: 42916 | B52: TARJETA | C52: JUNIO | D52: G. ADM | F52: 60 | G52: =+G51+E52-F52 -> 76.702
A53: 42916 | B53: TARJETA | C53: JUNIO | D53: P. SOCIAL | F53: 2 | G53: =+G52+E53-F53 -> 74.702
A54: 42949 | B54: 13374 | C54: JUNIO | D54: LUZ | F54: 72.7 | G54: =+G53+E54-F54 -> 2.002
A55: 42949 | B55: 13374 | C55: JUNIO | D55: AGUA | F55: 2 | G55: =+G54+E55-F55 -> 0.002
A56: 42947 | B56: POR COBRAR | C56: JULIO | D56: LUZ | E56: 65.7 | G56: =+G55+E56-F56 -> 65.702
D57: AGUA | E57: 2 | G57: =+G56+E57-F57 -> 67.702
D58: G. ADM | E58: 60 | G58: =+G57+E58-F58 -> 127.702
D59: P. SOCIAL | E59: 2 | G59: =+G58+E59-F59 -> 129.702
A60: 42941 | B60: TARJETA | C60: JULIO | D60: G. ADM | F60: 60 | G60: =+G59+E60-F60 -> 69.702
A61: 42947 | B61: TARJETA | C61: JULIO | D61: P. SOCIAL | F61: 2 | G61: =+G60+E61-F61 -> 67.702
A62: 42971 | B62: 13482 | C62: JULIO | D62: LUZ | F62: 65.7 | G62: =+G61+E62-F62 -> 2.002
A63: 42971 | B63: 13482 | C63: JULIO | D63: AGUA | F63: 2 | G63: =+G62+E63-F63 -> 0.002
A64: 42978 | B64: POR COBRAR | C64: AGOSTO | D64: LUZ | E64: 65.7 | G64: =+G63+E64-F64 -> 65.702
D65: AGUA | E65: 2 | G65: =+G64+E65-F65 -> 67.702
D66: G. ADM | E66: 60 | G66: =+G65+E66-F66 -> 127.702
D67: P. SOCIAL | E67: 2 | G67: =+G66+E67-F67 -> 129.702
D68: MULTA | E68: 85 | G68: =+G67+E68-F68 -> 214.702
A69: 42978 | B69: TARJETA | C69: AGOSTO | D69: G. ADM | F69: 60 | G69: =+G68+E69-F69 -> 154.702
A70: 42978 | B70: TARJETA | C70: AGOSTO | D70: P. SOCIAL | F70: 2 | G70: =+G69+E70-F70 -> 152.702
A71: 43067 | B71: 14130 | C71: AGOSTO | D71: LUZ | F71: 65.7 | G71: =+G70+E71-F71 -> 87.002
A72: 43067 | B72: 14130 | C72: AGOSTO | D72: AGUA | F72: 2 | G72: =+G71+E72-F72 -> 85.002
B73: EXONERACION 50% | C73: AGOSTO | D73: MULTA | F73: 42.5 | G73: =+G72+E73-F73 -> 42.502
A74: 44992 | B74: 26548 | C74: AGOSTO | D74: MULTA | F74: 42.5 | G74: =+G73+E74-F74 -> 0.002
A75: 43008 | B75: POR COBRAR | C75: SEPTIEMBRE | D75: LUZ | E75: 74.5 | G75: =+G74+E75-F75 -> 74.502
D76: AGUA | E76: 2 | G76: =+G75+E76-F76 -> 76.502
D77: G. ADM | E77: 60 | G77: =+G76+E77-F77 -> 136.502
D78: P. SOCIAL | E78: 2 | G78: =+G77+E78-F78 -> 138.502
A79: 42823 | D79: MULTA | E79: 85 | G79: =+G78+E79-F79 -> 223.502
A80: 43008 | B80: TARJETA | C80: SEPTIEMBRE | D80: G. ADM | F80: 60 | G80: =+G79+E80-F80 -> 163.502
A81: 43008 | B81: TARJETA | C81: SEPTIEMBRE | D81: P. SOCIAL | F81: 2 | G81: =+G80+E81-F81 -> 161.502
A82: 43067 | B82: 14130 | C82: SEPTIEMBRE | D82: LUZ | F82: 74.5 | G82: =+G81+E82-F82 -> 87.002
A83: 43067 | B83: 14130 | C83: SEPTIEMBRE | D83: AGUA | F83: 2 | G83: =+G82+E83-F83 -> 85.002
A84: 43186 | B84: 15057 | C84: SEPTIEMBRE | D84: MULTA | F84: 85 | G84: =+G83+E84-F84 -> 0.002
A85: 43039 | B85: POR COBRAR | C85: OCTUBRE | D85: LUZ | E85: 74.1 | G85: =+G84+E85-F85 -> 74.102
D86: AGUA | E86: 2 | G86: =+G85+E86-F86 -> 76.102
D87: G. ADM | E87: 60 | G87: =+G86+E87-F87 -> 136.102
D88: P. SOCIAL | E88: 2 | G88: =+G87+E88-F88 -> 138.102
D89: DEPOSITO | E89: 5 | G89: =+G88+E89-F89 -> 143.102
A90: 43039 | B90: TARJETA | C90: OCTUBRE | D90: G. ADM | F90: 60 | G90: =+G89+E90-F90 -> 83.102
A91: 43039 | B91: TARJETA | C91: OCTUBRE | D91: P. SOCIAL | F91: 2 | G91: =+G90+E91-F91 -> 81.102
A92: 43067 | B92: 14130 | C92: OCTUBRE | D92: LUZ | F92: 74.1 | G92: =+G91+E92-F92 -> 7.002
A93: 43067 | B93: 14130 | C93: OCTUBRE | D93: AGUA | F93: 2 | G93: =+G92+E93-F93 -> 5.002
A94: 43186 | B94: 15057 | C94: OCTUBRE | D94: DEPOSITO | F94: 5 | G94: =+G93+E94-F94 -> 0.002
A95: 43069 | B95: POR COBRAR | C95: NOVIEMBRE | D95: LUZ | E95: 79.1 | G95: =+G94+E95-F95 -> 79.102
D96: AGUA | E96: 2 | G96: =+G95+E96-F96 -> 81.102
D97: G. ADM | E97: 60 | G97: =+G96+E97-F97 -> 141.102
D98: P. SOCIAL | E98: 2 | G98: =+G97+E98-F98 -> 143.102
D99: DEPOSITO | E99: 5 | G99: =+G98+E99-F99 -> 148.102
A100: 43087 | B100: 14278 | C100: NOVIEMBRE | D100: LUZ | F100: 79.1 | G100: =+G99+E100-F100 -> 69.002
A101: 43087 | B101: 14278 | C101: NOVIEMBRE | D101: AGUA | F101: 2 | G101: =+G100+E101-F101 -> 67.002
A102: 43069 | B102: TARJETA | C102: NOVIEMBRE | D102: G. ADM | F102: 60 | G102: =+G101+E102-F102 -> 7.002
...

Sheet GUTIERREZ CASTILLO TERESA
B2: GUTIERREZ CASTILLO TERESA JESUS 21/6
A4: FECHA | B4: DOCUMENTO | C4: PERIODO | D4: CONCEPTO | E4: POR COBRAR | F4: PAGADO | G4: SALDO POR COBRAR
A5: 42736 | B5: SALDO AL 2016 | G5: 108.8
A6: 42767 | B6: 12191 | C6: A CUENTA 2016 | F6: 49.8 | G6: =+G5+E6-F6 -> 59
A7: 42786 | B7: 12306 | C7: A CUENTA 2016 | F7: 59 | G7: =+G6+E7-F7 -> 0
A8: 42766 | B8: POR COBRAR | C8: ENERO | D8: LUZ | E8: 24.5 | G8: =+G7+E8-F8 -> 24.5
D9: AGUA | E9: 4 | G9: =+G8+E9-F9 -> 28.5
D10: G. ADM | E10: 60 | G10: =+G9+E10-F10 -> 88.5
D11: P. SOCIAL | E11: 2 | G11: =+G10+E11-F11 -> 90.5
A12: 42765 | B12: TARJETA | C12: ENERO | D12: G. ADM | F12: 60 | G12: =+G11+E12-F12 -> 30.5
A13: 42765 | B13: TARJETA | C13: ENERO | D13: P. SOCIAL | F13: 2 | G13: =+G12+E13-F13 -> 28.5
A14: 42767 | B14: 12191 | C14: ENERO | D14: LUZ | F14: 24.5 | G14: =+G13+E14-F14 -> 4
A15: 42767 | B15: 12191 | C15: ENERO | D15: AGUA | F15: 4 | G15: =+G14+E15-F15 -> 0
A16: 42794 | B16: POR COBRAR | C16: FEBRERO | D16: LUZ | E16: 13 | G16: =+G15+E16-F16 -> 13
D17: AGUA | E17: 2 | G17: =+G16+E17-F17 -> 15
D18: G. ADM | E18: 56 | G18: =+G17+E18-F18 -> 71
D19: P. SOCIAL | E19: 2 | G19: =+G18+E19-F19 -> 73
D20: MULTA | E20: 85 | G20: =+G19+E20-F20 -> 158
A21: 42795 | B21: 12381 | C21: FEBRERO | D21: G. ADM | F21: 56 | G21: =+G20+E21-F21 -> 102
A22: 42795 | B22: 12381 | C22: FEBRERO | D22: P. SOCIAL | F22: 2 | G22: =+G21+E22-F22 -> 100
A23: 42894 | B23: 13985 | C23: FEBRERO | D23: LUZ | F23: 13 | G23: =+G22+E23-F23 -> 87
A24: 42894 | B24: 13086 | C24: FEBRERO | D24: AGUA | F24: 2 | G24: =+G23+E24-F24 -> 85
A25: 43067 | B25: 185-2017 | C25: FEBRERO | D25: MULTA | F25: 85 | G25: =+G24+E25-F25 -> 0
A26: 42825 | B26: POR COBRAR | C26: MARZO | D26: LUZ | E26: 12 | G26: =+G25+E26-F26 -> 12
D27: AGUA | E27: 2 | G27: =+G26+E27-F27 -> 14
D28: G. ADM | E28: 60 | G28: =+G27+E28-F28 -> 74
D29: P. SOCIAL | E29: 2 | G29: =+G28+E29-F29 -> 76
D30: MULTA | E30: 85 | G30: =+G29+E30-F30 -> 161
A31: 42894 | B31: 13985 | C31: MARZO | D31: G. ADM | F31: 60 | G31: =+G30+E31-F31 -> 101
A32: 42894 | B32: 13985 | C32: MARZO | D32: P. SOCIAL | F32: 2 | G32: =+G31+E32-F32 -> 99
A33: 42894 | B33: 13985 | C33: MARZO | D33: LUZ | F33: 12 | G33: =+G32+E33-F33 -> 87
A34: 42894 | B34: 13086 | C34: MARZO | D34: AGUA | F34: 2 | G34: =+G33+E34-F34 -> 85
A35: 43067 | B35: 185-2017 | C35: MARZO | D35: MULTA | F35: 85 | G35: =+G34+E35-F35 -> 0
A36: 42855 | B36: POR COBRAR | C36: ABRIL | D36: LUZ | E36: 13 | G36: =+G35+E36-F36 -> 13
D37: AGUA | E37: 2 | G37: =+G36+E37-F37 -> 15
D38: G. ADM | E38: 60 | G38: =+G37+E38-F38 -> 75
D39: P. SOCIAL | E39: 2 | G39: =+G38+E39-F39 -> 77
A40: 42894 | B40: 13985 | C40: ABRIL | D40: G. ADM | F40: 60 | G40: =+G39+E40-F40 -> 17
A41: 42894 | B41: 13985 | C41: ABRIL | D41: P. SOCIAL | F41: 2 | G41: =+G40+E41-F41 -> 15
A42: 42894 | B42: 13985 | C42: ABRIL | D42: LUZ | F42: 13 | G42: =+G41+E42-F42 -> 2
A43: 42894 | B43: 13086 | C43: ABRIL | D43: AGUA | F43: 2 | G43: =+G42+E43-F43 -> 0
A44: 42886 | B44: POR COBRAR | C44: MAYO | D44: LUZ | E44: 13 | G44: =+G43+E44-F44 -> 13
D45: AGUA | E45: 2 | G45: =+G44+E45-F45 -> 15
D46: G. ADM | E46: 60 | G46: =+G45+E46-F46 -> 75
D47: P. SOCIAL | E47: 2 | G47: =+G46+E47-F47 -> 77
A48: 42971 | B48: 13481 | C48: MAYO | D48: LUZ | F48: 13 | G48: =+G47+E48-F48 -> 64
A49: 42971 | B49: 13481 | C49: MAYO | D49: AGUA | F49: 2 | G49: =+G48+E49-F49 -> 62
A50: 43063 | B50: 14050 | C50: MAYO | D50: G. ADM | F50: 60 | G50: =+G49+E50-F50 -> 2
A51: 43063 | B51: 14050 | C51: MAYO | D51: P. SOCIAL | F51: 2 | G51: =+G50+E51-F51 -> 0
A52: 42916 | B52: POR COBRAR | C52: JUNIO | D52: LUZ | E52: 13 | G52: =+G51+E52-F52 -> 13
D53: AGUA | E53: 2 | G53: =+G52+E53-F53 -> 15
D54: G. ADM | E54: 60 | G54: =+G53+E54-F54 -> 75
D55: P. SOCIAL | E55: 2 | G55: =+G54+E55-F55 -> 77
A56: 42971 | B56: 13481 | C56: JUNIO | D56: LUZ | F56: 13 | G56: =+G55+E56-F56 -> 64
A57: 42971 | B57: 13481 | C57: JUNIO | D57: AGUA | F57: 2 | G57: =+G56+E57-F57 -> 62
A58: 43063 | B58: 14050 | C58: JUNIO | D58: G. ADM | F58: 60 | G58: =+G57+E58-F58 -> 2
A59: 43063 | B59: 14050 | C59: JUNIO | D59: P. SOCIAL | F59: 2 | G59: =+G58+E59-F59 -> 0
A60: 42947 | B60: POR COBRAR | C60: JULIO | D60: LUZ | E60: 13 | G60: =+G59+E60-F60 -> 13
D61: AGUA | E61: 2 | G61: =+G60+E61-F61 -> 15
D62: G. ADM | E62: 60 | G62: =+G61+E62-F62 -> 75
D63: P. SOCIAL | E63: 2 | G63: =+G62+E63-F63 -> 77
A64: 42971 | B64: 13481 | C64: JULIO | D64: LUZ | F64: 13 | G64: =+G63+E64-F64 -> 64
A65: 42971 | B65: 13481 | C65: JULIO | D65: AGUA | F65: 2 | G65: =+G64+E65-F65 -> 62
A66: 43063 | B66: 14050 | C66: JULIO | D66: G. ADM | F66: 60 | G66: =+G65+E66-F66 -> 2
A67: 43063 | B67: 14050 | C67: JULIO | D67: P. SOCIAL | F67: 2 | G67: =+G66+E67-F67 -> 0
A68: 42978 | B68: POR COBRAR | C68: AGOSTO | D68: LUZ | E68: 13 | G68: =+G67+E68-F68 -> 13
D69: AGUA | E69: 2 | G69: =+G68+E69-F69 -> 15
D70: G. ADM | E70: 60 | G70: =+G69+E70-F70 -> 75
D71: P. SOCIAL | E71: 2 | G71: =+G70+E71-F71 -> 77
D72: MULTA | E72: 85 | G72: =+G71+E72-F72 -> 162
A73: 43063 | B73: 14050 | C73: AGOSTO | D73: G. ADM | F73: 60 | G73: =+G72+E73-F73 -> 102
A74: 43063 | B74: 14050 | C74: AGOSTO | D74: P. SOCIAL | F74: 2 | G74: =+G73+E74-F74 -> 100
A75: 43063 | B75: 14050 | C75: AGOSTO | D75: LUZ | F75: 13 | G75: =+G74+E75-F75 -> 87
A76: 43063 | B76: 14050 | C76: AGOSTO | D76: AGUA | F76: 2 | G76: =+G75+E76-F76 -> 85
A77: 42975 | B77: EXONERACION | C77: AGOSTO | D77: MULTA | F77: 85 | G77: =+G76+E77-F77 -> 0
A78: 43008 | B78: POR COBRAR | C78: SEPTIEMBRE | D78: LUZ | E78: 8 | G78: =+G77+E78-F78 -> 8
D79: AGUA | E79: 2 | G79: =+G78+E79-F79 -> 10
D80: G. ADM | E80: 60 | G80: =+G79+E80-F80 -> 70
D81: P. SOCIAL | E81: 2 | G81: =+G80+E81-F81 -> 72
A82: 43063 | B82: 14051 | C82: SEPTIEMBRE | D82: G. ADM | F82: 60 | G82: =+G81+E82-F82 -> 12
A83: 43063 | B83: 14051 | C83: SEPTIEMBRE | D83: P. SOCIAL | F83: 2 | G83: =+G82+E83-F83 -> 10
A84: 43063 | B84: 14051 | C84: SEPTIEMBRE | D84: LUZ | F84: 8 | G84: =+G83+E84-F84 -> 2
A85: 43063 | B85: 14051 | C85: SEPTIEMBRE | D85: AGUA | F85: 2 | G85: =+G84+E85-F85 -> 0
A86: 43039 | B86: POR COBRAR | C86: OCTUBRE | D86: LUZ | E86: 8 | G86: =+G85+E86-F86 -> 8
D87: AGUA | E87: 2 | G87: =+G86+E87-F87 -> 10
D88: G. ADM | E88: 60 | G88: =+G87+E88-F88 -> 70
D89: P. SOCIAL | E89: 2 | G89: =+G88+E89-F89 -> 72
A90: 43063 | B90: 14051 | C90: OCTUBRE | D90: G. ADM | F90: 60 | G90: =+G89+E90-F90 -> 12
A91: 43063 | B91: 14051 | C91: OCTUBRE | D91: P. SOCIAL | F91: 2 | G91: =+G90+E91-F91 -> 10
A92: 43063 | B92: 14051 | C92: OCTUBRE | D92: LUZ | F92: 8 | G92: =+G91+E92-F92 -> 2
A93: 43063 | B93: 14051 | C93: OCTUBRE | D93: AGUA | F93: 2 | G93: =+G92+E93-F93 -> 0
A94: 43069 | B94: POR COBRAR | C94: NOVIEMBRE | D94: LUZ | E94: 8.2 | G94: =+G93+E94-F94 -> 8.2
D95: AGUA | E95: 2 | G95: =+G94+E95-F95 -> 10.2
D96: G. ADM | E96: 60 | G96: =+G95+E96-F96 -> 70.2
D97: P. SOCIAL | E97: 2 | G97: =+G96+E97-F97 -> 72.2
D98: P. S X FALL. FLORES EMMA | E98: 10 | G98: =+G97+E98-F98 -> 82.2
D99: FUMIGACION | E99: 10 | G99: =+G98+E99-F99 -> 92.2
A100: 42977 | B100: ACT. SANTA ROSA | D100: CUOTA | E100: 25 | G100: =+G99+E100-F100 -> 117.2
A101: 43063 | B101: 14055 | C101: NOVIEMBRE | D101: P. S X FALL. FLORES EMMA | F101: 10 | G101: =+G100+E101-F101 -> 107.2
A102: 42922 | B102: 5736 | C102: NOVIEMBRE | D102: FUMIGACION | F102: 10 | G102: =+G101+E102-F102 -> 97.2
...

Sheet GUTIERRES CASTRO JORGE
B2: GUTIERRES CASTRO JORGE RICARDO
A4: FECHA | B4: DOCUMENTO | C4: PERIODO | D4: CONCEPTO | E4: POR COBRAR | F4: PAGADO | G4: SALDO POR COBRAR
A5: 42736 | B5: SALDO AL 2016 | G5: 2460
A6: 42787 | B6: 12328 | C6: A CUENTA 2016 | F6: 85 | G6: =+G5+E6-F6 -> 2375
A7: 42787 | B7: 12331 | C7: A CUENTA 2016 | F7: 85 | G7: =+G6+E7-F7 -> 2290
A8: 44825 | B8: 25538 | C8: A CUENTA 2016 | F8: 1000 | G8: =+G7+E8-F8 -> 1290
A9: 44992 | B9: 26554 | C9: A CUENTA 2016 | F9: 30 | G9: =+G8+E9-F9 -> 1260
A10: 45741 | B10: 30775 | C10: A CUENTA 2016 | F10: 1260 | G10: =+G9+E10-F10 -> 0
A11: 42766 | B11: POR COBRAR | C11: ENERO | D11: LUZ | E11: 13.5 | G11: =+G10+E11-F11 -> 13.5
D12: AGUA | E12: 2.8 | G12: =+G11+E12-F12 -> 16.3
D13: G. ADM | E13: 60 | G13: =+G12+E13-F13 -> 76.3
D14: P. SOCIAL | E14: 2 | G14: =+G13+E14-F14 -> 78.3
A15: 42786 | B15: 12307 | C15: ENERO | D15: G. ADM | F15: 60 | G15: =+G14+E15-F15 -> 18.3
A16: 42786 | B16: 12307 | C16: ENERO | D16: P. SOCIAL | F16: 2 | G16: =+G15+E16-F16 -> 16.3
A17: 42786 | B17: 12308 | C17: ENERO | D17: LUZ | F17: 13.5 | G17: =+G16+E17-F17 -> 2.8
A18: 42786 | B18: 12308 | C18: ENERO | D18: AGUA | F18: 2.8 | G18: =+G17+E18-F18 -> 0
A19: 42794 | B19: POR COBRAR | C19: FEBRERO | D19: LUZ | E19: 13 | G19: =+G18+E19-F19 -> 13
D20: AGUA | E20: 2 | G20: =+G19+E20-F20 -> 15
D21: G. ADM | E21: 56 | G21: =+G20+E21-F21 -> 71
D22: P. SOCIAL | E22: 2 | G22: =+G21+E22-F22 -> 73
A23: 42795 | B23: 12382 | C23: FEBRERO | D23: G. ADM | F23: 56 | G23: =+G22+E23-F23 -> 17
A24: 42795 | B24: 12382 | C24: FEBRERO | D24: P. SOCIAL | F24: 2 | G24: =+G23+E24-F24 -> 15
A25: 42894 | B25: 13089 | C25: FEBRERO | D25: LUZ | F25: 13 | G25: =+G24+E25-F25 -> 2
A26: 42894 | B26: 13089 | C26: FEBRERO | D26: AGUA | F26: 2 | G26: =+G25+E26-F26 -> 0
A27: 42825 | B27: POR COBRAR | C27: MARZO | D27: LUZ | E27: 12 | G27: =+G26+E27-F27 -> 12
D28: AGUA | E28: 2 | G28: =+G27+E28-F28 -> 14
D29: G. ADM | E29: 60 | G29: =+G28+E29-F29 -> 74
D30: P. SOCIAL | E30: 2 | G30: =+G29+E30-F30 -> 76
A31: 42894 | B31: 13089 | C31: MARZO | D31: LUZ | F31: 12 | G31: =+G30+E31-F31 -> 64
A32: 42894 | B32: 13089 | C32: MARZO | D32: AGUA | F32: 2 | G32: =+G31+E32-F32 -> 62
A33: 42971 | B33: 13484 | C33: MARZO | D33: G. ADM | F33: 60 | G33: =+G32+E33-F33 -> 2
A34: 42971 | B34: 13484 | C34: MARZO | D34: P. SOCIAL | F34: 2 | G34: =+G33+E34-F34 -> 0
A35: 42855 | B35: POR COBRAR | C35: ABRIL | D35: LUZ | E35: 13 | G35: =+G34+E35-F35 -> 13
D36: AGUA | E36: 2 | G36: =+G35+E36-F36 -> 15
D37: G. ADM | E37: 60 | G37: =+G36+E37-F37 -> 75
D38: P. SOCIAL | E38: 2 | G38: =+G37+E38-F38 -> 77
A39: 42894 | B39: 13089 | C39: ABRIL | D39: LUZ | F39: 13 | G39: =+G38+E39-F39 -> 64
A40: 42894 | B40: 13809 | C40: ABRIL | D40: AGUA | F40: 2 | G40: =+G39+E40-F40 -> 62
A41: 42971 | B41: 13484 | C41: ABRIL | D41: G. ADM | F41: 60 | G41: =+G40+E41-F41 -> 2
A42: 42971 | B42: 13484 | C42: ABRIL | D42: P. SOCIAL | F42: 2 | G42: =+G41+E42-F42 -> 0
A43: 42886 | B43: POR COBRAR | C43: MAYO | D43: LUZ | E43: 13 | G43: =+G42+E43-F43 -> 13
D44: AGUA | E44: 2 | G44: =+G43+E44-F44 -> 15
D45: G. ADM | E45: 60 | G45: =+G44+E45-F45 -> 75
D46: P. SOCIAL | E46: 2 | G46: =+G45+E46-F46 -> 77
A47: 42971 | B47: 13483 | C47: MAYO | D47: LUZ | F47: 13 | G47: =+G46+E47-F47 -> 64
A48: 42971 | B48: 13483 | C48: MAYO | D48: AGUA | F48: 2 | G48: =+G47+E48-F48 -> 62
A49: 42971 | B49: 13484 | C49: MAYO | D49: G. ADM | F49: 60 | G49: =+G48+E49-F49 -> 2
A50: 42971 | B50: 13484 | C50: MAYO | D50: P. SOCIAL | F50: 2 | G50: =+G49+E50-F50 -> 0
A51: 42916 | B51: POR COBRAR | C51: JUNIO | D51: LUZ | E51: 13 | G51: =+G50+E51-F51 -> 13
D52: AGUA | E52: 2 | G52: =+G51+E52-F52 -> 15
D53: G. ADM | E53: 60 | G53: =+G52+E53-F53 -> 75
D54: P. SOCIAL | E54: 2 | G54: =+G53+E54-F54 -> 77
A55: 42971 | B55: 13483 | C55: JUNIO | D55: LUZ | F55: 13 | G55: =+G54+E55-F55 -> 64
A56: 42971 | B56: 13483 | C56: JUNIO | D56: AGUA | F56: 2 | G56: =+G55+E56-F56 -> 62
A57: 42971 | B57: 13484 | C57: JUNIO | D57: G. ADM | F57: 60 | G57: =+G56+E57-F57 -> 2
A58: 42971 | B58: 13484 | C58: JUNIO | D58: P. SOCIAL | F58: 2 | G58: =+G57+E58-F58 -> 0
A59: 42947 | B59: POR COBRAR | C59: JULIO | D59: LUZ | E59: 13 | G59: =+G58+E59-F59 -> 13
D60: AGUA | E60: 2 | G60: =+G59+E60-F60 -> 15
D61: G. ADM | E61: 60 | G61: =+G60+E61-F61 -> 75
D62: P. SOCIAL | E62: 2 | G62: =+G61+E62-F62 -> 77
A63: 42971 | B63: 13483 | C63: JULIO | D63: LUZ | F63: 13 | G63: =+G62+E63-F63 -> 64
A64: 42971 | B64: 13483 | C64: JULIO | D64: AGUA | F64: 2 | G64: =+G63+E64-F64 -> 62
A65: 42971 | B65: 13484 | C65: JULIO | D65: G. ADM | F65: 60 | G65: =+G64+E65-F65 -> 2
A66: 42971 | B66: 13484 | C66: JULIO | D66: P. SOCIAL | F66: 2 | G66: =+G65+E66-F66 -> 0
A67: 42978 | B67: POR COBRAR | C67: AGOSTO | D67: LUZ | E67: 13 | G67: =+G66+E67-F67 -> 13
D68: AGUA | E68: 2 | G68: =+G67+E68-F68 -> 15
D69: G. ADM | E69: 60 | G69: =+G68+E69-F69 -> 75
D70: P. SOCIAL | E70: 2 | G70: =+G69+E70-F70 -> 77
D71: MULTA | E71: 85 | G71: =+G70+E71-F71 -> 162
A72: 43001 | B72: 13665 | C72: AGOSTO | D72: LUZ | F72: 13 | G72: =+G71+E72-F72 -> 149
A73: 43001 | B73: 13665 | C73: AGOSTO | D73: AGUA | F73: 2 | G73: =+G72+E73-F73 -> 147
A74: 43017 | B74: 13810 | C74: AGOSTO | D74: G. ADM | F74: 60 | G74: =+G73+E74-F74 -> 87
A75: 43017 | B75: 13810 | C75: AGOSTO | D75: P. SOCIAL | F75: 2 | G75: =+G74+E75-F75 -> 85
A76: 44839 | B76: EXONERACION | C76: 0.5 | D76: MULTA | F76: 42.5 | G76: =+G75+E76-F76 -> 42.5
A77: 45741 | B77: 30775 | C77: AGOSTO | D77: MULTA | F77: 42.5 | G77: =+G76+E77-F77 -> 0
A78: 43008 | B78: POR COBRAR | C78: SEPTIEMBRE | D78: LUZ | E78: 15.5 | G78: =+G77+E78-F78 -> 15.5
D79: AGUA | E79: 1.3 | G79: =+G78+E79-F79 -> 16.8
D80: G. ADM | E80: 60 | G80: =+G79+E80-F80 -> 76.8
D81: P. SOCIAL | E81: 2 | G81: =+G80+E81-F81 -> 78.8
A82: 42788 | D82: MULTA | E82: 85 | G82: =+G81+E82-F82 -> 163.8
A83: 42823 | D83: MULTA | E83: 85 | G83: =+G82+E83-F83 -> 248.8
A84: 43017 | B84: 13810 | C84: SEPTIEMBRE | D84: G. ADM | F84: 60 | G84: =+G83+E84-F84 -> 188.8
A85: 43017 | B85: 13810 | C85: SEPTIEMBRE | D85: P. SOCIAL | F85: 2 | G85: =+G84+E85-F85 -> 186.8
A86: 43029 | B86: 13852 | C86: SEPTIEMBRE | D86: LUZ | F86: 15.5 | G86: =+G85+E86-F86 -> 171.3
A87: 43029 | B87: 13852 | C87: SEPTIEMBRE | D87: AGUA | F87: 1.3 | G87: =+G86+E87-F87 -> 170
A88: 43067 | B88: EXONERACION | C88: 42788 | D88: MULTA | F88: 85 | G88: =+G87+E88-F88 -> 85
A89: 43067 | B89: EXONERACION | C89: 42823 | D89: MULTA | F89: 85 | G89: =+G88+E89-F89 -> 0
A90: 43039 | B90: POR COBRAR | C90: OCTUBRE | D90: LUZ | E90: 15.4 | G90: =+G89+E90-F90 -> 15.4
D91: AGUA | E91: 2 | G91: =+G90+E91-F91 -> 17.4
D92: G. ADM | E92: 60 | G92: =+G91+E92-F92 -> 77.4
D93: P. SOCIAL | E93: 2 | G93: =+G92+E93-F93 -> 79.4
D94: FUMIGACION | E94: 10 | G94: =+G93+E94-F94 -> 89.4
A95: 42977 | B95: ACT. SANTA ROSA | D95: CUOTA | E95: 25 | G95: =+G94+E95-F95 -> 114.4
A96: 43039 | B96: TARJETA | C96: OCTUBRE | D96: G. ADM | F96: 60 | G96: =+G95+E96-F96 -> 54.4
A97: 43039 | B97: TARJETA | C97: OCTUBRE | D97: P. SOCIAL | F97: 2 | G97: =+G96+E97-F97 -> 52.4
A98: 43063 | B98: 14074 | C98: OCTUBRE | D98: LUZ | F98: 15.4 | G98: =+G97+E98-F98 -> 37
A99: 43063 | B99: 14074 | C99: OCTUBRE | D99: AGUA | F99: 2 | G99: =+G98+E99-F99 -> 35
A100: 42922 | B100: 5735 | C100: OCTUBRE | D100: FUMIGACION | F100: 10 | G100: =+G99+E100-F100 -> 25
A101: 43185 | B101: 7446 | C101: SANTA ROSA | D101: CUOTA | F101: 25 | G101: =+G100+E101-F101 -> 0
A102: 43069 | B102: POR COBRAR | C102: NOVIEMBRE | D102: LUZ | E102: 16.4 | G102: =+G101+E102-F102 -> 16.4
...

Sheet GUTIERREZ ROGER
B2: GUTIERREZ FLORES ROGER REYNAN
A4: FECHA | B4: DOCUMENTO | C4: PERIODO | D4: CONCEPTO | E4: POR COBRAR | F4: PAGADO | G4: SALDO POR COBRAR
A5: 42736 | B5: SALDO AL 2016 | G5: 386.6
A6: 42745 | B6: 12101 | C6: A CUENTA 2016 | F6: 150 | G6: =+G5+E6-F6 -> 236.6
A7: 42755 | B7: 12127 | C7: A CUENTA 2016 | F7: 156.1 | G7: =+G6+E7-F7 -> 80.5
A8: 42780 | B8: 12950 | C8: A CUENTA 2016 | F8: 50 | G8: =+G7+E8-F8 -> 30.5
A9: 42786 | B9: 12207 | C9: A CUENTA 2016 | F9: 30 | G9: =+G8+E9-F9 -> 0.5
A10: 43061 | B10: 10232 | C10: CANCELACION 2016 | F10: 0.5 | G10: =+G9+E10-F10 -> 2.8421709e-14
A11: 42766 | B11: POR COBRAR | C11: ENERO | D11: LUZ | E11: 154.6 | G11: =+G10+E11-F11 -> 154.6
D12: AGUA | E12: 51.9 | G12: =+G11+E12-F12 -> 206.5
D13: G. ADM | E13: 60 | G13: =+G12+E13-F13 -> 266.5
D14: P. SOCIAL | E14: 2 | G14: =+G13+E14-F14 -> 268.5
A15: 42765 | B15: TARJETA | C15: ENERO | D15: G. ADM | F15: 60 | G15: =+G14+E15-F15 -> 208.5
A16: 42765 | B16: TARJETA | C16: ENERO | D16: P. SOCIAL | F16: 2 | G16: =+G15+E16-F16 -> 206.5
A17: 42786 | B17: 12207 | C17: ENERO | D17: LUZ | F17: 154.6 | G17: =+G16+E17-F17 -> 51.9
A18: 42786 | B18: 12207 | C18: ENERO | D18: AGUA | F18: 51.9 | G18: =+G17+E18-F18 -> 0
A19: 42794 | B19: POR COBRAR | C19: FEBRERO | D19: LUZ | E19: 98.9 | G19: =+G18+E19-F19 -> 98.9
D20: AGUA | E20: 36 | G20: =+G19+E20-F20 -> 134.9
D21: G. ADM | E21: 56 | G21: =+G20+E21-F21 -> 190.9
D22: P. SOCIAL | E22: 2 | G22: =+G21+E22-F22 -> 192.9
A23: 42794 | B23: TARJETA | C23: FEBRERO | D23: G. ADM | F23: 56 | G23: =+G22+E23-F23 -> 136.9
A24: 42794 | B24: TARJETA | C24: FEBRERO | D24: P. SOCIAL | F24: 2 | G24: =+G23+E24-F24 -> 134.9
A25: 42821 | B25: 12499 | C25: FEBRERO | D25: LUZ | F25: 98.9 | G25: =+G24+E25-F25 -> 36
A26: 42821 | B26: 12499 | C26: FEBRERO | D26: AGUA | F26: 36 | G26: =+G25+E26-F26 -> 0
A27: 42825 | B27: POR COBRAR | C27: MARZO | D27: LUZ | E27: 94.3 | G27: =+G26+E27-F27 -> 94.3
D28: AGUA | E28: 37.8 | G28: =+G27+E28-F28 -> 132.1
D29: G. ADM | E29: 60 | G29: =+G28+E29-F29 -> 192.1
D30: P. SOCIAL | E30: 2 | G30: =+G29+E30-F30 -> 194.1
D31: P. SOCIAL POR FALLECIMIENTO | E31: 10 | G31: =+G30+E31-F31 -> 204.1
A32: 42825 | B32: TARJETA | C32: MARZO | D32: G. ADM | F32: 60 | G32: =+G31+E32-F32 -> 144.1
A33: 42825 | B33: TARJETA | C33: MARZO | D33: P. SOCIAL | F33: 2 | G33: =+G32+E33-F33 -> 142.1
A34: 42846 | B34: 12676 | C34: MARZO | D34: LUZ | F34: 94.3 | G34: =+G33+E34-F34 -> 47.8
A35: 42846 | B35: 12676 | C35: MARZO | D35: AGUA | F35: 37.8 | G35: =+G34+E35-F35 -> 10
A36: 42822 | B36: 12599 | C36: MARZO | D36: P. SOCIAL POR FALLECIMIENTO | F36: 10 | G36: =+G35+E36-F36 -> 0
A37: 42855 | B37: POR COBRAR | C37: ABRIL | D37: LUZ | E37: 97 | G37: =+G36+E37-F37 -> 97
D38: AGUA | E38: 37 | G38: =+G37+E38-F38 -> 134
D39: G. ADM | E39: 60 | G39: =+G38+E39-F39 -> 194
D40: P. SOCIAL | E40: 2 | G40: =+G39+E40-F40 -> 196
A41: 42855 | B41: TARJETA | C41: ABRIL | D41: G. ADM | F41: 60 | G41: =+G40+E41-F41 -> 136
A42: 42855 | B42: TARJETA | C42: ABRIL | D42: P. SOCIAL | F42: 2 | G42: =+G41+E42-F42 -> 134
A43: 42885 | B43: 12866 | C43: ABRIL | D43: LUZ | F43: 97 | G43: =+G42+E43-F43 -> 37
A44: 42885 | B44: 12866 | C44: ABRIL | D44: AGUA | F44: 37 | G44: =+G43+E44-F44 -> 0
A45: 42886 | B45: POR COBRAR | C45: MAYO | D45: LUZ | E45: 91.3 | G45: =+G44+E45-F45 -> 91.3
D46: AGUA | E46: 36.3 | G46: =+G45+E46-F46 -> 127.6
D47: G. ADM | E47: 60 | G47: =+G46+E47-F47 -> 187.6
D48: P. SOCIAL | E48: 2 | G48: =+G47+E48-F48 -> 189.6
A49: 42885 | B49: TARJETA | C49: MAYO | D49: G. ADM | F49: 60 | G49: =+G48+E49-F49 -> 129.6
A50: 42885 | B50: TARJETA | C50: MAYO | D50: P. SOCIAL | F50: 2 | G50: =+G49+E50-F50 -> 127.6
A51: 42914 | B51: 13163 | C51: MAYO | D51: LUZ | F51: 91.3 | G51: =+G50+E51-F51 -> 36.3
A52: 42914 | B52: 13163 | C52: MAYO | D52: AGUA | F52: 36.3 | G52: =+G51+E52-F52 -> 0
A53: 42916 | B53: POR COBRAR | C53: JUNIO | D53: LUZ | E53: 89.1 | G53: =+G52+E53-F53 -> 89.1
D54: AGUA | E54: 36.7 | G54: =+G53+E54-F54 -> 125.8
D55: G. ADM | E55: 60 | G55: =+G54+E55-F55 -> 185.8
D56: P. SOCIAL | E56: 2 | G56: =+G55+E56-F56 -> 187.8
A57: 42916 | B57: TARJETA | C57: JUNIO | D57: G. ADM | F57: 60 | G57: =+G56+E57-F57 -> 127.8
A58: 42916 | B58: TARJETA | C58: JUNIO | D58: P. SOCIAL | F58: 2 | G58: =+G57+E58-F58 -> 125.8
A59: 42947 | B59: 13282 | C59: JUNIO | D59: LUZ | F59: 89.1 | G59: =+G58+E59-F59 -> 36.7
A60: 42947 | B60: 13282 | C60: JUNIO | D60: AGUA | F60: 36.7 | G60: =+G59+E60-F60 -> 0
A61: 42947 | B61: POR COBRAR | C61: JULIO | D61: LUZ | E61: 82.1 | G61: =+G60+E61-F61 -> 82.1
D62: AGUA | E62: 36 | G62: =+G61+E62-F62 -> 118.1
D63: G. ADM | E63: 60 | G63: =+G62+E63-F63 -> 178.1
D64: P. SOCIAL | E64: 2 | G64: =+G63+E64-F64 -> 180.1
A65: 42947 | B65: TARJETA | C65: JULIO | D65: G. ADM | F65: 60 | G65: =+G64+E65-F65 -> 120.1
A66: 42947 | B66: TARJETA | C66: JULIO | D66: P. SOCIAL | F66: 2 | G66: =+G65+E66-F66 -> 118.1
A67: 42982 | B67: 13544 | C67: JULIO | D67: LUZ | F67: 82.1 | G67: =+G66+E67-F67 -> 36
A68: 42982 | B68: 13544 | C68: JULIO | D68: AGUA | F68: 36 | G68: =+G67+E68-F68 -> 0
A69: 42978 | B69: POR COBRAR | C69: AGOSTO | D69: LUZ | E69: 82.1 | G69: =+G68+E69-F69 -> 82.1
D70: AGUA | E70: 36 | G70: =+G69+E70-F70 -> 118.1
D71: G. ADM | E71: 60 | G71: =+G70+E71-F71 -> 178.1
D72: P. SOCIAL | E72: 2 | G72: =+G71+E72-F72 -> 180.1
A73: 42978 | B73: TARJETA | C73: AGOSTO | D73: G. ADM | F73: 60 | G73: =+G72+E73-F73 -> 120.1
A74: 42978 | B74: TARJETA | C74: AGOSTO | D74: P. SOCIAL | F74: 2 | G74: =+G73+E74-F74 -> 118.1
A75: 42998 | B75: 13624 | C75: AGOSTO | D75: LUZ | F75: 82.1 | G75: =+G74+E75-F75 -> 36
A76: 42998 | B76: 13624 | C76: AGOSTO | D76: AGUA | F76: 36 | G76: =+G75+E76-F76 -> 0
A77: 43008 | B77: POR COBRAR | C77: SEPTIEMBRE | D77: LUZ | E77: 73.5 | G77: =+G76+E77-F77 -> 73.5
D78: AGUA | E78: 36.8 | G78: =+G77+E78-F78 -> 110.3
D79: G. ADM | E79: 60 | G79: =+G78+E79-F79 -> 170.3
D80: P. SOCIAL | E80: 2 | G80: =+G79+E80-F80 -> 172.3
A81: 42823 | D81: MULTA | E81: 85 | G81: =+G80+E81-F81 -> 257.3
A82: 43008 | B82: TARJETA | C82: SEPTIEMBRE | D82: G. ADM | F82: 60 | G82: =+G81+E82-F82 -> 197.3
A83: 43008 | B83: TARJETA | C83: SEPTIEMBRE | D83: P. SOCIAL | F83: 2 | G83: =+G82+E83-F83 -> 195.3
A84: 43033 | B84: 13691 | C84: SEPTIEMBRE | D84: LUZ | F84: 73.5 | G84: =+G83+E84-F84 -> 121.8
A85: 43033 | B85: 13691 | C85: SEPTIEMBRE | D85: AGUA | F85: 23.9 | G85: =+G84+E85-F85 -> 97.9
A86: 43061 | B86: 10232 | C86: SEPTIEMBRE | D86: AGUA | F86: 12.9 | G86: =+G85+E86-F86 -> 85
A87: 43067 | B87: EXONERACION | C87: 42823 | D87: MULTA | F87: 85 | G87: =+G86+E87-F87 -> 0
A88: 43039 | B88: POR COBRAR | C88: OCTUBRE | D88: LUZ | E88: 73.1 | G88: =+G87+E88-F88 -> 73.1
D89: AGUA | E89: 36.3 | G89: =+G88+E89-F89 -> 109.4
D90: G. ADM | E90: 60 | G90: =+G89+E90-F90 -> 169.4
D91: P. SOCIAL | E91: 2 | G91: =+G90+E91-F91 -> 171.4
A92: 43039 | B92: TARJETA | C92: OCTUBRE | D92: G. ADM | F92: 60 | G92: =+G91+E92-F92 -> 111.4
A93: 43039 | B93: TARJETA | C93: OCTUBRE | D93: P. SOCIAL | F93: 2 | G93: =+G92+E93-F93 -> 109.4
A94: 43061 | B94: 10232 | C94: OCTUBRE | D94: LUZ | F94: 73.1 | G94: =+G93+E94-F94 -> 36.3
A95: 43061 | B95: 10232 | C95: OCTUBRE | D95: AGUA | F95: 36.3 | G95: =+G94+E95-F95 -> 0
A96: 43069 | B96: POR COBRAR | C96: NOVIEMBRE | D96: LUZ | E96: 78.1 | G96: =+G95+E96-F96 -> 78.1
D97: AGUA | E97: 36.3 | G97: =+G96+E97-F97 -> 114.4
D98: G. ADM | E98: 60 | G98: =+G97+E98-F98 -> 174.4
D99: P. SOCIAL | E99: 2 | G99: =+G98+E99-F99 -> 176.4
D100: P. S X FALL. FLORES EMMA | E100: 10 | G100: =+G99+E100-F100 -> 186.4
A101: 43068 | B101: 14197 | C101: NOVIEMBRE | D101: P. S X FALL. FLORES EMMA | F101: 10 | G101: =+G100+E101-F101 -> 176.4
A102: 43087 | B102: 14266 | C102: NOVIEMBRE | D102: LUZ | F102: 78.1 | G102: =+G101+E102-F102 -> 98.3
...

Sheet HALIRE YUCRA JOSUE
B2: HALIRE YUCRA JOSUE
A3: FECHA | B3: DOCUMENTO | C3: PERIODO | D3: CONCEPTO | E3: POR COBRAR | F3: PAGADO | G3: SALDO POR COBRAR
A4: 42736 | B4: SALDO AL 2016 | G4: 230.6
A5: 42786 | B5: 12293 | C5: A CUENTA 2016 | F5: 150.6 | G5: =+G4+E5-F5 -> 80
A6: 42786 | B6: 12294 | C6: A CUENTA 2016 | F6: 20 | G6: =+G5+E6-F6 -> 60
A7: 42971 | B7: 13466 | C7: CANCELACION 2016 | F7: 60 | G7: =+G6+E7-F7 -> 0
A8: 42766 | B8: POR COBRAR | C8: ENERO | D8: LUZ | E8: 43.3 | G8: =+G7+E8-F8 -> 43.3
D9: AGUA | E9: 2.8 | G9: =+G8+E9-F9 -> 46.1
D10: G. ADM | E10: 60 | G10: =+G9+E10-F10 -> 106.1
D11: P. SOCIAL | E11: 2 | G11: =+G10+E11-F11 -> 108.1
A12: 42765 | B12: TARJETA | C12: ENERO | D12: G. ADM | F12: 60 | G12: =+G11+E12-F12 -> 48.1
A13: 42765 | B13: TARJETA | C13: ENERO | D13: P. SOCIAL | F13: 2 | G13: =+G12+E13-F13 -> 46.1
A14: 42786 | B14: 12293 | C14: ENERO | D14: LUZ | F14: 43.3 | G14: =+G13+E14-F14 -> 2.8
A15: 42786 | B15: 12293 | C15: ENERO | D15: AGUA | F15: 2.8 | G15: =+G14+E15-F15 -> 0
A16: 42794 | B16: POR COBRAR | C16: FEBRERO | D16: LUZ | E16: 43.9 | G16: =+G15+E16-F16 -> 43.9
D17: AGUA | E17: 2 | G17: =+G16+E17-F17 -> 45.9
D18: G. ADM | E18: 56 | G18: =+G17+E18-F18 -> 101.9
D19: P. SOCIAL | E19: 2 | G19: =+G18+E19-F19 -> 103.9
A20: 42794 | B20: TARJETA | C20: FEBRERO | D20: G. ADM | F20: 56 | G20: =+G19+E20-F20 -> 47.9
A21: 42794 | B21: TARJETA | C21: FEBRERO | D21: P. SOCIAL | F21: 2 | G21: =+G20+E21-F21 -> 45.9
A22: 42816 | B22: 12437 | C22: FEBRERO | D22: LUZ | F22: 43.9 | G22: =+G21+E22-F22 -> 2
A23: 42816 | B23: 12347 | C23: FEBRERO | D23: AGUA | F23: 2 | G23: =+G22+E23-F23 -> 7.1054274e-15
A24: 42825 | B24: POR COBRAR | C24: MARZO | D24: LUZ | E24: 41.8 | G24: =+G23+E24-F24 -> 41.8
D25: AGUA | E25: 2 | G25: =+G24+E25-F25 -> 43.8
D26: G. ADM | E26: 60 | G26: =+G25+E26-F26 -> 103.8
D27: P. SOCIAL | E27: 2 | G27: =+G26+E27-F27 -> 105.8
D28: MULTA | E28: 85 | G28: =+G27+E28-F28 -> 190.8
A29: 42824 | B29: TARJETA | C29: MARZO | D29: G. ADM | F29: 60 | G29: =+G28+E29-F29 -> 130.8
A30: 42824 | B30: TARJETA | C30: MARZO | D30: P. SOCIAL | F30: 2 | G30: =+G29+E30-F30 -> 128.8
A31: 42850 | B31: 12699 | C31: MARZO | D31: LUZ | F31: 41.8 | G31: =+G30+E31-F31 -> 87
A32: 42850 | B32: 12699 | C32: MARZO | D32: AGUA | F32: 2 | G32: =+G31+E32-F32 -> 85
A33: 43067 | B33: 14144 | C33: MARZO | D33: MULTA | F33: 85 | G33: =+G32+E33-F33 -> 0
A34: 42855 | B34: POR COBRAR | C34: ABRIL | D34: LUZ | E34: 43.1 | G34: =+G33+E34-F34 -> 43.1
D35: AGUA | E35: 2 | G35: =+G34+E35-F35 -> 45.1
D36: G. ADM | E36: 60 | G36: =+G35+E36-F36 -> 105.1
D37: P. SOCIAL | E37: 2 | G37: =+G36+E37-F37 -> 107.1
A38: 42855 | B38: TARJETA | C38: ABRIL | D38: G. ADM | F38: 60 | G38: =+G37+E38-F38 -> 47.1
A39: 42855 | B39: TARJETA | C39: ABRIL | D39: P. SOCIAL | F39: 2 | G39: =+G38+E39-F39 -> 45.1
A40: 42877 | B40: 12799 | C40: ABRIL | D40: LUZ | F40: 43.1 | G40: =+G39+E40-F40 -> 2
A41: 42877 | B41: 12799 | C41: ABRIL | D41: AGUA | F41: 2 | G41: =+G40+E41-F41 -> -7.1054274e-15
A42: 42886 | B42: POR COBRAR | C42: MAYO | D42: LUZ | E42: 40.7 | G42: =+G41+E42-F42 -> 40.7
D43: AGUA | E43: 2 | G43: =+G42+E43-F43 -> 42.7
D44: G. ADM | E44: 60 | G44: =+G43+E44-F44 -> 102.7
D45: P. SOCIAL | E45: 2 | G45: =+G44+E45-F45 -> 104.7
A46: 42885 | B46: TARJETA | C46: MAYO | D46: G. ADM | F46: 60 | G46: =+G45+E46-F46 -> 44.7
A47: 42885 | B47: TARJETA | C47: MAYO | D47: P. SOCIAL | F47: 2 | G47: =+G46+E47-F47 -> 42.7
A48: 42947 | B48: 13289 | C48: MAYO | D48: LUZ | F48: 40.7 | G48: =+G47+E48-F48 -> 2
A49: 42947 | B49: 13289 | C49: MAYO | D49: AGUA | F49: 2 | G49: =+G48+E49-F49 -> -1.4210855e-14
A50: 42916 | B50: POR COBRAR | C50: JUNIO | D50: LUZ | E50: 39.9 | G50: =+G49+E50-F50 -> 39.9
D51: AGUA | E51: 2 | G51: =+G50+E51-F51 -> 41.9
D52: G. ADM | E52: 60 | G52: =+G51+E52-F52 -> 101.9
D53: P. SOCIAL | E53: 2 | G53: =+G52+E53-F53 -> 103.9
A54: 42916 | B54: TARJETA | C54: JUNIO | D54: G. ADM | F54: 60 | G54: =+G53+E54-F54 -> 43.9
A55: 42916 | B55: TARJETA | C55: JUNIO | D55: P. SOCIAL | F55: 2 | G55: =+G54+E55-F55 -> 41.9
A56: 42971 | B56: 13465 | C56: JUNIO | D56: LUZ | F56: 39.9 | G56: =+G55+E56-F56 -> 2
A57: 42971 | B57: 13465 | C57: JUNIO | D57: AGUA | F57: 2 | G57: =+G56+E57-F57 -> -2.1316282e-14
A58: 42947 | B58: POR COBRAR | C58: JULIO | D58: LUZ | E58: 36.8 | G58: =+G57+E58-F58 -> 36.8
D59: AGUA | E59: 2 | G59: =+G58+E59-F59 -> 38.8
D60: G. ADM | E60: 60 | G60: =+G59+E60-F60 -> 98.8
D61: P. SOCIAL | E61: 2 | G61: =+G60+E61-F61 -> 100.8
A62: 42947 | B62: TARJETA | C62: JULIO | D62: G. ADM | F62: 60 | G62: =+G61+E62-F62 -> 40.8
A63: 42947 | B63: TARJETA | C63: JULIO | D63: P. SOCIAL | F63: 2 | G63: =+G62+E63-F63 -> 38.8
A64: 42971 | B64: 13465 | C64: JULIO | D64: LUZ | F64: 36.8 | G64: =+G63+E64-F64 -> 2
A65: 42971 | B65: 13465 | C65: JULIO | D65: AGUA | F65: 2 | G65: =+G64+E65-F65 -> -1.4210855e-14
A66: 42978 | B66: POR COBRAR | C66: AGOSTO | D66: LUZ | E66: 36.8 | G66: =+G65+E66-F66 -> 36.8
D67: AGUA | E67: 2 | G67: =+G66+E67-F67 -> 38.8
D68: G. ADM | E68: 60 | G68: =+G67+E68-F68 -> 98.8
D69: P. SOCIAL | E69: 2 | G69: =+G68+E69-F69 -> 100.8
D70: MULTA | E70: 85 | G70: =+G69+E70-F70 -> 185.8
A71: 42978 | B71: TARJETA | C71: AGOSTO | D71: G. ADM | F71: 60 | G71: =+G70+E71-F71 -> 125.8
A72: 42978 | B72: TARJETA | C72: AGOSTO | D72: P. SOCIAL | F72: 2 | G72: =+G71+E72-F72 -> 123.8
A73: 43011 | B73: 13782 | C73: AGOSTO | D73: LUZ | F73: 36.8 | G73: =+G72+E73-F73 -> 87
A74: 43011 | B74: 13782 | C74: AGOSTO | D74: AGUA | F74: 2 | G74: =+G73+E74-F74 -> 85
A75: 43067 | B75: 14144 | C75: AGOSTO | D75: MULTA | F75: 85 | G75: =+G74+E75-F75 -> 0
A76: 43008 | B76: POR COBRAR | C76: SEPTIEMBRE | D76: LUZ | E76: 50.3 | G76: =+G75+E76-F76 -> 50.3
D77: AGUA | E77: 1.3 | G77: =+G76+E77-F77 -> 51.6
D78: G. ADM | E78: 60 | G78: =+G77+E78-F78 -> 111.6
D79: P. SOCIAL | E79: 2 | G79: =+G78+E79-F79 -> 113.6
A80: 43008 | B80: TARJETA | C80: SEPTIEMBRE | D80: G. ADM | F80: 60 | G80: =+G79+E80-F80 -> 53.6
A81: 43008 | B81: TARJETA | C81: SEPTIEMBRE | D81: P. SOCIAL | F81: 2 | G81: =+G80+E81-F81 -> 51.6
A82: 43031 | B82: 13866 | C82: SEPTIEMBRE | D82: LUZ | F82: 50.3 | G82: =+G81+E82-F82 -> 1.3
A83: 43031 | B83: 13866 | C83: SEPTIEMBRE | D83: AGUA | F83: 1.3 | G83: =+G82+E83-F83 -> -2.8865799e-15
A84: 43039 | B84: POR COBRAR | C84: OCTUBRE | D84: LUZ | E84: 37 | G84: =+G83+E84-F84 -> 37
D85: AGUA | E85: 2.7 | G85: =+G84+E85-F85 -> 39.7
D86: G. ADM | E86: 60 | G86: =+G85+E86-F86 -> 99.7
D87: P. SOCIAL | E87: 2 | G87: =+G86+E87-F87 -> 101.7
A88: 43039 | B88: TARJETA | C88: OCTUBRE | D88: G. ADM | F88: 60 | G88: =+G87+E88-F88 -> 41.7
A89: 43039 | B89: TARJETA | C89: OCTUBRE | D89: P. SOCIAL | F89: 2 | G89: =+G88+E89-F89 -> 39.7
A90: 43060 | B90: 10206 | C90: OCTUBRE | D90: LUZ | F90: 37 | G90: =+G89+E90-F90 -> 2.7
A91: 43060 | B91: 10206 | C91: OCTUBRE | D91: AGUA | F91: 2.7 | G91: =+G90+E91-F91 -> 0
A92: 43069 | B92: POR COBRAR | C92: NOVIEMBRE | D92: LUZ | E92: 37 | G92: =+G91+E92-F92 -> 37
D93: AGUA | E93: 2 | G93: =+G92+E93-F93 -> 39
D94: G. ADM | E94: 60 | G94: =+G93+E94-F94 -> 99
D95: P. SOCIAL | E95: 2 | G95: =+G94+E95-F95 -> 101
A96: 43087 | B96: 14288 | C96: NOVIEMBRE | D96: LUZ | F96: 37 | G96: =+G95+E96-F96 -> 64
A97: 43087 | B97: 14288 | C97: NOVIEMBRE | D97: AGUA | F97: 2 | G97: =+G96+E97-F97 -> 62
A98: 43069 | B98: TARJETA | C98: NOVIEMBRE | D98: G. ADM | F98: 60 | G98: =+G97+E98-F98 -> 2
A99: 43069 | B99: TARJETA | C99: NOVIEMBRE | D99: P. SOCIAL | F99: 2 | G99: =+G98+E99-F99 -> 0
A100: 43100 | B100: POR COBRAR | C100: DICIEMBRE | D100: LUZ | E100: 58.1 | G100: =+G99+E100-F100 -> 58.1
D101: AGUA | E101: 2 | G101: =+G100+E101-F101 -> 60.1
...

Sheet HEREDIA MARIA
B2: HEREDIA MUÑOZ DE BRAVO MARIA
A4: FECHA | B4: DOCUMENTO | C4: PERIODO | D4: CONCEPTO | E4: POR COBRAR | F4: PAGADO | G4: SALDO POR COBRAR
A5: 42736 | B5: SALDO AL 2016 | G5: 4416.8
A6: 42766 | B6: TARJETA | C6: A CUENTA 2016 | F6: 38 | G6: =+G5+E6-F6 -> 4378.8
A7: 42885 | B7: 12891 | C7: A CUENTA 2016 | F7: 154.8 | G7: =+G6+E7-F7 -> 4224
A8: 43099 | B8: TARJETA | C8: A CUENTA 2016 | F8: 700 | G8: =+G7+E8-F8 -> 3524
A9: 43131 | B9: TARJETA | C9: A CUENTA 2016 | F9: 350 | G9: =+G8+E9-F9 -> 3174
A10: 43373 | B10: TARJETA | C10: A CUENTA 2016 | F10: 75 | G10: =+G9+E10-F10 -> 3099
A11: 43895 | B11: 19877 | C11: A CUENTA 2016 | F11: 1000 | G11: =+G10+E11-F11 -> 2099
A12: 44734 | B12: DESCUENTO 50% | C12: MULTAS | F12: 450 | G12: =+G11+E12-F12 -> 1649
A13: 44754 | B13: R 25078 | C13: A CUENTA 2016 | F13: 1649 | G13: =+G12+E13-F13 -> 0
A14: 42766 | B14: POR COBRAR | C14: ENERO | D14: LUZ | E14: 51.8 | G14: =+G13+E14-F14 -> 51.8
D15: AGUA | E15: 2.7 | G15: =+G14+E15-F15 -> 54.5
D16: G. ADM | E16: 60 | G16: =+G15+E16-F16 -> 114.5
D17: P. SOCIAL | E17: 2 | G17: =+G16+E17-F17 -> 116.5
A18: 42766 | B18: TARJETA | C18: ENERO | D18: G. ADM | F18: 60 | G18: =+G17+E18-F18 -> 56.5
A19: 42766 | B19: TARJETA | C19: ENERO | D19: G. ADM | F19: 2 | G19: =+G18+E19-F19 -> 54.5
A20: 42885 | B20: 12891 | C20: ENERO | D20: LUZ | F20: 51.8 | G20: =+G19+E20-F20 -> 2.7
A21: 42885 | B21: 12891 | C21: ENERO | D21: AGUA | F21: 2.7 | G21: =+G20+E21-F21 -> 0
A22: 42794 | B22: POR COBRAR | C22: FEBRERO | D22: LUZ | E22: 74.9 | G22: =+G21+E22-F22 -> 74.9
D23: AGUA | E23: 2 | G23: =+G22+E23-F23 -> 76.9
D24: G. ADM | E24: 56 | G24: =+G23+E24-F24 -> 132.9
D25: P. SOCIAL | E25: 2 | G25: =+G24+E25-F25 -> 134.9
A26: 42794 | B26: TARJETA | C26: FEBRERO | D26: G. ADM | F26: 40 | G26: =+G25+E26-F26 -> 94.9
A27: 42885 | B27: 12891 | C27: FEBRERO | D27: LUZ | F27: 74.9 | G27: =+G26+E27-F27 -> 20
A28: 42885 | B28: 12891 | C28: FEBRERO | D28: AGUA | F28: 2 | G28: =+G27+E28-F28 -> 18
A29: 44754 | B29: R 25078 | C29: FEBRERO | D29: G. ADM | F29: 16 | G29: =+G28+E29-F29 -> 2
A30: 44754 | B30: R 25078 | C30: FEBRERO | D30: P. SOCIAL | F30: 2 | G30: =+G29+E30-F30 -> 0
A31: 42825 | B31: POR COBRAR | C31: MARZO | D31: LUZ | E31: 50.3 | G31: =+G30+E31-F31 -> 50.3
D32: AGUA | E32: 2 | G32: =+G31+E32-F32 -> 52.3
D33: G. ADM | E33: 60 | G33: =+G32+E33-F33 -> 112.3
D34: P. SOCIAL | E34: 2 | G34: =+G33+E34-F34 -> 114.3
A35: 42885 | B35: 12891 | C35: MARZO | D35: LUZ | F35: 50.3 | G35: =+G34+E35-F35 -> 64
A36: 42885 | B36: 12891 | C36: MARZO | D36: AGUA | F36: 2 | G36: =+G35+E36-F36 -> 62
A37: 44754 | B37: R 25078 | C37: MARZO | D37: G. ADM | F37: 60 | G37: =+G36+E37-F37 -> 2
A38: 44754 | B38: R 25078 | C38: MARZO | D38: P. SOCIAL | F38: 2 | G38: =+G37+E38-F38 -> 0
A39: 42855 | B39: POR COBRAR | C39: ABRIL | D39: LUZ | E39: 51.7 | G39: =+G38+E39-F39 -> 51.7
D40: AGUA | E40: 2 | G40: =+G39+E40-F40 -> 53.7
D41: G. ADM | E41: 60 | G41: =+G40+E41-F41 -> 113.7
D42: P. SOCIAL | E42: 2 | G42: =+G41+E42-F42 -> 115.7
A43: 42885 | B43: 12891 | C43: ABRIL | D43: LUZ | F43: 51.7 | G43: =+G42+E43-F43 -> 64
A44: 42885 | B44: 12891 | C44: ABRIL | D44: AGUA | F44: 2 | G44: =+G43+E44-F44 -> 62
A45: 44754 | B45: R 25078 | C45: ABRIL | D45: G. ADM | F45: 60 | G45: =+G44+E45-F45 -> 2
A46: 44754 | B46: R 25078 | C46: ABRIL | D46: P. SOCIAL | F46: 2 | G46: =+G45+E46-F46 -> 0
A47: 42886 | B47: POR COBRAR | C47: MAYO | D47: LUZ | E47: 48.6 | G47: =+G46+E47-F47 -> 48.6
D48: AGUA | E48: 2 | G48: =+G47+E48-F48 -> 50.6
D49: G. ADM | E49: 60 | G49: =+G48+E49-F49 -> 110.6
D50: P. SOCIAL | E50: 2 | G50: =+G49+E50-F50 -> 112.6
A51: 42971 | B51: 13474 | C51: MAYO | D51: LUZ | F51: 48.6 | G51: =+G50+E51-F51 -> 64
A52: 42971 | B52: 13474 | C52: MAYO | D52: AGUA | F52: 2 | G52: =+G51+E52-F52 -> 62
A53: 44754 | B53: R 25078 | C53: MAYO | D53: G. ADM | F53: 60 | G53: =+G52+E53-F53 -> 2
A54: 44754 | B54: R 25078 | C54: MAYO | D54: P. SOCIAL | F54: 2 | G54: =+G53+E54-F54 -> -7.1054274e-15
A55: 42916 | B55: POR COBRAR | C55: JUNIO | D55: LUZ | E55: 47.6 | G55: =+G54+E55-F55 -> 47.6
D56: AGUA | E56: 2 | G56: =+G55+E56-F56 -> 49.6
D57: G. ADM | E57: 60 | G57: =+G56+E57-F57 -> 109.6
D58: P. SOCIAL | E58: 2 | G58: =+G57+E58-F58 -> 111.6
A59: 42971 | B59: 13474 | C59: JUNIO | D59: LUZ | F59: 47.6 | G59: =+G58+E59-F59 -> 64 | I59: 43.6
A60: 42971 | B60: 13474 | C60: JUNIO | D60: AGUA | F60: 2 | G60: =+G59+E60-F60 -> 62
A61: 44754 | B61: R 25078 | C61: JUNIO | D61: G. ADM | F61: 60 | G61: =+G60+E61-F61 -> 2
A62: 44754 | B62: R 25078 | C62: JUNIO | D62: P. SOCIAL | F62: 2 | G62: =+G61+E62-F62 -> -7.1054274e-15
A63: 42947 | B63: POR COBRAR | C63: JULIO | D63: LUZ | E63: 43.6 | G63: =+G62+E63-F63 -> 43.6
D64: AGUA | E64: 2 | G64: =+G63+E64-F64 -> 45.6
D65: G. ADM | E65: 60 | G65: =+G64+E65-F65 -> 105.6
D66: P. SOCIAL | E66: 2 | G66: =+G65+E66-F66 -> 107.6
A67: 42971 | B67: 13474 | C67: JULIO | D67: LUZ | F67: 43.6 | G67: =+G66+E67-F67 -> 64
A68: 42971 | B68: 13474 | C68: JULIO | D68: AGUA | F68: 2 | G68: =+G67+E68-F68 -> 62
A69: 44754 | B69: R 25078 | C69: JULIO | D69: G. ADM | F69: 60 | G69: =+G68+E69-F69 -> 2
A70: 44754 | B70: R 25078 | C70: JULIO | D70: P. SOCIAL | F70: 2 | G70: =+G69+E70-F70 -> -7.1054274e-15
A71: 42978 | B71: POR COBRAR | C71: AGOSTO | D71: LUZ | E71: 43.6 | G71: =+G70+E71-F71 -> 43.6
D72: AGUA | E72: 2 | G72: =+G71+E72-F72 -> 45.6
D73: G. ADM | E73: 60 | G73: =+G72+E73-F73 -> 105.6
D74: P. SOCIAL | E74: 2 | G74: =+G73+E74-F74 -> 107.6
D75: MULTA | E75: 85 | G75: =+G74+E75-F75 -> 192.6
A76: 43067 | B76: EXONERACION | C76: AGOSTO | D76: MULTA | F76: 85 | G76: =+G75+E76-F76 -> 107.6
A77: 43145 | B77: 14617 | C77: AGOSTO | D77: LUZ | F77: 43.6 | G77: =+G76+E77-F77 -> 64
A78: 43145 | B78: 14617 | C78: AGOSTO | D78: AGUA | F78: 2 | G78: =+G77+E78-F78 -> 62
A79: 44754 | B79: R 25078 | C79: AGOSTO | D79: G. ADM | F79: 60 | G79: =+G78+E79-F79 -> 2
A80: 44754 | B80: R 25078 | C80: AGOSTO | D80: P. SOCIAL | F80: 2 | G80: =+G79+E80-F80 -> -7.1054274e-15
A81: 43008 | B81: POR COBRAR | C81: SEPTIEMBRE | D81: LUZ | E81: 44.5 | G81: =+G80+E81-F81 -> 44.5
D82: AGUA | E82: 2 | G82: =+G81+E82-F82 -> 46.5
D83: G. ADM | E83: 60 | G83: =+G82+E83-F83 -> 106.5
D84: P. SOCIAL | E84: 2 | G84: =+G83+E84-F84 -> 108.5
A85: 42788 | D85: MULTA | E85: 85 | G85: =+G84+E85-F85 -> 193.5
A86: 42823 | D86: MULTA | E86: 85 | G86: =+G85+E86-F86 -> 278.5
A87: 43067 | B87: EXONERACION | C87: 42788 | D87: MULTA | F87: 85 | G87: =+G86+E87-F87 -> 193.5
A88: 43067 | B88: EXONERACION | C88: 42823 | D88: MULTA | F88: 85 | G88: =+G87+E88-F88 -> 108.5
A89: 43145 | B89: 14617 | C89: SEPTIEMBRE | D89: LUZ | F89: 44.5 | G89: =+G88+E89-F89 -> 64
A90: 43145 | B90: 14617 | C90: SEPTIEMBRE | D90: AGUA | F90: 2 | G90: =+G89+E90-F90 -> 62
A91: 44754 | B91: R 25078 | C91: SEPTIEMBRE | D91: G. ADM | F91: 60 | G91: =+G90+E91-F91 -> 2
A92: 44754 | B92: R 25078 | C92: SEPTIEMBRE | D92: P. SOCIAL | F92: 2 | G92: =+G91+E92-F92 -> 0
A93: 43039 | B93: POR COBRAR | C93: OCTUBRE | D93: LUZ | E93: 44.3 | G93: =+G92+E93-F93 -> 44.3
D94: AGUA | E94: 2 | G94: =+G93+E94-F94 -> 46.3
D95: G. ADM | E95: 60 | G95: =+G94+E95-F95 -> 106.3
D96: P. SOCIAL | E96: 2 | G96: =+G95+E96-F96 -> 108.3
A97: 42977 | B97: ACT. SANTA ROSA | D97: CUOTA | E97: 25 | G97: =+G96+E97-F97 -> 133.3
A98: 43063 | B98: 14077 | C98: OCTUBRE | D98: LUZ | F98: 44.3 | G98: =+G97+E98-F98 -> 89
A99: 43063 | B99: 14077 | C99: OCTUBRE | D99: AGUA | F99: 2 | G99: =+G98+E99-F99 -> 87
A100: 44754 | B100: R 25078 | C100: OCTUBRE | D100: G. ADM | F100: 60 | G100: =+G99+E100-F100 -> 27
A101: 44754 | B101: R 25078 | C101: OCTUBRE | D101: P. SOCIAL | F101: 2 | G101: =+G100+E101-F101 -> 25
A102: 44754 | B102: R 25078 | C102: OCTUBRE | D102: CUOTA | F102: 25 | G102: =+G101+E102-F102 -> 0
...

Sheet HUAMANI DOMITILA
B2: HUAMANI ROMERO DOMITILA CLEOFE | I2: DOMITILA CLEOFE HUAMANI ROMERO
A4: FECHA | B4: DOCUMENTO | C4: PERIODO | D4: CONCEPTO | E4: POR COBRAR | F4: PAGADO | G4: SALDO POR COBRAR
A5: 42736 | B5: SALDO AL 2016 | G5: 292.9
A6: 42783 | B6: 12985 | C6: A CUENTA 2016 | F6: 292.9 | G6: =+G5+E6-F6 -> 0
A7: 42766 | B7: POR COBRAR | C7: ENERO | D7: LUZ | E7: 152.9 | G7: =+G6+E7-F7 -> 152.9
D8: AGUA | E8: 2.8 | G8: =+G7+E8-F8 -> 155.7
D9: G. ADM | E9: 60 | G9: =+G8+E9-F9 -> 215.7
D10: P. SOCIAL | E10: 2 | G10: =+G9+E10-F10 -> 217.7
A11: 42783 | B11: 12985 | C11: ENERO | D11: LUZ | F11: 152.9 | G11: =+G10+E11-F11 -> 64.8
A12: 42783 | B12: 12985 | C12: ENERO | D12: AGUA | F12: 2.8 | G12: =+G11+E12-F12 -> 62
A13: 42783 | B13: 12985 | C13: ENERO | D13: G. ADM | F13: 60 | G13: =+G12+E13-F13 -> 2
A14: 42783 | B14: 12985 | C14: ENERO | D14: P. SOCIAL | F14: 2 | G14: =+G13+E14-F14 -> 1.4210855e-14
A15: 42794 | B15: POR COBRAR | C15: FEBRERO | D15: LUZ | E15: 146.4 | G15: =+G14+E15-F15 -> 146.4
D16: AGUA | E16: 2 | G16: =+G15+E16-F16 -> 148.4
D17: G. ADM | E17: 56 | G17: =+G16+E17-F17 -> 204.4
D18: P. SOCIAL | E18: 2 | G18: =+G17+E18-F18 -> 206.4
D19: MULTA | E19: 85 | G19: =+G18+E19-F19 -> 291.4
A20: 42821 | B20: 12569 | C20: FEBRERO | D20: LUZ | F20: 4.4 | G20: =+G19+E20-F20 -> 287
A21: 42821 | B21: 12569 | C21: FEBRERO | D21: AGUA | F21: 2 | G21: =+G20+E21-F21 -> 285
A22: 42821 | B22: 12568 | C22: FEBRERO | D22: MULTA | F22: 85 | G22: =+G21+E22-F22 -> 200
A23: 42821 | B23: 12557 | C23: FEBRERO | D23: G. ADM | F23: 56 | G23: =+G22+E23-F23 -> 144
A24: 42821 | B24: 12557 | C24: FEBRERO | D24: P. SOCIAL | F24: 2 | G24: =+G23+E24-F24 -> 142
A25: 42821 | B25: 12557 | C25: FEBRERO | D25: LUZ | F25: 142 | G25: =+G24+E25-F25 -> 0
A26: 42825 | B26: POR COBRAR | C26: MARZO | D26: LUZ | E26: 140.1 | G26: =+G25+E26-F26 -> 140.1
D27: AGUA | E27: 2 | G27: =+G26+E27-F27 -> 142.1
D28: G. ADM | E28: 60 | G28: =+G27+E28-F28 -> 202.1
D29: P. SOCIAL | E29: 2 | G29: =+G28+E29-F29 -> 204.1
A30: 42850 | B30: 12698 | C30: MARZO | D30: G. ADM | F30: 60 | G30: =+G29+E30-F30 -> 144.1
A31: 42850 | B31: 12698 | C31: MARZO | D31: P. SOCIAL | F31: 2 | G31: =+G30+E31-F31 -> 142.1
A32: 42850 | B32: 12698 | C32: MARZO | D32: LUZ | F32: 140.1 | G32: =+G31+E32-F32 -> 2
A33: 42850 | B33: 12698 | C33: MARZO | D33: AGUA | F33: 2 | G33: =+G32+E33-F33 -> 0
A34: 42855 | B34: POR COBRAR | C34: ABRIL | D34: LUZ | E34: 143.2 | G34: =+G33+E34-F34 -> 143.2
D35: AGUA | E35: 2 | G35: =+G34+E35-F35 -> 145.2
D36: G. ADM | E36: 60 | G36: =+G35+E36-F36 -> 205.2
D37: P. SOCIAL | E37: 2 | G37: =+G36+E37-F37 -> 207.2
A38: 42882 | B38: 12839 | C38: ABRIL | D38: LUZ | F38: 143.2 | G38: =+G37+E38-F38 -> 64
A39: 42882 | B39: 12839 | C39: ABRIL | D39: AGUA | F39: 2 | G39: =+G38+E39-F39 -> 62
A40: 42882 | B40: 12839 | C40: ABRIL | D40: G. ADM | F40: 60 | G40: =+G39+E40-F40 -> 2
A41: 42882 | B41: 12839 | C41: ABRIL | D41: P. SOCIAL | F41: 2 | G41: =+G40+E41-F41 -> 0
A42: 42886 | B42: POR COBRAR | C42: MAYO | D42: LUZ | E42: 133.9 | G42: =+G41+E42-F42 -> 133.9
D43: AGUA | E43: 2 | G43: =+G42+E43-F43 -> 135.9
D44: G. ADM | E44: 60 | G44: =+G43+E44-F44 -> 195.9
D45: P. SOCIAL | E45: 2 | G45: =+G44+E45-F45 -> 197.9
A46: 42909 | B46: 13147 | C46: MAYO | D46: G. ADM | F46: 60 | G46: =+G45+E46-F46 -> 137.9
A47: 42909 | B47: 13147 | C47: MAYO | D47: P. SOCIAL | F47: 2 | G47: =+G46+E47-F47 -> 135.9
A48: 42909 | B48: 13147 | C48: MAYO | D48: LUZ | F48: 133.9 | G48: =+G47+E48-F48 -> 2
A49: 42909 | B49: 13147 | C49: MAYO | D49: AGUA | F49: 2 | G49: =+G48+E49-F49 -> 0
A50: 42916 | B50: POR COBRAR | C50: JUNIO | D50: LUZ | E50: 130.8 | G50: =+G49+E50-F50 -> 130.8
D51: AGUA | E51: 2 | G51: =+G50+E51-F51 -> 132.8
D52: G. ADM | E52: 60 | G52: =+G51+E52-F52 -> 192.8
D53: P. SOCIAL | E53: 2 | G53: =+G52+E53-F53 -> 194.8
A54: 42949 | B54: 13338 | C54: JUNIO | D54: G. ADM | F54: 60 | G54: =+G53+E54-F54 -> 134.8
A55: 42949 | B55: 13338 | C55: JUNIO | D55: P. SOCIAL | F55: 2 | G55: =+G54+E55-F55 -> 132.8
A56: 42949 | B56: 13338 | C56: JUNIO | D56: LUZ | F56: 130.8 | G56: =+G55+E56-F56 -> 2
A57: 42949 | B57: 13338 | C57: JUNIO | D57: AGUA | F57: 2 | G57: =+G56+E57-F57 -> 0
A58: 42947 | B58: POR COBRAR | C58: JULIO | D58: LUZ | E58: 118.7 | G58: =+G57+E58-F58 -> 118.7
D59: AGUA | E59: 2 | G59: =+G58+E59-F59 -> 120.7
D60: G. ADM | E60: 60 | G60: =+G59+E60-F60 -> 180.7
D61: P. SOCIAL | E61: 2 | G61: =+G60+E61-F61 -> 182.7
D62: P. SOCIAL X FALL. | E62: 10 | G62: =+G61+E62-F62 -> 192.7
A63: 42949 | B63: 13338 | C63: JULIO | D63: G. ADM | F63: 60 | G63: =+G62+E63-F63 -> 132.7
A64: 42949 | B64: 13338 | C64: JULIO | D64: P. SOCIAL | F64: 2 | G64: =+G63+E64-F64 -> 130.7
A65: 42949 | B65: 13338 | C65: JULIO | D65: P. SOCIAL X FALL. | F65: 10 | G65: =+G64+E65-F65 -> 120.7
A66: 42971 | B66: 13458 | C66: JULIO | D66: AGUA | F66: 2 | G66: =+G65+E66-F66 -> 118.7
A67: 42971 | B67: 13458 | C67: JULIO | D67: LUZ | F67: 118.7 | G67: =+G66+E67-F67 -> 0
A68: 42978 | B68: POR COBRAR | C68: AGOSTO | D68: LUZ | E68: 118.7 | G68: =+G67+E68-F68 -> 118.7
D69: AGUA | E69: 2 | G69: =+G68+E69-F69 -> 120.7
D70: G. ADM | E70: 60 | G70: =+G69+E70-F70 -> 180.7
D71: P. SOCIAL | E71: 2 | G71: =+G70+E71-F71 -> 182.7
A72: 42998 | B72: 13635 | C72: AGOSTO | D72: G. ADM | F72: 60 | G72: =+G71+E72-F72 -> 122.7
A73: 42998 | B73: 13635 | C73: AGOSTO | D73: P. SOCIAL | F73: 2 | G73: =+G72+E73-F73 -> 120.7
A74: 42998 | B74: 13635 | C74: AGOSTO | D74: AGUA | F74: 2 | G74: =+G73+E74-F74 -> 118.7
A75: 42998 | B75: 13635 | C75: AGOSTO | D75: LUZ | F75: 118.7 | G75: =+G74+E75-F75 -> 0
A76: 43008 | B76: POR COBRAR | C76: SEPTIEMBRE | D76: LUZ | E76: 40.6 | G76: =+G75+E76-F76 -> 40.6
D77: AGUA | E77: 1.3 | G77: =+G76+E77-F77 -> 41.9
D78: G. ADM | E78: 60 | G78: =+G77+E78-F78 -> 101.9
D79: P. SOCIAL | E79: 2 | G79: =+G78+E79-F79 -> 103.9
A80: 43031 | B80: 13857 | C80: SEPTIEMBRE | D80: G. ADM | F80: 60 | G80: =+G79+E80-F80 -> 43.9
A81: 43031 | B81: 13857 | C81: SEPTIEMBRE | D81: P. SOCIAL | F81: 2 | G81: =+G80+E81-F81 -> 41.9
A82: 43031 | B82: 13857 | C82: SEPTIEMBRE | D82: LUZ | F82: 40.6 | G82: =+G81+E82-F82 -> 1.3
A83: 43031 | B83: 13857 | C83: SEPTIEMBRE | D83: AGUA | F83: 1.3 | G83: =+G82+E83-F83 -> 4.2188475e-15
A84: 43039 | B84: POR COBRAR | C84: OCTUBRE | D84: LUZ | E84: 40.8 | G84: =+G83+E84-F84 -> 40.8
D85: AGUA | E85: 23 | G85: =+G84+E85-F85 -> 63.8
D86: G. ADM | E86: 60 | G86: =+G85+E86-F86 -> 123.8
D87: P. SOCIAL | E87: 2 | G87: =+G86+E87-F87 -> 125.8
A88: 43061 | B88: 10224 | C88: OCTUBRE | D88: G. ADM | F88: 60 | G88: =+G87+E88-F88 -> 65.8
A89: 43061 | B89: 10224 | C89: OCTUBRE | D89: P. SOCIAL | F89: 2 | G89: =+G88+E89-F89 -> 63.8
A90: 43061 | B90: 10224 | C90: OCTUBRE | D90: LUZ | F90: 40.8 | G90: =+G89+E90-F90 -> 23
A91: 43061 | B91: 10224 | C91: OCTUBRE | D91: AGUA | F91: 23 | G91: =+G90+E91-F91 -> 0
A92: 43069 | B92: POR COBRAR | C92: NOVIEMBRE | D92: LUZ | E92: 43.1 | G92: =+G91+E92-F92 -> 43.1
D93: AGUA | E93: 2 | G93: =+G92+E93-F93 -> 45.1
D94: G. ADM | E94: 60 | G94: =+G93+E94-F94 -> 105.1
D95: P. SOCIAL | E95: 2 | G95: =+G94+E95-F95 -> 107.1
A96: 43087 | B96: 14307 | C96: NOVIEMBRE | D96: G. ADM | F96: 60 | G96: =+G95+E96-F96 -> 47.1
A97: 43087 | B97: 14307 | C97: NOVIEMBRE | D97: P. SOCIAL | F97: 2 | G97: =+G96+E97-F97 -> 45.1
A98: 43087 | B98: 14307 | C98: NOVIEMBRE | D98: LUZ | F98: 43.1 | G98: =+G97+E98-F98 -> 2
A99: 43087 | B99: 14307 | C99: NOVIEMBRE | D99: AGUA | F99: 2 | G99: =+G98+E99-F99 -> -7.1054274e-15
A100: 43100 | B100: POR COBRAR | C100: DICIEMBRE | D100: LUZ | E100: 46.9 | G100: =+G99+E100-F100 -> 46.9
D101: AGUA | E101: 2 | G101: =+G100+E101-F101 -> 48.9
D102: G. ADM | E102: 60 | G102: =+G101+E102-F102 -> 108.9
...

Sheet HUASHUAYO EUDOSIA
B2: HUASHUAYO GOMEZ EUDOSIA
A4: FECHA | B4: DOCUMENTO | C4: PERIODO | D4: CONCEPTO | E4: POR COBRAR | F4: PAGADO | G4: SALDO POR COBRAR
A5: 42736 | B5: SALDO AL 2016 | G5: 168.2
A6: 42741 | B6: 12077 | C6: A CUENTA 2016 | F6: 114 | G6: =+G5+E6-F6 -> 54.2
A7: 42774 | B7: 12933 | C7: A CUENTA 2016 | F7: 54.2 | G7: =+G6+E7-F7 -> 0
A8: 42766 | B8: POR COBRAR | C8: ENERO | D8: LUZ | E8: 59 | G8: =+G7+E8-F8 -> 59
D9: AGUA | E9: 2.8 | G9: =+G8+E9-F9 -> 61.8
D10: G. ADM | E10: 60 | G10: =+G9+E10-F10 -> 121.8
D11: P. SOCIAL | E11: 2 | G11: =+G10+E11-F11 -> 123.8
A12: 42774 | B12: 12932 | C12: ENERO | D12: G. ADM | F12: 60 | G12: =+G11+E12-F12 -> 63.8
A13: 42774 | B13: 12932 | C13: ENERO | D13: P.S | F13: 2 | G13: =+G12+E13-F13 -> 61.8
A14: 42808 | B14: 12418 | C14: ENERO | D14: LUZ | F14: 59 | G14: =+G13+E14-F14 -> 2.8
A15: 42808 | B15: 12418 | C15: ENERO | D15: AGUA | F15: 2.8 | G15: =+G14+E15-F15 -> 0
A16: 42794 | B16: POR COBRAR | C16: FEBRERO | D16: LUZ | E16: 59.2 | G16: =+G15+E16-F16 -> 59.2
D17: AGUA | E17: 2 | G17: =+G16+E17-F17 -> 61.2
D18: G. ADM | E18: 56 | G18: =+G17+E18-F18 -> 117.2
D19: P. SOCIAL | E19: 2 | G19: =+G18+E19-F19 -> 119.2
D20: DEPOSITO | E20: 100 | G20: =+G19+E20-F20 -> 219.2
A21: 42808 | B21: 12418 | C21: FEBRERO | D21: G. ADM | F21: 56 | G21: =+G20+E21-F21 -> 163.2
A22: 42808 | B22: 12418 | C22: FEBRERO | D22: P.SOCIAL | F22: 2 | G22: =+G21+E22-F22 -> 161.2
A23: 42808 | B23: 12418 | C23: FEBRERO | D23: DEPOSITO | F23: 100 | G23: =+G22+E23-F23 -> 61.2
A24: 42829 | B24: 12630 | C24: FEBRERO | D24: LUZ | F24: 59.2 | G24: =+G23+E24-F24 -> 2
A25: 42829 | B25: 12630 | C25: FEBRERO | D25: AGUA | F25: 2 | G25: =+G24+E25-F25 -> -1.4210855e-14
A26: 42825 | B26: POR COBRAR | C26: MARZO | D26: LUZ | E26: 56 | G26: =+G25+E26-F26 -> 56
D27: AGUA | E27: 2 | G27: =+G26+E27-F27 -> 58
D28: G. ADM | E28: 60 | G28: =+G27+E28-F28 -> 118
D29: P. SOCIAL | E29: 2 | G29: =+G28+E29-F29 -> 120
D30: DEPOSITO | E30: 100 | G30: =+G29+E30-F30 -> 220
A31: 42829 | B31: 12630 | C31: MARZO | D31: G. ADM | F31: 60 | G31: =+G30+E31-F31 -> 160
A32: 42829 | B32: 12630 | C32: MARZO | D32: P. SOCIAL | F32: 2 | G32: =+G31+E32-F32 -> 158
A33: 42842 | B33: 12646 | C33: MARZO | D33: LUZ | F33: 56 | G33: =+G32+E33-F33 -> 102
A34: 42842 | B34: 12646 | C34: MARZO | D34: AGUA | F34: 2 | G34: =+G33+E34-F34 -> 100
A35: 42842 | B35: 12646 | C35: MARZO | D35: DEPOSITO | F35: 100 | G35: =+G34+E35-F35 -> 0
A36: 4 | B36: POR COBRAR | C36: ABRIL | D36: LUZ | E36: 58.3 | G36: =+G35+E36-F36 -> 58.3
D37: AGUA | E37: 2 | G37: =+G36+E37-F37 -> 60.3
D38: G. ADM | E38: 60 | G38: =+G37+E38-F38 -> 120.3
D39: P. SOCIAL | E39: 2 | G39: =+G38+E39-F39 -> 122.3
D40: DEPOSITO | E40: 100 | G40: =+G39+E40-F40 -> 222.3
A41: 42859 | B41: 12720 | C41: ABRIL | D41: G. ADM | F41: 60 | G41: =+G40+E41-F41 -> 162.3
A42: 42859 | B42: 12720 | C42: ABRIL | D42: P. SOCIAL | F42: 2 | G42: =+G41+E42-F42 -> 160.3
A43: 42859 | B43: 12720 | C43: ABRIL | D43: DEPOSITO | F43: 100 | G43: =+G42+E43-F43 -> 60.3
A44: 42880 | B44: 12815 | C44: ABRIL | D44: LUZ | F44: 58.3 | G44: =+G43+E44-F44 -> 2
A45: 42880 | B45: 12815 | C45: ABRIL | D45: AGUA | F45: 2 | G45: =+G44+E45-F45 -> 1.4210855e-14
A46: 42886 | B46: POR COBRAR | C46: MAYO | D46: LUZ | E46: 55.7 | G46: =+G45+E46-F46 -> 55.7
D47: AGUA | E47: 2 | G47: =+G46+E47-F47 -> 57.7
D48: G. ADM | E48: 60 | G48: =+G47+E48-F48 -> 117.7
D49: P. SOCIAL | E49: 2 | G49: =+G48+E49-F49 -> 119.7
D50: DEPOSITO | E50: 100 | G50: =+G49+E50-F50 -> 219.7
A51: 42891 | B51: 13054 | C51: MAYO | D51: G. ADM | F51: 60 | G51: =+G50+E51-F51 -> 159.7
A52: 42891 | B52: 13054 | C52: MAYO | D52: P. SOCIAL | F52: 2 | G52: =+G51+E52-F52 -> 157.7
A53: 42891 | B53: 13056 | C53: MAYO | D53: DEPOSITO | F53: 100 | G53: =+G52+E53-F53 -> 57.7
A54: 42909 | B54: 13138 | C54: MAYO | D54: LUZ | F54: 55.7 | G54: =+G53+E54-F54 -> 2
A55: 42912 | B55: 13138 | C55: MAYO | D55: AGUA | F55: 2 | G55: =+G54+E55-F55 -> 1.4210855e-14
A56: 42916 | B56: POR COBRAR | C56: JUNIO | D56: LUZ | E56: 54.1 | G56: =+G55+E56-F56 -> 54.1
D57: AGUA | E57: 2 | G57: =+G56+E57-F57 -> 56.1
D58: G. ADM | E58: 60 | G58: =+G57+E58-F58 -> 116.1
D59: P. SOCIAL | E59: 2 | G59: =+G58+E59-F59 -> 118.1
D60: DEPOSITO | E60: 100 | G60: =+G59+E60-F60 -> 218.1
A61: 42927 | B61: 13197 | C61: JUNIO | D61: DEPOSITO | F61: 100 | G61: =+G60+E61-F61 -> 118.1
A62: 42927 | B62: 13197 | C62: JUNIO | D62: G. ADM | F62: 60 | G62: =+G61+E62-F62 -> 58.1
A63: 42917 | B63: 13197 | C63: JUNIO | D63: P. SOCIAL | F63: 2 | G63: =+G62+E63-F63 -> 56.1
A64: 42950 | B64: 13416 | C64: JUNIO | D64: LUZ | F64: 54.1 | G64: =+G63+E64-F64 -> 2
A65: 42950 | B65: 13416 | C65: JUNIO | D65: AGUA | F65: 2 | G65: =+G64+E65-F65 -> 2.1316282e-14
A66: 42947 | B66: POR COBRAR | C66: JULIO | D66: LUZ | E66: 51.5 | G66: =+G65+E66-F66 -> 51.5
D67: AGUA | E67: 2 | G67: =+G66+E67-F67 -> 53.5
D68: G. ADM | E68: 60 | G68: =+G67+E68-F68 -> 113.5
D69: P. SOCIAL | E69: 2 | G69: =+G68+E69-F69 -> 115.5
D70: DEPOSITO | E70: 100 | G70: =+G69+E70-F70 -> 215.5
A71: 42950 | B71: 13415 | C71: JULIO | D71: G. ADM | F71: 60 | G71: =+G70+E71-F71 -> 155.5
A72: 42950 | B72: 13415 | C72: JULIO | D72: DEPOSITO | F72: 100 | G72: =+G71+E72-F72 -> 55.5
A73: 42950 | B73: 13415 | C73: JULIO | D73: P. SOCIAL | F73: 2 | G73: =+G72+E73-F73 -> 53.5
A74: 42970 | B74: 13455 | C74: JULIO | D74: LUZ | F74: 51.5 | G74: =+G73+E74-F74 -> 2
A75: 42970 | B75: 13455 | C75: JULIO | D75: AGUA | F75: 2 | G75: =+G74+E75-F75 -> 2.8421709e-14
A76: 42978 | B76: POR COBRAR | C76: AGOSTO | D76: LUZ | E76: 51.5 | G76: =+G75+E76-F76 -> 51.5
D77: AGUA | E77: 2 | G77: =+G76+E77-F77 -> 53.5
D78: G. ADM | E78: 60 | G78: =+G77+E78-F78 -> 113.5
D79: P. SOCIAL | E79: 2 | G79: =+G78+E79-F79 -> 115.5
D80: DEPOSITO | E80: 100 | G80: =+G79+E80-F80 -> 215.5
A81: 42970 | B81: 13455 | C81: AGOSTO | D81: DEPOSITO | F81: 100 | G81: =+G80+E81-F81 -> 115.5
A82: 42984 | B82: 13554 | C82: AGOSTO | D82: G. ADM | F82: 60 | G82: =+G81+E82-F82 -> 55.5
A83: 42984 | B83: 13554 | C83: AGOSTO | D83: P. SOCIAL | F83: 2 | G83: =+G82+E83-F83 -> 53.5
A84: 42998 | B84: 13625 | C84: AGOSTO | D84: LUZ | F84: 51.5 | G84: =+G83+E84-F84 -> 2
A85: 42998 | B85: 13625 | C85: AGOSTO | D85: AGUA | F85: 2 | G85: =+G84+E85-F85 -> 2.8421709e-14
A86: 43008 | B86: POR COBRAR | C86: SEPTIEMBRE | D86: LUZ | E86: 81.2 | G86: =+G85+E86-F86 -> 81.2
D87: AGUA | E87: 2 | G87: =+G86+E87-F87 -> 83.2
D88: G. ADM | E88: 60 | G88: =+G87+E88-F88 -> 143.2
D89: P. SOCIAL | E89: 2 | G89: =+G88+E89-F89 -> 145.2
D90: DEPOSITO | E90: 100 | G90: =+G89+E90-F90 -> 245.2
A91: 42788 | D91: MULTA | E91: 85 | G91: =+G90+E91-F91 -> 330.2
A92: 42823 | D92: MULTA | E92: 85 | G92: =+G91+E92-F92 -> 415.2
A93: 42951 | D93: MULTA | E93: 85 | G93: =+G92+E93-F93 -> 500.2
A94: 42998 | B94: 13626 | C94: SEPTIEMBRE | D94: DEPOSITO | F94: 100 | G94: =+G93+E94-F94 -> 400.2
A95: 43012 | B95: 13790 | C95: SEPTIEMBRE | D95: G. ADM | F95: 60 | G95: =+G94+E95-F95 -> 340.2
A96: 43012 | B96: 13790 | C96: SEPTIEMBRE | D96: P. SOCIAL | F96: 2 | G96: =+G95+E96-F96 -> 338.2
A97: 43029 | B97: 13851 | C97: SEPTIEMBRE | D97: LUZ | F97: 81.2 | G97: =+G96+E97-F97 -> 257
A98: 43029 | B98: 13851 | C98: SEPTIEMBRE | D98: AGUA | F98: 1.3 | G98: =+G97+E98-F98 -> 255.7
A99: 43062 | B99: 14014 | C99: SEPTIEMBRE | D99: AGUA | F99: 0.7 | G99: =+G98+E99-F99 -> 255
A100: 43067 | B100: EXONERACION | C100: 42788 | D100: MULTA | F100: 85 | G100: =+G99+E100-F100 -> 170
A101: 43067 | B101: EXONERACION | C101: 42823 | D101: MULTA | F101: 85 | G101: =+G100+E101-F101 -> 85
A102: 43069 | B102: 231-2017 | C102: 42951 | D102: MULTA | F102: 85 | G102: =+G101+E102-F102 -> 0
...

Sheet HUAYHUALLA DONATILA
B2: HUAYHUALLA DE LOPEZ DONATILA
A4: FECHA | B4: DOCUMENTO | C4: PERIODO | D4: CONCEPTO | E4: POR COBRAR | F4: PAGADO | G4: SALDO POR COBRAR
A5: 42736 | B5: SALDO AL 2016 | G5: 238.6
A6: 42754 | B6: 12121 | C6: A CUENTA 2016 | F6: 158.6 | G6: =+G5+E6-F6 -> 80
A7: 42783 | B7: 12976 | C7: A CUENTA 2016 | F7: 40 | G7: =+G6+E7-F7 -> 40
A8: 42821 | B8: 12519 | C8: A CUENTA 2016 | F8: 40 | G8: =+G7+E8-F8 -> 0
A9: 42766 | B9: POR COBRAR | C9: ENERO | D9: LUZ | E9: 60.3 | G9: =+G8+E9-F9 -> 60.3
D10: AGUA | E10: 31.8 | G10: =+G9+E10-F10 -> 92.1
