Workbook

Sheet Marin Rocha ESTEFANY
B2: MARIN ROCHA ESTEFANY JULISSA - ROCHA JULIIA
A4: FECHA | B4: DOCUMENTO | C4: PERIODO | D4: CONCEPTO | E4: POR COBRAR | F4: PAGADO | G4: SALDO POR COBRAR
A5: 42736 | B5: SALDO AL 2016 | G5: 156.6
A6: 42737 | B6: 12046 | C6: A CUENTA DEL 2016 | F6: 109.5 | G6: =+G5+E6-F6 -> 47.1
A7: 42768 | B7: 12196 | C7: A CUENTA DEL 2016 | F7: 47.1 | G7: =+G6+E7-F7 -> 0
A8: 42766 | B8: POR COBRAR | C8: ENERO | D8: LUZ | E8: 43.3 | G8: =+G7+E8-F8 -> 43.3
D9: AGUA | E9: 2.8 | G9: =+G8+E9-F9 -> 46.1
D10: G. ADM | E10: 60 | G10: =+G9+E10-F10 -> 106.1
D11: P. SOCIAL | E11: 2 | G11: =+G10+E11-F11 -> 108.1
D12: P.S.FALLEC. | E12: 10 | G12: =+G11+E12-F12 -> 118.1
A13: 42774 | B13: 12929 | C13: ENERO | D13: P.S.FALLEC. | F13: 10 | G13: =+G12+E13-F13 -> 108.1
A14: 42768 | B14: 12196 | C14: ENERO | D14: G. ADM | F14: 60 | G14: =+G13+E14-F14 -> 48.1
A15: 42768 | B15: 12196 | C15: ENERO | D15: P. SOCIAL | F15: 2 | G15: =+G14+E15-F15 -> 46.1
A16: 42786 | B16: 12252 | C16: ENERO | D16: LUZ | F16: 43.3 | G16: =+G15+E16-F16 -> 2.8
A17: 42786 | B17: 12252 | C17: ENERO | D17: AGUA | F17: 2.8 | G17: =+G16+E17-F17 -> 0
A18: 42794 | B18: POR COBRAR | C18: FEBRERO | D18: LUZ | E18: 43.9 | G18: =+G17+E18-F18 -> 43.9
D19: AGUA | E19: 2 | G19: =+G18+E19-F19 -> 45.9
D20: G. ADM | E20: 56 | G20: =+G19+E20-F20 -> 101.9
D21: P. SOCIAL | E21: 2 | G21: =+G20+E21-F21 -> 103.9
A22: 42794 | B22: 12378 | C22: FEBRERO | D22: G. ADM | F22: 56 | G22: =+G21+E22-F22 -> 47.9
A23: 42794 | B23: 12378 | C23: FEBRERO | D23: P. SOCIAL | F23: 2 | G23: =+G22+E23-F23 -> 45.9
A24: 42821 | B24: 12543 | C24: FEBRERO | D24: LUZ | F24: 43.9 | G24: =+G23+E24-F24 -> 2
A25: 42821 | B25: 12543 | C25: FEBRERO | D25: AGUA | F25: 2 | G25: =+G24+E25-F25 -> 7.1054274e-15
A26: 42825 | B26: POR COBRAR | C26: MARZO | D26: LUZ | E26: 41.8 | G26: =+G25+E26-F26 -> 41.8
D27: AGUA | E27: 2 | G27: =+G26+E27-F27 -> 43.8
D28: G. ADM | E28: 60 | G28: =+G27+E28-F28 -> 103.8
D29: P. SOCIAL | E29: 2 | G29: =+G28+E29-F29 -> 105.8
A30: 42885 | B30: 12882 | C30: MARZO | D30: LUZ | F30: 41.8 | G30: =+G29+E30-F30 -> 64
A31: 42885 | B31: 12882 | C31: MARZO | D31: AGUA | F31: 2 | G31: =+G30+E31-F31 -> 62
A32: 42885 | B32: 12882 | C32: MARZO | D32: G. ADM | F32: 60 | G32: =+G31+E32-F32 -> 2
A33: 42885 | B33: 12882 | C33: MARZO | D33: P. SOCIAL | F33: 2 | G33: =+G32+E33-F33 -> 1.4210855e-14
A34: 42855 | B34: POR COBRAR | C34: ABRIL | D34: LUZ | E34: 43.1 | G34: =+G33+E34-F34 -> 43.1
D35: AGUA | E35: 2 | G35: =+G34+E35-F35 -> 45.1
D36: G. ADM | E36: 60 | G36: =+G35+E36-F36 -> 105.1
D37: P. SOCIAL | E37: 2 | G37: =+G36+E37-F37 -> 107.1
A38: 42885 | B38: 12882 | C38: ABRIL | D38: LUZ | F38: 43.1 | G38: =+G37+E38-F38 -> 64
A39: 42885 | B39: 12882 | C39: ABRIL | D39: AGUA | F39: 2 | G39: =+G38+E39-F39 -> 62
A40: 42885 | B40: 12882 | C40: ABRIL | D40: G. ADM | F40: 60 | G40: =+G39+E40-F40 -> 2
A41: 42885 | B41: 12882 | C41: ABRIL | D41: P. SOCIAL | F41: 2 | G41: =+G40+E41-F41 -> 2.8421709e-14
A42: 42886 | B42: POR COBRAR | C42: MAYO | D42: LUZ | E42: 40.7 | G42: =+G41+E42-F42 -> 40.7
D43: AGUA | E43: 2 | G43: =+G42+E43-F43 -> 42.7
D44: G. ADM | E44: 60 | G44: =+G43+E44-F44 -> 102.7
D45: P. SOCIAL | E45: 2 | G45: =+G44+E45-F45 -> 104.7
A46: 42885 | B46: 12882 | C46: MAYO | D46: G. ADM | F46: 60 | G46: =+G45+E46-F46 -> 44.7
A47: 42885 | B47: 12882 | C47: MAYO | D47: P. SOCIAL | F47: 2 | G47: =+G46+E47-F47 -> 42.7
A48: 42948 | B48: 13317 | C48: MAYO | D48: LUZ | F48: 40.7 | G48: =+G47+E48-F48 -> 2
A49: 42948 | B49: 13317 | C49: MAYO | D49: AGUA | F49: 2 | G49: =+G48+E49-F49 -> 2.8421709e-14
A50: 42916 | B50: POR COBRAR | C50: JUNIO | D50: LUZ | E50: 39.7 | G50: =+G49+E50-F50 -> 39.7
D51: AGUA | E51: 2 | G51: =+G50+E51-F51 -> 41.7
D52: G. ADM | E52: 60 | G52: =+G51+E52-F52 -> 101.7
D53: P. SOCIAL | E53: 2 | G53: =+G52+E53-F53 -> 103.7
A54: 42948 | B54: 13317 | C54: JUNIO | D54: G. ADM | F54: 60 | G54: =+G53+E54-F54 -> 43.7
A55: 42948 | B55: 13317 | C55: JUNIO | D55: P. SOCIAL | F55: 2 | G55: =+G54+E55-F55 -> 41.7
A56: 42948 | B56: 13317 | C56: JUNIO | D56: LUZ | F56: 39.7 | G56: =+G55+E56-F56 -> 2
A57: 42948 | B57: 13317 | C57: JUNIO | D57: AGUA | F57: 2 | G57: =+G56+E57-F57 -> 2.8421709e-14
A58: 42947 | B58: POR COBRAR | C58: JULIO | D58: LUZ | E58: 36.8 | G58: =+G57+E58-F58 -> 36.8
D59: AGUA | E59: 2 | G59: =+G58+E59-F59 -> 38.8
D60: G. ADM | E60: 60 | G60: =+G59+E60-F60 -> 98.8
D61: P. SOCIAL | E61: 2 | G61: =+G60+E61-F61 -> 100.8
A62: 42948 | B62: 13317 | C62: JULIO | D62: G. ADM | F62: 60 | G62: =+G61+E62-F62 -> 40.8
A63: 42948 | B63: 13317 | C63: JULIO | D63: P. SOCIAL | F63: 2 | G63: =+G62+E63-F63 -> 38.8
A64: 42971 | B64: 13462 | C64: JULIO | D64: LUZ | F64: 36.8 | G64: =+G63+E64-F64 -> 2
A65: 42971 | B65: 13462 | C65: JULIO | D65: AGUA | F65: 2 | G65: =+G64+E65-F65 -> 2.8421709e-14
A66: 42978 | B66: POR COBRAR | C66: AGOSTO | D66: LUZ | E66: 36.8 | G66: =+G65+E66-F66 -> 36.8
D67: AGUA | E67: 2 | G67: =+G66+E67-F67 -> 38.8
D68: G. ADM | E68: 60 | G68: =+G67+E68-F68 -> 98.8
D69: P. SOCIAL | E69: 2 | G69: =+G68+E69-F69 -> 100.8
A70: 42991 | B70: 13570 | C70: AGOSTO | D70: G. ADM | F70: 60 | G70: =+G69+E70-F70 -> 40.8
A71: 42991 | B71: 13570 | C71: AGOSTO | D71: P. SOCIAL | F71: 2 | G71: =+G70+E71-F71 -> 38.8
A72: 43005 | B72: 13684 | C72: AGOSTO | D72: LUZ | F72: 36.8 | G72: =+G71+E72-F72 -> 2
A73: 43005 | B73: 13684 | C73: AGOSTO | D73: AGUA | F73: 2 | G73: =+G72+E73-F73 -> 2.8421709e-14
A74: 43008 | B74: POR COBRAR | C74: SEPTIEMBRE | D74: LUZ | E74: 40.6 | G74: =+G73+E74-F74 -> 40.6
D75: AGUA | E75: 2 | G75: =+G74+E75-F75 -> 42.6
D76: G. ADM | E76: 60 | G76: =+G75+E76-F76 -> 102.6
D77: P. SOCIAL | E77: 2 | G77: =+G76+E77-F77 -> 104.6
A78: 43038 | B78: 13904 | C78: SEPTIEMBRE | D78: LUZ | F78: 40.6 | G78: =+G77+E78-F78 -> 64
A79: 43038 | B79: 13904 | C79: SEPTIEMBRE | D79: AGUA | F79: 2 | G79: =+G78+E79-F79 -> 62
A80: 43060 | B80: 10204 | C80: SEPTIEMBRE | D80: G. ADM | F80: 60 | G80: =+G79+E80-F80 -> 2
A81: 43060 | B81: 10204 | C81: SEPTIEMBRE | D81: P. SOCIAL | F81: 2 | G81: =+G80+E81-F81 -> 2.8421709e-14
A82: 43039 | B82: POR COBRAR | C82: OCTUBRE | D82: LUZ | E82: 40.4 | G82: =+G81+E82-F82 -> 40.4
D83: AGUA | E83: 2 | G83: =+G82+E83-F83 -> 42.4
D84: G. ADM | E84: 60 | G84: =+G83+E84-F84 -> 102.4
D85: P. SOCIAL | E85: 2 | G85: =+G84+E85-F85 -> 104.4
A86: 43060 | B86: 10205 | C86: OCTUBRE | D86: G. ADM | F86: 60 | G86: =+G85+E86-F86 -> 44.4
A87: 43060 | B87: 10205 | C87: OCTUBRE | D87: P. SOCIAL | F87: 2 | G87: =+G86+E87-F87 -> 42.4
A88: 43063 | B88: 14048 | C88: OCTUBRE | D88: LUZ | F88: 40.4 | G88: =+G87+E88-F88 -> 2
A89: 43063 | B89: 14048 | C89: OCTUBRE | D89: AGUA | F89: 2 | G89: =+G88+E89-F89 -> 3.5527137e-14
A90: 43069 | B90: POR COBRAR | C90: NOVIEMBRE | D90: LUZ | E90: 43.1 | G90: =+G89+E90-F90 -> 43.1
D91: AGUA | E91: 2 | G91: =+G90+E91-F91 -> 45.1
D92: G. ADM | E92: 60 | G92: =+G91+E92-F92 -> 105.1
D93: P. SOCIAL | E93: 2 | G93: =+G92+E93-F93 -> 107.1
A94: 43087 | B94: 14303 | C94: NOVIEMBRE | D94: G. ADM | F94: 60 | G94: =+G93+E94-F94 -> 47.1
A95: 43087 | B95: 14303 | C95: NOVIEMBRE | D95: P. SOCIAL | F95: 2 | G95: =+G94+E95-F95 -> 45.1
A96: 43087 | B96: 14304 | C96: NOVIEMBRE | D96: LUZ | F96: 43.1 | G96: =+G95+E96-F96 -> 2
A97: 43087 | B97: 14304 | C97: NOVIEMBRE | D97: AGUA | F97: 2 | G97: =+G96+E97-F97 -> 3.5527137e-14
A98: 43100 | B98: POR COBRAR | C98: DICIEMBRE | D98: LUZ | E98: 46.9 | G98: =+G97+E98-F98 -> 46.9
D99: AGUA | E99: 2 | G99: =+G98+E99-F99 -> 48.9
D100: G. ADM | E100: 60 | G100: =+G99+E100-F100 -> 108.9
D101: P. SOCIAL | E101: 2 | G101: =+G100+E101-F101 -> 110.9
A102: 43099 | B102: 14373 | C102: DICIEMBRE | D102: G. ADM | F102: 60 | G102: =+G101+E102-F102 -> 50.9
...

Sheet MAYHUASCA  CLUDY
B2: CLUDY AYDE MAYHUASCA BASTIDAS
A4: FECHA | B4: DOCUMENTO | C4: PERIODO | D4: CONCEPTO | E4: POR COBRAR | F4: PAGADO | G4: SALDO POR COBRAR
A5: 42736 | B5: SALDO AL 2016 | G5: 1494.1
A6: 42754 | B6: 12125 | C6: A CUENTA 2016 | F6: 274.1 | G6: =+G5+E6-F6 -> 1220
A7: 42881 | B7: 12827 | C7: CANCELADO | F7: 1220 | G7: =+G6+E7-F7 -> 0
A8: 42766 | B8: POR COBRAR | C8: ENERO | D8: LUZ | E8: 167.5 | G8: =+G7+E8-F8 -> 167.5
D9: AGUA | E9: 32 | G9: =+G8+E9-F9 -> 199.5
D10: G. ADM | E10: 60 | G10: =+G9+E10-F10 -> 259.5
D11: P. SOCIAL | E11: 2 | G11: =+G10+E11-F11 -> 261.5
A12: 42766 | B12: TARJETA | C12: ENERO | D12: G. ADM | F12: 60 | G12: =+G11+E12-F12 -> 201.5
A13: 42766 | B13: TARJETA | C13: ENERO | D13: P. SOCIAL | F13: 2 | G13: =+G12+E13-F13 -> 199.5
A14: 42787 | B14: 12315 | C14: ENERO | D14: LUZ | F14: 167.5 | G14: =+G13+E14-F14 -> 32
A15: 42787 | B15: 12315 | C15: ENERO | D15: AGUA | F15: 32 | G15: =+G14+E15-F15 -> 0
A16: 42794 | B16: POR COBRAR | C16: FEBRERO | D16: LUZ | E16: 219.6 | G16: =+G15+E16-F16 -> 219.6
D17: AGUA | E17: 22 | G17: =+G16+E17-F17 -> 241.6
D18: G. ADM | E18: 56 | G18: =+G17+E18-F18 -> 297.6
D19: P. SOCIAL | E19: 2 | G19: =+G18+E19-F19 -> 299.6
A20: 42794 | B20: TARJETA | C20: FEBRERO | D20: G. ADM | F20: 56 | G20: =+G19+E20-F20 -> 243.6
A21: 42794 | B21: TARJETA | C21: FEBRERO | D21: P. SOCIAL | F21: 2 | G21: =+G20+E21-F21 -> 241.6
A22: 42821 | B22: 12532 | C22: FEBRERO | D22: LUZ | F22: 219.6 | G22: =+G21+E22-F22 -> 22
A23: 42821 | B23: 12532 | C23: FEBRERO | D23: AGUA | F23: 22 | G23: =+G22+E23-F23 -> 2.8421709e-14
A24: 42825 | B24: POR COBRAR | C24: MARZO | D24: LUZ | E24: 211.2 | G24: =+G23+E24-F24 -> 211.2
D25: AGUA | E25: 23.2 | G25: =+G24+E25-F25 -> 234.4
D26: G. ADM | E26: 60 | G26: =+G25+E26-F26 -> 294.4
D27: P. SOCIAL | E27: 2 | G27: =+G26+E27-F27 -> 296.4
A28: 42824 | B28: TARJETA | C28: MARZO | D28: G. ADM | F28: 60 | G28: =+G27+E28-F28 -> 236.4
A29: 42824 | B29: TARJETA | C29: MARZO | D29: P. SOCIAL | F29: 2 | G29: =+G28+E29-F29 -> 234.4
A30: 42851 | B30: 12702 | C30: MARZO | D30: LUZ | F30: 23.2 | G30: =+G29+E30-F30 -> 211.2
A31: 42851 | B31: 12702 | C31: MARZO | D31: AGUA | F31: 211.2 | G31: =+G30+E31-F31 -> 0
A32: 42855 | B32: POR COBRAR | C32: ABRIL | D32: LUZ | E32: 171 | G32: =+G31+E32-F32 -> 171
D33: AGUA | E33: 22.8 | G33: =+G32+E33-F33 -> 193.8
D34: G. ADM | E34: 60 | G34: =+G33+E34-F34 -> 253.8
D35: P. SOCIAL | E35: 2 | G35: =+G34+E35-F35 -> 255.8
A36: 42854 | B36: TARJETA | C36: ABRIL | D36: G. ADM | F36: 60 | G36: =+G35+E36-F36 -> 195.8
A37: 42854 | B37: TARJETA | C37: ABRIL | D37: P. SOCIAL | F37: 2 | G37: =+G36+E37-F37 -> 193.8
A38: 42872 | B38: 12763 | C38: ABRIL | D38: LUZ | F38: 171 | G38: =+G37+E38-F38 -> 22.8
A39: 42872 | B39: 12763 | C39: ABRIL | D39: AGUA | F39: 22.8 | G39: =+G38+E39-F39 -> 0
A40: 42886 | B40: POR COBRAR | C40: MAYO | D40: LUZ | E40: 148.6 | G40: =+G39+E40-F40 -> 148.6
D41: AGUA | E41: 22.3 | G41: =+G40+E41-F41 -> 170.9
D42: G. ADM | E42: 60 | G42: =+G41+E42-F42 -> 230.9
D43: P. SOCIAL | E43: 2 | G43: =+G42+E43-F43 -> 232.9
D44: MULTA | E44: 170 | G44: =+G43+E44-F44 -> 402.9
A45: 42886 | B45: TARJETA | C45: MAYO | D45: G. ADM | F45: 60 | G45: =+G44+E45-F45 -> 342.9
A46: 42886 | B46: TARJETA | C46: MAYO | D46: P. SOCIAL | F46: 2 | G46: =+G45+E46-F46 -> 340.9
A47: 42881 | B47: 12827 | C47: MAYO | D47: MULTA | F47: 170 | G47: =+G46+E47-F47 -> 170.9
A48: 42908 | B48: 13135 | C48: MAYO | D48: LUZ | F48: 148.6 | G48: =+G47+E48-F48 -> 22.3
A49: 42908 | B49: 13135 | C49: MAYO | D49: AGUA | F49: 22.3 | G49: =+G48+E49-F49 -> 0
A50: 42916 | B50: POR COBRAR | C50: JUNIO | D50: LUZ | E50: 145.5 | G50: =+G49+E50-F50 -> 145.5
D51: AGUA | E51: 22.3 | G51: =+G50+E51-F51 -> 167.8
D52: G. ADM | E52: 60 | G52: =+G51+E52-F52 -> 227.8
D53: P. SOCIAL | E53: 2 | G53: =+G52+E53-F53 -> 229.8
A54: 42916 | B54: TARJETA | C54: JUNIO | D54: G. ADM | F54: 60 | G54: =+G53+E54-F54 -> 169.8
A55: 42916 | B55: TARJETA | C55: JUNIO | D55: P. SOCIAL | F55: 2 | G55: =+G54+E55-F55 -> 167.8
A56: 42935 | B56: 13219 | C56: JUNIO | D56: LUZ | F56: 145.5 | G56: =+G55+E56-F56 -> 22.3
A57: 42935 | B57: 13219 | C57: JUNIO | D57: AGUA | F57: 22.3 | G57: =+G56+E57-F57 -> 0
A58: 42947 | B58: POR COBRAR | C58: JULIO | D58: LUZ | E58: 129.5 | G58: =+G57+E58-F58 -> 129.5
D59: AGUA | E59: 22.5 | G59: =+G58+E59-F59 -> 152
D60: G. ADM | E60: 60 | G60: =+G59+E60-F60 -> 212
D61: P. SOCIAL | E61: 2 | G61: =+G60+E61-F61 -> 214
A62: 42945 | B62: TARJETA | C62: JULIO | D62: G. ADM | F62: 60 | G62: =+G61+E62-F62 -> 154
A63: 42945 | B63: TARJETA | C63: JULIO | D63: P. SOCIAL | F63: 2 | G63: =+G62+E63-F63 -> 152
A64: 42971 | B64: 13471 | C64: JULIO | D64: LUZ | F64: 129.5 | G64: =+G63+E64-F64 -> 22.5
A65: 42971 | B65: 13471 | C65: JULIO | D65: AGUA | F65: 22.5 | G65: =+G64+E65-F65 -> 0
A66: 42978 | B66: POR COBRAR | C66: AGOSTO | D66: LUZ | E66: 129.5 | G66: =+G65+E66-F66 -> 129.5
D67: AGUA | E67: 22.5 | G67: =+G66+E67-F67 -> 152
D68: G. ADM | E68: 60 | G68: =+G67+E68-F68 -> 212
D69: P. SOCIAL | E69: 2 | G69: =+G68+E69-F69 -> 214
D70: MULTA | E70: 85 | G70: =+G69+E70-F70 -> 299
A71: 42978 | B71: TARJETA | C71: AGOSTO | D71: G. ADM | F71: 60 | G71: =+G70+E71-F71 -> 239
A72: 42978 | B72: TARJETA | C72: AGOSTO | D72: P. SOCIAL | F72: 2 | G72: =+G71+E72-F72 -> 237
A73: 42997 | B73: 13610 | C73: AGOSTO | D73: LUZ | F73: 129.5 | G73: =+G72+E73-F73 -> 107.5
A74: 42997 | B74: 13610 | C74: AGOSTO | D74: AGUA | F74: 22.5 | G74: =+G73+E74-F74 -> 85
A75: 43067 | B75: EX. POR TRANSF. | C75: AGOSTO | D75: MULTA | F75: 85 | G75: =+G74+E75-F75 -> 0
A76: 43008 | B76: POR COBRAR | C76: SEPTIEMBRE | D76: LUZ | E76: 156.8 | G76: =+G75+E76-F76 -> 156.8
D77: AGUA | E77: 14.7 | G77: =+G76+E77-F77 -> 171.5
D78: G. ADM | E78: 60 | G78: =+G77+E78-F78 -> 231.5
D79: P. SOCIAL | E79: 2 | G79: =+G78+E79-F79 -> 233.5
A80: 43008 | B80: TARJETA | C80: SEPTIEMBRE | D80: G. ADM | F80: 60 | G80: =+G79+E80-F80 -> 173.5
A81: 43008 | B81: TARJETA | C81: SEPTIEMBRE | D81: P. SOCIAL | F81: 2 | G81: =+G80+E81-F81 -> 171.5
A82: 43028 | B82: 13841 | C82: SEPTIEMBRE | D82: LUZ | F82: 156.8 | G82: =+G81+E82-F82 -> 14.7
A83: 43028 | B83: 13841 | C83: SEPTIEMBRE | D83: AGUA | F83: 14.7 | G83: =+G82+E83-F83 -> 0
A84: 43039 | B84: POR COBRAR | C84: OCTUBRE | D84: LUZ | E84: 156.8 | G84: =+G83+E84-F84 -> 156.8
D85: AGUA | E85: 22.3 | G85: =+G84+E85-F85 -> 179.1
D86: G. ADM | E86: 60 | G86: =+G85+E86-F86 -> 239.1
D87: P. SOCIAL | E87: 2 | G87: =+G86+E87-F87 -> 241.1
A88: 43039 | B88: TARJETA | C88: OCTUBRE | D88: G. ADM | F88: 60 | G88: =+G87+E88-F88 -> 181.1
A89: 43039 | B89: TARJETA | C89: OCTUBRE | D89: P. SOCIAL | F89: 2 | G89: =+G88+E89-F89 -> 179.1
A90: 43063 | B90: 14071 | C90: OCTUBRE | D90: LUZ | F90: 156.8 | G90: =+G89+E90-F90 -> 22.3
A91: 43063 | B91: 14071 | C91: OCTUBRE | D91: AGUA | F91: 22.3 | G91: =+G90+E91-F91 -> 0
A92: 43069 | B92: POR COBRAR | C92: NOVIEMBRE | D92: LUZ | E92: 167.4 | G92: =+G91+E92-F92 -> 167.4
D93: AGUA | E93: 22.3 | G93: =+G92+E93-F93 -> 189.7
D94: G. ADM | E94: 60 | G94: =+G93+E94-F94 -> 249.7
D95: P. SOCIAL | E95: 2 | G95: =+G94+E95-F95 -> 251.7
A96: 43069 | B96: TARJETA | C96: NOVIEMBRE | D96: G. ADM | F96: 60 | G96: =+G95+E96-F96 -> 191.7
A97: 43069 | B97: TARJETA | C97: NOVIEMBRE | D97: P. SOCIAL | F97: 2 | G97: =+G96+E97-F97 -> 189.7
A98: 43087 | B98: 14299 | C98: NOVIEMBRE | D98: LUZ | F98: 167.4 | G98: =+G97+E98-F98 -> 22.3
A99: 43087 | B99: 14299 | C99: NOVIEMBRE | D99: AGUA | F99: 22.3 | G99: =+G98+E99-F99 -> 0
A100: 43100 | B100: POR COBRAR | C100: DICIEMBRE | D100: LUZ | E100: 182.1 | G100: =+G99+E100-F100 -> 182.1
D101: AGUA | E101: 22.3 | G101: =+G100+E101-F101 -> 204.4
D102: G. ADM | E102: 60 | G102: =+G101+E102-F102 -> 264.4
...

Sheet MAYHUASCA MARILU
B2: MAYHUASCA BASTIDAS MARILU
A4: FECHA | B4: DOCUMENTO | C4: PERIODO | D4: CONCEPTO | E4: POR COBRAR | F4: PAGADO | G4: SALDO POR COBRAR
A5: 42736 | B5: SALDO AL 2016 | G5: 114
A6: 42400 | B6: 12186 | C6: A CUENTA 2016 | F6: 34 | G6: =+G5+E6-F6 -> 80
A7: 42787 | B7: 12355 | C7: A CUENTA 2016 | F7: 80 | G7: =+G6+E7-F7 -> 0
A8: 42766 | B8: POR COBRAR | C8: ENERO | D8: LUZ | E8: 32.1 | G8: =+G7+E8-F8 -> 32.1
D9: AGUA | E9: 2.8 | G9: =+G8+E9-F9 -> 34.9
D10: G. ADM | E10: 60 | G10: =+G9+E10-F10 -> 94.9
D11: P. SOCIAL | E11: 2 | G11: =+G10+E11-F11 -> 96.9
A12: 42765 | B12: TARJETA | C12: ENERO | D12: G. ADM | F12: 60 | G12: =+G11+E12-F12 -> 36.9
A13: 42765 | B13: TARJETA | C13: ENERO | D13: P. SOCIAL | F13: 2 | G13: =+G12+E13-F13 -> 34.9
A14: 42787 | B14: 12355 | C14: ENERO | D14: LUZ | F14: 32.1 | G14: =+G13+E14-F14 -> 2.8
A15: 42787 | B15: 12355 | C15: ENERO | D15: AGUA | F15: 2.8 | G15: =+G14+E15-F15 -> 4.4408921e-15
A16: 42794 | B16: POR COBRAR | C16: FEBRERO | D16: LUZ | E16: 57.2 | G16: =+G15+E16-F16 -> 57.2
D17: AGUA | E17: 2 | G17: =+G16+E17-F17 -> 59.2
D18: G. ADM | E18: 56 | G18: =+G17+E18-F18 -> 115.2
D19: P. SOCIAL | E19: 2 | G19: =+G18+E19-F19 -> 117.2
A20: 42794 | B20: TARJETA | C20: FEBRERO | D20: G. ADM | F20: 56 | G20: =+G19+E20-F20 -> 61.2
A21: 42794 | B21: TARJETA | C21: FEBRERO | D21: P. SOCIAL | F21: 2 | G21: =+G20+E21-F21 -> 59.2
A22: 42817 | B22: 12450 | C22: FEBRERO | D22: LUZ | F22: 57.2 | G22: =+G21+E22-F22 -> 2
A23: 42817 | B23: 12450 | C23: FEBRERO | D23: AGUA | F23: 2 | G23: =+G22+E23-F23 -> 1.4210855e-14
A24: 42825 | B24: POR COBRAR | C24: MARZO | D24: LUZ | E24: 44 | G24: =+G23+E24-F24 -> 44
D25: AGUA | E25: 2 | G25: =+G24+E25-F25 -> 46
D26: G. ADM | E26: 60 | G26: =+G25+E26-F26 -> 106
D27: P. SOCIAL | E27: 2 | G27: =+G26+E27-F27 -> 108
A28: 42824 | B28: TARJETA | C28: MARZO | D28: G. ADM | F28: 60 | G28: =+G27+E28-F28 -> 48
A29: 42824 | B29: TARJETA | C29: MARZO | D29: P. SOCIAL | F29: 2 | G29: =+G28+E29-F29 -> 46
A30: 42886 | B30: 13016 | C30: MARZO | D30: LUZ | F30: 44 | G30: =+G29+E30-F30 -> 2
A31: 42886 | B31: 13016 | C31: MARZO | D31: AGUA | F31: 2 | G31: =+G30+E31-F31 -> 1.4210855e-14
A32: 42855 | B32: POR COBRAR | C32: ABRIL | D32: LUZ | E32: 45.3 | G32: =+G31+E32-F32 -> 45.3
D33: AGUA | E33: 2 | G33: =+G32+E33-F33 -> 47.3
D34: G. ADM | E34: 60 | G34: =+G33+E34-F34 -> 107.3
D35: P. SOCIAL | E35: 2 | G35: =+G34+E35-F35 -> 109.3
A36: 42855 | B36: TARJETA | C36: ABRIL | D36: G. ADM | F36: 60 | G36: =+G35+E36-F36 -> 49.3
A37: 42855 | B37: TARJETA | C37: ABRIL | D37: P. SOCIAL | F37: 2 | G37: =+G36+E37-F37 -> 47.3
A38: 42886 | B38: 13016 | C38: ABRIL | D38: LUZ | F38: 45.3 | G38: =+G37+E38-F38 -> 2
A39: 42886 | B39: 13016 | C39: ABRIL | D39: AGUA | F39: 2 | G39: =+G38+E39-F39 -> 1.4210855e-14
A40: 42886 | B40: POR COBRAR | C40: MAYO | D40: LUZ | E40: 42.7 | G40: =+G39+E40-F40 -> 42.7
D41: AGUA | E41: 2 | G41: =+G40+E41-F41 -> 44.7
D42: G. ADM | E42: 60 | G42: =+G41+E42-F42 -> 104.7
D43: P. SOCIAL | E43: 2 | G43: =+G42+E43-F43 -> 106.7
A44: 42886 | B44: TARJETA | C44: MARZO | D44: G. ADM | F44: 60 | G44: =+G43+E44-F44 -> 46.7
A45: 42886 | B45: TARJETA | C45: MARZO | D45: P. SOCIAL | F45: 2 | G45: =+G44+E45-F45 -> 44.7
A46: 42956 | B46: 13430 | C46: MAYO | D46: LUZ | F46: 42.7 | G46: =+G45+E46-F46 -> 2
A47: 42956 | B47: 13430 | C47: MAYO | D47: AGUA | F47: 2 | G47: =+G46+E47-F47 -> 1.4210855e-14
A48: 42916 | B48: POR COBRAR | C48: JUNIO | D48: LUZ | E48: 41.6 | G48: =+G47+E48-F48 -> 41.6
D49: AGUA | E49: 2 | G49: =+G48+E49-F49 -> 43.6
D50: G. ADM | E50: 60 | G50: =+G49+E50-F50 -> 103.6
D51: P. SOCIAL | E51: 2 | G51: =+G50+E51-F51 -> 105.6
A52: 42916 | B52: TARJETA | C52: JUNIO | D52: G. ADM | F52: 60 | G52: =+G51+E52-F52 -> 45.6
A53: 42916 | B53: TARJETA | C53: JUNIO | D53: P. SOCIAL | F53: 2 | G53: =+G52+E53-F53 -> 43.6
A54: 42956 | B54: 13430 | C54: JUNIO | D54: LUZ | F54: 41.6 | G54: =+G53+E54-F54 -> 2
A55: 42956 | B55: 13430 | C55: JUNIO | D55: AGUA | F55: 2 | G55: =+G54+E55-F55 -> 2.1316282e-14
A56: 42947 | B56: POR COBRAR | C56: JULIO | D56: LUZ | E56: 38.5 | G56: =+G55+E56-F56 -> 38.5
D57: AGUA | E57: 2 | G57: =+G56+E57-F57 -> 40.5
D58: G. ADM | E58: 60 | G58: =+G57+E58-F58 -> 100.5
D59: P. SOCIAL | E59: 2 | G59: =+G58+E59-F59 -> 102.5
A60: 42945 | B60: TARJETA | C60: JULIO | D60: G. ADM | F60: 60 | G60: =+G59+E60-F60 -> 42.5
A61: 42945 | B61: TARJETA | C61: JULIO | D61: P. SOCIAL | F61: 2 | G61: =+G60+E61-F61 -> 40.5
A62: 42971 | B62: 13475 | C62: JULIO | D62: LUZ | F62: 38.5 | G62: =+G61+E62-F62 -> 2
A63: 42971 | B63: 13475 | C63: JULIO | D63: AGUA | F63: 2 | G63: =+G62+E63-F63 -> 2.8421709e-14
A64: 42978 | B64: POR COBRAR | C64: AGOSTO | D64: LUZ | E64: 38.5 | G64: =+G63+E64-F64 -> 38.5
D65: AGUA | E65: 2 | G65: =+G64+E65-F65 -> 40.5
D66: G. ADM | E66: 60 | G66: =+G65+E66-F66 -> 100.5
D67: P. SOCIAL | E67: 2 | G67: =+G66+E67-F67 -> 102.5
D68: MULTA | E68: 85 | G68: =+G67+E68-F68 -> 187.5
A69: 42978 | B69: TARJETA | C69: AGOSTO | D69: G. ADM | F69: 60 | G69: =+G68+E69-F69 -> 127.5
A70: 42978 | B70: TARJETA | C70: AGOSTO | D70: P. SOCIAL | F70: 2 | G70: =+G69+E70-F70 -> 125.5
A71: 43011 | B71: 13784 | C71: AGOSTO | D71: LUZ | F71: 38.5 | G71: =+G70+E71-F71 -> 87
A72: 43011 | B72: 13784 | C72: AGOSTO | D72: AGUA | F72: 2 | G72: =+G71+E72-F72 -> 85
A73: 43060 | B73: 10210 | C73: AGOSTO | D73: MULTA | F73: 85 | G73: =+G72+E73-F73 -> 0
A74: 43008 | B74: POR COBRAR | C74: SEPTIEMBRE | D74: LUZ | E74: 36.7 | G74: =+G73+E74-F74 -> 36.7
D75: AGUA | E75: 2 | G75: =+G74+E75-F75 -> 38.7
D76: G. ADM | E76: 60 | G76: =+G75+E76-F76 -> 98.7
D77: P. SOCIAL | E77: 2 | G77: =+G76+E77-F77 -> 100.7
A78: 43008 | B78: TARJETA | C78: SEPTIEMBRE | D78: G. ADM | F78: 60 | G78: =+G77+E78-F78 -> 40.7
A79: 43008 | B79: TARJETA | C79: SEPTIEMBRE | D79: P. SOCIAL | F79: 2 | G79: =+G78+E79-F79 -> 38.7
A80: 43049 | B80: 13959 | C80: SEPTIEMBRE | D80: LUZ | F80: 36.7 | G80: =+G79+E80-F80 -> 2
A81: 43049 | B81: 13959 | C81: SEPTIEMBRE | D81: AGUA | F81: 2 | G81: =+G80+E81-F81 -> 0
A82: 43039 | B82: POR COBRAR | C82: OCTUBRE | D82: LUZ | E82: 36.9 | G82: =+G81+E82-F82 -> 36.9
D83: AGUA | E83: 2 | G83: =+G82+E83-F83 -> 38.9
D84: G. ADM | E84: 60 | G84: =+G83+E84-F84 -> 98.9
D85: P. SOCIAL | E85: 2 | G85: =+G84+E85-F85 -> 100.9
A86: 43039 | B86: TARJETA | C86: OCTUBRE | D86: G. ADM | F86: 60 | G86: =+G85+E86-F86 -> 40.9
A87: 43039 | B87: TARJETA | C87: OCTUBRE | D87: P. SOCIAL | F87: 2 | G87: =+G86+E87-F87 -> 38.9
A88: 43060 | B88: 10211 | C88: OCTUBRE | D88: LUZ | F88: 36.9 | G88: =+G87+E88-F88 -> 2
A89: 43060 | B89: 10211 | C89: OCTUBRE | D89: AGUA | F89: 2 | G89: =+G88+E89-F89 -> 7.1054274e-15
A90: 43069 | B90: POR COBRAR | C90: NOVIEMBRE | D90: LUZ | E90: 39 | G90: =+G89+E90-F90 -> 39
D91: AGUA | E91: 2 | G91: =+G90+E91-F91 -> 41
D92: G. ADM | E92: 60 | G92: =+G91+E92-F92 -> 101
D93: P. SOCIAL | E93: 2 | G93: =+G92+E93-F93 -> 103
A94: 43087 | B94: 14277 | C94: NOVIEMBRE | D94: LUZ | F94: 39 | G94: =+G93+E94-F94 -> 64
A95: 43087 | B95: 14277 | C95: NOVIEMBRE | D95: AGUA | F95: 2 | G95: =+G94+E95-F95 -> 62
A96: 43069 | B96: TARJETA | C96: NOVIEMBRE | D96: G. ADM | F96: 60 | G96: =+G95+E96-F96 -> 2
A97: 43069 | B97: TARJETA | C97: NOVIEMBRE | D97: P. SOCIAL | F97: 2 | G97: =+G96+E97-F97 -> 0
A98: 43100 | B98: POR COBRAR | C98: DICIEMBRE | D98: LUZ | E98: 42.5 | G98: =+G97+E98-F98 -> 42.5
D99: AGUA | E99: 2 | G99: =+G98+E99-F99 -> 44.5
D100: G. ADM | E100: 60 | G100: =+G99+E100-F100 -> 104.5
D101: P. SOCIAL | E101: 2 | G101: =+G100+E101-F101 -> 106.5
A102: 43099 | B102: TARJETA | C102: DICIEMBRE | D102: G. ADM | F102: 60 | G102: =+G101+E102-F102 -> 46.5
...

Sheet MAYHUASCA ULISES
B2: MAYHUASCA BASTIDAS ULISES
A4: FECHA | B4: DOCUMENTO | C4: PERIODO | D4: CONCEPTO | E4: POR COBRAR | F4: PAGADO | G4: SALDO POR COBRAR
A5: 42736 | B5: SALDO AL 2016 | G5: 7193.5
A6: 42741 | B6: 12076 | C6: A CUENTA 2016 | F6: 118.5 | G6: =+G5+E6-F6 -> 7075
A7: 42783 | B7: 12984 | C7: A CUENTA 2016 | F7: 125.8 | G7: =+G6+E7-F7 -> 6949.2
A8: 42765 | B8: TARJETA | C8: A CUENTA 2016 | F8: 54 | G8: =+G7+E8-F8 -> 6895.2
A9: 42794 | B9: TARJETA | C9: A CUENTA 2016 | F9: 57 | G9: =+G8+E9-F9 -> 6838.2
A10: 42824 | B10: TARJETA | C10: A CUENTA 2016 | F10: 57 | G10: =+G9+E10-F10 -> 6781.2
A11: 42855 | B11: TARJETA | C11: A CUENTA 2016 | F11: 60 | G11: =+G10+E11-F11 -> 6721.2
A12: 42886 | B12: TARJETA | C12: A CUENTA 2016 | F12: 78 | G12: =+G11+E12-F12 -> 6643.2
A13: 42916 | B13: TARJETA | C13: A CUENTA 2016 | F13: 48 | G13: =+G12+E13-F13 -> 6595.2
A14: 42947 | B14: TARJETA | C14: A CUENTA 2016 | F14: 72 | G14: =+G13+E14-F14 -> 6523.2
A15: 42978 | B15: TARJETA | C15: A CUENTA 2016 | F15: 60 | G15: =+G14+E15-F15 -> 6463.2
A16: 43008 | B16: TARJETA | C16: A CUENTA 2016 | F16: 72 | G16: =+G15+E16-F16 -> 6391.2
A17: 43039 | B17: 13908 | C17: A CUENTA 2016 | F17: 922.1 | G17: =+G16+E17-F17 -> 5469.1
A18: 43039 | B18: TARJETA | C18: A CUENTA 2016 | F18: 18 | G18: =+G17+E18-F18 -> 5451.1
A19: 43131 | B19: 14592 | C19: A CUENTA 2016 | F19: 922.1 | G19: =+G18+E19-F19 -> 4529
A20: 43160 | B20: 14758 | C20: A CUENTA 2016 | F20: 922.1 | G20: =+G19+E20-F20 -> 3606.9
A21: 43190 | B21: 15069 | C21: A CUENTA 2016 | F21: 922.1 | G21: =+G20+E21-F21 -> 2684.8
A22: 43202 | B22: 15098 | C22: A CUENTA 2016 | F22: 922.1 | G22: =+G21+E22-F22 -> 1762.7
A23: 43202 | B23: 15099 | C23: A CUENTA 2016 | F23: 922.1 | G23: =+G22+E23-F23 -> 840.6
A24: 43222 | B24: 15284 | C24: A CUENTA 2016 | F24: 840.6 | G24: =+G23+E24-F24 -> 0
A25: 42766 | B25: POR COBRAR | C25: ENERO | D25: LUZ | E25: 109.2 | G25: =+G24+E25-F25 -> 109.2
D26: AGUA | E26: 22.8 | G26: =+G25+E26-F26 -> 132
D27: G. ADM | E27: 60 | G27: =+G26+E27-F27 -> 192
D28: P. SOCIAL | E28: 2 | G28: =+G27+E28-F28 -> 194
A29: 42761 | B29: TARJETA | C29: ENERO | D29: G. ADM | F29: 36 | G29: =+G28+E29-F29 -> 158
A30: 42796 | B30: 12390 | C30: ENERO | D30: LUZ | F30: 109.2 | G30: =+G29+E30-F30 -> 48.8
A31: 42796 | B31: 12390 | C31: ENERO | D31: AGUA | F31: 22.8 | G31: =+G30+E31-F31 -> 26
A32: 43222 | B32: 15284 | C32: ENERO | D32: G. ADM | F32: 24 | G32: =+G31+E32-F32 -> 2
A33: 43222 | B33: 15284 | C33: ENERO | D33: P. SOCIAL | F33: 2 | G33: =+G32+E33-F33 -> -3.5527137e-15
A34: 42794 | B34: POR COBRAR | C34: FEBRERO | D34: LUZ | E34: 134.6 | G34: =+G33+E34-F34 -> 134.6
D35: AGUA | E35: 16 | G35: =+G34+E35-F35 -> 150.6
D36: G. ADM | E36: 56 | G36: =+G35+E36-F36 -> 206.6
D37: P. SOCIAL | E37: 2 | G37: =+G36+E37-F37 -> 208.6
D38: MULTA | E38: 85 | G38: =+G37+E38-F38 -> 293.6
A39: 42794 | B39: TARJETA | C39: FEBRERO | D39: G. ADM | F39: 38 | G39: =+G38+E39-F39 -> 255.6
A40: 42844 | B40: 12658 | C40: FEBRERO | D40: LUZ | F40: 134.6 | G40: =+G39+E40-F40 -> 121
A41: 42844 | B41: 12658 | C41: FEBRERO | D41: AGUA | F41: 16 | G41: =+G40+E41-F41 -> 105
A42: 43222 | B42: 15284 | C42: FEBRERO | D42: G. ADM | F42: 18 | G42: =+G41+E42-F42 -> 87
A43: 43222 | B43: 15284 | C43: FEBRERO | D43: P. SOCIAL | F43: 2 | G43: =+G42+E43-F43 -> 85
A44: 43448 | B44: 16774 | C44: FEBRERO | D44: MULTA | F44: 85 | G44: =+G43+E44-F44 -> 0
A45: 42825 | B45: POR COBRAR | C45: MARZO | D45: LUZ | E45: 129.2 | G45: =+G44+E45-F45 -> 129.2
D46: AGUA | E46: 16.6 | G46: =+G45+E46-F46 -> 145.8
D47: G. ADM | E47: 60 | G47: =+G46+E47-F47 -> 205.8
D48: P. SOCIAL | E48: 2 | G48: =+G47+E48-F48 -> 207.8
A49: 42824 | B49: TARJETA | C49: MARZO | D49: G. ADM | F49: 38 | G49: =+G48+E49-F49 -> 169.8
A50: 42844 | B50: 12658 | C50: MARZO | D50: LUZ | F50: 129.2 | G50: =+G49+E50-F50 -> 40.6
A51: 42844 | B51: 12658 | C51: MARZO | D51: AGUA | F51: 16.6 | G51: =+G50+E51-F51 -> 24
A52: 43222 | B52: 15284 | C52: MARZO | D52: G. ADM | F52: 22 | G52: =+G51+E52-F52 -> 2
A53: 43222 | B53: 15284 | C53: MARZO | D53: P. SOCIAL | F53: 2 | G53: =+G52+E53-F53 -> -7.1054274e-15
A54: 42855 | B54: POR COBRAR | C54: ABRIL | D54: LUZ | E54: 131.3 | G54: =+G53+E54-F54 -> 131.3
D55: AGUA | E55: 16.3 | G55: =+G54+E55-F55 -> 147.6
D56: G. ADM | E56: 60 | G56: =+G55+E56-F56 -> 207.6
D57: P. SOCIAL | E57: 2 | G57: =+G56+E57-F57 -> 209.6
A58: 42851 | B58: TARJETA | C58: ABRIL | D58: G. ADM | F58: 40 | G58: =+G57+E58-F58 -> 169.6
A59: 42892 | B59: 13066 | C59: ABRIL | D59: LUZ | F59: 131.3 | G59: =+G58+E59-F59 -> 38.3
A60: 42892 | B60: 13066 | C60: ABRIL | D60: AGUA | F60: 16.3 | G60: =+G59+E60-F60 -> 22
A61: 43222 | B61: 15284 | C61: ABRIL | D61: G. ADM | F61: 11.5 | G61: =+G60+E61-F61 -> 10.5
A62: 43448 | B62: 16774 | C62: ABRIL | D62: G. ADM | F62: 8.5 | G62: =+G61+E62-F62 -> 2
A63: 43448 | B63: 16774 | C63: ABRIL | D63: P. SOCIAL | F63: 2 | G63: =+G62+E63-F63 -> 1.0658141e-14
A64: 42886 | B64: POR COBRAR | C64: MAYO | D64: LUZ | E64: 92.2 | G64: =+G63+E64-F64 -> 92.2
D65: AGUA | E65: 16 | G65: =+G64+E65-F65 -> 108.2
D66: G. ADM | E66: 60 | G66: =+G65+E66-F66 -> 168.2
D67: P. SOCIAL | E67: 2 | G67: =+G66+E67-F67 -> 170.2
A68: 42882 | B68: TARJETA | C68: MAYO | D68: G. ADM | F68: 52 | G68: =+G67+E68-F68 -> 118.2
A69: 42916 | B69: 13166 | C69: MAYO | D69: LUZ | F69: 92.2 | G69: =+G68+E69-F69 -> 26
A70: 42916 | B70: 13166 | C70: MAYO | D70: AGUA | F70: 16 | G70: =+G69+E70-F70 -> 10
A71: 43448 | B71: 16774 | C71: MAYO | D71: G. ADM | F71: 8 | G71: =+G70+E71-F71 -> 2
A72: 43448 | B72: 16774 | C72: MAYO | D72: P. SOCIAL | F72: 2 | G72: =+G71+E72-F72 -> 1.4210855e-14
A73: 42916 | B73: POR COBRAR | C73: JUNIO | D73: LUZ | E73: 90.2 | G73: =+G72+E73-F73 -> 90.2
D74: AGUA | E74: 16.2 | G74: =+G73+E74-F74 -> 106.4
D75: G. ADM | E75: 60 | G75: =+G74+E75-F75 -> 166.4
D76: P. SOCIAL | E76: 2 | G76: =+G75+E76-F76 -> 168.4
A77: 42916 | B77: TARJETA | C77: JUNIO | D77: G. ADM | F77: 32 | G77: =+G76+E77-F77 -> 136.4
A78: 42962 | B78: 13437 | C78: JUNIO | D78: LUZ | F78: 90.2 | G78: =+G77+E78-F78 -> 46.2
A79: 42962 | B79: 13437 | C79: JUNIO | D79: AGUA | F79: 16.2 | G79: =+G78+E79-F79 -> 30
A80: 43448 | B80: 16774 | C80: JUNIO | D80: G. ADM | F80: 28 | G80: =+G79+E80-F80 -> 2
A81: 43448 | B81: 16774 | C81: JUNIO | D81: P. SOCIAL | F81: 2 | G81: =+G80+E81-F81 -> 3.1974423e-14
A82: 42947 | B82: POR COBRAR | C82: JULIO | D82: LUZ | E82: 81 | G82: =+G81+E82-F82 -> 81
D83: AGUA | E83: 16 | G83: =+G82+E83-F83 -> 97
D84: G. ADM | E84: 60 | G84: =+G83+E84-F84 -> 157
D85: P. SOCIAL | E85: 2 | G85: =+G84+E85-F85 -> 159
A86: 42944 | B86: TARJETA | C86: JULIO | D86: G. ADM | F86: 48 | G86: =+G85+E86-F86 -> 111
A87: 42971 | B87: 13477 | C87: JULIO | D87: LUZ | F87: 81 | G87: =+G86+E87-F87 -> 30
A88: 42971 | B88: 13477 | C88: JULIO | D88: AGUA | F88: 16 | G88: =+G87+E88-F88 -> 14
A89: 43448 | B89: 16775 | C89: JULIO | D89: G. ADM | F89: 12 | G89: =+G88+E89-F89 -> 2
A90: 43448 | B90: 16775 | C90: JULIO | D90: P. SOCIAL | F90: 2 | G90: =+G89+E90-F90 -> 2.8421709e-14
A91: 42978 | B91: POR COBRAR | C91: AGOSTO | D91: LUZ | E91: 81 | G91: =+G90+E91-F91 -> 81
D92: AGUA | E92: 16 | G92: =+G91+E92-F92 -> 97
D93: G. ADM | E93: 60 | G93: =+G92+E93-F93 -> 157
D94: P. SOCIAL | E94: 2 | G94: =+G93+E94-F94 -> 159
D95: MULTA | E95: 85 | G95: =+G94+E95-F95 -> 244
A96: 42978 | B96: TARJETA | C96: AGOSTO | D96: G. ADM | F96: 40 | G96: =+G95+E96-F96 -> 204
A97: 42999 | B97: 13643 | C97: AGOSTO | D97: LUZ | F97: 81 | G97: =+G96+E97-F97 -> 123
A98: 42999 | B98: 13643 | C98: AGOSTO | D98: AGUA | F98: 16 | G98: =+G97+E98-F98 -> 107
A99: 43448 | B99: 16775 | C99: AGOSTO | D99: G. ADM | F99: 20 | G99: =+G98+E99-F99 -> 87
A100: 43448 | B100: 16775 | C100: AGOSTO | D100: P. SOCIAL | F100: 2 | G100: =+G99+E100-F100 -> 85
A101: 43448 | B101: 16775 | C101: AGOSTO | D101: MULTA | F101: 85 | G101: =+G100+E101-F101 -> 0
A102: 43008 | B102: POR COBRAR | C102: SEPTIEMBRE | D102: LUZ | E102: 119 | G102: =+G101+E102-F102 -> 119
...

Sheet MAYTA VIOLETA
B2: MAYTA COLQUI VIOLETA
A4: FECHA | B4: DOCUMENTO | C4: PERIODO | D4: CONCEPTO | E4: POR COBRAR | F4: PAGADO | G4: SALDO POR COBRAR
A5: 42736 | B5: SALDO AL 2016 | G5: 362
A6: 42784 | B6: 12989 | C6: A CUENTA 2016 | F6: 362 | G6: =+G5+E6-F6 -> 0
A7: 42766 | B7: POR COBRAR | C7: ENERO | D7: LUZ | E7: 65.6 | G7: =+G6+E7-F7 -> 65.6
D8: AGUA | E8: 22.8 | G8: =+G7+E8-F8 -> 88.4
D9: G. ADM | E9: 60 | G9: =+G8+E9-F9 -> 148.4
D10: P. SOCIAL | E10: 2 | G10: =+G9+E10-F10 -> 150.4
A11: 42759 | B11: TARJETA | C11: ENERO | D11: G. ADM | F11: 48 | G11: =+G10+E11-F11 -> 102.4
A12: 42784 | B12: 12989 | C12: ENERO | D12: G. ADM | F12: 12 | G12: =+G11+E12-F12 -> 90.4
A13: 42784 | B13: 12989 | C13: ENERO | D13: P. SOCIAL | F13: 2 | G13: =+G12+E13-F13 -> 88.4
A14: 42784 | B14: 12989 | C14: ENERO | D14: LUZ | F14: 65.6 | G14: =+G13+E14-F14 -> 22.8
A15: 42784 | B15: 12989 | C15: ENERO | D15: AGUA | F15: 22.8 | G15: =+G14+E15-F15 -> 0
A16: 42794 | B16: POR COBRAR | C16: FEBRERO | D16: LUZ | E16: 122.4 | G16: =+G15+E16-F16 -> 122.4
D17: AGUA | E17: 16 | G17: =+G16+E17-F17 -> 138.4
D18: G. ADM | E18: 56 | G18: =+G17+E18-F18 -> 194.4
D19: P. SOCIAL | E19: 2 | G19: =+G18+E19-F19 -> 196.4
A20: 42821 | B20: 12512 | C20: FEBRERO | D20: LUZ | F20: 122.4 | G20: =+G19+E20-F20 -> 74
A21: 42821 | B21: 12512 | C21: FEBRERO | D21: AGUA | F21: 16 | G21: =+G20+E21-F21 -> 58
A22: 42821 | B22: 12512 | C22: FEBRERO | D22: G. ADM | F22: 56 | G22: =+G21+E22-F22 -> 2
A23: 42821 | B23: 12512 | C23: FEBRERO | D23: P. SOCIAL | F23: 2 | G23: =+G22+E23-F23 -> 0
A24: 42825 | B24: POR COBRAR | C24: MARZO | D24: LUZ | E24: 64.2 | G24: =+G23+E24-F24 -> 64.2
D25: AGUA | E25: 16.6 | G25: =+G24+E25-F25 -> 80.8
D26: G. ADM | E26: 60 | G26: =+G25+E26-F26 -> 140.8
D27: P. SOCIAL | E27: 2 | G27: =+G26+E27-F27 -> 142.8
A28: 42891 | B28: 13051 | C28: MARZO | D28: LUZ | F28: 64.2 | G28: =+G27+E28-F28 -> 78.6
A29: 42891 | B29: 13051 | C29: MARZO | D29: AGUA | F29: 16.6 | G29: =+G28+E29-F29 -> 62
A30: 42891 | B30: 13051 | C30: MARZO | D30: P. SOCIAL | F30: 2 | G30: =+G29+E30-F30 -> 60
A31: 42891 | B31: 13051 | C31: MARZO | D31: G. ADM | F31: 60 | G31: =+G30+E31-F31 -> 0
A32: 42855 | B32: POR COBRAR | C32: ABRIL | D32: LUZ | E32: 65.7 | G32: =+G31+E32-F32 -> 65.7
D33: AGUA | E33: 16.3 | G33: =+G32+E33-F33 -> 82
D34: G. ADM | E34: 60 | G34: =+G33+E34-F34 -> 142
D35: P. SOCIAL | E35: 2 | G35: =+G34+E35-F35 -> 144
A36: 42891 | B36: 13051 | C36: ABRIL | D36: LUZ | F36: 65.7 | G36: =+G35+E36-F36 -> 78.3
A37: 42891 | B37: 13051 | C37: ABRIL | D37: AGUA | F37: 16.3 | G37: =+G36+E37-F37 -> 62
A38: 42891 | B38: 13051 | C38: ABRIL | D38: G. ADM | F38: 60 | G38: =+G37+E38-F38 -> 2
A39: 42891 | B39: 13051 | C39: ABRIL | D39: P. SOCIAL | F39: 2 | G39: =+G38+E39-F39 -> 0
A40: 42886 | B40: POR COBRAR | C40: MAYO | D40: LUZ | E40: 49.6 | G40: =+G39+E40-F40 -> 49.6
D41: AGUA | E41: 16 | G41: =+G40+E41-F41 -> 65.6
D42: G. ADM | E42: 60 | G42: =+G41+E42-F42 -> 125.6
D43: P. SOCIAL | E43: 2 | G43: =+G42+E43-F43 -> 127.6
A44: 42949 | B44: 13332 | C44: MAYO | D44: G. ADM | F44: 60 | G44: =+G43+E44-F44 -> 67.6
A45: 42949 | B45: 13332 | C45: MAYO | D45: P. SOCIAL | F45: 2 | G45: =+G44+E45-F45 -> 65.6
A46: 42949 | B46: 13333 | C46: MAYO | D46: LUZ | F46: 49.6 | G46: =+G45+E46-F46 -> 16
A47: 42949 | B47: 13333 | C47: MAYO | D47: AGUA | F47: 2 | G47: =+G46+E47-F47 -> 14
A48: 43063 | B48: 14040 | C48: MAYO | D48: AGUA | F48: 14 | G48: =+G47+E48-F48 -> 0
A49: 42916 | B49: POR COBRAR | C49: JUNIO | D49: LUZ | E49: 48.4 | G49: =+G48+E49-F49 -> 48.4
D50: AGUA | E50: 16 | G50: =+G49+E50-F50 -> 64.4
D51: G. ADM | E51: 60 | G51: =+G50+E51-F51 -> 124.4
D52: P. SOCIAL | E52: 2 | G52: =+G51+E52-F52 -> 126.4
A53: 42949 | B53: 13332 | C53: JUNIO | D53: G. ADM | F53: 60 | G53: =+G52+E53-F53 -> 66.4
A54: 42949 | B54: 13332 | C54: JUNIO | D54: P. SOCIAL | F54: 2 | G54: =+G53+E54-F54 -> 64.4
A55: 42949 | B55: 13333 | C55: JUNIO | D55: LUZ | F55: 48.4 | G55: =+G54+E55-F55 -> 16
A56: 42949 | B56: 13333 | C56: JUNIO | D56: AGUA | F56: 2 | G56: =+G55+E56-F56 -> 14
A57: 43063 | B57: 14040 | C57: JUNIO | D57: AGUA | F57: 14 | G57: =+G56+E57-F57 -> 0
A58: 42947 | B58: POR COBRAR | C58: JULIO | D58: LUZ | E58: 44.5 | G58: =+G57+E58-F58 -> 44.5
D59: AGUA | E59: 16 | G59: =+G58+E59-F59 -> 60.5
D60: G. ADM | E60: 60 | G60: =+G59+E60-F60 -> 120.5
D61: P. SOCIAL | E61: 2 | G61: =+G60+E61-F61 -> 122.5
D62: P. SOCIAL X FALL. | E62: 10 | G62: =+G61+E62-F62 -> 132.5
A63: 42949 | B63: 13332 | C63: JULIO | D63: G. ADM | F63: 60 | G63: =+G62+E63-F63 -> 72.5
A64: 42949 | B64: 13332 | C64: JULIO | D64: P. SOCIAL | F64: 2 | G64: =+G63+E64-F64 -> 70.5
A65: 42949 | B65: 13332 | C65: JULIO | D65: P. SOCIAL X FALL. | F65: 10 | G65: =+G64+E65-F65 -> 60.5
A66: 43000 | B66: 13651 | C66: JULIO | D66: LUZ | F66: 44.5 | G66: =+G65+E66-F66 -> 16
A67: 43000 | B67: 13651 | C67: JULIO | D67: AGUA | F67: 16 | G67: =+G66+E67-F67 -> 0
A68: 42978 | B68: POR COBRAR | C68: AGOSTO | D68: LUZ | E68: 44.5 | G68: =+G67+E68-F68 -> 44.5
D69: AGUA | E69: 16 | G69: =+G68+E69-F69 -> 60.5
D70: G. ADM | E70: 60 | G70: =+G69+E70-F70 -> 120.5
D71: P. SOCIAL | E71: 2 | G71: =+G70+E71-F71 -> 122.5
D72: MULTA | E72: 85 | G72: =+G71+E72-F72 -> 207.5
A73: 43000 | B73: 13651 | C73: AGOSTO | D73: G. ADM | F73: 60 | G73: =+G72+E73-F73 -> 147.5
A74: 43000 | B74: 13651 | C74: AGOSTO | D74: P. SOCIAL | F74: 2 | G74: =+G73+E74-F74 -> 145.5
A75: 43000 | B75: 13651 | C75: AGOSTO | D75: LUZ | F75: 44.5 | G75: =+G74+E75-F75 -> 101
A76: 43000 | B76: 13651 | C76: AGOSTO | D76: AGUA | F76: 16 | G76: =+G75+E76-F76 -> 85
A77: 43063 | B77: 14040 | C77: AGOSTO | D77: MULTA | F77: 85 | G77: =+G76+E77-F77 -> 0
A78: 43008 | B78: POR COBRAR | C78: SEPTIEMBRE | D78: LUZ | E78: 82.2 | G78: =+G77+E78-F78 -> 82.2
D79: AGUA | E79: 16 | G79: =+G78+E79-F79 -> 98.2
D80: G. ADM | E80: 60 | G80: =+G79+E80-F80 -> 158.2
D81: P. SOCIAL | E81: 2 | G81: =+G80+E81-F81 -> 160.2
A82: 43008 | B82: TARJETA | C82: SEPTIEMBRE | D82: G. ADM | F82: 60 | G82: =+G81+E82-F82 -> 100.2
A83: 43008 | B83: TARJETA | C83: SEPTIEMBRE | D83: P. SOCIAL | F83: 2 | G83: =+G82+E83-F83 -> 98.2
A84: 43063 | B84: 14040 | C84: SEPTIEMBRE | D84: LUZ | F84: 82.2 | G84: =+G83+E84-F84 -> 16
A85: 43063 | B85: 14040 | C85: SEPTIEMBRE | D85: AGUA | F85: 16 | G85: =+G84+E85-F85 -> -1.4210855e-14
A86: 43039 | B86: POR COBRAR | C86: OCTUBRE | D86: LUZ | E86: 81.8 | G86: =+G85+E86-F86 -> 81.8
D87: AGUA | E87: 16 | G87: =+G86+E87-F87 -> 97.8
D88: G. ADM | E88: 60 | G88: =+G87+E88-F88 -> 157.8
D89: P. SOCIAL | E89: 2 | G89: =+G88+E89-F89 -> 159.8
A90: 43039 | B90: TARJETA | C90: OCTUBRE | D90: G. ADM | F90: 34 | G90: =+G89+E90-F90 -> 125.8
A91: 43063 | B91: 14040 | C91: OCTUBRE | D91: LUZ | F91: 81.8 | G91: =+G90+E91-F91 -> 44
A92: 43063 | B92: 14040 | C92: OCTUBRE | D92: AGUA | F92: 16 | G92: =+G91+E92-F92 -> 28
A93: 43063 | B93: 14041 | C93: OCTUBRE | D93: P. SOCIAL | F93: 2 | G93: =+G92+E93-F93 -> 26
A94: 43063 | B94: 14041 | C94: OCTUBRE | D94: G. ADM | F94: 26 | G94: =+G93+E94-F94 -> 0
A95: 43069 | B95: POR COBRAR | C95: NOVIEMBRE | D95: LUZ | E95: 61.6 | G95: =+G94+E95-F95 -> 61.6
D96: AGUA | E96: 16 | G96: =+G95+E96-F96 -> 77.6
D97: G. ADM | E97: 60 | G97: =+G96+E97-F97 -> 137.6
D98: P. SOCIAL | E98: 2 | G98: =+G97+E98-F98 -> 139.6
D99: FUMIGACION | E99: 10 | G99: =+G98+E99-F99 -> 149.6
D100: P. S XFALL FLORES EMMA | E100: 10 | G100: =+G99+E100-F100 -> 159.6
A101: 43063 | B101: 14040 | C101: NOVIEMBRE | D101: P. S XFALL FLORES EMMA | F101: 10 | G101: =+G100+E101-F101 -> 149.6
A102: 43091 | B102: 14344 | C102: NOVIEMBRE | D102: LUZ | F102: 61.6 | G102: =+G101+E102-F102 -> 88
...

Sheet MEDINA VICENTA
B2: MEDINA JOTA DE CACERES VICENTA
A4: FECHA | B4: DOCUMENTO | C4: PERIODO | D4: CONCEPTO | E4: POR COBRAR | F4: PAGADO | G4: SALDO POR COBRAR
A5: 42736 | B5: SALDO AL 2016 | G5: 56.4
A6: 42786 | B6: 12270 | C6: A CUENTA 2016 | F6: 56.4 | G6: =+G5+E6-F6 -> 0
A7: 42766 | B7: POR COBRAR | C7: ENERO | D7: LUZ | E7: 92.9 | G7: =+G6+E7-F7 -> 92.9
D8: AGUA | E8: 2.8 | G8: =+G7+E8-F8 -> 95.7
D9: G. ADM | E9: 60 | G9: =+G8+E9-F9 -> 155.7
D10: P. SOCIAL | E10: 2 | G10: =+G9+E10-F10 -> 157.7
A11: 42786 | B11: 12270 | C11: ENERO | D11: LUZ | F11: 92.9 | G11: =+G10+E11-F11 -> 64.8
A12: 42786 | B12: 12270 | C12: ENERO | D12: AGUA | F12: 2.8 | G12: =+G11+E12-F12 -> 62
A13: 42786 | B13: 12270 | C13: ENERO | D13: G. ADM | F13: 60 | G13: =+G12+E13-F13 -> 2
A14: 42786 | B14: 12270 | C14: ENERO | D14: P. SOCIAL | F14: 2 | G14: =+G13+E14-F14 -> -1.4210855e-14
A15: 42794 | B15: POR COBRAR | C15: FEBRERO | D15: LUZ | E15: 94.5 | G15: =+G14+E15-F15 -> 94.5
D16: AGUA | E16: 2 | G16: =+G15+E16-F16 -> 96.5
D17: G. ADM | E17: 56 | G17: =+G16+E17-F17 -> 152.5
D18: P. SOCIAL | E18: 2 | G18: =+G17+E18-F18 -> 154.5
A19: 42822 | B19: 12604 | C19: FEBRERO | D19: LUZ | F19: 94.5 | G19: =+G18+E19-F19 -> 60
A20: 42822 | B20: 12604 | C20: FEBRERO | D20: AGUA | F20: 2 | G20: =+G19+E20-F20 -> 58
A21: 42822 | B21: 12604 | C21: FEBRERO | D21: G. ADM | F21: 56 | G21: =+G20+E21-F21 -> 2
A22: 42822 | B22: 12604 | C22: FEBRERO | D22: P. SOCIAL | F22: 2 | G22: =+G21+E22-F22 -> 0
A23: 42825 | B23: POR COBRAR | C23: MARZO | D23: LUZ | E23: 81.5 | G23: =+G22+E23-F23 -> 81.5
D24: AGUA | E24: 2 | G24: =+G23+E24-F24 -> 83.5
D25: G. ADM | E25: 60 | G25: =+G24+E25-F25 -> 143.5
D26: P. SOCIAL | E26: 2 | G26: =+G25+E26-F26 -> 145.5
A27: 42885 | B27: 12869 | C27: MARZO | D27: LUZ | F27: 81.5 | G27: =+G26+E27-F27 -> 64
A28: 42885 | B28: 12869 | C28: MARZO | D28: AGUA | F28: 2 | G28: =+G27+E28-F28 -> 62
A29: 42885 | B29: 12869 | C29: MARZO | D29: G. ADM | F29: 60 | G29: =+G28+E29-F29 -> 2
A30: 42885 | B30: 12869 | C30: MARZO | D30: P. SOCIAL | F30: 2 | G30: =+G29+E30-F30 -> 0
A31: 42855 | B31: POR COBRAR | C31: ABRIL | D31: LUZ | E31: 84.1 | G31: =+G30+E31-F31 -> 84.1
D32: AGUA | E32: 2 | G32: =+G31+E32-F32 -> 86.1
D33: G. ADM | E33: 60 | G33: =+G32+E33-F33 -> 146.1
D34: P. SOCIAL | E34: 2 | G34: =+G33+E34-F34 -> 148.1
A35: 42885 | B35: 12869 | C35: ABRIL | D35: LUZ | F35: 84.1 | G35: =+G34+E35-F35 -> 64
A36: 42885 | B36: 12869 | C36: ABRIL | D36: AGUA | F36: 2 | G36: =+G35+E36-F36 -> 62
A37: 42885 | B37: 12869 | C37: ABRIL | D37: G. ADM | F37: 60 | G37: =+G36+E37-F37 -> 2
A38: 42885 | B38: 12869 | C38: ABRIL | D38: P. SOCIAL | F38: 2 | G38: =+G37+E38-F38 -> 0
A39: 42886 | B39: POR COBRAR | C39: MAYO | D39: LUZ | E39: 79.5 | G39: =+G38+E39-F39 -> 79.5
D40: AGUA | E40: 2 | G40: =+G39+E40-F40 -> 81.5
D41: G. ADM | E41: 60 | G41: =+G40+E41-F41 -> 141.5
D42: P. SOCIAL | E42: 2 | G42: =+G41+E42-F42 -> 143.5
A43: 42949 | B43: 13369 | C43: MAYO | D43: G. ADM | F43: 60 | G43: =+G42+E43-F43 -> 83.5
A44: 42949 | B44: 13369 | C44: MAYO | D44: P. SOCIAL | F44: 2 | G44: =+G43+E44-F44 -> 81.5
A45: 42949 | B45: 13369 | C45: MAYO | D45: LUZ | F45: 79.5 | G45: =+G44+E45-F45 -> 2
A46: 42949 | B46: 13369 | C46: MAYO | D46: AGUA | F46: 2 | G46: =+G45+E46-F46 -> 0
A47: 42916 | B47: POR COBRAR | C47: JUNIO | D47: LUZ | E47: 77.4 | G47: =+G46+E47-F47 -> 77.4
D48: AGUA | E48: 2 | G48: =+G47+E48-F48 -> 79.4
D49: G. ADM | E49: 60 | G49: =+G48+E49-F49 -> 139.4
D50: P. SOCIAL | E50: 2 | G50: =+G49+E50-F50 -> 141.4
A51: 42949 | B51: 13369 | C51: JUNIO | D51: G. ADM | F51: 60 | G51: =+G50+E51-F51 -> 81.4
A52: 42949 | B52: 13369 | C52: JUNIO | D52: P. SOCIAL | F52: 2 | G52: =+G51+E52-F52 -> 79.4
A53: 42949 | B53: 13369 | C53: JUNIO | D53: LUZ | F53: 77.4 | G53: =+G52+E53-F53 -> 2
A54: 42949 | B54: 13369 | C54: JUNIO | D54: AGUA | F54: 2 | G54: =+G53+E54-F54 -> 0
A55: 42947 | B55: POR COBRAR | C55: JULIO | D55: LUZ | E55: 71.9 | G55: =+G54+E55-F55 -> 71.9
D56: AGUA | E56: 2 | G56: =+G55+E56-F56 -> 73.9
D57: G. ADM | E57: 60 | G57: =+G56+E57-F57 -> 133.9
D58: P. SOCIAL | E58: 2 | G58: =+G57+E58-F58 -> 135.9
A59: 42949 | B59: 13369 | C59: JULIO | D59: G. ADM | F59: 60 | G59: =+G58+E59-F59 -> 75.9
A60: 42949 | B60: 13369 | C60: JULIO | D60: P. SOCIAL | F60: 2 | G60: =+G59+E60-F60 -> 73.9
A61: 42997 | B61: 13616 | C61: JULIO | D61: LUZ | F61: 71.9 | G61: =+G60+E61-F61 -> 2
A62: 42997 | B62: 13616 | C62: JULIO | D62: AGUA | F62: 2 | G62: =+G61+E62-F62 -> 0
A63: 42978 | B63: POR COBRAR | C63: AGOSTO | D63: LUZ | E63: 71.9 | G63: =+G62+E63-F63 -> 71.9
D64: AGUA | E64: 2 | G64: =+G63+E64-F64 -> 73.9
D65: G. ADM | E65: 60 | G65: =+G64+E65-F65 -> 133.9
D66: P. SOCIAL | E66: 2 | G66: =+G65+E66-F66 -> 135.9
D67: MULTA | E67: 85 | G67: =+G66+E67-F67 -> 220.9
A68: 42997 | B68: 13616 | C68: AGOSTO | D68: G. ADM | F68: 60 | G68: =+G67+E68-F68 -> 160.9
A69: 42997 | B69: 13616 | C69: AGOSTO | D69: P. SOCIAL | F69: 2 | G69: =+G68+E69-F69 -> 158.9
A70: 42997 | B70: 13616 | C70: AGOSTO | D70: LUZ | F70: 71.9 | G70: =+G69+E70-F70 -> 87
A71: 42997 | B71: 13616 | C71: AGOSTO | D71: AGUA | F71: 2 | G71: =+G70+E71-F71 -> 85
A72: 43067 | B72: EXONERACION | C72: AGOSTO | D72: MULTA | F72: 85 | G72: =+G71+E72-F72 -> 0
A73: 43008 | B73: POR COBRAR | C73: SEPTIEMBRE | D73: LUZ | E73: 64.8 | G73: =+G72+E73-F73 -> 64.8
D74: AGUA | E74: 2 | G74: =+G73+E74-F74 -> 66.8
D75: G. ADM | E75: 60 | G75: =+G74+E75-F75 -> 126.8
D76: P. SOCIAL | E76: 2 | G76: =+G75+E76-F76 -> 128.8
A77: 43062 | B77: 14024 | C77: SEPTIEMBRE | D77: G. ADM | F77: 60 | G77: =+G76+E77-F77 -> 68.8
A78: 43062 | B78: 14024 | C78: SEPTIEMBRE | D78: P. SOCIAL | F78: 2 | G78: =+G77+E78-F78 -> 66.8
A79: 43062 | B79: 14024 | C79: SEPTIEMBRE | D79: LUZ | F79: 64.8 | G79: =+G78+E79-F79 -> 2
A80: 43062 | B80: 14024 | C80: SEPTIEMBRE | D80: AGUA | F80: 2 | G80: =+G79+E80-F80 -> 1.4210855e-14
A81: 43039 | B81: POR COBRAR | C81: OCTUBRE | D81: LUZ | E81: 64.5 | G81: =+G80+E81-F81 -> 64.5
D82: AGUA | E82: 2 | G82: =+G81+E82-F82 -> 66.5
D83: G. ADM | E83: 60 | G83: =+G82+E83-F83 -> 126.5
D84: P. SOCIAL | E84: 2 | G84: =+G83+E84-F84 -> 128.5
A85: 43062 | B85: 14024 | C85: OCTUBRE | D85: G. ADM | F85: 60 | G85: =+G84+E85-F85 -> 68.5
A86: 43062 | B86: 14024 | C86: OCTUBRE | D86: P. SOCIAL | F86: 2 | G86: =+G85+E86-F86 -> 66.5
A87: 43062 | B87: 14024 | C87: OCTUBRE | D87: LUZ | F87: 64.5 | G87: =+G86+E87-F87 -> 2
A88: 43062 | B88: 14024 | C88: OCTUBRE | D88: AGUA | F88: 2 | G88: =+G87+E88-F88 -> 0
A89: 43069 | B89: POR COBRAR | C89: NOVIEMBRE | D89: LUZ | E89: 68.8 | G89: =+G88+E89-F89 -> 68.8
D90: AGUA | E90: 2 | G90: =+G89+E90-F90 -> 70.8
D91: G. ADM | E91: 60 | G91: =+G90+E91-F91 -> 130.8
D92: P. SOCIAL | E92: 2 | G92: =+G91+E92-F92 -> 132.8
A93: 43108 | B93: 14404 | C93: NOVIEMBRE | D93: LUZ | F93: 68.8 | G93: =+G92+E93-F93 -> 64
A94: 43108 | B94: 14404 | C94: NOVIEMBRE | D94: AGUA | F94: 2 | G94: =+G93+E94-F94 -> 62
A95: 43108 | B95: 14404 | C95: NOVIEMBRE | D95: G. ADM | F95: 60 | G95: =+G94+E95-F95 -> 2
A96: 43108 | B96: 14404 | C96: NOVIEMBRE | D96: P. SOCIAL | F96: 2 | G96: =+G95+E96-F96 -> 1.4210855e-14
A97: 43100 | B97: POR COBRAR | C97: DICIEMBRE | D97: LUZ | E97: 74.8 | G97: =+G96+E97-F97 -> 74.8
D98: AGUA | E98: 2 | G98: =+G97+E98-F98 -> 76.8
D99: G. ADM | E99: 60 | G99: =+G98+E99-F99 -> 136.8
D100: P. SOCIAL | E100: 2 | G100: =+G99+E100-F100 -> 138.8
A101: 43146 | B101: 14633 | C101: DICIEMBRE | D101: LUZ | F101: 74.8 | G101: =+G100+E101-F101 -> 64
A102: 43146 | B102: 14633 | C102: DICIEMBRE | D102: AGUA | F102: 2 | G102: =+G101+E102-F102 -> 62
...

Sheet MEDINA JUAN CARLOS
B2: MEDINA MEDRANO JUAN CARLOS
A4: FECHA | B4: DOCUMENTO | C4: PERIODO | D4: CONCEPTO | E4: POR COBRAR | F4: PAGADO | G4: SALDO POR COBRAR
A5: 42736 | B5: SALDO AL 2016 | G5: 128.6
A6: 42786 | B6: 12246 | C6: A CUENTA 2016 | F6: 16 | G6: =+G5+E6-F6 -> 112.6
A7: 42782 | B7: 12961 | C7: A CUENTA 2016 | F7: 40.6 | G7: =+G6+E7-F7 -> 72
A8: 42844 | B8: 12653 | C8: A CUENTA 2016 | F8: 8 | G8: =+G7+E8-F8 -> 64
A9: 42884 | B9: 12841 | C9: A CUENTA 2016 | F9: 8 | G9: =+G8+E9-F9 -> 56
A10: 42860 | B10: 12727 | C10: A CUENTA 2016 | F10: 8 | G10: =+G9+E10-F10 -> 48
A11: 42933 | B11: 13212 | C11: A CUENTA 2016 | F11: 8 | G11: =+G10+E11-F11 -> 40
A12: 42949 | B12: 13326 | C12: A CUENTA 2016 | F12: 8 | G12: =+G11+E12-F12 -> 32
A13: 42986 | B13: 13556 | C13: A CUENTA 2016 | F13: 8 | G13: =+G12+E13-F13 -> 24
A14: 42999 | B14: 13642 | C14: A CUENTA 2016 | F14: 8 | G14: =+G13+E14-F14 -> 16
A15: 43046 | B15: 13941 | C15: A CUENTA 2016 | F15: 8 | G15: =+G14+E15-F15 -> 8
A16: 43066 | B16: 14112 | C16: CANCELACION 2016 | F16: 8 | G16: =+G15+E16-F16 -> 0
A17: 42766 | B17: POR COBRAR | C17: ENERO | D17: LUZ | E17: 36.9 | G17: =+G16+E17-F17 -> 36.9
D18: AGUA | E18: 2.8 | G18: =+G17+E18-F18 -> 39.7
D19: G. ADM | E19: 60 | G19: =+G18+E19-F19 -> 99.7
D20: P. SOCIAL | E20: 2 | G20: =+G19+E20-F20 -> 101.7
A21: 42765 | B21: TARJETA | C21: ENERO | D21: G. ADM | F21: 60 | G21: =+G20+E21-F21 -> 41.7
A22: 42765 | B22: TARJETA | C22: ENERO | D22: P. SOCIAL | F22: 2 | G22: =+G21+E22-F22 -> 39.7
A23: 42786 | B23: 12246 | C23: ENERO | D23: LUZ | F23: 36.9 | G23: =+G22+E23-F23 -> 2.8
A24: 42786 | B24: 12246 | C24: ENERO | D24: AGUA | F24: 2.8 | G24: =+G23+E24-F24 -> -9.7699626e-15
A25: 42794 | B25: POR COBRAR | C25: FEBRERO | D25: LUZ | E25: 37.3 | G25: =+G24+E25-F25 -> 37.3
D26: AGUA | E26: 2 | G26: =+G25+E26-F26 -> 39.3
D27: G. ADM | E27: 56 | G27: =+G26+E27-F27 -> 95.3
D28: P. SOCIAL | E28: 2 | G28: =+G27+E28-F28 -> 97.3
A29: 42794 | B29: TARJETA | C29: FEBRERO | D29: G. ADM | F29: 56 | G29: =+G28+E29-F29 -> 41.3
A30: 42794 | B30: TARJETA | C30: FEBRERO | D30: P. SOCIAL | F30: 2 | G30: =+G29+E30-F30 -> 39.3
A31: 42844 | B31: 12653 | C31: FEBRERO | D31: LUZ | F31: 37.3 | G31: =+G30+E31-F31 -> 2
A32: 42844 | B32: 12653 | C32: FEBRERO | D32: AGUA | F32: 2 | G32: =+G31+E32-F32 -> -1.4210855e-14
A33: 42825 | B33: POR COBRAR | C33: MARZO | D33: LUZ | E33: 35.4 | G33: =+G32+E33-F33 -> 35.4
D34: AGUA | E34: 2 | G34: =+G33+E34-F34 -> 37.4
D35: G. ADM | E35: 60 | G35: =+G34+E35-F35 -> 97.4
D36: P. SOCIAL | E36: 2 | G36: =+G35+E36-F36 -> 99.4
A37: 42824 | B37: TARJETA | C37: MARZO | D37: G. ADM | F37: 60 | G37: =+G36+E37-F37 -> 39.4
A38: 42824 | B38: TARJETA | C38: MARZO | D38: P. SOCIAL | F38: 2 | G38: =+G37+E38-F38 -> 37.4
A39: 42860 | B39: 12727 | C39: MARZO | D39: LUZ | F39: 35.4 | G39: =+G38+E39-F39 -> 2
A40: 42860 | B40: 12727 | C40: MARZO | D40: AGUA | F40: 2 | G40: =+G39+E40-F40 -> -2.1316282e-14
A41: 42855 | B41: POR COBRAR | C41: ABRIL | D41: LUZ | E41: 36.7 | G41: =+G40+E41-F41 -> 36.7
D42: AGUA | E42: 2 | G42: =+G41+E42-F42 -> 38.7
D43: G. ADM | E43: 60 | G43: =+G42+E43-F43 -> 98.7
D44: P. SOCIAL | E44: 2 | G44: =+G43+E44-F44 -> 100.7
A45: 42855 | B45: TARJETA | C45: ABRIL | D45: G. ADM | F45: 60 | G45: =+G44+E45-F45 -> 40.7
A46: 42855 | B46: TARJETA | C46: ABRIL | D46: P. SOCIAL | F46: 2 | G46: =+G45+E46-F46 -> 38.7
A47: 42884 | B47: 12841 | C47: ABRIL | D47: LUZ | F47: 36.7 | G47: =+G46+E47-F47 -> 2
A48: 42884 | B48: 12841 | C48: ABRIL | D48: AGUA | F48: 2 | G48: =+G47+E48-F48 -> -1.4210855e-14
A49: 42886 | B49: POR COBRAR | C49: MAYO | D49: LUZ | E49: 34.8 | G49: =+G48+E49-F49 -> 34.8
D50: AGUA | E50: 2 | G50: =+G49+E50-F50 -> 36.8
D51: G. ADM | E51: 60 | G51: =+G50+E51-F51 -> 96.8
D52: P. SOCIAL | E52: 2 | G52: =+G51+E52-F52 -> 98.8
A53: 42885 | B53: TARJETA | C53: MAYO | D53: G. ADM | F53: 60 | G53: =+G52+E53-F53 -> 38.8
A54: 42885 | B54: TARJETA | C54: MAYO | D54: P. SOCIAL | F54: 2 | G54: =+G53+E54-F54 -> 36.8
A55: 42933 | B55: 13211 | C55: MAYO | D55: LUZ | F55: 34.8 | G55: =+G54+E55-F55 -> 2
A56: 42933 | B56: 13211 | C56: MAYO | D56: AGUA | F56: 2 | G56: =+G55+E56-F56 -> -1.4210855e-14
A57: 42916 | B57: POR COBRAR | C57: JUNIO | D57: LUZ | E57: 33.9 | G57: =+G56+E57-F57 -> 33.9
D58: AGUA | E58: 2 | G58: =+G57+E58-F58 -> 35.9
D59: G. ADM | E59: 60 | G59: =+G58+E59-F59 -> 95.9
D60: P. SOCIAL | E60: 2 | G60: =+G59+E60-F60 -> 97.9
A61: 42916 | B61: TARJETA | C61: JUNIO | D61: G. ADM | F61: 60 | G61: =+G60+E61-F61 -> 37.9
A62: 42916 | B62: TARJETA | C62: JUNIO | D62: P. SOCIAL | F62: 2 | G62: =+G61+E62-F62 -> 35.9
A63: 42949 | B63: 13326 | C63: JUNIO | D63: LUZ | F63: 33.9 | G63: =+G62+E63-F63 -> 2
A64: 42949 | B64: 13326 | C64: JUNIO | D64: AGUA | F64: 2 | G64: =+G63+E64-F64 -> -2.1316282e-14
A65: 42947 | B65: POR COBRAR | C65: JULIO | D65: LUZ | E65: 31.7 | G65: =+G64+E65-F65 -> 31.7
D66: AGUA | E66: 2 | G66: =+G65+E66-F66 -> 33.7
D67: G. ADM | E67: 60 | G67: =+G66+E67-F67 -> 93.7
D68: P. SOCIAL | E68: 2 | G68: =+G67+E68-F68 -> 95.7
A69: 42947 | B69: TARJETA | C69: JULIO | D69: G. ADM | F69: 60 | G69: =+G68+E69-F69 -> 35.7
A70: 42947 | B70: TARJETA | C70: JULIO | D70: P. SOCIAL | F70: 2 | G70: =+G69+E70-F70 -> 33.7
A71: 42986 | B71: 13556 | C71: JULIO | D71: LUZ | F71: 31.7 | G71: =+G70+E71-F71 -> 2
A72: 42986 | B72: 13556 | C72: JULIO | D72: AGUA | F72: 2 | G72: =+G71+E72-F72 -> -2.4868996e-14
A73: 42978 | B73: POR COBRAR | C73: AGOSTO | D73: LUZ | E73: 31.7 | G73: =+G72+E73-F73 -> 31.7
D74: AGUA | E74: 2 | G74: =+G73+E74-F74 -> 33.7
D75: G. ADM | E75: 60 | G75: =+G74+E75-F75 -> 93.7
D76: P. SOCIAL | E76: 2 | G76: =+G75+E76-F76 -> 95.7
A77: 42978 | B77: TARJETA | C77: AGOSTO | D77: G. ADM | F77: 60 | G77: =+G76+E77-F77 -> 35.7
A78: 42978 | B78: TARJETA | C78: AGOSTO | D78: P. SOCIAL | F78: 2 | G78: =+G77+E78-F78 -> 33.7
A79: 42999 | B79: 13641 | C79: AGOSTO | D79: LUZ | F79: 31.7 | G79: =+G78+E79-F79 -> 2
A80: 42999 | B80: 13641 | C80: AGOSTO | D80: AGUA | F80: 2 | G80: =+G79+E80-F80 -> -2.4868996e-14
A81: 43008 | B81: POR COBRAR | C81: SEPTIEMBRE | D81: LUZ | E81: 38.7 | G81: =+G80+E81-F81 -> 38.7
D82: AGUA | E82: 2 | G82: =+G81+E82-F82 -> 40.7
D83: G. ADM | E83: 60 | G83: =+G82+E83-F83 -> 100.7
D84: P. SOCIAL | E84: 2 | G84: =+G83+E84-F84 -> 102.7
A85: 42823 | D85: MULTA | E85: 85 | G85: =+G84+E85-F85 -> 187.7
A86: 43008 | B86: TARJETA | C86: SEPTIEMBRE | D86: G. ADM | F86: 60 | G86: =+G85+E86-F86 -> 127.7
A87: 43008 | B87: TARJETA | C87: SEPTIEMBRE | D87: P. SOCIAL | F87: 2 | G87: =+G86+E87-F87 -> 125.7
A88: 43046 | B88: 13941 | C88: SEPTIEMBRE | D88: LUZ | F88: 38.7 | G88: =+G87+E88-F88 -> 87
A89: 43046 | B89: 13941 | C89: SEPTIEMBRE | D89: AGUA | F89: 2 | G89: =+G88+E89-F89 -> 85
A90: 43066 | B90: 14112 | C90: 42823 | D90: MULTA | F90: 85 | G90: =+G89+E90-F90 -> 0
A91: 43039 | B91: POR COBRAR | C91: OCTUBRE | D91: LUZ | E91: 38.5 | G91: =+G90+E91-F91 -> 38.5
D92: AGUA | E92: 2 | G92: =+G91+E92-F92 -> 40.5
D93: G. ADM | E93: 60 | G93: =+G92+E93-F93 -> 100.5
D94: P. SOCIAL | E94: 2 | G94: =+G93+E94-F94 -> 102.5
D95: P. S X FALL. FLORES EMMA | E95: 10 | G95: =+G94+E95-F95 -> 112.5
A96: 43039 | B96: TARJETA | C96: OCTUBRE | D96: G. ADM | F96: 60 | G96: =+G95+E96-F96 -> 52.5
A97: 43039 | B97: TARJETA | C97: OCTUBRE | D97: P. SOCIAL | F97: 2 | G97: =+G96+E97-F97 -> 50.5
A98: 43066 | B98: 14112 | C98: OCTUBRE | D98: LUZ | F98: 38.5 | G98: =+G97+E98-F98 -> 12
A99: 43066 | B99: 14112 | C99: OCTUBRE | D99: AGUA | F99: 2 | G99: =+G98+E99-F99 -> 10
A100: 43066 | B100: 14112 | C100: OCTUBRE | D100: P. S X FALL. FLORES EMMA | F100: 10 | G100: =+G99+E100-F100 -> 0
A101: 43069 | B101: POR COBRAR | C101: NOVIEMBRE | D101: LUZ | E101: 41.1 | G101: =+G100+E101-F101 -> 41.1
D102: AGUA | E102: 2 | G102: =+G101+E102-F102 -> 43.1
...

Sheet MELO MARINA 
B2: MELO BACA MARINA
A4: FECHA | B4: DOCUMENTO | C4: PERIODO | D4: CONCEPTO | E4: POR COBRAR | F4: PAGADO | G4: SALDO POR COBRAR
A5: 42736 | B5: SALDO AL 2016 | G5: 1931.4
A6: 42745 | B6: 12099 | C6: A CUENTA 2016 | F6: 368.7 | G6: =+G5+E6-F6 -> 1562.7
A7: 43021 | B7: 13825 | C7: CANCELACION 2016 | F7: 1562.7 | G7: =+G6+E7-F7 -> 0
A8: 42766 | B8: POR COBRAR | C8: ENERO | D8: LUZ | E8: 110.4 | G8: =+G7+E8-F8 -> 110.4
D9: AGUA | E9: 40.1 | G9: =+G8+E9-F9 -> 150.5
D10: G. ADM | E10: 60 | G10: =+G9+E10-F10 -> 210.5
D11: P. SOCIAL | E11: 2 | G11: =+G10+E11-F11 -> 212.5
A12: 42765 | B12: TARJETA | D12: G. ADM | F12: 60 | G12: =+G11+E12-F12 -> 152.5
A13: 42765 | B13: TARJETA | D13: P. SOCIAL | F13: 2 | G13: =+G12+E13-F13 -> 150.5
A14: 42787 | B14: 12325 | C14: ENERO | D14: LUZ | F14: 110.4 | G14: =+G13+E14-F14 -> 40.1
A15: 42787 | B15: 12325 | C15: ENERO | D15: AGUA | F15: 40.1 | G15: =+G14+E15-F15 -> 0
A16: 42794 | B16: POR COBRAR | C16: FEBRERO | D16: LUZ | E16: 127.9 | G16: =+G15+E16-F16 -> 127.9
D17: AGUA | E17: 27 | G17: =+G16+E17-F17 -> 154.9
D18: G. ADM | E18: 56 | G18: =+G17+E18-F18 -> 210.9
D19: P. SOCIAL | E19: 2 | G19: =+G18+E19-F19 -> 212.9
D20: MULTA | E20: 85 | G20: =+G19+E20-F20 -> 297.9
A21: 42794 | B21: TARJETA | D21: G. ADM | F21: 56 | G21: =+G20+E21-F21 -> 241.9
A22: 42794 | B22: TARJETA | D22: P. SOCIAL | F22: 2 | G22: =+G21+E22-F22 -> 239.9
A23: 42818 | B23: 12468 | C23: FEBRERO | D23: LUZ | F23: 127.9 | G23: =+G22+E23-F23 -> 112
A24: 42818 | B24: 12468 | C24: FEBRERO | D24: AGUA | F24: 27 | G24: =+G23+E24-F24 -> 85
A25: 43021 | B25: 13825 | C25: FEBRERO | D25: MULTA | F25: 85 | G25: =+G24+E25-F25 -> 0
A26: 42825 | B26: POR COBRAR | C26: MARZO | D26: LUZ | E26: 122.8 | G26: =+G25+E26-F26 -> 122.8
D27: AGUA | E27: 28.5 | G27: =+G26+E27-F27 -> 151.3
D28: G. ADM | E28: 60 | G28: =+G27+E28-F28 -> 211.3
D29: P. SOCIAL | E29: 2 | G29: =+G28+E29-F29 -> 213.3
A30: 42825 | B30: TARJETA | D30: G. ADM | F30: 60 | G30: =+G29+E30-F30 -> 153.3
A31: 42825 | B31: TARJETA | D31: P. SOCIAL | F31: 2 | G31: =+G30+E31-F31 -> 151.3
A32: 42863 | B32: 12731 | C32: MARZO | D32: LUZ | F32: 122.8 | G32: =+G31+E32-F32 -> 28.5
A33: 42863 | B33: 12731 | C33: MARZO | D33: AGUA | F33: 28.2 | G33: =+G32+E33-F33 -> 0.3
A34: 43021 | B34: 13825 | C34: MARZO | D34: AGUA | F34: 0.3 | G34: =+G33+E34-F34 -> 1.49325e-14
A35: 42855 | B35: POR COBRAR | C35: ABRIL | D35: LUZ | E35: 124.8 | G35: =+G34+E35-F35 -> 124.8
D36: AGUA | E36: 28 | G36: =+G35+E36-F36 -> 152.8
D37: G. ADM | E37: 60 | G37: =+G36+E37-F37 -> 212.8
D38: P. SOCIAL | E38: 2 | G38: =+G37+E38-F38 -> 214.8
A39: 42854 | B39: TARJETA | D39: G. ADM | F39: 60 | G39: =+G38+E39-F39 -> 154.8
A40: 42854 | B40: TARJETA | D40: P. SOCIAL | F40: 2 | G40: =+G39+E40-F40 -> 152.8
A41: 42909 | B41: 13148 | C41: ABRIL | D41: LUZ | F41: 124.8 | G41: =+G40+E41-F41 -> 28
A42: 42909 | B42: 13148 | C42: ABRIL | D42: AGUA | F42: 28 | G42: =+G41+E42-F42 -> 0
A43: 42886 | B43: POR COBRAR | C43: MAYO | D43: LUZ | E43: 116 | G43: =+G42+E43-F43 -> 116
D44: AGUA | E44: 27.4 | G44: =+G43+E44-F44 -> 143.4
D45: G. ADM | E45: 60 | G45: =+G44+E45-F45 -> 203.4
D46: P. SOCIAL | E46: 2 | G46: =+G45+E46-F46 -> 205.4
A47: 42886 | B47: TARJETA | C47: MAYO | D47: G. ADM | F47: 60 | G47: =+G46+E47-F47 -> 145.4
A48: 42886 | B48: TARJETA | C48: MAYO | D48: P. SOCIAL | F48: 2 | G48: =+G47+E48-F48 -> 143.4
A49: 43021 | B49: 13825 | C49: MAYO | D49: LUZ | F49: 116 | G49: =+G48+E49-F49 -> 27.4
A50: 43021 | B50: 13825 | C50: MAYO | D50: AGUA | F50: 27.4 | G50: =+G49+E50-F50 -> 0
A51: 42916 | B51: POR COBRAR | C51: JUNIO | D51: LUZ | E51: 113.5 | G51: =+G50+E51-F51 -> 113.5
D52: AGUA | E52: 27.4 | G52: =+G51+E52-F52 -> 140.9
D53: G. ADM | E53: 60 | G53: =+G52+E53-F53 -> 200.9
D54: P. SOCIAL | E54: 2 | G54: =+G53+E54-F54 -> 202.9
A55: 42916 | B55: TARJETA | C55: JUNIO | D55: G. ADM | F55: 60 | G55: =+G54+E55-F55 -> 142.9
A56: 42916 | B56: TARJETA | C56: JUNIO | D56: P. SOCIAL | F56: 2 | G56: =+G55+E56-F56 -> 140.9
A57: 43021 | B57: 13825 | C57: JUNIO | D57: LUZ | F57: 113.5 | G57: =+G56+E57-F57 -> 27.4
A58: 43021 | B58: 13825 | C58: JUNIO | D58: AGUA | F58: 27.4 | G58: =+G57+E58-F58 -> 0
A59: 42947 | B59: POR COBRAR | C59: JULIO | D59: LUZ | E59: 101.4 | G59: =+G58+E59-F59 -> 101.4
D60: AGUA | E60: 27.5 | G60: =+G59+E60-F60 -> 128.9
D61: G. ADM | E61: 60 | G61: =+G60+E61-F61 -> 188.9
D62: P. SOCIAL | E62: 2 | G62: =+G61+E62-F62 -> 190.9
A63: 42945 | B63: TARJETA | C63: JULIO | D63: G. ADM | F63: 60 | G63: =+G62+E63-F63 -> 130.9
A64: 42945 | B64: TARJETA | C64: JULIO | D64: P. SOCIAL | F64: 2 | G64: =+G63+E64-F64 -> 128.9
A65: 43021 | B65: 13825 | C65: JULIO | D65: LUZ | F65: 101.4 | G65: =+G64+E65-F65 -> 27.5
A66: 43021 | B66: 13825 | C66: JULIO | D66: AGUA | F66: 27.5 | G66: =+G65+E66-F66 -> 0
A67: 42978 | B67: POR COBRAR | C67: AGOSTO | D67: LUZ | E67: 101.4 | G67: =+G66+E67-F67 -> 101.4
D68: AGUA | E68: 27.5 | G68: =+G67+E68-F68 -> 128.9
D69: G. ADM | E69: 60 | G69: =+G68+E69-F69 -> 188.9
D70: P. SOCIAL | E70: 2 | G70: =+G69+E70-F70 -> 190.9
A71: 42978 | B71: TARJETA | C71: AGOSTO | D71: G. ADM | F71: 60 | G71: =+G70+E71-F71 -> 130.9
A72: 42978 | B72: TARJETA | C72: AGOSTO | D72: P. SOCIAL | F72: 2 | G72: =+G71+E72-F72 -> 128.9
A73: 43021 | B73: 13825 | C73: AGOSTO | D73: LUZ | F73: 101.4 | G73: =+G72+E73-F73 -> 27.5
A74: 43021 | B74: 13825 | C74: AGOSTO | D74: AGUA | F74: 27.5 | G74: =+G73+E74-F74 -> 0
A75: 43008 | B75: POR COBRAR | C75: SEPTIEMBRE | D75: LUZ | E75: 108.3 | G75: =+G74+E75-F75 -> 108.3
D76: AGUA | E76: 27.4 | G76: =+G75+E76-F76 -> 135.7
D77: G. ADM | E77: 60 | G77: =+G76+E77-F77 -> 195.7
D78: P. SOCIAL | E78: 2 | G78: =+G77+E78-F78 -> 197.7
A79: 42823 | D79: MULTA | E79: 85 | G79: =+G78+E79-F79 -> 282.7
A80: 43021 | B80: 13825 | C80: MARZO | D80: MULTA | F80: 85 | G80: =+G79+E80-F80 -> 197.7
A81: 43008 | B81: TARJETA | C81: SEPTIEMBRE | D81: G. ADM | F81: 60 | G81: =+G80+E81-F81 -> 137.7
A82: 43008 | B82: TARJETA | C82: SEPTIEMBRE | D82: P. SOCIAL | F82: 2 | G82: =+G81+E82-F82 -> 135.7
A83: 43060 | B83: 14000 | C83: SEPTIEMBRE | D83: LUZ | F83: 108.3 | G83: =+G82+E83-F83 -> 27.4
A84: 43060 | B84: 14000 | C84: SEPTIEMBRE | D84: AGUA | F84: 27.4 | G84: =+G83+E84-F84 -> 0
A85: 43039 | B85: POR COBRAR | C85: OCTUBRE | D85: LUZ | E85: 108.3 | G85: =+G84+E85-F85 -> 108.3
D86: AGUA | E86: 27.4 | G86: =+G85+E86-F86 -> 135.7
D87: G. ADM | E87: 60 | G87: =+G86+E87-F87 -> 195.7
D88: P. SOCIAL | E88: 2 | G88: =+G87+E88-F88 -> 197.7
A89: 43039 | B89: TARJETA | C89: OCTUBRE | D89: G. ADM | F89: 60 | G89: =+G88+E89-F89 -> 137.7
A90: 43039 | B90: TARJETA | C90: OCTUBRE | D90: P. SOCIAL | F90: 2 | G90: =+G89+E90-F90 -> 135.7
A91: 43060 | B91: 14000 | C91: OCTUBRE | D91: LUZ | F91: 108.3 | G91: =+G90+E91-F91 -> 27.4
A92: 43060 | B92: 14000 | C92: OCTUBRE | D92: AGUA | F92: 27.4 | G92: =+G91+E92-F92 -> 0
A93: 43069 | B93: POR COBRAR | C93: NOVIEMBRE | D93: LUZ | E93: 115 | G93: =+G92+E93-F93 -> 115
D94: AGUA | E94: 27.4 | G94: =+G93+E94-F94 -> 142.4
D95: G. ADM | E95: 60 | G95: =+G94+E95-F95 -> 202.4
D96: P. SOCIAL | E96: 2 | G96: =+G95+E96-F96 -> 204.4
A97: 43069 | B97: TARJETA | C97: NOVIEMBRE | D97: G. ADM | F97: 56 | G97: =+G96+E97-F97 -> 148.4
A98: 43180 | B98: 14877 | C98: NOVIEMBRE | D98: LUZ | F98: 115 | G98: =+G97+E98-F98 -> 33.4
A99: 43180 | B99: 14877 | C99: NOVIEMBRE | D99: AGUA | F99: 27.4 | G99: =+G98+E99-F99 -> 6
A100: 43180 | B100: 14877 | C100: NOVIEMBRE | D100: G. ADM | F100: 4 | G100: =+G99+E100-F100 -> 2
A101: 43180 | B101: 14877 | C101: NOVIEMBRE | D101: P. SOCIAL | F101: 2 | G101: =+G100+E101-F101 -> 7.1054274e-15
A102: 43100 | B102: POR COBRAR | C102: DICIEMBRE | D102: LUZ | E102: 125.1 | G102: =+G101+E102-F102 -> 125.1
...

Sheet MESIA GLADYS
B2: MESIA CRUZ GLADYS
A4: FECHA | B4: DOCUMENTO | C4: PERIODO | D4: CONCEPTO | E4: POR COBRAR | F4: PAGADO | G4: SALDO POR COBRAR
A5: 42736 | B5: SALDO AL 2016 | G5: 6205.7
A6: 42388 | B6: 9287 | C6: A CUENTA 2016 | F6: 73.6 | G6: =+G5+E6-F6 -> 6132.1
A7: 42064 | B7: 7368 | C7: A CUENTA 2016 | F7: 7 | G7: =+G6+E7-F7 -> 6125.1
A8: 42780 | B8: 12947 | C8: A CUENTA 2016 | F8: 31.9 | G8: =+G7+E8-F8 -> 6093.2
A9: 42780 | B9: 12949 | C9: A CUENTA 2016 | F9: 80 | G9: =+G8+E9-F9 -> 6013.2
A10: 43033 | B10: 13894 | C10: A CUENTA 2016 | F10: 1860.4 | G10: =+G9+E10-F10 -> 4152.8
A11: 43068 | B11: 14200 | C11: A CUENTA 2016 | F11: 1850.3 | G11: =+G10+E11-F11 -> 2302.5
A12: 43551 | B12: DESCUENO DEL 50% CARTA N° 018 | F12: 1151.2 | G12: =+G11+E12-F12 -> 1151.3
A13: 43552 | B13: 17581 | C13: A CUENTA 2016 | F13: 1151.3 | G13: =+G12+E13-F13 -> 0
A14: 42766 | B14: POR COBRAR | C14: ENERO | D14: LUZ | E14: 28.4 | G14: =+G13+E14-F14 -> 28.4
D15: AGUA | E15: 2.8 | G15: =+G14+E15-F15 -> 31.2
D16: G. ADM | E16: 60 | G16: =+G15+E16-F16 -> 91.2
D17: P. SOCIAL | E17: 2 | G17: =+G16+E17-F17 -> 93.2
A18: 42780 | B18: 12948 | C18: ENERO | D18: G. ADM | F18: 60 | G18: =+G17+E18-F18 -> 33.2
A19: 42780 | B19: 12948 | C19: ENERO | D19: P. SOCIAL | F19: 2 | G19: =+G18+E19-F19 -> 31.2 | I19: MULTAS | J19: 2009 | K19: 220
A20: 42816 | B20: 12438 | C20: ENERO | D20: LUZ | F20: 28.4 | G20: =+G19+E20-F20 -> 2.8 | J20: 2010 | K20: 330
A21: 42816 | B21: 12438 | C21: ENERO | D21: AGUA | F21: 2.8 | G21: =+G20+E21-F21 -> 4.4408921e-15 | J21: 2011 | K21: 315
A22: 42794 | B22: POR COBRAR | C22: FEBRERO | D22: LUZ | E22: 50.6 | G22: =+G21+E22-F22 -> 50.6 | J22: 2012 | K22: 217.5
D23: AGUA | E23: 2 | G23: =+G22+E23-F23 -> 52.6 | J23: 2014 | K23: 450
D24: G. ADM | E24: 56 | G24: =+G23+E24-F24 -> 108.6 | J24: 2015 | K24: 450
D25: P. SOCIAL | E25: 2 | G25: =+G24+E25-F25 -> 110.6 | J25: 2016 | K25: 320
A26: 42780 | B26: 12948 | C26: FEBRERO | D26: G. ADM | F26: 56 | G26: =+G25+E26-F26 -> 54.6
A27: 42780 | B27: 12948 | C27: FEBRERO | D27: P. SOCIAL | F27: 2 | G27: =+G26+E27-F27 -> 52.6 | K27: =SUM(K19:K26) -> 2302.5
A28: 42816 | B28: 12439 | C28: FEBRERO | D28: LUZ | F28: 50.6 | G28: =+G27+E28-F28 -> 2
A29: 42816 | B29: 12439 | C29: FEBRERO | D29: AGUA | F29: 2 | G29: =+G28+E29-F29 -> 7.1054274e-15
A30: 42825 | B30: POR COBRAR | C30: MARZO | D30: LUZ | E30: 28.2 | G30: =+G29+E30-F30 -> 28.2
D31: AGUA | E31: 2 | G31: =+G30+E31-F31 -> 30.2
D32: G. ADM | E32: 60 | G32: =+G31+E32-F32 -> 90.2
D33: P. SOCIAL | E33: 2 | G33: =+G32+E33-F33 -> 92.2
D34: LUZ 10:00 PM | E34: 20 | G34: =+G33+E34-F34 -> 112.2
A35: 42816 | B35: 12440 | C35: MARZO | D35: G. ADM | F35: 60 | G35: =+G34+E35-F35 -> 52.2
A36: 42816 | B36: 12440 | C36: MARZO | D36: P. SOCIAL | F36: 2 | G36: =+G35+E36-F36 -> 50.2
A37: 42873 | B37: 12769 | C37: MARZO | D37: LUZ | F37: 28.2 | G37: =+G36+E37-F37 -> 22
A38: 42873 | B38: 12769 | C38: MARZO | D38: AGUA | F38: 2 | G38: =+G37+E38-F38 -> 20
A39: 43068 | B39: 14201 | C39: MARZO | D39: LUZ 10:00 PM | F39: 20 | G39: =+G38+E39-F39 -> 0
A40: 42855 | B40: POR COBRAR | C40: ABRIL | D40: LUZ | E40: 29.6 | G40: =+G39+E40-F40 -> 29.6
D41: AGUA | E41: 2 | G41: =+G40+E41-F41 -> 31.6
D42: G. ADM | E42: 60 | G42: =+G41+E42-F42 -> 91.6
D43: P. SOCIAL | E43: 2 | G43: =+G42+E43-F43 -> 93.6
A44: 42873 | B44: 12769 | C44: ABRIL | D44: LUZ | F44: 29.6 | G44: =+G43+E44-F44 -> 64
A45: 42873 | B45: 12769 | C45: ABRIL | D45: AGUA | F45: 2 | G45: =+G44+E45-F45 -> 62
A46: 42873 | B46: 12765 | C46: ABRIL | D46: G. ADM | F46: 60 | G46: =+G45+E46-F46 -> 2
A47: 42873 | B47: 12765 | C47: ABRIL | D47: P. SOCIAL | F47: 2 | G47: =+G46+E47-F47 -> -7.1054274e-15
A48: 42886 | B48: POR COBRAR | C48: MAYO | D48: LUZ | E48: 26.9 | G48: =+G47+E48-F48 -> 26.9
D49: AGUA | E49: 2 | G49: =+G48+E49-F49 -> 28.9
D50: G. ADM | E50: 60 | G50: =+G49+E50-F50 -> 88.9
D51: P. SOCIAL | E51: 2 | G51: =+G50+E51-F51 -> 90.9
A52: 42873 | B52: 12765 | C52: MAYO | D52: G. ADM | F52: 60 | G52: =+G51+E52-F52 -> 30.9
A53: 42873 | B53: 12765 | C53: MAYO | D53: P. SOCIAL | F53: 2 | G53: =+G52+E53-F53 -> 28.9
A54: 42949 | B54: 13358 | C54: MAYO | D54: LUZ | F54: 26.9 | G54: =+G53+E54-F54 -> 2
A55: 42949 | B55: 13358 | C55: MAYO | D55: AGUA | F55: 2 | G55: =+G54+E55-F55 -> -7.1054274e-15
A56: 42916 | B56: POR COBRAR | C56: JUNIO | D56: LUZ | E56: 26.1 | G56: =+G55+E56-F56 -> 26.1
D57: AGUA | E57: 2 | G57: =+G56+E57-F57 -> 28.1
D58: G. ADM | E58: 60 | G58: =+G57+E58-F58 -> 88.1
D59: P. SOCIAL | E59: 2 | G59: =+G58+E59-F59 -> 90.1
A60: 42949 | B60: 13359 | C60: JUNIO | D60: G. ADM | F60: 60 | G60: =+G59+E60-F60 -> 30.1
A61: 42949 | B61: 13359 | C61: JUNIO | D61: P. SOCIAL | F61: 2 | G61: =+G60+E61-F61 -> 28.1
A62: 42949 | B62: 13358 | C62: JUNIO | D62: LUZ | F62: 26.1 | G62: =+G61+E62-F62 -> 2
A63: 42949 | B63: 13358 | C63: JUNIO | D63: AGUA | F63: 2 | G63: =+G62+E63-F63 -> -7.1054274e-15
A64: 42947 | B64: POR COBRAR | C64: JULIO | D64: LUZ | E64: 24.9 | G64: =+G63+E64-F64 -> 24.9
D65: AGUA | E65: 2 | G65: =+G64+E65-F65 -> 26.9
D66: G. ADM | E66: 60 | G66: =+G65+E66-F66 -> 86.9
D67: P. SOCIAL | E67: 2 | G67: =+G66+E67-F67 -> 88.9
A68: 42949 | B68: 13359 | C68: JULIO | D68: G. ADM | F68: 60 | G68: =+G67+E68-F68 -> 28.9
A69: 42949 | B69: 13359 | C69: JULIO | D69: P. SOCIAL | F69: 2 | G69: =+G68+E69-F69 -> 26.9
A70: 42996 | B70: 13595 | C70: JULIO | D70: LUZ | F70: 24.9 | G70: =+G69+E70-F70 -> 2
A71: 42996 | B71: 13595 | C71: JULIO | D71: AGUA | F71: 2 | G71: =+G70+E71-F71 -> -7.1054274e-15
A72: 42978 | B72: POR COBRAR | C72: AGOSTO | D72: LUZ | E72: 24.9 | G72: =+G71+E72-F72 -> 24.9
D73: AGUA | E73: 2 | G73: =+G72+E73-F73 -> 26.9
D74: G. ADM | E74: 60 | G74: =+G73+E74-F74 -> 86.9
D75: P. SOCIAL | E75: 2 | G75: =+G74+E75-F75 -> 88.9
A76: 42996 | B76: 13595 | C76: AGOSTO | D76: LUZ | F76: 24.9 | G76: =+G75+E76-F76 -> 64
A77: 42996 | B77: 13595 | C77: AGOSTO | D77: AGUA | F77: 2 | G77: =+G76+E77-F77 -> 62
A78: 42996 | B78: 13596 | C78: AGOSTO | D78: G. ADM | F78: 60 | G78: =+G77+E78-F78 -> 2
A79: 42996 | B79: 13596 | C79: AGOSTO | D79: P. SOCIAL | F79: 2 | G79: =+G78+E79-F79 -> -7.1054274e-15
A80: 43008 | B80: POR COBRAR | C80: SEPTIEMBRE | D80: LUZ | E80: 21.3 | G80: =+G79+E80-F80 -> 21.3
D81: AGUA | E81: 2 | G81: =+G80+E81-F81 -> 23.3
D82: G. ADM | E82: 60 | G82: =+G81+E82-F82 -> 83.3
D83: P. SOCIAL | E83: 2 | G83: =+G82+E83-F83 -> 85.3
A84: 42788 | D84: MULTA | E84: 85 | G84: =+G83+E84-F84 -> 170.3
A85: 42823 | D85: MULTA | E85: 85 | G85: =+G84+E85-F85 -> 255.3
A86: 42951 | D86: MULTA | E86: 85 | G86: =+G85+E86-F86 -> 340.3
A87: 42996 | B87: 13596 | C87: SEPTIEMBRE | D87: G. ADM | F87: 60 | G87: =+G86+E87-F87 -> 280.3
A88: 42996 | B88: 13596 | C88: SEPTIEMBRE | D88: P. SOCIAL | F88: 2 | G88: =+G87+E88-F88 -> 278.3
A89: 43053 | B89: 13974 | C89: SEPTIEMBRE | D89: LUZ | F89: 21.3 | G89: =+G88+E89-F89 -> 257
A90: 43053 | B90: 13974 | C90: SEPTIEMBRE | D90: AGUA | F90: 2 | G90: =+G89+E90-F90 -> 255
A91: 43067 | B91: EXNERACION | C91: 42788 | F91: 85 | G91: =+G90+E91-F91 -> 170
A92: 43067 | B92: EXNERACION | C92: 42823 | F92: 85 | G92: =+G91+E92-F92 -> 85
A93: 43067 | B93: EXNERACION | C93: 42951 | F93: 85 | G93: =+G92+E93-F93 -> 0
A94: 43039 | B94: POR COBRAR | C94: OCTUBRE | D94: LUZ | E94: 21.2 | G94: =+G93+E94-F94 -> 21.2
D95: AGUA | E95: 2 | G95: =+G94+E95-F95 -> 23.2
D96: G. ADM | E96: 60 | G96: =+G95+E96-F96 -> 83.2
D97: P. SOCIAL | E97: 2 | G97: =+G96+E97-F97 -> 85.2
A98: 43053 | B98: 13975 | C98: OCTUBRE | D98: G. ADM | F98: 60 | G98: =+G97+E98-F98 -> 25.2
A99: 43053 | B99: 13975 | C99: OCTUBRE | D99: P. SOCIAL | F99: 2 | G99: =+G98+E99-F99 -> 23.2
A100: 43068 | B100: 14201 | C100: OCTUBRE | D100: LUZ | F100: 21.2 | G100: =+G99+E100-F100 -> 2
A101: 43068 | B101: 14201 | C101: OCTUBRE | D101: AGUA | F101: 2 | G101: =+G100+E101-F101 -> 3.5527137e-15
A102: 43069 | B102: POR COBRAR | C102: NOVIEMBRE | D102: LUZ | E102: 22.6 | G102: =+G101+E102-F102 -> 22.6
...

Sheet NICHO  ESTHEPANY
B2: NICHO LOPEZ ESTHEPANY CARICIA
A4: FECHA | B4: DOCUMENTO | C4: PERIODO | D4: CONCEPTO | E4: POR COBRAR | F4: PAGADO | G4: SALDO POR COBRAR
G5: 0
A6: 45291 | B6: POR COBRAR | C6: DICIEMBRE | D6: LUZ | E6: 228 | G6: =G5+E6-F6 -> 228
D7: AGUA | E7: 59.2 | G7: =G6+E7-F7 -> 287.2
D8: G. ADM | E8: 60 | G8: =G7+E8-F8 -> 347.2
D9: P. SOCIAL | E9: 5 | G9: =G8+E9-F9 -> 352.2
A10: 45348 | B10: RI 28294 | C10: DICIEMBRE | D10: LUZ | F10: 228 | G10: =G9+E10-F10 -> 124.2
A11: 45348 | B11: RI 28294 | C11: DICIEMBRE | D11: AGUA | F11: 59.2 | G11: =G10+E11-F11 -> 65
A12: 45348 | B12: RI 28294 | C12: DICIEMBRE | D12: G. ADM | F12: 60 | G12: =G11+E12-F12 -> 5
A13: 45348 | B13: RI 28294 | C13: DICIEMBRE | D13: P. SOCIAL | F13: 5 | G13: =G12+E13-F13 -> -1.4210855e-14
A14: 45322 | B14: POR COBRAR | C14: ENERO | D14: LUZ | E14: 254.6 | G14: =G13+E14-F14 -> 254.6
D15: AGUA | E15: 70.2 | G15: =G14+E15-F15 -> 324.8
D16: G. ADM | E16: 60 | G16: =G15+E16-F16 -> 384.8
D17: P. SOCIAL | E17: 5 | G17: =G16+E17-F17 -> 389.8
D18: LIMPIEZA DE POZO SEPTICO | E18: 24.2 | G18: =G17+E18-F18 -> 414
A19: 45348 | B19: RI 28294 | C19: ENERO | D19: LUZ | F19: 254.6 | G19: =G18+E19-F19 -> 159.4
A20: 45348 | B20: RI 28294 | C20: ENERO | D20: AGUA | F20: 70.2 | G20: =G19+E20-F20 -> 89.2
A21: 45348 | B21: RI 28294 | C21: ENERO | D21: G. ADM | F21: 60 | G21: =G20+E21-F21 -> 29.2
A22: 45348 | B22: RI 28294 | C22: ENERO | D22: P. SOCIAL | F22: 5 | G22: =G21+E22-F22 -> 24.2
A23: 45358 | B23: RI 28511 | C23: ENERO | D23: LIMPIEZA DE POZO SEPTICO | F23: 24.2 | G23: =G22+E23-F23 -> -5.3290705e-14
A24: 45351 | B24: POR COBRAR | C24: FEBRERO | D24: LUZ | E24: 263.8 | G24: =G23+E24-F24 -> 263.8
D25: AGUA | E25: 59.7 | G25: =G24+E25-F25 -> 323.5
D26: G. ADM | E26: 58 | G26: =G25+E26-F26 -> 381.5
D27: P. SOCIAL | E27: 5 | G27: =G26+E27-F27 -> 386.5
A28: 45358 | B28: RI 28511 | C28: FEBRERO | D28: G. ADM | F28: 58 | G28: =G27+E28-F28 -> 328.5
A29: 45358 | B29: RI 28511 | C29: FEBRERO | D29: P. SOCIAL | F29: 5 | G29: =G28+E29-F29 -> 323.5
A30: 45376 | B30: 28609 | C30: FEBRERO | D30: LUZ | F30: 263.8 | G30: =G29+E30-F30 -> 59.7
A31: 45376 | B31: 28609 | C31: FEBRERO | D31: AGUA | F31: 59.7 | G31: =G30+E31-F31 -> -7.1054274e-14
A32: 45382 | B32: POR COBRAR | C32: MARZO | D32: LUZ | E32: 255.4 | G32: =G31+E32-F32 -> 255.4
D33: AGUA | E33: 41 | G33: =G32+E33-F33 -> 296.4
D34: G. ADM | E34: 60 | G34: =G33+E34-F34 -> 356.4
D35: P. SOCIAL | E35: 5 | G35: =G34+E35-F35 -> 361.4
A36: 45430 | B36: 28883 | C36: MARZO | D36: LUZ | F36: 255.4 | G36: =G35+E36-F36 -> 106
A37: 45430 | B37: 28883 | C37: MARZO | D37: AGUA | F37: 41 | G37: =G36+E37-F37 -> 65
A38: 45430 | B38: 28883 | C38: MARZO | D38: G. ADM | F38: 60 | G38: =G37+E38-F38 -> 5
A39: 45430 | B39: 28883 | C39: MARZO | D39: P. SOCIAL | F39: 5 | G39: =G38+E39-F39 -> -8.5265128e-14
A40: 45412 | B40: POR COBRAR | C40: ABRIL | D40: LUZ | E40: 253.9 | G40: =G39+E40-F40 -> 253.9
D41: AGUA | E41: 44.5 | G41: =G40+E41-F41 -> 298.4
D42: G. ADM | E42: 60 | G42: =G41+E42-F42 -> 358.4
D43: P. SOCIAL | E43: 5 | G43: =G42+E43-F43 -> 363.4
A44: 45461 | B44: 29027 | C44: ABRIL | D44: LUZ | F44: 253.9 | G44: =G43+E44-F44 -> 109.5
A45: 45461 | B45: 29027 | C45: ABRIL | D45: AGUA | F45: 44.5 | G45: =G44+E45-F45 -> 65
A46: 45461 | B46: 29027 | C46: ABRIL | D46: G. ADM | F46: 60 | G46: =G45+E46-F46 -> 5
A47: 45461 | B47: 29027 | C47: ABRIL | D47: P. SOCIAL | F47: 5 | G47: =G46+E47-F47 -> -8.5265128e-14
A48: 45443 | B48: POR COBRAR | C48: MAYO | D48: LUZ | E48: 231 | G48: =G47+E48-F48 -> 231
D49: AGUA | E49: 51.2 | G49: =G48+E49-F49 -> 282.2
D50: G. ADM | E50: 60 | G50: =G49+E50-F50 -> 342.2
D51: P. SOCIAL | E51: 5 | G51: =G50+E51-F51 -> 347.2
A52: 45469 | B52: 29105 | C52: MAYO | D52: LUZ | F52: 231 | G52: =G51+E52-F52 -> 116.2
A53: 45469 | B53: 29105 | C53: MAYO | D53: AGUA | F53: 51.2 | G53: =G52+E53-F53 -> 65
A54: 45469 | B54: 29105 | C54: MAYO | D54: G. ADM | F54: 60 | G54: =G53+E54-F54 -> 5
A55: 45469 | B55: 29105 | C55: MAYO | D55: P. SOCIAL | F55: 5 | G55: =G54+E55-F55 -> -7.1054274e-14
A56: 45473 | B56: POR COBRAR | C56: JUNIO | D56: LUZ | E56: 224.3 | G56: =G55+E56-F56 -> 224.3
D57: AGUA | E57: 52.2 | G57: =G56+E57-F57 -> 276.5
D58: G. ADM | E58: 60 | G58: =G57+E58-F58 -> 336.5
D59: P. SOCIAL | E59: 5 | G59: =G58+E59-F59 -> 341.5
A60: 45516 | B60: 29526 | C60: JUNIO | D60: LUZ | F60: 224.3 | G60: =G59+E60-F60 -> 117.2
A61: 45516 | B61: 29526 | C61: JUNIO | D61: AGUA | F61: 52.2 | G61: =G60+E61-F61 -> 65
A62: 45516 | B62: 29526 | C62: JUNIO | D62: G. ADM | F62: 60 | G62: =G61+E62-F62 -> 5
A63: 45516 | B63: 29526 | C63: JUNIO | D63: P. SOCIAL | F63: 5 | G63: =G62+E63-F63 -> -7.1054274e-14
A64: 45504 | B64: POR COBRAR | C64: JULIO | D64: LUZ | E64: 220.2 | G64: =G63+E64-F64 -> 220.2
D65: AGUA | E65: 66.5 | G65: =G64+E65-F65 -> 286.7
D66: G. ADM | E66: 60 | G66: =G65+E66-F66 -> 346.7
D67: P. SOCIAL | E67: 5 | G67: =G66+E67-F67 -> 351.7
D68: PAGO EXTRAORDINARIO PARA ARBITRIOS MUNICIPALES | E68: 250 | G68: =G67+E68-F68 -> 601.7
A69: 45538 | B69: 29602 | C69: JULIO | D69: LUZ | F69: 220.2 | G69: =G68+E69-F69 -> 381.5
A70: 45538 | B70: 29602 | C70: JULIO | D70: AGUA | F70: 66.5 | G70: =G69+E70-F70 -> 315
A71: 45538 | B71: 29602 | C71: JULIO | D71: G. ADM | F71: 60 | G71: =G70+E71-F71 -> 255
A72: 45538 | B72: 29602 | C72: JULIO | D72: P. SOCIAL | F72: 5 | G72: =G71+E72-F72 -> 250
A73: 45499 | B73: 29439 | C73: JULIO | D73: PAGO EXTRAORDINARIO PARA ARBITRIOS MUNICIPALES | F73: 250 | G73: =G72+E73-F73 -> 0
A74: 45535 | B74: POR COBRAR | C74: AGOSTO | D74: LUZ | E74: 220.9 | G74: =G73+E74-F74 -> 220.9
D75: AGUA | E75: 54.4 | G75: =G74+E75-F75 -> 275.3
D76: G. ADM | E76: 60 | G76: =G75+E76-F76 -> 335.3
D77: P. SOCIAL | E77: 5 | G77: =G76+E77-F77 -> 340.3
A78: 45568 | B78: 29764 | C78: AGOSTO | D78: LUZ | F78: 220.9 | G78: =G77+E78-F78 -> 119.4
A79: 45568 | B79: 29764 | C79: AGOSTO | D79: AGUA | F79: 54.4 | G79: =G78+E79-F79 -> 65
A80: 45568 | B80: 29764 | C80: AGOSTO | D80: G. ADM | F80: 60 | G80: =G79+E80-F80 -> 5
A81: 45568 | B81: 29764 | C81: AGOSTO | D81: P. SOCIAL | F81: 5 | G81: =G80+E81-F81 -> 0
A82: 45565 | B82: POR COBRAR | C82: SETIEMBRE | D82: LUZ | E82: 222.2 | G82: =G81+E82-F82 -> 222.2
D83: AGUA | E83: 57.5 | G83: =G82+E83-F83 -> 279.7
D84: G. ADM | E84: 60 | G84: =G83+E84-F84 -> 339.7
D85: P. SOCIAL | E85: 5 | G85: =G84+E85-F85 -> 344.7
A86: 45596 | B86: 29930 | C86: SETIEMBRE | D86: LUZ | F86: 222.2 | G86: =G85+E86-F86 -> 122.5
A87: 45596 | B87: 29930 | C87: SETIEMBRE | D87: AGUA | F87: 57.5 | G87: =G86+E87-F87 -> 65
A88: 45596 | B88: 29930 | C88: SETIEMBRE | D88: G. ADM | F88: 60 | G88: =G87+E88-F88 -> 5
A89: 45596 | B89: 29930 | C89: SETIEMBRE | D89: P. SOCIAL | F89: 5 | G89: =G88+E89-F89 -> 0
A90: 45596 | B90: POR COBRAR | C90: OCTUBRE | D90: LUZ | E90: 340.3 | G90: =G89+E90-F90 -> 340.3
D91: AGUA | E91: 57.6 | G91: =G90+E91-F91 -> 397.9
D92: G. ADM | E92: 60 | G92: =G91+E92-F92 -> 457.9
D93: P. SOCIAL | E93: 5 | G93: =G92+E93-F93 -> 462.9
A94: 45652 | B94: 30205 | C94: OCTUBRE | D94: LUZ | F94: 340.3 | G94: =G93+E94-F94 -> 122.6
A95: 45652 | B95: 30205 | C95: OCTUBRE | D95: AGUA | F95: 57.6 | G95: =G94+E95-F95 -> 65 | K95: NICHO ESTHEPANY
A96: 45652 | B96: 30205 | C96: OCTUBRE | D96: G. ADM | F96: 60 | G96: =G95+E96-F96 -> 5 | J96: 2024 | K96: DICIEMBRE | L96: LUZ | N96: 380.5
A97: 45652 | B97: 30205 | C97: OCTUBRE | D97: P. SOCIAL | F97: 5 | G97: =G96+E97-F97 -> 2.8421709e-14 | L97: AGUA | N97: 57.3
A98: 45626 | B98: POR COBRAR | C98: NOVIEMBRE | D98: LUZ | E98: 366.8 | G98: =G97+E98-F98 -> 366.8 | L98: G. ADM | N98: 60
D99: AGUA | E99: 68.5 | G99: =G98+E99-F99 -> 435.3 | L99: P. SOCIAL | N99: 5
D100: G. ADM | E100: 60 | G100: =G99+E100-F100 -> 495.3 | J100: 2025 | K100: ENERO | L100: LUZ | M100: 345
D101: P. SOCIAL | E101: 5 | G101: =G100+E101-F101 -> 500.3 | L101: AGUA | M101: 35.6
A102: 45687 | B102: 30398 | C102: NOVIEMBRE | D102: LUZ | F102: 366.8 | G102: =G101+E102-F102 -> 133.5 | L102: G. ADM | M102: 60
...

Sheet ÑAHUI AURELIO
B2: ÑAHUI RUIZ AURELIO
A4: FECHA | B4: DOCUMENTO | C4: PERIODO | D4: CONCEPTO | E4: POR COBRAR | F4: PAGADO | G4: SALDO POR COBRAR
A5: 42736 | B5: SALDO AL 2016 | G5: 247.3
A6: 42751 | B6: 12110 | C6: CANCELACION DEL 2016 | F6: 247.3 | G6: =+G5+E6-F6 -> 0
A7: 42766 | B7: POR COBRAR | C7: ENERO | D7: LUZ | E7: 63.9 | G7: =+G6+E7-F7 -> 63.9
D8: AGUA | E8: 2.8 | G8: =+G7+E8-F8 -> 66.7
D9: G. ADM | E9: 60 | G9: =+G8+E9-F9 -> 126.7
D10: P. SOCIAL | E10: 2 | G10: =+G9+E10-F10 -> 128.7
A11: 42786 | B11: 12310 | C11: ENERO | D11: G. ADM | F11: 60 | G11: =+G10+E11-F11 -> 68.7
A12: 42786 | B12: 12310 | C12: ENERO | D12: P. SOCIAL | F12: 2 | G12: =+G11+E12-F12 -> 66.7
A13: 42786 | B13: 12310 | C13: ENERO | D13: LUZ | F13: 38 | G13: =+G12+E13-F13 -> 28.7
A14: 42787 | B14: 12346 | C14: ENERO | D14: LUZ | F14: 25.9 | G14: =+G13+E14-F14 -> 2.8
A15: 42787 | B15: 12346 | C15: ENERO | D15: AGUA | F15: 2.8 | G15: =+G14+E15-F15 -> -9.7699626e-15
A16: 42794 | B16: POR COBRAR | C16: FEBRERO | D16: LUZ | E16: 61.4 | G16: =+G15+E16-F16 -> 61.4
D17: AGUA | E17: 2 | G17: =+G16+E17-F17 -> 63.4
D18: G. ADM | E18: 56 | G18: =+G17+E18-F18 -> 119.4
D19: P. SOCIAL | E19: 2 | G19: =+G18+E19-F19 -> 121.4
A20: 42821 | B20: 12487 | C20: FEBRERO | D20: LUZ | F20: 61.4 | G20: =+G19+E20-F20 -> 60
A21: 42821 | B21: 12487 | C21: FEBRERO | D21: AGUA | F21: 2 | G21: =+G20+E21-F21 -> 58
A22: 42821 | B22: 12487 | C22: FEBRERO | D22: G. ADM | F22: 56 | G22: =+G21+E22-F22 -> 2
A23: 42821 | B23: 12487 | C23: FEBRERO | D23: P. SOCIAL | F23: 2 | G23: =+G22+E23-F23 -> -7.1054274e-15
A24: 42825 | B24: POR COBRAR | C24: MARZO | D24: LUZ | E24: 58.1 | G24: =+G23+E24-F24 -> 58.1
D25: AGUA | E25: 2 | G25: =+G24+E25-F25 -> 60.1
D26: G. ADM | E26: 60 | G26: =+G25+E26-F26 -> 120.1
D27: P. SOCIAL | E27: 2 | G27: =+G26+E27-F27 -> 122.1
A28: 42847 | B28: 12687 | C28: MARZO | D28: LUZ | F28: 58.1 | G28: =+G27+E28-F28 -> 64
A29: 42847 | B29: 12687 | C29: MARZO | D29: AGUA | F29: 2 | G29: =+G28+E29-F29 -> 62
A30: 42847 | B30: 12687 | C30: MARZO | D30: G. ADM | F30: 60 | G30: =+G29+E30-F30 -> 2
A31: 42847 | B31: 12687 | C31: MARZO | D31: P. SOCIAL | F31: 2 | G31: =+G30+E31-F31 -> -7.1054274e-15
A32: 42855 | B32: POR COBRAR | C32: ABRIL | D32: LUZ | E32: 60.4 | G32: =+G31+E32-F32 -> 60.4
D33: AGUA | E33: 2 | G33: =+G32+E33-F33 -> 62.4
D34: G. ADM | E34: 60 | G34: =+G33+E34-F34 -> 122.4
D35: P. SOCIAL | E35: 2 | G35: =+G34+E35-F35 -> 124.4
A36: 42887 | B36: 13026 | C36: ABRIL | D36: AGUA | F36: 2 | G36: =+G35+E36-F36 -> 122.4
A37: 42887 | B37: 13026 | C37: ABRIL | D37: LUZ | F37: 60.4 | G37: =+G36+E37-F37 -> 62
A38: 42887 | B38: 13026 | C38: ABRIL | D38: P. SOCIAL | F38: 2 | G38: =+G37+E38-F38 -> 60
A39: 42887 | B39: 13026 | C39: ABRIL | D39: G. ADM | F39: 60 | G39: =+G38+E39-F39 -> 0
A40: 42886 | B40: POR COBRAR | C40: MAYO | D40: LUZ | E40: 57.7 | G40: =+G39+E40-F40 -> 57.7
D41: AGUA | E41: 2 | G41: =+G40+E41-F41 -> 59.7
D42: G. ADM | E42: 60 | G42: =+G41+E42-F42 -> 119.7
D43: P. SOCIAL | E43: 2 | G43: =+G42+E43-F43 -> 121.7
A44: 42909 | B44: 13146 | C44: MAYO | D44: AGUA | F44: 2 | G44: =+G43+E44-F44 -> 119.7
A45: 42909 | B45: 13146 | C45: MAYO | D45: LUZ | F45: 57.7 | G45: =+G44+E45-F45 -> 62
A46: 42909 | B46: 13146 | C46: MAYO | D46: G. ADM | F46: 60 | G46: =+G45+E46-F46 -> 2
A47: 42909 | B47: 13146 | C47: MAYO | D47: P. SOCIAL | F47: 2 | G47: =+G46+E47-F47 -> 0
A48: 42916 | B48: POR COBRAR | C48: JUNIO | D48: LUZ | E48: 56.1 | G48: =+G47+E48-F48 -> 56.1
D49: AGUA | E49: 2 | G49: =+G48+E49-F49 -> 58.1
D50: G. ADM | E50: 60 | G50: =+G49+E50-F50 -> 118.1
D51: P. SOCIAL | E51: 2 | G51: =+G50+E51-F51 -> 120.1
A52: 42937 | B52: 13234 | C52: JUNIO | D52: G. ADM | F52: 2 | G52: =+G51+E52-F52 -> 118.1
A53: 42937 | B53: 13234 | C53: JUNIO | D53: P. SOCIAL | F53: 60 | G53: =+G52+E53-F53 -> 58.1
A54: 42937 | B54: 13234 | C54: JUNIO | D54: AGUA | F54: 2 | G54: =+G53+E54-F54 -> 56.1
A55: 42937 | B55: 13234 | C55: JUNIO | D55: LUZ | F55: 56.1 | G55: =+G54+E55-F55 -> 0
A56: 42947 | B56: POR COBRAR | C56: JULIO | D56: LUZ | E56: 53.2 | G56: =+G55+E56-F56 -> 53.2
D57: AGUA | E57: 2 | G57: =+G56+E57-F57 -> 55.2
D58: G. ADM | E58: 60 | G58: =+G57+E58-F58 -> 115.2
D59: P. SOCIAL | E59: 2 | G59: =+G58+E59-F59 -> 117.2
A60: 42949 | B60: 13380 | C60: JULIO | D60: G. ADM | F60: 60 | G60: =+G59+E60-F60 -> 57.2
A61: 42949 | B61: 13380 | C61: JULIO | D61: P. SOCIAL | F61: 2 | G61: =+G60+E61-F61 -> 55.2
A62: 42972 | B62: 13489 | C62: JULIO | D62: LUZ | F62: 53.2 | G62: =+G61+E62-F62 -> 2
A63: 42972 | B63: 13489 | C63: JULIO | D63: AGUA | F63: 2 | G63: =+G62+E63-F63 -> 0
A64: 42978 | B64: POR COBRAR | C64: AGOSTO | D64: LUZ | E64: 53.2 | G64: =+G63+E64-F64 -> 53.2
D65: AGUA | E65: 2 | G65: =+G64+E65-F65 -> 55.2
D66: G. ADM | E66: 60 | G66: =+G65+E66-F66 -> 115.2
D67: P. SOCIAL | E67: 2 | G67: =+G66+E67-F67 -> 117.2
A68: 42991 | B68: 13574 | C68: AGOSTO | D68: G. ADM | F68: 60 | G68: =+G67+E68-F68 -> 57.2
A69: 42991 | B69: 13574 | C69: AGOSTO | D69: P. SOCIAL | F69: 2 | G69: =+G68+E69-F69 -> 55.2
A70: 43000 | B70: 13649 | C70: AGOSTO | D70: LUZ | F70: 53.2 | G70: =+G69+E70-F70 -> 2
A71: 43000 | B71: 13649 | C71: AGOSTO | D71: AGUA | F71: 2 | G71: =+G70+E71-F71 -> 0
A72: 43008 | B72: POR COBRAR | C72: SEPTIEMBRE | D72: LUZ | E72: 38.7 | G72: =+G71+E72-F72 -> 38.7
D73: AGUA | E73: 2 | G73: =+G72+E73-F73 -> 40.7
D74: G. ADM | E74: 60 | G74: =+G73+E74-F74 -> 100.7
D75: P. SOCIAL | E75: 2 | G75: =+G74+E75-F75 -> 102.7
A76: 43034 | B76: 13898 | C76: SEPTIEMBRE | D76: LUZ | F76: 38.7 | G76: =+G75+E76-F76 -> 64
A77: 43034 | B77: 13898 | C77: SEPTIEMBRE | D77: AGUA | F77: 2 | G77: =+G76+E77-F77 -> 62
A78: 43034 | B78: 13899 | C78: SEPTIEMBRE | D78: G. ADM | F78: 60 | G78: =+G77+E78-F78 -> 2
A79: 43034 | B79: 13899 | C79: SEPTIEMBRE | D79: P. SOCIAL | F79: 2 | G79: =+G78+E79-F79 -> 0
A80: 43039 | B80: POR COBRAR | C80: OCTUBRE | D80: LUZ | E80: 38.5 | G80: =+G79+E80-F80 -> 38.5
D81: AGUA | E81: 2 | G81: =+G80+E81-F81 -> 40.5
D82: G. ADM | E82: 60 | G82: =+G81+E82-F82 -> 100.5
D83: P. SOCIAL | E83: 2 | G83: =+G82+E83-F83 -> 102.5
A84: 43049 | B84: 13952 | C84: OCTUBRE | D84: G. ADM | F84: 60 | G84: =+G83+E84-F84 -> 42.5
A85: 43049 | B85: 13952 | C85: OCTUBRE | D85: P. SOCIAL | F85: 2 | G85: =+G84+E85-F85 -> 40.5
A86: 43063 | B86: 14068 | C86: OCTUBRE | D86: LUZ | F86: 38.5 | G86: =+G85+E86-F86 -> 2
A87: 43063 | B87: 14068 | C87: OCTUBRE | D87: AGUA | F87: 2 | G87: =+G86+E87-F87 -> 0
A88: 43069 | B88: POR COBRAR | C88: NOVIEMBRE | D88: LUZ | E88: 41 | G88: =+G87+E88-F88 -> 41
D89: AGUA | E89: 2 | G89: =+G88+E89-F89 -> 43
D90: G. ADM | E90: 60 | G90: =+G89+E90-F90 -> 103
D91: P. SOCIAL | E91: 2 | G91: =+G90+E91-F91 -> 105
A92: 43085 | B92: 14232 | C92: NOVIEMBRE | D92: G. ADM | F92: 60 | G92: =+G91+E92-F92 -> 45
A93: 43085 | B93: 14232 | C93: NOVIEMBRE | D93: P. SOCIAL | F93: 2 | G93: =+G92+E93-F93 -> 43
A94: 43085 | B94: 14232 | C94: NOVIEMBRE | D94: LUZ | F94: 41 | G94: =+G93+E94-F94 -> 2
A95: 43085 | B95: 14232 | C95: NOVIEMBRE | D95: AGUA | F95: 2 | G95: =+G94+E95-F95 -> 0
A96: 43100 | B96: POR COBRAR | C96: DICIEMBRE | D96: LUZ | E96: 44.7 | G96: =+G95+E96-F96 -> 44.7
D97: AGUA | E97: 2 | G97: =+G96+E97-F97 -> 46.7
D98: G. ADM | E98: 60 | G98: =+G97+E98-F98 -> 106.7
D99: P. SOCIAL | E99: 2 | G99: =+G98+E99-F99 -> 108.7
A100: 43117 | B100: 14437 | C100: DICIEMBRE | D100: LUZ | F100: 44.7 | G100: =+G99+E100-F100 -> 64
A101: 43117 | B101: 14437 | C101: DICIEMBRE | D101: AGUA | F101: 2 | G101: =+G100+E101-F101 -> 62
A102: 43153 | B102: 14698 | C102: DICIEMBRE | D102: G. ADM | F102: 60 | G102: =+G101+E102-F102 -> 2
...

Sheet OJEDA EDSON
B3: OJEDA CAMPOS EDSON
A5: FECHA | B5: DOCUMENTO | C5: PERIODO | D5: CONCEPTO | E5: POR COBRAR | F5: PAGADO | G5: SALDO POR COBRAR
A6: 42736 | B6: SALDO AL 2016 | G6: 1092.8
A7: 42887 | E7: 10 | G7: =+G6+E7-F7 -> 1102.8
A8: 43068 | B8: 14204 | C8: A CUENTA 2016 | F8: 262.5 | G8: =+G7+E8-F8 -> 840.3
A9: 43530 | B9: 17296 | C9: A CUENTA 2016 | F9: 500 | G9: =+G8+E9-F9 -> 340.3
A10: 43545 | B10: 17366 | C10: A CUENTA 2016 | F10: 134.6 | G10: =+G9+E10-F10 -> 205.7
A11: 43587 | B11: 17716 | C11: CANCELACION 2016 | F11: 205.7 | G11: =+G10+E11-F11 -> 0
A12: 42766 | B12: POR COBRAR | C12: ENERO | D12: LUZ | E12: 192.1 | G12: =+G11+E12-F12 -> 192.1
D13: AGUA | E13: 21 | G13: =+G12+E13-F13 -> 213.1
D14: G. ADM | E14: 60 | G14: =+G13+E14-F14 -> 273.1
D15: P. SOCIAL | E15: 2 | G15: =+G14+E15-F15 -> 275.1
A16: 42765 | B16: TARJETA | C16: ENERO | D16: LUZ | F16: 192.1 | G16: =+G15+E16-F16 -> 83
A17: 42765 | B17: TARJETA | C17: ENERO | D17: AGUA | F17: 17.9 | G17: =+G16+E17-F17 -> 65.1
A18: 42765 | B18: TARJETA | C18: ENERO | D18: G. ADM | F18: 42 | G18: =+G17+E18-F18 -> 23.1
A19: 42855 | B19: TARJETA | C19: ENERO | D19: AGUA | F19: 0.6 | G19: =+G18+E19-F19 -> 22.5
A20: 42886 | B20: TARJETA | C20: ENERO | D20: AGUA | F20: 2.5 | G20: =+G19+E20-F20 -> 20
A21: 42886 | B21: TARJETA | C21: ENERO | D21: P. SOCIAL | F21: 2 | G21: =+G20+E21-F21 -> 18
A22: 43008 | B22: TARJETA | C22: ENERO | D22: G. ADM | F22: 18 | G22: =+G21+E22-F22 -> 0
A23: 42794 | B23: POR COBRAR | C23: FEBRERO | D23: LUZ | E23: 228.5 | G23: =+G22+E23-F23 -> 228.5
D24: AGUA | E24: 13.5 | G24: =+G23+E24-F24 -> 242
D25: G. ADM | E25: 56 | G25: =+G24+E25-F25 -> 298
D26: P. SOCIAL | E26: 2 | G26: =+G25+E26-F26 -> 300
D27: MULTA | E27: 85 | G27: =+G26+E27-F27 -> 385
A28: 42794 | B28: TARJETA | C28: FEBRERO | D28: LUZ | F28: 228.5 | G28: =+G27+E28-F28 -> 156.5
A29: 42794 | B29: TARJETA | C29: FEBRERO | D29: AGUA | F29: 1.5 | G29: =+G28+E29-F29 -> 155
A30: 42794 | B30: TARJETA | C30: FEBRERO | D30: G. ADM | F30: 46 | G30: =+G29+E30-F30 -> 109
A31: 42886 | B31: TARJETA | C31: FEBRERO | D31: AGUA | F31: 12 | G31: =+G30+E31-F31 -> 97
A32: 42886 | B32: TARJETA | C32: FEBRERO | D32: P. SOCIAL | F32: 2 | G32: =+G31+E32-F32 -> 95
A33: 43008 | B33: TARJETA | C33: FEBRERO | D33: G. ADM | F33: 10 | G33: =+G32+E33-F33 -> 85
A34: 43587 | B34: 17716 | C34: FEBRERO | D34: MULTA | F34: 85 | G34: =+G33+E34-F34 -> 0
A35: 42825 | B35: POR COBRAR | C35: MARZO | D35: LUZ | E35: 219.7 | G35: =+G34+E35-F35 -> 219.7
D36: AGUA | E36: 14 | G36: =+G35+E36-F36 -> 233.7
D37: G. ADM | E37: 60 | G37: =+G36+E37-F37 -> 293.7
D38: P. SOCIAL | E38: 2 | G38: =+G37+E38-F38 -> 295.7
A39: 42824 | B39: TARJETA | C39: MARZO | D39: LUZ | F39: 219.7 | G39: =+G38+E39-F39 -> 76
A40: 42824 | B40: TARJETA | C40: MARZO | D40: AGUA | F40: 10.3 | G40: =+G39+E40-F40 -> 65.7
A41: 42824 | B41: TARJETA | C41: MARZO | D41: G. ADM | F41: 46 | G41: =+G40+E41-F41 -> 19.7
A42: 42855 | B42: TARJETA | C42: MARZO | D42: AGUA | F42: 3.7 | G42: =+G41+E42-F42 -> 16
A43: 42886 | B43: TARJETA | C43: MARZO | D43: P. SOCIAL | F43: 2 | G43: =+G42+E43-F43 -> 14
A44: 43008 | B44: TARJETA | C44: MARZO | D44: G. ADM | F44: 14 | G44: =+G43+E44-F44 -> 0
A45: 42855 | B45: POR COBRAR | C45: ABRIL | D45: LUZ | E45: 222 | G45: =+G44+E45-F45 -> 222
D46: AGUA | E46: 13.7 | G46: =+G45+E46-F46 -> 235.7
D47: G. ADM | E47: 60 | G47: =+G46+E47-F47 -> 295.7
D48: P. SOCIAL | E48: 2 | G48: =+G47+E48-F48 -> 297.7
A49: 42855 | B49: TARJETA | C49: ABRIL | D49: LUZ | F49: 222 | G49: =+G48+E49-F49 -> 75.7
A50: 42855 | B50: TARJETA | C50: ABRIL | D50: AGUA | F50: 13.7 | G50: =+G49+E50-F50 -> 62
A51: 42855 | B51: TARJETA | C51: ABRIL | D51: G. ADM | F51: 48 | G51: =+G50+E51-F51 -> 14
A52: 42947 | B52: TARJETA | C52: ABRIL | D52: P. SOCIAL | F52: 2 | G52: =+G51+E52-F52 -> 12
A53: 43008 | B53: TARJETA | C53: ABRIL | D53: G. ADM | F53: 12 | G53: =+G52+E53-F53 -> -1.4210855e-14
A54: 42886 | B54: POR COBRAR | C54: MAYO | D54: LUZ | E54: 206.1 | G54: =+G53+E54-F54 -> 206.1
D55: AGUA | E55: 13.4 | G55: =+G54+E55-F55 -> 219.5
D56: G. ADM | E56: 60 | G56: =+G55+E56-F56 -> 279.5
D57: P. SOCIAL | E57: 2 | G57: =+G56+E57-F57 -> 281.5
A58: 42886 | B58: TARJETA | C58: MAYO | D58: G. ADM | F58: 48 | G58: =+G57+E58-F58 -> 233.5
A59: 42886 | B59: TARJETA | C59: MAYO | D59: LUZ | F59: 206.1 | G59: =+G58+E59-F59 -> 27.4
A60: 42886 | B60: TARJETA | C60: MAYO | D60: AGUA | F60: 13.4 | G60: =+G59+E60-F60 -> 14
A61: 43008 | B61: TARJETA | C61: MAYO | D61: G. ADM | F61: 1.6 | G61: =+G60+E61-F61 -> 12.4
A62: 43587 | B62: 17716 | C62: FEBRERO | D62: G. ADM | F62: 10.4 | G62: =+G61+E62-F62 -> 2
A63: 43587 | B63: 17716 | C63: FEBRERO | F63: 2 | G63: =+G62+E63-F63 -> 5.3290705e-15
A64: 42916 | B64: POR COBRAR | C64: JUNIO | D64: LUZ | E64: 201.8 | G64: =+G63+E64-F64 -> 201.8
D65: AGUA | E65: 13.4 | G65: =+G64+E65-F65 -> 215.2
D66: G. ADM | E66: 60 | G66: =+G65+E66-F66 -> 275.2
D67: P. SOCIAL | E67: 2 | G67: =+G66+E67-F67 -> 277.2
A68: 42916 | B68: TARJETA | C68: JUNIO | D68: G. ADM | F68: 36 | G68: =+G67+E68-F68 -> 241.2
A69: 42916 | B69: TARJETA | C69: JUNIO | D69: LUZ | F69: 180 | G69: =+G68+E69-F69 -> 61.2
A70: 42947 | B70: TARJETA | C70: JUNIO | D70: LUZ | F70: 21.8 | G70: =+G69+E70-F70 -> 39.4
A71: 42947 | B71: TARJETA | C71: JUNIO | D71: AGUA | F71: 13.4 | G71: =+G70+E71-F71 -> 26
A72: 43587 | B72: 17716 | C72: JUNIO | D72: G. ADM | F72: 24 | G72: =+G71+E72-F72 -> 2
A73: 43587 | B73: 17716 | C73: JUNIO | D73: P. SOCIAL | F73: 2 | G73: =+G72+E73-F73 -> 4.9737992e-14
A74: 42947 | B74: POR COBRAR | C74: JULIO | D74: LUZ | E74: 178.8 | G74: =+G73+E74-F74 -> 178.8
D75: AGUA | E75: 13.5 | G75: =+G74+E75-F75 -> 192.3
D76: G. ADM | E76: 60 | G76: =+G75+E76-F76 -> 252.3
D77: P. SOCIAL | E77: 2 | G77: =+G76+E77-F77 -> 254.3
A78: 42945 | B78: TARJETA | C78: JULIO | D78: G. ADM | F78: 46 | G78: =+G77+E78-F78 -> 208.3
A79: 42947 | B79: TARJETA | C79: JULIO | D79: LUZ | F79: 178.8 | G79: =+G78+E79-F79 -> 29.5
A80: 42947 | B80: TARJETA | C80: JULIO | D80: AGUA | F80: 13.5 | G80: =+G79+E80-F80 -> 16
A81: 43587 | B81: 17716 | C81: FEBRERO | D81: G. ADM | F81: 14 | G81: =+G80+E81-F81 -> 2
A82: 43587 | B82: 17716 | C82: FEBRERO | D82: P. SOCIAL | F82: 2 | G82: =+G81+E82-F82 -> 5.6843419e-14
A83: 42978 | B83: POR COBRAR | C83: AGOSTO | D83: LUZ | E83: 178.8 | G83: =+G82+E83-F83 -> 178.8
D84: AGUA | E84: 13.5 | G84: =+G83+E84-F84 -> 192.3
D85: G. ADM | E85: 60 | G85: =+G84+E85-F85 -> 252.3
D86: P. SOCIAL | E86: 2 | G86: =+G85+E86-F86 -> 254.3
D87: MULTA | E87: 85 | G87: =+G86+E87-F87 -> 339.3
A88: 42978 | B88: TARJETA | C88: AGOSTO | D88: G. ADM | F88: 36 | G88: =+G87+E88-F88 -> 303.3
A89: 42978 | B89: TARJETA | C89: AGOSTO | D89: LUZ | F89: 178.8 | G89: =+G88+E89-F89 -> 124.5
A90: 42978 | B90: TARJETA | C90: AGOSTO | D90: AGUA | F90: 1.7 | G90: =+G89+E90-F90 -> 122.8
A91: 43008 | B91: TARJETA | C91: AGOSTO | D91: AGUA | F91: 11.8 | G91: =+G90+E91-F91 -> 111
A92: 43587 | B92: 17716 | C92: AGOSTO | D92: MULTA | F92: 85 | G92: =+G91+E92-F92 -> 26
A93: 43587 | B93: 17716 | C93: AGOSTO | D93: G. ADM | F93: 24 | G93: =+G92+E93-F93 -> 2
A94: 43587 | B94: 17716 | C94: AGOSTO | D94: P. SOCIAL | F94: 2 | G94: =+G93+E94-F94 -> 5.6843419e-14
A95: 43008 | B95: POR COBRAR | C95: SEPTIEMBRE | D95: LUZ | E95: 169.2 | G95: =+G94+E95-F95 -> 169.2
D96: AGUA | E96: 13.4 | G96: =+G95+E96-F96 -> 182.6
D97: G. ADM | E97: 60 | G97: =+G96+E97-F97 -> 242.6
D98: P. SOCIAL | E98: 2 | G98: =+G97+E98-F98 -> 244.6
A99: 42823 | D99: MULTA | E99: 85 | G99: =+G98+E99-F99 -> 329.6
A100: 43008 | B100: TARJETA | C100: SEPTIEMBRE | D100: G. ADM | F100: 50 | G100: =+G99+E100-F100 -> 279.6
A101: 43008 | B101: TARJETA | C101: SEPTIEMBRE | D101: LUZ | F101: 169.2 | G101: =+G100+E101-F101 -> 110.4
A102: 43008 | B102: TARJETA | C102: SEPTIEMBRE | D102: AGUA | F102: 13.4 | G102: =+G101+E102-F102 -> 97
A103: 43587 | B103: 17716 | C103: SEPTIEMBRE | D103: MULTA | F103: 43.9 | G103: =+G102+E103-F103 -> 53.1
...

Sheet OQUENDO MELESIA
B2: OQUENDO ARISACA MELESIA ROSARIO
A4: FECHA | B4: DOCUMENTO | C4: PERIODO | D4: CONCEPTO | E4: POR COBRAR | F4: PAGADO | G4: SALDO POR COBRAR
A5: 42736 | B5: SALDO AL 2016 | G5: 104.9
A6: 42773 | B6: 12967 | C6: A CUENTA 2016 | F6: 104.9 | G6: =+G5+E6-F6 -> 0
A7: 42766 | B7: POR COBRAR | C7: ENERO | D7: LUZ | E7: 35 | G7: =+G6+E7-F7 -> 35
D8: AGUA | E8: 2.8 | G8: =+G7+E8-F8 -> 37.8
D9: G. ADM | E9: 60 | G9: =+G8+E9-F9 -> 97.8
D10: P. SOCIAL | E10: 2 | G10: =+G9+E10-F10 -> 99.8
A11: 42766 | B11: TARJETA | C11: ENERO | D11: G. ADM | F11: 60 | G11: =+G10+E11-F11 -> 39.8
A12: 42766 | B12: TARJETA | C12: ENERO | D12: P. SOCIAL | F12: 2 | G12: =+G11+E12-F12 -> 37.8
A13: 42786 | B13: 12227 | C13: ENERO | D13: LUZ | F13: 35 | G13: =+G12+E13-F13 -> 2.8
A14: 42786 | B14: 12227 | C14: ENERO | D14: AGUA | F14: 2.8 | G14: =+G13+E14-F14 -> 0
A15: 42794 | B15: POR COBRAR | C15: FEBRERO | D15: LUZ | E15: 13 | G15: =+G14+E15-F15 -> 13
D16: AGUA | E16: 2 | G16: =+G15+E16-F16 -> 15
D17: G. ADM | E17: 56 | G17: =+G16+E17-F17 -> 71
D18: P. SOCIAL | E18: 2 | G18: =+G17+E18-F18 -> 73
A19: 42780 | B19: TARJETA | C19: FEBRERO | D19: G. ADM | F19: 20 | G19: =+G18+E19-F19 -> 53
A20: 42822 | B20: 12576 | C20: FEBRERO | D20: LUZ | F20: 13 | G20: =+G19+E20-F20 -> 40
A21: 42822 | B21: 12576 | C21: FEBRERO | D21: AGUA | F21: 2 | G21: =+G20+E21-F21 -> 38
A22: 42822 | B22: 12576 | C22: FEBRERO | D22: G. ADM | F22: 36 | G22: =+G21+E22-F22 -> 2
A23: 42822 | B23: 12576 | C23: FEBRERO | D23: P. SOCIAL | F23: 2 | G23: =+G22+E23-F23 -> 0
A24: 42825 | B24: POR COBRAR | C24: MARZO | D24: LUZ | E24: 29 | G24: =+G23+E24-F24 -> 29
D25: AGUA | E25: 2 | G25: =+G24+E25-F25 -> 31
D26: G. ADM | E26: 60 | G26: =+G25+E26-F26 -> 91
D27: P. SOCIAL | E27: 2 | G27: =+G26+E27-F27 -> 93
A28: 42823 | B28: TARJETA | C28: MARZO | D28: G. ADM | F28: 63 | G28: =+G27+E28-F28 -> 30
A29: 42823 | B29: TARJETA | C29: MARZO | D29: P. SOCIAL | F29: 2 | G29: =+G28+E29-F29 -> 28
A30: 42885 | B30: 12875 | C30: MARZO | D30: LUZ | F30: 26 | G30: =+G29+E30-F30 -> 2
A31: 42885 | B31: 12875 | C31: MARZO | D31: AGUA | F31: 2 | G31: =+G30+E31-F31 -> 0
A32: 42855 | B32: POR COBRAR | C32: ABRIL | D32: LUZ | E32: 30.2 | G32: =+G31+E32-F32 -> 30.2
D33: AGUA | E33: 2 | G33: =+G32+E33-F33 -> 32.2
D34: G. ADM | E34: 60 | G34: =+G33+E34-F34 -> 92.2
D35: P. SOCIAL | E35: 2 | G35: =+G34+E35-F35 -> 94.2
D36: CAMBIO DE GIRO | E36: 300 | G36: =+G35+E36-F36 -> 394.2
A37: 42855 | B37: TARJETA | C37: ABRIL | D37: G. ADM | F37: 60 | G37: =+G36+E37-F37 -> 334.2
A38: 42828 | B38: TARJETA | C38: ABRIL | D38: P. SOCIAL | F38: 2 | G38: =+G37+E38-F38 -> 332.2
A39: 42885 | B39: 12875 | C39: ABRIL | D39: LUZ | F39: 30.2 | G39: =+G38+E39-F39 -> 302
A40: 42885 | B40: 12875 | C40: ABRIL | D40: AGUA | F40: 2 | G40: =+G39+E40-F40 -> 300
A41: 42830 | B41: 12631 | C41: ABRIL | D41: CAMBIO DE GIRO | F41: 300 | G41: =+G40+E41-F41 -> 0
A42: 42886 | B42: POR COBRAR | C42: MAYO | D42: LUZ | E42: 28.8 | G42: =+G41+E42-F42 -> 28.8
D43: AGUA | E43: 2 | G43: =+G42+E43-F43 -> 30.8
D44: G. ADM | E44: 60 | G44: =+G43+E44-F44 -> 90.8
D45: P. SOCIAL | E45: 2 | G45: =+G44+E45-F45 -> 92.8
A46: 42885 | B46: TARJETA | C46: MAYO | D46: G. ADM | F46: 60 | G46: =+G45+E46-F46 -> 32.8
A47: 42885 | B47: TARJETA | C47: MAYO | D47: P. SOCIAL | F47: 2 | G47: =+G46+E47-F47 -> 30.8
A48: 42949 | B48: 13343 | C48: MAYO | D48: LUZ | F48: 28.8 | G48: =+G47+E48-F48 -> 2
A49: 42949 | B49: 13343 | C49: MAYO | D49: AGUA | F49: 2 | G49: =+G48+E49-F49 -> -3.5527137e-15
A50: 42916 | B50: POR COBRAR | C50: JUNIO | D50: LUZ | E50: 28 | G50: =+G49+E50-F50 -> 28
D51: AGUA | E51: 2 | G51: =+G50+E51-F51 -> 30
D52: G. ADM | E52: 60 | G52: =+G51+E52-F52 -> 90
D53: P. SOCIAL | E53: 2 | G53: =+G52+E53-F53 -> 92
A54: 42916 | B54: TARJETA | C54: JUNIO | D54: G. ADM | F54: 60 | G54: =+G53+E54-F54 -> 32
A55: 42916 | B55: TARJETA | C55: JUNIO | D55: P. SOCIAL | F55: 2 | G55: =+G54+E55-F55 -> 30
A56: 42949 | B56: 13343 | C56: JUNIO | D56: LUZ | F56: 28 | G56: =+G55+E56-F56 -> 2
A57: 42949 | B57: 13343 | C57: JUNIO | D57: AGUA | F57: 2 | G57: =+G56+E57-F57 -> 0
A58: 42947 | B58: POR COBRAR | C58: JULIO | D58: LUZ | E58: 26.6 | G58: =+G57+E58-F58 -> 26.6
D59: AGUA | E59: 2 | G59: =+G58+E59-F59 -> 28.6
D60: G. ADM | E60: 60 | G60: =+G59+E60-F60 -> 88.6
D61: P. SOCIAL | E61: 2 | G61: =+G60+E61-F61 -> 90.6
A62: 42947 | B62: TARJETA | C62: JULIO | D62: G. ADM | F62: 60 | G62: =+G61+E62-F62 -> 30.6
A63: 42947 | B63: TARJETA | C63: JULIO | D63: P. SOCIAL | F63: 2 | G63: =+G62+E63-F63 -> 28.6
A64: 43067 | B64: 14158 | C64: JULIO | D64: LUZ | F64: 26.6 | G64: =+G63+E64-F64 -> 2
A65: 43067 | B65: 14158 | C65: JULIO | D65: AGUA | F65: 2 | G65: =+G64+E65-F65 -> -7.1054274e-15
A66: 42978 | B66: POR COBRAR | C66: AGOSTO | D66: LUZ | E66: 26.6 | G66: =+G65+E66-F66 -> 26.6
D67: AGUA | E67: 2 | G67: =+G66+E67-F67 -> 28.6
D68: G. ADM | E68: 60 | G68: =+G67+E68-F68 -> 88.6
D69: P. SOCIAL | E69: 2 | G69: =+G68+E69-F69 -> 90.6
D70: MULTA | E70: 85 | G70: =+G69+E70-F70 -> 175.6
A71: 42978 | B71: TARJETA | C71: AGOSTO | D71: G. ADM | F71: 60 | G71: =+G70+E71-F71 -> 115.6
A72: 42978 | B72: TARJETA | C72: AGOSTO | D72: P. SOCIAL | F72: 2 | G72: =+G71+E72-F72 -> 113.6
A73: 43067 | B73: 14158 | C73: AGOSTO | D73: LUZ | F73: 26.6 | G73: =+G72+E73-F73 -> 87
A74: 43067 | B74: 14158 | C74: AGOSTO | D74: AGUA | F74: 2 | G74: =+G73+E74-F74 -> 85
A75: 43068 | B75: 14174 | C75: AGOSTO | D75: MULTA | F75: 85 | G75: =+G74+E75-F75 -> 0
A76: 43008 | B76: POR COBRAR | C76: SEPTIEMBRE | D76: LUZ | E76: 44.5 | G76: =+G75+E76-F76 -> 44.5
D77: AGUA | E77: 2 | G77: =+G76+E77-F77 -> 46.5
D78: G. ADM | E78: 60 | G78: =+G77+E78-F78 -> 106.5
D79: P. SOCIAL | E79: 2 | G79: =+G78+E79-F79 -> 108.5
A80: 43008 | B80: TARJETA | C80: SEPTIEMBRE | D80: G. ADM | F80: 60 | G80: =+G79+E80-F80 -> 48.5
A81: 43008 | B81: TARJETA | C81: SEPTIEMBRE | D81: P. SOCIAL | F81: 2 | G81: =+G80+E81-F81 -> 46.5
A82: 43067 | B82: 14158 | C82: SEPTIEMBRE | D82: LUZ | F82: 44.5 | G82: =+G81+E82-F82 -> 2
A83: 43067 | B83: 14158 | C83: SEPTIEMBRE | D83: AGUA | F83: 2 | G83: =+G82+E83-F83 -> 0
A84: 43039 | B84: POR COBRAR | C84: OCTUBRE | D84: LUZ | E84: 44.6 | G84: =+G83+E84-F84 -> 44.6
D85: AGUA | E85: 2 | G85: =+G84+E85-F85 -> 46.6
D86: G. ADM | E86: 60 | G86: =+G85+E86-F86 -> 106.6
D87: P. SOCIAL | E87: 2 | G87: =+G86+E87-F87 -> 108.6
A88: 43039 | B88: TARJETA | C88: OCTUBRE | D88: G. ADM | F88: 60 | G88: =+G87+E88-F88 -> 48.6
A89: 43039 | B89: TARJETA | C89: OCTUBRE | D89: P. SOCIAL | F89: 2 | G89: =+G88+E89-F89 -> 46.6
A90: 43067 | B90: 14158 | C90: OCTUBRE | D90: LUZ | F90: 44.6 | G90: =+G89+E90-F90 -> 2
A91: 43067 | B91: 14158 | C91: OCTUBRE | D91: AGUA | F91: 2 | G91: =+G90+E91-F91 -> -7.1054274e-15
A92: 43069 | B92: POR COBRAR | C92: NOVIEMBRE | D92: LUZ | E92: 47.3 | G92: =+G91+E92-F92 -> 47.3
D93: AGUA | E93: 2 | G93: =+G92+E93-F93 -> 49.3
D94: G. ADM | E94: 60 | G94: =+G93+E94-F94 -> 109.3
D95: P. SOCIAL | E95: 2 | G95: =+G94+E95-F95 -> 111.3
A96: 43088 | B96: 14318 | C96: NOVIEMBRE | D96: LUZ | F96: 47.3 | G96: =+G95+E96-F96 -> 64
A97: 43088 | B97: 14318 | C97: NOVIEMBRE | D97: AGUA | F97: 2 | G97: =+G96+E97-F97 -> 62
A98: 43069 | B98: TARJETA | C98: NOVIEMBRE | D98: G. ADM | F98: 60 | G98: =+G97+E98-F98 -> 2
A99: 43157 | B99: 14736 | C99: NOVIEMBRE | D99: P. SOCIAL | F99: 2 | G99: =+G98+E99-F99 -> -1.4210855e-14
A100: 43100 | B100: POR COBRAR | C100: DICIEMBRE | D100: LUZ | E100: 51.4 | G100: =+G99+E100-F100 -> 51.4
D101: AGUA | E101: 2 | G101: =+G100+E101-F101 -> 53.4
D102: G. ADM | E102: 60 | G102: =+G101+E102-F102 -> 113.4
...

Sheet OQUENDO JESSICA
B2: OQUENDO QUISPE JESSICA
A4: FECHA | B4: DOCUMENTO | C4: PERIODO | D4: CONCEPTO | E4: POR COBRAR | F4: PAGADO | G4: SALDO POR COBRAR
A5: 42736 | B5: SALDO AL 2016 | G5: 113.1
A6: 42762 | B6: 12168 | C6: A CUENTA 2016 | F6: 113.1 | G6: =+G5+E6-F6 -> 0
A7: 42766 | B7: POR COBRAR | C7: ENERO | D7: LUZ | E7: 13.5 | G7: =+G6+E7-F7 -> 13.5
D8: AGUA | E8: 2.8 | G8: =+G7+E8-F8 -> 16.3
D9: G. ADM | E9: 60 | G9: =+G8+E9-F9 -> 76.3
D10: P. SOCIAL | E10: 2 | G10: =+G9+E10-F10 -> 78.3
A11: 42765 | B11: TARJETA | C11: ENERO | D11: G. ADM | F11: 60 | G11: =+G10+E11-F11 -> 18.3
A12: 42765 | B12: TARJETA | C12: ENERO | D12: P. SOCIAL | F12: 2 | G12: =+G11+E12-F12 -> 16.3
A13: 42786 | B13: 12295 | C13: ENERO | D13: LUZ | F13: 13.5 | G13: =+G12+E13-F13 -> 2.8
A14: 42786 | B14: 12295 | C14: ENERO | D14: AGUA | F14: 2.8 | G14: =+G13+E14-F14 -> 0
A15: 42794 | B15: POR COBRAR | C15: FEBRERO | D15: LUZ | E15: 13 | G15: =+G14+E15-F15 -> 13
D16: AGUA | E16: 2 | G16: =+G15+E16-F16 -> 15
D17: G. ADM | E17: 56 | G17: =+G16+E17-F17 -> 71
D18: P. SOCIAL | E18: 2 | G18: =+G17+E18-F18 -> 73
A19: 42794 | B19: TARJETA | C19: FEBRERO | D19: G. ADM | F19: 56 | G19: =+G18+E19-F19 -> 17
A20: 42794 | B20: TARJETA | C20: FEBRERO | D20: P. SOCIAL | F20: 2 | G20: =+G19+E20-F20 -> 15
A21: 42821 | B21: 12551 | C21: FEBRERO | D21: LUZ | F21: 13 | G21: =+G20+E21-F21 -> 2
A22: 42793 | B22: 12551 | C22: FEBRERO | D22: AGUA | F22: 2 | G22: =+G21+E22-F22 -> 0
A23: 42825 | B23: POR COBRAR | C23: MARZO | D23: LUZ | E23: 12 | G23: =+G22+E23-F23 -> 12
D24: AGUA | E24: 2 | G24: =+G23+E24-F24 -> 14
D25: G. ADM | E25: 60 | G25: =+G24+E25-F25 -> 74
D26: P. SOCIAL | E26: 2 | G26: =+G25+E26-F26 -> 76
A27: 42824 | B27: TARJETA | C27: MARZO | D27: G. ADM | F27: 60 | G27: =+G26+E27-F27 -> 16
A28: 42824 | B28: TARJETA | C28: MARZO | D28: P. SOCIAL | F28: 2 | G28: =+G27+E28-F28 -> 14
A29: 42864 | B29: 12738 | C29: MARZO | D29: LUZ | F29: 12 | G29: =+G28+E29-F29 -> 2
A30: 42864 | B30: 12738 | C30: MARZO | D30: AGUA | F30: 2 | G30: =+G29+E30-F30 -> 0
A31: 42855 | B31: POR COBRAR | C31: ABRIL | D31: LUZ | E31: 13 | G31: =+G30+E31-F31 -> 13
D32: AGUA | E32: 2 | G32: =+G31+E32-F32 -> 15
D33: G. ADM | E33: 60 | G33: =+G32+E33-F33 -> 75
D34: P. SOCIAL | E34: 2 | G34: =+G33+E34-F34 -> 77
A35: 42854 | B35: TARJETA | C35: ABRIL | D35: G. ADM | F35: 60 | G35: =+G34+E35-F35 -> 17
A36: 42854 | B36: TARJETA | C36: ABRIL | D36: P. SOCIAL | F36: 2 | G36: =+G35+E36-F36 -> 15
A37: 42887 | B37: 13022 | C37: ABRIL | D37: LUZ | F37: 13 | G37: =+G36+E37-F37 -> 2
A38: 42887 | B38: 13022 | C38: ABRIL | D38: AGUA | F38: 2 | G38: =+G37+E38-F38 -> 0
A39: 42886 | B39: POR COBRAR | C39: MAYO | D39: LUZ | E39: 13 | G39: =+G38+E39-F39 -> 13
D40: AGUA | E40: 2 | G40: =+G39+E40-F40 -> 15
D41: G. ADM | E41: 60 | G41: =+G40+E41-F41 -> 75
D42: P. SOCIAL | E42: 2 | G42: =+G41+E42-F42 -> 77
A43: 42885 | B43: TARJETA | C43: MAYO | D43: G. ADM | F43: 60 | G43: =+G42+E43-F43 -> 17
A44: 42885 | B44: TARJETA | C44: MAYO | D44: P. SOCIAL | F44: 2 | G44: =+G43+E44-F44 -> 15
A45: 42949 | B45: 13347 | C45: MAYO | D45: LUZ | F45: 13 | G45: =+G44+E45-F45 -> 2
A46: 42949 | B46: 13347 | C46: MAYO | D46: AGUA | F46: 2 | G46: =+G45+E46-F46 -> 0
A47: 42916 | B47: POR COBRAR | C47: JUNIO | D47: LUZ | E47: 12.5 | G47: =+G46+E47-F47 -> 12.5
D48: AGUA | E48: 2 | G48: =+G47+E48-F48 -> 14.5
D49: G. ADM | E49: 60 | G49: =+G48+E49-F49 -> 74.5
D50: P. SOCIAL | E50: 2 | G50: =+G49+E50-F50 -> 76.5
A51: 42916 | B51: TARJETA | C51: JUNIO | D51: G. ADM | F51: 60 | G51: =+G50+E51-F51 -> 16.5
A52: 42916 | B52: TARJETA | C52: JUNIO | D52: P. SOCIAL | F52: 2 | G52: =+G51+E52-F52 -> 14.5
A53: 42949 | B53: 13347 | C53: JUNIO | D53: LUZ | F53: 12.5 | G53: =+G52+E53-F53 -> 2
A54: 42949 | B54: 13347 | C54: JUNIO | D54: AGUA | F54: 2 | G54: =+G53+E54-F54 -> 0
A55: 42947 | B55: POR COBRAR | C55: JULIO | D55: LUZ | E55: 109.1 | G55: =+G54+E55-F55 -> 109.1
D56: AGUA | E56: 2 | G56: =+G55+E56-F56 -> 111.1
D57: G. ADM | E57: 60 | G57: =+G56+E57-F57 -> 171.1
D58: P. SOCIAL | E58: 2 | G58: =+G57+E58-F58 -> 173.1
A59: 42947 | B59: TARJETA | C59: JULIO | D59: G. ADM | F59: 60 | G59: =+G58+E59-F59 -> 113.1
A60: 42947 | B60: TARJETA | C60: JULIO | D60: P. SOCIAL | F60: 2 | G60: =+G59+E60-F60 -> 111.1
A61: 43003 | B61: 13676 | C61: JULIO | D61: LUZ | F61: 109.1 | G61: =+G60+E61-F61 -> 2
A62: 43003 | B62: 13676 | C62: JULIO | D62: AGUA | F62: 2 | G62: =+G61+E62-F62 -> 0
A63: 42978 | B63: POR COBRAR | C63: AGOSTO | D63: LUZ | E63: 109.1 | G63: =+G62+E63-F63 -> 109.1
D64: AGUA | E64: 2 | G64: =+G63+E64-F64 -> 111.1
D65: G. ADM | E65: 60 | G65: =+G64+E65-F65 -> 171.1
D66: P. SOCIAL | E66: 2 | G66: =+G65+E66-F66 -> 173.1
A67: 42978 | B67: TARJETA | C67: AGOSTO | D67: G. ADM | F67: 60 | G67: =+G66+E67-F67 -> 113.1
A68: 42978 | B68: TARJETA | C68: AGOSTO | D68: P. SOCIAL | F68: 2 | G68: =+G67+E68-F68 -> 111.1
A69: 43003 | B69: 13676 | C69: AGOSTO | D69: LUZ | F69: 109.1 | G69: =+G68+E69-F69 -> 2
A70: 43003 | B70: 13676 | C70: AGOSTO | D70: AGUA | F70: 2 | G70: =+G69+E70-F70 -> 0
A71: 43008 | B71: POR COBRAR | C71: SEPTIEMBRE | D71: LUZ | E71: 117 | G71: =+G70+E71-F71 -> 117
D72: AGUA | E72: 2 | G72: =+G71+E72-F72 -> 119
D73: G. ADM | E73: 60 | G73: =+G72+E73-F73 -> 179
D74: P. SOCIAL | E74: 2 | G74: =+G73+E74-F74 -> 181
A75: 43008 | B75: TARJETA | C75: SEPTIEMBRE | D75: G. ADM | F75: 60 | G75: =+G74+E75-F75 -> 121
A76: 43008 | B76: TARJETA | C76: SEPTIEMBRE | D76: P. SOCIAL | F76: 2 | G76: =+G75+E76-F76 -> 119
A77: 43042 | B77: 13920 | C77: SEPTIEMBRE | D77: LUZ | F77: 117 | G77: =+G76+E77-F77 -> 2
A78: 43042 | B78: 13920 | C78: SEPTIEMBRE | D78: AGUA | F78: 2 | G78: =+G77+E78-F78 -> 0
A79: 43039 | B79: POR COBRAR | C79: OCTUBRE | D79: LUZ | E79: 116.4 | G79: =+G78+E79-F79 -> 116.4
D80: AGUA | E80: 2 | G80: =+G79+E80-F80 -> 118.4
D81: G. ADM | E81: 60 | G81: =+G80+E81-F81 -> 178.4
D82: P. SOCIAL | E82: 2 | G82: =+G81+E82-F82 -> 180.4
A83: 43039 | B83: TARJETA | C83: OCTUBRE | D83: G. ADM | F83: 56 | G83: =+G82+E83-F83 -> 124.4
A84: 43042 | B84: 13920 | C84: OCTUBRE | D84: G. ADM | F84: 4 | G84: =+G83+E84-F84 -> 120.4
A85: 43042 | B85: 13920 | C85: OCTUBRE | D85: P. SOCIAL | F85: 2 | G85: =+G84+E85-F85 -> 118.4
A86: 43068 | B86: 14194 | C86: OCTUBRE | D86: LUZ | F86: 116.4 | G86: =+G85+E86-F86 -> 2
A87: 43068 | B87: 14194 | C87: OCTUBRE | D87: AGUA | F87: 2 | G87: =+G86+E87-F87 -> 0
A88: 43069 | B88: POR COBRAR | C88: NOVIEMBRE | D88: LUZ | E88: 124.3 | G88: =+G87+E88-F88 -> 124.3
D89: AGUA | E89: 2 | G89: =+G88+E89-F89 -> 126.3
D90: G. ADM | E90: 60 | G90: =+G89+E90-F90 -> 186.3
D91: P. SOCIAL | E91: 2 | G91: =+G90+E91-F91 -> 188.3
A92: 43119 | B92: 14524 | C92: NOVIEMBRE | D92: LUZ | F92: 124.3 | G92: =+G91+E92-F92 -> 64
A93: 43119 | B93: 14524 | C93: NOVIEMBRE | D93: AGUA | F93: 2 | G93: =+G92+E93-F93 -> 62
A94: 43119 | B94: 14524 | C94: NOVIEMBRE | D94: G. ADM | F94: 60 | G94: =+G93+E94-F94 -> 2
A95: 43119 | B95: 14524 | C95: NOVIEMBRE | D95: P. SOCIAL | F95: 2 | G95: =+G94+E95-F95 -> 1.4210855e-14
A96: 43100 | B96: POR COBRAR | C96: DICIEMBRE | D96: LUZ | E96: 135.2 | G96: =+G95+E96-F96 -> 135.2
D97: AGUA | E97: 2 | G97: =+G96+E97-F97 -> 137.2
D98: G. ADM | E98: 60 | G98: =+G97+E98-F98 -> 197.2
D99: P. SOCIAL | E99: 2 | G99: =+G98+E99-F99 -> 199.2
A100: 43119 | B100: 14525 | C100: DICIEMBRE | D100: LUZ | F100: 135.2 | G100: =+G99+E100-F100 -> 64
A101: 43119 | B101: 14525 | C101: DICIEMBRE | D101: AGUA | F101: 2 | G101: =+G100+E101-F101 -> 62
A102: 43119 | B102: 14525 | C102: DICIEMBRE | D102: G. ADM | F102: 60 | G102: =+G101+E102-F102 -> 2
...

Sheet OQUENDO MIGUEL
B2: OQUENDO QUISPE MIGUEL
A4: FECHA | B4: DOCUMENTO | C4: PERIODO | D4: CONCEPTO | E4: POR COBRAR | F4: PAGADO | G4: SALDO POR COBRAR
A5: 42736 | B5: SALDO AL 2016 | G5: 1378.4
A6: 42786 | B6: 12275 | C6: A CUENTA DEL 2016 | F6: 62.4 | G6: =+G5+E6-F6 -> 1316
A7: 42786 | B7: 12276 | C7: A CUENTA DEL 2016 | F7: 321 | G7: =+G6+E7-F7 -> 995
A8: 42786 | B8: 12280 | C8: A CUENTA DEL 2016 | F8: 225 | G8: =+G7+E8-F8 -> 770
A9: 42786 | B9: 12281 | C9: A CUENTA DEL 2016 | F9: 450 | G9: =+G8+E9-F9 -> 320
A10: 42793 | B10: 12374 | C10: A CUENTA DEL 2016 | F10: 320 | G10: =+G9+E10-F10 -> 0
A11: 42766 | B11: POR COBRAR | C11: ENERO | D11: LUZ | E11: 13.5 | G11: =+G10+E11-F11 -> 13.5
D12: AGUA | E12: 2.8 | G12: =+G11+E12-F12 -> 16.3
D13: G. ADM | E13: 60 | G13: =+G12+E13-F13 -> 76.3
D14: P. SOCIAL | E14: 2 | G14: =+G13+E14-F14 -> 78.3
D15: P. SOCIAL XFALL. | E15: 10 | G15: =+G14+E15-F15 -> 88.3
A16: 42786 | B16: 12276 | C16: ENERO | D16: G. ADM | F16: 60 | G16: =+G15+E16-F16 -> 28.3
A17: 42786 | B17: 12276 | C17: ENERO | D17: P. SOCIAL | F17: 2 | G17: =+G16+E17-F17 -> 26.3
A18: 42793 | B18: 12373 | C18: ENERO | D18: P. SOCIAL XFALL. | F18: 10 | G18: =+G17+E18-F18 -> 16.3
A19: 42786 | B19: 12275 | C19: ENERO | D19: AGUA | F19: 2.8 | G19: =+G18+E19-F19 -> 13.5
A20: 42786 | B20: 12275 | C20: ENERO | D20: LUZ | F20: 13.5 | G20: =+G19+E20-F20 -> 0
A21: 42794 | B21: POR COBRAR | C21: FEBRERO | D21: LUZ | E21: 14.5 | G21: =+G20+E21-F21 -> 14.5
D22: AGUA | E22: 3 | G22: =+G21+E22-F22 -> 17.5
D23: G. ADM | E23: 56 | G23: =+G22+E23-F23 -> 73.5
D24: P. SOCIAL | E24: 2 | G24: =+G23+E24-F24 -> 75.5
D25: MULTA | E25: 85 | G25: =+G24+E25-F25 -> 160.5
A26: 42793 | B26: 12373 | C26: FEBRERO | D26: G. ADM | F26: 56 | G26: =+G25+E26-F26 -> 104.5
A27: 42793 | B27: 12373 | C27: FEBRERO | D27: P. SOCIAL | F27: 2 | G27: =+G26+E27-F27 -> 102.5
A28: 42793 | B28: 12373 | C28: FEBRERO | D28: LUZ | F28: 14.5 | G28: =+G27+E28-F28 -> 88
A29: 42793 | B29: 12373 | C29: FEBRERO | D29: AGUA | F29: 3 | G29: =+G28+E29-F29 -> 85
A30: 42793 | B30: 12375 | C30: FEBRERO | D30: MULTA | F30: 85 | G30: =+G29+E30-F30 -> 0
A31: 42825 | B31: POR COBRAR | C31: MARZO | D31: LUZ | E31: 12 | G31: =+G30+E31-F31 -> 12
D32: AGUA | E32: 0 | G32: =+G31+E32-F32 -> 12
D33: G. ADM | E33: 60 | G33: =+G32+E33-F33 -> 72
D34: P. SOCIAL | E34: 2 | G34: =+G33+E34-F34 -> 74
A35: 42870 | B35: 12751 | C35: MARZO | D35: G. ADM | F35: 60 | G35: =+G34+E35-F35 -> 14
A36: 42870 | B36: 12751 | C36: MARZO | D36: P. SOCIAL | F36: 2 | G36: =+G35+E36-F36 -> 12
A37: 42870 | B37: 12751 | C37: MARZO | D37: LUZ | F37: 12 | G37: =+G36+E37-F37 -> 0
A38: 42855 | B38: POR COBRAR | C38: ABRIL | D38: LUZ | E38: 13 | G38: =+G37+E38-F38 -> 13
D39: AGUA | E39: 2 | G39: =+G38+E39-F39 -> 15
D40: G. ADM | E40: 60 | G40: =+G39+E40-F40 -> 75
D41: P. SOCIAL | E41: 2 | G41: =+G40+E41-F41 -> 77
A42: 42870 | B42: 12751 | C42: ABRIL | D42: G. ADM | F42: 60 | G42: =+G41+E42-F42 -> 17
A43: 42870 | B43: 12751 | C43: ABRIL | D43: AGUA | F43: 2 | G43: =+G42+E43-F43 -> 15
A44: 42870 | B44: 72751 | C44: ABRIL | D44: LUZ | F44: 13 | G44: =+G43+E44-F44 -> 2
A45: 42886 | B45: POR COBRAR | C45: MAYO | D45: LUZ | E45: 13 | G45: =+G44+E45-F45 -> 15
D46: AGUA | E46: 2 | G46: =+G45+E46-F46 -> 17
D47: G. ADM | E47: 60 | G47: =+G46+E47-F47 -> 77
D48: P. SOCIAL | E48: 2 | G48: =+G47+E48-F48 -> 79
D49: DERECHO DE TRANFERENCIA | E49: 6000 | G49: =+G48+E49-F49 -> 6079
A50: 42886 | B50: TARJETA | C50: MAYO | D50: G. ADM | F50: 32 | G50: =+G49+E50-F50 -> 6047
A51: 42886 | B51: TARJETA | C51: MAYO | D51: P. SOCIAL | F51: 2 | G51: =+G50+E51-F51 -> 6045
A52: 42870 | B52: 12752 | C52: MAYO | D52: G. ADM | F52: 30 | G52: =+G51+E52-F52 -> 6015
A53: 42870 | B53: 12750 | C53: MAYO | D53: DERECHO DE TRANFERENCIA | F53: 6000 | G53: =+G52+E53-F53 -> 15
A54: 42949 | B54: 13349 | C54: MAYO | D54: LUZ | F54: 13 | G54: =+G53+E54-F54 -> 2
A55: 42949 | B55: 13349 | C55: MAYO | D55: AGUA | F55: 2 | G55: =+G54+E55-F55 -> 0
A56: 42916 | B56: POR COBRAR | C56: JUNIO | D56: LUZ | E56: 12.5 | G56: =+G55+E56-F56 -> 12.5
D57: AGUA | E57: 2 | G57: =+G56+E57-F57 -> 14.5
D58: G. ADM | E58: 60 | G58: =+G57+E58-F58 -> 74.5
D59: P. SOCIAL | E59: 2 | G59: =+G58+E59-F59 -> 76.5
A60: 42916 | B60: TARJETA | C60: JUNIO | D60: G. ADM | F60: 60 | G60: =+G59+E60-F60 -> 16.5
A61: 42916 | B61: TARJETA | C61: JUNIO | D61: P. SOCIAL | F61: 2 | G61: =+G60+E61-F61 -> 14.5
A62: 42949 | B62: 13349 | C62: JUNIO | D62: LUZ | F62: 12.5 | G62: =+G61+E62-F62 -> 2
A63: 42949 | B63: 13349 | C63: JUNIO | D63: AGUA | F63: 2 | G63: =+G62+E63-F63 -> 0
A64: 42947 | B64: POR COBRAR | C64: JULIO | D64: LUZ | E64: 13 | G64: =+G63+E64-F64 -> 13
D65: AGUA | E65: 2 | G65: =+G64+E65-F65 -> 15
D66: G. ADM | E66: 60 | G66: =+G65+E66-F66 -> 75
D67: P. SOCIAL | E67: 2 | G67: =+G66+E67-F67 -> 77
D68: P. SOCIAL XFALL. | E68: 10 | G68: =+G67+E68-F68 -> 87
A69: 42947 | B69: TARJETA | C69: JULIO | D69: G. ADM | F69: 60 | G69: =+G68+E69-F69 -> 27
A70: 42947 | B70: TARJETA | C70: JULIO | D70: P. SOCIAL | F70: 2 | G70: =+G69+E70-F70 -> 25
A71: 42950 | B71: 13403 | C71: JULIO | D71: P. SOCIAL XFALL. | F71: 10 | G71: =+G70+E71-F71 -> 15
A72: 43000 | B72: 13659 | C72: JULIO | D72: LUZ | F72: 13 | G72: =+G71+E72-F72 -> 2
A73: 43000 | B73: 13659 | C73: JULIO | D73: AGUA | F73: 2 | G73: =+G72+E73-F73 -> 0
A74: 42978 | B74: POR COBRAR | C74: AGOSTO | D74: LUZ | E74: 13 | G74: =+G73+E74-F74 -> 13
D75: AGUA | E75: 2 | G75: =+G74+E75-F75 -> 15
D76: G. ADM | E76: 60 | G76: =+G75+E76-F76 -> 75
D77: P. SOCIAL | E77: 2 | G77: =+G76+E77-F77 -> 77
A78: 42978 | B78: TARJETA | C78: AGOSTO | D78: G. ADM | F78: 60 | G78: =+G77+E78-F78 -> 17
A79: 42978 | B79: TARJETA | C79: AGOSTO | D79: P. SOCIAL | F79: 2 | G79: =+G78+E79-F79 -> 15
A80: 43000 | B80: 13659 | C80: AGOSTO | D80: LUZ | F80: 13 | G80: =+G79+E80-F80 -> 2
A81: 43000 | B81: 13659 | C81: AGOSTO | D81: AGUA | F81: 2 | G81: =+G80+E81-F81 -> 0
A82: 43008 | B82: POR COBRAR | C82: SEPTIEMBRE | D82: LUZ | E82: 17.4 | G82: =+G81+E82-F82 -> 17.4
D83: AGUA | E83: 2 | G83: =+G82+E83-F83 -> 19.4
D84: G. ADM | E84: 60 | G84: =+G83+E84-F84 -> 79.4
D85: P. SOCIAL | E85: 2 | G85: =+G84+E85-F85 -> 81.4
A86: 42951 | D86: MULTA | E86: 85 | G86: =+G85+E86-F86 -> 166.4
A87: 43008 | B87: TARJETA | C87: SEPTIEMBRE | D87: G. ADM | F87: 60 | G87: =+G86+E87-F87 -> 106.4
A88: 43008 | B88: TARJETA | C88: SEPTIEMBRE | D88: P. SOCIAL | F88: 2 | G88: =+G87+E88-F88 -> 104.4
A89: 43042 | B89: 13919 | C89: SEPTIEMBRE | D89: LUZ | F89: 17.4 | G89: =+G88+E89-F89 -> 87
A90: 43042 | B90: 13919 | C90: SEPTIEMBRE | D90: AGUA | F90: 2 | G90: =+G89+E90-F90 -> 85
A91: 43067 | B91: EXONERACION | C91: 42951 | D91: MULTA | F91: 85 | G91: =+G90+E91-F91 -> 0
A92: 43039 | B92: POR COBRAR | C92: OCTUBRE | D92: LUZ | E92: 17.3 | G92: =+G91+E92-F92 -> 17.3
D93: AGUA | E93: 2 | G93: =+G92+E93-F93 -> 19.3
D94: G. ADM | E94: 60 | G94: =+G93+E94-F94 -> 79.3
D95: P. SOCIAL | E95: 2 | G95: =+G94+E95-F95 -> 81.3
A96: 43039 | B96: 13919 | C96: OCTUBRE | D96: G. ADM | F96: 60 | G96: =+G95+E96-F96 -> 21.3
A97: 43039 | B97: 13919 | C97: OCTUBRE | D97: P. SOCIAL | F97: 2 | G97: =+G96+E97-F97 -> 19.3
A98: 43068 | B98: 14193 | C98: OCTUBRE | D98: LUZ | F98: 17.3 | G98: =+G97+E98-F98 -> 2
A99: 43068 | B99: 14193 | C99: OCTUBRE | D99: AGUA | F99: 2 | G99: =+G98+E99-F99 -> -3.5527137e-15
A100: 43069 | B100: POR COBRAR | C100: NOVIEMBRE | D100: LUZ | E100: 18.5 | G100: =+G99+E100-F100 -> 18.5
D101: AGUA | E101: 2 | G101: =+G100+E101-F101 -> 20.5
D102: G. ADM | E102: 60 | G102: =+G101+E102-F102 -> 80.5
...

Sheet ORTIZ WELINTONH
B2: ORTIZ ÑAUPA WELINTONH
A4: FECHA | B4: DOCUMENTO | C4: PERIODO | D4: CONCEPTO | E4: POR COBRAR | F4: PAGADO | G4: SALDO POR COBRAR
A5: 42736 | B5: SALDO AL 2016 | G5: 1048.8
A6: 42889 | B6: 13044 | C6: A CUENTA 2016 | F6: 209.8 | G6: =+G5+E6-F6 -> 839
A7: 42885 | B7: TARJETA | C7: A CUENTA 2016 | F7: 80 | G7: =+G6+E7-F7 -> 759
A8: 42941 | B8: 13255 | C8: A CUENTA 2016 | F8: 64 | G8: =+G7+E8-F8 -> 695
A9: 42736 | B9: TARJETA | C9: A CUENTA 2016 | F9: 90 | G9: =+G8+E9-F9 -> 605
A10: 42794 | B10: TARJETA | C10: A CUENTA 2016 | F10: 100 | G10: =+G9+E10-F10 -> 505
A11: 42824 | B11: TARJETA | C11: A CUENTA 2016 | F11: 100 | G11: =+G10+E11-F11 -> 405
A12: 42855 | B12: TARJETA | C12: A CUENTA 2016 | F12: 90 | G12: =+G11+E12-F12 -> 315
A13: 43517 | B13: 17178 | C13: CANCELACION 2016 | F13: 315 | G13: =+G12+E13-F13 -> 0
A14: 42766 | B14: POR COBRAR | C14: ENERO | D14: LUZ | E14: 248.5 | G14: =+G13+E14-F14 -> 248.5
D15: AGUA | E15: 42.8 | G15: =+G14+E15-F15 -> 291.3
D16: G. ADM | E16: 60 | G16: =+G15+E16-F16 -> 351.3
D17: P. SOCIAL | E17: 2 | G17: =+G16+E17-F17 -> 353.3
A18: 42762 | B18: TARJETA | C18: ENERO | D18: G. ADM | F18: 18 | G18: =+G17+E18-F18 -> 335.3
A19: 42762 | B19: TARJETA | C19: ENERO | D19: LUZ | F19: 72 | G19: =+G18+E19-F19 -> 263.3
A20: 42889 | B20: 13044 | C20: ENERO | D20: LUZ | F20: 176.5 | G20: =+G19+E20-F20 -> 86.8
A21: 42892 | B21: 13074 | C21: ENERO | D21: AGUA | F21: 42.8 | G21: =+G20+E21-F21 -> 44
A22: 43517 | B22: 17178 | C22: ENERO | D22: G. ADM | F22: 35 | G22: =+G21+E22-F22 -> 9
A23: 43522 | B23: 17197 | C23: ENERO | D23: G. ADM | F23: 7 | G23: =+G22+E23-F23 -> 2
A24: 43522 | B24: 17197 | C24: ENERO | D24: P. SOCIAL | F24: 2 | G24: =+G23+E24-F24 -> 1.4210855e-14
A25: 42794 | B25: POR COBRAR | C25: FEBRERO | D25: LUZ | E25: 168.8 | G25: =+G24+E25-F25 -> 168.8
D26: AGUA | E26: 30 | G26: =+G25+E26-F26 -> 198.8
D27: G. ADM | E27: 56 | G27: =+G26+E27-F27 -> 254.8
D28: P. SOCIAL | E28: 2 | G28: =+G27+E28-F28 -> 256.8
D29: RECONEXION | E29: 30 | G29: =+G28+E29-F29 -> 286.8
D30: MULTA | E30: 85 | G30: =+G29+E30-F30 -> 371.8
A31: 42791 | B31: TARJETA | C31: FEBRERO | D31: G. ADM | F31: 20 | G31: =+G30+E31-F31 -> 351.8
A32: 42791 | B32: TARJETA | C32: FEBRERO | D32: LUZ | F32: 80 | G32: =+G31+E32-F32 -> 271.8
A33: 42889 | B33: 13044 | C33: FEBRERO | D33: LUZ | F33: 88.8 | G33: =+G32+E33-F33 -> 183
A34: 42889 | B34: 13044 | C34: FEBRERO | D34: RECONEXION | F34: 30 | G34: =+G33+E34-F34 -> 153
A35: 42892 | B35: 13074 | C35: FEBRERO | D35: AGUA | F35: 30 | G35: =+G34+E35-F35 -> 123
A36: 43067 | B36: EXONERACION | C36: FEBRERO | D36: MULTA | F36: 85 | G36: =+G35+E36-F36 -> 38
A37: 43522 | B37: 17197 | C37: FEBRERO | D37: G. ADM | F37: 36 | G37: =+G36+E37-F37 -> 2
A38: 43522 | B38: 17197 | C38: FEBRERO | D38: P. SOCIAL | F38: 2 | G38: =+G37+E38-F38 -> 0
A39: 42825 | B39: POR COBRAR | C39: MARZO | D39: LUZ | E39: 162.2 | G39: =+G38+E39-F39 -> 162.2
D40: AGUA | E40: 31.2 | G40: =+G39+E40-F40 -> 193.4
D41: G. ADM | E41: 60 | G41: =+G40+E41-F41 -> 253.4
D42: P. SOCIAL | E42: 2 | G42: =+G41+E42-F42 -> 255.4
D43: MULTA | E43: 85 | G43: =+G42+E43-F43 -> 340.4
A44: 42824 | B44: TARJETA | C44: MARZO | D44: G. ADM | F44: 20 | G44: =+G43+E44-F44 -> 320.4
A45: 42824 | B45: TARJETA | C45: MARZO | D45: LUZ | F45: 80 | G45: =+G44+E45-F45 -> 240.4
A46: 42889 | B46: 13044 | C46: MARZO | D46: LUZ | F46: 24.9 | G46: =+G45+E46-F46 -> 215.5
A47: 42891 | B47: 13063 | C47: MARZO | D47: LUZ | F47: 57.3 | G47: =+G46+E47-F47 -> 158.2
A48: 42892 | B48: 13074 | C48: MARZO | D48: AGUA | F48: 31.2 | G48: =+G47+E48-F48 -> 127
A49: 43067 | B49: EXONERACION | C49: MARZO | D49: MULTA | F49: 85 | G49: =+G48+E49-F49 -> 42
A50: 43522 | B50: 17197 | C50: MARZO | D50: G. ADM | F50: 40 | G50: =+G49+E50-F50 -> 2
A51: 43522 | B51: 17197 | C51: MARZO | D51: P. SOCIAL | F51: 2 | G51: =+G50+E51-F51 -> -1.4210855e-14
A52: 42855 | B52: POR COBRAR | C52: ABRIL | D52: LUZ | E52: 164.6 | G52: =+G51+E52-F52 -> 164.6
D53: AGUA | E53: 30.6 | G53: =+G52+E53-F53 -> 195.2
D54: G. ADM | E54: 60 | G54: =+G53+E54-F54 -> 255.2
D55: P. SOCIAL | E55: 2 | G55: =+G54+E55-F55 -> 257.2
A56: 42855 | B56: TARJETA | C56: ABRIL | D56: G. ADM | F56: 18 | G56: =+G55+E56-F56 -> 239.2
A57: 42855 | B57: TARJETA | C57: ABRIL | D57: LUZ | F57: 72 | G57: =+G56+E57-F57 -> 167.2
A58: 42891 | B58: 13063 | C58: ABRIL | D58: LUZ | F58: 92.6 | G58: =+G57+E58-F58 -> 74.6
A59: 42892 | B59: 13074 | C59: ABRIL | D59: AGUA | F59: 30.6 | G59: =+G58+E59-F59 -> 44
A60: 43522 | B60: 17197 | C60: ABRIL | D60: G. ADM | F60: 42 | G60: =+G59+E60-F60 -> 2
A61: 43522 | B61: 17197 | C61: ABRIL | D61: P. SOCIAL | F61: 2 | G61: =+G60+E61-F61 -> -6.3948846e-14
A62: 42886 | B62: POR COBRAR | C62: MAYO | D62: LUZ | E62: 152.6 | G62: =+G61+E62-F62 -> 152.6
D63: AGUA | E63: 30 | G63: =+G62+E63-F63 -> 182.6
D64: G. ADM | E64: 60 | G64: =+G63+E64-F64 -> 242.6
D65: P. SOCIAL | E65: 2 | G65: =+G64+E65-F65 -> 244.6
A66: 42885 | B66: TARJETA | C66: MAYO | D66: G. ADM | F66: 16 | G66: =+G65+E66-F66 -> 228.6
A67: 42885 | B67: TARJETA | C67: MAYO | D67: LUZ | F67: 64 | G67: =+G66+E67-F67 -> 164.6
A68: 42941 | B68: 13255 | C68: MAYO | D68: LUZ | F68: 88.6 | G68: =+G67+E68-F68 -> 76
A69: 42941 | B69: 13255 | C69: MAYO | D69: AGUA | F69: 30 | G69: =+G68+E69-F69 -> 46
A70: 43522 | B70: 17197 | C70: MAYO | D70: G. ADM | F70: 44 | G70: =+G69+E70-F70 -> 2
A71: 43522 | B71: 17197 | C71: MAYO | D71: P. SOCIAL | F71: 2 | G71: =+G70+E71-F71 -> -5.6843419e-14
A72: 42916 | B72: POR COBRAR | C72: JUNIO | D72: LUZ | E72: 148.4 | G72: =+G71+E72-F72 -> 148.4
D73: AGUA | E73: 30 | G73: =+G72+E73-F73 -> 178.4
D74: G. ADM | E74: 60 | G74: =+G73+E74-F74 -> 238.4
D75: P. SOCIAL | E75: 2 | G75: =+G74+E75-F75 -> 240.4
D76: RECONEXION | E76: 30 | G76: =+G75+E76-F76 -> 270.4
A77: 42889 | B77: 13044 | C77: JUNIO | D77: RECONEXION | F77: 30 | G77: =+G76+E77-F77 -> 240.4
A78: 42916 | B78: TARJETA | C78: JUNIO | D78: G. ADM | F78: 60 | G78: =+G77+E78-F78 -> 180.4
A79: 42916 | B79: TARJETA | C79: JUNIO | D79: P. SOCIAL | F79: 2 | G79: =+G78+E79-F79 -> 178.4
A80: 42986 | B80: 13559 | C80: JUNIO | D80: LUZ | F80: 148.4 | G80: =+G79+E80-F80 -> 30
A81: 43031 | B81: 13865 | C81: JUNIO | D81: AGUA | F81: 30 | G81: =+G80+E81-F81 -> -2.8421709e-14
A82: 42947 | B82: POR COBRAR | C82: JULIO | D82: LUZ | E82: 132.9 | G82: =+G81+E82-F82 -> 132.9
D83: AGUA | E83: 30 | G83: =+G82+E83-F83 -> 162.9
D84: G. ADM | E84: 60 | G84: =+G83+E84-F84 -> 222.9
D85: P. SOCIAL | E85: 2 | G85: =+G84+E85-F85 -> 224.9
A86: 42947 | B86: TARJETA | C86: JULIO | D86: G. ADM | F86: 60 | G86: =+G85+E86-F86 -> 164.9
A87: 42947 | B87: TARJETA | C87: JULIO | D87: P. SOCIAL | F87: 2 | G87: =+G86+E87-F87 -> 162.9
A88: 43031 | B88: 13865 | C88: JULIO | D88: LUZ | F88: 132.9 | G88: =+G87+E88-F88 -> 30
A89: 43031 | B89: 13865 | C89: JULIO | D89: AGUA | F89: 30 | G89: =+G88+E89-F89 -> -2.8421709e-14
A90: 42978 | B90: POR COBRAR | C90: AGOSTO | D90: LUZ | E90: 132.9 | G90: =+G89+E90-F90 -> 132.9
D91: AGUA | E91: 30 | G91: =+G90+E91-F91 -> 162.9
D92: G. ADM | E92: 60 | G92: =+G91+E92-F92 -> 222.9
D93: P. SOCIAL | E93: 2 | G93: =+G92+E93-F93 -> 224.9
D94: MULTA | E94: 85 | G94: =+G93+E94-F94 -> 309.9
A95: 42978 | B95: TARJETA | C95: AGOSTO | D95: G. ADM | F95: 60 | G95: =+G94+E95-F95 -> 249.9
A96: 42978 | B96: TARJETA | C96: AGOSTO | D96: P. SOCIAL | F96: 2 | G96: =+G95+E96-F96 -> 247.9
A97: 43146 | B97: 14638 | C97: AGOSTO | D97: LUZ | F97: 132.9 | G97: =+G96+E97-F97 -> 115
A98: 43146 | B98: 14638 | C98: AGOSTO | D98: AGUA | F98: 30 | G98: =+G97+E98-F98 -> 85
A99: 43522 | B99: 17197 | C99: AGOSTO | D99: MULTA | F99: 21 | G99: =+G98+E99-F99 -> 64
A100: 43525 | B100: 17276 | C100: AGOSTO | D100: MULTA | F100: 64 | G100: =+G99+E100-F100 -> 0
A101: 43008 | B101: POR COBRAR | C101: SEPTIEMBRE | D101: LUZ | E101: 176 | G101: =+G100+E101-F101 -> 176
D102: AGUA | E102: 30 | G102: =+G101+E102-F102 -> 206
...

Sheet PACOMPIA GIOVANNI
B2: PACOMPIA CARDEÑA GIOVANNI
A4: FECHA | B4: DOCUMENTO | C4: PERIODO | D4: CONCEPTO | E4: POR COBRAR | F4: PAGADO | G4: SALDO POR COBRAR
A5: 42736 | B5: SALDO AL 2016 | G5: 2263.2
A6: 42754 | B6: 12124 | C6: A CUENTA 2016 | F6: 65.7 | G6: =+G5+E6-F6 -> 2197.5
A7: 43026 | B7: 13831 | C7: A CUENTA 2016 | F7: 10 | G7: =+G6+E7-F7 -> 2187.5
A8: 42766 | B8: POR COBRAR | C8: ENERO | D8: LUZ | E8: 50.4 | G8: =+G7+E8-F8 -> 2237.9
D9: AGUA | E9: 2.8 | G9: =+G8+E9-F9 -> 2240.7
D10: G. ADM | E10: 60 | G10: =+G9+E10-F10 -> 2300.7
D11: P. SOCIAL | E11: 2 | G11: =+G10+E11-F11 -> 2302.7
A12: 42769 | B12: 12907 | C12: ENERO | D12: G. ADM | F12: 60 | G12: =+G11+E12-F12 -> 2242.7
A13: 42769 | B13: 12907 | C13: ENERO | D13: P. SOCIAL | F13: 2 | G13: =+G12+E13-F13 -> 2240.7
A14: 42790 | B14: 12364 | C14: ENERO | D14: LUZ | F14: 50.4 | G14: =+G13+E14-F14 -> 2190.3
A15: 42790 | B15: 12364 | C15: ENERO | D15: AGUA | F15: 2.8 | G15: =+G14+E15-F15 -> 2187.5
A16: 42794 | B16: POR COBRAR | C16: FEBRERO | D16: LUZ | E16: 72.4 | G16: =+G15+E16-F16 -> 2259.9
D17: AGUA | E17: 2 | G17: =+G16+E17-F17 -> 2261.9
D18: G. ADM | E18: 56 | G18: =+G17+E18-F18 -> 2317.9
D19: P. SOCIAL | E19: 2 | G19: =+G18+E19-F19 -> 2319.9
D20: MULTA | E20: 85 | G20: =+G19+E20-F20 -> 2404.9
A21: 42801 | B21: 12404 | C21: FEBRERO | D21: G. ADM | F21: 56 | G21: =+G20+E21-F21 -> 2348.9
A22: 42801 | B22: 12404 | C22: FEBRERO | D22: P. SOCIAL | F22: 2 | G22: =+G21+E22-F22 -> 2346.9
A23: 42815 | B23: 12427 | C23: FEBRERO | D23: LUZ | F23: 72.4 | G23: =+G22+E23-F23 -> 2274.5
A24: 42815 | B24: 12427 | C24: FEBRERO | D24: AGUA | F24: 2 | G24: =+G23+E24-F24 -> 2272.5
A25: 42825 | B25: POR COBRAR | C25: MARZO | D25: LUZ | E25: 68.7 | G25: =+G24+E25-F25 -> 2341.2
D26: AGUA | E26: 2 | G26: =+G25+E26-F26 -> 2343.2
D27: G. ADM | E27: 60 | G27: =+G26+E27-F27 -> 2403.2
D28: P. SOCIAL | E28: 2 | G28: =+G27+E28-F28 -> 2405.2
A29: 42831 | B29: 12633 | C29: MARZO | D29: G. ADM | F29: 60 | G29: =+G28+E29-F29 -> 2345.2
A30: 42831 | B30: 12633 | C30: MARZO | D30: P. SOCIAL | F30: 2 | G30: =+G29+E30-F30 -> 2343.2
A31: 42845 | B31: 12662 | C31: MARZO | D31: LUZ | F31: 68.7 | G31: =+G30+E31-F31 -> 2274.5
A32: 42845 | B32: 12662 | C32: MARZO | D32: AGUA | F32: 2 | G32: =+G31+E32-F32 -> 2272.5
A33: 42855 | B33: POR COBRAR | C33: ABRIL | D33: LUZ | E33: 49.7 | G33: =+G32+E33-F33 -> 2322.2
D34: AGUA | E34: 2 | G34: =+G33+E34-F34 -> 2324.2
D35: G. ADM | E35: 60 | G35: =+G34+E35-F35 -> 2384.2
D36: P. SOCIAL | E36: 2 | G36: =+G35+E36-F36 -> 2386.2
A37: 42863 | B37: 12729 | C37: ABRIL | D37: G. ADM | F37: 60 | G37: =+G36+E37-F37 -> 2326.2
A38: 42863 | B38: 12729 | C38: ABRIL | D38: P. SOCIAL | F38: 2 | G38: =+G37+E38-F38 -> 2324.2
A39: 42874 | B39: 12778 | C39: ABRIL | D39: LUZ | F39: 49.7 | G39: =+G38+E39-F39 -> 2274.5
A40: 42874 | B40: 12778 | C40: ABRIL | D40: AGUA | F40: 2 | G40: =+G39+E40-F40 -> 2272.5
A41: 42886 | B41: POR COBRAR | C41: MAYO | D41: LUZ | E41: 47.8 | G41: =+G40+E41-F41 -> 2320.3
D42: AGUA | E42: 2 | G42: =+G41+E42-F42 -> 2322.3
D43: G. ADM | E43: 60 | G43: =+G42+E43-F43 -> 2382.3
D44: P. SOCIAL | E44: 2 | G44: =+G43+E44-F44 -> 2384.3
A45: 42888 | B45: 13040 | C45: MAYO | D45: G. ADM | F45: 60 | G45: =+G44+E45-F45 -> 2324.3
A46: 42888 | B46: 13040 | C46: MAYO | D46: P. SOCIAL | F46: 2 | G46: =+G45+E46-F46 -> 2322.3
A47: 42902 | B47: 13103 | C47: MAYO | D47: LUZ | F47: 47.8 | G47: =+G46+E47-F47 -> 2274.5
A48: 42902 | B48: 13103 | C48: MAYO | D48: AGUA | F48: 2 | G48: =+G47+E48-F48 -> 2272.5
A49: 42916 | B49: POR COBRAR | C49: JUNIO | D49: LUZ | E49: 46.4 | G49: =+G48+E49-F49 -> 2318.9
D50: AGUA | E50: 2 | G50: =+G49+E50-F50 -> 2320.9
D51: G. ADM | E51: 60 | G51: =+G50+E51-F51 -> 2380.9
D52: P. SOCIAL | E52: 2 | G52: =+G51+E52-F52 -> 2382.9
A53: 42916 | B53: 13170 | C53: JUNIO | D53: G. ADM | F53: 60 | G53: =+G52+E53-F53 -> 2322.9
A54: 42916 | B54: 13170 | C54: JUNIO | D54: P. SOCIAL | F54: 2 | G54: =+G53+E54-F54 -> 2320.9
A55: 42936 | B55: 13223 | C55: JUNIO | D55: LUZ | F55: 46.4 | G55: =+G54+E55-F55 -> 2274.5
A56: 42936 | B56: 13223 | C56: JUNIO | D56: AGUA | F56: 2 | G56: =+G55+E56-F56 -> 2272.5
A57: 42947 | B57: POR COBRAR | C57: JULIO | D57: LUZ | E57: 44.7 | G57: =+G56+E57-F57 -> 2317.2
D58: AGUA | E58: 2 | G58: =+G57+E58-F58 -> 2319.2
D59: G. ADM | E59: 60 | G59: =+G58+E59-F59 -> 2379.2
D60: P. SOCIAL | E60: 2 | G60: =+G59+E60-F60 -> 2381.2
A61: 42948 | B61: 13304 | C61: JULIO | D61: G. ADM | F61: 60 | G61: =+G60+E61-F61 -> 2321.2
A62: 42948 | B62: 13304 | C62: JULIO | D62: P. SOCIAL | F62: 2 | G62: =+G61+E62-F62 -> 2319.2
A63: 42970 | B63: 13454 | C63: JULIO | D63: LUZ | F63: 44.7 | G63: =+G62+E63-F63 -> 2274.5
A64: 42970 | B64: 13454 | C64: JULIO | D64: AGUA | F64: 2 | G64: =+G63+E64-F64 -> 2272.5
A65: 42978 | B65: POR COBRAR | C65: AGOSTO | D65: LUZ | E65: 44.7 | G65: =+G64+E65-F65 -> 2317.2
D66: AGUA | E66: 2 | G66: =+G65+E66-F66 -> 2319.2
D67: G. ADM | E67: 60 | G67: =+G66+E67-F67 -> 2379.2
D68: P. SOCIAL | E68: 2 | G68: =+G67+E68-F68 -> 2381.2
D69: MULTA | E69: 85 | G69: =+G68+E69-F69 -> 2466.2
A70: 42975 | B70: 13510 | C70: AGOSTO | D70: G. ADM | F70: 60 | G70: =+G69+E70-F70 -> 2406.2
A71: 42975 | B71: 13510 | C71: AGOSTO | D71: P. SOCIAL | F71: 2 | G71: =+G70+E71-F71 -> 2404.2
A72: 42996 | B72: 13586 | C72: AGOSTO | D72: LUZ | F72: 44.7 | G72: =+G71+E72-F72 -> 2359.5
A73: 42996 | B73: 13586 | C73: AGOSTO | D73: AGUA | F73: 2 | G73: =+G72+E73-F73 -> 2357.5
A74: 43008 | B74: POR COBRAR | C74: SEPTIEMBRE | D74: LUZ | E74: 56.1 | G74: =+G73+E74-F74 -> 2413.6
D75: AGUA | E75: 1.3 | G75: =+G74+E75-F75 -> 2414.9
D76: G. ADM | E76: 60 | G76: =+G75+E76-F76 -> 2474.9
D77: P. SOCIAL | E77: 2 | G77: =+G76+E77-F77 -> 2476.9
A78: 42823 | D78: MULTA | E78: 85 | G78: =+G77+E78-F78 -> 2561.9
A79: 43003 | B79: 13670 | C79: SEPTIEMBRE | D79: G. ADM | F79: 60 | G79: =+G78+E79-F79 -> 2501.9
A80: 43003 | B80: 13670 | C80: SEPTIEMBRE | D80: P. SOCIAL | F80: 2 | G80: =+G79+E80-F80 -> 2499.9
A81: 43032 | B81: 13878 | C81: SEPTIEMBRE | D81: LUZ | F81: 56.1 | G81: =+G80+E81-F81 -> 2443.8
A82: 43032 | B82: 13878 | C82: SEPTIEMBRE | D82: AGUA | F82: 1.3 | G82: =+G81+E82-F82 -> 2442.5
A83: 43039 | B83: POR COBRAR | C83: OCTUBRE | D83: LUZ | E83: 55.8 | G83: =+G82+E83-F83 -> 2498.3
D84: AGUA | E84: 2 | G84: =+G83+E84-F84 -> 2500.3
D85: G. ADM | E85: 60 | G85: =+G84+E85-F85 -> 2560.3
D86: P. SOCIAL | E86: 2 | G86: =+G85+E86-F86 -> 2562.3
D87: FUMIGACION | E87: 10 | G87: =+G86+E87-F87 -> 2572.3
A88: 43039 | B88: 13906 | C88: OCTUBRE | D88: G. ADM | F88: 60 | G88: =+G87+E88-F88 -> 2512.3
A89: 43039 | B89: 13906 | C89: OCTUBRE | D89: P. SOCIAL | F89: 2 | G89: =+G88+E89-F89 -> 2510.3
A90: 43064 | B90: 14092 | C90: OCTUBRE | D90: LUZ | F90: 55.8 | G90: =+G89+E90-F90 -> 2454.5
A91: 43064 | B91: 14092 | C91: OCTUBRE | D91: AGUA | F91: 2 | G91: =+G90+E91-F91 -> 2452.5
A92: 42922 | B92: 5737 | C92: OCTUBRE | D92: FUMIGACION | F92: 10 | G92: =+G91+E92-F92 -> 2442.5
A93: 43069 | B93: POR COBRAR | C93: NOVIEMBRE | D93: LUZ | E93: 59.6 | G93: =+G92+E93-F93 -> 2502.1
D94: AGUA | E94: 2 | G94: =+G93+E94-F94 -> 2504.1
D95: G. ADM | E95: 60 | G95: =+G94+E95-F95 -> 2564.1
D96: P. SOCIAL | E96: 2 | G96: =+G95+E96-F96 -> 2566.1
A97: 43068 | B97: 14164 | C97: NOVIEMBRE | D97: G. ADM | F97: 60 | G97: =+G96+E97-F97 -> 2506.1
A98: 43068 | B98: 14164 | C98: NOVIEMBRE | D98: P. SOCIAL | F98: 2 | G98: =+G97+E98-F98 -> 2504.1
A99: 43087 | B99: 14241 | C99: NOVIEMBRE | D99: LUZ | F99: 59.6 | G99: =+G98+E99-F99 -> 2444.5
A100: 43087 | B100: 14241 | C100: NOVIEMBRE | D100: AGUA | F100: 2 | G100: =+G99+E100-F100 -> 2442.5
A101: 43100 | B101: POR COBRAR | C101: DICIEMBRE | D101: LUZ | E101: 64.8 | G101: =+G100+E101-F101 -> 2507.3
D102: AGUA | E102: 2 | G102: =+G101+E102-F102 -> 2509.3
...

Sheet PALOMINO CECILIA
B2: PALOMINO HANCCO CECILIA
A4: FECHA | B4: DOCUMENTO | C4: PERIODO | D4: CONCEPTO | E4: POR COBRAR | F4: PAGADO | G4: SALDO POR COBRAR
A5: 42736 | B5: SALDO AL 2016 | G5: 175.7
A6: 42786 | B6: 12272 | C6: A CUENTA 2016 | F6: 95.7 | G6: =+G5+E6-F6 -> 80
A7: 42821 | B7: 12533 | C7: A CUENTA 2016 | F7: 80 | G7: =+G6+E7-F7 -> 0
A8: 42766 | B8: POR COBRAR | C8: ENERO | D8: LUZ | E8: 69.9 | G8: =+G7+E8-F8 -> 69.9
D9: AGUA | E9: 33 | G9: =+G8+E9-F9 -> 102.9
D10: G. ADM | E10: 60 | G10: =+G9+E10-F10 -> 162.9
D11: P. SOCIAL | E11: 2 | G11: =+G10+E11-F11 -> 164.9
A12: 42765 | B12: TARJETA | C12: ENERO | D12: G. ADM | F12: 60 | G12: =+G11+E12-F12 -> 104.9
A13: 42765 | B13: TARJETA | C13: ENERO | D13: P. SOCIAL | F13: 2 | G13: =+G12+E13-F13 -> 102.9
A14: 42786 | B14: 12272 | C14: ENERO | D14: LUZ | F14: 69.9 | G14: =+G13+E14-F14 -> 33
A15: 42786 | B15: 12272 | C15: ENERO | D15: AGUA | F15: 33 | G15: =+G14+E15-F15 -> 0
A16: 42794 | B16: POR COBRAR | C16: FEBRERO | D16: LUZ | E16: 73.8 | G16: =+G15+E16-F16 -> 73.8
D17: AGUA | E17: 21 | G17: =+G16+E17-F17 -> 94.8
D18: G. ADM | E18: 56 | G18: =+G17+E18-F18 -> 150.8
D19: P. SOCIAL | E19: 2 | G19: =+G18+E19-F19 -> 152.8
A20: 42793 | B20: TARJETA | C20: FEBRERO | D20: G. ADM | F20: 54 | G20: =+G19+E20-F20 -> 98.8
A21: 42795 | B21: 12383 | C21: FEBRERO | D21: G. ADM | F21: 2 | G21: =+G20+E21-F21 -> 96.8
A22: 42795 | B22: 12383 | C22: FEBRERO | D22: P. SOCIAL | F22: 2 | G22: =+G21+E22-F22 -> 94.8
A23: 42821 | B23: 12533 | C23: FEBRERO | D23: LUZ | F23: 73.8 | G23: =+G22+E23-F23 -> 21
A24: 42821 | B24: 12533 | C24: FEBRERO | D24: AGUA | F24: 21 | G24: =+G23+E24-F24 -> 0
A25: 42825 | B25: POR COBRAR | C25: MARZO | D25: LUZ | E25: 70.6 | G25: =+G24+E25-F25 -> 70.6
D26: AGUA | E26: 22.9 | G26: =+G25+E26-F26 -> 93.5
D27: G. ADM | E27: 60 | G27: =+G26+E27-F27 -> 153.5
D28: P. SOCIAL | E28: 2 | G28: =+G27+E28-F28 -> 155.5
A29: 42824 | B29: TARJETA | C29: MARZO | D29: G. ADM | F29: 60 | G29: =+G28+E29-F29 -> 95.5
A30: 42824 | B30: TARJETA | C30: MARZO | D30: P. SOCIAL | F30: 2 | G30: =+G29+E30-F30 -> 93.5
A31: 42888 | B31: 13037 | C31: MARZO | D31: LUZ | F31: 70.6 | G31: =+G30+E31-F31 -> 22.9
A32: 42888 | B32: 13037 | C32: MARZO | D32: AGUA | F32: 22.9 | G32: =+G31+E32-F32 -> 0
A33: 42855 | B33: POR COBRAR | C33: ABRIL | D33: LUZ | E33: 72.1 | G33: =+G32+E33-F33 -> 72.1
D34: AGUA | E34: 22.5 | G34: =+G33+E34-F34 -> 94.6
D35: G. ADM | E35: 60 | G35: =+G34+E35-F35 -> 154.6
D36: P. SOCIAL | E36: 2 | G36: =+G35+E36-F36 -> 156.6
A37: 42855 | B37: TARJETA | C37: ABRIL | D37: G. ADM | F37: 60 | G37: =+G36+E37-F37 -> 96.6
A38: 42855 | B38: TARJETA | C38: ABRIL | D38: P. SOCIAL | F38: 2 | G38: =+G37+E38-F38 -> 94.6
A39: 42888 | B39: 13037 | C39: ABRIL | D39: LUZ | F39: 72.1 | G39: =+G38+E39-F39 -> 22.5
A40: 42888 | B40: 13037 | C40: ABRIL | D40: AGUA | F40: 22.5 | G40: =+G39+E40-F40 -> 0
A41: 42886 | B41: POR COBRAR | C41: MAYO | D41: LUZ | E41: 67.5 | G41: =+G40+E41-F41 -> 67.5
D42: AGUA | E42: 22 | G42: =+G41+E42-F42 -> 89.5
D43: G. ADM | E43: 60 | G43: =+G42+E43-F43 -> 149.5
D44: P. SOCIAL | E44: 2 | G44: =+G43+E44-F44 -> 151.5
A45: 42882 | B45: TARJETA | C45: MAYO | D45: G. ADM | F45: 60 | G45: =+G44+E45-F45 -> 91.5
A46: 42882 | B46: TARJETA | C46: MAYO | D46: P. SOCIAL | F46: 2 | G46: =+G45+E46-F46 -> 89.5
A47: 42920 | B47: 13182 | C47: MAYO | D47: LUZ | F47: 67.5 | G47: =+G46+E47-F47 -> 22
A48: 42920 | B48: 13182 | C48: MAYO | D48: AGUA | F48: 22 | G48: =+G47+E48-F48 -> 0
A49: 42916 | B49: POR COBRAR | C49: JUNIO | D49: LUZ | E49: 65.9 | G49: =+G48+E49-F49 -> 65.9
D50: AGUA | E50: 22 | G50: =+G49+E50-F50 -> 87.9
D51: G. ADM | E51: 60 | G51: =+G50+E51-F51 -> 147.9
D52: P. SOCIAL | E52: 2 | G52: =+G51+E52-F52 -> 149.9
A53: 42916 | B53: TARJETA | C53: JUNIO | D53: G. ADM | F53: 60 | G53: =+G52+E53-F53 -> 89.9
A54: 42916 | B54: TARJETA | C54: JUNIO | D54: P. SOCIAL | F54: 2 | G54: =+G53+E54-F54 -> 87.9
A55: 42942 | B55: 13258 | C55: JUNIO | D55: LUZ | F55: 65.9 | G55: =+G54+E55-F55 -> 22
A56: 42942 | B56: 13258 | C56: JUNIO | D56: AGUA | F56: 22 | G56: =+G55+E56-F56 -> 0
A57: 42947 | B57: POR COBRAR | C57: JULIO | D57: LUZ | E57: 59.8 | G57: =+G56+E57-F57 -> 59.8
D58: AGUA | E58: 22 | G58: =+G57+E58-F58 -> 81.8
D59: G. ADM | E59: 60 | G59: =+G58+E59-F59 -> 141.8
D60: P. SOCIAL | E60: 2 | G60: =+G59+E60-F60 -> 143.8
A61: 42945 | B61: TARJETA | C61: JULIO | D61: G. ADM | F61: 60 | G61: =+G60+E61-F61 -> 83.8
A62: 42945 | B62: TARJETA | C62: JULIO | D62: P. SOCIAL | F62: 2 | G62: =+G61+E62-F62 -> 81.8
A63: 42972 | B63: 13485 | C63: JULIO | D63: LUZ | F63: 59.8 | G63: =+G62+E63-F63 -> 22
A64: 42972 | B64: 13485 | C64: JULIO | D64: AGUA | F64: 22 | G64: =+G63+E64-F64 -> 0
A65: 42978 | B65: POR COBRAR | C65: AGOSTO | D65: LUZ | E65: 59.8 | G65: =+G64+E65-F65 -> 59.8
D66: AGUA | E66: 22 | G66: =+G65+E66-F66 -> 81.8
D67: G. ADM | E67: 60 | G67: =+G66+E67-F67 -> 141.8
D68: P. SOCIAL | E68: 2 | G68: =+G67+E68-F68 -> 143.8
D69: MULTA | E69: 85 | G69: =+G68+E69-F69 -> 228.8
A70: 42978 | B70: TARJETA | C70: AGOSTO | D70: G. ADM | F70: 60 | G70: =+G69+E70-F70 -> 168.8
A71: 42978 | B71: TARJETA | C71: AGOSTO | D71: P. SOCIAL | F71: 2 | G71: =+G70+E71-F71 -> 166.8
A72: 42997 | B72: 13607 | C72: AGOSTO | D72: LUZ | F72: 59.8 | G72: =+G71+E72-F72 -> 107
A73: 42997 | B73: 13607 | C73: AGOSTO | D73: AGUA | F73: 22 | G73: =+G72+E73-F73 -> 85
A74: 43001 | B74: 023-2017 | C74: AGOSTO | D74: MULTA | F74: 85 | G74: =+G73+E74-F74 -> 0
A75: 43008 | B75: POR COBRAR | C75: SEPTIEMBRE | D75: LUZ | E75: 50.3 | G75: =+G74+E75-F75 -> 50.3
D76: AGUA | E76: 22 | G76: =+G75+E76-F76 -> 72.3
D77: G. ADM | E77: 60 | G77: =+G76+E77-F77 -> 132.3
D78: P. SOCIAL | E78: 2 | G78: =+G77+E78-F78 -> 134.3
A79: 43008 | B79: TARJETA | C79: SEPTIEMBRE | D79: G. ADM | F79: 60 | G79: =+G78+E79-F79 -> 74.3
A80: 43008 | B80: TARJETA | C80: SEPTIEMBRE | D80: P. SOCIAL | F80: 2 | G80: =+G79+E80-F80 -> 72.3
A81: 43038 | B81: 13903 | C81: SEPTIEMBRE | D81: LUZ | F81: 50.3 | G81: =+G80+E81-F81 -> 22
A82: 43038 | B82: 13903 | C82: SEPTIEMBRE | D82: AGUA | F82: 22 | G82: =+G81+E82-F82 -> 0
A83: 43039 | B83: POR COBRAR | C83: OCTUBRE | D83: LUZ | E83: 50.1 | G83: =+G82+E83-F83 -> 50.1
D84: AGUA | E84: 22 | G84: =+G83+E84-F84 -> 72.1
D85: G. ADM | E85: 60 | G85: =+G84+E85-F85 -> 132.1
D86: P. SOCIAL | E86: 2 | G86: =+G85+E86-F86 -> 134.1
A87: 43039 | B87: TARJETA | C87: OCTUBRE | D87: G. ADM | F87: 60 | G87: =+G86+E87-F87 -> 74.1
A88: 43039 | B88: TARJETA | C88: OCTUBRE | D88: P. SOCIAL | F88: 2 | G88: =+G87+E88-F88 -> 72.1
A89: 43063 | B89: 14047 | C89: OCTUBRE | D89: LUZ | F89: 50.1 | G89: =+G88+E89-F89 -> 22
A90: 43063 | B90: 14047 | C90: OCTUBRE | D90: AGUA | F90: 22 | G90: =+G89+E90-F90 -> 0
A91: 43069 | B91: POR COBRAR | C91: NOVIEMBRE | D91: LUZ | E91: 53.4 | G91: =+G90+E91-F91 -> 53.4
D92: AGUA | E92: 22 | G92: =+G91+E92-F92 -> 75.4
D93: G. ADM | E93: 60 | G93: =+G92+E93-F93 -> 135.4
D94: P. SOCIAL | E94: 2 | G94: =+G93+E94-F94 -> 137.4
A95: 43088 | B95: 14322 | C95: NOVIEMBRE | D95: LUZ | F95: 53.4 | G95: =+G94+E95-F95 -> 84
A96: 43088 | B96: 14322 | C96: NOVIEMBRE | D96: AGUA | F96: 22 | G96: =+G95+E96-F96 -> 62
A97: 43069 | B97: TARJETA | C97: NOVIEMBRE | D97: G. ADM | F97: 60 | G97: =+G96+E97-F97 -> 2
A98: 43069 | B98: TARJETA | C98: NOVIEMBRE | D98: P. SOCIAL | F98: 2 | G98: =+G97+E98-F98 -> 0
A99: 43100 | B99: POR COBRAR | C99: DICIEMBRE | D99: LUZ | E99: 58.1 | G99: =+G98+E99-F99 -> 58.1
D100: AGUA | E100: 22 | G100: =+G99+E100-F100 -> 80.1
D101: G. ADM | E101: 60 | G101: =+G100+E101-F101 -> 140.1
D102: P. SOCIAL | E102: 2 | G102: =+G101+E102-F102 -> 142.1
...

Sheet PALOMINO SILVIO
B2: PALOMINO TENORIO SILVIO EDUARDO
A4: FECHA | B4: DOCUMENTO | C4: PERIODO | D4: CONCEPTO | E4: POR COBRAR | F4: PAGADO | G4: SALDO POR COBRAR
A5: 42736 | B5: SALDO AL 2016 | G5: 354
A6: 42781 | B6: 12952 | C6: A CUENTAS 2016 | F6: 274 | G6: =+G5+E6-F6 -> 80
A7: 43060 | B7: 10214 | C7: CANCELACION 2016 | F7: 80 | G7: =+G6+E7-F7 -> 0
A8: 42766 | B8: POR COBRAR | C8: ENERO | D8: LUZ | E8: 94.3 | G8: =+G7+E8-F8 -> 94.3
D9: AGUA | E9: 61 | G9: =+G8+E9-F9 -> 155.3
D10: G. ADM | E10: 60 | G10: =+G9+E10-F10 -> 215.3
D11: P. SOCIAL | E11: 2 | G11: =+G10+E11-F11 -> 217.3
D12: MULTA P. SEPTICO | E12: 100 | G12: =+G11+E12-F12 -> 317.3
A13: 42765 | B13: TARJETA | C13: ENERO | D13: G. ADM | F13: 60 | G13: =+G12+E13-F13 -> 257.3
A14: 42765 | B14: TARJETA | C14: ENERO | D14: P. SOCIAL | F14: 2 | G14: =+G13+E14-F14 -> 255.3
A15: 42784 | B15: 12992 | C15: ENERO | D15: MULTA P. SEPTICO | F15: 100 | G15: =+G14+E15-F15 -> 155.3
A16: 42784 | B16: 12993 | C16: ENERO | D16: LUZ | F16: 94.3 | G16: =+G15+E16-F16 -> 61
A17: 42784 | B17: 12993 | C17: ENERO | D17: AGUA | F17: 61 | G17: =+G16+E17-F17 -> 0
A18: 42794 | B18: POR COBRAR | C18: FEBRERO | D18: LUZ | E18: 102.5 | G18: =+G17+E18-F18 -> 102.5
D19: AGUA | E19: 43 | G19: =+G18+E19-F19 -> 145.5
D20: G. ADM | E20: 56 | G20: =+G19+E20-F20 -> 201.5
D21: P. SOCIAL | E21: 2 | G21: =+G20+E21-F21 -> 203.5
A22: 42794 | B22: TARJETA | C22: FEBRERO | D22: G. ADM | F22: 56 | G22: =+G21+E22-F22 -> 147.5
A23: 42794 | B23: TARJETA | C23: FEBRERO | D23: P. SOCIAL | F23: 2 | G23: =+G22+E23-F23 -> 145.5
A24: 42822 | B24: 12578 | C24: FEBRERO | D24: LUZ | F24: 102.5 | G24: =+G23+E24-F24 -> 43
A25: 42822 | B25: 12578 | C25: FEBRERO | D25: AGUA | F25: 43 | G25: =+G24+E25-F25 -> 0
A26: 42825 | B26: POR COBRAR | C26: MARZO | D26: LUZ | E26: 98.3 | G26: =+G25+E26-F26 -> 98.3
D27: AGUA | E27: 44.7 | G27: =+G26+E27-F27 -> 143
D28: G. ADM | E28: 60 | G28: =+G27+E28-F28 -> 203
D29: P. SOCIAL | E29: 2 | G29: =+G28+E29-F29 -> 205
A30: 42824 | B30: TARJETA | C30: MARZO | D30: G. ADM | F30: 60 | G30: =+G29+E30-F30 -> 145
A31: 42824 | B31: TARJETA | C31: MARZO | D31: P. SOCIAL | F31: 2 | G31: =+G30+E31-F31 -> 143
A32: 42850 | B32: 12697 | C32: MARZO | D32: LUZ | F32: 98.3 | G32: =+G31+E32-F32 -> 44.7
A33: 42850 | B33: 12697 | C33: MARZO | D33: AGUA | F33: 44.7 | G33: =+G32+E33-F33 -> 0
A34: 42855 | B34: POR COBRAR | C34: ABRIL | D34: LUZ | E34: 100.1 | G34: =+G33+E34-F34 -> 100.1
D35: AGUA | E35: 44 | G35: =+G34+E35-F35 -> 144.1
D36: G. ADM | E36: 60 | G36: =+G35+E36-F36 -> 204.1
D37: P. SOCIAL | E37: 2 | G37: =+G36+E37-F37 -> 206.1
A38: 42855 | B38: TARJETA | C38: ABRIL | D38: G. ADM | F38: 60 | G38: =+G37+E38-F38 -> 146.1
A39: 42855 | B39: TARJETA | C39: ABRIL | D39: P. SOCIAL | F39: 2 | G39: =+G38+E39-F39 -> 144.1
A40: 42877 | B40: 12797 | C40: ABRIL | D40: LUZ | F40: 100.1 | G40: =+G39+E40-F40 -> 44
A41: 42877 | B41: 12797 | C41: ABRIL | D41: AGUA | F41: 44 | G41: =+G40+E41-F41 -> 0
A42: 42886 | B42: POR COBRAR | C42: MAYO | D42: LUZ | E42: 60.5 | G42: =+G41+E42-F42 -> 60.5
D43: AGUA | E43: 43 | G43: =+G42+E43-F43 -> 103.5
D44: G. ADM | E44: 60 | G44: =+G43+E44-F44 -> 163.5
D45: P. SOCIAL | E45: 2 | G45: =+G44+E45-F45 -> 165.5
A46: 42886 | B46: TARJETA | C46: MAYO | D46: G. ADM | F46: 60 | G46: =+G45+E46-F46 -> 105.5
A47: 42886 | B47: TARJETA | C47: MAYO | D47: P. SOCIAL | F47: 2 | G47: =+G46+E47-F47 -> 103.5
A48: 42909 | B48: 13142 | C48: MAYO | D48: LUZ | F48: 60.5 | G48: =+G47+E48-F48 -> 43
A49: 42909 | B49: 13142 | C49: MAYO | D49: AGUA | F49: 43 | G49: =+G48+E49-F49 -> 0
A50: 42916 | B50: POR COBRAR | C50: JUNIO | D50: LUZ | E50: 59.1 | G50: =+G49+E50-F50 -> 59.1
D51: AGUA | E51: 43 | G51: =+G50+E51-F51 -> 102.1
D52: G. ADM | E52: 60 | G52: =+G51+E52-F52 -> 162.1
D53: P. SOCIAL | E53: 2 | G53: =+G52+E53-F53 -> 164.1
A54: 42916 | B54: TARJETA | C54: JUNIO | D54: G. ADM | F54: 50 | G54: =+G53+E54-F54 -> 114.1
A55: 42940 | B55: 13237 | C55: JUNIO | D55: AGUA | F55: 43 | G55: =+G54+E55-F55 -> 71.1
A56: 42940 | B56: 13237 | C56: JUNIO | D56: LUZ | F56: 59.1 | G56: =+G55+E56-F56 -> 12
A57: 42949 | B57: 13363 | C57: JUNIO | D57: G. ADM | F57: 10 | G57: =+G56+E57-F57 -> 2
A58: 42949 | B58: 13363 | C58: JUNIO | D58: P. SOCIAL | F58: 2 | G58: =+G57+E58-F58 -> -7.1054274e-15
A59: 42947 | B59: POR COBRAR | C59: JULIO | D59: LUZ | E59: 70.8 | G59: =+G58+E59-F59 -> 70.8
D60: AGUA | E60: 43 | G60: =+G59+E60-F60 -> 113.8
D61: G. ADM | E61: 60 | G61: =+G60+E61-F61 -> 173.8
D62: P. SOCIAL | E62: 2 | G62: =+G61+E62-F62 -> 175.8
A63: 42945 | B63: TARJETA | C63: JULIO | D63: G. ADM | F63: 60 | G63: =+G62+E63-F63 -> 115.8
A64: 42945 | B64: TARJETA | C64: JULIO | D64: P. SOCIAL | F64: 2 | G64: =+G63+E64-F64 -> 113.8
A65: 42971 | B65: 13470 | C65: JULIO | D65: LUZ | F65: 70.8 | G65: =+G64+E65-F65 -> 43
A66: 42971 | B66: 13470 | C66: JULIO | D66: AGUA | F66: 43 | G66: =+G65+E66-F66 -> 0
A67: 42978 | B67: POR COBRAR | C67: AGOSTO | D67: LUZ | E67: 70.8 | G67: =+G66+E67-F67 -> 70.8
D68: AGUA | E68: 43 | G68: =+G67+E68-F68 -> 113.8
D69: G. ADM | E69: 60 | G69: =+G68+E69-F69 -> 173.8
D70: P. SOCIAL | E70: 2 | G70: =+G69+E70-F70 -> 175.8
A71: 42978 | B71: TARJETA | C71: AGOSTO | D71: G. ADM | F71: 60 | G71: =+G70+E71-F71 -> 115.8
A72: 42978 | B72: TARJETA | C72: AGOSTO | D72: P. SOCIAL | F72: 2 | G72: =+G71+E72-F72 -> 113.8
A73: 43003 | B73: 13674 | C73: AGOSTO | D73: LUZ | F73: 70.8 | G73: =+G72+E73-F73 -> 43
A74: 43003 | B74: 13674 | C74: AGOSTO | D74: AGUA | F74: 43 | G74: =+G73+E74-F74 -> 0
A75: 43008 | B75: POR COBRAR | C75: SEPTIEMBRE | D75: LUZ | E75: 68.7 | G75: =+G74+E75-F75 -> 68.7
D76: AGUA | E76: 28.3 | G76: =+G75+E76-F76 -> 97
D77: G. ADM | E77: 60 | G77: =+G76+E77-F77 -> 157
D78: P. SOCIAL | E78: 2 | G78: =+G77+E78-F78 -> 159
A79: 43008 | B79: TARJETA | C79: SEPTIEMBRE | D79: G. ADM | F79: 60 | G79: =+G78+E79-F79 -> 99
A80: 43008 | B80: TARJETA | C80: SEPTIEMBRE | D80: P. SOCIAL | F80: 2 | G80: =+G79+E80-F80 -> 97
A81: 43032 | B81: 13879 | C81: SEPTIEMBRE | D81: LUZ | F81: 68.7 | G81: =+G80+E81-F81 -> 28.3
A82: 43032 | B82: 13879 | C82: SEPTIEMBRE | D82: AGUA | F82: 28.3 | G82: =+G81+E82-F82 -> 0
A83: 43039 | B83: POR COBRAR | C83: OCTUBRE | D83: LUZ | E83: 68.3 | G83: =+G82+E83-F83 -> 68.3
D84: AGUA | E84: 43 | G84: =+G83+E84-F84 -> 111.3
D85: G. ADM | E85: 60 | G85: =+G84+E85-F85 -> 171.3
D86: P. SOCIAL | E86: 2 | G86: =+G85+E86-F86 -> 173.3
D87: FUMIGACION | E87: 10 | G87: =+G86+E87-F87 -> 183.3
A88: 43039 | B88: TARJETA | C88: OCTUBRE | D88: G. ADM | F88: 60 | G88: =+G87+E88-F88 -> 123.3
A89: 43039 | B89: TARJETA | C89: OCTUBRE | D89: P. SOCIAL | F89: 2 | G89: =+G88+E89-F89 -> 121.3
A90: 43066 | B90: 14113 | C90: OCTUBRE | D90: LUZ | F90: 68.3 | G90: =+G89+E90-F90 -> 53
A91: 43066 | B91: 14113 | C91: OCTUBRE | D91: AGUA | F91: 43 | G91: =+G90+E91-F91 -> 10
A92: 42921 | B92: 5680 | C92: OCTUBRE | D92: FUMIGACION | F92: 10 | G92: =+G91+E92-F92 -> 1.4210855e-14
A93: 43069 | B93: POR COBRAR | C93: NOVIEMBRE | D93: LUZ | E93: 72.9 | G93: =+G92+E93-F93 -> 72.9
D94: AGUA | E94: 43 | G94: =+G93+E94-F94 -> 115.9
D95: G. ADM | E95: 60 | G95: =+G94+E95-F95 -> 175.9
D96: P. SOCIAL | E96: 2 | G96: =+G95+E96-F96 -> 177.9
A97: 43095 | B97: 14347 | C97: NOVIEMBRE | D97: LUZ | F97: 72.9 | G97: =+G96+E97-F97 -> 105
A98: 43095 | B98: 14347 | C98: NOVIEMBRE | D98: AGUA | F98: 43 | G98: =+G97+E98-F98 -> 62
A99: 43069 | B99: TARJETA | C99: NOVIEMBRE | D99: G. ADM | F99: 50 | G99: =+G98+E99-F99 -> 12
A100: 43180 | B100: 14876 | C100: NOVIEMBRE | D100: G. ADM | F100: 10 | G100: =+G99+E100-F100 -> 2
A101: 43180 | B101: 14876 | C101: NOVIEMBRE | D101: P. SOCIAL | F101: 2 | G101: =+G100+E101-F101 -> 2.8421709e-14
A102: 43100 | B102: POR COBRAR | C102: DICIEMBRE | D102: LUZ | E102: 79.3 | G102: =+G101+E102-F102 -> 79.3
...

Sheet PALOMINO EUSEBIO
B2: PALOMINO VELASQUEZ EUSEBIO
A4: FECHA | B4: DOCUMENTO | C4: PERIODO | D4: CONCEPTO | E4: POR COBRAR | F4: PAGADO | G4: SALDO POR COBRAR
A5: 42736 | B5: SALDO AL 2016 | G5: 448.2
A6: 42740 | B6: 12071 | C6: A CUENTA 2016 | F6: 199.5 | G6: =+G5+E6-F6 -> 248.7
A7: 42787 | B7: 12351 | C7: A CUENTA 2016 | F7: 168.7 | G7: =+G6+E7-F7 -> 80
A8: 43067 | B8: 14149 | C8: CANCELACION 2016 | F8: 80 | G8: =+G7+E8-F8 -> 0
A9: 42766 | B9: POR COBRAR | C9: ENERO | D9: LUZ | E9: 144.3 | G9: =+G8+E9-F9 -> 144.3
D10: AGUA | E10: 19.1 | G10: =+G9+E10-F10 -> 163.4
D11: G. ADM | E11: 60 | G11: =+G10+E11-F11 -> 223.4
D12: P. SOCIAL | E12: 2 | G12: =+G11+E12-F12 -> 225.4
A13: 42765 | B13: TARJETA | C13: ENERO | D13: G. ADM | F13: 60 | G13: =+G12+E13-F13 -> 165.4
A14: 42765 | B14: TARJETA | C14: ENERO | D14: P. SOCIAL | F14: 2 | G14: =+G13+E14-F14 -> 163.4
A15: 42787 | B15: 12356 | C15: ENERO | D15: LUZ | F15: 144.3 | G15: =+G14+E15-F15 -> 19.1
A16: 42787 | B16: 12356 | C16: ENERO | D16: AGUA | F16: 19.1 | G16: =+G15+E16-F16 -> 0
A17: 42794 | B17: POR COBRAR | C17: FEBRERO | D17: LUZ | E17: 171 | G17: =+G16+E17-F17 -> 171
D18: AGUA | E18: 13 | G18: =+G17+E18-F18 -> 184
D19: G. ADM | E19: 56 | G19: =+G18+E19-F19 -> 240
D20: P. SOCIAL | E20: 2 | G20: =+G19+E20-F20 -> 242
A21: 42794 | B21: TARJETA | C21: FEBRERO | D21: G. ADM | F21: 56 | G21: =+G20+E21-F21 -> 186
A22: 42794 | B22: TARJETA | C22: FEBRERO | D22: P. SOCIAL | F22: 2 | G22: =+G21+E22-F22 -> 184
A23: 42822 | B23: 12591 | C23: FEBRERO | D23: LUZ | F23: 171 | G23: =+G22+E23-F23 -> 13
A24: 42822 | B24: 12591 | C24: FEBRERO | D24: AGUA | F24: 13 | G24: =+G23+E24-F24 -> 0
A25: 42825 | B25: POR COBRAR | C25: MARZO | D25: LUZ | E25: 164.3 | G25: =+G24+E25-F25 -> 164.3
D26: AGUA | E26: 14 | G26: =+G25+E26-F26 -> 178.3
D27: G. ADM | E27: 60 | G27: =+G26+E27-F27 -> 238.3
D28: P. SOCIAL | E28: 2 | G28: =+G27+E28-F28 -> 240.3
A29: 42824 | B29: TARJETA | C29: MARZO | D29: G. ADM | F29: 60 | G29: =+G28+E29-F29 -> 180.3
A30: 42824 | B30: TARJETA | C30: MARZO | D30: P. SOCIAL | F30: 2 | G30: =+G29+E30-F30 -> 178.3
A31: 42887 | B31: 13027 | C31: MARZO | D31: LUZ | F31: 164.3 | G31: =+G30+E31-F31 -> 14
A32: 42887 | B32: 13027 | C32: MARZO | D32: AGUA | F32: 14 | G32: =+G31+E32-F32 -> 0
A33: 42855 | B33: POR COBRAR | C33: ABRIL | D33: LUZ | E33: 166.7 | G33: =+G32+E33-F33 -> 166.7
D34: AGUA | E34: 13.7 | G34: =+G33+E34-F34 -> 180.4
D35: G. ADM | E35: 60 | G35: =+G34+E35-F35 -> 240.4
D36: P. SOCIAL | E36: 2 | G36: =+G35+E36-F36 -> 242.4
A37: 42842 | B37: TARJETA | C37: ABRIL | D37: G. ADM | F37: 34 | G37: =+G36+E37-F37 -> 208.4
A38: 42892 | B38: 13073 | C38: ABRIL | D38: LUZ | F38: 166.7 | G38: =+G37+E38-F38 -> 41.7
A39: 42892 | B39: 13073 | C39: ABRIL | D39: AGUA | F39: 13.7 | G39: =+G38+E39-F39 -> 28
A40: 42949 | B40: 13384 | C40: ABRIL | D40: G. ADM | F40: 26 | G40: =+G39+E40-F40 -> 2
A41: 42949 | B41: 13384 | C41: ABRIL | D41: P. SOCIAL | F41: 2 | G41: =+G40+E41-F41 -> -1.0658141e-14
A42: 42886 | B42: POR COBRAR | C42: MAYO | D42: LUZ | E42: 154.6 | G42: =+G41+E42-F42 -> 154.6
D43: AGUA | E43: 13.4 | G43: =+G42+E43-F43 -> 168
D44: G. ADM | E44: 60 | G44: =+G43+E44-F44 -> 228
D45: P. SOCIAL | E45: 2 | G45: =+G44+E45-F45 -> 230
A46: 42886 | B46: TARJETA | C46: MAYO | D46: G. ADM | F46: 60 | G46: =+G45+E46-F46 -> 170
A47: 42886 | B47: TARJETA | C47: MAYO | D47: P. SOCIAL | F47: 2 | G47: =+G46+E47-F47 -> 168
A48: 42949 | B48: 13384 | C48: MAYO | D48: LUZ | F48: 154.6 | G48: =+G47+E48-F48 -> 13.4
A49: 42949 | B49: 13384 | C49: MAYO | D49: AGUA | F49: 13.4 | G49: =+G48+E49-F49 -> 0
A50: 42916 | B50: POR COBRAR | C50: JUNIO | D50: LUZ | E50: 151.4 | G50: =+G49+E50-F50 -> 151.4
D51: AGUA | E51: 14 | G51: =+G50+E51-F51 -> 165.4
D52: G. ADM | E52: 60 | G52: =+G51+E52-F52 -> 225.4
D53: P. SOCIAL | E53: 2 | G53: =+G52+E53-F53 -> 227.4
A54: 42916 | B54: TARJETA | C54: JUNIO | D54: G. ADM | F54: 60 | G54: =+G53+E54-F54 -> 167.4
A55: 42916 | B55: TARJETA | C55: JUNIO | D55: P. SOCIAL | F55: 2 | G55: =+G54+E55-F55 -> 165.4
A56: 42949 | B56: 13384 | C56: JUNIO | D56: LUZ | F56: 151.4 | G56: =+G55+E56-F56 -> 14
A57: 42949 | B57: 13384 | C57: JUNIO | D57: AGUA | F57: 14 | G57: =+G56+E57-F57 -> 0
A58: 42947 | B58: POR COBRAR | C58: JULIO | D58: LUZ | E58: 134.6 | G58: =+G57+E58-F58 -> 134.6
D59: AGUA | E59: 13.5 | G59: =+G58+E59-F59 -> 148.1
D60: G. ADM | E60: 60 | G60: =+G59+E60-F60 -> 208.1
D61: P. SOCIAL | E61: 2 | G61: =+G60+E61-F61 -> 210.1
A62: 42947 | B62: TARJETA | C62: JULIO | D62: G. ADM | F62: 60 | G62: =+G61+E62-F62 -> 150.1
A63: 42947 | B63: TARJETA | C63: JULIO | D63: P. SOCIAL | F63: 2 | G63: =+G62+E63-F63 -> 148.1
A64: 42992 | B64: 13577 | C64: JULIO | D64: LUZ | F64: 134.6 | G64: =+G63+E64-F64 -> 13.5
A65: 42992 | B65: 13577 | C65: JULIO | D65: AGUA | F65: 13.5 | G65: =+G64+E65-F65 -> 0
A66: 42978 | B66: POR COBRAR | C66: AGOSTO | D66: LUZ | E66: 134.6 | G66: =+G65+E66-F66 -> 134.6
D67: AGUA | E67: 13.5 | G67: =+G66+E67-F67 -> 148.1
D68: G. ADM | E68: 60 | G68: =+G67+E68-F68 -> 208.1
D69: P. SOCIAL | E69: 2 | G69: =+G68+E69-F69 -> 210.1
A70: 42978 | B70: TARJETA | C70: AGOSTO | D70: G. ADM | F70: 60 | G70: =+G69+E70-F70 -> 150.1
A71: 42978 | B71: TARJETA | C71: AGOSTO | D71: P. SOCIAL | F71: 2 | G71: =+G70+E71-F71 -> 148.1
A72: 43045 | B72: 13932 | C72: AGOSTO | D72: LUZ | F72: 134.6 | G72: =+G71+E72-F72 -> 13.5
A73: 43045 | B73: 13932 | C73: AGOSTO | D73: AGUA | F73: 13.5 | G73: =+G72+E73-F73 -> 0
A74: 43008 | B74: POR COBRAR | C74: SEPTIEMBRE | D74: LUZ | E74: 69.6 | G74: =+G73+E74-F74 -> 69.6
D75: AGUA | E75: 13.4 | G75: =+G74+E75-F75 -> 83
D76: G. ADM | E76: 60 | G76: =+G75+E76-F76 -> 143
D77: P. SOCIAL | E77: 2 | G77: =+G76+E77-F77 -> 145
A78: 43008 | B78: TARJETA | C78: SEPTIEMBRE | D78: G. ADM | F78: 28 | G78: =+G77+E78-F78 -> 117
A79: 43045 | B79: 13932 | C79: SEPTIEMBRE | D79: G. ADM | F79: 32 | G79: =+G78+E79-F79 -> 85
A80: 43045 | B80: 13932 | C80: SEPTIEMBRE | D80: P. SOCIAL | F80: 2 | G80: =+G79+E80-F80 -> 83
A81: 43064 | B81: 14091 | C81: SEPTIEMBRE | D81: LUZ | F81: 69.6 | G81: =+G80+E81-F81 -> 13.4
A82: 43064 | B82: 14091 | C82: SEPTIEMBRE | D82: AGUA | F82: 13.4 | G82: =+G81+E82-F82 -> 0
A83: 43039 | B83: POR COBRAR | C83: OCTUBRE | D83: LUZ | E83: 69.3 | G83: =+G82+E83-F83 -> 69.3
D84: AGUA | E84: 13.5 | G84: =+G83+E84-F84 -> 82.8
D85: G. ADM | E85: 60 | G85: =+G84+E85-F85 -> 142.8
D86: P. SOCIAL | E86: 2 | G86: =+G85+E86-F86 -> 144.8
A87: 43039 | B87: TARJETA | C87: OCTUBRE | D87: G. ADM | F87: 60 | G87: =+G86+E87-F87 -> 84.8
A88: 43039 | B88: TARJETA | C88: OCTUBRE | D88: P. SOCIAL | F88: 2 | G88: =+G87+E88-F88 -> 82.8
A89: 43067 | B89: 14133 | C89: OCTUBRE | D89: LUZ | F89: 69.3 | G89: =+G88+E89-F89 -> 13.5
A90: 43067 | B90: 14133 | C90: OCTUBRE | D90: AGUA | F90: 13.5 | G90: =+G89+E90-F90 -> 1.4210855e-14
A91: 43069 | B91: POR COBRAR | C91: NOVIEMBRE | D91: LUZ | E91: 74 | G91: =+G90+E91-F91 -> 74
D92: AGUA | E92: 13.5 | G92: =+G91+E92-F92 -> 87.5
D93: G. ADM | E93: 60 | G93: =+G92+E93-F93 -> 147.5
D94: P. SOCIAL | E94: 2 | G94: =+G93+E94-F94 -> 149.5
A95: 43099 | B95: 14372 | C95: NOVIEMBRE | D95: LUZ | F95: 74 | G95: =+G94+E95-F95 -> 75.5
A96: 43099 | B96: 14372 | C96: NOVIEMBRE | D96: AGUA | F96: 13.5 | G96: =+G95+E96-F96 -> 62
A97: 43069 | B97: TARJETA | C97: NOVIEMBRE | D97: G. ADM | F97: 60 | G97: =+G96+E97-F97 -> 2
A98: 43069 | B98: TARJETA | C98: NOVIEMBRE | D98: P. SOCIAL | F98: 2 | G98: =+G97+E98-F98 -> 0
A99: 43100 | B99: POR COBRAR | C99: DICIEMBRE | D99: LUZ | E99: 80.4 | G99: =+G98+E99-F99 -> 80.4
D100: AGUA | E100: 13.4 | G100: =+G99+E100-F100 -> 93.8
D101: G. ADM | E101: 60 | G101: =+G100+E101-F101 -> 153.8
D102: P. SOCIAL | E102: 2 | G102: =+G101+E102-F102 -> 155.8
...

Sheet PAREDES FLORES OSCAR
B2: PAREDES FLORES OSCAR
A4: FECHA | B4: DOCUMENTO | C4: PERIODO | D4: CONCEPTO | E4: POR COBRAR | F4: PAGADO | G4: SALDO POR COBRAR
A5: 42736 | B5: SALDO AL 2016 | G5: 231.7
A6: 42782 | B6: 12964 | C6: A CUENTA 2016 | F6: 62 | G6: =+G5+E6-F6 -> 169.7
A7: 42782 | B7: 12965 | C7: A CUENTA 2016 | F7: 169.7 | G7: =+G6+E7-F7 -> 0
A8: 42766 | B8: POR COBRAR | C8: ENERO | D8: LUZ | E8: 199.2 | G8: =+G7+E8-F8 -> 199.2
D9: AGUA | E9: 2.8 | G9: =+G8+E9-F9 -> 202
D10: G. ADM | E10: 60 | G10: =+G9+E10-F10 -> 262
D11: P. SOCIAL | E11: 2 | G11: =+G10+E11-F11 -> 264
A12: 42786 | B12: 12216 | C12: ENERO | D12: G. ADM | F12: 60 | G12: =+G11+E12-F12 -> 204
A13: 42786 | B13: 12216 | C13: ENERO | D13: P. SOCIAL | F13: 2 | G13: =+G12+E13-F13 -> 202
A14: 42786 | B14: 12282 | C14: ENERO | D14: AGUA | F14: 2.8 | G14: =+G13+E14-F14 -> 199.2
A15: 42786 | B15: 12282 | C15: ENERO | D15: LUZ | F15: 199.2 | G15: =+G14+E15-F15 -> 0
A16: 42794 | B16: POR COBRAR | C16: FEBRERO | D16: LUZ | E16: 213.9 | G16: =+G15+E16-F16 -> 213.9
D17: AGUA | E17: 2 | G17: =+G16+E17-F17 -> 215.9
D18: G. ADM | E18: 56 | G18: =+G17+E18-F18 -> 271.9
D19: P. SOCIAL | E19: 2 | G19: =+G18+E19-F19 -> 273.9
A20: 42818 | B20: 12458 | C20: FEBRERO | D20: G. ADM | F20: 56 | G20: =+G19+E20-F20 -> 217.9
A21: 42818 | B21: 12458 | C21: FEBRERO | D21: P. SOCIAL | F21: 2 | G21: =+G20+E21-F21 -> 215.9
A22: 42821 | B22: 12567 | C22: FEBRERO | D22: AGUA | F22: 2 | G22: =+G21+E22-F22 -> 213.9
A23: 42821 | B23: 12567 | C23: FEBRERO | D23: LUZ | F23: 213.9 | G23: =+G22+E23-F23 -> 0
A24: 42825 | B24: POR COBRAR | C24: MARZO | D24: LUZ | E24: 194.4 | G24: =+G23+E24-F24 -> 194.4
D25: AGUA | E25: 2 | G25: =+G24+E25-F25 -> 196.4
D26: G. ADM | E26: 60 | G26: =+G25+E26-F26 -> 256.4
D27: P. SOCIAL | E27: 2 | G27: =+G26+E27-F27 -> 258.4
A28: 42874 | B28: 12783 | C28: MARZO | D28: LUZ | F28: 194.4 | G28: =+G27+E28-F28 -> 64
A29: 42874 | B29: 12783 | C29: MARZO | D29: AGUA | F29: 2 | G29: =+G28+E29-F29 -> 62
A30: 42938 | B30: 13235 | C30: MARZO | D30: P. SOCIAL | F30: 2 | G30: =+G29+E30-F30 -> 60
A31: 42938 | B31: 13235 | C31: MARZO | D31: G. ADM | F31: 60 | G31: =+G30+E31-F31 -> 0
A32: 42855 | B32: POR COBRAR | C32: ABRIL | D32: LUZ | E32: 146.4 | G32: =+G31+E32-F32 -> 146.4
D33: AGUA | E33: 2 | G33: =+G32+E33-F33 -> 148.4
D34: G. ADM | E34: 60 | G34: =+G33+E34-F34 -> 208.4
D35: P. SOCIAL | E35: 2 | G35: =+G34+E35-F35 -> 210.4
A36: 42891 | B36: 13053 | C36: ABRIL | D36: LUZ | F36: 146.4 | G36: =+G35+E36-F36 -> 64
A37: 42891 | B37: 13053 | C37: ABRIL | D37: AGUA | F37: 2 | G37: =+G36+E37-F37 -> 62
A38: 42937 | B38: 13232 | C38: ABRIL | D38: G. ADM | F38: 60 | G38: =+G37+E38-F38 -> 2
A39: 42937 | B39: 13232 | C39: ABRIL | D39: P. SOCIAL | F39: 2 | G39: =+G38+E39-F39 -> 0
A40: 42886 | B40: POR COBRAR | C40: MAYO | D40: LUZ | E40: 168.6 | G40: =+G39+E40-F40 -> 168.6
D41: AGUA | E41: 2 | G41: =+G40+E41-F41 -> 170.6
D42: G. ADM | E42: 60 | G42: =+G41+E42-F42 -> 230.6
D43: P. SOCIAL | E43: 2 | G43: =+G42+E43-F43 -> 232.6
A44: 42926 | B44: 13189 | C44: MAYO | D44: LUZ | F44: 168.6 | G44: =+G43+E44-F44 -> 64
A45: 42926 | B45: 13189 | C45: MAYO | D45: AGUA | F45: 2 | G45: =+G44+E45-F45 -> 62
A46: 42940 | B46: 13240 | C46: MAYO | D46: G. ADM | F46: 60 | G46: =+G45+E46-F46 -> 2
A47: 42940 | B47: 13240 | C47: MAYO | D47: P. SOCIAL | F47: 2 | G47: =+G46+E47-F47 -> 0
A48: 42916 | B48: POR COBRAR | C48: JUNIO | D48: LUZ | E48: 180.4 | G48: =+G47+E48-F48 -> 180.4
D49: AGUA | E49: 2 | G49: =+G48+E49-F49 -> 182.4
D50: G. ADM | E50: 60 | G50: =+G49+E50-F50 -> 242.4
D51: P. SOCIAL | E51: 2 | G51: =+G50+E51-F51 -> 244.4
A52: 42940 | B52: 13246 | C52: JUNIO | D52: G. ADM | F52: 60 | G52: =+G51+E52-F52 -> 184.4
A53: 42940 | B53: 13246 | C53: JUNIO | D53: P. SOCIAL | F53: 2 | G53: =+G52+E53-F53 -> 182.4
A54: 42943 | B54: 13275 | C54: JUNIO | D54: LUZ | F54: 180.4 | G54: =+G53+E54-F54 -> 2
A55: 42943 | B55: 13275 | C55: JUNIO | D55: AGUA | F55: 2 | G55: =+G54+E55-F55 -> 0
A56: 42946 | B56: POR COBRAR | C56: JULIO | D56: LUZ | E56: 162 | G56: =+G55+E56-F56 -> 162
D57: AGUA | E57: 2 | G57: =+G56+E57-F57 -> 164
D58: G. ADM | E58: 60 | G58: =+G57+E58-F58 -> 224
D59: P. SOCIAL | E59: 2 | G59: =+G58+E59-F59 -> 226
A60: 42942 | B60: 13261 | C60: JULIO | D60: G. ADM | F60: 60 | G60: =+G59+E60-F60 -> 166
A61: 42942 | B61: 13261 | C61: JULIO | D61: P. SOCIAL | F61: 2 | G61: =+G60+E61-F61 -> 164
A62: 42992 | B62: 13575 | C62: JULIO | D62: LUZ | F62: 162 | G62: =+G61+E62-F62 -> 2
A63: 42992 | B63: 13575 | C63: JULIO | D63: AGUA | F63: 2 | G63: =+G62+E63-F63 -> 0
A64: 42978 | B64: POR COBRAR | C64: AGOSTO | D64: LUZ | E64: 162 | G64: =+G63+E64-F64 -> 162
D65: AGUA | E65: 2 | G65: =+G64+E65-F65 -> 164
D66: G. ADM | E66: 60 | G66: =+G65+E66-F66 -> 224
D67: P. SOCIAL | E67: 2 | G67: =+G66+E67-F67 -> 226
A68: 43012 | B68: 13794 | C68: AGOSTO | D68: LUZ | F68: 162 | G68: =+G67+E68-F68 -> 64
A69: 43012 | B69: 13794 | C69: AGOSTO | D69: AGUA | F69: 2 | G69: =+G68+E69-F69 -> 62
A70: 43053 | B70: 13976 | C70: AGOSTO | D70: G. ADM | F70: 60 | G70: =+G69+E70-F70 -> 2
A71: 43053 | B71: 13976 | C71: AGOSTO | D71: P. SOCIAL | F71: 2 | G71: =+G70+E71-F71 -> 0
A72: 43008 | B72: POR COBRAR | C72: SEPTIEMBRE | D72: LUZ | E72: 152.8 | G72: =+G71+E72-F72 -> 152.8
D73: AGUA | E73: 2 | G73: =+G72+E73-F73 -> 154.8
D74: G. ADM | E74: 60 | G74: =+G73+E74-F74 -> 214.8
D75: P. SOCIAL | E75: 2 | G75: =+G74+E75-F75 -> 216.8
A76: 43053 | B76: 13976 | C76: SEPTIEMBRE | D76: G. ADM | F76: 60 | G76: =+G75+E76-F76 -> 156.8
A77: 43053 | B77: 13976 | C77: SEPTIEMBRE | D77: P. SOCIAL | F77: 2 | G77: =+G76+E77-F77 -> 154.8
A78: 43059 | B78: 13997 | C78: SEPTIEMBRE | D78: LUZ | F78: 152.8 | G78: =+G77+E78-F78 -> 2
A79: 43059 | B79: 13997 | C79: SEPTIEMBRE | D79: AGUA | F79: 2 | G79: =+G78+E79-F79 -> 0
A80: 43039 | B80: POR COBRAR | C80: OCTUBRE | D80: LUZ | E80: 152 | G80: =+G79+E80-F80 -> 152
D81: AGUA | E81: 2 | G81: =+G80+E81-F81 -> 154
D82: G. ADM | E82: 60 | G82: =+G81+E82-F82 -> 214
D83: P. SOCIAL | E83: 2 | G83: =+G82+E83-F83 -> 216
A84: 43053 | B84: 13976 | C84: OCTUBRE | D84: G. ADM | F84: 60 | G84: =+G83+E84-F84 -> 156
A85: 43053 | B85: 13976 | C85: OCTUBRE | D85: P. SOCIAL | F85: 2 | G85: =+G84+E85-F85 -> 154
A86: 43063 | B86: 14056 | C86: OCTUBRE | D86: LUZ | F86: 152 | G86: =+G85+E86-F86 -> 2
A87: 43063 | B87: 14056 | C87: OCTUBRE | D87: AGUA | F87: 2 | G87: =+G86+E87-F87 -> 0
A88: 43069 | B88: POR COBRAR | C88: NOVIEMBRE | D88: LUZ | E88: 162.2 | G88: =+G87+E88-F88 -> 162.2
D89: AGUA | E89: 2 | G89: =+G88+E89-F89 -> 164.2
D90: G. ADM | E90: 60 | G90: =+G89+E90-F90 -> 224.2
D91: P. SOCIAL | E91: 2 | G91: =+G90+E91-F91 -> 226.2
A92: 43088 | B92: 14313 | C92: NOVIEMBRE | D92: LUZ | F92: 162.2 | G92: =+G91+E92-F92 -> 64
A93: 43088 | B93: 14313 | C93: NOVIEMBRE | D93: AGUA | F93: 2 | G93: =+G92+E93-F93 -> 62
A94: 43097 | B94: 14357 | C94: NOVIEMBRE | D94: G. ADM | F94: 60 | G94: =+G93+E94-F94 -> 2
A95: 43097 | B95: 14357 | C95: NOVIEMBRE | D95: P. SOCIAL | F95: 2 | G95: =+G94+E95-F95 -> 0
A96: 43100 | B96: POR COBRAR | C96: DICIEMBRE | D96: LUZ | E96: 176.5 | G96: =+G95+E96-F96 -> 176.5
D97: AGUA | E97: 2 | G97: =+G96+E97-F97 -> 178.5
D98: G. ADM | E98: 60 | G98: =+G97+E98-F98 -> 238.5
D99: P. SOCIAL | E99: 2 | G99: =+G98+E99-F99 -> 240.5
A100: 43118 | B100: 14465 | C100: DICIEMBRE | D100: LUZ | F100: 176.5 | G100: =+G99+E100-F100 -> 64
A101: 43118 | B101: 14465 | C101: DICIEMBRE | D101: AGUA | F101: 2 | G101: =+G100+E101-F101 -> 62
A102: 43150 | B102: 14659 | C102: DICIEMBRE | D102: G. ADM | F102: 60 | G102: =+G101+E102-F102 -> 2
...

Sheet PAREDES DIANA
B2: PAREDES MORALES DIANA VONNET
A4: FECHA | B4: DOCUMENTO | C4: PERIODO | D4: CONCEPTO | E4: POR COBRAR | F4: PAGADO | G4: SALDO POR COBRAR
A5: 42736 | B5: SALDO AL 2016 | G5: 380.7
A6: 42761 | B6: 12163 | C6: A CUENTA 2016 | F6: 124 | G6: =+G5+E6-F6 -> 256.7
A7: 42786 | B7: 12214 | C7: A CUENTA 2016 | F7: 253.7 | G7: =+G6+E7-F7 -> 3
A8: 42786 | B8: 12215 | C8: A CUENTA 2016 | F8: 3 | G8: =+G7+E8-F8 -> 0
A9: 42766 | B9: POR COBRAR | C9: ENERO | D9: LUZ | E9: 126.9 | G9: =+G8+E9-F9 -> 126.9
D10: AGUA | E10: 2.8 | G10: =+G9+E10-F10 -> 129.7
D11: G. ADM | E11: 60 | G11: =+G10+E11-F11 -> 189.7
D12: P. SOCIAL | E12: 2 | G12: =+G11+E12-F12 -> 191.7
A13: 42786 | B13: 12214 | C13: ENERO | D13: G. ADM | F13: 60 | G13: =+G12+E13-F13 -> 131.7
A14: 42786 | B14: 12214 | C14: ENERO | D14: P. SOCIAL | F14: 2 | G14: =+G13+E14-F14 -> 129.7
A15: 42786 | B15: 12214 | C15: ENERO | D15: LUZ | F15: 126.9 | G15: =+G14+E15-F15 -> 2.8
A16: 42786 | B16: 12215 | C16: ENERO | D16: AGUA | F16: 2.8 | G16: =+G15+E16-F16 -> 1.1546319e-14
A17: 42794 | B17: POR COBRAR | C17: FEBRERO | D17: LUZ | E17: 129.9 | G17: =+G16+E17-F17 -> 129.9
D18: AGUA | E18: 2 | G18: =+G17+E18-F18 -> 131.9
D19: G. ADM | E19: 56 | G19: =+G18+E19-F19 -> 187.9
D20: P. SOCIAL | E20: 2 | G20: =+G19+E20-F20 -> 189.9
A21: 42821 | B21: 12525 | C21: FEBRERO | D21: G. ADM | F21: 56 | G21: =+G20+E21-F21 -> 133.9
A22: 42821 | B22: 12525 | C22: FEBRERO | D22: P. SOCIAL | F22: 2 | G22: =+G21+E22-F22 -> 131.9
A23: 42821 | B23: 12525 | C23: FEBRERO | D23: LUZ | F23: 129.9 | G23: =+G22+E23-F23 -> 2
A24: 42821 | B24: 12525 | C24: FEBRERO | D24: AGUA | F24: 2 | G24: =+G23+E24-F24 -> 0
A25: 42825 | B25: POR COBRAR | C25: MARZO | D25: LUZ | E25: 117.7 | G25: =+G24+E25-F25 -> 117.7
D26: AGUA | E26: 2 | G26: =+G25+E26-F26 -> 119.7
D27: G. ADM | E27: 60 | G27: =+G26+E27-F27 -> 179.7
D28: P. SOCIAL | E28: 2 | G28: =+G27+E28-F28 -> 181.7
D29: MULTA | E29: 85 | G29: =+G28+E29-F29 -> 266.7
A30: 42882 | B30: 12836 | C30: MARZO | D30: LUZ | F30: 117.7 | G30: =+G29+E30-F30 -> 149
A31: 42882 | B31: 12836 | C31: MARZO | D31: AGUA | F31: 2 | G31: =+G30+E31-F31 -> 147
A32: 42920 | B32: 13180 | C32: MARZO | D32: G. ADM | F32: 60 | G32: =+G31+E32-F32 -> 87
A33: 42920 | B33: 13180 | C33: MARZO | D33: P. SOCIAL | F33: 2 | G33: =+G32+E33-F33 -> 85
A34: 42949 | B34: 13355 | C34: MARZO | D34: MULTA | F34: 85 | G34: =+G33+E34-F34 -> 0
A35: 42855 | B35: POR COBRAR | C35: ABRIL | D35: LUZ | E35: 127.1 | G35: =+G34+E35-F35 -> 127.1
D36: AGUA | E36: 2 | G36: =+G35+E36-F36 -> 129.1
D37: G. ADM | E37: 60 | G37: =+G36+E37-F37 -> 189.1
D38: P. SOCIAL | E38: 2 | G38: =+G37+E38-F38 -> 191.1
A39: 42891 | B39: 13052 | C39: ABRIL | D39: LUZ | F39: 127.1 | G39: =+G38+E39-F39 -> 64
A40: 42891 | B40: 13052 | C40: ABRIL | D40: AGUA | F40: 2 | G40: =+G39+E40-F40 -> 62
A41: 42949 | B41: 13355 | C41: ABRIL | D41: G. ADM | F41: 60 | G41: =+G40+E41-F41 -> 2
A42: 42949 | B42: 13355 | C42: ABRIL | D42: P. SOCIAL | F42: 2 | G42: =+G41+E42-F42 -> 0
A43: 42886 | B43: POR COBRAR | C43: MAYO | D43: LUZ | E43: 89.4 | G43: =+G42+E43-F43 -> 89.4
D44: AGUA | E44: 2 | G44: =+G43+E44-F44 -> 91.4
D45: G. ADM | E45: 60 | G45: =+G44+E45-F45 -> 151.4
D46: P. SOCIAL | E46: 2 | G46: =+G45+E46-F46 -> 153.4
A47: 42927 | B47: 13199 | C47: MAYO | D47: LUZ | F47: 89.4 | G47: =+G46+E47-F47 -> 64
A48: 42927 | B48: 13199 | C48: MAYO | D48: AGUA | F48: 2 | G48: =+G47+E48-F48 -> 62
A49: 42949 | B49: 13355 | C49: MAYO | D49: G. ADM | F49: 60 | G49: =+G48+E49-F49 -> 2
A50: 42949 | B50: 13355 | C50: MAYO | D50: P. SOCIAL | F50: 2 | G50: =+G49+E50-F50 -> 0
A51: 42916 | B51: POR COBRAR | C51: JUNIO | D51: LUZ | E51: 87.1 | G51: =+G50+E51-F51 -> 87.1
D52: AGUA | E52: 2 | G52: =+G51+E52-F52 -> 89.1
D53: G. ADM | E53: 60 | G53: =+G52+E53-F53 -> 149.1
D54: P. SOCIAL | E54: 2 | G54: =+G53+E54-F54 -> 151.1
A55: 42949 | B55: 13355 | C55: JUNIO | D55: G. ADM | F55: 60 | G55: =+G54+E55-F55 -> 91.1
A56: 42949 | B56: 13355 | C56: JUNIO | D56: P. SOCIAL | F56: 2 | G56: =+G55+E56-F56 -> 89.1
A57: 42949 | B57: 13355 | C57: JUNIO | D57: LUZ | F57: 87.1 | G57: =+G56+E57-F57 -> 2
A58: 42949 | B58: 13355 | C58: JUNIO | D58: AGUA | F58: 2 | G58: =+G57+E58-F58 -> 0
A59: 42947 | B59: POR COBRAR | C59: JULIO | D59: LUZ | E59: 84.7 | G59: =+G58+E59-F59 -> 84.7
D60: AGUA | E60: 2 | G60: =+G59+E60-F60 -> 86.7
D61: G. ADM | E61: 60 | G61: =+G60+E61-F61 -> 146.7
D62: P. SOCIAL | E62: 2 | G62: =+G61+E62-F62 -> 148.7
A63: 42949 | B63: 13355 | C63: JULIO | D63: G. ADM | F63: 60 | G63: =+G62+E63-F63 -> 88.7
A64: 42949 | B64: 13355 | C64: JULIO | D64: P. SOCIAL | F64: 2 | G64: =+G63+E64-F64 -> 86.7
A65: 43014 | B65: 13800 | C65: JULIO | D65: LUZ | F65: 84.7 | G65: =+G64+E65-F65 -> 2
A66: 43014 | B66: 13800 | C66: JULIO | D66: AGUA | F66: 2 | G66: =+G65+E66-F66 -> -1.4210855e-14
A67: 42978 | B67: POR COBRAR | C67: AGOSTO | D67: LUZ | E67: 84.7 | G67: =+G66+E67-F67 -> 84.7
D68: AGUA | E68: 2 | G68: =+G67+E68-F68 -> 86.7
D69: G. ADM | E69: 60 | G69: =+G68+E69-F69 -> 146.7
D70: P. SOCIAL | E70: 2 | G70: =+G69+E70-F70 -> 148.7
A71: 43014 | B71: 13800 | C71: AGOSTO | D71: LUZ | F71: 84.7 | G71: =+G70+E71-F71 -> 64
A72: 43014 | B72: 13800 | C72: AGOSTO | D72: AGUA | F72: 2 | G72: =+G71+E72-F72 -> 62
A73: 43068 | B73: 14172 | C73: AGOSTO | D73: G. ADM | F73: 60 | G73: =+G72+E73-F73 -> 2
A74: 43068 | B74: 14172 | C74: AGOSTO | D74: P. SOCIAL | F74: 2 | G74: =+G73+E74-F74 -> -1.4210855e-14
A75: 43008 | B75: POR COBRAR | C75: SEPTIEMBRE | D75: LUZ | E75: 107.3 | G75: =+G74+E75-F75 -> 107.3
D76: AGUA | E76: 2 | G76: =+G75+E76-F76 -> 109.3
D77: G. ADM | E77: 60 | G77: =+G76+E77-F77 -> 169.3
D78: P. SOCIAL | E78: 2 | G78: =+G77+E78-F78 -> 171.3
A79: 42788 | D79: MULTA | E79: 85 | G79: =+G78+E79-F79 -> 256.3
A80: 43202 | B80: 15097 | C80: SEPTIEMBRE | D80: P.SOCIAL | F80: 2 | G80: =+G79+E80-F80 -> 254.3
A81: 43202 | B81: 15096 | C81: SEPTIEMBRE | D81: G. ADM | F81: 60 | G81: =+G80+E81-F81 -> 194.3
A82: 43067 | B82: EXONERACION | C82: 42788 | D82: MULTA | F82: 85 | G82: =+G81+E82-F82 -> 109.3
A83: 43068 | B83: 14172 | C83: SEPTIEMBRE | D83: LUZ | F83: 107.3 | G83: =+G82+E83-F83 -> 2
A84: 43068 | B84: 14172 | C84: SEPTIEMBRE | D84: AGUA | F84: 2 | G84: =+G83+E84-F84 -> -4.2632564e-14
A85: 43039 | B85: POR COBRAR | C85: OCTUBRE | D85: LUZ | E85: 106.8 | G85: =+G84+E85-F85 -> 106.8
D86: AGUA | E86: 2 | G86: =+G85+E86-F86 -> 108.8
D87: G. ADM | E87: 60 | G87: =+G86+E87-F87 -> 168.8
D88: P. SOCIAL | E88: 2 | G88: =+G87+E88-F88 -> 170.8
A89: 43202 | B89: 15097 | C89: OCTUBRE | D89: P.SOCIAL | F89: 2 | G89: =+G88+E89-F89 -> 168.8
A90: 43202 | B90: 15096 | C90: OCTUBRE | D90: G. ADM | F90: 60 | G90: =+G89+E90-F90 -> 108.8
A91: 43193 | B91: 15076 | C91: OCTUBRE | D91: LUZ | F91: 106.8 | G91: =+G90+E91-F91 -> 2
A92: 43193 | B92: 15076 | C92: OCTUBRE | D92: AGUA | F92: 2 | G92: =+G91+E92-F92 -> -4.2632564e-14
A93: 43069 | B93: POR COBRAR | C93: NOVIEMBRE | D93: LUZ | E93: 114 | G93: =+G92+E93-F93 -> 114
D94: AGUA | E94: 2 | G94: =+G93+E94-F94 -> 116
D95: G. ADM | E95: 60 | G95: =+G94+E95-F95 -> 176
D96: P. SOCIAL | E96: 2 | G96: =+G95+E96-F96 -> 178
D97: P. S X FALL. FLORES EMMA | E97: 10 | G97: =+G96+E97-F97 -> 188
A98: 43129 | B98: 14583 | C98: NOVIEMBRE | D98: LUZ | F98: 114 | G98: =+G97+E98-F98 -> 74
A99: 43129 | B99: 14583 | C99: NOVIEMBRE | D99: AGUA | F99: 2 | G99: =+G98+E99-F99 -> 72
A100: 43262 | B100: 15492 | C100: NOVIEMBRE | D100: G. ADM | F100: 60 | G100: =+G99+E100-F100 -> 12
A101: 43262 | B101: 15492 | C101: NOVIEMBRE | D101: P. SOCIAL | F101: 2 | G101: =+G100+E101-F101 -> 10
A102: 43851 | B102: 19538 | C102: NOVIEMBRE | D102: P. S X FALL. FLORES EMMA | F102: 10 | G102: =+G101+E102-F102 -> -5.6843419e-14
...

Sheet PAREDES OSCAR MARTIN
B2: PAREDES MORALES OSCAR MARTIN
A4: FECHA | B4: DOCUMENTO | C4: PERIODO | D4: CONCEPTO | E4: POR COBRAR | F4: PAGADO | G4: SALDO POR COBRAR
A5: 42736 | B5: SALDO AL 2016 | G5: 318
A6: 42887 | B6: 13024 | C6: A CUENTA 2016 | F6: 194 | G6: =+G5+E6-F6 -> 124
A7: 43501 | B7: 17109 | C7: CANCELACION 2016 | F7: 124 | G7: =+G6+E7-F7 -> 0
A8: 42766 | B8: POR COBRAR | C8: ENERO | D8: LUZ | E8: 133.3 | G8: =+G7+E8-F8 -> 133.3
D9: AGUA | E9: 2.7 | G9: =+G8+E9-F9 -> 136
D10: G. ADM | E10: 60 | G10: =+G9+E10-F10 -> 196
D11: P. SOCIAL | E11: 2 | G11: =+G10+E11-F11 -> 198
A12: 42887 | B12: 13024 | C12: ENERO | D12: LUZ | F12: 133.3 | G12: =+G11+E12-F12 -> 64.7
A13: 42887 | B13: 13024 | C13: ENERO | D13: AGUA | F13: 2.7 | G13: =+G12+E13-F13 -> 62
A14: 43501 | B14: 17109 | C14: ENERO | D14: G. ADM | F14: 60 | G14: =+G13+E14-F14 -> 2
A15: 43501 | B15: 17109 | C15: ENERO | D15: P. SOCIAL | F15: 2 | G15: =+G14+E15-F15 -> -1.4210855e-14
A16: 42794 | B16: POR COBRAR | C16: FEBRERO | D16: LUZ | E16: 127.7 | G16: =+G15+E16-F16 -> 127.7
D17: AGUA | E17: 2 | G17: =+G16+E17-F17 -> 129.7
D18: G. ADM | E18: 56 | G18: =+G17+E18-F18 -> 185.7
D19: P. SOCIAL | E19: 2 | G19: =+G18+E19-F19 -> 187.7
A20: 42887 | B20: 13024 | C20: FEBRERO | D20: LUZ | F20: 127.7 | G20: =+G19+E20-F20 -> 60
A21: 42887 | B21: 13024 | C21: FEBRERO | D21: AGUA | F21: 2 | G21: =+G20+E21-F21 -> 58
A22: 43501 | B22: 17109 | C22: FEBRERO | D22: G. ADM | F22: 14 | G22: =+G21+E22-F22 -> 44
A23: 43889 | B23: 19847 | C23: FEBRERO | D23: G. ADM | F23: 42 | G23: =+G22+E23-F23 -> 2
A24: 43889 | B24: 19847 | C24: FEBRERO | D24: P. SOCIAL | F24: 2 | G24: =+G23+E24-F24 -> -1.4210855e-14
A25: 42825 | B25: POR COBRAR | C25: MARZO | D25: LUZ | E25: 122 | G25: =+G24+E25-F25 -> 122
D26: AGUA | E26: 2 | G26: =+G25+E26-F26 -> 124
D27: G. ADM | E27: 60 | G27: =+G26+E27-F27 -> 184
D28: P. SOCIAL | E28: 2 | G28: =+G27+E28-F28 -> 186
A29: 42887 | B29: 13024 | C29: MARZO | D29: LUZ | F29: 122 | G29: =+G28+E29-F29 -> 64
A30: 42887 | B30: 13024 | C30: MARZO | D30: AGUA | F30: 2 | G30: =+G29+E30-F30 -> 62
A31: 43889 | B31: 19847 | C31: MARZO | D31: G. ADM | F31: 60 | G31: =+G30+E31-F31 -> 2
A32: 43889 | B32: 19847 | C32: MARZO | D32: P. SOCIAL | F32: 2 | G32: =+G31+E32-F32 -> 0
A33: 42855 | B33: POR COBRAR | C33: ABRIL | D33: LUZ | E33: 124.9 | G33: =+G32+E33-F33 -> 124.9
D34: AGUA | E34: 2 | G34: =+G33+E34-F34 -> 126.9
D35: G. ADM | E35: 60 | G35: =+G34+E35-F35 -> 186.9
D36: P. SOCIAL | E36: 2 | G36: =+G35+E36-F36 -> 188.9
A37: 42887 | B37: 13031 | C37: ABRIL | D37: LUZ | F37: 124.9 | G37: =+G36+E37-F37 -> 64
A38: 42887 | B38: 13031 | C38: ABRIL | D38: AGUA | F38: 2 | G38: =+G37+E38-F38 -> 62
A39: 43889 | B39: 19847 | C39: ABRIL | D39: G. ADM | F39: 60 | G39: =+G38+E39-F39 -> 2
A40: 43889 | B40: 19847 | C40: ABRIL | D40: P. SOCIAL | F40: 2 | G40: =+G39+E40-F40 -> 0
A41: 42886 | B41: POR COBRAR | C41: MAYO | D41: LUZ | E41: 117.1 | G41: =+G40+E41-F41 -> 117.1
D42: AGUA | E42: 2 | G42: =+G41+E42-F42 -> 119.1
D43: G. ADM | E43: 60 | G43: =+G42+E43-F43 -> 179.1
D44: P. SOCIAL | E44: 2 | G44: =+G43+E44-F44 -> 181.1
A45: 43007 | B45: 13704 | C45: MAYO | D45: LUZ | F45: 117.1 | G45: =+G44+E45-F45 -> 64
A46: 43007 | B46: 13704 | C46: MAYO | D46: AGUA | F46: 2 | G46: =+G45+E46-F46 -> 62
A47: 43889 | B47: 19847 | C47: MAYO | D47: G. ADM | F47: 60 | G47: =+G46+E47-F47 -> 2
A48: 43889 | B48: 19847 | C48: MAYO | D48: P.SOCIAL | F48: 2 | G48: =+G47+E48-F48 -> 0
A49: 42916 | B49: POR COBRAR | C49: JUNIO | D49: RECONEXION | E49: 30 | G49: =+G48+E49-F49 -> 30
D50: LUZ | E50: 114.4 | G50: =+G49+E50-F50 -> 144.4
D51: AGUA | E51: 2 | G51: =+G50+E51-F51 -> 146.4
D52: G. ADM | E52: 60 | G52: =+G51+E52-F52 -> 206.4
D53: P. SOCIAL | E53: 2 | G53: =+G52+E53-F53 -> 208.4
A54: 42887 | B54: 13024 | C54: JUNIO | D54: RECONEXION | F54: 30 | G54: =+G53+E54-F54 -> 178.4
A55: 43007 | B55: 13704 | C55: JUNIO | D55: LUZ | F55: 114.4 | G55: =+G54+E55-F55 -> 64
A56: 43007 | B56: 13704 | C56: JUNIO | D56: AGUA | F56: 2 | G56: =+G55+E56-F56 -> 62
A57: 43889 | B57: 19847 | C57: JUNIO | D57: G. ADM | F57: 60 | G57: =+G56+E57-F57 -> 2
A58: 43889 | B58: 19847 | C58: JUNIO | D58: P.SOCIAL | F58: 2 | G58: =+G57+E58-F58 -> 0
A59: 42947 | B59: POR COBRAR | C59: JULIO | D59: LUZ | E59: 104.2 | G59: =+G58+E59-F59 -> 104.2
D60: AGUA | E60: 2 | G60: =+G59+E60-F60 -> 106.2
D61: G. ADM | E61: 60 | G61: =+G60+E61-F61 -> 166.2
D62: P. SOCIAL | E62: 2 | G62: =+G61+E62-F62 -> 168.2
A63: 42971 | B63: 13460 | C63: JULIO | D63: LUZ | F63: 104.2 | G63: =+G62+E63-F63 -> 64
A64: 42971 | B64: 13460 | C64: JULIO | D64: AGUA | F64: 2 | G64: =+G63+E64-F64 -> 62
A65: 43889 | B65: 19847 | C65: JULIO | D65: G. ADM | F65: 60 | G65: =+G64+E65-F65 -> 2
A66: 43889 | B66: 19847 | C66: JULIO | D66: P.SOCIAL | F66: 2 | G66: =+G65+E66-F66 -> -1.4210855e-14
A67: 42978 | B67: POR COBRAR | C67: AGOSTO | D67: LUZ | E67: 104.2 | G67: =+G66+E67-F67 -> 104.2
D68: AGUA | E68: 2 | G68: =+G67+E68-F68 -> 106.2
D69: G. ADM | E69: 60 | G69: =+G68+E69-F69 -> 166.2
D70: P. SOCIAL | E70: 2 | G70: =+G69+E70-F70 -> 168.2
A71: 43099 | B71: 14367 | C71: AGOSTO | D71: LUZ | F71: 104.2 | G71: =+G70+E71-F71 -> 64
A72: 43099 | B72: 14367 | C72: AGOSTO | D72: AGUA | F72: 2 | G72: =+G71+E72-F72 -> 62
A73: 43889 | B73: 19847 | C73: AGOSTO | D73: G. ADM | F73: 60 | G73: =+G72+E73-F73 -> 2
A74: 43889 | B74: 19847 | C74: AGOSTO | D74: P.SOCIAL | F74: 2 | G74: =+G73+E74-F74 -> -1.4210855e-14
A75: 43008 | B75: POR COBRAR | C75: SEPTIEMBRE | D75: LUZ | E75: 108.3 | G75: =+G74+E75-F75 -> 108.3
D76: AGUA | E76: 2 | G76: =+G75+E76-F76 -> 110.3
D77: G. ADM | E77: 60 | G77: =+G76+E77-F77 -> 170.3
D78: P. SOCIAL | E78: 2 | G78: =+G77+E78-F78 -> 172.3
A79: 42788 | D79: MULTA | E79: 85 | G79: =+G78+E79-F79 -> 257.3
A80: 42823 | D80: MULTA | E80: 85 | G80: =+G79+E80-F80 -> 342.3
A81: 42951 | D81: MULTA | E81: 85 | G81: =+G80+E81-F81 -> 427.3
A82: 43099 | B82: 14367 | C82: SEPTIEMBRE | D82: LUZ | F82: 108.3 | G82: =+G81+E82-F82 -> 319
A83: 43099 | B83: 14367 | C83: SEPTIEMBRE | D83: AGUA | F83: 2 | G83: =+G82+E83-F83 -> 317
A84: 43889 | B84: 19847 | C84: SEPTIEMBRE | D84: G. ADM | F84: 60 | G84: =+G83+E84-F84 -> 257
A85: 43889 | B85: 19847 | C85: SEPTIEMBRE | D85: P.SOCIAL | F85: 2 | G85: =+G84+E85-F85 -> 255
B86: EXONERACION | D86: MULTA | F86: 42.5 | G86: =+G85+E86-F86 -> 212.5
B87: EXONERACION | D87: MULTA | F87: 42.5 | G87: =+G86+E87-F87 -> 170
B88: EXONERACION | D88: MULTA | F88: 42.5 | G88: =+G87+E88-F88 -> 127.5
A89: 45291 | B89: TARJETA-DIC | C89: SEPTIEMBRE | D89: MULTA | F89: 42.5 | G89: =+G88+E89-F89 -> 85
A90: 45291 | B90: TARJETA-DIC | C90: SEPTIEMBRE | D90: MULTA | F90: 42.5 | G90: =+G89+E90-F90 -> 42.5
A91: 45291 | B91: TARJETA-DIC | C91: SEPTIEMBRE | D91: MULTA | F91: 42.5 | G91: =+G90+E91-F91 -> -5.6843419e-14
A92: 43039 | B92: POR COBRAR | C92: OCTUBRE | D92: LUZ | E92: 107.8 | G92: =+G91+E92-F92 -> 107.8
D93: AGUA | E93: 2 | G93: =+G92+E93-F93 -> 109.8
D94: G. ADM | E94: 60 | G94: =+G93+E94-F94 -> 169.8
D95: P. SOCIAL | E95: 2 | G95: =+G94+E95-F95 -> 171.8
A96: 43236 | B96: 15322 | C96: OCTUBRE | D96: LUZ | F96: 107.8 | G96: =+G95+E96-F96 -> 64
A97: 43236 | B97: 15322 | C97: OCTUBRE | D97: AGUA | F97: 2 | G97: =+G96+E97-F97 -> 62
A98: 43889 | B98: 19847 | C98: OCTUBRE | D98: G. ADM | F98: 60 | G98: =+G97+E98-F98 -> 2
A99: 43889 | B99: 19847 | C99: OCTUBRE | D99: P.SOCIAL | F99: 2 | G99: =+G98+E99-F99 -> -4.2632564e-14
A100: 43434 | B100: POR COBRAR | C100: NOVIEMBRE | D100: LUZ | E100: 115 | G100: =+G99+E100-F100 -> 115
D101: AGUA | E101: 2 | G101: =+G100+E101-F101 -> 117
D102: G. ADM | E102: 60 | G102: =+G101+E102-F102 -> 177
...

Sheet PEREZ SATURNINA
B2: PEREZ PONCE DE ROMERO SATURNINA
A4: FECHA | B4: DOCUMENTO | C4: PERIODO | D4: CONCEPTO | E4: POR COBRAR | F4: PAGADO | G4: SALDO POR COBRAR
A5: 42736 | B5: SALDO AL 2016 | G5: 193.1
A6: 42846 | B6: 12671 | C6: CANCELACION DEL 2016 | F6: 193.1 | G6: =+G5+E6-F6 -> 0
A7: 42766 | B7: POR COBRAR | C7: ENERO | D7: LUZ | E7: 56.1 | G7: =+G6+E7-F7 -> 56.1
D8: AGUA | E8: 2.8 | G8: =+G7+E8-F8 -> 58.9
D9: G. ADM | E9: 60 | G9: =+G8+E9-F9 -> 118.9
D10: P. SOCIAL | E10: 2 | G10: =+G9+E10-F10 -> 120.9
A11: 42765 | B11: TARJETA | C11: ENERO | D11: G. ADM | F11: 60 | G11: =+G10+E11-F11 -> 60.9
A12: 42765 | B12: TARJETA | C12: ENERO | D12: P. SOCIAL | F12: 2 | G12: =+G11+E12-F12 -> 58.9
A13: 42846 | B13: 12671 | C13: ENERO | D13: LUZ | F13: 56.1 | G13: =+G12+E13-F13 -> 2.8
A14: 42846 | B14: 12671 | C14: ENERO | D14: AGUA | F14: 2.8 | G14: =+G13+E14-F14 -> 4.4408921e-15
A15: 42794 | B15: POR COBRAR | C15: FEBRERO | D15: LUZ | E15: 85.9 | G15: =+G14+E15-F15 -> 85.9
D16: AGUA | E16: 2 | G16: =+G15+E16-F16 -> 87.9
D17: G. ADM | E17: 56 | G17: =+G16+E17-F17 -> 143.9
D18: P. SOCIAL | E18: 2 | G18: =+G17+E18-F18 -> 145.9
A19: 42794 | B19: TARJETA | C19: FEBRERO | D19: G. ADM | F19: 56 | G19: =+G18+E19-F19 -> 89.9
A20: 42794 | B20: TARJETA | C20: FEBRERO | D20: P. SOCIAL | F20: 2 | G20: =+G19+E20-F20 -> 87.9
A21: 42846 | B21: 12671 | C21: FEBRERO | D21: LUZ | F21: 85.9 | G21: =+G20+E21-F21 -> 2
A22: 42846 | B22: 12671 | C22: FEBRERO | D22: AGUA | F22: 2 | G22: =+G21+E22-F22 -> 0
A23: 42825 | B23: POR COBRAR | C23: MARZO | D23: LUZ | E23: 82.3 | G23: =+G22+E23-F23 -> 82.3
D24: AGUA | E24: 2 | G24: =+G23+E24-F24 -> 84.3
D25: G. ADM | E25: 60 | G25: =+G24+E25-F25 -> 144.3
D26: P. SOCIAL | E26: 2 | G26: =+G25+E26-F26 -> 146.3
A27: 42824 | B27: TARJETA | C27: MARZO | D27: G. ADM | F27: 60 | G27: =+G26+E27-F27 -> 86.3
A28: 42824 | B28: TARJETA | C28: MARZO | D28: P. SOCIAL | F28: 2 | G28: =+G27+E28-F28 -> 84.3
A29: 42846 | B29: 12671 | C29: MARZO | D29: LUZ | F29: 82.3 | G29: =+G28+E29-F29 -> 2
A30: 42846 | B30: 12671 | C30: MARZO | D30: AGUA | F30: 2 | G30: =+G29+E30-F30 -> 1.4210855e-14
A31: 42855 | B31: POR COBRAR | C31: ABRIL | D31: LUZ | E31: 62.5 | G31: =+G30+E31-F31 -> 62.5
D32: AGUA | E32: 2 | G32: =+G31+E32-F32 -> 64.5
D33: G. ADM | E33: 60 | G33: =+G32+E33-F33 -> 124.5
D34: P. SOCIAL | E34: 2 | G34: =+G33+E34-F34 -> 126.5
A35: 42854 | B35: TARJETA | C35: ABRIL | D35: G. ADM | F35: 60 | G35: =+G34+E35-F35 -> 66.5
A36: 42854 | B36: TARJETA | C36: ABRIL | D36: P. SOCIAL | F36: 2 | G36: =+G35+E36-F36 -> 64.5
A37: 43116 | B37: 14423 | C37: ABRIL | D37: LUZ | F37: 62.5 | G37: =+G36+E37-F37 -> 2
A38: 43116 | B38: 14423 | C38: ABRIL | D38: AGUA | F38: 2 | G38: =+G37+E38-F38 -> 1.4210855e-14
A39: 42886 | B39: POR COBRAR | C39: MAYO | D39: LUZ | E39: 58.5 | G39: =+G38+E39-F39 -> 58.5
D40: AGUA | E40: 2 | G40: =+G39+E40-F40 -> 60.5
D41: G. ADM | E41: 60 | G41: =+G40+E41-F41 -> 120.5
D42: P. SOCIAL | E42: 2 | G42: =+G41+E42-F42 -> 122.5
A43: 42885 | B43: TARJETA | C43: MAYO | D43: G. ADM | F43: 60 | G43: =+G42+E43-F43 -> 62.5
A44: 42885 | B44: TARJETA | C44: MAYO | D44: P. SOCIAL | F44: 2 | G44: =+G43+E44-F44 -> 60.5
A45: 43116 | B45: 14424 | C45: MAYO | D45: LUZ | F45: 58.5 | G45: =+G44+E45-F45 -> 2
A46: 43116 | B46: 14424 | C46: MAYO | D46: AGUA | F46: 2 | G46: =+G45+E46-F46 -> 1.4210855e-14
A47: 42916 | B47: POR COBRAR | C47: JUNIO | D47: LUZ | E47: 57.2 | G47: =+G46+E47-F47 -> 57.2
D48: AGUA | E48: 2 | G48: =+G47+E48-F48 -> 59.2
D49: G. ADM | E49: 60 | G49: =+G48+E49-F49 -> 119.2
D50: P. SOCIAL | E50: 2 | G50: =+G49+E50-F50 -> 121.2
A51: 42916 | B51: TARJETA | C51: JUNIO | D51: G. ADM | F51: 60 | G51: =+G50+E51-F51 -> 61.2
A52: 42916 | B52: TARJETA | C52: JUNIO | D52: P. SOCIAL | F52: 2 | G52: =+G51+E52-F52 -> 59.2
A53: 43116 | B53: 14425 | C53: JUNIO | D53: LUZ | F53: 57.2 | G53: =+G52+E53-F53 -> 2
A54: 43116 | B54: 14425 | C54: JUNIO | D54: AGUA | F54: 2 | G54: =+G53+E54-F54 -> 1.4210855e-14
A55: 42947 | B55: POR COBRAR | C55: JULIO | D55: LUZ | E55: 52.1 | G55: =+G54+E55-F55 -> 52.1
D56: AGUA | E56: 2 | G56: =+G55+E56-F56 -> 54.1
D57: G. ADM | E57: 60 | G57: =+G56+E57-F57 -> 114.1
D58: P. SOCIAL | E58: 2 | G58: =+G57+E58-F58 -> 116.1
A59: 42945 | B59: TARJETA | C59: JULIO | D59: G. ADM | F59: 60 | G59: =+G58+E59-F59 -> 56.1
A60: 42945 | B60: TARJETA | C60: JULIO | D60: P. SOCIAL | F60: 2 | G60: =+G59+E60-F60 -> 54.1
A61: 43116 | B61: 14426 | C61: JULIO | D61: LUZ | F61: 52.1 | G61: =+G60+E61-F61 -> 2
A62: 43116 | B62: 14426 | C62: JULIO | D62: AGUA | F62: 2 | G62: =+G61+E62-F62 -> 2.1316282e-14
A63: 42978 | B63: POR COBRAR | C63: AGOSTO | D63: LUZ | E63: 52.1 | G63: =+G62+E63-F63 -> 52.1
D64: AGUA | E64: 2 | G64: =+G63+E64-F64 -> 54.1
D65: G. ADM | E65: 60 | G65: =+G64+E65-F65 -> 114.1
D66: P. SOCIAL | E66: 2 | G66: =+G65+E66-F66 -> 116.1
A67: 42978 | B67: TARJETA | C67: AGOSTO | D67: G. ADM | F67: 60 | G67: =+G66+E67-F67 -> 56.1
A68: 42978 | B68: TARJETA | C68: AGOSTO | D68: P. SOCIAL | F68: 2 | G68: =+G67+E68-F68 -> 54.1
A69: 43116 | B69: 14427 | C69: AGOSTO | D69: LUZ | F69: 52.1 | G69: =+G68+E69-F69 -> 2
A70: 43116 | B70: 14427 | C70: AGOSTO | D70: AGUA | F70: 2 | G70: =+G69+E70-F70 -> 2.1316282e-14
A71: 43008 | B71: POR COBRAR | C71: SEPTIEMBRE | D71: LUZ | E71: 61.9 | G71: =+G70+E71-F71 -> 61.9
D72: AGUA | E72: 2 | G72: =+G71+E72-F72 -> 63.9
D73: G. ADM | E73: 60 | G73: =+G72+E73-F73 -> 123.9
D74: P. SOCIAL | E74: 2 | G74: =+G73+E74-F74 -> 125.9
A75: 42788 | D75: MULTA | E75: 85 | G75: =+G74+E75-F75 -> 210.9
A76: 42823 | D76: MULTA | E76: 85 | G76: =+G75+E76-F76 -> 295.9
A77: 43008 | B77: TARJETA | C77: SEPTIEMBRE | D77: G. ADM | F77: 60 | G77: =+G76+E77-F77 -> 235.9
A78: 43008 | B78: TARJETA | C78: SEPTIEMBRE | D78: P. SOCIAL | F78: 2 | G78: =+G77+E78-F78 -> 233.9
A79: 43067 | B79: EXONERACION | C79: 42788 | D79: MULTA | F79: 85 | G79: =+G78+E79-F79 -> 148.9
A80: 43067 | B80: EXONERACION | C80: 42823 | D80: MULTA | F80: 85 | G80: =+G79+E80-F80 -> 63.9
A81: 43116 | B81: 14428 | C81: SEPTIEMBRE | D81: LUZ | F81: 61.9 | G81: =+G80+E81-F81 -> 2
A82: 43116 | B82: 14428 | C82: SEPTIEMBRE | D82: AGUA | F82: 2 | G82: =+G81+E82-F82 -> 3.5527137e-14
A83: 43039 | B83: POR COBRAR | C83: OCTUBRE | D83: LUZ | E83: 61.6 | G83: =+G82+E83-F83 -> 61.6
D84: AGUA | E84: 2 | G84: =+G83+E84-F84 -> 63.6
D85: G. ADM | E85: 60 | G85: =+G84+E85-F85 -> 123.6
D86: P. SOCIAL | E86: 2 | G86: =+G85+E86-F86 -> 125.6
A87: 43039 | B87: TARJETA | C87: OCTUBRE | D87: G. ADM | F87: 60 | G87: =+G86+E87-F87 -> 65.6
A88: 43039 | B88: TARJETA | C88: OCTUBRE | D88: P. SOCIAL | F88: 2 | G88: =+G87+E88-F88 -> 63.6
A89: 43116 | B89: 14429 | C89: OCTUBRE | D89: LUZ | F89: 61.6 | G89: =+G88+E89-F89 -> 2
A90: 43116 | B90: 14429 | C90: OCTUBRE | D90: AGUA | F90: 2 | G90: =+G89+E90-F90 -> 3.5527137e-14
A91: 43069 | B91: POR COBRAR | C91: NOVIEMBRE | D91: LUZ | E91: 65.7 | G91: =+G90+E91-F91 -> 65.7
D92: AGUA | E92: 2 | G92: =+G91+E92-F92 -> 67.7
D93: G. ADM | E93: 60 | G93: =+G92+E93-F93 -> 127.7
D94: P. SOCIAL | E94: 2 | G94: =+G93+E94-F94 -> 129.7
D95: P. S X FALL. FLORES EMMA | E95: 10 | G95: =+G94+E95-F95 -> 139.7
D96: FUMIGACION | E96: 10 | G96: =+G95+E96-F96 -> 149.7
A97: 43069 | B97: TARJETA | C97: NOVIEMBRE | D97: G. ADM | F97: 16 | G97: =+G96+E97-F97 -> 133.7
A98: 43116 | B98: 14430 | C98: NOVIEMBRE | D98: LUZ | F98: 65.7 | G98: =+G97+E98-F98 -> 68
A99: 43116 | B99: 14430 | C99: NOVIEMBRE | D99: AGUA | F99: 2 | G99: =+G98+E99-F99 -> 66
A100: 42920 | B100: 5568 | C100: NOVIEMBRE | D100: FUMIGACION | F100: 10 | G100: =+G99+E100-F100 -> 56
A101: 43271 | B101: 15516 | C101: NOVIEMBRE | D101: G. ADM | F101: 44 | G101: =+G100+E101-F101 -> 12
A102: 43271 | B102: 15516 | C102: NOVIEMBRE | D102: P. SOCIAL | F102: 2 | G102: =+G101+E102-F102 -> 10
...

Sheet PEREZ EPIFANIA
B2: PEREZ QUISPE EPIFANIA RICARDINA
A4: FECHA | B4: DOCUMENTO | C4: PERIODO | D4: CONCEPTO | E4: POR COBRAR | F4: PAGADO | G4: SALDO POR COBRAR
A5: 42736 | B5: SALDO AL 2016 | G5: 232.2
A6: 42758 | B6: 12134 | C6: A CUENTA 2016 | F6: 62 | G6: =+G5+E6-F6 -> 170.2
A7: 42758 | B7: 12135 | C7: A CUENTA 2016 | F7: 91.2 | G7: =+G6+E7-F7 -> 79
A8: 42786 | B8: 12273 | C8: A CUENTA 2016 | F8: 59 | G8: =+G7+E8-F8 -> 20
A9: 43182 | B9: 14945 | C9: A CUENTA 2016 | F9: 20 | G9: =+G8+E9-F9 -> 0
A10: 42766 | B10: POR COBRAR | C10: ENERO | D10: LUZ | E10: 75.9 | G10: =+G9+E10-F10 -> 75.9
D11: AGUA | E11: 2.8 | G11: =+G10+E11-F11 -> 78.7
D12: G. ADM | E12: 60 | G12: =+G11+E12-F12 -> 138.7
D13: P. SOCIAL | E13: 2 | G13: =+G12+E13-F13 -> 140.7
D14: PS X FALLEC. | E14: 10 | G14: =+G13+E14-F14 -> 150.7
A15: 42758 | B15: 12149 | C15: ENERO | D15: PS X FALLEC. | F15: 10 | G15: =+G14+E15-F15 -> 140.7
A16: 42786 | B16: 12273 | C16: ENERO | D16: G. ADM | F16: 60 | G16: =+G15+E16-F16 -> 80.7
A17: 42786 | B17: 12273 | C17: ENERO | D17: P. SOCIAL | F17: 2 | G17: =+G16+E17-F17 -> 78.7
A18: 42786 | B18: 12273 | C18: ENERO | D18: LUZ | F18: 75.9 | G18: =+G17+E18-F18 -> 2.8
A19: 42786 | B19: 12273 | C19: ENERO | D19: AGUA | F19: 2.8 | G19: =+G18+E19-F19 -> -1.687539e-14
A20: 42794 | B20: POR COBRAR | C20: FEBRERO | D20: LUZ | E20: 76.8 | G20: =+G19+E20-F20 -> 76.8
D21: AGUA | E21: 2 | G21: =+G20+E21-F21 -> 78.8
D22: G. ADM | E22: 56 | G22: =+G21+E22-F22 -> 134.8
D23: P. SOCIAL | E23: 2 | G23: =+G22+E23-F23 -> 136.8
A24: 42818 | B24: 12465 | C24: FEBRERO | D24: G. ADM | F24: 56 | G24: =+G23+E24-F24 -> 80.8
A25: 42818 | B25: 12465 | C25: FEBRERO | D25: P. SOCIAL | F25: 2 | G25: =+G24+E25-F25 -> 78.8
A26: 42818 | B26: 12465 | C26: FEBRERO | D26: LUZ | F26: 76.8 | G26: =+G25+E26-F26 -> 2
A27: 42818 | B27: 12465 | C27: FEBRERO | D27: AGUA | F27: 2 | G27: =+G26+E27-F27 -> -1.4210855e-14
A28: 42825 | B28: POR COBRAR | C28: MARZO | D28: LUZ | E28: 73 | G28: =+G27+E28-F28 -> 73
D29: AGUA | E29: 2 | G29: =+G28+E29-F29 -> 75
D30: G. ADM | E30: 60 | G30: =+G29+E30-F30 -> 135
D31: P. SOCIAL | E31: 2 | G31: =+G30+E31-F31 -> 137
A32: 42851 | B32: 12700 | C32: MARZO | D32: G. ADM | F32: 60 | G32: =+G31+E32-F32 -> 77
A33: 42851 | B33: 12700 | C33: MARZO | D33: P. SOCIAL | F33: 2 | G33: =+G32+E33-F33 -> 75
A34: 42851 | B34: 12701 | C34: MARZO | D34: LUZ | F34: 73 | G34: =+G33+E34-F34 -> 2
A35: 42851 | B35: 12701 | C35: MARZO | D35: AGUA | F35: 2 | G35: =+G34+E35-F35 -> 0
A36: 42855 | B36: POR COBRAR | C36: ABRIL | D36: LUZ | E36: 75.5 | G36: =+G35+E36-F36 -> 75.5
D37: AGUA | E37: 2 | G37: =+G36+E37-F37 -> 77.5
D38: G. ADM | E38: 60 | G38: =+G37+E38-F38 -> 137.5
D39: P. SOCIAL | E39: 2 | G39: =+G38+E39-F39 -> 139.5
A40: 42885 | B40: 12889 | C40: ABRIL | D40: G. ADM | F40: 60 | G40: =+G39+E40-F40 -> 79.5
A41: 42885 | B41: 12889 | C41: ABRIL | D41: P. SOCIAL | F41: 2 | G41: =+G40+E41-F41 -> 77.5
A42: 42885 | B42: 12890 | C42: ABRIL | D42: LUZ | F42: 75.5 | G42: =+G41+E42-F42 -> 2
A43: 42885 | B43: 12890 | C43: ABRIL | D43: AGUA | F43: 2 | G43: =+G42+E43-F43 -> 0
A44: 42886 | B44: POR COBRAR | C44: MAYO | D44: LUZ | E44: 71.5 | G44: =+G43+E44-F44 -> 71.5
D45: AGUA | E45: 2 | G45: =+G44+E45-F45 -> 73.5
D46: G. ADM | E46: 60 | G46: =+G45+E46-F46 -> 133.5
D47: P. SOCIAL | E47: 2 | G47: =+G46+E47-F47 -> 135.5
A48: 42943 | B48: 13272 | C48: MAYO | D48: G. ADM | F48: 60 | G48: =+G47+E48-F48 -> 75.5
A49: 42943 | B49: 13272 | C49: MAYO | D49: P. SOCIAL | F49: 2 | G49: =+G48+E49-F49 -> 73.5
A50: 42943 | B50: 13273 | C50: MAYO | D50: LUZ | F50: 71.5 | G50: =+G49+E50-F50 -> 2
A51: 42943 | B51: 13273 | C51: MAYO | D51: AGUA | F51: 2 | G51: =+G50+E51-F51 -> 0
A52: 42916 | B52: POR COBRAR | C52: JUNIO | D52: LUZ | E52: 69.7 | G52: =+G51+E52-F52 -> 69.7
D53: AGUA | E53: 2 | G53: =+G52+E53-F53 -> 71.7
D54: G. ADM | E54: 60 | G54: =+G53+E54-F54 -> 131.7
D55: P. SOCIAL | E55: 2 | G55: =+G54+E55-F55 -> 133.7
A56: 42943 | B56: 13272 | C56: JUNIO | D56: G. ADM | F56: 60 | G56: =+G55+E56-F56 -> 73.7
A57: 42943 | B57: 13272 | C57: JUNIO | D57: P. SOCIAL | F57: 2 | G57: =+G56+E57-F57 -> 71.7
A58: 42943 | B58: 13273 | C58: JUNIO | D58: LUZ | F58: 69.7 | G58: =+G57+E58-F58 -> 2
A59: 42943 | B59: 13273 | C59: JUNIO | D59: AGUA | F59: 2 | G59: =+G58+E59-F59 -> -1.4210855e-14
A60: 42947 | B60: POR COBRAR | C60: JULIO | D60: LUZ | E60: 56.6 | G60: =+G59+E60-F60 -> 56.6
D61: AGUA | E61: 2 | G61: =+G60+E61-F61 -> 58.6
D62: G. ADM | E62: 60 | G62: =+G61+E62-F62 -> 118.6
D63: P. SOCIAL | E63: 2 | G63: =+G62+E63-F63 -> 120.6
A64: 42950 | B64: 13397 | C64: JULIO | D64: G. ADM | F64: 60 | G64: =+G63+E64-F64 -> 60.6
A65: 42950 | B65: 13397 | C65: JULIO | D65: P. SOCIAL | F65: 2 | G65: =+G64+E65-F65 -> 58.6
A66: 43011 | B66: 13780 | C66: JULIO | D66: LUZ | F66: 56.6 | G66: =+G65+E66-F66 -> 2
A67: 43011 | B67: 13780 | C67: JULIO | D67: AGUA | F67: 2 | G67: =+G66+E67-F67 -> -7.1054274e-15
A68: 42978 | B68: POR COBRAR | C68: AGOSTO | D68: LUZ | E68: 56.6 | G68: =+G67+E68-F68 -> 56.6
D69: AGUA | E69: 2 | G69: =+G68+E69-F69 -> 58.6
D70: G. ADM | E70: 60 | G70: =+G69+E70-F70 -> 118.6
D71: P. SOCIAL | E71: 2 | G71: =+G70+E71-F71 -> 120.6
A72: 43011 | B72: 13781 | C72: AGOSTO | D72: G. ADM | F72: 60 | G72: =+G71+E72-F72 -> 60.6
A73: 43011 | B73: 13781 | C73: AGOSTO | D73: P. SOCIAL | F73: 2 | G73: =+G72+E73-F73 -> 58.6
A74: 43011 | B74: 13780 | C74: AGOSTO | D74: LUZ | F74: 56.6 | G74: =+G73+E74-F74 -> 2
A75: 43011 | B75: 13780 | C75: AGOSTO | D75: AGUA | F75: 2 | G75: =+G74+E75-F75 -> -7.1054274e-15
A76: 43008 | B76: POR COBRAR | C76: SEPTIEMBRE | D76: LUZ | E76: 54.2 | G76: =+G75+E76-F76 -> 54.2
D77: AGUA | E77: 2 | G77: =+G76+E77-F77 -> 56.2
D78: G. ADM | E78: 60 | G78: =+G77+E78-F78 -> 116.2
D79: P. SOCIAL | E79: 2 | G79: =+G78+E79-F79 -> 118.2
A80: 43067 | B80: 14155 | C80: SEPTIEMBRE | D80: G. ADM | F80: 60 | G80: =+G79+E80-F80 -> 58.2
A81: 43067 | B81: 14155 | C81: SEPTIEMBRE | D81: P. SOCIAL | F81: 2 | G81: =+G80+E81-F81 -> 56.2
A82: 43067 | B82: 14155 | C82: SEPTIEMBRE | D82: LUZ | F82: 54.2 | G82: =+G81+E82-F82 -> 2
A83: 43067 | B83: 14155 | C83: SEPTIEMBRE | D83: AGUA | F83: 2 | G83: =+G82+E83-F83 -> -1.4210855e-14
A84: 43039 | B84: POR COBRAR | C84: OCTUBRE | D84: LUZ | E84: 53.9 | G84: =+G83+E84-F84 -> 53.9
D85: AGUA | E85: 2 | G85: =+G84+E85-F85 -> 55.9
D86: G. ADM | E86: 60 | G86: =+G85+E86-F86 -> 115.9
D87: P. SOCIAL | E87: 2 | G87: =+G86+E87-F87 -> 117.9
A88: 43067 | B88: 14155 | C88: OCTUBRE | D88: G. ADM | F88: 60 | G88: =+G87+E88-F88 -> 57.9
A89: 43067 | B89: 14155 | C89: OCTUBRE | D89: P. SOCIAL | F89: 2 | G89: =+G88+E89-F89 -> 55.9
A90: 43067 | B90: 14155 | C90: OCTUBRE | D90: LUZ | F90: 53.9 | G90: =+G89+E90-F90 -> 2
A91: 43067 | B91: 14155 | C91: OCTUBRE | D91: AGUA | F91: 2 | G91: =+G90+E91-F91 -> -2.1316282e-14
A92: 43069 | B92: POR COBRAR | C92: NOVIEMBRE | D92: LUZ | E92: 57.5 | G92: =+G91+E92-F92 -> 57.5
D93: AGUA | E93: 2 | G93: =+G92+E93-F93 -> 59.5
D94: G. ADM | E94: 60 | G94: =+G93+E94-F94 -> 119.5
D95: P. SOCIAL | E95: 2 | G95: =+G94+E95-F95 -> 121.5
D96: P. S X FALL. FLORES EMMA | E96: 10 | G96: =+G95+E96-F96 -> 131.5
A97: 43067 | B97: 14156 | C97: NOVIEMBRE | D97: P. S X FALL. FLORES EMMA | F97: 10 | G97: =+G96+E97-F97 -> 121.5
A98: 43145 | B98: 14618 | C98: NOVIEMBRE | D98: LUZ | F98: 57.5 | G98: =+G97+E98-F98 -> 64
A99: 43145 | B99: 14618 | C99: NOVIEMBRE | D99: AGUA | F99: 2 | G99: =+G98+E99-F99 -> 62
A100: 43145 | B100: 14619 | C100: NOVIEMBRE | D100: G. ADM | F100: 60 | G100: =+G99+E100-F100 -> 2
A101: 43145 | B101: 14619 | C101: NOVIEMBRE | D101: P. SOCIAL | F101: 2 | G101: =+G100+E101-F101 -> -2.8421709e-14
A102: 43100 | B102: POR COBRAR | C102: DICIEMBRE | D102: LUZ | E102: 84.9 | G102: =+G101+E102-F102 -> 84.9
...

Sheet PITTMAN NELLY
B2: PITTMAN CONCEPCION NELLY MARIA
A4: FECHA | B4: DOCUMENTO | C4: PERIODO | D4: CONCEPTO | E4: POR COBRAR | F4: PAGADO | G4: SALDO POR COBRAR
A5: 42736 | B5: SALDO AL 2016 | G5: 807.7
A6: 42758 | B6: 12138 | C6: A CUENTA 2016 | F6: 62 | G6: =+G5+E6-F6 -> 745.7
A7: 42758 | B7: 12139 | C7: A CUENTA 2016 | F7: 62 | G7: =+G6+E7-F7 -> 683.7
A8: 42758 | B8: 12140 | C8: A CUENTA 2016 | F8: 62 | G8: =+G7+E8-F8 -> 621.7
A9: 42758 | B9: 12141 | C9: A CUENTA 2016 | F9: 62 | G9: =+G8+E9-F9 -> 559.7
A10: 42758 | B10: 12142 | C10: A CUENTA 2016 | F10: 62 | G10: =+G9+E10-F10 -> 497.7
A11: 42758 | B11: 12143 | C11: A CUENTA 2016 | F11: 62 | G11: =+G10+E11-F11 -> 435.7
A12: 42758 | B12: 12144 | C12: A CUENTA 2016 | F12: 62 | G12: =+G11+E12-F12 -> 373.7
A13: 42772 | B13: 12918 | C13: A CUENTA 2016 | F13: 119 | G13: =+G12+E13-F13 -> 254.7
A14: 42782 | B14: 12962 | C14: A CUENTA 2016 | F14: 144.7 | G14: =+G13+E14-F14 -> 110
A15: 42822 | B15: 12594 | C15: A CUENTA 2016 | F15: 38 | G15: =+G14+E15-F15 -> 72
A16: 42822 | B16: 12595 | C16: A CUENTA 2016 | F16: 72 | G16: =+G15+E16-F16 -> 0
A17: 42766 | B17: POR COBRAR | C17: ENERO | D17: LUZ | E17: 121.6 | G17: =+G16+E17-F17 -> 121.6
D18: AGUA | E18: 2.8 | G18: =+G17+E18-F18 -> 124.4
D19: G. ADM | E19: 60 | G19: =+G18+E19-F19 -> 184.4
D20: P. SOCIAL | E20: 2 | G20: =+G19+E20-F20 -> 186.4
A21: 42786 | B21: 12250 | C21: ENERO | D21: LUZ | F21: 121.6 | G21: =+G20+E21-F21 -> 64.8
A22: 42786 | B22: 12250 | C22: ENERO | D22: AGUA | F22: 2.8 | G22: =+G21+E22-F22 -> 62
A23: 42949 | B23: TARJETA | C23: ENERO | D23: P. SOCIAL | F23: 2 | G23: =+G22+E23-F23 -> 60
A24: 42949 | B24: TARJETA | C24: ENERO | D24: G. ADM | F24: 60 | G24: =+G23+E24-F24 -> 0
A25: 42794 | B25: POR COBRAR | C25: FEBRERO | D25: LUZ | E25: 124.3 | G25: =+G24+E25-F25 -> 124.3
D26: AGUA | E26: 2 | G26: =+G25+E26-F26 -> 126.3
D27: G. ADM | E27: 56 | G27: =+G26+E27-F27 -> 182.3
D28: P. SOCIAL | E28: 2 | G28: =+G27+E28-F28 -> 184.3
A29: 42788 | B29: TARJETA | C29: FEBRERO | D29: G. ADM | F29: 10 | G29: =+G28+E29-F29 -> 174.3
A30: 42821 | B30: 12523 | C30: FEBRERO | D30: LUZ | F30: 124.3 | G30: =+G29+E30-F30 -> 50
A31: 42821 | B31: 12523 | C31: FEBRERO | D31: AGUA | F31: 2 | G31: =+G30+E31-F31 -> 48
A32: 42822 | B32: 12595 | C32: FEBRERO | D32: G. ADM | F32: 46 | G32: =+G31+E32-F32 -> 2
A33: 42822 | B33: 12595 | C33: FEBRERO | D33: P. SOCIAL | F33: 2 | G33: =+G32+E33-F33 -> 1.4210855e-14
A34: 42825 | B34: POR COBRAR | C34: MARZO | D34: LUZ | E34: 118.8 | G34: =+G33+E34-F34 -> 118.8
D35: AGUA | E35: 2 | G35: =+G34+E35-F35 -> 120.8
D36: G. ADM | E36: 60 | G36: =+G35+E36-F36 -> 180.8
D37: P. SOCIAL | E37: 2 | G37: =+G36+E37-F37 -> 182.8
A38: 42870 | B38: 12749 | C38: MARZO | D38: LUZ | F38: 118.8 | G38: =+G37+E38-F38 -> 64
A39: 42870 | B39: 12749 | C39: MARZO | D39: AGUA | F39: 2 | G39: =+G38+E39-F39 -> 62
A40: 42949 | B40: 13379 | C40: MARZO | D40: G. ADM | F40: 60 | G40: =+G39+E40-F40 -> 2
A41: 42949 | B41: 13379 | C41: MARZO | D41: P. SOCIAL | F41: 2 | G41: =+G40+E41-F41 -> 1.4210855e-14
A42: 42855 | B42: POR COBRAR | C42: ABRIL | D42: LUZ | E42: 121.7 | G42: =+G41+E42-F42 -> 121.7
D43: AGUA | E43: 2 | G43: =+G42+E43-F43 -> 123.7
D44: G. ADM | E44: 60 | G44: =+G43+E44-F44 -> 183.7
D45: P. SOCIAL | E45: 2 | G45: =+G44+E45-F45 -> 185.7
A46: 42892 | B46: 13067 | C46: ABRIL | D46: LUZ | F46: 121.7 | G46: =+G45+E46-F46 -> 64
A47: 42892 | B47: 13067 | C47: ABRIL | D47: AGUA | F47: 2 | G47: =+G46+E47-F47 -> 62
A48: 42949 | B48: 13379 | C48: ABRIL | D48: G. ADM | F48: 60 | G48: =+G47+E48-F48 -> 2
A49: 42949 | B49: 13379 | C49: ABRIL | D49: P. SOCIAL | F49: 2 | G49: =+G48+E49-F49 -> 1.4210855e-14
A50: 42886 | B50: POR COBRAR | C50: MAYO | D50: LUZ | E50: 116.1 | G50: =+G49+E50-F50 -> 116.1
D51: AGUA | E51: 2 | G51: =+G50+E51-F51 -> 118.1
D52: G. ADM | E52: 60 | G52: =+G51+E52-F52 -> 178.1
D53: P. SOCIAL | E53: 2 | G53: =+G52+E53-F53 -> 180.1
A54: 42943 | B54: 13276 | C54: MAYO | D54: LUZ | F54: 116.1 | G54: =+G53+E54-F54 -> 64
A55: 42943 | B55: 13276 | C55: MAYO | D55: AGUA | F55: 2 | G55: =+G54+E55-F55 -> 62
A56: 42949 | B56: 13379 | C56: MAYO | D56: G. ADM | F56: 60 | G56: =+G55+E56-F56 -> 2
A57: 42949 | B57: 13379 | C57: MAYO | D57: P. SOCIAL | F57: 2 | G57: =+G56+E57-F57 -> 2.8421709e-14
A58: 42916 | B58: POR COBRAR | C58: JUNIO | D58: LUZ | E58: 103.7 | G58: =+G57+E58-F58 -> 103.7
D59: AGUA | E59: 2 | G59: =+G58+E59-F59 -> 105.7
D60: G. ADM | E60: 60 | G60: =+G59+E60-F60 -> 165.7
D61: P. SOCIAL | E61: 2 | G61: =+G60+E61-F61 -> 167.7
A62: 42943 | B62: 13276 | C62: JUNIO | D62: LUZ | F62: 103.7 | G62: =+G61+E62-F62 -> 64
A63: 42943 | B63: 13276 | C63: JUNIO | D63: AGUA | F63: 2 | G63: =+G62+E63-F63 -> 62
A64: 42949 | B64: 13379 | C64: JUNIO | D64: G. ADM | F64: 60 | G64: =+G63+E64-F64 -> 2
A65: 42949 | B65: 13379 | C65: JUNIO | D65: P. SOCIAL | F65: 2 | G65: =+G64+E65-F65 -> 4.2632564e-14
A66: 42947 | B66: POR COBRAR | C66: JULIO | D66: LUZ | E66: 103.4 | G66: =+G65+E66-F66 -> 103.4
D67: AGUA | E67: 2 | G67: =+G66+E67-F67 -> 105.4
D68: G. ADM | E68: 60 | G68: =+G67+E68-F68 -> 165.4
D69: P. SOCIAL | E69: 2 | G69: =+G68+E69-F69 -> 167.4
A70: 42949 | B70: 13379 | C70: JULIO | D70: G. ADM | F70: 60 | G70: =+G69+E70-F70 -> 107.4
A71: 42949 | B71: 13379 | C71: JULIO | D71: P. SOCIAL | F71: 2 | G71: =+G70+E71-F71 -> 105.4
A72: 42984 | B72: 13550 | C72: JULIO | D72: LUZ | F72: 103.4 | G72: =+G71+E72-F72 -> 2
A73: 42984 | B73: 13550 | C73: JULIO | D73: AGUA | F73: 2 | G73: =+G72+E73-F73 -> 2.8421709e-14
A74: 42978 | B74: POR COBRAR | C74: AGOSTO | D74: LUZ | E74: 103.4 | G74: =+G73+E74-F74 -> 103.4
D75: AGUA | E75: 2 | G75: =+G74+E75-F75 -> 105.4
D76: G. ADM | E76: 60 | G76: =+G75+E76-F76 -> 165.4
D77: P. SOCIAL | E77: 2 | G77: =+G76+E77-F77 -> 167.4
A78: 43052 | B78: 13969 | C78: AGOSTO | D78: LUZ | F78: 103.4 | G78: =+G77+E78-F78 -> 64
A79: 43052 | B79: 13969 | C79: AGOSTO | D79: AGUA | F79: 2 | G79: =+G78+E79-F79 -> 62
A80: 43052 | B80: 13969 | C80: AGOSTO | D80: G. ADM | F80: 60 | G80: =+G79+E80-F80 -> 2
A81: 43052 | B81: 13969 | C81: AGOSTO | D81: P. SOCIAL | F81: 2 | G81: =+G80+E81-F81 -> 2.8421709e-14
A82: 43008 | B82: POR COBRAR | C82: SEPTIEMBRE | D82: LUZ | E82: 69.2 | G82: =+G81+E82-F82 -> 69.2
D83: AGUA | E83: 2 | G83: =+G82+E83-F83 -> 71.2
D84: G. ADM | E84: 60 | G84: =+G83+E84-F84 -> 131.2
D85: P. SOCIAL | E85: 2 | G85: =+G84+E85-F85 -> 133.2
A86: 42823 | D86: MULTA | E86: 85 | G86: =+G85+E86-F86 -> 218.2
A87: 43052 | B87: 13969 | C87: SEPTIEMBRE | D87: LUZ | F87: 69.2 | G87: =+G86+E87-F87 -> 149
A88: 43052 | B88: 13969 | C88: SEPTIEMBRE | D88: AGUA | F88: 2 | G88: =+G87+E88-F88 -> 147
A89: 43052 | B89: 13969 | C89: SEPTIEMBRE | D89: G. ADM | F89: 60 | G89: =+G88+E89-F89 -> 87
A90: 43052 | B90: 13969 | C90: SEPTIEMBRE | D90: P. SOCIAL | F90: 2 | G90: =+G89+E90-F90 -> 85
A91: 43216 | B91: 15227 | C91: SEPTIEMBRE | D91: MULTA | F91: 85 | G91: =+G90+E91-F91 -> 0
A92: 43039 | B92: POR COBRAR | C92: OCTUBRE | D92: LUZ | E92: 68.8 | G92: =+G91+E92-F92 -> 68.8
D93: AGUA | E93: 2 | G93: =+G92+E93-F93 -> 70.8
D94: G. ADM | E94: 60 | G94: =+G93+E94-F94 -> 130.8
D95: P. SOCIAL | E95: 2 | G95: =+G94+E95-F95 -> 132.8
A96: 43066 | B96: 14102 | C96: OCTUBRE | D96: LUZ | F96: 68.8 | G96: =+G95+E96-F96 -> 64
A97: 43066 | B97: 14102 | C97: OCTUBRE | D97: AGUA | F97: 2 | G97: =+G96+E97-F97 -> 62
