Workbook

Sheet ROJAS LIONILA
B2: ROJAS IGNACIO LEONILA
A4: FECHA | B4: DOCUMENTO | C4: PERIODO | D4: CONCEPTO | E4: POR COBRAR | F4: PAGADO | G4: SALDO POR COBRAR
A5: 42736 | B5: SALDO AL 2016 | G5: 2385
A6: 42745 | B6: 12093 | C6: A CUENTA 2016 | F6: 62 | G6: =+G5+E6-F6 -> 2323
A7: 42802 | B7: 12409 | C7: A CUENTA 2016 | F7: 103 | G7: =+G6+E7-F7 -> 2220
A8: 42877 | B8: 12796 | C8: A CUENTA 2016 | F8: 73.8 | G8: =+G7+E8-F8 -> 2146.2
A9: 44848 | B9: R 25629 | C9: A CUENTA 2016 | F9: 914 | G9: =+G8+E9-F9 -> 1232.2
A10: 44848 | B10: R 25629 | C10: MULTAS 2016 | F10: 616.3 | G10: =+G9+E10-F10 -> 615.9
A11: 44847 | B11: EXONERACION | C11: MULTAS 50% | F11: 615.9 | G11: =+G10+E11-F11 -> 0
A12: 42766 | B12: POR COBRAR | C12: ENERO | D12: LUZ | E12: 79.1 | G12: =+G11+E12-F12 -> 79.1
D13: AGUA | E13: 2.7 | G13: =+G12+E13-F13 -> 81.8
D14: G. ADM | E14: 60 | G14: =+G13+E14-F14 -> 141.8
D15: P. SOCIAL | E15: 2 | G15: =+G14+E15-F15 -> 143.8
A16: 42774 | B16: 12928 | C16: ENERO | D16: G. ADM | F16: 60 | G16: =+G15+E16-F16 -> 83.8
A17: 42774 | B17: 12928 | C17: ENERO | D17: P. SOCIAL | F17: 2 | G17: =+G16+E17-F17 -> 81.8
A18: 42877 | B18: 12796 | C18: ENERO | D18: LUZ | F18: 79.1 | G18: =+G17+E18-F18 -> 2.7
A19: 42877 | B19: 12796 | C19: ENERO | D19: AGUA | F19: 2.7 | G19: =+G18+E19-F19 -> 1.687539e-14
A20: 42794 | B20: POR COBRAR | C20: FEBRERO | D20: LUZ | E20: 74.6 | G20: =+G19+E20-F20 -> 74.6
D21: AGUA | E21: 2 | G21: =+G20+E21-F21 -> 76.6
D22: G. ADM | E22: 56 | G22: =+G21+E22-F22 -> 132.6
D23: P. SOCIAL | E23: 2 | G23: =+G22+E23-F23 -> 134.6
D24: MULTA | E24: 85 | G24: =+G23+E24-F24 -> 219.6
A25: 42801 | B25: 12401 | C25: FEBRERO | D25: ALQUILER | F25: 56 | G25: =+G24+E25-F25 -> 163.6
A26: 42801 | B26: 12401 | C26: FEBRERO | D26: P. SOCIAL | F26: 2 | G26: =+G25+E26-F26 -> 161.6
A27: 42877 | B27: 12796 | C27: FEBRERO | D27: LUZ | F27: 74.6 | G27: =+G26+E27-F27 -> 87
A28: 42877 | B28: 12796 | C28: FEBRERO | D28: AGUA | F28: 2 | G28: =+G27+E28-F28 -> 85
A29: 43067 | B29: EXONERACION | C29: FEBRERO | D29: MULTA | F29: 85 | G29: =+G28+E29-F29 -> 0
A30: 42825 | B30: POR COBRAR | C30: MARZO | D30: LUZ | E30: 73.2 | G30: =+G29+E30-F30 -> 73.2
D31: AGUA | E31: 2 | G31: =+G30+E31-F31 -> 75.2
D32: G. ADM | E32: 60 | G32: =+G31+E32-F32 -> 135.2
D33: P. SOCIAL | E33: 2 | G33: =+G32+E33-F33 -> 137.2
A34: 42833 | B34: 12636 | C34: MARZO | D34: G. ADM | F34: 60 | G34: =+G33+E34-F34 -> 77.2
A35: 42833 | B35: 12636 | C35: MARZO | D35: P. SOCIAL | F35: 2 | G35: =+G34+E35-F35 -> 75.2
A36: 42885 | B36: 13002 | C36: MARZO | D36: LUZ | F36: 73.2 | G36: =+G35+E36-F36 -> 2
A37: 42885 | B37: 13002 | C37: MARZO | D37: AGUA | F37: 2 | G37: =+G36+E37-F37 -> -1.4210855e-14
A38: 42855 | B38: POR COBRAR | C38: ABRIL | D38: LUZ | E38: 51.8 | G38: =+G37+E38-F38 -> 51.8
D39: AGUA | E39: 2 | G39: =+G38+E39-F39 -> 53.8
D40: G. ADM | E40: 60 | G40: =+G39+E40-F40 -> 113.8
D41: P. SOCIAL | E41: 2 | G41: =+G40+E41-F41 -> 115.8
A42: 42861 | B42: 12728 | C42: ABRIL | D42: G. ADM | F42: 60 | G42: =+G41+E42-F42 -> 55.8
A43: 42861 | B43: 12728 | C43: ABRIL | D43: P. SOCIAL | F43: 2 | G43: =+G42+E43-F43 -> 53.8
A44: 43019 | B44: 13815 | C44: ABRIL | D44: LUZ | F44: 51.8 | G44: =+G43+E44-F44 -> 2
A45: 43019 | B45: 13815 | C45: ABRIL | D45: AGUA | F45: 2 | G45: =+G44+E45-F45 -> -1.4210855e-14
A46: 42886 | B46: POR COBRAR | C46: MAYO | D46: LUZ | E46: 49.8 | G46: =+G45+E46-F46 -> 49.8
D47: AGUA | E47: 2 | G47: =+G46+E47-F47 -> 51.8
D48: G. ADM | E48: 60 | G48: =+G47+E48-F48 -> 111.8
D49: P. SOCIAL | E49: 2 | G49: =+G48+E49-F49 -> 113.8
A50: 42921 | B50: 13185 | C50: MAYO | D50: G. ADM | F50: 60 | G50: =+G49+E50-F50 -> 53.8
A51: 42921 | B51: 13185 | C51: MAYO | D51: P. SOCIAL | F51: 2 | G51: =+G50+E51-F51 -> 51.8
A52: 43019 | B52: 13815 | C52: MAYO | D52: LUZ | F52: 49.8 | G52: =+G51+E52-F52 -> 2
A53: 43019 | B53: 13815 | C53: MAYO | D53: AGUA | F53: 2 | G53: =+G52+E53-F53 -> -1.4210855e-14
A54: 42916 | B54: POR COBRAR | C54: JUNIO | D54: LUZ | E54: 48.3 | G54: =+G53+E54-F54 -> 48.3
D55: AGUA | E55: 2 | G55: =+G54+E55-F55 -> 50.3
D56: G. ADM | E56: 60 | G56: =+G55+E56-F56 -> 110.3
D57: P. SOCIAL | E57: 2 | G57: =+G56+E57-F57 -> 112.3
A58: 42921 | B58: 13184 | C58: JUNIO | D58: G. ADM | F58: 60 | G58: =+G57+E58-F58 -> 52.3
A59: 42921 | B59: 13184 | C59: JUNIO | D59: G. ADM | F59: 2 | G59: =+G58+E59-F59 -> 50.3
A60: 43019 | B60: 13815 | C60: JUNIO | D60: LUZ | F60: 48.3 | G60: =+G59+E60-F60 -> 2
A61: 43019 | B61: 13815 | C61: JUNIO | D61: AGUA | F61: 2 | G61: =+G60+E61-F61 -> -1.4210855e-14
A62: 42947 | B62: POR COBRAR | C62: JULIO | D62: LUZ | E62: 46.4 | G62: =+G61+E62-F62 -> 46.4
D63: AGUA | E63: 2 | G63: =+G62+E63-F63 -> 48.4
D64: G. ADM | E64: 60 | G64: =+G63+E64-F64 -> 108.4
D65: P. SOCIAL | E65: 2 | G65: =+G64+E65-F65 -> 110.4
A66: 42954 | B66: 13424 | C66: JULIO | D66: G. ADM | F66: 60 | G66: =+G65+E66-F66 -> 50.4
A67: 42954 | B67: 13424 | C67: JULIO | D67: P. SOCIAL | F67: 2 | G67: =+G66+E67-F67 -> 48.4
A68: 43073 | B68: 14215 | C68: JULIO | D68: LUZ | F68: 46.4 | G68: =+G67+E68-F68 -> 2
A69: 43073 | B69: 14215 | C69: JULIO | D69: AGUA | F69: 2 | G69: =+G68+E69-F69 -> -2.1316282e-14
A70: 42978 | B70: POR COBRAR | C70: AGOSTO | D70: LUZ | E70: 46.4 | G70: =+G69+E70-F70 -> 46.4
D71: AGUA | E71: 2 | G71: =+G70+E71-F71 -> 48.4
D72: G. ADM | E72: 60 | G72: =+G71+E72-F72 -> 108.4
D73: P. SOCIAL | E73: 2 | G73: =+G72+E73-F73 -> 110.4
D74: MULTA | E74: 85 | G74: =+G73+E74-F74 -> 195.4
A75: 43046 | B75: 13937 | C75: AGOSTO | D75: G. ADM | F75: 60 | G75: =+G74+E75-F75 -> 135.4
A76: 43046 | B76: 13937 | C76: AGOSTO | D76: P. SOCIAL | F76: 2 | G76: =+G75+E76-F76 -> 133.4
A77: 43073 | B77: 14215 | C77: AGOSTO | D77: LUZ | F77: 46.4 | G77: =+G76+E77-F77 -> 87
A78: 43073 | B78: 14215 | C78: AGOSTO | D78: AGUA | F78: 2 | G78: =+G77+E78-F78 -> 85
A79: 43209 | B79: EXONERACION | C79: 42951 | D79: MULTA | F79: 85 | G79: =+G78+E79-F79 -> 0
A80: 43008 | B80: POR COBRAR | C80: SEPTIEMBRE | D80: LUZ | E80: 32.9 | G80: =+G79+E80-F80 -> 32.9
D81: AGUA | E81: 2 | G81: =+G80+E81-F81 -> 34.9
D82: G. ADM | E82: 60 | G82: =+G81+E82-F82 -> 94.9
D83: P. SOCIAL | E83: 2 | G83: =+G82+E83-F83 -> 96.9
A84: 42823 | D84: MULTA | E84: 85 | G84: =+G83+E84-F84 -> 181.9
A85: 43046 | B85: 13938 | C85: SEPTIEMBRE | D85: G. ADM | F85: 60 | G85: =+G84+E85-F85 -> 121.9
A86: 43046 | B86: 13938 | C86: SEPTIEMBRE | D86: P. SOCIAL | F86: 2 | G86: =+G85+E86-F86 -> 119.9
A87: 43067 | B87: EXONERACION | C87: 42823 | D87: MULTA | F87: 85 | G87: =+G86+E87-F87 -> 34.9
A88: 43073 | B88: 14215 | C88: SEPTIEMBRE | D88: LUZ | F88: 32.9 | G88: =+G87+E88-F88 -> 2
A89: 43073 | B89: 14215 | C89: SEPTIEMBRE | D89: AGUA | F89: 2 | G89: =+G88+E89-F89 -> 7.1054274e-15
A90: 43039 | B90: POR COBRAR | C90: OCTUBRE | D90: LUZ | E90: 32.7 | G90: =+G89+E90-F90 -> 32.7
D91: AGUA | E91: 2 | G91: =+G90+E91-F91 -> 34.7
D92: G. ADM | E92: 60 | G92: =+G91+E92-F92 -> 94.7
D93: P. SOCIAL | E93: 2 | G93: =+G92+E93-F93 -> 96.7
A94: 42977 | B94: ACT. SANTA ROSA | D94: CUOTA | E94: 25 | G94: =+G93+E94-F94 -> 121.7
A95: 43046 | B95: 13939 | C95: OCTUBRE | D95: G. ADM | F95: 60 | G95: =+G94+E95-F95 -> 61.7
A96: 43046 | B96: 13939 | C96: OCTUBRE | D96: P. SOCIAL | F96: 2 | G96: =+G95+E96-F96 -> 59.7
A97: 43073 | B97: 14215 | C97: OCTUBRE | D97: LUZ | F97: 32.7 | G97: =+G96+E97-F97 -> 27
A98: 43073 | B98: 14215 | C98: OCTUBRE | D98: AGUA | F98: 2 | G98: =+G97+E98-F98 -> 25
A99: 44840 | B99: 25590 | C99: OCTUBRE | D99: CUOTA | F99: 25 | G99: =+G98+E99-F99 -> 0
A100: 43069 | B100: POR COBRAR | C100: NOVIEMBRE | D100: LUZ | E100: 35 | G100: =+G99+E100-F100 -> 35
D101: AGUA | E101: 2 | G101: =+G100+E101-F101 -> 37
D102: G. ADM | E102: 60 | G102: =+G101+E102-F102 -> 97
...

Sheet ROMERO JAVIER
B2: ROMERO NINAHUAMAN JAVIER
A4: FECHA | B4: DOCUMENTO | C4: PERIODO | D4: CONCEPTO | E4: POR COBRAR | F4: PAGADO | G4: SALDO POR COBRAR
A5: 42736 | B5: SALDO AL 2016 | G5: 324.7
A6: 42786 | B6: 12254 | C6: A CUENTA 2016 | F6: 318 | G6: =+G5+E6-F6 -> 6.7
A7: 42786 | B7: 12259 | C7: A CUENTA 2016 | F7: 6 | G7: =+G6+E7-F7 -> 0.7
A8: 43067 | B8: 14136 | C8: CANCELACION 2016 | F8: 0.7 | G8: =+G7+E8-F8 -> -1.1324275e-14
A9: 42766 | B9: POR COBRAR | C9: ENERO | D9: LUZ | E9: 68.5 | G9: =+G8+E9-F9 -> 68.5
D10: AGUA | E10: 2.8 | G10: =+G9+E10-F10 -> 71.3
D11: G. ADM | E11: 60 | G11: =+G10+E11-F11 -> 131.3
D12: P. SOCIAL | E12: 2 | G12: =+G11+E12-F12 -> 133.3
A13: 42786 | B13: 12254 | C13: ENERO | D13: G. ADM | F13: 60 | G13: =+G12+E13-F13 -> 73.3
A14: 42786 | B14: 12254 | C14: ENERO | D14: P. SOCIAL | F14: 2 | G14: =+G13+E14-F14 -> 71.3
A15: 42786 | B15: 12254 | C15: ENERO | D15: LUZ | F15: 68.5 | G15: =+G14+E15-F15 -> 2.8
A16: 42786 | B16: 12259 | C16: ENERO | D16: AGUA | F16: 2.8 | G16: =+G15+E16-F16 -> -1.687539e-14
A17: 42794 | B17: POR COBRAR | C17: FEBRERO | D17: LUZ | E17: 69.8 | G17: =+G16+E17-F17 -> 69.8
D18: AGUA | E18: 2 | G18: =+G17+E18-F18 -> 71.8
D19: G. ADM | E19: 56 | G19: =+G18+E19-F19 -> 127.8
D20: P. SOCIAL | E20: 2 | G20: =+G19+E20-F20 -> 129.8
A21: 42821 | B21: 12538 | C21: FEBRERO | D21: G. ADM | F21: 56 | G21: =+G20+E21-F21 -> 73.8
A22: 42821 | B22: 12538 | C22: FEBRERO | D22: P. SOCIAL | F22: 2 | G22: =+G21+E22-F22 -> 71.8
A23: 42821 | B23: 12538 | C23: FEBRERO | D23: LUZ | F23: 69.8 | G23: =+G22+E23-F23 -> 2
A24: 42821 | B24: 12538 | C24: FEBRERO | D24: AGUA | F24: 2 | G24: =+G23+E24-F24 -> -1.4210855e-14
A25: 42825 | B25: POR COBRAR | C25: MARZO | D25: LUZ | E25: 65.5 | G25: =+G24+E25-F25 -> 65.5
D26: AGUA | E26: 2 | G26: =+G25+E26-F26 -> 67.5
D27: G. ADM | E27: 60 | G27: =+G26+E27-F27 -> 127.5
D28: P. SOCIAL | E28: 2 | G28: =+G27+E28-F28 -> 129.5
A29: 42886 | B29: 13011 | C29: MARZO | D29: LUZ | F29: 65.5 | G29: =+G28+E29-F29 -> 64
A30: 42886 | B30: 13011 | C30: MARZO | D30: AGUA | F30: 2 | G30: =+G29+E30-F30 -> 62
A31: 43067 | B31: 14136 | C31: MARZO | D31: G. ADM | F31: 60 | G31: =+G30+E31-F31 -> 2
A32: 43067 | B32: 14136 | C32: MARZO | D32: P. SOCIAL | F32: 2 | G32: =+G31+E32-F32 -> 0
A33: 42855 | B33: POR COBRAR | C33: ABRIL | D33: LUZ | E33: 67.9 | G33: =+G32+E33-F33 -> 67.9
D34: AGUA | E34: 2 | G34: =+G33+E34-F34 -> 69.9
D35: G. ADM | E35: 60 | G35: =+G34+E35-F35 -> 129.9
D36: P. SOCIAL | E36: 2 | G36: =+G35+E36-F36 -> 131.9
A37: 42886 | B37: 13011 | C37: ABRIL | D37: LUZ | F37: 67.9 | G37: =+G36+E37-F37 -> 64
A38: 42886 | B38: 13011 | C38: ABRIL | D38: AGUA | F38: 2 | G38: =+G37+E38-F38 -> 62
A39: 43067 | B39: 14136 | C39: ABRIL | D39: G. ADM | F39: 60 | G39: =+G38+E39-F39 -> 2
A40: 43067 | B40: 14136 | C40: ABRIL | D40: P. SOCIAL | F40: 2 | G40: =+G39+E40-F40 -> 0
A41: 42886 | B41: POR COBRAR | C41: MAYO | D41: LUZ | E41: 64.6 | G41: =+G40+E41-F41 -> 64.6
D42: AGUA | E42: 2 | G42: =+G41+E42-F42 -> 66.6
D43: G. ADM | E43: 60 | G43: =+G42+E43-F43 -> 126.6
D44: P. SOCIAL | E44: 2 | G44: =+G43+E44-F44 -> 128.6
A45: 42975 | B45: 13513 | C45: MAYO | D45: LUZ | F45: 64.6 | G45: =+G44+E45-F45 -> 64
A46: 42975 | B46: 13513 | C46: MAYO | D46: AGUA | F46: 2 | G46: =+G45+E46-F46 -> 62
A47: 43067 | B47: 14136 | C47: MAYO | D47: G. ADM | F47: 60 | G47: =+G46+E47-F47 -> 2
A48: 43067 | B48: 14136 | C48: MAYO | D48: P. SOCIAL | F48: 2 | G48: =+G47+E48-F48 -> 0
A49: 42916 | B49: POR COBRAR | C49: JUNIO | D49: LUZ | E49: 63.4 | G49: =+G48+E49-F49 -> 63.4
D50: AGUA | E50: 2 | G50: =+G49+E50-F50 -> 65.4
D51: G. ADM | E51: 60 | G51: =+G50+E51-F51 -> 125.4
D52: P. SOCIAL | E52: 2 | G52: =+G51+E52-F52 -> 127.4
A53: 42975 | B53: 13513 | C53: JUNIO | D53: LUZ | F53: 63.4 | G53: =+G52+E53-F53 -> 64
A54: 42975 | B54: 13513 | C54: JUNIO | D54: AGUA | F54: 2 | G54: =+G53+E54-F54 -> 62
A55: 43067 | B55: 14136 | C55: JUNIO | D55: G. ADM | F55: 60 | G55: =+G54+E55-F55 -> 2
A56: 43067 | B56: 14136 | C56: JUNIO | D56: P. SOCIAL | F56: 2 | G56: =+G55+E56-F56 -> 0
A57: 42947 | B57: POR COBRAR | C57: JULIO | D57: LUZ | E57: 59.2 | G57: =+G56+E57-F57 -> 59.2
D58: AGUA | E58: 2 | G58: =+G57+E58-F58 -> 61.2
D59: G. ADM | E59: 60 | G59: =+G58+E59-F59 -> 121.2
D60: P. SOCIAL | E60: 2 | G60: =+G59+E60-F60 -> 123.2
A61: 42975 | B61: 13513 | C61: JULIO | D61: LUZ | F61: 59.2 | G61: =+G60+E61-F61 -> 64
A62: 42975 | B62: 13513 | C62: JULIO | D62: AGUA | F62: 2 | G62: =+G61+E62-F62 -> 62
A63: 43067 | B63: 14137 | C63: JULIO | D63: G. ADM | F63: 60 | G63: =+G62+E63-F63 -> 2
A64: 43067 | B64: 14137 | C64: JULIO | D64: P. SOCIAL | F64: 2 | G64: =+G63+E64-F64 -> 0
A65: 42978 | B65: POR COBRAR | C65: AGOSTO | D65: LUZ | E65: 59.2 | G65: =+G64+E65-F65 -> 59.2
D66: AGUA | E66: 2 | G66: =+G65+E66-F66 -> 61.2
D67: G. ADM | E67: 60 | G67: =+G66+E67-F67 -> 121.2
D68: P. SOCIAL | E68: 2 | G68: =+G67+E68-F68 -> 123.2
D69: MULTA | E69: 85 | G69: =+G68+E69-F69 -> 208.2
A70: 43033 | B70: 13883 | C70: AGOSTO | D70: LUZ | F70: 59.2 | G70: =+G69+E70-F70 -> 149
A71: 43033 | B71: 13883 | C71: AGOSTO | D71: AGUA | F71: 2 | G71: =+G70+E71-F71 -> 147
A72: 43067 | B72: 14137 | C72: AGOSTO | D72: G. ADM | F72: 60 | G72: =+G71+E72-F72 -> 87
A73: 43067 | B73: 14137 | C73: AGOSTO | D73: P. SOCIAL | F73: 2 | G73: =+G72+E73-F73 -> 85
A74: 43067 | B74: 14137 | C74: AGOSTO | D74: MULTA | F74: 85 | G74: =+G73+E74-F74 -> 0
A75: 43008 | B75: POR COBRAR | C75: SEPTIEMBRE | D75: LUZ | E75: 38.2 | G75: =+G74+E75-F75 -> 38.2
D76: AGUA | E76: 1.3 | G76: =+G75+E76-F76 -> 39.5
D77: G. ADM | E77: 60 | G77: =+G76+E77-F77 -> 99.5
D78: P. SOCIAL | E78: 2 | G78: =+G77+E78-F78 -> 101.5
A79: 43033 | B79: 13888 | C79: SEPTIEMBRE | D79: LUZ | F79: 38.2 | G79: =+G78+E79-F79 -> 63.3
A80: 43033 | B80: 13888 | C80: SEPTIEMBRE | D80: AGUA | F80: 1.3 | G80: =+G79+E80-F80 -> 62
A81: 43067 | B81: 14137 | C81: SEPTIEMBRE | D81: G. ADM | F81: 60 | G81: =+G80+E81-F81 -> 2
A82: 43067 | B82: 14137 | C82: SEPTIEMBRE | D82: P. SOCIAL | F82: 2 | G82: =+G81+E82-F82 -> 0
A83: 43039 | B83: POR COBRAR | C83: OCTUBRE | D83: LUZ | E83: 38 | G83: =+G82+E83-F83 -> 38
D84: AGUA | E84: 2.7 | G84: =+G83+E84-F84 -> 40.7
D85: G. ADM | E85: 60 | G85: =+G84+E85-F85 -> 100.7
D86: P. SOCIAL | E86: 2 | G86: =+G85+E86-F86 -> 102.7
A87: 43067 | B87: 14137 | C87: OCTUBRE | D87: G. ADM | F87: 60 | G87: =+G86+E87-F87 -> 42.7
A88: 43067 | B88: 14137 | C88: OCTUBRE | D88: P. SOCIAL | F88: 2 | G88: =+G87+E88-F88 -> 40.7
A89: 43067 | B89: 14137 | C89: OCTUBRE | D89: LUZ | F89: 38 | G89: =+G88+E89-F89 -> 2.7
A90: 43067 | B90: 14137 | C90: OCTUBRE | D90: AGUA | F90: 2.7 | G90: =+G89+E90-F90 -> 0
A91: 43069 | B91: POR COBRAR | C91: NOVIEMBRE | D91: LUZ | E91: 40.6 | G91: =+G90+E91-F91 -> 40.6
D92: AGUA | E92: 2 | G92: =+G91+E92-F92 -> 42.6
D93: G. ADM | E93: 60 | G93: =+G92+E93-F93 -> 102.6
D94: P. SOCIAL | E94: 2 | G94: =+G93+E94-F94 -> 104.6
D95: P. S X FALL. FLORES EMMA | E95: 10 | G95: =+G94+E95-F95 -> 114.6
A96: 43067 | B96: 14137 | C96: NOVIEMBRE | D96: P. S X FALL. FLORES EMMA | F96: 10 | G96: =+G95+E96-F96 -> 104.6
A97: 43145 | B97: 14615 | C97: NOVIEMBRE | D97: LUZ | F97: 40.6 | G97: =+G96+E97-F97 -> 64
A98: 43145 | B98: 14615 | C98: NOVIEMBRE | D98: AGUA | F98: 2 | G98: =+G97+E98-F98 -> 62
A99: 43185 | B99: 14980 | C99: NOVIEMBRE | D99: G. ADM | F99: 60 | G99: =+G98+E99-F99 -> 2
A100: 43185 | B100: 14980 | C100: NOVIEMBRE | D100: P. SOCIAL | F100: 2 | G100: =+G99+E100-F100 -> -7.1054274e-15
A101: 43100 | B101: POR COBRAR | C101: DICIEMBRE | D101: LUZ | E101: 44.1 | G101: =+G100+E101-F101 -> 44.1
D102: AGUA | E102: 2 | G102: =+G101+E102-F102 -> 46.1
...

Sheet ROMERO ESTEBAN
B2: ROMERO YSLA ESTEBAN LIDIO
A4: FECHA | B4: DOCUMENTO | C4: PERIODO | D4: CONCEPTO | E4: POR COBRAR | F4: PAGADO | G4: SALDO POR COBRAR
A5: 42736 | B5: SALDO AL 2016 | G5: 7584.3
A6: 42752 | B6: 12111 | C6: A CUENTA 2016 | F6: 49.8 | G6: =+G5+E6-F6 -> 7534.5
A7: 42761 | B7: 12161 | C7: A CUENTA 2016 | F7: 250 | G7: =+G6+E7-F7 -> 7284.5
A8: 42817 | B8: 12443 | C8: A CUENTA 2016 | F8: 250 | G8: =+G7+E8-F8 -> 7034.5
A9: 42847 | B9: 12685 | C9: A CUENTA 2016 | F9: 250 | G9: =+G8+E9-F9 -> 6784.5
A10: 43060 | B10: 10201 | C10: A CUENTA 2016 | F10: 250 | G10: =+G9+E10-F10 -> 6534.5
A11: 43125 | B11: 14580 | C11: A CUENTA 2016 | F11: 500 | G11: =+G10+E11-F11 -> 6034.5
A12: 43157 | B12: 14530 | C12: A CUENTA 2016 | F12: 250 | G12: =+G11+E12-F12 -> 5784.5
A13: 43270 | B13: 15511 | C13: A CUENTA 2016 | F13: 250 | G13: =+G12+E13-F13 -> 5534.5
A14: 43318 | B14: 15930 | C14: A CUENTA 2016 | F14: 250 | G14: =+G13+E14-F14 -> 5284.5
A15: 43354 | B15: 16110 | C15: A CUENTA 2016 | F15: 500 | G15: =+G14+E15-F15 -> 4784.5
A16: 43389 | B16: 16330 | C16: A CUENTA 2016 | F16: 250 | G16: =+G15+E16-F16 -> 4534.5
A17: 43426 | B17: 16586 | C17: A CUENTA 2016 | F17: 250 | G17: =+G16+E17-F17 -> 4284.5
... A29: 44648 | B29: 24669 | C29: A CUENTA 2016 | F29: 134.5 | G29: =+G28+E29-F29 -> 0
A30: 42766 | B30: POR COBRAR | C30: ENERO | D30: LUZ | E30: 32.7 | G30: =+G29+E30-F30 -> 32.7
D31: AGUA | E31: 2.8 | G31: =+G30+E31-F31 -> 35.5
D32: G. ADM | E32: 60 | G32: =+G31+E32-F32 -> 95.5
D33: P. SOCIAL | E33: 2 | G33: =+G32+E33-F33 -> 97.5
A34: 42815 | B34: 12425 | C34: ENERO | D34: LUZ | F34: 32.7 | G34: =+G33+E34-F34 -> 64.8
A35: 42815 | B35: 12425 | C35: ENERO | D35: AGUA | F35: 2.8 | G35: =+G34+E35-F35 -> 62
A36: 42817 | B36: 12444 | C36: ENERO | D36: G. ADM | F36: 60 | G36: =+G35+E36-F36 -> 2
A37: 42817 | B37: 12444 | C37: ENERO | D37: P. SOCIAL | F37: 2 | G37: =+G36+E37-F37 -> 0
A38: 42794 | B38: POR COBRAR | C38: FEBRERO | D38: LUZ | E38: 32.9 | G38: =+G37+E38-F38 -> 32.9
D39: AGUA | E39: 2 | G39: =+G38+E39-F39 -> 34.9
D40: G. ADM | E40: 56 | G40: =+G39+E40-F40 -> 90.9
D41: P. SOCIAL | E41: 2 | G41: =+G40+E41-F41 -> 92.9
D42: MULTA | E42: 85 | G42: =+G41+E42-F42 -> 177.9
A43: 42815 | B43: 12425 | C43: FEBRERO | D43: LUZ | F43: 32.9 | G43: =+G42+E43-F43 -> 145
A44: 42815 | B44: 12425 | C44: FEBRERO | D44: AGUA | F44: 2 | G44: =+G43+E44-F44 -> 143
A45: 42860 | B45: 12816 | C45: FEBRERO | D45: G. ADM | F45: 56 | G45: =+G44+E45-F45 -> 87
A46: 43060 | B46: 10201 | C46: FEBRERO | D46: P. SOCIAL | F46: 2 | G46: =+G45+E46-F46 -> 85
A47: 43067 | B47: EXONERACION | C47: FEBRERO | D47: MULTA | F47: 85 | G47: =+G46+E47-F47 -> 0
A48: 42825 | B48: POR COBRAR | C48: MARZO | D48: LUZ | E48: 31.2 | G48: =+G47+E48-F48 -> 31.2
D49: AGUA | E49: 2 | G49: =+G48+E49-F49 -> 33.2
D50: G. ADM | E50: 60 | G50: =+G49+E50-F50 -> 93.2
D51: P. SOCIAL | E51: 2 | G51: =+G50+E51-F51 -> 95.2
D52: MULTA | E52: 85 | G52: =+G51+E52-F52 -> 180.2
A53: 42864 | B53: 12737 | C53: MARZO | D53: LUZ | F53: 31.2 | G53: =+G52+E53-F53 -> 149
A54: 42864 | B54: 12737 | C54: MARZO | D54: AGUA | F54: 2 | G54: =+G53+E54-F54 -> 147
A55: 42860 | B55: 12816 | C55: MARZO | D55: G. ADM | F55: 60 | G55: =+G54+E55-F55 -> 87
A56: 43060 | B56: 10201 | C56: MARZO | D56: P. SOCIAL | F56: 2 | G56: =+G55+E56-F56 -> 85
A57: 43067 | B57: EXONERACION | C57: MARZO | D57: MULTA | F57: 85 | G57: =+G56+E57-F57 -> 0
A58: 42855 | B58: POR COBRAR | C58: ABRIL | D58: LUZ | E58: 32.4 | G58: =+G57+E58-F58 -> 32.4
D59: AGUA | E59: 2 | G59: =+G58+E59-F59 -> 34.4
D60: G. ADM | E60: 60 | G60: =+G59+E60-F60 -> 94.4
D61: P. SOCIAL | E61: 2 | G61: =+G60+E61-F61 -> 96.4
A62: 42860 | B62: 12816 | C62: ABRIL | D62: G. ADM | F62: 60 | G62: =+G61+E62-F62 -> 36.4
A63: 42987 | B63: 13563 | C63: ABRIL | D63: LUZ | F63: 32.4 | G63: =+G62+E63-F63 -> 4
A64: 42996 | B64: 13598 | C64: ABRIL | D64: AGUA | F64: 2 | G64: =+G63+E64-F64 -> 2
A65: 43060 | B65: 10201 | C65: ABRIL | D65: P. SOCIAL | F65: 2 | G65: =+G64+E65-F65 -> 7.1054274e-15
A66: 42886 | B66: POR COBRAR | C66: MAYO | D66: LUZ | E66: 30.8 | G66: =+G65+E66-F66 -> 30.8
D67: AGUA | E67: 2 | G67: =+G66+E67-F67 -> 32.8
D68: G. ADM | E68: 60 | G68: =+G67+E68-F68 -> 92.8
D69: P. SOCIAL | E69: 2 | G69: =+G68+E69-F69 -> 94.8
A70: 42860 | B70: 12816 | C70: MAYO | D70: G. ADM | F70: 60 | G70: =+G69+E70-F70 -> 34.8
A71: 42987 | B71: 13563 | C71: MAYO | D71: LUZ | F71: 30.8 | G71: =+G70+E71-F71 -> 4
A72: 42996 | B72: 13598 | C72: MAYO | D72: AGUA | F72: 2 | G72: =+G71+E72-F72 -> 2
A73: 43060 | B73: 10201 | C73: MAYO | D73: P. SOCIAL | F73: 2 | G73: =+G72+E73-F73 -> 1.0658141e-14
A74: 42916 | B74: POR COBRAR | C74: JUNIO | D74: LUZ | E74: 30.3 | G74: =+G73+E74-F74 -> 30.3
D75: AGUA | E75: 2 | G75: =+G74+E75-F75 -> 32.3
D76: G. ADM | E76: 60 | G76: =+G75+E76-F76 -> 92.3
D77: P. SOCIAL | E77: 2 | G77: =+G76+E77-F77 -> 94.3
A78: 42996 | B78: 13598 | C78: JUNIO | D78: LUZ | F78: 30.3 | G78: =+G77+E78-F78 -> 64
A79: 42996 | B79: 13598 | C79: JUNIO | D79: AGUA | F79: 2 | G79: =+G78+E79-F79 -> 62
A80: 43019 | B80: 13813 | C80: JUNIO | D80: G. ADM | F80: 60 | G80: =+G79+E80-F80 -> 2
A81: 43060 | B81: 10201 | C81: JUNIO | D81: P. SOCIAL | F81: 2 | G81: =+G80+E81-F81 -> 1.4210855e-14
A82: 42947 | B82: POR COBRAR | C82: JULIO | D82: LUZ | E82: 28.3 | G82: =+G81+E82-F82 -> 28.3
D83: AGUA | E83: 2 | G83: =+G82+E83-F83 -> 30.3
D84: G. ADM | E84: 60 | G84: =+G83+E84-F84 -> 90.3
D85: P. SOCIAL | E85: 2 | G85: =+G84+E85-F85 -> 92.3
A86: 42996 | B86: 13598 | C86: JULIO | D86: LUZ | F86: 28.3 | G86: =+G85+E86-F86 -> 64
A87: 42996 | B87: 13598 | C87: JULIO | D87: AGUA | F87: 2 | G87: =+G86+E87-F87 -> 62
A88: 43019 | B88: 13813 | C88: JULIO | D88: G. ADM | F88: 60 | G88: =+G87+E88-F88 -> 2
A89: 43060 | B89: 10201 | C89: JULIO | D89: P. SOCIAL | F89: 2 | G89: =+G88+E89-F89 -> 1.4210855e-14
A90: 42978 | B90: POR COBRAR | C90: AGOSTO | D90: LUZ | E90: 28.3 | G90: =+G89+E90-F90 -> 28.3
D91: AGUA | E91: 2 | G91: =+G90+E91-F91 -> 30.3
D92: G. ADM | E92: 60 | G92: =+G91+E92-F92 -> 90.3
D93: P. SOCIAL | E93: 2 | G93: =+G92+E93-F93 -> 92.3
D94: MULTA | E94: 85 | G94: =+G93+E94-F94 -> 177.3
A95: 43209 | B95: EXONERACION | C95: 42951 | D95: MULTA | F95: 85 | G95: =+G94+E95-F95 -> 92.3
A96: 43019 | B96: 13813 | C96: AGOSTO | D96: G. ADM | F96: 60 | G96: =+G95+E96-F96 -> 32.3
A97: 43019 | B97: 13814 | C97: AGOSTO | D97: LUZ | F97: 28.3 | G97: =+G96+E97-F97 -> 4
A98: 43019 | B98: 13814 | C98: AGOSTO | D98: AGUA | F98: 2 | G98: =+G97+E98-F98 -> 2
A99: 43060 | B99: 10201 | C99: AGOSTO | D99: P. SOCIAL | F99: 2 | G99: =+G98+E99-F99 -> 1.0658141e-14
A100: 43008 | B100: POR COBRAR | C100: SEPTIEMBRE | D100: LUZ | E100: 15.5 | G100: =+G99+E100-F100 -> 15.5
D101: AGUA | E101: 2 | G101: =+G100+E101-F101 -> 17.5
D102: G. ADM | E102: 60 | G102: =+G101+E102-F102 -> 77.5
D103: P. SOCIAL | E103: 2 | G103: =+G102+E103-F103 -> 79.5
A104: 43019 | B104: 13813 | C104: SEPTIEMBRE | D104: G. ADM | F104: 60 | G104: =+G103+E104-F104 -> 19.5
A105: 43060 | B105: 10201 | C105: SEPTIEMBRE | D105: P. SOCIAL | F105: 2 | G105: =+G104+E105-F105 -> 17.5
A106: 43063 | B106: 14083 | C106: SEPTIEMBRE | D106: LUZ | F106: 15.5 | G106: =+G105+E106-F106 -> 2
A107: 43063 | B107: 14083 | C107: SEPTIEMBRE | D107: AGUA | F107: 2 | G107: =+G106+E107-F107 -> 1.4210855e-14
A108: 43039 | B108: POR COBRAR | C108: OCTUBRE | D108: LUZ | E108: 15.4 | G108: =+G107+E108-F108 -> 15.4
D109: AGUA | E109: 2 | G109: =+G108+E109-F109 -> 17.4
D110: G. ADM | E110: 60 | G110: =+G109+E110-F110 -> 77.4
D111: P. SOCIAL | E111: 2 | G111: =+G110+E111-F111 -> 79.4
A112: 43019 | B112: 13813 | C112: OCTUBRE | D112: G. ADM | F112: 60 | G112: =+G111+E112-F112 -> 19.4
A113: 43060 | B113: 10201 | C113: OCTUBRE | D113: P. SOCIAL | F113: 2 | G113: =+G112+E113-F113 -> 17.4
...

Sheet SAAVEDRA LUIS
A2: SAAVEDRA CURIPUMA LUIS HUMBERTO
A4: FECHA | B4: DOCUMENTO | C4: PERIODO | D4: CONCEPTO | E4: POR COBRAR | F4: PAGADO | G4: SALDO POR COBRAR
A5: 42736 | B5: SALDO AL 2016 | G5: 156.7
A6: 42786 | B6: 12288 | C6: A CUENTA 2016 | F6: 141.7 | G6: =+G5+E6-F6 -> 15
A7: 42786 | B7: 12292 | C7: A CUENTA 2016 | F7: 15 | G7: =+G6+E7-F7 -> 0
A8: 42766 | B8: POR COBRAR | C8: ENERO | D8: LUZ | E8: 68.5 | G8: =+G7+E8-F8 -> 68.5
D9: AGUA | E9: 2.8 | G9: =+G8+E9-F9 -> 71.3
D10: G. ADM | E10: 60 | G10: =+G9+E10-F10 -> 131.3
D11: P. SOCIAL | E11: 2 | G11: =+G10+E11-F11 -> 133.3
D12: P.S.FALLEC. | E12: 10 | G12: =+G11+E12-F12 -> 143.3
A13: 42765 | B13: TARJETA | C13: ENERO | D13: G. ADM | F13: 60 | G13: =+G12+E13-F13 -> 83.3
A14: 42765 | B14: TARJETA | C14: ENERO | D14: P. SOCIAL | F14: 2 | G14: =+G13+E14-F14 -> 81.3
A15: 42786 | B15: 12288 | C15: ENERO | D15: LUZ | F15: 68.5 | G15: =+G14+E15-F15 -> 12.8
A16: 42786 | B16: 12288 | C16: ENERO | D16: AGUA | F16: 2.8 | G16: =+G15+E16-F16 -> 10
A17: 42786 | B17: 12292 | C17: ENERO | D17: P.S.FALLEC. | F17: 10 | G17: =+G16+E17-F17 -> 0
A18: 42794 | B18: POR COBRAR | C18: FEBRERO | D18: LUZ | E18: 75.5 | G18: =+G17+E18-F18 -> 75.5
D19: AGUA | E19: 2 | G19: =+G18+E19-F19 -> 77.5
D20: G. ADM | E20: 56 | G20: =+G19+E20-F20 -> 133.5
D21: P. SOCIAL | E21: 2 | G21: =+G20+E21-F21 -> 135.5
A22: 42794 | B22: TARJETA | C22: FEBRERO | D22: G. ADM | F22: 56 | G22: =+G21+E22-F22 -> 79.5
A23: 42794 | B23: TARJETA | C23: FEBRERO | D23: P. SOCIAL | F23: 2 | G23: =+G22+E23-F23 -> 77.5
A24: 42822 | B24: 12598 | C24: FEBRERO | D24: LUZ | F24: 75.5 | G24: =+G23+E24-F24 -> 2
A25: 42822 | B25: 12598 | C25: FEBRERO | D25: AGUA | F25: 2 | G25: =+G24+E25-F25 -> 0
A26: 42825 | B26: POR COBRAR | C26: MARZO | D26: LUZ | E26: 71.9 | G26: =+G25+E26-F26 -> 71.9
D27: AGUA | E27: 2 | G27: =+G26+E27-F27 -> 73.9
D28: G. ADM | E28: 60 | G28: =+G27+E28-F28 -> 133.9
D29: P. SOCIAL | E29: 2 | G29: =+G28+E29-F29 -> 135.9
A30: 42824 | B30: TARJETA | C30: MARZO | D30: G. ADM | F30: 60 | G30: =+G29+E30-F30 -> 75.9
A31: 42824 | B31: TARJETA | C31: MARZO | D31: P. SOCIAL | F31: 2 | G31: =+G30+E31-F31 -> 73.9
A32: 42885 | B32: 12859 | C32: MARZO | D32: LUZ | F32: 71.9 | G32: =+G31+E32-F32 -> 2
A33: 42885 | B33: 12859 | C33: MARZO | D33: AGUA | F33: 2 | G33: =+G32+E33-F33 -> 0
A34: 42855 | B34: POR COBRAR | C34: ABRIL | D34: LUZ | E34: 74.4 | G34: =+G33+E34-F34 -> 74.4
D35: AGUA | E35: 2 | G35: =+G34+E35-F35 -> 76.4
D36: G. ADM | E36: 60 | G36: =+G35+E36-F36 -> 136.4
D37: P. SOCIAL | E37: 2 | G37: =+G36+E37-F37 -> 138.4
A38: 42855 | B38: TARJETA | C38: ABRIL | D38: G. ADM | F38: 60 | G38: =+G37+E38-F38 -> 78.4
A39: 42855 | B39: TARJETA | C39: ABRIL | D39: P. SOCIAL | F39: 2 | G39: =+G38+E39-F39 -> 76.4
A40: 42885 | B40: 12859 | C40: ABRIL | D40: LUZ | F40: 74.4 | G40: =+G39+E40-F40 -> 2
A41: 42885 | B41: 12859 | C41: ABRIL | D41: AGUA | F41: 2 | G41: =+G40+E41-F41 -> 0
A42: 42886 | B42: POR COBRAR | C42: MAYO | D42: LUZ | E42: 70.6 | G42: =+G41+E42-F42 -> 70.6
D43: AGUA | E43: 2 | G43: =+G42+E43-F43 -> 72.6
D44: G. ADM | E44: 60 | G44: =+G43+E44-F44 -> 132.6
D45: P. SOCIAL | E45: 2 | G45: =+G44+E45-F45 -> 134.6
A46: 42885 | B46: TARJETA | C46: MAYO | D46: G. ADM | F46: 60 | G46: =+G45+E46-F46 -> 74.6
A47: 42885 | B47: TARJETA | C47: MAYO | D47: P. SOCIAL | F47: 2 | G47: =+G46+E47-F47 -> 72.6
A48: 42949 | B48: 13344 | C48: MAYO | D48: LUZ | F48: 70.6 | G48: =+G47+E48-F48 -> 2
A49: 42949 | B49: 13344 | C49: MAYO | D49: AGUA | F49: 2 | G49: =+G48+E49-F49 -> 0
A50: 42916 | B50: POR COBRAR | C50: JUNIO | E50: 68.7 | G50: =+G49+E50-F50 -> 68.7
E51: 2 | G51: =+G50+E51-F51 -> 70.7
E52: 60 | G52: =+G51+E52-F52 -> 130.7
E53: 2 | G53: =+G52+E53-F53 -> 132.7
A54: 42916 | B54: TARJETA | C54: JUNIO | D54: G. ADM | F54: 60 | G54: =+G53+E54-F54 -> 72.7
A55: 42916 | B55: TARJETA | C55: JUNIO | D55: P. SOCIAL | F55: 2 | G55: =+G54+E55-F55 -> 70.7
A56: 42949 | B56: 13344 | C56: JUNIO | D56: AGUA | F56: 2 | G56: =+G55+E56-F56 -> 68.7
A57: 42949 | B57: 13344 | C57: JUNIO | D57: LUZ | F57: 68.7 | G57: =+G56+E57-F57 -> 0
A58: 42947 | B58: POR COBRAR | C58: JULIO | D58: LUZ | E58: 64.3 | G58: =+G57+E58-F58 -> 64.3
D59: AGUA | E59: 2 | G59: =+G58+E59-F59 -> 66.3
D60: G. ADM | E60: 60 | G60: =+G59+E60-F60 -> 126.3
D61: P. SOCIAL | E61: 2 | G61: =+G60+E61-F61 -> 128.3
A62: 42947 | B62: TARJETA | C62: JULIO | D62: G. ADM | F62: 60 | G62: =+G61+E62-F62 -> 68.3
A63: 42947 | B63: TARJETA | C63: JULIO | D63: P. SOCIAL | F63: 2 | G63: =+G62+E63-F63 -> 66.3
A64: 43001 | B64: 13663 | C64: JULIO | D64: LUZ | F64: 64.3 | G64: =+G63+E64-F64 -> 2
A65: 43001 | B65: 13663 | C65: JULIO | D65: AGUA | F65: 2 | G65: =+G64+E65-F65 -> 1.4210855e-14
A66: 42978 | B66: POR COBRAR | C66: AGOSTO | D66: LUZ | E66: 64.3 | G66: =+G65+E66-F66 -> 64.3
D67: AGUA | E67: 2 | G67: =+G66+E67-F67 -> 66.3
D68: G. ADM | E68: 60 | G68: =+G67+E68-F68 -> 126.3
D69: P. SOCIAL | E69: 2 | G69: =+G68+E69-F69 -> 128.3
A70: 42978 | B70: TARJETA | C70: AGOSTO | D70: G. ADM | F70: 60 | G70: =+G69+E70-F70 -> 68.3
A71: 42978 | B71: TARJETA | C71: AGOSTO | D71: P. SOCIAL | F71: 2 | G71: =+G70+E71-F71 -> 66.3
A72: 43001 | B72: 13663 | C72: AGOSTO | D72: LUZ | F72: 64.3 | G72: =+G71+E72-F72 -> 2
A73: 43001 | B73: 13663 | C73: AGOSTO | D73: AGUA | F73: 2 | G73: =+G72+E73-F73 -> 1.4210855e-14
A74: 43008 | B74: POR COBRAR | C74: SEPTIEMBRE | D74: LUZ | E74: 46.4 | G74: =+G73+E74-F74 -> 46.4
D75: AGUA | E75: 2 | G75: =+G74+E75-F75 -> 48.4
D76: G. ADM | E76: 60 | G76: =+G75+E76-F76 -> 108.4
D77: P. SOCIAL | E77: 2 | G77: =+G76+E77-F77 -> 110.4
A78: 43008 | B78: TARJETA | C78: SEPTIEMBRE | D78: G. ADM | F78: 60 | G78: =+G77+E78-F78 -> 50.4
A79: 43008 | B79: TARJETA | C79: SEPTIEMBRE | D79: P. SOCIAL | F79: 2 | G79: =+G78+E79-F79 -> 48.4
A80: 43067 | B80: 14127 | C80: SEPTIEMBRE | D80: LUZ | F80: 46.4 | G80: =+G79+E80-F80 -> 2
A81: 43067 | B81: 14127 | C81: SEPTIEMBRE | D81: AGUA | F81: 2 | G81: =+G80+E81-F81 -> 7.1054274e-15
A82: 43039 | B82: POR COBRAR | C82: OCTUBRE | D82: LUZ | E82: 46.2 | G82: =+G81+E82-F82 -> 46.2
D83: AGUA | E83: 2 | G83: =+G82+E83-F83 -> 48.2
D84: G. ADM | E84: 60 | G84: =+G83+E84-F84 -> 108.2
D85: P. SOCIAL | E85: 2 | G85: =+G84+E85-F85 -> 110.2
A86: 43039 | B86: TARJETA | C86: OCTUBRE | D86: G. ADM | F86: 60 | G86: =+G85+E86-F86 -> 50.2
A87: 43039 | B87: TARJETA | C87: OCTUBRE | D87: P. SOCIAL | F87: 2 | G87: =+G86+E87-F87 -> 48.2
A88: 43067 | B88: 14127 | C88: NOVIEMBRE | D88: AGUA | F88: 46.2 | G88: =+G87+E88-F88 -> 2
A89: 43067 | B89: 14127 | C89: NOVIEMBRE | D89: LUZ | F89: 2 | G89: =+G88+E89-F89 -> 1.4210855e-14
A90: 43069 | B90: POR COBRAR | C90: NOVIEMBRE | D90: LUZ | E90: 49.3 | G90: =+G89+E90-F90 -> 49.3
D91: AGUA | E91: 2 | G91: =+G90+E91-F91 -> 51.3
D92: G. ADM | E92: 60 | G92: =+G91+E92-F92 -> 111.3
D93: P. SOCIAL | E93: 2 | G93: =+G92+E93-F93 -> 113.3
A94: 43087 | B94: 14270 | C94: NOVIEMBRE | D94: LUZ | F94: 49.3 | G94: =+G93+E94-F94 -> 64
A95: 43087 | B95: 14270 | C95: NOVIEMBRE | D95: AGUA | F95: 2 | G95: =+G94+E95-F95 -> 62
A96: 43069 | B96: TARJETA | C96: NOVIEMBRE | D96: G. ADM | F96: 60 | G96: =+G95+E96-F96 -> 2
A97: 43069 | B97: TARJETA | C97: NOVIEMBRE | D97: P. SOCIAL | F97: 2 | G97: =+G96+E97-F97 -> 1.4210855e-14
A98: 43100 | B98: POR COBRAR | C98: DICIEMBRE | D98: LUZ | E98: 76 | G98: =+G97+E98-F98 -> 76
D99: AGUA | E99: 2 | G99: =+G98+E99-F99 -> 78
D100: G. ADM | E100: 60 | G100: =+G99+E100-F100 -> 138
D101: P. SOCIAL | E101: 2 | G101: =+G100+E101-F101 -> 140
A102: 43100 | B102: TARJETA | C102: DICIEMBRE | D102: G. ADM | F102: 60 | G102: =+G101+E102-F102 -> 80
...

Sheet SALAS RUTH
B2: SALAS MONTALVO RUTH
A4: FECHA | B4: DOCUMENTO | C4: PERIODO | D4: CONCEPTO | E4: POR COBRAR | F4: PAGADO | G4: SALDO POR COBRAR
A5: 42736 | B5: SALDO AL 2016 | G5: 326.8
A6: 42786 | B6: 12260 | C6: A CUENTA 2016 | F6: 267.8 | G6: =+G5+E6-F6 -> 59
A7: 42786 | B7: 12261 | C7: A CUENTA 2016 | F7: 59 | G7: =+G6+E7-F7 -> 0
A8: 42766 | B8: POR COBRAR | C8: ENERO | D8: LUZ | E8: 69.6 | G8: =+G7+E8-F8 -> 69.6
D9: AGUA | E9: 2.8 | G9: =+G8+E9-F9 -> 72.4
D10: G. ADM | E10: 60 | G10: =+G9+E10-F10 -> 132.4
D11: P. SOCIAL | E11: 2 | G11: =+G10+E11-F11 -> 134.4
A12: 42786 | B12: 12260 | C12: ENERO | D12: G. ADM | F12: 60 | G12: =+G11+E12-F12 -> 74.4
A13: 42786 | B13: 12260 | C13: ENERO | D13: P. SOCIAL | F13: 2 | G13: =+G12+E13-F13 -> 72.4
A14: 42786 | B14: 12260 | C14: ENERO | D14: AGUA | F14: 2.8 | G14: =+G13+E14-F14 -> 69.6
A15: 42786 | B15: 12260 | C15: ENERO | D15: LUZ | F15: 69.6 | G15: =+G14+E15-F15 -> 0
A16: 42794 | B16: POR COBRAR | C16: FEBRERO | D16: LUZ | E16: 70.2 | G16: =+G15+E16-F16 -> 70.2
D17: AGUA | E17: 2 | G17: =+G16+E17-F17 -> 72.2
D18: G. ADM | E18: 56 | G18: =+G17+E18-F18 -> 128.2
D19: P. SOCIAL | E19: 2 | G19: =+G18+E19-F19 -> 130.2
A20: 42821 | B20: 12539 | C20: FEBRERO | D20: G. ADM | F20: 56 | G20: =+G19+E20-F20 -> 74.2
A21: 42821 | B21: 12539 | C21: FEBRERO | D21: P. SOCIAL | F21: 2 | G21: =+G20+E21-F21 -> 72.2
A22: 42821 | B22: 12539 | C22: FEBRERO | D22: LUZ | F22: 70.2 | G22: =+G21+E22-F22 -> 2
A23: 42821 | B23: 12539 | C23: FEBRERO | D23: AGUA | F23: 2 | G23: =+G22+E23-F23 -> -1.4210855e-14
A24: 42825 | B24: POR COBRAR | C24: MARZO | D24: LUZ | E24: 66.6 | G24: =+G23+E24-F24 -> 66.6
D25: AGUA | E25: 2 | G25: =+G24+E25-F25 -> 68.6
D26: G. ADM | E26: 60 | G26: =+G25+E26-F26 -> 128.6
D27: P. SOCIAL | E27: 2 | G27: =+G26+E27-F27 -> 130.6
A28: 42886 | B28: 13012 | C28: MARZO | D28: LUZ | F28: 66.6 | G28: =+G27+E28-F28 -> 64
A29: 42886 | B29: 13012 | C29: MARZO | D29: AGUA | F29: 2 | G29: =+G28+E29-F29 -> 62
A30: 42949 | B30: 13362 | C30: MARZO | D30: P. SOCIAL | F30: 2 | G30: =+G29+E30-F30 -> 60
A31: 42949 | B31: 13362 | C31: MARZO | D31: G. ADM | F31: 60 | G31: =+G30+E31-F31 -> 0
A32: 42855 | B32: POR COBRAR | C32: ABRIL | D32: LUZ | E32: 69 | G32: =+G31+E32-F32 -> 69
D33: AGUA | E33: 2 | G33: =+G32+E33-F33 -> 71
D34: G. ADM | E34: 60 | G34: =+G33+E34-F34 -> 131
D35: P. SOCIAL | E35: 2 | G35: =+G34+E35-F35 -> 133
A36: 42886 | B36: 13012 | C36: ABRIL | D36: LUZ | F36: 69 | G36: =+G35+E36-F36 -> 64
A37: 42886 | B37: 13012 | C37: ABRIL | D37: AGUA | F37: 2 | G37: =+G36+E37-F37 -> 62
A38: 42949 | B38: 13362 | C38: ABRIL | D38: G. ADM | F38: 60 | G38: =+G37+E38-F38 -> 2
A39: 42949 | B39: 13362 | C39: ABRIL | D39: P. SOCIAL | F39: 2 | G39: =+G38+E39-F39 -> 0
A40: 42886 | B40: POR COBRAR | C40: MAYO | D40: LUZ | E40: 65.6 | G40: =+G39+E40-F40 -> 65.6
D41: AGUA | E41: 2 | G41: =+G40+E41-F41 -> 67.6
D42: G. ADM | E42: 60 | G42: =+G41+E42-F42 -> 127.6
D43: P. SOCIAL | E43: 2 | G43: =+G42+E43-F43 -> 129.6
A44: 42949 | B44: 13362 | C44: MAYO | D44: G. ADM | F44: 60 | G44: =+G43+E44-F44 -> 69.6
A45: 42949 | B45: 13362 | C45: MAYO | D45: P. SOCIAL | F45: 2 | G45: =+G44+E45-F45 -> 67.6
A46: 42949 | B46: 13362 | C46: MAYO | D46: LUZ | F46: 65.6 | G46: =+G45+E46-F46 -> 2
A47: 42949 | B47: 13362 | C47: MAYO | D47: AGUA | F47: 2 | G47: =+G46+E47-F47 -> 0
A48: 42916 | B48: POR COBRAR | C48: JUNIO | D48: LUZ | E48: 63.8 | G48: =+G47+E48-F48 -> 63.8
D49: AGUA | E49: 2 | G49: =+G48+E49-F49 -> 65.8
D50: G. ADM | E50: 60 | G50: =+G49+E50-F50 -> 125.8
D51: P. SOCIAL | E51: 2 | G51: =+G50+E51-F51 -> 127.8
A52: 42949 | B52: 13362 | C52: JUNIO | D52: G. ADM | F52: 60 | G52: =+G51+E52-F52 -> 67.8
A53: 42949 | B53: 13362 | C53: JUNIO | D53: P. SOCIAL | F53: 2 | G53: =+G52+E53-F53 -> 65.8
A54: 42949 | B54: 13362 | C54: JUNIO | D54: LUZ | F54: 63.8 | G54: =+G53+E54-F54 -> 2
A55: 42949 | B55: 13362 | C55: JUNIO | D55: AGUA | F55: 2 | G55: =+G54+E55-F55 -> 0
A56: 42947 | B56: POR COBRAR | C56: JULIO | D56: LUZ | E56: 60 | G56: =+G55+E56-F56 -> 60
D57: AGUA | E57: 2 | G57: =+G56+E57-F57 -> 62
D58: G. ADM | E58: 60 | G58: =+G57+E58-F58 -> 122
D59: P. SOCIAL | E59: 2 | G59: =+G58+E59-F59 -> 124
A60: 42949 | B60: 13362 | C60: JULIO | D60: G. ADM | F60: 60 | G60: =+G59+E60-F60 -> 64
A61: 42949 | B61: 13362 | C61: JULIO | D61: P. SOCIAL | F61: 2 | G61: =+G60+E61-F61 -> 62
A62: 43033 | B62: 13889 | C62: JULIO | D62: LUZ | F62: 60 | G62: =+G61+E62-F62 -> 2
A63: 43033 | B63: 13889 | C63: JULIO | D63: AGUA | F63: 2 | G63: =+G62+E63-F63 -> 0
A64: 42978 | B64: POR COBRAR | C64: AGOSTO | D64: LUZ | E64: 60 | G64: =+G63+E64-F64 -> 60
D65: AGUA | E65: 2 | G65: =+G64+E65-F65 -> 62
D66: G. ADM | E66: 60 | G66: =+G65+E66-F66 -> 122
D67: P. SOCIAL | E67: 2 | G67: =+G66+E67-F67 -> 124
A68: 43033 | B68: 13889 | C68: AGOSTO | D68: LUZ | F68: 60 | G68: =+G67+E68-F68 -> 64
A69: 43033 | B69: 13889 | C69: AGOSTO | D69: AGUA | F69: 2 | G69: =+G68+E69-F69 -> 62
A70: 43067 | B70: 14138 | C70: AGOSTO | D70: G. ADM | F70: 60 | G70: =+G69+E70-F70 -> 2
A71: 43067 | B71: 14138 | C71: AGOSTO | D71: P. SOCIAL | F71: 2 | G71: =+G70+E71-F71 -> 0
A72: 43008 | B72: POR COBRAR | C72: SEPTIEMBRE | D72: LUZ | E72: 46.4 | G72: =+G71+E72-F72 -> 46.4
D73: AGUA | E73: 2 | G73: =+G72+E73-F73 -> 48.4
D74: G. ADM | E74: 60 | G74: =+G73+E74-F74 -> 108.4
D75: P. SOCIAL | E75: 2 | G75: =+G74+E75-F75 -> 110.4
A76: 43067 | B76: 14138 | C76: SEPTIEMBRE | D76: LUZ | F76: 60 | G76: =+G75+E76-F76 -> 50.4
A77: 43067 | B77: 14138 | C77: SEPTIEMBRE | D77: AGUA | F77: 2 | G77: =+G76+E77-F77 -> 48.4
A78: 43067 | B78: 14138 | C78: SEPTIEMBRE | D78: LUZ | F78: 46.4 | G78: =+G77+E78-F78 -> 2
A79: 43067 | B79: 14138 | C79: SEPTIEMBRE | D79: AGUA | F79: 2 | G79: =+G78+E79-F79 -> 7.1054274e-15
A80: 43039 | B80: POR COBRAR | C80: OCTUBRE | D80: LUZ | E80: 46.2 | G80: =+G79+E80-F80 -> 46.2
D81: AGUA | E81: 2 | G81: =+G80+E81-F81 -> 48.2
D82: G. ADM | E82: 60 | G82: =+G81+E82-F82 -> 108.2
D83: P. SOCIAL | E83: 2 | G83: =+G82+E83-F83 -> 110.2
D84: FUMIGACION | E84: 10 | G84: =+G83+E84-F84 -> 120.2
A85: 43067 | B85: 14138 | C85: OCTUBRE | D85: G. ADM | F85: 60 | G85: =+G84+E85-F85 -> 60.2
A86: 43067 | B86: 14138 | C86: OCTUBRE | D86: P. SOCIAL | F86: 2 | G86: =+G85+E86-F86 -> 58.2
A87: 43067 | B87: 14138 | C87: OCTUBRE | D87: LUZ | F87: 46.2 | G87: =+G86+E87-F87 -> 12
A88: 43067 | B88: 14138 | C88: OCTUBRE | D88: AGUA | F88: 2 | G88: =+G87+E88-F88 -> 10
A89: 42928 | B89: 5749 | C89: OCTUBRE | D89: FUMIGACION | F89: 10 | G89: =+G88+E89-F89 -> 1.4210855e-14
A90: 43069 | B90: POR COBRAR | C90: NOVIEMBRE | D90: LUZ | E90: 49.3 | G90: =+G89+E90-F90 -> 49.3
D91: AGUA | E91: 2 | G91: =+G90+E91-F91 -> 51.3
D92: G. ADM | E92: 60 | G92: =+G91+E92-F92 -> 111.3
D93: P. SOCIAL | E93: 2 | G93: =+G92+E93-F93 -> 113.3
A94: 43145 | B94: 14616 | C94: NOVIEMBRE | D94: LUZ | F94: 49.3 | G94: =+G93+E94-F94 -> 64
A95: 43145 | B95: 14616 | C95: NOVIEMBRE | D95: AGUA | F95: 2 | G95: =+G94+E95-F95 -> 62
A96: 43185 | B96: 14981 | C96: NOVIEMBRE | D96: G. ADM | F96: 60 | G96: =+G95+E96-F96 -> 2
A97: 43185 | B97: 14981 | C97: NOVIEMBRE | D97: P. SOCIAL | F97: 2 | G97: =+G96+E97-F97 -> 1.4210855e-14
A98: 43100 | B98: POR COBRAR | C98: DICIEMBRE | D98: LUZ | E98: 53.6 | G98: =+G97+E98-F98 -> 53.6
D99: AGUA | E99: 2 | G99: =+G98+E99-F99 -> 55.6
D100: G. ADM | E100: 60 | G100: =+G99+E100-F100 -> 115.6
D101: P. SOCIAL | E101: 2 | G101: =+G100+E101-F101 -> 117.6
A102: 43145 | B102: 14616 | C102: DICIEMBRE | D102: LUZ | F102: 53.6 | G102: =+G101+E102-F102 -> 64
...

Sheet SALAZAR VICTORIA
B2: SALAZAR CONCEPCION VICTORIA
A4: FECHA | B4: DOCUMENTO | C4: PERIODO | D4: CONCEPTO | E4: POR COBRAR | F4: PAGADO | G4: SALDO POR COBRAR
A5: 42736 | B5: SALDO AL 2016 | G5: 23.1
A6: 42758 | B6: 12147 | C6: CANCELADO | F6: 23.1 | G6: =+G5+E6-F6 -> 0
A7: 42766 | B7: POR COBRAR | C7: ENERO | D7: LUZ | E7: 20.4 | G7: =+G6+E7-F7 -> 20.4
D8: AGUA | E8: 2.8 | G8: =+G7+E8-F8 -> 23.2
D9: G. ADM | E9: 60 | G9: =+G8+E9-F9 -> 83.2
D10: P. SOCIAL | E10: 2 | G10: =+G9+E10-F10 -> 85.2
A11: 42766 | B11: TARJETA | C11: ENERO | D11: G. ADM | F11: 60 | G11: =+G10+E11-F11 -> 25.2
A12: 42766 | B12: TARJETA | C12: ENERO | D12: P. SOCIAL | F12: 2 | G12: =+G11+E12-F12 -> 23.2
A13: 42783 | B13: 12982 | C13: ENERO | D13: LUZ | F13: 20.4 | G13: =+G12+E13-F13 -> 2.8
A14: 42783 | B14: 12982 | C14: ENERO | D14: AGUA | F14: 2.8 | G14: =+G13+E14-F14 -> 4.4408921e-15
A15: 42794 | B15: POR COBRAR | C15: FEBRERO | D15: LUZ | E15: 19.6 | G15: =+G14+E15-F15 -> 19.6
D16: AGUA | E16: 2 | G16: =+G15+E16-F16 -> 21.6
D17: G. ADM | E17: 56 | G17: =+G16+E17-F17 -> 77.6
D18: P. SOCIAL | E18: 2 | G18: =+G17+E18-F18 -> 79.6
A19: 42794 | B19: TARJETA | C19: FEBRERO | D19: G. ADM | F19: 56 | G19: =+G18+E19-F19 -> 23.6
A20: 42794 | B20: TARJETA | C20: FEBRERO | D20: P. SOCIAL | F20: 2 | G20: =+G19+E20-F20 -> 21.6
A21: 42818 | B21: 12470 | C21: FEBRERO | D21: LUZ | F21: 19.6 | G21: =+G20+E21-F21 -> 2
A22: 42818 | B22: 12470 | C22: FEBRERO | D22: AGUA | F22: 2 | G22: =+G21+E22-F22 -> 7.1054274e-15 | K22: 5
A23: 42825 | B23: POR COBRAR | C23: MARZO | D23: LUZ | E23: 18.4 | G23: =+G22+E23-F23 -> 18.4 | K23: 36000.15
D24: AGUA | E24: 2 | G24: =+G23+E24-F24 -> 20.4 | K24: 3799.6
D25: G. ADM | E25: 60 | G25: =+G24+E25-F25 -> 80.4
D26: P. SOCIAL | E26: 2 | G26: =+G25+E26-F26 -> 82.4
A27: 42824 | B27: TARJETA | C27: MARZO | D27: G. ADM | F27: 60 | G27: =+G26+E27-F27 -> 22.4
A28: 42824 | B28: TARJETA | C28: MARZO | D28: P. SOCIAL | F28: 2 | G28: =+G27+E28-F28 -> 20.4
A29: 42857 | B29: 12713 | C29: MARZO | D29: LUZ | F29: 18.4 | G29: =+G28+E29-F29 -> 2
A30: 42857 | B30: 12713 | C30: MARZO | D30: AGUA | F30: 2 | G30: =+G29+E30-F30 -> 7.1054274e-15
A31: 42855 | B31: POR COBRAR | C31: ABRIL | D31: LUZ | E31: 19.5 | G31: =+G30+E31-F31 -> 19.5
D32: AGUA | E32: 2 | G32: =+G31+E32-F32 -> 21.5
D33: G. ADM | E33: 60 | G33: =+G32+E33-F33 -> 81.5
D34: P. SOCIAL | E34: 2 | G34: =+G33+E34-F34 -> 83.5
A35: 42854 | B35: TARJETA | C35: ABRIL | D35: G. ADM | F35: 60 | G35: =+G34+E35-F35 -> 23.5
A36: 42854 | B36: TARJETA | C36: ABRIL | D36: P. SOCIAL | F36: 2 | G36: =+G35+E36-F36 -> 21.5
A37: 42948 | B37: 13314 | C37: ABRIL | D37: LUZ | F37: 19.5 | G37: =+G36+E37-F37 -> 2
A38: 42948 | B38: 13314 | C38: ABRIL | D38: AGUA | F38: 2 | G38: =+G37+E38-F38 -> 0
A39: 42886 | B39: POR COBRAR | C39: MAYO | D39: LUZ | E39: 18.9 | G39: =+G38+E39-F39 -> 18.9
D40: AGUA | E40: 2 | G40: =+G39+E40-F40 -> 20.9
D41: G. ADM | E41: 60 | G41: =+G40+E41-F41 -> 80.9
D42: P. SOCIAL | E42: 2 | G42: =+G41+E42-F42 -> 82.9
A43: 42885 | B43: TARJETA | C43: MAYO | D43: G. ADM | F43: 60 | G43: =+G42+E43-F43 -> 22.9
A44: 42885 | B44: TARJETA | C44: MAYO | D44: P. SOCIAL | F44: 2 | G44: =+G43+E44-F44 -> 20.9
A45: 42905 | B45: 13110 | C45: MAYO | D45: LUZ | F45: 18.9 | G45: =+G44+E45-F45 -> 2
A46: 42905 | B46: 13110 | C46: MAYO | D46: AGUA | F46: 2 | G46: =+G45+E46-F46 -> 7.1054274e-15
A47: 42905 | B47: POR COBRAR | C47: JUNIO | D47: LUZ | E47: 18.3 | G47: =+G46+E47-F47 -> 18.3
D48: AGUA | E48: 2 | G48: =+G47+E48-F48 -> 20.3
D49: G. ADM | E49: 60 | G49: =+G48+E49-F49 -> 80.3
D50: P. SOCIAL | E50: 2 | G50: =+G49+E50-F50 -> 82.3
A51: 42916 | B51: TARJETA | C51: JUNIO | D51: G. ADM | F51: 60 | G51: =+G50+E51-F51 -> 22.3
A52: 42916 | B52: TARJETA | C52: JUNIO | D52: P. SOCIAL | F52: 2 | G52: =+G51+E52-F52 -> 20.3
A53: 42948 | B53: 13314 | C53: JUNIO | D53: LUZ | F53: 18.3 | G53: =+G52+E53-F53 -> 2
A54: 42948 | B54: 13314 | C54: JUNIO | D54: AGUA | F54: 2 | G54: =+G53+E54-F54 -> 1.0658141e-14
A55: 42947 | B55: POR COBRAR | C55: JULIO | D55: LUZ | E55: 18.1 | G55: =+G54+E55-F55 -> 18.1
D56: AGUA | E56: 2 | G56: =+G55+E56-F56 -> 20.1
D57: G. ADM | E57: 60 | G57: =+G56+E57-F57 -> 80.1
D58: P. SOCIAL | E58: 2 | G58: =+G57+E58-F58 -> 82.1
A59: 42947 | B59: TARJETA | C59: JULIO | D59: G. ADM | F59: 60 | G59: =+G58+E59-F59 -> 22.1
A60: 42947 | B60: TARJETA | C60: JULIO | D60: P. SOCIAL | F60: 2 | G60: =+G59+E60-F60 -> 20.1
A61: 42990 | B61: 13567 | C61: JULIO | D61: LUZ | F61: 18.1 | G61: =+G60+E61-F61 -> 2
A62: 42990 | B62: 13567 | C62: JULIO | D62: AGUA | F62: 2 | G62: =+G61+E62-F62 -> 7.1054274e-15
A63: 42978 | B63: POR COBRAR | C63: AGOSTO | D63: LUZ | E63: 18.1 | G63: =+G62+E63-F63 -> 18.1
D64: AGUA | E64: 2 | G64: =+G63+E64-F64 -> 20.1
D65: G. ADM | E65: 60 | G65: =+G64+E65-F65 -> 80.1
D66: P. SOCIAL | E66: 2 | G66: =+G65+E66-F66 -> 82.1
A67: 42990 | B67: 13567 | C67: AGOSTO | D67: G. ADM | F67: 6 | G67: =+G66+E67-F67 -> 76.1
A68: 42978 | B68: TARJETA | C68: AGOSTO | D68: G. ADM | F68: 54 | G68: =+G67+E68-F68 -> 22.1
A69: 42990 | B69: 13567 | C69: AGOSTO | D69: P. SOCIAL | F69: 2 | G69: =+G68+E69-F69 -> 20.1
A70: 43018 | B70: 13811 | C70: AGOSTO | D70: LUZ | F70: 18.1 | G70: =+G69+E70-F70 -> 2
A71: 43018 | B71: 13811 | C71: AGOSTO | D71: AGUA | F71: 2 | G71: =+G70+E71-F71 -> 7.1054274e-15
A72: 43008 | B72: POR COBRAR | C72: SEPTIEMBRE | D72: LUZ | E72: 15.5 | G72: =+G71+E72-F72 -> 15.5
D73: AGUA | E73: 2 | G73: =+G72+E73-F73 -> 17.5
D74: G. ADM | E74: 60 | G74: =+G73+E74-F74 -> 77.5
D75: P. SOCIAL | E75: 2 | G75: =+G74+E75-F75 -> 79.5
A76: 42823 | D76: MULTA | E76: 85 | G76: =+G75+E76-F76 -> 164.5
A77: 43008 | B77: TARJETA | C77: SEPTIEMBRE | D77: G. ADM | F77: 60 | G77: =+G76+E77-F77 -> 104.5
A78: 43008 | B78: TARJETA | C78: SEPTIEMBRE | D78: P. SOCIAL | F78: 2 | G78: =+G77+E78-F78 -> 102.5
A79: 43049 | B79: 13956 | C79: SEPTIEMBRE | D79: LUZ | F79: 15.5 | G79: =+G78+E79-F79 -> 87
A80: 43049 | B80: 13956 | C80: SEPTIEMBRE | D80: AGUA | F80: 2 | G80: =+G79+E80-F80 -> 85
A81: 43067 | B81: EXONERACION | C81: 42823 | D81: MULTA | F81: 85 | G81: =+G80+E81-F81 -> 0
A82: 43039 | B82: POR COBRAR | C82: OCTUBRE | D82: LUZ | E82: 15.4 | G82: =+G81+E82-F82 -> 15.4
D83: AGUA | E83: 2 | G83: =+G82+E83-F83 -> 17.4
D84: G. ADM | E84: 60 | G84: =+G83+E84-F84 -> 77.4
D85: P. SOCIAL | E85: 2 | G85: =+G84+E85-F85 -> 79.4
A86: 43039 | B86: TARJETA | C86: OCTUBRE | D86: G. ADM | F86: 60 | G86: =+G85+E86-F86 -> 19.4
A87: 43039 | B87: TARJETA | C87: OCTUBRE | D87: P. SOCIAL | F87: 2 | G87: =+G86+E87-F87 -> 17.4
A88: 43063 | B88: 14078 | C88: OCTUBRE | D88: LUZ | F88: 15.4 | G88: =+G87+E88-F88 -> 2
A89: 43063 | B89: 14078 | C89: OCTUBRE | D89: AGUA | F89: 2 | G89: =+G88+E89-F89 -> 5.3290705e-15
A90: 43069 | B90: POR COBRAR | C90: NOVIEMBRE | D90: LUZ | E90: 16.4 | G90: =+G89+E90-F90 -> 16.4
D91: AGUA | E91: 2 | G91: =+G90+E91-F91 -> 18.4
D92: G. ADM | E92: 60 | G92: =+G91+E92-F92 -> 78.4
D93: P. SOCIAL | E93: 2 | G93: =+G92+E93-F93 -> 80.4
A94: 43085 | B94: 14233 | C94: NOVIEMBRE | D94: LUZ | F94: 16.4 | G94: =+G93+E94-F94 -> 64
A95: 43085 | B95: 14233 | C95: NOVIEMBRE | D95: AGUA | F95: 2 | G95: =+G94+E95-F95 -> 62
A96: 43069 | B96: TARJETA | C96: NOVIEMBRE | D96: G. ADM | F96: 60 | G96: =+G95+E96-F96 -> 2
A97: 43069 | B97: TARJETA | C97: NOVIEMBRE | D97: P. SOCIAL | F97: 2 | G97: =+G96+E97-F97 -> 0
A98: 43100 | B98: POR COBRAR | C98: DICIEMBRE | D98: LUZ | E98: 17.9 | G98: =+G97+E98-F98 -> 17.9
D99: AGUA | E99: 2 | G99: =+G98+E99-F99 -> 19.9
D100: G. ADM | E100: 60 | G100: =+G99+E100-F100 -> 79.9
D101: P. SOCIAL | E101: 2 | G101: =+G100+E101-F101 -> 81.9
A102: 43106 | B102: 14399 | C102: DICIEMBRE | D102: G. ADM | F102: 12 | G102: =+G101+E102-F102 -> 69.9
...

Sheet SALVATIERRA ALLISON
A1: SALVATIERRA OQUENDO ALLISON ADRIANA | J1: SALVATIERRA AYALA JUAN
A4: FECHA | B4: DOCUMENTO | C4: PERIODO | D4: CONCEPTO | E4: POR COBRAR | F4: PAGADO | G4: SALDO POR COBRAR
A5: 42736 | B5: SALDO AL 2016 | G5: 425
A6: 42786 | B6: 12264 | C6: A CUENTA 2016 | F6: 359 | G6: =+G5+E6-F6 -> 66
A7: 42817 | B7: 12445 | C7: A CUENTA 2016 | F7: 66 | G7: =+G6+E7-F7 -> 0
A8: 42766 | B8: POR COBRAR | C8: ENERO | D8: LUZ | E8: 97 | G8: =+G7+E8-F8 -> 97
D9: AGUA | E9: 44.6 | G9: =+G8+E9-F9 -> 141.6
D10: G. ADM | E10: 60 | G10: =+G9+E10-F10 -> 201.6
D11: P. SOCIAL | E11: 2 | G11: =+G10+E11-F11 -> 203.6
D12: P.S.FALLEC. | E12: 10 | G12: =+G11+E12-F12 -> 213.6
A13: 42765 | B13: TARJETA | C13: ENERO | D13: G. ADM | F13: 60 | G13: =+G12+E13-F13 -> 153.6
A14: 42765 | B14: TARJETA | C14: ENERO | D14: P. SOCIAL | F14: 2 | G14: =+G13+E14-F14 -> 151.6
A15: 42817 | B15: 12446 | C15: ENERO | D15: P.S.FALLEC. | F15: 10 | G15: =+G14+E15-F15 -> 141.6
A16: 42844 | B16: 12652 | C16: ENERO | D16: LUZ | F16: 97 | G16: =+G15+E16-F16 -> 44.6
A17: 42844 | B17: 12652 | C17: ENERO | D17: AGUA | F17: 36 | G17: =+G16+E17-F17 -> 8.6
A18: 42841 | B18: 12656 | C18: ENERO | D18: AGUA | F18: 8.6 | G18: =+G17+E18-F18 -> 0
A19: 42794 | B19: POR COBRAR | C19: FEBRERO | D19: LUZ | E19: 97 | G19: =+G18+E19-F19 -> 97
D20: AGUA | E20: 36 | G20: =+G19+E20-F20 -> 133
D21: G. ADM | E21: 56 | G21: =+G20+E21-F21 -> 189
D22: P. SOCIAL | E22: 2 | G22: =+G21+E22-F22 -> 191
A23: 42793 | B23: TARJETA | D23: G. ADM | F23: 54 | G23: =+G22+E23-F23 -> 137
A24: 42795 | B24: 12387 | C24: FEBRERO | D24: G. ADM | F24: 2 | G24: =+G23+E24-F24 -> 135
A25: 42795 | B25: 12387 | C25: FEBRERO | D25: P. SOCIAL | F25: 2 | G25: =+G24+E25-F25 -> 133
A26: 42844 | B26: 12652 | C26: FEBRERO | D26: LUZ | F26: 67 | G26: =+G25+E26-F26 -> 66
A27: 42873 | B27: 12764 | C27: FEBRERO | D27: LUZ | F27: 30 | G27: =+G26+E27-F27 -> 36
A28: 42873 | B28: 12764 | C28: FEBRERO | D28: AGUA | F28: 36 | G28: =+G27+E28-F28 -> 0
A29: 42825 | B29: POR COBRAR | C29: MARZO | D29: LUZ | E29: 92.9 | G29: =+G28+E29-F29 -> 92.9
D30: AGUA | E30: 37.8 | G30: =+G29+E30-F30 -> 130.7
D31: G. ADM | E31: 60 | G31: =+G30+E31-F31 -> 190.7
D32: P. SOCIAL | E32: 2 | G32: =+G31+E32-F32 -> 192.7
A33: 42824 | B33: TARJETA | C33: MARZO | D33: G. ADM | F33: 60 | G33: =+G32+E33-F33 -> 132.7
A34: 42824 | B34: TARJETA | C34: MARZO | D34: P. SOCIAL | F34: 2 | G34: =+G33+E34-F34 -> 130.7
A35: 42873 | B35: 12764 | C35: MARZO | D35: LUZ | F35: 92.9 | G35: =+G34+E35-F35 -> 37.8
A36: 42873 | B36: 12764 | C36: MARZO | D36: AGUA | F36: 37.8 | G36: =+G35+E36-F36 -> 0
A37: 42855 | B37: POR COBRAR | C37: ABRIL | D37: LUZ | E37: 77.5 | G37: =+G36+E37-F37 -> 77.5
D38: AGUA | E38: 37 | G38: =+G37+E38-F38 -> 114.5
D39: G. ADM | E39: 60 | G39: =+G38+E39-F39 -> 174.5
D40: P. SOCIAL | E40: 2 | G40: =+G39+E40-F40 -> 176.5
A41: 42855 | B41: TARJETA | C41: ABRIL | D41: G. ADM | F41: 60 | G41: =+G40+E41-F41 -> 116.5
A42: 42855 | B42: TARJETA | C42: ABRIL | D42: P. SOCIAL | F42: 2 | G42: =+G41+E42-F42 -> 114.5
A43: 42928 | B43: 13203 | C43: ABRIL | D43: LUZ | F43: 77.5 | G43: =+G42+E43-F43 -> 37
A44: 42928 | B44: 13203 | C44: ABRIL | D44: AGUA | F44: 37 | G44: =+G43+E44-F44 -> 0
A45: 42886 | B45: POR COBRAR | C45: MAYO | D45: LUZ | E45: 72.4 | G45: =+G44+E45-F45 -> 72.4
D46: AGUA | E46: 36.3 | G46: =+G45+E46-F46 -> 108.7
D47: G. ADM | E47: 60 | G47: =+G46+E47-F47 -> 168.7
D48: P. SOCIAL | E48: 2 | G48: =+G47+E48-F48 -> 170.7
A49: 42885 | B49: TARJETA | C49: MAYO | D49: G. ADM | F49: 60 | G49: =+G48+E49-F49 -> 110.7
A50: 42885 | B50: TARJETA | C50: MAYO | D50: P. SOCIAL | F50: 2 | G50: =+G49+E50-F50 -> 108.7
A51: 42928 | B51: 13203 | C51: MAYO | D51: LUZ | F51: 72.4 | G51: =+G50+E51-F51 -> 36.3
A52: 42928 | B52: 13203 | C52: MAYO | D52: AGUA | F52: 36.3 | G52: =+G51+E52-F52 -> 0
A53: 42916 | B53: POR COBRAR | C53: JUNIO | D53: LUZ | E53: 70.6 | G53: =+G52+E53-F53 -> 70.6
D54: AGUA | E54: 36 | G54: =+G53+E54-F54 -> 106.6
D55: G. ADM | E55: 60 | G55: =+G54+E55-F55 -> 166.6
D56: P. SOCIAL | E56: 2 | G56: =+G55+E56-F56 -> 168.6
A57: 42916 | B57: TARJETA | C57: JUNIO | D57: G. ADM | F57: 60 | G57: =+G56+E57-F57 -> 108.6
A58: 42916 | B58: TARJETA | C58: JUNIO | D58: P. SOCIAL | F58: 2 | G58: =+G57+E58-F58 -> 106.6
A59: 43011 | B59: 13786 | C59: JUNIO | D59: LUZ | F59: 70.6 | G59: =+G58+E59-F59 -> 36
A60: 43011 | B60: 13786 | C60: JUNIO | D60: AGUA | F60: 36 | G60: =+G59+E60-F60 -> 0
A61: 42947 | B61: POR COBRAR | C61: JULIO | D61: LUZ | E61: 64 | G61: =+G60+E61-F61 -> 64
D62: AGUA | E62: 36 | G62: =+G61+E62-F62 -> 100
D63: G. ADM | E63: 60 | G63: =+G62+E63-F63 -> 160
D64: P. SOCIAL | E64: 2 | G64: =+G63+E64-F64 -> 162
A65: 42947 | B65: TARJETA | C65: JULIO | D65: G. ADM | F65: 60 | G65: =+G64+E65-F65 -> 102
A66: 42947 | B66: TARJETA | C66: JULIO | D66: P. SOCIAL | F66: 2 | G66: =+G65+E66-F66 -> 100
A67: 43011 | B67: 13786 | C67: JULIO | D67: LUZ | F67: 64 | G67: =+G66+E67-F67 -> 36
A68: 43011 | B68: 13786 | C68: JULIO | D68: AGUA | F68: 36 | G68: =+G67+E68-F68 -> 0
A69: 42978 | B69: POR COBRAR | C69: AGOSTO | D69: LUZ | E69: 64 | G69: =+G68+E69-F69 -> 64
D70: AGUA | E70: 36 | G70: =+G69+E70-F70 -> 100
D71: G. ADM | E71: 60 | G71: =+G70+E71-F71 -> 160
D72: P. SOCIAL | E72: 2 | G72: =+G71+E72-F72 -> 162
A73: 42978 | B73: TARJETA | C73: AGOSTO | D73: G. ADM | F73: 60 | G73: =+G72+E73-F73 -> 102
A74: 42978 | B74: TARJETA | C74: AGOSTO | D74: P. SOCIAL | F74: 2 | G74: =+G73+E74-F74 -> 100
A75: 43011 | B75: 13786 | C75: AGOSTO | D75: LUZ | F75: 64 | G75: =+G74+E75-F75 -> 36
A76: 43011 | B76: 13786 | C76: AGOSTO | D76: AGUA | F76: 36 | G76: =+G75+E76-F76 -> 0
A77: 43008 | B77: POR COBRAR | C77: SEPTIEMBRE | D77: LUZ | E77: 83.2 | G77: =+G76+E77-F77 -> 83.2
D78: AGUA | E78: 36.3 | G78: =+G77+E78-F78 -> 119.5
D79: G. ADM | E79: 60 | G79: =+G78+E79-F79 -> 179.5
D80: P. SOCIAL | E80: 2 | G80: =+G79+E80-F80 -> 181.5
A81: 42788 | D81: MULTA | E81: 85 | G81: =+G80+E81-F81 -> 266.5
A82: 42823 | D82: MULTA | E82: 85 | G82: =+G81+E82-F82 -> 351.5
A83: 42951 | D83: MULTA | E83: 85 | G83: =+G82+E83-F83 -> 436.5
A84: 43008 | B84: TARJETA | C84: SEPTIEMBRE | D84: G. ADM | F84: 60 | G84: =+G83+E84-F84 -> 376.5
A85: 43008 | B85: TARJETA | C85: SEPTIEMBRE | D85: P. SOCIAL | F85: 2 | G85: =+G84+E85-F85 -> 374.5
A86: 43067 | B86: EXONERACION | C86: 42788 | D86: MULTA | F86: 85 | G86: =+G85+E86-F86 -> 289.5
A87: 43067 | B87: EXONERACION | C87: 42823 | D87: MULTA | F87: 85 | G87: =+G86+E87-F87 -> 204.5
A88: 43067 | B88: EXONERACION | C88: 42951 | D88: MULTA | F88: 85 | G88: =+G87+E88-F88 -> 119.5
A89: 43067 | B89: 14145 | C89: SEPTIEMBRE | D89: LUZ | F89: 83.2 | G89: =+G88+E89-F89 -> 36.3
A90: 43067 | B90: 14145 | C90: SEPTIEMBRE | D90: AGUA | F90: 36.3 | G90: =+G89+E90-F90 -> 0
A91: 43039 | B91: POR COBRAR | C91: OCTUBRE | D91: LUZ | E91: 82.7 | G91: =+G90+E91-F91 -> 82.7
D92: AGUA | E92: 36.4 | G92: =+G91+E92-F92 -> 119.1
D93: G. ADM | E93: 60 | G93: =+G92+E93-F93 -> 179.1
D94: P. SOCIAL | E94: 2 | G94: =+G93+E94-F94 -> 181.1
A95: 43039 | B95: TARJETA | C95: OCTUBRE | D95: G. ADM | F95: 60 | G95: =+G94+E95-F95 -> 121.1
A96: 43039 | B96: TARJETA | C96: OCTUBRE | D96: P. SOCIAL | F96: 2 | G96: =+G95+E96-F96 -> 119.1
A97: 43067 | B97: 14145 | C97: OCTUBRE | D97: LUZ | F97: 82.7 | G97: =+G96+E97-F97 -> 36.4
A98: 43067 | B98: 14145 | C98: OCTUBRE | D98: AGUA | F98: 36.4 | G98: =+G97+E98-F98 -> 0
A99: 43069 | B99: POR COBRAR | C99: NOVIEMBRE | D99: LUZ | E99: 88.3 | G99: =+G98+E99-F99 -> 88.3
D100: AGUA | E100: 36.3 | G100: =+G99+E100-F100 -> 124.6
D101: G. ADM | E101: 60 | G101: =+G100+E101-F101 -> 184.6
D102: P. SOCIAL | E102: 2 | G102: =+G101+E102-F102 -> 186.6
...

Sheet SANCHEZ JUDITH
B2: SANCHEZ RODRIGUEZ JUDITH IRIS
A4: FECHA | B4: DOCUMENTO | C4: PERIODO | D4: CONCEPTO | E4: POR COBRAR | F4: PAGADO | G4: SALDO POR COBRAR
A5: 42736 | B5: SALDO AL 2016 | G5: 479.3
A6: 42736 | B6: AGAU RESIDUAL | E6: 80 | G6: =+G5+E6-F6 -> 559.3
A7: 42736 | B7: 12059 | C7: A CUENTA 2016 | F7: 20 | G7: =+G6+E7-F7 -> 539.3
A8: 42740 | B8: 12073 | C8: A CUENTA 2016 | F8: 8 | G8: =+G7+E8-F8 -> 531.3
A9: 42758 | B9: 12136 | C9: A CUENTA 2016 | F9: 75.3 | G9: =+G8+E9-F9 -> 456
A10: 44847 | B10: 25615 | C10: A CUENTA 2016 | F10: 456 | G10: =+G9+E10-F10 -> 0
A11: 42766 | B11: POR COBRAR | C11: ENERO | D11: LUZ | E11: 57.1 | G11: =+G10+E11-F11 -> 57.1
D12: AGUA | E12: 15.5 | G12: =+G11+E12-F12 -> 72.6
D13: G. ADM | E13: 60 | G13: =+G12+E13-F13 -> 132.6
D14: P. SOCIAL | E14: 2 | G14: =+G13+E14-F14 -> 134.6
A15: 42763 | B15: TARJETA | C15: ENERO | D15: G. ADM | F15: 60 | G15: =+G14+E15-F15 -> 74.6
A16: 42763 | B16: TARJETA | C16: ENERO | D16: P. SOCIAL | F16: 2 | G16: =+G15+E16-F16 -> 72.6
A17: 42786 | B17: 12247 | C17: ENERO | D17: LUZ | F17: 57.1 | G17: =+G16+E17-F17 -> 15.5
A18: 42786 | B18: 12247 | C18: ENERO | D18: AGUA | F18: 15.5 | G18: =+G17+E18-F18 -> 0
A19: 42794 | B19: POR COBRAR | C19: FEBRERO | D19: LUZ | E19: 58.3 | G19: =+G18+E19-F19 -> 58.3
D20: AGUA | E20: 11 | G20: =+G19+E20-F20 -> 69.3
D21: G. ADM | E21: 56 | G21: =+G20+E21-F21 -> 125.3
D22: P. SOCIAL | E22: 2 | G22: =+G21+E22-F22 -> 127.3
A23: 42768 | B23: TARJETA | C23: FEBRERO | D23: G. ADM | F23: 56 | G23: =+G22+E23-F23 -> 71.3
A24: 42794 | B24: TARJETA | C24: FEBRERO | D24: P. SOCIAL | F24: 2 | G24: =+G23+E24-F24 -> 69.3
A25: 42816 | B25: 12436 | C25: FEBRERO | D25: LUZ | F25: 58.3 | G25: =+G24+E25-F25 -> 11
A26: 42816 | B26: 12436 | C26: FEBRERO | D26: AGUA | F26: 11 | G26: =+G25+E26-F26 -> 0
A27: 42825 | B27: POR COBRAR | C27: MARZO | D27: LUZ | E27: 55.7 | G27: =+G26+E27-F27 -> 55.7
D28: AGUA | E28: 11.3 | G28: =+G27+E28-F28 -> 67
D29: G. ADM | E29: 60 | G29: =+G28+E29-F29 -> 127
D30: P. SOCIAL | E30: 2 | G30: =+G29+E30-F30 -> 129
A31: 42825 | B31: TARJETA | C31: MARZO | D31: G. ADM | F31: 60 | G31: =+G30+E31-F31 -> 69
A32: 42825 | B32: TARJETA | C32: MARZO | D32: P. SOCIAL | F32: 2 | G32: =+G31+E32-F32 -> 67
A33: 42847 | B33: 12684 | C33: MARZO | D33: LUZ | F33: 55.7 | G33: =+G32+E33-F33 -> 11.3
A34: 42847 | B34: 12684 | C34: MARZO | D34: AGUA | F34: 11.3 | G34: =+G33+E34-F34 -> 0
A35: 42855 | B35: POR COBRAR | C35: ABRIL | D35: LUZ | E35: 57.1 | G35: =+G34+E35-F35 -> 57.1
D36: AGUA | E36: 11 | G36: =+G35+E36-F36 -> 68.1
D37: G. ADM | E37: 60 | G37: =+G36+E37-F37 -> 128.1
D38: P. SOCIAL | E38: 2 | G38: =+G37+E38-F38 -> 130.1
A39: 42854 | B39: TARJETA | C39: ABRIL | D39: G. ADM | F39: 60 | G39: =+G38+E39-F39 -> 70.1
A40: 42854 | B40: TARJETA | C40: ABRIL | D40: P. SOCIAL | F40: 2 | G40: =+G39+E40-F40 -> 68.1
A41: 42879 | B41: 12808 | C41: ABRIL | D41: LUZ | F41: 57.1 | G41: =+G40+E41-F41 -> 11
A42: 42879 | B42: 12808 | C42: ABRIL | D42: AGUA | F42: 11 | G42: =+G41+E42-F42 -> 0
A43: 42886 | B43: POR COBRAR | C43: MAYO | D43: LUZ | E43: 63.5 | G43: =+G42+E43-F43 -> 63.5
D44: AGUA | E44: 10.9 | G44: =+G43+E44-F44 -> 74.4
D45: G. ADM | E45: 60 | G45: =+G44+E45-F45 -> 134.4
D46: P. SOCIAL | E46: 2 | G46: =+G45+E46-F46 -> 136.4
A47: 42885 | B47: TARJETA | C47: MAYO | D47: G. ADM | F47: 60 | G47: =+G46+E47-F47 -> 76.4
A48: 42885 | B48: TARJETA | C48: MAYO | D48: P. SOCIAL | F48: 2 | G48: =+G47+E48-F48 -> 74.4
A49: 42909 | B49: 13139 | C49: MAYO | D49: LUZ | F49: 63.5 | G49: =+G48+E49-F49 -> 10.9
A50: 42909 | B50: 13139 | C50: MAYO | D50: AGUA | F50: 10.9 | G50: =+G49+E50-F50 -> 0
A51: 42916 | B51: POR COBRAR | C51: JUNIO | D51: LUZ | E51: 62 | G51: =+G50+E51-F51 -> 62
D52: AGUA | E52: 10.9 | G52: =+G51+E52-F52 -> 72.9
D53: G. ADM | E53: 60 | G53: =+G52+E53-F53 -> 132.9
D54: P. SOCIAL | E54: 2 | G54: =+G53+E54-F54 -> 134.9
A55: 42914 | B55: TARJETA | C55: JUNIO | D55: G. ADM | F55: 60 | G55: =+G54+E55-F55 -> 74.9
A56: 42914 | B56: TARJETA | C56: JUNIO | D56: P. SOCIAL | F56: 2 | G56: =+G55+E56-F56 -> 72.9
A57: 42937 | B57: 13231 | C57: JUNIO | D57: LUZ | F57: 62 | G57: =+G56+E57-F57 -> 10.9
A58: 42937 | B58: 13231 | C58: JUNIO | D58: AGUA | F58: 10.9 | G58: =+G57+E58-F58 -> 0
A59: 42947 | B59: POR COBRAR | C59: JULIO | D59: LUZ | E59: 56.4 | G59: =+G58+E59-F59 -> 56.4
D60: AGUA | E60: 11 | G60: =+G59+E60-F60 -> 67.4
D61: G. ADM | E61: 60 | G61: =+G60+E61-F61 -> 127.4
D62: P. SOCIAL | E62: 2 | G62: =+G61+E62-F62 -> 129.4
A63: 42938 | B63: TARJETA | C63: JULIO | D63: G. ADM | F63: 60 | G63: =+G62+E63-F63 -> 69.4
A64: 42938 | B64: TARJETA | C64: JULIO | D64: P. SOCIAL | F64: 2 | G64: =+G63+E64-F64 -> 67.4
A65: 42969 | B65: 13448 | C65: JULIO | D65: LUZ | F65: 56.4 | G65: =+G64+E65-F65 -> 11
A66: 42969 | B66: 13448 | C66: JULIO | D66: AGUA | F66: 11 | G66: =+G65+E66-F66 -> 0
A67: 42978 | B67: POR COBRAR | C67: AGOSTO | D67: LUZ | E67: 56.4 | G67: =+G66+E67-F67 -> 56.4
D68: AGUA | E68: 11 | G68: =+G67+E68-F68 -> 67.4
D69: G. ADM | E69: 60 | G69: =+G68+E69-F69 -> 127.4
D70: P. SOCIAL | E70: 2 | G70: =+G69+E70-F70 -> 129.4
D71: MULTA | E71: 85 | G71: =+G70+E71-F71 -> 214.4
A72: 42978 | B72: TARJETA | C72: AGOSTO | D72: G. ADM | F72: 60 | G72: =+G71+E72-F72 -> 154.4
A73: 42978 | B73: TARJETA | C73: AGOSTO | D73: P. SOCIAL | F73: 2 | G73: =+G72+E73-F73 -> 152.4
A74: 42999 | B74: 13645 | C74: AGOSTO | D74: LUZ | F74: 56.4 | G74: =+G73+E74-F74 -> 96
A75: 42999 | B75: 13645 | C75: AGOSTO | D75: AGUA | F75: 11 | G75: =+G74+E75-F75 -> 85
A76: 43067 | B76: EXONERACION | C76: AGOSTO | D76: MULTA | F76: 85 | G76: =+G75+E76-F76 -> 0
A77: 43008 | B77: POR COBRAR | C77: SEPTIEMBRE | D77: LUZ | E77: 49.3 | G77: =+G76+E77-F77 -> 49.3
D78: AGUA | E78: 7.1 | G78: =+G77+E78-F78 -> 56.4
D79: G. ADM | E79: 60 | G79: =+G78+E79-F79 -> 116.4
D80: P. SOCIAL | E80: 2 | G80: =+G79+E80-F80 -> 118.4
A81: 42788 | D81: MULTA | E81: 85 | G81: =+G80+E81-F81 -> 203.4
A82: 42823 | D82: MULTA | E82: 85 | G82: =+G81+E82-F82 -> 288.4
A83: 43008 | B83: TARJETA | C83: SEPTIEMBRE | D83: G. ADM | F83: 60 | G83: =+G82+E83-F83 -> 228.4
A84: 43008 | B84: TARJETA | C84: SEPTIEMBRE | D84: P. SOCIAL | F84: 2 | G84: =+G83+E84-F84 -> 226.4
A85: 43031 | B85: 13858 | C85: SEPTIEMBRE | D85: LUZ | F85: 49.3 | G85: =+G84+E85-F85 -> 177.1
A86: 43031 | B86: 13858 | C86: SEPTIEMBRE | D86: AGUA | F86: 7.1 | G86: =+G85+E86-F86 -> 170
A87: 43067 | B87: EXONERACION | C87: 42788 | D87: MULTA | F87: 85 | G87: =+G86+E87-F87 -> 85
A88: 43067 | B88: EXONERACION | C88: 42823 | D88: MULTA | F88: 85 | G88: =+G87+E88-F88 -> 0
A89: 43039 | B89: POR COBRAR | C89: OCTUBRE | D89: LUZ | E89: 49.5 | G89: =+G88+E89-F89 -> 49.5
D90: AGUA | E90: 10.9 | G90: =+G89+E90-F90 -> 60.4
D91: G. ADM | E91: 60 | G91: =+G90+E91-F91 -> 120.4
D92: P. SOCIAL | E92: 2 | G92: =+G91+E92-F92 -> 122.4
A93: 43039 | B93: TARJETA | C93: OCTUBRE | D93: G. ADM | F93: 56 | G93: =+G92+E93-F93 -> 66.4
A94: 43061 | B94: 10225 | C94: OCTUBRE | D94: LUZ | F94: 49.5 | G94: =+G93+E94-F94 -> 16.9
A95: 43061 | B95: 10225 | C95: OCTUBRE | D95: AGUA | F95: 10.9 | G95: =+G94+E95-F95 -> 6
A96: 43061 | B96: 10225 | C96: OCTUBRE | D96: G. ADM | F96: 4 | G96: =+G95+E96-F96 -> 2
A97: 43061 | B97: 10225 | C97: OCTUBRE | D97: P. SOCIAL | F97: 2 | G97: =+G96+E97-F97 -> 5.3290705e-15
A98: 43069 | B98: POR COBRAR | C98: NOVIEMBRE | D98: LUZ | E98: 52.4 | G98: =+G97+E98-F98 -> 52.4
D99: AGUA | E99: 10.9 | G99: =+G98+E99-F99 -> 63.3
D100: G. ADM | E100: 60 | G100: =+G99+E100-F100 -> 123.3
D101: P. SOCIAL | E101: 2 | G101: =+G100+E101-F101 -> 125.3
D102: P. S X FALL. FLORES EMMA | E102: 10 | G102: =+G101+E102-F102 -> 135.3
...

Sheet SANCHEZ ASTO YOLANDA
B2: SANCHEZ ASTO DE TORRES YOLANDA
A4: FECHA | B4: DOCUMENTO | C4: PERIODO | D4: CONCEPTO | E4: POR COBRAR | F4: PAGADO | G4: SALDO POR COBRAR
A5: 42736 | B5: SALDO AL 2016 | G5: 153.4
A6: 42783 | B6: 12968 | C6: A CUENTA 2016 | F6: 153.4 | G6: =+G5+E6-F6 -> 0
A7: 42766 | B7: POR COBRAR | C7: ENERO | D7: LUZ | E7: 35.5 | G7: =+G6+E7-F7 -> 35.5
D8: AGUA | E8: 2.8 | G8: =+G7+E8-F8 -> 38.3
D9: G. ADM | E9: 60 | G9: =+G8+E9-F9 -> 98.3
D10: P. SOCIAL | E10: 2 | G10: =+G9+E10-F10 -> 100.3
B11: TARJETA | C11: ENERO | D11: G. ADM | F11: 60 | G11: =+G10+E11-F11 -> 40.3
B12: TARJETA | C12: ENERO | D12: P. SOCIAL | F12: 2 | G12: =+G11+E12-F12 -> 38.3
A13: 42786 | B13: 12228 | C13: ENERO | D13: AGUA | F13: 2.8 | G13: =+G12+E13-F13 -> 35.5
A14: 42786 | B14: 12228 | C14: ENERO | D14: LUZ | F14: 35.5 | G14: =+G13+E14-F14 -> 0
A15: 42794 | B15: POR COBRAR | C15: FEBRERO | D15: LUZ | E15: 43.7 | G15: =+G14+E15-F15 -> 43.7
D16: AGUA | E16: 2 | G16: =+G15+E16-F16 -> 45.7
D17: G. ADM | E17: 56 | G17: =+G16+E17-F17 -> 101.7
D18: P. SOCIAL | E18: 2 | G18: =+G17+E18-F18 -> 103.7
B19: TARJETA | C19: FEBRERO | D19: G. ADM | F19: 56 | G19: =+G18+E19-F19 -> 47.7
B20: TARJETA | C20: FEBRERO | D20: P. SOCIAL | F20: 2 | G20: =+G19+E20-F20 -> 45.7
A21: 42819 | B21: 12476 | C21: FEBRERO | D21: LUZ | F21: 43.7 | G21: =+G20+E21-F21 -> 2
A22: 42819 | B22: 12476 | C22: FEBRERO | D22: AGUA | F22: 2 | G22: =+G21+E22-F22 -> 0
A23: 42825 | B23: POR COBRAR | C23: MARZO | D23: LUZ | E23: 41 | G23: =+G22+E23-F23 -> 41
D24: AGUA | E24: 2 | G24: =+G23+E24-F24 -> 43
D25: G. ADM | E25: 60 | G25: =+G24+E25-F25 -> 103
D26: P. SOCIAL | E26: 2 | G26: =+G25+E26-F26 -> 105
B27: TARJETA | C27: MARZO | D27: G. ADM | F27: 60 | G27: =+G26+E27-F27 -> 45
B28: TARJETA | C28: MARZO | D28: P. SOCIAL | F28: 2 | G28: =+G27+E28-F28 -> 43
A29: 42884 | B29: 12854 | C29: MARZO | D29: LUZ | F29: 41 | G29: =+G28+E29-F29 -> 2
A30: 42884 | B30: 12854 | C30: MARZO | D30: AGUA | F30: 2 | G30: =+G29+E30-F30 -> 0
A31: 42855 | B31: POR COBRAR | C31: ABRIL | D31: LUZ | E31: 43.2 | G31: =+G30+E31-F31 -> 43.2
D32: AGUA | E32: 2 | G32: =+G31+E32-F32 -> 45.2
D33: G. ADM | E33: 60 | G33: =+G32+E33-F33 -> 105.2
D34: P. SOCIAL | E34: 2 | G34: =+G33+E34-F34 -> 107.2
B35: TARJETA | C35: ABRIL | D35: G. ADM | F35: 60 | G35: =+G34+E35-F35 -> 47.2
B36: TARJETA | C36: ABRIL | D36: P. SOCIAL | F36: 2 | G36: =+G35+E36-F36 -> 45.2
A37: 42884 | B37: 12854 | C37: ABRIL | D37: LUZ | F37: 43.2 | G37: =+G36+E37-F37 -> 2
A38: 42884 | B38: 12854 | C38: ABRIL | D38: AGUA | F38: 2 | G38: =+G37+E38-F38 -> 0
A39: 42886 | B39: POR COBRAR | C39: MAYO | D39: LUZ | E39: 41.8 | G39: =+G38+E39-F39 -> 41.8
D40: AGUA | E40: 2 | G40: =+G39+E40-F40 -> 43.8
D41: G. ADM | E41: 60 | G41: =+G40+E41-F41 -> 103.8
D42: P. SOCIAL | E42: 2 | G42: =+G41+E42-F42 -> 105.8
A43: 42885 | B43: TARJETA | C43: MAYO | D43: G. ADM | F43: 60 | G43: =+G42+E43-F43 -> 45.8
A44: 42885 | B44: TARJETA | C44: MAYO | D44: P. SOCIAL | F44: 2 | G44: =+G43+E44-F44 -> 43.8
A45: 42949 | B45: 13342 | C45: MAYO | D45: LUZ | F45: 41.8 | G45: =+G44+E45-F45 -> 2
A46: 42949 | B46: 13342 | C46: MAYO | D46: AGUA | F46: 2 | G46: =+G45+E46-F46 -> 0
A47: 42916 | B47: POR COBRAR | C47: JUNIO | D47: LUZ | E47: 40.5 | G47: =+G46+E47-F47 -> 40.5
D48: AGUA | E48: 2 | G48: =+G47+E48-F48 -> 42.5
D49: G. ADM | E49: 60 | G49: =+G48+E49-F49 -> 102.5
D50: P. SOCIAL | E50: 2 | G50: =+G49+E50-F50 -> 104.5
A51: 42916 | B51: TARJETA | C51: JUNIO | D51: G. ADM | F51: 60 | G51: =+G50+E51-F51 -> 44.5
A52: 42916 | B52: TARJETA | C52: JUNIO | D52: P. SOCIAL | F52: 2 | G52: =+G51+E52-F52 -> 42.5
A53: 42949 | B53: 13342 | C53: JUNIO | D53: LUZ | F53: 40.5 | G53: =+G52+E53-F53 -> 2
A54: 42949 | B54: 13342 | C54: JUNIO | D54: AGUA | F54: 2 | G54: =+G53+E54-F54 -> 0
A55: 42947 | B55: POR COBRAR | C55: JULIO | D55: LUZ | E55: 39.6 | G55: =+G54+E55-F55 -> 39.6
D56: AGUA | E56: 2 | G56: =+G55+E56-F56 -> 41.6
D57: G. ADM | E57: 60 | G57: =+G56+E57-F57 -> 101.6
D58: P. SOCIAL | E58: 2 | G58: =+G57+E58-F58 -> 103.6
A59: 42947 | B59: TARJETA | C59: JULIO | D59: G. ADM | F59: 60 | G59: =+G58+E59-F59 -> 43.6
A60: 42947 | B60: TARJETA | C60: JULIO | D60: P. SOCIAL | F60: 2 | G60: =+G59+E60-F60 -> 41.6
A61: 43012 | B61: 13788 | C61: JULIO | D61: LUZ | F61: 39.6 | G61: =+G60+E61-F61 -> 2
A62: 43012 | B62: 13788 | C62: JULIO | D62: AGUA | F62: 2 | G62: =+G61+E62-F62 -> -7.1054274e-15
A63: 42978 | B63: POR COBRAR | C63: AGOSTO | D63: LUZ | E63: 39.6 | G63: =+G62+E63-F63 -> 39.6
D64: AGUA | E64: 2 | G64: =+G63+E64-F64 -> 41.6
D65: G. ADM | E65: 60 | G65: =+G64+E65-F65 -> 101.6
D66: P. SOCIAL | E66: 2 | G66: =+G65+E66-F66 -> 103.6
D67: MULTA | E67: 85 | G67: =+G66+E67-F67 -> 188.6
A68: 42978 | B68: TARJETA | C68: AGOSTO | D68: G. ADM | F68: 60 | G68: =+G67+E68-F68 -> 128.6
A69: 42978 | B69: TARJETA | C69: AGOSTO | D69: P. SOCIAL | F69: 2 | G69: =+G68+E69-F69 -> 126.6
A70: 43012 | B70: 13788 | C70: AGOSTO | D70: LUZ | F70: 39.6 | G70: =+G69+E70-F70 -> 87
A71: 43012 | B71: 13788 | C71: AGOSTO | D71: AGUA | F71: 2 | G71: =+G70+E71-F71 -> 85
A72: 43067 | B72: EXONERACION | C72: AGOSTO | D72: MULTA | F72: 85 | G72: =+G71+E72-F72 -> 0
A73: 43008 | B73: POR COBRAR | C73: SEPTIEMBRE | D73: LUZ | E73: 38.7 | G73: =+G72+E73-F73 -> 38.7
D74: AGUA | E74: 2 | G74: =+G73+E74-F74 -> 40.7
D75: G. ADM | E75: 60 | G75: =+G74+E75-F75 -> 100.7
D76: P. SOCIAL | E76: 2 | G76: =+G75+E76-F76 -> 102.7
A77: 42788 | D77: MULTA | E77: 85 | G77: =+G76+E77-F77 -> 187.7
A78: 42823 | D78: MULTA | E78: 85 | G78: =+G77+E78-F78 -> 272.7
A79: 43008 | B79: TARJETA | C79: SEPTIEMBRE | D79: G. ADM | F79: 60 | G79: =+G78+E79-F79 -> 212.7
A80: 43008 | B80: TARJETA | C80: SEPTIEMBRE | D80: P. SOCIAL | F80: 2 | G80: =+G79+E80-F80 -> 210.7
A81: 43056 | B81: 13987 | C81: SEPTIEMBRE | D81: LUZ | F81: 38.7 | G81: =+G80+E81-F81 -> 172
A82: 43056 | B82: 13987 | C82: SEPTIEMBRE | D82: AGUA | F82: 2 | G82: =+G81+E82-F82 -> 170
A83: 43067 | B83: EXONERACION | C83: 42788 | D83: MULTA | F83: 85 | G83: =+G82+E83-F83 -> 85
A84: 43067 | B84: EXONERACION | C84: 42823 | D84: MULTA | F84: 85 | G84: =+G83+E84-F84 -> 0
A85: 43039 | B85: POR COBRAR | C85: OCTUBRE | D85: LUZ | E85: 30.8 | G85: =+G84+E85-F85 -> 30.8
D86: AGUA | E86: 2 | G86: =+G85+E86-F86 -> 32.8
D87: G. ADM | E87: 60 | G87: =+G86+E87-F87 -> 92.8
D88: P. SOCIAL | E88: 2 | G88: =+G87+E88-F88 -> 94.8
A89: 43039 | B89: TARJETA | C89: OCTUBRE | D89: G. ADM | F89: 60 | G89: =+G88+E89-F89 -> 34.8
A90: 43039 | B90: TARJETA | C90: OCTUBRE | D90: P. SOCIAL | F90: 2 | G90: =+G89+E90-F90 -> 32.8
A91: 43062 | B91: 14008 | C91: OCTUBRE | D91: AGUA | F91: 2 | G91: =+G90+E91-F91 -> 30.8
A92: 43062 | B92: 14008 | C92: OCTUBRE | D92: LUZ | F92: 30.8 | G92: =+G91+E92-F92 -> 0
A93: 43069 | B93: POR COBRAR | C93: NOVIEMBRE | D93: LUZ | E93: 32.9 | G93: =+G92+E93-F93 -> 32.9
D94: AGUA | E94: 2 | G94: =+G93+E94-F94 -> 34.9
D95: G. ADM | E95: 60 | G95: =+G94+E95-F95 -> 94.9
D96: P. SOCIAL | E96: 2 | G96: =+G95+E96-F96 -> 96.9
A97: 43089 | B97: 14336 | C97: NOVIEMBRE | D97: LUZ | F97: 32.9 | G97: =+G96+E97-F97 -> 64
A98: 43089 | B98: 14336 | C98: NOVIEMBRE | D98: AGUA | F98: 2 | G98: =+G97+E98-F98 -> 62
A99: 43069 | B99: TARJETA | C99: NOVIEMBRE | D99: G. ADM | F99: 60 | G99: =+G98+E99-F99 -> 2
A100: 43069 | B100: TARJETA | C100: NOVIEMBRE | D100: P. SOCIAL | F100: 2 | G100: =+G99+E100-F100 -> 0
A101: 43100 | B101: POR COBRAR | C101: DICIEMBRE | D101: LUZ | E101: 35.8 | G101: =+G100+E101-F101 -> 35.8
D102: AGUA | E102: 2 | G102: =+G101+E102-F102 -> 37.8
...

Sheet SANCHEZ LUCIA
B2: SANCHEZ SOTOS LUCIA
A4: FECHA | B4: DOCUMENTO | C4: PERIODO | D4: CONCEPTO | E4: POR COBRAR | F4: PAGADO | G4: SALDO POR COBRAR
A5: 42736 | B5: SALDO AL 2016 | G5: 122.9
A6: 42772 | B6: 12922 | C6: CANCELADO | F6: 122.9 | G6: =+G5+E6-F6 -> 0
A7: 42766 | B7: POR COBRAR | C7: ENERO | D7: LUZ | E7: 58.9 | G7: =+G6+E7-F7 -> 58.9
D8: AGUA | E8: 2.8 | G8: =+G7+E8-F8 -> 61.7
D9: G. ADM | E9: 60 | G9: =+G8+E9-F9 -> 121.7
D10: P. SOCIAL | E10: 2 | G10: =+G9+E10-F10 -> 123.7
A11: 42765 | B11: TARJETA | C11: ENERO | D11: G. ADM | F11: 60 | G11: =+G10+E11-F11 -> 63.7
A12: 42765 | B12: TARJETA | C12: ENERO | D12: P. SOCIAL | F12: 2 | G12: =+G11+E12-F12 -> 61.7
A13: 42803 | B13: 12410 | C13: ENERO | D13: AGUA | F13: 2.8 | G13: =+G12+E13-F13 -> 58.9
A14: 42803 | B14: 12410 | C14: ENERO | D14: LUZ | F14: 58.9 | G14: =+G13+E14-F14 -> 0
A15: 42794 | B15: POR COBRAR | C15: FEBRERO | D15: LUZ | E15: 59.2 | G15: =+G14+E15-F15 -> 59.2
D16: AGUA | E16: 2 | G16: =+G15+E16-F16 -> 61.2
D17: G. ADM | E17: 56 | G17: =+G16+E17-F17 -> 117.2
D18: P. SOCIAL | E18: 2 | G18: =+G17+E18-F18 -> 119.2
D19: MULTA | E19: 85 | G19: =+G18+E19-F19 -> 204.2
A20: 42794 | B20: TARJETA | C20: FEBRERO | D20: G. ADM | F20: 56 | G20: =+G19+E20-F20 -> 148.2
A21: 42794 | B21: TARJETA | C21: FEBRERO | D21: P. SOCIAL | F21: 2 | G21: =+G20+E21-F21 -> 146.2
A22: 42817 | B22: 12453 | C22: FEBRERO | D22: LUZ | F22: 59.2 | G22: =+G21+E22-F22 -> 87
A23: 42817 | B23: 12453 | C23: FEBRERO | D23: AGUA | F23: 2 | G23: =+G22+E23-F23 -> 85
A24: 42818 | B24: 12472 | C24: FEBRERO | D24: MULTA | F24: 85 | G24: =+G23+E24-F24 -> 0
A25: 42825 | B25: POR COBRAR | C25: MARZO | D25: LUZ | E25: 56 | G25: =+G24+E25-F25 -> 56
D26: AGUA | E26: 2 | G26: =+G25+E26-F26 -> 58
D27: G. ADM | E27: 60 | G27: =+G26+E27-F27 -> 118
D28: P. SOCIAL | E28: 2 | G28: =+G27+E28-F28 -> 120
A29: 42824 | B29: TARJETA | C29: MARZO | D29: G. ADM | F29: 60 | G29: =+G28+E29-F29 -> 60
A30: 42824 | B30: TARJETA | C30: MARZO | D30: P. SOCIAL | F30: 2 | G30: =+G29+E30-F30 -> 58
A31: 42849 | B31: 12694 | C31: MARZO | D31: LUZ | F31: 56 | G31: =+G30+E31-F31 -> 2
A32: 42849 | B32: 12694 | C32: MARZO | D32: AGUA | F32: 2 | G32: =+G31+E32-F32 -> 0
A33: 42855 | B33: POR COBRAR | C33: ABRIL | D33: LUZ | E33: 58.3 | G33: =+G32+E33-F33 -> 58.3
D34: AGUA | E34: 2 | G34: =+G33+E34-F34 -> 60.3
D35: G. ADM | E35: 60 | G35: =+G34+E35-F35 -> 120.3
D36: P. SOCIAL | E36: 2 | G36: =+G35+E36-F36 -> 122.3
A37: 42855 | B37: TARJETA | C37: ABRIL | D37: G. ADM | F37: 60 | G37: =+G36+E37-F37 -> 62.3
A38: 42855 | B38: TARJETA | C38: ABRIL | D38: P. SOCIAL | F38: 2 | G38: =+G37+E38-F38 -> 60.3
A39: 42884 | B39: 12857 | C39: ABRIL | D39: LUZ | F39: 58.3 | G39: =+G38+E39-F39 -> 2
A40: 42884 | B40: 12857 | C40: ABRIL | D40: AGUA | F40: 2 | G40: =+G39+E40-F40 -> 0
A41: 42886 | B41: POR COBRAR | C41: MAYO | D41: LUZ | E41: 55.7 | G41: =+G40+E41-F41 -> 55.7
D42: AGUA | E42: 2 | G42: =+G41+E42-F42 -> 57.7
D43: G. ADM | E43: 60 | G43: =+G42+E43-F43 -> 117.7
D44: P. SOCIAL | E44: 2 | G44: =+G43+E44-F44 -> 119.7
A45: 42885 | B45: TARJETA | C45: MAYO | D45: G. ADM | F45: 60 | G45: =+G44+E45-F45 -> 59.7
A46: 42885 | B46: TARJETA | C46: MAYO | D46: P. SOCIAL | F46: 2 | G46: =+G45+E46-F46 -> 57.7
A47: 42914 | B47: 13165 | C47: MAYO | D47: LUZ | F47: 55.7 | G47: =+G46+E47-F47 -> 2
A48: 42914 | B48: 13165 | C48: MAYO | D48: AGUA | F48: 2 | G48: =+G47+E48-F48 -> 0
A49: 42916 | B49: POR COBRAR | C49: JUNIO | D49: LUZ | E49: 54.1 | G49: =+G48+E49-F49 -> 54.1
D50: AGUA | E50: 2 | G50: =+G49+E50-F50 -> 56.1
D51: G. ADM | E51: 60 | G51: =+G50+E51-F51 -> 116.1
D52: P. SOCIAL | E52: 2 | G52: =+G51+E52-F52 -> 118.1
A53: 42916 | B53: TARJETA | C53: JUNIO | D53: G. ADM | F53: 60 | G53: =+G52+E53-F53 -> 58.1
A54: 42916 | B54: TARJETA | C54: JUNIO | D54: P. SOCIAL | F54: 2 | G54: =+G53+E54-F54 -> 56.1
A55: 42937 | B55: 13233 | C55: JUNIO | D55: AGUA | F55: 2 | G55: =+G54+E55-F55 -> 54.1
A56: 42937 | B56: 13233 | C56: JUNIO | D56: LUZ | F56: 54.1 | G56: =+G55+E56-F56 -> 0
A57: 42947 | B57: POR COBRAR | C57: JULIO | D57: LUZ | E57: 51.5 | G57: =+G56+E57-F57 -> 51.5
D58: AGUA | E58: 2 | G58: =+G57+E58-F58 -> 53.5
D59: G. ADM | E59: 60 | G59: =+G58+E59-F59 -> 113.5
D60: P. SOCIAL | E60: 2 | G60: =+G59+E60-F60 -> 115.5
A61: 42947 | B61: TARJETA | C61: JULIO | D61: G. ADM | F61: 60 | G61: =+G60+E61-F61 -> 55.5
A62: 42947 | B62: TARJETA | C62: JULIO | D62: P. SOCIAL | F62: 2 | G62: =+G61+E62-F62 -> 53.5
A63: 42972 | B63: 13499 | C63: JULIO | D63: LUZ | F63: 51.5 | G63: =+G62+E63-F63 -> 2
A64: 42972 | B64: 13499 | C64: JULIO | D64: AGUA | F64: 2 | G64: =+G63+E64-F64 -> 0
A65: 42978 | B65: POR COBRAR | C65: AGOSTO | D65: LUZ | E65: 51.5 | G65: =+G64+E65-F65 -> 51.5
D66: AGUA | E66: 2 | G66: =+G65+E66-F66 -> 53.5
D67: G. ADM | E67: 60 | G67: =+G66+E67-F67 -> 113.5
D68: P. SOCIAL | E68: 2 | G68: =+G67+E68-F68 -> 115.5
A69: 42978 | B69: TARJETA | C69: AGOSTO | D69: G. ADM | F69: 60 | G69: =+G68+E69-F69 -> 55.5
A70: 42978 | B70: TARJETA | C70: AGOSTO | D70: P. SOCIAL | F70: 2 | G70: =+G69+E70-F70 -> 53.5
A71: 43000 | B71: 13653 | C71: AGOSTO | D71: LUZ | F71: 51.5 | G71: =+G70+E71-F71 -> 2
A72: 43000 | B72: 13653 | C72: AGOSTO | D72: AGUA | F72: 2 | G72: =+G71+E72-F72 -> 0
A73: 43008 | B73: POR COBRAR | C73: SEPTIEMBRE | D73: LUZ | E73: 38.5 | G73: =+G72+E73-F73 -> 38.5
D74: AGUA | E74: 1.3 | G74: =+G73+E74-F74 -> 39.8
D75: G. ADM | E75: 60 | G75: =+G74+E75-F75 -> 99.8
D76: P. SOCIAL | E76: 2 | G76: =+G75+E76-F76 -> 101.8
A77: 43008 | B77: TARJETA | C77: SEPTIEMBRE | D77: G. ADM | F77: 60 | G77: =+G76+E77-F77 -> 41.8
A78: 43008 | B78: TARJETA | C78: SEPTIEMBRE | D78: P. SOCIAL | F78: 2 | G78: =+G77+E78-F78 -> 39.8
A79: 43028 | B79: 13844 | C79: SEPTIEMBRE | D79: LUZ | F79: 38.5 | G79: =+G78+E79-F79 -> 1.3
A80: 43028 | B80: 13844 | C80: SEPTIEMBRE | D80: AGUA | F80: 1.3 | G80: =+G79+E80-F80 -> -2.8865799e-15
A81: 43039 | B81: POR COBRAR | C81: OCTUBRE | D81: LUZ | E81: 38.5 | G81: =+G80+E81-F81 -> 38.5
D82: AGUA | E82: 2 | G82: =+G81+E82-F82 -> 40.5
D83: G. ADM | E83: 60 | G83: =+G82+E83-F83 -> 100.5
D84: P. SOCIAL | E84: 2 | G84: =+G83+E84-F84 -> 102.5
A85: 43039 | B85: TARJETA | C85: OCTUBRE | D85: G. ADM | F85: 60 | G85: =+G84+E85-F85 -> 42.5
A86: 43039 | B86: TARJETA | C86: OCTUBRE | D86: P. SOCIAL | F86: 2 | G86: =+G85+E86-F86 -> 40.5
A87: 43063 | B87: 14079 | C87: OCTUBRE | D87: LUZ | F87: 38.5 | G87: =+G86+E87-F87 -> 2
A88: 43063 | B88: 14079 | C88: OCTUBRE | D88: AGUA | F88: 2 | G88: =+G87+E88-F88 -> 0
A89: 43069 | B89: POR COBRAR | C89: NOVIEMBRE | D89: LUZ | E89: 41.1 | G89: =+G88+E89-F89 -> 41.1
D90: AGUA | E90: 2 | G90: =+G89+E90-F90 -> 43.1
D91: G. ADM | E91: 60 | G91: =+G90+E91-F91 -> 103.1
D92: P. SOCIAL | E92: 2 | G92: =+G91+E92-F92 -> 105.1
A93: 43087 | B93: 14271 | C93: NOVIEMBRE | D93: LUZ | F93: 41.1 | G93: =+G92+E93-F93 -> 64
A94: 43087 | B94: 14271 | C94: NOVIEMBRE | D94: AGUA | F94: 2 | G94: =+G93+E94-F94 -> 62
A95: 43069 | B95: TARJETA | C95: NOVIEMBRE | D95: G. ADM | F95: 60 | G95: =+G94+E95-F95 -> 2
A96: 43069 | B96: TARJETA | C96: NOVIEMBRE | D96: P. SOCIAL | F96: 2 | G96: =+G95+E96-F96 -> -7.1054274e-15
A97: 43100 | B97: POR COBRAR | C97: DICIEMBRE | D97: LUZ | E97: 55.9 | G97: =+G96+E97-F97 -> 55.9
D98: AGUA | E98: 2 | G98: =+G97+E98-F98 -> 57.9
D99: G. ADM | E99: 60 | G99: =+G98+E99-F99 -> 117.9
D100: P. SOCIAL | E100: 2 | G100: =+G99+E100-F100 -> 119.9
A101: 43099 | B101: TARJETA | C101: DICIEMBRE | D101: G. ADM | F101: 60 | G101: =+G100+E101-F101 -> 59.9
A102: 43099 | B102: TARJETA | C102: DICIEMBRE | D102: P. SOCIAL | F102: 2 | G102: =+G101+E102-F102 -> 57.9
...

Sheet SANTILLAN ZOILA
B2: SANTILLAN MESIA ZOILA
A4: FECHA | B4: DOCUMENTO | C4: PERIODO | D4: CONCEPTO | E4: POR COBRAR | F4: PAGADO | G4: SALDO POR COBRAR
A5: 42736 | B5: SALDO AL 2016 | G5: 186.8
A6: 42787 | B6: 12324 | C6: A CUENTA 2016 | F6: 62.8 | G6: =+G5+E6-F6 -> 124
A7: 42787 | B7: 12327 | C7: CANCELADO | F7: 124 | G7: =+G6+E7-F7 -> 0
A8: 42766 | B8: POR COBRAR | C8: ENERO | D8: LUZ | E8: 29.6 | G8: =+G7+E8-F8 -> 29.6
D9: AGUA | E9: 2.8 | G9: =+G8+E9-F9 -> 32.4
D10: G. ADM | E10: 60 | G10: =+G9+E10-F10 -> 92.4
D11: P. SOCIAL | E11: 2 | G11: =+G10+E11-F11 -> 94.4
A12: 42787 | B12: 12324 | C12: ENERO | D12: LUZ | F12: 29.6 | G12: =+G11+E12-F12 -> 64.8
A13: 42787 | B13: 12324 | C13: ENERO | D13: AGUA | F13: 2.8 | G13: =+G12+E13-F13 -> 62
A14: 42787 | B14: 12327 | C14: ENERO | D14: G. ADM | F14: 60 | G14: =+G13+E14-F14 -> 2
A15: 42787 | B15: 12327 | C15: ENERO | D15: P. SOCIAL | F15: 2 | G15: =+G14+E15-F15 -> 1.4210855e-14
A16: 42794 | B16: POR COBRAR | C16: FEBRERO | D16: LUZ | E16: 28.5 | G16: =+G15+E16-F16 -> 28.5
D17: AGUA | E17: 2 | G17: =+G16+E17-F17 -> 30.5
D18: G. ADM | E18: 56 | G18: =+G17+E18-F18 -> 86.5
D19: P. SOCIAL | E19: 2 | G19: =+G18+E19-F19 -> 88.5
A20: 42822 | B20: 12596 | C20: FEBRERO | D20: G. ADM | F20: 56 | G20: =+G19+E20-F20 -> 32.5
A21: 42822 | B21: 12596 | C21: FEBRERO | D21: P. SOCIAL | F21: 2 | G21: =+G20+E21-F21 -> 30.5
A22: 42822 | B22: 12596 | C22: FEBRERO | D22: LUZ | F22: 28.5 | G22: =+G21+E22-F22 -> 2
A23: 42822 | B23: 12596 | C23: FEBRERO | D23: AGUA | F23: 2 | G23: =+G22+E23-F23 -> 1.4210855e-14
A24: 42825 | B24: POR COBRAR | C24: MARZO | D24: LUZ | E24: 26.9 | G24: =+G23+E24-F24 -> 26.9
D25: AGUA | E25: 2 | G25: =+G24+E25-F25 -> 28.9
D26: G. ADM | E26: 60 | G26: =+G25+E26-F26 -> 88.9
D27: P. SOCIAL | E27: 2 | G27: =+G26+E27-F27 -> 90.9
A28: 42893 | B28: 13078 | C28: MARZO | D28: LUZ | F28: 26.9 | G28: =+G27+E28-F28 -> 64
A29: 42893 | B29: 13078 | C29: MARZO | D29: AGUA | F29: 2 | G29: =+G28+E29-F29 -> 62
A30: 42950 | B30: 13420 | C30: MARZO | D30: G. ADM | F30: 60 | G30: =+G29+E30-F30 -> 2
A31: 42950 | B31: 13420 | C31: MARZO | D31: P. SOCIAL | F31: 2 | G31: =+G30+E31-F31 -> 0
A32: 42855 | B32: POR COBRAR | C32: ABRIL | D32: LUZ | E32: 28.1 | G32: =+G31+E32-F32 -> 28.1
D33: AGUA | E33: 2 | G33: =+G32+E33-F33 -> 30.1
D34: G. ADM | E34: 60 | G34: =+G33+E34-F34 -> 90.1
D35: P. SOCIAL | E35: 2 | G35: =+G34+E35-F35 -> 92.1
A36: 42893 | B36: 13078 | C36: ABRIL | D36: LUZ | F36: 28.1 | G36: =+G35+E36-F36 -> 64
A37: 42893 | B37: 13078 | C37: ABRIL | D37: AGUA | F37: 2 | G37: =+G36+E37-F37 -> 62
A38: 42950 | B38: 13392 | C38: ABRIL | D38: P. SOCIAL | F38: 2 | G38: =+G37+E38-F38 -> 60
A39: 42950 | B39: 13392 | C39: ABRIL | D39: G. ADM | F39: 60 | G39: =+G38+E39-F39 -> 0
A40: 42886 | B40: POR COBRAR | C40: MAYO | D40: LUZ | E40: 26.9 | G40: =+G39+E40-F40 -> 26.9
D41: AGUA | E41: 2 | G41: =+G40+E41-F41 -> 28.9
D42: G. ADM | E42: 60 | G42: =+G41+E42-F42 -> 88.9
D43: P. SOCIAL | E43: 2 | G43: =+G42+E43-F43 -> 90.9
A44: 42950 | B44: 13392 | C44: MAYO | D44: G. ADM | F44: 60 | G44: =+G43+E44-F44 -> 30.9
A45: 42950 | B45: 13392 | C45: MAYO | D45: P. SOCIAL | F45: 2 | G45: =+G44+E45-F45 -> 28.9
A46: 42950 | B46: 13393 | C46: MAYO | D46: LUZ | F46: 26.9 | G46: =+G45+E46-F46 -> 2
A47: 42950 | B47: 13393 | C47: MAYO | D47: AGUA | F47: 2 | G47: =+G46+E47-F47 -> 7.1054274e-15
A48: 42916 | B48: POR COBRAR | C48: JUNIO | D48: LUZ | E48: 26.1 | G48: =+G47+E48-F48 -> 26.1
D49: AGUA | E49: 2 | G49: =+G48+E49-F49 -> 28.1
D50: G. ADM | E50: 60 | G50: =+G49+E50-F50 -> 88.1
D51: P. SOCIAL | E51: 2 | G51: =+G50+E51-F51 -> 90.1
A52: 42950 | B52: 13393 | C52: JUNIO | D52: LUZ | F52: 26.1 | G52: =+G51+E52-F52 -> 64
A53: 42950 | B53: 13393 | C53: JUNIO | D53: AGUA | F53: 2 | G53: =+G52+E53-F53 -> 62
A54: 42950 | B54: 13392 | C54: JUNIO | D54: G. ADM | F54: 60 | G54: =+G53+E54-F54 -> 2
A55: 42950 | B55: 13392 | C55: JUNIO | D55: P. SOCIAL | F55: 2 | G55: =+G54+E55-F55 -> 0
A56: 42947 | B56: POR COBRAR | C56: JULIO | D56: LUZ | E56: 24.9 | G56: =+G55+E56-F56 -> 24.9
D57: AGUA | E57: 2 | G57: =+G56+E57-F57 -> 26.9
D58: G. ADM | E58: 60 | G58: =+G57+E58-F58 -> 86.9
D59: P. SOCIAL | E59: 2 | G59: =+G58+E59-F59 -> 88.9
A60: 42950 | B60: 13392 | C60: JULIO | D60: P. SOCIAL | F60: 2 | G60: =+G59+E60-F60 -> 86.9
A61: 42950 | B61: 13392 | C61: JULIO | D61: G. ADM | F61: 60 | G61: =+G60+E61-F61 -> 26.9
A62: 42971 | B62: 13476 | C62: JULIO | D62: LUZ | F62: 24.9 | G62: =+G61+E62-F62 -> 2
A63: 42971 | B63: 13476 | C63: JULIO | D63: AGUA | F63: 2 | G63: =+G62+E63-F63 -> 7.1054274e-15
A64: 42978 | B64: POR COBRAR | C64: AGOSTO | D64: LUZ | E64: 24.9 | G64: =+G63+E64-F64 -> 24.9
D65: AGUA | E65: 2 | G65: =+G64+E65-F65 -> 26.9
D66: G. ADM | E66: 60 | G66: =+G65+E66-F66 -> 86.9
D67: P. SOCIAL | E67: 2 | G67: =+G66+E67-F67 -> 88.9
A68: 42978 | B68: TARJETA | C68: AGOSTO | D68: G. ADM | F68: 60 | G68: =+G67+E68-F68 -> 28.9
A69: 42978 | B69: TARJETA | C69: AGOSTO | D69: P. SOCIAL | F69: 2 | G69: =+G68+E69-F69 -> 26.9
A70: 43067 | B70: 14152 | C70: AGOSTO | D70: LUZ | F70: 24.9 | G70: =+G69+E70-F70 -> 2
A71: 43067 | B71: 14152 | C71: AGOSTO | D71: AGUA | F71: 2 | G71: =+G70+E71-F71 -> 7.1054274e-15
A72: 43008 | B72: POR COBRAR | C72: SEPTIEMBRE | D72: LUZ | E72: 21.3 | G72: =+G71+E72-F72 -> 21.3
D73: AGUA | E73: 2 | G73: =+G72+E73-F73 -> 23.3
D74: G. ADM | E74: 60 | G74: =+G73+E74-F74 -> 83.3
D75: P. SOCIAL | E75: 2 | G75: =+G74+E75-F75 -> 85.3
A76: 43008 | B76: TARJETA | C76: SEPTIEMBRE | D76: G. ADM | F76: 20 | G76: =+G75+E76-F76 -> 65.3
A77: 43067 | B77: 14152 | C77: SEPTIEMBRE | D77: G. ADM | F77: 40 | G77: =+G76+E77-F77 -> 25.3 | K77: 223.8
A78: 43067 | B78: 14152 | C78: SEPTIEMBRE | D78: P. SOCIAL | F78: 2 | G78: =+G77+E78-F78 -> 23.3 | K78: =250.8-K77 -> 27
A79: 43067 | B79: 14152 | C79: SEPTIEMBRE | D79: LUZ | F79: 21.3 | G79: =+G78+E79-F79 -> 2
A80: 43067 | B80: 14152 | C80: SEPTIEMBRE | D80: AGUA | F80: 2 | G80: =+G79+E80-F80 -> 1.0658141e-14
A81: 43039 | B81: POR COBRAR | C81: OCTUBRE | D81: LUZ | E81: 21.2 | G81: =+G80+E81-F81 -> 21.2
D82: AGUA | E82: 2 | G82: =+G81+E82-F82 -> 23.2
D83: G. ADM | E83: 60 | G83: =+G82+E83-F83 -> 83.2
D84: P. SOCIAL | E84: 2 | G84: =+G83+E84-F84 -> 85.2
A85: 43039 | B85: TARJETA | C85: OCTUBRE | D85: G. ADM | F85: 60 | G85: =+G84+E85-F85 -> 25.2
A86: 43039 | B86: TARJETA | C86: OCTUBRE | D86: P. SOCIAL | F86: 2 | G86: =+G85+E86-F86 -> 23.2
A87: 43067 | B87: 14152 | C87: OCTUBRE | D87: LUZ | F87: 21.2 | G87: =+G86+E87-F87 -> 2
A88: 43067 | B88: 14152 | C88: OCTUBRE | D88: AGUA | F88: 2 | G88: =+G87+E88-F88 -> 1.7763568e-14
A89: 43069 | B89: POR COBRAR | C89: NOVIEMBRE | D89: LUZ | E89: 22.6 | G89: =+G88+E89-F89 -> 22.6
D90: AGUA | E90: 2 | G90: =+G89+E90-F90 -> 24.6
D91: G. ADM | E91: 60 | G91: =+G90+E91-F91 -> 84.6
D92: P. SOCIAL | E92: 2 | G92: =+G91+E92-F92 -> 86.6
D93: P. S X FALL. FLORES EMMA | E93: 10 | G93: =+G92+E93-F93 -> 96.6
A94: 43069 | B94: TARJETA | C94: NOVIEMBRE | D94: G. ADM | F94: 15 | G94: =+G93+E94-F94 -> 81.6
A95: 43161 | B95: 14782 | C95: NOVIEMBRE | D95: LUZ | F95: 22.6 | G95: =+G94+E95-F95 -> 59
A96: 43161 | B96: 14782 | C96: NOVIEMBRE | D96: AGUA | F96: 2 | G96: =+G95+E96-F96 -> 57
A97: 43161 | B97: 14782 | C97: NOVIEMBRE | D97: G. ADM | F97: 45 | G97: =+G96+E97-F97 -> 12
A98: 43161 | B98: 14782 | C98: NOVIEMBRE | D98: P. SOCIAL | F98: 2 | G98: =+G97+E98-F98 -> 10
A99: 43186 | B99: 15050 | C99: NOVIEMBRE | D99: P. S X FALL. FLORES EMMA | F99: 10 | G99: =+G98+E99-F99 -> 2.1316282e-14
A100: 43100 | B100: POR COBRAR | C100: DICIEMBRE | D100: LUZ | E100: 24.6 | G100: =+G99+E100-F100 -> 24.6
D101: AGUA | E101: 2 | G101: =+G100+E101-F101 -> 26.6
D102: G. ADM | E102: 60 | G102: =+G101+E102-F102 -> 86.6
...

Sheet SEGOVIA  VILLAFUERTE
B2: SEGOVIA VILLAFUERTE DE PONCE JUSTINA
A4: FECHA | B4: DOCUMENTO | C4: PERIODO | D4: CONCEPTO | E4: POR COBRAR | F4: PAGADO | G4: SALDO POR COBRAR
A5: 42736 | B5: SALDO AL 2016 | G5: 183.8
A6: 42765 | B6: 12175 | C6: A CUENTA 2016 | F6: 62 | G6: =+G5+E6-F6 -> 121.8
A7: 42786 | B7: 12297 | C7: CANCELACION 2016 | F7: 121.8 | G7: =+G6+E7-F7 -> 0
A8: 42766 | B8: POR COBRAR | C8: ENERO | D8: LUZ | E8: 50.4 | G8: =+G7+E8-F8 -> 50.4
D9: AGUA | E9: 2.8 | G9: =+G8+E9-F9 -> 53.2
D10: G. ADM | E10: 60 | G10: =+G9+E10-F10 -> 113.2
D11: P. SOCIAL | E11: 2 | G11: =+G10+E11-F11 -> 115.2
A12: 42822 | B12: 12617 | C12: ENERO | D12: G. ADM | F12: 40 | G12: =+G11+E12-F12 -> 75.2
A13: 42766 | B13: TARJETA | C13: ENERO | D13: G. ADM | F13: 20 | G13: =+G12+E13-F13 -> 55.2
A14: 42766 | B14: TARJETA | C14: ENERO | D14: P. SOCIAL | F14: 2 | G14: =+G13+E14-F14 -> 53.2
A15: 42786 | B15: 12297 | C15: ENERO | D15: LUZ | F15: 50.4 | G15: =+G14+E15-F15 -> 2.8
A16: 42786 | B16: 12297 | C16: ENERO | D16: AGUA | F16: 2.8 | G16: =+G15+E16-F16 -> -9.7699626e-15
A17: 42794 | B17: POR COBRAR | C17: FEBRERO | D17: LUZ | E17: 72.4 | G17: =+G16+E17-F17 -> 72.4
D18: AGUA | E18: 2 | G18: =+G17+E18-F18 -> 74.4
D19: G. ADM | E19: 56 | G19: =+G18+E19-F19 -> 130.4 | K19: 16
D20: P. SOCIAL | E20: 2 | G20: =+G19+E20-F20 -> 132.4 | K20: 13 | M20: 164
D21: FALLECIMIENTO | E21: 10 | G21: =+G20+E21-F21 -> 142.4 | K21: 16 | M21: =185-M20 -> 21
A22: 42788 | B22: TARJETA | C22: FEBRERO | D22: FALLECIMIENTO | F22: 10 | G22: =+G21+E22-F22 -> 132.4 | K22: 16
A23: 42788 | B23: TARJETA | C23: FEBRERO | D23: G. ADM | F23: 56 | G23: =+G22+E23-F23 -> 76.4 | K23: 13
A24: 42788 | B24: TARJETA | C24: FEBRERO | D24: P. SOCIAL | F24: 2 | G24: =+G23+E24-F24 -> 74.4 | K24: 12
A25: 42822 | B25: 12618 | C25: FEBRERO | D25: LUZ | F25: 72.4 | G25: =+G24+E25-F25 -> 2 | K25: 2
A26: 42822 | B26: 12618 | C26: FEBRERO | D26: AGUA | F26: 2 | G26: =+G25+E26-F26 -> -2.8421709e-14
A27: 42825 | B27: POR COBRAR | C27: MARZO | D27: LUZ | E27: 47.4 | G27: =+G26+E27-F27 -> 47.4
D28: AGUA | E28: 2 | G28: =+G27+E28-F28 -> 49.4
D29: G. ADM | E29: 60 | G29: =+G28+E29-F29 -> 109.4
D30: P. SOCIAL | E30: 2 | G30: =+G29+E30-F30 -> 111.4
D31: P. SOCIAL X FALLEC. | E31: 10 | G31: =+G30+E31-F31 -> 121.4
A32: 42822 | B32: 12617 | C32: MARZO | D32: P. SOCIAL X FALLEC. | F32: 10 | G32: =+G31+E32-F32 -> 111.4
A33: 42825 | B33: 12625 | C33: MARZO | D33: G. ADM | F33: 60 | G33: =+G32+E33-F33 -> 51.4
A34: 42825 | B34: 12625 | C34: MARZO | D34: P. SOCIAL | F34: 2 | G34: =+G33+E34-F34 -> 49.4
A35: 42893 | B35: 13083 | C35: MARZO | D35: LUZ | F35: 47.4 | G35: =+G34+E35-F35 -> 2
A36: 42893 | B36: 13083 | C36: MARZO | D36: AGUA | F36: 2 | G36: =+G35+E36-F36 -> -2.1316282e-14
A37: 42855 | B37: POR COBRAR | C37: ABRIL | D37: LUZ | E37: 49.7 | G37: =+G36+E37-F37 -> 49.7
D38: AGUA | E38: 2 | G38: =+G37+E38-F38 -> 51.7
D39: G. ADM | E39: 60 | G39: =+G38+E39-F39 -> 111.7
D40: P. SOCIAL | E40: 2 | G40: =+G39+E40-F40 -> 113.7
A41: 42893 | B41: 13083 | C41: ABRIL | D41: LUZ | F41: 49.7 | G41: =+G40+E41-F41 -> 64
A42: 42893 | B42: 13083 | C42: ABRIL | D42: AGUA | F42: 2 | G42: =+G41+E42-F42 -> 62
A43: 42940 | B43: 13249 | C43: ABRIL | D43: G. ADM | F43: 60 | G43: =+G42+E43-F43 -> 2
A44: 42940 | B44: 13249 | C44: ABRIL | D44: P. SOCIAL | F44: 2 | G44: =+G43+E44-F44 -> -1.4210855e-14
A45: 42886 | B45: POR COBRAR | C45: MAYO | D45: LUZ | E45: 34.8 | G45: =+G44+E45-F45 -> 34.8
D46: AGUA | E46: 2 | G46: =+G45+E46-F46 -> 36.8
D47: G. ADM | E47: 60 | G47: =+G46+E47-F47 -> 96.8
D48: P. SOCIAL | E48: 2 | G48: =+G47+E48-F48 -> 98.8
A49: 42940 | B49: 13249 | C49: MAYO | D49: G. ADM | F49: 60 | G49: =+G48+E49-F49 -> 38.8
A50: 42940 | B50: 13249 | C50: MAYO | D50: P. SOCIAL | F50: 2 | G50: =+G49+E50-F50 -> 36.8
A51: 42949 | B51: 13364 | C51: MAYO | D51: LUZ | F51: 34.8 | G51: =+G50+E51-F51 -> 2
A52: 42949 | B52: 13364 | C52: MAYO | D52: AGUA | F52: 2 | G52: =+G51+E52-F52 -> -1.4210855e-14
A53: 42916 | B53: POR COBRAR | C53: JUNIO | D53: LUZ | E53: 33.9 | G53: =+G52+E53-F53 -> 33.9
D54: AGUA | E54: 2 | G54: =+G53+E54-F54 -> 35.9
D55: G. ADM | E55: 60 | G55: =+G54+E55-F55 -> 95.9
D56: P. SOCIAL | E56: 2 | G56: =+G55+E56-F56 -> 97.9
A57: 42940 | B57: 13249 | C57: JUNIO | D57: G. ADM | F57: 60 | G57: =+G56+E57-F57 -> 37.9
A58: 42940 | B58: 13249 | C58: JUNIO | D58: P. SOCIAL | F58: 2 | G58: =+G57+E58-F58 -> 35.9
A59: 42949 | B59: 13364 | C59: JUNIO | D59: LUZ | F59: 33.9 | G59: =+G58+E59-F59 -> 2
A60: 42949 | B60: 13364 | C60: JUNIO | D60: AGUA | F60: 2 | G60: =+G59+E60-F60 -> -2.1316282e-14
A61: 42947 | B61: POR COBRAR | C61: JULIO | D61: LUZ | E61: 44.7 | G61: =+G60+E61-F61 -> 44.7
D62: AGUA | E62: 2 | G62: =+G61+E62-F62 -> 46.7
D63: G. ADM | E63: 60 | G63: =+G62+E63-F63 -> 106.7
D64: P. SOCIAL | E64: 2 | G64: =+G63+E64-F64 -> 108.7
D65: FUMIGACION | E65: 10 | G65: =+G64+E65-F65 -> 118.7
D66: P. SOCIAL X FALLEC. | E66: 10 | G66: =+G65+E66-F66 -> 128.7
A67: 42949 | B67: 13364 | C67: JULIO | D67: FUMIGACION | F67: 10 | G67: =+G66+E67-F67 -> 118.7
A68: 42949 | B68: 13364 | C68: JULIO | D68: P. SOCIAL X FALLEC. | F68: 10 | G68: =+G67+E68-F68 -> 108.7
A69: 42949 | B69: 13366 | C69: JULIO | D69: P. SOCIAL | F69: 2 | G69: =+G68+E69-F69 -> 106.7
A70: 42949 | B70: 13366 | C70: JULIO | D70: G. ADM | F70: 60 | G70: =+G69+E70-F70 -> 46.7
A71: 43005 | B71: 13692 | C71: JULIO | D71: AGUA | F71: 2 | G71: =+G70+E71-F71 -> 44.7
A72: 43005 | B72: 13692 | C72: JULIO | D72: LUZ | F72: 44.7 | G72: =+G71+E72-F72 -> 0
A73: 42978 | B73: POR COBRAR | C73: AGOSTO | D73: LUZ | E73: 44.7 | G73: =+G72+E73-F73 -> 44.7
D74: AGUA | E74: 2 | G74: =+G73+E74-F74 -> 46.7
D75: G. ADM | E75: 60 | G75: =+G74+E75-F75 -> 106.7
D76: P. SOCIAL | E76: 2 | G76: =+G75+E76-F76 -> 108.7
A77: 43054 | B77: 13984 | C77: AGOSTO | D77: G. ADM | F77: 60 | G77: =+G76+E77-F77 -> 48.7
A78: 43054 | B78: 13984 | C78: AGOSTO | D78: P. SOCIAL | F78: 2 | G78: =+G77+E78-F78 -> 46.7
A79: 43067 | B79: 14151 | C79: AGOSTO | D79: LUZ | F79: 44.7 | G79: =+G78+E79-F79 -> 2
A80: 43067 | B80: 14151 | C80: AGOSTO | D80: AGUA | F80: 2 | G80: =+G79+E80-F80 -> 0
A81: 43008 | B81: POR COBRAR | C81: SEPTIEMBRE | D81: LUZ | E81: 37.8 | G81: =+G80+E81-F81 -> 37.8
D82: AGUA | E82: 2 | G82: =+G81+E82-F82 -> 39.8
D83: G. ADM | E83: 60 | G83: =+G82+E83-F83 -> 99.8
D84: P. SOCIAL | E84: 2 | G84: =+G83+E84-F84 -> 101.8
A85: 42823 | D85: MULTA | E85: 85 | G85: =+G84+E85-F85 -> 186.8
A86: 43054 | B86: 13984 | C86: SEPTIEMBRE | D86: G. ADM | F86: 60 | G86: =+G85+E86-F86 -> 126.8
A87: 43054 | B87: 13984 | C87: SEPTIEMBRE | D87: P. SOCIAL | F87: 2 | G87: =+G86+E87-F87 -> 124.8
A88: 43067 | B88: EXONERACION | C88: 42823 | D88: MULTA | F88: 85 | G88: =+G87+E88-F88 -> 39.8
A89: 43067 | B89: 14151 | C89: SEPTIEMBRE | D89: LUZ | F89: 37.8 | G89: =+G88+E89-F89 -> 2
A90: 43067 | B90: 14151 | C90: SEPTIEMBRE | D90: AGUA | F90: 2 | G90: =+G89+E90-F90 -> 1.4210855e-14
A91: 43039 | B91: POR COBRAR | C91: OCTUBRE | D91: LUZ | E91: 37.5 | G91: =+G90+E91-F91 -> 37.5
D92: AGUA | E92: 2 | G92: =+G91+E92-F92 -> 39.5
D93: G. ADM | E93: 60 | G93: =+G92+E93-F93 -> 99.5
D94: P. SOCIAL | E94: 2 | G94: =+G93+E94-F94 -> 101.5
A95: 43054 | B95: 13984 | C95: OCTUBRE | D95: G. ADM | F95: 60 | G95: =+G94+E95-F95 -> 41.5
A96: 43054 | B96: 13984 | C96: OCTUBRE | D96: P. SOCIAL | F96: 2 | G96: =+G95+E96-F96 -> 39.5
A97: 43067 | B97: 14151 | C97: OCTUBRE | D97: LUZ | F97: 37.5 | G97: =+G96+E97-F97 -> 2
A98: 43067 | B98: 14151 | C98: OCTUBRE | D98: AGUA | F98: 2 | G98: =+G97+E98-F98 -> 1.4210855e-14
A99: 43069 | B99: POR COBRAR | C99: NOVIEMBRE | D99: LUZ | E99: 40 | G99: =+G98+E99-F99 -> 40
D100: AGUA | E100: 2 | G100: =+G99+E100-F100 -> 42
D101: G. ADM | E101: 60 | G101: =+G100+E101-F101 -> 102
D102: P. SOCIAL | E102: 2 | G102: =+G101+E102-F102 -> 104
...

Sheet SERMEÑO JAVIER
B2: SERMEÑO GUTIERREZ JAVIER YGNACIO
A4: FECHA | B4: DOCUMENTO | C4: PERIODO | D4: CONCEPTO | E4: POR COBRAR | F4: PAGADO | G4: SALDO POR COBRAR
A5: 42736 | B5: SALDO AL 2016 | G5: 433.3
A6: 42752 | B6: 12112 | C6: CANCELADO | F6: 433.3 | G6: =+G5+E6-F6 -> 0
A7: 42766 | B7: POR COBRAR | C7: ENERO | D7: LUZ | E7: 174.8 | G7: =+G6+E7-F7 -> 174.8
D8: AGUA | E8: 19.2 | G8: =+G7+E8-F8 -> 194
D9: G. ADM | E9: 60 | G9: =+G8+E9-F9 -> 254
D10: P. SOCIAL | E10: 2 | G10: =+G9+E10-F10 -> 256
A11: 42765 | B11: TARJETA | C11: ENERO | D11: G. ADM | F11: 60 | G11: =+G10+E11-F11 -> 196
A12: 42765 | B12: TARJETA | C12: ENERO | D12: P. SOCIAL | F12: 2 | G12: =+G11+E12-F12 -> 194
A13: 42786 | B13: 12206 | C13: ENERO | D13: LUZ | F13: 174.8 | G13: =+G12+E13-F13 -> 19.2
A14: 42786 | B14: 12206 | C14: ENERO | D14: AGUA | F14: 19.2 | G14: =+G13+E14-F14 -> 0
A15: 42794 | B15: POR COBRAR | C15: FEBRERO | D15: LUZ | E15: 179.6 | G15: =+G14+E15-F15 -> 179.6
D16: AGUA | E16: 13 | G16: =+G15+E16-F16 -> 192.6
D17: G. ADM | E17: 56 | G17: =+G16+E17-F17 -> 248.6
D18: P. SOCIAL | E18: 2 | G18: =+G17+E18-F18 -> 250.6
A19: 42794 | B19: TARJETA | C19: FEBRERO | D19: G. ADM | F19: 56 | G19: =+G18+E19-F19 -> 194.6
A20: 42794 | B20: TARJETA | C20: FEBRERO | D20: P. SOCIAL | F20: 2 | G20: =+G19+E20-F20 -> 192.6
A21: 42821 | B21: 12534 | C21: FEBRERO | D21: LUZ | F21: 179.6 | G21: =+G20+E21-F21 -> 13
A22: 42821 | B22: 12534 | C22: FEBRERO | D22: AGUA | F22: 13 | G22: =+G21+E22-F22 -> 0
A23: 42825 | B23: POR COBRAR | C23: MARZO | D23: LUZ | E23: 172 | G23: =+G22+E23-F23 -> 172
D24: AGUA | E24: 14 | G24: =+G23+E24-F24 -> 186
D25: G. ADM | E25: 60 | G25: =+G24+E25-F25 -> 246
D26: P. SOCIAL | E26: 2 | G26: =+G25+E26-F26 -> 248
D27: P. SOCIAL X FALLEC. | E27: 10 | G27: =+G26+E27-F27 -> 258
A28: 42822 | B28: 12581 | C28: MARZO | D28: P. SOCIAL X FALLEC. | F28: 10 | G28: =+G27+E28-F28 -> 248
A29: 42825 | B29: TARJETA | C29: MARZO | D29: G. ADM | F29: 60 | G29: =+G28+E29-F29 -> 188
A30: 42825 | B30: TARJETA | C30: MARZO | D30: P. SOCIAL | F30: 2 | G30: =+G29+E30-F30 -> 186
A31: 42846 | B31: 12678 | C31: MARZO | D31: LUZ | F31: 172 | G31: =+G30+E31-F31 -> 14
A32: 42846 | B32: 12678 | C32: MARZO | D32: AGUA | F32: 14 | G32: =+G31+E32-F32 -> 0
A33: 42855 | B33: POR COBRAR | C33: ABRIL | D33: LUZ | E33: 175.4 | G33: =+G32+E33-F33 -> 175.4
D34: AGUA | E34: 13.7 | G34: =+G33+E34-F34 -> 189.1
D35: G. ADM | E35: 60 | G35: =+G34+E35-F35 -> 249.1
D36: P. SOCIAL | E36: 2 | G36: =+G35+E36-F36 -> 251.1
A37: 42854 | B37: TARJETA | C37: ABRIL | D37: G. ADM | F37: 60 | G37: =+G36+E37-F37 -> 191.1
A38: 42854 | B38: TARJETA | C38: ABRIL | D38: P. SOCIAL | F38: 2 | G38: =+G37+E38-F38 -> 189.1
A39: 42886 | B39: 13009 | C39: ABRIL | D39: LUZ | F39: 175.4 | G39: =+G38+E39-F39 -> 13.7
A40: 42886 | B40: 13009 | C40: ABRIL | D40: AGUA | F40: 13.7 | G40: =+G39+E40-F40 -> 0
A41: 42886 | B41: POR COBRAR | C41: MAYO | D41: LUZ | E41: 163.6 | G41: =+G40+E41-F41 -> 163.6
D42: AGUA | E42: 13.4 | G42: =+G41+E42-F42 -> 177
D43: G. ADM | E43: 60 | G43: =+G42+E43-F43 -> 237
D44: P. SOCIAL | E44: 2 | G44: =+G43+E44-F44 -> 239
A45: 42885 | B45: TARJETA | C45: MAYO | D45: G. ADM | F45: 60 | G45: =+G44+E45-F45 -> 179
A46: 42885 | B46: TARJETA | C46: MAYO | D46: P. SOCIAL | F46: 2 | G46: =+G45+E46-F46 -> 177
A47: 42909 | B47: 13145 | C47: MAYO | D47: LUZ | F47: 163.6 | G47: =+G46+E47-F47 -> 13.4
A48: 42909 | B48: 13145 | C48: MAYO | D48: AGUA | F48: 13.4 | G48: =+G47+E48-F48 -> 0
A49: 42916 | B49: POR COBRAR | C49: JUNIO | D49: LUZ | E49: 160 | G49: =+G48+E49-F49 -> 160
D50: AGUA | E50: 13.5 | G50: =+G49+E50-F50 -> 173.5
D51: G. ADM | E51: 60 | G51: =+G50+E51-F51 -> 233.5
D52: P. SOCIAL | E52: 2 | G52: =+G51+E52-F52 -> 235.5
A53: 42916 | B53: TARJETA | C53: JUNIO | D53: G. ADM | F53: 60 | G53: =+G52+E53-F53 -> 175.5
A54: 42916 | B54: TARJETA | C54: JUNIO | D54: P. SOCIAL | F54: 2 | G54: =+G53+E54-F54 -> 173.5
A55: 42947 | B55: 13280 | C55: JUNIO | D55: LUZ | F55: 160 | G55: =+G54+E55-F55 -> 13.5
A56: 42947 | B56: 13280 | C56: JUNIO | D56: AGUA | F56: 13.5 | G56: =+G55+E56-F56 -> 0
A57: 42947 | B57: POR COBRAR | C57: JULIO | D57: LUZ | E57: 144.2 | G57: =+G56+E57-F57 -> 144.2
D58: AGUA | E58: 13.5 | G58: =+G57+E58-F58 -> 157.7
D59: G. ADM | E59: 60 | G59: =+G58+E59-F59 -> 217.7
D60: P. SOCIAL | E60: 2 | G60: =+G59+E60-F60 -> 219.7
A61: 42945 | B61: TARJETA | C61: JULIO | D61: G. ADM | F61: 60 | G61: =+G60+E61-F61 -> 159.7
A62: 42945 | B62: TARJETA | C62: JULIO | D62: P. SOCIAL | F62: 2 | G62: =+G61+E62-F62 -> 157.7
A63: 42972 | B63: 13493 | C63: JULIO | D63: LUZ | F63: 144.2 | G63: =+G62+E63-F63 -> 13.5
A64: 42972 | B64: 13493 | C64: JULIO | D64: AGUA | F64: 13.5 | G64: =+G63+E64-F64 -> 0
A65: 42978 | B65: POR COBRAR | C65: AGOSTO | D65: LUZ | E65: 144.2 | G65: =+G64+E65-F65 -> 144.2
D66: AGUA | E66: 13.5 | G66: =+G65+E66-F66 -> 157.7
D67: G. ADM | E67: 60 | G67: =+G66+E67-F67 -> 217.7
D68: P. SOCIAL | E68: 2 | G68: =+G67+E68-F68 -> 219.7
A69: 42978 | B69: TARJETA | C69: AGOSTO | D69: P. SOCIAL | F69: 60 | G69: =+G68+E69-F69 -> 159.7
A70: 42978 | B70: TARJETA | C70: AGOSTO | D70: G. ADM | F70: 2 | G70: =+G69+E70-F70 -> 157.7
A71: 42996 | B71: 13584 | C71: AGOSTO | D71: LUZ | F71: 144.2 | G71: =+G70+E71-F71 -> 13.5
A72: 42996 | B72: 13584 | C72: AGOSTO | D72: AGUA | F72: 13.5 | G72: =+G71+E72-F72 -> 0
A73: 43008 | B73: POR COBRAR | C73: SEPTIEMBRE | D73: LUZ | E73: 149.9 | F73: 0 | G73: =+G72+E73-F73 -> 149.9
D74: AGUA | E74: 8.9 | G74: =+G73+E74-F74 -> 158.8
D75: G. ADM | E75: 60 | G75: =+G74+E75-F75 -> 218.8
D76: P. SOCIAL | E76: 2 | G76: =+G75+E76-F76 -> 220.8
A77: 43008 | B77: TARJETA | C77: SEPTIEMBRE | D77: G. ADM | F77: 60 | G77: =+G76+E77-F77 -> 160.8
A78: 43008 | B78: TARJETA | C78: SEPTIEMBRE | D78: P. SOCIAL | F78: 2 | G78: =+G77+E78-F78 -> 158.8
A79: 43029 | B79: 13847 | C79: SEPTIEMBRE | D79: LUZ | F79: 149.9 | G79: =+G78+E79-F79 -> 8.9
A80: 43029 | B80: 13847 | C80: SEPTIEMBRE | D80: AGUA | F80: 8.9 | G80: =+G79+E80-F80 -> 0
A81: 43039 | B81: POR COBRAR | C81: OCTUBRE | D81: LUZ | E81: 150.4 | G81: =+G80+E81-F81 -> 150.4
D82: AGUA | E82: 13.5 | G82: =+G81+E82-F82 -> 163.9
D83: G. ADM | E83: 60 | G83: =+G82+E83-F83 -> 223.9
D84: P. SOCIAL | E84: 2 | G84: =+G83+E84-F84 -> 225.9
A85: 43039 | B85: TARJETA | C85: OCTUBRE | D85: G. ADM | F85: 60 | G85: =+G84+E85-F85 -> 165.9
A86: 43039 | B86: TARJETA | C86: OCTUBRE | D86: P. SOCIAL | F86: 2 | G86: =+G85+E86-F86 -> 163.9
A87: 43060 | B87: 10207 | C87: OCTUBRE | D87: LUZ | F87: 150.4 | G87: =+G86+E87-F87 -> 13.5
A88: 43060 | B88: 10207 | C88: OCTUBRE | D88: AGUA | F88: 13.5 | G88: =+G87+E88-F88 -> 0
A89: 43069 | B89: POR COBRAR | C89: NOVIEMBRE | D89: LUZ | E89: 190 | G89: =+G88+E89-F89 -> 190
D90: AGUA | E90: 13.4 | G90: =+G89+E90-F90 -> 203.4
D91: G. ADM | E91: 60 | G91: =+G90+E91-F91 -> 263.4
D92: P. SOCIAL | E92: 2 | G92: =+G91+E92-F92 -> 265.4
A93: 43069 | B93: POR COBRAR | C93: NOVIEMBRE | D93: ALQUILER AUDITORIO | E93: 200 | G93: =+G92+E93-F93 -> 465.4
A94: 43060 | B94: 13999 | C94: NOVIEMBRE | D94: ALQUILER AUDITORIO | F94: 200 | G94: =+G93+E94-F94 -> 265.4
A95: 43087 | B95: 14261 | C95: NOVIEMBRE | D95: LUZ | F95: 190 | G95: =+G94+E95-F95 -> 75.4
A96: 43087 | B96: 14261 | C96: NOVIEMBRE | D96: AGUA | F96: 13.4 | G96: =+G95+E96-F96 -> 62
A97: 43069 | B97: TARJETA | C97: NOVIEMBRE | D97: G. ADM | F97: 60 | G97: =+G96+E97-F97 -> 2
A98: 43069 | B98: TARJETA | C98: NOVIEMBRE | D98: P. SOCIAL | F98: 2 | G98: =+G97+E98-F98 -> -2.1316282e-14
A99: 43100 | B99: POR COBRAR | C99: DICIEMBRE | D99: LUZ | E99: 206.7 | G99: =+G98+E99-F99 -> 206.7
D100: AGUA | E100: 13.5 | G100: =+G99+E100-F100 -> 220.2
D101: G. ADM | E101: 60 | G101: =+G100+E101-F101 -> 280.2
D102: P. SOCIAL | E102: 2 | G102: =+G101+E102-F102 -> 282.2
...

Sheet Soria Tapia Edith
B2: EDITH CATALINA SORIA TAPIA
A4: FECHA | B4: DOCUMENTO | C4: PERIODO | D4: CONCEPTO | E4: POR COBRAR | F4: PAGADO | G4: SALDO POR COBRAR
A5: 42736 | B5: SALDO AL 2016 | G5: 763.6
A6: 42739 | B6: 12065 | C6: A CUENTA 2016 | F6: 496.5 | G6: =+G5+E6-F6 -> 267.1
A7: 42739 | B7: 12066 | C7: A CUENTA 2016 | F7: 9 | G7: =+G6+E7-F7 -> 258.1
A8: 42910 | B8: 13149 | C8: A CUENTA 2016 | F8: 171.1 | G8: =+G7+E8-F8 -> 87
A9: 42912 | B9: 13153 | C9: A CUENTA 2016 | F9: 3 | G9: =+G8+E9-F9 -> 84
A10: 43368 | B10: 16248 | C10: A CUENTA 2016 | F10: 59 | G10: =+G9+E10-F10 -> 25
F11: 25 | G11: =+G10+E11-F11 -> 2.8421709e-14
A12: 42766 | B12: POR COBRAR | C12: ENERO | D12: LUZ | E12: 163 | G12: =+G11+E12-F12 -> 163
D13: AGUA | E13: 2 | G13: =+G12+E13-F13 -> 165
D14: G. ADM | E14: 60 | G14: =+G13+E14-F14 -> 225
D15: P. SOCIAL | E15: 2 | G15: =+G14+E15-F15 -> 227
A16: 42875 | B16: 12785 | C16: ENERO | D16: G. ADM | F16: 60 | G16: =+G15+E16-F16 -> 167
A17: 42875 | B17: 12785 | C17: ENERO | D17: P. SOCIAL | F17: 2 | G17: =+G16+E17-F17 -> 165
A18: 42910 | B18: 13149 | C18: ENERO | D18: LUZ | F18: 163 | G18: =+G17+E18-F18 -> 2
A19: 42912 | B19: 13153 | C19: ENERO | D19: AGUA | F19: 2 | G19: =+G18+E19-F19 -> 2.8421709e-14
A20: 42794 | B20: POR COBRAR | C20: FEBRERO | D20: LUZ | E20: 167 | G20: =+G19+E20-F20 -> 167
D21: AGUA | E21: 2 | G21: =+G20+E21-F21 -> 169
D22: G. ADM | E22: 56 | G22: =+G21+E22-F22 -> 225
D23: P. SOCIAL | E23: 2 | G23: =+G22+E23-F23 -> 227
D24: MULTA | E24: 85 | G24: =+G23+E24-F24 -> 312
A25: 42875 | B25: 12785 | C25: FEBRERO | D25: G. ADM | F25: 56 | G25: =+G24+E25-F25 -> 256
A26: 42875 | B26: 12785 | C26: FEBRERO | D26: P. SOCIAL | F26: 2 | G26: =+G25+E26-F26 -> 254
A27: 42910 | B27: 13149 | C27: FEBRERO | D27: LUZ | F27: 167 | G27: =+G26+E27-F27 -> 87
A28: 42912 | B28: 13153 | C28: FEBRERO | D28: AGUA | F28: 2 | G28: =+G27+E28-F28 -> 85
A29: 43067 | B29: EXONERACION | C29: FEBRERO | D29: MULTA | F29: 85 | G29: =+G28+E29-F29 -> 0
A30: 42825 | B30: POR COBRAR | C30: MARZO | D30: LUZ | E30: 160.3 | G30: =+G29+E30-F30 -> 160.3
D31: AGUA | E31: 2 | G31: =+G30+E31-F31 -> 162.3
D32: G. ADM | E32: 60 | G32: =+G31+E32-F32 -> 222.3
D33: P. SOCIAL | E33: 2 | G33: =+G32+E33-F33 -> 224.3
A34: 42875 | B34: 12785 | C34: MARZO | D34: G. ADM | F34: 60 | G34: =+G33+E34-F34 -> 164.3
A35: 42875 | B35: 12785 | C35: MARZO | D35: P. SOCIAL | F35: 2 | G35: =+G34+E35-F35 -> 162.3
A36: 42910 | B36: 13149 | C36: MARZO | D36: LUZ | F36: 160.3 | G36: =+G35+E36-F36 -> 2
A37: 42912 | B37: 13153 | C37: MARZO | D37: AGUA | F37: 2 | G37: =+G36+E37-F37 -> 0
A38: 42855 | B38: POR COBRAR | C38: ABRIL | D38: LUZ | E38: 164.2 | G38: =+G37+E38-F38 -> 164.2
D39: AGUA | E39: 2 | G39: =+G38+E39-F39 -> 166.2
D40: G. ADM | E40: 60 | G40: =+G39+E40-F40 -> 226.2
D41: P. SOCIAL | E41: 2 | G41: =+G40+E41-F41 -> 228.2
A42: 42875 | B42: 12785 | C42: ABRIL | D42: G. ADM | F42: 60 | G42: =+G41+E42-F42 -> 168.2
A43: 42875 | B43: 12785 | C43: ABRIL | D43: P. SOCIAL | F43: 2 | G43: =+G42+E43-F43 -> 166.2
A44: 42912 | B44: 13153 | C44: ABRIL | D44: LUZ | F44: 164.2 | G44: =+G43+E44-F44 -> 2
A45: 42912 | B45: 13153 | C45: ABRIL | D45: AGUA | F45: 2 | G45: =+G44+E45-F45 -> 0
A46: 42886 | B46: POR COBRAR | C46: MAYO | D46: LUZ | E46: 152.7 | G46: =+G45+E46-F46 -> 152.7
D47: AGUA | E47: 2 | G47: =+G46+E47-F47 -> 154.7
D48: G. ADM | E48: 60 | G48: =+G47+E48-F48 -> 214.7
D49: P. SOCIAL | E49: 2 | G49: =+G48+E49-F49 -> 216.7
A50: 42912 | B50: 13153 | C50: MAYO | D50: LUZ | F50: 152.7 | G50: =+G49+E50-F50 -> 64
A51: 42912 | B51: 13153 | C51: MAYO | D51: AGUA | F51: 2 | G51: =+G50+E51-F51 -> 62
A52: 43084 | B52: 14230 | C52: MAYO | D52: G. ADM | F52: 60 | G52: =+G51+E52-F52 -> 2
A53: 43084 | B53: 14230 | C53: MAYO | D53: P. SOCIAL | F53: 2 | G53: =+G52+E53-F53 -> 0
A54: 42916 | B54: POR COBRAR | C54: JUNIO | D54: LUZ | E54: 149.3 | G54: =+G53+E54-F54 -> 149.3
D55: AGUA | E55: 2 | G55: =+G54+E55-F55 -> 151.3
D56: G. ADM | E56: 60 | G56: =+G55+E56-F56 -> 211.3
D57: P. SOCIAL | E57: 2 | G57: =+G56+E57-F57 -> 213.3
A58: 43084 | B58: 14230 | C58: JUNIO | D58: G. ADM | F58: 60 | G58: =+G57+E58-F58 -> 153.3
A59: 43084 | B59: 14230 | C59: JUNIO | D59: P. SOCIAL | F59: 2 | G59: =+G58+E59-F59 -> 151.3
A60: 43084 | B60: 14230 | C60: JUNIO | D60: LUZ | F60: 149.3 | G60: =+G59+E60-F60 -> 2
A61: 43084 | B61: 14230 | C61: JUNIO | D61: AGUA | F61: 2 | G61: =+G60+E61-F61 -> 0
A62: 42947 | B62: POR COBRAR | C62: JULIO | D62: LUZ | E62: 134.8 | G62: =+G61+E62-F62 -> 134.8
D63: AGUA | E63: 2 | G63: =+G62+E63-F63 -> 136.8
D64: G. ADM | E64: 60 | G64: =+G63+E64-F64 -> 196.8
D65: P. SOCIAL | E65: 2 | G65: =+G64+E65-F65 -> 198.8
A66: 43084 | B66: 14230 | C66: JULIO | D66: G. ADM | F66: 60 | G66: =+G65+E66-F66 -> 138.8
A67: 43084 | B67: 14230 | C67: JULIO | D67: P. SOCIAL | F67: 2 | G67: =+G66+E67-F67 -> 136.8
A68: 43084 | B68: 14230 | C68: JULIO | D68: LUZ | F68: 134.8 | G68: =+G67+E68-F68 -> 2
A69: 43084 | B69: 14230 | C69: JULIO | D69: AGUA | F69: 2 | G69: =+G68+E69-F69 -> 0
A70: 42978 | B70: POR COBRAR | C70: AGOSTO | D70: LUZ | E70: 134.8 | G70: =+G69+E70-F70 -> 134.8
D71: AGUA | E71: 2 | G71: =+G70+E71-F71 -> 136.8
D72: G. ADM | E72: 60 | G72: =+G71+E72-F72 -> 196.8
D73: P. SOCIAL | E73: 2 | G73: =+G72+E73-F73 -> 198.8
D74: MULTA | E74: 85 | G74: =+G73+E74-F74 -> 283.8
A75: 43067 | B75: EXONERACION | C75: AGOSTO | D75: MULTA | F75: 85 | G75: =+G74+E75-F75 -> 198.8
A76: 43084 | B76: 14231 | C76: AGOSTO | D76: G. ADM | F76: 60 | G76: =+G75+E76-F76 -> 138.8
A77: 43084 | B77: 14231 | C77: AGOSTO | D77: P. SOCIAL | F77: 2 | G77: =+G76+E77-F77 -> 136.8
A78: 43084 | B78: 14231 | C78: AGOSTO | D78: LUZ | F78: 134.8 | G78: =+G77+E78-F78 -> 2
A79: 43084 | B79: 14231 | C79: AGOSTO | D79: AGUA | F79: 2 | G79: =+G78+E79-F79 -> 0
A80: 43008 | B80: POR COBRAR | C80: SEPTIEMBRE | D80: LUZ | E80: 99.1 | G80: =+G79+E80-F80 -> 99.1
D81: AGUA | E81: 2 | G81: =+G80+E81-F81 -> 101.1
D82: G. ADM | E82: 60 | G82: =+G81+E82-F82 -> 161.1
D83: P. SOCIAL | E83: 2 | G83: =+G82+E83-F83 -> 163.1
A84: 42823 | D84: MULTA | E84: 85 | G84: =+G83+E84-F84 -> 248.1
A85: 43067 | B85: EXONERACION | C85: 42823 | D85: MULTA | F85: 85 | G85: =+G84+E85-F85 -> 163.1
A86: 43084 | B86: 14231 | C86: SEPTIEMBRE | D86: G. ADM | F86: 60 | G86: =+G85+E86-F86 -> 103.1
A87: 43084 | B87: 14231 | C87: SEPTIEMBRE | D87: P. SOCIAL | F87: 2 | G87: =+G86+E87-F87 -> 101.1
A88: 43084 | B88: 14231 | C88: SEPTIEMBRE | D88: LUZ | F88: 99.1 | G88: =+G87+E88-F88 -> 2
A89: 43084 | B89: 14231 | C89: SEPTIEMBRE | D89: AGUA | F89: 2 | G89: =+G88+E89-F89 -> 0
A90: 43039 | B90: POR COBRAR | C90: OCTUBRE | D90: LUZ | E90: 98.6 | G90: =+G89+E90-F90 -> 98.6
D91: AGUA | E91: 2 | G91: =+G90+E91-F91 -> 100.6
D92: G. ADM | E92: 60 | G92: =+G91+E92-F92 -> 160.6
D93: P. SOCIAL | E93: 2 | G93: =+G92+E93-F93 -> 162.6
A94: 43084 | B94: 14231 | C94: OCTUBRE | D94: G. ADM | F94: 60 | G94: =+G93+E94-F94 -> 102.6
A95: 43084 | B95: 14231 | C95: OCTUBRE | D95: P. SOCIAL | F95: 2 | G95: =+G94+E95-F95 -> 100.6
A96: 43084 | B96: 14231 | C96: OCTUBRE | D96: LUZ | F96: 98.6 | G96: =+G95+E96-F96 -> 2
A97: 43084 | B97: 14231 | C97: OCTUBRE | D97: AGUA | F97: 2 | G97: =+G96+E97-F97 -> 0
A98: 43069 | B98: POR COBRAR | C98: NOVIEMBRE | D98: LUZ | E98: 105.3 | G98: =+G97+E98-F98 -> 105.3
D99: AGUA | E99: 2 | G99: =+G98+E99-F99 -> 107.3
D100: G. ADM | E100: 60 | G100: =+G99+E100-F100 -> 167.3
D101: P. SOCIAL | E101: 2 | G101: =+G100+E101-F101 -> 169.3
D102: P. S X FALL. FLORES EMMA | E102: 10 | G102: =+G101+E102-F102 -> 179.3
...

Sheet SOSA JUANA
B2: SOSA VALDIVIA JUANA
A4: FECHA | B4: DOCUMENTO | C4: PERIODO | D4: CONCEPTO | E4: POR COBRAR | F4: PAGADO | G4: SALDO POR COBRAR
A5: 42736 | B5: SALDO AL 2016 | G5: 38.9
A6: 42786 | B6: 12278 | C6: CANCELADO | F6: 38.9 | G6: =+G5+E6-F6 -> 0
A7: 42766 | B7: POR COBRAR | C7: ENERO | D7: LUZ | E7: 44.1 | G7: =+G6+E7-F7 -> 44.1
D8: AGUA | E8: 2.8 | G8: =+G7+E8-F8 -> 46.9
D9: G. ADM | E9: 60 | G9: =+G8+E9-F9 -> 106.9
D10: P. SOCIAL | E10: 2 | G10: =+G9+E10-F10 -> 108.9
A11: 42756 | B11: 12130 | C11: ENERO | D11: G. ADM | F11: 60 | G11: =+G10+E11-F11 -> 48.9
A12: 42756 | B12: 12130 | C12: ENERO | D12: P. SOCIAL | F12: 2 | G12: =+G11+E12-F12 -> 46.9
A13: 42786 | B13: 12278 | C13: ENERO | D13: LUZ | F13: 44.1 | G13: =+G12+E13-F13 -> 2.8
A14: 42786 | B14: 12278 | C14: ENERO | D14: AGUA | F14: 2.8 | G14: =+G13+E14-F14 -> 4.4408921e-15
A15: 42794 | B15: POR COBRAR | C15: FEBRERO | D15: LUZ | E15: 43.7 | G15: =+G14+E15-F15 -> 43.7
D16: AGUA | E16: 2 | G16: =+G15+E16-F16 -> 45.7
D17: G. ADM | E17: 60 | G17: =+G16+E17-F17 -> 105.7
D18: P. SOCIAL | E18: 2 | G18: =+G17+E18-F18 -> 107.7
A19: 42782 | B19: 12960 | C19: FEBRERO | D19: G. ADM | F19: 60 | G19: =+G18+E19-F19 -> 47.7
A20: 42782 | B20: 12960 | C20: FEBRERO | D20: P. SOCIAL | F20: 2 | G20: =+G19+E20-F20 -> 45.7
A21: 42822 | B21: 12603 | C21: FEBRERO | D21: AGUA | F21: 2 | G21: =+G20+E21-F21 -> 43.7
A22: 42822 | B22: 12603 | C22: FEBRERO | D22: LUZ | F22: 43.7 | G22: =+G21+E22-F22 -> 0
A23: 42825 | B23: POR COBRAR | C23: MARZO | D23: LUZ | E23: 41 | G23: =+G22+E23-F23 -> 41
D24: AGUA | E24: 2 | G24: =+G23+E24-F24 -> 43
D25: G. ADM | E25: 60 | G25: =+G24+E25-F25 -> 103
D26: P. SOCIAL | E26: 2 | G26: =+G25+E26-F26 -> 105
A27: 42821 | B27: 12492 | C27: MARZO | D27: G. ADM | F27: 60 | G27: =+G26+E27-F27 -> 45
A28: 42821 | B28: 12492 | C28: MARZO | D28: P. SOCIAL | F28: 2 | G28: =+G27+E28-F28 -> 43
A29: 42885 | B29: 12876 | C29: MARZO | D29: AGUA | F29: 2 | G29: =+G28+E29-F29 -> 41
A30: 42885 | B30: 12876 | C30: MARZO | D30: LUZ | F30: 41 | G30: =+G29+E30-F30 -> 0
A31: 42855 | B31: POR COBRAR | C31: ABRIL | D31: LUZ | E31: 43.2 | G31: =+G30+E31-F31 -> 43.2
D32: AGUA | E32: 2 | G32: =+G31+E32-F32 -> 45.2
D33: G. ADM | E33: 60 | G33: =+G32+E33-F33 -> 105.2
D34: P. SOCIAL | E34: 2 | G34: =+G33+E34-F34 -> 107.2
A35: 42877 | B35: 12801 | C35: ABRIL | D35: G. ADM | F35: 60 | G35: =+G34+E35-F35 -> 47.2
A36: 42877 | B36: 12801 | C36: ABRIL | D36: P. SOCIAL | F36: 2 | G36: =+G35+E36-F36 -> 45.2
A37: 42885 | B37: 12876 | C37: ABRIL | D37: AGUA | F37: 2 | G37: =+G36+E37-F37 -> 43.2
A38: 42885 | B38: 12876 | C38: ABRIL | D38: LUZ | F38: 43.2 | G38: =+G37+E38-F38 -> 0
A39: 42886 | B39: POR COBRAR | C39: MAYO | D39: LUZ | E39: 41.8 | G39: =+G38+E39-F39 -> 41.8
D40: AGUA | E40: 2 | G40: =+G39+E40-F40 -> 43.8
D41: G. ADM | E41: 60 | G41: =+G40+E41-F41 -> 103.8
D42: P. SOCIAL | E42: 2 | G42: =+G41+E42-F42 -> 105.8
A43: 42928 | B43: 13202 | C43: MAYO | D43: G. ADM | F43: 60 | G43: =+G42+E43-F43 -> 45.8
A44: 42928 | B44: 13202 | C44: MAYO | D44: P. SOCIAL | F44: 2 | G44: =+G43+E44-F44 -> 43.8
A45: 42949 | B45: 13365 | C45: MAYO | D45: AGUA | F45: 2 | G45: =+G44+E45-F45 -> 41.8
A46: 42949 | B46: 13365 | C46: MAYO | D46: LUZ | F46: 41.8 | G46: =+G45+E46-F46 -> 0
A47: 42916 | B47: POR COBRAR | C47: JUNIO | D47: LUZ | E47: 40.5 | G47: =+G46+E47-F47 -> 40.5
D48: AGUA | E48: 2 | G48: =+G47+E48-F48 -> 42.5
D49: G. ADM | E49: 60 | G49: =+G48+E49-F49 -> 102.5
D50: P. SOCIAL | E50: 2 | G50: =+G49+E50-F50 -> 104.5
A51: 42928 | B51: 13202 | C51: JUNIO | D51: G. ADM | F51: 60 | G51: =+G50+E51-F51 -> 44.5
A52: 42928 | B52: 13202 | C52: JUNIO | D52: P. SOCIAL | F52: 2 | G52: =+G51+E52-F52 -> 42.5
A53: 42949 | B53: 13365 | C53: JUNIO | D53: AGUA | F53: 2 | G53: =+G52+E53-F53 -> 40.5
A54: 42949 | B54: 13365 | C54: JUNIO | D54: LUZ | F54: 40.5 | G54: =+G53+E54-F54 -> 0
A55: 42947 | B55: POR COBRAR | C55: JULIO | D55: LUZ | E55: 39.6 | G55: =+G54+E55-F55 -> 39.6
D56: AGUA | E56: 2 | G56: =+G55+E56-F56 -> 41.6
D57: G. ADM | E57: 60 | G57: =+G56+E57-F57 -> 101.6
D58: P. SOCIAL | E58: 2 | G58: =+G57+E58-F58 -> 103.6
A59: 42928 | B59: 13202 | C59: JULIO | D59: P. SOCIAL | F59: 2 | G59: =+G58+E59-F59 -> 101.6
A60: 42928 | B60: 13202 | C60: JULIO | D60: G. ADM | F60: 60 | G60: =+G59+E60-F60 -> 41.6
A61: 42997 | B61: 13615 | C61: JULIO | D61: LUZ | F61: 2 | G61: =+G60+E61-F61 -> 39.6
A62: 42997 | B62: 13615 | C62: JULIO | D62: AGUA | F62: 39.6 | G62: =+G61+E62-F62 -> 0
A63: 42978 | B63: POR COBRAR | C63: AGOSTO | D63: LUZ | E63: 39.6 | G63: =+G62+E63-F63 -> 39.6
D64: AGUA | E64: 2 | G64: =+G63+E64-F64 -> 41.6
D65: G. ADM | E65: 60 | G65: =+G64+E65-F65 -> 101.6
D66: P. SOCIAL | E66: 2 | G66: =+G65+E66-F66 -> 103.6
D67: MULTA | E67: 85 | G67: =+G66+E67-F67 -> 188.6
A68: 42961 | B68: 13434 | C68: AGOSTO | D68: G. ADM | F68: 60 | G68: =+G67+E68-F68 -> 128.6
A69: 42961 | B69: 13434 | C69: AGOSTO | D69: P. SOCIAL | F69: 2 | G69: =+G68+E69-F69 -> 126.6
A70: 42997 | B70: 13615 | C70: AGOSTO | D70: LUZ | F70: 2 | G70: =+G69+E70-F70 -> 124.6
A71: 42997 | B71: 13615 | C71: AGOSTO | D71: AGUA | F71: 39.6 | G71: =+G70+E71-F71 -> 85
A72: 43062 | B72: 14020 | C72: AGOSTO | D72: MULTA | F72: 85 | G72: =+G71+E72-F72 -> 0
A73: 43008 | B73: POR COBRAR | C73: SEPTIEMBRE | D73: LUZ | E73: 23.2 | G73: =+G72+E73-F73 -> 23.2
D74: AGUA | E74: 2 | G74: =+G73+E74-F74 -> 25.2
D75: G. ADM | E75: 60 | G75: =+G74+E75-F75 -> 85.2
D76: P. SOCIAL | E76: 2 | G76: =+G75+E76-F76 -> 87.2
A77: 42788 | D77: MULTA | E77: 85 | G77: =+G76+E77-F77 -> 172.2
A78: 42823 | D78: MULTA | E78: 85 | G78: =+G77+E78-F78 -> 257.2
A79: 43062 | B79: 14020 | C79: SEPTIEMBRE | D79: MULTA | F79: 85 | G79: =+G78+E79-F79 -> 172.2
A80: 43062 | B80: 14020 | C80: SEPTIEMBRE | D80: MULTA | F80: 85 | G80: =+G79+E80-F80 -> 87.2
A81: 43062 | B81: 14020 | C81: SEPTIEMBRE | D81: G. ADM | F81: 60 | G81: =+G80+E81-F81 -> 27.2
A82: 43062 | B82: 14020 | C82: SEPTIEMBRE | D82: P. SOCIAL | F82: 2 | G82: =+G81+E82-F82 -> 25.2
A83: 43062 | B83: 14023 | C83: SEPTIEMBRE | D83: LUZ | F83: 23.2 | G83: =+G82+E83-F83 -> 2
A84: 43062 | B84: 14023 | C84: SEPTIEMBRE | D84: AGUA | F84: 2 | G84: =+G83+E84-F84 -> -1.0658141e-14
A85: 43039 | B85: POR COBRAR | C85: OCTUBRE | D85: LUZ | E85: 23.1 | G85: =+G84+E85-F85 -> 23.1
D86: AGUA | E86: 2 | G86: =+G85+E86-F86 -> 25.1
D87: G. ADM | E87: 60 | G87: =+G86+E87-F87 -> 85.1
D88: P. SOCIAL | E88: 2 | G88: =+G87+E88-F88 -> 87.1
A89: 43062 | B89: 14020 | C89: OCTUBRE | D89: G. ADM | F89: 60 | G89: =+G88+E89-F89 -> 27.1
A90: 43062 | B90: 14020 | C90: OCTUBRE | D90: P. SOCIAL | F90: 2 | G90: =+G89+E90-F90 -> 25.1
A91: 43062 | B91: 14023 | C91: OCTUBRE | D91: AGUA | F91: 2 | G91: =+G90+E91-F91 -> 23.1
A92: 43062 | B92: 14023 | C92: OCTUBRE | D92: LUZ | F92: 23.1 | G92: =+G91+E92-F92 -> 0
A93: 43069 | B93: POR COBRAR | C93: NOVIEMBRE | D93: LUZ | E93: 24.6 | G93: =+G92+E93-F93 -> 24.6
D94: AGUA | E94: 2 | G94: =+G93+E94-F94 -> 26.6
D95: G. ADM | E95: 60 | G95: =+G94+E95-F95 -> 86.6
D96: P. SOCIAL | E96: 2 | G96: =+G95+E96-F96 -> 88.6
D97: P. S X FALL. EMMA FLORES | E97: 10 | G97: =+G96+E97-F97 -> 98.6
A98: 43062 | B98: 14020 | C98: NOVIEMBRE | D98: G. ADM | F98: 60 | G98: =+G97+E98-F98 -> 38.6
A99: 43062 | B99: 14020 | C99: NOVIEMBRE | D99: P. SOCIAL | F99: 2 | G99: =+G98+E99-F99 -> 36.6
A100: 43062 | B100: 14020 | C100: NOVIEMBRE | D100: P. S X FALL. EMMA FLORES | F100: 10 | G100: =+G99+E100-F100 -> 26.6
A101: 43108 | B101: 14406 | C101: NOVIEMBRE | D101: LUZ | F101: 24.6 | G101: =+G100+E101-F101 -> 2
A102: 43108 | B102: 14406 | C102: NOVIEMBRE | D102: AGUA | F102: 2 | G102: =+G101+E102-F102 -> -7.1054274e-15
...

Sheet SOTO SOFIA
B2: SOTO GALLEGO DE VALERO SOFIA
A4: FECHA | B4: DOCUMENTO | C4: PERIODO | D4: CONCEPTO | E4: POR COBRAR | F4: PAGADO | G4: SALDO POR COBRAR
A5: 42736 | B5: SALDO AL 2016 | G5: 372
A6: 42887 | B6: AGUA RESIDUAL | E6: 45.6 | G6: =+G5+E6-F6 -> 417.6
A7: 42745 | B7: 12088 | C7: A CUENTA 2016 | F7: 372 | G7: =+G6+E7-F7 -> 45.6
A8: 42887 | B8: 13025 | C8: CANCELACION DEL 2016 | F8: 45.6 | G8: =+G7+E8-F8 -> 0
A9: 42766 | B9: POR COBRAR | C9: ENERO | D9: LUZ | E9: 19.9 | G9: =+G8+E9-F9 -> 19.9
D10: AGUA | E10: 2.7 | G10: =+G9+E10-F10 -> 22.6
D11: G. ADM | E11: 60 | G11: =+G10+E11-F11 -> 82.6
D12: P. SOCIAL | E12: 2 | G12: =+G11+E12-F12 -> 84.6
A13: 42818 | B13: 12462 | C13: ENERO | D13: G. ADM | F13: 60 | G13: =+G12+E13-F13 -> 24.6
A14: 42818 | B14: 12462 | C14: ENERO | D14: P. SOCIAL | F14: 2 | G14: =+G13+E14-F14 -> 22.6
A15: 42887 | B15: 13025 | C15: ENERO | D15: LUZ | F15: 2.7 | G15: =+G14+E15-F15 -> 19.9
A16: 42887 | B16: 13025 | C16: ENERO | D16: AGUA | F16: 19.9 | G16: =+G15+E16-F16 -> 0
A17: 42794 | B17: POR COBRAR | C17: FEBRERO | D17: LUZ | E17: 19.6 | G17: =+G16+E17-F17 -> 19.6
D18: AGUA | E18: 2 | G18: =+G17+E18-F18 -> 21.6
D19: G. ADM | E19: 56 | G19: =+G18+E19-F19 -> 77.6
D20: P. SOCIAL | E20: 2 | G20: =+G19+E20-F20 -> 79.6
A21: 42818 | B21: 12462 | C21: FEBRERO | D21: G. ADM | F21: 56 | G21: =+G20+E21-F21 -> 23.6
A22: 42818 | B22: 12462 | C22: FEBRERO | D22: P. SOCIAL | F22: 2 | G22: =+G21+E22-F22 -> 21.6
A23: 42887 | B23: 13025 | C23: FEBRERO | D23: LUZ | F23: 19.6 | G23: =+G22+E23-F23 -> 2
A24: 42887 | B24: 13025 | C24: FEBRERO | D24: AGUA | F24: 2 | G24: =+G23+E24-F24 -> -7.1054274e-15
A25: 42825 | B25: POR COBRAR | C25: MARZO | D25: LUZ | E25: 18.4 | G25: =+G24+E25-F25 -> 18.4
D26: AGUA | E26: 2 | G26: =+G25+E26-F26 -> 20.4
D27: G. ADM | E27: 60 | G27: =+G26+E27-F27 -> 80.4
D28: P. SOCIAL | E28: 2 | G28: =+G27+E28-F28 -> 82.4
A29: 42887 | B29: 13025 | C29: MARZO | D29: LUZ | F29: 18.4 | G29: =+G28+E29-F29 -> 64
A30: 42887 | B30: 13025 | C30: MARZO | D30: AGUA | F30: 2 | G30: =+G29+E30-F30 -> 62
A31: 42926 | B31: 13193 | C31: MARZO | D31: G. ADM | F31: 60 | G31: =+G30+E31-F31 -> 2
A32: 42926 | B32: 13193 | C32: MARZO | D32: P. SOCIAL | F32: 2 | G32: =+G31+E32-F32 -> -7.1054274e-15
A33: 42855 | B33: POR COBRAR | C33: ABRIL | D33: LUZ | E33: 19.5 | G33: =+G32+E33-F33 -> 19.5
D34: AGUA | E34: 2 | G34: =+G33+E34-F34 -> 21.5
D35: G. ADM | E35: 60 | G35: =+G34+E35-F35 -> 81.5
D36: P. SOCIAL | E36: 2 | G36: =+G35+E36-F36 -> 83.5
A37: 42887 | B37: 13025 | C37: ABRIL | D37: LUZ | F37: 19.5 | G37: =+G36+E37-F37 -> 64
A38: 42887 | B38: 13025 | C38: ABRIL | D38: AGUA | F38: 2 | G38: =+G37+E38-F38 -> 62
A39: 42926 | B39: 13193 | C39: ABRIL | D39: G. ADM | F39: 60 | G39: =+G38+E39-F39 -> 2
A40: 42926 | B40: 13193 | C40: ABRIL | D40: P. SOCIAL | F40: 2 | G40: =+G39+E40-F40 -> 0
A41: 42886 | B41: POR COBRAR | C41: MAYO | D41: LUZ | E41: 18.9 | G41: =+G40+E41-F41 -> 18.9
D42: AGUA | E42: 2 | G42: =+G41+E42-F42 -> 20.9
D43: G. ADM | E43: 60 | G43: =+G42+E43-F43 -> 80.9
D44: P. SOCIAL | E44: 2 | G44: =+G43+E44-F44 -> 82.9
A45: 42926 | B45: 13193 | C45: MAYO | D45: G. ADM | F45: 60 | G45: =+G44+E45-F45 -> 22.9
A46: 42926 | B46: 13193 | C46: MAYO | D46: P. SOCIAL | F46: 2 | G46: =+G45+E46-F46 -> 20.9
A47: 42971 | B47: 13461 | C47: MAYO | D47: LUZ | F47: 18.9 | G47: =+G46+E47-F47 -> 2
A48: 42971 | B48: 13461 | C48: MAYO | D48: AGUA | F48: 2 | G48: =+G47+E48-F48 -> 7.1054274e-15
A49: 42916 | B49: POR COBRAR | C49: JUNIO | D49: LUZ | E49: 18.8 | G49: =+G48+E49-F49 -> 18.8
D50: AGUA | E50: 2 | G50: =+G49+E50-F50 -> 20.8
D51: G. ADM | E51: 60 | G51: =+G50+E51-F51 -> 80.8
D52: P. SOCIAL | E52: 2 | G52: =+G51+E52-F52 -> 82.8
D53: CORTE/RECONECCION | E53: 30 | G53: =+G52+E53-F53 -> 112.8
A54: 42887 | B54: 13025 | C54: JUNIO | D54: CORTE/RECONECCION | F54: 30 | G54: =+G53+E54-F54 -> 82.8
A55: 42926 | B55: 13193 | C55: JUNIO | D55: G. ADM | F55: 60 | G55: =+G54+E55-F55 -> 22.8
A56: 42926 | B56: 13193 | C56: JUNIO | D56: P. SOCIAL | F56: 2 | G56: =+G55+E56-F56 -> 20.8
A57: 42971 | B57: 13461 | C57: JUNIO | D57: LUZ | F57: 18.8 | G57: =+G56+E57-F57 -> 2
A58: 42971 | B58: 13461 | C58: JUNIO | D58: AGUA | F58: 2 | G58: =+G57+E58-F58 -> 1.0658141e-14
A59: 42947 | B59: POR COBRAR | C59: JULIO | D59: LUZ | E59: 18.1 | G59: =+G58+E59-F59 -> 18.1
D60: AGUA | E60: 2 | G60: =+G59+E60-F60 -> 20.1
D61: G. ADM | E61: 60 | G61: =+G60+E61-F61 -> 80.1
D62: P. SOCIAL | E62: 2 | G62: =+G61+E62-F62 -> 82.1
A63: 42971 | B63: 13461 | C63: JULIO | D63: LUZ | F63: 18.1 | G63: =+G62+E63-F63 -> 64
A64: 42971 | B64: 13461 | C64: JULIO | D64: AGUA | F64: 2 | G64: =+G63+E64-F64 -> 62
A65: 43049 | B65: 13955 | C65: JULIO | D65: G. ADM | F65: 60 | G65: =+G64+E65-F65 -> 2
A66: 43049 | B66: 13955 | C66: JULIO | D66: P. SOCIAL | F66: 2 | G66: =+G65+E66-F66 -> 0
A67: 42978 | B67: POR COBRAR | C67: AGOSTO | D67: LUZ | E67: 18.1 | G67: =+G66+E67-F67 -> 18.1
D68: AGUA | E68: 2 | G68: =+G67+E68-F68 -> 20.1
D69: G. ADM | E69: 60 | G69: =+G68+E69-F69 -> 80.1
D70: P. SOCIAL | E70: 2 | G70: =+G69+E70-F70 -> 82.1
D71: MULTA | E71: 85 | G71: =+G70+E71-F71 -> 167.1
A72: 43007 | B72: 13710 | C72: AGOSTO | D72: LUZ | F72: 18.1 | G72: =+G71+E72-F72 -> 149
A73: 43007 | B73: 13710 | C73: AGOSTO | D73: AGUA | F73: 2 | G73: =+G72+E73-F73 -> 147 | J73: 44853
A74: 43049 | B74: 13955 | C74: AGOSTO | D74: G. ADM | F74: 60 | G74: =+G73+E74-F74 -> 87
A75: 43049 | B75: 13955 | C75: AGOSTO | D75: P. SOCIAL | F75: 2 | G75: =+G74+E75-F75 -> 85
A76: 44853 | B76: 0.5 | C76: EXONERACION | D76: MULTA | F76: 42.5 | G76: =+G75+E76-F76 -> 42.5
A77: 44875 | B77: 25766 | C77: AGOSTO | D77: MULTA | F77: 42.5 | G77: =+G76+E77-F77 -> 0
A78: 43008 | B78: POR COBRAR | C78: SEPTIEMBRE | D78: LUZ | E78: 13.5 | G78: =+G77+E78-F78 -> 13.5
D79: AGUA | E79: 2 | G79: =+G78+E79-F79 -> 15.5
D80: G. ADM | E80: 60 | G80: =+G79+E80-F80 -> 75.5
D81: P. SOCIAL | E81: 2 | G81: =+G80+E81-F81 -> 77.5
A82: 42788 | D82: MULTA | E82: 85 | G82: =+G81+E82-F82 -> 162.5
A83: 42823 | D83: MULTA | E83: 85 | G83: =+G82+E83-F83 -> 247.5
A84: 43049 | B84: 13955 | C84: SEPTIEMBRE | D84: G. ADM | F84: 60 | G84: =+G83+E84-F84 -> 187.5
A85: 43049 | B85: 13955 | C85: SEPTIEMBRE | D85: P. SOCIAL | F85: 2 | G85: =+G84+E85-F85 -> 185.5
A86: 43067 | B86: EXONERACION | C86: 42788 | D86: MULTA | F86: 85 | G86: =+G85+E86-F86 -> 100.5
A87: 43067 | B87: EXONERACION | C87: 42823 | D87: MULTA | F87: 85 | G87: =+G86+E87-F87 -> 15.5
A88: 43118 | B88: 14440 | C88: SEPTIEMBRE | D88: LUZ | F88: 13.5 | G88: =+G87+E88-F88 -> 2
A89: 43118 | B89: 14440 | C89: SEPTIEMBRE | D89: AGUA | F89: 2 | G89: =+G88+E89-F89 -> 0
A90: 43039 | B90: POR COBRAR | C90: OCTUBRE | D90: LUZ | E90: 13.5 | G90: =+G89+E90-F90 -> 13.5
D91: AGUA | E91: 2 | G91: =+G90+E91-F91 -> 15.5
D92: G. ADM | E92: 60 | G92: =+G91+E92-F92 -> 75.5
D93: P. SOCIAL | E93: 2 | G93: =+G92+E93-F93 -> 77.5
A94: 42977 | B94: ACT. SANTA ROSA | D94: CUOTA | E94: 25 | G94: =+G93+E94-F94 -> 102.5
A95: 43049 | B95: 13955 | C95: OCTUBRE | D95: G. ADM | F95: 60 | G95: =+G94+E95-F95 -> 42.5
A96: 43049 | B96: 13955 | C96: OCTUBRE | D96: P. SOCIAL | F96: 2 | G96: =+G95+E96-F96 -> 40.5
A97: 43118 | B97: 14440 | C97: OCTUBRE | D97: LUZ | F97: 13.5 | G97: =+G96+E97-F97 -> 27
A98: 43118 | B98: 14440 | C98: OCTUBRE | D98: AGUA | F98: 2 | G98: =+G97+E98-F98 -> 25
A99: 44847 | B99: 25617 | C99: OCTUBRE | D99: CUOTA | F99: 25 | G99: =+G98+E99-F99 -> 0
A100: 43069 | B100: POR COBRAR | C100: NOVIEMBRE | D100: LUZ | E100: 14.4 | G100: =+G99+E100-F100 -> 14.4
D101: AGUA | E101: 2 | G101: =+G100+E101-F101 -> 16.4
D102: G. ADM | E102: 60 | G102: =+G101+E102-F102 -> 76.4
...

Sheet SOTO MARIA 
B2: SOTO VARGAS DE FLORES MARIA DEL CARMEN
A4: FECHA | B4: DOCUMENTO | C4: PERIODO | D4: CONCEPTO | E4: POR COBRAR | F4: PAGADO | G4: SALDO POR COBRAR
A5: 42736 | B5: SALDO AL 2016 | G5: 23.1
A6: 42787 | B6: 12354 | C6: A CUENTA 2016 | F6: 23.1 | G6: =+G5+E6-F6 -> 0
A7: 42766 | B7: POR COBRAR | C7: ENERO | D7: LUZ | E7: 19.9 | G7: =+G6+E7-F7 -> 19.9
D8: AGUA | E8: 2.8 | G8: =+G7+E8-F8 -> 22.7
D9: G. ADM | E9: 60 | G9: =+G8+E9-F9 -> 82.7
D10: P. SOCIAL | E10: 2 | G10: =+G9+E10-F10 -> 84.7
A11: 42766 | B11: TARJETA | C11: ENERO | D11: G. ADM | F11: 60 | G11: =+G10+E11-F11 -> 24.7
A12: 42766 | B12: TARJETA | C12: ENERO | D12: P. SOCIAL | F12: 2 | G12: =+G11+E12-F12 -> 22.7
A13: 42787 | B13: 12353 | C13: ENERO | D13: LUZ | F13: 19.9 | G13: =+G12+E13-F13 -> 2.8
A14: 42787 | B14: 12353 | C14: ENERO | D14: AGUA | F14: 2.8 | G14: =+G13+E14-F14 -> 4.4408921e-15
A15: 42794 | B15: POR COBRAR | C15: FEBRERO | D15: LUZ | E15: 21.8 | G15: =+G14+E15-F15 -> 21.8
D16: AGUA | E16: 2 | G16: =+G15+E16-F16 -> 23.8
D17: G. ADM | E17: 56 | G17: =+G16+E17-F17 -> 79.8
D18: P. SOCIAL | E18: 2 | G18: =+G17+E18-F18 -> 81.8
A19: 42794 | B19: TARJETA | C19: FEBRERO | D19: G. ADM | F19: 56 | G19: =+G18+E19-F19 -> 25.8
A20: 42794 | B20: TARJETA | C20: FEBRERO | D20: P. SOCIAL | F20: 2 | G20: =+G19+E20-F20 -> 23.8
A21: 42819 | B21: 12477 | C21: FEBRERO | D21: LUZ | F21: 21.8 | G21: =+G20+E21-F21 -> 2
A22: 42819 | B22: 12477 | C22: FEBRERO | D22: AGUA | F22: 2 | G22: =+G21+E22-F22 -> 1.0658141e-14
A23: 42825 | B23: POR COBRAR | C23: MARZO | D23: LUZ | E23: 20.5 | G23: =+G22+E23-F23 -> 20.5
D24: AGUA | E24: 2 | G24: =+G23+E24-F24 -> 22.5
D25: G. ADM | E25: 60 | G25: =+G24+E25-F25 -> 82.5
D26: P. SOCIAL | E26: 2 | G26: =+G25+E26-F26 -> 84.5
A27: 42823 | B27: TARJETA | C27: MARZO | D27: G. ADM | F27: 60 | G27: =+G26+E27-F27 -> 24.5
A28: 42823 | B28: TARJETA | C28: MARZO | D28: P. SOCIAL | F28: 2 | G28: =+G27+E28-F28 -> 22.5
A29: 42884 | B29: 12858 | C29: MARZO | D29: LUZ | F29: 20.5 | G29: =+G28+E29-F29 -> 2
A30: 42884 | B30: 12858 | C30: MARZO | D30: AGUA | F30: 2 | G30: =+G29+E30-F30 -> 1.4210855e-14
A31: 42855 | B31: POR COBRAR | C31: ABRIL | D31: LUZ | E31: 21.6 | G31: =+G30+E31-F31 -> 21.6
D32: AGUA | E32: 2 | G32: =+G31+E32-F32 -> 23.6
D33: G. ADM | E33: 60 | G33: =+G32+E33-F33 -> 83.6
D34: P. SOCIAL | E34: 2 | G34: =+G33+E34-F34 -> 85.6
A35: 42855 | B35: TARJETA | C35: ABRIL | D35: G. ADM | F35: 60 | G35: =+G34+E35-F35 -> 25.6
A36: 42855 | B36: TARJETA | C36: ABRIL | D36: P. SOCIAL | F36: 2 | G36: =+G35+E36-F36 -> 23.6
A37: 42884 | B37: 12858 | C37: ABRIL | D37: LUZ | F37: 21.6 | G37: =+G36+E37-F37 -> 2
A38: 42884 | B38: 12858 | C38: ABRIL | D38: AGUA | F38: 2 | G38: =+G37+E38-F38 -> 2.1316282e-14
A39: 42886 | B39: POR COBRAR | C39: MAYO | D39: LUZ | E39: 20.9 | G39: =+G38+E39-F39 -> 20.9
D40: AGUA | E40: 2 | G40: =+G39+E40-F40 -> 22.9
D41: G. ADM | E41: 60 | G41: =+G40+E41-F41 -> 82.9
D42: P. SOCIAL | E42: 2 | G42: =+G41+E42-F42 -> 84.9
A43: 42886 | B43: TARJETA | C43: MAYO | D43: G. ADM | F43: 60 | G43: =+G42+E43-F43 -> 24.9
A44: 42886 | B44: TARJETA | C44: MAYO | D44: P. SOCIAL | F44: 2 | G44: =+G43+E44-F44 -> 22.9
A45: 42919 | B45: 13176 | C45: MAYO | D45: LUZ | F45: 20.9 | G45: =+G44+E45-F45 -> 2
A46: 42919 | B46: 13176 | C46: MAYO | D46: AGUA | F46: 2 | G46: =+G45+E46-F46 -> 2.1316282e-14
A47: 42916 | B47: POR COBRAR | C47: JUNIO | D47: LUZ | E47: 20.3 | G47: =+G46+E47-F47 -> 20.3
D48: AGUA | E48: 2 | G48: =+G47+E48-F48 -> 22.3
D49: G. ADM | E49: 60 | G49: =+G48+E49-F49 -> 82.3
D50: P. SOCIAL | E50: 2 | G50: =+G49+E50-F50 -> 84.3
A51: 42916 | B51: TARJETA | C51: JUNIO | D51: G. ADM | F51: 60 | G51: =+G50+E51-F51 -> 24.3
A52: 42916 | B52: TARJETA | C52: JUNIO | D52: P. SOCIAL | F52: 2 | G52: =+G51+E52-F52 -> 22.3
A53: 42936 | B53: 13227 | C53: JUNIO | D53: LUZ | F53: 20.3 | G53: =+G52+E53-F53 -> 2
A54: 42936 | B54: 13227 | C54: JUNIO | D54: AGUA | F54: 2 | G54: =+G53+E54-F54 -> 2.4868996e-14
A55: 42947 | B55: POR COBRAR | C55: JULIO | D55: LUZ | E55: 19.8 | G55: =+G54+E55-F55 -> 19.8
D56: AGUA | E56: 2 | G56: =+G55+E56-F56 -> 21.8
D57: G. ADM | E57: 60 | G57: =+G56+E57-F57 -> 81.8
D58: P. SOCIAL | E58: 2 | G58: =+G57+E58-F58 -> 83.8
A59: 42947 | B59: TARJETA | C59: JULIO | D59: G. ADM | F59: 60 | G59: =+G58+E59-F59 -> 23.8
A60: 42947 | B60: TARJETA | C60: JULIO | D60: P. SOCIAL | F60: 2 | G60: =+G59+E60-F60 -> 21.8
A61: 42998 | B61: 13631 | C61: JULIO | D61: LUZ | F61: 19.8 | G61: =+G60+E61-F61 -> 2
A62: 42998 | B62: 13631 | C62: JULIO | D62: AGUA | F62: 2 | G62: =+G61+E62-F62 -> 2.4868996e-14
A63: 42978 | B63: POR COBRAR | C63: AGOSTO | D63: LUZ | E63: 19.8 | G63: =+G62+E63-F63 -> 19.8
D64: AGUA | E64: 2 | G64: =+G63+E64-F64 -> 21.8
D65: G. ADM | E65: 60 | G65: =+G64+E65-F65 -> 81.8
D66: P. SOCIAL | E66: 2 | G66: =+G65+E66-F66 -> 83.8
A67: 42978 | B67: TARJETA | C67: AGOSTO | D67: G. ADM | F67: 50 | G67: =+G66+E67-F67 -> 33.8
A68: 42998 | B68: 13631 | C68: AGOSTO | D68: G. ADM | F68: 10 | G68: =+G67+E68-F68 -> 23.8
A69: 42998 | B69: 13631 | C69: AGOSTO | D69: P. SOCIAL | F69: 2 | G69: =+G68+E69-F69 -> 21.8
A70: 42998 | B70: 13631 | C70: AGOSTO | D70: LUZ | F70: 19.8 | G70: =+G69+E70-F70 -> 2
A71: 42998 | B71: 13631 | C71: AGOSTO | D71: AGUA | F71: 2 | G71: =+G70+E71-F71 -> 2.4868996e-14
A72: 43008 | B72: POR COBRAR | C72: SEPTIEMBRE | D72: LUZ | E72: 25.1 | G72: =+G71+E72-F72 -> 25.1
D73: AGUA | E73: 2 | G73: =+G72+E73-F73 -> 27.1
D74: G. ADM | E74: 60 | G74: =+G73+E74-F74 -> 87.1
D75: P. SOCIAL | E75: 2 | G75: =+G74+E75-F75 -> 89.1
A76: 43008 | B76: TARJETA | C76: SEPTIEMBRE | D76: G. ADM | F76: 60 | G76: =+G75+E76-F76 -> 29.1
A77: 43008 | B77: TARJETA | C77: SEPTIEMBRE | D77: P. SOCIAL | F77: 2 | G77: =+G76+E77-F77 -> 27.1
A78: 43057 | B78: 13993 | C78: SEPTIEMBRE | D78: LUZ | F78: 25.1 | G78: =+G77+E78-F78 -> 2
A79: 43057 | B79: 13993 | C79: SEPTIEMBRE | D79: AGUA | F79: 2 | G79: =+G78+E79-F79 -> 2.1316282e-14
A80: 43039 | B80: POR COBRAR | C80: OCTUBRE | D80: LUZ | E80: 25 | G80: =+G79+E80-F80 -> 25
D81: AGUA | E81: 2.7 | G81: =+G80+E81-F81 -> 27.7
D82: G. ADM | E82: 60 | G82: =+G81+E82-F82 -> 87.7
D83: P. SOCIAL | E83: 2 | G83: =+G82+E83-F83 -> 89.7
A84: 43039 | B84: TARJETA | C84: OCTUBRE | D84: G. ADM | F84: 60 | G84: =+G83+E84-F84 -> 29.7
A85: 43039 | B85: TARJETA | C85: OCTUBRE | D85: P. SOCIAL | F85: 2 | G85: =+G84+E85-F85 -> 27.7
A86: 43062 | B86: 14010 | C86: OCTUBRE | D86: LUZ | F86: 25 | G86: =+G85+E86-F86 -> 2.7
A87: 43062 | B87: 14010 | C87: OCTUBRE | D87: AGUA | F87: 2.7 | G87: =+G86+E87-F87 -> 1.687539e-14
A88: 43069 | B88: POR COBRAR | C88: NOVIEMBRE | D88: LUZ | E88: 16.4 | G88: =+G87+E88-F88 -> 16.4
D89: AGUA | E89: 2 | G89: =+G88+E89-F89 -> 18.4
D90: G. ADM | E90: 60 | G90: =+G89+E90-F90 -> 78.4
D91: P. SOCIAL | E91: 2 | G91: =+G90+E91-F91 -> 80.4
A92: 43087 | B92: 14243 | C92: NOVIEMBRE | D92: LUZ | F92: 16.4 | G92: =+G91+E92-F92 -> 64
A93: 43087 | B93: 14243 | C93: NOVIEMBRE | D93: AGUA | F93: 2 | G93: =+G92+E93-F93 -> 62
A94: 43069 | B94: TARJETA | C94: NOVIEMBRE | D94: G. ADM | F94: 60 | G94: =+G93+E94-F94 -> 2
A95: 43069 | B95: TARJETA | C95: NOVIEMBRE | D95: P. SOCIAL | F95: 2 | G95: =+G94+E95-F95 -> 2.8421709e-14
A96: 43100 | B96: POR COBRAR | C96: DICIEMBRE | D96: LUZ | E96: 17.9 | G96: =+G95+E96-F96 -> 17.9
D97: AGUA | E97: 2 | G97: =+G96+E97-F97 -> 19.9
D98: G. ADM | E98: 60 | G98: =+G97+E98-F98 -> 79.9
D99: P. SOCIAL | E99: 2 | G99: =+G98+E99-F99 -> 81.9
A100: 43099 | B100: TARJETA | C100: DICIEMBRE | D100: G. ADM | F100: 60 | G100: =+G99+E100-F100 -> 21.9
A101: 43099 | B101: TARJETA | C101: DICIEMBRE | D101: P. SOCIAL | F101: 2 | G101: =+G100+E101-F101 -> 19.9
A102: 43118 | B102: 14441 | C102: DICIEMBRE | D102: LUZ | F102: 17.9 | G102: =+G101+E102-F102 -> 2
...

Sheet ORDOÑEZ AZUL
B2: ORDOÑEZ NICHO AZUL CARILE
A4: FECHA | B4: DOCUMENTO | C4: PERIODO | D4: CONCEPTO | E4: POR COBRAR | F4: PAGADO | G4: SALDO POR COBRAR
A5: 42736 | B5: SALDO AL 2016 | G5: 384.6
A6: 42784 | B6: 12991 | C6: A CUENTA 2016 | F6: 299.6 | G6: =+G5+E6-F6 -> 85
A7: 185-02 | B7: 12994 | C7: A CUENTA 2016 | F7: 85 | G7: =+G6+E7-F7 -> 0
A8: 42766 | B8: POR COBRAR | C8: ENERO | D8: LUZ | E8: 66.7 | G8: =+G7+E8-F8 -> 66.7
D9: AGUA | E9: 2.8 | G9: =+G8+E9-F9 -> 69.5
D10: G. ADM | E10: 60 | G10: =+G9+E10-F10 -> 129.5
D11: P. SOCIAL | E11: 2 | G11: =+G10+E11-F11 -> 131.5
A12: 42784 | B12: 12991 | C12: ENERO | D12: LUZ | F12: 66.7 | G12: =+G11+E12-F12 -> 64.8
A13: 42784 | B13: 12991 | C13: ENERO | D13: AGUA | F13: 2.8 | G13: =+G12+E13-F13 -> 62
A14: 42784 | B14: 12991 | C14: ENERO | D14: G. ADM | F14: 60 | G14: =+G13+E14-F14 -> 2
A15: 42784 | B15: 12991 | C15: ENERO | D15: P. SOCIAL | F15: 2 | G15: =+G14+E15-F15 -> 0
A16: 42794 | B16: POR COBRAR | C16: FEBRERO | D16: LUZ | E16: 68.3 | G16: =+G15+E16-F16 -> 68.3
D17: AGUA | E17: 2 | G17: =+G16+E17-F17 -> 70.3
D18: G. ADM | E18: 56 | G18: =+G17+E18-F18 -> 126.3
D19: P. SOCIAL | E19: 2 | G19: =+G18+E19-F19 -> 128.3
A20: 42882 | B20: 12833 | C20: FEBRERO | D20: LUZ | F20: 68.3 | G20: =+G19+E20-F20 -> 60
A21: 42882 | B21: 12833 | C21: FEBRERO | D21: AGUA | F21: 2 | G21: =+G20+E21-F21 -> 58
A22: 42882 | B22: 12834 | C22: FEBRERO | D22: G. ADM | F22: 56 | G22: =+G21+E22-F22 -> 2
A23: 42882 | B23: 12834 | C23: FEBRERO | D23: P. SOCIAL | F23: 2 | G23: =+G22+E23-F23 -> 1.4210855e-14
A24: 42825 | B24: POR COBRAR | C24: MARZO | D24: LUZ | E24: 65.3 | G24: =+G23+E24-F24 -> 65.3
D25: AGUA | E25: 2 | G25: =+G24+E25-F25 -> 67.3
D26: G. ADM | E26: 60 | G26: =+G25+E26-F26 -> 127.3
D27: P. SOCIAL | E27: 2 | G27: =+G26+E27-F27 -> 129.3
A28: 42882 | B28: 12833 | C28: MARZO | D28: LUZ | F28: 65.3 | G28: =+G27+E28-F28 -> 64
A29: 42882 | B29: 12833 | C29: MARZO | D29: AGUA | F29: 2 | G29: =+G28+E29-F29 -> 62
A30: 42882 | B30: 12834 | C30: MARZO | D30: G. ADM | F30: 60 | G30: =+G29+E30-F30 -> 2
A31: 42882 | B31: 12834 | C31: MARZO | D31: P. SOCIAL | F31: 2 | G31: =+G30+E31-F31 -> 1.4210855e-14
A32: 42855 | B32: POR COBRAR | C32: ABRIL | D32: LUZ | E32: 66.8 | G32: =+G31+E32-F32 -> 66.8
D33: AGUA | E33: 2 | G33: =+G32+E33-F33 -> 68.8
D34: G. ADM | E34: 60 | G34: =+G33+E34-F34 -> 128.8
D35: P. SOCIAL | E35: 2 | G35: =+G34+E35-F35 -> 130.8
A36: 42882 | B36: 12833 | C36: ABRIL | D36: LUZ | F36: 66.8 | G36: =+G35+E36-F36 -> 64
A37: 42882 | B37: 12833 | C37: ABRIL | D37: AGUA | F37: 2 | G37: =+G36+E37-F37 -> 62
A38: 42882 | B38: 12834 | C38: ABRIL | D38: G. ADM | F38: 60 | G38: =+G37+E38-F38 -> 2
A39: 42882 | B39: 12834 | C39: ABRIL | D39: P. SOCIAL | F39: 2 | G39: =+G38+E39-F39 -> 1.4210855e-14
A40: 42886 | B40: POR COBRAR | C40: MAYO | D40: LUZ | E40: 62 | G40: =+G39+E40-F40 -> 62
D41: AGUA | E41: 2 | G41: =+G40+E41-F41 -> 64
D42: G. ADM | E42: 60 | G42: =+G41+E42-F42 -> 124
D43: P. SOCIAL | E43: 2 | G43: =+G42+E43-F43 -> 126
A44: 42933 | B44: 13210 | C44: MAYO | D44: G. ADM | F44: 60 | G44: =+G43+E44-F44 -> 66
A45: 42933 | B45: 13210 | C45: MAYO | D45: P. SOCIAL | F45: 2 | G45: =+G44+E45-F45 -> 64
A46: 42933 | B46: 13210 | C46: MAYO | D46: LUZ | F46: 62 | G46: =+G45+E46-F46 -> 2
A47: 42933 | B47: 13210 | C47: MAYO | D47: AGUA | F47: 2 | G47: =+G46+E47-F47 -> 1.4210855e-14
A48: 42916 | B48: POR COBRAR | C48: JUNIO | D48: LUZ | E48: 61.1 | G48: =+G47+E48-F48 -> 61.1
D49: AGUA | E49: 2 | G49: =+G48+E49-F49 -> 63.1
D50: G. ADM | E50: 60 | G50: =+G49+E50-F50 -> 123.1
D51: P. SOCIAL | E51: 2 | G51: =+G50+E51-F51 -> 125.1
A52: 42933 | B52: 13210 | C52: JUNIO | D52: G. ADM | F52: 60 | G52: =+G51+E52-F52 -> 65.1
A53: 42933 | B53: 13210 | C53: JUNIO | D53: P. SOCIAL | F53: 2 | G53: =+G52+E53-F53 -> 63.1
A54: 42933 | B54: 13210 | C54: JUNIO | D54: LUZ | F54: 61.1 | G54: =+G53+E54-F54 -> 2
A55: 42933 | B55: 13210 | C55: JUNIO | D55: AGUA | F55: 2 | G55: =+G54+E55-F55 -> 2.1316282e-14
A56: 42947 | B56: POR COBRAR | C56: JULIO | D56: LUZ | E56: 55.5 | G56: =+G55+E56-F56 -> 55.5
D57: AGUA | E57: 2 | G57: =+G56+E57-F57 -> 57.5
D58: G. ADM | E58: 60 | G58: =+G57+E58-F58 -> 117.5
D59: P. SOCIAL | E59: 2 | G59: =+G58+E59-F59 -> 119.5
A60: 42990 | B60: 13566 | C60: JULIO | D60: G. ADM | F60: 60 | G60: =+G59+E60-F60 -> 59.5
A61: 42990 | B61: 13566 | C61: JULIO | D61: P. SOCIAL | F61: 2 | G61: =+G60+E61-F61 -> 57.5
A62: 42990 | B62: 13566 | C62: JULIO | D62: LUZ | F62: 55.5 | G62: =+G61+E62-F62 -> 2
A63: 42990 | B63: 13566 | C63: JULIO | D63: AGUA | F63: 2 | G63: =+G62+E63-F63 -> 2.8421709e-14
A64: 42978 | B64: POR COBRAR | C64: AGOSTO | D64: LUZ | E64: 55.5 | G64: =+G63+E64-F64 -> 55.5
D65: AGUA | E65: 2 | G65: =+G64+E65-F65 -> 57.5
D66: G. ADM | E66: 60 | G66: =+G65+E66-F66 -> 117.5
D67: P. SOCIAL | E67: 2 | G67: =+G66+E67-F67 -> 119.5
D68: MULTA | E68: 85 | G68: =+G67+E68-F68 -> 204.5
A69: 42990 | B69: 13566 | C69: AGOSTO | D69: G. ADM | F69: 60 | G69: =+G68+E69-F69 -> 144.5
A70: 42990 | B70: 13566 | C70: AGOSTO | D70: P. SOCIAL | F70: 2 | G70: =+G69+E70-F70 -> 142.5
A71: 43025 | B71: 13829 | C71: AGOSTO | D71: LUZ | F71: 55.5 | G71: =+G70+E71-F71 -> 87
A72: 43025 | B72: 13829 | C72: AGOSTO | D72: AGUA | F72: 2 | G72: =+G71+E72-F72 -> 85
A73: 43053 | B73: 13978 | C73: AGOSTO | D73: MULTA | F73: 85 | G73: =+G72+E73-F73 -> 0
A74: 43008 | B74: POR COBRAR | C74: SEPTIEMBRE | D74: LUZ | E74: 58 | G74: =+G73+E74-F74 -> 58
D75: AGUA | E75: 2 | G75: =+G74+E75-F75 -> 60
D76: G. ADM | E76: 60 | G76: =+G75+E76-F76 -> 120
D77: P. SOCIAL | E77: 2 | G77: =+G76+E77-F77 -> 122
A78: 42823 | D78: MULTA | E78: 85 | G78: =+G77+E78-F78 -> 207
A79: 43025 | B79: 13829 | C79: SEPTIEMBRE | D79: G. ADM | F79: 60 | G79: =+G78+E79-F79 -> 147
A80: 43025 | B80: 13829 | C80: SEPTIEMBRE | D80: P. SOCIAL | F80: 2 | G80: =+G79+E80-F80 -> 145
A81: 43053 | B81: 13978 | C81: 42823 | D81: MULTA | F81: 85 | G81: =+G80+E81-F81 -> 60
A82: 43053 | B82: 13978 | C82: SEPTIEMBRE | D82: LUZ | F82: 58 | G82: =+G81+E82-F82 -> 2
A83: 43053 | B83: 13978 | C83: SEPTIEMBRE | D83: AGUA | F83: 2 | G83: =+G82+E83-F83 -> 0
A84: 43039 | B84: POR COBRAR | C84: OCTUBRE | D84: LUZ | E84: 86.6 | G84: =+G83+E84-F84 -> 86.6
D85: AGUA | E85: 2 | G85: =+G84+E85-F85 -> 88.6
D86: G. ADM | E86: 60 | G86: =+G85+E86-F86 -> 148.6
D87: P. SOCIAL | E87: 2 | G87: =+G86+E87-F87 -> 150.6
A88: 43053 | B88: 13978 | C88: OCTUBRE | D88: G. ADM | F88: 60 | G88: =+G87+E88-F88 -> 90.6
A89: 43053 | B89: 13978 | C89: OCTUBRE | D89: P. SOCIAL | F89: 2 | G89: =+G88+E89-F89 -> 88.6
A90: 43066 | B90: 14098 | C90: OCTUBRE | D90: LUZ | F90: 86.6 | G90: =+G89+E90-F90 -> 2
A91: 43066 | B91: 14098 | C91: OCTUBRE | D91: AGUA | F91: 2 | G91: =+G90+E91-F91 -> 0
A92: 43069 | B92: POR COBRAR | C92: NOVIEMBRE | D92: LUZ | E92: 92.5 | G92: =+G91+E92-F92 -> 92.5
D93: AGUA | E93: 2 | G93: =+G92+E93-F93 -> 94.5
D94: G. ADM | E94: 60 | G94: =+G93+E94-F94 -> 154.5
D95: P. SOCIAL | E95: 2 | G95: =+G94+E95-F95 -> 156.5
A96: 43108 | B96: 14409 | C96: NOVIEMBRE | D96: G. ADM | F96: 60 | G96: =+G95+E96-F96 -> 96.5
A97: 43108 | B97: 14409 | C97: NOVIEMBRE | D97: P. SOCIAL | F97: 2 | G97: =+G96+E97-F97 -> 94.5
A98: 43108 | B98: 14409 | C98: NOVIEMBRE | D98: LUZ | F98: 92.5 | G98: =+G97+E98-F98 -> 2
A99: 43108 | B99: 14409 | C99: NOVIEMBRE | D99: AGUA | F99: 2 | G99: =+G98+E99-F99 -> 0
A100: 43100 | B100: POR COBRAR | C100: DICIEMBRE | D100: LUZ | E100: 100.5 | G100: =+G99+E100-F100 -> 100.5
D101: AGUA | E101: 2 | G101: =+G100+E101-F101 -> 102.5
D102: G. ADM | E102: 60 | G102: =+G101+E102-F102 -> 162.5
...

Sheet TAIPE EUGENIO
B2: TAIPE OQUENDO EUGENIO JOEL
A4: FECHA | B4: DOCUMENTO | C4: PERIODO | D4: CONCEPTO | E4: POR COBRAR | F4: PAGADO | G4: SALDO POR COBRAR
A5: 42736 | B5: SALDO AL 2016 | G5: 110.4
A6: 42783 | B6: 12969 | C6: A CUENTA 2016 | F6: 110.4 | G6: =+G5+E6-F6 -> 0
A7: 42766 | B7: POR COBRAR | C7: ENERO | D7: LUZ | E7: 52.6 | G7: =+G6+E7-F7 -> 52.6
D8: AGUA | E8: 2.8 | G8: =+G7+E8-F8 -> 55.4
D9: G. ADM | E9: 60 | G9: =+G8+E9-F9 -> 115.4
D10: P. SOCIAL | E10: 2 | G10: =+G9+E10-F10 -> 117.4
A11: 42765 | B11: TARJETA | D11: G. ADM | F11: 60 | G11: =+G10+E11-F11 -> 57.4
A12: 42765 | B12: TARJETA | D12: P. SOCIAL | F12: 2 | G12: =+G11+E12-F12 -> 55.4
A13: 42786 | B13: 12226 | C13: ENERO | D13: AGUA | F13: 2.8 | G13: =+G12+E13-F13 -> 52.6
A14: 42786 | B14: 12226 | C14: ENERO | D14: LUZ | F14: 52.6 | G14: =+G13+E14-F14 -> 0
A15: 42794 | B15: POR COBRAR | C15: FEBRERO | D15: LUZ | E15: 52.5 | G15: =+G14+E15-F15 -> 52.5
D16: AGUA | E16: 2 | G16: =+G15+E16-F16 -> 54.5
D17: G. ADM | E17: 56 | G17: =+G16+E17-F17 -> 110.5
D18: P. SOCIAL | E18: 2 | G18: =+G17+E18-F18 -> 112.5
A19: 42794 | B19: TARJETA | D19: G. ADM | F19: 56 | G19: =+G18+E19-F19 -> 56.5
A20: 42794 | B20: TARJETA | D20: P. SOCIAL | F20: 2 | G20: =+G19+E20-F20 -> 54.5
A21: 42819 | B21: 12475 | C21: FEBRERO | D21: LUZ | F21: 52.5 | G21: =+G20+E21-F21 -> 2
A22: 42819 | B22: 12475 | C22: FEBRERO | D22: AGUA | F22: 2 | G22: =+G21+E22-F22 -> 0
A23: 42825 | B23: POR COBRAR | C23: MARZO | D23: LUZ | E23: 49.6 | G23: =+G22+E23-F23 -> 49.6
D24: AGUA | E24: 2 | G24: =+G23+E24-F24 -> 51.6
D25: G. ADM | E25: 60 | G25: =+G24+E25-F25 -> 111.6
D26: P. SOCIAL | E26: 2 | G26: =+G25+E26-F26 -> 113.6
A27: 42824 | B27: TARJETA | D27: G. ADM | F27: 60 | G27: =+G26+E27-F27 -> 53.6
A28: 42824 | B28: TARJETA | D28: P. SOCIAL | F28: 2 | G28: =+G27+E28-F28 -> 51.6
A29: 42884 | B29: 12853 | C29: MARZO | D29: AGUA | F29: 2 | G29: =+G28+E29-F29 -> 49.6
A30: 42884 | B30: 12853 | C30: MARZO | D30: LUZ | F30: 49.6 | G30: =+G29+E30-F30 -> 0
A31: 42855 | B31: POR COBRAR | C31: ABRIL | D31: LUZ | E31: 51.8 | G31: =+G30+E31-F31 -> 51.8
D32: AGUA | E32: 2 | G32: =+G31+E32-F32 -> 53.8
D33: G. ADM | E33: 60 | G33: =+G32+E33-F33 -> 113.8
D34: P. SOCIAL | E34: 2 | G34: =+G33+E34-F34 -> 115.8
A35: 42855 | B35: TARJETA | D35: G. ADM | F35: 60 | G35: =+G34+E35-F35 -> 55.8
A36: 42855 | B36: TARJETA | D36: P. SOCIAL | F36: 2 | G36: =+G35+E36-F36 -> 53.8
A37: 42884 | B37: 12853 | C37: ABRIL | D37: LUZ | F37: 51.8 | G37: =+G36+E37-F37 -> 2
A38: 42884 | B38: 12853 | C38: ABRIL | D38: AGUA | F38: 2 | G38: =+G37+E38-F38 -> 0
A39: 42886 | B39: POR COBRAR | C39: MAYO | D39: LUZ | E39: 49.8 | G39: =+G38+E39-F39 -> 49.8
D40: AGUA | E40: 2 | G40: =+G39+E40-F40 -> 51.8
D41: G. ADM | E41: 60 | G41: =+G40+E41-F41 -> 111.8
D42: P. SOCIAL | E42: 2 | G42: =+G41+E42-F42 -> 113.8
A43: 42885 | B43: TARJETA | C43: MAYO | D43: G. ADM | F43: 60 | G43: =+G42+E43-F43 -> 53.8
A44: 42885 | B44: TARJETA | C44: MAYO | D44: P. SOCIAL | F44: 2 | G44: =+G43+E44-F44 -> 51.8
A45: 42949 | B45: 13341 | C45: MAYO | D45: LUZ | F45: 49.8 | G45: =+G44+E45-F45 -> 2
A46: 42949 | B46: 13341 | C46: MAYO | D46: AGUA | F46: 2 | G46: =+G45+E46-F46 -> 0
A47: 42916 | B47: POR COBRAR | C47: JUNIO | D47: LUZ | E47: 48.3 | G47: =+G46+E47-F47 -> 48.3
D48: AGUA | E48: 2 | G48: =+G47+E48-F48 -> 50.3
D49: G. ADM | E49: 60 | G49: =+G48+E49-F49 -> 110.3
D50: P. SOCIAL | E50: 2 | G50: =+G49+E50-F50 -> 112.3
A51: 42916 | B51: TARJETA | C51: JUNIO | D51: G. ADM | F51: 60 | G51: =+G50+E51-F51 -> 52.3
A52: 42916 | B52: TARJETA | C52: JUNIO | D52: P. SOCIAL | F52: 2 | G52: =+G51+E52-F52 -> 50.3
A53: 42949 | B53: 13341 | C53: JUNIO | D53: LUZ | F53: 48.3 | G53: =+G52+E53-F53 -> 2
A54: 42949 | B54: 13341 | C54: JUNIO | D54: AGUA | F54: 2 | G54: =+G53+E54-F54 -> 0
A55: 42947 | B55: POR COBRAR | C55: JULIO | D55: LUZ | E55: 46.4 | G55: =+G54+E55-F55 -> 46.4
D56: AGUA | E56: 2 | G56: =+G55+E56-F56 -> 48.4
D57: G. ADM | E57: 60 | G57: =+G56+E57-F57 -> 108.4
D58: P. SOCIAL | E58: 2 | G58: =+G57+E58-F58 -> 110.4
A59: 42947 | B59: TARJETA | C59: JULIO | D59: G. ADM | F59: 60 | G59: =+G58+E59-F59 -> 50.4
A60: 42947 | B60: TARJETA | C60: JULIO | D60: P. SOCIAL | F60: 2 | G60: =+G59+E60-F60 -> 48.4
A61: 43012 | B61: 13789 | C61: JULIO | D61: LUZ | F61: 46.4 | G61: =+G60+E61-F61 -> 2
A62: 43012 | B62: 13789 | C62: JULIO | D62: AGUA | F62: 2 | G62: =+G61+E62-F62 -> 7.1054274e-15
A63: 42978 | B63: POR COBRAR | C63: AGOSTO | D63: LUZ | E63: 46.4 | G63: =+G62+E63-F63 -> 46.4
D64: AGUA | E64: 2 | G64: =+G63+E64-F64 -> 48.4
D65: G. ADM | E65: 60 | G65: =+G64+E65-F65 -> 108.4
D66: P. SOCIAL | E66: 2 | G66: =+G65+E66-F66 -> 110.4
D67: MULTA | E67: 85 | G67: =+G66+E67-F67 -> 195.4 | I67: DESCUENTO DEL 50 %EN LAS MULTAS PASADAS EN SESION DEL CONSEJO EL 10 DE DICIEMBRE DEL 2019
A68: 42978 | B68: TARJETA | C68: AGOSTO | D68: G. ADM | F68: 60 | G68: =+G67+E68-F68 -> 135.4
A69: 42978 | B69: TARJETA | C69: AGOSTO | D69: P. SOCIAL | F69: 2 | G69: =+G68+E69-F69 -> 133.4
A70: 43012 | B70: 13789 | C70: AGOSTO | D70: LUZ | F70: 46.4 | G70: =+G69+E70-F70 -> 87
A71: 43012 | B71: 13789 | C71: AGOSTO | D71: AGUA | F71: 2 | G71: =+G70+E71-F71 -> 85
A72: 44527 | B72: DESCUENTO | C72: AGOSTO | D72: MULTA | F72: 42.5 | G72: =+G71+E72-F72 -> 42.5
A73: 44607 | B73: 24224 | C73: AGOSTO | D73: MULTA | F73: 42.5 | G73: =+G72+E73-F73 -> 0
A74: 43008 | B74: POR COBRAR | C74: SEPTIEMBRE | D74: LUZ | E74: 31 | G74: =+G73+E74-F74 -> 31
D75: AGUA | E75: 2 | G75: =+G74+E75-F75 -> 33
D76: G. ADM | E76: 60 | G76: =+G75+E76-F76 -> 93
D77: P. SOCIAL | E77: 2 | G77: =+G76+E77-F77 -> 95
A78: 42788 | D78: MULTA | E78: 85 | G78: =+G77+E78-F78 -> 180
A79: 42823 | D79: MULTA | E79: 85 | G79: =+G78+E79-F79 -> 265
A80: 43008 | B80: TARJETA | C80: SEPTIEMBRE | D80: G. ADM | F80: 60 | G80: =+G79+E80-F80 -> 205
A81: 43008 | B81: TARJETA | C81: SEPTIEMBRE | D81: P. SOCIAL | F81: 2 | G81: =+G80+E81-F81 -> 203
A82: 43056 | B82: 13989 | C82: SEPTIEMBRE | D82: LUZ | F82: 31 | G82: =+G81+E82-F82 -> 172
A83: 43056 | B83: 13989 | C83: SEPTIEMBRE | D83: AGUA | F83: 2 | G83: =+G82+E83-F83 -> 170
A84: 43067 | B84: EXONERACION | C84: 42788 | D84: MULTA | F84: 85 | G84: =+G83+E84-F84 -> 85
A85: 43067 | B85: EXONERACION | C85: 42823 | D85: MULTA | F85: 85 | G85: =+G84+E85-F85 -> 0
A86: 43039 | B86: POR COBRAR | C86: OCTUBRE | D86: LUZ | E86: 30.8 | G86: =+G85+E86-F86 -> 30.8
D87: AGUA | E87: 2 | G87: =+G86+E87-F87 -> 32.8
D88: G. ADM | E88: 60 | G88: =+G87+E88-F88 -> 92.8
D89: P. SOCIAL | E89: 2 | G89: =+G88+E89-F89 -> 94.8
A90: 43039 | B90: TARJETA | C90: OCTUBRE | D90: G. ADM | F90: 60 | G90: =+G89+E90-F90 -> 34.8
A91: 43039 | B91: TARJETA | C91: OCTUBRE | D91: P. SOCIAL | F91: 2 | G91: =+G90+E91-F91 -> 32.8
A92: 43062 | B92: 14007 | C92: OCTUBRE | D92: AGUA | F92: 30.8 | G92: =+G91+E92-F92 -> 2
A93: 43062 | B93: 14007 | C93: OCTUBRE | D93: LUZ | F93: 2 | G93: =+G92+E93-F93 -> -3.5527137e-15
A94: 43069 | B94: POR COBRAR | C94: NOVIEMBRE | D94: LUZ | E94: 32.9 | G94: =+G93+E94-F94 -> 32.9
D95: AGUA | E95: 2 | G95: =+G94+E95-F95 -> 34.9
D96: G. ADM | E96: 60 | G96: =+G95+E96-F96 -> 94.9
D97: P. SOCIAL | E97: 2 | G97: =+G96+E97-F97 -> 96.9
A98: 43089 | B98: 14335 | C98: NOVIEMBRE | D98: LUZ | F98: 32.9 | G98: =+G97+E98-F98 -> 64
A99: 43089 | B99: 14335 | C99: NOVIEMBRE | D99: AGUA | F99: 2 | G99: =+G98+E99-F99 -> 62
A100: 43069 | B100: TARJETA | C100: NOVIEMBRE | D100: G. ADM | F100: 60 | G100: =+G99+E100-F100 -> 2
A101: 43069 | B101: TARJETA | C101: NOVIEMBRE | D101: P. SOCIAL | F101: 2 | G101: =+G100+E101-F101 -> -7.1054274e-15
A102: 43100 | B102: POR COBRAR | C102: DICIEMBRE | D102: LUZ | E102: 35.8 | G102: =+G101+E102-F102 -> 35.8
...

Sheet TELLO MARINO
B2: TELLO ALVAREZ MARINO
A4: FECHA | B4: DOCUMENTO | C4: PERIODO | D4: CONCEPTO | E4: POR COBRAR | F4: PAGADO | G4: SALDO POR COBRAR
A5: 42736 | B5: SALDO AL 2016 | G5: 1892.1
A6: 42888 | B6: 13034 | C6: A CUENTA 2016 | D6: DEUDA | F6: 455.9 | G6: =+G5+E6-F6 -> 1436.2
A7: 42888 | B7: 13036 | C7: A CUENTA 2016 | D7: DEUDA | F7: 300 | G7: =+G6+E7-F7 -> 1136.2
A8: 44858 | B8: R25667 | C8: A CUENTA 2016 | D8: DEUDA | F8: 500 | G8: =+G7+E8-F8 -> 636.2
A9: 44896 | B9: R 25887 | C9: A CUENTA 2016 | D9: DEUDA | F9: 500 | G9: =+G8+E9-F9 -> 136.2
A10: 44925 | B10: R 26042 | C10: A CUENTA 2016 | D10: DEUDA | F10: 136.2 | G10: =+G9+E10-F10 -> 0
A11: 42766 | B11: POR COBRAR | C11: ENERO | D11: LUZ | E11: 110.9 | G11: =+G10+E11-F11 -> 110.9
D12: AGUA | E12: 2.8 | G12: =+G11+E12-F12 -> 113.7
D13: G. ADM | E13: 60 | G13: =+G12+E13-F13 -> 173.7
D14: P. SOCIAL | E14: 2 | G14: =+G13+E14-F14 -> 175.7
A15: 42765 | B15: TARJETA | C15: ENERO | D15: LUZ | F15: 103 | G15: =+G14+E15-F15 -> 72.7
A16: 42765 | B16: TARJETA | C16: ENERO | D16: G. ADM | F16: 60 | G16: =+G15+E16-F16 -> 12.7
A17: 42765 | B17: TARJETA | C17: ENERO | D17: P. SOCIAL | F17: 2 | G17: =+G16+E17-F17 -> 10.7
A18: 42888 | B18: 13033 | C18: ENERO | D18: LUZ | F18: 7.9 | G18: =+G17+E18-F18 -> 2.8
A19: 42888 | B19: 13033 | C19: ENERO | D19: AGUA | F19: 2.8 | G19: =+G18+E19-F19 -> -1.1546319e-14
A20: 42794 | B20: POR COBRAR | C20: FEBRERO | D20: LUZ | E20: 117.7 | G20: =+G19+E20-F20 -> 117.7
D21: AGUA | E21: 2 | G21: =+G20+E21-F21 -> 119.7
D22: G. ADM | E22: 56 | G22: =+G21+E22-F22 -> 175.7
D23: P. SOCIAL | E23: 2 | G23: =+G22+E23-F23 -> 177.7
D24: MULTA | E24: 85 | G24: =+G23+E24-F24 -> 262.7
A25: 42788 | B25: TARJETA | C25: FEBRERO | D25: LUZ | F25: 49 | G25: =+G24+E25-F25 -> 213.7
A26: 42788 | B26: TARJETA | C26: FEBRERO | D26: G. ADM | F26: 28 | G26: =+G25+E26-F26 -> 185.7
A27: 42888 | B27: 13033 | C27: FEBRERO | D27: LUZ | F27: 68.7 | G27: =+G26+E27-F27 -> 117
A28: 42888 | B28: 13033 | C28: FEBRERO | D28: AGUA | F28: 2 | G28: =+G27+E28-F28 -> 115
A29: 42947 | B29: TARJETA | C29: FEBRERO | D29: P. SOCIAL | F29: 2 | G29: =+G28+E29-F29 -> 113
A30: 43067 | B30: EXONERACION | C30: FEBRERO | D30: MULTA | F30: 85 | G30: =+G29+E30-F30 -> 28
A31: 44925 | B31: R 26042 | C31: FEBRERO | D31: G. ADM | F31: 28 | G31: =+G30+E31-F31 -> 0
A32: 42825 | B32: POR COBRAR | C32: MARZO | D32: LUZ | E32: 112.4 | G32: =+G31+E32-F32 -> 112.4
D33: AGUA | E33: 2 | G33: =+G32+E33-F33 -> 114.4
D34: G. ADM | E34: 60 | G34: =+G33+E34-F34 -> 174.4
D35: P. SOCIAL | E35: 2 | G35: =+G34+E35-F35 -> 176.4
A36: 42825 | B36: TARJETA | C36: MARZO | D36: LUZ | F36: 73.5 | G36: =+G35+E36-F36 -> 102.9
A37: 42825 | B37: TARJETA | C37: MARZO | D37: G. ADM | F37: 42 | G37: =+G36+E37-F37 -> 60.9
A38: 42888 | B38: 13033 | C38: MARZO | D38: LUZ | F38: 38.9 | G38: =+G37+E38-F38 -> 22
A39: 42888 | B39: 13033 | C39: MARZO | D39: AGUA | F39: 2 | G39: =+G38+E39-F39 -> 20
A40: 42947 | B40: TARJETA | C40: MARZO | D40: P. SOCIAL | F40: 2 | G40: =+G39+E40-F40 -> 18
A41: 44925 | B41: R 26042 | C41: MARZO | D41: G. ADM | F41: 18 | G41: =+G40+E41-F41 -> 0
A42: 42855 | B42: POR COBRAR | C42: ABRIL | D42: LUZ | E42: 115.5 | G42: =+G41+E42-F42 -> 115.5
D43: AGUA | E43: 2 | G43: =+G42+E43-F43 -> 117.5
D44: G. ADM | E44: 60 | G44: =+G43+E44-F44 -> 177.5
D45: P. SOCIAL | E45: 2 | G45: =+G44+E45-F45 -> 179.5
A46: 42854 | B46: TARJETA | C46: ABRIL | D46: LUZ | F46: 105 | G46: =+G45+E46-F46 -> 74.5
A47: 42854 | B47: TARJETA | C47: ABRIL | D47: G. ADM | F47: 60 | G47: =+G46+E47-F47 -> 14.5
A48: 42854 | B48: TARJETA | C48: ABRIL | D48: P. SOCIAL | F48: 2 | G48: =+G47+E48-F48 -> 12.5
A49: 42888 | B49: 13033 | C49: ABRIL | D49: LUZ | F49: 10.5 | G49: =+G48+E49-F49 -> 2
A50: 42888 | B50: 13033 | C50: ABRIL | D50: AGUA | F50: 2 | G50: =+G49+E50-F50 -> 0
A51: 42886 | B51: POR COBRAR | C51: MAYO | D51: LUZ | E51: 108.2 | G51: =+G50+E51-F51 -> 108.2
D52: AGUA | E52: 2 | G52: =+G51+E52-F52 -> 110.2
D53: G. ADM | E53: 60 | G53: =+G52+E53-F53 -> 170.2
D54: P. SOCIAL | E54: 2 | G54: =+G53+E54-F54 -> 172.2
A55: 42879 | B55: TARJETA | C55: MAYO | D55: G. ADM | F55: 28 | G55: =+G54+E55-F55 -> 144.2
A56: 42879 | B56: TARJETA | C56: MAYO | D56: LUZ | F56: 49 | G56: =+G55+E56-F56 -> 95.2
A57: 42972 | B57: 13497 | C57: MAYO | D57: LUZ | F57: 59.2 | G57: =+G56+E57-F57 -> 36
A58: 42972 | B58: 13497 | C58: MAYO | D58: AGUA | F58: 2 | G58: =+G57+E58-F58 -> 34
A59: 42947 | B59: TARJETA | C59: MAYO | D59: P. SOCIAL | F59: 2 | G59: =+G58+E59-F59 -> 32
A60: 44925 | B60: R 26042 | C60: MAYO | D60: G. ADM | F60: 32 | G60: =+G59+E60-F60 -> 0
A61: 42916 | B61: POR COBRAR | C61: JUNIO | D61: LUZ | E61: 105.7 | G61: =+G60+E61-F61 -> 105.7
D62: AGUA | E62: 2 | G62: =+G61+E62-F62 -> 107.7
D63: G. ADM | E63: 60 | G63: =+G62+E63-F63 -> 167.7
D64: P. SOCIAL | E64: 2 | G64: =+G63+E64-F64 -> 169.7
D65: CORTE/RECONCCION | E65: 30 | G65: =+G64+E65-F65 -> 199.7
A66: 42913 | B66: TARJETA | C66: JUNIO | D66: G. ADM | F66: 44 | G66: =+G65+E66-F66 -> 155.7
A67: 42913 | B67: TARJETA | C67: JUNIO | D67: LUZ | F67: 77 | G67: =+G66+E67-F67 -> 78.7
A68: 42888 | B68: 13033 | C68: JUNIO | D68: CORTE/RECONCCION | F68: 30 | G68: =+G67+E68-F68 -> 48.7
A69: 42972 | B69: 13494 | C69: JUNIO | D69: LUZ | F69: 28.7 | G69: =+G68+E69-F69 -> 20
A70: 42972 | B70: 13494 | C70: JUNIO | D70: AGUA | F70: 2 | G70: =+G69+E70-F70 -> 18
A71: 42947 | B71: TARJETA | C71: JUNIO | D71: P. SOCIAL | F71: 0.4 | G71: =+G70+E71-F71 -> 17.6
A72: 44925 | B72: R 26042 | C72: JUNIO | D72: G. ADM | F72: 16 | G72: =+G71+E72-F72 -> 1.6
A73: 44925 | B73: R 26042 | C73: JUNIO | D73: P. SOCIAL | F73: 1.6 | G73: =+G72+E73-F73 -> -9.3258734e-15
A74: 42947 | B74: POR COBRAR | C74: JULIO | D74: LUZ | E74: 96.6 | G74: =+G73+E74-F74 -> 96.6
D75: AGUA | E75: 2 | G75: =+G74+E75-F75 -> 98.6
D76: G. ADM | E76: 60 | G76: =+G75+E76-F76 -> 158.6
D77: P. SOCIAL | E77: 2 | G77: =+G76+E77-F77 -> 160.6
A78: 42941 | B78: TARJETA | C78: JULIO | D78: G. ADM | F78: 60 | G78: =+G77+E78-F78 -> 100.6
A79: 42941 | B79: TARJETA | C79: JULIO | D79: P. SOCIAL | F79: 2 | G79: =+G78+E79-F79 -> 98.6
A80: 42947 | B80: TARJETA | C80: JULIO | D80: LUZ | F80: 96.6 | G80: =+G79+E80-F80 -> 2
A81: 42947 | B81: TARJETA | C81: JULIO | D81: AGUA | F81: 2 | G81: =+G80+E81-F81 -> -2.8421709e-14
A82: 42978 | B82: POR COBRAR | C82: AGOSTO | D82: LUZ | E82: 96.6 | G82: =+G81+E82-F82 -> 96.6
D83: AGUA | E83: 2 | G83: =+G82+E83-F83 -> 98.6
D84: G. ADM | E84: 60 | G84: =+G83+E84-F84 -> 158.6
D85: P. SOCIAL | E85: 2 | G85: =+G84+E85-F85 -> 160.6
D86: MULTA | E86: 85 | G86: =+G85+E86-F86 -> 245.6
A87: 42978 | B87: TARJETA | C87: AGOSTO | D87: G. ADM | F87: 60 | G87: =+G86+E87-F87 -> 185.6
A88: 42978 | B88: TARJETA | C88: AGOSTO | D88: P. SOCIAL | F88: 2 | G88: =+G87+E88-F88 -> 183.6
A89: 43067 | B89: EXONERACION | C89: AGOSTO | D89: MULTA | F89: 85 | G89: =+G88+E89-F89 -> 98.6
A90: 43104 | B90: 14392 | C90: AGOSTO | D90: LUZ | F90: 96.6 | G90: =+G89+E90-F90 -> 2
A91: 43104 | B91: 14392 | C91: AGOSTO | D91: AGUA | F91: 2 | G91: =+G90+E91-F91 -> -2.8421709e-14
A92: 43008 | B92: POR COBRAR | C92: SEPTIEMBRE | D92: LUZ | E92: 84.1 | G92: =+G91+E92-F92 -> 84.1
D93: AGUA | E93: 2 | G93: =+G92+E93-F93 -> 86.1
D94: G. ADM | E94: 60 | G94: =+G93+E94-F94 -> 146.1
D95: P. SOCIAL | E95: 2 | G95: =+G94+E95-F95 -> 148.1
A96: 42823 | D96: MULTA | E96: 85 | G96: =+G95+E96-F96 -> 233.1
A97: 43008 | B97: TARJETA | C97: SEPTIEMBRE | D97: LUZ | F97: 84.1 | G97: =+G96+E97-F97 -> 149
A98: 43008 | B98: TARJETA | C98: SEPTIEMBRE | D98: AGUA | F98: 2 | G98: =+G97+E98-F98 -> 147
A99: 43067 | B99: EXONERACION | C99: 42823 | D99: MULTA | F99: 85 | G99: =+G98+E99-F99 -> 62
A100: 44925 | B100: R 26042 | C100: SEPTIEMBRE | D100: G. ADM | F100: 60 | G100: =+G99+E100-F100 -> 2
A101: 44925 | B101: R 26042 | C101: SEPTIEMBRE | D101: P. SOCIAL | F101: 2 | G101: =+G100+E101-F101 -> -2.8421709e-14
A102: 43039 | B102: POR COBRAR | C102: OCTUBRE | D102: LUZ | E102: 83.7 | G102: =+G101+E102-F102 -> 83.7
...

Sheet TELLO EDGAR
B2: TELLO QUINTANA EDGAR
A4: FECHA | B4: DOCUMENTO | C4: PERIODO | D4: CONCEPTO | E4: POR COBRAR | F4: PAGADO | G4: SALDO POR COBRAR
A5: 42736 | B5: SALDO AL 2016 | G5: 233
A6: 42809 | B6: 12419 | C6: A CUENTA 2016 | F6: 233 | G6: =+G5+E6-F6 -> 0
A7: 42766 | B7: POR COBRAR | C7: ENERO | D7: LUZ | E7: 76.3 | G7: =+G6+E7-F7 -> 76.3
D8: AGUA | E8: 50 | G8: =+G7+E8-F8 -> 126.3
D9: G. ADM | E9: 60 | G9: =+G8+E9-F9 -> 186.3
D10: P. SOCIAL | E10: 2 | G10: =+G9+E10-F10 -> 188.3
A11: 42761 | B11: TARJETA | C11: ENERO | D11: G. ADM | F11: 52 | G11: =+G10+E11-F11 -> 136.3
A12: 42851 | B12: TARJETA | C12: ENERO | D12: LUZ | F12: 43 | G12: =+G11+E12-F12 -> 93.3
A13: 42809 | B13: 12420 | C13: ENERO | D13: G. ADM | F13: 8 | G13: =+G12+E13-F13 -> 85.3
A14: 42809 | B14: 12420 | C14: ENERO | D14: P. SOCIAL | F14: 2 | G14: =+G13+E14-F14 -> 83.3
A15: 42809 | B15: 12420 | C15: ENERO | D15: LUZ | F15: 33.3 | G15: =+G14+E15-F15 -> 50
A16: 42809 | B16: 12420 | C16: ENERO | D16: AGUA | F16: 50 | G16: =+G15+E16-F16 -> 0
A17: 42794 | B17: POR COBRAR | C17: FEBRERO | D17: LUZ | E17: 83.7 | G17: =+G16+E17-F17 -> 83.7
D18: AGUA | E18: 35 | G18: =+G17+E18-F18 -> 118.7
D19: G. ADM | E19: 56 | G19: =+G18+E19-F19 -> 174.7
D20: P. SOCIAL | E20: 2 | G20: =+G19+E20-F20 -> 176.7
A21: 42786 | B21: TARJETA | C21: FEBRERO | D21: LUZ | F21: 30 | G21: =+G20+E21-F21 -> 146.7
A22: 42786 | B22: TARJETA | C22: FEBRERO | D22: G. ADM | F22: 56 | G22: =+G21+E22-F22 -> 90.7
A23: 42786 | B23: TARJETA | C23: FEBRERO | D23: P. SOCIAL | F23: 2 | G23: =+G22+E23-F23 -> 88.7
A24: 42888 | B24: 13041 | C24: FEBRERO | D24: LUZ | F24: 53.7 | G24: =+G23+E24-F24 -> 35
A25: 42888 | B25: 13041 | C25: FEBRERO | D25: AGUA | F25: 35 | G25: =+G24+E25-F25 -> 0
A26: 42825 | B26: POR COBRAR | C26: MARZO | D26: LUZ | E26: 80 | G26: =+G25+E26-F26 -> 80
D27: AGUA | E27: 36.4 | G27: =+G26+E27-F27 -> 116.4
D28: G. ADM | E28: 60 | G28: =+G27+E28-F28 -> 176.4
D29: P. SOCIAL | E29: 2 | G29: =+G28+E29-F29 -> 178.4
D30: TRANFERENCIA | E30: 6000 | G30: =+G29+E30-F30 -> 6178.4
A31: 42808 | B31: TARJETA | C31: MARZO | D31: LUZ | F31: 31 | G31: =+G30+E31-F31 -> 6147.4
A32: 42808 | B32: TARJETA | C32: MARZO | D32: G. ADM | F32: 29 | G32: =+G31+E32-F32 -> 6118.4
A33: 42824 | B33: 12623 | C33: MARZO | D33: TRANFERENCIA | F33: 6000 | G33: =+G32+E33-F33 -> 118.4
A34: 42888 | B34: 13041 | C34: MARZO | D34: AGUA | F34: 36.4 | G34: =+G33+E34-F34 -> 82
A35: 42888 | B35: 13041 | C35: MARZO | D35: LUZ | F35: 49 | G35: =+G34+E35-F35 -> 33
A36: 42950 | B36: 13409 | C36: MARZO | D36: G. ADM | F36: 31 | G36: =+G35+E36-F36 -> 2
A37: 42950 | B37: 13409 | C37: MARZO | D37: P. SOCIAL | F37: 2 | G37: =+G36+E37-F37 -> -3.6948222e-13
A38: 42855 | B38: POR COBRAR | C38: ABRIL | D38: LUZ | E38: 81.8 | G38: =+G37+E38-F38 -> 81.8
D39: AGUA | E39: 35.7 | G39: =+G38+E39-F39 -> 117.5
D40: G. ADM | E40: 60 | G40: =+G39+E40-F40 -> 177.5
D41: P. SOCIAL | E41: 2 | G41: =+G40+E41-F41 -> 179.5
A42: 42853 | B42: TARJETA | C42: ABRIL | D42: LUZ | F42: 65 | G42: =+G41+E42-F42 -> 114.5
A43: 42853 | B43: TARJETA | C43: ABRIL | D43: G. ADM | F43: 26 | G43: =+G42+E43-F43 -> 88.5
A44: 42888 | B44: 13041 | C44: ABRIL | D44: LUZ | F44: 16.8 | G44: =+G43+E44-F44 -> 71.7
A45: 42888 | B45: 13041 | C45: ABRIL | D45: AGUA | F45: 35.7 | G45: =+G44+E45-F45 -> 36
A46: 42950 | B46: 13409 | C46: ABRIL | D46: G. ADM | F46: 34 | G46: =+G45+E46-F46 -> 2
A47: 42950 | B47: 13409 | C47: ABRIL | D47: P. SOCIAL | F47: 2 | G47: =+G46+E47-F47 -> -3.6948222e-13
A48: 42886 | B48: POR COBRAR | C48: MAYO | D48: LUZ | E48: 76.4 | G48: =+G47+E48-F48 -> 76.4
D49: AGUA | E49: 35 | G49: =+G48+E49-F49 -> 111.4
D50: G. ADM | E50: 60 | G50: =+G49+E50-F50 -> 171.4
D51: P. SOCIAL | E51: 2 | G51: =+G50+E51-F51 -> 173.4
A52: 42863 | B52: TARJETA | C52: MAYO | D52: LUZ | F52: 20 | G52: =+G51+E52-F52 -> 153.4
A53: 42863 | B53: TARJETA | C53: MAYO | D53: G. ADM | F53: 8 | G53: =+G52+E53-F53 -> 145.4
A54: 42950 | B54: 13409 | C54: MAYO | D54: G. ADM | F54: 52 | G54: =+G53+E54-F54 -> 93.4
A55: 42950 | B55: 13409 | C55: MAYO | D55: P. SOCIAL | F55: 2 | G55: =+G54+E55-F55 -> 91.4
A56: 42950 | B56: 13409 | C56: MAYO | D56: LUZ | F56: 56.4 | G56: =+G55+E56-F56 -> 35
A57: 42950 | B57: 13409 | C57: MAYO | D57: AGUA | F57: 35 | G57: =+G56+E57-F57 -> -3.623768e-13
A58: 42916 | B58: POR COBRAR | C58: JUNIO | D58: LUZ | E58: 74.6 | G58: =+G57+E58-F58 -> 74.6
D59: AGUA | E59: 35 | G59: =+G58+E59-F59 -> 109.6
D60: G. ADM | E60: 60 | G60: =+G59+E60-F60 -> 169.6
D61: P. SOCIAL | E61: 2 | G61: =+G60+E61-F61 -> 171.6
A62: 42916 | B62: TARJETA | C62: JUNIO | D62: LUZ | F62: 74.6 | G62: =+G61+E62-F62 -> 97
A63: 42916 | B63: TARJETA | C63: JUNIO | D63: AGUA | F63: 31.4 | G63: =+G62+E63-F63 -> 65.6
A64: 42916 | B64: TARJETA | C64: JUNIO | D64: G. ADM | F64: 60 | G64: =+G63+E64-F64 -> 5.6
A65: 42916 | B65: TARJETA | C65: JUNIO | D65: P. SOCIAL | F65: 2 | G65: =+G64+E65-F65 -> 3.6
A66: 42950 | B66: 13409 | C66: JUNIO | D66: AGUA | F66: 3.6 | G66: =+G65+E66-F66 -> -3.7525538e-13
A67: 42947 | B67: POR COBRAR | C67: JULIO | D67: LUZ | E67: 67.4 | G67: =+G66+E67-F67 -> 67.4
D68: AGUA | E68: 35 | G68: =+G67+E68-F68 -> 102.4
D69: G. ADM | E69: 60 | G69: =+G68+E69-F69 -> 162.4
D70: P. SOCIAL | E70: 2 | G70: =+G69+E70-F70 -> 164.4
A71: 42945 | B71: TARJETA | C71: JULIO | D71: G. ADM | F71: 48 | G71: =+G70+E71-F71 -> 116.4
A72: 42950 | B72: 13409 | C72: JULIO | D72: G. ADM | F72: 12 | G72: =+G71+E72-F72 -> 104.4
A73: 42950 | B73: 13409 | C73: JULIO | D73: P. SOCIAL | F73: 2 | G73: =+G72+E73-F73 -> 102.4
A74: 42947 | B74: TARJETA | C74: JULIO | D74: LUZ | F74: 67.4 | G74: =+G73+E74-F74 -> 35
A75: 42947 | B75: TARJETA | C75: JULIO | D75: AGUA | F75: 4.6 | G75: =+G74+E75-F75 -> 30.4
A76: 42978 | B76: TARJETA | C76: JULIO | D76: AGUA | F76: 30.4 | G76: =+G75+E76-F76 -> -3.6948222e-13
A77: 42948 | B77: POR COBRAR | C77: AGOSTO | D77: LUZ | E77: 67.4 | G77: =+G76+E77-F77 -> 67.4
D78: AGUA | E78: 35 | G78: =+G77+E78-F78 -> 102.4
D79: G. ADM | E79: 60 | G79: =+G78+E79-F79 -> 162.4
D80: P. SOCIAL | E80: 2 | G80: =+G79+E80-F80 -> 164.4
A81: 42978 | B81: TARJETA | C81: AGOSTO | D81: G. ADM | F81: 52 | G81: =+G80+E81-F81 -> 112.4
A82: 42978 | B82: TARJETA | C82: AGOSTO | D82: AGUA | F82: 35 | G82: =+G81+E82-F82 -> 77.4
A83: 42978 | B83: TARJETA | C83: AGOSTO | D83: LUZ | F83: 12.6 | G83: =+G82+E83-F83 -> 64.8
A84: 43008 | B84: TARJETA | C84: AGOSTO | D84: LUZ | F84: 54.8 | G84: =+G83+E84-F84 -> 10
A85: 43068 | B85: 14206 | C85: AGOSTO | D85: G. ADM | F85: 8 | G85: =+G84+E85-F85 -> 2
A86: 43068 | B86: 14206 | C86: AGOSTO | D86: P. SOCIAL | F86: 2 | G86: =+G85+E86-F86 -> -3.5527137e-13
A87: 43008 | B87: POR COBRAR | C87: SEPTIEMBRE | D87: LUZ | E87: 89 | G87: =+G86+E87-F87 -> 89
D88: AGUA | E88: 35 | G88: =+G87+E88-F88 -> 124
D89: G. ADM | E89: 60 | G89: =+G88+E89-F89 -> 184
D90: P. SOCIAL | E90: 2 | G90: =+G89+E90-F90 -> 186
A91: 42788 | D91: MULTA | E91: 85 | G91: =+G90+E91-F91 -> 271
A92: 42823 | D92: MULTA | E92: 85 | G92: =+G91+E92-F92 -> 356
A93: 43008 | B93: TARJETA | C93: SEPTIEMBRE | D93: G. ADM | F93: 60 | G93: =+G92+E93-F93 -> 296
A94: 43008 | B94: TARJETA | C94: SEPTIEMBRE | D94: LUZ | F94: 35.2 | G94: =+G93+E94-F94 -> 260.8
A95: 43008 | B95: TARJETA | C95: SEPTIEMBRE | D95: LUZ | F95: 0.2 | G95: =+G94+E95-F95 -> 260.6
A96: 43008 | B96: TARJETA | C96: SEPTIEMBRE | D96: AGUA | F96: 35 | G96: =+G95+E96-F96 -> 225.6
A97: 43039 | B97: TARJETA | C97: SEPTIEMBRE | D97: LUZ | F97: 53.6 | G97: =+G96+E97-F97 -> 172
A98: 43067 | B98: EXONERACION | C98: 42788 | D98: MULTA | F98: 85 | G98: =+G97+E98-F98 -> 87
A99: 43067 | B99: EXONERACION | C99: 42823 | D99: MULTA | F99: 85 | G99: =+G98+E99-F99 -> 2
A100: 43068 | B100: 14206 | C100: SEPTIEMBRE | D100: P. SOCIAL | F100: 2 | G100: =+G99+E100-F100 -> -3.126388e-13
A101: 43039 | B101: POR COBRAR | C101: OCTUBRE | D101: LUZ | E101: 88 | G101: =+G100+E101-F101 -> 88
D102: AGUA | E102: 35 | G102: =+G101+E102-F102 -> 123
...

Sheet TINEO CABRERA SONIA
B2: TINEO CABRERA SONIA
A4: FECHA | B4: DOCUMENTO | C4: PERIODO | D4: CONCEPTO | E4: POR COBRAR | F4: PAGADO | G4: SALDO POR COBRAR
A5: 42736 | B5: SALDO AL 2016 | G5: 4578.2
A6: 42886 | B6: 13017 | C6: A CUENTA 2016 | F6: 1000 | G6: =+G5+E6-F6 -> 3578.2
A7: 42855 | B7: TARJETA | C7: A CUENTA 2016 | F7: 95 | G7: =+G6+E7-F7 -> 3483.2
A8: 42882 | B8: TARJETA | C8: A CUENTA 2016 | F8: 100 | G8: =+G7+E8-F8 -> 3383.2
A9: 43087 | B9: 14238 | C9: A CUENTA 2016 | F9: 406.8 | G9: =+G8+E9-F9 -> 2976.4
A10: 43308 | B10: 15838 | C10: A CUENTA 2016 | F10: 150 | G10: =+G9+E10-F10 -> 2826.4
A11: 43308 | B11: 15839 | C11: A CUENTA 2016 | F11: 82 | G11: =+G10+E11-F11 -> 2744.4
A12: 43308 | B12: 15840 | C12: A CUENTA 2016 | F12: 66 | G12: =+G11+E12-F12 -> 2678.4
A13: 43360 | B13: 16140 | C13: A CUENTA 2016 | F13: 430 | G13: =+G12+E13-F13 -> 2248.4
A14: 43411 | B14: 16546 | C14: A CUENTA 2016 | F14: 354.7 | G14: =+G13+E14-F14 -> 1893.7
A15: 43411 | B15: 16547 | C15: A CUENTA 2016 | F15: 75.3 | G15: =+G14+E15-F15 -> 1818.4
C16: EXONERACION 50% MULTA | F16: 600 | G16: =+G15+E16-F16 -> 1218.4
A17: 43818 | B17: 19328 | C17: CANCELACION 2016 | F17: 1218.4 | G17: =+G16+E17-F17 -> 0
A18: 42766 | B18: POR COBRAR | C18: ENERO | D18: LUZ | E18: 13.5 | F18: 0 | G18: =+G17+E18-F18 -> 13.5
D19: AGUA | E19: 2.7 | G19: =+G18+E19-F19 -> 16.2
D20: G. ADM | E20: 60 | G20: =+G19+E20-F20 -> 76.2
D21: P. SOCIAL | E21: 2 | G21: =+G20+E21-F21 -> 78.2
A22: 42765 | B22: TARJETA | C22: ENERO | D22: G. ADM | F22: 60 | G22: =+G21+E22-F22 -> 18.2
A23: 42765 | B23: TARJETA | C23: ENERO | D23: P. SOCIAL | F23: 2 | G23: =+G22+E23-F23 -> 16.2
A24: 43011 | B24: 13778 | C24: ENERO | D24: LUZ | F24: 13.5 | G24: =+G23+E24-F24 -> 2.7
A25: 43011 | B25: 13778 | C25: ENERO | D25: AGUA | F25: 2.7 | G25: =+G24+E25-F25 -> 0
A26: 42794 | B26: POR COBRAR | C26: FEBRERO | D26: LUZ | E26: 13 | G26: =+G25+E26-F26 -> 13
D27: AGUA | E27: 2 | G27: =+G26+E27-F27 -> 15
D28: G. ADM | E28: 56 | G28: =+G27+E28-F28 -> 71
D29: P. SOCIAL | E29: 2 | G29: =+G28+E29-F29 -> 73
D30: MULTA | E30: 85 | G30: =+G29+E30-F30 -> 158
A31: 42794 | B31: TARJETA | C31: FEBRERO | D31: G. ADM | F31: 56 | G31: =+G30+E31-F31 -> 102
A32: 42794 | B32: TARJETA | C32: FEBRERO | D32: P. SOCIAL | F32: 2 | G32: =+G31+E32-F32 -> 100
A33: 43011 | B33: 13778 | C33: FEBRERO | D33: LUZ | F33: 13 | G33: =+G32+E33-F33 -> 87
A34: 43011 | B34: 13778 | C34: FEBRERO | D34: AGUA | F34: 2 | G34: =+G33+E34-F34 -> 85
A35: 43067 | B35: EXONERACION | C35: FEBRERO | D35: MULTA | F35: 85 | G35: =+G34+E35-F35 -> 0
A36: 42825 | B36: POR COBRAR | C36: MARZO | D36: LUZ | E36: 12 | G36: =+G35+E36-F36 -> 12
D37: AGUA | E37: 2 | G37: =+G36+E37-F37 -> 14
D38: G. ADM | E38: 60 | G38: =+G37+E38-F38 -> 74
D39: P. SOCIAL | E39: 2 | G39: =+G38+E39-F39 -> 76
A40: 42824 | B40: TARJETA | C40: MARZO | D40: G. ADM | F40: 60 | G40: =+G39+E40-F40 -> 16
A41: 42824 | B41: TARJETA | C41: MARZO | D41: P. SOCIAL | F41: 2 | G41: =+G40+E41-F41 -> 14
A42: 43011 | B42: 13778 | C42: MARZO | D42: LUZ | F42: 12 | G42: =+G41+E42-F42 -> 2
A43: 43011 | B43: 13778 | C43: MARZO | D43: AGUA | F43: 2 | G43: =+G42+E43-F43 -> 0
A44: 42855 | B44: POR COBRAR | C44: ABRIL | D44: LUZ | E44: 13 | G44: =+G43+E44-F44 -> 13
D45: AGUA | E45: 2 | G45: =+G44+E45-F45 -> 15
D46: G. ADM | E46: 60 | G46: =+G45+E46-F46 -> 75
D47: P. SOCIAL | E47: 2 | G47: =+G46+E47-F47 -> 77
A48: 42855 | B48: TARJETA | C48: ABRIL | D48: G. ADM | F48: 60 | G48: =+G47+E48-F48 -> 17
A49: 42855 | B49: TARJETA | C49: ABRIL | D49: P. SOCIAL | F49: 2 | G49: =+G48+E49-F49 -> 15
A50: 43011 | B50: 13778 | C50: ABRIL | D50: LUZ | F50: 13 | G50: =+G49+E50-F50 -> 2
A51: 43011 | B51: 13778 | C51: ABRIL | D51: AGUA | F51: 2 | G51: =+G50+E51-F51 -> 0
A52: 42886 | B52: POR COBRAR | C52: MAYO | D52: LUZ | E52: 13 | G52: =+G51+E52-F52 -> 13
D53: AGUA | E53: 2 | G53: =+G52+E53-F53 -> 15
D54: G. ADM | E54: 60 | G54: =+G53+E54-F54 -> 75
D55: P. SOCIAL | E55: 2 | G55: =+G54+E55-F55 -> 77
A56: 42885 | B56: TARJETA | C56: MAYO | D56: G. ADM | F56: 60 | G56: =+G55+E56-F56 -> 17
A57: 42885 | B57: TARJETA | C57: MAYO | D57: P. SOCIAL | F57: 2 | G57: =+G56+E57-F57 -> 15
A58: 43011 | B58: 13779 | C58: MAYO | D58: LUZ | F58: 13 | G58: =+G57+E58-F58 -> 2
A59: 43011 | B59: 13779 | C59: MAYO | D59: AGUA | F59: 2 | G59: =+G58+E59-F59 -> 0
A60: 42916 | B60: POR COBRAR | C60: JUNIO | D60: LUZ | E60: 12.5 | G60: =+G59+E60-F60 -> 12.5
D61: AGUA | E61: 2 | G61: =+G60+E61-F61 -> 14.5
D62: G. ADM | E62: 60 | G62: =+G61+E62-F62 -> 74.5
D63: P. SOCIAL | E63: 2 | G63: =+G62+E63-F63 -> 76.5
A64: 42916 | B64: TARJETA | C64: JUNIO | D64: G. ADM | F64: 60 | G64: =+G63+E64-F64 -> 16.5
A65: 42916 | B65: TARJETA | C65: JUNIO | D65: P. SOCIAL | F65: 2 | G65: =+G64+E65-F65 -> 14.5
A66: 43011 | B66: 13779 | C66: JUNIO | D66: LUZ | F66: 12.5 | G66: =+G65+E66-F66 -> 2
A67: 43011 | B67: 13779 | C67: JUNIO | D67: AGUA | F67: 2 | G67: =+G66+E67-F67 -> 0
A68: 42947 | B68: POR COBRAR | C68: JULIO | D68: LUZ | E68: 13 | G68: =+G67+E68-F68 -> 13
D69: AGUA | E69: 2 | G69: =+G68+E69-F69 -> 15
D70: G. ADM | E70: 60 | G70: =+G69+E70-F70 -> 75
D71: P. SOCIAL | E71: 2 | G71: =+G70+E71-F71 -> 77
A72: 42945 | B72: TARJETA | C72: JULIO | D72: G. ADM | F72: 60 | G72: =+G71+E72-F72 -> 17
A73: 42945 | B73: TARJETA | C73: JULIO | D73: P. SOCIAL | F73: 2 | G73: =+G72+E73-F73 -> 15
A74: 43011 | B74: 13779 | C74: JULIO | D74: LUZ | F74: 13 | G74: =+G73+E74-F74 -> 2
A75: 43011 | B75: 13779 | C75: JULIO | D75: AGUA | F75: 2 | G75: =+G74+E75-F75 -> 0
A76: 42978 | B76: POR COBRAR | C76: AGOSTO | D76: LUZ | E76: 13 | G76: =+G75+E76-F76 -> 13
D77: AGUA | E77: 2 | G77: =+G76+E77-F77 -> 15
D78: G. ADM | E78: 60 | G78: =+G77+E78-F78 -> 75
D79: P. SOCIAL | E79: 2 | G79: =+G78+E79-F79 -> 77
D80: MULTA | E80: 85 | G80: =+G79+E80-F80 -> 162
A81: 42978 | B81: TARJETA | C81: AGOSTO | D81: G. ADM | F81: 60 | G81: =+G80+E81-F81 -> 102
A82: 42978 | B82: TARJETA | C82: AGOSTO | D82: P. SOCIAL | F82: 2 | G82: =+G81+E82-F82 -> 100
A83: 43011 | B83: 13779 | C83: AGOSTO | D83: LUZ | F83: 13 | G83: =+G82+E83-F83 -> 87
A84: 43011 | B84: 13779 | C84: AGOSTO | D84: AGUA | F84: 2 | G84: =+G83+E84-F84 -> 85
A85: 43067 | B85: EXONERACION | C85: AGOSTO | D85: MULTA | F85: 85 | G85: =+G84+E85-F85 -> 0
A86: 43008 | B86: POR COBRAR | C86: SEPTIEMBRE | D86: LUZ | E86: 8 | G86: =+G85+E86-F86 -> 8
D87: AGUA | E87: 2 | G87: =+G86+E87-F87 -> 10
D88: G. ADM | E88: 60 | G88: =+G87+E88-F88 -> 70
D89: P. SOCIAL | E89: 2 | G89: =+G88+E89-F89 -> 72
A90: 42823 | D90: MULTA | E90: 85 | G90: =+G89+E90-F90 -> 157
A91: 43008 | B91: TARJETA | C91: SEPTIEMBRE | D91: G. ADM | F91: 60 | G91: =+G90+E91-F91 -> 97
A92: 43008 | B92: TARJETA | C92: SEPTIEMBRE | D92: P. SOCIAL | F92: 2 | G92: =+G91+E92-F92 -> 95
A93: 43067 | B93: EXONERACION | C93: 42823 | D93: MULTA | F93: 85 | G93: =+G92+E93-F93 -> 10
A94: 43087 | B94: 14238 | C94: SEPTIEMBRE | D94: LUZ | F94: 8 | G94: =+G93+E94-F94 -> 2
A95: 43087 | B95: 14238 | C95: SEPTIEMBRE | D95: AGUA | F95: 2 | G95: =+G94+E95-F95 -> 0
A96: 43039 | B96: POR COBRAR | C96: OCTUBRE | D96: LUZ | E96: 8 | G96: =+G95+E96-F96 -> 8
D97: AGUA | E97: 2 | G97: =+G96+E97-F97 -> 10
D98: G. ADM | E98: 60 | G98: =+G97+E98-F98 -> 70
D99: P. SOCIAL | E99: 2 | G99: =+G98+E99-F99 -> 72
A100: 42977 | B100: ACT. SANTA ROSA | D100: CUOTA | E100: 25 | G100: =+G99+E100-F100 -> 97
A101: 43039 | B101: TARJETA | C101: OCTUBRE | D101: G. ADM | F101: 60 | G101: =+G100+E101-F101 -> 37
A102: 43039 | B102: TARJETA | C102: OCTUBRE | D102: P. SOCIAL | F102: 2 | G102: =+G101+E102-F102 -> 35
...

Sheet TINTAYA PATRICIA
B2: TINTTAYA CAHUANA PATRICIA
A4: FECHA | B4: DOCUMENTO | C4: PERIODO | D4: CONCEPTO | E4: POR COBRAR | F4: PAGADO | G4: SALDO POR COBRAR
A5: 42736 | B5: SALDO AL 2016 | G5: 93.6
A6: 42786 | B6: 12258 | C6: A CUENTA 2016 | F6: 93.6 | G6: =+G5+E6-F6 -> 0
A7: 42766 | B7: POR COBRAR | C7: ENERO | D7: LUZ | E7: 52.5 | G7: =+G6+E7-F7 -> 52.5
D8: AGUA | E8: 2.86 | G8: =+G7+E8-F8 -> 55.36
D9: G. ADM | E9: 60 | G9: =+G8+E9-F9 -> 115.36
D10: P. SOCIAL | E10: 2 | G10: =+G9+E10-F10 -> 117.36
A11: 42765 | B11: TARJETA | C11: ENERO | D11: G. ADM | F11: 60 | G11: =+G10+E11-F11 -> 57.36
A12: 42765 | B12: TARJETA | C12: ENERO | D12: P. SOCIAL | F12: 2 | G12: =+G11+E12-F12 -> 55.36
A13: 42786 | B13: 12258 | C13: ENERO | D13: LUZ | F13: 52.5 | G13: =+G12+E13-F13 -> 2.86
A14: 42786 | B14: 12258 | C14: ENERO | D14: AGUA | F14: 2.86 | G14: =+G13+E14-F14 -> 0
A15: 42794 | B15: POR COBRAR | C15: FEBRERO | D15: LUZ | E15: 52.5 | G15: =+G14+E15-F15 -> 52.5
D16: AGUA | E16: 2.8 | G16: =+G15+E16-F16 -> 55.3
D17: G. ADM | E17: 56 | G17: =+G16+E17-F17 -> 111.3
D18: P. SOCIAL | E18: 2 | G18: =+G17+E18-F18 -> 113.3
A19: 42794 | B19: TARJETA | C19: FEBRERO | D19: G. ADM | F19: 56 | G19: =+G18+E19-F19 -> 57.3
A20: 42794 | B20: TARJETA | C20: FEBRERO | D20: P. SOCIAL | F20: 2 | G20: =+G19+E20-F20 -> 55.3
A21: 42836 | B21: 12639 | C21: FEBRERO | D21: LUZ | F21: 52.5 | G21: =+G20+E21-F21 -> 2.8
A22: 42836 | B22: 12639 | C22: FEBRERO | D22: AGUA | F22: 2.8 | G22: =+G21+E22-F22 -> 0
A23: 42825 | B23: POR COBRAR | C23: MARZO | D23: LUZ | E23: 49.6 | G23: =+G22+E23-F23 -> 49.6
D24: AGUA | E24: 2 | G24: =+G23+E24-F24 -> 51.6
D25: G. ADM | E25: 60 | G25: =+G24+E25-F25 -> 111.6
D26: P. SOCIAL | E26: 2 | G26: =+G25+E26-F26 -> 113.6
A27: 42824 | B27: TARJETA | C27: MARZO | D27: G. ADM | F27: 60 | G27: =+G26+E27-F27 -> 53.6
A28: 42824 | B28: TARJETA | C28: MARZO | D28: P. SOCIAL | F28: 2 | G28: =+G27+E28-F28 -> 51.6
A29: 42836 | B29: 12639 | C29: MARZO | D29: AGUA | F29: 2 | G29: =+G28+E29-F29 -> 49.6
A30: 42836 | B30: 12639 | C30: MARZO | D30: LUZ | F30: 49.6 | G30: =+G29+E30-F30 -> 0
A31: 42855 | B31: POR COBRAR | C31: ABRIL | D31: LUZ | E31: 51.8 | G31: =+G30+E31-F31 -> 51.8
D32: AGUA | E32: 2 | G32: =+G31+E32-F32 -> 53.8
D33: G. ADM | E33: 60 | G33: =+G32+E33-F33 -> 113.8
D34: P. SOCIAL | E34: 2 | G34: =+G33+E34-F34 -> 115.8
A35: 42855 | B35: TARJETA | C35: ABRIL | D35: G. ADM | F35: 60 | G35: =+G34+E35-F35 -> 55.8
A36: 42855 | B36: TARJETA | C36: ABRIL | D36: P. SOCIAL | F36: 2 | G36: =+G35+E36-F36 -> 53.8
A37: 42908 | B37: 13125 | C37: ABRIL | D37: LUZ | F37: 51.8 | G37: =+G36+E37-F37 -> 2
A38: 42908 | B38: 13125 | C38: ABRIL | D38: AGUA | F38: 2 | G38: =+G37+E38-F38 -> 0
A39: 42886 | B39: POR COBRAR | C39: MAYO | D39: LUZ | E39: 49.8 | G39: =+G38+E39-F39 -> 49.8
D40: AGUA | E40: 2 | G40: =+G39+E40-F40 -> 51.8
D41: G. ADM | E41: 60 | G41: =+G40+E41-F41 -> 111.8
D42: P. SOCIAL | E42: 2 | G42: =+G41+E42-F42 -> 113.8
A43: 42885 | B43: TARJETA | C43: MAYO | D43: G. ADM | F43: 60 | G43: =+G42+E43-F43 -> 53.8
A44: 42885 | B44: TARJETA | C44: MAYO | D44: P. SOCIAL | F44: 2 | G44: =+G43+E44-F44 -> 51.8
A45: 42908 | B45: 13025 | C45: MAYO | D45: LUZ | F45: 49.8 | G45: =+G44+E45-F45 -> 2
A46: 42908 | B46: 13025 | C46: MAYO | D46: AGUA | F46: 2 | G46: =+G45+E46-F46 -> 0
A47: 42916 | B47: POR COBRAR | C47: JUNIO | D47: LUZ | E47: 49 | G47: =+G46+E47-F47 -> 49
D48: AGUA | E48: 2 | G48: =+G47+E48-F48 -> 51
D49: G. ADM | E49: 60 | G49: =+G48+E49-F49 -> 111
D50: P. SOCIAL | E50: 2 | G50: =+G49+E50-F50 -> 113
A51: 42916 | B51: TARJETA | C51: JUNIO | D51: G. ADM | F51: 60 | G51: =+G50+E51-F51 -> 53
A52: 42916 | B52: TARJETA | C52: JUNIO | D52: P. SOCIAL | F52: 2 | G52: =+G51+E52-F52 -> 51
A53: 42972 | B53: 13496 | C53: JUNIO | D53: LUZ | F53: 49 | G53: =+G52+E53-F53 -> 2
A54: 42972 | B54: 13496 | C54: JUNIO | D54: AGUA | F54: 2 | G54: =+G53+E54-F54 -> 0
A55: 42947 | B55: POR COBRAR | C55: JULIO | D55: LUZ | E55: 46.4 | G55: =+G54+E55-F55 -> 46.4
D56: AGUA | E56: 2 | G56: =+G55+E56-F56 -> 48.4
D57: G. ADM | E57: 60 | G57: =+G56+E57-F57 -> 108.4
D58: P. SOCIAL | E58: 2 | G58: =+G57+E58-F58 -> 110.4
A59: 42947 | B59: TARJETA | C59: JULIO | D59: G. ADM | F59: 60 | G59: =+G58+E59-F59 -> 50.4
A60: 42947 | B60: TARJETA | C60: JULIO | D60: P. SOCIAL | F60: 2 | G60: =+G59+E60-F60 -> 48.4
A61: 42972 | B61: 13496 | C61: JULIO | D61: LUZ | F61: 46.4 | G61: =+G60+E61-F61 -> 2
A62: 42972 | B62: 13496 | C62: JULIO | D62: AGUA | F62: 2 | G62: =+G61+E62-F62 -> 7.1054274e-15
A63: 42978 | B63: POR COBRAR | C63: AGOSTO | D63: LUZ | E63: 46.4 | G63: =+G62+E63-F63 -> 46.4
D64: AGUA | E64: 2 | G64: =+G63+E64-F64 -> 48.4
D65: G. ADM | E65: 60 | G65: =+G64+E65-F65 -> 108.4
D66: P. SOCIAL | E66: 2 | G66: =+G65+E66-F66 -> 110.4
D67: MULTA | E67: 85 | G67: =+G66+E67-F67 -> 195.4
A68: 42978 | B68: TARJETA | C68: AGOSTO | D68: G. ADM | F68: 60 | G68: =+G67+E68-F68 -> 135.4
A69: 42978 | B69: TARJETA | C69: AGOSTO | D69: P. SOCIAL | F69: 2 | G69: =+G68+E69-F69 -> 133.4
A70: 43000 | B70: 13657 | C70: AGOSTO | D70: LUZ | F70: 46.4 | G70: =+G69+E70-F70 -> 87
A71: 43000 | B71: 13657 | C71: AGOSTO | D71: AGUA | F71: 2 | G71: =+G70+E71-F71 -> 85
A72: 43284 | B72: EXONERACION | C72: 42951 | D72: MULTA | F72: 85 | G72: =+G71+E72-F72 -> 0
A73: 43008 | B73: POR COBRAR | C73: SEPTIEMBRE | D73: LUZ | E73: 32.9 | G73: =+G72+E73-F73 -> 32.9
D74: AGUA | E74: 2 | G74: =+G73+E74-F74 -> 34.9
D75: G. ADM | E75: 60 | G75: =+G74+E75-F75 -> 94.9
D76: P. SOCIAL | E76: 2 | G76: =+G75+E76-F76 -> 96.9
A77: 42788 | D77: MULTA | E77: 85 | G77: =+G76+E77-F77 -> 181.9
A78: 42823 | D78: MULTA | E78: 85 | G78: =+G77+E78-F78 -> 266.9
A79: 43008 | B79: TARJETA | C79: SEPTIEMBRE | D79: G. ADM | F79: 60 | G79: =+G78+E79-F79 -> 206.9
A80: 43008 | B80: TARJETA | C80: SEPTIEMBRE | D80: P. SOCIAL | F80: 2 | G80: =+G79+E80-F80 -> 204.9
A81: 43049 | B81: 13960 | C81: SEPTIEMBRE | D81: LUZ | F81: 32.9 | G81: =+G80+E81-F81 -> 172
A82: 43049 | B82: 13960 | C82: SEPTIEMBRE | D82: AGUA | F82: 2 | G82: =+G81+E82-F82 -> 170
A83: 43067 | B83: EXONERACION | C83: 42788 | D83: MULTA | F83: 85 | G83: =+G82+E83-F83 -> 85
A84: 43067 | B84: EXONERACION | C84: 42823 | D84: MULTA | F84: 85 | G84: =+G83+E84-F84 -> 0
A85: 43039 | B85: POR COBRAR | C85: OCTUBRE | D85: LUZ | E85: 32.7 | G85: =+G84+E85-F85 -> 32.7
D86: AGUA | E86: 2 | G86: =+G85+E86-F86 -> 34.7
D87: G. ADM | E87: 60 | G87: =+G86+E87-F87 -> 94.7
D88: P. SOCIAL | E88: 2 | G88: =+G87+E88-F88 -> 96.7
A89: 43039 | B89: TARJETA | C89: OCTUBRE | D89: G. ADM | F89: 60 | G89: =+G88+E89-F89 -> 36.7
A90: 43039 | B90: TARJETA | C90: OCTUBRE | D90: P. SOCIAL | F90: 2 | G90: =+G89+E90-F90 -> 34.7
A91: 43063 | B91: 14080 | C91: OCTUBRE | D91: LUZ | F91: 32.7 | G91: =+G90+E91-F91 -> 2
A92: 43063 | B92: 14080 | C92: OCTUBRE | D92: AGUA | F92: 2 | G92: =+G91+E92-F92 -> 0
A93: 43069 | B93: POR COBRAR | C93: NOVIEMBRE | D93: LUZ | E93: 34.9 | G93: =+G92+E93-F93 -> 34.9
D94: AGUA | E94: 2 | G94: =+G93+E94-F94 -> 36.9
D95: G. ADM | E95: 60 | G95: =+G94+E95-F95 -> 96.9
D96: P. SOCIAL | E96: 2 | G96: =+G95+E96-F96 -> 98.9
D97: P. S X FALL. FLORES EMMA | E97: 10 | G97: =+G96+E97-F97 -> 108.9
A98: 43064 | B98: 14096 | C98: NOVIEMBRE | D98: P. S X FALL. FLORES EMMA | F98: 10 | G98: =+G97+E98-F98 -> 98.9
A99: 43069 | B99: TARJETA | C99: NOVIEMBRE | D99: G. ADM | F99: 60 | G99: =+G98+E99-F99 -> 38.9
A100: 43069 | B100: TARJETA | C100: NOVIEMBRE | D100: P. SOCIAL | F100: 2 | G100: =+G99+E100-F100 -> 36.9
A101: 43087 | B101: 14298 | C101: NOVIEMBRE | D101: LUZ | F101: 34.9 | G101: =+G100+E101-F101 -> 2
A102: 43087 | B102: 14298 | C102: NOVIEMBRE | D102: AGUA | F102: 2 | G102: =+G101+E102-F102 -> 7.1054274e-15
...

Sheet TITO JESUSA
B2: TITO FALCON JESUSA RICARDINA
A4: FECHA | B4: DOCUMENTO | C4: PERIODO | D4: CONCEPTO | E4: POR COBRAR | F4: PAGADO | G4: SALDO POR COBRAR
A5: 42736 | B5: SALDO AL 2016 | G5: 392
A6: 42740 | B6: 12069 | C6: A CUENTA 2016 | F6: 151.5 | G6: =+G5+E6-F6 -> 240.5
A7: 42773 | B7: 12924 | C7: A CUENTA 2016 | F7: 160.5 | G7: =+G6+E7-F7 -> 80
A8: 42947 | B8: 13291 | C8: A CUENTA 2016 | F8: 20 | G8: =+G7+E8-F8 -> 60
A9: 43068 | B9: 14178 | C9: CANCELACION 2016 | F9: 60 | G9: =+G8+E9-F9 -> 0
A10: 42766 | B10: POR COBRAR | C10: ENERO | D10: LUZ | E10: 150.7 | G10: =+G9+E10-F10 -> 150.7
D11: AGUA | E11: 35.5 | G11: =+G10+E11-F11 -> 186.2
D12: G. ADM | E12: 60 | G12: =+G11+E12-F12 -> 246.2
D13: P. SOCIAL | E13: 2 | G13: =+G12+E13-F13 -> 248.2
A14: 42766 | B14: TARJETA | C14: ENERO | D14: G. ADM | F14: 60 | G14: =+G13+E14-F14 -> 188.2
A15: 42766 | B15: TARJETA | C15: ENERO | D15: P. SOCIAL | F15: 2 | G15: =+G14+E15-F15 -> 186.2
A16: 42800 | B16: 12399 | C16: ENERO | D16: LUZ | F16: 150.7 | G16: =+G15+E16-F16 -> 35.5
A17: 42800 | B17: 12399 | C17: ENERO | D17: AGUA | F17: 35.5 | G17: =+G16+E17-F17 -> 0
A18: 42794 | B18: POR COBRAR | C18: FEBRERO | D18: LUZ | E18: 155.5 | G18: =+G17+E18-F18 -> 155.5
D19: AGUA | E19: 24.9 | G19: =+G18+E19-F19 -> 180.4
D20: G. ADM | E20: 56 | G20: =+G19+E20-F20 -> 236.4
D21: P. SOCIAL | E21: 2 | G21: =+G20+E21-F21 -> 238.4
D22: P.S. X FALLEC. | E22: 10 | G22: =+G21+E22-F22 -> 248.4
A23: 42794 | B23: TARJETA | C23: FEBRERO | D23: G. ADM | F23: 56 | G23: =+G22+E23-F23 -> 192.4
A24: 42794 | B24: TARJETA | C24: FEBRERO | D24: P. SOCIAL | F24: 2 | G24: =+G23+E24-F24 -> 190.4
A25: 42773 | B25: 12925 | C25: FEBRERO | D25: P.S. X FALLEC. | F25: 10 | G25: =+G24+E25-F25 -> 180.4
A26: 42822 | B26: 12606 | C26: FEBRERO | D26: LUZ | F26: 155.5 | G26: =+G25+E26-F26 -> 24.9
A27: 42822 | B27: 12606 | C27: FEBRERO | D27: AGUA | F27: 24.9 | G27: =+G26+E27-F27 -> 0
A28: 42825 | B28: POR COBRAR | C28: MARZO | D28: LUZ | E28: 133.4 | G28: =+G27+E28-F28 -> 133.4
D29: AGUA | E29: 25.8 | G29: =+G28+E29-F29 -> 159.2
D30: G. ADM | E30: 60 | G30: =+G29+E30-F30 -> 219.2
D31: P. SOCIAL | E31: 2 | G31: =+G30+E31-F31 -> 221.2
A32: 42824 | B32: TARJETA | C32: MARZO | D32: G. ADM | F32: 60 | G32: =+G31+E32-F32 -> 161.2
A33: 42854 | B33: TARJETA | C33: MARZO | D33: P. SOCIAL | F33: 2 | G33: =+G32+E33-F33 -> 159.2
A34: 42857 | B34: 12710 | C34: MARZO | D34: LUZ | F34: 133.4 | G34: =+G33+E34-F34 -> 25.8
A35: 42857 | B35: 12710 | C35: MARZO | D35: AGUA | F35: 25.8 | G35: =+G34+E35-F35 -> 0
A36: 42855 | B36: POR COBRAR | C36: ABRIL | D36: LUZ | E36: 135.6 | G36: =+G35+E36-F36 -> 135.6
D37: AGUA | E37: 25.4 | G37: =+G36+E37-F37 -> 161
D38: G. ADM | E38: 60 | G38: =+G37+E38-F38 -> 221
D39: P. SOCIAL | E39: 2 | G39: =+G38+E39-F39 -> 223
B40: TARJETA | C40: ABRIL | D40: G. ADM | F40: 60 | G40: =+G39+E40-F40 -> 163
B41: TARJETA | C41: ABRIL | D41: P. SOCIAL | F41: 2 | G41: =+G40+E41-F41 -> 161
A42: 42884 | B42: 12851 | C42: ABRIL | D42: LUZ | F42: 135.6 | G42: =+G41+E42-F42 -> 25.4
A43: 42884 | B43: 12851 | C43: ABRIL | D43: AGUA | F43: 25.4 | G43: =+G42+E43-F43 -> 0
A44: 42886 | B44: POR COBRAR | C44: MAYO | D44: LUZ | E44: 110 | G44: =+G43+E44-F44 -> 110
D45: AGUA | E45: 24.9 | G45: =+G44+E45-F45 -> 134.9
D46: G. ADM | E46: 60 | G46: =+G45+E46-F46 -> 194.9
D47: P. SOCIAL | E47: 2 | G47: =+G46+E47-F47 -> 196.9
A48: 42886 | B48: TARJETA | C48: MAYO | D48: G. ADM | F48: 60 | G48: =+G47+E48-F48 -> 136.9
A49: 42886 | B49: TARJETA | C49: MAYO | D49: P. SOCIAL | F49: 2 | G49: =+G48+E49-F49 -> 134.9
A50: 42906 | B50: 13111 | C50: MAYO | D50: LUZ | F50: 110 | G50: =+G49+E50-F50 -> 24.9
A51: 42906 | B51: 13111 | C51: MAYO | D51: AGUA | F51: 24.9 | G51: =+G50+E51-F51 -> 0
A52: 42916 | B52: POR COBRAR | C52: JUNIO | D52: LUZ | E52: 108.6 | G52: =+G51+E52-F52 -> 108.6
D53: AGUA | E53: 25.5 | G53: =+G52+E53-F53 -> 134.1
D54: G. ADM | E54: 60 | G54: =+G53+E54-F54 -> 194.1
D55: P. SOCIAL | E55: 2 | G55: =+G54+E55-F55 -> 196.1
A56: 42916 | B56: TARJETA | C56: JUNIO | D56: G. ADM | F56: 60 | G56: =+G55+E56-F56 -> 136.1
A57: 42916 | B57: TARJETA | C57: JUNIO | D57: P. SOCIAL | F57: 2 | G57: =+G56+E57-F57 -> 134.1
A58: 42947 | B58: 13291 | C58: JUNIO | D58: LUZ | F58: 108.6 | G58: =+G57+E58-F58 -> 25.5
A59: 42947 | B59: 13291 | C59: JUNIO | D59: AGUA | F59: 25.5 | G59: =+G58+E59-F59 -> 0
A60: 42947 | B60: POR COBRAR | C60: JULIO | D60: LUZ | E60: 109.9 | G60: =+G59+E60-F60 -> 109.9
D61: AGUA | E61: 25 | G61: =+G60+E61-F61 -> 134.9
D62: G. ADM | E62: 60 | G62: =+G61+E62-F62 -> 194.9
D63: P. SOCIAL | E63: 2 | G63: =+G62+E63-F63 -> 196.9
A64: 42947 | B64: TARJETA | C64: JULIO | D64: G. ADM | F64: 60 | G64: =+G63+E64-F64 -> 136.9
A65: 3107 | B65: TARJETA | C65: JULIO | D65: P. SOCIAL | F65: 2 | G65: =+G64+E65-F65 -> 134.9
A66: 42971 | B66: 13473 | C66: JULIO | D66: LUZ | F66: 109.9 | G66: =+G65+E66-F66 -> 25
A67: 42971 | B67: 13473 | C67: JULIO | D67: AGUA | F67: 25 | G67: =+G66+E67-F67 -> 0
A68: 42978 | B68: POR COBRAR | C68: AGOSTO | D68: LUZ | E68: 109.9 | G68: =+G67+E68-F68 -> 109.9
D69: AGUA | E69: 25 | G69: =+G68+E69-F69 -> 134.9
D70: G. ADM | E70: 60 | G70: =+G69+E70-F70 -> 194.9
D71: P. SOCIAL | E71: 2 | G71: =+G70+E71-F71 -> 196.9
D72: MULTA | E72: 85 | G72: =+G71+E72-F72 -> 281.9
A73: 42978 | B73: TARJETA | C73: AGOSTO | D73: G. ADM | F73: 60 | G73: =+G72+E73-F73 -> 221.9
A74: 42978 | B74: TARJETA | C74: AGOSTO | D74: P. SOCIAL | F74: 2 | G74: =+G73+E74-F74 -> 219.9
A75: 43004 | B75: 13679 | C75: AGOSTO | D75: LUZ | F75: 109.9 | G75: =+G74+E75-F75 -> 110
A76: 43004 | B76: 13679 | C76: AGOSTO | D76: AGUA | F76: 25 | G76: =+G75+E76-F76 -> 85
A77: 43001 | B77: 22-2017 | C77: AGOSTO | D77: MULTA | F77: 85 | G77: =+G76+E77-F77 -> 0
A78: 43008 | B78: POR COBRAR | C78: SEPTIEMBRE | D78: LUZ | E78: 101.9 | G78: =+G77+E78-F78 -> 101.9
D79: AGUA | E79: 16.4 | G79: =+G78+E79-F79 -> 118.3
D80: G. ADM | E80: 60 | G80: =+G79+E80-F80 -> 178.3
D81: P. SOCIAL | E81: 2 | G81: =+G80+E81-F81 -> 180.3
A82: 42788 | D82: MULTA | E82: 85 | G82: =+G81+E82-F82 -> 265.3
A83: 42823 | D83: MULTA | E83: 85 | G83: =+G82+E83-F83 -> 350.3
A84: 43008 | B84: TARJETA | C84: SEPTIEMBRE | D84: G. ADM | F84: 60 | G84: =+G83+E84-F84 -> 290.3
A85: 43008 | B85: TARJETA | C85: SEPTIEMBRE | D85: P. SOCIAL | F85: 2 | G85: =+G84+E85-F85 -> 288.3
A86: 43028 | B86: 13842 | C86: SEPTIEMBRE | D86: LUZ | F86: 101.9 | G86: =+G85+E86-F86 -> 186.4
A87: 43028 | B87: 13842 | C87: SEPTIEMBRE | D87: AGUA | F87: 16.4 | G87: =+G86+E87-F87 -> 170
A88: 43067 | B88: EXONERACION | C88: 42788 | D88: MULTA | F88: 85 | G88: =+G87+E88-F88 -> 85
A89: 43067 | B89: EXONERACION | C89: 42823 | D89: MULTA | F89: 85 | G89: =+G88+E89-F89 -> 0
A90: 43039 | B90: POR COBRAR | C90: OCTUBRE | D90: LUZ | E90: 102 | G90: =+G89+E90-F90 -> 102
D91: AGUA | E91: 24.9 | G91: =+G90+E91-F91 -> 126.9
D92: G. ADM | E92: 60 | G92: =+G91+E92-F92 -> 186.9
D93: P. SOCIAL | E93: 2 | G93: =+G92+E93-F93 -> 188.9
D94: FUMIGACION | E94: 10 | G94: =+G93+E94-F94 -> 198.9
A95: 43039 | B95: TARJETA | C95: OCTUBRE | D95: G. ADM | F95: 60 | G95: =+G94+E95-F95 -> 138.9
A96: 43039 | B96: TARJETA | C96: OCTUBRE | D96: P. SOCIAL | F96: 2 | G96: =+G95+E96-F96 -> 136.9
A97: 43064 | B97: 14097 | C97: OCTUBRE | D97: LUZ | F97: 102 | G97: =+G96+E97-F97 -> 34.9
A98: 43064 | B98: 14097 | C98: OCTUBRE | D98: AGUA | F98: 24.9 | G98: =+G97+E98-F98 -> 10
A99: 42921 | B99: 5665 | C99: OCTUBRE | D99: FUMIGACION | F99: 10 | G99: =+G98+E99-F99 -> 0
A100: 43069 | B100: POR COBRAR | C100: NOVIEMBRE | D100: LUZ | E100: 108.9 | G100: =+G99+E100-F100 -> 108.9
D101: AGUA | E101: 24.9 | G101: =+G100+E101-F101 -> 133.8
D102: G. ADM | E102: 60 | G102: =+G101+E102-F102 -> 193.8
...

Sheet TORRES MARCELINO
B2: TORRES ANYOSA MARCELINO
A4: FECHA | B4: DOCUMENTO | C4: PERIODO | D4: CONCEPTO | E4: POR COBRAR | F4: PAGADO | G4: SALDO POR COBRAR
A5: 42736 | B5: SALDO AL 2016 | G5: 669.2
A6: 42885 | B6: 12895 | C6: A CUENTA 2016 | F6: 175.2 | G6: =+G5+E6-F6 -> 494
A7: 43388 | B7: 16312 | C7: CANCELACION | F7: 494 | G7: =+G6+E7-F7 -> 0
A8: 42766 | B8: POR COBRAR | C8: ENERO | D8: LUZ | E8: 86.5 | G8: =+G7+E8-F8 -> 86.5
D9: AGUA | E9: 2.7 | G9: =+G8+E9-F9 -> 89.2
D10: G. ADM | E10: 60 | G10: =+G9+E10-F10 -> 149.2
D11: P. SOCIAL | E11: 2 | G11: =+G10+E11-F11 -> 151.2
D12: DEPOSITO | E12: 90 | G12: =+G11+E12-F12 -> 241.2
A13: 42885 | B13: 12895 | C13: ENERO | D13: AGUA | F13: 2.7 | G13: =+G12+E13-F13 -> 238.5
A14: 42885 | B14: 12895 | C14: ENERO | D14: LUZ | F14: 86.5 | G14: =+G13+E14-F14 -> 152
A15: 43388 | B15: 16312 | C15: ENERO | D15: G. ADM | F15: 60 | G15: =+G14+E15-F15 -> 92
A16: 43388 | B16: 16312 | C16: ENERO | D16: P. SOCIAL | F16: 2 | G16: =+G15+E16-F16 -> 90
A17: 43388 | B17: 16312 | C17: ENERO | D17: DEPOSITO | F17: 90 | G17: =+G16+E17-F17 -> 0
A18: 42794 | B18: POR COBRAR | C18: FEBRERO | D18: LUZ | E18: 88.9 | G18: =+G17+E18-F18 -> 88.9
D19: AGUA | E19: 2 | G19: =+G18+E19-F19 -> 90.9 | R19: 53.8
D20: G. ADM | E20: 56 | G20: =+G19+E20-F20 -> 146.9 | R20: 10.4
D21: P. SOCIAL | E21: 2 | G21: =+G20+E21-F21 -> 148.9
D22: MULTA | E22: 85 | G22: =+G21+E22-F22 -> 233.9
D23: DEPOSITO | E23: 90 | G23: =+G22+E23-F23 -> 323.9
A24: 42885 | B24: 12895 | C24: FEBRERO | D24: AGUA | F24: 2 | G24: =+G23+E24-F24 -> 321.9
A25: 42885 | B25: 12895 | C25: FEBRERO | D25: LUZ | F25: 88.9 | G25: =+G24+E25-F25 -> 233
A26: 43388 | B26: 16312 | C26: FEBRERO | D26: G. ADM | F26: 56 | G26: =+G25+E26-F26 -> 177
A27: 43388 | B27: 16312 | C27: FEBRERO | D27: P. SOCIAL | F27: 2 | G27: =+G26+E27-F27 -> 175
A28: 43388 | B28: 16312 | C28: FEBRERO | D28: DEPOSITO | F28: 90 | G28: =+G27+E28-F28 -> 85
A29: 43388 | B29: 16312 | C29: FEBRERO | D29: MULTA | F29: 85 | G29: =+G28+E29-F29 -> 0
A30: 42825 | B30: POR COBRAR | C30: MARZO | D30: LUZ | E30: 94.3 | G30: =+G29+E30-F30 -> 94.3
D31: AGUA | E31: 2 | G31: =+G30+E31-F31 -> 96.3
D32: G. ADM | E32: 60 | G32: =+G31+E32-F32 -> 156.3
D33: P. SOCIAL | E33: 2 | G33: =+G32+E33-F33 -> 158.3
D34: DEPOSITO | E34: 90 | G34: =+G33+E34-F34 -> 248.3
A35: 42885 | B35: 12895 | C35: MARZO | D35: AGUA | F35: 2 | G35: =+G34+E35-F35 -> 246.3
A36: 42885 | B36: 12895 | C36: MARZO | D36: LUZ | F36: 94.3 | G36: =+G35+E36-F36 -> 152
A37: 43388 | B37: 16313 | C37: MARZO | D37: G. ADM | F37: 60 | G37: =+G36+E37-F37 -> 92
A38: 43388 | B38: 16313 | C38: MARZO | D38: P. SOCIAL | F38: 2 | G38: =+G37+E38-F38 -> 90
A39: 43388 | B39: 16313 | C39: MARZO | D39: DEPOSITO | F39: 90 | G39: =+G38+E39-F39 -> 0
A40: 42855 | B40: POR COBRAR | C40: ABRIL | D40: LUZ | E40: 97 | G40: =+G39+E40-F40 -> 97
D41: AGUA | E41: 2 | G41: =+G40+E41-F41 -> 99
D42: G. ADM | E42: 60 | G42: =+G41+E42-F42 -> 159
D43: P. SOCIAL | E43: 2 | G43: =+G42+E43-F43 -> 161
D44: RECONEXION | E44: 60 | G44: =+G43+E44-F44 -> 221
D45: DEPOSITO | E45: 90 | G45: =+G44+E45-F45 -> 311
A46: 42885 | B46: 12895 | C46: ABRIL | D46: AGUA | F46: 2 | G46: =+G45+E46-F46 -> 309
A47: 42885 | B47: 12895 | C47: ABRIL | D47: RECONEXION | F47: 60 | G47: =+G46+E47-F47 -> 249
A48: 42885 | B48: 12895 | C48: ABRIL | D48: LUZ | F48: 97 | G48: =+G47+E48-F48 -> 152
A49: 43388 | B49: 16313 | C49: ABRIL | D49: G. ADM | F49: 60 | G49: =+G48+E49-F49 -> 92
A50: 43388 | B50: 16313 | C50: ABRIL | D50: P. SOCIAL | F50: 2 | G50: =+G49+E50-F50 -> 90
A51: 43388 | B51: 16313 | C51: ABRIL | D51: DEPOSITO | F51: 90 | G51: =+G50+E51-F51 -> 0
A52: 42886 | B52: POR COBRAR | C52: MAYO | D52: LUZ | E52: 71.5 | G52: =+G51+E52-F52 -> 71.5
D53: AGUA | E53: 2 | G53: =+G52+E53-F53 -> 73.5
D54: G. ADM | E54: 60 | G54: =+G53+E54-F54 -> 133.5
D55: P. SOCIAL | E55: 2 | G55: =+G54+E55-F55 -> 135.5
D56: DEPOSITO | E56: 90 | G56: =+G55+E56-F56 -> 225.5
A57: 42985 | B57: 13520 | C57: MAYO | D57: LUZ | F57: 71.5 | G57: =+G56+E57-F57 -> 154
A58: 42985 | B58: 13520 | C58: MAYO | D58: AGUA | F58: 2 | G58: =+G57+E58-F58 -> 152
A59: 43388 | B59: 16313 | C59: MAYO | D59: G. ADM | F59: 60 | G59: =+G58+E59-F59 -> 92
A60: 43388 | B60: 16313 | C60: MAYO | D60: P. SOCIAL | F60: 2 | G60: =+G59+E60-F60 -> 90
A61: 43388 | B61: 16313 | C61: MAYO | D61: DEPOSITO | F61: 90 | G61: =+G60+E61-F61 -> 0
A62: 42916 | B62: POR COBRAR | C62: JUNIO | D62: LUZ | E62: 70.2 | G62: =+G61+E62-F62 -> 70.2
D63: AGUA | E63: 2 | G63: =+G62+E63-F63 -> 72.2
D64: G. ADM | E64: 60 | G64: =+G63+E64-F64 -> 132.2
D65: P. SOCIAL | E65: 2 | G65: =+G64+E65-F65 -> 134.2
D66: DEPOSITO | E66: 90 | G66: =+G65+E66-F66 -> 224.2
A67: 42985 | B67: 13520 | C67: JUNIO | D67: LUZ | F67: 70.2 | G67: =+G66+E67-F67 -> 154
A68: 42985 | B68: 13520 | C68: JUNIO | D68: AGUA | F68: 2 | G68: =+G67+E68-F68 -> 152
A69: 43388 | B69: 16314 | C69: JUNIO | D69: DEPOSITO | F69: 80 | G69: =+G68+E69-F69 -> 72
A70: 43470 | B70: 16834 | C70: JUNIO | D70: G. ADM | F70: 60 | G70: =+G69+E70-F70 -> 12
A71: 43470 | B71: 16834 | C71: JUNIO | D71: P. SOCIAL | F71: 2 | G71: =+G70+E71-F71 -> 10
A72: 43470 | B72: 16834 | C72: JUNIO | D72: DEPOSITO | F72: 10 | G72: =+G71+E72-F72 -> 0
A73: 42947 | B73: POR COBRAR | C73: JULIO | D73: LUZ | E73: 65.1 | G73: =+G72+E73-F73 -> 65.1
D74: AGUA | E74: 2 | G74: =+G73+E74-F74 -> 67.1
D75: G. ADM | E75: 60 | G75: =+G74+E75-F75 -> 127.1
D76: P. SOCIAL | E76: 2 | G76: =+G75+E76-F76 -> 129.1
D77: DEPOSITO | E77: 90 | G77: =+G76+E77-F77 -> 219.1
A78: 42985 | B78: 13520 | C78: JULIO | D78: LUZ | F78: 65.1 | G78: =+G77+E78-F78 -> 154
A79: 42985 | B79: 13520 | C79: JULIO | D79: AGUA | F79: 2 | G79: =+G78+E79-F79 -> 152
A80: 43470 | B80: 16834 | C80: JULIO | D80: G. ADM | F80: 60 | G80: =+G79+E80-F80 -> 92
A81: 43470 | B81: 16834 | C81: JULIO | D81: P. SOCIAL | F81: 2 | G81: =+G80+E81-F81 -> 90
A82: 43470 | B82: 16834 | C82: JULIO | D82: DEPOSITO | F82: 90 | G82: =+G81+E82-F82 -> 0
A83: 42978 | B83: POR COBRAR | C83: AGOSTO | D83: LUZ | E83: 65.1 | G83: =+G82+E83-F83 -> 65.1
D84: AGUA | E84: 2 | G84: =+G83+E84-F84 -> 67.1
D85: G. ADM | E85: 60 | G85: =+G84+E85-F85 -> 127.1
D86: P. SOCIAL | E86: 2 | G86: =+G85+E86-F86 -> 129.1
D87: DEPOSITO | E87: 90 | G87: =+G86+E87-F87 -> 219.1
D88: MULTA | E88: 85 | G88: =+G87+E88-F88 -> 304.1
A89: 43063 | B89: 14084 | C89: AGOSTO | D89: LUZ | F89: 52 | G89: =+G88+E89-F89 -> 252.1
A90: 43063 | B90: 14084 | C90: AGOSTO | D90: AGUA | F90: 2 | G90: =+G89+E90-F90 -> 250.1
A91: 43236 | B91: 15317 | C91: AGOSTO | D91: LUZ | F91: 13.1 | G91: =+G90+E91-F91 -> 237
A92: 43470 | B92: 16834 | C92: AGOSTO | D92: G. ADM | F92: 60 | G92: =+G91+E92-F92 -> 177
A93: 43470 | B93: 16834 | C93: AGOSTO | D93: P. SOCIAL | F93: 2 | G93: =+G92+E93-F93 -> 175
A94: 43470 | B94: 16834 | C94: AGOSTO | D94: DEPOSITO | F94: 90 | G94: =+G93+E94-F94 -> 85
A95: 43470 | B95: 16834 | C95: AGOSTO | D95: MULTA | F95: 85 | G95: =+G94+E95-F95 -> 0
A96: 43008 | B96: POR COBRAR | C96: SEPTIEMBRE | D96: LUZ | E96: 52.2 | G96: =+G95+E96-F96 -> 52.2
D97: AGUA | E97: 2 | G97: =+G96+E97-F97 -> 54.2
D98: G. ADM | E98: 60 | G98: =+G97+E98-F98 -> 114.2
D99: P. SOCIAL | E99: 2 | G99: =+G98+E99-F99 -> 116.2
D100: DEPOSITO | E100: 90 | G100: =+G99+E100-F100 -> 206.2
A101: 42823 | D101: MULTA | E101: 85 | G101: =+G100+E101-F101 -> 291.2
A102: 43236 | B102: 15317 | C102: SEPTIEMBRE | D102: LUZ | F102: 52.2 | G102: =+G101+E102-F102 -> 239
...

Sheet TORRES FRANCISCO
B2: TORRES ASTO FRANCISCO
A4: FECHA | B4: DOCUMENTO | C4: PERIODO | D4: CONCEPTO | E4: POR COBRAR | F4: PAGADO | G4: SALDO POR COBRAR
A5: 42736 | B5: SALDO AL 2016 | G5: 206.9
A6: 42758 | B6: 12145 | C6: A CUENTA 2016 | F6: 146.9 | G6: =+G5+E6-F6 -> 60
A7: 42787 | B7: 12313 | C7: A CUENTA 2016 | F7: 20 | G7: =+G6+E7-F7 -> 40
A8: 42821 | B8: 12540 | C8: A CUENTA 2016 | F8: 20 | G8: =+G7+E8-F8 -> 20
A9: 42852 | B9: 12706 | C9: CANCELADO | F9: 20 | G9: =+G8+E9-F9 -> 0
A10: 42766 | B10: POR COBRAR | C10: ENERO | D10: LUZ | E10: 81.5 | G10: =+G9+E10-F10 -> 81.5
D11: AGUA | E11: 44.6 | G11: =+G10+E11-F11 -> 126.1
D12: G. ADM | E12: 60 | G12: =+G11+E12-F12 -> 186.1
D13: P. SOCIAL | E13: 2 | G13: =+G12+E13-F13 -> 188.1
A14: 42766 | B14: TARJETA | C14: ENERO | D14: G. ADM | F14: 22 | G14: =+G13+E14-F14 -> 166.1
A15: 42787 | B15: 12313 | C15: ENERO | D15: G. ADM | F15: 38 | G15: =+G14+E15-F15 -> 128.1
A16: 42787 | B16: 12313 | C16: ENERO | D16: P. SOCIAL | F16: 2 | G16: =+G15+E16-F16 -> 126.1
A17: 42787 | B17: 12313 | C17: ENERO | D17: LUZ | F17: 81.5 | G17: =+G16+E17-F17 -> 44.6
A18: 42787 | B18: 12313 | C18: ENERO | D18: AGUA | F18: 44.6 | G18: =+G17+E18-F18 -> 0
A19: 42794 | B19: POR COBRAR | C19: FEBRERO | D19: LUZ | E19: 100.3 | G19: =+G18+E19-F19 -> 100.3
D20: AGUA | E20: 31 | G20: =+G19+E20-F20 -> 131.3
D21: G. ADM | E21: 56 | G21: =+G20+E21-F21 -> 187.3
D22: P. SOCIAL | E22: 2 | G22: =+G21+E22-F22 -> 189.3
A23: 42821 | B23: 12540 | C23: FEBRERO | D23: G. ADM | F23: 56 | G23: =+G22+E23-F23 -> 133.3
A24: 42821 | B24: 12540 | C24: FEBRERO | D24: P. SOCIAL | F24: 2 | G24: =+G23+E24-F24 -> 131.3
A25: 42821 | B25: 12540 | C25: FEBRERO | D25: LUZ | F25: 100.3 | G25: =+G24+E25-F25 -> 31
A26: 42821 | B26: 12540 | C26: FEBRERO | D26: AGUA | F26: 31 | G26: =+G25+E26-F26 -> 0
A27: 42825 | B27: POR COBRAR | C27: MARZO | D27: LUZ | E27: 96.1 | G27: =+G26+E27-F27 -> 96.1
D28: AGUA | E28: 32.5 | G28: =+G27+E28-F28 -> 128.6
D29: G. ADM | E29: 60 | G29: =+G28+E29-F29 -> 188.6
D30: P. SOCIAL | E30: 2 | G30: =+G29+E30-F30 -> 190.6
A31: 42824 | B31: TARJETA | C31: MARZO | D31: G. ADM | F31: 60 | G31: =+G30+E31-F31 -> 130.6
A32: 42824 | B32: TARJETA | C32: MARZO | D32: P. SOCIAL | F32: 2 | G32: =+G31+E32-F32 -> 128.6
A33: 42852 | B33: 12704 | C33: MARZO | D33: LUZ | F33: 96.1 | G33: =+G32+E33-F33 -> 32.5
A34: 42852 | B34: 12704 | C34: MARZO | D34: AGUA | F34: 32.5 | G34: =+G33+E34-F34 -> 0
A35: 42855 | B35: POR COBRAR | C35: ABRIL | D35: LUZ | E35: 97.9 | G35: =+G34+E35-F35 -> 97.9
D36: AGUA | E36: 31.9 | G36: =+G35+E36-F36 -> 129.8
D37: G. ADM | E37: 60 | G37: =+G36+E37-F37 -> 189.8
D38: P. SOCIAL | E38: 2 | G38: =+G37+E38-F38 -> 191.8
A39: 42885 | B39: 12860 | C39: ABRIL | D39: LUZ | F39: 97.9 | G39: =+G38+E39-F39 -> 93.9
A40: 42885 | B40: 12860 | C40: ABRIL | D40: AGUA | F40: 31.9 | G40: =+G39+E40-F40 -> 62
A41: 42885 | B41: 12860 | C41: ABRIL | D41: G. ADM | F41: 60 | G41: =+G40+E41-F41 -> 2
A42: 42885 | B42: 12860 | C42: ABRIL | D42: P. SOCIAL | F42: 2 | G42: =+G41+E42-F42 -> 7.1054274e-15
A43: 42886 | B43: POR COBRAR | C43: MAYO | D43: LUZ | E43: 71.4 | G43: =+G42+E43-F43 -> 71.4
D44: AGUA | E44: 31.2 | G44: =+G43+E44-F44 -> 102.6
D45: G. ADM | E45: 60 | G45: =+G44+E45-F45 -> 162.6
D46: P. SOCIAL | E46: 2 | G46: =+G45+E46-F46 -> 164.6
A47: 42886 | B47: TARJETA | C47: MAYO | D47: G. ADM | F47: 60 | G47: =+G46+E47-F47 -> 104.6
A48: 42886 | B48: TARJETA | C48: MAYO | D48: P. SOCIAL | F48: 2 | G48: =+G47+E48-F48 -> 102.6
A49: 42913 | B49: 13160 | C49: MAYO | D49: LUZ | F49: 71.4 | G49: =+G48+E49-F49 -> 31.2
A50: 42913 | B50: 13160 | C50: MAYO | D50: AGUA | F50: 31.2 | G50: =+G49+E50-F50 -> 0
A51: 42916 | B51: POR COBRAR | C51: JUNIO | D51: LUZ | E51: 69.8 | G51: =+G50+E51-F51 -> 69.8
D52: AGUA | E52: 40.5 | G52: =+G51+E52-F52 -> 110.3
D53: G. ADM | E53: 60 | G53: =+G52+E53-F53 -> 170.3
D54: P. SOCIAL | E54: 2 | G54: =+G53+E54-F54 -> 172.3
A55: 42950 | B55: 13391 | C55: JUNIO | D55: G. ADM | F55: 60 | G55: =+G54+E55-F55 -> 112.3
A56: 42950 | B56: 13391 | C56: JUNIO | D56: P. SOCIAL | F56: 2 | G56: =+G55+E56-F56 -> 110.3
A57: 42950 | B57: 13391 | C57: JUNIO | D57: LUZ | F57: 69.8 | G57: =+G56+E57-F57 -> 40.5
A58: 42950 | B58: 13391 | C58: JUNIO | D58: AGUA | F58: 40.5 | G58: =+G57+E58-F58 -> 0
A59: 42947 | B59: POR COBRAR | C59: JULIO | D59: LUZ | E59: 58.1 | G59: =+G58+E59-F59 -> 58.1
D60: AGUA | E60: 31 | G60: =+G59+E60-F60 -> 89.1
D61: G. ADM | E61: 60 | G61: =+G60+E61-F61 -> 149.1
D62: P. SOCIAL | E62: 2 | G62: =+G61+E62-F62 -> 151.1
A63: 42947 | B63: TARJETA | C63: JULIO | D63: G. ADM | F63: 60 | G63: =+G62+E63-F63 -> 91.1
A64: 42947 | B64: TARJETA | C64: JULIO | D64: P. SOCIAL | F64: 2 | G64: =+G63+E64-F64 -> 89.1
A65: 43020 | B65: 13816 | C65: JULIO | D65: LUZ | F65: 58.1 | G65: =+G64+E65-F65 -> 31
A66: 43020 | B66: 13816 | C66: JULIO | D66: AGUA | F66: 31 | G66: =+G65+E66-F66 -> 0
A67: 42978 | B67: POR COBRAR | C67: AGOSTO | D67: LUZ | E67: 58.1 | G67: =+G66+E67-F67 -> 58.1
D68: AGUA | E68: 31 | G68: =+G67+E68-F68 -> 89.1
D69: G. ADM | E69: 60 | G69: =+G68+E69-F69 -> 149.1
D70: P. SOCIAL | E70: 2 | G70: =+G69+E70-F70 -> 151.1
A71: 42978 | B71: TARJETA | C71: AGOSTO | D71: G. ADM | F71: 8 | G71: =+G70+E71-F71 -> 143.1
A72: 43020 | B72: 13816 | C72: AGOSTO | D72: G. ADM | F72: 52 | G72: =+G71+E72-F72 -> 91.1
A73: 43020 | B73: 13816 | C73: AGOSTO | D73: P. SOCIAL | F73: 2 | G73: =+G72+E73-F73 -> 89.1
A74: 43020 | B74: 13816 | C74: AGOSTO | D74: LUZ | F74: 58.1 | G74: =+G73+E74-F74 -> 31
A75: 43020 | B75: 13816 | C75: AGOSTO | D75: AGUA | F75: 31 | G75: =+G74+E75-F75 -> 0
A76: 43008 | B76: POR COBRAR | C76: SEPTIEMBRE | D76: LUZ | E76: 66.7 | G76: =+G75+E76-F76 -> 66.7
D77: AGUA | E77: 31.2 | G77: =+G76+E77-F77 -> 97.9
D78: G. ADM | E78: 60 | G78: =+G77+E78-F78 -> 157.9
D79: P. SOCIAL | E79: 2 | G79: =+G78+E79-F79 -> 159.9
A80: 43008 | B80: TARJETA | C80: SEPTIEMBRE | D80: G. ADM | F80: 60 | G80: =+G79+E80-F80 -> 99.9
A81: 43008 | B81: TARJETA | C81: SEPTIEMBRE | D81: P. SOCIAL | F81: 2 | G81: =+G80+E81-F81 -> 97.9
A82: 43050 | B82: 13967 | C82: SEPTIEMBRE | D82: LUZ | F82: 66.7 | G82: =+G81+E82-F82 -> 31.2
A83: 43050 | B83: 13967 | C83: SEPTIEMBRE | D83: AGUA | F83: 31.2 | G83: =+G82+E83-F83 -> 0
A84: 43039 | B84: POR COBRAR | C84: OCTUBRE | D84: LUZ | E84: 73.1 | G84: =+G83+E84-F84 -> 73.1
D85: AGUA | E85: 31.3 | G85: =+G84+E85-F85 -> 104.4
D86: G. ADM | E86: 60 | G86: =+G85+E86-F86 -> 164.4
D87: P. SOCIAL | E87: 2 | G87: =+G86+E87-F87 -> 166.4
D88: FUMIGACION | E88: 10 | G88: =+G87+E88-F88 -> 176.4
A89: 43039 | B89: TARJETA | C89: OCTUBRE | D89: G. ADM | F89: 54 | G89: =+G88+E89-F89 -> 122.4
A90: 43050 | B90: 13967 | C90: OCTUBRE | D90: G. ADM | F90: 6 | G90: =+G89+E90-F90 -> 116.4
A91: 43050 | B91: 13967 | C91: OCTUBRE | D91: P. SOCIAL | F91: 2 | G91: =+G90+E91-F91 -> 114.4
A92: 43064 | B92: 14087 | C92: OCTUBRE | D92: LUZ | F92: 73.1 | G92: =+G91+E92-F92 -> 41.3
A93: 43064 | B93: 14087 | C93: OCTUBRE | D93: AGUA | F93: 31.3 | G93: =+G92+E93-F93 -> 10
A94: 42921 | B94: 5718 | C94: OCTUBRE | D94: FUMIGACION | F94: 10 | G94: =+G93+E94-F94 -> -1.7763568e-14
A95: 43069 | B95: POR COBRAR | C95: NOVIEMBRE | D95: LUZ | E95: 78.1 | G95: =+G94+E95-F95 -> 78.1
D96: AGUA | E96: 31.2 | G96: =+G95+E96-F96 -> 109.3
D97: G. ADM | E97: 60 | G97: =+G96+E97-F97 -> 169.3
D98: P. SOCIAL | E98: 2 | G98: =+G97+E98-F98 -> 171.3
A99: 43064 | B99: 14087 | C99: NOVIEMBRE | D99: G. ADM | F99: 46 | G99: =+G98+E99-F99 -> 125.3
A100: 43064 | B100: 14087 | C100: NOVIEMBRE | D100: P. SOCIAL | F100: 2 | G100: =+G99+E100-F100 -> 123.3
A101: 43089 | B101: 14330 | C101: NOVIEMBRE | D101: LUZ | F101: 78.1 | G101: =+G100+E101-F101 -> 45.2
A102: 43089 | B102: 14330 | C102: NOVIEMBRE | D102: AGUA | F102: 31.2 | G102: =+G101+E102-F102 -> 14
...

Sheet TORRES NERY(F)
B2: TORRES ASTO NERY (F)
A4: FECHA | B4: DOCUMENTO | C4: PERIODO | D4: CONCEPTO | E4: POR COBRAR | F4: PAGADO | G4: SALDO POR COBRAR
A5: 42736 | B5: SALDO AL 2016 | G5: 2767.1
A6: 42760 | B6: TARJETA | C6: A CUENTA 2016 | F6: 100 | G6: =+G5+E6-F6 -> 2667.1
A7: 42794 | B7: TARJETA | C7: A CUENTA 2016 | F7: 50 | G7: =+G6+E7-F7 -> 2617.1
A8: 42821 | B8: TARJETA | C8: A CUENTA 2016 | F8: 30 | G8: =+G7+E8-F8 -> 2587.1
A9: 42830 | B9: TARJETA | C9: A CUENTA 2016 | F9: 10 | G9: =+G8+E9-F9 -> 2577.1
A10: 42916 | B10: TARJETA | C10: A CUENTA 2016 | F10: 90 | G10: =+G9+E10-F10 -> 2487.1
A11: 42942 | B11: TARJETA | C11: A CUENTA 2016 | F11: 100 | G11: =+G10+E11-F11 -> 2387.1
A12: 42978 | B12: TARJETA | C12: A CUENTA 2016 | F12: 30 | G12: =+G11+E12-F12 -> 2357.1
A13: 43108 | B13: 14410 | C13: A CUENTA 2016 | F13: 128.3 | G13: =+G12+E13-F13 -> 2228.8
