Workbook

Sheet 01-04-2026
A1: INGRESOS DEL DIA 01-04-2026
A3: INQUILINO | B3: COMPROBANTE | C3: DETALLE | D3: LUZ | E3: AGUA | F3: ALQUILER | G3: ESPACIO | H3: PARQUEO | I3: TICKET | J3: TOTAL
A4: JOSE | B4: TK 50817 | C4: 46113 | I4: 10 | J4: =SUM(D4:I4) -> 10
J5: =SUM(D5:I5) -> 0
A6: SEVEN DAYS CORPORATION S.A.C. | B6: E001-356 | C6: 46113 | G6: 60 | J6: =SUM(D6:I6) -> 60
A7: ARGUELLO MANZANILLA NARCYS ALEXANDER | B7: E001-357 | C7: 46082 | F7: 130 | J7: =SUM(D7:I7) -> 130
J8: =SUM(D8:I8) -> 0
A9: MARI SOL QUISPE CHAVEZ | B9: EB01-7111 | C9: 46054 | F9: 100 | J9: =SUM(D9:I9) -> 100
A10: DIANA ZENAIDA SANCHEZ PRADO | B10: EB01-7112 | C10: 46082 | F10: 1000 | J10: =SUM(D10:I10) -> 1000
A11: ANATOLIA CHIPANA DE VARGAS | B11: EB01-7113 | C11: 46082 | F11: 200 | J11: =SUM(D11:I11) -> 200
A12: JANETT CONSUELO CASTRO RODRIGUEZ | B12: EB01-7114 | C12: 46023 | F12: 150 | J12: =SUM(D12:I12) -> 150
A13: DOMINICA LUCIANA FLORES LAREDO | B13: EB01-7115 | C13: 46023 | F13: 100 | J13: =SUM(D13:I13) -> 100
C14: 46054 | F14: 100 | J14: =SUM(D14:I14) -> 100
A15: MARY CRISPIN FLORES | B15: EB01-7116 | C15: 46113 | G15: 30 | J15: =SUM(D15:I15) -> 30
A16: PARQUEO | B16: EB01-7119 | C16: 46113 | J16: =SUM(D16:I16) -> 0
H17: 72.5 | J17: =SUM(D17:I17) -> 72.5
J18: =SUM(D18:I18) -> 0
J19: =SUM(D19:I19) -> 0
J20: =SUM(D20:I20) -> 0
J21: =SUM(D21:I21) -> 0
J22: =SUM(D22:I22) -> 0
J23: =SUM(D23:I23) -> 0
A24: TOTAL | D24: =SUM(D4:D23) -> 0 | E24: =SUM(E4:E23) -> 0 | F24: =SUM(F4:F23) -> 1780 | G24: =SUM(G4:G23) -> 90 | H24: =SUM(H4:H23) -> 72.5 | I24: =SUM(I4:I23) -> 10 | J24: =SUM(J4:J23) -> 1952.5
A26: BBVA
A27: INQUILINOS | B27: COMPROBANTE | C27: DETALLE | D27: LUZ | E27: AGUA | F27: ALQUILER | G27: ESPACIO | H27: DEPOSITO | I27: TICKET | J27: TOTAL
A28: SAYDA YUPANQUI QUISPE | B28: EB01-7117 | C28: 46082 | F28: 500 | J28: =SUM(D28:I28) -> 500
J29: =SUM(D29:I29) -> 0
J30: =SUM(D30:I30) -> 0
J31: =SUM(D31:I31) -> 0 | L31: TOTAL QR | M31: =J32+J40 -> 500
A32: TOTAL | J32: =SUM(J28:J31) -> 500
A34: BBVA
A35: SOCIOS | B35: RECIBO DE SERVICIO | C35: DETALLE | D35: LUZ | E35: AGUA | F35: G. ADM | G35: P. SOCIAL | H35: DEPOSITO | I35: P.S X FALLECIMIENTO | J35: TOTAL
J36: =SUM(D36:I36) -> 0
J37: =SUM(D37:I37) -> 0
J38: =SUM(D38:I38) -> 0
J39: =SUM(D39:I39) -> 0
A40: TOTAL | J40: =SUM(J36:J39) -> 0
A44: SOCIO | B44: RECIBO DE SERVICIO | C44: DETALLE | D44: LUZ | E44: AGUA | F44: G. ADM | G44: P. SOCIAL | H44: P.S X FALLECIMIENTO | I44: DEPOSITO | J44: TOTAL
J45: =SUM(D45:I45) -> 0
J46: =SUM(D46:I46) -> 0
J47: =SUM(D47:I47) -> 0
J48: =SUM(D48:I48) -> 0
J49: =SUM(D49:I49) -> 0
J50: =SUM(D50:I50) -> 0
J51: =SUM(D51:I51) -> 0
J52: =SUM(D52:I52) -> 0
J53: =SUM(D53:I53) -> 0
J54: =SUM(D54:I54) -> 0
J55: =SUM(D55:I55) -> 0
J56: =SUM(D56:I56) -> 0
... J58: =SUM(D58:I58) -> 0
A59: TOTAL | D59: =SUM(D45:D58) -> 0 | E59: =SUM(E45:E58) -> 0 | F59: =SUM(F45:F58) -> 0 | G59: =SUM(G45:G58) -> 0 | H59: =SUM(H45:H58) -> 0 | I59: =SUM(I45:I58) -> 0 | J59: =SUM(J45:J58) -> 0
A62: TOTAL DE INGRESOS | J62: =+J24+J59 -> 1952.5
A65: SRTA. FATIMA SIHUE
A66: COBRANZA SOCIOS
A67: COBRANZA INQUILINOS
A70: SRA. MARIA CUYA ARANGO
A71: COBRANZA DE BAÑO DEL 1ER PISO | J71: 501.5
A74: COBRANZA DE BAÑO DEL 2DO PISO
A76: TOTAL GENERAL DE INGRESOS | J76: =SUM(J62:J75) -> 2454
A78: EGRESOS DEL DIA 01-04-2026
A79: CAJA
A80: RESPONSABLE | B80: COMPROBANTE | C80: DETALLE | J80: TOTAL
A81: LOPEZ NELLY | B81: RC 8597 | C81: DIETA MES DE MARZO 2026 AL CARGO DE GERENTE | J81: 450
A82: POMACANCHARI NICANOR | B82: RC 8598 | C82: LIMPIEZA DEL MERCADO (REEMPLAZO DEL SR JAVIER VASQUEZ) DEL DIA 01-04-2026 | J82: 50
A83: SAAVEDRA LUIS | B83: 14636 | C83: 5 CUADERNOS STANFORD PARA EL CONSEJO DE ADM | J83: 27.5
B84: 14637 | C84: 2 CUADERNOS STANFORD PARA EL CONSEJO DE ADM | J84: 11
B85: 14638 | C85: 1 CUADERNO STANFORD PARA EL CONSEJO DE ADM | J85: 5.5
A95: TOTAL DE EGRESOS | J95: =SUM(J81:J94) -> 544
A98: RESUMEN
A99: TOTAL GENERAL | B99: =+J76 -> 2454
A100: TOTAL DE EGRESOS | B100: =+J95 -> 544
A101: SALDO | B101: =++B99-B100 -> 1910

Sheet 02-04-2026
A1: INGRESOS DEL DIA 02-04-2026
A3: INQUILINO | B3: COMPROBANTE | C3: DETALLE | D3: LUZ | E3: AGUA | F3: ALQUILER | G3: ESPACIO | H3: PARQUEO | I3: TICKET | J3: TOTAL
A4: PARQUEO | B4: EB01-7120 | C4: 46113 | H4: 59 | J4: =SUM(D4:I4) -> 59
J5: =SUM(D5:I5) -> 0
J6: =SUM(D6:I6) -> 0
J7: =SUM(D7:I7) -> 0
J8: =SUM(D8:I8) -> 0
J9: =SUM(D9:I9) -> 0
J10: =SUM(D10:I10) -> 0
J11: =SUM(D11:I11) -> 0
J12: =SUM(D12:I12) -> 0
J13: =SUM(D13:I13) -> 0
J14: =SUM(D14:I14) -> 0
J15: =SUM(D15:I15) -> 0
J16: =SUM(D16:I16) -> 0
... J21: =SUM(D21:I21) -> 0
A22: TOTAL | D22: =SUM(D4:D21) -> 0 | E22: =SUM(E4:E21) -> 0 | F22: =SUM(F4:F21) -> 0 | G22: =SUM(G4:G21) -> 0 | H22: =SUM(H4:H21) -> 59 | I22: =SUM(I4:I21) -> 0 | J22: =SUM(J4:J21) -> 59
A24: BBVA
A25: INQUILINOS | B25: COMPROBANTE | C25: DETALLE | D25: LUZ | E25: AGUA | F25: ALQUILER | G25: ESPACIO | H25: DEPOSITO | I25: TICKET | J25: TOTAL
J26: =SUM(D26:I26) -> 0
J27: =SUM(D27:I27) -> 0
J28: =SUM(D28:I28) -> 0
J29: =SUM(D29:I29) -> 0 | L29: TOTAL QR | M29: =J30+J38 -> 0
A30: TOTAL | J30: =SUM(J26:J29) -> 0
A32: BBVA
A33: SOCIOS | B33: RECIBO DE SERVICIO | C33: DETALLE | D33: LUZ | E33: AGUA | F33: G. ADM | G33: P. SOCIAL | H33: DEPOSITO | I33: P.S X FALLECIMIENTO | J33: TOTAL
J34: =SUM(D34:I34) -> 0
J35: =SUM(D35:I35) -> 0
J36: =SUM(D36:I36) -> 0
J37: =SUM(D37:I37) -> 0
A38: TOTAL | J38: =SUM(J34:J37) -> 0
A42: SOCIO | B42: RECIBO DE SERVICIO | C42: DETALLE | D42: LUZ | E42: AGUA | F42: G. ADM | G42: P. SOCIAL | H42: P.S X FALLECIMIENTO | I42: DEPOSITO | J42: TOTAL
J43: =SUM(D43:I43) -> 0
J44: =SUM(D44:I44) -> 0
J45: =SUM(D45:I45) -> 0
J46: =SUM(D46:I46) -> 0
J47: =SUM(D47:I47) -> 0
J48: =SUM(D48:I48) -> 0
J49: =SUM(D49:I49) -> 0
J50: =SUM(D50:I50) -> 0
J51: =SUM(D51:I51) -> 0
J52: =SUM(D52:I52) -> 0
J53: =SUM(D53:I53) -> 0
J54: =SUM(D54:I54) -> 0
... J56: =SUM(D56:I56) -> 0
A57: TOTAL | D57: =SUM(D43:D56) -> 0 | E57: =SUM(E43:E56) -> 0 | F57: =SUM(F43:F56) -> 0 | G57: =SUM(G43:G56) -> 0 | H57: =SUM(H43:H56) -> 0 | I57: =SUM(I43:I56) -> 0 | J57: =SUM(J43:J56) -> 0
A60: TOTAL DE INGRESOS | J60: =+J22+J57 -> 59
A63: SRTA. FATIMA SIHUE
A64: COBRANZA SOCIOS
A65: COBRANZA INQUILINOS
A68: SRA. MARIA CUYA ARANGO
A69: COBRANZA DE BAÑO DEL 1ER PISO | J69: 436
A72: COBRANZA DE BAÑO DEL 2DO PISO
A74: TOTAL GENERAL DE INGRESOS | J74: =SUM(J60:J73) -> 495
A76: EGRESOS DEL DIA 02-04-2026
A77: CAJA
A78: RESPONSABLE | B78: COMPROBANTE | C78: DETALLE | J78: TOTAL
A92: TOTAL DE EGRESOS | J92: =SUM(J79:J91) -> 0
A95: RESUMEN
A96: TOTAL GENERAL | B96: =+J74 -> 495
A97: TOTAL DE EGRESOS | B97: =+J92 -> 0
A98: SALDO | B98: =++B96-B97 -> 495

Sheet 03-04-2026
A1: INGRESOS DEL DIA 03-04-2026
A3: INQUILINO | B3: COMPROBANTE | C3: DETALLE | D3: LUZ | E3: AGUA | F3: ALQUILER | G3: ESPACIO | H3: PARQUEO | I3: TICKET | J3: TOTAL
A4: PARQUEO | B4: EB01-7123 | C4: 46113 | H4: 30.9 | J4: =SUM(D4:I4) -> 30.9
J5: =SUM(D5:I5) -> 0
J6: =SUM(D6:I6) -> 0
J7: =SUM(D7:I7) -> 0
J8: =SUM(D8:I8) -> 0
J9: =SUM(D9:I9) -> 0
J10: =SUM(D10:I10) -> 0
J11: =SUM(D11:I11) -> 0
J12: =SUM(D12:I12) -> 0
J13: =SUM(D13:I13) -> 0
J14: =SUM(D14:I14) -> 0
J15: =SUM(D15:I15) -> 0
J16: =SUM(D16:I16) -> 0
... J21: =SUM(D21:I21) -> 0
A22: TOTAL | D22: =SUM(D4:D21) -> 0 | E22: =SUM(E4:E21) -> 0 | F22: =SUM(F4:F21) -> 0 | G22: =SUM(G4:G21) -> 0 | H22: =SUM(H4:H21) -> 30.9 | I22: =SUM(I4:I21) -> 0 | J22: =SUM(J4:J21) -> 30.9
A24: BBVA
A25: INQUILINOS | B25: COMPROBANTE | C25: DETALLE | D25: LUZ | E25: AGUA | F25: ALQUILER | G25: ESPACIO | H25: DEPOSITO | I25: TICKET | J25: TOTAL
J26: =SUM(D26:I26) -> 0
J27: =SUM(D27:I27) -> 0
J28: =SUM(D28:I28) -> 0
J29: =SUM(D29:I29) -> 0 | L29: TOTAL QR | M29: =J30+J38 -> 0
A30: TOTAL | J30: =SUM(J26:J29) -> 0
A32: BBVA
A33: SOCIOS | B33: RECIBO DE SERVICIO | C33: DETALLE | D33: LUZ | E33: AGUA | F33: G. ADM | G33: P. SOCIAL | H33: DEPOSITO | I33: P.S X FALLECIMIENTO | J33: TOTAL
J34: =SUM(D34:I34) -> 0
J35: =SUM(D35:I35) -> 0
J36: =SUM(D36:I36) -> 0
J37: =SUM(D37:I37) -> 0
A38: TOTAL | J38: =SUM(J34:J37) -> 0
A42: SOCIO | B42: RECIBO DE SERVICIO | C42: DETALLE | D42: LUZ | E42: AGUA | F42: G. ADM | G42: P. SOCIAL | H42: P.S X FALLECIMIENTO | I42: DEPOSITO | J42: TOTAL
J43: =SUM(D43:I43) -> 0
J44: =SUM(D44:I44) -> 0
J45: =SUM(D45:I45) -> 0
J46: =SUM(D46:I46) -> 0
J47: =SUM(D47:I47) -> 0
J48: =SUM(D48:I48) -> 0
J49: =SUM(D49:I49) -> 0
J50: =SUM(D50:I50) -> 0
J51: =SUM(D51:I51) -> 0
J52: =SUM(D52:I52) -> 0
J53: =SUM(D53:I53) -> 0
J54: =SUM(D54:I54) -> 0
... J56: =SUM(D56:I56) -> 0
A57: TOTAL | D57: =SUM(D43:D56) -> 0 | E57: =SUM(E43:E56) -> 0 | F57: =SUM(F43:F56) -> 0 | G57: =SUM(G43:G56) -> 0 | H57: =SUM(H43:H56) -> 0 | I57: =SUM(I43:I56) -> 0 | J57: =SUM(J43:J56) -> 0
A60: TOTAL DE INGRESOS | J60: =+J22+J57 -> 30.9
A63: SRTA. FATIMA SIHUE
A64: COBRANZA SOCIOS
A65: COBRANZA INQUILINOS
A68: SRA. MARIA CUYA ARANGO
A69: COBRANZA DE BAÑO DEL 1ER PISO | J69: 226.5
A72: COBRANZA DE BAÑO DEL 2DO PISO
A74: TOTAL GENERAL DE INGRESOS | J74: =SUM(J60:J73) -> 257.4
A76: EGRESOS DEL DIA 03-04-2026
A77: CAJA
A78: RESPONSABLE | B78: COMPROBANTE | C78: DETALLE | J78: TOTAL
A92: TOTAL DE EGRESOS | J92: =SUM(J79:J91) -> 0
A95: RESUMEN
A96: TOTAL GENERAL | B96: =+J74 -> 257.4
A97: TOTAL DE EGRESOS | B97: =+J92 -> 0
A98: SALDO | B98: =++B96-B97 -> 257.4

Sheet 04-04-2026
A1: INGRESOS DEL DIA 04-04-2026
A3: INQUILINO | B3: COMPROBANTE | C3: DETALLE | D3: LUZ | E3: AGUA | F3: ALQUILER | G3: LOCAL 2DO PISO | H3: PARQUEO | I3: TICKET | J3: TOTAL
A4: JOSE | B4: TK 50818 | I4: 10 | J4: =SUM(D4:I4) -> 10
J5: =SUM(D5:I5) -> 0
A6: VIOLETA ANANI RETAMOZO ORE | B6: EB01-7124 | C6: 46113 | G6: 650 | J6: =SUM(D6:I6) -> 650
A7: PRUDENCIO TUEROS QUISPE | B7: EB01-7125 | C7: 46082 | F7: 500 | J7: =SUM(D7:I7) -> 500
J8: =SUM(D8:I8) -> 0
J9: =SUM(D9:I9) -> 0
J10: =SUM(D10:I10) -> 0
J11: =SUM(D11:I11) -> 0
J12: =SUM(D12:I12) -> 0
J13: =SUM(D13:I13) -> 0
J14: =SUM(D14:I14) -> 0
J15: =SUM(D15:I15) -> 0
J16: =SUM(D16:I16) -> 0
J17: =SUM(D17:I17) -> 0
J18: =SUM(D18:I18) -> 0
J19: =SUM(D19:I19) -> 0
... J21: =SUM(D21:I21) -> 0
A22: TOTAL | D22: =SUM(D4:D21) -> 0 | E22: =SUM(E4:E21) -> 0 | F22: =SUM(F4:F21) -> 500 | G22: =SUM(G4:G21) -> 650 | H22: =SUM(H4:H21) -> 0 | I22: =SUM(I4:I21) -> 10 | J22: =SUM(J4:J21) -> 1160
A24: BBVA
A25: INQUILINOS | B25: COMPROBANTE | C25: DETALLE | D25: LUZ | E25: AGUA | F25: ALQUILER | G25: ESPACIO | H25: DEPOSITO | I25: TICKET | J25: TOTAL
J26: =SUM(D26:I26) -> 0
J27: =SUM(D27:I27) -> 0
J28: =SUM(D28:I28) -> 0
J29: =SUM(D29:I29) -> 0 | L29: TOTAL QR | M29: =J30+J38 -> 0
A30: TOTAL | J30: =SUM(J26:J29) -> 0
A32: BBVA
A33: SOCIOS | B33: RECIBO DE SERVICIO | C33: DETALLE | D33: LUZ | E33: AGUA | F33: G. ADM | G33: P. SOCIAL | H33: DEPOSITO | I33: P.S X FALLECIMIENTO | J33: TOTAL
J34: =SUM(D34:I34) -> 0
J35: =SUM(D35:I35) -> 0
J36: =SUM(D36:I36) -> 0
J37: =SUM(D37:I37) -> 0
A38: TOTAL | J38: =SUM(J34:J37) -> 0
A42: SOCIO | B42: RECIBO DE SERVICIO | C42: DETALLE | D42: LUZ | E42: AGUA | F42: G. ADM | G42: P. SOCIAL | H42: P.S X FALLECIMIENTO | I42: DEPOSITO | J42: TOTAL
J43: =SUM(D43:I43) -> 0
J44: =SUM(D44:I44) -> 0
J45: =SUM(D45:I45) -> 0
J46: =SUM(D46:I46) -> 0
J47: =SUM(D47:I47) -> 0
J48: =SUM(D48:I48) -> 0
J49: =SUM(D49:I49) -> 0
J50: =SUM(D50:I50) -> 0
J51: =SUM(D51:I51) -> 0
J52: =SUM(D52:I52) -> 0
J53: =SUM(D53:I53) -> 0
J54: =SUM(D54:I54) -> 0
... J56: =SUM(D56:I56) -> 0
A57: TOTAL | D57: =SUM(D43:D56) -> 0 | E57: =SUM(E43:E56) -> 0 | F57: =SUM(F43:F56) -> 0 | G57: =SUM(G43:G56) -> 0 | H57: =SUM(H43:H56) -> 0 | I57: =SUM(I43:I56) -> 0 | J57: =SUM(J43:J56) -> 0
A60: TOTAL DE INGRESOS | J60: =+J22+J57 -> 1160
A63: SRTA. FATIMA SIHUE
A64: COBRANZA SOCIOS
A65: COBRANZA INQUILINOS
A68: SRA. MARIA CUYA ARANGO
A69: COBRANZA DE BAÑO DEL 1ER PISO | J69: 377.5
A72: COBRANZA DE BAÑO DEL 2DO PISO
A74: TOTAL GENERAL DE INGRESOS | J74: =SUM(J60:J73) -> 1537.5
A76: EGRESOS DEL DIA 04-04-2026
A77: CAJA
A78: RESPONSABLE | B78: COMPROBANTE | C78: DETALLE | J78: TOTAL
A79: DELGADO SANCHEZ MARIA DENNIS | B79: E001-122 | C79: BOCADITOS PARA EL VIA CRUCIS DE LA IGLESIA SAN ESTEBAN REY DE HUNGRIA | J79: 61.4
A80: COMPAÑÍA HARD DISCOUNT S.A.C. | B80: FA39-00501317 | C80: GASEOSAS PARA EL VIA CRUCIS | J80: 31
A81: SERVICIOS ALIMENTARIOS H&J CHOCOCHANTY | B81: 267-1-000006 | C81: BOCADITOS DULCES PARA EL VIA CRUCIS | J81: 50
A82: PAREDES FLORES OSCAR | B82: RC 8599 | C82: DIETA MES DE MARZO 2026 AL CARGO DE PRESIDENTE DEL CONSEJO DE ADM | J82: 600
A92: TOTAL DE EGRESOS | J92: =SUM(J79:J91) -> 742.4
A95: RESUMEN
A96: TOTAL GENERAL | B96: =+J74 -> 1537.5
A97: TOTAL DE EGRESOS | B97: =+J92 -> 742.4
A98: SALDO | B98: =++B96-B97 -> 795.1

Sheet 05-04-2026
A1: INGRESOS DEL DIA 05-04-2026
A3: INQUILINO | B3: COMPROBANTE | C3: DETALLE | D3: LUZ | E3: AGUA | F3: ALQUILER | G3: ESPACIO | H3: PARQUEO | I3: TICKET | J3: TOTAL
A4: MARI SOL QUISPE CHAVEZ | B4: EB01-7128 | F4: 100 | J4: =SUM(D4:I4) -> 100
J5: =SUM(D5:I5) -> 0
J6: =SUM(D6:I6) -> 0
J7: =SUM(D7:I7) -> 0
J8: =SUM(D8:I8) -> 0
J9: =SUM(D9:I9) -> 0
J10: =SUM(D10:I10) -> 0
J11: =SUM(D11:I11) -> 0
J12: =SUM(D12:I12) -> 0
J13: =SUM(D13:I13) -> 0
J14: =SUM(D14:I14) -> 0
J15: =SUM(D15:I15) -> 0
J16: =SUM(D16:I16) -> 0
... J21: =SUM(D21:I21) -> 0
A22: TOTAL | D22: =SUM(D4:D21) -> 0 | E22: =SUM(E4:E21) -> 0 | F22: =SUM(F4:F21) -> 100 | H22: =SUM(H4:H21) -> 0 | I22: =SUM(I4:I21) -> 0 | J22: =SUM(J4:J21) -> 100
A24: BBVA
A25: INQUILINOS | B25: COMPROBANTE | C25: DETALLE | D25: LUZ | E25: AGUA | F25: ALQUILER | G25: ESPACIO | H25: DEPOSITO | I25: TICKET | J25: TOTAL
J26: =SUM(D26:I26) -> 0
J27: =SUM(D27:I27) -> 0
J28: =SUM(D28:I28) -> 0
J29: =SUM(D29:I29) -> 0 | L29: TOTAL QR | M29: =J30+J38 -> 0
A30: TOTAL | J30: =SUM(J26:J29) -> 0
A32: BBVA
A33: SOCIOS | B33: RECIBO DE SERVICIO | C33: DETALLE | D33: LUZ | E33: AGUA | F33: G. ADM | G33: P. SOCIAL | H33: DEPOSITO | I33: P.S X FALLECIMIENTO | J33: TOTAL
J34: =SUM(D34:I34) -> 0
J35: =SUM(D35:I35) -> 0
J36: =SUM(D36:I36) -> 0
J37: =SUM(D37:I37) -> 0
A38: TOTAL | J38: =SUM(J34:J37) -> 0
A42: SOCIO | B42: RECIBO DE SERVICIO | C42: DETALLE | D42: LUZ | E42: AGUA | F42: G. ADM | G42: P. SOCIAL | H42: P.S X FALLECIMIENTO | I42: DEPOSITO | J42: TOTAL
J43: =SUM(D43:I43) -> 0
J44: =SUM(D44:I44) -> 0
J45: =SUM(D45:I45) -> 0
J46: =SUM(D46:I46) -> 0
J47: =SUM(D47:I47) -> 0
J48: =SUM(D48:I48) -> 0
J49: =SUM(D49:I49) -> 0
J50: =SUM(D50:I50) -> 0
J51: =SUM(D51:I51) -> 0
J52: =SUM(D52:I52) -> 0
J53: =SUM(D53:I53) -> 0
J54: =SUM(D54:I54) -> 0
... J56: =SUM(D56:I56) -> 0
A57: TOTAL | D57: =SUM(D43:D56) -> 0 | E57: =SUM(E43:E56) -> 0 | F57: =SUM(F43:F56) -> 0 | G57: =SUM(G43:G56) -> 0 | H57: =SUM(H43:H56) -> 0 | I57: =SUM(I43:I56) -> 0 | J57: =SUM(J43:J56) -> 0
A60: TOTAL DE INGRESOS | J60: =+J22+J57 -> 100
A63: SRTA. FATIMA SIHUE
A64: COBRANZA SOCIOS
A65: COBRANZA INQUILINOS
A68: SRA. MARIA CUYA ARANGO
A69: COBRANZA DE BAÑO DEL 1ER PISO | J69: 504.5
A72: COBRANZA DE BAÑO DEL 2DO PISO
A74: TOTAL GENERAL DE INGRESOS | J74: =SUM(J60:J73) -> 604.5
A76: EGRESOS DEL DIA 05-04-2026
A77: CAJA
A78: RESPONSABLE | B78: COMPROBANTE | C78: DETALLE | J78: TOTAL
A92: TOTAL DE EGRESOS | J92: =SUM(J79:J91) -> 0
A95: RESUMEN
A96: TOTAL GENERAL | B96: =+J74 -> 604.5
A97: TOTAL DE EGRESOS | B97: =+J92 -> 0
A98: SALDO | B98: =++B96-B97 -> 604.5

Sheet 06-04-2026
A1: INGRESOS DEL DIA 06-04-2026
A3: INQUILINO | B3: COMPROBANTE | C3: DETALLE | D3: LUZ | E3: AGUA | F3: ALQUILER | G3: ESPACIO | H3: PARQUEO | I3: TICKET | J3: TOTAL
A4: MARI SOL QUISPE CHAVEZ | B4: EB01-7129 | C4: 46054 | F4: 100 | J4: =SUM(D4:I4) -> 100
A5: EDGAR SALVADOR ALVAREZ CHIARA | B5: EB01-7130 | C5: 46082 | F5: 450 | J5: =SUM(D5:I5) -> 450
A6: OBDULIA CERRON GALVAN | B6: EB01-7131 | C6: 46114 | F6: 450 | J6: =SUM(D6:I6) -> 450
A7: PARQUEO | B7: EB01-7132 | C7: 46114 | H7: 60.4 | J7: =SUM(D7:I7) -> 60.4
A8: MARLENE YAUYOS MENDIETA | B8: EB01-7133 | C8: 46023 | F8: 200 | J8: =SUM(D8:I8) -> 200
A9: PATRICIA PAOLA QUISPE MAMANI | B9: EB01-7134 | C9: 46082 | F9: 700 | J9: =SUM(D9:I9) -> 700
A10: PARQUEO | B10: EB01-7136 | C10: 46114 | H10: 76 | J10: =SUM(D10:I10) -> 76
J11: =SUM(D11:I11) -> 0
A12: JOSE | B12: TK 50819 | C12: 46114 | I12: 10 | J12: =SUM(D12:I12) -> 10
A13: JOSE DESARMADORES | B13: TK 50820 | C13: 46114 | I13: 10 | J13: =SUM(D13:I13) -> 10
J14: =SUM(D14:I14) -> 0
A15: NOTA DE CREDITO | B15: EB01-95 | F15: -100 | J15: =SUM(D15:I15) -> -100
J16: =SUM(D16:I16) -> 0
J17: =SUM(D17:I17) -> 0
J18: =SUM(D18:I18) -> 0
J19: =SUM(D19:I19) -> 0
J20: =SUM(D20:I20) -> 0
J21: =SUM(D21:I21) -> 0
J22: =SUM(D22:I22) -> 0
J23: =SUM(D23:I23) -> 0
A24: TOTAL | D24: =SUM(D4:D23) -> 0 | E24: =SUM(E4:E23) -> 0 | F24: =SUM(F4:F23) -> 1800 | G24: =SUM(G4:G23) -> 0 | H24: =SUM(H4:H23) -> 136.4 | I24: =SUM(I4:I23) -> 20 | J24: =SUM(J4:J23) -> 1956.4
A26: BBVA
A27: INQUILINOS | B27: COMPROBANTE | C27: DETALLE | D27: LUZ | E27: AGUA | F27: ALQUILER | G27: ESPACIO | H27: DEPOSITO | I27: TICKET | J27: TOTAL
J28: =SUM(D28:I28) -> 0
J29: =SUM(D29:I29) -> 0
J30: =SUM(D30:I30) -> 0
J31: =SUM(D31:I31) -> 0 | L31: TOTAL QR | M31: =J32+J40 -> 65
A32: TOTAL | J32: =SUM(J28:J31) -> 0
A34: BBVA
A35: SOCIOS | B35: RECIBO DE SERVICIO | C35: DETALLE | D35: LUZ | E35: AGUA | F35: G. ADM | G35: P. SOCIAL | H35: DEPOSITO | I35: P.S X FALLECIMIENTO | J35: TOTAL
A36: PRADO ZOZIMA | B36: RI 32929 | C36: 46082 | F36: 60 | G36: 5 | J36: =SUM(D36:I36) -> 65
J37: =SUM(D37:I37) -> 0
J38: =SUM(D38:I38) -> 0
J39: =SUM(D39:I39) -> 0
A40: TOTAL | J40: =SUM(J36:J39) -> 65
A44: SOCIO | B44: RECIBO DE SERVICIO | C44: DETALLE | D44: LUZ | E44: AGUA | F44: G. ADM | G44: P. SOCIAL | H44: P.S X FALLECIMIENTO | I44: DEPOSITO | J44: TOTAL
J45: =SUM(D45:I45) -> 0
J46: =SUM(D46:I46) -> 0
J47: =SUM(D47:I47) -> 0
J48: =SUM(D48:I48) -> 0
J49: =SUM(D49:I49) -> 0
J50: =SUM(D50:I50) -> 0
J51: =SUM(D51:I51) -> 0
J52: =SUM(D52:I52) -> 0
J53: =SUM(D53:I53) -> 0
J54: =SUM(D54:I54) -> 0
J55: =SUM(D55:I55) -> 0
J56: =SUM(D56:I56) -> 0
J57: =SUM(D57:I57) -> 0
A58: TOTAL | D58: =SUM(D45:D57) -> 0 | E58: =SUM(E45:E57) -> 0 | F58: =SUM(F45:F57) -> 0 | G58: =SUM(G45:G57) -> 0 | H58: =SUM(H45:H57) -> 0 | I58: =SUM(I45:I57) -> 0 | J58: =SUM(J45:J57) -> 0
A61: TOTAL DE INGRESOS | J61: =+J24+J58 -> 1956.4
A64: SRTA. FATIMA SIHUE
A65: COBRANZA SOCIOS
A66: COBRANZA INQUILINOS
A69: SRA. MARIA CUYA ARANGO
A70: COBRANZA DE BAÑO DEL 1ER PISO | J70: 352.5
A73: COBRANZA DE BAÑO DEL 2DO PISO
A75: TOTAL GENERAL DE INGRESOS | J75: =SUM(J61:J74) -> 2308.9
A77: EGRESOS DEL DIA 06-04-2026
A78: CAJA
A79: RESPONSABLE | B79: COMPROBANTE | C79: DETALLE | J79: TOTAL
A80: ZENEIDE BELLIDO DE LA TORRE DE CHUQUITAIPE | B80: 439 | C80: 1 GUANTE PARA LA SRA DE LOS SSHH | J80: 3.5
A81: VILLAR RONCAL DIGNA | B81: F001-0003655 | C81: 1 CHAPA PERILLA FORTE PARA LA PUERTA DEL ALMACEN DEL SEGUNDO PISO | J81: 42
A82: COTRINA MANRIQUE TITO | B82: E001-191 | C82: CAMBIO Y COLOCACION DE NUEVA CHAPA PARA LA PUERTA DEL ALMACEN DEL SEGUNDO PISO. | J82: 20
A83: SOTO MARIA | B83: RC 8600 | C83: DIETA MES DE MARZO 2026 AL CARGO DE VOCAL TITULAR DEL CONSEJO DE ADM | J83: 200
A90: TOTAL DE EGRESOS | J90: =SUM(J80:J89) -> 265.5
A93: RESUMEN
A94: TOTAL GENERAL | B94: =+J75 -> 2308.9
A95: TOTAL DE EGRESOS | B95: =+J90 -> 265.5
A96: SALDO | B96: =++B94-B95 -> 2043.4

Sheet 07-04-2026
A1: INGRESOS DEL DIA 07-04-2026
A3: INQUILINO | B3: COMPROBANTE | C3: DETALLE | D3: LUZ | E3: AGUA | F3: ALQUILER | G3: LOCAL DEL 2DO PISO | H3: PARQUEO | I3: TICKET | J3: TOTAL
A4: FEDERICO MANUEL LEONARDO AMARILLO | B4: EB01-7137 | C4: 46082 | F4: 140 | J4: =SUM(D4:I4) -> 140
A5: ROSANA PILAR LEONARDO AMARILLO | B5: EB01-7138 | C5: 46082 | F5: 140 | J5: =SUM(D5:I5) -> 140
A6: FERNANDO MARTIN OBREGON CASTILLO | B6: EB01-7139 | C6: 46082 | F6: 140 | J6: =SUM(D6:I6) -> 140
A7: IDALINA MONTENEGRO BAUTISTA | B7: EB01-7140 | C7: 46054 | F7: 300 | J7: =SUM(D7:I7) -> 300
A8: ROMULO HUAMANI JANAMPA | B8: EB01-7141 | C8: 46174 | G8: 350 | J8: =SUM(D8:I8) -> 350
A9: HAYDEE LOPEZ CERRON | B9: EB01-7142 | C9: 46082 | F9: 500 | J9: =SUM(D9:I9) -> 500
A10: GRACIELA BUSTAMANTE CHILON | B10: EB01-7143 | C10: 46082 | F10: 500 | J10: =SUM(D10:I10) -> 500
A11: REYNALDO RIGOBERTO VERA ROMERO | B11: EB01-7146 | C11: 46113 | G11: 300 | J11: =SUM(D11:I11) -> 300
A12: PARQUEO | B12: EB01-7147 | C12: 46113 | H12: 67 | J12: =SUM(D12:I12) -> 67
J13: =SUM(D13:I13) -> 0
A14: FERNANDO MARTIN OBREGON CASTILLO | B14: RII 3318 | C14: 45962 | D14: 42.7 | E14: 5 | J14: =SUM(D14:I14) -> 47.7
C15: 45992 | D15: 42.9 | E15: 5 | J15: =SUM(D15:I15) -> 47.9
C16: 46023 | D16: 38.3 | E16: 3 | J16: =SUM(D16:I16) -> 41.3
C17: 46054 | D17: 37.9 | E17: 6 | J17: =SUM(D17:I17) -> 43.9
A18: HAYDEE LOPEZ CERRON | B18: RII 3319 | C18: 46054 | D18: 14.4 | E18: 6 | J18: =SUM(D18:I18) -> 20.4
A19: YAURIMUCHA URSULA | B19: RII 3320 | C19: 46054 | D19: 14.4 | E19: 6 | J19: =SUM(D19:I19) -> 20.4
A20: GRACIELA BUSTAMANTE CHILON | B20: RII 3321 | C20: 46054 | D20: 6.6 | E20: 6 | J20: =SUM(D20:I20) -> 12.6
J21: =SUM(D21:I21) -> 0
J22: =SUM(D22:I22) -> 0
A23: TOTAL | D23: =SUM(D4:D22) -> 197.2 | E23: =SUM(E4:E22) -> 37 | F23: =SUM(F4:F22) -> 1720 | G23: =SUM(G4:G22) -> 650 | H23: =SUM(H4:H22) -> 67 | I23: =SUM(I4:I22) -> 0 | J23: =SUM(J4:J22) -> 2671.2
A25: BBVA
A26: INQUILINOS | B26: COMPROBANTE | C26: DETALLE | D26: LUZ | E26: AGUA | F26: ALQUILER | G26: ESPACIO | H26: DEPOSITO | I26: TICKET | J26: TOTAL
A27: ROMINA DEL CARMEN HERRERA PEVES | B27: EB01-7144 | C27: 46082 | F27: 600 | J27: =SUM(D27:I27) -> 600
B28: RII 3322 | C28: 46054 | D28: 30 | E28: 15 | J28: =SUM(D28:I28) -> 45
J29: =SUM(D29:I29) -> 0
J30: =SUM(D30:I30) -> 0 | L30: TOTAL QR | M30: =J31+J39 -> 645
A31: TOTAL | J31: =SUM(J27:J30) -> 645
A33: BBVA
A34: SOCIOS | B34: RECIBO DE SERVICIO | C34: DETALLE | D34: LUZ | E34: AGUA | F34: G. ADM | G34: P. SOCIAL | H34: DEPOSITO | I34: P.S X FALLECIMIENTO | J34: TOTAL
J35: =SUM(D35:I35) -> 0
J36: =SUM(D36:I36) -> 0
J37: =SUM(D37:I37) -> 0
J38: =SUM(D38:I38) -> 0
A39: TOTAL | J39: =SUM(J35:J38) -> 0
A43: SOCIO | B43: RECIBO DE SERVICIO | C43: DETALLE | D43: LUZ | E43: AGUA | F43: G. ADM | G43: P. SOCIAL | H43: P.S X FALLECIMIENTO | I43: DEPOSITO | J43: TOTAL
J44: =SUM(D44:I44) -> 0
J45: =SUM(D45:I45) -> 0
J46: =SUM(D46:I46) -> 0
J47: =SUM(D47:I47) -> 0
J48: =SUM(D48:I48) -> 0
J49: =SUM(D49:I49) -> 0
J50: =SUM(D50:I50) -> 0
J51: =SUM(D51:I51) -> 0
J52: =SUM(D52:I52) -> 0
J53: =SUM(D53:I53) -> 0
J54: =SUM(D54:I54) -> 0
J55: =SUM(D55:I55) -> 0
... J57: =SUM(D57:I57) -> 0
A58: TOTAL | D58: =SUM(D44:D57) -> 0 | E58: =SUM(E44:E57) -> 0 | F58: =SUM(F44:F57) -> 0 | G58: =SUM(G44:G57) -> 0 | H58: =SUM(H44:H57) -> 0 | I58: =SUM(I44:I57) -> 0 | J58: =SUM(J44:J57) -> 0
A61: TOTAL DE INGRESOS | J61: =+J23+J58 -> 2671.2
A64: SRTA. FATIMA SIHUE
A65: COBRANZA SOCIOS
A66: COBRANZA INQUILINOS
A69: SRA. MARIA CUYA ARANGO
A70: COBRANZA DE BAÑO DEL 1ER PISO | J70: 481
A73: COBRANZA DE BAÑO DEL 2DO PISO
A75: TOTAL GENERAL DE INGRESOS | J75: =SUM(J61:J74) -> 3152.2
A77: EGRESOS DEL DIA 07-04-2026
A78: CAJA
A79: RESPONSABLE | B79: COMPROBANTE | C79: DETALLE | J79: TOTAL
A80: ALVAREZ CAMPOS ROLANDO | B80: 14852 | C80: 01 CAFÉ ALTOMAYO + AZUCAR PARA LOS VIGILANTES TURNO NOCHE | J80: 28.9
A90: TOTAL DE EGRESOS | J90: =SUM(J80:J89) -> 28.9
A93: RESUMEN
A94: TOTAL GENERAL | B94: =+J75 -> 3152.2
A95: TOTAL DE EGRESOS | B95: =+J90 -> 28.9
A96: SALDO | B96: =++B94-B95 -> 3123.3

Sheet 08-04-2026
A1: INGRESOS DEL DIA 08-04-2026
A3: INQUILINO | B3: COMPROBANTE | C3: DETALLE | D3: LUZ | E3: AGUA | F3: ALQUILER | G3: ESPACIO | H3: PARQUEO | I3: MULTA POR CAPACITACION | J3: TOTAL
A4: CLAROS TORRES SANTOS JESUS | B4: E001-358 | C4: 46054 | F4: 250 | J4: =SUM(D4:I4) -> 250
A5: IMPULSO SALUD S.A.C. | B5: E001-359 | C5: 46113 | G5: 40 | J5: =SUM(D5:I5) -> 40
J6: =SUM(D6:I6) -> 0
A7: MARI SOL QUISPE CHAVEZ | B7: EB01-7148 | C7: 46082 | F7: 100 | J7: =SUM(D7:I7) -> 100
A8: ASAEL CASTILLO ZAPATA | B8: EB01-7149 | C8: 46054 | F8: 700 | J8: =SUM(D8:I8) -> 700
A9: CLEMENCIA BEATRIZ GARCIA MEDINA VDA DE MOLINA | B9: EB01-7150 | C9: 46082 | F9: 250 | J9: =SUM(D9:I9) -> 250
A10: LISBETH KARITO QUISPE NAPUCHE | B10: EB01-7151 | C10: 46023 | F10: 300 | J10: =SUM(D10:I10) -> 300
A11: CASILDA CATALINA REBAZA REBAZA | B11: EB01-7152 | C11: 46054 | F11: 150 | J11: =SUM(D11:I11) -> 150
A12: DAYSI ELIZABETH AZURZA TRIBIÑOS | B12: EB01-7154 | C12: 46082 | F12: 129.6 | J12: =SUM(D12:I12) -> 129.6
A13: ERIKA BENITES TRIBIÑOS | B13: EB01-7155 | C13: 46054 | F13: 300 | J13: =SUM(D13:I13) -> 300
C14: 46082 | F14: 129.6 | J14: =SUM(D14:I14) -> 129.6
A15: SANDRA LIZ MUJICA PALOMINO | B15: EB01-7157 | C15: 46054 | F15: 19.5 | J15: =SUM(D15:I15) -> 19.5
A16: JESSICA PATRICIA SALDAÑA DONAYRE | B16: EB01-7159 | C16: 46023 | F16: 300 | J16: =SUM(D16:I16) -> 300
A17: DAVID VICENTE CCENCHO CARRASCO | B17: EB01-7161 | C17: 46082 | F17: 500 | J17: =SUM(D17:I17) -> 500
A18: YESENIA BEATRIZ DAVILA HILARES | B18: EB01-7162 | C18: 46082 | F18: 500 | J18: =SUM(D18:I18) -> 500
A19: ASHLEY MARYORI PEÑA VILLANUEVA | B19: EB01-7164 | C19: 46113 | F19: 1000 | J19: =SUM(D19:I19) -> 1000
A20: ELMER BURGA CARRASCO | B20: EB01-7165 | C20: 46054 | F20: 58 | J20: =SUM(D20:I20) -> 58
C21: 46023 | F21: 242 | J21: =SUM(D21:I21) -> 242
A22: DOMINICA LUCIANA FLORES LAREDO | B22: EB01-7166 | C22: 46054 | F22: 200 | J22: =SUM(D22:I22) -> 200
A23: JANETT CONSUELO CASTRO RODRIGUEZ | B23: EB01-7167 | C23: 46054 | F23: 150 | J23: =SUM(D23:I23) -> 150
A24: LIDIA AGRIPINA CONDORI MAMANI | B24: EB01-7168 | C24: 46023 | F24: 50 | J24: =SUM(D24:I24) -> 50
C25: 46054 | F25: 150 | J25: =SUM(D25:I25) -> 150
A26: PARQUEO | B26: EB01-7170 | C26: 46113 | H26: 64.5 | J26: =SUM(D26:I26) -> 64.5
J27: =SUM(D27:I27) -> 0
J28: =SUM(D28:I28) -> 0
A29: CLEMENCIA BEATRIZ GARCIA MEDINA VDA DE MOLINA | B29: RII 3324 | C29: 45992 | D29: 10 | E29: 5 | J29: =SUM(D29:I29) -> 15
C30: 46023 | D30: 15 | E30: 3 | J30: =SUM(D30:I30) -> 18
C31: 46054 | D31: 14.4 | E31: 6 | J31: =SUM(D31:I31) -> 20.4
A32: REBAZA CASILDA | B32: RII 3325 | C32: 46023 | I32: 28.3 | J32: =SUM(D32:I32) -> 28.3
C33: 46054 | D33: 9.2 | E33: 6 | J33: =SUM(D33:I33) -> 15.2
A34: AZURZA DAYSI | B34: RII 3327 | C34: 46054 | D34: 4.4 | E34: 6 | J34: =SUM(D34:I34) -> 10.4
A35: BENITES ERIKA | B35: RII 3328 | C35: 46054 | D35: 14.4 | E35: 6 | J35: =SUM(D35:I35) -> 20.4
A36: MUJICA SANDRA | B36: RII 3329 | C36: 46023 | D36: 21.1 | E36: 3 | I36: 28.3 | J36: =SUM(D36:I36) -> 52.4
C37: 46054 | D37: 22.1 | E37: 6 | J37: =SUM(D37:I37) -> 28.1
A38: CCENCHO DAVID | B38: RII 3332 | C38: 46023 | I38: 28.3 | J38: =SUM(D38:I38) -> 28.3
C39: 46054 | D39: 14.4 | E39: 6 | J39: =SUM(D39:I39) -> 20.4
A40: DAVILA YESENIA | B40: RII 3333 | C40: 46023 | I40: 28.3 | J40: =SUM(D40:I40) -> 28.3
C41: 46054 | D41: 14.4 | E41: 6 | J41: =SUM(D41:I41) -> 20.4
A42: HERNANDEZ LILIBETH | B42: RII 3334 | C42: 46054 | D42: 34 | E42: 6 | J42: =SUM(D42:I42) -> 40
A43: ARREDONDO GLADYS | B43: RII 3335 | C43: 46054 | D43: 14.4 | E43: 6 | J43: =SUM(D43:I43) -> 20.4
A44: ASHLEY MARYORI PEÑA VILLANUEVA | B44: RII 3336 | C44: 46054 | D44: 29.6 | E44: 6 | J44: =SUM(D44:I44) -> 35.6
A45: CERDAN MARIA | B45: RII 3337 | C45: 46054 | D45: 14.4 | E45: 6 | J45: =SUM(D45:I45) -> 20.4
A46: JANETT CONSUELO CASTRO RODRIGUEZ | B46: RII 3338 | C46: 46054 | D46: 5 | E46: 6 | J46: =SUM(D46:I46) -> 11
J47: =SUM(D47:I47) -> 0
J48: =SUM(D48:I48) -> 0
J49: =SUM(D49:I49) -> 0
A50: TOTAL | D50: =SUM(D4:D49) -> 236.8 | E50: =SUM(E4:E49) -> 83 | F50: =SUM(F4:F49) -> 5478.7 | G50: =SUM(G4:G49) -> 40 | H50: =SUM(H4:H49) -> 64.5 | I50: =SUM(I4:I49) -> 113.2 | J50: =SUM(J4:J49) -> 6016.2
A52: BBVA
A53: INQUILINOS | B53: COMPROBANTE | C53: DETALLE | D53: LUZ | E53: AGUA | F53: ALQUILER | G53: ESPACIO | H53: DEPOSITO | I53: TICKET | J53: TOTAL
A54: ASAEL CASTILLO ZAPATA | B54: RII 3323 | C54: 46023 | D54: 35.5 | E54: 3 | J54: =SUM(D54:I54) -> 38.5
C55: 46054 | D55: 35 | E55: 6 | J55: =SUM(D55:I55) -> 41
A56: AZURZA DAYSI | B56: RII 3326 | C56: 46054 | D56: 10 | J56: =SUM(D56:I56) -> 10
A57: SALDAÑA JESSICA | B57: RII 3330 | C57: 46054 | D57: 48.5 | E57: 6 | J57: =SUM(D57:I57) -> 54.5
A58: CARRASCO MERY | B58: RII 3331 | C58: 46023 | D58: 15 | E58: 3 | J58: =SUM(D58:I58) -> 18
C59: 46054 | D59: 14.4 | E59: 6 | J59: =SUM(D59:I59) -> 20.4
J60: =SUM(D60:I60) -> 0
J61: =SUM(D61:I61) -> 0
J62: =SUM(D62:I62) -> 0
A63: DAYSI ELIZABETH AZURZA TRIBIÑOS | B63: EB01-7153 | C63: 46054 | F63: 300 | J63: =SUM(D63:I63) -> 300
A64: LISBETH LUCIA MALLMA CONDORI | B64: EB01-7156 | C64: 46023 | F64: 163.8 | J64: =SUM(D64:I64) -> 163.8
C65: 46054 | F65: 136.2 | J65: =SUM(D65:I65) -> 136.2
A66: SANDRA LIZ MUJICA PALOMINO | B66: EB01-7158 | C66: 46023 | F66: 69 | J66: =SUM(D66:I66) -> 69
C67: 46054 | F67: 131 | J67: =SUM(D67:I67) -> 131
A68: MERY RUTH CARRASCO PICHIHUA | B68: EB01-7160 | C68: 46054 | F68: 80 | J68: =SUM(D68:I68) -> 80
C69: 46082 | F69: 112 | J69: =SUM(D69:I69) -> 112
A70: HERNANDEZ HERNANDEZ LILIBETH MARIA | B70: EB01-7163 | C70: 46023 | F70: 400 | J70: =SUM(D70:I70) -> 400
C71: 46054 | F71: 500 | J71: =SUM(D71:I71) -> 500
J72: =SUM(D72:I72) -> 0
J73: =SUM(D73:I73) -> 0
J74: =SUM(D74:I74) -> 0
J75: =SUM(D75:I75) -> 0
J76: =SUM(D76:I76) -> 0 | L76: TOTAL QR | M76: =J77+J85 -> 2074.4
A77: TOTAL | J77: =SUM(J54:J76) -> 2074.4
A79: BBVA
A80: SOCIOS | B80: RECIBO DE SERVICIO | C80: DETALLE | D80: LUZ | E80: AGUA | F80: G. ADM | G80: P. SOCIAL | H80: DEPOSITO | I80: P.S X FALLECIMIENTO | J80: TOTAL
J81: =SUM(D81:I81) -> 0
J82: =SUM(D82:I82) -> 0
J83: =SUM(D83:I83) -> 0
J84: =SUM(D84:I84) -> 0
A85: TOTAL | J85: =SUM(J81:J84) -> 0
A89: SOCIO | B89: RECIBO DE SERVICIO | C89: DETALLE | D89: LUZ | E89: AGUA | F89: G. ADM | G89: P. SOCIAL | H89: P.S X FALLECIMIENTO | I89: DEPOSITO | J89: TOTAL
A90: AYALA ELISEO | B90: RI 32930 | F90: 60 | G90: 5 | I90: 150 | J90: =SUM(D90:I90) -> 215
A91: AYALA NORMA | B91: RI 32931 | F91: 60 | G91: 5 | J91: =SUM(D91:I91) -> 65
A92: HUASHUAYO EUDOSIA | B92: RI 32932 | F92: 60 | G92: 5 | I92: 200 | J92: =SUM(D92:I92) -> 265
J93: =SUM(D93:I93) -> 0
J94: =SUM(D94:I94) -> 0
J95: =SUM(D95:I95) -> 0
J96: =SUM(D96:I96) -> 0
A97: TOTAL | D97: =SUM(D90:D96) -> 0 | E97: =SUM(E90:E96) -> 0 | F97: =SUM(F90:F96) -> 180 | G97: =SUM(G90:G96) -> 15 | H97: =SUM(H90:H96) -> 0 | I97: =SUM(I90:I96) -> 350 | J97: =SUM(J90:J96) -> 545
A100: TOTAL DE INGRESOS | J100: =+J50+J97 -> 6561.2
A103: SRTA. FATIMA SIHUE
A104: COBRANZA SOCIOS
A105: COBRANZA INQUILINOS
A108: SRA. MARIA CUYA ARANGO
A109: COBRANZA DE BAÑO DEL 1ER PISO | J109: 496
A112: COBRANZA DE BAÑO DEL 2DO PISO
A114: TOTAL GENERAL DE INGRESOS | J114: =SUM(J100:J113) -> 7057.2
A116: EGRESOS DEL DIA 08-04-2026
...

Sheet 09-04-2026
A1: INGRESOS DEL DIA 09-04-2026
A3: INQUILINO | B3: COMPROBANTE | C3: DETALLE | D3: LUZ | E3: AGUA | F3: ALQUILER | G3: ESPACIO | H3: PARQUEO | I3: MULTA POR CAPACITACION | J3: TOTAL
A4: ADMINISTRADORA DE SERVICIOS FUNERARIOS SAC | B4: E001-361 | C4: 46113 | G4: 30 | J4: =SUM(D4:I4) -> 30
J5: =SUM(D5:I5) -> 0
A6: CARLOS ARTURO CERVANTES GARCIA | B6: EB01-7171 | C6: 46082 | F6: 500 | J6: =SUM(D6:I6) -> 500
A7: DORIS MAYHUASCA BASTIDAS | B7: EB01-7172 | C7: 46082 | F7: 230 | J7: =SUM(D7:I7) -> 230
A8: MARIBEL GOMEZ MITMA | B8: EB01-7173 | C8: 46054 | F8: 50 | J8: =SUM(D8:I8) -> 50
C9: 46082 | F9: 200 | J9: =SUM(D9:I9) -> 200
A10: PARQUEO | B10: EB01-7174 | C10: 46113 | H10: 44.9 | J10: =SUM(D10:I10) -> 44.9
J11: =SUM(D11:I11) -> 0
J12: =SUM(D12:I12) -> 0
J13: =SUM(D13:I13) -> 0
J14: =SUM(D14:I14) -> 0
J15: =SUM(D15:I15) -> 0
J16: =SUM(D16:I16) -> 0
A17: CARLOS ARTURO CERVANTES GARCIA | B17: RII 3339 | C17: 46023 | I17: 28.3 | J17: =SUM(D17:I17) -> 28.3
C18: 46054 | D18: 14.4 | E18: 6 | J18: =SUM(D18:I18) -> 20.4
A19: MAYHUASCA DORIS | B19: RII 3340 | C19: 46023 | D19: 9.9 | E19: 3 | J19: =SUM(D19:I19) -> 12.9
C20: 46054 | D20: 9 | E20: 6 | J20: =SUM(D20:I20) -> 15
J21: =SUM(D21:I21) -> 0
J22: =SUM(D22:I22) -> 0
J23: =SUM(D23:I23) -> 0
J24: =SUM(D24:I24) -> 0
J25: =SUM(D25:I25) -> 0
J26: =SUM(D26:I26) -> 0
A27: TOTAL | D27: =SUM(D4:D26) -> 33.3 | E27: =SUM(E4:E26) -> 15 | F27: =SUM(F4:F26) -> 980 | G27: =SUM(G4:G26) -> 30 | H27: =SUM(H4:H26) -> 44.9 | I27: =SUM(I4:I26) -> 28.3 | J27: =SUM(J4:J26) -> 1131.5
A29: BBVA
A30: INQUILINOS | B30: COMPROBANTE | C30: DETALLE | D30: LUZ | E30: AGUA | F30: ALQUILER | G30: ESPACIO | H30: DEPOSITO | I30: TICKET | J30: TOTAL
A31: VASQUEZ TAFUR SONIA ALBERTINA | B31: E001-360 | C31: 46113 | G31: 60 | J31: =SUM(D31:I31) -> 60
A32: COLINA SIRLEY | B32: RII 3341 | C32: 46023 | D32: 89.9 | E32: 6.4 | J32: =SUM(D32:I32) -> 96.3
C33: 46054 | D33: 88.6 | E33: 15 | J33: =SUM(D33:I33) -> 103.6
J36: =SUM(D36:I36) -> 0 | L36: TOTAL QR | M36: =J37+J47 -> 642.8
A37: TOTAL | J37: =SUM(J31:J36) -> 259.9
A39: BBVA
A40: SOCIOS | B40: RECIBO DE SERVICIO | C40: DETALLE | D40: LUZ | E40: AGUA | F40: G. ADM | G40: P. SOCIAL | H40: DEPOSITO | I40: P.S X FALLECIMIENTO | J40: TOTAL
A41: CUEVAS ENRIQUE | B41: RI 32933 | C41: 46082 | F41: 60 | G41: 5 | J41: =SUM(D41:I41) -> 65
A42: LUJAN JUAN | B42: RI 32934 | C42: 46054 | D42: 96.5 | E42: 21.4 | J42: =SUM(D42:I42) -> 117.9
A43: CALLE ALVAREZ MARCO | B43: RI 32935 | C43: 46082 | H43: 200 | J43: =SUM(D43:I43) -> 200
J44: =SUM(D44:I44) -> 0
J45: =SUM(D45:I45) -> 0
J46: =SUM(D46:I46) -> 0
A47: TOTAL | J47: =SUM(J41:J46) -> 382.9
A51: SOCIO | B51: RECIBO DE SERVICIO | C51: DETALLE | D51: LUZ | E51: AGUA | F51: G. ADM | G51: P. SOCIAL | H51: P.S X FALLECIMIENTO | I51: DEPOSITO | J51: TOTAL
J52: =SUM(D52:I52) -> 0
J53: =SUM(D53:I53) -> 0
J54: =SUM(D54:I54) -> 0
J55: =SUM(D55:I55) -> 0
J56: =SUM(D56:I56) -> 0
J57: =SUM(D57:I57) -> 0
J58: =SUM(D58:I58) -> 0
J59: =SUM(D59:I59) -> 0
J60: =SUM(D60:I60) -> 0
J61: =SUM(D61:I61) -> 0
J62: =SUM(D62:I62) -> 0
J63: =SUM(D63:I63) -> 0
... J65: =SUM(D65:I65) -> 0
A66: TOTAL | D66: =SUM(D52:D65) -> 0 | E66: =SUM(E52:E65) -> 0 | F66: =SUM(F52:F65) -> 0 | G66: =SUM(G52:G65) -> 0 | H66: =SUM(H52:H65) -> 0 | I66: =SUM(I52:I65) -> 0 | J66: =SUM(J52:J65) -> 0
A69: TOTAL DE INGRESOS | J69: =+J27+J66 -> 1131.5
A72: SRTA. FATIMA SIHUE
A73: COBRANZA SOCIOS
A74: COBRANZA INQUILINOS
A77: SRA. MARIA CUYA ARANGO
A78: COBRANZA DE BAÑO DEL 1ER PISO | J78: 495
A81: COBRANZA DE BAÑO DEL 2DO PISO
A83: TOTAL GENERAL DE INGRESOS | J83: =SUM(J69:J82) -> 1626.5
A85: EGRESOS DEL DIA 09-04-2026
A86: CAJA
A87: RESPONSABLE | B87: COMPROBANTE | C87: DETALLE | J87: TOTAL
A88: POMACANCHARI NICANOR | B88: RC 8603 | C88: LIMPIEZA DEL MERCADO DEL DIA 07-04-2026 Y 08-04-2026 | J88: 100
A89: SIHU FELIX FATIMA | B89: RC 8604 | C89: COMPRA DE 12 CACHANGAS PARA EL LONCHE DEL CONSEJO DE ADM | J89: 18
A90: CADENA DE COMERCIO PERU S.A.C. | B90: F349-00001070 | C90: 1 SPORADE DE 1.5 LT PARA LA SESION DEL CONSEJO DE ADM | J90: 5.5
A91: FERRETERIA Y MATIZADOS EL REY E.I.R.L. | B91: E001 1211 | C91: 2 FOCO BOTELLA LED Y 1 TUBO DE ABASTO (SSHH PRIMER PISO) PARA LA COOPERATIVA. | J91: 53
A92: AFP PRIMA | B92: 2526428901 | C92: PAGO DE AFP PRIMA | J92: 411.5
A93: AFP INTEGRA | B93: 5526430417 | C93: PAGO DE AFP INTEGRA | J93: 196
A94: AFP PROFUTURO | B94: 3526430697 | C94: PAGO DE AFP PROFUTURO | J94: 569.1
A99: TOTAL DE EGRESOS | J99: =SUM(J88:J98) -> 1353.1
A102: RESUMEN
A103: TOTAL GENERAL | B103: =+J83 -> 1626.5
A104: TOTAL DE EGRESOS | B104: =+J99 -> 1353.1
A105: SALDO | B105: =++B103-B104 -> 273.4

Sheet 10-04-2026
A1: INGRESOS DEL DIA 10-04-2026
A3: INQUILINO | B3: COMPROBANTE | C3: DETALLE | D3: LUZ | E3: AGUA | F3: ALQUILER | G3: ESPACIO | H3: PARQUEO | I3: TICKET | J3: TOTAL
A4: JOSE | B4: TK 50821 | C4: 46113 | I4: 10 | J4: =SUM(D4:I4) -> 10
J5: =SUM(D5:I5) -> 0
A6: ANATOLIA CHIPANA DE VARGAS | B6: EB01-7176 | C6: 46082 | G6: 100 | J6: =SUM(D6:I6) -> 100
A7: ORFELITA HERRERA CAMPOS | B7: EB01-7178 | C7: 46082 | F7: 200 | J7: =SUM(D7:I7) -> 200
A8: PARQUEO | B8: EB01-7181 | C8: 46113 | H8: 72 | J8: =SUM(D8:I8) -> 72
J9: =SUM(D9:I9) -> 0
J10: =SUM(D10:I10) -> 0
J11: =SUM(D11:I11) -> 0
J12: =SUM(D12:I12) -> 0
J13: =SUM(D13:I13) -> 0
J14: =SUM(D14:I14) -> 0
J15: =SUM(D15:I15) -> 0 | N15: 0
J16: =SUM(D16:I16) -> 0
J17: =SUM(D17:I17) -> 0
J18: =SUM(D18:I18) -> 0
J19: =SUM(D19:I19) -> 0
J20: =SUM(D20:I20) -> 0
J21: =SUM(D21:I21) -> 0
A22: TOTAL | D22: =SUM(D4:D21) -> 0 | E22: =SUM(E4:E21) -> 0 | F22: =SUM(F4:F21) -> 200 | G22: =SUM(G4:G21) -> 100 | H22: =SUM(H4:H21) -> 72 | I22: =SUM(I4:I21) -> 10 | J22: =SUM(J4:J21) -> 382
A24: BBVA
A25: INQUILINOS | B25: COMPROBANTE | C25: DETALLE | D25: LUZ | E25: AGUA | F25: ALQUILER | G25: ESPACIO | H25: DEPOSITO | I25: TICKET | J25: TOTAL
A26: ECO PLAZA MERCADO XI S.A.C. | B26: E001-362 | C26: 46113 | G26: 200 | J26: =SUM(D26:I26) -> 200
A27: ORFELITA HERRERA CAMPOS | B27: EB01-7177 | C27: 46082 | F27: 400 | J27: =SUM(D27:I27) -> 400
A28: MARCO ANTONIO SOTOMAYOR CARBAJAL | B28: EB01-7180 | C28: 46113 | G28: 30 | J28: =SUM(D28:I28) -> 30
J29: =SUM(D29:I29) -> 0 | L29: TOTAL QR | M29: =J30+J38 -> 756
A30: TOTAL | J30: =SUM(J26:J29) -> 630
A32: BBVA
A33: SOCIOS | B33: RECIBO DE SERVICIO | C33: DETALLE | D33: LUZ | E33: AGUA | F33: G. ADM | G33: P. SOCIAL | H33: DEPOSITO | I33: P.S X FALLECIMIENTO | J33: TOTAL
A34: LUJAN JUAN | B34: RI 32936 | C34: 46054 | F34: 56 | G34: 5 | J34: =SUM(D34:I34) -> 61
C35: 46082 | F35: 60 | G35: 5 | J35: =SUM(D35:I35) -> 65
J36: =SUM(D36:I36) -> 0
J37: =SUM(D37:I37) -> 0
A38: TOTAL | J38: =SUM(J34:J37) -> 126
A42: SOCIO | B42: RECIBO DE SERVICIO | C42: DETALLE | D42: LUZ | E42: AGUA | F42: G. ADM | G42: P. SOCIAL | H42: P.S X FALLECIMIENTO | I42: TALONARIO SANTA ROSA | J42: TOTAL
A43: ANULADO | B43: RI 32937 | J43: =SUM(D43:I43) -> 0
A44: FALCON HECTOR | B44: RI 32938 | C44: 45870 | I44: 15 | J44: =SUM(D44:I44) -> 15
C45: 46023 | F45: 60 | G45: 5 | H45: 10 | J45: =SUM(D45:I45) -> 75
C46: 46054 | F46: 56 | G46: 5 | J46: =SUM(D46:I46) -> 61
C47: 46082 | F47: 60 | G47: 5 | J47: =SUM(D47:I47) -> 65
C48: 46113 | F48: 60 | G48: 5 | J48: =SUM(D48:I48) -> 65
B49: RI 32939 | C49: 46143 | F49: 60 | G49: 5 | J49: =SUM(D49:I49) -> 65
C50: 46174 | F50: 60 | G50: 5 | J50: =SUM(D50:I50) -> 65
A51: SOSA JUANA | B51: RI 32940 | C51: 46023 | F51: 60 | G51: 5 | H51: 10 | J51: =SUM(D51:I51) -> 75
C52: 46054 | F52: 56 | G52: 5 | J52: =SUM(D52:I52) -> 61
C53: 46082 | F53: 60 | G53: 5 | J53: =SUM(D53:I53) -> 65
C54: 46113 | F54: 60 | G54: 5 | J54: =SUM(D54:I54) -> 65
B55: RI 32941 | C55: 46143 | F55: 60 | G55: 5 | J55: =SUM(D55:I55) -> 65
C56: 46174 | F56: 60 | G56: 5 | J56: =SUM(D56:I56) -> 65
J57: =SUM(D57:I57) -> 0
J58: =SUM(D58:I58) -> 0
J59: =SUM(D59:I59) -> 0
A60: TOTAL | D60: =SUM(D43:D59) -> 0 | E60: =SUM(E43:E59) -> 0 | F60: =SUM(F43:F59) -> 712 | G60: =SUM(G43:G59) -> 60 | H60: =SUM(H43:H59) -> 20 | I60: =SUM(I43:I59) -> 15 | J60: =SUM(J43:J59) -> 807
A63: TOTAL DE INGRESOS | J63: =+J22+J60 -> 1189
A66: SRTA. FATIMA SIHUE
A67: COBRANZA SOCIOS | J67: 1916
A68: COBRANZA INQUILINOS | J68: 2645 | K68: =J67+J68 -> 4561
K69: 100
K70: =K68+K69 -> 4661
A71: SRA. MARIA CUYA ARANGO | L71: 100 | M71: 20 | N71: =L71*M71 -> 2000
A72: COBRANZA DE BAÑO DEL 1ER PISO | J72: 502 | L72: 50 | M72: 26 | N72: =L72*M72 -> 1300
L73: 20 | M73: 62 | N73: =L73*M73 -> 1240
L74: 10 | M74: 9 | N74: =L74*M74 -> 90
A75: COBRANZA DE BAÑO DEL 2DO PISO | L75: 5 | M75: 3 | N75: =L75*M75 -> 15
L76: 2 | M76: 2 | N76: =L76*M76 -> 4
A77: TOTAL GENERAL DE INGRESOS | J77: =SUM(J63:J76) -> 6252 | L77: 1 | M77: 12 | N77: =L77*M77 -> 12
N78: =SUM(N71:N77) -> 4661
A79: EGRESOS DEL DIA 10-04-2026
A80: CAJA
A81: RESPONSABLE | B81: COMPROBANTE | C81: DETALLE | J81: TOTAL
A82: SAAVEDRA LUIS | B82: 14639 | C82: 2 PARES DE PILA AAA PARA EL TECLADO DE LA SECRETARIA DE LA OFICINA DE ADM | J82: 5
A83: PAREDES OSCAR | B83: RC 8605 | C83: PASAJE PARA IR A DEPOSITAR AL BANCO BBVA | J83: 6.5
A84: JAVIER ALFREDO VASQUEZ GARCIA | B84: 4859 | C84: ADELANTO DE SUELDO MES DE ABRIL 2026 | J84: 100
A90: TOTAL DE EGRESOS | J90: =SUM(J82:J89) -> 111.5
A93: RESUMEN
A94: TOTAL GENERAL | B94: =+J77 -> 6252
A95: TOTAL DE EGRESOS | B95: =+J90 -> 111.5
A96: SALDO | B96: =++B94-B95 -> 6140.5

Sheet 11-04-2026
A1: INGRESOS DEL DIA 11-04-2026
A3: INQUILINO | B3: COMPROBANTE | C3: DETALLE | D3: LUZ | E3: AGUA | F3: ALQUILER | G3: ESPACIO | H3: PARQUEO | I3: TICKET | J3: TOTAL
A4: ADMINISTRADORA DE SERVICIOS FUNERARIOS SAC | B4: E001-363 | C4: 46113 | G4: 30 | J4: =SUM(D4:I4) -> 30
J5: =SUM(D5:I5) -> 0
A6: JOSE | B6: TK 50822 | C6: 46113 | I6: 10 | J6: =SUM(D6:I6) -> 10
J7: =SUM(D7:I7) -> 0
A8: PARQUEO | B8: EB01-7183 | C8: 46113 | H8: 65 | J8: =SUM(D8:I8) -> 65
J9: =SUM(D9:I9) -> 0
J10: =SUM(D10:I10) -> 0
J11: =SUM(D11:I11) -> 0
J12: =SUM(D12:I12) -> 0
J13: =SUM(D13:I13) -> 0
J14: =SUM(D14:I14) -> 0
J15: =SUM(D15:I15) -> 0
J16: =SUM(D16:I16) -> 0
J17: =SUM(D17:I17) -> 0
J18: =SUM(D18:I18) -> 0
J19: =SUM(D19:I19) -> 0
J20: =SUM(D20:I20) -> 0
J21: =SUM(D21:I21) -> 0
A22: TOTAL | D22: =SUM(D4:D21) -> 0 | E22: =SUM(E4:E21) -> 0 | F22: =SUM(F4:F21) -> 0 | G22: =SUM(G4:G21) -> 30 | H22: =SUM(H4:H21) -> 65 | I22: =SUM(I4:I21) -> 10 | J22: =SUM(J4:J21) -> 105
A24: BBVA
A25: INQUILINOS | B25: COMPROBANTE | C25: DETALLE | D25: LUZ | E25: AGUA | F25: ALQUILER | G25: ESPACIO | H25: GARANTIA DE ALQ. | I25: TICKET | J25: TOTAL
A26: ROSA ARMANDINA RENTERIA HUANCAS | B26: EB01-7182 | C26: 46113 | F26: 500 | J26: =SUM(D26:I26) -> 500
B27: RII 3342 | C27: 46113 | H27: 1000 | J27: =SUM(D27:I27) -> 1000
J28: =SUM(D28:I28) -> 0
J29: =SUM(D29:I29) -> 0 | L29: TOTAL QR | M29: =J30+J38 -> 1500
A30: TOTAL | J30: =SUM(J26:J29) -> 1500
A32: BBVA
A33: SOCIOS | B33: RECIBO DE SERVICIO | C33: DETALLE | D33: LUZ | E33: AGUA | F33: G. ADM | G33: P. SOCIAL | H33: DEPOSITO | I33: P.S X FALLECIMIENTO | J33: TOTAL
J34: =SUM(D34:I34) -> 0
J35: =SUM(D35:I35) -> 0
J36: =SUM(D36:I36) -> 0
J37: =SUM(D37:I37) -> 0
A38: TOTAL | J38: =SUM(J34:J37) -> 0
A42: SOCIO | B42: RECIBO DE SERVICIO | C42: DETALLE | D42: LUZ | E42: AGUA | F42: G. ADM | G42: P. SOCIAL | H42: P.S X FALLECIMIENTO | I42: DEPOSITO | J42: TOTAL
J43: =SUM(D43:I43) -> 0
J44: =SUM(D44:I44) -> 0
J45: =SUM(D45:I45) -> 0
J46: =SUM(D46:I46) -> 0
J47: =SUM(D47:I47) -> 0
J48: =SUM(D48:I48) -> 0
J49: =SUM(D49:I49) -> 0
J50: =SUM(D50:I50) -> 0
J51: =SUM(D51:I51) -> 0
J52: =SUM(D52:I52) -> 0
J53: =SUM(D53:I53) -> 0
J54: =SUM(D54:I54) -> 0
... J56: =SUM(D56:I56) -> 0
A57: TOTAL | D57: =SUM(D43:D56) -> 0 | E57: =SUM(E43:E56) -> 0 | F57: =SUM(F43:F56) -> 0 | G57: =SUM(G43:G56) -> 0 | H57: =SUM(H43:H56) -> 0 | I57: =SUM(I43:I56) -> 0 | J57: =SUM(J43:J56) -> 0
A60: TOTAL DE INGRESOS | J60: =+J22+J57 -> 105
A63: SRTA. FATIMA SIHUE
A64: COBRANZA SOCIOS
A65: COBRANZA INQUILINOS
A68: SRA. MARIA CUYA ARANGO
A69: COBRANZA DE BAÑO DEL 1ER PISO | J69: 508.5
A72: COBRANZA DE BAÑO DEL 2DO PISO
A74: TOTAL GENERAL DE INGRESOS | J74: =SUM(J60:J73) -> 613.5
A76: EGRESOS DEL DIA 11-04-2026
A77: CAJA
A78: RESPONSABLE | B78: COMPROBANTE | C78: DETALLE | J78: TOTAL
A79: CORNEJO PILAR | B79: RC 8606 | C79: DIETA MES DE MARZO 2026 AL CARGO DE PRESIDENTA DEL CONSEJO DE VIGILANCIA | J79: 300
A89: TOTAL DE EGRESOS | J89: =SUM(J79:J88) -> 300
A92: RESUMEN
A93: TOTAL GENERAL | B93: =+J74 -> 613.5
A94: TOTAL DE EGRESOS | B94: =+J89 -> 300
A95: SALDO | B95: =++B93-B94 -> 313.5

Sheet 12-04-2026
A1: INGRESOS DEL DIA 12-04-2026
A3: INQUILINO | B3: COMPROBANTE | C3: DETALLE | D3: LUZ | E3: AGUA | F3: ALQUILER | G3: ESPACIO | H3: PARQUEO | I3: TICKET | J3: TOTAL
J4: =SUM(D4:I4) -> 0
J5: =SUM(D5:I5) -> 0
J6: =SUM(D6:I6) -> 0
J7: =SUM(D7:I7) -> 0
J8: =SUM(D8:I8) -> 0
J9: =SUM(D9:I9) -> 0
J10: =SUM(D10:I10) -> 0
J11: =SUM(D11:I11) -> 0
J12: =SUM(D12:I12) -> 0
J13: =SUM(D13:I13) -> 0
J14: =SUM(D14:I14) -> 0
J15: =SUM(D15:I15) -> 0
... J21: =SUM(D21:I21) -> 0
A22: TOTAL | D22: =SUM(D4:D21) -> 0 | E22: =SUM(E4:E21) -> 0 | F22: =SUM(F4:F21) -> 0 | H22: =SUM(H4:H21) -> 0 | I22: =SUM(I4:I21) -> 0 | J22: =SUM(J4:J21) -> 0
A24: BBVA
A25: INQUILINOS | B25: COMPROBANTE | C25: DETALLE | D25: LUZ | E25: AGUA | F25: ALQUILER | G25: ESPACIO | H25: DEPOSITO | I25: TICKET | J25: TOTAL
J26: =SUM(D26:I26) -> 0
J27: =SUM(D27:I27) -> 0
J28: =SUM(D28:I28) -> 0
J29: =SUM(D29:I29) -> 0 | L29: TOTAL QR | M29: =J30+J38 -> 0
A30: TOTAL | J30: =SUM(J26:J29) -> 0
A32: BBVA
A33: SOCIOS | B33: RECIBO DE SERVICIO | C33: DETALLE | D33: LUZ | E33: AGUA | F33: G. ADM | G33: P. SOCIAL | H33: DEPOSITO | I33: P.S X FALLECIMIENTO | J33: TOTAL
J34: =SUM(D34:I34) -> 0
J35: =SUM(D35:I35) -> 0
J36: =SUM(D36:I36) -> 0
J37: =SUM(D37:I37) -> 0
A38: TOTAL | J38: =SUM(J34:J37) -> 0
A42: SOCIO | B42: RECIBO DE SERVICIO | C42: DETALLE | D42: LUZ | E42: AGUA | F42: G. ADM | G42: P. SOCIAL | H42: P.S X FALLECIMIENTO | I42: DEPOSITO | J42: TOTAL
J43: =SUM(D43:I43) -> 0
J44: =SUM(D44:I44) -> 0
J45: =SUM(D45:I45) -> 0
J46: =SUM(D46:I46) -> 0
J47: =SUM(D47:I47) -> 0
J48: =SUM(D48:I48) -> 0
J49: =SUM(D49:I49) -> 0
J50: =SUM(D50:I50) -> 0
J51: =SUM(D51:I51) -> 0
J52: =SUM(D52:I52) -> 0
J53: =SUM(D53:I53) -> 0
J54: =SUM(D54:I54) -> 0
... J56: =SUM(D56:I56) -> 0
A57: TOTAL | D57: =SUM(D43:D56) -> 0 | E57: =SUM(E43:E56) -> 0 | F57: =SUM(F43:F56) -> 0 | G57: =SUM(G43:G56) -> 0 | H57: =SUM(H43:H56) -> 0 | I57: =SUM(I43:I56) -> 0 | J57: =SUM(J43:J56) -> 0
A60: TOTAL DE INGRESOS | J60: =+J22+J57 -> 0
A63: SRTA. FATIMA SIHUE
A64: COBRANZA SOCIOS
A65: COBRANZA INQUILINOS
A68: SRA. MARIA CUYA ARANGO
A69: COBRANZA DE BAÑO DEL 1ER PISO | J69: 566
A72: COBRANZA DE BAÑO DEL 2DO PISO
A74: TOTAL GENERAL DE INGRESOS | J74: =SUM(J60:J73) -> 566
A76: EGRESOS DEL DIA 12-04-2026
A77: CAJA
A78: RESPONSABLE | B78: COMPROBANTE | C78: DETALLE | J78: TOTAL
A92: TOTAL DE EGRESOS | J92: =SUM(J79:J91) -> 0
A95: RESUMEN
A96: TOTAL GENERAL | B96: =+J74 -> 566
A97: TOTAL DE EGRESOS | B97: =+J92 -> 0
A98: SALDO | B98: =++B96-B97 -> 566

Sheet 13-04-2026
A1: INGRESOS DEL DIA 13-04-2026
A3: INQUILINO | B3: COMPROBANTE | C3: DETALLE | D3: LUZ | E3: AGUA | F3: ALQUILER | G3: ESPACIO | H3: PARQUEO | I3: TICKET | J3: TOTAL
A4: JOSE | B4: TK 50823 | C4: 46113 | I4: 10 | J4: =SUM(D4:I4) -> 10
B5: TK 50824 | C5: 46113 | I5: 10 | J5: =SUM(D5:I5) -> 10
J6: =SUM(D6:I6) -> 0
J7: =SUM(D7:I7) -> 0
J8: =SUM(D8:I8) -> 0
J9: =SUM(D9:I9) -> 0
J10: =SUM(D10:I10) -> 0
J11: =SUM(D11:I11) -> 0
J12: =SUM(D12:I12) -> 0
J13: =SUM(D13:I13) -> 0
J14: =SUM(D14:I14) -> 0
J15: =SUM(D15:I15) -> 0
J16: =SUM(D16:I16) -> 0
J17: =SUM(D17:I17) -> 0
... J21: =SUM(D21:I21) -> 0
A22: TOTAL | D22: =SUM(D4:D21) -> 0 | E22: =SUM(E4:E21) -> 0 | F22: =SUM(F4:F21) -> 0 | H22: =SUM(H4:H21) -> 0 | I22: =SUM(I4:I21) -> 20 | J22: =SUM(J4:J21) -> 20
A24: BBVA
A25: INQUILINOS | B25: COMPROBANTE | C25: DETALLE | D25: LUZ | E25: AGUA | F25: ALQUILER | G25: ESPACIO | H25: DEPOSITO | I25: TICKET | J25: TOTAL
A26: ORFELITA HERRERA CAMPOS | B26: RII 3343 | C26: 46054 | D26: 30.4 | E26: 6 | J26: =SUM(D26:I26) -> 36.4
J27: =SUM(D27:I27) -> 0
J28: =SUM(D28:I28) -> 0
J29: =SUM(D29:I29) -> 0 | L29: TOTAL QR | M29: =J30+J38 -> 36.4
A30: TOTAL | J30: =SUM(J26:J29) -> 36.4
A32: BBVA
A33: SOCIOS | B33: RECIBO DE SERVICIO | C33: DETALLE | D33: LUZ | E33: AGUA | F33: G. ADM | G33: P. SOCIAL | H33: DEPOSITO | I33: P.S X FALLECIMIENTO | J33: TOTAL
J34: =SUM(D34:I34) -> 0
J35: =SUM(D35:I35) -> 0
J36: =SUM(D36:I36) -> 0
J37: =SUM(D37:I37) -> 0
A38: TOTAL | J38: =SUM(J34:J37) -> 0
A42: SOCIO | B42: RECIBO DE SERVICIO | C42: DETALLE | D42: LUZ | E42: AGUA | F42: G. ADM | G42: P. SOCIAL | H42: P.S X FALLECIMIENTO | I42: DEPOSITO | J42: TOTAL
A43: PORRAS OLIMPIA | B43: RI 32942 | C43: 46054 | D43: 5.9 | E43: 10 | F43: 56 | G43: 5 | J43: =SUM(D43:I43) -> 76.9
C44: 46082 | F44: 60 | G44: 5 | J44: =SUM(D44:I44) -> 65
J45: =SUM(D45:I45) -> 0
J46: =SUM(D46:I46) -> 0
J47: =SUM(D47:I47) -> 0
J48: =SUM(D48:I48) -> 0
J49: =SUM(D49:I49) -> 0
J50: =SUM(D50:I50) -> 0
J51: =SUM(D51:I51) -> 0
J52: =SUM(D52:I52) -> 0
J53: =SUM(D53:I53) -> 0
J54: =SUM(D54:I54) -> 0
J55: =SUM(D55:I55) -> 0
J56: =SUM(D56:I56) -> 0
A57: TOTAL | D57: =SUM(D43:D56) -> 5.9 | E57: =SUM(E43:E56) -> 10 | F57: =SUM(F43:F56) -> 116 | G57: =SUM(G43:G56) -> 10 | H57: =SUM(H43:H56) -> 0 | I57: =SUM(I43:I56) -> 0 | J57: =SUM(J43:J56) -> 141.9
A60: TOTAL DE INGRESOS | J60: =+J22+J57 -> 161.9
A63: SRTA. TATIANA VILLANUEVA
A64: COBRANZA SOCIOS
A65: COBRANZA INQUILINOS
A68: SRA. MARIA CUYA ARANGO
A69: COBRANZA DE BAÑO DEL 1ER PISO | J69: 349
A72: COBRANZA DE BAÑO DEL 2DO PISO
A74: TOTAL GENERAL DE INGRESOS | J74: =SUM(J60:J73) -> 510.9
A76: EGRESOS DEL DIA 13-04-2026
A77: CAJA
A78: RESPONSABLE | B78: COMPROBANTE | C78: DETALLE | J78: TOTAL
A79: NICHO ESTHEPANY | B79: 1638 | C79: 1 CABLE PODER PARA LA IMPRESORA DE LA OFICINA DE LA COOPERATIVA | J79: 15
A80: GARCIA AQUINO SANTOS | B80: E001-479 | C80: SERVICIO DE MANTENIMIENTO DE BROTHER - TONER AZUL Y NEGRO - SERVICIO DE KONICA MINOLTA 2 TONER (IMPRESORAS DE LA OFICINA DE LA COOPERATIVA) | J80: 535
A81: HURTADO PAZ WILDER | B81: 112181 | C81: VACACIONES TRUNCAS | J81: 462.9
A82: YACTAYO DE LA CRUZ RAQUEL ESMERALDA | B82: E001-172 | C82: MATERIALES PARA EL ARREGLO DE LOS SSHH DE DAMAS PRIMER PISO Y VARONES SEGUNDO PISO. | J82: 71.5
A89: TOTAL DE EGRESOS | J89: =SUM(J79:J88) -> 1084.4
A92: RESUMEN
A93: TOTAL GENERAL | B93: =+J74 -> 510.9
A94: TOTAL DE EGRESOS | B94: =+J89 -> 1084.4
A95: SALDO | B95: =++B93-B94 -> -573.5

Sheet 14-04-2026
A1: INGRESOS DEL DIA 14-04-2026
A3: INQUILINO | B3: COMPROBANTE | C3: DETALLE | D3: LUZ | E3: AGUA | F3: DEPOSITO | G3: ESPACIO | H3: PARQUEO | I3: TICKET | J3: TOTAL
A4: JOSE | B4: TK 50825 | C4: 46113 | I4: 10 | J4: =SUM(D4:I4) -> 10
J5: =SUM(D5:I5) -> 0
A6: ACCO VICTOR | B6: RII 3344 | C6: 46054 | F6: 150 | J6: =SUM(D6:I6) -> 150
C7: 46054 | F7: 150 | J7: =SUM(D7:I7) -> 150
C8: 46082 | F8: 150 | J8: =SUM(D8:I8) -> 150
C9: 46082 | F9: 150 | J9: =SUM(D9:I9) -> 150
J10: =SUM(D10:I10) -> 0
A11: PARQUEO | B11: EB01-7188 | C11: 46113 | H11: 70 | J11: =SUM(D11:I11) -> 70
J12: =SUM(D12:I12) -> 0
J13: =SUM(D13:I13) -> 0
J14: =SUM(D14:I14) -> 0
J15: =SUM(D15:I15) -> 0
J16: =SUM(D16:I16) -> 0
J17: =SUM(D17:I17) -> 0
J18: =SUM(D18:I18) -> 0
J19: =SUM(D19:I19) -> 0
J20: =SUM(D20:I20) -> 0
J21: =SUM(D21:I21) -> 0
A22: TOTAL | D22: =SUM(D4:D21) -> 0 | E22: =SUM(E4:E21) -> 0 | F22: =SUM(F4:F21) -> 600 | H22: =SUM(H4:H21) -> 70 | I22: =SUM(I4:I21) -> 10 | J22: =SUM(J4:J21) -> 680
A24: BBVA
A25: INQUILINOS | B25: COMPROBANTE | C25: DETALLE | D25: LUZ | E25: AGUA | F25: ALQUILER | G25: ESPACIO | H25: DEPOSITO | I25: TICKET | J25: TOTAL
A26: ADMINISTRADORA DE SERVICIOS FUNERARIOS SAC | B26: E001-364 | C26: 46113 | G26: 60 | J26: =SUM(D26:I26) -> 60
J27: =SUM(D27:I27) -> 0
J28: =SUM(D28:I28) -> 0
J29: =SUM(D29:I29) -> 0 | L29: TOTAL QR | M29: =J30+J38 -> 60
A30: TOTAL | J30: =SUM(J26:J29) -> 60
A32: BBVA
A33: SOCIOS | B33: RECIBO DE SERVICIO | C33: DETALLE | D33: LUZ | E33: AGUA | F33: G. ADM | G33: P. SOCIAL | H33: DEPOSITO | I33: P.S X FALLECIMIENTO | J33: TOTAL
J34: =SUM(D34:I34) -> 0
J35: =SUM(D35:I35) -> 0
J36: =SUM(D36:I36) -> 0
J37: =SUM(D37:I37) -> 0
A38: TOTAL | J38: =SUM(J34:J37) -> 0
A42: SOCIO | B42: RECIBO DE SERVICIO | C42: DETALLE | D42: LUZ | E42: AGUA | F42: G. ADM | G42: P. SOCIAL | H42: P.S X FALLECIMIENTO | I42: DEPOSITO | J42: TOTAL
A43: HUAMAN VISITACION | B43: RI 32943 | C43: 46082 | F43: 60 | G43: 5 | J43: =SUM(D43:I43) -> 65
J44: =SUM(D44:I44) -> 0
J45: =SUM(D45:I45) -> 0
J46: =SUM(D46:I46) -> 0
J47: =SUM(D47:I47) -> 0
J48: =SUM(D48:I48) -> 0
J49: =SUM(D49:I49) -> 0
J50: =SUM(D50:I50) -> 0
J51: =SUM(D51:I51) -> 0
J52: =SUM(D52:I52) -> 0
J53: =SUM(D53:I53) -> 0
J54: =SUM(D54:I54) -> 0
J55: =SUM(D55:I55) -> 0
J56: =SUM(D56:I56) -> 0
A57: TOTAL | D57: =SUM(D43:D56) -> 0 | E57: =SUM(E43:E56) -> 0 | F57: =SUM(F43:F56) -> 60 | G57: =SUM(G43:G56) -> 5 | H57: =SUM(H43:H56) -> 0 | I57: =SUM(I43:I56) -> 0 | J57: =SUM(J43:J56) -> 65
A60: TOTAL DE INGRESOS | J60: =+J22+J57 -> 745
A63: SRTA. FATIMA SIHUE
A64: COBRANZA SOCIOS
A65: COBRANZA INQUILINOS
A68: SRA. MARIA CUYA ARANGO
A69: COBRANZA DE BAÑO DEL 1ER PISO | J69: 494.5
A72: COBRANZA DE BAÑO DEL 2DO PISO
A74: TOTAL GENERAL DE INGRESOS | J74: =SUM(J60:J73) -> 1239.5
A76: EGRESOS DEL DIA 14-04-2026
A77: CAJA
A78: RESPONSABLE | B78: COMPROBANTE | C78: DETALLE | J78: TOTAL
A79: BUSTAMANTE JOSE | B79: RC 8607 | C79: PASAJE PARA IR A LA MUNICIPALIDAD, LLEVAR DOCUMENTACION | J79: 10
A89: TOTAL DE EGRESOS | J89: =SUM(J79:J88) -> 10
A92: RESUMEN
A93: TOTAL GENERAL | B93: =+J74 -> 1239.5
A94: TOTAL DE EGRESOS | B94: =+J89 -> 10
A95: SALDO | B95: =++B93-B94 -> 1229.5

Sheet 15-04-2026
A1: INGRESOS DEL DIA 15-04-2026
A3: INQUILINO | B3: COMPROBANTE | C3: DETALLE | D3: LUZ | E3: AGUA | F3: ALQUILER | G3: MULTA POR CAPACITACION | H3: PARQUEO | I3: TICKET | J3: TOTAL
A4: JOSE | B4: TK 50826 | C4: 46113 | I4: 10 | J4: =SUM(D4:I4) -> 10
J5: =SUM(D5:I5) -> 0
A6: QUISPE MARISOL | B6: EB01-7189 | C6: 46082 | F6: 100 | J6: =SUM(D6:I6) -> 100
A7: MARTHA ESPERANZA ALARCON ESPINOZA | B7: EB01-7191 | C7: 46082 | F7: 550 | J7: =SUM(D7:I7) -> 550
A8: ROSA PALOMINO CUSI | B8: EB01-7192 | C8: 46113 | F8: 650 | J8: =SUM(D8:I8) -> 650
A9: MIRIAN MILAGROS PRADO CATAÑO | B9: EB01-7193 | C9: 46082 | F9: 600 | J9: =SUM(D9:I9) -> 600
A10: ABEL ANCHAYA HUAMAN | B10: EB01-7194 | C10: 46023 | F10: 400 | J10: =SUM(D10:I10) -> 400
A11: SIMONA CHAMBI APAZA | B11: EB01-7195 | C11: 46054 | F11: 200 | J11: =SUM(D11:I11) -> 200
A12: JOSE ULISES BUSTAMANTE DE LA CRUZ | B12: EB01-7196 | C12: 45870 | F12: 150 | J12: =SUM(D12:I12) -> 150
C13: 45901 | F13: 150 | J13: =SUM(D13:I13) -> 150
A14: HECTOR AIRE MALPARTIDA | B14: EB01-7197 | C14: 46082 | F14: 100 | J14: =SUM(D14:I14) -> 100
A15: MERY RUTH CARRASCO PICHIHUA | B15: EB01-7198 | C15: 46082 | F15: 188 | J15: =SUM(D15:I15) -> 188
A16: LISBETH LUCIA MALLMA CONDORI | B16: EB01-7199 | C16: 46054 | F16: 191.6 | J16: =SUM(D16:I16) -> 191.6
A17: JANETT CONSUELO CASTRO RODRIGUEZ | B17: EB01-7200 | C17: 46054 | F17: 100 | J17: =SUM(D17:I17) -> 100
A18: DOMINICA LUCIANA FLORES LAREDO | B18: EB01-7201 | C18: 46054 | F18: 100 | J18: =SUM(D18:I18) -> 100
A19: ALEX ENRIQUE CAHUANA PUCURIMAY | B19: EB01-7202 | C19: 45992 | F19: 109 | J19: =SUM(D19:I19) -> 109
C20: 46023 | F20: 311.6 | J20: =SUM(D20:I20) -> 311.6
A21: MARLENE YAUYOS MENDIETA | B21: EB01-7204 | C21: 46023 | F21: 300 | J21: =SUM(D21:I21) -> 300
C22: 46054 | F22: 500 | J22: =SUM(D22:I22) -> 500
C23: 46082 | F23: 500 | J23: =SUM(D23:I23) -> 500
A24: PARQUEO | B24: EB01-7206 | C24: 46113 | H24: 74.5 | J24: =SUM(D24:I24) -> 74.5
J25: =SUM(D25:I25) -> 0
A26: CLAROS TORRES SANTOS JESUS | B26: RII 3346 | C26: 46054 | D26: 20 | J26: =SUM(D26:I26) -> 20
A27: MARTHA ESPERANZA ALARCON ESPINOZA | B27: RII 3348 | C27: 46082 | D27: 36 | E27: 15 | J27: =SUM(D27:I27) -> 51
A28: ROSA PALOMINO CUSI | B28: RII 3349 | C28: 46054 | D28: 21.4 | E28: 6 | J28: =SUM(D28:I28) -> 27.4
A29: PRADO MILAGROS | B29: RII 3350 | C29: 46054 | D29: 44 | E29: 6 | J29: =SUM(D29:I29) -> 50
A30: CHAMBI SIMONA | B30: RII 3351 | C30: 46023 | D30: 15 | E30: 3 | G30: 28.3 | J30: =SUM(D30:I30) -> 46.3
C31: 46054 | D31: 14.4 | E31: 6 | J31: =SUM(D31:I31) -> 20.4
A32: HECTOR AIRE MALPARTIDA | B32: RII 3352 | C32: 46023 | G32: 28.3 | J32: =SUM(D32:I32) -> 28.3
C33: 46054 | D33: 16 | E33: 11 | J33: =SUM(D33:I33) -> 27
A34: LISBETH LUCIA MALLMA CONDORI | B34: RII 3354 | C34: 46023 | D34: 36.2 | E34: 3 | G34: 28.3 | J34: =SUM(D34:I34) -> 67.5
C35: 46054 | D35: 34.9 | E35: 6 | J35: =SUM(D35:I35) -> 40.9
A36: ALEX ENRIQUE CAHUANA PUCURIMAY | B36: RII 3355 | C36: 46023 | D36: 20 | E36: 59.4 | J36: =SUM(D36:I36) -> 79.4
A37: MARLENE YAUYOS MENDIETA | B37: RII 3356 | C37: 45992 | D37: 10 | E37: 5 | J37: =SUM(D37:I37) -> 15
C38: 46023 | D38: 15 | E38: 3 | J38: =SUM(D38:I38) -> 18
C39: 46054 | D39: 14.4 | E39: 6 | J39: =SUM(D39:I39) -> 20.4
J40: =SUM(D40:I40) -> 0
J41: =SUM(D41:I41) -> 0
J42: =SUM(D42:I42) -> 0
A43: TOTAL | D43: =SUM(D4:D42) -> 297.3 | E43: =SUM(E4:E42) -> 129.4 | F43: =SUM(F4:F42) -> 5200.2 | G43: =SUM(G4:G42) -> 84.9 | H43: =SUM(H4:H42) -> 74.5 | I43: =SUM(I4:I42) -> 10 | J43: =SUM(J4:J42) -> 5796.3
A45: BBVA
A46: INQUILINOS | B46: COMPROBANTE | C46: DETALLE | D46: LUZ | E46: AGUA | F46: ALQUILER | G46: ESPACIO | H46: DEPOSITO | I46: MULTA POR CAPACITACION | J46: TOTAL
A47: CLAROS TORRES SANTOS JESUS | B47: E001-365 | C47: 46054 | F47: 50 | J47: =SUM(D47:I47) -> 50
C48: 46082 | F48: 150 | J48: =SUM(D48:I48) -> 150
A49: ANGIE MARGARITA LEON RODRIGUEZ | B49: EB01-7190 | C49: 46082 | F49: 850 | J49: =SUM(D49:I49) -> 850
A50: JESSICA PATRICIA SALDAÑA DONAYRE | B50: EB01-7203 | C50: 46023 | F50: 250 | J50: =SUM(D50:I50) -> 250
J51: =SUM(D51:I51) -> 0
A52: CLAROS TORRES SANTOS JESUS | B52: RII 3345 | C52: 46054 | D52: 0.1 | E52: 6 | J52: =SUM(D52:I52) -> 6.1
A53: ANGIE MARGARITA LEON RODRIGUEZ | B53: RII 3347 | C53: 46023 | I53: 28.3 | J53: =SUM(D53:I53) -> 28.3
C54: 46054 | D54: 16.1 | E54: 6 | J54: =SUM(D54:I54) -> 22.1
A55: SALAZAR MARIA | B55: RII 3353 | C55: 46054 | D55: 13.8 | E55: 6 | J55: =SUM(D55:I55) -> 19.8
A56: LEON RODRIUEZ ANGIE | B56: RII 3357 | C56: 46082 | D56: 39.6 | J56: =SUM(D56:I56) -> 39.6
J57: =SUM(D57:I57) -> 0
J58: =SUM(D58:I58) -> 0
J59: =SUM(D59:I59) -> 0
J60: =SUM(D60:I60) -> 0 | L60: TOTAL QR | M60: =J61+J69 -> 1415.9
A61: TOTAL | D61: =SUM(D47:D60) -> 69.6 | E61: =SUM(E47:E60) -> 18 | F61: =SUM(F47:F60) -> 1300 | G61: =SUM(G47:G60) -> 0 | H61: =SUM(H47:H60) -> 0 | I61: =SUM(I47:I60) -> 28.3 | J61: =SUM(J47:J60) -> 1415.9
A63: BBVA
A64: SOCIOS | B64: RECIBO DE SERVICIO | C64: DETALLE | D64: LUZ | E64: AGUA | F64: G. ADM | G64: P. SOCIAL | H64: DEPOSITO | I64: P.S X FALLECIMIENTO | J64: TOTAL
J65: =SUM(D65:I65) -> 0
J66: =SUM(D66:I66) -> 0
J67: =SUM(D67:I67) -> 0
J68: =SUM(D68:I68) -> 0
A69: TOTAL | J69: =SUM(J65:J68) -> 0
A73: SOCIO | B73: RECIBO DE SERVICIO | C73: DETALLE | D73: LUZ | E73: AGUA | F73: G. ADM | G73: P. SOCIAL | H73: P.S X FALLECIMIENTO | I73: DEPOSITO | J73: TOTAL
J74: =SUM(D74:I74) -> 0
J75: =SUM(D75:I75) -> 0
J76: =SUM(D76:I76) -> 0
J77: =SUM(D77:I77) -> 0
J78: =SUM(D78:I78) -> 0
J79: =SUM(D79:I79) -> 0
J80: =SUM(D80:I80) -> 0
J81: =SUM(D81:I81) -> 0
J82: =SUM(D82:I82) -> 0
J83: =SUM(D83:I83) -> 0
J84: =SUM(D84:I84) -> 0
J85: =SUM(D85:I85) -> 0
... J87: =SUM(D87:I87) -> 0
A88: TOTAL | D88: =SUM(D74:D87) -> 0 | E88: =SUM(E74:E87) -> 0 | F88: =SUM(F74:F87) -> 0 | G88: =SUM(G74:G87) -> 0 | H88: =SUM(H74:H87) -> 0 | I88: =SUM(I74:I87) -> 0 | J88: =SUM(J74:J87) -> 0
A91: TOTAL DE INGRESOS | J91: =+J43+J88 -> 5796.3
A94: SRTA. FATIMA SIHUE
A95: COBRANZA SOCIOS
A96: COBRANZA INQUILINOS
A99: SRA. MARIA CUYA ARANGO
A100: COBRANZA DE BAÑO DEL 1ER PISO | J100: 491
A103: COBRANZA DE BAÑO DEL 2DO PISO
A105: TOTAL GENERAL DE INGRESOS | J105: =SUM(J91:J104) -> 6287.3
A107: EGRESOS DEL DIA 15-04-2026
A108: CAJA
A109: RESPONSABLE | B109: COMPROBANTE | C109: DETALLE | J109: TOTAL
A110: MATIAS CAHUANA ACUÑA | B110: 1637 | C110: ADELANTO DE SUELDO MES DE ABRIL 2026 | J110: 600
A111: CARLOS ORMEÑO HERNANDEZ | B111: 2808 | C111: ADELANTO DE SUELDO MES DE ABRIL 2026 | J111: 600
A112: SANTOS PALOMINO CAMPOS | B112: 2809 | C112: ADELANTO DE SUELDO MES DE ABRIL 2026 | J112: 600
A113: NICANOR POMACANCHARI | B113: 2810 | C113: ADELANTO DE SUELDO MES DE ABRIL 2026 | J113: 600
A114: TUEROS PRUDENCIO | B114: 2811 | C114: ADELANTO DE SUELDO MES DE ABRIL 2026 | J114: 600
A115: MARIA CUYA ARANGO | B115: 2812 | C115: ADELANTO DE SUELDO MES DE ABRIL 2026 | J115: 600
A116: TATIANA | B116: 2813 | C116: ADELANTO DE SUELDO MES DE ABRIL 2026 | J116: 450
A117: FATIMA | B117: 7454 | C117: ADELANTO DE SUELDO MES DE ABRIL 2026 | J117: 600
...

Sheet 16-04-2026
A1: INGRESOS DEL DIA 16-04-2026
A3: INQUILINO | B3: COMPROBANTE | C3: DETALLE | D3: LUZ | E3: AGUA | F3: ALQUILER | G3: ESPACIO | H3: PARQUEO | I3: TICKET | J3: TOTAL
A4: JOSE | B4: TK 50827 | C4: 46113 | I4: 10 | J4: =SUM(D4:I4) -> 10
J5: =SUM(D5:I5) -> 0
A6: LISBETH KARITO QUISPE NAPUCHE | B6: EB01-7207 | C6: 46054 | F6: 300 | J6: =SUM(D6:I6) -> 300
A7: LUIS ABRAHAM SUAREZ REBAZA | B7: EB01-7208 | C7: 46082 | F7: 500 | J7: =SUM(D7:I7) -> 500
A8: SIRLEY KARINA COLINA CORREA | B8: EB01-7209 | C8: 46082 | F8: 1200 | J8: =SUM(D8:I8) -> 1200
A9: FLORENCIA ASUNTA ALVAREZ BERRIO | B9: EB01-7211 | C9: 46082 | F9: 700 | J9: =SUM(D9:I9) -> 700
A10: PARQUEO | B10: EB01-7213 | C10: 46113 | H10: 68 | J10: =SUM(D10:I10) -> 68
J11: =SUM(D11:I11) -> 0
J12: =SUM(D12:I12) -> 0
J13: =SUM(D13:I13) -> 0
J14: =SUM(D14:I14) -> 0
J15: =SUM(D15:I15) -> 0
J16: =SUM(D16:I16) -> 0
A17: TOTAL | D17: =SUM(D4:D16) -> 0 | E17: =SUM(E4:E16) -> 0 | F17: =SUM(F4:F16) -> 2700 | H17: =SUM(H4:H16) -> 68 | I17: =SUM(I4:I16) -> 10 | J17: =SUM(J4:J16) -> 2778
A19: BBVA
A20: INQUILINOS | B20: COMPROBANTE | C20: DETALLE | D20: LUZ | E20: AGUA | F20: ALQUILER | G20: ESPACIO | H20: DEPOSITO | I20: TICKET | J20: TOTAL
A21: ENTREMENTES SAC | B21: E001-366 | C21: 46113 | G21: 60 | J21: =SUM(D21:I21) -> 60
A22: MARIBEL GOMEZ MITMA | B22: EB01-7210 | C22: 46082 | G22: 100 | J22: =SUM(D22:I22) -> 100
J23: =SUM(D23:I23) -> 0
J24: =SUM(D24:I24) -> 0 | L24: TOTAL QR | M24: =J25+J33 -> 550.2
A25: TOTAL | J25: =SUM(J21:J24) -> 160
A27: BBVA
A28: SOCIOS | B28: RECIBO DE SERVICIO | C28: DETALLE | D28: LUZ | E28: AGUA | F28: G. ADM | G28: P. SOCIAL | H28: DEPOSITO | I28: P.S X FALLECIMIENTO | J28: TOTAL
A29: MARIN MARIA LUZ | B29: RI 32944 | C29: 46023 | H29: 97.2 | J29: =SUM(D29:I29) -> 97.2
C30: 46054 | D30: 22 | E30: 10 | F30: 56 | G30: 5 | H30: 200 | J30: =SUM(D30:I30) -> 293
J31: =SUM(D31:I31) -> 0
J32: =SUM(D32:I32) -> 0
A33: TOTAL | J33: =SUM(J29:J32) -> 390.2
A37: SOCIO | B37: RECIBO DE SERVICIO | C37: DETALLE | D37: LUZ | E37: AGUA | F37: G. ADM | G37: P. SOCIAL | H37: P.S X FALLECIMIENTO | I37: DEPOSITO | J37: TOTAL
A38: SALAZAR VICTORIA | B38: RI 32945 | C38: 46082 | F38: 60 | G38: 5 | J38: =SUM(D38:I38) -> 65
A39: ROJAS ERICK | B39: RI 32946 | C39: 46082 | F39: 20 | G39: 5 | J39: =SUM(D39:I39) -> 25
J40: =SUM(D40:I40) -> 0
J41: =SUM(D41:I41) -> 0
J42: =SUM(D42:I42) -> 0
J43: =SUM(D43:I43) -> 0
J44: =SUM(D44:I44) -> 0
J45: =SUM(D45:I45) -> 0
J46: =SUM(D46:I46) -> 0
J47: =SUM(D47:I47) -> 0
J48: =SUM(D48:I48) -> 0
A49: TOTAL | D49: =SUM(D38:D48) -> 0 | E49: =SUM(E38:E48) -> 0 | F49: =SUM(F38:F48) -> 80 | G49: =SUM(G38:G48) -> 10 | H49: =SUM(H38:H48) -> 0 | I49: =SUM(I38:I48) -> 0 | J49: =SUM(J38:J48) -> 90
A52: TOTAL DE INGRESOS | J52: =+J17+J49 -> 2868
A55: SRTA. FATIMA SIHUE
A56: COBRANZA SOCIOS
A57: COBRANZA INQUILINOS
A60: SRA. MARIA CUYA ARANGO
A61: COBRANZA DE BAÑO DEL 1ER PISO | J61: 486
A64: COBRANZA DE BAÑO DEL 2DO PISO
A66: TOTAL GENERAL DE INGRESOS | J66: =SUM(J52:J65) -> 3354
A68: EGRESOS DEL DIA 16-04-2026
A69: CAJA
A70: RESPONSABLE | B70: COMPROBANTE | C70: DETALLE | J70: TOTAL
A71: CASTILLO ZAPATA ASAEL | B71: EB01 - 31 | C71: PAD MOUSE PARA EL ESCRITORIO DE LA CONTADORA | J71: 15
A72: OXXO | B72: F349-00001091 | C72: 1 INKA COLA DE 3LT PARA LA SESION DEL CONSEJO DE ADM | J72: 11.9
A73: MPU CONTRATISTAS GENERALES S.A.C. | B73: 7765832788 | C73: DETRACCION DE LA FACTURA E001-331 | J73: 113
A74: SALDAÑA PATRICIA | B74: 887 | C74: 1 COCA DE 3LT PARA LA SESION DEL CONSEJO DE ADM | J74: 11
A81: TOTAL DE EGRESOS | J81: =SUM(J71:J80) -> 150.9
A84: RESUMEN
A85: TOTAL GENERAL | B85: =+J66 -> 3354
A86: TOTAL DE EGRESOS | B86: =+J81 -> 150.9
A87: SALDO | B87: =++B85-B86 -> 3203.1

Sheet 17-04-2026
A1: INGRESOS DEL DIA 17-04-2026
A3: INQUILINO | B3: COMPROBANTE | C3: DETALLE | D3: LUZ | E3: AGUA | F3: ALQUILER | G3: ESPACIO | H3: PARQUEO | I3: TICKET | J3: ALQUILER LOCAL 2DO PISO | K3: TOTAL
K4: =SUM(D4:J4) -> 0
K5: =SUM(D5:J5) -> 0
A6: ROMULO HUAMANI JANAMPA | B6: EB01-7214 | C6: 46113 | J6: 100 | K6: =SUM(D6:J6) -> 100
A7: BACILIO ANTONIO CAYO HUAMANI | B7: EB01-7216 | C7: 46082 | F7: 300 | K7: =SUM(D7:J7) -> 300
A8: PARQUEO | B8: EB01-7218 | C8: 46113 | H8: 54.6 | K8: =SUM(D8:J8) -> 54.6
K9: =SUM(D9:J9) -> 0
A10: ADMINISTRADORA DE SERVICIOS FUNERARIOS SAC | B10: E001-367 | C10: 46113 | G10: 30 | K10: =SUM(D10:J10) -> 30
K11: =SUM(D11:J11) -> 0
K12: =SUM(D12:J12) -> 0
K13: =SUM(D13:J13) -> 0
K14: =SUM(D14:J14) -> 0
K15: =SUM(D15:J15) -> 0
K16: =SUM(D16:J16) -> 0
K17: =SUM(D17:J17) -> 0
K18: =SUM(D18:J18) -> 0
K19: =SUM(D19:J19) -> 0
K20: =SUM(D20:J20) -> 0
K21: =SUM(D21:J21) -> 0
K22: =SUM(D22:J22) -> 0
A23: TOTAL | D23: =SUM(D4:D22) -> 0 | E23: =SUM(E4:E22) -> 0 | F23: =SUM(F4:F22) -> 300 | G23: =SUM(G4:G22) -> 30 | H23: =SUM(H4:H22) -> 54.6 | I23: =SUM(I4:I22) -> 0 | J23: =SUM(J4:J22) -> 100 | K23: =SUM(K4:K22) -> 484.6
A25: BBVA
A26: INQUILINOS | B26: COMPROBANTE | C26: DETALLE | D26: LUZ | E26: AGUA | F26: ALQUILER | G26: ESPACIO | H26: DEPOSITO | I26: TICKET | K26: TOTAL
A27: MARIANNE OLGA CELIA SANTIAGO JIMENEZ | B27: EB01-7215 | C27: 46113 | G27: 30 | K27: =SUM(D27:I27) -> 30
K29: =SUM(D29:I29) -> 0
K30: =SUM(D30:I30) -> 0 | M30: TOTAL QR | N30: =K31+K39 -> 30
A31: TOTAL | D31: =SUM(D27:D30) -> 0 | E31: =SUM(E27:E30) -> 0 | F31: =SUM(F27:F30) -> 0 | G31: =SUM(G27:G30) -> 30 | H31: =SUM(H27:H30) -> 0 | I31: =SUM(I27:I30) -> 0 | J31: =SUM(J27:J30) -> 0 | K31: =SUM(K27:K30) -> 30
A33: BBVA
A34: SOCIOS | B34: RECIBO DE SERVICIO | C34: DETALLE | D34: LUZ | E34: AGUA | F34: G. ADM | G34: P. SOCIAL | H34: DEPOSITO | I34: P.S X FALLECIMIENTO | K34: TOTAL
K35: =SUM(D35:I35) -> 0
K36: =SUM(D36:I36) -> 0
K37: =SUM(D37:I37) -> 0
K38: =SUM(D38:I38) -> 0
A39: TOTAL | D39: =SUM(D35:D38) -> 0 | E39: =SUM(E35:E38) -> 0 | F39: =SUM(F35:F38) -> 0 | G39: =SUM(G35:G38) -> 0 | H39: =SUM(H35:H38) -> 0 | I39: =SUM(I35:I38) -> 0 | J39: =SUM(J35:J38) -> 0 | K39: =SUM(K35:K38) -> 0
A43: SOCIO | B43: RECIBO DE SERVICIO | C43: DETALLE | D43: LUZ | E43: AGUA | F43: G. ADM | G43: P. SOCIAL | H43: P.S X FALLECIMIENTO | I43: DEPOSITO | J43: MULTA | K43: TOTAL
A44: ORTIZ WELINTONH | B44: RI 32947 | C44: 45962 | J44: 113 | K44: =SUM(D44:J44) -> 113
C45: 46054 | D45: 172.6 | E45: 13.3 | K45: =SUM(D45:J45) -> 185.9
C46: 46082 | J46: 113 | K46: =SUM(D46:J46) -> 113
A47: YRUPAILLA ISIDRO | B47: RI 32948 | C47: 46082 | F47: 60 | G47: 5 | K47: =SUM(D47:J47) -> 65
K48: =SUM(D48:J48) -> 0
K49: =SUM(D49:J49) -> 0
K50: =SUM(D50:J50) -> 0
K51: =SUM(D51:J51) -> 0
K52: =SUM(D52:J52) -> 0
K53: =SUM(D53:J53) -> 0
K54: =SUM(D54:J54) -> 0
K55: =SUM(D55:J55) -> 0
K56: =SUM(D56:J56) -> 0
K57: =SUM(D57:J57) -> 0
A58: TOTAL | D58: =SUM(D44:D57) -> 172.6 | E58: =SUM(E44:E57) -> 13.3 | F58: =SUM(F44:F57) -> 60 | G58: =SUM(G44:G57) -> 5 | H58: =SUM(H44:H57) -> 0 | I58: =SUM(I44:I57) -> 0 | K58: =SUM(K44:K57) -> 476.9
A61: TOTAL DE INGRESOS | K61: =+K23+K58 -> 961.5
A64: SRTA. TATIHANA VILLANUEVA
A65: COBRANZA SOCIOS | K65: 1834
A66: COBRANZA INQUILINOS | K66: 2745 | L66: =K65+K66 -> 4579
L67: 100
L68: =L66+L67 -> 4679
A69: SRA. MARIA CUYA ARANGO | M69: 100 | N69: 17 | O69: =N69*M69 -> 1700
A70: COBRANZA DE BAÑO DEL 1ER PISO | K70: 521 | M70: 50 | N70: 37 | O70: =N70*M70 -> 1850
M71: 20 | N71: 49 | O71: =N71*M71 -> 980
M72: 10 | N72: 12 | O72: =N72*M72 -> 120
A73: COBRANZA DE BAÑO DEL 2DO PISO | M73: 5 | N73: 1 | O73: =N73*M73 -> 5
M74: 2 | N74: 7 | O74: =N74*M74 -> 14
A75: TOTAL GENERAL DE INGRESOS | K75: =SUM(K61:K74) -> 6061.5 | M75: 1 | N75: 10 | O75: =N75*M75 -> 10
O76: =SUM(O69:O75) -> 4679
A77: EGRESOS DEL DIA 17-04-2026
A78: CAJA
A79: RESPONSABLE | B79: COMPROBANTE | C79: DETALLE | K79: TOTAL
A90: TOTAL DE EGRESOS | K90: =SUM(K80:K89) -> 0
A93: RESUMEN
A94: TOTAL GENERAL | B94: =+K75 -> 6061.5
A95: TOTAL DE EGRESOS | B95: =+K90 -> 0
A96: SALDO | B96: =++B94-B95 -> 6061.5

Sheet 18-04-2026
A1: INGRESOS DEL DIA 18-04-2026
A3: INQUILINO | B3: COMPROBANTE | C3: DETALLE | D3: LUZ | E3: AGUA | F3: ALQUILER | G3: ESPACIO | H3: PARQUEO | I3: TICKET | J3: ALQUILER LOCAL 2DO PISO | K3: TOTAL
A4: PARQUEO | B4: EB01-7219 | C4: 46113 | H4: 71.6 | K4: =SUM(D4:J4) -> 71.6
K5: =SUM(D5:J5) -> 0
K6: =SUM(D6:J6) -> 0
K7: =SUM(D7:J7) -> 0
K8: =SUM(D8:J8) -> 0
K9: =SUM(D9:J9) -> 0
K10: =SUM(D10:J10) -> 0
K11: =SUM(D11:J11) -> 0
K12: =SUM(D12:J12) -> 0
K13: =SUM(D13:J13) -> 0
K14: =SUM(D14:J14) -> 0
K15: =SUM(D15:J15) -> 0
K16: =SUM(D16:J16) -> 0
... K22: =SUM(D22:J22) -> 0
A23: TOTAL | D23: =SUM(D4:D22) -> 0 | E23: =SUM(E4:E22) -> 0 | F23: =SUM(F4:F22) -> 0 | G23: =SUM(G4:G22) -> 0 | H23: =SUM(H4:H22) -> 71.6 | I23: =SUM(I4:I22) -> 0 | J23: =SUM(J4:J22) -> 0 | K23: =SUM(K4:K22) -> 71.6
A25: BBVA
A26: INQUILINOS | B26: COMPROBANTE | C26: DETALLE | D26: LUZ | E26: AGUA | F26: ALQUILER | G26: ESPACIO | H26: DEPOSITO | I26: TICKET | K26: TOTAL
A27: VASQUEZ TAFUR SONIA ALBERTINA | B27: E001-368 | C27: 46113 | G27: 30 | K27: =SUM(D27:I27) -> 30
K29: =SUM(D29:I29) -> 0
K30: =SUM(D30:I30) -> 0 | M30: TOTAL QR | N30: =K31+K39 -> 30
A31: TOTAL | D31: =SUM(D27:D30) -> 0 | E31: =SUM(E27:E30) -> 0 | F31: =SUM(F27:F30) -> 0 | G31: =SUM(G27:G30) -> 30 | H31: =SUM(H27:H30) -> 0 | I31: =SUM(I27:I30) -> 0 | J31: =SUM(J27:J30) -> 0 | K31: =SUM(K27:K30) -> 30
A33: BBVA
A34: SOCIOS | B34: RECIBO DE SERVICIO | C34: DETALLE | D34: LUZ | E34: AGUA | F34: G. ADM | G34: P. SOCIAL | H34: DEPOSITO | I34: P.S X FALLECIMIENTO | K34: TOTAL
K35: =SUM(D35:I35) -> 0
K36: =SUM(D36:I36) -> 0
K37: =SUM(D37:I37) -> 0
K38: =SUM(D38:I38) -> 0
A39: TOTAL | D39: =SUM(D35:D38) -> 0 | E39: =SUM(E35:E38) -> 0 | F39: =SUM(F35:F38) -> 0 | G39: =SUM(G35:G38) -> 0 | H39: =SUM(H35:H38) -> 0 | I39: =SUM(I35:I38) -> 0 | J39: =SUM(J35:J38) -> 0 | K39: =SUM(K35:K38) -> 0
A43: SOCIO | B43: RECIBO DE SERVICIO | C43: DETALLE | D43: LUZ | E43: AGUA | F43: G. ADM | G43: P. SOCIAL | H43: P.S X FALLECIMIENTO | I43: DEPOSITO | J43: MULTA | K43: TOTAL
K50: =SUM(D50:J50) -> 0
K51: =SUM(D51:J51) -> 0
K52: =SUM(D52:J52) -> 0
K53: =SUM(D53:J53) -> 0
K54: =SUM(D54:J54) -> 0
K55: =SUM(D55:J55) -> 0
K56: =SUM(D56:J56) -> 0
K57: =SUM(D57:J57) -> 0
A58: TOTAL | D58: =SUM(D44:D57) -> 0 | E58: =SUM(E44:E57) -> 0 | F58: =SUM(F44:F57) -> 0 | G58: =SUM(G44:G57) -> 0 | H58: =SUM(H44:H57) -> 0 | I58: =SUM(I44:I57) -> 0 | K58: =SUM(K44:K57) -> 0
A61: TOTAL DE INGRESOS | K61: =+K23+K58 -> 71.6
A64: SRTA. TATIHANA VILLANUEVA
A65: COBRANZA SOCIOS
A66: COBRANZA INQUILINOS
A69: SRA. MARIA CUYA ARANGO
A70: COBRANZA DE BAÑO DEL 1ER PISO | K70: 491
A73: COBRANZA DE BAÑO DEL 2DO PISO
A75: TOTAL GENERAL DE INGRESOS | K75: =SUM(K61:K74) -> 562.6
A77: EGRESOS DEL DIA 18-04-2026
A78: CAJA
A79: RESPONSABLE | B79: COMPROBANTE | C79: DETALLE | K79: TOTAL
A80: IMAN SOLUCIONES GRAFICAS EIRL | B80: E001-83 | C80: ADELANTO DE PAGO PARA LA ELABORACION DE LOS TALONARIOS DEL DIA DE LA MADRE | K80: 410
A90: TOTAL DE EGRESOS | K90: =SUM(K80:K89) -> 410
A103: RESUMEN
A104: TOTAL GENERAL | B104: =+K75 -> 562.6
A105: TOTAL DE EGRESOS | B105: =+K90 -> 410
A106: SALDO | B106: =++B104-B105 -> 152.6

Sheet 19-04-2026
A1: INGRESOS DEL DIA 19-04-2026
A3: INQUILINO | B3: COMPROBANTE | C3: DETALLE | D3: LUZ | E3: AGUA | F3: ALQUILER | G3: ESPACIO | H3: PARQUEO | I3: TICKET | J3: ALQUILER LOCAL 2DO PISO | K3: TOTAL
K4: =SUM(D4:J4) -> 0
K5: =SUM(D5:J5) -> 0
K6: =SUM(D6:J6) -> 0
K7: =SUM(D7:J7) -> 0
K8: =SUM(D8:J8) -> 0
K9: =SUM(D9:J9) -> 0
K10: =SUM(D10:J10) -> 0
K11: =SUM(D11:J11) -> 0
K12: =SUM(D12:J12) -> 0
K13: =SUM(D13:J13) -> 0
K14: =SUM(D14:J14) -> 0
K15: =SUM(D15:J15) -> 0
... K22: =SUM(D22:J22) -> 0
A23: TOTAL | D23: =SUM(D4:D22) -> 0 | E23: =SUM(E4:E22) -> 0 | F23: =SUM(F4:F22) -> 0 | G23: =SUM(G4:G22) -> 0 | H23: =SUM(H4:H22) -> 0 | I23: =SUM(I4:I22) -> 0 | J23: =SUM(J4:J22) -> 0 | K23: =SUM(K4:K22) -> 0
A25: BBVA
A26: INQUILINOS | B26: COMPROBANTE | C26: DETALLE | D26: LUZ | E26: AGUA | F26: ALQUILER | G26: ESPACIO | H26: DEPOSITO | I26: TICKET | K26: TOTAL
K27: =SUM(D27:I27) -> 0
K29: =SUM(D29:I29) -> 0
K30: =SUM(D30:I30) -> 0 | M30: TOTAL QR | N30: =K31+K39 -> 0
A31: TOTAL | D31: =SUM(D27:D30) -> 0 | E31: =SUM(E27:E30) -> 0 | F31: =SUM(F27:F30) -> 0 | G31: =SUM(G27:G30) -> 0 | H31: =SUM(H27:H30) -> 0 | I31: =SUM(I27:I30) -> 0 | J31: =SUM(J27:J30) -> 0 | K31: =SUM(K27:K30) -> 0
A33: BBVA
A34: SOCIOS | B34: RECIBO DE SERVICIO | C34: DETALLE | D34: LUZ | E34: AGUA | F34: G. ADM | G34: P. SOCIAL | H34: DEPOSITO | I34: P.S X FALLECIMIENTO | K34: TOTAL
K35: =SUM(D35:I35) -> 0
K36: =SUM(D36:I36) -> 0
K37: =SUM(D37:I37) -> 0
K38: =SUM(D38:I38) -> 0
A39: TOTAL | D39: =SUM(D35:D38) -> 0 | E39: =SUM(E35:E38) -> 0 | F39: =SUM(F35:F38) -> 0 | G39: =SUM(G35:G38) -> 0 | H39: =SUM(H35:H38) -> 0 | I39: =SUM(I35:I38) -> 0 | J39: =SUM(J35:J38) -> 0 | K39: =SUM(K35:K38) -> 0
A43: SOCIO | B43: RECIBO DE SERVICIO | C43: DETALLE | D43: LUZ | E43: AGUA | F43: G. ADM | G43: P. SOCIAL | H43: P.S X FALLECIMIENTO | I43: DEPOSITO | J43: MULTA | K43: TOTAL
K44: =SUM(D44:J44) -> 0
K45: =SUM(D45:J45) -> 0
K46: =SUM(D46:J46) -> 0
K47: =SUM(D47:J47) -> 0
K48: =SUM(D48:J48) -> 0
K49: =SUM(D49:J49) -> 0
K50: =SUM(D50:J50) -> 0
K51: =SUM(D51:J51) -> 0
K52: =SUM(D52:J52) -> 0
K53: =SUM(D53:J53) -> 0
K54: =SUM(D54:J54) -> 0
K55: =SUM(D55:J55) -> 0
... K57: =SUM(D57:J57) -> 0
A58: TOTAL | D58: =SUM(D44:D57) -> 0 | E58: =SUM(E44:E57) -> 0 | F58: =SUM(F44:F57) -> 0 | G58: =SUM(G44:G57) -> 0 | H58: =SUM(H44:H57) -> 0 | I58: =SUM(I44:I57) -> 0 | K58: =SUM(K44:K57) -> 0
A61: TOTAL DE INGRESOS | K61: =+K23+K58 -> 0
A64: SRTA. TATIHANA VILLANUEVA
A65: COBRANZA SOCIOS
A66: COBRANZA INQUILINOS
A69: SRA. MARIA CUYA ARANGO
A70: COBRANZA DE BAÑO DEL 1ER PISO | K70: 486
A73: COBRANZA DE BAÑO DEL 2DO PISO
A75: TOTAL GENERAL DE INGRESOS | K75: =SUM(K61:K74) -> 486
A77: EGRESOS DEL DIA 19-04-2026
A78: CAJA
A79: RESPONSABLE | B79: COMPROBANTE | C79: DETALLE | K79: TOTAL
A90: TOTAL DE EGRESOS | K90: =SUM(K80:K89) -> 0
A93: RESUMEN
A94: TOTAL GENERAL | B94: =+K75 -> 486
A95: TOTAL DE EGRESOS | B95: =+K90 -> 0
A96: SALDO | B96: =++B94-B95 -> 486

Sheet 20-04-2026
A1: INGRESOS DEL DIA 20-04-2026
A3: INQUILINO | B3: COMPROBANTE | C3: DETALLE | D3: LUZ | E3: AGUA | F3: ALQUILER | G3: ESPACIO | H3: PARQUEO | I3: TICKET | J3: ALQUILER LOCAL 2DO PISO | K3: TOTAL
A4: JOSE | B4: TK 50828 | C4: 46113 | I4: 10 | K4: =SUM(D4:J4) -> 10
A5: JOSE DESARMADORES | B5: TK 50829 | C5: 46113 | I5: 10 | K5: =SUM(D5:J5) -> 10
A6: JOSE | B6: TK 50830 | C6: 46113 | I6: 10 | K6: =SUM(D6:J6) -> 10
K7: =SUM(D7:J7) -> 0
A8: TERESA PEÑA VDA DE VILLANUEVA | B8: EB01-7222 | C8: 46082 | F8: 600 | K8: =SUM(D8:J8) -> 600
A9: KARINA LUZ LUCIANO INGA | B9: EB01-7223 | C9: 46082 | F9: 300 | K9: =SUM(D9:J9) -> 300
A10: PARQUEO | B10: EB01-7225 | C10: 46113 | H10: 75.3 | K10: =SUM(D10:J10) -> 75.3
K11: =SUM(D11:J11) -> 0
A12: TERESA PEÑA VDA DE VILLANUEVA | B12: RII 33580 | C12: 46054 | D12: 14.4 | E12: 6 | K12: =SUM(D12:J12) -> 20.4
K13: =SUM(D13:J13) -> 0
K14: =SUM(D14:J14) -> 0
K15: =SUM(D15:J15) -> 0
K16: =SUM(D16:J16) -> 0
K17: =SUM(D17:J17) -> 0
K18: =SUM(D18:J18) -> 0
K19: =SUM(D19:J19) -> 0
K20: =SUM(D20:J20) -> 0
K21: =SUM(D21:J21) -> 0
K22: =SUM(D22:J22) -> 0
K23: =SUM(D23:J23) -> 0
K24: =SUM(D24:J24) -> 0
A25: TOTAL | D25: =SUM(D4:D24) -> 14.4 | E25: =SUM(E4:E24) -> 6 | F25: =SUM(F4:F24) -> 900 | G25: =SUM(G4:G24) -> 0 | H25: =SUM(H4:H24) -> 75.3 | I25: =SUM(I4:I24) -> 30 | J25: =SUM(J4:J24) -> 0 | K25: =SUM(K4:K24) -> 1025.7
A27: BBVA
A28: INQUILINOS | B28: COMPROBANTE | C28: DETALLE | D28: LUZ | E28: AGUA | F28: ALQUILER | G28: ESPACIO | H28: DEPOSITO | I28: TICKET | K28: TOTAL
A29: VISIONA TRADE S.A.C. | B29: E001-369 | C29: 46113 | G29: 30 | K29: =SUM(D29:I29) -> 30
A30: MARIELA CUNIAS SANTOS | B30: EB01-7224 | C30: 46113 | F30: 500 | K30: =SUM(D30:I30) -> 500
K31: =SUM(D31:I31) -> 0
K32: =SUM(D32:I32) -> 0 | M32: TOTAL QR | N32: =K33+K41 -> 1266.2
A33: TOTAL | D33: =SUM(D29:D32) -> 0 | E33: =SUM(E29:E32) -> 0 | F33: =SUM(F29:F32) -> 500 | G33: =SUM(G29:G32) -> 30 | H33: =SUM(H29:H32) -> 0 | I33: =SUM(I29:I32) -> 0 | J33: =SUM(J29:J32) -> 0 | K33: =SUM(K29:K32) -> 530
A35: BBVA
A36: SOCIOS | B36: RECIBO DE SERVICIO | C36: DETALLE | D36: LUZ | E36: AGUA | F36: G. ADM | G36: P. SOCIAL | H36: DEPOSITO | I36: P.S X FALLECIMIENTO | K36: TOTAL
A37: FLORES FLORES IRENE | B37: RI 32949 | C37: 46082 | D37: 552.8 | E37: 118.4 | F37: 60 | G37: 5 | K37: =SUM(D37:I37) -> 736.2
K38: =SUM(D38:I38) -> 0
K39: =SUM(D39:I39) -> 0
K40: =SUM(D40:I40) -> 0
A41: TOTAL | D41: =SUM(D37:D40) -> 552.8 | E41: =SUM(E37:E40) -> 118.4 | F41: =SUM(F37:F40) -> 60 | G41: =SUM(G37:G40) -> 5 | H41: =SUM(H37:H40) -> 0 | I41: =SUM(I37:I40) -> 0 | J41: =SUM(J37:J40) -> 0 | K41: =SUM(K37:K40) -> 736.2
A45: SOCIO | B45: RECIBO DE SERVICIO | C45: DETALLE | D45: LUZ | E45: AGUA | F45: G. ADM | G45: P. SOCIAL | H45: P.S X FALLECIMIENTO | I45: DEPOSITO | J45: MULTA | K45: TOTAL
K46: =SUM(D46:J46) -> 0
K47: =SUM(D47:J47) -> 0
K48: =SUM(D48:J48) -> 0
K49: =SUM(D49:J49) -> 0
K50: =SUM(D50:J50) -> 0
K51: =SUM(D51:J51) -> 0
K52: =SUM(D52:J52) -> 0
K53: =SUM(D53:J53) -> 0
K54: =SUM(D54:J54) -> 0
K55: =SUM(D55:J55) -> 0
K56: =SUM(D56:J56) -> 0
K57: =SUM(D57:J57) -> 0
... K59: =SUM(D59:J59) -> 0
A60: TOTAL | D60: =SUM(D46:D59) -> 0 | E60: =SUM(E46:E59) -> 0 | F60: =SUM(F46:F59) -> 0 | G60: =SUM(G46:G59) -> 0 | H60: =SUM(H46:H59) -> 0 | I60: =SUM(I46:I59) -> 0 | K60: =SUM(K46:K59) -> 0
A63: TOTAL DE INGRESOS | K63: =+K25+K60 -> 1025.7
A66: SRTA. TATIHANA VILLANUEVA
A67: COBRANZA SOCIOS
A68: COBRANZA INQUILINOS
A71: SRA. MARIA CUYA ARANGO
A72: COBRANZA DE BAÑO DEL 1ER PISO | K72: 342
A75: COBRANZA DE BAÑO DEL 2DO PISO
A77: TOTAL GENERAL DE INGRESOS | K77: =SUM(K63:K76) -> 1367.7
A79: EGRESOS DEL DIA 20-04-2026
A80: CAJA
A81: RESPONSABLE | B81: COMPROBANTE | C81: DETALLE | K81: TOTAL
A82: COTRINA MANRIQUE TITO | B82: E001-192 | C82: RETIRO DE PUERTA ENROLLABLE - DESINSTALACION DEL SISTEMA ELECTRICO DEL PUESTO 32-E. | K82: 140
A83: RAMIREZ ROSA | B83: RC 8610 | C83: REEMPLAZO DE LA SRA. DE LOS SSHH DEL PRIMER PISO DE LOS DIAS 05-04 ; 11-04 ; 12-04 Y 19-04. | K83: 320
A84: PAREDES FLORES OSCAR | B84: RC 8611 | C84: BOTAR DESMONTE DEL PUESTO 32-E. | K84: 80
A85: SERVICIOS GENERALES TOMANGUILLA-KUELAP | B85: N° E001-64 | C85: A CUENTA POR RECARGA DE 8 EXTINTORES DE 12 KG | K85: 100
A86: HERRERA ORFELITA | B86: RC 8612 | C86: ARREGLO DE COSTURA DE LA CHOMPA DEL VIGILANTE SR TUEROS QUISPE | K86: 7
A92: TOTAL DE EGRESOS | K92: =SUM(K82:K91) -> 647
A94: RESUMEN
A95: TOTAL GENERAL | B95: =+K77 -> 1367.7
A96: TOTAL DE EGRESOS | B96: =+K92 -> 647
A97: SALDO | B97: =++B95-B96 -> 720.7

Sheet 21-04-2026
A1: INGRESOS DEL DIA 21-04-2026
A3: INQUILINO | B3: COMPROBANTE | C3: DETALLE | D3: LUZ | E3: AGUA | F3: ALQUILER | G3: ESPACIO | H3: PARQUEO | I3: TICKET | J3: ALQUILER LOCAL 2DO PISO | K3: TOTAL
A4: JOSE | B4: TK 50831 | C4: 46113 | I4: 10 | K4: =SUM(D4:J4) -> 10
K5: =SUM(D5:J5) -> 0
A6: LILIA RUFINA ZANABRIA LADERA DE COCHACHI | B6: EB01-7227 | C6: 46082 | F6: 350 | K6: =SUM(D6:J6) -> 350
A7: PARQUEO | B7: EB01-7228 | C7: 46113 | H7: 55 | K7: =SUM(D7:J7) -> 55
K8: =SUM(D8:J8) -> 0
K9: =SUM(D9:J9) -> 0
K10: =SUM(D10:J10) -> 0
K11: =SUM(D11:J11) -> 0
K12: =SUM(D12:J12) -> 0
K13: =SUM(D13:J13) -> 0
A14: LILIA RUFINA ZANABRIA LADERA DE COCHACHI | B14: RII 3359 | C14: 46054 | D14: 19.1 | E14: 6 | K14: =SUM(D14:J14) -> 25.1
K15: =SUM(D15:J15) -> 0
K16: =SUM(D16:J16) -> 0
K17: =SUM(D17:J17) -> 0
K18: =SUM(D18:J18) -> 0
K19: =SUM(D19:J19) -> 0
K20: =SUM(D20:J20) -> 0
K21: =SUM(D21:J21) -> 0
K22: =SUM(D22:J22) -> 0
A23: TOTAL | D23: =SUM(D4:D22) -> 19.1 | E23: =SUM(E4:E22) -> 6 | F23: =SUM(F4:F22) -> 350 | G23: =SUM(G4:G22) -> 0 | H23: =SUM(H4:H22) -> 55 | I23: =SUM(I4:I22) -> 10 | J23: =SUM(J4:J22) -> 0 | K23: =SUM(K4:K22) -> 440.1
A25: BBVA
A26: INQUILINOS | B26: COMPROBANTE | C26: DETALLE | D26: LUZ | E26: AGUA | F26: ALQUILER | G26: ESPACIO | H26: DEPOSITO | I26: TICKET | K26: TOTAL
K27: =SUM(D27:I27) -> 0
K29: =SUM(D29:I29) -> 0
K30: =SUM(D30:I30) -> 0 | M30: TOTAL QR | N30: =K31+K39 -> 0
A31: TOTAL | D31: =SUM(D27:D30) -> 0 | E31: =SUM(E27:E30) -> 0 | F31: =SUM(F27:F30) -> 0 | G31: =SUM(G27:G30) -> 0 | H31: =SUM(H27:H30) -> 0 | I31: =SUM(I27:I30) -> 0 | J31: =SUM(J27:J30) -> 0 | K31: =SUM(K27:K30) -> 0
A33: BBVA
A34: SOCIOS | B34: RECIBO DE SERVICIO | C34: DETALLE | D34: LUZ | E34: AGUA | F34: G. ADM | G34: P. SOCIAL | H34: DEPOSITO | I34: P.S X FALLECIMIENTO | K34: TOTAL
K35: =SUM(D35:I35) -> 0
K36: =SUM(D36:I36) -> 0
K37: =SUM(D37:I37) -> 0
K38: =SUM(D38:I38) -> 0
A39: TOTAL | D39: =SUM(D35:D38) -> 0 | E39: =SUM(E35:E38) -> 0 | F39: =SUM(F35:F38) -> 0 | G39: =SUM(G35:G38) -> 0 | H39: =SUM(H35:H38) -> 0 | I39: =SUM(I35:I38) -> 0 | J39: =SUM(J35:J38) -> 0 | K39: =SUM(K35:K38) -> 0
A43: SOCIO | B43: RECIBO DE SERVICIO | C43: DETALLE | D43: LUZ | E43: AGUA | F43: G. ADM | G43: P. SOCIAL | H43: P.S X FALLECIMIENTO | I43: DEPOSITO | J43: MULTA | K43: TOTAL
A44: VILCHEZ LOURDES | B44: RI 32950 | C44: 46082 | D44: 766.5 | E44: 76 | I44: 200 | K44: =SUM(D44:J44) -> 1042.5
K45: =SUM(D45:J45) -> 0
K46: =SUM(D46:J46) -> 0
K47: =SUM(D47:J47) -> 0
K48: =SUM(D48:J48) -> 0
K49: =SUM(D49:J49) -> 0
K50: =SUM(D50:J50) -> 0
K51: =SUM(D51:J51) -> 0
K52: =SUM(D52:J52) -> 0
K53: =SUM(D53:J53) -> 0
K54: =SUM(D54:J54) -> 0
K55: =SUM(D55:J55) -> 0
K56: =SUM(D56:J56) -> 0
K57: =SUM(D57:J57) -> 0
A58: TOTAL | D58: =SUM(D44:D57) -> 766.5 | E58: =SUM(E44:E57) -> 76 | F58: =SUM(F44:F57) -> 0 | G58: =SUM(G44:G57) -> 0 | H58: =SUM(H44:H57) -> 0 | I58: =SUM(I44:I57) -> 200 | J58: =SUM(J44:J57) -> 0 | K58: =SUM(K44:K57) -> 1042.5
A61: TOTAL DE INGRESOS | K61: =+K23+K58 -> 1482.6
A64: SRTA. TATIHANA VILLANUEVA
A65: COBRANZA SOCIOS
A66: COBRANZA INQUILINOS
A69: SRA. MARIA CUYA ARANGO
A70: COBRANZA DE BAÑO DEL 1ER PISO | K70: 542.5
A73: COBRANZA DE BAÑO DEL 2DO PISO
A75: TOTAL GENERAL DE INGRESOS | K75: =SUM(K61:K74) -> 2025.1
A77: EGRESOS DEL DIA 21-04-2026
A78: CAJA
A79: RESPONSABLE | B79: COMPROBANTE | C79: DETALLE | K79: TOTAL
A80: LUISAO CARLOS TOMANGUILLA CACHAY | B80: N° E001-64 | C80: CANCELACION POR RECARGA DE 8 EXTINTORES DE 12 KG Y CAMBIO DE 2 RELOJ | K80: 104
A81: VILCHEZ LOURDES | B81: RC 8613 | C81: DIETA MES DE MARZO 2026 AL CARGO DE VOCAL SUPLENTE DEL CONSEJO DE ADM | K81: 150
A82: FERRETERIA Y MATIZADOS EL REY E.I.R.L. | B82: E001-1215 | C82: MATERIALES PARA EL ARREGLO DEL PUESTO 32-E | K82: 166.5
B83: E001-1216 | C83: MATERIALES PARA EL ARREGLO DEL PUESTO 32-E | K83: 510.5
A90: TOTAL DE EGRESOS | K90: =SUM(K80:K89) -> 931
A93: RESUMEN
A94: TOTAL GENERAL | B94: =+K75 -> 2025.1
A95: TOTAL DE EGRESOS | B95: =+K90 -> 931
A96: SALDO | B96: =++B94-B95 -> 1094.1

Sheet 22-04-2026
A1: INGRESOS DEL DIA 22-04-2026
A3: INQUILINO | B3: COMPROBANTE | C3: DETALLE | D3: LUZ | E3: AGUA | F3: ALQUILER | G3: TALONARIO SANTA ROSA | H3: PARQUEO | I3: TICKET | J3: ALQUILER LOCAL 2DO PISO | K3: TOTAL
A4: JOSE | B4: TK 50832 | C4: 46113 | I4: 10 | K4: =SUM(D4:J4) -> 10
K5: =SUM(D5:J5) -> 0
A6: CLAROS TORRES SANTOS JESUS | B6: E001-370 | C6: 46082 | F6: 150 | K6: =SUM(D6:J6) -> 150
K7: =SUM(D7:J7) -> 0
A8: JESSICA PATRICIA SALDAÑA DONAYRE | B8: EB01-7231 | C8: 46054 | F8: 100 | K8: =SUM(D8:J8) -> 100
A9: MARI SOL QUISPE CHAVEZ | B9: EB01-7232 | C9: 46082 | F9: 100 | K9: =SUM(D9:J9) -> 100
A10: MAXIMO FLAVIO HUAMANÍ CONTRERAS | B10: EB01-7233 | C10: 46113 | F10: 400 | K10: =SUM(D10:J10) -> 400
A11: CASILDA CATALINA REBAZA REBAZA | B11: EB01-7234 | C11: 46082 | F11: 350 | K11: =SUM(D11:J11) -> 350
A12: ABEL ANCHAYA HUAMAN | B12: EB01-7235 | C12: 46023 | F12: 200 | K12: =SUM(D12:J12) -> 200
C13: 46054 | F13: 100 | K13: =SUM(D13:J13) -> 100
A14: IDALINA MONTENEGRO BAUTISTA | B14: EB01-7237 | C14: 46082 | F14: 200 | K14: =SUM(D14:J14) -> 200
A15: JANETT CONSUELO CASTRO RODRIGUEZ | B15: EB01-7238 | C15: 46054 | F15: 100 | K15: =SUM(D15:J15) -> 100
A16: DAYSI ELIZABETH AZURZA TRIBIÑOS | B16: EB01-7239 | C16: 46082 | F16: 150 | K16: =SUM(D16:J16) -> 150
A17: ERIKA BENITES TRIBIÑOS | B17: EB01-7240 | C17: 46082 | F17: 150 | K17: =SUM(D17:J17) -> 150
A18: ASAEL CASTILLO ZAPATA | B18: EB01-7242 | C18: 46082 | F18: 300 | K18: =SUM(D18:J18) -> 300
A19: GLADIS ARREDONDO GARCIA | B19: EB01-7243 | C19: 46082 | F19: 100 | K19: =SUM(D19:J19) -> 100
A20: DOMINICA LUCIANA FLORES LAREDO | B20: EB01-7244 | C20: 46082 | F20: 100 | K20: =SUM(D20:J20) -> 100
A21: ELMER BURGA CARRASCO | B21: EB01-7245 | C21: 46082 | F21: 300 | K21: =SUM(D21:J21) -> 300
A22: LIDIA AGRIPINA CONDORI MAMANI | B22: EB01-7246 | C22: 46054 | F22: 200 | K22: =SUM(D22:J22) -> 200
A23: MERY RUTH CARRASCO PICHIHUA | B23: EB01-7249 | C23: 46082 | F23: 100 | K23: =SUM(D23:J23) -> 100
A24: HERNANDEZ HERNANDEZ LILIBETH MARIA | B24: EB01-7250 | C24: 46082 | F24: 200 | K24: =SUM(D24:J24) -> 200
A25: PARQUEO | B25: EB01-7252 | C25: 46113 | H25: 64 | K25: =SUM(D25:J25) -> 64
A27: REBAZA CASILDA | B27: RII 3360 | C27: 46082 | D27: 8 | E27: 6 | K27: =SUM(D27:J27) -> 14
A28: QUISPE PATRICIA | B28: RII 3362 | C28: 46054 | D28: 14.4 | E28: 6 | K28: =SUM(D28:J28) -> 20.4
C29: 46082 | D29: 5.6 | E29: 6 | K29: =SUM(D29:J29) -> 11.6
A30: CHOQUEHUANCA DERSE | B30: RII 3363 | C30: 46082 | D30: 6.3 | E30: 6 | K30: =SUM(D30:J30) -> 12.3
A31: CONDORI LIDIA | B31: RII 3364 | C31: 45870 | G31: 15 | K31: =SUM(D31:J31) -> 15
C32: 46054 | D32: 8.9 | E32: 6 | K32: =SUM(D32:J32) -> 14.9
C33: 46082 | D33: 6.5 | E33: 6 | K33: =SUM(D33:J33) -> 12.5
A34: ARMESTA JUANA | B34: RII 3368 | C34: 45931 | D34: 10.6 | E34: 6 | K34: =SUM(D34:J34) -> 16.6
C35: 45962 | D35: 8.5 | E35: 5 | K35: =SUM(D35:J35) -> 13.5
C36: 45992 | D36: 9.4 | E36: 5 | K36: =SUM(D36:J36) -> 14.4
C37: 46023 | D37: 11.6 | E37: 3 | K37: =SUM(D37:J37) -> 14.6
C38: 46054 | D38: 11.6 | E38: 6 | K38: =SUM(D38:J38) -> 17.6
B39: RII 3369 | C39: 46082 | D39: 9.6 | E39: 6 | K39: =SUM(D39:J39) -> 15.6
A40: MERY RUTH CARRASCO PICHIHUA | B40: RII 3370 | C40: 46082 | D40: 5.6 | E40: 15 | K40: =SUM(D40:J40) -> 20.6
A41: HERNANDEZ HERNANDEZ LILIBETH MARIA | B41: RII 3371 | C41: 46082 | D41: 34 | E41: 6 | K41: =SUM(D41:J41) -> 40
K42: =SUM(D42:J42) -> 0
K43: =SUM(D43:J43) -> 0
K44: =SUM(D44:J44) -> 0
A45: TOTAL | D45: =SUM(D4:D44) -> 150.6 | E45: =SUM(E4:E44) -> 88 | F45: =SUM(F4:F44) -> 3300 | G45: =SUM(G4:G44) -> 15 | H45: =SUM(H4:H44) -> 64 | I45: =SUM(I4:I44) -> 10 | J45: =SUM(J4:J44) -> 0 | K45: =SUM(K4:K44) -> 3627.6
A47: BBVA
A48: INQUILINOS | B48: COMPROBANTE | C48: DETALLE | D48: LUZ | E48: AGUA | F48: ALQUILER | G48: ESPACIO | H48: DEPOSITO | I48: TICKET | K48: TOTAL
A49: JESSICA PATRICIA SALDAÑA DONAYRE | B49: EB01-7230 | C49: 46023 | F49: 150 | K49: =SUM(D49:I49) -> 150
A50: IDALINA MONTENEGRO BAUTISTA | B50: EB01-7236 | C50: 46082 | F50: 100 | K50: =SUM(D50:I50) -> 100
A51: ASAEL CASTILLO ZAPATA | B51: EB01-7241 | C51: 46082 | F51: 400 | K51: =SUM(D51:I51) -> 400
A52: SANDRA LIZ MUJICA PALOMINO | B52: EB01-7247 | C52: 46054 | F52: 200 | K52: =SUM(D52:I52) -> 200
A53: LISBETH LUCIA MALLMA CONDORI | B53: EB01-7248 | C53: 46054 | F53: 100 | K53: =SUM(D53:I53) -> 100
A54: ZANABRIA LILIA | B54: RII 3361 | C54: 46082 | D54: 13.3 | E54: 6 | K54: =SUM(D54:I54) -> 19.3
A55: LEONARDO FEDERICO | B55: RII 3365 | C55: 45962 | D55: 9.2 | E55: 5 | K55: =SUM(D55:I55) -> 14.2
C56: 45992 | D56: 8.9 | E56: 5 | K56: =SUM(D56:I56) -> 13.9
C57: 46023 | D57: 7 | E57: 3 | K57: =SUM(D57:I57) -> 10
C58: 46054 | D58: 9 | E58: 6 | K58: =SUM(D58:I58) -> 15
B59: RII 3366 | C59: 46082 | D59: 7 | E59: 6 | K59: =SUM(D59:I59) -> 13
A60: LEONARDO ROSANA | B60: RII 3367 | C60: 45962 | D60: 37 | E60: 5 | K60: =SUM(D60:I60) -> 42
C61: 45992 | D61: 35.5 | E61: 5 | K61: =SUM(D61:I61) -> 40.5
C62: 46023 | D62: 30.8 | E62: 3 | K62: =SUM(D62:I62) -> 33.8
C63: 46054 | D63: 31.6 | E63: 6 | K63: =SUM(D63:I63) -> 37.6
C64: 46082 | D64: 27.4 | E64: 6 | K64: =SUM(D64:I64) -> 33.4
K65: =SUM(D65:I65) -> 0
A66: FERREYRA TANIA | B66: E001-371 | C66: 46113 | F66: 350 | K66: =SUM(D66:I66) -> 350
K67: =SUM(D67:I67) -> 0
K68: =SUM(D68:I68) -> 0 | M68: TOTAL QR | N68: =K69+K77 -> 1572.7
A69: TOTAL | D69: =SUM(D49:D68) -> 216.7 | E69: =SUM(E49:E68) -> 56 | F69: =SUM(F49:F68) -> 1300 | G69: =SUM(G49:G68) -> 0 | H69: =SUM(H49:H68) -> 0 | I69: =SUM(I49:I68) -> 0 | J69: =SUM(J49:J68) -> 0 | K69: =SUM(K49:K68) -> 1572.7
A71: BBVA
A72: SOCIOS | B72: RECIBO DE SERVICIO | C72: DETALLE | D72: LUZ | E72: AGUA | F72: G. ADM | G72: P. SOCIAL | H72: DEPOSITO | I72: P.S X FALLECIMIENTO | K72: TOTAL
K73: =SUM(D73:I73) -> 0
K74: =SUM(D74:I74) -> 0
K75: =SUM(D75:I75) -> 0
K76: =SUM(D76:I76) -> 0
A77: TOTAL | D77: =SUM(D73:D76) -> 0 | E77: =SUM(E73:E76) -> 0 | F77: =SUM(F73:F76) -> 0 | G77: =SUM(G73:G76) -> 0 | H77: =SUM(H73:H76) -> 0 | I77: =SUM(I73:I76) -> 0 | J77: =SUM(J73:J76) -> 0 | K77: =SUM(K73:K76) -> 0
A81: SOCIO | B81: RECIBO DE SERVICIO | C81: DETALLE | D81: LUZ | E81: AGUA | F81: G. ADM | G81: P. SOCIAL | H81: P.S X FALLECIMIENTO | I81: DEPOSITO | J81: MULTA | K81: TOTAL
A82: CUYA ALBERTO | B82: RI 32951 | C82: 46023 | D82: 39.4 | E82: 5 | K82: =SUM(D82:J82) -> 44.4
A83: BURGA ELIDA | B83: RI 32952 | C83: 46023 | D83: 34.4 | E83: 5 | F83: 60 | G83: 5 | K83: =SUM(D83:J83) -> 104.4
A84: QUISPE COPAYO ELIO | B84: RI 32953 | C84: 46082 | D84: 958.3 | E84: 64.1 | K84: =SUM(D84:J84) -> 1022.4
A85: REYES MILENA | B85: RI 32954 | C85: 46082 | D85: 1167.5 | E85: 16.7 | K85: =SUM(D85:J85) -> 1184.2
K86: =SUM(D86:J86) -> 0
K87: =SUM(D87:J87) -> 0
K88: =SUM(D88:J88) -> 0
K89: =SUM(D89:J89) -> 0
K90: =SUM(D90:J90) -> 0
K91: =SUM(D91:J91) -> 0
K92: =SUM(D92:J92) -> 0
K93: =SUM(D93:J93) -> 0
K94: =SUM(D94:J94) -> 0
K95: =SUM(D95:J95) -> 0
A96: TOTAL | D96: =SUM(D82:D95) -> 2199.6 | E96: =SUM(E82:E95) -> 90.8 | F96: =SUM(F82:F95) -> 60 | G96: =SUM(G82:G95) -> 5 | H96: =SUM(H82:H95) -> 0 | I96: =SUM(I82:I95) -> 0 | K96: =SUM(K82:K95) -> 2355.4
A99: TOTAL DE INGRESOS | K99: =+K45+K96 -> 5983
A102: SRTA. TATIHANA VILLANUEVA
A103: COBRANZA SOCIOS
A104: COBRANZA INQUILINOS
A107: SRA. MARIA CUYA ARANGO
A108: COBRANZA DE BAÑO DEL 1ER PISO | K108: 538
A111: COBRANZA DE BAÑO DEL 2DO PISO
A113: TOTAL GENERAL DE INGRESOS | K113: =SUM(K99:K112) -> 6521
A115: EGRESOS DEL DIA 22-04-2026
A116: CAJA
A117: RESPONSABLE | B117: COMPROBANTE | C117: DETALLE | K117: TOTAL
...

Sheet 23-04-2026
A1: INGRESOS DEL DIA 23-04-2026
A3: INQUILINO | B3: COMPROBANTE | C3: DETALLE | D3: LUZ | E3: AGUA | F3: ALQUILER | G3: ESPACIO | H3: PARQUEO | I3: TICKET | J3: ALQUILER LOCAL 2DO PISO | K3: TOTAL
A4: JOSE | B4: TK 50833 | C4: 46113 | I4: 10 | K4: =SUM(D4:J4) -> 10
K5: =SUM(D5:J5) -> 0
A6: PARQUEO | B6: EB01-7255 | C6: 46113 | H6: 59.5 | K6: =SUM(D6:J6) -> 59.5
K7: =SUM(D7:J7) -> 0
K8: =SUM(D8:J8) -> 0
K9: =SUM(D9:J9) -> 0
K10: =SUM(D10:J10) -> 0
K11: =SUM(D11:J11) -> 0
K12: =SUM(D12:J12) -> 0
K13: =SUM(D13:J13) -> 0
K14: =SUM(D14:J14) -> 0
K15: =SUM(D15:J15) -> 0
K16: =SUM(D16:J16) -> 0
K17: =SUM(D17:J17) -> 0
K18: =SUM(D18:J18) -> 0
... K22: =SUM(D22:J22) -> 0
A23: TOTAL | D23: =SUM(D4:D22) -> 0 | E23: =SUM(E4:E22) -> 0 | F23: =SUM(F4:F22) -> 0 | G23: =SUM(G4:G22) -> 0 | H23: =SUM(H4:H22) -> 59.5 | I23: =SUM(I4:I22) -> 10 | J23: =SUM(J4:J22) -> 0 | K23: =SUM(K4:K22) -> 69.5
A25: BBVA
A26: INQUILINOS | B26: COMPROBANTE | C26: DETALLE | D26: LUZ | E26: AGUA | F26: ALQUILER | G26: ESPACIO | H26: DEPOSITO | I26: TICKET | K26: TOTAL
A27: GLADYS ENCARNACION PAUCARPOMA | B27: EB01-7253 | C27: 46082 | F27: 500 | K27: =SUM(D27:I27) -> 500
B28: RII 3372 | C28: 46082 | D28: 29 | E28: 6 | K28: =SUM(D28:I28) -> 35
A29: MAPFRE PERU COMPAÑIA DE SEGUROS Y REASEGUROS | B29: E001-372 | C29: 46113 | G29: 30 | K29: =SUM(D29:I29) -> 30
K30: =SUM(D30:I30) -> 0 | M30: TOTAL QR | N30: =K31+K39 -> 565
A31: TOTAL | D31: =SUM(D27:D30) -> 29 | E31: =SUM(E27:E30) -> 6 | F31: =SUM(F27:F30) -> 500 | G31: =SUM(G27:G30) -> 30 | H31: =SUM(H27:H30) -> 0 | I31: =SUM(I27:I30) -> 0 | J31: =SUM(J27:J30) -> 0 | K31: =SUM(K27:K30) -> 565
A33: BBVA
A34: SOCIOS | B34: RECIBO DE SERVICIO | C34: DETALLE | D34: LUZ | E34: AGUA | F34: G. ADM | G34: P. SOCIAL | H34: DEPOSITO | I34: P.S X FALLECIMIENTO | K34: TOTAL
K35: =SUM(D35:I35) -> 0
K36: =SUM(D36:I36) -> 0
K37: =SUM(D37:I37) -> 0
K38: =SUM(D38:I38) -> 0
A39: TOTAL | D39: =SUM(D35:D38) -> 0 | E39: =SUM(E35:E38) -> 0 | F39: =SUM(F35:F38) -> 0 | G39: =SUM(G35:G38) -> 0 | H39: =SUM(H35:H38) -> 0 | I39: =SUM(I35:I38) -> 0 | J39: =SUM(J35:J38) -> 0 | K39: =SUM(K35:K38) -> 0
A43: SOCIO | B43: RECIBO DE SERVICIO | C43: DETALLE | D43: LUZ | E43: AGUA | F43: G. ADM | G43: P. SOCIAL | H43: P.S X FALLECIMIENTO | I43: DEPOSITO | J43: MULTA | K43: TOTAL
A44: TORRES FRANCISCO | B44: RI 32955 | C44: 46082 | D44: 52.4 | E44: 75 | K44: =SUM(D44:J44) -> 127.4
C45: 46113 | F45: 60 | G45: 5 | K45: =SUM(D45:J45) -> 65
A46: SALAS JUDITH | B46: RI 32956 | C46: 46082 | D46: 56.1 | K46: =SUM(D46:J46) -> 56.1
A47: QUISPE VIDAL | B47: RI 32957 | C47: 46082 | D47: 586.2 | E47: 17.2 | F47: 60 | G47: 5 | K47: =SUM(D47:J47) -> 668.4
A48: ESTELA ELVIA | B48: RI 32958 | C48: 46082 | D48: 232.4 | E48: 70.4 | F48: 60 | G48: 5 | K48: =SUM(D48:J48) -> 367.8
A49: SALAS JUDITH | B49: RI 32959 | C49: 46113 | F49: 60 | G49: 5 | K49: =SUM(D49:J49) -> 65
K50: =SUM(D50:J50) -> 0
K51: =SUM(D51:J51) -> 0
K52: =SUM(D52:J52) -> 0
K53: =SUM(D53:J53) -> 0
K54: =SUM(D54:J54) -> 0
K55: =SUM(D55:J55) -> 0
K56: =SUM(D56:J56) -> 0
K57: =SUM(D57:J57) -> 0
A58: TOTAL | D58: =SUM(D44:D57) -> 927.1 | E58: =SUM(E44:E57) -> 162.6 | F58: =SUM(F44:F57) -> 240 | G58: =SUM(G44:G57) -> 20 | H58: =SUM(H44:H57) -> 0 | I58: =SUM(I44:I57) -> 0 | K58: =SUM(K44:K57) -> 1349.7
A61: TOTAL DE INGRESOS | K61: =+K23+K58 -> 1419.2
A64: SRTA. TATIHANA VILLANUEVA
A65: COBRANZA SOCIOS
A66: COBRANZA INQUILINOS
A69: SRA. MARIA CUYA ARANGO
A70: COBRANZA DE BAÑO DEL 1ER PISO | K70: 546
A73: COBRANZA DE BAÑO DEL 2DO PISO
A75: TOTAL GENERAL DE INGRESOS | K75: =SUM(K61:K74) -> 1965.2
A77: EGRESOS DEL DIA 23-04-2026
A78: CAJA
A79: RESPONSABLE | B79: COMPROBANTE | C79: DETALLE | K79: TOTAL
A80: VILLAR RONCAL DIGNA | B80: F001-0003712 | C80: MATERIAL PARA EL ARRELO DEL PUESTO 32-E | K80: 24
A81: PODER JUDICIAL | B81: 67765 | C81: 09970 - Derecho de notificación judicial - CASO DIEGO | K81: 11.4
A82: SUNARP | B82: 1051398 | C82: COPIA LITERAL DE PARTIDA PARA REGISTROS PUBLICOS | K82: 19.8
A83: DELGADO SANCHEZ MARIA DENNIS | B83: E001-123 | C83: EMPANADAS PARA LA SESION DEL CONSEJO DE ADM. DEL DIA 16-04-2026 | K83: 64
A84: LAS DELICIAS | B84: F010-0015691 | C84: 1 TORTA POR EL CUMPLEAÑOS DE LA SRA MARIA SOTO | K84: 52
A85: VILLANUEVA TATIHANA | B85: RC 8621 | C85: PASAJE PARA LA COMPRA DE LA SRA MARIA SOTO POR SU CUMPLEAÑOS | K85: 2
A86: POMACANCHARI FELICES NICANOR | B86: E001- 86 | C86: ELABORACION DEL PISO DEL PUESTO 32-E Y PINTADO DE LA PUERTA ENROLLABLE | K86: 330
A87: SERGIO A. DEL CASTILLO | B87: F001-025747 | C87: LEGALIZACION DE FIRMA PARA REGISTROS PUBLICOS | K87: 330
A88: SALDAÑA PATRICIA | B88: 892 | C88: 1 VELA PARA LA TORTA DE LA SRA MARIA SOTO | K88: 5
A89: OXXO | B89: F349-00001113 | C89: 1 AGUA CIELO DE 2.5 LT Y 1 INKA KOLA DE 3LT PARA LA SESION DEL CONSEJO DE ADM. | K89: 15.6
A90: ZENAIDE BELLIDO DE LA TORRE | B90: 882 | C90: 1 JALON DE JABON LIQUIDO PARA LOS SSHH DEL PRIMER PISO | K90: 13.5
A91: TOTAL DE EGRESOS | K91: =SUM(K80:K90) -> 867.3
A94: RESUMEN
A95: TOTAL GENERAL | B95: =+K75 -> 1965.2
A96: TOTAL DE EGRESOS | B96: =+K91 -> 867.3
A97: SALDO | B97: =++B95-B96 -> 1097.9

Sheet 24-04-2026
A1: INGRESOS DEL DIA 24-04-2026
A3: INQUILINO | B3: COMPROBANTE | C3: DETALLE | D3: LUZ | E3: AGUA | F3: ALQUILER | G3: ESPACIO | H3: PARQUEO | I3: TICKET | J3: ALQUILER LOCAL 2DO PISO | K3: TOTAL
A4: JOSE | B4: TK 50834 | C4: 46113 | I4: 10 | K4: =SUM(D4:J4) -> 10
K5: =SUM(D5:J5) -> 0
A6: LISBETH KARITO QUISPE NAPUCHE | B6: EB01-7256 | C6: 46082 | F6: 300 | K6: =SUM(D6:J6) -> 300
A7: PARQUEO | B7: EB01-7258 | C7: 46113 | H7: 61.2 | K7: =SUM(D7:J7) -> 61.2
K8: =SUM(D8:J8) -> 0
K9: =SUM(D9:J9) -> 0
K10: =SUM(D10:J10) -> 0
K11: =SUM(D11:J11) -> 0
K12: =SUM(D12:J12) -> 0
K13: =SUM(D13:J13) -> 0
K14: =SUM(D14:J14) -> 0
K15: =SUM(D15:J15) -> 0
K16: =SUM(D16:J16) -> 0
K17: =SUM(D17:J17) -> 0
K18: =SUM(D18:J18) -> 0
K19: =SUM(D19:J19) -> 0
... K22: =SUM(D22:J22) -> 0
A23: TOTAL | D23: =SUM(D4:D22) -> 0 | E23: =SUM(E4:E22) -> 0 | F23: =SUM(F4:F22) -> 300 | G23: =SUM(G4:G22) -> 0 | H23: =SUM(H4:H22) -> 61.2 | I23: =SUM(I4:I22) -> 10 | J23: =SUM(J4:J22) -> 0 | K23: =SUM(K4:K22) -> 371.2
A25: BBVA
A26: INQUILINOS | B26: COMPROBANTE | C26: DETALLE | D26: LUZ | E26: AGUA | F26: ALQUILER | G26: ESPACIO | H26: DEPOSITO | I26: TICKET | K26: TOTAL
A27: VASQUEZ TAFUR SONIA ALBERTINA | B27: E001-373 | C27: 46113 | G27: 30 | K27: =SUM(D27:I27) -> 30
K29: =SUM(D29:I29) -> 0
K30: =SUM(D30:I30) -> 0 | M30: TOTAL QR | N30: =K31+K39 -> 30
A31: TOTAL | D31: =SUM(D27:D30) -> 0 | E31: =SUM(E27:E30) -> 0 | F31: =SUM(F27:F30) -> 0 | G31: =SUM(G27:G30) -> 30 | H31: =SUM(H27:H30) -> 0 | I31: =SUM(I27:I30) -> 0 | J31: =SUM(J27:J30) -> 0 | K31: =SUM(K27:K30) -> 30
A33: BBVA
A34: SOCIOS | B34: RECIBO DE SERVICIO | C34: DETALLE | D34: LUZ | E34: AGUA | F34: G. ADM | G34: P. SOCIAL | H34: DEPOSITO | I34: P.S X FALLECIMIENTO | K34: TOTAL
K35: =SUM(D35:I35) -> 0
K36: =SUM(D36:I36) -> 0
K37: =SUM(D37:I37) -> 0
K38: =SUM(D38:I38) -> 0
A39: TOTAL | D39: =SUM(D35:D38) -> 0 | E39: =SUM(E35:E38) -> 0 | F39: =SUM(F35:F38) -> 0 | G39: =SUM(G35:G38) -> 0 | H39: =SUM(H35:H38) -> 0 | I39: =SUM(I35:I38) -> 0 | J39: =SUM(J35:J38) -> 0 | K39: =SUM(K35:K38) -> 0
A43: SOCIO | B43: RECIBO DE SERVICIO | C43: DETALLE | D43: LUZ | E43: AGUA | F43: G. ADM | G43: P. SOCIAL | H43: P.S X FALLECIMIENTO | I43: DEPOSITO | J43: MULTA | K43: TOTAL
A44: CRUZ LUIS | B44: RI 32960 | C44: 46082 | D44: 23.3 | E44: 6 | K44: =SUM(D44:J44) -> 29.3
A45: BERNAOLA FLORENCIA | B45: RI 32961 | C45: 46082 | F45: 60 | G45: 5 | K45: =SUM(D45:J45) -> 65
K46: =SUM(D46:J46) -> 0
K47: =SUM(D47:J47) -> 0
K48: =SUM(D48:J48) -> 0
K49: =SUM(D49:J49) -> 0
K50: =SUM(D50:J50) -> 0
K51: =SUM(D51:J51) -> 0
K52: =SUM(D52:J52) -> 0
K53: =SUM(D53:J53) -> 0
K54: =SUM(D54:J54) -> 0
K55: =SUM(D55:J55) -> 0
K56: =SUM(D56:J56) -> 0
K57: =SUM(D57:J57) -> 0
A58: TOTAL | D58: =SUM(D44:D57) -> 23.3 | E58: =SUM(E44:E57) -> 6 | F58: =SUM(F44:F57) -> 60 | G58: =SUM(G44:G57) -> 5 | H58: =SUM(H44:H57) -> 0 | I58: =SUM(I44:I57) -> 0 | K58: =SUM(K44:K57) -> 94.3
A61: TOTAL DE INGRESOS | K61: =+K23+K58 -> 465.5
A64: SRTA. TATIHANA VILLANUEVA
A65: COBRANZA SOCIOS | K65: 1495
A66: COBRANZA INQUILINOS | K66: 2220 | L66: =K65+K66 -> 3715
L67: 100
L68: =L66+L67 -> 3815
A69: SRA. MARIA CUYA ARANGO | M69: 100 | N69: 19 | O69: =N69*M69 -> 1900
A70: COBRANZA DE BAÑO DEL 1ER PISO | K70: 520 | M70: 50 | N70: 21 | O70: =N70*M70 -> 1050
M71: 20 | N71: 37 | O71: =N71*M71 -> 740
M72: 10 | N72: 9 | O72: =N72*M72 -> 90
A73: COBRANZA DE BAÑO DEL 2DO PISO | M73: 5 | N73: 5 | O73: =N73*M73 -> 25
M74: 2 | N74: 4 | O74: =N74*M74 -> 8
A75: TOTAL GENERAL DE INGRESOS | K75: =SUM(K61:K74) -> 4700.5 | M75: 1 | N75: 2 | O75: =N75*M75 -> 2
O76: =SUM(O69:O75) -> 3815
A77: EGRESOS DEL DIA 24-04-2026
A78: CAJA
A79: RESPONSABLE | B79: COMPROBANTE | C79: DETALLE | K79: TOTAL
A80: PROMART | B80: FA01-02390172 | C80: BLOCKS DE VIDRIOS + PEGAMENTO PARA EL ARREGLO DEL TRAGLUZ DEL SEGUNDO PISO. | K80: 105.4
A81: PAREDE OSCAR | B81: RC 8622 | C81: PASAJE PARA IR A DEPOSITAR AL BANCO BBVA Y A COMPRAR A PROMART MATERIALES | K81: 22.5
A82: ACCO NOA VICTOR ALONSOACCO NOA VICTOR ALONSO | B82: EB01-1094 | C82: PLATOS DE TORTA Y CUCHARITAS POR EL CUMPLEAÑOS DE LA SRA MARIA SOTO | K82: 5
A90: TOTAL DE EGRESOS | K90: =SUM(K80:K89) -> 132.9
A93: RESUMEN
A94: TOTAL GENERAL | B94: =+K75 -> 4700.5
A95: TOTAL DE EGRESOS | B95: =+K90 -> 132.9
A96: SALDO | B96: =++B94-B95 -> 4567.6

Sheet 25-04-2026
A1: INGRESOS DEL DIA 25-04-2026
A3: INQUILINO | B3: COMPROBANTE | C3: DETALLE | D3: LUZ | E3: AGUA | F3: ALQUILER | G3: ESPACIO | H3: PARQUEO | I3: TICKET | J3: ALQUILER LOCAL 2DO PISO | K3: TOTAL
A4: JOSE | B4: TK 50835 | C4: 46113 | I4: 10 | K4: =SUM(D4:J4) -> 10
K5: =SUM(D5:J5) -> 0
A6: PARQUEO | B6: EB01-7260 | C6: 46113 | H6: 61.5 | K6: =SUM(D6:J6) -> 61.5
K7: =SUM(D7:J7) -> 0
K8: =SUM(D8:J8) -> 0
K9: =SUM(D9:J9) -> 0
K10: =SUM(D10:J10) -> 0
K11: =SUM(D11:J11) -> 0
K12: =SUM(D12:J12) -> 0
K13: =SUM(D13:J13) -> 0
K14: =SUM(D14:J14) -> 0
K15: =SUM(D15:J15) -> 0
K16: =SUM(D16:J16) -> 0
K17: =SUM(D17:J17) -> 0
K18: =SUM(D18:J18) -> 0
... K22: =SUM(D22:J22) -> 0
A23: TOTAL | D23: =SUM(D4:D22) -> 0 | E23: =SUM(E4:E22) -> 0 | F23: =SUM(F4:F22) -> 0 | G23: =SUM(G4:G22) -> 0 | H23: =SUM(H4:H22) -> 61.5 | I23: =SUM(I4:I22) -> 10 | J23: =SUM(J4:J22) -> 0 | K23: =SUM(K4:K22) -> 71.5
A25: BBVA
A26: INQUILINOS | B26: COMPROBANTE | C26: DETALLE | D26: LUZ | E26: AGUA | F26: ALQUILER | G26: ESPACIO | H26: DEPOSITO | I26: TICKET | K26: TOTAL
A27: VASQUEZ TAFUR SONIA ALBERTINA | B27: E001-374 | C27: 46113 | F27: 30 | K27: =SUM(D27:I27) -> 30
K29: =SUM(D29:I29) -> 0
K30: =SUM(D30:I30) -> 0 | M30: TOTAL QR | N30: =K31+K39 -> 30
A31: TOTAL | D31: =SUM(D27:D30) -> 0 | E31: =SUM(E27:E30) -> 0 | F31: =SUM(F27:F30) -> 30 | G31: =SUM(G27:G30) -> 0 | H31: =SUM(H27:H30) -> 0 | I31: =SUM(I27:I30) -> 0 | J31: =SUM(J27:J30) -> 0 | K31: =SUM(K27:K30) -> 30
A33: BBVA
A34: SOCIOS | B34: RECIBO DE SERVICIO | C34: DETALLE | D34: LUZ | E34: AGUA | F34: G. ADM | G34: P. SOCIAL | H34: DEPOSITO | I34: P.S X FALLECIMIENTO | K34: TOTAL
K35: =SUM(D35:I35) -> 0
K36: =SUM(D36:I36) -> 0
K37: =SUM(D37:I37) -> 0
K38: =SUM(D38:I38) -> 0
A39: TOTAL | D39: =SUM(D35:D38) -> 0 | E39: =SUM(E35:E38) -> 0 | F39: =SUM(F35:F38) -> 0 | G39: =SUM(G35:G38) -> 0 | H39: =SUM(H35:H38) -> 0 | I39: =SUM(I35:I38) -> 0 | J39: =SUM(J35:J38) -> 0 | K39: =SUM(K35:K38) -> 0
A43: SOCIO | B43: RECIBO DE SERVICIO | C43: DETALLE | D43: LUZ | E43: AGUA | F43: G. ADM | G43: P. SOCIAL | H43: P.S X FALLECIMIENTO | I43: DEPOSITO | J43: MULTA | K43: TOTAL
A44: ESPEJO ROSA | B44: RI 32962 | C44: 46082 | D44: 101.8 | E44: 6 | F44: 60 | G44: 5 | K44: =SUM(D44:J44) -> 172.8
A45: REYES NANCY | B45: RI 32963 | C45: 46082 | F45: 60 | G45: 5 | K45: =SUM(D45:J45) -> 65
K46: =SUM(D46:J46) -> 0
K47: =SUM(D47:J47) -> 0
K48: =SUM(D48:J48) -> 0
K49: =SUM(D49:J49) -> 0
K50: =SUM(D50:J50) -> 0
K51: =SUM(D51:J51) -> 0
K52: =SUM(D52:J52) -> 0
K53: =SUM(D53:J53) -> 0
K54: =SUM(D54:J54) -> 0
K55: =SUM(D55:J55) -> 0
K56: =SUM(D56:J56) -> 0
K57: =SUM(D57:J57) -> 0
A58: TOTAL | D58: =SUM(D44:D57) -> 101.8 | E58: =SUM(E44:E57) -> 6 | F58: =SUM(F44:F57) -> 120 | G58: =SUM(G44:G57) -> 10 | H58: =SUM(H44:H57) -> 0 | I58: =SUM(I44:I57) -> 0 | K58: =SUM(K44:K57) -> 237.8
A61: TOTAL DE INGRESOS | K61: =+K23+K58 -> 309.3
A64: SRTA. TATIHANA VILLANUEVA
A65: COBRANZA SOCIOS
A66: COBRANZA INQUILINOS
A69: SRA. MARIA CUYA ARANGO
A70: COBRANZA DE BAÑO DEL 1ER PISO | K70: 521.5
A73: COBRANZA DE BAÑO DEL 2DO PISO
A75: TOTAL GENERAL DE INGRESOS | K75: =SUM(K61:K74) -> 830.8
A77: EGRESOS DEL DIA 25-04-2026
A78: CAJA
A79: RESPONSABLE | B79: COMPROBANTE | C79: DETALLE | K79: TOTAL
A80: PAREDES FLORES OSCAR | B80: RC 8623 | C80: ALMUERZO POR EL DIA DE LA SECRETARIA | K80: 30
A90: TOTAL DE EGRESOS | K90: =SUM(K80:K89) -> 30
A93: RESUMEN
A94: TOTAL GENERAL | B94: =+K75 -> 830.8
A95: TOTAL DE EGRESOS | B95: =+K90 -> 30
A96: SALDO | B96: =++B94-B95 -> 800.8

Sheet 26-04-2026
A1: INGRESOS DEL DIA 26-04-2026
A3: INQUILINO | B3: COMPROBANTE | C3: DETALLE | D3: LUZ | E3: AGUA | F3: ALQUILER | G3: ESPACIO | H3: PARQUEO | I3: TICKET | J3: ALQUILER LOCAL 2DO PISO | K3: TOTAL
K4: =SUM(D4:J4) -> 0
K5: =SUM(D5:J5) -> 0
K6: =SUM(D6:J6) -> 0
K7: =SUM(D7:J7) -> 0
K8: =SUM(D8:J8) -> 0
K9: =SUM(D9:J9) -> 0
K10: =SUM(D10:J10) -> 0
K11: =SUM(D11:J11) -> 0
K12: =SUM(D12:J12) -> 0
K13: =SUM(D13:J13) -> 0
K14: =SUM(D14:J14) -> 0
K15: =SUM(D15:J15) -> 0
... K22: =SUM(D22:J22) -> 0
A23: TOTAL | D23: =SUM(D4:D22) -> 0 | E23: =SUM(E4:E22) -> 0 | F23: =SUM(F4:F22) -> 0 | G23: =SUM(G4:G22) -> 0 | H23: =SUM(H4:H22) -> 0 | I23: =SUM(I4:I22) -> 0 | J23: =SUM(J4:J22) -> 0 | K23: =SUM(K4:K22) -> 0
A25: BBVA
A26: INQUILINOS | B26: COMPROBANTE | C26: DETALLE | D26: LUZ | E26: AGUA | F26: ALQUILER | G26: ESPACIO | H26: DEPOSITO | I26: TICKET | K26: TOTAL
K27: =SUM(D27:I27) -> 0
K29: =SUM(D29:I29) -> 0
K30: =SUM(D30:I30) -> 0 | M30: TOTAL QR | N30: =K31+K39 -> 0
A31: TOTAL | D31: =SUM(D27:D30) -> 0 | E31: =SUM(E27:E30) -> 0 | F31: =SUM(F27:F30) -> 0 | G31: =SUM(G27:G30) -> 0 | H31: =SUM(H27:H30) -> 0 | I31: =SUM(I27:I30) -> 0 | J31: =SUM(J27:J30) -> 0 | K31: =SUM(K27:K30) -> 0
A33: BBVA
A34: SOCIOS | B34: RECIBO DE SERVICIO | C34: DETALLE | D34: LUZ | E34: AGUA | F34: G. ADM | G34: P. SOCIAL | H34: DEPOSITO | I34: P.S X FALLECIMIENTO | K34: TOTAL
K35: =SUM(D35:I35) -> 0
K36: =SUM(D36:I36) -> 0
K37: =SUM(D37:I37) -> 0
K38: =SUM(D38:I38) -> 0
A39: TOTAL | D39: =SUM(D35:D38) -> 0 | E39: =SUM(E35:E38) -> 0 | F39: =SUM(F35:F38) -> 0 | G39: =SUM(G35:G38) -> 0 | H39: =SUM(H35:H38) -> 0 | I39: =SUM(I35:I38) -> 0 | J39: =SUM(J35:J38) -> 0 | K39: =SUM(K35:K38) -> 0
A43: SOCIO | B43: RECIBO DE SERVICIO | C43: DETALLE | D43: LUZ | E43: AGUA | F43: G. ADM | G43: P. SOCIAL | H43: P.S X FALLECIMIENTO | I43: DEPOSITO | J43: MULTA | K43: TOTAL
K44: =SUM(D44:J44) -> 0
K45: =SUM(D45:J45) -> 0
K46: =SUM(D46:J46) -> 0
K47: =SUM(D47:J47) -> 0
K48: =SUM(D48:J48) -> 0
K49: =SUM(D49:J49) -> 0
K50: =SUM(D50:J50) -> 0
K51: =SUM(D51:J51) -> 0
K52: =SUM(D52:J52) -> 0
K53: =SUM(D53:J53) -> 0
K54: =SUM(D54:J54) -> 0
K55: =SUM(D55:J55) -> 0
... K57: =SUM(D57:J57) -> 0
A58: TOTAL | D58: =SUM(D44:D57) -> 0 | E58: =SUM(E44:E57) -> 0 | F58: =SUM(F44:F57) -> 0 | G58: =SUM(G44:G57) -> 0 | H58: =SUM(H44:H57) -> 0 | I58: =SUM(I44:I57) -> 0 | K58: =SUM(K44:K57) -> 0
A61: TOTAL DE INGRESOS | K61: =+K23+K58 -> 0
A64: SRTA. TATIHANA VILLANUEVA
A65: COBRANZA SOCIOS
A66: COBRANZA INQUILINOS
A69: SRA. MARIA CUYA ARANGO
A70: COBRANZA DE BAÑO DEL 1ER PISO | K70: 598
A73: COBRANZA DE BAÑO DEL 2DO PISO
A75: TOTAL GENERAL DE INGRESOS | K75: =SUM(K61:K74) -> 598
A77: EGRESOS DEL DIA 19-04-2026
A78: CAJA
A79: RESPONSABLE | B79: COMPROBANTE | C79: DETALLE | K79: TOTAL
A90: TOTAL DE EGRESOS | K90: =SUM(K80:K89) -> 0
A93: RESUMEN
A94: TOTAL GENERAL | B94: =+K75 -> 598
A95: TOTAL DE EGRESOS | B95: =+K90 -> 0
A96: SALDO | B96: =++B94-B95 -> 598

Sheet 27-04-2026
A1: INGRESOS DEL DIA 27-04-2026
A3: INQUILINO | B3: COMPROBANTE | C3: DETALLE | D3: LUZ | E3: AGUA | F3: ALQUILER | G3: ESPACIO | H3: PARQUEO | I3: TICKET | J3: FUMIGACION | K3: TOTAL
A4: JOSE | B4: TK 50836 | C4: 46113 | I4: 10 | K4: =SUM(D4:J4) -> 10
A5: JOSE DESARMADORES | B5: TK 50837 | C5: 46113 | I5: 10 | K5: =SUM(D5:J5) -> 10
A6: JOSE | B6: TK 50838 | C6: 46113 | I6: 10 | K6: =SUM(D6:J6) -> 10
A7: JOSE | B7: TK 50839 | C7: 46113 | I7: 10 | K7: =SUM(D7:J7) -> 10
K8: =SUM(D8:J8) -> 0
A9: EDGAR SALVADOR ALVAREZ CHIARA | B9: EB01-7262 | C9: 46082 | F9: 50 | K9: =SUM(D9:J9) -> 50
A10: PARQUEO | B10: EB01-7264 | C10: 46113 | H10: 70.7 | K10: =SUM(D10:J10) -> 70.7
K11: =SUM(D11:J11) -> 0
K12: =SUM(D12:J12) -> 0
A13: EDGAR SALVADOR ALVAREZ CHIARA | B13: RII 3373 | C13: 46054 | D13: 8.5 | E13: 6 | K13: =SUM(D13:J13) -> 14.5
C14: 46082 | D14: 8.1 | E14: 6 | K14: =SUM(D14:J14) -> 14.1
K15: =SUM(D15:J15) -> 0
K16: =SUM(D16:J16) -> 0
K17: =SUM(D17:J17) -> 0
A18: LOPEZ CERRON HAYDEE | B18: 11091 | C18: 46113 | J18: 5 | K18: =SUM(D18:J18) -> 5
A19: EDGAR SALVADOR ALVAREZ CHIARA | B19: 11092 | C19: 46113 | J19: 5 | K19: =SUM(D19:J19) -> 5
K20: =SUM(D20:J20) -> 0
K21: =SUM(D21:J21) -> 0
K22: =SUM(D22:J22) -> 0
K23: =SUM(D23:J23) -> 0
K24: =SUM(D24:J24) -> 0
A25: TOTAL | D25: =SUM(D4:D24) -> 16.6 | E25: =SUM(E4:E24) -> 12 | F25: =SUM(F4:F24) -> 50 | G25: =SUM(G4:G24) -> 0 | H25: =SUM(H4:H24) -> 70.7 | I25: =SUM(I4:I24) -> 40 | J25: =SUM(J4:J24) -> 10 | K25: =SUM(K4:K24) -> 199.3
A27: BBVA
A28: INQUILINOS | B28: COMPROBANTE | C28: DETALLE | D28: LUZ | E28: AGUA | F28: ALQUILER | G28: ESPACIO | H28: DEPOSITO | I28: TICKET | K28: TOTAL
A29: ADMINISTRADORA DE SERVICIOS FUNERARIOS SAC | B29: E001-375 | C29: 46113 | G29: 30 | K29: =SUM(D29:I29) -> 30
K31: =SUM(D31:I31) -> 0
K32: =SUM(D32:I32) -> 0 | M32: TOTAL QR | N32: =K33+K41 -> 679.1
A33: TOTAL | D33: =SUM(D29:D32) -> 0 | E33: =SUM(E29:E32) -> 0 | F33: =SUM(F29:F32) -> 0 | G33: =SUM(G29:G32) -> 30 | H33: =SUM(H29:H32) -> 0 | I33: =SUM(I29:I32) -> 0 | J33: =SUM(J29:J32) -> 0 | K33: =SUM(K29:K32) -> 30
A35: BBVA
A36: SOCIOS | B36: RECIBO DE SERVICIO | C36: DETALLE | D36: LUZ | E36: AGUA | F36: G. ADM | G36: P. SOCIAL | H36: DEPOSITO | I36: P.S X FALLECIMIENTO | K36: TOTAL
A37: CCOYLLO POLANCO DANIEL | B37: RI 32965 | C37: 46082 | D37: 335.2 | E37: 6 | F37: 60 | G37: 5 | K37: =SUM(D37:I37) -> 406.2
A38: REYES NANCY | B38: RI 32966 | C38: 46082 | D38: 227.9 | E38: 15 | K38: =SUM(D38:I38) -> 242.9
K39: =SUM(D39:I39) -> 0
K40: =SUM(D40:I40) -> 0
A41: TOTAL | D41: =SUM(D37:D40) -> 563.1 | E41: =SUM(E37:E40) -> 21 | F41: =SUM(F37:F40) -> 60 | G41: =SUM(G37:G40) -> 5 | H41: =SUM(H37:H40) -> 0 | I41: =SUM(I37:I40) -> 0 | J41: =SUM(J37:J40) -> 0 | K41: =SUM(K37:K40) -> 649.1
A45: SOCIO | B45: RECIBO DE SERVICIO | C45: DETALLE | D45: LUZ | E45: AGUA | F45: G. ADM | G45: P. SOCIAL | H45: P.S X FALLECIMIENTO | I45: FUMIGACION | J45: MULTA | K45: TOTAL
A46: DE LA CRUZ JOSE | B46: RI 32964 | C46: 46082 | D46: 74 | E46: 28.4 | K46: =SUM(D46:J46) -> 102.4
A47: ZAPATA ROSANA | B47: RI 32967 | C47: 46082 | F47: 60 | G47: 5 | K47: =SUM(D47:J47) -> 65
K48: =SUM(D48:J48) -> 0
K49: =SUM(D49:J49) -> 0
A50: MAYTA VIOLETA | B50: 11090 | C50: 46113 | I50: 5 | K50: =SUM(D50:J50) -> 5
A51: VARA ALICIA | B51: 11093 | C51: 46113 | I51: 5 | K51: =SUM(D51:J51) -> 5
K52: =SUM(D52:J52) -> 0
A53: MAYHUASCA CLUDY | B53: RI 32968 | C53: 46082 | D53: 358.6 | E53: 30 | K53: =SUM(D53:J53) -> 388.6
K54: =SUM(D54:J54) -> 0
K55: =SUM(D55:J55) -> 0
K56: =SUM(D56:J56) -> 0
K57: =SUM(D57:J57) -> 0
K58: =SUM(D58:J58) -> 0
K59: =SUM(D59:J59) -> 0
K60: =SUM(D60:J60) -> 0
A61: TOTAL | D61: =SUM(D46:D60) -> 432.6 | E61: =SUM(E46:E60) -> 58.4 | F61: =SUM(F46:F60) -> 60 | G61: =SUM(G46:G60) -> 5 | H61: =SUM(H46:H60) -> 0 | I61: =SUM(I46:I60) -> 10 | K61: =SUM(K46:K60) -> 566
A64: TOTAL DE INGRESOS | K64: =+K25+K61 -> 765.3
A67: SRTA. TATIHANA VILLANUEVA
A68: COBRANZA SOCIOS
A69: COBRANZA INQUILINOS
A72: SRA. MARIA CUYA ARANGO
A73: COBRANZA DE BAÑO DEL 1ER PISO | K73: 335.5
A76: COBRANZA DE BAÑO DEL 2DO PISO
A78: TOTAL GENERAL DE INGRESOS | K78: =SUM(K64:K77) -> 1100.8
A80: EGRESOS DEL DIA 27-04-2026
A81: CAJA
A82: RESPONSABLE | B82: COMPROBANTE | C82: DETALLE | K82: TOTAL
A83: SAAVEDRA LUIS | B83: 14777 | C83: 1/2 PLANCHA DE TECNOPOR PARA EL TRAGALUZ DEL SEGUNDO PISO | K83: 5
A84: ANCAJIMA CESAR | B84: 5381 | C84: ADELANTO PARA LA FABRICACIÓN E INSTALACIÓN DE PANELES METÁLICOS PARA EL PUESTO 32-E | K84: 2500
A85: ZENAIDE BELLIDO DE LA TORRE | B85: 883 | C85: 1 JALON DE JABON LIQUIDO PARA LOS SSHH DEL PRIMER PISO | K85: 13.5
A86: YACTAYO DE LA CRUZ RAQUEL ESMERALDA | B86: E001 189 | C86: MATERIAL PARA EL ARREGLO DEL TRAGALUZ DEL SEGUNDO PISO | K86: 37
A87: RAMIREZ ROSA | B87: RC 8624 | C87: REEMPLAZO DE LA SRA DE LOS SSHH DEL PRIMER PISO DEL DIA 26-04-2026 | K87: 80
A88: PAREDES FLORES OSCAR | B88: RC 8625 | C88: ARREGLO DE LA FUGA DEL CAÑO DEL SEGUNDO PISO | K88: 50
A93: TOTAL DE EGRESOS | K93: =SUM(K83:K92) -> 2685.5
A96: RESUMEN
A97: TOTAL GENERAL | B97: =+K78 -> 1100.8
A98: TOTAL DE EGRESOS | B98: =+K93 -> 2685.5
A99: SALDO | B99: =++B97-B98 -> -1584.7

Sheet 28-04-2026
A1: INGRESOS DEL DIA 28-04-2026
A3: INQUILINO | B3: COMPROBANTE | C3: DETALLE | D3: LUZ | E3: AGUA | F3: ALQUILER | G3: ESPACIO | H3: PARQUEO | I3: TICKET | J3: ALQUILER LOCAL 2DO PISO | K3: TOTAL
A4: JOSE | B4: TK 50840 | C4: 46113 | I4: 10 | K4: =SUM(D4:J4) -> 10
K5: =SUM(D5:J5) -> 0
A6: MARI SOL QUISPE CHAVEZ | B6: EB01-7265 | C6: 46082 | F6: 100 | K6: =SUM(D6:J6) -> 100
A7: PARQUEO | B7: EB01-7266 | C7: 46113 | H7: 66.4 | K7: =SUM(D7:J7) -> 66.4
K8: =SUM(D8:J8) -> 0
A9: ALVAREZ FLORENCIA | B9: RII 3374 | C9: 46054 | D9: 20.2 | E9: 6 | K9: =SUM(D9:J9) -> 26.2
C10: 46082 | D10: 19.7 | E10: 6 | K10: =SUM(D10:J10) -> 25.7
A11: YUPANQUI SAYDA | B11: RII 3375 | C11: 46054 | D11: 235.2 | E11: 6 | K11: =SUM(D11:J11) -> 241.2
K12: =SUM(D12:J12) -> 0
K13: =SUM(D13:J13) -> 0
K14: =SUM(D14:J14) -> 0
K15: =SUM(D15:J15) -> 0
K16: =SUM(D16:J16) -> 0
K17: =SUM(D17:J17) -> 0
K18: =SUM(D18:J18) -> 0
K19: =SUM(D19:J19) -> 0
K20: =SUM(D20:J20) -> 0
K21: =SUM(D21:J21) -> 0
K22: =SUM(D22:J22) -> 0
K23: =SUM(D23:J23) -> 0
A24: TOTAL | D24: =SUM(D4:D23) -> 275.1 | E24: =SUM(E4:E23) -> 18 | F24: =SUM(F4:F23) -> 100 | G24: =SUM(G4:G23) -> 0 | H24: =SUM(H4:H23) -> 66.4 | I24: =SUM(I4:I23) -> 10 | J24: =SUM(J4:J23) -> 0 | K24: =SUM(K4:K23) -> 469.5
A26: BBVA
A27: INQUILINOS | B27: COMPROBANTE | C27: DETALLE | D27: LUZ | E27: AGUA | F27: ALQUILER | G27: ESPACIO | H27: DEPOSITO | I27: TICKET | K27: TOTAL
K28: =SUM(D28:I28) -> 0
K30: =SUM(D30:I30) -> 0
K31: =SUM(D31:I31) -> 0 | M31: TOTAL QR | N31: =K32+K41 -> 867.2
A32: TOTAL | D32: =SUM(D28:D31) -> 0 | E32: =SUM(E28:E31) -> 0 | F32: =SUM(F28:F31) -> 0 | G32: =SUM(G28:G31) -> 0 | H32: =SUM(H28:H31) -> 0 | I32: =SUM(I28:I31) -> 0 | J32: =SUM(J28:J31) -> 0 | K32: =SUM(K28:K31) -> 0
A34: BBVA
A35: SOCIOS | B35: RECIBO DE SERVICIO | C35: DETALLE | D35: LUZ | E35: AGUA | F35: G. ADM | G35: P. SOCIAL | H35: DEPOSITO | I35: P.S X FALLECIMIENTO | K35: TOTAL
A36: ALVAREZ CAMPOS VICTOR | B36: RI 32969 | C36: 46113 | F36: 60 | G36: 5 | K36: =SUM(D36:I36) -> 65
A37: PALOMINO EUSEBIO | B37: RI 32970 | C37: 46082 | D37: 615.4 | E37: 40.3 | F37: 20 | G37: 5 | K37: =SUM(D37:I37) -> 680.7
A38: PLAZA ROSA | B38: RI 32972 | C38: 46082 | D38: 5 | E38: 6 | F38: 60 | G38: 5 | K38: =SUM(D38:I38) -> 76
A39: CUEVAS ENRIQUE | B39: RI 32975 | C39: 46082 | D39: 39.5 | E39: 6 | K39: =SUM(D39:I39) -> 45.5
K40: =SUM(D40:I40) -> 0
A41: TOTAL | D41: =SUM(D36:D40) -> 659.9 | E41: =SUM(E36:E40) -> 52.3 | F41: =SUM(F36:F40) -> 140 | G41: =SUM(G36:G40) -> 15 | H41: =SUM(H36:H40) -> 0 | I41: =SUM(I36:I40) -> 0 | J41: =SUM(J36:J40) -> 0 | K41: =SUM(K36:K40) -> 867.2
A45: SOCIO | B45: RECIBO DE SERVICIO | C45: DETALLE | D45: LUZ | E45: AGUA | F45: G. ADM | G45: P. SOCIAL | H45: FUMIGACION | I45: DEPOSITO | J45: MULTA | K45: TOTAL
A46: DE LA CRUZ JOSE | B46: 11094 | C46: 46082 | H46: 5 | K46: =SUM(D46:J46) -> 5
K47: =SUM(D47:J47) -> 0
A48: CHIRINOS MARIA | B48: RI 32971 | C48: 46082 | D48: 117.6 | E48: 22.2 | K48: =SUM(D48:J48) -> 139.8
A49: OQUENDO MIGUEL | B49: RI 32973 | C49: 46082 | D49: 554.7 | E49: 6 | K49: =SUM(D49:J49) -> 560.7
A50: QUISPE ADRIANA | B50: RI 32974 | C50: 46082 | D50: 376.2 | E50: 59 | K50: =SUM(D50:J50) -> 435.2
A51: PITTMAN NELLY | B51: RI 32976 | C51: 46082 | D51: 39.5 | E51: 6 | K51: =SUM(D51:J51) -> 45.5
A52: CORDOVA MARCO | B52: RI 32977 | C52: 46082 | D52: 47.4 | E52: 192.1 | F52: 60 | G52: 5 | K52: =SUM(D52:J52) -> 304.5
K53: =SUM(D53:J53) -> 0
K54: =SUM(D54:J54) -> 0
K55: =SUM(D55:J55) -> 0
K56: =SUM(D56:J56) -> 0
K57: =SUM(D57:J57) -> 0
K58: =SUM(D58:J58) -> 0
K59: =SUM(D59:J59) -> 0
A60: TOTAL | D60: =SUM(D46:D59) -> 1135.4 | E60: =SUM(E46:E59) -> 285.3 | F60: =SUM(F46:F59) -> 60 | G60: =SUM(G46:G59) -> 5 | H60: =SUM(H46:H59) -> 5 | I60: =SUM(I46:I59) -> 0 | K60: =SUM(K46:K59) -> 1490.7
A63: TOTAL DE INGRESOS | K63: =+K24+K60 -> 1960.2
A66: SRTA. TATIHANA VILLANUEVA
A67: COBRANZA SOCIOS
A68: COBRANZA INQUILINOS
A71: SRA. MARIA CUYA ARANGO
A72: COBRANZA DE BAÑO DEL 1ER PISO | K72: 539
A75: COBRANZA DE BAÑO DEL 2DO PISO
A77: TOTAL GENERAL DE INGRESOS | K77: =SUM(K63:K76) -> 2499.2
A79: EGRESOS DEL DIA 28-04-2026
A80: CAJA
A81: RESPONSABLE | B81: COMPROBANTE | C81: DETALLE | K81: TOTAL
A82: HUAMAN YCHPAS DIOSDADO | B82: FFF3-000321 | C82: 14 GALONES DE JABON LIQUIDO PARA LOS SSHH DEL PRIMER PISO | K82: 190
A83: PAREDES FLORES OSCAR | B83: RC 8626 | C83: PASAJE PARA IR A COMPRAR A CIUDAD DE DIOS GALONES DE JABON LIQUIDO | K83: 10
A92: TOTAL DE EGRESOS | K92: =SUM(K82:K91) -> 200
A95: RESUMEN
A96: TOTAL GENERAL | B96: =+K77 -> 2499.2
A97: TOTAL DE EGRESOS | B97: =+K92 -> 200
A98: SALDO | B98: =++B96-B97 -> 2299.2

Sheet 29-04-2026
A1: INGRESOS DEL DIA 29-04-2026
A3: INQUILINO | B3: COMPROBANTE | C3: DETALLE | D3: LUZ | E3: AGUA | F3: ALQUILER | G3: ESPACIO | H3: PARQUEO | I3: TICKET | J3: ALQUILER LOCAL 2DO PISO | K3: TOTAL
K4: =SUM(D4:J4) -> 0
K5: =SUM(D5:J5) -> 0
A6: CLAROS TORRES SANTOS JESUS | B6: E001-376 | C6: 46082 | F6: 150 | K6: =SUM(D6:J6) -> 150
K7: =SUM(D7:J7) -> 0
A8: AZURZA DAYSI | B8: RII 3376 | C8: 46082 | D8: 5.6 | E8: 6 | K8: =SUM(D8:J8) -> 11.6
A9: BENITES ERIKA | B9: RII 3377 | C9: 46082 | D9: 5.6 | E9: 6 | K9: =SUM(D9:J9) -> 11.6
A10: CHAMBI SIMONA | B10: RII 3378 | C10: 46082 | D10: 5.6 | E10: 6 | K10: =SUM(D10:J10) -> 11.6
A11: CLAROS SANTOS | B11: RII 3379 | C11: 46082 | D11: 20.1 | E11: 6 | K11: =SUM(D11:J11) -> 26.1
A12: DURAND BLANCA | B12: RII 3381 | C12: 46023 | D12: 36 | E12: 8 | K12: =SUM(D12:J12) -> 44
C13: 46082 | D13: 36 | E13: 15 | K13: =SUM(D13:J13) -> 51
A14: PFUÑO VICTOR | B14: RII 3382 | C14: 45992 | D14: 10 | E14: 5 | K14: =SUM(D14:J14) -> 15
C15: 46023 | D15: 15 | E15: 3 | K15: =SUM(D15:J15) -> 18
C16: 46054 | D16: 14.4 | E16: 6 | K16: =SUM(D16:J16) -> 20.4
K18: =SUM(D18:J18) -> 0
A19: ERIKA BENITES TRIBIÑOS | B19: EB01-7268 | C19: 46082 | F19: 220.4 | K19: =SUM(D19:J19) -> 220.4
A20: DAYSI ELIZABETH AZURZA TRIBIÑOS | B20: EB01-7269 | C20: 46082 | F20: 220.4 | K20: =SUM(D20:J20) -> 220.4
A21: SIMONA CHAMBI APAZA | B21: EB01-7270 | C21: 46054 | F21: 300 | K21: =SUM(D21:J21) -> 300
C22: 46082 | F22: 500 | K22: =SUM(D22:J22) -> 500
A23: ABEL ANCHAYA HUAMAN | B23: EB01-7272 | C23: 46054 | F23: 100 | K23: =SUM(D23:J23) -> 100
A24: JESSICA PATRICIA SALDAÑA DONAYRE | B24: EB01-7273 | C24: 46054 | F24: 300 | K24: =SUM(D24:J24) -> 300
A25: BLANCA NIEVES DURAND CHACÓN | B25: EB01-7274 | C25: 46113 | F25: 550 | K25: =SUM(D25:J25) -> 550
A26: LIDIA AGRIPINA CONDORI MAMANI | B26: EB01-7276 | C26: 46054 | F26: 100 | K26: =SUM(D26:J26) -> 100
A27: MARIBEL GOMEZ MITMA | B27: EB01-7278 | C27: 46082 | F27: 60 | K27: =SUM(D27:J27) -> 60
A28: PARQUEO | B28: EB01-7281 | C28: 46113 | H28: 59.5 | K28: =SUM(D28:J28) -> 59.5
K29: =SUM(D29:J29) -> 0
K30: =SUM(D30:J30) -> 0
K31: =SUM(D31:J31) -> 0
A32: TOTAL | D32: =SUM(D4:D31) -> 148.3 | E32: =SUM(E4:E31) -> 61 | F32: =SUM(F4:F31) -> 2500.8 | G32: =SUM(G4:G31) -> 0 | H32: =SUM(H4:H31) -> 59.5 | I32: =SUM(I4:I31) -> 0 | J32: =SUM(J4:J31) -> 0 | K32: =SUM(K4:K31) -> 2769.6
A34: BBVA
A35: INQUILINOS | B35: COMPROBANTE | C35: DETALLE | D35: LUZ | E35: AGUA | F35: ALQUILER | G35: ESPACIO | H35: DEPOSITO | I35: TICKET | K35: TOTAL
A36: JANETT CONSUELO CASTRO RODRIGUEZ | B36: EB01-7271 | C36: 46054 | F36: 150 | K36: =SUM(D36:I36) -> 150
C37: 46082 | F37: 50 | K37: =SUM(D37:I37) -> 50
A38: GABRIELA MILAGROS CAMARENA ESTRADA | B38: EB01-7275 | C38: 46113 | G38: 60 | K38: =SUM(D38:I38) -> 60
A39: MARIBEL GOMEZ MITMA | B39: EB01-7277 | C39: 46082 | F39: 40 | K39: =SUM(D39:I39) -> 40
A40: MARIA ROSARIO SALAZAR VASQUEZ | B40: EB01-7279 | C40: 46054 | F40: 100 | K40: =SUM(D40:I40) -> 100
A42: JESSICA PATRICIA SALDAÑA DONAYRE | B42: RII 3380 | C42: 46082 | D42: 50.5 | E42: 6 | K42: =SUM(D42:I42) -> 56.5
K43: =SUM(D43:I43) -> 0
K44: =SUM(D44:I44) -> 0
K45: =SUM(D45:I45) -> 0 | M45: TOTAL QR | N45: =K46+K54 -> 456.5
A46: TOTAL | D46: =SUM(D36:D45) -> 50.5 | E46: =SUM(E36:E45) -> 6 | F46: =SUM(F36:F45) -> 340 | G46: =SUM(G36:G45) -> 60 | H46: =SUM(H36:H45) -> 0 | I46: =SUM(I36:I45) -> 0 | J46: =SUM(J36:J45) -> 0 | K46: =SUM(K36:K45) -> 456.5
A48: BBVA
A49: SOCIOS | B49: RECIBO DE SERVICIO | C49: DETALLE | D49: LUZ | E49: AGUA | F49: G. ADM | G49: P. SOCIAL | H49: DEPOSITO | I49: P.S X FALLECIMIENTO | K49: TOTAL
K50: =SUM(D50:I50) -> 0
K51: =SUM(D51:I51) -> 0
K52: =SUM(D52:I52) -> 0
K53: =SUM(D53:I53) -> 0
A54: TOTAL | D54: =SUM(D50:D53) -> 0 | E54: =SUM(E50:E53) -> 0 | F54: =SUM(F50:F53) -> 0 | G54: =SUM(G50:G53) -> 0 | H54: =SUM(H50:H53) -> 0 | I54: =SUM(I50:I53) -> 0 | J54: =SUM(J50:J53) -> 0 | K54: =SUM(K50:K53) -> 0
A58: SOCIO | B58: RECIBO DE SERVICIO | C58: DETALLE | D58: LUZ | E58: AGUA | F58: G. ADM | G58: P. SOCIAL | H58: P.S X FALLECIMIENTO | I58: DEPOSITO | J58: MULTA | K58: TOTAL
A59: QUISPE LUCIANO | B59: RI 32978 | C59: 46082 | D59: 39.5 | E59: 6 | K59: =SUM(D59:J59) -> 45.5
A60: JUAREZ LEONOR | B60: RI 32979 | C60: 46082 | D60: 114.3 | E60: 211.4 | F60: 60 | G60: 5 | K60: =SUM(D60:J60) -> 390.7
A61: GUTIERREZ ROGER | B61: RI 32980 | C61: 46082 | D61: 81 | E61: 187.6 | F61: 60 | G61: 5 | K61: =SUM(D61:J61) -> 333.6
A62: VILLANUEVA ROSA | B62: RI 32981 | C62: 46082 | D62: 34.2 | E62: 6 | F62: 200 | K62: =SUM(D62:J62) -> 240.2
A63: MELO MARINA | B63: RI 32982 | C63: 46082 | D63: 708.2 | E63: 34.4 | K63: =SUM(D63:J63) -> 742.6
A64: CARTAGENA BENJAMIN | B64: RI 32983 | C64: 46082 | D64: 10.9 | E64: 24.9 | K64: =SUM(D64:J64) -> 35.8
A65: CARTAGENA ALVARO | B65: RI 32984 | C65: 46082 | I65: 200 | K65: =SUM(D65:J65) -> 200
A66: SAAVEDRA LUIS | B66: RI 32985 | C66: 46082 | D66: 50.5 | E66: 6 | F66: 52 | G66: 5 | K66: =SUM(D66:J66) -> 113.5
A67: BRAVO ANA | B67: RI 32986 | C67: 46082 | D67: 108.8 | E67: 6 | F67: 60 | G67: 5 | K67: =SUM(D67:J67) -> 179.8
A68: SANCHEZ LUCIA | B68: RI 32987 | C68: 46082 | D68: 25.6 | E68: 6 | F68: 60 | G68: 5 | K68: =SUM(D68:J68) -> 96.6
K69: =SUM(D69:J69) -> 0
K70: =SUM(D70:J70) -> 0
K71: =SUM(D71:J71) -> 0
K72: =SUM(D72:J72) -> 0
A73: TOTAL | D73: =SUM(D59:D72) -> 1173 | E73: =SUM(E59:E72) -> 488.3 | F73: =SUM(F59:F72) -> 492 | G73: =SUM(G59:G72) -> 25 | H73: =SUM(H59:H72) -> 0 | I73: =SUM(I59:I72) -> 200 | K73: =SUM(K59:K72) -> 2378.3
A76: TOTAL DE INGRESOS | K76: =+K32+K73 -> 5147.9
A79: SRTA. TATIHANA VILLANUEVA
A80: COBRANZA SOCIOS | K80: 1907
A81: COBRANZA INQUILINOS | K81: 1350 | L81: =K80+K81 -> 3257
L82: 100
L83: =SUM(L81:L82) -> 3357 | M83: 200 | N83: 1 | O83: =N83*M83 -> 200
A84: SRA. MARIA CUYA ARANGO | M84: 100 | N84: 12 | O84: =N84*M84 -> 1200
A85: COBRANZA DE BAÑO DEL 1ER PISO | K85: 534 | M85: 50 | N85: 18 | O85: =N85*M85 -> 900
M86: 20 | N86: 51 | O86: =N86*M86 -> 1020
M87: 10 | N87: 2 | O87: =N87*M87 -> 20
A88: COBRANZA DE BAÑO DEL 2DO PISO | M88: 5 | N88: 1 | O88: =N88*M88 -> 5
M89: 1 | N89: 10 | O89: =N89*M89 -> 10
A90: TOTAL GENERAL DE INGRESOS | K90: =SUM(K76:K89) -> 8938.9 | M90: 0.5 | N90: 4 | O90: =N90*M90 -> 2
O91: =SUM(O83:O90) -> 3357
A92: EGRESOS DEL DIA 29-04-2026
A93: CAJA
A94: RESPONSABLE | B94: COMPROBANTE | C94: DETALLE | K94: TOTAL
A95: COTRINA MANRIQUE TITO | B95: E001-193 | C95: REPARACION DE PUERTA (CAMBIO DE CUERDA) Y ARREGLO DEL PASAMANOS DE LAS ESCALERAS AL SEGUNDO PISO DE LA COOPERATIVA | K95: 190
A96: ALVAREZ CAMPOS ROLANDO | B96: 14857 | C96: CAFÉ+AZUCAR+BETUN PARA LOS VIGILANTES | K96: 38.4
A97: ALVAREZ CAMPOS ROLANDO | B97: 14858 | C97: CAFE+AZUCAR PARA LA OFICINA DE ADM. DE LA COOPERATIVA | K97: 26.2
A98: CUYA LLAMACURI VICTORIANO | B98: E001-397 | C98: ANTIPULGAS ASUNTOL PARA LAS MASCOTAS DE LA COOPERATIVA | K98: 55
A105: TOTAL DE EGRESOS | K105: =SUM(K95:K104) -> 309.6
A108: RESUMEN
A109: TOTAL GENERAL | B109: =+K90 -> 8938.9
A110: TOTAL DE EGRESOS | B110: =+K105 -> 309.6
A111: SALDO | B111: =++B109-B110 -> 8629.3

Sheet 30-04-2026
A1: INGRESOS DEL DIA 30-04-2026
A3: INQUILINO | B3: COMPROBANTE | C3: DETALLE | D3: LUZ | E3: AGUA | F3: ALQUILER | G3: ESPACIO | H3: PARQUEO | I3: TICKET | J3: ALQUILER LOCAL 2DO PISO | K3: TOTAL
A4: JOSE | B4: TK 50841 | C4: 46113 | I4: 10 | K4: =SUM(D4:J4) -> 10
A5: JOSE | B5: TK 50842 | C5: 46113 | I5: 10 | K5: =SUM(D5:J5) -> 10
K6: =SUM(D6:J6) -> 0
A7: JULIO HECTOR ESPARTA CARDENAS | B7: EB01-7303 | C7: 46113 | F7: 350 | K7: =SUM(D7:J7) -> 350
A8: PARQUEO | B8: EB01-7308 | C8: 46113 | H8: 56.3 | K8: =SUM(D8:J8) -> 56.3
K9: =SUM(D9:J9) -> 0
K10: =SUM(D10:J10) -> 0
K11: =SUM(D11:J11) -> 0
K12: =SUM(D12:J12) -> 0
K13: =SUM(D13:J13) -> 0
K14: =SUM(D14:J14) -> 0
A15: JULIO HECTOR ESPARTA CARDENAS | B15: RII 3385 | C15: 46082 | D15: 44 | E15: 10 | K15: =SUM(D15:J15) -> 54
K16: =SUM(D16:J16) -> 0
K17: =SUM(D17:J17) -> 0
K18: =SUM(D18:J18) -> 0
A19: VASQUEZ TAFUR SONIA ALBERTINA | B19: E001-378 | C19: 46113 | G19: 30 | K19: =SUM(D19:J19) -> 30
A20: ARGUELLO MANZANILLA NARCYS ALEXANDER | B20: E001-379 | C20: 46113 | F20: 140 | K20: =SUM(D20:J20) -> 140
K21: =SUM(D21:J21) -> 0
K22: =SUM(D22:J22) -> 0
K23: =SUM(D23:J23) -> 0
A24: TOTAL | D24: =SUM(D4:D23) -> 44 | E24: =SUM(E4:E23) -> 10 | F24: =SUM(F4:F23) -> 490 | G24: =SUM(G4:G23) -> 30 | H24: =SUM(H4:H23) -> 56.3 | I24: =SUM(I4:I23) -> 20 | J24: =SUM(J4:J23) -> 0 | K24: =SUM(K4:K23) -> 650.3
A26: BBVA
A27: INQUILINOS | B27: COMPROBANTE | C27: DETALLE | D27: LUZ | E27: AGUA | F27: ALQUILER | G27: ESPACIO | H27: DEPOSITO | I27: TICKET | K27: TOTAL
A28: MARGARITA JUANA GOMERO DULANTO | B28: EB01-7304 | C28: 46113 | F28: 300 | K28: =SUM(D28:I28) -> 300
A29: LISBETH LUCIA MALLMA CONDORI | B29: EB01-7305 | C29: 46054 | F29: 72.2 | K29: =SUM(D29:I29) -> 72.2
C30: 46082 | F30: 44 | K30: =SUM(D30:I30) -> 44
A31: SANDRA LIZ MUJICA PALOMINO | B31: EB01-7306 | C31: 46054 | F31: 149.5 | K31: =SUM(D31:I31) -> 149.5
C32: 46082 | F32: 10.5 | K32: =SUM(D32:I32) -> 10.5
K33: =SUM(D33:I33) -> 0
A34: MARGARITA JUANA GOMERO DULANTO | B34: RII 3386 | C34: 46082 | D34: 28.3 | E34: 6 | K34: =SUM(D34:I34) -> 34.3
A35: LISBETH LUCIA MALLMA CONDORI | B35: RII 3387 | C35: 46082 | D35: 37.8 | E35: 6 | K35: =SUM(D35:I35) -> 43.8
K36: =SUM(D36:I36) -> 0
K37: =SUM(D37:I37) -> 0 | M37: TOTAL QR | N37: =K38+K46 -> 737.2
A38: TOTAL | D38: =SUM(D28:D37) -> 66.1 | E38: =SUM(E28:E37) -> 12 | F38: =SUM(F28:F37) -> 576.2 | G38: =SUM(G28:G37) -> 0 | H38: =SUM(H28:H37) -> 0 | I38: =SUM(I28:I37) -> 0 | J38: =SUM(J28:J37) -> 0 | K38: =SUM(K28:K37) -> 654.3
A40: BBVA
A41: SOCIOS | B41: RECIBO DE SERVICIO | C41: DETALLE | D41: LUZ | E41: AGUA | F41: G. ADM | G41: P. SOCIAL | H41: DEPOSITO | I41: P.S X FALLECIMIENTO | K41: TOTAL
A42: GUTIERREZ CASTRO JORGE | B42: RI 32991 | C42: 46082 | D42: 11.9 | E42: 6 | F42: 60 | G42: 5 | K42: =SUM(D42:I42) -> 82.9
K43: =SUM(D43:I43) -> 0
K44: =SUM(D44:I44) -> 0
K45: =SUM(D45:I45) -> 0
A46: TOTAL | D46: =SUM(D42:D45) -> 11.9 | E46: =SUM(E42:E45) -> 6 | F46: =SUM(F42:F45) -> 60 | G46: =SUM(G42:G45) -> 5 | H46: =SUM(H42:H45) -> 0 | I46: =SUM(I42:I45) -> 0 | J46: =SUM(J42:J45) -> 0 | K46: =SUM(K42:K45) -> 82.9
A50: SOCIO | B50: RECIBO DE SERVICIO | C50: DETALLE | D50: LUZ | E50: AGUA | F50: G. ADM | G50: P. SOCIAL | H50: P.S X FALLECIMIENTO | I50: FUMIGACION | J50: MULTA | K50: TOTAL
A51: CASTRO AQUILA | B51: RI 32990 | C51: 46082 | J51: 113 | K51: =SUM(D51:J51) -> 113
A52: CHALLCO NICOLAZA | B52: RI 32992 | C52: 46082 | D52: 379.5 | E52: 40.2 | K52: =SUM(D52:J52) -> 419.7
A53: QUISPE ROSA | B53: RI 32993 | C53: 46082 | D53: 447.5 | E53: 12.1 | F53: 40 | G53: 5 | K53: =SUM(D53:J53) -> 504.6
A54: CALDERON SEGUNDO | B54: RI 32994 | C54: 46082 | D54: 199.8 | E54: 65.1 | F54: 60 | G54: 5 | K54: =SUM(D54:J54) -> 329.9
A55: OJEDA EDSON | B55: RI 32995 | C55: 46082 | D55: 640.3 | E55: 33.6 | K55: =SUM(D55:J55) -> 673.9
A56: RAMOZ CUEVA PEDRO | B56: RI 32996 | C56: 46082 | D56: 27.4 | E56: 164 | F56: 60 | G56: 5 | K56: =SUM(D56:J56) -> 256.4
K57: =SUM(D57:J57) -> 0
K58: =SUM(D58:J58) -> 0
K59: =SUM(D59:J59) -> 0
A60: CARRASCO FELICITAS | B60: 11095 | C60: 46113 | I60: 5 | K60: =SUM(D60:J60) -> 5
K61: =SUM(D61:J61) -> 0
K62: =SUM(D62:J62) -> 0
K63: =SUM(D63:J63) -> 0
A64: TOTAL | D64: =SUM(D51:D63) -> 1694.5 | E64: =SUM(E51:E63) -> 315 | F64: =SUM(F51:F63) -> 160 | G64: =SUM(G51:G63) -> 15 | H64: =SUM(H51:H63) -> 0 | I64: =SUM(I51:I63) -> 5 | J64: =SUM(J51:J63) -> 113 | K64: =SUM(K51:K63) -> 2302.5
A67: TOTAL DE INGRESOS | K67: =+K24+K64 -> 2952.8
A70: SRTA. TATIHANA VILLANUEVA
A71: COBRANZA SOCIOS
A72: COBRANZA INQUILINOS
A75: SRA. MARIA CUYA ARANGO
A76: COBRANZA DE BAÑO DEL 1ER PISO | K76: 525.5
A79: COBRANZA DE BAÑO DEL 2DO PISO
A81: TOTAL GENERAL DE INGRESOS | K81: =SUM(K67:K80) -> 3478.3
A83: EGRESOS DEL DIA 30-04-2026
A84: CAJA
A85: RESPONSABLE | B85: COMPROBANTE | C85: DETALLE | K85: TOTAL
A86: CAMAN HUABLOCHO LLENY SANDYBELL | B86: E001 576 | C86: ASESORIA CONTABLE DEL MES DE ABRIL 2026 | K86: 1900
A87: CAYRO CARI RUBEN | B87: E001 208 | C87: ASESORIA LEGAL Y CONSULTORIA DEL MES DE ABRIL 2026 | K87: 1840
A88: MATIAS CAHUANA ACUÑA | B88: 890315 | C88: SUELDO DEL MES DE ABRIL 2026 | K88: 1609.6
A89: CARLOS ORMEÑO HERNANDEZ | B89: 891454 | C89: SUELDO DEL MES DE ABRIL 2026 | K89: 1065.2
A90: SANTOS PALOMINO CAMPOS | B90: 892562 | C90: SUELDO DEL MES DE ABRIL 2026 | K90: 1711.6
A91: NICANOR POMACANCHARI | B91: 893477 | C91: SUELDO DEL MES DE ABRIL 2026 | K91: 1022.1
A92: TUEROS PRUDENCIO | B92: 894283 | C92: SUELDO DEL MES DE ABRIL 2026 | K92: 1137.4
A93: SIHUE FELIX FATIMA | B93: 895204 | C93: SUELDO DEL MES DE ABRIL 2026 | K93: 927.7
A94: CUYA ARANGO MARIA | B94: 896490 | C94: SUELDO DEL MES DE ABRIL 2026 | K94: 1282.4
A95: PANQUIEZ LOPEZ DENIS | B95: 897728 | C95: SUELDO DEL MES DE ABRIL 2026 | K95: 1268.3
A96: GUZMAN AEDO ALEX | B96: 898831 | C96: SUELDO DEL MES DE ABRIL 2026 | K96: 387.9
A97: VILLANUEVA PARIASCA TATIHANA | B97: 899804 | C97: SUELDO DEL MES DE ABRIL 2026 | K97: 642.4
A98: CACCIRE PALOMINO LUIS | B98: 900682 | C98: SUELDO DEL MES DE ABRIL 2026 | K98: 1325
A99: SUNARP | B99: 2026-373-6444 | C99: SOLICITUD DE INSCRIPCIÓN DE TITULO | K99: 33
A100: SANTILLAN ZOILA | B100: RC 8627 | C100: DIETA MES DE MARZO 2026 AL CARGO DE VICEPRESIDENTA DEL CONSEJO DE VIGILANCIA | K100: 250
A101: TUSE MANUEL | B101: RC 8628 | C101: REEMPLAZO DEL SR NICANOR DE LOS DIAS 21-04 Y 28-04, TAMBIEN LIEMPIEZA DE LOS SSHH DEL 2DO PISO | K101: 105
A105: TOTAL DE EGRESOS | K105: =SUM(K86:K104) -> 16507.6
A108: RESUMEN
A109: TOTAL GENERAL | B109: =+K81 -> 3478.3
A110: TOTAL DE EGRESOS | B110: =+K105 -> 16507.6
A111: SALDO | B111: =++B109-B110 -> -13029.3

Sheet ARQUEO RESUMIDO
B2: OFICINA | E2: COBRADOR | H2: 46113
B3: SOCIOS | C3: INQUILINOS | D3: TOTAL | E3: SOCIOS | F3: INQUILINOS | G3: TOTAL | H3: SS.HH | I3: INGRESOS | J3: EGRESOS | K3: SALDO | L3: EGRESOS BOVEDA | M3: CAJA | N3: BOVEDA SANTO ROSA | O3: ACTIVIDAD SANTA ROSA | P3: BOVEDA SR. OSCAR | Q3: DEPOSITO AL BCO | R3: BOVEDA TOTAL | S3: ACUMULADO | T3: DOLARES | V3: PAGO CON QR
A4: SAL. INI. | B4: 2026 | M4: 5566.9 | N4: 1774 | O4: 9152.6 | P4: 40758.3 | R4: =SUM(P4+O4+N4)-Q4 -> 51684.9 | S4: =+M4+R4 -> 57251.8 | T4: 5266
A5: 46113 | B5: =+'01-04-2026'!J29 -> 0 | C5: =+'01-04-2026'!J24 -> 1952.5 | D5: =B5+C5 -> 1952.5 | H5: =+'01-04-2026'!J71 -> 501.5 | I5: =D5+G5+H5 -> 2454 | J5: =+'01-04-2026'!J95 -> 544 | K5: =I5-J5 -> 1910 | M5: =M4+K5 -> 7476.9 | R5: =SUM(P5+O5+N5)-Q5-L5+R4 -> 51684.9 | S5: =+M5+R5 -> 59161.8 | V5: =+'01-04-2026'!M31 -> 500
A6: 46114 | B6: =+'02-04-2026'!J30 -> 0 | C6: =+'02-04-2026'!J22 -> 59 | D6: =B6+C6 -> 59 | H6: =+'02-04-2026'!J69 -> 436 | I6: =D6+G6+H6 -> 495 | J6: =+'02-04-2026'!J96 -> 0 | K6: =I6-J6 -> 495 | M6: =M5+K6 -> 7971.9 | R6: =SUM(P6+O6+N6)-Q6-L6+R5 -> 51684.9 | S6: =+M6+R6 -> 59656.8 | V6: =+'02-04-2026'!M29 -> 0
A7: 46115 | B7: =+'03-04-2026'!J31 -> 0 | C7: =+'03-04-2026'!J22 -> 30.9 | D7: =B7+C7 -> 30.9 | H7: =+'03-04-2026'!J69 -> 226.5 | I7: =D7+G7+H7 -> 257.4 | J7: =+'03-04-2026'!J97 -> 0 | K7: =I7-J7 -> 257.4 | M7: =M6+K7 -> 8229.3 | R7: =SUM(P7+O7+N7)-Q7-L7+R6 -> 51684.9 | S7: =+M7+R7 -> 59914.2 | V7: =+'03-04-2026'!M29 -> 0
A8: 46116 | B8: =+'04-04-2026'!J32 -> 0 | C8: =+'04-04-2026'!J22 -> 1160 | D8: =B8+C8 -> 1160 | H8: =+'04-04-2026'!J69 -> 377.5 | I8: =D8+G8+H8 -> 1537.5 | J8: =+'04-04-2026'!J92 -> 742.4 | K8: =I8-J8 -> 795.1 | M8: =M7+K8 -> 9024.4 | R8: =SUM(P8+O8+N8)-Q8-L8+R7 -> 51684.9 | S8: =+M8+R8 -> 60709.3 | V8: =+'04-04-2026'!M29 -> 0
A9: 46117 | B9: =+'05-04-2026'!J57 -> 0 | C9: =+'05-04-2026'!J22 -> 100 | D9: =B9+C9 -> 100 | H9: =+'05-04-2026'!J69 -> 504.5 | I9: =D9+G9+H9 -> 604.5 | J9: =+'05-04-2026'!J93 -> 0 | K9: =I9-J9 -> 604.5 | M9: =M8+K9 -> 9628.9 | R9: =SUM(P9+O9+N9)-Q9-L9+R8 -> 51684.9 | S9: =+M9+R9 -> 61313.8 | V9: =+'05-04-2026'!M29 -> 0
A10: 46118 | B10: =+'06-04-2026'!J58 -> 0 | C10: =+'06-04-2026'!J24 -> 1956.4 | D10: =B10+C10 -> 1956.4 | H10: =+'06-04-2026'!J70 -> 352.5 | I10: =D10+G10+H10 -> 2308.9 | J10: =+'06-04-2026'!J90 -> 265.5 | K10: =I10-J10 -> 2043.4 | M10: =M9+K10-P10 -> 3972.3 | P10: 7700 | R10: =SUM(P10+O10+N10)-Q10-L10+R9 -> 59384.9 | S10: =+M10+R10 -> 63357.2 | V10: =+'06-04-2026'!M31 -> 65
A11: 46119 | B11: =+'07-04-2026'!J60 -> 0 | C11: =+'07-04-2026'!J23 -> 2671.2 | D11: =B11+C11 -> 2671.2 | H11: =+'07-04-2026'!J70 -> 481 | I11: =D11+G11+H11 -> 3152.2 | J11: =+'07-04-2026'!J90 -> 28.9 | K11: =I11-J11 -> 3123.3 | M11: =M10+K11 -> 7095.6 | R11: =SUM(P11+O11+N11)-Q11-L11+R10 -> 59384.9 | S11: =+M11+R11 -> 66480.5 | V11: =+'07-04-2026'!M30 -> 645 | Y11: FATIMA
A12: 46120 | B12: =+'08-04-2026'!J97 -> 545 | C12: =+'08-04-2026'!J50 -> 6016.2 | D12: =B12+C12 -> 6561.2 | H12: =+'08-04-2026'!J109 -> 496 | I12: =D12+G12+H12 -> 7057.2 | J12: =+'08-04-2026'!J132 -> 1492.5 | K12: =I12-J12 -> 5564.7 | M12: =M11+K12 -> 12660.3 | R12: =SUM(P12+O12+N12)-Q12-L12+R11 -> 59384.9 | S12: =+M12+R12 -> 72045.2 | V12: =+'08-04-2026'!M76 -> 2074.4 | Z12: 200 | AA12: =Y12*Z12 -> 0
A13: 46121 | B13: =+'09-04-2026'!J105 -> 0 | C13: =+'09-04-2026'!J27 -> 1131.5 | D13: =B13+C13 -> 1131.5 | H13: =+'09-04-2026'!J78 -> 495 | I13: =D13+G13+H13 -> 1626.5 | J13: =+'09-04-2026'!J99 -> 1353.1 | K13: =I13-J13 -> 273.4 | M13: =M12+K13-P13 -> 6933.7 | P13: 6000 | R13: =SUM(P13+O13+N13)-Q13-L13+R12 -> 65384.9 | S13: =+M13+R13 -> 72318.6 | V13: =+'09-04-2026'!M36 -> 642.8 | Y13: 30 | Z13: 100 | AA13: =Y13*Z13 -> 3000
A14: 46122 | B14: =+'10-04-2026'!J60 -> 807 | C14: =+'10-04-2026'!J22 -> 382 | D14: =B14+C14 -> 1189 | E14: =+'10-04-2026'!J67 -> 1916 | F14: =+'10-04-2026'!J68 -> 2645 | G14: =F14+E14 -> 4561 | H14: =+'10-04-2026'!J72 -> 502 | I14: =D14+G14+H14 -> 6252 | J14: =+'10-04-2026'!J90 -> 111.5 | K14: =I14-J14 -> 6140.5 | M14: =M13+K14 -> 13074.2 | Q14: 34000 | R14: =SUM(P14+O14+N14)-Q14-L14+R13 -> 31384.9 | S14: =+M14+R14 -> 44459.1 | V14: =+'10-04-2026'!M29 -> 756 | Y14: 104 | Z14: 50 | AA14: =Y14*Z14 -> 5200
A15: 46123 | B15: =+'11-04-2026'!J57 -> 0 | C15: =+'11-04-2026'!J22 -> 105 | D15: =B15+C15 -> 105 | H15: =+'11-04-2026'!J69 -> 508.5 | I15: =D15+G15+H15 -> 613.5 | J15: =+'11-04-2026'!J89 -> 300 | K15: =I15-J15 -> 313.5 | M15: =M14+K15-P15 -> 4887.7 | P15: 8500 | R15: =SUM(P15+O15+N15)-Q15-L15+R14 -> 39884.9 | S15: =+M15+R15 -> 44772.6 | V15: =+'11-04-2026'!M29 -> 1500 | Y15: 1 | Z15: 20 | AA15: =Y15*Z15 -> 20
A16: 46124 | B16: =+'11-04-2026'!J58 -> 0 | C16: =+'11-04-2026'!J23 -> 0 | D16: =B16+C16 -> 0 | H16: =+'12-04-2026'!J69 -> 566 | I16: =D16+G16+H16 -> 566 | J16: =+'11-04-2026'!J90 -> 0 | K16: =I16-J16 -> 566 | M16: =M15+K16 -> 5453.7 | R16: =SUM(P16+O16+N16)-Q16-L16+R15 -> 39884.9 | S16: =+M16+R16 -> 45338.6 | V16: =+'12-04-2026'!M42 -> 0 | Y16: 3 | Z16: 10 | AA16: =Y16*Z16 -> 30
A17: 46125 | B17: =+'13-04-2026'!J57 -> 141.9 | C17: =+'13-04-2026'!J22 -> 20 | D17: =B17+C17 -> 161.9 | H17: =+'13-04-2026'!J69 -> 349 | I17: =D17+G17+H17 -> 510.9 | J17: =+'13-04-2026'!J89 -> 1084.4 | K17: =I17-J17 -> -573.5 | M17: =M16+K17 -> 4880.2 | R17: =SUM(P17+O17+N17)-Q17-L17+R16 -> 39884.9 | S17: =+M17+R17 -> 44765.1 | V17: =+'13-04-2026'!M29 -> 36.4 | Z17: 1 | AA17: =Y17*Z17 -> 0
A18: 46126 | B18: =+'14-04-2026'!J57 -> 65 | C18: =+'14-04-2026'!J22 -> 680 | D18: =B18+C18 -> 745 | H18: =+'14-04-2026'!J69 -> 494.5 | I18: =D18+G18+H18 -> 1239.5 | J18: =+'14-04-2026'!J89 -> 10 | K18: =I18-J18 -> 1229.5 | M18: =M17+K18 -> 6109.7 | R18: =SUM(P18+O18+N18)-Q18-L18+R17 -> 39884.9 | S18: =+M18+R18 -> 45994.6 | V18: =+'14-04-2026'!M29 -> 60 | Z18: 1 | AA18: =Y18*Z18 -> 0
A19: 46127 | B19: =+'15-04-2026'!J88 -> 0 | C19: =+'15-04-2026'!J43 -> 5796.3 | D19: =B19+C19 -> 5796.3 | H19: =+'15-04-2026'!J100 -> 491 | I19: =D19+G19+H19 -> 6287.3 | J19: =+'15-04-2026'!J124 -> 6750 | K19: =I19-J19 -> -462.7 | M19: =M18+K19 -> 5647 | R19: =SUM(P19+O19+N19)-Q19-L19+R18 -> 39884.9 | S19: =+M19+R19 -> 45531.9 | V19: =+'15-04-2026'!M60 -> 1415.9 | X19: SENCILLO | Y19: 98.8 | Z19: 1 | AA19: =Y19*Z19 -> 98.8
A20: 46128 | B20: =+'16-04-2026'!J49 -> 90 | C20: =+'16-04-2026'!J17 -> 2778 | D20: =B20+C20 -> 2868 | H20: =+'16-04-2026'!J61 -> 486 | I20: =D20+G20+H20 -> 3354 | J20: =+'16-04-2026'!J81 -> 150.9 | K20: =I20-J20 -> 3203.1 | M20: =M19+K20 -> 8850.1 | R20: =SUM(P20+O20+N20)-Q20-L20+R19 -> 39884.9 | S20: =+M20+R20 -> 48735 | V20: =+'16-04-2026'!M46 -> 0 | X20: MONEDAS DE 50 | Y20: 100 | Z20: 1 | AA20: =Y20*Z20 -> 100
A21: 46129 | B21: =+'17-04-2026'!K58 -> 476.9 | C21: =+'17-04-2026'!K23 -> 484.6 | D21: =B21+C21 -> 961.5 | E21: =+'17-04-2026'!K65 -> 1834 | F21: =+'17-04-2026'!K66 -> 2745 | G21: =F21+E21 -> 4579 | H21: =+'17-04-2026'!K70 -> 521 | I21: =D21+G21+H21 -> 6061.5 | J21: =+'17-04-2026'!K124 -> 0 | K21: =I21-J21 -> 6061.5 | M21: =M20+K21-P21 -> 6911.6 | P21: 8000 | R21: =SUM(P21+O21+N21)-Q21-L21+R20 -> 47884.9 | S21: =+M21+R21 -> 54796.5 | V21: =+'17-04-2026'!N30 -> 30 | X21: BAÑO | Y21: 200 | Z21: 1 | AA21: =Y21*Z21 -> 200
A22: 46130 | B22: =+'18-04-2026'!K58 -> 0 | C22: =+'18-04-2026'!K23 -> 71.6 | D22: =B22+C22 -> 71.6 | H22: =+'18-04-2026'!K70 -> 491 | I22: =D22+G22+H22 -> 562.6 | J22: =+'18-04-2026'!K90 -> 410 | K22: =I22-J22 -> 152.6 | M22: =M21+K22 -> 7064.2 | P22: 960 | R22: =SUM(P22+O22+N22)-Q22-L22+R21 -> 48844.9 | S22: =+M22+R22 -> 55909.1 | V22: =+'18-04-2026'!N30 -> 30 | X22: YUCRA | Y22: 400 | Z22: 1 | AA22: =Y22*Z22 -> 400
A23: 46131 | B23: =+'18-04-2026'!J24 -> 0 | C23: =+'18-04-2026'!K24 -> 0 | D23: =B23+C23 -> 0 | H23: =+'19-04-2026'!K70 -> 486 | I23: =D23+G23+H23 -> 486 | J23: =+'18-04-2026'!K102 -> 0 | K23: =I23-J23 -> 486 | M23: =M22+K23 -> 7550.2 | R23: =SUM(P23+O23+N23)-Q23-L23+R22 -> 48844.9 | S23: =+M23+R23 -> 56395.1 | V23: =+'19-04-2026'!M49 -> 0 | AA23: =SUM(AA12:AA22) -> 9048.8
A24: 46132 | B24: =+'18-04-2026'!J25 -> 0 | C24: =+'20-04-2026'!K25 -> 1025.7 | D24: =B24+C24 -> 1025.7 | H24: =+'20-04-2026'!K72 -> 342 | I24: =D24+G24+H24 -> 1367.7 | J24: =+'20-04-2026'!K92 -> 647 | K24: =I24-J24 -> 720.7 | M24: =M23+K24 -> 8270.9 | R24: =SUM(P24+O24+N24)-Q24-L24+R23 -> 48844.9 | S24: =+M24+R24 -> 57115.8 | V24: =+'20-04-2026'!N32 -> 1266.2
A25: 46133 | B25: =+'21-04-2026'!K58 -> 1042.5 | C25: =+'21-04-2026'!K23 -> 440.1 | D25: =B25+C25 -> 1482.6 | H25: =+'21-04-2026'!K70 -> 542.5 | I25: =D25+G25+H25 -> 2025.1 | J25: =+'21-04-2026'!K90 -> 931 | K25: =I25-J25 -> 1094.1 | M25: =M24+K25 -> 9365 | R25: =SUM(P25+O25+N25)-Q25-L25+R24 -> 48844.9 | S25: =+M25+R25 -> 58209.9 | V25: =+'21-04-2026'!M51 -> 0
A26: 46134 | B26: =+'22-04-2026'!K96 -> 2355.4 | C26: =+'22-04-2026'!K45 -> 3627.6 | D26: =B26+C26 -> 5983 | H26: =+'22-04-2026'!K108 -> 538 | I26: =D26+G26+H26 -> 6521 | J26: =+'22-04-2026'!K128 -> 1216 | K26: =I26-J26 -> 5305 | M26: =M25+K26 -> 14670 | R26: =SUM(P26+O26+N26)-Q26-L26+R25 -> 48844.9 | S26: =+M26+R26 -> 63514.9 | V26: =+'22-04-2026'!N68 -> 1572.7
A27: 46135 | B27: =+'23-04-2026'!K58 -> 1349.7 | C27: =+'23-04-2026'!K23 -> 69.5 | D27: =B27+C27 -> 1419.2 | H27: =+'23-04-2026'!K70 -> 546 | I27: =D27+G27+H27 -> 1965.2 | J27: =+'23-04-2026'!K91 -> 867.3 | K27: =I27-J27 -> 1097.9 | M27: =M26+K27-P27 -> 6767.9 | P27: 9000 | R27: =SUM(P27+O27+N27)-Q27-L27+R26 -> 57844.9 | S27: =+M27+R27 -> 64612.8 | V27: =+'23-04-2026'!N30 -> 565 | AA27: =M35-AA23 -> 0
A28: 46136 | B28: =+'24-04-2026'!K58 -> 94.3 | C28: =+'24-04-2026'!K23 -> 371.2 | D28: =B28+C28 -> 465.5 | E28: =+'24-04-2026'!K65 -> 1495 | F28: =+'24-04-2026'!K66 -> 2220 | G28: =F28+E28 -> 3715 | H28: =+'24-04-2026'!K70 -> 520 | I28: =D28+G28+H28 -> 4700.5 | J28: =+'24-04-2026'!K90 -> 132.9 | K28: =I28-J28 -> 4567.6 | M28: =M27+K28 -> 11335.5 | Q28: 29600 | R28: =SUM(P28+O28+N28)-Q28-L28+R27 -> 28244.9 | S28: =+M28+R28 -> 39580.4 | V28: =+'17-04-2026'!M54 -> 0
A29: 46137 | B29: =+'25-04-2026'!K58 -> 237.8 | C29: =+'25-04-2026'!K23 -> 71.5 | D29: =B29+C29 -> 309.3 | H29: =+'25-04-2026'!K70 -> 521.5 | I29: =D29+G29+H29 -> 830.8 | J29: =+'25-04-2026'!K90 -> 30 | K29: =I29-J29 -> 800.8 | M29: =M28+K29 -> 12136.3 | R29: =SUM(P29+O29+N29)-Q29-L29+R28 -> 28244.9 | S29: =+M29+R29 -> 40381.2 | V29: =+'17-04-2026'!M55 -> 0 | X29: NUMERO | Y29: DENOMINACION
A30: 46138 | B30: =+'26-04-2026'!K59 -> 0 | C30: =+'26-04-2026'!K24 -> 0 | D30: =B30+C30 -> 0 | H30: =+'26-04-2026'!K70 -> 598 | I30: =D30+G30+H30 -> 598 | J30: =+'26-04-2026'!K91 -> 0 | K30: =I30-J30 -> 598 | M30: =M29+K30 -> 12734.3 | R30: =SUM(P30+O30+N30)-Q30-L30+R29 -> 28244.9 | S30: =+M30+R30 -> 40979.2 | V30: =+'17-04-2026'!M56 -> 0 | X30: 3 | Y30: 5 | Z30: =+X30*Y30 -> 15
A31: 46139 | B31: =+'27-04-2026'!K61 -> 566 | C31: =+'27-04-2026'!K25 -> 199.3 | D31: =B31+C31 -> 765.3 | H31: =+'27-04-2026'!K73 -> 335.5 | I31: =D31+G31+H31 -> 1100.8 | J31: =+'27-04-2026'!K93 -> 2685.5 | K31: =I31-J31 -> -1584.7 | M31: =M30+K31 -> 11149.6 | R31: =SUM(P31+O31+N31)-Q31-L31+R30 -> 28244.9 | S31: =+M31+R31 -> 39394.5 | V31: =+'17-04-2026'!M57 -> 0 | X31: 2 | Y31: 2 | Z31: =+X31*Y31 -> 4
A32: 46140 | B32: =+'28-04-2026'!K60 -> 1490.7 | C32: =+'28-04-2026'!K24 -> 469.5 | D32: =B32+C32 -> 1960.2 | H32: =+'28-04-2026'!K72 -> 539 | I32: =D32+G32+H32 -> 2499.2 | J32: =+'28-04-2026'!K92 -> 200 | K32: =I32-J32 -> 2299.2 | M32: =M31+K32 -> 13448.8 | O32: 121.2 | R32: =SUM(P32+O32+N32)-Q32-L32+R31 -> 28366.1 | S32: =+M32+R32 -> 41814.9 | V32: =+'17-04-2026'!M58 -> 0 | X32: 6 | Y32: 1 | Z32: =+X32*Y32 -> 6
A33: 46141 | B33: =+'29-04-2026'!K73 -> 2378.3 | C33: =+'29-04-2026'!K32 -> 2769.6 | D33: =B33+C33 -> 5147.9 | E33: =+'29-04-2026'!K80 -> 1907 | F33: =+'29-04-2026'!K81 -> 1350 | G33: =F33+E33 -> 3257 | H33: =+'29-04-2026'!K85 -> 534 | I33: =D33+G33+H33 -> 8938.9 | J33: =+'29-04-2026'!K105 -> 309.6 | K33: =I33-J33 -> 8629.3 | M33: =M32+K33 -> 22078.1 | R33: =SUM(P33+O33+N33)-Q33-L33+R32 -> 28366.1 | S33: =+M33+R33 -> 50444.2 | V33: =+'17-04-2026'!M59 -> 0 | X33: 15 | Y33: 0.5 | Z33: =+X33*Y33 -> 7.5
A34: 46142 | B34: =+'30-04-2026'!K64 -> 2302.5 | C34: =+'30-04-2026'!K24 -> 650.3 | D34: =B34+C34 -> 2952.8 | H34: =+'30-04-2026'!K76 -> 525.5 | I34: =D34+G34+H34 -> 3478.3 | J34: =+'30-04-2026'!K105 -> 16507.6 | K34: =I34-J34 -> -13029.3 | M34: =M33+K34 -> 9048.8 | R34: =SUM(P34+O34+N34)-Q34-L34+R33 -> 28366.1 | S34: =+M34+R34 -> 37414.9 | V34: =+'17-04-2026'!M60 -> 0 | X34: 15 | Y34: 0.2 | Z34: =+X34*Y34 -> 3
M35: =M34+K35 -> 9048.8 | R35: =SUM(P35+O35+N35)-Q35-L35+R34 -> 28366.1 | S35: =+M35+R35 -> 37414.9 | V35: =+'17-04-2026'!M61 -> 0 | X35: 38 | Y35: 0.1 | Z35: =+X35*Y35 -> 3.8
B36: =SUM(B5:B35) -> 13943 | C36: =SUM(C5:C35) -> 35089.5 | D36: =SUM(D5:D35) -> 49032.5 | E36: =SUM(E5:E35) -> 7152 | F36: =SUM(F5:F35) -> 8960 | G36: =SUM(G5:G35) -> 16112 | H36: =SUM(H5:H35) -> 14307.5 | I36: =SUM(I5:I35) -> 79452 | ... K36: =SUM(K5:K35) -> 42681.9 | M36: =I36+M4-J36 -> 48248.8 | N36: =N4+N9+N22+N15+N21+N23+N29+N30 -> 1774 | O36: =SUM(O4:O35) -> 9273.8 | P36: =SUM(P4:P35) -> 80918.3 | Q36: =SUM(Q4:Q35) -> 63600 | T36: =SUM(T4:T35) -> 5266 | V36: =SUM(V5:V35) -> 11159.4
Z37: =SUM(Z30:Z36) -> 39.3
Y38: SENCILLO 0.50 | Z38: 59.5
P39: =P36-Q36 -> 17318.3 | Z39: =Z37+Z38 -> 98.8
B42: CCI BBVA | C42: 011 338 000100019602 10 | M42: =S35-M35 -> 28366.1
B43: N DE CUENTA | C43: 0011 0338 0100019602 10
