Workbook

Sheet 2016
D1: Enero | J1: Febrero | P1: Marzo | V1: Abril | AB1: 42491 | AH1: 42522 | AN1: 42552 | AT1: 42583 | AZ1: set-16 | BF1: 42644 | BL1: 42675 | BR1: 42705 | BX1: DEUDA | BY1: DEUDA | BZ1: TOTAL DE DEUDA | CC1: DETALLE DE DEUDA 2016
A2: N° | B2: APELLIDOS Y NOMBRES | C2: 2015 | D2: Gast. Adm. | E2: Prev. Social | F2: Luz | G2: Agua | H2: Deposito | I2: Multa | J2: Gast. Adm. | K2: Prev. Social | L2: Luz | M2: Agua | N2: Deposito | O2: Multa | P2: Gast. Adm. | Q2: Prev. Social | R2: Luz | S2: Agua | T2: Deposito | U2: Multa | V2: Gast. Adm. | W2: Prev. Social | X2: Luz | Y2: Agua | Z2: Deposito | AA2: Multa | AB2: Gast. Adm. | AC2: Prev. Social | AD2: Luz | AE2: Agua | AF2: Deposito | AG2: Multa | AH2: Gast. Adm. | AI2: Prev. Social | AJ2: Luz | AK2: Agua | AL2: Deposito | AM2: Multa | AN2: Gast. Adm. | AO2: Prev. Social | AP2: Luz | AQ2: Agua | AR2: Deposito | AS2: Multa | AT2: Gast. Adm. | AU2: Prev. Social | AV2: Luz | AW2: Agua | AX2: Deposito | AY2: Multa | AZ2: Gast. Adm. | BA2: Prev. Social | BB2: Luz | BC2: Agua | BD2: Deposito | BE2: Multa | BF2: Gast. Adm. | BG2: Prev. Social | BH2: Luz | BI2: Agua | BJ2: Deposito | BK2: Multa | BL2: Gast. Adm. | BM2: Prev. Social | BN2: Luz | BO2: Agua | BP2: Deposito | BQ2: Multa | BR2: Gast. Adm. | BS2: Prev. Social | BT2: Luz | BU2: Agua | BV2: Deposito | BW2: Multa | BX2: 2016 | BY2: 2015 | CC2: G.A. | CD2: P.S. | CE2: LUZ | CF2: AGUA | CG2: DEPOSITO | CH2: MULTA y/o VARIOS
A3: 1 | B3: AGUIRRE QUISPE WILFREDO GILMER | C3: 0 | D3: 0 | E3: 0 | F3: 0 | G3: 0 | H3: 0 | I3: 0 | J3: 0 | K3: 0 | L3: 0 | M3: 0 | N3: 0 | O3: 0 | P3: 0 | Q3: 0 | R3: 0 | S3: 0 | T3: 0 | V3: 0 | W3: 0 | X3: 0 | Y3: 0 | Z3: 0 | AA3: 0 | AB3: 0 | AC3: 0 | AD3: 0 | AE3: 0 | AF3: 0 | AG3: 0 | AH3: 0 | AI3: 0 | AJ3: 0 | AK3: 0 | AL3: 0 | AN3: 0 | AO3: 0 | AP3: 0 | AQ3: 0 | AR3: 0 | AT3: 0 | AU3: 0 | AV3: 0 | AW3: 0 | AX3: 0 | AY3: 0 | AZ3: 0 | BA3: 0 | BB3: 0 | BC3: 0 | BF3: 0 | BG3: 0 | BH3: 0 | BI3: 0 | BL3: 0 | BM3: 0 | BN3: 0 | BO3: 0 | BR3: 0 | BS3: 0 | BT3: 57.2 | BU3: 3 | BX3: =SUM(D3:BW3) -> 60.2 | BY3: =C3 -> 0 | BZ3: =BX3+BY3 -> 60.2 | CC3: =D3+J3+P3+V3+AB3+AH3+AN3+AT3+AZ3+BF3+BL3+BR3 -> 0 | CD3: =E3+K3+Q3+W3+AC3+AI3+AO3+AU3+BA3+BG3+BM3+BS3 -> 0 | CE3: =F3+L3+R3+X3+AD3+AJ3+AP3+AV3+BB3+BH3+BN3+BT3 -> 57.2 | CF3: =G3+M3+S3+Y3+AE3+AK3+AQ3+AW3+BC3+BI3+BO3+BU3 -> 3 | CG3: =H3+N3+T3+Z3+AF3+AL3+AR3+AX3+BJ3+BP3+BV3+BD3 -> 0 | CH3: =I3+O3+U3+AA3+AG3+AM3+AS3+AY3+BE3+BK3+BQ3+BW3 -> 0
A4: 2 | B4: ALARCON ANAMPA NANCY GUISELA | C4: 0 | D4: 0 | E4: 0 | F4: 0 | G4: 0 | H4: 0 | I4: 0 | J4: 0 | K4: 0 | L4: 0 | M4: 0 | N4: 0 | O4: 0 | P4: 0 | Q4: 0 | R4: 0 | S4: 0 | T4: 0 | U4: 0 | V4: 0 | W4: 0 | X4: 0 | Y4: 0 | Z4: 0 | AA4: 0 | AB4: 0 | AC4: 0 | AD4: 0 | AE4: 0 | AF4: 0 | AG4: 0 | AH4: 0 | AI4: 0 | AJ4: 0 | AK4: 0 | AL4: 0 | AM4: 0 | AN4: 0 | AO4: 0 | AP4: 0 | AQ4: 0 | AR4: 0 | AS4: 0 | AT4: 0 | AU4: 0 | AV4: 0 | AW4: 0 | AX4: 0 | AY4: 0 | AZ4: 0 | BA4: 0 | BB4: 0 | BC4: 0 | BF4: 0 | BG4: 0 | BH4: 0 | BI4: 0 | BL4: 0 | BM4: 0 | BN4: 0 | BO4: 0 | BR4: 60 | BS4: 2 | BT4: 42.5 | BU4: 3 | BX4: =SUM(D4:BW4) -> 107.5 | BY4: =C4 -> 0 | BZ4: =BX4+BY4 -> 107.5 | CC4: =D4+J4+P4+V4+AB4+AH4+AN4+AT4+AZ4+BF4+BL4+BR4 -> 60 | CD4: =E4+K4+Q4+W4+AC4+AI4+AO4+AU4+BA4+BG4+BM4+BS4 -> 2 | CE4: =F4+L4+R4+X4+AD4+AJ4+AP4+AV4+BB4+BH4+BN4+BT4 -> 42.5 | CF4: =G4+M4+S4+Y4+AE4+AK4+AQ4+AW4+BC4+BI4+BO4+BU4 -> 3 | CG4: =H4+N4+T4+Z4+AF4+AL4+AR4+AX4+BJ4+BP4+BV4+BD4 -> 0 | CH4: =I4+O4+U4+AA4+AG4+AM4+AS4+AY4+BE4+BK4+BQ4+BW4 -> 0
A5: 3 | B5: ALHUAY PALOMINO DE ALHUAY JUANA | C5: 0 | D5: 0 | E5: 0 | F5: 0 | G5: 0 | H5: 0 | I5: 0 | J5: 0 | K5: 0 | L5: 0 | M5: 0 | N5: 0 | O5: 0 | P5: 0 | Q5: 0 | R5: 0 | S5: 0 | T5: 0 | U5: 0 | V5: 0 | W5: 0 | X5: 0 | Y5: 0 | Z5: 0 | AA5: 0 | AB5: 0 | AC5: 0 | AD5: 0 | AE5: 0 | AF5: 0 | AG5: 0 | AH5: 0 | AI5: 0 | AJ5: 0 | AK5: 0 | AL5: 0 | AM5: 0 | AN5: 0 | AO5: 0 | AP5: 0 | AQ5: 0 | AR5: 0 | AS5: 0 | AT5: 0 | AU5: 0 | AV5: 0 | AW5: 0 | AX5: 0 | AY5: 0 | AZ5: 0 | BA5: 0 | BB5: 0 | BC5: 0 | BE5: 0 | BF5: 0 | BG5: 0 | BH5: 0 | BI5: 0 | BL5: 0 | BM5: 0 | BN5: 84.5 | BO5: 39 | BR5: 0 | BS5: 0 | BT5: 91 | BU5: 39 | BW5: 80 | BX5: =SUM(D5:BW5) -> 333.5 | BY5: =C5 -> 0 | BZ5: =BX5+BY5 -> 333.5 | CC5: =D5+J5+P5+V5+AB5+AH5+AN5+AT5+AZ5+BF5+BL5+BR5 -> 0 | CD5: =E5+K5+Q5+W5+AC5+AI5+AO5+AU5+BA5+BG5+BM5+BS5 -> 0 | CE5: =F5+L5+R5+X5+AD5+AJ5+AP5+AV5+BB5+BH5+BN5+BT5 -> 175.5 | CF5: =G5+M5+S5+Y5+AE5+AK5+AQ5+AW5+BC5+BI5+BO5+BU5 -> 78 | CG5: =H5+N5+T5+Z5+AF5+AL5+AR5+AX5+BJ5+BP5+BV5+BD5 -> 0 | CH5: =I5+O5+U5+AA5+AG5+AM5+AS5+AY5+BE5+BK5+BQ5+BW5 -> 80
A6: 4 | B6: ALVAREZ CAMPOS LELIA AMERICA | C6: 0 | D6: 0 | E6: 0 | F6: 0 | G6: 0 | H6: 0 | I6: 0 | J6: 0 | K6: 0 | L6: 0 | M6: 0 | N6: 0 | O6: 0 | P6: 0 | Q6: 0 | R6: 0 | S6: 0 | T6: 0 | U6: 0 | V6: 0 | W6: 0 | X6: 0 | Y6: 0 | Z6: 0 | AA6: 0 | AB6: 0 | AC6: 0 | AD6: 0 | AE6: 0 | AF6: 0 | AG6: 0 | AH6: 0 | AI6: 0 | AJ6: 0 | AK6: 0 | AL6: 0 | AM6: 0 | AN6: 0 | AO6: 0 | AP6: 0 | AQ6: 0 | AR6: 0 | AS6: 0 | AT6: 0 | AU6: 0 | AV6: 0 | AW6: 0 | AX6: 0 | AY6: 0 | AZ6: 0 | BA6: 0 | BB6: 0 | BC6: 0 | BF6: 0 | BG6: 0 | BH6: 0 | BI6: 0 | BL6: 0 | BM6: 0 | BN6: 35.5 | BO6: 3 | BQ6: 59 | BR6: 0 | BS6: 0 | BT6: 37.6 | BU6: 3 | BX6: =SUM(D6:BW6) -> 138.1 | BY6: =C6 -> 0 | BZ6: =BX6+BY6 -> 138.1 | CC6: =D6+J6+P6+V6+AB6+AH6+AN6+AT6+AZ6+BF6+BL6+BR6 -> 0 | CD6: =E6+K6+Q6+W6+AC6+AI6+AO6+AU6+BA6+BG6+BM6+BS6 -> 0 | CE6: =F6+L6+R6+X6+AD6+AJ6+AP6+AV6+BB6+BH6+BN6+BT6 -> 73.1 | CF6: =G6+M6+S6+Y6+AE6+AK6+AQ6+AW6+BC6+BI6+BO6+BU6 -> 6 | CG6: =H6+N6+T6+Z6+AF6+AL6+AR6+AX6+BJ6+BP6+BV6+BD6 -> 0 | CH6: =I6+O6+U6+AA6+AG6+AM6+AS6+AY6+BE6+BK6+BQ6+BW6 -> 59
A7: 5 | B7: ALVAREZ CAMPOS ROLANDO | C7: 0 | D7: 0 | E7: 0 | F7: 0 | G7: 0 | H7: 0 | I7: 0 | J7: 0 | K7: 0 | L7: 0 | M7: 0 | N7: 0 | O7: 0 | P7: 0 | Q7: 0 | R7: 0 | S7: 0 | T7: 0 | U7: 0 | V7: 0 | W7: 0 | X7: 0 | Y7: 0 | Z7: 0 | AA7: 0 | AB7: 0 | AC7: 0 | AD7: 0 | AE7: 0 | AF7: 0 | AG7: 0 | AH7: 0 | AI7: 0 | AJ7: 0 | AK7: 0 | AL7: 0 | AM7: 0 | AN7: 0 | AO7: 0 | AP7: 0 | AQ7: 0 | AR7: 0 | AS7: 0 | AT7: 0 | AU7: 0 | AV7: 0 | AW7: 0 | AX7: 0 | AY7: 0 | AZ7: 0 | BA7: 0 | BB7: 0 | BC7: 0 | BD7: 0 | BE7: 0 | BF7: 0 | BG7: 0 | BH7: 0 | BI7: 0 | BJ7: 0 | BL7: 60 | BM7: 2 | BN7: 71 | BO7: 3 | BP7: 70 | BR7: 60 | BS7: 2 | BT7: 75.2 | BU7: 3 | BV7: 70 | BX7: =SUM(D7:BW7) -> 416.2 | BY7: =C7 -> 0 | BZ7: =BX7+BY7 -> 416.2 | CC7: =D7+J7+P7+V7+AB7+AH7+AN7+AT7+AZ7+BF7+BL7+BR7 -> 120 | CD7: =E7+K7+Q7+W7+AC7+AI7+AO7+AU7+BA7+BG7+BM7+BS7 -> 4 | CE7: =F7+L7+R7+X7+AD7+AJ7+AP7+AV7+BB7+BH7+BN7+BT7 -> 146.2 | CF7: =G7+M7+S7+Y7+AE7+AK7+AQ7+AW7+BC7+BI7+BO7+BU7 -> 6 | CG7: =H7+N7+T7+Z7+AF7+AL7+AR7+AX7+BJ7+BP7+BV7+BD7 -> 140 | CH7: =I7+O7+U7+AA7+AG7+AM7+AS7+AY7+BE7+BK7+BQ7+BW7 -> 0
A8: 6 | B8: ALVAREZ CAMPOS VICTOR | C8: 0 | D8: 0 | E8: 0 | F8: 0 | G8: 0 | H8: 0 | I8: 0 | J8: 0 | K8: 0 | L8: 0 | M8: 0 | N8: 0 | O8: 0 | P8: 0 | Q8: 0 | R8: 0 | S8: 0 | T8: 0 | U8: 0 | V8: 0 | W8: 0 | X8: 0 | Y8: 0 | Z8: 0 | AA8: 0 | AB8: 0 | AC8: 0 | AD8: 0 | AE8: 0 | AF8: 0 | AG8: 0 | AH8: 0 | AI8: 0 | AJ8: 0 | AK8: 0 | AL8: 0 | AM8: 0 | AN8: 0 | AO8: 0 | AP8: 0 | AQ8: 0 | AR8: 0 | AS8: 0 | AT8: 0 | AU8: 0 | AV8: 0 | AW8: 0 | AX8: 0 | AY8: 0 | AZ8: 0 | BA8: 0 | BB8: 0 | BC8: 0 | BF8: 0 | BG8: 0 | BH8: 0 | BI8: 0 | BL8: 0 | BM8: 0 | BN8: 0 | BO8: 0 | BR8: 0 | BS8: 0 | BT8: 44.1 | BU8: 3 | BX8: =SUM(D8:BW8) -> 47.1 | BY8: =C8 -> 0 | BZ8: =BX8+BY8 -> 47.1 | CC8: =D8+J8+P8+V8+AB8+AH8+AN8+AT8+AZ8+BF8+BL8+BR8 -> 0 | CD8: =E8+K8+Q8+W8+AC8+AI8+AO8+AU8+BA8+BG8+BM8+BS8 -> 0 | CE8: =F8+L8+R8+X8+AD8+AJ8+AP8+AV8+BB8+BH8+BN8+BT8 -> 44.1 | CF8: =G8+M8+S8+Y8+AE8+AK8+AQ8+AW8+BC8+BI8+BO8+BU8 -> 3 | CG8: =H8+N8+T8+Z8+AF8+AL8+AR8+AX8+BJ8+BP8+BV8+BD8 -> 0 | CH8: =I8+O8+U8+AA8+AG8+AM8+AS8+AY8+BE8+BK8+BQ8+BW8 -> 0
A9: 7 | B9: ALVAREZ MARIN MARIANELA | C9: 2327 | D9: 0 | E9: 0 | F9: 0 | G9: 0 | H9: 0 | I9: 0 | J9: 0 | K9: 0 | L9: 0 | M9: 0 | N9: 0 | O9: 0 | P9: 0 | Q9: 0 | R9: 0 | S9: 0 | T9: 0 | V9: 0 | W9: 0 | X9: 0 | Y9: 0 | Z9: 0 | AA9: 0 | AB9: 0 | AC9: 0 | AD9: 0 | AE9: 0 | AF9: 0 | AG9: 0 | AH9: 0 | AI9: 0 | AJ9: 0 | AK9: 0 | AL9: 0 | AN9: 0 | AO9: 0 | AP9: 0 | AQ9: 0 | AR9: 0 | AT9: 0 | AU9: 0 | AV9: 0 | AW9: 0 | AX9: 0 | AY9: 0 | AZ9: 0 | BA9: 0 | BB9: 0 | BC9: 0 | BF9: 0 | BG9: 0 | BH9: 0 | BI9: 0 | BL9: 0 | BM9: 0 | BN9: 13.5 | BO9: 3 | BQ9: 59 | BR9: 0 | BS9: 0 | BT9: 13.6 | BU9: 3 | BX9: =SUM(D9:BW9) -> 92.1 | BY9: =C9 -> 2327 | BZ9: =BX9+BY9 -> 2419.1 | CC9: =D9+J9+P9+V9+AB9+AH9+AN9+AT9+AZ9+BF9+BL9+BR9 -> 0 | CD9: =E9+K9+Q9+W9+AC9+AI9+AO9+AU9+BA9+BG9+BM9+BS9 -> 0 | CE9: =F9+L9+R9+X9+AD9+AJ9+AP9+AV9+BB9+BH9+BN9+BT9 -> 27.1 | CF9: =G9+M9+S9+Y9+AE9+AK9+AQ9+AW9+BC9+BI9+BO9+BU9 -> 6 | CG9: =H9+N9+T9+Z9+AF9+AL9+AR9+AX9+BJ9+BP9+BV9+BD9 -> 0 | CH9: =I9+O9+U9+AA9+AG9+AM9+AS9+AY9+BE9+BK9+BQ9+BW9 -> 59
A10: 8 | B10: ALVAREZ MARIN NEIL ROLANDO | C10: 3190.5 | D10: 60 | E10: 2 | F10: 16 | G10: 3 | H10: 0 | I10: 0 | J10: 58 | K10: 2 | L10: 19.5 | M10: 3.5 | N10: 0 | O10: 0 | P10: 60 | Q10: 2 | R10: 18 | S10: 3 | T10: 0 | U10: 75 | V10: 60 | W10: 2 | X10: 12 | Y10: 3.5 | Z10: 0 | AA10: 0 | AB10: 60 | AC10: 2 | AD10: 11 | AE10: 4 | AF10: 0 | AG10: 0 | AH10: 60 | AI10: 2 | AJ10: 10 | AK10: 3 | AL10: 0 | AM10: 75 | AN10: 60 | AO10: 2 | AP10: 8.5 | AQ10: 3 | AR10: 0 | AS10: 85 | AT10: 60 | AU10: 2 | AV10: 0 | AW10: 0 | AX10: 0 | AY10: 25 | AZ10: 60 | BA10: 2 | BB10: 0 | BC10: 0 | BF10: 60 | BG10: 2 | BH10: 9.5 | BI10: 6 | BL10: 60 | BM10: 2 | BN10: 13.5 | BO10: 3 | BQ10: =59+85 -> 144 | BR10: 60 | BS10: 2 | BT10: 13.6 | BU10: 2.8 | BX10: =SUM(D10:BW10) -> 1312.4 | BY10: =C10 -> 3190.5 | BZ10: =BX10+BY10 -> 4502.9 | CC10: =D10+J10+P10+V10+AB10+AH10+AN10+AT10+AZ10+BF10+BL10+BR10 -> 718 | CD10: =E10+K10+Q10+W10+AC10+AI10+AO10+AU10+BA10+BG10+BM10+BS10 -> 24 | CE10: =F10+L10+R10+X10+AD10+AJ10+AP10+AV10+BB10+BH10+BN10+BT10 -> 131.6 | CF10: =G10+M10+S10+Y10+AE10+AK10+AQ10+AW10+BC10+BI10+BO10+BU10 -> 34.8 | CG10: =H10+N10+T10+Z10+AF10+AL10+AR10+AX10+BJ10+BP10+BV10+BD10 -> 0 | CH10: =I10+O10+U10+AA10+AG10+AM10+AS10+AY10+BE10+BK10+BQ10+BW10 -> 404
A11: 9 | B11: ANAMPA CORAHUA CLEMENCIA MIGDONIA | C11: 0 | D11: 0 | E11: 0 | F11: 0 | G11: 0 | H11: 0 | I11: 0 | J11: 0 | K11: 0 | L11: 0 | M11: 0 | N11: 0 | O11: 0 | P11: 0 | Q11: 0 | R11: 0 | S11: 0 | T11: 0 | V11: 0 | W11: 0 | X11: 0 | Y11: 0 | Z11: 0 | AA11: 0 | AB11: 0 | AC11: 0 | AD11: 0 | AE11: 0 | AF11: 0 | AG11: 0 | AH11: 0 | AI11: 0 | AJ11: 0 | AK11: 0 | AL11: 0 | AM11: 0 | AN11: 0 | AO11: 0 | AP11: 0 | AQ11: 0 | AR11: 0 | AT11: 0 | AU11: 0 | AV11: 0 | AW11: 0 | AX11: 0 | AZ11: 0 | BA11: 0 | BB11: 0 | BC11: 0 | BD11: 0 | BF11: 0 | BG11: 0 | BH11: 0 | BI11: 0 | BJ11: 0 | BL11: 0 | BM11: 0 | BN11: 0 | BO11: 0 | BP11: 0 | BR11: 60 | BS11: 2 | BT11: 64.3 | BU11: 3 | BV11: 60 | BX11: =SUM(D11:BW11) -> 189.3 | BY11: =C11 -> 0 | BZ11: =BX11+BY11 -> 189.3 | CC11: =D11+J11+P11+V11+AB11+AH11+AN11+AT11+AZ11+BF11+BL11+BR11 -> 60 | CD11: =E11+K11+Q11+W11+AC11+AI11+AO11+AU11+BA11+BG11+BM11+BS11 -> 2 | CE11: =F11+L11+R11+X11+AD11+AJ11+AP11+AV11+BB11+BH11+BN11+BT11 -> 64.3 | CF11: =G11+M11+S11+Y11+AE11+AK11+AQ11+AW11+BC11+BI11+BO11+BU11 -> 3 | CG11: =H11+N11+T11+Z11+AF11+AL11+AR11+AX11+BJ11+BP11+BV11+BD11 -> 60 | CH11: =I11+O11+U11+AA11+AG11+AM11+AS11+AY11+BE11+BK11+BQ11+BW11 -> 0
A12: 10 | B12: ANCCO LEON VALENTINA | C12: 0 | D12: 0 | E12: 0 | F12: 0 | G12: 0 | H12: 0 | I12: 0 | J12: 0 | K12: 0 | L12: 0 | M12: 0 | N12: 0 | O12: 0 | P12: 0 | Q12: 0 | R12: 0 | S12: 0 | T12: 0 | V12: 0 | W12: 0 | X12: 0 | Y12: 0 | Z12: 0 | AB12: 0 | AC12: 0 | AD12: 0 | AE12: 0 | AF12: 0 | AH12: 0 | AI12: 0 | AJ12: 0 | AK12: 0 | AL12: 0 | AN12: 0 | AO12: 0 | AP12: 0 | AQ12: 0 | AR12: 0 | AT12: 0 | AU12: 0 | AV12: 0 | AW12: 0 | AX12: 0 | AZ12: 0 | BA12: 0 | BB12: 0 | BC12: 0 | BF12: 0 | BG12: 0 | BH12: 0 | BI12: 0 | BL12: 60 | BM12: 2 | BN12: 51 | BO12: 3 | BQ12: 59 | BR12: 60 | BS12: 2 | BT12: 53.4 | BU12: 3 | BX12: =SUM(D12:BW12) -> 293.4 | BY12: =C12 -> 0 | BZ12: =BX12+BY12 -> 293.4 | CC12: =D12+J12+P12+V12+AB12+AH12+AN12+AT12+AZ12+BF12+BL12+BR12 -> 120 | CD12: =E12+K12+Q12+W12+AC12+AI12+AO12+AU12+BA12+BG12+BM12+BS12 -> 4 | CE12: =F12+L12+R12+X12+AD12+AJ12+AP12+AV12+BB12+BH12+BN12+BT12 -> 104.4 | CF12: =G12+M12+S12+Y12+AE12+AK12+AQ12+AW12+BC12+BI12+BO12+BU12 -> 6 | CG12: =H12+N12+T12+Z12+AF12+AL12+AR12+AX12+BJ12+BP12+BV12+BD12 -> 0 | CH12: =I12+O12+U12+AA12+AG12+AM12+AS12+AY12+BE12+BK12+BQ12+BW12 -> 59
A13: 11 | B13: ATANASIO ORTEGA MAXIMILIANA | C13: 362 | D13: 0 | E13: 0 | F13: 0 | G13: 0 | H13: 0 | J13: 0 | K13: 0 | L13: 0 | M13: 0 | N13: 0 | P13: 0 | Q13: 0 | R13: 0 | S13: 0 | T13: 0 | V13: 0 | W13: 0 | X13: 0 | Y13: 0 | Z13: 0 | AB13: 0 | AC13: 0 | AD13: 0 | AE13: 0 | AF13: 0 | AH13: 0 | AI13: 0 | AJ13: 0 | AK13: 0 | AL13: 0 | AN13: 0 | AO13: 0 | AP13: 0 | AQ13: 0 | AR13: 0 | AT13: 0 | AU13: 0 | AV13: 0 | AW13: 0 | AX13: 0 | AZ13: 0 | BA13: 0 | BB13: 0 | BC13: 0 | BF13: 0 | BG13: 0 | BH13: 0 | BI13: 0 | BL13: 0 | BM13: 0 | BN13: 51.5 | BO13: 3 | BQ13: 59 | BR13: 0 | BS13: 0 | BT13: 55 | BU13: 3 | BX13: =SUM(D13:BW13) -> 171.5 | BY13: =C13 -> 362 | BZ13: =BX13+BY13 -> 533.5 | CC13: =D13+J13+P13+V13+AB13+AH13+AN13+AT13+AZ13+BF13+BL13+BR13 -> 0 | CD13: =E13+K13+Q13+W13+AC13+AI13+AO13+AU13+BA13+BG13+BM13+BS13 -> 0 | CE13: =F13+L13+R13+X13+AD13+AJ13+AP13+AV13+BB13+BH13+BN13+BT13 -> 106.5 | CF13: =G13+M13+S13+Y13+AE13+AK13+AQ13+AW13+BC13+BI13+BO13+BU13 -> 6 | CG13: =H13+N13+T13+Z13+AF13+AL13+AR13+AX13+BJ13+BP13+BV13+BD13 -> 0 | CH13: =I13+O13+U13+AA13+AG13+AM13+AS13+AY13+BE13+BK13+BQ13+BW13 -> 59
A14: 12 | B14: AYALA HUASHUAYO NORMA GLADYS | C14: 75 | D14: 0 | E14: 0 | F14: 0 | G14: 0 | H14: 0 | J14: 0 | K14: 0 | L14: 0 | M14: 0 | N14: 0 | P14: 0 | Q14: 0 | R14: 0 | S14: 0 | T14: 0 | V14: 0 | W14: 0 | X14: 0 | Y14: 0 | Z14: 0 | AB14: 0 | AC14: 0 | AD14: 0 | AE14: 0 | AF14: 0 | AH14: 0 | AI14: 0 | AJ14: 0 | AK14: 0 | AL14: 0 | AN14: 0 | AO14: 0 | AP14: 0 | AQ14: 0 | AR14: 0 | AT14: 0 | AU14: 0 | AV14: 0 | AW14: 0 | AX14: 0 | AZ14: 0 | BA14: 0 | BB14: 0 | BC14: 0 | BF14: 0 | BG14: 0 | BH14: 0 | BI14: 0 | BL14: 0 | BM14: 0 | BN14: 35 | BO14: 3 | BR14: 60 | BS14: 2 | BT14: 35.9 | BU14: 3 | BX14: =SUM(D14:BW14) -> 138.9 | BY14: =C14 -> 75 | BZ14: =BX14+BY14 -> 213.9 | CC14: =D14+J14+P14+V14+AB14+AH14+AN14+AT14+AZ14+BF14+BL14+BR14 -> 60 | CD14: =E14+K14+Q14+W14+AC14+AI14+AO14+AU14+BA14+BG14+BM14+BS14 -> 2 | CE14: =F14+L14+R14+X14+AD14+AJ14+AP14+AV14+BB14+BH14+BN14+BT14 -> 70.9 | CF14: =G14+M14+S14+Y14+AE14+AK14+AQ14+AW14+BC14+BI14+BO14+BU14 -> 6 | CG14: =H14+N14+T14+Z14+AF14+AL14+AR14+AX14+BJ14+BP14+BV14+BD14 -> 0 | CH14: =I14+O14+U14+AA14+AG14+AM14+AS14+AY14+BE14+BK14+BQ14+BW14 -> 0
A15: 13 | B15: AYALA TABOADA ELISEO | C15: 0 | D15: 0 | E15: 0 | F15: 0 | G15: 0 | H15: 0 | J15: 0 | K15: 0 | L15: 0 | M15: 0 | N15: 0 | P15: 0 | Q15: 0 | R15: 0 | S15: 0 | T15: 0 | V15: 0 | W15: 0 | X15: 0 | Y15: 0 | Z15: 0 | AB15: 0 | AC15: 0 | AD15: 0 | AE15: 0 | AF15: 0 | AH15: 0 | AI15: 0 | AJ15: 0 | AK15: 0 | AL15: 0 | AN15: 0 | AO15: 0 | AP15: 0 | AQ15: 0 | AR15: 0 | AT15: 0 | AU15: 0 | AV15: 0 | AW15: 0 | AX15: 0 | AZ15: 0 | BA15: 0 | BB15: 0 | BC15: 0 | BD15: 0 | BF15: 0 | BG15: 0 | BH15: 0 | BI15: 0 | BJ15: 0 | BL15: 0 | BM15: 0 | BN15: 79 | BO15: 3 | BP15: 0 | BR15: 60 | BS15: 2 | BT15: 83.9 | BU15: 3 | BV15: 80 | BX15: =SUM(D15:BW15) -> 310.9 | BY15: =C15 -> 0 | BZ15: =BX15+BY15 -> 310.9 | CC15: =D15+J15+P15+V15+AB15+AH15+AN15+AT15+AZ15+BF15+BL15+BR15 -> 60 | CD15: =E15+K15+Q15+W15+AC15+AI15+AO15+AU15+BA15+BG15+BM15+BS15 -> 2 | CE15: =F15+L15+R15+X15+AD15+AJ15+AP15+AV15+BB15+BH15+BN15+BT15 -> 162.9 | CF15: =G15+M15+S15+Y15+AE15+AK15+AQ15+AW15+BC15+BI15+BO15+BU15 -> 6 | CG15: =H15+N15+T15+Z15+AF15+AL15+AR15+AX15+BJ15+BP15+BV15+BD15 -> 80 | CH15: =I15+O15+U15+AA15+AG15+AM15+AS15+AY15+BE15+BK15+BQ15+BW15 -> 0
A16: 14 | B16: BASTIDAS MEDINA DINA | C16: 275 | D16: 0 | E16: 0 | F16: 0 | G16: 0 | H16: 0 | J16: 0 | K16: 0 | L16: 0 | M16: 0 | N16: 0 | P16: 0 | Q16: 0 | R16: 0 | S16: 0 | T16: 0 | U16: 75 | V16: 60 | W16: 2 | X16: 0 | Y16: 0 | Z16: 0 | AB16: 60 | AC16: 2 | AD16: 0 | AE16: 0 | AF16: 0 | AH16: 60 | AI16: 2 | AJ16: 0 | AK16: 0 | AL16: 0 | AM16: 75 | AN16: 60 | AO16: 2 | AP16: 0 | AQ16: 0 | AR16: 0 | AS16: 85 | AT16: 60 | AU16: 2 | AV16: 0 | AW16: 0 | AX16: 0 | AZ16: 60 | BA16: 2 | BB16: 0 | BC16: 0 | BF16: 60 | BG16: 2 | BH16: 0 | BI16: 0 | BL16: 60 | BM16: 2 | BN16: 45.5 | BO16: 3 | BQ16: =59+85 -> 144 | BR16: 60 | BS16: 2 | BT16: 48.5 | BU16: 3 | BX16: =SUM(D16:BW16) -> 1037 | BY16: =C16 -> 275 | BZ16: =BX16+BY16 -> 1312 | CC16: =D16+J16+P16+V16+AB16+AH16+AN16+AT16+AZ16+BF16+BL16+BR16 -> 540 | CD16: =E16+K16+Q16+W16+AC16+AI16+AO16+AU16+BA16+BG16+BM16+BS16 -> 18 | CE16: =F16+L16+R16+X16+AD16+AJ16+AP16+AV16+BB16+BH16+BN16+BT16 -> 94 | CF16: =G16+M16+S16+Y16+AE16+AK16+AQ16+AW16+BC16+BI16+BO16+BU16 -> 6 | CG16: =H16+N16+T16+Z16+AF16+AL16+AR16+AX16+BJ16+BP16+BV16+BD16 -> 0 | CH16: =I16+O16+U16+AA16+AG16+AM16+AS16+AY16+BE16+BK16+BQ16+BW16 -> 379
A17: 15 | B17: BASTIDAS MEDINA HERMENEGILDO | C17: 0 | D17: 0 | E17: 0 | F17: 0 | G17: 0 | H17: 0 | J17: 0 | K17: 0 | L17: 0 | M17: 0 | N17: 0 | P17: 0 | Q17: 0 | R17: 0 | S17: 0 | T17: 0 | V17: 0 | W17: 0 | X17: 0 | Y17: 0 | Z17: 0 | AB17: 0 | AC17: 0 | AD17: 0 | AE17: 0 | AF17: 0 | AH17: 0 | AI17: 0 | AJ17: 0 | AK17: 0 | AL17: 0 | AN17: 0 | AO17: 0 | AP17: 0 | AQ17: 0 | AR17: 0 | AT17: 0 | AU17: 0 | AV17: 0 | AW17: 0 | AX17: 0 | AZ17: 0 | BA17: 0 | BB17: 0 | BC17: 0 | BF17: 0 | BG17: 0 | BH17: 0 | BI17: 0 | BL17: 60 | BM17: 2 | BN17: 33.5 | BO17: 3 | BR17: 60 | BS17: 2 | BT17: 35.4 | BU17: 3 | BW17: 80 | BX17: =SUM(D17:BW17) -> 278.9 | BY17: =C17 -> 0 | BZ17: =BX17+BY17 -> 278.9 | CC17: =D17+J17+P17+V17+AB17+AH17+AN17+AT17+AZ17+BF17+BL17+BR17 -> 120 | CD17: =E17+K17+Q17+W17+AC17+AI17+AO17+AU17+BA17+BG17+BM17+BS17 -> 4 | CE17: =F17+L17+R17+X17+AD17+AJ17+AP17+AV17+BB17+BH17+BN17+BT17 -> 68.9 | CF17: =G17+M17+S17+Y17+AE17+AK17+AQ17+AW17+BC17+BI17+BO17+BU17 -> 6 | CG17: =H17+N17+T17+Z17+AF17+AL17+AR17+AX17+BJ17+BP17+BV17+BD17 -> 0 | CH17: =I17+O17+U17+AA17+AG17+AM17+AS17+AY17+BE17+BK17+BQ17+BW17 -> 80
A18: 16 | B18: BERNAOLA DE PRADO FLORENCIA | C18: 0 | D18: 0 | E18: 0 | F18: 0 | G18: 0 | H18: 0 | J18: 0 | K18: 0 | L18: 0 | M18: 0 | N18: 0 | P18: 0 | Q18: 0 | R18: 0 | S18: 0 | T18: 0 | V18: 0 | W18: 0 | X18: 0 | Y18: 0 | Z18: 0 | AB18: 0 | AC18: 0 | AD18: 0 | AE18: 0 | AF18: 0 | AH18: 0 | AI18: 0 | AJ18: 0 | AK18: 0 | AL18: 0 | AN18: 0 | AO18: 0 | AP18: 0 | AQ18: 0 | AR18: 0 | AT18: 0 | AU18: 0 | AV18: 0 | AW18: 0 | AX18: 0 | AZ18: 0 | BA18: 0 | BB18: 0 | BC18: 0 | BF18: 0 | BG18: 0 | BH18: 0 | BI18: 0 | BL18: 0 | BM18: 0 | BN18: 0 | BO18: 0 | BR18: 0 | BS18: 0 | BT18: 69.2 | BU18: 19 | BW18: 80 | BX18: =SUM(D18:BW18) -> 168.2 | BY18: =C18 -> 0 | BZ18: =BX18+BY18 -> 168.2 | CC18: =D18+J18+P18+V18+AB18+AH18+AN18+AT18+AZ18+BF18+BL18+BR18 -> 0 | CD18: =E18+K18+Q18+W18+AC18+AI18+AO18+AU18+BA18+BG18+BM18+BS18 -> 0 | CE18: =F18+L18+R18+X18+AD18+AJ18+AP18+AV18+BB18+BH18+BN18+BT18 -> 69.2 | CF18: =G18+M18+S18+Y18+AE18+AK18+AQ18+AW18+BC18+BI18+BO18+BU18 -> 19 | CG18: =H18+N18+T18+Z18+AF18+AL18+AR18+AX18+BJ18+BP18+BV18+BD18 -> 0 | CH18: =I18+O18+U18+AA18+AG18+AM18+AS18+AY18+BE18+BK18+BQ18+BW18 -> 80
A19: 17 | B19: BRAVO HEREDIA ANA MARITZA | C19: 3464.5 | D19: 0 | E19: 0 | F19: 0 | G19: 0 | H19: 0 | J19: 0 | K19: 0 | L19: 0 | M19: 0 | N19: 0 | P19: 0 | Q19: 0 | R19: 0 | S19: 0 | T19: 0 | U19: 75 | V19: 0 | W19: 0 | X19: 0 | Y19: 0 | Z19: 0 | AB19: 0 | AC19: 0 | AD19: 0 | AE19: 0 | AF19: 0 | AH19: 0 | AI19: 0 | AJ19: 0 | AK19: 0 | AL19: 0 | AM19: 75 | AN19: 0 | AO19: 0 | AP19: 0 | AQ19: 0 | AR19: 0 | AS19: 85 | AT19: 0 | AU19: 0 | AV19: 0 | AW19: 0 | AX19: 0 | AZ19: 0 | BA19: 0 | BB19: 0 | BC19: 0 | BF19: 0 | BG19: 0 | BH19: 0 | BI19: 0 | BL19: 0 | BM19: 0 | BN19: 0 | BO19: 0 | BQ19: 85 | BR19: 0 | BS19: 0 | BT19: 51.2 | BU19: 3 | BX19: =SUM(D19:BW19) -> 374.2 | BY19: =C19 -> 3464.5 | BZ19: =BX19+BY19 -> 3838.7 | CC19: =D19+J19+P19+V19+AB19+AH19+AN19+AT19+AZ19+BF19+BL19+BR19 -> 0 | CD19: =E19+K19+Q19+W19+AC19+AI19+AO19+AU19+BA19+BG19+BM19+BS19 -> 0 | CE19: =F19+L19+R19+X19+AD19+AJ19+AP19+AV19+BB19+BH19+BN19+BT19 -> 51.2 | CF19: =G19+M19+S19+Y19+AE19+AK19+AQ19+AW19+BC19+BI19+BO19+BU19 -> 3 | CG19: =H19+N19+T19+Z19+AF19+AL19+AR19+AX19+BJ19+BP19+BV19+BD19 -> 0 | CH19: =I19+O19+U19+AA19+AG19+AM19+AS19+AY19+BE19+BK19+BQ19+BW19 -> 320
A20: 18 | B20: BURGA CARRASCO ELIDA | C20: 0 | D20: 0 | E20: 0 | F20: 0 | G20: 0 | H20: 0 | J20: 0 | K20: 0 | L20: 0 | M20: 0 | N20: 0 | P20: 0 | Q20: 0 | R20: 0 | S20: 0 | T20: 0 | V20: 0 | W20: 0 | X20: 0 | Y20: 0 | Z20: 0 | AB20: 0 | AC20: 0 | AD20: 0 | AE20: 0 | AF20: 0 | AH20: 0 | AI20: 0 | AJ20: 0 | AK20: 0 | AL20: 0 | AN20: 0 | AO20: 0 | AP20: 0 | AQ20: 0 | AR20: 0 | AT20: 0 | AU20: 0 | AV20: 0 | AW20: 0 | AX20: 0 | AZ20: 0 | BA20: 0 | BB20: 0 | BC20: 0 | BF20: 0 | BG20: 0 | BH20: 0 | BI20: 0 | BL20: 0 | BM20: 0 | BN20: 0 | BO20: 0 | BQ20: 85 | BR20: 0 | BS20: 0 | BT20: 105.7 | BU20: 3 | BX20: =SUM(D20:BW20) -> 193.7 | BY20: =C20 -> 0 | BZ20: =BX20+BY20 -> 193.7 | CC20: =D20+J20+P20+V20+AB20+AH20+AN20+AT20+AZ20+BF20+BL20+BR20 -> 0 | CD20: =E20+K20+Q20+W20+AC20+AI20+AO20+AU20+BA20+BG20+BM20+BS20 -> 0 | CE20: =F20+L20+R20+X20+AD20+AJ20+AP20+AV20+BB20+BH20+BN20+BT20 -> 105.7 | CF20: =G20+M20+S20+Y20+AE20+AK20+AQ20+AW20+BC20+BI20+BO20+BU20 -> 3 | CG20: =H20+N20+T20+Z20+AF20+AL20+AR20+AX20+BJ20+BP20+BV20+BD20 -> 0 | CH20: =I20+O20+U20+AA20+AG20+AM20+AS20+AY20+BE20+BK20+BQ20+BW20 -> 85
A21: 19 | B21: CABALLERO CALZADO GLADYS VICTORIA | C21: 0 | D21: 0 | E21: 0 | F21: 0 | G21: 0 | H21: 0 | J21: 0 | K21: 0 | L21: 0 | M21: 0 | N21: 0 | P21: 0 | Q21: 0 | R21: 0 | S21: 0 | T21: 0 | V21: 0 | W21: 0 | X21: 0 | Y21: 0 | Z21: 0 | AB21: 0 | AC21: 0 | AD21: 0 | AE21: 0 | AF21: 0 | AH21: 0 | AI21: 0 | AJ21: 0 | AK21: 0 | AL21: 0 | AN21: 0 | AO21: 0 | AP21: 0 | AQ21: 0 | AR21: 0 | AT21: 0 | AU21: 0 | AV21: 0 | AW21: 0 | AX21: 0 | AZ21: 0 | BA21: 0 | BB21: 0 | BC21: 0 | BF21: 0 | BG21: 0 | BH21: 0 | BI21: 0 | BL21: 0 | BM21: 0 | BN21: 21.5 | BO21: 3 | BR21: 0 | BS21: 0 | BT21: 22.3 | BU21: 3 | BX21: =SUM(D21:BW21) -> 49.8 | BY21: =C21 -> 0 | BZ21: =BX21+BY21 -> 49.8 | CC21: =D21+J21+P21+V21+AB21+AH21+AN21+AT21+AZ21+BF21+BL21+BR21 -> 0 | CD21: =E21+K21+Q21+W21+AC21+AI21+AO21+AU21+BA21+BG21+BM21+BS21 -> 0 | CE21: =F21+L21+R21+X21+AD21+AJ21+AP21+AV21+BB21+BH21+BN21+BT21 -> 43.8 | CF21: =G21+M21+S21+Y21+AE21+AK21+AQ21+AW21+BC21+BI21+BO21+BU21 -> 6 | CG21: =H21+N21+T21+Z21+AF21+AL21+AR21+AX21+BJ21+BP21+BV21+BD21 -> 0 | CH21: =I21+O21+U21+AA21+AG21+AM21+AS21+AY21+BE21+BK21+BQ21+BW21 -> 0
A22: 20 | B22: CAHUANA VDA DE DAVILA VICENTINA | C22: 0 | D22: 0 | E22: 0 | F22: 0 | G22: 0 | H22: 0 | J22: 0 | K22: 0 | L22: 0 | M22: 0 | N22: 0 | P22: 0 | Q22: 0 | R22: 0 | S22: 0 | T22: 0 | V22: 0 | W22: 0 | X22: 0 | Y22: 0 | Z22: 0 | AB22: 0 | AC22: 0 | AD22: 0 | AE22: 0 | AF22: 0 | AH22: 0 | AI22: 0 | AJ22: 0 | AK22: 0 | AL22: 0 | AN22: 0 | AO22: 0 | AP22: 0 | AQ22: 0 | AR22: 0 | AT22: 0 | AU22: 0 | AV22: 0 | AW22: 0 | AX22: 0 | AZ22: 0 | BA22: 0 | BB22: 0 | BC22: 0 | BF22: 0 | BG22: 0 | BH22: 0 | BI22: 0 | BL22: 0 | BM22: 0 | BN22: 64.5 | BO22: 42 | BR22: 0 | BS22: 0 | BT22: 69.2 | BU22: 42 | BW22: 80 | BX22: =SUM(D22:BW22) -> 297.7 | BY22: =C22 -> 0 | BZ22: =BX22+BY22 -> 297.7 | CC22: =D22+J22+P22+V22+AB22+AH22+AN22+AT22+AZ22+BF22+BL22+BR22 -> 0 | CD22: =E22+K22+Q22+W22+AC22+AI22+AO22+AU22+BA22+BG22+BM22+BS22 -> 0 | CE22: =F22+L22+R22+X22+AD22+AJ22+AP22+AV22+BB22+BH22+BN22+BT22 -> 133.7 | CF22: =G22+M22+S22+Y22+AE22+AK22+AQ22+AW22+BC22+BI22+BO22+BU22 -> 84 | CG22: =H22+N22+T22+Z22+AF22+AL22+AR22+AX22+BJ22+BP22+BV22+BD22 -> 0 | CH22: =I22+O22+U22+AA22+AG22+AM22+AS22+AY22+BE22+BK22+BQ22+BW22 -> 80
A23: 21 | B23: CAJALEON CARRASCO LUIS ENRIQUE | C23: 100 | D23: 0 | E23: 0 | F23: 0 | G23: 0 | H23: 0 | J23: 0 | K23: 0 | L23: 0 | M23: 0 | N23: 0 | P23: 0 | Q23: 0 | R23: 0 | S23: 0 | T23: 0 | V23: 0 | W23: 0 | X23: 0 | Y23: 0 | Z23: 0 | AB23: 0 | AC23: 0 | AD23: 0 | AE23: 0 | AF23: 0 | AH23: 0 | AI23: 0 | AJ23: 0 | AK23: 0 | AL23: 0 | AN23: 0 | AO23: 0 | AP23: 0 | AQ23: 0 | AR23: 0 | AT23: 0 | AU23: 0 | AV23: 0 | AW23: 0 | AX23: 0 | AZ23: 0 | BA23: 0 | BB23: 0 | BC23: 0 | BF23: 0 | BG23: 0 | BH23: 0 | BI23: 0 | BL23: 0 | BM23: 0 | BN23: 0 | BO23: 9 | BR23: 0 | BS23: 0 | BU23: 15.2 | BW23: 80 | BX23: =SUM(D23:BW23) -> 104.2 | BY23: =C23 -> 100 | BZ23: =BX23+BY23 -> 204.2 | CC23: =D23+J23+P23+V23+AB23+AH23+AN23+AT23+AZ23+BF23+BL23+BR23 -> 0 | CD23: =E23+K23+Q23+W23+AC23+AI23+AO23+AU23+BA23+BG23+BM23+BS23 -> 0 | CE23: =F23+L23+R23+X23+AD23+AJ23+AP23+AV23+BB23+BH23+BN23+BT23 -> 0 | CF23: =G23+M23+S23+Y23+AE23+AK23+AQ23+AW23+BC23+BI23+BO23+BU23 -> 24.2 | CG23: =H23+N23+T23+Z23+AF23+AL23+AR23+AX23+BJ23+BP23+BV23+BD23 -> 0 | CH23: =I23+O23+U23+AA23+AG23+AM23+AS23+AY23+BE23+BK23+BQ23+BW23 -> 80
A24: 22 | B24: CAJALEON HIDALGO TEODORO | C24: 0 | D24: 0 | E24: 0 | F24: 0 | G24: 0 | H24: 0 | J24: 0 | K24: 0 | L24: 0 | M24: 0 | N24: 0 | P24: 0 | Q24: 0 | R24: 0 | S24: 0 | T24: 0 | V24: 0 | W24: 0 | X24: 0 | Y24: 0 | Z24: 0 | AB24: 0 | AC24: 0 | AD24: 0 | AE24: 0 | AF24: 0 | AH24: 0 | AI24: 0 | AJ24: 0 | AK24: 0 | AL24: 0 | AN24: 0 | AO24: 0 | AP24: 0 | AQ24: 0 | AR24: 0 | AT24: 0 | AU24: 0 | AV24: 0 | AW24: 0 | AX24: 0 | AZ24: 0 | BA24: 0 | BB24: 0 | BC24: 0 | BE24: 15 | BF24: 0 | BG24: 0 | BH24: 0 | BI24: 0 | BL24: 0 | BM24: 0 | BN24: 0 | BO24: 0 | BR24: 14 | BS24: 2 | BU24: 37.5 | BV24: 84.5 | BW24: 80 | BX24: =SUM(D24:BW24) -> 233 | BY24: =C24 -> 0 | BZ24: =BX24+BY24 -> 233 | CC24: =D24+J24+P24+V24+AB24+AH24+AN24+AT24+AZ24+BF24+BL24+BR24 -> 14 | CD24: =E24+K24+Q24+W24+AC24+AI24+AO24+AU24+BA24+BG24+BM24+BS24 -> 2 | CE24: =F24+L24+R24+X24+AD24+AJ24+AP24+AV24+BB24+BH24+BN24+BT24 -> 0 | CF24: =G24+M24+S24+Y24+AE24+AK24+AQ24+AW24+BC24+BI24+BO24+BU24 -> 37.5 | CG24: =H24+N24+T24+Z24+AF24+AL24+AR24+AX24+BJ24+BP24+BV24+BD24 -> 84.5 | CH24: =I24+O24+U24+AA24+AG24+AM24+AS24+AY24+BE24+BK24+BQ24+BW24 -> 95
A25: 23 | B25: CALDERON TORRES ALDO EDGAR | C25: 2821.5 | D25: 60 | E25: 2 | F25: 86 | G25: 3 | H25: 0 | J25: 58 | K25: 2 | L25: 89.5 | M25: 3.5 | N25: 0 | P25: 60 | Q25: 2 | R25: 88 | S25: 3 | T25: 0 | U25: 75 | V25: 60 | W25: 2 | X25: 24 | Y25: 3.5 | Z25: 0 | AB25: 60 | AC25: 2 | AD25: 23 | AE25: 4 | AF25: 0 | AG25: 30 | AH25: 60 | AI25: 2 | AJ25: 20 | AK25: 3 | AL25: 0 | AM25: 75 | AN25: 60 | AO25: 2 | AP25: 18.5 | AQ25: 3 | AR25: 0 | AS25: 85 | AT25: 60 | AU25: 2 | AV25: 17.5 | AW25: 2.5 | AX25: 0 | AY25: 25 | AZ25: 60 | BA25: 2 | BB25: 20.5 | BC25: 2 | BE25: 15 | BF25: 60 | BG25: 2 | BH25: 19 | BI25: 6 | BL25: 60 | BM25: 2 | BN25: 27 | BO25: 3 | BQ25: =59+85 -> 144 | BR25: 60 | BS25: 2 | BT25: 27.2 | BU25: 3 | BX25: =SUM(D25:BW25) -> 1690.7 | BY25: =C25 -> 2821.5 | BZ25: =BX25+BY25 -> 4512.2 | CC25: =D25+J25+P25+V25+AB25+AH25+AN25+AT25+AZ25+BF25+BL25+BR25 -> 718 | CD25: =E25+K25+Q25+W25+AC25+AI25+AO25+AU25+BA25+BG25+BM25+BS25 -> 24 | CE25: =F25+L25+R25+X25+AD25+AJ25+AP25+AV25+BB25+BH25+BN25+BT25 -> 460.2 | CF25: =G25+M25+S25+Y25+AE25+AK25+AQ25+AW25+BC25+BI25+BO25+BU25 -> 39.5 | CG25: =H25+N25+T25+Z25+AF25+AL25+AR25+AX25+BJ25+BP25+BV25+BD25 -> 0 | CH25: =I25+O25+U25+AA25+AG25+AM25+AS25+AY25+BE25+BK25+BQ25+BW25 -> 449
A26: 24 | B26: CALDERON VERA SEGUNDO ALCIDES | C26: 10 | D26: 0 | E26: 0 | F26: 0 | G26: 0 | H26: 0 | J26: 0 | K26: 0 | L26: 0 | M26: 0 | N26: 0 | P26: 0 | Q26: 0 | R26: 0 | S26: 0 | T26: 0 | V26: 0 | W26: 0 | X26: 0 | Y26: 0 | Z26: 0 | AB26: 0 | AC26: 0 | AD26: 0 | AE26: 0 | AF26: 0 | AH26: 0 | AI26: 0 | AJ26: 0 | AK26: 0 | AL26: 0 | AN26: 0 | AO26: 0 | AP26: 0 | AQ26: 0 | AR26: 0 | AT26: 0 | AU26: 0 | AV26: 0 | AW26: 0 | AX26: 0 | AZ26: 0 | BA26: 0 | BB26: 0 | BC26: 0 | BF26: 0 | BG26: 0 | BH26: 0 | BI26: 0 | BL26: 60 | BM26: 2 | BN26: 81.5 | BO26: 55 | BR26: 60 | BS26: 2 | BT26: 87.7 | BU26: 55 | BW26: 80 | BX26: =SUM(D26:BW26) -> 483.2 | BY26: =C26 -> 10 | BZ26: =BX26+BY26 -> 493.2 | CC26: =D26+J26+P26+V26+AB26+AH26+AN26+AT26+AZ26+BF26+BL26+BR26 -> 120 | CD26: =E26+K26+Q26+W26+AC26+AI26+AO26+AU26+BA26+BG26+BM26+BS26 -> 4 | CE26: =F26+L26+R26+X26+AD26+AJ26+AP26+AV26+BB26+BH26+BN26+BT26 -> 169.2 | CF26: =G26+M26+S26+Y26+AE26+AK26+AQ26+AW26+BC26+BI26+BO26+BU26 -> 110 | CG26: =H26+N26+T26+Z26+AF26+AL26+AR26+AX26+BJ26+BP26+BV26+BD26 -> 0 | CH26: =I26+O26+U26+AA26+AG26+AM26+AS26+AY26+BE26+BK26+BQ26+BW26 -> 80
A27: 25 | B27: CALLE CALLE FIDEL | C27: 0 | D27: 0 | E27: 0 | F27: 0 | G27: 0 | H27: 0 | J27: 0 | K27: 0 | L27: 0 | M27: 0 | N27: 0 | P27: 0 | Q27: 0 | R27: 0 | S27: 0 | T27: 0 | V27: 0 | W27: 0 | X27: 0 | Y27: 0 | Z27: 0 | AB27: 0 | AC27: 0 | AD27: 0 | AE27: 0 | AF27: 0 | AH27: 0 | AI27: 0 | AJ27: 0 | AK27: 0 | AL27: 0 | AN27: 0 | AO27: 0 | AP27: 0 | AQ27: 0 | AR27: 0 | AT27: 0 | AU27: 0 | AV27: 0 | AW27: 0 | AX27: 0 | AZ27: 0 | BA27: 0 | BB27: 0 | BC27: 0 | BF27: 0 | BG27: 0 | BH27: 0 | BI27: 0 | BL27: 0 | BM27: 0 | BN27: 68 | BO27: 3 | BQ27: 59 | BR27: 0 | BS27: 0 | BT27: 71.9 | BU27: 3 | BX27: =SUM(D27:BW27) -> 204.9 | BY27: =C27 -> 0 | BZ27: =BX27+BY27 -> 204.9 | CC27: =D27+J27+P27+V27+AB27+AH27+AN27+AT27+AZ27+BF27+BL27+BR27 -> 0 | CD27: =E27+K27+Q27+W27+AC27+AI27+AO27+AU27+BA27+BG27+BM27+BS27 -> 0 | CE27: =F27+L27+R27+X27+AD27+AJ27+AP27+AV27+BB27+BH27+BN27+BT27 -> 139.9 | CF27: =G27+M27+S27+Y27+AE27+AK27+AQ27+AW27+BC27+BI27+BO27+BU27 -> 6 | CG27: =H27+N27+T27+Z27+AF27+AL27+AR27+AX27+BJ27+BP27+BV27+BD27 -> 0 | CH27: =I27+O27+U27+AA27+AG27+AM27+AS27+AY27+BE27+BK27+BQ27+BW27 -> 59
A28: 26 | B28: CAMPUZANO CABELLO VICENTA DONATILA | C28: 144 | D28: 60 | E28: 2 | F28: 0 | G28: 0 | H28: 0 | J28: 58 | K28: 2 | L28: 0 | M28: 0 | N28: 0 | P28: 60 | Q28: 2 | R28: 0 | S28: 0 | T28: 0 | U28: 75 | V28: 60 | W28: 2 | X28: 0 | Y28: 0 | Z28: 0 | AB28: 60 | AC28: 2 | AD28: 0 | AE28: 0 | AF28: 0 | AH28: 60 | AI28: 2 | AJ28: 0 | AK28: 0 | AL28: 0 | AM28: 75 | AN28: 60 | AO28: 2 | AP28: 0 | AQ28: 0 | AR28: 0 | AS28: 85 | AT28: 60 | AU28: 2 | AV28: 0 | AW28: 0 | AX28: 0 | AY28: 25 | AZ28: 60 | BA28: 2 | BB28: 0 | BC28: 0 | BF28: 60 | BG28: 2 | BH28: 0 | BI28: 0 | BL28: 60 | BM28: 2 | BN28: 35.5 | BO28: 3 | BQ28: =59+85 -> 144 | BR28: 60 | BS28: 2 | BT28: 37.6 | BU28: 3 | BW28: 80 | BX28: =SUM(D28:BW28) -> 1305.1 | BY28: =C28 -> 144 | BZ28: =BX28+BY28 -> 1449.1 | CC28: =D28+J28+P28+V28+AB28+AH28+AN28+AT28+AZ28+BF28+BL28+BR28 -> 718 | CD28: =E28+K28+Q28+W28+AC28+AI28+AO28+AU28+BA28+BG28+BM28+BS28 -> 24 | CE28: =F28+L28+R28+X28+AD28+AJ28+AP28+AV28+BB28+BH28+BN28+BT28 -> 73.1 | CF28: =G28+M28+S28+Y28+AE28+AK28+AQ28+AW28+BC28+BI28+BO28+BU28 -> 6 | CG28: =H28+N28+T28+Z28+AF28+AL28+AR28+AX28+BJ28+BP28+BV28+BD28 -> 0 | CH28: =I28+O28+U28+AA28+AG28+AM28+AS28+AY28+BE28+BK28+BQ28+BW28 -> 484
A29: 27 | B29: CARDEÑA VILLAFUERTE ALEJANDRINA | C29: 1897.5 | D29: 0 | E29: 0 | F29: 0 | G29: 0 | H29: 0 | J29: 0 | K29: 0 | L29: 0 | M29: 0 | N29: 0 | P29: 0 | Q29: 0 | R29: 0 | S29: 0 | T29: 0 | U29: 75 | V29: 0 | W29: 0 | X29: 0 | Y29: 0 | Z29: 0 | AB29: 0 | AC29: 0 | AD29: 0 | AE29: 0 | AF29: 0 | AH29: 0 | AI29: 0 | AJ29: 0 | AK29: 0 | AL29: 0 | AM29: 75 | AN29: 0 | AO29: 0 | AP29: 0 | AQ29: 0 | AR29: 0 | AS29: 85 | AT29: 0 | AU29: 0 | AV29: 0 | AW29: 0 | AX29: 0 | AZ29: 0 | BA29: 0 | BB29: 0 | BC29: 0 | BF29: 0 | BG29: 0 | BH29: 0 | BI29: 0 | BL29: 0 | BM29: 0 | BN29: 0 | BO29: 0 | BQ29: 85 | BR29: 0 | BS29: 0 | BT29: 148.2 | BU29: 39 | BW29: 80 | BX29: =SUM(D29:BW29) -> 587.2 | BY29: =C29 -> 1897.5 | BZ29: =BX29+BY29 -> 2484.7 | CC29: =D29+J29+P29+V29+AB29+AH29+AN29+AT29+AZ29+BF29+BL29+BR29 -> 0 | CD29: =E29+K29+Q29+W29+AC29+AI29+AO29+AU29+BA29+BG29+BM29+BS29 -> 0 | CE29: =F29+L29+R29+X29+AD29+AJ29+AP29+AV29+BB29+BH29+BN29+BT29 -> 148.2 | CF29: =G29+M29+S29+Y29+AE29+AK29+AQ29+AW29+BC29+BI29+BO29+BU29 -> 39 | CG29: =H29+N29+T29+Z29+AF29+AL29+AR29+AX29+BJ29+BP29+BV29+BD29 -> 0 | CH29: =I29+O29+U29+AA29+AG29+AM29+AS29+AY29+BE29+BK29+BQ29+BW29 -> 400
A30: 28 | B30: CARPIO VASQUEZ TEOFILA | C30: 0 | D30: 0 | E30: 0 | F30: 0 | G30: 0 | H30: 0 | J30: 0 | K30: 0 | L30: 0 | M30: 0 | N30: 0 | P30: 0 | Q30: 0 | R30: 0 | S30: 0 | T30: 0 | V30: 0 | W30: 0 | X30: 0 | Y30: 0 | Z30: 0 | AB30: 0 | AC30: 0 | AD30: 0 | AE30: 0 | AF30: 0 | AH30: 0 | AI30: 0 | AJ30: 0 | AK30: 0 | AL30: 0 | AN30: 0 | AO30: 0 | AP30: 0 | AQ30: 0 | AR30: 0 | AT30: 0 | AU30: 0 | AV30: 0 | AW30: 0 | AX30: 0 | AZ30: 0 | BA30: 0 | BB30: 0 | BC30: 0 | BF30: 0 | BG30: 0 | BH30: 0 | BI30: 0 | BL30: 60 | BM30: 2 | BN30: 13.5 | BO30: 3 | BR30: 60 | BS30: 2 | BT30: 22.3 | BU30: 3 | BX30: =SUM(D30:BW30) -> 165.8 | BY30: =C30 -> 0 | BZ30: =BX30+BY30 -> 165.8 | CC30: =D30+J30+P30+V30+AB30+AH30+AN30+AT30+AZ30+BF30+BL30+BR30 -> 120 | CD30: =E30+K30+Q30+W30+AC30+AI30+AO30+AU30+BA30+BG30+BM30+BS30 -> 4 | CE30: =F30+L30+R30+X30+AD30+AJ30+AP30+AV30+BB30+BH30+BN30+BT30 -> 35.8 | CF30: =G30+M30+S30+Y30+AE30+AK30+AQ30+AW30+BC30+BI30+BO30+BU30 -> 6 | CG30: =H30+N30+T30+Z30+AF30+AL30+AR30+AX30+BJ30+BP30+BV30+BD30 -> 0 | CH30: =I30+O30+U30+AA30+AG30+AM30+AS30+AY30+BE30+BK30+BQ30+BW30 -> 0
A31: 29 | B31: CARRASCO SALVATIERRA FELICITA | C31: 0 | D31: 0 | E31: 0 | F31: 0 | G31: 0 | H31: 0 | J31: 0 | K31: 0 | L31: 0 | M31: 0 | N31: 0 | P31: 0 | Q31: 0 | R31: 0 | S31: 0 | T31: 0 | V31: 0 | W31: 0 | X31: 0 | Y31: 0 | Z31: 0 | AB31: 0 | AC31: 0 | AD31: 0 | AE31: 0 | AF31: 0 | AH31: 0 | AI31: 0 | AJ31: 0 | AK31: 0 | AL31: 0 | AN31: 0 | AO31: 0 | AP31: 0 | AQ31: 0 | AR31: 0 | AT31: 0 | AU31: 0 | AV31: 0 | AW31: 0 | AX31: 0 | AZ31: 0 | BA31: 0 | BB31: 0 | BC31: 0 | BF31: 0 | BG31: 0 | BH31: 0 | BI31: 0 | BL31: 0 | BM31: 0 | BN31: 0 | BO31: 14 | BR31: 0 | BS31: 0 | BU31: 8.7 | BW31: 80 | BX31: =SUM(D31:BW31) -> 102.7 | BY31: =C31 -> 0 | BZ31: =BX31+BY31 -> 102.7 | CC31: =D31+J31+P31+V31+AB31+AH31+AN31+AT31+AZ31+BF31+BL31+BR31 -> 0 | CD31: =E31+K31+Q31+W31+AC31+AI31+AO31+AU31+BA31+BG31+BM31+BS31 -> 0 | CE31: =F31+L31+R31+X31+AD31+AJ31+AP31+AV31+BB31+BH31+BN31+BT31 -> 0 | CF31: =G31+M31+S31+Y31+AE31+AK31+AQ31+AW31+BC31+BI31+BO31+BU31 -> 22.7 | CG31: =H31+N31+T31+Z31+AF31+AL31+AR31+AX31+BJ31+BP31+BV31+BD31 -> 0 | CH31: =I31+O31+U31+AA31+AG31+AM31+AS31+AY31+BE31+BK31+BQ31+BW31 -> 80
A32: 30 | B32: CARTAJENA MAMANI BENJAMIN D | C32: 0 | D32: 0 | E32: 0 | F32: 0 | G32: 0 | H32: 0 | J32: 0 | K32: 0 | L32: 0 | M32: 0 | N32: 0 | P32: 0 | Q32: 0 | R32: 0 | S32: 0 | T32: 0 | V32: 0 | W32: 0 | X32: 0 | Y32: 0 | Z32: 0 | AB32: 0 | AC32: 0 | AD32: 0 | AE32: 0 | AF32: 0 | AH32: 0 | AI32: 0 | AJ32: 0 | AK32: 0 | AL32: 0 | AN32: 0 | AO32: 0 | AP32: 0 | AQ32: 0 | AR32: 0 | AT32: 0 | AU32: 0 | AV32: 0 | AW32: 0 | AX32: 0 | AZ32: 0 | BA32: 0 | BB32: 0 | BC32: 0 | BF32: 0 | BG32: 0 | BH32: 0 | BI32: 0 | BL32: 0 | BM32: 0 | BR32: 0 | BS32: 0 | BT32: 41.9 | BU32: 3 | BW32: 80 | BX32: =SUM(D32:BW32) -> 124.9 | BY32: =C32 -> 0 | BZ32: =BX32+BY32 -> 124.9 | CC32: =D32+J32+P32+V32+AB32+AH32+AN32+AT32+AZ32+BF32+BL32+BR32 -> 0 | CD32: =E32+K32+Q32+W32+AC32+AI32+AO32+AU32+BA32+BG32+BM32+BS32 -> 0 | CE32: =F32+L32+R32+X32+AD32+AJ32+AP32+AV32+BB32+BH32+BN32+BT32 -> 41.9 | CF32: =G32+M32+S32+Y32+AE32+AK32+AQ32+AW32+BC32+BI32+BO32+BU32 -> 3 | CG32: =H32+N32+T32+Z32+AF32+AL32+AR32+AX32+BJ32+BP32+BV32+BD32 -> 0 | CH32: =I32+O32+U32+AA32+AG32+AM32+AS32+AY32+BE32+BK32+BQ32+BW32 -> 80
A33: 31 | B33: CARTAJENA PALOMINO ALVARO BENJAMIN | C33: 0 | D33: 0 | E33: 0 | F33: 0 | G33: 0 | H33: 0 | J33: 0 | K33: 0 | L33: 0 | M33: 0 | N33: 0 | P33: 0 | Q33: 0 | R33: 0 | S33: 0 | T33: 0 | V33: 0 | W33: 0 | X33: 0 | Y33: 0 | Z33: 0 | AB33: 0 | AC33: 0 | AD33: 0 | AE33: 0 | AF33: 0 | AH33: 0 | AI33: 0 | AJ33: 0 | AK33: 0 | AL33: 0 | AN33: 0 | AO33: 0 | AP33: 0 | AQ33: 0 | AR33: 0 | AT33: 0 | AU33: 0 | AV33: 0 | AW33: 0 | AX33: 0 | AZ33: 0 | BA33: 0 | BB33: 0 | BC33: 0 | BF33: 0 | BG33: 0 | BH33: 0 | BI33: 0 | BL33: 0 | BM33: 0 | BN33: 35.5 | BO33: 3 | BR33: 0 | BS33: 0 | BT33: 37.6 | BU33: 3 | BW33: 80 | BX33: =SUM(D33:BW33) -> 159.1 | BY33: =C33 -> 0 | BZ33: =BX33+BY33 -> 159.1 | CC33: =D33+J33+P33+V33+AB33+AH33+AN33+AT33+AZ33+BF33+BL33+BR33 -> 0 | CD33: =E33+K33+Q33+W33+AC33+AI33+AO33+AU33+BA33+BG33+BM33+BS33 -> 0 | CE33: =F33+L33+R33+X33+AD33+AJ33+AP33+AV33+BB33+BH33+BN33+BT33 -> 73.1 | CF33: =G33+M33+S33+Y33+AE33+AK33+AQ33+AW33+BC33+BI33+BO33+BU33 -> 6 | CG33: =H33+N33+T33+Z33+AF33+AL33+AR33+AX33+BJ33+BP33+BV33+BD33 -> 0 | CH33: =I33+O33+U33+AA33+AG33+AM33+AS33+AY33+BE33+BK33+BQ33+BW33 -> 80
A34: 32 | B34: CASTRO ALEJANDRO HORTENCIA LUCILA | C34: 0 | D34: 0 | E34: 0 | F34: 0 | G34: 0 | H34: 0 | J34: 0 | K34: 0 | L34: 0 | M34: 0 | N34: 0 | P34: 0 | Q34: 0 | R34: 0 | S34: 0 | T34: 0 | V34: 0 | W34: 0 | X34: 0 | Y34: 0 | Z34: 0 | AB34: 0 | AC34: 0 | AD34: 0 | AE34: 0 | AF34: 0 | AH34: 0 | AI34: 0 | AJ34: 0 | AK34: 0 | AL34: 0 | AN34: 0 | AO34: 0 | AP34: 0 | AQ34: 0 | AR34: 0 | AT34: 0 | AU34: 0 | AV34: 0 | AW34: 0 | AX34: 0 | AZ34: 0 | BA34: 0 | BB34: 0 | BC34: 0 | BF34: 0 | BG34: 0 | BH34: 0 | BI34: 0 | BL34: 0 | BM34: 0 | BN34: 21.5 | BO34: 3 | BQ34: 59 | BR34: 0 | BS34: 0 | BT34: 22.3 | BU34: 3 | BX34: =SUM(D34:BW34) -> 108.8 | BY34: =C34 -> 0 | BZ34: =BX34+BY34 -> 108.8 | CC34: =D34+J34+P34+V34+AB34+AH34+AN34+AT34+AZ34+BF34+BL34+BR34 -> 0 | CD34: =E34+K34+Q34+W34+AC34+AI34+AO34+AU34+BA34+BG34+BM34+BS34 -> 0 | CE34: =F34+L34+R34+X34+AD34+AJ34+AP34+AV34+BB34+BH34+BN34+BT34 -> 43.8 | CF34: =G34+M34+S34+Y34+AE34+AK34+AQ34+AW34+BC34+BI34+BO34+BU34 -> 6 | CG34: =H34+N34+T34+Z34+AF34+AL34+AR34+AX34+BJ34+BP34+BV34+BD34 -> 0 | CH34: =I34+O34+U34+AA34+AG34+AM34+AS34+AY34+BE34+BK34+BQ34+BW34 -> 59
A35: 33 | B35: CASTRO GUTIERREZ AQUILA LUCRECIA | C35: 0 | D35: 0 | E35: 0 | F35: 0 | G35: 0 | H35: 0 | J35: 0 | K35: 0 | L35: 0 | M35: 0 | N35: 0 | P35: 0 | Q35: 0 | R35: 0 | S35: 0 | T35: 0 | V35: 0 | W35: 0 | X35: 0 | Y35: 0 | Z35: 0 | AB35: 0 | AC35: 0 | AD35: 0 | AE35: 0 | AF35: 0 | AH35: 0 | AI35: 0 | AJ35: 0 | AK35: 0 | AL35: 0 | AN35: 0 | AO35: 0 | AP35: 0 | AQ35: 0 | AR35: 0 | AT35: 0 | AU35: 0 | AV35: 0 | AW35: 0 | AX35: 0 | AZ35: 0 | BA35: 0 | BB35: 0 | BC35: 0 | BF35: 0 | BG35: 0 | BH35: 0 | BI35: 0 | BL35: 0 | BM35: 0 | BN35: 76 | BO35: 3 | BR35: 60 | BS35: 2 | BT35: 80.6 | BU35: 3 | BX35: =SUM(D35:BW35) -> 224.6 | BY35: =C35 -> 0 | BZ35: =BX35+BY35 -> 224.6 | CC35: =D35+J35+P35+V35+AB35+AH35+AN35+AT35+AZ35+BF35+BL35+BR35 -> 60 | CD35: =E35+K35+Q35+W35+AC35+AI35+AO35+AU35+BA35+BG35+BM35+BS35 -> 2 | CE35: =F35+L35+R35+X35+AD35+AJ35+AP35+AV35+BB35+BH35+BN35+BT35 -> 156.6 | CF35: =G35+M35+S35+Y35+AE35+AK35+AQ35+AW35+BC35+BI35+BO35+BU35 -> 6 | CG35: =H35+N35+T35+Z35+AF35+AL35+AR35+AX35+BJ35+BP35+BV35+BD35 -> 0 | CH35: =I35+O35+U35+AA35+AG35+AM35+AS35+AY35+BE35+BK35+BQ35+BW35 -> 0
A36: 34 | B36: CCOYLLO CHINCHAY DANIEL MASIA | C36: 633.6 | D36: 0 | E36: 0 | F36: 0 | G36: 0 | H36: 0 | J36: 0 | K36: 0 | L36: 0 | M36: 0 | N36: 0 | P36: 0 | Q36: 0 | R36: 0 | S36: 0 | T36: 0 | V36: 0 | W36: 0 | X36: 0 | Y36: 0 | Z36: 0 | AB36: 0 | AC36: 0 | AD36: 0 | AE36: 0 | AF36: 0 | AH36: 0 | AI36: 0 | AJ36: 0 | AK36: 0 | AL36: 0 | AN36: 0 | AO36: 0 | AP36: 0 | AQ36: 0 | AR36: 0 | AS36: 50.5 | AT36: 0 | AU36: 0 | AV36: 0 | AW36: 0 | AX36: 0 | AZ36: 0 | BA36: 0 | BB36: 0 | BC36: 0 | BF36: 0 | BG36: 0 | BH36: 0 | BI36: 0 | BJ36: 0 | BL36: 0 | BM36: 0 | BN36: 0 | BO36: 0 | BR36: 0 | BS36: 0 | BV36: 0 | BX36: =SUM(D36:BW36) -> 50.5 | BY36: =C36 -> 633.6 | BZ36: =BX36+BY36 -> 684.1 | CC36: =D36+J36+P36+V36+AB36+AH36+AN36+AT36+AZ36+BF36+BL36+BR36 -> 0 | CD36: =E36+K36+Q36+W36+AC36+AI36+AO36+AU36+BA36+BG36+BM36+BS36 -> 0 | CE36: =F36+L36+R36+X36+AD36+AJ36+AP36+AV36+BB36+BH36+BN36+BT36 -> 0 | CF36: =G36+M36+S36+Y36+AE36+AK36+AQ36+AW36+BC36+BI36+BO36+BU36 -> 0 | CG36: =H36+N36+T36+Z36+AF36+AL36+AR36+AX36+BJ36+BP36+BV36+BD36 -> 0 | CH36: =I36+O36+U36+AA36+AG36+AM36+AS36+AY36+BE36+BK36+BQ36+BW36 -> 50.5
A37: 35 | B37: CCOYLLO CHINCHAY JUDITH NATY | C37: 492 | D37: 0 | E37: 0 | F37: 0 | G37: 0 | H37: 0 | J37: 0 | K37: 0 | L37: 0 | M37: 0 | N37: 0 | P37: 0 | Q37: 0 | R37: 0 | S37: 0 | T37: 0 | U37: 72.5 | V37: 0 | W37: 0 | X37: 0 | Y37: 0 | Z37: 0 | AB37: 0 | AC37: 0 | AD37: 0 | AE37: 0 | AF37: 0 | AH37: 0 | AI37: 0 | AJ37: 0 | AK37: 0 | AL37: 0 | AM37: 75 | AN37: 0 | AO37: 0 | AP37: 0 | AQ37: 0 | AR37: 0 | AS37: 85 | AT37: 0 | AU37: 0 | AV37: 0 | AW37: 0 | AX37: 0 | AZ37: 0 | BA37: 0 | BB37: 0 | BC37: 0 | BF37: 0 | BG37: 0 | BH37: 0 | BI37: 0 | BL37: 0 | BM37: 0 | BN37: 0 | BO37: 0 | BR37: 0 | BS37: 0 | BX37: =SUM(D37:BW37) -> 232.5 | BY37: =C37 -> 492 | BZ37: =BX37+BY37 -> 724.5 | CC37: =D37+J37+P37+V37+AB37+AH37+AN37+AT37+AZ37+BF37+BL37+BR37 -> 0 | CD37: =E37+K37+Q37+W37+AC37+AI37+AO37+AU37+BA37+BG37+BM37+BS37 -> 0 | CE37: =F37+L37+R37+X37+AD37+AJ37+AP37+AV37+BB37+BH37+BN37+BT37 -> 0 | CF37: =G37+M37+S37+Y37+AE37+AK37+AQ37+AW37+BC37+BI37+BO37+BU37 -> 0 | CG37: =H37+N37+T37+Z37+AF37+AL37+AR37+AX37+BJ37+BP37+BV37+BD37 -> 0 | CH37: =I37+O37+U37+AA37+AG37+AM37+AS37+AY37+BE37+BK37+BQ37+BW37 -> 232.5
A38: 36 | B38: CCOYLLO POLANCO DANIEL | C38: 0 | D38: 0 | E38: 0 | F38: 0 | G38: 0 | H38: 0 | J38: 0 | K38: 0 | L38: 0 | M38: 0 | N38: 0 | P38: 0 | Q38: 0 | R38: 0 | S38: 0 | T38: 0 | V38: 0 | W38: 0 | X38: 0 | Y38: 0 | Z38: 0 | AB38: 0 | AC38: 0 | AD38: 0 | AE38: 0 | AF38: 0 | AH38: 0 | AI38: 0 | AJ38: 0 | AK38: 0 | AL38: 0 | AN38: 0 | AO38: 0 | AP38: 0 | AQ38: 0 | AR38: 0 | AT38: 0 | AU38: 0 | AV38: 0 | AW38: 0 | AX38: 0 | AZ38: 0 | BA38: 0 | BB38: 0 | BC38: 0 | BF38: 0 | BG38: 0 | BH38: 0 | BI38: 0 | BL38: 0 | BM38: 0 | BN38: 0 | BO38: 0 | BR38: 0 | BS38: 0 | BT38: 13.6 | BU38: 3 | BX38: =SUM(D38:BW38) -> 16.6 | BY38: =C38 -> 0 | BZ38: =BX38+BY38 -> 16.6 | CC38: =D38+J38+P38+V38+AB38+AH38+AN38+AT38+AZ38+BF38+BL38+BR38 -> 0 | CD38: =E38+K38+Q38+W38+AC38+AI38+AO38+AU38+BA38+BG38+BM38+BS38 -> 0 | CE38: =F38+L38+R38+X38+AD38+AJ38+AP38+AV38+BB38+BH38+BN38+BT38 -> 13.6 | CF38: =G38+M38+S38+Y38+AE38+AK38+AQ38+AW38+BC38+BI38+BO38+BU38 -> 3 | CG38: =H38+N38+T38+Z38+AF38+AL38+AR38+AX38+BJ38+BP38+BV38+BD38 -> 0 | CH38: =I38+O38+U38+AA38+AG38+AM38+AS38+AY38+BE38+BK38+BQ38+BW38 -> 0
A39: 37 | B39: CCOYLLO POLANCO GERMAN | C39: 0 | D39: 0 | E39: 0 | F39: 0 | G39: 0 | H39: 0 | J39: 0 | K39: 0 | L39: 0 | M39: 0 | N39: 0 | P39: 0 | Q39: 0 | R39: 0 | S39: 0 | T39: 0 | V39: 0 | W39: 0 | X39: 0 | Y39: 0 | Z39: 0 | AB39: 0 | AC39: 0 | AD39: 0 | AE39: 0 | AF39: 0 | AH39: 0 | AI39: 0 | AJ39: 0 | AK39: 0 | AL39: 0 | AN39: 0 | AO39: 0 | AP39: 0 | AQ39: 0 | AR39: 0 | AS39: 0 | AT39: 0 | AU39: 0 | AV39: 0 | AW39: 0 | AX39: 0 | AZ39: 0 | BA39: 0 | BB39: 0 | BC39: 0 | BD39: 0 | BF39: 0 | BG39: 0 | BH39: 0 | BI39: 0 | BJ39: 0 | BL39: 0 | BM39: 0 | BN39: 49 | BO39: 3 | BR39: 0 | BS39: 0 | BX39: =SUM(D39:BW39) -> 52 | BY39: =C39 -> 0 | BZ39: =BX39+BY39 -> 52 | CC39: =D39+J39+P39+V39+AB39+AH39+AN39+AT39+AZ39+BF39+BL39+BR39 -> 0 | CD39: =E39+K39+Q39+W39+AC39+AI39+AO39+AU39+BA39+BG39+BM39+BS39 -> 0 | CE39: =F39+L39+R39+X39+AD39+AJ39+AP39+AV39+BB39+BH39+BN39+BT39 -> 49 | CF39: =G39+M39+S39+Y39+AE39+AK39+AQ39+AW39+BC39+BI39+BO39+BU39 -> 3 | CG39: =H39+N39+T39+Z39+AF39+AL39+AR39+AX39+BJ39+BP39+BV39+BD39 -> 0 | CH39: =I39+O39+U39+AA39+AG39+AM39+AS39+AY39+BE39+BK39+BQ39+BW39 -> 0
A40: 38 | B40: CERDA YUPANQUI CARMEN ROSA | C40: 0 | D40: 0 | E40: 0 | F40: 0 | G40: 0 | H40: 0 | J40: 0 | K40: 0 | L40: 0 | M40: 0 | N40: 0 | P40: 0 | Q40: 0 | R40: 0 | S40: 0 | T40: 0 | V40: 0 | W40: 0 | X40: 0 | Y40: 0 | Z40: 0 | AB40: 0 | AC40: 0 | AD40: 0 | AE40: 0 | AF40: 0 | AH40: 0 | AI40: 0 | AJ40: 0 | AK40: 0 | AL40: 0 | AN40: 0 | AO40: 0 | AP40: 0 | AQ40: 0 | AR40: 0 | AT40: 0 | AU40: 0 | AV40: 0 | AW40: 0 | AX40: 0 | AZ40: 0 | BA40: 0 | BB40: 0 | BC40: 0 | BF40: 0 | BG40: 0 | BH40: 0 | BI40: 0 | BL40: 60 | BM40: 2 | BN40: 27.5 | BO40: 3 | BR40: 60 | BS40: 2 | BT40: 28.9 | BU40: 3 | BX40: =SUM(D40:BW40) -> 186.4 | BY40: =C40 -> 0 | BZ40: =BX40+BY40 -> 186.4 | CC40: =D40+J40+P40+V40+AB40+AH40+AN40+AT40+AZ40+BF40+BL40+BR40 -> 120 | CD40: =E40+K40+Q40+W40+AC40+AI40+AO40+AU40+BA40+BG40+BM40+BS40 -> 4 | CE40: =F40+L40+R40+X40+AD40+AJ40+AP40+AV40+BB40+BH40+BN40+BT40 -> 56.4 | CF40: =G40+M40+S40+Y40+AE40+AK40+AQ40+AW40+BC40+BI40+BO40+BU40 -> 6 | CG40: =H40+N40+T40+Z40+AF40+AL40+AR40+AX40+BJ40+BP40+BV40+BD40 -> 0 | CH40: =I40+O40+U40+AA40+AG40+AM40+AS40+AY40+BE40+BK40+BQ40+BW40 -> 0
A41: 39 | B41: CHALLCO DE PALOMINO NICOLAZA | C41: 0 | D41: 0 | E41: 0 | F41: 0 | G41: 0 | H41: 0 | J41: 0 | K41: 0 | L41: 0 | M41: 0 | N41: 0 | P41: 0 | Q41: 0 | R41: 0 | S41: 0 | T41: 0 | V41: 0 | W41: 0 | X41: 0 | Y41: 0 | Z41: 0 | AB41: 0 | AC41: 0 | AD41: 0 | AE41: 0 | AF41: 0 | AH41: 0 | AI41: 0 | AJ41: 0 | AK41: 0 | AL41: 0 | AN41: 0 | AO41: 0 | AP41: 0 | AQ41: 0 | AR41: 0 | AT41: 0 | AU41: 0 | AV41: 0 | AW41: 0 | AX41: 0 | AZ41: 0 | BA41: 0 | BB41: 0 | BC41: 0 | BF41: 0 | BG41: 0 | BH41: 0 | BI41: 0 | BL41: 0 | BM41: 0 | BN41: 181.5 | BO41: 21 | BR41: 0 | BS41: 0 | BT41: 196.7 | BU41: 21 | BW41: 80 | BX41: =SUM(D41:BW41) -> 500.2 | BY41: =C41 -> 0 | BZ41: =BX41+BY41 -> 500.2 | CC41: =D41+J41+P41+V41+AB41+AH41+AN41+AT41+AZ41+BF41+BL41+BR41 -> 0 | CD41: =E41+K41+Q41+W41+AC41+AI41+AO41+AU41+BA41+BG41+BM41+BS41 -> 0 | CE41: =F41+L41+R41+X41+AD41+AJ41+AP41+AV41+BB41+BH41+BN41+BT41 -> 378.2 | CF41: =G41+M41+S41+Y41+AE41+AK41+AQ41+AW41+BC41+BI41+BO41+BU41 -> 42 | CG41: =H41+N41+T41+Z41+AF41+AL41+AR41+AX41+BJ41+BP41+BV41+BD41 -> 0 | CH41: =I41+O41+U41+AA41+AG41+AM41+AS41+AY41+BE41+BK41+BQ41+BW41 -> 80
A42: 40 | B42: CHIRINOS CABRACANCHA MARIA LOURDES | C42: 0 | D42: 0 | E42: 0 | F42: 0 | G42: 0 | H42: 0 | J42: 0 | K42: 0 | L42: 0 | M42: 0 | N42: 0 | P42: 0 | Q42: 0 | R42: 0 | S42: 0 | T42: 0 | V42: 0 | W42: 0 | X42: 0 | Y42: 0 | Z42: 0 | AB42: 0 | AC42: 0 | AD42: 0 | AE42: 0 | AF42: 0 | AH42: 0 | AI42: 0 | AJ42: 0 | AK42: 0 | AL42: 0 | AN42: 0 | AO42: 0 | AP42: 0 | AQ42: 0 | AR42: 0 | AT42: 0 | AU42: 0 | AV42: 0 | AW42: 0 | AX42: 0 | AZ42: 0 | BA42: 0 | BB42: 0 | BC42: 0 | BF42: 0 | BG42: 0 | BH42: 0 | BI42: 0 | BL42: 0 | BM42: 0 | BN42: 103 | BO42: 39 | BR42: 0 | BS42: 0 | BT42: 128.6 | BU42: 39 | BW42: 80 | BX42: =SUM(D42:BW42) -> 389.6 | BY42: =C42 -> 0 | BZ42: =BX42+BY42 -> 389.6 | CC42: =D42+J42+P42+V42+AB42+AH42+AN42+AT42+AZ42+BF42+BL42+BR42 -> 0 | CD42: =E42+K42+Q42+W42+AC42+AI42+AO42+AU42+BA42+BG42+BM42+BS42 -> 0 | CE42: =F42+L42+R42+X42+AD42+AJ42+AP42+AV42+BB42+BH42+BN42+BT42 -> 231.6 | CF42: =G42+M42+S42+Y42+AE42+AK42+AQ42+AW42+BC42+BI42+BO42+BU42 -> 78 | CG42: =H42+N42+T42+Z42+AF42+AL42+AR42+AX42+BJ42+BP42+BV42+BD42 -> 0 | CH42: =I42+O42+U42+AA42+AG42+AM42+AS42+AY42+BE42+BK42+BQ42+BW42 -> 80
A43: 41 | B43: CHOQUE ALATA MARTHA NELIDA | C43: 0 | D43: 0 | E43: 0 | F43: 0 | G43: 0 | H43: 0 | J43: 0 | K43: 0 | L43: 0 | M43: 0 | N43: 0 | P43: 0 | Q43: 0 | R43: 0 | S43: 0 | T43: 0 | V43: 0 | W43: 0 | X43: 0 | Y43: 0 | Z43: 0 | AB43: 0 | AC43: 0 | AD43: 0 | AE43: 0 | AF43: 0 | AH43: 0 | AI43: 0 | AJ43: 0 | AK43: 0 | AL43: 0 | AN43: 0 | AO43: 0 | AP43: 0 | AQ43: 0 | AR43: 0 | AT43: 0 | AU43: 0 | AV43: 0 | AW43: 0 | AX43: 0 | AZ43: 0 | BA43: 0 | BB43: 0 | BC43: 0 | BF43: 0 | BG43: 0 | BH43: 0 | BI43: 0 | BL43: 0 | BM43: 0 | BN43: 64 | BO43: 3 | BR43: 0 | BS43: 0 | BT43: 67.5 | BU43: 3 | BX43: =SUM(D43:BW43) -> 137.5 | BY43: =C43 -> 0 | BZ43: =BX43+BY43 -> 137.5 | CC43: =D43+J43+P43+V43+AB43+AH43+AN43+AT43+AZ43+BF43+BL43+BR43 -> 0 | CD43: =E43+K43+Q43+W43+AC43+AI43+AO43+AU43+BA43+BG43+BM43+BS43 -> 0 | CE43: =F43+L43+R43+X43+AD43+AJ43+AP43+AV43+BB43+BH43+BN43+BT43 -> 131.5 | CF43: =G43+M43+S43+Y43+AE43+AK43+AQ43+AW43+BC43+BI43+BO43+BU43 -> 6 | CG43: =H43+N43+T43+Z43+AF43+AL43+AR43+AX43+BJ43+BP43+BV43+BD43 -> 0 | CH43: =I43+O43+U43+AA43+AG43+AM43+AS43+AY43+BE43+BK43+BQ43+BW43 -> 0
A44: 42 | B44: CHOQUE HUAMANI FELIX CEFERINO | C44: 0 | D44: 0 | E44: 0 | F44: 0 | G44: 0 | H44: 0 | J44: 0 | K44: 0 | L44: 0 | M44: 0 | N44: 0 | P44: 0 | Q44: 0 | R44: 0 | S44: 0 | T44: 0 | V44: 0 | W44: 0 | X44: 0 | Y44: 0 | Z44: 0 | AB44: 0 | AC44: 0 | AD44: 0 | AE44: 0 | AF44: 0 | AH44: 0 | AI44: 0 | AJ44: 0 | AK44: 0 | AL44: 0 | AN44: 0 | AO44: 0 | AP44: 0 | AQ44: 0 | AR44: 0 | AT44: 0 | AU44: 0 | AV44: 0 | AW44: 0 | AX44: 0 | AZ44: 0 | BA44: 0 | BB44: 0 | BC44: 0 | BF44: 0 | BG44: 0 | BH44: 0 | BI44: 0 | BL44: 60 | BM44: 2 | BN44: 37.5 | BO44: 55 | BR44: 60 | BS44: 2 | BT44: 37.8 | BU44: 55 | BW44: 80 | BX44: =SUM(D44:BW44) -> 389.3 | BY44: =C44 -> 0 | BZ44: =BX44+BY44 -> 389.3 | CC44: =D44+J44+P44+V44+AB44+AH44+AN44+AT44+AZ44+BF44+BL44+BR44 -> 120 | CD44: =E44+K44+Q44+W44+AC44+AI44+AO44+AU44+BA44+BG44+BM44+BS44 -> 4 | CE44: =F44+L44+R44+X44+AD44+AJ44+AP44+AV44+BB44+BH44+BN44+BT44 -> 75.3 | CF44: =G44+M44+S44+Y44+AE44+AK44+AQ44+AW44+BC44+BI44+BO44+BU44 -> 110 | CG44: =H44+N44+T44+Z44+AF44+AL44+AR44+AX44+BJ44+BP44+BV44+BD44 -> 0 | CH44: =I44+O44+U44+AA44+AG44+AM44+AS44+AY44+BE44+BK44+BQ44+BW44 -> 80
A45: 43 | B45: CHUCHULLO HACHA JOSE PEDRO | C45: 0 | D45: 0 | E45: 0 | F45: 0 | G45: 0 | H45: 0 | J45: 0 | K45: 0 | L45: 0 | M45: 0 | N45: 0 | P45: 0 | Q45: 0 | R45: 0 | S45: 0 | T45: 0 | V45: 0 | W45: 0 | X45: 0 | Y45: 0 | Z45: 0 | AB45: 0 | AC45: 0 | AD45: 0 | AE45: 0 | AF45: 0 | AH45: 0 | AI45: 0 | AJ45: 0 | AK45: 0 | AL45: 0 | AN45: 0 | AO45: 0 | AP45: 0 | AQ45: 0 | AR45: 0 | AT45: 0 | AU45: 0 | AV45: 0 | AW45: 0 | AX45: 0 | AZ45: 0 | BA45: 0 | BB45: 0 | BC45: 0 | BD45: 0 | BF45: 0 | BG45: 0 | BH45: 0 | BI45: 0 | BJ45: 0 | BL45: 0 | BM45: 0 | BN45: 67 | BO45: 3 | BP45: 60 | BR45: 0 | BS45: 0 | BT45: 70.8 | BU45: 3 | BV45: 60 | BX45: =SUM(D45:BW45) -> 263.8 | BY45: =C45 -> 0 | BZ45: =BX45+BY45 -> 263.8 | CC45: =D45+J45+P45+V45+AB45+AH45+AN45+AT45+AZ45+BF45+BL45+BR45 -> 0 | CD45: =E45+K45+Q45+W45+AC45+AI45+AO45+AU45+BA45+BG45+BM45+BS45 -> 0 | CE45: =F45+L45+R45+X45+AD45+AJ45+AP45+AV45+BB45+BH45+BN45+BT45 -> 137.8 | CF45: =G45+M45+S45+Y45+AE45+AK45+AQ45+AW45+BC45+BI45+BO45+BU45 -> 6 | CG45: =H45+N45+T45+Z45+AF45+AL45+AR45+AX45+BJ45+BP45+BV45+BD45 -> 120 | CH45: =I45+O45+U45+AA45+AG45+AM45+AS45+AY45+BE45+BK45+BQ45+BW45 -> 0
A46: 44 | B46: CLEMENTE ALLER CIRILA | C46: 0 | D46: 0 | E46: 0 | F46: 0 | G46: 0 | H46: 0 | J46: 0 | K46: 0 | L46: 0 | M46: 0 | N46: 0 | P46: 0 | Q46: 0 | R46: 0 | S46: 0 | T46: 0 | V46: 0 | W46: 0 | X46: 0 | Y46: 0 | Z46: 0 | AB46: 0 | AC46: 0 | AD46: 0 | AE46: 0 | AF46: 0 | AH46: 0 | AI46: 0 | AJ46: 0 | AK46: 0 | AL46: 0 | AN46: 0 | AO46: 0 | AP46: 0 | AQ46: 0 | AR46: 0 | AT46: 0 | AU46: 0 | AV46: 0 | AW46: 0 | AX46: 0 | AZ46: 0 | BA46: 0 | BB46: 0 | BC46: 0 | BF46: 0 | BG46: 0 | BH46: 123.5 | BI46: 6 | BL46: 0 | BM46: 0 | BN46: 131 | BO46: 3 | BQ46: 59 | BR46: 0 | BS46: 0 | BT46: 140.6 | BU46: 3 | BX46: =SUM(D46:BW46) -> 466.1 | BY46: =C46 -> 0 | BZ46: =BX46+BY46 -> 466.1 | CC46: =D46+J46+P46+V46+AB46+AH46+AN46+AT46+AZ46+BF46+BL46+BR46 -> 0 | CD46: =E46+K46+Q46+W46+AC46+AI46+AO46+AU46+BA46+BG46+BM46+BS46 -> 0 | CE46: =F46+L46+R46+X46+AD46+AJ46+AP46+AV46+BB46+BH46+BN46+BT46 -> 395.1 | CF46: =G46+M46+S46+Y46+AE46+AK46+AQ46+AW46+BC46+BI46+BO46+BU46 -> 12 | CG46: =H46+N46+T46+Z46+AF46+AL46+AR46+AX46+BJ46+BP46+BV46+BD46 -> 0 | CH46: =I46+O46+U46+AA46+AG46+AM46+AS46+AY46+BE46+BK46+BQ46+BW46 -> 59
A47: 45 | B47: CORDOVA PEREZ MARCO ANTONIO | C47: 38 | D47: 0 | E47: 0 | F47: 0 | G47: 0 | H47: 0 | J47: 0 | K47: 0 | L47: 0 | M47: 0 | N47: 0 | P47: 0 | Q47: 0 | R47: 0 | S47: 0 | T47: 0 | V47: 0 | W47: 0 | X47: 0 | Y47: 0 | Z47: 0 | AB47: 0 | AC47: 0 | AD47: 0 | AE47: 0 | AF47: 0 | AH47: 0 | AI47: 0 | AJ47: 0 | AK47: 0 | AL47: 0 | AN47: 0 | AO47: 0 | AP47: 0 | AQ47: 0 | AR47: 0 | AT47: 0 | AU47: 0 | AV47: 0 | AW47: 0 | AX47: 0 | AZ47: 0 | BA47: 0 | BB47: 0 | BC47: 0 | BF47: 0 | BG47: 0 | BH47: 0 | BI47: 0 | BL47: 0 | BM47: 0 | BN47: 27.5 | BO47: 55 | BR47: 0 | BS47: 0 | BT47: 28.9 | BU47: 55 | BW47: 80 | BX47: =SUM(D47:BW47) -> 246.4 | BY47: =C47 -> 38 | BZ47: =BX47+BY47 -> 284.4 | CC47: =D47+J47+P47+V47+AB47+AH47+AN47+AT47+AZ47+BF47+BL47+BR47 -> 0 | CD47: =E47+K47+Q47+W47+AC47+AI47+AO47+AU47+BA47+BG47+BM47+BS47 -> 0 | CE47: =F47+L47+R47+X47+AD47+AJ47+AP47+AV47+BB47+BH47+BN47+BT47 -> 56.4 | CF47: =G47+M47+S47+Y47+AE47+AK47+AQ47+AW47+BC47+BI47+BO47+BU47 -> 110 | CG47: =H47+N47+T47+Z47+AF47+AL47+AR47+AX47+BJ47+BP47+BV47+BD47 -> 0 | CH47: =I47+O47+U47+AA47+AG47+AM47+AS47+AY47+BE47+BK47+BQ47+BW47 -> 80
A48: 46 | B48: CORNEJO DONATO DE CORDOVA ESTELA PILAR | C48: 0 | E48: 0 | F48: 0 | G48: 0 | H48: 0 | I48: 520 | J48: 4 | K48: 0 | L48: 0 | M48: 0 | N48: 0 | P48: 0 | Q48: 0 | R48: 0 | S48: 0 | T48: 0 | V48: 0 | W48: 0 | X48: 0 | Y48: 0 | Z48: 0 | AB48: 0 | AC48: 0 | AD48: 0 | AE48: 0 | AF48: 0 | AH48: 0 | AI48: 0 | AJ48: 0 | AK48: 0 | AL48: 55 | AN48: 0 | AO48: 0 | AP48: 0 | AQ48: 0 | AR48: 55 | AT48: 0 | AU48: 0 | AV48: 0 | AW48: 0 | AX48: 55 | AZ48: 0 | BA48: 0 | BB48: 0 | BC48: 0 | BD48: 55 | BF48: 0 | BG48: 0 | BH48: 0 | BI48: 0 | BJ48: 55 | BL48: 0 | BM48: 0 | BN48: 27.5 | BO48: 3 | BP48: 55 | BR48: 6 | BS48: 2 | BT48: 46.3 | BU48: 3 | BV48: 55 | BX48: =SUM(D48:BW48) -> 996.8 | BY48: =C48 -> 0 | BZ48: =BX48+BY48 -> 996.8 | CC48: =D48+J48+P48+V48+AB48+AH48+AN48+AT48+AZ48+BF48+BL48+BR48 -> 10 | CD48: =E48+K48+Q48+W48+AC48+AI48+AO48+AU48+BA48+BG48+BM48+BS48 -> 2 | CE48: =F48+L48+R48+X48+AD48+AJ48+AP48+AV48+BB48+BH48+BN48+BT48 -> 73.8 | CF48: =G48+M48+S48+Y48+AE48+AK48+AQ48+AW48+BC48+BI48+BO48+BU48 -> 6 | CG48: =H48+N48+T48+Z48+AF48+AL48+AR48+AX48+BJ48+BP48+BV48+BD48 -> 385 | CH48: =I48+O48+U48+AA48+AG48+AM48+AS48+AY48+BE48+BK48+BQ48+BW48 -> 520
A49: 47 | B49: CRUZ JARAMILLO LUIS | C49: 0 | D49: 0 | E49: 0 | F49: 0 | G49: 0 | H49: 0 | J49: 0 | K49: 0 | L49: 0 | M49: 0 | N49: 0 | P49: 0 | Q49: 0 | R49: 0 | S49: 0 | T49: 0 | V49: 0 | W49: 0 | X49: 0 | Y49: 0 | Z49: 0 | AB49: 0 | AC49: 0 | AD49: 0 | AE49: 0 | AF49: 0 | AH49: 0 | AI49: 0 | AJ49: 0 | AK49: 0 | AL49: 0 | AN49: 0 | AO49: 0 | AP49: 0 | AQ49: 0 | AR49: 0 | AT49: 0 | AU49: 0 | AV49: 0 | AW49: 0 | AX49: 0 | AZ49: 0 | BA49: 0 | BB49: 0 | BC49: 0 | BF49: 0 | BG49: 0 | BH49: 0 | BI49: 0 | BL49: 0 | BM49: 0 | BN49: 70.5 | BO49: 3 | BR49: 0 | BS49: 0 | BT49: 75.7 | BU49: 3 | BX49: =SUM(D49:BW49) -> 152.2 | BY49: =C49 -> 0 | BZ49: =BX49+BY49 -> 152.2 | CC49: =D49+J49+P49+V49+AB49+AH49+AN49+AT49+AZ49+BF49+BL49+BR49 -> 0 | CD49: =E49+K49+Q49+W49+AC49+AI49+AO49+AU49+BA49+BG49+BM49+BS49 -> 0 | CE49: =F49+L49+R49+X49+AD49+AJ49+AP49+AV49+BB49+BH49+BN49+BT49 -> 146.2 | CF49: =G49+M49+S49+Y49+AE49+AK49+AQ49+AW49+BC49+BI49+BO49+BU49 -> 6 | CG49: =H49+N49+T49+Z49+AF49+AL49+AR49+AX49+BJ49+BP49+BV49+BD49 -> 0 | CH49: =I49+O49+U49+AA49+AG49+AM49+AS49+AY49+BE49+BK49+BQ49+BW49 -> 0
A50: 48 | B50: CUCHO DE LA CRUZ SAUL | C50: 0 | D50: 0 | E50: 0 | F50: 0 | G50: 0 | H50: 0 | J50: 0 | K50: 0 | L50: 0 | M50: 0 | N50: 0 | P50: 0 | Q50: 0 | R50: 0 | S50: 0 | T50: 0 | V50: 0 | W50: 0 | X50: 0 | Y50: 0 | Z50: 0 | AB50: 0 | AC50: 0 | AD50: 0 | AE50: 0 | AF50: 0 | AH50: 0 | AI50: 0 | AJ50: 0 | AK50: 0 | AL50: 0 | AN50: 0 | AO50: 0 | AP50: 0 | AQ50: 0 | AR50: 0 | AT50: 0 | AU50: 0 | AV50: 0 | AW50: 0 | AX50: 0 | AZ50: 0 | BA50: 0 | BB50: 0 | BC50: 0 | BF50: 0 | BG50: 0 | BH50: 0 | BI50: 0 | BL50: 0 | BM50: 0 | BN50: 101.5 | BO50: 3 | BR50: 0 | BS50: 0 | BT50: 109.5 | BU50: 3 | BX50: =SUM(D50:BW50) -> 217 | BY50: =C50 -> 0 | BZ50: =BX50+BY50 -> 217 | CC50: =D50+J50+P50+V50+AB50+AH50+AN50+AT50+AZ50+BF50+BL50+BR50 -> 0 | CD50: =E50+K50+Q50+W50+AC50+AI50+AO50+AU50+BA50+BG50+BM50+BS50 -> 0 | CE50: =F50+L50+R50+X50+AD50+AJ50+AP50+AV50+BB50+BH50+BN50+BT50 -> 211 | CF50: =G50+M50+S50+Y50+AE50+AK50+AQ50+AW50+BC50+BI50+BO50+BU50 -> 6 | CG50: =H50+N50+T50+Z50+AF50+AL50+AR50+AX50+BJ50+BP50+BV50+BD50 -> 0 | CH50: =I50+O50+U50+AA50+AG50+AM50+AS50+AY50+BE50+BK50+BQ50+BW50 -> 0
A51: 49 | B51: CUEVAS MAYO ENRIQUE | C51: 0 | D51: 0 | E51: 0 | F51: 0 | G51: 0 | H51: 0 | J51: 0 | K51: 0 | L51: 0 | M51: 0 | N51: 0 | P51: 0 | Q51: 0 | R51: 0 | S51: 0 | T51: 0 | V51: 0 | W51: 0 | X51: 0 | Y51: 0 | Z51: 0 | AB51: 0 | AC51: 0 | AD51: 0 | AE51: 0 | AF51: 0 | AH51: 0 | AI51: 0 | AJ51: 0 | AK51: 0 | AL51: 0 | AN51: 0 | AO51: 0 | AP51: 0 | AQ51: 0 | AR51: 0 | AT51: 0 | AU51: 0 | AV51: 0 | AW51: 0 | AX51: 0 | AZ51: 0 | BA51: 0 | BB51: 0 | BC51: 0 | BF51: 0 | BG51: 0 | BH51: 0 | BI51: 0 | BL51: 60 | BM51: 2 | BN51: 77 | BO51: 3 | BR51: 60 | BS51: 2 | BT51: 81.7 | BU51: 3 | BX51: =SUM(D51:BW51) -> 288.7 | BY51: =C51 -> 0 | BZ51: =BX51+BY51 -> 288.7 | CC51: =D51+J51+P51+V51+AB51+AH51+AN51+AT51+AZ51+BF51+BL51+BR51 -> 120 | CD51: =E51+K51+Q51+W51+AC51+AI51+AO51+AU51+BA51+BG51+BM51+BS51 -> 4 | CE51: =F51+L51+R51+X51+AD51+AJ51+AP51+AV51+BB51+BH51+BN51+BT51 -> 158.7 | CF51: =G51+M51+S51+Y51+AE51+AK51+AQ51+AW51+BC51+BI51+BO51+BU51 -> 6 | CG51: =H51+N51+T51+Z51+AF51+AL51+AR51+AX51+BJ51+BP51+BV51+BD51 -> 0 | CH51: =I51+O51+U51+AA51+AG51+AM51+AS51+AY51+BE51+BK51+BQ51+BW51 -> 0
A52: 50 | B52: CULE CARRASCO HAYDEE MONICA | C52: 0 | D52: 0 | E52: 0 | F52: 0 | G52: 0 | H52: 0 | J52: 0 | K52: 0 | L52: 0 | M52: 0 | N52: 0 | P52: 0 | Q52: 0 | R52: 0 | S52: 0 | T52: 0 | V52: 0 | W52: 0 | X52: 0 | Y52: 0 | Z52: 0 | AB52: 0 | AC52: 0 | AD52: 0 | AE52: 0 | AF52: 0 | AH52: 8.5 | AI52: 2 | AJ52: 0 | AK52: 0 | AL52: 0 | AN52: 28 | AO52: 2 | AP52: 0 | AQ52: 0 | AR52: 0 | AT52: 32 | AU52: 2 | AV52: 0 | AW52: 0 | AX52: 0 | AZ52: 44 | BA52: 2 | BB52: 0 | BC52: 0 | BE52: 15 | BF52: 40 | BG52: 2 | BH52: 0 | BI52: 0 | BL52: 14 | BM52: 2 | BN52: 0 | BO52: 38.5 | BQ52: 85 | BR52: 30 | BS52: 2 | BT52: 11.1 | BU52: 55 | BW52: 80 | BX52: =SUM(D52:BW52) -> 495.1 | BY52: =C52 -> 0 | BZ52: =BX52+BY52 -> 495.1 | CC52: =D52+J52+P52+V52+AB52+AH52+AN52+AT52+AZ52+BF52+BL52+BR52 -> 196.5 | CD52: =E52+K52+Q52+W52+AC52+AI52+AO52+AU52+BA52+BG52+BM52+BS52 -> 14 | CE52: =F52+L52+R52+X52+AD52+AJ52+AP52+AV52+BB52+BH52+BN52+BT52 -> 11.1 | CF52: =G52+M52+S52+Y52+AE52+AK52+AQ52+AW52+BC52+BI52+BO52+BU52 -> 93.5 | CG52: =H52+N52+T52+Z52+AF52+AL52+AR52+AX52+BJ52+BP52+BV52+BD52 -> 0 | CH52: =I52+O52+U52+AA52+AG52+AM52+AS52+AY52+BE52+BK52+BQ52+BW52 -> 180
A53: 51 | B53: CUSI LAURA SONIA | C53: 0 | D53: 0 | E53: 0 | F53: 0 | G53: 0 | H53: 0 | J53: 0 | K53: 0 | L53: 0 | M53: 0 | N53: 0 | P53: 0 | Q53: 0 | R53: 0 | S53: 0 | T53: 0 | V53: 0 | W53: 0 | X53: 0 | Y53: 0 | Z53: 0 | AB53: 0 | AC53: 0 | AD53: 0 | AE53: 0 | AF53: 0 | AH53: 0 | AI53: 0 | AJ53: 0 | AK53: 0 | AL53: 0 | AN53: 0 | AO53: 0 | AP53: 0 | AQ53: 0 | AR53: 0 | AT53: 0 | AU53: 0 | AV53: 0 | AW53: 0 | AX53: 0 | AZ53: 0 | BA53: 0 | BB53: 0 | BC53: 0 | BF53: 0 | BG53: 0 | BH53: 0 | BI53: 0 | BL53: 0 | BM53: 0 | BN53: 0 | BO53: 0 | BR53: 0 | BS53: 0 | BT53: 28.9 | BU53: 3 | BX53: =SUM(D53:BW53) -> 31.9 | BY53: =C53 -> 0 | BZ53: =BX53+BY53 -> 31.9 | CC53: =D53+J53+P53+V53+AB53+AH53+AN53+AT53+AZ53+BF53+BL53+BR53 -> 0 | CD53: =E53+K53+Q53+W53+AC53+AI53+AO53+AU53+BA53+BG53+BM53+BS53 -> 0 | CE53: =F53+L53+R53+X53+AD53+AJ53+AP53+AV53+BB53+BH53+BN53+BT53 -> 28.9 | CF53: =G53+M53+S53+Y53+AE53+AK53+AQ53+AW53+BC53+BI53+BO53+BU53 -> 3 | CG53: =H53+N53+T53+Z53+AF53+AL53+AR53+AX53+BJ53+BP53+BV53+BD53 -> 0 | CH53: =I53+O53+U53+AA53+AG53+AM53+AS53+AY53+BE53+BK53+BQ53+BW53 -> 0
A54: 52 | B54: DAVILA CAHUANA MARISOL | C54: 279.5 | D54: 0 | E54: 0 | F54: 0 | G54: 0 | H54: 0 | J54: 0 | K54: 0 | L54: 0 | M54: 0 | N54: 0 | P54: 0 | Q54: 0 | R54: 0 | S54: 0 | T54: 0 | V54: 0 | W54: 0 | X54: 0 | Y54: 0 | Z54: 0 | AB54: 0 | AC54: 0 | AD54: 0 | AE54: 0 | AF54: 0 | AH54: 0 | AI54: 0 | AJ54: 0 | AK54: 0 | AL54: 0 | AN54: 0 | AO54: 0 | AP54: 0 | AQ54: 0 | AR54: 0 | AT54: 0 | AU54: 0 | AV54: 0 | AW54: 0 | AX54: 0 | AZ54: 0 | BA54: 0 | BB54: 0 | BC54: 0 | BF54: 0 | BG54: 0 | BH54: 0 | BI54: 0 | BL54: 60 | BM54: 2 | BN54: 248 | BO54: 3 | BQ54: =85+59 -> 144 | BR54: 60 | BS54: 2 | BT54: 268.1 | BU54: 3 | BX54: =SUM(D54:BW54) -> 790.1 | BY54: =C54 -> 279.5 | BZ54: =BX54+BY54 -> 1069.6 | CC54: =D54+J54+P54+V54+AB54+AH54+AN54+AT54+AZ54+BF54+BL54+BR54 -> 120 | CD54: =E54+K54+Q54+W54+AC54+AI54+AO54+AU54+BA54+BG54+BM54+BS54 -> 4 | CE54: =F54+L54+R54+X54+AD54+AJ54+AP54+AV54+BB54+BH54+BN54+BT54 -> 516.1 | CF54: =G54+M54+S54+Y54+AE54+AK54+AQ54+AW54+BC54+BI54+BO54+BU54 -> 6 | CG54: =H54+N54+T54+Z54+AF54+AL54+AR54+AX54+BJ54+BP54+BV54+BD54 -> 0 | CH54: =I54+O54+U54+AA54+AG54+AM54+AS54+AY54+BE54+BK54+BQ54+BW54 -> 144
A55: 53 | B55: DE LA CRUZ ESTEBAN JOSE | C55: 5300.9 | D55: 0 | E55: 0 | F55: 0 | G55: 0 | H55: 0 | J55: 0 | K55: 0 | L55: 0 | M55: 0 | N55: 0 | P55: 0 | Q55: 0 | R55: 0 | S55: 0 | T55: 0 | V55: 0 | W55: 0 | X55: 0 | Y55: 0 | Z55: 0 | AB55: 0 | AC55: 0 | AD55: 0 | AE55: 0 | AF55: 0 | AH55: 0 | AI55: 0 | AJ55: 0 | AK55: 0 | AL55: 0 | AN55: 0 | AO55: 0 | AP55: 0 | AQ55: 0 | AR55: 0 | AT55: 0 | AU55: 0 | AV55: 0 | AW55: 0 | AX55: 0 | AZ55: 0 | BA55: 0 | BB55: 0 | BC55: 0 | BF55: 0 | BG55: 0 | BH55: 0 | BI55: 0 | BL55: 0 | BM55: 0 | BN55: 0 | BO55: 0 | BR55: 20 | BS55: 2 | BT55: 61.6 | BU55: 35 | BW55: 80 | BX55: =SUM(D55:BW55) -> 198.6 | BY55: =C55 -> 5300.9 | BZ55: =BX55+BY55 -> 5499.5 | CC55: =D55+J55+P55+V55+AB55+AH55+AN55+AT55+AZ55+BF55+BL55+BR55 -> 20 | CD55: =E55+K55+Q55+W55+AC55+AI55+AO55+AU55+BA55+BG55+BM55+BS55 -> 2 | CE55: =F55+L55+R55+X55+AD55+AJ55+AP55+AV55+BB55+BH55+BN55+BT55 -> 61.6 | CF55: =G55+M55+S55+Y55+AE55+AK55+AQ55+AW55+BC55+BI55+BO55+BU55 -> 35 | CG55: =H55+N55+T55+Z55+AF55+AL55+AR55+AX55+BJ55+BP55+BV55+BD55 -> 0 | CH55: =I55+O55+U55+AA55+AG55+AM55+AS55+AY55+BE55+BK55+BQ55+BW55 -> 80
A56: 54 | B56: ESPEJO URBANO ROSA FLORENCIA | C56: 0 | D56: 0 | E56: 0 | F56: 0 | G56: 0 | H56: 0 | J56: 0 | K56: 0 | L56: 0 | M56: 0 | N56: 0 | P56: 0 | Q56: 0 | R56: 0 | S56: 0 | T56: 0 | V56: 0 | W56: 0 | X56: 0 | Y56: 0 | Z56: 0 | AB56: 0 | AC56: 0 | AD56: 0 | AE56: 0 | AF56: 0 | AH56: 0 | AI56: 0 | AJ56: 0 | AK56: 0 | AL56: 0 | AN56: 0 | AO56: 0 | AP56: 0 | AQ56: 0 | AR56: 0 | AT56: 0 | AU56: 0 | AV56: 0 | AW56: 0 | AX56: 0 | AZ56: 0 | BA56: 0 | BB56: 0 | BC56: 0 | BF56: 0 | BG56: 0 | BH56: 0 | BI56: 0 | BL56: 0 | BM56: 0 | BN56: 49 | BO56: 3 | BR56: 0 | BS56: 0 | BX56: =SUM(D56:BW56) -> 52 | BY56: =C56 -> 0 | BZ56: =BX56+BY56 -> 52 | CC56: =D56+J56+P56+V56+AB56+AH56+AN56+AT56+AZ56+BF56+BL56+BR56 -> 0 | CD56: =E56+K56+Q56+W56+AC56+AI56+AO56+AU56+BA56+BG56+BM56+BS56 -> 0 | CE56: =F56+L56+R56+X56+AD56+AJ56+AP56+AV56+BB56+BH56+BN56+BT56 -> 49 | CF56: =G56+M56+S56+Y56+AE56+AK56+AQ56+AW56+BC56+BI56+BO56+BU56 -> 3 | CG56: =H56+N56+T56+Z56+AF56+AL56+AR56+AX56+BJ56+BP56+BV56+BD56 -> 0 | CH56: =I56+O56+U56+AA56+AG56+AM56+AS56+AY56+BE56+BK56+BQ56+BW56 -> 0
A57: 55 | B57: ESTELA SUAREZ ELVIA | C57: 0 | D57: 0 | E57: 0 | F57: 0 | G57: 0 | H57: 0 | J57: 0 | K57: 0 | L57: 0 | M57: 0 | N57: 0 | P57: 0 | Q57: 0 | R57: 0 | S57: 0 | T57: 0 | V57: 0 | W57: 0 | X57: 0 | Y57: 0 | Z57: 0 | AB57: 0 | AC57: 0 | AD57: 0 | AE57: 0 | AF57: 0 | AH57: 0 | AI57: 0 | AJ57: 0 | AK57: 0 | AL57: 0 | AN57: 0 | AO57: 0 | AP57: 0 | AQ57: 0 | AR57: 0 | AT57: 0 | AU57: 0 | AV57: 0 | AW57: 0 | AX57: 0 | AZ57: 0 | BA57: 0 | BB57: 0 | BC57: 0 | BF57: 0 | BG57: 0 | BH57: 0 | BI57: 0 | BL57: 0 | BM57: 0 | BN57: 0 | BO57: 0 | BR57: 60 | BS57: 2 | BT57: 76.8 | BU57: 35 | BW57: 80 | BX57: =SUM(D57:BW57) -> 253.8 | BY57: =C57 -> 0 | BZ57: =BX57+BY57 -> 253.8 | CC57: =D57+J57+P57+V57+AB57+AH57+AN57+AT57+AZ57+BF57+BL57+BR57 -> 60 | CD57: =E57+K57+Q57+W57+AC57+AI57+AO57+AU57+BA57+BG57+BM57+BS57 -> 2 | CE57: =F57+L57+R57+X57+AD57+AJ57+AP57+AV57+BB57+BH57+BN57+BT57 -> 76.8 | CF57: =G57+M57+S57+Y57+AE57+AK57+AQ57+AW57+BC57+BI57+BO57+BU57 -> 35 | CG57: =H57+N57+T57+Z57+AF57+AL57+AR57+AX57+BJ57+BP57+BV57+BD57 -> 0 | CH57: =I57+O57+U57+AA57+AG57+AM57+AS57+AY57+BE57+BK57+BQ57+BW57 -> 80
A58: 56 | B58: ESTRADA OSORIO DONATO | C58: 371 | D58: 42 | E58: 2 | F58: 0 | G58: 0 | H58: 0 | J58: 48 | K58: 2 | L58: 0 | M58: 0 | N58: 0 | P58: 60 | Q58: 2 | R58: 0 | S58: 0 | T58: 0 | V58: 46 | W58: 2 | X58: 0 | Y58: 0 | Z58: 0 | AB58: 50 | AC58: 2 | AD58: 0 | AE58: 0 | AF58: 0 | AH58: 49 | AI58: 2 | AJ58: 0 | AK58: 0 | AL58: 0 | AN58: 36 | AO58: 2 | AP58: 0 | AQ58: 0 | AR58: 0 | AT58: 36 | AU58: 2 | AV58: 0 | AW58: 0 | AX58: 0 | AZ58: 26 | BA58: 2 | BB58: 0 | BC58: 0 | BF58: 32 | BG58: 2 | BH58: 0 | BI58: 0 | BL58: 38 | BM58: 2 | BN58: 27.5 | BO58: 73 | BR58: 46 | BS58: 2 | BT58: 28.9 | BU58: 73 | BW58: 180 | BX58: =SUM(D58:BW58) -> 915.4 | BY58: =C58 -> 371 | BZ58: =BX58+BY58 -> 1286.4 | CC58: =D58+J58+P58+V58+AB58+AH58+AN58+AT58+AZ58+BF58+BL58+BR58 -> 509 | CD58: =E58+K58+Q58+W58+AC58+AI58+AO58+AU58+BA58+BG58+BM58+BS58 -> 24 | CE58: =F58+L58+R58+X58+AD58+AJ58+AP58+AV58+BB58+BH58+BN58+BT58 -> 56.4 | CF58: =G58+M58+S58+Y58+AE58+AK58+AQ58+AW58+BC58+BI58+BO58+BU58 -> 146 | CG58: =H58+N58+T58+Z58+AF58+AL58+AR58+AX58+BJ58+BP58+BV58+BD58 -> 0 | CH58: =I58+O58+U58+AA58+AG58+AM58+AS58+AY58+BE58+BK58+BQ58+BW58 -> 180
A59: 57 | B59: FALCON CHIARA HECTOR | C59: 0 | D59: 0 | E59: 0 | F59: 0 | G59: 0 | H59: 0 | J59: 0 | K59: 0 | L59: 0 | M59: 0 | N59: 0 | P59: 0 | Q59: 0 | R59: 0 | S59: 0 | T59: 0 | V59: 0 | W59: 0 | X59: 0 | Y59: 0 | Z59: 0 | AB59: 0 | AC59: 0 | AD59: 0 | AE59: 0 | AF59: 0 | AH59: 0 | AI59: 0 | AJ59: 0 | AK59: 0 | AL59: 0 | AN59: 0 | AO59: 0 | AP59: 0 | AQ59: 0 | AR59: 0 | AT59: 0 | AU59: 0 | AV59: 0 | AW59: 0 | AX59: 0 | AZ59: 0 | BA59: 0 | BB59: 0 | BC59: 0 | BD59: 0 | BF59: 0 | BG59: 0 | BH59: 0 | BI59: 0 | BJ59: 0 | BL59: 0 | BM59: 0 | BN59: 0 | BO59: 0 | BP59: 0 | BR59: 0 | BS59: 0 | BT59: 77.3 | BU59: 3 | BV59: 0 | BX59: =SUM(D59:BW59) -> 80.3 | BY59: =C59 -> 0 | BZ59: =BX59+BY59 -> 80.3 | CC59: =D59+J59+P59+V59+AB59+AH59+AN59+AT59+AZ59+BF59+BL59+BR59 -> 0 | CD59: =E59+K59+Q59+W59+AC59+AI59+AO59+AU59+BA59+BG59+BM59+BS59 -> 0 | CE59: =F59+L59+R59+X59+AD59+AJ59+AP59+AV59+BB59+BH59+BN59+BT59 -> 77.3 | CF59: =G59+M59+S59+Y59+AE59+AK59+AQ59+AW59+BC59+BI59+BO59+BU59 -> 3 | CG59: =H59+N59+T59+Z59+AF59+AL59+AR59+AX59+BJ59+BP59+BV59+BD59 -> 0 | CH59: =I59+O59+U59+AA59+AG59+AM59+AS59+AY59+BE59+BK59+BQ59+BW59 -> 0
A60: 58 | B60: FLORES FLORES DE ROMERO EMMA SOFIA | C60: 0 | D60: 0 | E60: 0 | F60: 0 | G60: 0 | H60: 0 | J60: 0 | K60: 0 | L60: 0 | M60: 0 | N60: 0 | P60: 0 | Q60: 0 | R60: 0 | S60: 0 | T60: 0 | V60: 0 | W60: 0 | X60: 0 | Y60: 0 | Z60: 0 | AB60: 0 | AC60: 0 | AD60: 0 | AE60: 0 | AF60: 0 | AH60: 0 | AI60: 0 | AJ60: 0 | AK60: 0 | AL60: 0 | AN60: 0 | AO60: 0 | AP60: 0 | AQ60: 0 | AR60: 0 | AT60: 0 | AU60: 0 | AV60: 0 | AW60: 0 | AX60: 0 | AZ60: 0 | BA60: 0 | BB60: 0 | BC60: 0 | BF60: 0 | BG60: 0 | BH60: 0 | BI60: 0 | BL60: 0 | BM60: 0 | BN60: 17.5 | BO60: 35 | BR60: 0 | BS60: 0 | BT60: 0.6 | BU60: 35 | BW60: 80 | BX60: =SUM(D60:BW60) -> 168.1 | BY60: =C60 -> 0 | BZ60: =BX60+BY60 -> 168.1 | CC60: =D60+J60+P60+V60+AB60+AH60+AN60+AT60+AZ60+BF60+BL60+BR60 -> 0 | CD60: =E60+K60+Q60+W60+AC60+AI60+AO60+AU60+BA60+BG60+BM60+BS60 -> 0 | CE60: =F60+L60+R60+X60+AD60+AJ60+AP60+AV60+BB60+BH60+BN60+BT60 -> 18.1 | CF60: =G60+M60+S60+Y60+AE60+AK60+AQ60+AW60+BC60+BI60+BO60+BU60 -> 70 | CG60: =H60+N60+T60+Z60+AF60+AL60+AR60+AX60+BJ60+BP60+BV60+BD60 -> 0 | CH60: =I60+O60+U60+AA60+AG60+AM60+AS60+AY60+BE60+BK60+BQ60+BW60 -> 80
A61: 59 | B61: FLORES FLORES IRENE BERTILIA | C61: 0 | D61: 0 | E61: 0 | F61: 0 | G61: 0 | H61: 0 | J61: 0 | K61: 0 | L61: 0 | M61: 0 | N61: 0 | P61: 0 | Q61: 0 | R61: 0 | S61: 0 | T61: 0 | V61: 0 | W61: 0 | X61: 0 | Y61: 0 | Z61: 0 | AB61: 0 | AC61: 0 | AD61: 0 | AE61: 0 | AF61: 0 | AH61: 0 | AI61: 0 | AJ61: 0 | AK61: 0 | AL61: 0 | AN61: 0 | AO61: 0 | AP61: 0 | AQ61: 0 | AR61: 0 | AT61: 0 | AU61: 0 | AV61: 0 | AW61: 0 | AX61: 0 | AZ61: 0 | BA61: 0 | BB61: 0 | BC61: 0 | BF61: 0 | BG61: 0 | BH61: 0 | BI61: 0 | BL61: 0 | BM61: 0 | BN61: 0 | BO61: 19.5 | BR61: 0 | BS61: 0 | BT61: 0 | BU61: 0 | BV61: 0 | BW61: 80 | BX61: =SUM(D61:BW61) -> 99.5 | BY61: =C61 -> 0 | BZ61: =BX61+BY61 -> 99.5 | CC61: =D61+J61+P61+V61+AB61+AH61+AN61+AT61+AZ61+BF61+BL61+BR61 -> 0 | CD61: =E61+K61+Q61+W61+AC61+AI61+AO61+AU61+BA61+BG61+BM61+BS61 -> 0 | CE61: =F61+L61+R61+X61+AD61+AJ61+AP61+AV61+BB61+BH61+BN61+BT61 -> 0 | CF61: =G61+M61+S61+Y61+AE61+AK61+AQ61+AW61+BC61+BI61+BO61+BU61 -> 19.5 | CG61: =H61+N61+T61+Z61+AF61+AL61+AR61+AX61+BJ61+BP61+BV61+BD61 -> 0 | CH61: =I61+O61+U61+AA61+AG61+AM61+AS61+AY61+BE61+BK61+BQ61+BW61 -> 80
A62: 60 | B62: FLORES FLORES UMBELINA DORA | C62: 361 | D62: 0 | E62: 0 | F62: 0 | G62: 0 | H62: 0 | J62: 0 | K62: 0 | L62: 0 | M62: 0 | N62: 0 | P62: 0 | Q62: 0 | R62: 0 | S62: 0 | T62: 0 | V62: 0 | W62: 0 | X62: 0 | Y62: 0 | Z62: 0 | AB62: 0 | AC62: 0 | AD62: 0 | AE62: 0 | AF62: 0 | AH62: 0 | AI62: 0 | AJ62: 0 | AK62: 0 | AL62: 0 | AN62: 0 | AO62: 0 | AP62: 0 | AQ62: 0 | AR62: 0 | AT62: 0 | AU62: 0 | AV62: 0 | AW62: 0 | AX62: 0 | AZ62: 0 | BA62: 0 | BB62: 0 | BC62: 0 | BE62: 15 | BF62: 0 | BG62: 0 | BH62: 0 | BI62: 0 | BL62: 0 | BM62: 0 | BN62: 70.5 | BO62: 39 | BR62: 0 | BS62: 0 | BT62: 75.7 | BU62: 39 | BW62: 80 | BX62: =SUM(D62:BW62) -> 319.2 | BY62: =C62 -> 361 | BZ62: =BX62+BY62 -> 680.2 | CC62: =D62+J62+P62+V62+AB62+AH62+AN62+AT62+AZ62+BF62+BL62+BR62 -> 0 | CD62: =E62+K62+Q62+W62+AC62+AI62+AO62+AU62+BA62+BG62+BM62+BS62 -> 0 | CE62: =F62+L62+R62+X62+AD62+AJ62+AP62+AV62+BB62+BH62+BN62+BT62 -> 146.2 | CF62: =G62+M62+S62+Y62+AE62+AK62+AQ62+AW62+BC62+BI62+BO62+BU62 -> 78 | CG62: =H62+N62+T62+Z62+AF62+AL62+AR62+AX62+BJ62+BP62+BV62+BD62 -> 0 | CH62: =I62+O62+U62+AA62+AG62+AM62+AS62+AY62+BE62+BK62+BQ62+BW62 -> 95
A63: 61 | B63: FLORES MATTO ANTONIO | C63: 675 | D63: 0 | E63: 0 | F63: 0 | G63: 0 | H63: 0 | J63: 20 | K63: 0 | L63: 0 | M63: 0 | N63: 0 | P63: 60 | Q63: 0 | R63: 0 | S63: 0 | T63: 0 | U63: 75 | V63: 0 | W63: 0 | X63: 0 | Y63: 0 | Z63: 0 | AB63: 0 | AC63: 0 | AD63: 0 | AE63: 0 | AF63: 0 | AH63: 0 | AI63: 0 | AJ63: 0 | AK63: 0 | AL63: 0 | AM63: 75 | AN63: 0 | AO63: 0 | AP63: 0 | AQ63: 0 | AR63: 0 | AS63: 85 | AT63: 0 | AU63: 0 | AV63: 0 | AW63: 0 | AX63: 0 | AZ63: 0 | BA63: 0 | BB63: 0 | BC63: 0 | BF63: 60 | BG63: 0 | BH63: 0 | BI63: 0 | BL63: 60 | BM63: 0 | BN63: 27.5 | BO63: 3 | BQ63: =85+59 -> 144 | BR63: 60 | BS63: 2 | BT63: 28.9 | BU63: 3 | BX63: =SUM(D63:BW63) -> 703.4 | BY63: =C63 -> 675 | BZ63: =BX63+BY63 -> 1378.4 | CC63: =D63+J63+P63+V63+AB63+AH63+AN63+AT63+AZ63+BF63+BL63+BR63 -> 260 | CD63: =E63+K63+Q63+W63+AC63+AI63+AO63+AU63+BA63+BG63+BM63+BS63 -> 2 | CE63: =F63+L63+R63+X63+AD63+AJ63+AP63+AV63+BB63+BH63+BN63+BT63 -> 56.4 | CF63: =G63+M63+S63+Y63+AE63+AK63+AQ63+AW63+BC63+BI63+BO63+BU63 -> 6 | CG63: =H63+N63+T63+Z63+AF63+AL63+AR63+AX63+BJ63+BP63+BV63+BD63 -> 0 | CH63: =I63+O63+U63+AA63+AG63+AM63+AS63+AY63+BE63+BK63+BQ63+BW63 -> 379
A64: 62 | B64: FLORES YATO FRANCISCA DOLORES | C64: 0 | D64: 0 | E64: 0 | F64: 0 | G64: 0 | H64: 0 | J64: 0 | K64: 0 | L64: 0 | M64: 0 | N64: 0 | P64: 0 | Q64: 0 | R64: 0 | S64: 0 | T64: 0 | V64: 0 | W64: 0 | X64: 0 | Y64: 0 | Z64: 0 | AB64: 0 | AC64: 0 | AD64: 0 | AE64: 0 | AF64: 0 | AH64: 0 | AI64: 0 | AJ64: 0 | AK64: 0 | AL64: 0 | AN64: 0 | AO64: 0 | AP64: 0 | AQ64: 0 | AR64: 0 | AT64: 0 | AU64: 0 | AV64: 0 | AW64: 0 | AX64: 0 | AZ64: 0 | BA64: 0 | BB64: 0 | BC64: 0 | BF64: 0 | BG64: 0 | BH64: 0 | BI64: 0 | BL64: 60 | BM64: 2 | BN64: 195 | BO64: 3 | BQ64: 59 | BR64: 60 | BS64: 2 | BT64: 210.3 | BU64: 3 | BX64: =SUM(D64:BW64) -> 594.3 | BY64: =C64 -> 0 | BZ64: =BX64+BY64 -> 594.3 | CC64: =D64+J64+P64+V64+AB64+AH64+AN64+AT64+AZ64+BF64+BL64+BR64 -> 120 | CD64: =E64+K64+Q64+W64+AC64+AI64+AO64+AU64+BA64+BG64+BM64+BS64 -> 4 | CE64: =F64+L64+R64+X64+AD64+AJ64+AP64+AV64+BB64+BH64+BN64+BT64 -> 405.3 | CF64: =G64+M64+S64+Y64+AE64+AK64+AQ64+AW64+BC64+BI64+BO64+BU64 -> 6 | CG64: =H64+N64+T64+Z64+AF64+AL64+AR64+AX64+BJ64+BP64+BV64+BD64 -> 0 | CH64: =I64+O64+U64+AA64+AG64+AM64+AS64+AY64+BE64+BK64+BQ64+BW64 -> 59
A65: 63 | B65: GAVILAN MOSQUERA NORMA | C65: 12061.13 | D65: 0 | E65: 0 | F65: 0 | G65: 0 | H65: 0 | J65: 0 | K65: 0 | L65: 0 | M65: 0 | N65: 0 | P65: 0 | Q65: 0 | R65: 0 | S65: 0 | T65: 0 | U65: 75 | V65: 0 | W65: 0 | X65: 0 | Y65: 0 | Z65: 0 | AB65: 0 | AC65: 0 | AD65: 0 | AE65: 0 | AF65: 0 | AH65: 0 | AI65: 0 | AJ65: 0 | AK65: 0 | AL65: 0 | AM65: 75 | AN65: 0 | AO65: 0 | AP65: 0 | AQ65: 0 | AR65: 0 | AS65: 85 | AT65: 0 | AU65: 0 | AV65: 0 | AW65: 0 | AX65: 0 | AZ65: 0 | BA65: 0 | BB65: 0 | BC65: 0 | BF65: 0 | BG65: 0 | BH65: 0 | BI65: 0 | BL65: 0 | BM65: 0 | BN65: 132.5 | BO65: 39 | BQ65: 85 | BR65: 0 | BS65: 0 | BT65: 143.3 | BU65: 39 | BW65: 80 | BX65: =SUM(D65:BW65) -> 753.8 | BY65: =C65 -> 12061.13 | BZ65: =BX65+BY65 -> 12814.93 | CC65: =D65+J65+P65+V65+AB65+AH65+AN65+AT65+AZ65+BF65+BL65+BR65 -> 0 | CD65: =E65+K65+Q65+W65+AC65+AI65+AO65+AU65+BA65+BG65+BM65+BS65 -> 0 | CE65: =F65+L65+R65+X65+AD65+AJ65+AP65+AV65+BB65+BH65+BN65+BT65 -> 275.8 | CF65: =G65+M65+S65+Y65+AE65+AK65+AQ65+AW65+BC65+BI65+BO65+BU65 -> 78 | CG65: =H65+N65+T65+Z65+AF65+AL65+AR65+AX65+BJ65+BP65+BV65+BD65 -> 0 | CH65: =I65+O65+U65+AA65+AG65+AM65+AS65+AY65+BE65+BK65+BQ65+BW65 -> 400
A66: 64 | B66: GONZALES LOZANO JHENNY FRANK | C66: 260 | D66: 0 | E66: 0 | F66: 0 | G66: 0 | H66: 0 | J66: 0 | K66: 0 | L66: 0 | M66: 0 | N66: 0 | P66: 0 | Q66: 0 | R66: 0 | S66: 0 | T66: 0 | U66: 75 | V66: 0 | W66: 0 | X66: 0 | Y66: 0 | Z66: 0 | AB66: 0 | AC66: 0 | AD66: 0 | AE66: 0 | AF66: 0 | AG66: 200 | AH66: 0 | AI66: 0 | AJ66: 0 | AK66: 0 | AL66: 0 | AM66: 75 | AN66: 60 | AO66: 2 | AP66: 0 | AQ66: 0 | AR66: 0 | AS66: 85 | AT66: 60 | AU66: 2 | AV66: 0 | AW66: 0 | AX66: 0 | AY66: 25 | AZ66: 60 | BA66: 2 | BB66: 0 | BC66: 0 | BF66: 60 | BG66: 2 | BH66: 0 | BI66: 0 | BL66: 60 | BM66: 2 | BN66: 0 | BO66: 0 | BQ66: 85 | BR66: 60 | BS66: 2 | BT66: 20.1 | BU66: 55 | BW66: 80 | BX66: =SUM(D66:BW66) -> 1072.1 | BY66: =C66 -> 260 | BZ66: =BX66+BY66 -> 1332.1 | CC66: =D66+J66+P66+V66+AB66+AH66+AN66+AT66+AZ66+BF66+BL66+BR66 -> 360 | CD66: =E66+K66+Q66+W66+AC66+AI66+AO66+AU66+BA66+BG66+BM66+BS66 -> 12 | CE66: =F66+L66+R66+X66+AD66+AJ66+AP66+AV66+BB66+BH66+BN66+BT66 -> 20.1 | CF66: =G66+M66+S66+Y66+AE66+AK66+AQ66+AW66+BC66+BI66+BO66+BU66 -> 55 | CG66: =H66+N66+T66+Z66+AF66+AL66+AR66+AX66+BJ66+BP66+BV66+BD66 -> 0 | CH66: =I66+O66+U66+AA66+AG66+AM66+AS66+AY66+BE66+BK66+BQ66+BW66 -> 625
A67: 65 | B67: GUTIERRES CASTRO JORGE RICARDO | C67: 1580.7 | D67: 22 | E67: 2 | F67: 0 | G67: 0 | H67: 0 | J67: 2 | K67: 2 | L67: 0 | M67: 0 | N67: 0 | P67: 0 | Q67: 0 | R67: 0 | S67: 0 | T67: 0 | V67: 36 | W67: 2 | X67: 12 | Y67: 3.5 | Z67: 0 | AB67: 60 | AC67: 2 | AD67: 11 | AE67: 4 | AF67: 0 | AH67: 22 | AI67: 2 | AJ67: 0 | AL67: 0 | AN67: 32 | AO67: 2 | AP67: 0 | AR67: 0 | AT67: 0 | AU67: 2 | AV67: 0 | AX67: 0 | AZ67: 44 | BA67: 2 | BB67: 0 | BF67: 60 | BG67: 2 | BH67: 0 | BL67: 60 | BM67: 2 | BN67: 21.5 | BO67: 3 | BQ67: 59 | BR67: 60 | BS67: 2 | BT67: 22.3 | BU67: 3 | BW67: 320 | BX67: =SUM(D67:BW67) -> 879.3 | BY67: =C67 -> 1580.7 | BZ67: =BX67+BY67 -> 2460 | CC67: =D67+J67+P67+V67+AB67+AH67+AN67+AT67+AZ67+BF67+BL67+BR67 -> 398 | CD67: =E67+K67+Q67+W67+AC67+AI67+AO67+AU67+BA67+BG67+BM67+BS67 -> 22 | CE67: =F67+L67+R67+X67+AD67+AJ67+AP67+AV67+BB67+BH67+BN67+BT67 -> 66.8 | CF67: =G67+M67+S67+Y67+AE67+AK67+AQ67+AW67+BC67+BI67+BO67+BU67 -> 13.5 | CG67: =H67+N67+T67+Z67+AF67+AL67+AR67+AX67+BJ67+BP67+BV67+BD67 -> 0 | CH67: =I67+O67+U67+AA67+AG67+AM67+AS67+AY67+BE67+BK67+BQ67+BW67 -> 379
A68: 66 | B68: GUTIERREZ CASTILLO TERESA JESUS | C68: 0 | D68: 0 | E68: 0 | F68: 0 | G68: 0 | H68: 0 | J68: 0 | K68: 0 | L68: 0 | M68: 0 | N68: 0 | P68: 0 | Q68: 0 | R68: 0 | S68: 0 | T68: 0 | V68: 0 | W68: 0 | X68: 0 | Y68: 0 | Z68: 0 | AB68: 0 | AC68: 0 | AD68: 0 | AE68: 0 | AF68: 0 | AH68: 0 | AI68: 0 | AJ68: 0 | AK68: 0 | AL68: 0 | AN68: 0 | AO68: 0 | AP68: 0 | AQ68: 0 | AR68: 0 | AT68: 0 | AU68: 0 | AV68: 0 | AW68: 0 | AX68: 0 | AZ68: 0 | BA68: 0 | BB68: 0 | BC68: 0 | BF68: 0 | BG68: 0 | BH68: 0 | BI68: 0 | BL68: 0 | BM68: 0 | BN68: 21.5 | BO68: 3 | BQ68: 59 | BR68: 0 | BS68: 0 | BT68: 22.3 | BU68: 3 | BX68: =SUM(D68:BW68) -> 108.8 | BY68: =C68 -> 0 | BZ68: =BX68+BY68 -> 108.8 | CC68: =D68+J68+P68+V68+AB68+AH68+AN68+AT68+AZ68+BF68+BL68+BR68 -> 0 | CD68: =E68+K68+Q68+W68+AC68+AI68+AO68+AU68+BA68+BG68+BM68+BS68 -> 0 | CE68: =F68+L68+R68+X68+AD68+AJ68+AP68+AV68+BB68+BH68+BN68+BT68 -> 43.8 | CF68: =G68+M68+S68+Y68+AE68+AK68+AQ68+AW68+BC68+BI68+BO68+BU68 -> 6 | CG68: =H68+N68+T68+Z68+AF68+AL68+AR68+AX68+BJ68+BP68+BV68+BD68 -> 0 | CH68: =I68+O68+U68+AA68+AG68+AM68+AS68+AY68+BE68+BK68+BQ68+BW68 -> 59
A69: 67 | B69: GUTIERREZ CASTILLO JORGE | C69: 0 | D69: 0 | E69: 0 | F69: 0 | G69: 0 | H69: 0 | J69: 0 | K69: 0 | L69: 0 | M69: 0 | N69: 0 | P69: 0 | Q69: 0 | R69: 0 | S69: 0 | T69: 0 | V69: 0 | W69: 0 | X69: 0 | Y69: 0 | Z69: 0 | AB69: 0 | AC69: 0 | AD69: 0 | AE69: 0 | AF69: 0 | AH69: 0 | AI69: 0 | AJ69: 0 | AK69: 0 | AL69: 0 | AN69: 0 | AO69: 0 | AP69: 0 | AQ69: 0 | AR69: 0 | AT69: 0 | AU69: 0 | AV69: 0 | AW69: 0 | AX69: 0 | AZ69: 0 | BA69: 0 | BB69: 0 | BC69: 0 | BF69: 0 | BG69: 0 | BH69: 0 | BI69: 0 | BL69: 0 | BM69: 0 | BN69: 75.5 | BO69: 3 | BR69: 0 | BS69: 0 | BT69: 81.2 | BU69: 3 | BX69: =SUM(D69:BW69) -> 162.7 | BY69: =C69 -> 0 | BZ69: =BX69+BY69 -> 162.7 | CC69: =D69+J69+P69+V69+AB69+AH69+AN69+AT69+AZ69+BF69+BL69+BR69 -> 0 | CD69: =E69+K69+Q69+W69+AC69+AI69+AO69+AU69+BA69+BG69+BM69+BS69 -> 0 | CE69: =F69+L69+R69+X69+AD69+AJ69+AP69+AV69+BB69+BH69+BN69+BT69 -> 156.7 | CF69: =G69+M69+S69+Y69+AE69+AK69+AQ69+AW69+BC69+BI69+BO69+BU69 -> 6 | CG69: =H69+N69+T69+Z69+AF69+AL69+AR69+AX69+BJ69+BP69+BV69+BD69 -> 0 | CH69: =I69+O69+U69+AA69+AG69+AM69+AS69+AY69+BE69+BK69+BQ69+BW69 -> 0
A70: 68 | B70: GUTIERREZ FLORES ROGER REYNAN | C70: 0 | D70: 0 | E70: 0 | F70: 0 | G70: 0 | H70: 0 | J70: 0 | K70: 0 | L70: 0 | M70: 0 | N70: 0 | P70: 0 | Q70: 0 | R70: 0 | S70: 0 | T70: 0 | V70: 0 | W70: 0 | X70: 0 | Y70: 0 | Z70: 0 | AB70: 0 | AC70: 0 | AD70: 0 | AE70: 0 | AF70: 0 | AH70: 0 | AI70: 0 | AJ70: 0 | AK70: 0 | AL70: 0 | AN70: 0 | AO70: 0 | AP70: 0 | AQ70: 0 | AR70: 0 | AT70: 0 | AU70: 0 | AV70: 0 | AW70: 0 | AX70: 0 | AZ70: 0 | BA70: 0 | BB70: 0 | BC70: 0 | BF70: 0 | BG70: 0 | BH70: 0 | BI70: 0 | BL70: 0 | BM70: 0 | BN70: 93.5 | BO70: 57 | BR70: 0 | BS70: 0 | BT70: 99.1 | BU70: 57 | BW70: 80 | BX70: =SUM(D70:BW70) -> 386.6 | BY70: =C70 -> 0 | BZ70: =BX70+BY70 -> 386.6 | CC70: =D70+J70+P70+V70+AB70+AH70+AN70+AT70+AZ70+BF70+BL70+BR70 -> 0 | CD70: =E70+K70+Q70+W70+AC70+AI70+AO70+AU70+BA70+BG70+BM70+BS70 -> 0 | CE70: =F70+L70+R70+X70+AD70+AJ70+AP70+AV70+BB70+BH70+BN70+BT70 -> 192.6 | CF70: =G70+M70+S70+Y70+AE70+AK70+AQ70+AW70+BC70+BI70+BO70+BU70 -> 114 | CG70: =H70+N70+T70+Z70+AF70+AL70+AR70+AX70+BJ70+BP70+BV70+BD70 -> 0 | CH70: =I70+O70+U70+AA70+AG70+AM70+AS70+AY70+BE70+BK70+BQ70+BW70 -> 80
A71: 69 | B71: HEREDIA MUÑOZ DE BRAVO MARIA | C71: 3757 | D71: 0 | E71: 0 | F71: 0 | G71: 0 | H71: 0 | J71: 58 | K71: 0 | L71: 0 | M71: 0 | N71: 0 | P71: 60 | Q71: 0 | R71: 0 | S71: 0 | T71: 0 | V71: 0 | W71: 0 | X71: 0 | Y71: 0 | Z71: 0 | AB71: 60 | AC71: 0 | AD71: 0 | AE71: 0 | AF71: 0 | AH71: 60 | AI71: 0 | AJ71: 0 | AK71: 0 | AL71: 0 | AN71: 60 | AO71: 0 | AP71: 0 | AQ71: 0 | AR71: 0 | AT71: 60 | AU71: 0 | AV71: 0 | AW71: 0 | AX71: 0 | AY71: 25 | AZ71: 60 | BA71: 0 | BB71: 0 | BC71: 0 | BF71: 60 | BG71: 2 | BH71: 0 | BI71: 0 | BL71: 0 | BM71: 0 | BN71: 43.5 | BO71: 3 | BQ71: 59 | BR71: 0 | BS71: 0 | BT71: 46.3 | BU71: 3 | BX71: =SUM(D71:BW71) -> 659.8 | BY71: =C71 -> 3757 | BZ71: =BX71+BY71 -> 4416.8 | CC71: =D71+J71+P71+V71+AB71+AH71+AN71+AT71+AZ71+BF71+BL71+BR71 -> 478 | CD71: =E71+K71+Q71+W71+AC71+AI71+AO71+AU71+BA71+BG71+BM71+BS71 -> 2 | CE71: =F71+L71+R71+X71+AD71+AJ71+AP71+AV71+BB71+BH71+BN71+BT71 -> 89.8 | CF71: =G71+M71+S71+Y71+AE71+AK71+AQ71+AW71+BC71+BI71+BO71+BU71 -> 6 | CG71: =H71+N71+T71+Z71+AF71+AL71+AR71+AX71+BJ71+BP71+BV71+BD71 -> 0 | CH71: =I71+O71+U71+AA71+AG71+AM71+AS71+AY71+BE71+BK71+BQ71+BW71 -> 84
A72: 70 | B72: HUAMANI ROMERO DOMITILA | C72: 0 | D72: 0 | E72: 0 | F72: 0 | G72: 0 | H72: 0 | J72: 0 | K72: 0 | L72: 0 | M72: 0 | N72: 0 | P72: 0 | Q72: 0 | R72: 0 | S72: 0 | T72: 0 | V72: 0 | W72: 0 | X72: 0 | Y72: 0 | Z72: 0 | AB72: 0 | AC72: 0 | AD72: 0 | AE72: 0 | AF72: 0 | AH72: 0 | AI72: 0 | AJ72: 0 | AK72: 0 | AL72: 0 | AN72: 0 | AO72: 0 | AP72: 0 | AQ72: 0 | AR72: 0 | AT72: 0 | AU72: 0 | AV72: 0 | AW72: 0 | AX72: 0 | AZ72: 0 | BA72: 0 | BB72: 0 | BC72: 0 | BF72: 0 | BG72: 0 | BH72: 0 | BI72: 0 | BL72: 0 | BM72: 0 | BN72: 130 | BO72: 3 | BR72: 0 | BS72: 0 | BT72: 156.9 | BU72: 3 | BX72: =SUM(D72:BW72) -> 292.9 | BY72: =C72 -> 0 | BZ72: =BX72+BY72 -> 292.9 | CC72: =D72+J72+P72+V72+AB72+AH72+AN72+AT72+AZ72+BF72+BL72+BR72 -> 0 | CD72: =E72+K72+Q72+W72+AC72+AI72+AO72+AU72+BA72+BG72+BM72+BS72 -> 0 | CE72: =F72+L72+R72+X72+AD72+AJ72+AP72+AV72+BB72+BH72+BN72+BT72 -> 286.9 | CF72: =G72+M72+S72+Y72+AE72+AK72+AQ72+AW72+BC72+BI72+BO72+BU72 -> 6 | CG72: =H72+N72+T72+Z72+AF72+AL72+AR72+AX72+BJ72+BP72+BV72+BD72 -> 0 | CH72: =I72+O72+U72+AA72+AG72+AM72+AS72+AY72+BE72+BK72+BQ72+BW72 -> 0
A73: 71 | B73: HUASHUAYO GOMEZ EUDOSIA | C73: 0 | D73: 0 | E73: 0 | F73: 0 | G73: 0 | H73: 0 | J73: 0 | K73: 0 | L73: 0 | M73: 0 | N73: 0 | P73: 0 | Q73: 0 | R73: 0 | S73: 0 | T73: 0 | V73: 0 | W73: 0 | X73: 0 | Y73: 0 | Z73: 0 | AB73: 0 | AC73: 0 | AD73: 0 | AE73: 0 | AF73: 0 | AH73: 0 | AI73: 0 | AJ73: 0 | AK73: 0 | AL73: 0 | AN73: 0 | AO73: 0 | AP73: 0 | AQ73: 0 | AR73: 0 | AT73: 0 | AU73: 0 | AV73: 0 | AW73: 0 | AX73: 0 | AZ73: 0 | BA73: 0 | BB73: 0 | BC73: 0 | BF73: 0 | BG73: 0 | BH73: 0 | BI73: 0 | BL73: 0 | BM73: 0 | BN73: 49 | BO73: 3 | BR73: 60 | BS73: 2 | BT73: 51.2 | BU73: 3 | BX73: =SUM(D73:BW73) -> 168.2 | BY73: =C73 -> 0 | BZ73: =BX73+BY73 -> 168.2 | CC73: =D73+J73+P73+V73+AB73+AH73+AN73+AT73+AZ73+BF73+BL73+BR73 -> 60 | CD73: =E73+K73+Q73+W73+AC73+AI73+AO73+AU73+BA73+BG73+BM73+BS73 -> 2 | CE73: =F73+L73+R73+X73+AD73+AJ73+AP73+AV73+BB73+BH73+BN73+BT73 -> 100.2 | CF73: =G73+M73+S73+Y73+AE73+AK73+AQ73+AW73+BC73+BI73+BO73+BU73 -> 6 | CG73: =H73+N73+T73+Z73+AF73+AL73+AR73+AX73+BJ73+BP73+BV73+BD73 -> 0 | CH73: =I73+O73+U73+AA73+AG73+AM73+AS73+AY73+BE73+BK73+BQ73+BW73 -> 0
A74: 72 | B74: HUAYHUALLA DE LOPEZ DONATILA | C74: 0 | D74: 0 | E74: 0 | F74: 0 | G74: 0 | H74: 0 | J74: 0 | K74: 0 | L74: 0 | M74: 0 | N74: 0 | P74: 0 | Q74: 0 | R74: 0 | S74: 0 | T74: 0 | V74: 0 | W74: 0 | X74: 0 | Y74: 0 | Z74: 0 | AB74: 0 | AC74: 0 | AD74: 0 | AE74: 0 | AF74: 0 | AH74: 0 | AI74: 0 | AJ74: 0 | AK74: 0 | AL74: 0 | AN74: 0 | AO74: 0 | AP74: 0 | AQ74: 0 | AR74: 0 | AT74: 0 | AU74: 0 | AV74: 0 | AW74: 0 | AX74: 0 | AZ74: 0 | BA74: 0 | BB74: 0 | BC74: 0 | BF74: 0 | BG74: 0 | BH74: 0 | BI74: 0 | BL74: 0 | BM74: 0 | BN74: 0 | BO74: 0 | BR74: 60 | BS74: 2 | BT74: 61.6 | BU74: 35 | BW74: 80 | BX74: =SUM(D74:BW74) -> 238.6 | BY74: =C74 -> 0 | BZ74: =BX74+BY74 -> 238.6 | CC74: =D74+J74+P74+V74+AB74+AH74+AN74+AT74+AZ74+BF74+BL74+BR74 -> 60 | CD74: =E74+K74+Q74+W74+AC74+AI74+AO74+AU74+BA74+BG74+BM74+BS74 -> 2 | CE74: =F74+L74+R74+X74+AD74+AJ74+AP74+AV74+BB74+BH74+BN74+BT74 -> 61.6 | CF74: =G74+M74+S74+Y74+AE74+AK74+AQ74+AW74+BC74+BI74+BO74+BU74 -> 35 | CG74: =H74+N74+T74+Z74+AF74+AL74+AR74+AX74+BJ74+BP74+BV74+BD74 -> 0 | CH74: =I74+O74+U74+AA74+AG74+AM74+AS74+AY74+BE74+BK74+BQ74+BW74 -> 80
A75: 73 | B75: JARA ALVARES CRISTALINA | C75: 0 | D75: 0 | E75: 0 | F75: 0 | G75: 0 | H75: 0 | J75: 0 | K75: 0 | L75: 0 | M75: 0 | N75: 0 | P75: 0 | Q75: 0 | R75: 0 | S75: 0 | T75: 0 | V75: 0 | W75: 0 | X75: 0 | Y75: 0 | Z75: 0 | AB75: 0 | AC75: 0 | AD75: 0 | AE75: 0 | AF75: 0 | AH75: 0 | AI75: 0 | AJ75: 0 | AK75: 0 | AL75: 0 | AN75: 0 | AO75: 0 | AP75: 0 | AQ75: 0 | AR75: 0 | AT75: 0 | AU75: 0 | AV75: 0 | AW75: 0 | AX75: 0 | AZ75: 0 | BA75: 0 | BB75: 0 | BC75: 0 | BF75: 0 | BG75: 0 | BH75: 0 | BI75: 0 | BL75: 0 | BM75: 0 | BN75: 73.5 | BO75: 3 | BR75: 0 | BS75: 0 | BT75: 79 | BU75: 3 | BX75: =SUM(D75:BW75) -> 158.5 | BY75: =C75 -> 0 | BZ75: =BX75+BY75 -> 158.5 | CC75: =D75+J75+P75+V75+AB75+AH75+AN75+AT75+AZ75+BF75+BL75+BR75 -> 0 | CD75: =E75+K75+Q75+W75+AC75+AI75+AO75+AU75+BA75+BG75+BM75+BS75 -> 0 | CE75: =F75+L75+R75+X75+AD75+AJ75+AP75+AV75+BB75+BH75+BN75+BT75 -> 152.5 | CF75: =G75+M75+S75+Y75+AE75+AK75+AQ75+AW75+BC75+BI75+BO75+BU75 -> 6 | CG75: =H75+N75+T75+Z75+AF75+AL75+AR75+AX75+BJ75+BP75+BV75+BD75 -> 0 | CH75: =I75+O75+U75+AA75+AG75+AM75+AS75+AY75+BE75+BK75+BQ75+BW75 -> 0
A76: 74 | B76: JARA ALVAREZ MARIA CENAIDA | C76: 0 | D76: 0 | E76: 0 | F76: 0 | G76: 0 | H76: 0 | J76: 0 | K76: 0 | L76: 0 | M76: 0 | N76: 0 | P76: 0 | Q76: 0 | R76: 0 | S76: 0 | T76: 0 | V76: 0 | W76: 0 | X76: 0 | Y76: 0 | Z76: 0 | AB76: 0 | AC76: 0 | AD76: 0 | AE76: 0 | AF76: 0 | AH76: 0 | AI76: 0 | AJ76: 0 | AK76: 0 | AL76: 0 | AN76: 0 | AO76: 0 | AP76: 0 | AQ76: 0 | AR76: 0 | AT76: 0 | AU76: 0 | AV76: 0 | AW76: 0 | AX76: 0 | AZ76: 0 | BA76: 0 | BB76: 0 | BC76: 0 | BF76: 0 | BG76: 0 | BH76: 0 | BI76: 0 | BL76: 60 | BM76: 2 | BN76: 81 | BO76: 3 | BR76: 60 | BS76: 2 | BT76: 86.1 | BU76: 3 | BX76: =SUM(D76:BW76) -> 297.1 | BY76: =C76 -> 0 | BZ76: =BX76+BY76 -> 297.1 | CC76: =D76+J76+P76+V76+AB76+AH76+AN76+AT76+AZ76+BF76+BL76+BR76 -> 120 | CD76: =E76+K76+Q76+W76+AC76+AI76+AO76+AU76+BA76+BG76+BM76+BS76 -> 4 | CE76: =F76+L76+R76+X76+AD76+AJ76+AP76+AV76+BB76+BH76+BN76+BT76 -> 167.1 | CF76: =G76+M76+S76+Y76+AE76+AK76+AQ76+AW76+BC76+BI76+BO76+BU76 -> 6 | CG76: =H76+N76+T76+Z76+AF76+AL76+AR76+AX76+BJ76+BP76+BV76+BD76 -> 0 | CH76: =I76+O76+U76+AA76+AG76+AM76+AS76+AY76+BE76+BK76+BQ76+BW76 -> 0
A77: 75 | B77: JARA ALVAREZ SANTOS PEDRO | C77: 0 | D77: 0 | E77: 0 | F77: 0 | G77: 0 | H77: 0 | J77: 0 | K77: 0 | L77: 0 | M77: 0 | N77: 0 | P77: 0 | Q77: 0 | R77: 0 | S77: 0 | T77: 0 | V77: 0 | W77: 0 | X77: 0 | Y77: 0 | Z77: 0 | AB77: 0 | AC77: 0 | AD77: 0 | AE77: 0 | AF77: 0 | AH77: 0 | AI77: 0 | AJ77: 0 | AK77: 0 | AL77: 0 | AN77: 0 | AO77: 0 | AP77: 0 | AQ77: 0 | AR77: 0 | AT77: 0 | AU77: 0 | AV77: 0 | AW77: 0 | AX77: 0 | AZ77: 0 | BA77: 0 | BB77: 0 | BC77: 0 | BF77: 0 | BG77: 0 | BH77: 0 | BI77: 0 | BL77: 0 | BM77: 0 | BN77: 0 | BO77: 0 | BR77: 22 | BS77: 2 | BT77: 22.4 | BU77: 3 | BX77: =SUM(D77:BW77) -> 49.4 | BY77: =C77 -> 0 | BZ77: =BX77+BY77 -> 49.4 | CC77: =D77+J77+P77+V77+AB77+AH77+AN77+AT77+AZ77+BF77+BL77+BR77 -> 22 | CD77: =E77+K77+Q77+W77+AC77+AI77+AO77+AU77+BA77+BG77+BM77+BS77 -> 2 | CE77: =F77+L77+R77+X77+AD77+AJ77+AP77+AV77+BB77+BH77+BN77+BT77 -> 22.4 | CF77: =G77+M77+S77+Y77+AE77+AK77+AQ77+AW77+BC77+BI77+BO77+BU77 -> 3 | CG77: =H77+N77+T77+Z77+AF77+AL77+AR77+AX77+BJ77+BP77+BV77+BD77 -> 0 | CH77: =I77+O77+U77+AA77+AG77+AM77+AS77+AY77+BE77+BK77+BQ77+BW77 -> 0
A78: 76 | B78: JUAREZ CUELLAR LEONOR | C78: 0 | D78: 0 | E78: 0 | F78: 0 | G78: 0 | H78: 0 | J78: 0 | K78: 0 | L78: 0 | M78: 0 | N78: 0 | P78: 0 | Q78: 0 | R78: 0 | S78: 0 | T78: 0 | V78: 0 | W78: 0 | X78: 0 | Y78: 0 | Z78: 0 | AB78: 0 | AC78: 0 | AD78: 0 | AE78: 0 | AF78: 0 | AH78: 0 | AI78: 0 | AJ78: 0 | AK78: 0 | AL78: 0 | AN78: 0 | AO78: 0 | AP78: 0 | AQ78: 0 | AR78: 0 | AT78: 0 | AU78: 0 | AV78: 0 | AW78: 0 | AX78: 0 | AZ78: 0 | BA78: 0 | BB78: 0 | BC78: 0 | BF78: 0 | BG78: 0 | BH78: 0 | BI78: 0 | BL78: 0 | BM78: 0 | BN78: 58 | BO78: 3 | BQ78: 59 | BR78: 60 | BS78: 2 | BT78: 61 | BU78: 3 | BX78: =SUM(D78:BW78) -> 246 | BY78: =C78 -> 0 | BZ78: =BX78+BY78 -> 246 | CC78: =D78+J78+P78+V78+AB78+AH78+AN78+AT78+AZ78+BF78+BL78+BR78 -> 60 | CD78: =E78+K78+Q78+W78+AC78+AI78+AO78+AU78+BA78+BG78+BM78+BS78 -> 2 | CE78: =F78+L78+R78+X78+AD78+AJ78+AP78+AV78+BB78+BH78+BN78+BT78 -> 119 | CF78: =G78+M78+S78+Y78+AE78+AK78+AQ78+AW78+BC78+BI78+BO78+BU78 -> 6 | CG78: =H78+N78+T78+Z78+AF78+AL78+AR78+AX78+BJ78+BP78+BV78+BD78 -> 0 | CH78: =I78+O78+U78+AA78+AG78+AM78+AS78+AY78+BE78+BK78+BQ78+BW78 -> 59
A79: 77 | B79: JARA TORRES FLOR (fallecida Nery Torres) | C79: 1366.9 | D79: 22 | E79: 2 | F79: 41 | G79: 35 | H79: 0 | J79: 8 | K79: 2 | L79: 20.5 | M79: 37 | N79: 0 | P79: 20 | Q79: 2 | R79: 39 | S79: 37 | T79: 0 | V79: 38 | W79: 2 | X79: 49 | Y79: 38 | Z79: 0 | AB79: 26 | AC79: 2 | AD79: 44 | AE79: 40 | AF79: 0 | AH79: 38 | AI79: 2 | AJ79: 67 | AK79: 39 | AL79: 0 | AN79: 20 | AO79: 2 | AP79: 30 | AQ79: 39 | AR79: 0 | AT79: 16 | AU79: 2 | AV79: 21 | AW79: 35.5 | AX79: 0 | AZ79: 36 | BA79: 2 | BB79: 65 | BC79: 36 | BF79: 30 | BG79: 2 | BH79: 53.5 | BI79: 42 | BL79: 26 | BM79: 2 | BN79: 47.5 | BO79: 39 | BR79: 28 | BS79: 2 | BX79: =SUM(D79:BW79) -> 1227 | BY79: =C79 -> 1366.9 | BZ79: =BX79+BY79 -> 2593.9 | CC79: =D79+J79+P79+V79+AB79+AH79+AN79+AT79+AZ79+BF79+BL79+BR79 -> 308 | CD79: =E79+K79+Q79+W79+AC79+AI79+AO79+AU79+BA79+BG79+BM79+BS79 -> 24 | CE79: =F79+L79+R79+X79+AD79+AJ79+AP79+AV79+BB79+BH79+BN79+BT79 -> 477.5 | CF79: =G79+M79+S79+Y79+AE79+AK79+AQ79+AW79+BC79+BI79+BO79+BU79 -> 417.5 | CG79: =H79+N79+T79+Z79+AF79+AL79+AR79+AX79+BJ79+BP79+BV79+BD79 -> 0 | CH79: =I79+O79+U79+AA79+AG79+AM79+AS79+AY79+BE79+BK79+BQ79+BW79 -> 0
A80: 78 | B80: LAGOS LUNA DE LEIVA ZAIDA | C80: 0 | D80: 0 | E80: 0 | F80: 0 | G80: 0 | H80: 0 | J80: 0 | K80: 0 | L80: 0 | M80: 0 | N80: 0 | P80: 0 | Q80: 0 | R80: 0 | S80: 0 | T80: 0 | V80: 0 | W80: 0 | X80: 0 | Y80: 0 | Z80: 0 | AB80: 0 | AC80: 0 | AD80: 0 | AE80: 0 | AF80: 0 | AH80: 0 | AI80: 0 | AJ80: 0 | AK80: 0 | AL80: 0 | AN80: 0 | AO80: 0 | AP80: 0 | AQ80: 0 | AR80: 0 | AT80: 0 | AU80: 0 | AV80: 0 | AW80: 0 | AX80: 0 | AZ80: 0 | BA80: 0 | BB80: 0 | BC80: 0 | BF80: 0 | BG80: 0 | BH80: 0 | BI80: 0 | BL80: 0 | BM80: 0 | BN80: 0 | BO80: 0 | BR80: 0 | BS80: 0 | BT80: 0 | BU80: 0 | BV80: 0 | BX80: =SUM(D80:BW80) -> 0 | BY80: =C80 -> 0 | BZ80: =BX80+BY80 -> 0 | CC80: =D80+J80+P80+V80+AB80+AH80+AN80+AT80+AZ80+BF80+BL80+BR80 -> 0 | CD80: =E80+K80+Q80+W80+AC80+AI80+AO80+AU80+BA80+BG80+BM80+BS80 -> 0 | CE80: =F80+L80+R80+X80+AD80+AJ80+AP80+AV80+BB80+BH80+BN80+BT80 -> 0 | CF80: =G80+M80+S80+Y80+AE80+AK80+AQ80+AW80+BC80+BI80+BO80+BU80 -> 0 | CG80: =H80+N80+T80+Z80+AF80+AL80+AR80+AX80+BJ80+BP80+BV80+BD80 -> 0 | CH80: =I80+O80+U80+AA80+AG80+AM80+AS80+AY80+BE80+BK80+BQ80+BW80 -> 0
A81: 79 | B81: LOPEZ HUAYHUALLA NELLY NATIVIDAD | C81: 0 | D81: 0 | E81: 0 | F81: 0 | G81: 0 | H81: 0 | J81: 0 | K81: 0 | L81: 0 | M81: 0 | N81: 0 | P81: 0 | Q81: 0 | R81: 0 | S81: 0 | T81: 0 | V81: 0 | W81: 0 | X81: 0 | Y81: 0 | Z81: 0 | AB81: 0 | AC81: 0 | AD81: 0 | AE81: 0 | AF81: 0 | AH81: 0 | AI81: 0 | AJ81: 0 | AK81: 0 | AL81: 0 | AN81: 0 | AO81: 0 | AP81: 0 | AQ81: 0 | AR81: 0 | AT81: 0 | AU81: 0 | AV81: 0 | AW81: 0 | AX81: 0 | AZ81: 0 | BA81: 0 | BB81: 0 | BC81: 0 | BE81: 15 | BF81: 0 | BG81: 0 | BH81: 0 | BI81: 0 | BL81: 60 | BM81: 2 | BN81: 62.5 | BO81: 35 | BR81: 60 | BS81: 2 | BT81: 67 | BU81: 35 | BW81: 80 | BX81: =SUM(D81:BW81) -> 418.5 | BY81: =C81 -> 0 | BZ81: =BX81+BY81 -> 418.5 | CC81: =D81+J81+P81+V81+AB81+AH81+AN81+AT81+AZ81+BF81+BL81+BR81 -> 120 | CD81: =E81+K81+Q81+W81+AC81+AI81+AO81+AU81+BA81+BG81+BM81+BS81 -> 4 | CE81: =F81+L81+R81+X81+AD81+AJ81+AP81+AV81+BB81+BH81+BN81+BT81 -> 129.5 | CF81: =G81+M81+S81+Y81+AE81+AK81+AQ81+AW81+BC81+BI81+BO81+BU81 -> 70 | CG81: =H81+N81+T81+Z81+AF81+AL81+AR81+AX81+BJ81+BP81+BV81+BD81 -> 0 | CH81: =I81+O81+U81+AA81+AG81+AM81+AS81+AY81+BE81+BK81+BQ81+BW81 -> 95
A82: 80 | B82: LUJAN GONZALES MARINO JUAN | C82: 0 | D82: 0 | E82: 0 | F82: 0 | G82: 0 | H82: 0 | J82: 0 | K82: 0 | L82: 0 | M82: 0 | N82: 0 | P82: 0 | Q82: 0 | R82: 0 | S82: 0 | T82: 0 | V82: 0 | W82: 0 | X82: 0 | Y82: 0 | Z82: 0 | AB82: 0 | AC82: 0 | AD82: 0 | AE82: 0 | AF82: 0 | AH82: 0 | AI82: 0 | AJ82: 0 | AK82: 0 | AL82: 0 | AN82: 0 | AO82: 0 | AP82: 0 | AQ82: 0 | AR82: 0 | AT82: 0 | AU82: 0 | AV82: 0 | AW82: 0 | AX82: 0 | AZ82: 0 | BA82: 0 | BB82: 0 | BC82: 0 | BF82: 0 | BG82: 0 | BH82: 0 | BI82: 0 | BL82: 60 | BM82: 2 | BN82: 50.5 | BO82: 35 | BR82: 60 | BS82: 2 | BT82: 53.9 | BU82: 35 | BW82: 80 | BX82: =SUM(D82:BW82) -> 378.4 | BY82: =C82 -> 0 | BZ82: =BX82+BY82 -> 378.4 | CC82: =D82+J82+P82+V82+AB82+AH82+AN82+AT82+AZ82+BF82+BL82+BR82 -> 120 | CD82: =E82+K82+Q82+W82+AC82+AI82+AO82+AU82+BA82+BG82+BM82+BS82 -> 4 | CE82: =F82+L82+R82+X82+AD82+AJ82+AP82+AV82+BB82+BH82+BN82+BT82 -> 104.4 | CF82: =G82+M82+S82+Y82+AE82+AK82+AQ82+AW82+BC82+BI82+BO82+BU82 -> 70 | CG82: =H82+N82+T82+Z82+AF82+AL82+AR82+AX82+BJ82+BP82+BV82+BD82 -> 0 | CH82: =I82+O82+U82+AA82+AG82+AM82+AS82+AY82+BE82+BK82+BQ82+BW82 -> 80
A83: 81 | B83: LIMAS VARGAS CARMEN ROSA | C83: 0 | D83: 0 | E83: 0 | F83: 0 | G83: 0 | H83: 0 | J83: 0 | K83: 0 | L83: 0 | M83: 0 | N83: 0 | P83: 0 | Q83: 0 | R83: 0 | S83: 0 | T83: 0 | V83: 0 | W83: 0 | X83: 0 | Y83: 0 | Z83: 0 | AB83: 0 | AC83: 0 | AD83: 0 | AE83: 0 | AF83: 0 | AH83: 0 | AI83: 0 | AJ83: 0 | AK83: 0 | AL83: 0 | AN83: 0 | AO83: 0 | AP83: 0 | AQ83: 0 | AR83: 0 | AT83: 0 | AU83: 0 | AV83: 0 | AW83: 0 | AX83: 0 | AZ83: 0 | BA83: 0 | BB83: 0 | BC83: 0 | BF83: 0 | BG83: 0 | BH83: 0 | BI83: 0 | BL83: 60 | BM83: 2 | BN83: 61 | BO83: 3 | BQ83: 59 | BR83: 60 | BS83: 2 | BT83: 64 | BU83: 3 | BX83: =SUM(D83:BW83) -> 314 | BY83: =C83 -> 0 | BZ83: =BX83+BY83 -> 314 | CC83: =D83+J83+P83+V83+AB83+AH83+AN83+AT83+AZ83+BF83+BL83+BR83 -> 120 | CD83: =E83+K83+Q83+W83+AC83+AI83+AO83+AU83+BA83+BG83+BM83+BS83 -> 4 | CE83: =F83+L83+R83+X83+AD83+AJ83+AP83+AV83+BB83+BH83+BN83+BT83 -> 125 | CF83: =G83+M83+S83+Y83+AE83+AK83+AQ83+AW83+BC83+BI83+BO83+BU83 -> 6 | CG83: =H83+N83+T83+Z83+AF83+AL83+AR83+AX83+BJ83+BP83+BV83+BD83 -> 0 | CH83: =I83+O83+U83+AA83+AG83+AM83+AS83+AY83+BE83+BK83+BQ83+BW83 -> 59
A84: 82 | B84: MALLQUI JULCA ALEJANDRINO TEODORO | C84: 0 | D84: 0 | E84: 0 | F84: 0 | G84: 0 | H84: 0 | J84: 0 | K84: 0 | L84: 0 | M84: 0 | N84: 0 | P84: 0 | Q84: 0 | R84: 0 | S84: 0 | T84: 0 | V84: 0 | W84: 0 | X84: 0 | Y84: 0 | Z84: 0 | AB84: 0 | AC84: 0 | AD84: 0 | AE84: 0 | AF84: 0 | AH84: 0 | AI84: 0 | AJ84: 0 | AK84: 0 | AL84: 0 | AN84: 0 | AO84: 0 | AP84: 0 | AQ84: 0 | AR84: 0 | AS84: 85 | AT84: 0 | AU84: 0 | AV84: 0 | AW84: 0 | AX84: 0 | AZ84: 0 | BA84: 0 | BB84: 0 | BC84: 0 | BF84: 0 | BG84: 0 | BH84: 0 | BI84: 0 | BL84: 60 | BM84: 2 | BN84: 49.5 | BO84: 35 | BR84: 60 | BS84: 2 | BT84: 52.8 | BU84: 35 | BW84: 80 | BX84: =SUM(D84:BW84) -> 461.3 | BY84: =C84 -> 0 | BZ84: =BX84+BY84 -> 461.3 | CC84: =D84+J84+P84+V84+AB84+AH84+AN84+AT84+AZ84+BF84+BL84+BR84 -> 120 | CD84: =E84+K84+Q84+W84+AC84+AI84+AO84+AU84+BA84+BG84+BM84+BS84 -> 4 | CE84: =F84+L84+R84+X84+AD84+AJ84+AP84+AV84+BB84+BH84+BN84+BT84 -> 102.3 | CF84: =G84+M84+S84+Y84+AE84+AK84+AQ84+AW84+BC84+BI84+BO84+BU84 -> 70 | CG84: =H84+N84+T84+Z84+AF84+AL84+AR84+AX84+BJ84+BP84+BV84+BD84 -> 0 | CH84: =I84+O84+U84+AA84+AG84+AM84+AS84+AY84+BE84+BK84+BQ84+BW84 -> 165
A85: 83 | B85: MARIN ARECHE ANTONIO | C85: 1387 | D85: 0 | E85: 0 | F85: 0 | G85: 0 | H85: 0 | J85: 0 | K85: 0 | L85: 0 | M85: 0 | N85: 0 | P85: 0 | Q85: 0 | R85: 0 | S85: 0 | T85: 0 | V85: 0 | W85: 0 | X85: 0 | Y85: 0 | Z85: 0 | AB85: 0 | AC85: 0 | AD85: 0 | AE85: 0 | AF85: 25 | AH85: 0 | AI85: 0 | AJ85: 0 | AK85: 0 | AL85: 25 | AN85: 0 | AO85: 0 | AP85: 0 | AQ85: 0 | AR85: 25 | AT85: 0 | AU85: 0 | AV85: 0 | AW85: 0 | AX85: 25 | AZ85: 60 | BA85: 2 | BB85: 0 | BC85: 0 | BD85: 25 | BE85: 45 | BF85: 60 | BG85: 2 | BH85: 0 | BI85: 0 | BJ85: 25 | BL85: 0 | BM85: 2 | BN85: 29.5 | BO85: 3 | BP85: 25 | BQ85: 59 | BR85: 0 | BS85: 2 | BT85: 81 | BU85: 3 | BV85: 25 | BX85: =SUM(D85:BW85) -> 548.5 | BY85: =C85 -> 1387 | BZ85: =BX85+BY85 -> 1935.5 | CC85: =D85+J85+P85+V85+AB85+AH85+AN85+AT85+AZ85+BF85+BL85+BR85 -> 120 | CD85: =E85+K85+Q85+W85+AC85+AI85+AO85+AU85+BA85+BG85+BM85+BS85 -> 8 | CE85: =F85+L85+R85+X85+AD85+AJ85+AP85+AV85+BB85+BH85+BN85+BT85 -> 110.5 | CF85: =G85+M85+S85+Y85+AE85+AK85+AQ85+AW85+BC85+BI85+BO85+BU85 -> 6 | CG85: =H85+N85+T85+Z85+AF85+AL85+AR85+AX85+BJ85+BP85+BV85+BD85 -> 200 | CH85: =I85+O85+U85+AA85+AG85+AM85+AS85+AY85+BE85+BK85+BQ85+BW85 -> 104
A86: 84 | B86: MARIN HUAMAN DE SALAMANCA MARIA YNES | C86: 0 | D86: 0 | E86: 0 | F86: 0 | G86: 0 | H86: 0 | J86: 0 | K86: 0 | L86: 0 | M86: 0 | N86: 0 | P86: 0 | Q86: 0 | R86: 0 | S86: 0 | T86: 0 | V86: 0 | W86: 0 | X86: 0 | Y86: 0 | Z86: 0 | AB86: 0 | AC86: 0 | AD86: 0 | AE86: 0 | AF86: 0 | AH86: 0 | AI86: 0 | AJ86: 0 | AK86: 0 | AL86: 0 | AN86: 0 | AO86: 0 | AP86: 0 | AQ86: 0 | AR86: 0 | AT86: 0 | AU86: 0 | AV86: 0 | AW86: 0 | AX86: 0 | AZ86: 0 | BA86: 0 | BB86: 0 | BC86: 0 | BF86: 0 | BG86: 0 | BH86: 0 | BI86: 0 | BL86: 0 | BM86: 0 | BN86: 0 | BO86: 0 | BT86: 153.6 | BU86: 25 | BX86: =SUM(D86:BW86) -> 178.6 | BY86: =C86 -> 0 | BZ86: =BX86+BY86 -> 178.6 | CC86: =D86+J86+P86+V86+AB86+AH86+AN86+AT86+AZ86+BF86+BL86+BR86 -> 0 | CD86: =E86+K86+Q86+W86+AC86+AI86+AO86+AU86+BA86+BG86+BM86+BS86 -> 0 | CE86: =F86+L86+R86+X86+AD86+AJ86+AP86+AV86+BB86+BH86+BN86+BT86 -> 153.6 | CF86: =G86+M86+S86+Y86+AE86+AK86+AQ86+AW86+BC86+BI86+BO86+BU86 -> 25 | CG86: =H86+N86+T86+Z86+AF86+AL86+AR86+AX86+BJ86+BP86+BV86+BD86 -> 0 | CH86: =I86+O86+U86+AA86+AG86+AM86+AS86+AY86+BE86+BK86+BQ86+BW86 -> 0
A87: 85 | B87: MAMANI SALAZAR JOSE (Fallecido Mamani Yanarico) | C87: 1754.3 | D87: 0 | E87: 0 | F87: 0 | G87: 0 | H87: 0 | J87: 0 | K87: 0 | L87: 0 | M87: 0 | N87: 0 | P87: 0 | Q87: 0 | R87: 0 | S87: 0 | T87: 0 | V87: 0 | W87: 0 | X87: 0 | Y87: 0 | Z87: 0 | AB87: 0 | AC87: 0 | AD87: 0 | AE87: 0 | AF87: 0 | AH87: 0 | AI87: 0 | AJ87: 0 | AK87: 0 | AL87: 0 | AN87: 0 | AO87: 0 | AP87: 0 | AQ87: 0 | AR87: 0 | AT87: 0 | AU87: 0 | AV87: 0 | AW87: 0 | AX87: 0 | AZ87: 0 | BA87: 0 | BB87: 0 | BC87: 0 | BF87: 0 | BG87: 0 | BH87: 0 | BI87: 0 | BL87: 0 | BM87: 0 | BN87: 0 | BO87: 0 | BR87: 0 | BS87: 0 | BX87: =SUM(D87:BW87) -> 0 | BY87: =C87 -> 1754.3 | BZ87: =BX87+BY87 -> 1754.3 | CC87: =D87+J87+P87+V87+AB87+AH87+AN87+AT87+AZ87+BF87+BL87+BR87 -> 0 | CD87: =E87+K87+Q87+W87+AC87+AI87+AO87+AU87+BA87+BG87+BM87+BS87 -> 0 | CE87: =F87+L87+R87+X87+AD87+AJ87+AP87+AV87+BB87+BH87+BN87+BT87 -> 0 | CF87: =G87+M87+S87+Y87+AE87+AK87+AQ87+AW87+BC87+BI87+BO87+BU87 -> 0 | CG87: =H87+N87+T87+Z87+AF87+AL87+AR87+AX87+BJ87+BP87+BV87+BD87 -> 0 | CH87: =I87+O87+U87+AA87+AG87+AM87+AS87+AY87+BE87+BK87+BQ87+BW87 -> 0
A88: 86 | B88: MARIN HUAMAN MARIO | C88: 0 | D88: 0 | E88: 0 | F88: 0 | G88: 0 | H88: 0 | J88: 0 | K88: 0 | L88: 0 | M88: 0 | N88: 0 | P88: 0 | Q88: 0 | R88: 0 | S88: 0 | T88: 0 | V88: 0 | W88: 0 | X88: 0 | Y88: 0 | Z88: 0 | AB88: 0 | AC88: 0 | AD88: 0 | AE88: 0 | AF88: 0 | AH88: 0 | AI88: 0 | AJ88: 0 | AK88: 0 | AL88: 0 | AN88: 0 | AO88: 0 | AP88: 0 | AQ88: 0 | AR88: 0 | AT88: 0 | AU88: 0 | AV88: 0 | AW88: 0 | AX88: 0 | AZ88: 0 | BA88: 0 | BB88: 0 | BC88: 0 | BF88: 0 | BG88: 0 | BH88: 0 | BI88: 0 | BL88: 0 | BM88: 0 | BN88: 0 | BO88: 0 | BR88: 0 | BS88: 0 | BX88: =SUM(D88:BW88) -> 0 | BY88: =C88 -> 0 | BZ88: =BX88+BY88 -> 0 | CC88: =D88+J88+P88+V88+AB88+AH88+AN88+AT88+AZ88+BF88+BL88+BR88 -> 0 | CD88: =E88+K88+Q88+W88+AC88+AI88+AO88+AU88+BA88+BG88+BM88+BS88 -> 0 | CE88: =F88+L88+R88+X88+AD88+AJ88+AP88+AV88+BB88+BH88+BN88+BT88 -> 0 | CF88: =G88+M88+S88+Y88+AE88+AK88+AQ88+AW88+BC88+BI88+BO88+BU88 -> 0 | CG88: =H88+N88+T88+Z88+AF88+AL88+AR88+AX88+BJ88+BP88+BV88+BD88 -> 0 | CH88: =I88+O88+U88+AA88+AG88+AM88+AS88+AY88+BE88+BK88+BQ88+BW88 -> 0
A89: 87 | B89: MARIN ILIZARDE BASILISA | C89: 0 | D89: 0 | E89: 0 | F89: 0 | G89: 0 | H89: 0 | J89: 0 | K89: 0 | L89: 0 | M89: 0 | N89: 0 | P89: 0 | Q89: 0 | R89: 0 | S89: 0 | T89: 0 | V89: 0 | W89: 0 | X89: 0 | Y89: 0 | Z89: 0 | AB89: 0 | AC89: 0 | AD89: 0 | AE89: 0 | AF89: 0 | AH89: 0 | AI89: 0 | AJ89: 0 | AK89: 0 | AL89: 0 | AN89: 0 | AO89: 0 | AP89: 0 | AQ89: 0 | AR89: 0 | AT89: 0 | AU89: 0 | AV89: 0 | AW89: 0 | AX89: 0 | AZ89: 0 | BA89: 0 | BB89: 0 | BC89: 0 | BF89: 0 | BG89: 0 | BH89: 0 | BI89: 0 | BL89: 0 | BM89: 0 | BN89: 0 | BO89: 0 | BR89: 0 | BS89: 0 | BX89: =SUM(D89:BW89) -> 0 | BY89: =C89 -> 0 | BZ89: =BX89+BY89 -> 0 | CC89: =D89+J89+P89+V89+AB89+AH89+AN89+AT89+AZ89+BF89+BL89+BR89 -> 0 | CD89: =E89+K89+Q89+W89+AC89+AI89+AO89+AU89+BA89+BG89+BM89+BS89 -> 0 | CE89: =F89+L89+R89+X89+AD89+AJ89+AP89+AV89+BB89+BH89+BN89+BT89 -> 0 | CF89: =G89+M89+S89+Y89+AE89+AK89+AQ89+AW89+BC89+BI89+BO89+BU89 -> 0 | CG89: =H89+N89+T89+Z89+AF89+AL89+AR89+AX89+BJ89+BP89+BV89+BD89 -> 0 | CH89: =I89+O89+U89+AA89+AG89+AM89+AS89+AY89+BE89+BK89+BQ89+BW89 -> 0
A90: 88 | B90: MARIN LONDOÑE EDUARDO SANTIAGO | C90: 0 | D90: 0 | E90: 0 | F90: 0 | G90: 0 | H90: 0 | J90: 0 | K90: 0 | L90: 0 | M90: 0 | N90: 0 | P90: 0 | Q90: 0 | R90: 0 | S90: 0 | T90: 0 | V90: 0 | W90: 0 | X90: 0 | Y90: 0 | Z90: 0 | AB90: 0 | AC90: 0 | AD90: 0 | AE90: 0 | AF90: 0 | AH90: 0 | AI90: 0 | AJ90: 0 | AK90: 0 | AL90: 0 | AN90: 0 | AO90: 0 | AP90: 0 | AQ90: 0 | AR90: 0 | AT90: 0 | AU90: 0 | AV90: 0 | AW90: 0 | AX90: 0 | AZ90: 0 | BA90: 0 | BB90: 0 | BC90: 0 | BF90: 0 | BG90: 0 | BH90: 0 | BI90: 0 | BL90: 0 | BM90: 0 | BN90: 67.5 | BO90: 3 | BQ90: 59 | BR90: 0 | BS90: 0 | BX90: =SUM(D90:BW90) -> 129.5 | BY90: =C90 -> 0 | BZ90: =BX90+BY90 -> 129.5 | CC90: =D90+J90+P90+V90+AB90+AH90+AN90+AT90+AZ90+BF90+BL90+BR90 -> 0 | CD90: =E90+K90+Q90+W90+AC90+AI90+AO90+AU90+BA90+BG90+BM90+BS90 -> 0 | CE90: =F90+L90+R90+X90+AD90+AJ90+AP90+AV90+BB90+BH90+BN90+BT90 -> 67.5 | CF90: =G90+M90+S90+Y90+AE90+AK90+AQ90+AW90+BC90+BI90+BO90+BU90 -> 3 | CG90: =H90+N90+T90+Z90+AF90+AL90+AR90+AX90+BJ90+BP90+BV90+BD90 -> 0 | CH90: =I90+O90+U90+AA90+AG90+AM90+AS90+AY90+BE90+BK90+BQ90+BW90 -> 59
A91: 89 | B91: MARIN LONDOÑE MARIA LUZ | C91: 0 | D91: 0 | E91: 0 | F91: 0 | G91: 0 | H91: 0 | J91: 0 | K91: 0 | L91: 0 | M91: 0 | N91: 0 | P91: 0 | Q91: 0 | R91: 0 | S91: 0 | T91: 0 | V91: 0 | W91: 0 | X91: 0 | Y91: 0 | Z91: 0 | AB91: 0 | AC91: 0 | AD91: 0 | AE91: 0 | AF91: 0 | AH91: 0 | AI91: 0 | AJ91: 0 | AK91: 0 | AL91: 0 | AN91: 0 | AO91: 0 | AP91: 0 | AQ91: 0 | AR91: 0 | AT91: 0 | AU91: 0 | AV91: 0 | AW91: 0 | AX91: 0 | AZ91: 0 | BA91: 0 | BB91: 0 | BC91: 0 | BD91: 0 | BE91: 30 | BF91: 0 | BG91: 0 | BH91: 0 | BI91: 0 | BJ91: 0 | BL91: 0 | BM91: 0 | BN91: 37.5 | BO91: 3 | BQ91: 59 | BR91: 0 | BS91: 0 | BX91: =SUM(D91:BW91) -> 129.5 | BY91: =C91 -> 0 | BZ91: =BX91+BY91 -> 129.5 | CC91: =D91+J91+P91+V91+AB91+AH91+AN91+AT91+AZ91+BF91+BL91+BR91 -> 0 | CD91: =E91+K91+Q91+W91+AC91+AI91+AO91+AU91+BA91+BG91+BM91+BS91 -> 0 | CE91: =F91+L91+R91+X91+AD91+AJ91+AP91+AV91+BB91+BH91+BN91+BT91 -> 37.5 | CF91: =G91+M91+S91+Y91+AE91+AK91+AQ91+AW91+BC91+BI91+BO91+BU91 -> 3 | CG91: =H91+N91+T91+Z91+AF91+AL91+AR91+AX91+BJ91+BP91+BV91+BD91 -> 0 | CH91: =I91+O91+U91+AA91+AG91+AM91+AS91+AY91+BE91+BK91+BQ91+BW91 -> 89
A92: 90 | B92: MAYHUASCA BASTIDAS MARILU | C92: 0 | D92: 0 | E92: 0 | F92: 0 | G92: 0 | H92: 0 | J92: 0 | K92: 0 | L92: 0 | M92: 0 | N92: 0 | P92: 0 | Q92: 0 | R92: 0 | S92: 0 | T92: 0 | V92: 0 | W92: 0 | X92: 0 | Y92: 0 | Z92: 0 | AB92: 0 | AC92: 0 | AD92: 0 | AE92: 0 | AF92: 0 | AH92: 0 | AI92: 0 | AJ92: 0 | AK92: 0 | AL92: 0 | AN92: 0 | AO92: 0 | AP92: 0 | AQ92: 0 | AR92: 0 | AT92: 0 | AU92: 0 | AV92: 0 | AW92: 0 | AX92: 0 | AZ92: 0 | BA92: 0 | BB92: 0 | BC92: 0 | BF92: 0 | BG92: 0 | BH92: 0 | BI92: 0 | BL92: 0 | BM92: 0 | BN92: 0 | BO92: 0 | BR92: 0 | BS92: 0 | BX92: =SUM(D92:BW92) -> 0 | BY92: =C92 -> 0 | BZ92: =BX92+BY92 -> 0 | CC92: =D92+J92+P92+V92+AB92+AH92+AN92+AT92+AZ92+BF92+BL92+BR92 -> 0 | CD92: =E92+K92+Q92+W92+AC92+AI92+AO92+AU92+BA92+BG92+BM92+BS92 -> 0 | CE92: =F92+L92+R92+X92+AD92+AJ92+AP92+AV92+BB92+BH92+BN92+BT92 -> 0 | CF92: =G92+M92+S92+Y92+AE92+AK92+AQ92+AW92+BC92+BI92+BO92+BU92 -> 0 | CG92: =H92+N92+T92+Z92+AF92+AL92+AR92+AX92+BJ92+BP92+BV92+BD92 -> 0 | CH92: =I92+O92+U92+AA92+AG92+AM92+AS92+AY92+BE92+BK92+BQ92+BW92 -> 0
A93: 91 | B93: MAYHUASCA BASTIDAS ULISES | C93: 6192.18 | D93: 34 | E93: 2 | F93: 0 | G93: 0 | H93: 0 | J93: 42 | K93: 2 | L93: 0 | M93: 0 | N93: 0 | P93: 32 | Q93: 2 | R93: 0 | S93: 0 | T93: 0 | U93: 75 | V93: 34 | W93: 2 | X93: 0 | Y93: 0 | Z93: 0 | AB93: 40 | AC93: 2 | AD93: 0 | AE93: 0 | AF93: 0 | AH93: 40 | AI93: 2 | AJ93: 0 | AK93: 0 | AL93: 0 | AM93: 75 | AN93: 28 | AO93: 2 | AP93: 0 | AQ93: 0 | AR93: 0 | AS93: 85 | AT93: 36 | AU93: 2 | AV93: 0 | AW93: 0 | AX93: 0 | AZ93: 28 | BA93: 2 | BB93: 0 | BC93: 0 | BF93: 18 | BG93: 2 | BH93: 0 | BI93: 0 | BL93: 30 | BM93: 2 | BN93: 93.5 | BO93: 25 | BQ93: 85 | BR93: 6 | BS93: 2 | BX93: =SUM(D93:BW93) -> 830.5 | BY93: =C93 -> 6192.18 | BZ93: =BX93+BY93 -> 7022.68 | CC93: =D93+J93+P93+V93+AB93+AH93+AN93+AT93+AZ93+BF93+BL93+BR93 -> 368 | CD93: =E93+K93+Q93+W93+AC93+AI93+AO93+AU93+BA93+BG93+BM93+BS93 -> 24 | CE93: =F93+L93+R93+X93+AD93+AJ93+AP93+AV93+BB93+BH93+BN93+BT93 -> 93.5 | CF93: =G93+M93+S93+Y93+AE93+AK93+AQ93+AW93+BC93+BI93+BO93+BU93 -> 25 | CG93: =H93+N93+T93+Z93+AF93+AL93+AR93+AX93+BJ93+BP93+BV93+BD93 -> 0 | CH93: =I93+O93+U93+AA93+AG93+AM93+AS93+AY93+BE93+BK93+BQ93+BW93 -> 320
A94: 92 | B94: MAYTA COLQUI VIOLETA | C94: 0 | D94: 0 | E94: 0 | F94: 0 | G94: 0 | H94: 0 | J94: 0 | K94: 0 | L94: 0 | M94: 0 | N94: 0 | P94: 0 | Q94: 0 | R94: 0 | S94: 0 | T94: 0 | V94: 0 | W94: 0 | X94: 0 | Y94: 0 | Z94: 0 | AB94: 0 | AC94: 0 | AD94: 0 | AE94: 0 | AF94: 0 | AH94: 0 | AI94: 0 | AJ94: 0 | AK94: 0 | AL94: 0 | AN94: 0 | AO94: 0 | AP94: 0 | AQ94: 0 | AR94: 0 | AT94: 0 | AU94: 0 | AV94: 0 | AW94: 0 | AX94: 0 | AZ94: 0 | BA94: 0 | BB94: 0 | BC94: 0 | BF94: 0 | BG94: 0 | BH94: 0 | BI94: 0 | BL94: 0 | BM94: 0 | BN94: 62.5 | BO94: 25 | BQ94: 85 | BR94: 0 | BS94: 0 | BX94: =SUM(D94:BW94) -> 172.5 | BY94: =C94 -> 0 | BZ94: =BX94+BY94 -> 172.5 | CC94: =D94+J94+P94+V94+AB94+AH94+AN94+AT94+AZ94+BF94+BL94+BR94 -> 0 | CD94: =E94+K94+Q94+W94+AC94+AI94+AO94+AU94+BA94+BG94+BM94+BS94 -> 0 | CE94: =F94+L94+R94+X94+AD94+AJ94+AP94+AV94+BB94+BH94+BN94+BT94 -> 62.5 | CF94: =G94+M94+S94+Y94+AE94+AK94+AQ94+AW94+BC94+BI94+BO94+BU94 -> 25 | CG94: =H94+N94+T94+Z94+AF94+AL94+AR94+AX94+BJ94+BP94+BV94+BD94 -> 0 | CH94: =I94+O94+U94+AA94+AG94+AM94+AS94+AY94+BE94+BK94+BQ94+BW94 -> 85
A95: 93 | B95: MAITA RIVERA SANTIAGO ATENCIO | C95: 0 | D95: 0 | E95: 0 | F95: 0 | G95: 0 | H95: 0 | J95: 0 | K95: 0 | L95: 0 | M95: 0 | N95: 0 | P95: 0 | Q95: 0 | R95: 0 | S95: 0 | T95: 0 | V95: 0 | W95: 0 | X95: 0 | Y95: 0 | Z95: 0 | AB95: 4 | AC95: 2 | AD95: 0 | AE95: 0 | AF95: 0 | AH95: 0 | AI95: 0 | AJ95: 0 | AK95: 0 | AL95: 0 | AN95: 0 | AO95: 0 | AP95: 0 | AQ95: 0 | AR95: 0 | AS95: 85 | AT95: 0 | AU95: 0 | AV95: 0 | AW95: 0 | AX95: 0 | AY95: 0 | AZ95: 0 | BA95: 0 | BB95: 0 | BC95: 0 | BF95: 0 | BG95: 0 | BH95: 0 | BI95: 0 | BL95: 0 | BM95: 0 | BN95: 42.5 | BO95: 35 | BQ95: 85 | BR95: 0 | BS95: 0 | BX95: =SUM(D95:BW95) -> 253.5 | BY95: =C95 -> 0 | BZ95: =BX95+BY95 -> 253.5 | CC95: =D95+J95+P95+V95+AB95+AH95+AN95+AT95+AZ95+BF95+BL95+BR95 -> 4 | CD95: =E95+K95+Q95+W95+AC95+AI95+AO95+AU95+BA95+BG95+BM95+BS95 -> 2 | CE95: =F95+L95+R95+X95+AD95+AJ95+AP95+AV95+BB95+BH95+BN95+BT95 -> 42.5 | CF95: =G95+M95+S95+Y95+AE95+AK95+AQ95+AW95+BC95+BI95+BO95+BU95 -> 35 | CG95: =H95+N95+T95+Z95+AF95+AL95+AR95+AX95+BJ95+BP95+BV95+BD95 -> 0 | CH95: =I95+O95+U95+AA95+AG95+AM95+AS95+AY95+BE95+BK95+BQ95+BW95 -> 170
A96: 94 | B96: MEDINA JOTA DE CACERES VICENTA | C96: 0 | D96: 0 | E96: 0 | F96: 0 | G96: 0 | H96: 0 | J96: 0 | K96: 0 | L96: 0 | M96: 0 | N96: 0 | P96: 0 | Q96: 0 | R96: 0 | S96: 0 | T96: 0 | V96: 0 | W96: 0 | X96: 0 | Y96: 0 | Z96: 0 | AB96: 0 | AC96: 0 | AD96: 0 | AE96: 0 | AF96: 0 | AH96: 0 | AI96: 0 | AJ96: 0 | AK96: 0 | AL96: 0 | AN96: 0 | AO96: 0 | AP96: 0 | AQ96: 0 | AR96: 0 | AT96: 0 | AU96: 0 | AV96: 0 | AW96: 0 | AX96: 0 | AZ96: 0 | BA96: 0 | BB96: 0 | BC96: 0 | BF96: 0 | BG96: 0 | BH96: 0 | BI96: 0 | BL96: 0 | BM96: 0 | BN96: 0 | BO96: 0 | BR96: 0 | BS96: 0 | BX96: =SUM(D96:BW96) -> 0 | BY96: =C96 -> 0 | BZ96: =BX96+BY96 -> 0 | CC96: =D96+J96+P96+V96+AB96+AH96+AN96+AT96+AZ96+BF96+BL96+BR96 -> 0 | CD96: =E96+K96+Q96+W96+AC96+AI96+AO96+AU96+BA96+BG96+BM96+BS96 -> 0 | CE96: =F96+L96+R96+X96+AD96+AJ96+AP96+AV96+BB96+BH96+BN96+BT96 -> 0 | CF96: =G96+M96+S96+Y96+AE96+AK96+AQ96+AW96+BC96+BI96+BO96+BU96 -> 0 | CG96: =H96+N96+T96+Z96+AF96+AL96+AR96+AX96+BJ96+BP96+BV96+BD96 -> 0 | CH96: =I96+O96+U96+AA96+AG96+AM96+AS96+AY96+BE96+BK96+BQ96+BW96 -> 0
A97: 95 | B97: MEDINA MEDRANO CARLOS | C97: 0 | D97: 0 | E97: 0 | F97: 0 | G97: 0 | H97: 0 | J97: 0 | K97: 0 | L97: 0 | M97: 0 | N97: 0 | P97: 0 | Q97: 0 | R97: 0 | S97: 0 | T97: 0 | V97: 0 | W97: 0 | X97: 0 | Y97: 0 | Z97: 0 | AB97: 0 | AC97: 0 | AD97: 0 | AE97: 0 | AF97: 0 | AH97: 0 | AI97: 0 | AJ97: 0 | AK97: 0 | AL97: 0 | AN97: 0 | AO97: 0 | AP97: 0 | AQ97: 0 | AR97: 0 | AT97: 0 | AU97: 0 | AV97: 0 | AW97: 0 | AX97: 0 | AZ97: 0 | BA97: 0 | BB97: 0 | BC97: 0 | BF97: 0 | BG97: 0 | BH97: 0 | BI97: 0 | BL97: 0 | BM97: 0 | BN97: 0 | BO97: 0 | BR97: 6 | BS97: 2 | BX97: =SUM(D97:BW97) -> 8 | BY97: =C97 -> 0 | BZ97: =BX97+BY97 -> 8 | CC97: =D97+J97+P97+V97+AB97+AH97+AN97+AT97+AZ97+BF97+BL97+BR97 -> 6 | CD97: =E97+K97+Q97+W97+AC97+AI97+AO97+AU97+BA97+BG97+BM97+BS97 -> 2 | CE97: =F97+L97+R97+X97+AD97+AJ97+AP97+AV97+BB97+BH97+BN97+BT97 -> 0 | CF97: =G97+M97+S97+Y97+AE97+AK97+AQ97+AW97+BC97+BI97+BO97+BU97 -> 0 | CG97: =H97+N97+T97+Z97+AF97+AL97+AR97+AX97+BJ97+BP97+BV97+BD97 -> 0 | CH97: =I97+O97+U97+AA97+AG97+AM97+AS97+AY97+BE97+BK97+BQ97+BW97 -> 0
A98: 96 | B98: MEDRANO ANDIA DIONISIA DE CASTILLO | C98: 41 | D98: 0 | E98: 0 | F98: 0 | G98: 0 | H98: 0 | J98: 0 | K98: 0 | L98: 0 | M98: 0 | N98: 0 | P98: 0 | Q98: 0 | R98: 0 | S98: 0 | T98: 0 | V98: 0 | W98: 0 | X98: 0 | Y98: 0 | Z98: 0 | AB98: 0 | AC98: 0 | AD98: 0 | AE98: 0 | AF98: 0 | AH98: 0 | AI98: 0 | AJ98: 0 | AK98: 0 | AL98: 0 | AN98: 0 | AO98: 0 | AP98: 0 | AQ98: 0 | AR98: 0 | AT98: 0 | AU98: 0 | AV98: 0 | AW98: 0 | AX98: 0 | AY98: 25 | AZ98: 0 | BA98: 0 | BB98: 0 | BC98: 0 | BF98: 0 | BG98: 0 | BH98: 0 | BI98: 0 | BL98: 0 | BM98: 0 | BN98: 79.5 | BO98: 57 | BR98: 0 | BS98: 0 | BX98: =SUM(D98:BW98) -> 161.5 | BY98: =C98 -> 41 | BZ98: =BX98+BY98 -> 202.5 | CC98: =D98+J98+P98+V98+AB98+AH98+AN98+AT98+AZ98+BF98+BL98+BR98 -> 0 | CD98: =E98+K98+Q98+W98+AC98+AI98+AO98+AU98+BA98+BG98+BM98+BS98 -> 0 | CE98: =F98+L98+R98+X98+AD98+AJ98+AP98+AV98+BB98+BH98+BN98+BT98 -> 79.5 | CF98: =G98+M98+S98+Y98+AE98+AK98+AQ98+AW98+BC98+BI98+BO98+BU98 -> 57 | CG98: =H98+N98+T98+Z98+AF98+AL98+AR98+AX98+BJ98+BP98+BV98+BD98 -> 0 | CH98: =I98+O98+U98+AA98+AG98+AM98+AS98+AY98+BE98+BK98+BQ98+BW98 -> 25
A99: 97 | B99: MEJIA HUAMAN ÑAHUE DE ARCE VICTORIA | C99: 2173.1 | D99: 0 | E99: 0 | F99: 0 | G99: 0 | H99: 0 | J99: 0 | K99: 0 | L99: 0 | M99: 0 | N99: 0 | P99: 0 | Q99: 0 | R99: 0 | S99: 0 | T99: 0 | V99: 0 | W99: 0 | X99: 0 | Y99: 0 | Z99: 0 | AB99: 0 | AC99: 0 | AD99: 0 | AE99: 0 | AF99: 0 | AH99: 0 | AI99: 0 | AJ99: 0 | AK99: 0 | AL99: 0 | AN99: 0 | AO99: 0 | AP99: 0 | AQ99: 0 | AR99: 0 | AT99: 0 | AU99: 0 | AV99: 0 | AW99: 0 | AX99: 0 | AZ99: 0 | BA99: 0 | BB99: 0 | BC99: 0 | BF99: 0 | BG99: 0 | BH99: 0 | BI99: 0 | BL99: 0 | BM99: 0 | BN99: 199.5 | BO99: 21 | BQ99: 59 | BR99: 0 | BS99: 0 | BX99: =SUM(D99:BW99) -> 279.5 | BY99: =C99 -> 2173.1 | BZ99: =BX99+BY99 -> 2452.6 | CC99: =D99+J99+P99+V99+AB99+AH99+AN99+AT99+AZ99+BF99+BL99+BR99 -> 0 | CD99: =E99+K99+Q99+W99+AC99+AI99+AO99+AU99+BA99+BG99+BM99+BS99 -> 0 | CE99: =F99+L99+R99+X99+AD99+AJ99+AP99+AV99+BB99+BH99+BN99+BT99 -> 199.5 | CF99: =G99+M99+S99+Y99+AE99+AK99+AQ99+AW99+BC99+BI99+BO99+BU99 -> 21 | CG99: =H99+N99+T99+Z99+AF99+AL99+AR99+AX99+BJ99+BP99+BV99+BD99 -> 0 | CH99: =I99+O99+U99+AA99+AG99+AM99+AS99+AY99+BE99+BK99+BQ99+BW99 -> 59
A100: 98 | B100: MELO BACA MARINA | C100: 1243 | D100: 0 | E100: 0 | F100: 0 | G100: 0 | H100: 0 | J100: 0 | K100: 0 | L100: 0 | M100: 0 | N100: 0 | P100: 0 | Q100: 0 | R100: 0 | S100: 0 | T100: 0 | U100: 75 | V100: 0 | W100: 0 | X100: 0 | Y100: 0 | Z100: 0 | AB100: 0 | AC100: 0 | AD100: 0 | AE100: 0 | AF100: 0 | AH100: 0 | AI100: 0 | AJ100: 0 | AK100: 0 | AL100: 0 | AM100: 75 | AN100: 0 | AO100: 0 | AP100: 0 | AQ100: 0 | AR100: 0 | AS100: 85 | AT100: 0 | AU100: 0 | AV100: 0 | AW100: 0 | AX100: 0 | AZ100: 0 | BA100: 0 | BB100: 0 | BC100: 0 | BF100: 0 | BG100: 0 | BH100: 0 | BI100: 0 | BL100: 0 | BM100: 0 | BN100: 97.5 | BO100: 43 | BQ100: 85 | BR100: 0 | BS100: 0 | BX100: =SUM(D100:BW100) -> 460.5 | BY100: =C100 -> 1243 | BZ100: =BX100+BY100 -> 1703.5 | CC100: =D100+J100+P100+V100+AB100+AH100+AN100+AT100+AZ100+BF100+BL100+BR100 -> 0 | CD100: =E100+K100+Q100+W100+AC100+AI100+AO100+AU100+BA100+BG100+BM100+BS100 -> 0 | CE100: =F100+L100+R100+X100+AD100+AJ100+AP100+AV100+BB100+BH100+BN100+BT100 -> 97.5 | CF100: =G100+M100+S100+Y100+AE100+AK100+AQ100+AW100+BC100+BI100+BO100+BU100 -> 43 | CG100: =H100+N100+T100+Z100+AF100+AL100+AR100+AX100+BJ100+BP100+BV100+BD100 -> 0 | CH100: =I100+O100+U100+AA100+AG100+AM100+AS100+AY100+BE100+BK100+BQ100+BW100 -> 320
...

Sheet Choquehuanca David
A2: CHOQUEHUANCA HUAMAN DAVID
A4: FECHA | B4: DOCUMENTO | C4: PERIODO | D4: CONCEPTO | E4: POR COBRAR | F4: PAGADO | G4: SALDO POR COBRAR
G5: 0
A6: 45200 | B6: POR COBRAR | C6: OCTUBRE | D6: GARANTIA | E6: 500 | G6: =+G5+E6-F6 -> 500
D7: ALQUILER | E7: 500 | G7: =+G6+E7-F7 -> 1000
D8: LUZ | E8: 24.3 | G8: =+G7+E8-F8 -> 1024.3
D9: AGUA | E9: 2 | G9: =+G8+E9-F9 -> 1026.3
A10: 45198 | B10: EB01-2687 | C10: OCTUBRE | D10: GARANTIA | F10: 500 | G10: =+G9+E10-F10 -> 526.3
A11: 45198 | B11: EB01-2688 | C11: OCTUBRE | D11: ALQUILER | F11: 500 | G11: =+G10+E11-F11 -> 26.3
A12: 45264 | B12: RII 1921 | C12: OCTUBRE | D12: LUZ | F12: 24.3 | G12: =+G11+E12-F12 -> 2
A13: 45264 | B13: RII 1921 | C13: OCTUBRE | D13: AGUA | F13: 2 | G13: =+G12+E13-F13 -> -4.6185278e-14
A14: 45260 | B14: POR COBRAR | C14: NOVIEMBRE | D14: LUZ | E14: 26.4 | G14: =+G13+E14-F14 -> 26.4
D15: AGUA | E15: 10 | G15: =+G14+E15-F15 -> 36.4
D16: ALQUILER | E16: 500 | G16: =+G15+E16-F16 -> 536.4
A17: 45234 | B17: EB01-2869 | C17: MOVIEMBRE | D17: ALQUILER | F17: 500 | G17: =+G16+E17-F17 -> 36.4
A18: 45299 | B18: RII 1984 | C18: MOVIEMBRE | D18: LUZ | F18: 26.4 | G18: =+G17+E18-F18 -> 10
A19: 45299 | B19: RII 1984 | C19: MOVIEMBRE | D19: AGUA | F19: 10 | G19: =+G18+E19-F19 -> -2.1316282e-14
A20: 45291 | B20: POR COBRAR | C20: DICIEMBRE | D20: LUZ | E20: 28.2 | G20: =+G19+E20-F20 -> 28.2
D21: AGUA | E21: 5 | G21: =+G20+E21-F21 -> 33.2
D22: ALQUILER | E22: 500 | G22: =+G21+E22-F22 -> 533.2
A23: 45264 | B23: EB01-3005 | C23: DICIEMBRE | D23: ALQUILER | F23: 500 | G23: =+G22+E23-F23 -> 33.2
A24: 45331 | B24: RII 2045 | C24: DICIEMBRE | D24: LUZ | F24: 28.2 | G24: =+G23+E24-F24 -> 5
A25: 45331 | B25: RII 2045 | C25: DICIEMBRE | D25: AGUA | F25: 5 | G25: =+G24+E25-F25 -> -6.750156e-14
A26: 45322 | B26: POR COBRAR | C26: ENERO | D26: LUZ | E26: 31.5 | G26: =+G25+E26-F26 -> 31.5
D27: AGUA | E27: 8.8 | G27: =+G26+E27-F27 -> 40.3
D28: ALQUILER | E28: 500 | G28: =+G27+E28-F28 -> 540.3
A29: 45299 | B29: EB01-3164 | C29: ENERO | D29: ALQUILER | F29: 500 | G29: =+G28+E29-F29 -> 40.3
A30: 45362 | B30: RII 2088 | C30: ENERO | D30: LUZ | F30: 31.5 | G30: =+G29+E30-F30 -> 8.8
A31: 45362 | B31: RII 2088 | C31: ENERO | D31: AGUA | F31: 8.8 | G31: =+G30+E31-F31 -> -4.6185278e-14
A32: 45351 | B32: POR COBRAR | C32: FEBRERO | D32: LUZ | E32: 32.6 | G32: =+G31+E32-F32 -> 32.6
D33: AGUA | E33: 5 | G33: =+G32+E33-F33 -> 37.6
D34: ALQUILER | E34: 500 | G34: =+G33+E34-F34 -> 537.6
A35: 45331 | B35: EB01-3312 | C35: FEBRERO | D35: ALQUILER | F35: 500 | G35: =+G34+E35-F35 -> 37.6
A36: 45434 | B36: RII 2198 | C36: FEBRERO | D36: LUZ | F36: 32.6 | G36: =+G35+E36-F36 -> 5
A37: 45434 | B37: RII 2198 | C37: FEBRERO | D37: AGUA | F37: 5 | G37: =+G36+E37-F37 -> -9.2370556e-14
A38: 45382 | B38: POR COBRAR | C38: MARZO | D38: LUZ | E38: 31.6 | G38: =+G37+E38-F38 -> 31.6
D39: AGUA | E39: 5 | G39: =+G38+E39-F39 -> 36.6
D40: ALQUILER | E40: 500 | G40: =+G39+E40-F40 -> 536.6
A41: 45362 | B41: EB01-3419 | C41: MARZO | D41: ALQUILER | F41: 500 | G41: =+G40+E41-F41 -> 36.6
A42: 45434 | B42: RII 2198 | C42: MARZO | D42: LUZ | F42: 31.6 | G42: =+G41+E42-F42 -> 5
A43: 45434 | B43: RII 2198 | C43: MARZO | D43: AGUA | F43: 5 | G43: =+G42+E43-F43 -> -9.2370556e-14
A44: 45412 | B44: POR COBRAR | C44: ABRIL | D44: LUZ | E44: 31.4 | G44: =+G43+E44-F44 -> 31.4
D45: AGUA | E45: 5 | G45: =+G44+E45-F45 -> 36.4
D46: ALQUILER | E46: 500 | G46: =+G45+E46-F46 -> 536.4
A47: 45434 | B47: RII 2198 | C47: ABRIL | D47: LUZ | F47: 31.4 | G47: =+G46+E47-F47 -> 505
A48: 45434 | B48: RII 2198 | C48: ABRIL | D48: AGUA | F48: 5 | G48: =+G47+E48-F48 -> 500
A49: 45434 | B49: EB01-3715 | C49: ABRIL | D49: ALQUILER | F49: 500 | G49: =+G48+E49-F49 -> 0
A50: 45443 | B50: POR COBRAR | C50: MAYO | D50: LUZ | E50: 28.6 | G50: =+G49+E50-F50 -> 28.6
D51: AGUA | E51: 5 | G51: =+G50+E51-F51 -> 33.6
D52: ALQUILER | E52: 500 | G52: =+G51+E52-F52 -> 533.6
A53: 45476 | B53: RII 2272 | C53: MAYO | D53: LUZ | F53: 28.6 | G53: =+G52+E53-F53 -> 505
A54: 45476 | B54: RII 2272 | C54: MAYO | D54: AGUA | F54: 5 | G54: =+G53+E54-F54 -> 500
A55: 45476 | B55: EB01-3920 | C55: MAYO | D55: ALQUILER | F55: 500 | G55: =+G54+E55-F55 -> 0
A56: 45473 | B56: POR COBRAR | C56: JUNIO | D56: LUZ | E56: 27.7 | G56: =+G55+E56-F56 -> 27.7
D57: AGUA | E57: 7 | G57: =+G56+E57-F57 -> 34.7
D58: ALQUILER | E58: 500 | G58: =+G57+E58-F58 -> 534.7
A59: 45476 | B59: EB01-3920 | C59: JUNIO | D59: ALQUILER | F59: 500 | G59: =+G58+E59-F59 -> 34.7
A60: 45504 | B60: RII 2335 | C60: JUNIO | D60: LUZ | F60: 27.7 | G60: =+G59+E60-F60 -> 7
A61: 45504 | B61: RII 2335 | C61: JUNIO | D61: AGUA | F61: 7 | G61: =+G60+E61-F61 -> 4.6185278e-14
A62: 45504 | B62: POR COBRAR | C62: JULIO | D62: LUZ | E62: 27.2 | G62: =+G61+E62-F62 -> 27.2 | I62: CHOQUEHUANCA DAVID
D63: AGUA | E63: 7 | G63: =+G62+E63-F63 -> 34.2 | H63: 2024 | I63: AGOSTO | J63: LUZ | K63: 27.3
D64: ALQUILER | E64: 500 | G64: =+G63+E64-F64 -> 534.2 | J64: AGUA | K64: 7
A65: 45504 | B65: EB01-4048 | C65: JULIO | D65: ALQUILER | F65: 500 | G65: =+G64+E65-F65 -> 34.2 | I65: SETIEMBRE | J65: LUZ | K65: 27.5
A66: 45546 | B66: RII 2405 | C66: JULIO | D66: LUZ | F66: 27.2 | G66: =+G65+E66-F66 -> 7 | J66: AGUA | K66: 5
A67: 45546 | B67: RII 2405 | C67: JULIO | D67: AGUA | F67: 7 | G67: =+G66+E67-F67 -> 4.6185278e-14 | J67: ALQUILER | K67: 180
A68: 45535 | B68: POR COBRAR | C68: AGOSTO | D68: LUZ | E68: 27.3 | G68: =+G67+E68-F68 -> 27.3 | K68: =SUM(K63:K67) -> 246.8
D69: AGUA | E69: 7 | G69: =+G68+E69-F69 -> 34.3
D70: ALQUILER | E70: 500 | G70: =+G69+E70-F70 -> 534.3
A71: 45535 | B71: EB01-4178 | C71: AGOSTO | D71: ALQUILER | F71: 420 | G71: =+G70+E71-F71 -> 114.3
A72: 45546 | B72: EB01-4227 | C72: AGOSTO | D72: ALQUILER | F72: 80 | G72: =+G71+E72-F72 -> 34.3
A73: 45586 | B73: RII 2475 | C73: AGOSTO | D73: LUZ | F73: 27.3 | G73: =+G72+E73-F73 -> 7
A74: 45586 | B74: RII 2475 | C74: AGOSTO | D74: AGUA | F74: 7 | G74: =+G73+E74-F74 -> 6.750156e-14
A75: 45565 | B75: POR COBRAR | C75: SETIEMBRE | D75: LUZ | E75: 27.5 | G75: =+G74+E75-F75 -> 27.5
D76: AGUA | E76: 5 | G76: =+G75+E76-F76 -> 32.5
D77: ALQUILER | E77: 500 | G77: =+G76+E77-F77 -> 532.5
A78: 45565 | B78: EB01-4329 | C78: SETIEMBRE | D78: ALQUILER | F78: 320 | G78: =+G77+E78-F78 -> 212.5
A79: 45586 | B79: RII 2475 | C79: SETIEMBRE | D79: LUZ | F79: 27.5 | G79: =+G78+E79-F79 -> 185
A80: 45586 | B80: RII 2475 | C80: SETIEMBRE | D80: AGUA | F80: 5 | G80: =+G79+E80-F80 -> 180
A81: 45596 | B81: EB01- | C81: SETIEMBRE | D81: ALQUILER | F81: 180 | G81: =+G80+E81-F81 -> 0
A82: 45596 | B82: POR COBRAR | C82: OCTUBRE | D82: LUZ | E82: 6.4 | G82: =+G81+E82-F82 -> 6.4
D83: AGUA | E83: 7 | G83: =+G82+E83-F83 -> 13.4
D84: ALQUILER | E84: 500 | G84: =+G83+E84-F84 -> 513.4
A85: 45596 | B85: EB01-4486 | C85: OCTUBRE | D85: ALQUILER | F85: 400 | G85: =+G84+E85-F85 -> 113.4
A86: 45630 | B86: EB01-4651 | C86: OCTUBRE | D86: ALQUILER | F86: 100 | G86: =+G85+E86-F86 -> 13.4
A87: 45630 | B87: RII 2549 | C87: OCTUBRE | D87: LUZ | F87: 6.4 | G87: =+G86+E87-F87 -> 7
A88: 45630 | B88: RII 2549 | C88: OCTUBRE | D88: AGUA | F88: 7 | G88: =+G87+E88-F88 -> -2.3092639e-14
A89: 45626 | B89: POR COBRAR | C89: NOVIEMBRE | D89: LUZ | E89: 7.5 | G89: =+G88+E89-F89 -> 7.5
D90: AGUA | E90: 7 | G90: =+G89+E90-F90 -> 14.5
D91: ALQUILER | E91: 500 | G91: =+G90+E91-F91 -> 514.5
A92: 45626 | B92: EB01-4635 | C92: NOVIEMBRE | D92: ALQUILER | F92: 500 | G92: =+G91+E92-F92 -> 14.5
A93: 45685 | B93: RII 2638 | C93: NOVIEMBRE | D93: LUZ | F93: 7.5 | G93: =+G92+E93-F93 -> 7
A94: 45685 | B94: RII 2638 | C94: NOVIEMBRE | D94: AGUA | F94: 7 | G94: =+G93+E94-F94 -> 0
A95: 45657 | B95: POR COBRAR | C95: DICIEMBRE | D95: LUZ | E95: 10.1 | G95: =+G94+E95-F95 -> 10.1
D96: AGUA | E96: 3 | G96: =+G95+E96-F96 -> 13.1
D97: ALQUILER | E97: 500 | G97: =+G96+E97-F97 -> 513.1
A98: 45657 | B98: EB01-4778 | C98: DICIEMBRE | D98: ALQUILER | F98: 500 | G98: =+G97+E98-F98 -> 13.1
A99: 45685 | B99: RII 2638 | C99: DICIEMBRE | D99: LUZ | F99: 10.1 | G99: =+G98+E99-F99 -> 3
A100: 45685 | B100: RII 2638 | C100: DICIEMBRE | D100: AGUA | F100: 3 | G100: =+G99+E100-F100 -> 2.3092639e-14
A101: 45688 | B101: POR COBRAR | C101: ENERO | D101: LUZ | E101: 8.3 | G101: =+G100+E101-F101 -> 8.3
D102: AGUA | E102: 3 | G102: =+G101+E102-F102 -> 11.3 | I102: CHOQUEHUANCA DAVID
...

Sheet MALLMA CONDORI LISBETH
A3: MALLMA CONDORI LIZBETH LUCIA
A5: FECHA | B5: DOCUMENTO | C5: PERIODO | D5: CONCEPTO | E5: POR COBRAR | F5: PAGADO | G5: SALDO POR COBRAR
A6: 42736 | B6: SALDO AL 2016 | G6: 1037.4
A7: 42739 | B7: 12014 | C7: A CUENTA DEL 2016 | F7: 292.5 | G7: =+G6+E7-F7 -> 744.9
A8: 42774 | B8: 12229 | C8: A CUENTA DEL 2016 | F8: 100 | G8: =+G7+E8-F8 -> 644.9
A9: 42782 | B9: 12267 | C9: A CUENTA DEL 2016 | F9: 100 | G9: =+G8+E9-F9 -> 544.9
A10: 42797 | B10: 12329 | C10: A CUENTA DEL 2016 | F10: 44.9 | G10: =+G9+E10-F10 -> 500
A11: 42766 | B11: 12189 | C11: A CUENTA DEL 2016 | F11: 500 | G11: =+G10+E11-F11 -> 0
A12: 42766 | B12: POR COBRAR | C12: ENERO | D12: LUZ | E12: 41.2 | G12: =+G11+E12-F12 -> 41.2
D13: AGUA | E13: 2.8 | G13: =+G12+E13-F13 -> 44
D14: ALQUILER | E14: 300 | G14: =+G13+E14-F14 -> 344
A15: 42797 | B15: 12329 | C15: ENERO | D15: LUZ | F15: 41.2 | G15: =+G14+E15-F15 -> 302.8
A16: 42797 | B16: 12329 | C16: ENERO | D16: AGUA | F16: 2.8 | G16: =+G15+E16-F16 -> 300
A17: 42800 | B17: 12332 | C17: ENERO | D17: ALQUILER | F17: 50 | G17: =+G16+E17-F17 -> 250
A18: 42800 | B18: 12348 | C18: ENERO | D18: ALQUILER | F18: 50 | G18: =+G17+E18-F18 -> 200
A19: 42802 | B19: 12369 | C19: ENERO | D19: ALQUILER | F19: 50 | G19: =+G18+E19-F19 -> 150
A20: 42804 | B20: 12376 | C20: ENERO | D20: ALQUILER | F20: 50 | G20: =+G19+E20-F20 -> 100
A21: 42808 | B21: 12399 | C21: ENERO | D21: ALQUILER | F21: 50 | G21: =+G20+E21-F21 -> 50
A22: 42808 | B22: 12402 | C22: ENERO | D22: ALQUILER | F22: 50 | G22: =+G21+E22-F22 -> 0
A23: 42794 | B23: POR COBRAR | C23: FEBRERO | D23: LUZ | E23: 41.7 | G23: =+G22+E23-F23 -> 41.7
D24: AGUA | E24: 2 | G24: =+G23+E24-F24 -> 43.7
D25: ALQUILER | E25: 300 | G25: =+G24+E25-F25 -> 343.7
A26: 42859 | B26: 12614 | C26: FEBRERO | D26: ALQUILER | F26: 300 | G26: =+G25+E26-F26 -> 43.7
A27: 42859 | B27: 12614 | C27: FEBRERO | D27: LUZ | F27: 41.7 | G27: =+G26+E27-F27 -> 2
A28: 42859 | B28: 12614 | C28: FEBRERO | D28: AGUA | F28: 2 | G28: =+G27+E28-F28 -> -1.4210855e-14
A29: 42825 | B29: POR COBRAR | C29: MARZO | D29: LUZ | E29: 39.7 | G29: =+G28+E29-F29 -> 39.7
D30: AGUA | E30: 2 | G30: =+G29+E30-F30 -> 41.7
D31: ALQUILER | E31: 300 | G31: =+G30+E31-F31 -> 341.7
A32: 42859 | B32: 12614 | C32: MARZO | D32: ALQUILER | F32: 6.3 | G32: =+G31+E32-F32 -> 335.4
A33: 42885 | B33: 12729 | C33: MARZO | D33: LUZ | F33: 39.7 | G33: =+G32+E33-F33 -> 295.7
A34: 42885 | B34: 12729 | C34: MARZO | D34: AGUA | F34: 2 | G34: =+G33+E34-F34 -> 293.7
A35: 42898 | B35: 12818 | C35: MARZO | D35: ALQUILER | F35: 293.7 | G35: =+G34+E35-F35 -> 0
A36: 42855 | B36: POR COBRAR | C36: ABRIL | D36: LUZ | E36: 41 | G36: =+G35+E36-F36 -> 41
D37: AGUA | E37: 2 | G37: =+G36+E37-F37 -> 43
D38: ALQUILER | E38: 300 | G38: =+G37+E38-F38 -> 343
A39: 42882 | B39: 12714 | C39: ABRIL | D39: ALQUILER | F39: 100 | G39: =+G38+E39-F39 -> 243
A40: 42898 | B40: 12818 | C40: ABRIL | D40: ALQUILER | F40: 1.3 | G40: =+G39+E40-F40 -> 241.7
A41: 42894 | B41: 12802 | C41: ABRIL | D41: ALQUILER | F41: 100 | G41: =+G40+E41-F41 -> 141.7
A42: 42916 | B42: 12901 | C42: ABRIL | D42: ALQUILER | F42: 98.7 | G42: =+G41+E42-F42 -> 43
A43: 42928 | B43: 12996 | C43: ABRIL | D43: LUZ | F43: 41 | G43: =+G42+E43-F43 -> 2
A44: 42928 | B44: 12996 | C44: ABRIL | D44: AGUA | F44: 2 | G44: =+G43+E44-F44 -> -1.4210855e-14
A45: 42886 | B45: POR COBRAR | D45: LUZ | E45: 38.7 | G45: =+G44+E45-F45 -> 38.7
D46: AGUA | E46: 2 | G46: =+G45+E46-F46 -> 40.7
D47: ALQUILER | E47: 300 | G47: =+G46+E47-F47 -> 340.7
A48: 42916 | B48: 12901 | C48: MAYO | D48: ALQUILER | F48: 111.3 | G48: =+G47+E48-F48 -> 229.4
A49: 42928 | B49: 12996 | C49: MAYO | D49: LUZ | F49: 38.7 | G49: =+G48+E49-F49 -> 190.7
A50: 42928 | B50: 12996 | C50: MAYO | D50: AGUA | F50: 2 | G50: =+G49+E50-F50 -> 188.7
A51: 42947 | B51: 13078 | C51: MAYO | D51: ALQUILER | F51: 188.7 | G51: =+G50+E51-F51 -> 0
A52: 42916 | B52: POR COBRAR | C52: JUNIO | D52: LUZ | E52: 38 | G52: =+G51+E52-F52 -> 38
D53: AGUA | E53: 2 | G53: =+G52+E53-F53 -> 40
D54: ALQUILER | E54: 300 | G54: =+G53+E54-F54 -> 340
A55: 42947 | B55: 13078 | C55: JUNIO | D55: ALQUILER | F55: 111.3 | G55: =+G54+E55-F55 -> 228.7
A56: 42984 | B56: 13403 | C56: JUNIO | D56: LUZ | F56: 38 | G56: =+G55+E56-F56 -> 190.7
A57: 42984 | B57: 13403 | C57: JUNIO | D57: AGUA | F57: 2 | G57: =+G56+E57-F57 -> 188.7
A58: 42996 | B58: 13488 | C58: JUNIO | D58: ALQUILER | F58: 188.7 | G58: =+G57+E58-F58 -> 0
A59: 42947 | B59: POR COBRAR | C59: JULIO | D59: LUZ | E59: 35.1 | G59: =+G58+E59-F59 -> 35.1
D60: AGUA | E60: 2 | G60: =+G59+E60-F60 -> 37.1
D61: ALQUILER | E61: 300 | G61: =+G60+E61-F61 -> 337.1
A62: 42984 | B62: 13403 | C62: JULIO | D62: LUZ | F62: 35.1 | G62: =+G61+E62-F62 -> 302
A63: 42984 | B63: 13403 | C63: JULIO | D63: AGUA | F63: 2 | G63: =+G62+E63-F63 -> 300
A64: 42979 | B64: 13355 | C64: JULIO | D64: ALQUILER | F64: 150 | G64: =+G63+E64-F64 -> 150
A65: 42996 | B65: 13488 | C65: JULIO | D65: ALQUILER | F65: 11.3 | G65: =+G64+E65-F65 -> 138.7
A66: 43014 | B66: 13609 | C66: JULIO | D66: ALQUILER | F66: 138.7 | G66: =+G65+E66-F66 -> 0
A67: 42978 | B67: POR COBRAR | C67: AGOSTO | D67: LUZ | E67: 37.7 | G67: =+G66+E67-F67 -> 37.7
D68: AGUA | E68: 2 | G68: =+G67+E68-F68 -> 39.7
D69: ALQUILER | E69: 300 | G69: =+G68+E69-F69 -> 339.7
A70: 43008 | B70: 13553 | C70: AGOSTO | D70: ALQUILER | F70: 190 | G70: =+G69+E70-F70 -> 149.7
A71: 43025 | B71: 13640 | C71: AGOSTO | D71: ALQUILER | F71: 100 | G71: =+G70+E71-F71 -> 49.7
A72: 43039 | B72: 13724 | C72: AGOSTO | D72: ALQUILER | F72: 10 | G72: =+G71+E72-F72 -> 39.7
A73: 43034 | B73: 13695 | C73: AGOSTO | D73: LUZ | F73: 37.7 | G73: =+G72+E73-F73 -> 2
A74: 43034 | B74: 13695 | C74: AGOSTO | D74: AGUA | F74: 2 | G74: =+G73+E74-F74 -> -1.4210855e-14
A75: 43008 | B75: POR COBRAR | C75: SEPTIEMBRE | D75: LUZ | E75: 32.9 | G75: =+G74+E75-F75 -> 32.9
D76: AGUA | E76: 2 | G76: =+G75+E76-F76 -> 34.9
D77: ALQUILER | E77: 300 | G77: =+G76+E77-F77 -> 334.9
A78: 43039 | B78: 13724 | C78: SEPTIEMBRE | D78: ALQUILER | F78: 195 | G78: =+G77+E78-F78 -> 139.9
A79: 43047 | B79: 13772 | C79: SEPTIEMBRE | D79: ALQUILER | F79: 95 | G79: =+G78+E79-F79 -> 44.9
A80: 43049 | B80: 13781 | C80: SEPTIEMBRE | D80: ALQUILER | F80: 10 | G80: =+G79+E80-F80 -> 34.9
A81: 43034 | B81: 13695 | C81: SEPTIEMBRE | D81: LUZ | F81: 32.9 | G81: =+G80+E81-F81 -> 2
A82: 43034 | B82: 13695 | C82: SEPTIEMBRE | D82: AGUA | F82: 2 | G82: =+G81+E82-F82 -> -2.1316282e-14
A83: 43039 | B83: POR COBRAR | C83: OCTUBRE | D83: LUZ | E83: 32.7 | G83: =+G82+E83-F83 -> 32.7
D84: AGUA | E84: 2 | G84: =+G83+E84-F84 -> 34.7
D85: ALQUILER | E85: 300 | G85: =+G84+E85-F85 -> 334.7
A86: 43049 | B86: 13781 | C86: OCTUBRE | D86: ALQUILER | F86: 90 | G86: =+G85+E86-F86 -> 244.7
A87: 43057 | C87: OCTUBRE | D87: ALQUILER | F87: 100 | G87: =+G86+E87-F87 -> 144.7
A88: 43069 | B88: 13862 | C88: OCTUBRE | D88: ALQUILER | F88: 50 | G88: =+G87+E88-F88 -> 94.7
A89: 43096 | B89: 13978 | C89: OCTUBRE | D89: LUZ | F89: 32.7 | G89: =+G88+E89-F89 -> 62
A90: 43096 | B90: 13978 | C90: OCTUBRE | D90: AGUA | F90: 2 | G90: =+G89+E90-F90 -> 60
A91: 43464 | B91: 14012 | C91: OCTUBRE | D91: ALQUILER | F91: 60 | G91: =+G90+E91-F91 -> 0
A92: 43069 | B92: POR COBRAR | C92: NOVIEMBRE | D92: LUZ | E92: 35 | G92: =+G91+E92-F92 -> 35
D93: AGUA | E93: 2 | G93: =+G92+E93-F93 -> 37
D94: ALQUILER | E94: 300 | G94: =+G93+E94-F94 -> 337
D95: PARRILLA | E95: 30 | G95: =+G94+E95-F95 -> 367
A96: 43461 | B96: 13978 | C96: NOVIEMBRE | D96: LUZ | F96: 35 | G96: =+G95+E96-F96 -> 332
A97: 43461 | B97: 13978 | C97: NOVIEMBRE | D97: AGUA | F97: 2 | G97: =+G96+E97-F97 -> 330
A98: 43464 | B98: 14012 | C98: NOVIEMBRE | D98: ALQUILER | F98: 240 | G98: =+G97+E98-F98 -> 90
A99: 43116 | B99: 14076 | C99: NOVIEMBRE | D99: ALQUILER | F99: 60 | G99: =+G98+E99-F99 -> 30
A100: 43998 | B100: B001-0001399 | C100: NOVIEMBRE | D100: PARRILLA | F100: 30 | G100: =+G99+E100-F100 -> 0
A101: 43100 | B101: POR COBRAR | C101: DICIEMBRE | D101: LUZ | E101: 54.7 | G101: =+G100+E101-F101 -> 54.7
D102: AGUA | E102: 2 | G102: =+G101+E102-F102 -> 56.7
D103: ALQUILER | E103: 300 | G103: =+G102+E103-F103 -> 356.7
...

Sheet MAYHUASCA DORIS
B3: MAYHUASCA BASTIDAS DORIS
A5: FECHA | B5: DOCUMENTO | C5: PERIODO | D5: CONCEPTO | E5: POR COBRAR | F5: PAGADO | G5: SALDO POR COBRAR
A6: 42736 | B6: SALDO AL 2016 | G6: 438.1
A7: 42737 | B7: 12000 | C7: A CUENTA DEL 2016 | F7: 41.5 | G7: =+G6+E7-F7 -> 396.6
A8: 42744 | B8: 12052 | C8: A CUENTA DEL 2016 | F8: 300 | G8: =+G7+E8-F8 -> 96.6
A9: 42752 | B9: 12106 | C9: A CUENTA DEL 2016 | F9: 16.6 | G9: =+G8+E9-F9 -> 80
A10: 42830 | B10: 12489 | C10: CANCELACION DEL 2016 | F10: 80 | G10: =+G9+E10-F10 -> 0
A11: 42766 | B11: POR COBRAR | C11: ENERO | D11: LUZ | E11: 13.5 | G11: =+G10+E11-F11 -> 13.5
D12: AGUA | E12: 2.8 | G12: =+G11+E12-F12 -> 16.3
D13: ALQUILER | E13: 300 | G13: =+G12+E13-F13 -> 316.3
A14: 42800 | B14: 12343 | C14: ENERO | D14: LUZ | F14: 13.5 | G14: =+G13+E14-F14 -> 302.8
A15: 42800 | B15: 12343 | C15: ENERO | D15: AGUA | F15: 2.8 | G15: =+G14+E15-F15 -> 300
A16: 42779 | B16: 12253 | C16: ENERO | D16: ALQUILER | F16: 300 | G16: =+G15+E16-F16 -> 0
A17: 42794 | B17: POR COBRAR | C17: FEBRERO | D17: LUZ | E17: 13 | G17: =+G16+E17-F17 -> 13
D18: AGUA | E18: 2 | G18: =+G17+E18-F18 -> 15
D19: ALQUILER | E19: 300 | G19: =+G18+E19-F19 -> 315
A20: 42800 | B20: 12343 | C20: FEBRERO | D20: ALQUILER | F20: 300 | G20: =+G19+E20-F20 -> 15
A21: 42817 | B21: 12437 | C21: FEBRERO | D21: LUZ | F21: 13 | G21: =+G20+E21-F21 -> 2
A22: 42817 | B22: 12437 | C22: FEBRERO | D22: AGUA | F22: 2 | G22: =+G21+E22-F22 -> 0
A23: 42825 | B23: POR COBRAR | C23: MARZO | D23: LUZ | E23: 12 | G23: =+G22+E23-F23 -> 12
D24: AGUA | E24: 2 | G24: =+G23+E24-F24 -> 14
D25: ALQUILER | E25: 300 | G25: =+G24+E25-F25 -> 314
A26: 42830 | B26: 12489 | C26: MARZO | D26: ALQUILER | F26: 300 | G26: =+G25+E26-F26 -> 14
A27: 42846 | B27: 12566 | C27: MARZO | D27: LUZ | F27: 12 | G27: =+G26+E27-F27 -> 2
A28: 42846 | B28: 12566 | C28: MARZO | D28: AGUA | F28: 2 | G28: =+G27+E28-F28 -> 0
A29: 42855 | B29: POR COBRAR | C29: ABRIL | D29: LUZ | E29: 13 | G29: =+G28+E29-F29 -> 13
D30: AGUA | E30: 2 | G30: =+G29+E30-F30 -> 15
D31: ALQUILER | E31: 300 | G31: =+G30+E31-F31 -> 315
A32: 42863 | B32: 12653 | C32: ABRIL | D32: ALQUILER | F32: 300 | G32: =+G31+E32-F32 -> 15
A33: 42881 | B33: 12713 | C33: ABRIL | D33: LUZ | F33: 13 | G33: =+G32+E33-F33 -> 2
A34: 42881 | B34: 12713 | C34: ABRIL | D34: AGUA | F34: 2 | G34: =+G33+E34-F34 -> 0
A35: 42886 | B35: POR COBRAR | C35: MAYO | D35: LUZ | E35: 13 | G35: =+G34+E35-F35 -> 13
D36: AGUA | E36: 2 | G36: =+G35+E36-F36 -> 15
D37: ALQUILER | E37: 300 | G37: =+G36+E37-F37 -> 315
A38: 42891 | B38: 12780 | C38: MAYO | D38: ALQUILER | F38: 300 | G38: =+G37+E38-F38 -> 15
A39: 42921 | B39: 12955 | C39: MAYO | D39: LUZ | F39: 13 | G39: =+G38+E39-F39 -> 2
A40: 42921 | B40: 12955 | C40: MAYO | D40: AGUA | F40: 2 | G40: =+G39+E40-F40 -> 0
A41: 42946 | B41: POR COBRAR | C41: JUNIO | D41: LUZ | E41: 12.5 | G41: =+G40+E41-F41 -> 12.5
D42: AGUA | E42: 2 | G42: =+G41+E42-F42 -> 14.5
D43: ALQUILER | E43: 300 | G43: =+G42+E43-F43 -> 314.5
A44: 42921 | B44: 12955 | C44: JUNIO | D44: ALQUILER | F44: 300 | G44: =+G43+E44-F44 -> 14.5
A45: 42954 | B45: 13233 | D45: LUZ | F45: 12.5 | G45: =+G44+E45-F45 -> 2
A46: 42954 | B46: 13233 | C46: JUNIO | D46: AGUA | F46: 2 | G46: =+G45+E46-F46 -> 0
A47: 42947 | B47: POR COBRAR | C47: JULIO | D47: LUZ | E47: 13 | G47: =+G46+E47-F47 -> 13
D48: AGUA | E48: 2 | G48: =+G47+E48-F48 -> 15
D49: ALQUILER | E49: 300 | G49: =+G48+E49-F49 -> 315
A50: 42954 | B50: 13233 | C50: JULIO | D50: ALQUILER | F50: 300 | G50: =+G49+E50-F50 -> 15
A51: 42975 | B51: 13340 | C51: JULIO | D51: LUZ | F51: 13 | G51: =+G50+E51-F51 -> 2
A52: 42975 | B52: 13340 | C52: JULIO | D52: AGUA | F52: 2 | G52: =+G51+E52-F52 -> 0
A53: 42978 | B53: POR COBRAR | C53: AGOSTO | D53: LUZ | E53: 13 | G53: =+G52+E53-F53 -> 13
D54: AGUA | E54: 2 | G54: =+G53+E54-F54 -> 15
D55: ALQUILER | E55: 300 | G55: =+G54+E55-F55 -> 315
A56: 42985 | B56: 13417 | C56: AGOSTO | D56: ALQUILER | F56: 300 | G56: =+G55+E56-F56 -> 15
A57: 43003 | B57: 13522 | C57: AGOSTO | D57: LUZ | F57: 13 | G57: =+G56+E57-F57 -> 2
A58: 43003 | B58: 13522 | C58: AGOSTO | D58: AGUA | F58: 2 | G58: =+G57+E58-F58 -> 0
A59: 43008 | B59: POR COBRAR | C59: SEPTIEMBRE | D59: LUZ | E59: 7.8 | G59: =+G58+E59-F59 -> 7.8
D60: AGUA | E60: 2 | G60: =+G59+E60-F60 -> 9.8
D61: ALQUILER | E61: 300 | G61: =+G60+E61-F61 -> 309.8
A62: 43010 | B62: 13581 | C62: SEPTIEMBRE | D62: ALQUILER | F62: 300 | G62: =+G61+E62-F62 -> 9.8
A63: 43031 | B63: 13678 | C63: SEPTIEMBRE | D63: LUZ | F63: 7.8 | G63: =+G62+E63-F63 -> 2
A64: 43031 | B64: 13678 | C64: SEPTIEMBRE | D64: AGUA | F64: 1.3 | G64: =+G63+E64-F64 -> 0.7
A65: 43062 | B65: 13818 | C65: SEPTIEMBRE | D65: AGUA | F65: 0.7 | G65: =+G64+E65-F65 -> 1.1546319e-14
A66: 43039 | B66: POR COBRAR | C66: OCTUBRE | D66: LUZ | E66: 8 | G66: =+G65+E66-F66 -> 8
D67: AGUA | E67: 2 | G67: =+G66+E67-F67 -> 10
D68: ALQUILER | E68: 300 | G68: =+G67+E68-F68 -> 310
A69: 43046 | B69: 13765 | C69: OCTUBRE | D69: ALQUILER | F69: 300 | G69: =+G68+E69-F69 -> 10
A70: 43062 | B70: 13818 | C70: OCTUBRE | D70: LUZ | F70: 8 | G70: =+G69+E70-F70 -> 2
A71: 43062 | B71: 13818 | C71: OCTUBRE | D71: AGUA | F71: 2 | G71: =+G70+E71-F71 -> 0
A72: 43069 | B72: POR COBRAR | C72: NOVIEMBRE | D72: LUZ | E72: 8.2 | G72: =+G71+E72-F72 -> 8.2
D73: AGUA | E73: 2 | G73: =+G72+E73-F73 -> 10.2
D74: ALQUILER | E74: 300 | G74: =+G73+E74-F74 -> 310.2
A75: 43073 | B75: 13895 | C75: NOVIEMBRE | D75: ALQUILER | F75: 300 | G75: =+G74+E75-F75 -> 10.2
A76: 43463 | B76: 13993 | C76: NOVIEMBRE | D76: LUZ | F76: 8.2 | G76: =+G75+E76-F76 -> 2
A77: 43463 | B77: 13993 | C77: NOVIEMBRE | D77: AGUA | F77: 2 | G77: =+G76+E77-F77 -> -1.0658141e-14
A78: 43100 | B78: POR COBRAR | C78: DICIEMBRE | D78: LUZ | E78: 8.9 | G78: =+G77+E78-F78 -> 8.9
D79: AGUA | E79: 2 | G79: =+G78+E79-F79 -> 10.9
D80: ALQUILER | E80: 300 | G80: =+G79+E80-F80 -> 310.9
A81: 43098 | B81: 13993 | C81: DICIEMBRE | D81: ALQUILER | F81: 300 | G81: =+G80+E81-F81 -> 10.9
A82: 43118 | B82: 14094 | C82: DICIEMBRE | D82: LUZ | F82: 8.9 | G82: =+G81+E82-F82 -> 2
A83: 43118 | B83: 14094 | C83: DICIEMBRE | D83: AGUA | F83: 2 | G83: =+G82+E83-F83 -> -2.3092639e-14
A84: 43131 | B84: POR COBRAR | C84: ENERO | D84: LUZ | E84: 8 | G84: =+G83+E84-F84 -> 8
D85: AGUA | E85: 2 | G85: =+G84+E85-F85 -> 10
D86: ALQUILER | E86: 300 | G86: =+G85+E86-F86 -> 310
A87: 43136 | C87: ENERO | D87: ALQUILER | F87: 300 | G87: =+G86+E87-F87 -> 10
A88: 43159 | B88: 14263 | C88: ENERO | D88: LUZ | F88: 8 | G88: =+G87+E88-F88 -> 2
A89: 43159 | B89: 14263 | C89: ENERO | D89: AGUA | F89: 2 | G89: =+G88+E89-F89 -> 0
A90: 43159 | B90: POR COBRAR | C90: FEBRERO | D90: LUZ | E90: 9.9 | G90: =+G89+E90-F90 -> 9.9
D91: AGUA | E91: 2 | G91: =+G90+E91-F91 -> 11.9
D92: ALQUILER | E92: 300 | G92: =+G91+E92-F92 -> 311.9
A93: 43159 | B93: 14263 | C93: FEBRERO | D93: ALQUILER | F93: 300 | G93: =+G92+E93-F93 -> 11.9
A94: 43192 | B94: 14428 | C94: FEBRERO | D94: LUZ | F94: 9.9 | G94: =+G93+E94-F94 -> 2
A95: 43192 | B95: 14428 | C95: FEBRERO | D95: AGUA | F95: 2 | G95: =+G94+E95-F95 -> -2.3092639e-14
A96: 43190 | B96: POR COBRAR | C96: MARZO | D96: LUZ | E96: 9.5 | G96: =+G95+E96-F96 -> 9.5
D97: AGUA | E97: 2 | G97: =+G96+E97-F97 -> 11.5
D98: ALQUILER | E98: 300 | G98: =+G97+E98-F98 -> 311.5
A99: 43192 | B99: 14428 | C99: MARZO | D99: ALQUILER | F99: 300 | G99: =+G98+E99-F99 -> 11.5
A100: 43208 | B100: 14497 | C100: MARZO | D100: LUZ | F100: 9.5 | G100: =+G99+E100-F100 -> 2
A101: 43208 | B101: 14497 | C101: MARZO | D101: AGUA | F101: 2 | G101: =+G100+E101-F101 -> 0
A102: 43220 | B102: POR COBRAR | C102: ABRIL | D102: LUZ | E102: 9.8 | G102: =+G101+E102-F102 -> 9.8
D103: AGUA | E103: 2 | G103: =+G102+E103-F103 -> 11.8
...

Sheet MIRANDA FELICITA
B3: MIRANDA CACERES FELICITA
A5: FECHA | B5: DOCUMENTO | C5: PERIODO | D5: CONCEPTO | E5: POR COBRAR | F5: PAGADO | G5: SALDO POR COBRAR
A6: 42736 | B6: SALDO AL 2016 | G6: 273.3
A7: 42738 | B7: 12008 | C7: A CUENTA DEL 2016 | F7: 150 | G7: =+G6+E7-F7 -> 123.3
A8: 42751 | B8: 12091 | C8: A CUENTA DEL 2016 | F8: 43.3 | G8: =+G7+E8-F8 -> 80
A9: 42831 | B9: 12488 | C9: A CUENTA DEL 2016 | F9: 10 | G9: =+G8+E9-F9 -> 70
A10: 42858 | B10: 12606 | C10: A CUENTA DEL 2016 | F10: 10 | G10: =+G9+E10-F10 -> 60
A11: 42919 | B11: 12939 | C11: A CUENTA DEL 2016 | F11: 10 | G11: =+G10+E11-F11 -> 50
A12: 42947 | B12: 13072 | C12: A CUENTA DEL 2016 | F12: 10 | G12: =+G11+E12-F12 -> 40
A13: 43073 | B13: 13902 | C13: A CUENTA DEL 2016 | F13: 20 | G13: =+G12+E13-F13 -> 20
A14: 43098 | B14: 13999 | C14: CANCELACION DEL 2016 | F14: 20 | G14: =+G13+E14-F14 -> 0
A15: 42766 | B15: POR COBRAR | C15: ENERO | D15: LUZ | E15: 41.3 | G15: =+G14+E15-F15 -> 41.3
D16: AGUA | E16: 2.8 | G16: =+G15+E16-F16 -> 44.1
D17: ALQUILER | E17: 210 | G17: =+G16+E17-F17 -> 254.1
A18: 42800 | B18: 12345 | C18: ENERO | D18: ALQUILER | F18: 100 | G18: =+G17+E18-F18 -> 154.1
A19: 42786 | B19: 12279 | C19: ENERO | D19: LUZ | F19: 41.3 | G19: =+G18+E19-F19 -> 112.8
A20: 42786 | B20: 12779 | C20: ENERO | D20: AGUA | F20: 2.8 | G20: =+G19+E20-F20 -> 110
A21: 42786 | B21: 12779 | C21: ENERO | D21: ALQUILER | F21: 50 | G21: =+G20+E21-F21 -> 60
A22: 42751 | B22: 12091 | C22: ENERO | D22: ALQUILER | F22: 60 | G22: =+G21+E22-F22 -> 0
A23: 42794 | B23: POR COBRAR | C23: FEBRERO | D23: LUZ | E23: 50.6 | G23: =+G22+E23-F23 -> 50.6
D24: AGUA | E24: 2 | G24: =+G23+E24-F24 -> 52.6
D25: ALQUILER | E25: 210 | G25: =+G24+E25-F25 -> 262.6
A26: 42808 | B26: 12401 | C26: FEBRERO | D26: ALQUILER | F26: 100 | G26: =+G25+E26-F26 -> 162.6
A27: 42821 | B27: 12446 | C27: FEBRERO | D27: LUZ | F27: 50.6 | G27: =+G26+E27-F27 -> 112
A28: 42821 | B28: 12446 | C28: FEBRERO | D28: AGUA | F28: 2 | G28: =+G27+E28-F28 -> 110
A29: 42814 | B29: 12416 | C29: FEBRERO | D29: ALQUILER | F29: 110 | G29: =+G28+E29-F29 -> 0
A30: 42825 | B30: POR COBRAR | C30: MARZO | D30: LUZ | E30: 48.2 | G30: =+G29+E30-F30 -> 48.2
D31: AGUA | E31: 2 | G31: =+G30+E31-F31 -> 50.2
D32: ALQUILER | E32: 210 | G32: =+G31+E32-F32 -> 260.2
A33: 42821 | B33: 12446 | C33: MARZO | D33: ALQUILER | F33: 60 | G33: =+G32+E33-F33 -> 200.2
A34: 42828 | B34: 12472 | C34: MARZO | D34: ALQUILER | F34: 100 | G34: =+G33+E34-F34 -> 100.2
A35: 42831 | B35: 12488 | C35: MARZO | D35: ALQUILER | F35: 50 | G35: =+G34+E35-F35 -> 50.2
A36: 42844 | B36: 12556 | C36: MARZO | D36: LUZ | F36: 48.2 | G36: =+G35+E36-F36 -> 2
A37: 42844 | B37: 12556 | C37: MARZO | D37: AGUA | F37: 2 | G37: =+G36+E37-F37 -> -1.4210855e-14
A38: 42855 | B38: POR COBRAR | C38: ABRIL | D38: LUZ | E38: 49.6 | G38: =+G37+E38-F38 -> 49.6
D39: AGUA | E39: 2 | G39: =+G38+E39-F39 -> 51.6
D40: ALQUILER | E40: 210 | G40: =+G39+E40-F40 -> 261.6
A41: 42844 | B41: 12556 | C41: ABRIL | D41: ALQUILER | F41: 60 | G41: =+G40+E41-F41 -> 201.6
A42: 42858 | B42: 12606 | C42: ABRIL | D42: ALQUILER | F42: 150 | G42: =+G41+E42-F42 -> 51.6
A43: 42877 | B43: 12703 | C43: ABRIL | D43: LUZ | F43: 49.6 | G43: =+G42+E43-F43 -> 2
A44: 42877 | B44: 12703 | C44: ABRIL | D44: AGUA | F44: 2 | G44: =+G43+E44-F44 -> -3.5527137e-14
A45: 42886 | B45: POR COBRAR | C45: MAYO | D45: LUZ | E45: 36.8 | G45: =+G44+E45-F45 -> 36.8
D46: AGUA | E46: 2 | G46: =+G45+E46-F46 -> 38.8
D47: ALQUILER | E47: 210 | G47: =+G46+E47-F47 -> 248.8
A48: 42877 | B48: 12703 | C48: MAYO | D48: ALQUILER | F48: 60 | G48: =+G47+E48-F48 -> 188.8
A49: 42885 | B49: 12746 | C49: MAYO | D49: ALQUILER | F49: 150 | G49: =+G48+E49-F49 -> 38.8
A50: 42906 | B50: 13113 | C50: MAYO | D50: LUZ | F50: 36.8 | G50: =+G49+E50-F50 -> 2
A51: 42906 | B51: 13113 | C51: MAYO | D51: AGUA | F51: 2 | G51: =+G50+E51-F51 -> -4.2632564e-14
A52: 42916 | B52: POR COBRAR | C52: JUNIO | D52: LUZ | E52: 35.8 | G52: =+G51+E52-F52 -> 35.8
D53: AGUA | E53: 2 | G53: =+G52+E53-F53 -> 37.8
D54: ALQUILER | E54: 210 | G54: =+G53+E54-F54 -> 247.8
A55: 42919 | B55: 12939 | C55: JUNIO | D55: ALQUILER | F55: 100 | G55: =+G54+E55-F55 -> 147.8
A56: 42906 | B56: 13113 | C56: JUNIO | D56: ALQUILER | F56: 110 | G56: =+G55+E56-F56 -> 37.8
A57: 42934 | B57: 13030 | C57: JUNIO | D57: LUZ | F57: 35.8 | G57: =+G56+E57-F57 -> 2
A58: 42934 | B58: 13030 | C58: JUNIO | D58: AGUA | F58: 2 | G58: =+G57+E58-F58 -> -4.2632564e-14
A59: 42947 | B59: POR COBRAR | C59: JULIO | D59: LUZ | E59: 33.4 | G59: =+G58+E59-F59 -> 33.4
D60: AGUA | E60: 2 | G60: =+G59+E60-F60 -> 35.4
D61: ALQUILER | E61: 210 | G61: =+G60+E61-F61 -> 245.4
A62: 42934 | B62: 13030 | C62: JULIO | D62: ALQUILER | F62: 110 | G62: =+G61+E62-F62 -> 135.4
A63: 42947 | B63: 13072 | C63: JULIO | D63: ALQUILER | F63: 100 | G63: =+G62+E63-F63 -> 35.4
A64: 42972 | B64: 13331 | C64: JULIO | D64: LUZ | F64: 33.4 | G64: =+G63+E64-F64 -> 2
A65: 42972 | B65: 13331 | C65: JULIO | D65: AGUA | F65: 2 | G65: =+G64+E65-F65 -> -4.9737992e-14
A66: 42978 | B66: POR COBRAR | C66: AGOSTO | D66: LUZ | E66: 33.4 | G66: =+G65+E66-F66 -> 33.4
D67: AGUA | E67: 2 | G67: =+G66+E67-F67 -> 35.4
D68: ALQUILER | E68: 210 | G68: =+G67+E68-F68 -> 245.4
A69: 42968 | B69: 13291 | C69: AGOSTO | D69: ALQUILER | F69: 150 | G69: =+G68+E69-F69 -> 95.4
A70: 42987 | B70: 13432 | C70: AGOSTO | D70: ALQUILER | F70: 60 | G70: =+G69+E70-F70 -> 35.4
A71: 42996 | B71: 13490 | C71: AGOSTO | D71: LUZ | F71: 33.4 | G71: =+G70+E71-F71 -> 2
A72: 42996 | B72: 13490 | C72: AGOSTO | D72: AGUA | F72: 2 | G72: =+G71+E72-F72 -> -4.9737992e-14
A73: 43008 | B73: POR COBRAR | C73: SEPIEMBRE | D73: LUZ | E73: 30.8 | G73: =+G72+E73-F73 -> 30.8
D74: AGUA | E74: 2 | G74: =+G73+E74-F74 -> 32.8
D75: ALQUILER | E75: 210 | G75: =+G74+E75-F75 -> 242.8
A76: 42996 | B76: 13490 | C76: SEPIEMBRE | D76: ALQUILER | F76: 70 | G76: =+G75+E76-F76 -> 172.8
A77: 43011 | B77: 13590 | C77: SEPIEMBRE | D77: ALQUILER | F77: 140 | G77: =+G76+E77-F77 -> 32.8
A78: 43027 | B78: 13658 | C78: SEPIEMBRE | D78: LUZ | F78: 30.8 | G78: =+G77+E78-F78 -> 2
A79: 43027 | B79: 13658 | C79: SEPIEMBRE | D79: AGUA | F79: 1.3 | G79: =+G78+E79-F79 -> 0.7
A80: 43038 | B80: 13714 | C80: SEPIEMBRE | D80: AGUA | F80: 0.7 | G80: =+G79+E80-F80 -> -4.6185278e-14
A81: 43039 | B81: POR COBRAR | C81: OCTUBRE | D81: LUZ | E81: 30.8 | G81: =+G80+E81-F81 -> 30.8
D82: AGUA | E82: 2 | G82: =+G81+E82-F82 -> 32.8
D83: ALQUILER | E83: 210 | G83: =+G82+E83-F83 -> 242.8
A84: 43027 | B84: 13658 | C84: OCTUBRE | D84: ALQUILER | F84: 100 | G84: =+G83+E84-F84 -> 142.8
A85: 43038 | B85: 13714 | C85: OCTUBRE | D85: ALQUILER | F85: 110 | G85: =+G84+E85-F85 -> 32.8
A86: 43062 | B86: 13821 | C86: OCTUBRE | D86: LUZ | F86: 30.8 | G86: =+G85+E86-F86 -> 2
A87: 43062 | B87: 13821 | C87: OCTUBRE | D87: AGUA | F87: 2 | G87: =+G86+E87-F87 -> -4.6185278e-14
A88: 43069 | B88: POR COBRAR | C88: NOVIEMBRE | D88: LUZ | E88: 32.9 | G88: =+G87+E88-F88 -> 32.9
D89: AGUA | E89: 2 | G89: =+G88+E89-F89 -> 34.9
D90: ALQUILER | E90: 210 | G90: =+G89+E90-F90 -> 244.9
A91: 43068 | B91: 13861 | C91: NOVIEMBRE | D91: ALQUILER | F91: 210 | G91: =+G90+E91-F91 -> 34.9
A92: 43087 | B92: 13951 | C92: NOVIEMBRE | D92: AGUA | F92: 2 | G92: =+G91+E92-F92 -> 32.9
A93: 43087 | B93: 13951 | C93: NOVIEMBRE | D93: LUZ | F93: 32.9 | G93: =+G92+E93-F93 -> 0
A94: 43100 | B94: POR COBRAR | C94: DICIEMBRE | D94: LUZ | E94: 35.8 | G94: =+G93+E94-F94 -> 35.8
D95: AGUA | E95: 2 | G95: =+G94+E95-F95 -> 37.8
D96: ALQUILER | E96: 210 | G96: =+G95+E96-F96 -> 247.8
A97: 43098 | B97: 13999 | C97: DICIEMBRE | D97: ALQUILER | F97: 210 | G97: =+G96+E97-F97 -> 37.8
A98: 43118 | B98: 14085 | C98: DICIEMBRE | D98: LUZ | F98: 35.8 | G98: =+G97+E98-F98 -> 2
A99: 43118 | B99: 14085 | C99: DICIEMBRE | D99: AGUA | F99: 2 | G99: =+G98+E99-F99 -> 1.4210855e-14
A100: 43131 | B100: POR COBRAR | C100: ENERO | D100: LUZ | E100: 31.8 | G100: =+G99+E100-F100 -> 31.8
D101: AGUA | E101: 2 | G101: =+G100+E101-F101 -> 33.8
D102: ALQUILER | E102: 210 | G102: =+G101+E102-F102 -> 243.8
A103: 43143 | B103: 14208 | C103: ENERO | D103: ALQUILER | F103: 210 | G103: =+G102+E103-F103 -> 33.8
...

Sheet MUJICA SANDRA 
B3: MUJICA PALOMINO SANDRA
A5: FECHA | B5: DOCUMENTO | C5: PERIODO | D5: CONCEPTO | E5: POR COBRAR | F5: PAGADO | G5: SALDO POR COBRAR
A6: 42736 | B6: SALDO AL 2016 | G6: 674.2
A7: 42795 | B7: 12309 | C7: A CUENTA DEL 2016 | F7: 370 | G7: =+G6+E7-F7 -> 304.2
A8: 42797 | B8: 12328 | C8: A CUENTA DEL 2016 | F8: 4.2 | G8: =+G7+E8-F8 -> 300
A9: 42766 | B9: 12173 | C9: A CUENTA DEL 2016 | F9: 300 | G9: =+G8+E9-F9 -> 0
A10: 42766 | B10: POR COBRAR | C10: ENERO | D10: LUZ | E10: 34.5 | G10: =+G9+E10-F10 -> 34.5
D11: AGUA | E11: 2.8 | G11: =+G10+E11-F11 -> 37.3
D12: ALQUILER | E12: 300 | G12: =+G11+E12-F12 -> 337.3
A13: 42795 | B13: 12309 | C13: ENERO | D13: ALQUILER | F13: 300 | G13: =+G12+E13-F13 -> 37.3
A14: 42797 | B14: 12328 | C14: ENERO | D14: LUZ | F14: 34.5 | G14: =+G13+E14-F14 -> 2.8
D15: AGUA | F15: 2.8 | G15: =+G14+E15-F15 -> 1.1546319e-14
A16: 42794 | B16: POR COBRAR | C16: FEBRERO | D16: LUZ | E16: 28.5 | G16: =+G15+E16-F16 -> 28.5
D17: AGUA | E17: 2 | G17: =+G16+E17-F17 -> 30.5
D18: ALQUILER | E18: 300 | G18: =+G17+E18-F18 -> 330.5
A19: 42800 | B19: 12334 | C19: FEBRERO | D19: ALQUILER | F19: 20 | G19: =+G18+E19-F19 -> 310.5
A20: 42800 | B20: 12349 | C20: FEBRERO | D20: ALQUILER | F20: 20 | G20: =+G19+E20-F20 -> 290.5
A21: 42802 | B21: 12366 | C21: FEBRERO | D21: ALQUILER | F21: 20 | G21: =+G20+E21-F21 -> 270.5
A22: 42804 | B22: 12375 | C22: FEBRERO | D22: ALQUILER | F22: 20 | G22: =+G21+E22-F22 -> 250.5
A23: 42808 | B23: 12400 | C23: FEBRERO | D23: ALQUILER | F23: 20 | G23: =+G22+E23-F23 -> 230.5
A24: 42831 | B24: 12492 | C24: FEBRERO | D24: ALQUILER | F24: 200 | G24: =+G23+E24-F24 -> 30.5
A25: 42831 | B25: 12493 | C25: FEBRERO | D25: LUZ | F25: 20 | G25: =+G24+E25-F25 -> 10.5
A26: 42927 | B26: 12986 | C26: FEBRERO | D26: LUZ | F26: 8.5 | G26: =+G25+E26-F26 -> 2
A27: 42927 | B27: 12986 | C27: FEBRERO | D27: AGUA | F27: 2 | G27: =+G26+E27-F27 -> 0
A28: 42825 | B28: POR COBRAR | C28: MARZO | D28: LUZ | E28: 26.9 | G28: =+G27+E28-F28 -> 26.9
D29: AGUA | E29: 2 | G29: =+G28+E29-F29 -> 28.9
D30: ALQUILER | E30: 300 | G30: =+G29+E30-F30 -> 328.9
A31: 42859 | B31: 12628 | C31: MARZO | D31: ALQUILER | F31: 250 | G31: =+G30+E31-F31 -> 78.9
A32: 42885 | B32: 12726 | C32: MARZO | D32: ALQUILER | F32: 50 | G32: =+G31+E32-F32 -> 28.9
A33: 42927 | B33: 12986 | C33: MARZO | D33: LUZ | F33: 26.9 | G33: =+G32+E33-F33 -> 2
A34: 42927 | B34: 12986 | C34: MARZO | D34: AGUA | F34: 2 | G34: =+G33+E34-F34 -> -2.1316282e-14
A35: 42855 | B35: POR COBRAR | C35: ABRIL | D35: LUZ | E35: 28.1 | G35: =+G34+E35-F35 -> 28.1
D36: AGUA | E36: 2 | G36: =+G35+E36-F36 -> 30.1
D37: ALQUILER | E37: 300 | G37: =+G36+E37-F37 -> 330.1
A38: 42885 | B38: 12726 | C38: ABRIL | D38: ALQUILER | F38: 50 | G38: =+G37+E38-F38 -> 280.1
A39: 42898 | B39: 12820 | C39: ABRIL | D39: ALQUILER | F39: 180 | G39: =+G38+E39-F39 -> 100.1
A40: 42916 | B40: 12908 | C40: ABRIL | D40: ALQUILER | F40: 70 | G40: =+G39+E40-F40 -> 30.1
A41: 42927 | B41: 12986 | C41: ABRIL | D41: LUZ | F41: 28.1 | G41: =+G40+E41-F41 -> 2
A42: 42927 | B42: 12986 | C42: ABRIL | D42: AGUA | F42: 2 | G42: =+G41+E42-F42 -> -3.5527137e-14
A43: 42886 | B43: POR COBRAR | C43: MAYO | D43: LUZ | E43: 32.8 | G43: =+G42+E43-F43 -> 32.8
D44: AGUA | E44: 2 | G44: =+G43+E44-F44 -> 34.8
D45: ALQUILER | E45: 300 | G45: =+G44+E45-F45 -> 334.8
A46: 42916 | B46: 12908 | C46: MAYO | D46: ALQUILER | F46: 40 | G46: =+G45+E46-F46 -> 294.8
A47: 42927 | B47: 12986 | C47: MAYO | D47: ALQUILER | F47: 95.7 | G47: =+G46+E47-F47 -> 199.1
A48: 42927 | B48: 12986 | C48: MAYO | D48: LUZ | F48: 32.8 | G48: =+G47+E48-F48 -> 166.3
A49: 42927 | B49: 12986 | C49: MAYO | D49: AGUA | F49: 2 | G49: =+G48+E49-F49 -> 164.3
A50: 42947 | B50: 13084 | C50: MAYO | D50: ALQUILER | F50: 135 | G50: =+G49+E50-F50 -> 29.3
A51: 42979 | B51: 13364 | C51: MAYO | D51: ALQUILER | F51: 28.6 | G51: =+G50+E51-F51 -> 0.7
A52: 43034 | B52: 13700 | C52: MAYO | D52: ALQUILER | F52: 0.7 | G52: =+G51+E52-F52 -> -4.6851412e-14
A53: 42916 | B53: POR COBRAR | C53: JUNIO | D53: LUZ | E53: 32.2 | G53: =+G52+E53-F53 -> 32.2
D54: AGUA | E54: 2 | G54: =+G53+E54-F54 -> 34.2
D55: ALQUILER | E55: 300 | G55: =+G54+E55-F55 -> 334.2
A56: 42979 | B56: 13364 | C56: JUNIO | D56: ALQUILER | F56: 51.4 | G56: =+G55+E56-F56 -> 282.8
A57: 43008 | B57: 13561 | C57: JUNIO | D57: ALQUILER | F57: 85 | G57: =+G56+E57-F57 -> 197.8
A58: 43087 | B58: 13952 | C58: JUNIO | D58: LUZ | F58: 32.2 | G58: =+G57+E58-F58 -> 165.6
A59: 43087 | B59: 13952 | C59: JUNIO | D59: AGUA | F59: 2 | G59: =+G58+E59-F59 -> 163.6
A60: 43034 | B60: 13700 | C60: JUNIO | D60: ALQUILER | F60: 163.6 | G60: =+G59+E60-F60 -> 0
A61: 42947 | B61: POR COBRAR | C61: JULIO | D61: LUZ | E61: 30 | G61: =+G60+E61-F61 -> 30
D62: AGUA | E62: 2 | G62: =+G61+E62-F62 -> 32
D63: ALQUILER | E63: 300 | G63: =+G62+E63-F63 -> 332
A64: 43087 | B64: 13952 | C64: JULIO | D64: LUZ | F64: 30 | G64: =+G63+E64-F64 -> 302
A65: 43087 | B65: 13952 | C65: JULIO | D65: AGUA | F65: 2 | G65: =+G64+E65-F65 -> 300
A66: 43034 | B66: 13700 | C66: JULIO | D66: ALQUILER | F66: 300 | G66: =+G65+E66-F66 -> 0
A67: 42978 | B67: POR COBRAR | C67: AGOSTO | D67: LUZ | E67: 30 | G67: =+G66+E67-F67 -> 30
D68: AGUA | E68: 2 | G68: =+G67+E68-F68 -> 32
D69: ALQUILER | E69: 300 | G69: =+G68+E69-F69 -> 332
A70: 43034 | B70: 13700 | C70: AGOSTO | D70: ALQUILER | F70: 135.7 | G70: =+G69+E70-F70 -> 196.3
A71: 43038 | B71: 13716 | C71: AGOSTO | D71: ALQUILER | F71: 100 | G71: =+G70+E71-F71 -> 96.3
A72: 43039 | B72: 13732 | C72: AGOSTO | D72: ALQUILER | F72: 64.3 | G72: =+G71+E72-F72 -> 32
A73: 43238 | B73: 14622 | C73: AGOSTO | D73: LUZ | F73: 30 | G73: =+G72+E73-F73 -> 2
A74: 43238 | B74: 14622 | C74: AGOSTO | D74: AGUA | F74: 2 | G74: =+G73+E74-F74 -> 1.4210855e-14
A75: 43008 | B75: POR COBRAR | C75: SEPTIEMBRE | D75: LUZ | E75: 27.1 | G75: =+G74+E75-F75 -> 27.1
D76: AGUA | E76: 2 | G76: =+G75+E76-F76 -> 29.1
D77: ALQUILER | E77: 300 | G77: =+G76+E77-F77 -> 329.1
A78: 43039 | B78: 13732 | C78: SEPTIEMBRE | D78: ALQUILER | F78: 55.7 | G78: =+G77+E78-F78 -> 273.4
A79: 43069 | B79: 13869 | C79: SEPTIEMBRE | D79: ALQUILER | F79: 15 | G79: =+G78+E79-F79 -> 258.4
A80: 43099 | B80: 14019 | C80: SEPTIEMBRE | D80: ALQUILER | F80: 229.3 | G80: =+G79+E80-F80 -> 29.1
A81: 43238 | B81: 14622 | C81: SEPTIEMBRE | D81: LUZ | F81: 27.1 | G81: =+G80+E81-F81 -> 2
A82: 43238 | B82: 14622 | C82: SEPTIEMBRE | D82: AGUA | F82: 2 | G82: =+G81+E82-F82 -> 2.1316282e-14
A83: 43039 | B83: POR COBRAR | C83: OCTUBRE | D83: LUZ | E83: 27 | G83: =+G82+E83-F83 -> 27
D84: AGUA | E84: 2 | G84: =+G83+E84-F84 -> 29
D85: ALQUILER | E85: 300 | G85: =+G84+E85-F85 -> 329
A86: 43099 | B86: 14019 | C86: OCTUBRE | D86: ALQUILER | F86: 110.7 | G86: =+G85+E86-F86 -> 218.3
A87: 43117 | B87: 14079 | C87: OCTUBRE | D87: ALQUILER | F87: 150 | G87: =+G86+E87-F87 -> 68.3
A88: 43140 | B88: 14199 | C88: OCTUBRE | D88: ALQUILER | F88: 39.3 | G88: =+G87+E88-F88 -> 29
A89: 43238 | B89: 14622 | C89: OCTUBRE | D89: LUZ | F89: 27 | G89: =+G88+E89-F89 -> 2
A90: 43238 | B90: 14622 | C90: OCTUBRE | D90: AGUA | F90: 2 | G90: =+G89+E90-F90 -> 1.4210855e-14
A91: 43069 | B91: POR COBRAR | C91: NOVIEMBRE | D91: LUZ | E91: 28.8 | G91: =+G90+E91-F91 -> 28.8
D92: AGUA | E92: 2 | G92: =+G91+E92-F92 -> 30.8
D93: ALQUILER | E93: 300 | G93: =+G92+E93-F93 -> 330.8
A94: 43140 | B94: 14199 | C94: NOVIEMBRE | D94: ALQUILER | F94: 300 | G94: =+G93+E94-F94 -> 30.8
A95: 43238 | B95: 14622 | C95: NOVIEMBRE | D95: LUZ | F95: 28.8 | G95: =+G94+E95-F95 -> 2
A96: 43238 | B96: 14622 | C96: NOVIEMBRE | D96: AGUA | F96: 2 | G96: =+G95+E96-F96 -> 1.0658141e-14
A97: 43100 | B97: POR COBRAR | C97: DICIEMBRE | D97: LUZ | E97: 31.3 | G97: =+G96+E97-F97 -> 31.3
D98: AGUA | E98: 2 | G98: =+G97+E98-F98 -> 33.3
D99: ALQUILER | E99: 300 | G99: =+G98+E99-F99 -> 333.3
A100: 43140 | B100: 14199 | C100: DICIEMBRE | D100: ALQUILER | F100: 110.7 | G100: =+G99+E100-F100 -> 222.6
A101: 43159 | B101: 14284 | C101: DICIEMBRE | D101: ALQUILER | F101: 137 | G101: =+G100+E101-F101 -> 85.6
A102: 43172 | B102: 14357 | C102: DICIEMBRE | D102: ALQUILER | F102: 52.3 | G102: =+G101+E102-F102 -> 33.3
A103: 43238 | B103: 14622 | C103: DICIEMBRE | D103: LUZ | F103: 31.3 | G103: =+G102+E103-F103 -> 2
...

Sheet OBREGON FERNANDO
B2: FERNANDO MARTIN OBREGON CASTILLO
A4: FECHA | B4: DOCUMENTO | C4: PERIODO | D4: CONCEPTO | E4: POR COBRAR | F4: PAGADO | G4: SALDO POR COBRAR
A6: 44926 | B6: POR COBRAR | C6: NOVIEMBRE | D6: GARANTIA | E6: 350 | G6: =G5+E6-F6 -> 350
D7: ALQUILER | E7: 350 | G7: =G6+E7-F7 -> 700
A8: 44865 | B8: EB01-1405 | C8: DICIEMBRE | D8: GARANTIA | F8: 350 | G8: =G7+E8-F8 -> 350
A9: 44897 | B9: EB01-1540 | C9: DICIEMBRE | D9: ALQUILER | F9: 350 | G9: =G8+E9-F9 -> 0
A10: 44926 | B10: POR COBRAR | C10: DICIEMBRE | D10: LUZ | E10: 29.7 | G10: =G9+E10-F10 -> 29.7
D11: AGUA | E11: 5.7 | G11: =G10+E11-F11 -> 35.4
D12: ALQUILER | E12: 350 | G12: =G11+E12-F12 -> 385.4
A13: 44933 | B13: EB01-1653 | C13: DICIEMBRE | D13: ALQUILER | F13: 350 | G13: =G12+E13-F13 -> 35.4
A14: 45009 | B14: RII 1449 | C14: DICIEMBRE | D14: LUZ | F14: 29.7 | G14: =G13+E14-F14 -> 5.7
A15: 45009 | B15: RII 1449 | C15: DICIEMBRE | D15: AGUA | F15: 5.7 | G15: =G14+E15-F15 -> -2.220446e-14
A16: 44926 | B16: POR COBRAR | C16: ENERO | D16: LUZ | E16: 33.1 | G16: =G15+E16-F16 -> 33.1
D17: AGUA | E17: 4.8 | G17: =G16+E17-F17 -> 37.9
D18: ALQUILER | E18: 350 | G18: =G17+E18-F18 -> 387.9
A19: 44957 | B19: EB01-1745 | C19: ENERO | D19: ALQUILER | F19: 165 | G19: =G18+E19-F19 -> 222.9
A20: 45009 | B20: RII 1449 | C20: ENERO | D20: LUZ | F20: 33.1 | G20: =G19+E20-F20 -> 189.8
A21: 45009 | B21: RII 1449 | C21: ENERO | D21: AGUA | F21: 4.8 | G21: =G20+E21-F21 -> 185
A22: 45009 | B22: EB01-1911 | C22: ENERO | D22: ALQUILER | F22: 185 | G22: =G21+E22-F22 -> 0
A23: 44985 | B23: POR COBRAR | C23: FEBRERO | D23: LUZ | E23: 36.1 | G23: =G22+E23-F23 -> 36.1
D24: AGUA | E24: 1.2 | G24: =G23+E24-F24 -> 37.3
D25: ALQUILER | E25: 350 | G25: =G24+E25-F25 -> 387.3
A26: 44985 | B26: EB01-1848 | C26: FEBRERO | D26: ALQUILER | F26: 205 | G26: =G25+E26-F26 -> 182.3
A27: 45028 | B27: RII 1500 | C27: FEBRERO | D27: LUZ | F27: 36.1 | G27: =G26+E27-F27 -> 146.2
A28: 45028 | B28: RII 1500 | C28: FEBRERO | D28: AGUA | F28: 1.2 | G28: =G27+E28-F28 -> 145
A29: 45028 | B29: EB01-2015 | C29: FEBRERO | D29: ALQUILER | F29: 145 | G29: =G28+E29-F29 -> 0
A30: 44985 | B30: POR COBRAR | C30: MARZO | D30: LUZ | E30: 33.2 | G30: =G29+E30-F30 -> 33.2
D31: AGUA | E31: 1.3 | G31: =G30+E31-F31 -> 34.5
D32: ALQUILER | E32: 350 | G32: =G31+E32-F32 -> 384.5
A33: 45016 | B33: EB01-1974 | C33: MARZO | D33: ALQUILER | F33: 220 | G33: =G32+E33-F33 -> 164.5
A34: 45028 | B34: EB01-2015 | C34: MARZO | D34: ALQUILER | F34: 130 | G34: =G33+E34-F34 -> 34.5
A35: 45084 | B35: RII 1611 | C35: MARZO | D35: LUZ | F35: 33.2 | G35: =G34+E35-F35 -> 1.3
A36: 45084 | B36: RII 1611 | C36: MARZO | D36: AGUA | F36: 1.3 | G36: =G35+E36-F36 -> -2.8865799e-15
A37: 45046 | B37: POR COBRAR | C37: ABRIL | D37: LUZ | E37: 34.7 | G37: =G36+E37-F37 -> 34.7
D38: AGUA | E38: 1.5 | G38: =G37+E38-F38 -> 36.2
D39: ALQUILER | E39: 350 | G39: =G38+E39-F39 -> 386.2
A40: 45046 | B40: EB01-2093 | C40: ABRIL | D40: ALQUILER | F40: 350 | G40: =G39+E40-F40 -> 36.2
A41: 45084 | B41: RII 1611 | C41: ABRIL | D41: LUZ | F41: 34.7 | G41: =G40+E41-F41 -> 1.5
A42: 45084 | B42: RII 1611 | C42: ABRIL | D42: AGUA | F42: 1.5 | G42: =G41+E42-F42 -> -1.4210855e-14
A43: 45046 | B43: POR COBRAR | C43: MAYO | D43: LUZ | E43: 32.1 | G43: =G42+E43-F43 -> 32.1
D44: AGUA | E44: 2.1 | G44: =G43+E44-F44 -> 34.2
D45: ALQUILER | E45: 350 | G45: =G44+E45-F45 -> 384.2
A46: 45077 | B46: EB01-2225 | C46: MAYO | D46: ALQUILER | F46: 350 | G46: =G45+E46-F46 -> 34.2
D47: TALONARIO MAMÁ | E47: 10 | G47: =G46+E47-F47 -> 44.2
A48: 45210 | B48: RII 1830 | C48: MAYO | D48: LUZ | F48: 32.1 | G48: =G47+E48-F48 -> 12.1
A49: 45210 | B49: RII 1830 | C49: MAYO | D49: AGUA | F49: 2.1 | G49: =G48+E49-F49 -> 10
A50: 45210 | B50: RII 1830 | C50: MAYO | D50: TALONARIO MAMÁ | F50: 10 | G50: =G49+E50-F50 -> 0
A51: 45107 | B51: POR COBRAR | C51: JUNIO | D51: LUZ | E51: 32.7 | G51: =G50+E51-F51 -> 32.7
D52: AGUA | E52: 2 | G52: =G51+E52-F52 -> 34.7
D53: ALQUILER | E53: 350 | G53: =G52+E53-F53 -> 384.7
A54: 45111 | B54: EB01-2346 | C54: JUNIO | D54: ALQUILER | F54: 230 | G54: =G53+E54-F54 -> 154.7
A55: 45210 | B55: EB01-2766 | C55: JUNIO | D55: ALQUILER | F55: 56.5 | G55: =G54+E55-F55 -> 98.2
A56: 45210 | B56: RII 1830 | C56: JUNIO | D56: LUZ | F56: 32.7 | G56: =G55+E56-F56 -> 65.5
A57: 45210 | B57: RII 1830 | C57: JUNIO | D57: AGUA | F57: 2 | G57: =G56+E57-F57 -> 63.5
A58: 45245 | B58: EB01-2898 | C58: JUNIO | D58: ALQUILER | F58: 63.5 | G58: =G57+E58-F58 -> 0
A59: 45138 | B59: POR COBRAR | C59: JULIO | D59: LUZ | E59: 30.8 | G59: =G58+E59-F59 -> 30.8
D60: AGUA | E60: 2 | G60: =G59+E60-F60 -> 32.8
D61: ALQUILER | E61: 350 | G61: =G60+E61-F61 -> 382.8
A62: 45138 | B62: EB01-2470 | C62: JULIO | D62: ALQUILER | F62: 220 | G62: =G61+E62-F62 -> 162.8
A63: 45156 | B63: EB01-2543 | C63: JULIO | D63: ALQUILER | F63: 130 | G63: =G62+E63-F63 -> 32.8
A64: 45210 | B64: RII 1830 | C64: JULIO | D64: LUZ | F64: 30.8 | G64: =G63+E64-F64 -> 2
A65: 45210 | B65: RII 1830 | C65: JULIO | D65: AGUA | F65: 2 | G65: =G64+E65-F65 -> 1.0658141e-14
A66: 45169 | B66: POR COBRAR | C66: AGOSTO | D66: LUZ | E66: 29.5 | G66: =G65+E66-F66 -> 29.5
D67: AGUA | E67: 2.3 | G67: =G66+E67-F67 -> 31.8
D68: ALQUILER | E68: 350 | G68: =G67+E68-F68 -> 381.8
A69: 45169 | B69: EB01-2604 | C69: AGOSTO | D69: ALQUILER | F69: 260 | G69: =G68+E69-F69 -> 121.8
A70: 45210 | B70: RII 1830 | C70: AGOSTO | D70: LUZ | F70: 29.5 | G70: =G69+E70-F70 -> 92.3
A71: 45210 | B71: RII 1830 | C71: AGOSTO | D71: AGUA | F71: 2.3 | G71: =G70+E71-F71 -> 90
A72: 45245 | B72: EB01-2898 | C72: AGOSTO | D72: ALQUILER | F72: 90 | G72: =G71+E72-F72 -> 0
A73: 45199 | B73: POR COBRAR | C73: SETIEMBRE | D73: LUZ | E73: 29.3 | G73: =G72+E73-F73 -> 29.3
D74: AGUA | E74: 2 | G74: =G73+E74-F74 -> 31.3
D75: ALQUILER | E75: 350 | G75: =G74+E75-F75 -> 381.3
A76: 45199 | B76: EB01-2719 | C76: SETIEMBRE | D76: ALQUILER | F76: 260 | G76: =G75+E76-F76 -> 121.3
A77: 45245 | B77: RII 1874 | C77: SETIEMBRE | D77: LUZ | F77: 29.3 | G77: =G76+E77-F77 -> 92
A78: 45245 | B78: RII 1874 | C78: SETIEMBRE | D78: AGUA | F78: 2 | G78: =G77+E78-F78 -> 90
A79: 45245 | B79: EB01-2898 | C79: SETIEMBRE | D79: ALQUILER | F79: 90 | G79: =G78+E79-F79 -> 0
A80: 45230 | B80: POR COBRAR | C80: OCTUBRE | D80: LUZ | E80: 28.5 | G80: =G79+E80-F80 -> 28.5
D81: AGUA | E81: 2 | G81: =G80+E81-F81 -> 30.5
D82: ALQUILER | E82: 350 | G82: =G81+E82-F82 -> 380.5
A83: 45230 | B83: EB01-2859 | C83: OCTUBRE | D83: ALQUILER | F83: 260 | G83: =G82+E83-F83 -> 120.5
A84: 45245 | B84: RII 1874 | C84: OCTUBRE | D84: LUZ | F84: 28.5 | G84: =G83+E84-F84 -> 92
A85: 45245 | B85: RII 1874 | C85: OCTUBRE | D85: AGUA | F85: 2 | G85: =G84+E85-F85 -> 90
A86: 45245 | B86: EB01-2898 | C86: OCTUBRE | D86: ALQUILER | F86: 90 | G86: =G85+E86-F86 -> 0 | I86: 2023
A87: 45260 | B87: POR COBRAR | C87: NOVIEMBRE | D87: LUZ | E87: 31 | G87: =G86+E87-F87 -> 31
D88: AGUA | E88: 10 | G88: =G87+E88-F88 -> 41
D89: ALQUILER | E89: 350 | G89: =G88+E89-F89 -> 391
A90: 45260 | B90: EB01-2993 | C90: NOVIEMBRE | D90: ALQUILER | F90: 268 | G90: =G89+E90-F90 -> 123
A91: 45328 | B91: RII 2040 | C91: NOVIEMBRE | D91: LUZ | F91: 31 | G91: =G90+E91-F91 -> 92
A92: 45328 | B92: RII 2040 | C92: NOVIEMBRE | D92: AGUA | F92: 10 | G92: =G91+E92-F92 -> 82
A93: 45328 | B93: EB01-3299 | C93: NOVIEMBRE | D93: ALQUILER | F93: 82 | G93: =G92+E93-F93 -> 0 | I93: VILCA MARIA
A94: 45291 | B94: POR COBRAR | C94: DICIEMBRE | D94: LUZ | E94: 33.1 | G94: =G93+E94-F94 -> 33.1
D95: AGUA | E95: 5 | G95: =G94+E95-F95 -> 38.1
D96: ALQUILER | E96: 350 | G96: =G95+E96-F96 -> 388.1
A97: 45291 | B97: EB01-3126 | C97: DICIEMBRE | D97: ALQUILER | F97: 300 | G97: =G96+E97-F97 -> 88.1
A98: 45328 | B98: RII 2040 | C98: DICIEMBRE | D98: LUZ | F98: 33.1 | G98: =G97+E98-F98 -> 55
A99: 45328 | B99: RII 2040 | C99: DICIEMBRE | D99: AGUA | F99: 5 | G99: =G98+E99-F99 -> 50
A100: 45328 | B100: EB01-3299 | C100: DICIEMBRE | D100: ALQUILER | F100: 50 | G100: =G99+E100-F100 -> 0 | I100: VILCA MARIA
A101: 45322 | B101: POR COBRAR | C101: ENERO | D101: LUZ | E101: 37 | G101: =G100+E101-F101 -> 37
D102: AGUA | E102: 8.8 | G102: =G101+E102-F102 -> 45.8
D103: ALQUILER | E103: 350 | G103: =G102+E103-F103 -> 395.8
...

Sheet PALOMINO ROSA
B2: PALOMINO CUSI ROSA | J2: INGRESO DIA 15/12/2021
A3: FECHA | B3: DOCUMENTO | C3: PERIODO | D3: CONCEPTO | E3: POR COBRAR | F3: PAGADO | G3: SALDO POR COBRAR | J3: 44465773
A5: 44196 | B5: POR COBRAR | C5: DICIEMBRE | D5: ALQUILER | E5: 500 | G5: =+G4+E5-F5 -> 500
D6: LUZ | E6: 36.1 | G6: =+G5+E6-F6 -> 536.1
D7: AGUA | E7: 4.4 | G7: =+G6+E7-F7 -> 540.5
A8: 44541 | B8: EB01-261 | C8: DICIEMBRE | D8: ALQUILER | F8: 500 | G8: =+G7+E8-F8 -> 40.5
A9: 44590 | B9: RII 000910 | C9: DICIEMBRE | D9: LUZ | F9: 36.1 | G9: =+G8+E9-F9 -> 4.4
A10: 44590 | B10: RII 000910 | C10: DICIEMBRE | D10: AGUA | F10: 4.4 | G10: =+G9+E10-F10 -> 0
A11: 44592 | B11: POR COBRAR | C11: ENERO | D11: ALQUILER | E11: 500 | G11: =+G10+E11-F11 -> 500
D12: LUZ | E12: 89.9 | G12: =+G11+E12-F12 -> 589.9
D13: AGUA | E13: 1.3 | G13: =+G12+E13-F13 -> 591.2
A14: 44578 | B14: EB01-391 | C14: ENERO | D14: ALQUILER | F14: 500 | G14: =+G13+E14-F14 -> 91.2
A15: 44617 | B15: RII 000936 | C15: ENERO | D15: LUZ | F15: 89.9 | G15: =+G14+E15-F15 -> 1.3
A16: 44617 | B16: RII 000936 | C16: ENERO | D16: AGUA | F16: 1.3 | G16: =+G15+E16-F16 -> -7.3940853e-14
A17: 44620 | B17: POR COBRAR | C17: FEBRERO | D17: LUZ | E17: 58.5 | G17: =+G16+E17-F17 -> 58.5
D18: AGUA | E18: 4.3 | G18: =+G17+E18-F18 -> 62.8
D19: ALQUILER | E19: 500 | G19: =+G18+E19-F19 -> 562.8
A20: 44608 | B20: EB01-488 | C20: FEBRERO | D20: ALQUILER | F20: 500 | G20: =+G19+E20-F20 -> 62.8
A21: 44670 | B21: RII 001017 | C21: FEBRERO | D21: LUZ | F21: 58.5 | G21: =+G20+E21-F21 -> 4.3
A22: 44670 | B22: RII 001017 | C22: FEBRERO | D22: AGUA | F22: 4.3 | G22: =+G21+E22-F22 -> -4.5297099e-14
A23: 44651 | B23: POR COBRAR | C23: MARZO | D23: LUZ | E23: 58.4 | G23: =+G22+E23-F23 -> 58.4
D24: AGUA | E24: 5.2 | G24: =+G23+E24-F24 -> 63.6
D25: ALQUILER | E25: 500 | G25: =+G24+E25-F25 -> 563.6
A26: 44636 | B26: EB01-584 | C26: MARZO | D26: ALQUILER | F26: 500 | G26: =+G25+E26-F26 -> 63.6
A27: 44692 | B27: RII 1040 | C27: MARZO | D27: LUZ | F27: 58.4 | G27: =+G26+E27-F27 -> 5.2
A28: 44692 | B28: RII 1040 | C28: MARZO | D28: AGUA | F28: 5.2 | G28: =+G27+E28-F28 -> -8.970602e-14
A29: 44681 | B29: POR COBRAR | C29: ABRIL | D29: LUZ | E29: 59.4 | G29: =+G28+E29-F29 -> 59.4
D30: AGUA | E30: 2.8 | G30: =+G29+E30-F30 -> 62.2
D31: ALQUILER | E31: 500 | G31: =+G30+E31-F31 -> 562.2
A32: 44670 | B32: EB01-721 | C32: ABRIL | D32: ALQUILER | F32: 500 | G32: =+G31+E32-F32 -> 62.2
A33: 44712 | B33: RII 1065 | C33: ABRIL | D33: LUZ | F33: 59.4 | G33: =+G32+E33-F33 -> 2.8
A34: 44712 | B34: RII 1065 | C34: ABRIL | D34: AGUA | F34: 2.8 | G34: =+G33+E34-F34 -> -6.6613381e-14
A35: 44712 | B35: POR COBRAR | C35: MAYO | D35: LUZ | E35: 56.8 | G35: =+G34+E35-F35 -> 56.8
D36: AGUA | E36: 9.1 | G36: =+G35+E36-F36 -> 65.9
D37: ALQUILER | E37: 500 | G37: =+G36+E37-F37 -> 565.9
D38: FUMIGACION | E38: 6 | G38: =+G37+E38-F38 -> 571.9
A39: 44699 | B39: EB01-817 | C39: MAYO | D39: ALQUILER | F39: 500 | G39: =+G38+E39-F39 -> 71.9
A40: 44758 | B40: RII 1120 | C40: MAYO | D40: LUZ | F40: 56.8 | G40: =+G39+E40-F40 -> 15.1
A41: 44758 | B41: RII 1120 | C41: MAYO | D41: AGUA | F41: 9.1 | G41: =+G40+E41-F41 -> 6
A42: 44900 | B42: RII 1306 | C42: MAYO | D42: FUMIGACION | F42: 6 | G42: =+G41+E42-F42 -> -1.9539925e-14
A43: 44742 | B43: POR COBRAR | C43: JUNIO | D43: LUZ | E43: 55 | G43: =+G42+E43-F43 -> 55
D44: AGUA | E44: 6.9 | G44: =+G43+E44-F44 -> 61.9
D45: ALQUILER | E45: 500 | G45: =+G44+E45-F45 -> 561.9
A46: 44728 | B46: EB01-920 | C46: JUNIO | D46: ALQUILER | F46: 500 | G46: =+G45+E46-F46 -> 61.9
A47: 44789 | B47: RII 1159 | C47: JUNIO | D47: LUZ | F47: 55 | G47: =+G46+E47-F47 -> 6.9
A48: 44789 | B48: RII 1159 | C48: JUNIO | D48: AGUA | F48: 6.9 | G48: =+G47+E48-F48 -> -2.3092639e-14
A49: 44773 | B49: POR COBRAR | C49: JULIO | D49: LUZ | E49: 54.8 | G49: =+G48+E49-F49 -> 54.8
D50: AGUA | E50: 9.7 | G50: =+G49+E50-F50 -> 64.5
D51: ALQUILER | E51: 500 | G51: =+G50+E51-F51 -> 564.5
A52: 44758 | B52: EB01-1024 | C52: JULIO | D52: ALQUILER | F52: 500 | G52: =+G51+E52-F52 -> 64.5
A53: 44821 | B53: RII 1209 | C53: JULIO | D53: LUZ | F53: 54.8 | G53: =+G52+E53-F53 -> 9.7
A54: 44821 | B54: RII 1209 | C54: JULIO | D54: AGUA | F54: 9.7 | G54: =+G53+E54-F54 -> 0
A55: 44804 | B55: POR COBRAR | C55: AGOSTO | D55: LUZ | E55: 55.1 | G55: =+G54+E55-F55 -> 55.1
D56: AGUA | E56: 7 | G56: =+G55+E56-F56 -> 62.1
D57: ALQUILER | E57: 500 | G57: =+G56+E57-F57 -> 562.1
A58: 44789 | B58: EB01-1144 | C58: AGOSTO | D58: ALQUILER | F58: 500 | G58: =+G57+E58-F58 -> 62.1
A59: 44881 | B59: RII 1281 | C59: AGOSTO | D59: LUZ | F59: 50 | G59: =+G58+E59-F59 -> 12.1
A60: 44900 | B60: RII 1306 | C60: AGOSTO | D60: LUZ | F60: 5.1 | G60: =+G59+E60-F60 -> 7
A61: 44900 | B61: RII 1306 | C61: AGOSTO | D61: AGUA | F61: 7 | G61: =+G60+E61-F61 -> 2.3092639e-14
A62: 44834 | B62: POR COBRAR | C62: SETIEMBRE | D62: LUZ | E62: 48.9 | G62: =+G61+E62-F62 -> 48.9
D63: AGUA | E63: 8.2 | G63: =+G62+E63-F63 -> 57.1
D64: ALQUILER | E64: 500 | G64: =+G63+E64-F64 -> 557.1
A65: 44821 | B65: EB01-1258 | C65: SETIEMBRE | D65: ALQUILER | F65: 500 | G65: =+G64+E65-F65 -> 57.1
A66: 44867 | B66: RII 1263 | C66: SETIEMBRE | D66: LUZ | F66: 48.9 | G66: =+G65+E66-F66 -> 8.2
A67: 44867 | B67: RII 1263 | C67: SETIEMBRE | D67: AGUA | F67: 8.2 | G67: =+G66+E67-F67 -> 2.4868996e-14
A68: 44865 | B68: POR COBRAR | C68: OCTUBRE | D68: LUZ | E68: 48.7 | G68: =+G67+E68-F68 -> 48.7
D69: AGUA | E69: 4.9 | G69: =+G68+E69-F69 -> 53.6
D70: ALQUILER | E70: 500 | G70: =+G69+E70-F70 -> 553.6
A71: 44852 | B71: EB01-1365 | C71: OCTUBRE | D71: ALQUILER | F71: 500 | G71: =+G70+E71-F71 -> 53.6
A72: 44900 | B72: RII 1306 | C72: OCTUBRE | D72: LUZ | F72: 48.7 | G72: =+G71+E72-F72 -> 4.9
A73: 44900 | B73: RII 1306 | C73: OCTUBRE | D73: AGUA | F73: 4.9 | G73: =+G72+E73-F73 -> 1.9539925e-14
A74: 44895 | B74: POR COBRAR | C74: NOVIEMBRE | D74: LUZ | E74: 54.4 | G74: =+G73+E74-F74 -> 54.4
D75: AGUA | E75: 6.3 | G75: =+G74+E75-F75 -> 60.7
D76: ALQUILER | E76: 500 | G76: =+G75+E76-F76 -> 560.7
A77: 44881 | B77: EB01-1471 | C77: NOVIEMBRE | D77: ALQUILER | F77: 500 | G77: =+G76+E77-F77 -> 60.7
A78: 44923 | B78: RII 1319 | C78: NOVIEMBRE | D78: LUZ | F78: 54.4 | G78: =+G77+E78-F78 -> 6.3
A79: 44923 | B79: RII 1319 | C79: NOVIEMBRE | D79: AGUA | F79: 6.3 | G79: =+G78+E79-F79 -> 4.7073456e-14
A80: 44926 | B80: POR COBRAR | C80: DICIEMBRE | D80: LUZ | E80: 62.2 | G80: =+G79+E80-F80 -> 62.2
D81: AGUA | E81: 5.7 | G81: =+G80+E81-F81 -> 67.9
D82: ALQUILER | E82: 500 | G82: =+G81+E82-F82 -> 567.9
A83: 44915 | B83: EB01-1577 | C83: DICIEMBRE | D83: ALQUILER | F83: 500 | G83: =+G82+E83-F83 -> 67.9
A84: 44949 | B84: EB01-1352 | C84: DICIEMBRE | D84: LUZ | F84: 62.2 | G84: =+G83+E84-F84 -> 5.7
A85: 44949 | B85: EB01-1352 | C85: DICIEMBRE | D85: AGUA | F85: 5.7 | G85: =+G84+E85-F85 -> 8.7929664e-14
A86: 44957 | B86: POR COBRAR | C86: ENERO | D86: LUZ | E86: 62.5 | G86: =+G85+E86-F86 -> 62.5
D87: AGUA | E87: 4.8 | G87: =+G86+E87-F87 -> 67.3
D88: ALQUILER | E88: 500 | G88: =+G87+E88-F88 -> 567.3
A89: 44949 | B89: EB01-1686 | C89: ENERO | D89: ALQUILER | F89: 500 | G89: =+G88+E89-F89 -> 67.3
A90: 44991 | B90: RII 1417 | C90: ENERO | D90: LUZ | F90: 62.5 | G90: =+G89+E90-F90 -> 4.8
A91: 44991 | B91: RII 1417 | C91: ENERO | D91: AGUA | F91: 4.8 | G91: =+G90+E91-F91 -> 6.8389738e-14
A92: 44985 | B92: POR COBRAR | C92: FEBRERO | D92: LUZ | E92: 68.1 | G92: =+G91+E92-F92 -> 68.1
D93: AGUA | E93: 1.2 | G93: =+G92+E93-F93 -> 69.3
D94: ALQUILER | E94: 500 | G94: =+G93+E94-F94 -> 569.3
A95: 44979 | B95: EB01-1798 | C95: FEBRERO | D95: ALQUILER | F95: 500 | G95: =+G94+E95-F95 -> 69.3
A96: 45010 | B96: RII 1465 | C96: FEBRERO | D96: LUZ | F96: 68.1 | G96: =+G95+E96-F96 -> 1.2
A97: 45010 | B97: RII 1465 | C97: FEBRERO | D97: AGUA | F97: 1.2 | G97: =+G96+E97-F97 -> 7.3940853e-14
A98: 45016 | B98: POR COBRAR | C98: MARZO | D98: LUZ | E98: 62.7 | G98: =+G97+E98-F98 -> 62.7
D99: AGUA | E99: 1.3 | G99: =+G98+E99-F99 -> 64
D100: ALQUILER | E100: 500 | G100: =+G99+E100-F100 -> 564
A101: 45005 | B101: EB01-1902 | C101: MARZO | D101: ALQUILER | F101: 500 | G101: =+G100+E101-F101 -> 64
A102: 45044 | B102: RII 1518 | C102: MARZO | D102: LUZ | F102: 62.7 | G102: =+G101+E102-F102 -> 1.3
...

Sheet PEÑA TEREZA
B3: PEÑA VDA DE VILLANUEVA TEREZA
A5: FECHA | B5: DOCUMENTO | C5: PERIODO | D5: CONCEPTO | E5: POR COBRAR | F5: PAGADO | G5: SALDO POR COBRAR
A6: 42736 | B6: SALDO AL 2016 | G6: 235.3
A7: 42737 | B7: 11993 | C7: ACUENTA DEL 2016 | F7: 210 | G7: =+G6+E7-F7 -> 25.3
A8: 42754 | B8: 12119 | C8: ACUENTA DEL 2016 | F8: 25.3 | G8: =+G7+E8-F8 -> 0
A9: 42766 | B9: POR COBRAR | C9: ENERO | D9: LUZ | E9: 22.8 | G9: =+G8+E9-F9 -> 22.8
A10: 42766 | D10: AGUA | E10: 2.8 | G10: =+G9+E10-F10 -> 25.6
A11: 42766 | D11: ALQUILER | E11: 210 | G11: =+G10+E11-F11 -> 235.6
A12: 42800 | B12: 12336 | C12: ENERO | D12: AGUA | F12: 2.8 | G12: =+G11+E12-F12 -> 232.8
A13: 42800 | B13: 12336 | C13: ENERO | D13: LUZ | F13: 22.8 | G13: =+G12+E13-F13 -> 210
A14: 42772 | B14: 12217 | C14: ENERO | D14: ALQUILER | F14: 210 | G14: =+G13+E14-F14 -> 0
A15: 42794 | B15: POR COBRAR | C15: FEBRERO | D15: LUZ | E15: 21.8 | G15: =+G14+E15-F15 -> 21.8
D16: AGUA | E16: 2 | G16: =+G15+E16-F16 -> 23.8
D17: ALQUILER | E17: 210 | G17: =+G16+E17-F17 -> 233.8
A18: 42800 | B18: 12336 | C18: FEBRERO | D18: ALQUILER | F18: 210 | G18: =+G17+E18-F18 -> 23.8
A19: 42830 | B19: 12486 | C19: FEBRERO | D19: LUZ | F19: 21.8 | G19: =+G18+E19-F19 -> 2
A20: 42830 | B20: 12486 | C20: FEBRERO | D20: AGUA | F20: 2 | G20: =+G19+E20-F20 -> 1.0658141e-14
A21: 42825 | B21: POR COBRAR | C21: MARZO | D21: LUZ | E21: 21.6 | G21: =+G20+E21-F21 -> 21.6
D22: AGUA | E22: 2 | G22: =+G21+E22-F22 -> 23.6
D23: ALQUILER | E23: 210 | G23: =+G22+E23-F23 -> 233.6
A24: 42830 | B24: 12486 | C24: MARZO | D24: ALQUILER | F24: 210 | G24: =+G23+E24-F24 -> 23.6
A25: 42870 | B25: 12681 | C25: MARZO | D25: LUZ | F25: 21.6 | G25: =+G24+E25-F25 -> 2
A26: 42870 | B26: 12681 | C26: MARZO | D26: AGUA | F26: 2 | G26: =+G25+E26-F26 -> 2.1316282e-14
A27: 42855 | B27: POR COBRAR | C27: ABRIL | D27: LUZ | E27: 20.6 | G27: =+G26+E27-F27 -> 20.6
D28: AGUA | E28: 2 | G28: =+G27+E28-F28 -> 22.6
D29: ALQUILER | E29: 210 | G29: =+G28+E29-F29 -> 232.6
A30: 42870 | B30: 12681 | C30: ABRIL | D30: ALQUILER | F30: 210 | G30: =+G29+E30-F30 -> 22.6
A31: 42908 | B31: 12872 | C31: ABRIL | D31: LUZ | F31: 20.6 | G31: =+G30+E31-F31 -> 2
A32: 42908 | B32: 12872 | C32: ABRIL | D32: AGUA | F32: 2 | G32: =+G31+E32-F32 -> 2.1316282e-14
A33: 42886 | B33: POR COBRAR | C33: MAYO | D33: LUZ | E33: 20.9 | G33: =+G32+E33-F33 -> 20.9
D34: AGUA | E34: 2 | G34: =+G33+E34-F34 -> 22.9
D35: ALQUILER | E35: 210 | G35: =+G34+E35-F35 -> 232.9
A36: 42908 | B36: 12872 | C36: MAYO | D36: ALQUILER | F36: 210 | G36: =+G35+E36-F36 -> 22.9
A37: 42908 | B37: 12872 | C37: MAYO | D37: LUZ | F37: 20.9 | G37: =+G36+E37-F37 -> 2
A38: 42908 | B38: 12872 | C38: MAYO | D38: AGUA | F38: 2 | G38: =+G37+E38-F38 -> 3.5527137e-14
A39: 42916 | B39: POR COBRAR | C39: JUNIO | D39: LUZ | E39: 20.3 | G39: =+G38+E39-F39 -> 20.3
D40: AGUA | E40: 2 | G40: =+G39+E40-F40 -> 22.3
D41: ALQUILER | E41: 210 | G41: =+G40+E41-F41 -> 232.3
A42: 42936 | B42: 13037 | C42: JUNIO | D42: ALQUILER | F42: 210 | G42: =+G41+E42-F42 -> 22.3
A43: 42936 | B43: 13038 | C43: JUNIO | D43: LUZ | F43: 20.3 | G43: =+G42+E43-F43 -> 2
A44: 42936 | B44: 13038 | C44: JUNIO | D44: AGUA | F44: 2 | G44: =+G43+E44-F44 -> 3.907985e-14
A45: 42947 | B45: POR COBRAR | C45: JULIO | D45: LUZ | E45: 19.8 | G45: =+G44+E45-F45 -> 19.8
D46: AGUA | E46: 2 | G46: =+G45+E46-F46 -> 21.8
D47: ALQUILER | E47: 210 | G47: =+G46+E47-F47 -> 231.8
A48: 42965 | B48: 13275 | C48: JULIO | D48: ALQUILER | F48: 210 | G48: =+G47+E48-F48 -> 21.8
A49: 42986 | B49: 13426 | C49: JULIO | D49: LUZ | F49: 19.8 | G49: =+G48+E49-F49 -> 2
A50: 42986 | B50: 13426 | C50: JULIO | D50: AGUA | F50: 2 | G50: =+G49+E50-F50 -> 3.907985e-14
A51: 42978 | B51: POR COBRAR | C51: AGOSTO | D51: LUZ | E51: 19.8 | G51: =+G50+E51-F51 -> 19.8
D52: AGUA | E52: 2 | G52: =+G51+E52-F52 -> 21.8
D53: ALQUILER | E53: 210 | G53: =+G52+E53-F53 -> 231.8
A54: 42986 | B54: 13426 | C54: AGOSTO | D54: ALQUILER | F54: 210 | G54: =+G53+E54-F54 -> 21.8
A55: 43032 | B55: 13682 | C55: AGOSTO | D55: LUZ | F55: 19.8 | G55: =+G54+E55-F55 -> 2
A56: 43032 | B56: 13682 | C56: AGOSTO | D56: AGUA | F56: 2 | G56: =+G55+E56-F56 -> 3.907985e-14
A57: 43008 | B57: POR COBRAR | C57: SEPTIEMBRE | D57: LUZ | E57: 15.5 | G57: =+G56+E57-F57 -> 15.5
D58: AGUA | E58: 2 | G58: =+G57+E58-F58 -> 17.5
D59: ALQUILER | E59: 210 | G59: =+G58+E59-F59 -> 227.5
A60: 42986 | B60: 13426 | C60: SEPTIEMBRE | D60: ALQUILER | F60: 210 | G60: =+G59+E60-F60 -> 17.5
A61: 43032 | B61: 13682 | C61: SEPTIEMBRE | D61: LUZ | F61: 15.5 | G61: =+G60+E61-F61 -> 2
A62: 43032 | B62: 13682 | C62: SEPTIEMBRE | D62: AGUA | F62: 1.3 | G62: =+G61+E62-F62 -> 0.7
A63: 43131 | B63: 14164 | C63: SEPTIEMBRE | D63: AGUA | F63: 0.7 | G63: =+G62+E63-F63 -> 2.8421709e-14
A64: 43039 | B64: POR COBRAR | C64: OCTUBRE | D64: LUZ | E64: 15.4 | G64: =+G63+E64-F64 -> 15.4
D65: AGUA | E65: 2 | G65: =+G64+E65-F65 -> 17.4
D66: ALQUILER | E66: 210 | G66: =+G65+E66-F66 -> 227.4
A67: 43032 | B67: 13682 | C67: OCTUBRE | D67: ALQUILER | F67: 210 | G67: =+G66+E67-F67 -> 17.4
A68: 43085 | B68: 13949 | C68: OCTUBRE | D68: LUZ | F68: 15.4 | G68: =+G67+E68-F68 -> 2
A69: 43085 | B69: 13949 | C69: OCTUBRE | D69: AGUA | F69: 2 | G69: =+G68+E69-F69 -> 3.375078e-14
A70: 43069 | B70: POR COBRAR | C70: NOVIEMBRE | D70: LUZ | E70: 16.5 | G70: =+G69+E70-F70 -> 16.5
D71: AGUA | E71: 2 | G71: =+G70+E71-F71 -> 18.5
D72: ALQUILER | E72: 210 | G72: =+G71+E72-F72 -> 228.5
A73: 43085 | B73: 13949 | C73: NOVIEMBRE | D73: ALQUILER | F73: 210 | G73: =+G72+E73-F73 -> 18.5
A74: 43097 | B74: 13988 | C74: NOVIEMBRE | D74: LUZ | F74: 16.5 | G74: =+G73+E74-F74 -> 2
A75: 43097 | B75: 13988 | C75: NOVIEMBRE | D75: AGUA | F75: 2 | G75: =+G74+E75-F75 -> 2.8421709e-14
A76: 43100 | B76: POR COBRAR | C76: DICIEMBRE | D76: LUZ | E76: 17.9 | G76: =+G75+E76-F76 -> 17.9
D77: AGUA | E77: 2 | G77: =+G76+E77-F77 -> 19.9
D78: ALQUILER | E78: 210 | G78: =+G77+E78-F78 -> 229.9
A79: 43097 | B79: 13988 | C79: DICIEMBRE | D79: ALQUILER | F79: 210 | G79: =+G78+E79-F79 -> 19.9
A80: 43118 | B80: 14084 | C80: DICIEMBRE | D80: LUZ | F80: 17.9 | G80: =+G79+E80-F80 -> 2
A81: 43118 | B81: 14084 | C81: DICIEMBRE | D81: AGUA | F81: 2 | G81: =+G80+E81-F81 -> 3.5527137e-14
A82: 43131 | B82: POR COBRAR | C82: ENERO | D82: LUZ | E82: 15.9 | G82: =+G81+E82-F82 -> 15.9
D83: AGUA | E83: 2 | G83: =+G82+E83-F83 -> 17.9
D84: ALQUILER | E84: 210 | G84: =+G83+E84-F84 -> 227.9
A85: 43131 | B85: 14164 | C85: ENERO | D85: ALQUILER | F85: 210 | G85: =+G84+E85-F85 -> 17.9
A86: 43161 | B86: 14318 | C86: ENERO | D86: LUZ | F86: 15.9 | G86: =+G85+E86-F86 -> 2
A87: 43161 | B87: 14318 | C87: ENERO | D87: AGUA | F87: 2 | G87: =+G86+E87-F87 -> 3.375078e-14
A88: 43159 | B88: POR COBRAR | C88: FEBRERO | D88: LUZ | E88: 19.8 | G88: =+G87+E88-F88 -> 19.8
D89: AGUA | E89: 2 | G89: =+G88+E89-F89 -> 21.8
D90: ALQUILER | E90: 210 | G90: =+G89+E90-F90 -> 231.8
A91: 43161 | B91: 14318 | C91: FEBRERO | D91: ALQUILER | F91: 210 | G91: =+G90+E91-F91 -> 21.8
A92: 43192 | B92: 14423 | C92: FEBRERO | D92: LUZ | F92: 19.8 | G92: =+G91+E92-F92 -> 2
A93: 43192 | B93: 14423 | C93: FEBRERO | D93: AGUA | F93: 2 | G93: =+G92+E93-F93 -> 3.907985e-14
A94: 43190 | B94: POR COBRAR | C94: MARZO | D94: LUZ | E94: 19 | G94: =+G93+E94-F94 -> 19
D95: AGUA | E95: 2 | G95: =+G94+E95-F95 -> 21
D96: ALQUILER | E96: 210 | G96: =+G95+E96-F96 -> 231
A97: 43192 | B97: 14423 | C97: MARZO | D97: ALQUILER | F97: 210 | G97: =+G96+E97-F97 -> 21
A98: 43227 | B98: 14575 | C98: MARZO | D98: LUZ | F98: 19 | G98: =+G97+E98-F98 -> 2
A99: 43227 | B99: 14575 | C99: MARZO | D99: AGUA | F99: 2 | G99: =+G98+E99-F99 -> 2.8421709e-14
A100: 43220 | B100: POR COBRAR | C100: ABRIL | D100: LUZ | E100: 19.6 | G100: =+G99+E100-F100 -> 19.6
D101: AGUA | E101: 2 | G101: =+G100+E101-F101 -> 21.6
D102: ALQUILER | E102: 210 | G102: =+G101+E102-F102 -> 231.6
A103: 43227 | B103: 14575 | C103: ABRIL | D103: ALQUILER | F103: 210 | G103: =+G102+E103-F103 -> 21.6
...

Sheet PEÑA ASHLEY
A3: PEÑA VILLANUEVA ASHLEY MARYORI
I4: DNI | J4: 72336226
A5: FECHA | B5: DOCUMENTO | C5: PERIODO | D5: CONCEPTO | E5: POR COBRAR | F5: PAGADO | G5: SALDO POR COBRAR
A7: 45900 | B7: POR COBRAR | C7: AGOSTO | D7: ALQUILER | E7: 1000 | G7: =G6+E7-F7 -> 1000
D8: GARANTIA | E8: 1000 | G8: =G7+E8-F8 -> 2000
D9: LUZ | E9: 11 | G9: =G8+E9-F9 -> 2011
D10: AGUA | E10: 8 | G10: =G9+E10-F10 -> 2019
A11: 45880 | B11: RII 2947 | C11: AGOSTO | D11: GARANTIA | F11: 1000 | G11: =G10+E11-F11 -> 1019
A12: 45881 | B12: EB01-5865 | C12: AGOSTO | D12: ALQUILER | F12: 1000 | G12: =G11+E12-F12 -> 19
A13: 45953 | B13: RII 3048 | C13: AGOSTO | D13: LUZ | F13: 11 | G13: =G12+E13-F13 -> 8
A14: 45953 | B14: RII 3048 | C14: AGOSTO | D14: AGUA | F14: 8 | G14: =G13+E14-F14 -> 0
A15: 45930 | B15: POR COBRAR | C15: SETIEMBRE | D15: LUZ | E15: 32.7 | G15: =G14+E15-F15 -> 32.7
D16: AGUA | E16: 4 | G16: =G15+E16-F16 -> 36.7 | J16: AGOSTO | K16: LUZ | L16: 11
D17: ALQUILER | E17: 1000 | G17: =G16+E17-F17 -> 1036.7 | K17: AGUA | L17: 8
A18: 45881 | B18: EB01-5865 | C18: SETIEMBRE | D18: ALQUILER | F18: 633 | G18: =G17+E18-F18 -> 403.7 | J18: SETIEMBRE | K18: LUZ | L18: 32.7
A19: 45923 | B19: EB01-6020 | C19: SETIEMBRE | D19: ALQUILER | F19: 367 | G19: =G18+E19-F19 -> 36.7 | K19: AGUA | L19: 4
A20: 45953 | B20: RII 3048 | C20: SETIEMBRE | D20: LUZ | F20: 32.7 | G20: =G19+E20-F20 -> 4
A21: 45953 | B21: RII 3048 | C21: SETIEMBRE | D21: AGUA | F21: 4 | G21: =G20+E21-F21 -> 4.2632564e-14
A22: 45961 | B22: POR COBRAR | C22: OCTUBRE | D22: LUZ | E22: 32.2 | G22: =G21+E22-F22 -> 32.2 | K22: 100 | L22: =SUM(L16:L19) -> 55.7 | M22: =K22-L22 -> 44.3
D23: AGUA | E23: 6 | G23: =G22+E23-F23 -> 38.2
D24: ALQUILER | E24: 1000 | G24: =G23+E24-F24 -> 1038.2 | J24: 2026 | K24: ENERO | L24: LUZ | M24: 30.1
A25: 45933 | B25: EB01-6099 | C25: OCTUBRE | D25: ALQUILER | F25: 1000 | G25: =G24+E25-F25 -> 38.2 | L25: AGUA | M25: 3
A26: 45993 | B26: RII 3125 | C26: OCTUBRE | D26: LUZ | F26: 32.2 | G26: =G25+E26-F26 -> 6 | L26: MULTA X CAPACITACION | M26: 28.3
A27: 45993 | B27: RII 3125 | C27: OCTUBRE | D27: AGUA | F27: 6 | G27: =G26+E27-F27 -> 4.2632564e-14 | M27: =SUM(M24:M26) -> 61.4
A28: 45991 | B28: POR COBRAR | C28: NOVIEMBRE | D28: LUZ | E28: 30.5 | G28: =G27+E28-F28 -> 30.5
D29: AGUA | E29: 5 | G29: =G28+E29-F29 -> 35.5
D30: ALQUILER | E30: 1000 | G30: =G29+E30-F30 -> 1035.5
A31: 45991 | B31: EB01-6261 | C31: NOVIEMBRE | D31: ALQUILER | F31: 1000 | G31: =G30+E31-F31 -> 35.5
A32: 46020 | B32: RII 3150 | C32: NOVIEMBRE | D32: LUZ | F32: 30.5 | G32: =G31+E32-F32 -> 5
A33: 46020 | B33: RII 3150 | C33: NOVIEMBRE | D33: AGUA | F33: 5 | G33: =G32+E33-F33 -> 0 | L33: LUZ | M33: 30.1
A34: 46022 | B34: POR COBRAR | C34: DICIEMBRE | D34: LUZ | E34: 30.9 | G34: =G33+E34-F34 -> 30.9 | L34: AGUA | M34: 3
D35: AGUA | E35: 5 | G35: =G34+E35-F35 -> 35.9 | M35: 1000
D36: ALQUILER | E36: 1000 | G36: =G35+E36-F36 -> 1035.9 | L36: 1100 | M36: =SUM(M33:M35) -> 1033.1 | N36: =L36-M36 -> 66.9
A37: 45993 | B37: EB01-6415 | C37: DICIEMBRE | D37: ALQUILER | F37: 1000 | G37: =G36+E37-F37 -> 35.9
A38: 46055 | B38: RII 3228 | C38: DICIEMBRE | D38: LUZ | F38: 30.9 | G38: =G37+E38-F38 -> 5
A39: 46055 | B39: RII 3228 | C39: DICIEMBRE | D39: AGUA | F39: 5 | G39: =G38+E39-F39 -> 9.2370556e-14
A40: 46053 | B40: POR COBRAR | C40: ENERO | D40: LUZ | E40: 30.1 | G40: =G39+E40-F40 -> 30.1
D41: AGUA | E41: 3 | G41: =G40+E41-F41 -> 33.1
D42: ALQUILER | E42: 1000 | G42: =G41+E42-F42 -> 1033.1
D43: MULTA X CAPACITACION | E43: 28.3 | G43: =G42+E43-F43 -> 1061.4
A44: 46020 | B44: EB01-6546 | C44: ENERO | D44: ALQUILER | F44: 1000 | G44: =G43+E44-F44 -> 61.4
A45: 46086 | B45: RII 3287 | C45: ENERO | D45: LUZ | F45: 30.1 | G45: =G44+E45-F45 -> 31.3
A46: 46086 | B46: RII 3287 | C46: ENERO | D46: AGUA | F46: 3 | G46: =G45+E46-F46 -> 28.3
A47: 46081 | B47: POR COBRAR | C47: FEBRERO | D47: LUZ | E47: 29.6 | G47: =G46+E47-F47 -> 57.9
D48: AGUA | E48: 6 | G48: =G47+E48-F48 -> 63.9
D49: ALQUILER | E49: 1000 | G49: =G48+E49-F49 -> 1063.9
A50: 46055 | B50: EB01-6785 | C50: FEBRERO | D50: ALQUILER | F50: 1000 | G50: =G49+E50-F50 -> 63.9
A51: 46120 | B51: RII 3336 | C51: FEBRERO | D51: LUZ | F51: 29.6 | G51: =G50+E51-F51 -> 34.3
A52: 46120 | B52: RII 3336 | C52: FEBRERO | D52: AGUA | F52: 6 | G52: =G51+E52-F52 -> 28.3
A53: 46112 | B53: POR COBRAR | C53: MARZO | D53: LUZ | E53: 31.1 | G53: =G52+E53-F53 -> 59.4
D54: AGUA | E54: 6 | G54: =G53+E54-F54 -> 65.4
D55: ALQUILER | E55: 1000 | G55: =G54+E55-F55 -> 1065.4 | K55: PEÑA VILLANUEVA ASHLEY MARYORI
A56: 46086 | B56: EB01-6983 | C56: MARZO | D56: ALQUILER | F56: 1000 | G56: =G55+E56-F56 -> 65.4 | J56: 2026 | K56: ENERO | L56: MULTA X CAPACITACION | M56: 28.3
A57: 46142 | B57: POR COBRAR | C57: ABRIL | D57: LUZ | G57: =G56+E57-F57 -> 65.4 | M57: =SUM(M56:M56) -> 28.3
D58: AGUA | G58: =G57+E58-F58 -> 65.4
D59: ALQUILER | E59: 1000 | G59: =G58+E59-F59 -> 1065.4
A60: 46120 | B60: EB01-7164 | C60: ABRIL | D60: ALQUILER | F60: 1000 | G60: =G59+E60-F60 -> 65.4
G61: =G60+E61-F61 -> 65.4
G62: =G61+E62-F62 -> 65.4
G63: =G62+E63-F63 -> 65.4
G64: =G63+E64-F64 -> 65.4
G65: =G64+E65-F65 -> 65.4
G66: =G65+E66-F66 -> 65.4
G67: =G66+E67-F67 -> 65.4
G68: =G67+E68-F68 -> 65.4
G69: =G68+E69-F69 -> 65.4
G70: =G69+E70-F70 -> 65.4
G71: =G70+E71-F71 -> 65.4
G72: =G71+E72-F72 -> 65.4
... G314: =G313+E314-F314 -> 65.4

Sheet PFUÑO VICTOR
B3: PFUÑO RAMOS VICTOR
A5: FECHA | B5: DOCUMENTO | C5: PERIODO | D5: CONCEPTO | E5: POR COBRAR | F5: PAGADO | G5: SALDO POR COBRAR
A6: 42736 | B6: SALDO AL 2016 | G6: 263.1
A7: 42739 | B7: 12022 | C7: ACUENTA DEL 2016 | F7: 36.5 | G7: =+G6+E7-F7 -> 226.6
A8: 42751 | B8: 12093 | C8: ACUENTA DEL 2016 | F8: 226.6 | G8: =+G7+E8-F8 -> 0
A9: 42766 | B9: POR COBRAR | C9: ENERO | D9: LUZ | E9: 13.5 | G9: =+G8+E9-F9 -> 13.5
D10: AGUA | E10: 2.8 | G10: =+G9+E10-F10 -> 16.3
D11: ALQUILER | E11: 210 | G11: =+G10+E11-F11 -> 226.3
A12: 42781 | B12: 12264 | C12: ENERO | D12: ALQUILER | F12: 210 | G12: =+G11+E12-F12 -> 16.3
A13: 42794 | B13: 12305 | C13: ENERO | D13: LUZ | F13: 13.5 | G13: =+G12+E13-F13 -> 2.8
A14: 42794 | B14: 12305 | C14: ENERO | D14: AGUA | F14: 2.8 | G14: =+G13+E14-F14 -> 1.1546319e-14
A15: 42794 | B15: POR COBRAR | C15: FEBRERO | D15: LUZ | E15: 13 | G15: =+G14+E15-F15 -> 13
D16: AGUA | E16: 2 | G16: =+G15+E16-F16 -> 15
D17: ALQUILER | E17: 210 | G17: =+G16+E17-F17 -> 225
A18: 42807 | B18: 12391 | C18: FEBRERO | D18: ALQUILER | F18: 210 | G18: =+G17+E18-F18 -> 15
A19: 42832 | B19: 12497 | C19: FEBRERO | D19: LUZ | F19: 13 | G19: =+G18+E19-F19 -> 2
A20: 42832 | B20: 12497 | C20: FEBRERO | D20: AGUA | F20: 2 | G20: =+G19+E20-F20 -> 0
A21: 42825 | B21: POR COBRAR | C21: MARZO | D21: LUZ | E21: 12 | G21: =+G20+E21-F21 -> 12
D22: AGUA | E22: 2 | G22: =+G21+E22-F22 -> 14
D23: ALQUILER | E23: 210 | G23: =+G22+E23-F23 -> 224
A24: 42835 | B24: 12522 | C24: MARZO | D24: ALQUILER | F24: 210 | G24: =+G23+E24-F24 -> 14
A25: 42863 | B25: 12657 | C25: MARZO | D25: LUZ | F25: 12 | G25: =+G24+E25-F25 -> 2
A26: 42863 | B26: 12657 | C26: MARZO | D26: AGUA | F26: 2 | G26: =+G25+E26-F26 -> 0
A27: 42855 | B27: POR COBRAR | C27: ABRIL | D27: LUZ | E27: 13 | G27: =+G26+E27-F27 -> 13
D28: AGUA | E28: 2 | G28: =+G27+E28-F28 -> 15
D29: ALQUILER | E29: 210 | G29: =+G28+E29-F29 -> 225
A30: 42863 | B30: 12657 | C30: ABRIL | D30: ALQUILER | F30: 210 | G30: =+G29+E30-F30 -> 15
A31: 42891 | B31: 12788 | C31: ABRIL | D31: LUZ | F31: 13 | G31: =+G30+E31-F31 -> 2
A32: 42891 | B32: 12788 | C32: ABRIL | D32: AGUA | F32: 2 | G32: =+G31+E32-F32 -> 0
A33: 42886 | B33: POR COBRAR | C33: MAYO | D33: LUZ | E33: 13 | G33: =+G32+E33-F33 -> 13
D34: AGUA | E34: 2 | G34: =+G33+E34-F34 -> 15
D35: ALQUILER | E35: 210 | G35: =+G34+E35-F35 -> 225
A36: 42900 | B36: 12833 | C36: MAYO | D36: ALQUILER | F36: 210 | G36: =+G35+E36-F36 -> 15
A37: 42927 | B37: 12988 | C37: MAYO | D37: LUZ | F37: 13 | G37: =+G36+E37-F37 -> 2
A38: 42927 | B38: 12988 | C38: MAYO | D38: AGUA | F38: 2 | G38: =+G37+E38-F38 -> 0
A39: 42916 | B39: POR COBRAR | C39: JUNIO | D39: LUZ | E39: 12.5 | G39: =+G38+E39-F39 -> 12.5
D40: AGUA | E40: 2 | G40: =+G39+E40-F40 -> 14.5
D41: ALQUILER | E41: 210 | G41: =+G40+E41-F41 -> 224.5
A42: 42927 | B42: 12988 | C42: JUNIO | D42: ALQUILER | F42: 210 | G42: =+G41+E42-F42 -> 14.5
A43: 42955 | B43: 13243 | C43: JUNIO | D43: LUZ | F43: 12.5 | G43: =+G42+E43-F43 -> 2
A44: 42955 | B44: 13243 | C44: JUNIO | D44: AGUA | F44: 2 | G44: =+G43+E44-F44 -> 0
A45: 42947 | B45: POR COBRAR | C45: JULIO | D45: LUZ | E45: 13 | G45: =+G44+E45-F45 -> 13
D46: AGUA | E46: 2 | G46: =+G45+E46-F46 -> 15
D47: ALQUILER | E47: 210 | G47: =+G46+E47-F47 -> 225
A48: 42955 | B48: 13243 | C48: JULIO | D48: ALQUILER | F48: 210 | G48: =+G47+E48-F48 -> 15
A49: 42986 | B49: 13429 | C49: JULIO | D49: LUZ | F49: 13 | G49: =+G48+E49-F49 -> 2
A50: 42986 | B50: 13429 | C50: JULIO | D50: AGUA | F50: 2 | G50: =+G49+E50-F50 -> 0
A51: 42978 | B51: POR COBRAR | C51: AGOSTO | D51: LUZ | E51: 13 | G51: =+G50+E51-F51 -> 13
D52: AGUA | E52: 2 | G52: =+G51+E52-F52 -> 15
D53: ALQUILER | E53: 210 | G53: =+G52+E53-F53 -> 225
A54: 42986 | B54: 13429 | C54: AGOSTO | D54: ALQUILER | F54: 210 | G54: =+G53+E54-F54 -> 15
A55: 43017 | B55: 13614 | C55: AGOSTO | D55: LUZ | F55: 13 | G55: =+G54+E55-F55 -> 2
A56: 43017 | B56: 13614 | C56: AGOSTO | D56: AGUA | F56: 2 | G56: =+G55+E56-F56 -> 0
A57: 43008 | B57: POR COBRAR | C57: SEPTIEMBRE | D57: LUZ | E57: 8 | G57: =+G56+E57-F57 -> 8
D58: AGUA | E58: 2 | G58: =+G57+E58-F58 -> 10
D59: ALQUILER | E59: 210 | G59: =+G58+E59-F59 -> 220
A60: 43017 | B60: 13614 | C60: SEPTIEMBRE | D60: ALQUILER | F60: 210 | G60: =+G59+E60-F60 -> 10
A61: 42745 | B61: 13776 | C61: SEPTIEMBRE | D61: LUZ | F61: 7.7 | G61: =+G60+E61-F61 -> 2.3
A62: 42745 | B62: 13776 | C62: SEPTIEMBRE | D62: AGUA | F62: 2 | G62: =+G61+E62-F62 -> 0.3
A63: 43130 | B63: 14160 | C63: SEPTIEMBRE | D63: LUZ | F63: 0.3 | G63: =+G62+E63-F63 -> 0
A64: 43039 | B64: POR COBRAR | C64: OCTUBRE | D64: LUZ | E64: 8 | G64: =+G63+E64-F64 -> 8
D65: AGUA | E65: 2 | G65: =+G64+E65-F65 -> 10
D66: ALQUILER | E66: 210 | G66: =+G65+E66-F66 -> 220
A67: 43049 | B67: 13776 | C67: OCTUBRE | D67: ALQUILER | F67: 210 | G67: =+G66+E67-F67 -> 10
A68: 43063 | B68: 13838 | C68: OCTUBRE | D68: LUZ | F68: 8 | G68: =+G67+E68-F68 -> 2
A69: 43063 | B69: 13838 | C69: OCTUBRE | D69: AGUA | F69: 2 | G69: =+G68+E69-F69 -> 0
A70: 43069 | B70: POR COBRAR | C70: NOVIEMBRE | D70: LUZ | E70: 8.2 | G70: =+G69+E70-F70 -> 8.2
D71: AGUA | E71: 2 | G71: =+G70+E71-F71 -> 10.2
D72: ALQUILER | E72: 210 | G72: =+G71+E72-F72 -> 220.2
A73: 43080 | B73: 13927 | C73: NOVIEMBRE | D73: ALQUILER | F73: 210 | G73: =+G72+E73-F73 -> 10.2
A74: 43099 | B74: 14008 | C74: NOVIEMBRE | D74: LUZ | F74: 8.2 | G74: =+G73+E74-F74 -> 2
A75: 43099 | B75: 14008 | C75: NOVIEMBRE | D75: AGUA | F75: 2 | G75: =+G74+E75-F75 -> -1.0658141e-14
A76: 43100 | B76: POR COBRAR | C76: DICIEMBRE | D76: LUZ | E76: 8.9 | G76: =+G75+E76-F76 -> 8.9
D77: AGUA | E77: 2 | G77: =+G76+E77-F77 -> 10.9
D78: ALQUILER | E78: 210 | G78: =+G77+E78-F78 -> 220.9
A79: 43099 | B79: 14008 | C79: DICIEMBRE | D79: ALQUILER | F79: 210 | G79: =+G78+E79-F79 -> 10.9
A80: 43130 | B80: 14160 | C80: DICIEMBRE | D80: LUZ | F80: 8.9 | G80: =+G79+E80-F80 -> 2
A81: 43130 | B81: 14160 | C81: DICIEMBRE | D81: AGUA | F81: 2 | G81: =+G80+E81-F81 -> -2.3092639e-14
A82: 43131 | B82: POR COBRAR | C82: ENERO | D82: LUZ | E82: 8 | G82: =+G81+E82-F82 -> 8
D83: AGUA | E83: 2 | G83: =+G82+E83-F83 -> 10
D84: ALQUILER | E84: 210 | G84: =+G83+E84-F84 -> 220
A85: 43144 | B85: 14209 | C85: ENERO | D85: ALQUILER | F85: 210 | G85: =+G84+E85-F85 -> 10
A86: 43160 | B86: 14301 | C86: ENERO | D86: LUZ | F86: 8 | G86: =+G85+E86-F86 -> 2
A87: 43160 | B87: 14301 | C87: ENERO | D87: AGUA | F87: 2 | G87: =+G86+E87-F87 -> -2.8421709e-14
A88: 43159 | B88: POR COBRAR | C88: FEBRERO | D88: LUZ | E88: 9.9 | G88: =+G87+E88-F88 -> 9.9
D89: AGUA | E89: 2 | G89: =+G88+E89-F89 -> 11.9
D90: ALQUILER | E90: 210 | G90: =+G89+E90-F90 -> 221.9
A91: 43206 | B91: 14483 | C91: FEBRERO | D91: LUZ | F91: 9.9 | G91: =+G90+E91-F91 -> 212
A92: 43206 | B92: 14483 | C92: FEBRERO | D92: AGUA | F92: 2 | G92: =+G91+E92-F92 -> 210
A93: 43174 | B93: 14364 | C93: FEBRERO | D93: ALQUILER | F93: 210 | G93: =+G92+E93-F93 -> 0
A94: 43190 | B94: POR COBRAR | C94: MARZO | D94: LUZ | E94: 9.5 | G94: =+G93+E94-F94 -> 9.5
D95: AGUA | E95: 2 | G95: =+G94+E95-F95 -> 11.5
D96: ALQUILER | E96: 210 | G96: =+G95+E96-F96 -> 221.5
A97: 43206 | B97: 14483 | C97: MARZO | D97: ALQUILER | F97: 210 | G97: =+G96+E97-F97 -> 11.5
A98: 43235 | B98: 14601 | C98: MARZO | D98: LUZ | F98: 9.5 | G98: =+G97+E98-F98 -> 2
A99: 43235 | B99: 14601 | C99: MARZO | D99: AGUA | F99: 2 | G99: =+G98+E99-F99 -> 0
A100: 43220 | B100: POR COBRAR | C100: ABRIL | D100: LUZ | E100: 9.8 | G100: =+G99+E100-F100 -> 9.8
D101: AGUA | E101: 2 | G101: =+G100+E101-F101 -> 11.8
D102: ALQUILER | E102: 210 | G102: =+G101+E102-F102 -> 221.8
A103: 43235 | B103: 14601 | C103: ABRIL | D103: ALQUILER | F103: 210 | G103: =+G102+E103-F103 -> 11.8
...

Sheet PRADO MILAGROS
B3: PRADO CATAÑO MIRIAM MILAGROS
A5: FECHA | B5: DOCUMENTO | C5: PERIODO | D5: CONCEPTO | E5: POR COBRAR | F5: PAGADO | G5: SALDO POR COBRAR
G6: =+E6-F6 -> 0
A7: 43159 | B7: POR COBRAR | C7: FEBRERO | D7: LUZ | E7: 40 | G7: =+G6+E7-F7 -> 40
D8: AGUA | E8: 2 | G8: =+G7+E8-F8 -> 42
D9: ALQUILER | E9: 600 | G9: =+G8+E9-F9 -> 642
D10: GARANTIA | E10: 600 | G10: =+G9+E10-F10 -> 1242
A11: 43145 | B11: 14213 | C11: FEBRERO | D11: ALQUILER | F11: 600 | G11: =+G10+E11-F11 -> 642
A12: 43145 | B12: 14213 | C12: FEBRERO | D12: GARANTIA | F12: 600 | G12: =+G11+E12-F12 -> 42
A13: 43229 | B13: 14584 | C13: FEBRERO | D13: LUZ | F13: 40 | G13: =+G12+E13-F13 -> 2
A14: 43229 | B14: 14584 | C14: FEBRERO | D14: AGUA | F14: 2 | G14: =+G13+E14-F14 -> 0
A15: 43190 | B15: POR COBRAR | C15: MARZO | D15: LUZ | E15: 74.8 | G15: =+G14+E15-F15 -> 74.8
D16: AGUA | E16: 2 | G16: =+G15+E16-F16 -> 76.8
D17: ALQUILER | E17: 600 | G17: =+G16+E17-F17 -> 676.8
A18: 43229 | B18: 14584 | C18: MARZO | D18: LUZ | F18: 74.8 | G18: =+G17+E18-F18 -> 602
A19: 43229 | B19: 14584 | C19: MARZO | D19: AGUA | F19: 2 | G19: =+G18+E19-F19 -> 600
A20: 43229 | B20: 14584 | C20: MARZO | D20: ALQUILER | F20: 600 | G20: =+G19+E20-F20 -> 0
A21: 43220 | B21: POR COBRAR | C21: ABRIL | D21: LUZ | E21: 57.5 | G21: =+G20+E21-F21 -> 57.5
D22: AGUA | E22: 2 | G22: =+G21+E22-F22 -> 59.5
D23: ALQUILER | E23: 600 | G23: =+G22+E23-F23 -> 659.5
D24: MULTA | E24: 10 | G24: =+G23+E24-F24 -> 669.5
A25: 43229 | B25: 15484 | C25: ABRIL | D25: ALQUILER | F25: 600 | G25: =+G24+E25-F25 -> 69.5
A26: 43278 | B26: 14835 | C26: ABRIL | D26: LUZ | F26: 57.5 | G26: =+G25+E26-F26 -> 12
A27: 43278 | B27: 14835 | C27: ABRIL | D27: AGUA | F27: 2 | G27: =+G26+E27-F27 -> 10
A28: 43278 | B28: 14835 | C28: ABRIL | D28: MULTA | F28: 10 | G28: =+G27+E28-F28 -> 0
A29: 43251 | B29: POR COBRAR | C29: MAYO | D29: LUZ | E29: 52.4 | G29: =+G28+E29-F29 -> 52.4
D30: AGUA | E30: 2 | G30: =+G29+E30-F30 -> 54.4
D31: ALQUILER | E31: 600 | G31: =+G30+E31-F31 -> 654.4
A32: 43278 | B32: 14835 | C32: MAYO | D32: LUZ | F32: 52.4 | G32: =+G31+E32-F32 -> 602
A33: 43278 | B33: 14835 | C33: MAYO | D33: AGUA | F33: 2 | G33: =+G32+E33-F33 -> 600
A34: 43278 | B34: 14835 | C34: MAYO | D34: ALQUILER | F34: 600 | G34: =+G33+E34-F34 -> 0
A35: 43281 | B35: POR COBRAR | C35: JUNIO | D35: LUZ | E35: 48.4 | G35: =+G34+E35-F35 -> 48.4
D36: AGUA | E36: 4 | G36: =+G35+E36-F36 -> 52.4
D37: ALQUILER | E37: 600 | G37: =+G36+E37-F37 -> 652.4
A38: 43336 | B38: 15104 | C38: JUNIO | D38: LUZ | F38: 48.4 | G38: =+G37+E38-F38 -> 604
A39: 43336 | B39: 15104 | C39: JUNIO | D39: AGUA | F39: 4 | G39: =+G38+E39-F39 -> 600
A40: 43336 | B40: 15104 | C40: JUNIO | D40: ALQUILER | F40: 600 | G40: =+G39+E40-F40 -> 0
A41: 43312 | B41: POR COBRAR | C41: JULIO | D41: LUZ | E41: 47.4 | G41: =+G40+E41-F41 -> 47.4
D42: AGUA | E42: 2 | G42: =+G41+E42-F42 -> 49.4
D43: ALQUILER | E43: 600 | G43: =+G42+E43-F43 -> 649.4
A44: 43374 | B44: 15291 | C44: JULIO | D44: ALQUILER | F44: 110 | G44: =+G43+E44-F44 -> 539.4
A45: 43391 | B45: 15353 | C45: JULIO | D45: LUZ | F45: 47.4 | G45: =+G44+E45-F45 -> 492
A46: 43391 | B46: 15353 | C46: JULIO | D46: AGUA | F46: 2 | G46: =+G45+E46-F46 -> 490
A47: 43391 | B47: 15353 | C47: JULIO | D47: ALQUILER | F47: 490 | G47: =+G46+E47-F47 -> 0
A48: 43343 | B48: POR COBRAR | C48: AGOSTO | D48: LUZ | E48: 47.3 | G48: =+G47+E48-F48 -> 47.3
D49: AGUA | E49: 2 | G49: =+G48+E49-F49 -> 49.3
D50: ALQUILER | E50: 600 | G50: =+G49+E50-F50 -> 649.3
A51: 43391 | B51: 15353 | C51: AGOSTO | D51: ALQUILER | F51: 160.6 | G51: =+G50+E51-F51 -> 488.7
A52: 43412 | B52: 15476 | C52: AGOSTO | D52: ALQUILER | F52: 439.4 | G52: =+G51+E52-F52 -> 49.3
A53: 43412 | B53: 15476 | C53: AGOSTO | D53: LUZ | F53: 47.3 | G53: =+G52+E53-F53 -> 2
A54: 43412 | B54: 15476 | C54: AGOSTO | D54: AGUA | F54: 2 | G54: =+G53+E54-F54 -> -4.2632564e-14
A55: 43373 | B55: POR COBRAR | C55: SETIEMBRE | D55: LUZ | E55: 48.3 | G55: =+G54+E55-F55 -> 48.3
D56: AGUA | E56: 4 | G56: =+G55+E56-F56 -> 52.3
D57: ALQUILER | E57: 600 | G57: =+G56+E57-F57 -> 652.3
A58: 43412 | B58: 15476 | C58: SETIEMBRE | D58: LUZ | F58: 11.3 | G58: =+G57+E58-F58 -> 641
A59: 43434 | B59: 15561 | C59: SETIEMBRE | D59: ALQUILER | F59: 370 | G59: =+G58+E59-F59 -> 271
A60: 43455 | B60: 15634 | C60: SETIEMBRE | D60: LUZ | F60: 37 | G60: =+G59+E60-F60 -> 234
A61: 43455 | B61: 15634 | C61: SETIEMBRE | D61: AGUA | F61: 4 | G61: =+G60+E61-F61 -> 230
A62: 43455 | B62: 15634 | C62: SETIEMBRE | D62: ALQUILER | F62: 230 | G62: =+G61+E62-F62 -> 0
A63: 43404 | B63: POR COBRAR | C63: OCTUBRE | D63: LUZ | E63: 48.6 | G63: =+G62+E63-F63 -> 48.6
D64: AGUA | E64: 5 | G64: =+G63+E64-F64 -> 53.6
D65: ALQUILER | E65: 600 | G65: =+G64+E65-F65 -> 653.6
A66: 43455 | B66: 15634 | C66: OCTUBRE | D66: LUZ | F66: 48.6 | G66: =+G65+E66-F66 -> 605
A67: 43455 | B67: 15634 | C67: OCTUBRE | D67: AGUA | F67: 5 | G67: =+G66+E67-F67 -> 600
A68: 43455 | B68: 15634 | C68: OCTUBRE | D68: ALQUILER | F68: 600 | G68: =+G67+E68-F68 -> 0
A69: 43434 | B69: POR COBRAR | C69: NOVIEMBRE | D69: LUZ | E69: 49.9 | G69: =+G68+E69-F69 -> 49.9
D70: AGUA | E70: 5 | G70: =+G69+E70-F70 -> 54.9
D71: ALQUILER | E71: 600 | G71: =+G70+E71-F71 -> 654.9
A72: 43455 | B72: 15634 | C72: NOVIEMBRE | D72: ALQUILER | F72: 75.4 | G72: =+G71+E72-F72 -> 579.5
A73: 43830 | B73: 15707 | C73: NOVIEMBRE | D73: ALQUILER | F73: 24.6 | G73: =+G72+E73-F73 -> 554.9
A74: 43472 | B74: 15751 | C74: NOVIEMBRE | D74: ALQUILER | F74: 500 | G74: =+G73+E74-F74 -> 54.9
A75: 43487 | B75: 15809 | C75: NOVIEMBRE | D75: LUZ | F75: 49.9 | G75: =+G74+E75-F75 -> 5
A76: 43487 | B76: 15809 | C76: NOVIEMBRE | D76: AGUA | F76: 5 | G76: =+G75+E76-F76 -> -2.1316282e-14
A77: 43465 | B77: POR COBRAR | C77: DICIEMBRE | D77: LUZ | E77: 53.4 | G77: =+G76+E77-F77 -> 53.4
D78: AGUA | E78: 5 | G78: =+G77+E78-F78 -> 58.4
D79: ALQUILER | E79: 600 | G79: =+G78+E79-F79 -> 658.4
A80: 43830 | B80: 15707 | C80: DICIEMBRE | D80: ALQUILER | F80: 375.4 | G80: =+G79+E80-F80 -> 283
A81: 43487 | B81: 15809 | C81: DICIEMBRE | D81: ALQUILER | F81: 224.6 | G81: =+G80+E81-F81 -> 58.4
A82: 43591 | B82: B001-0000226 | C82: DICIEMBRE | D82: LUZ | F82: 53.4 | G82: =+G81+E82-F82 -> 5
A83: 43591 | B83: B001-0000226 | C83: DICIEMBRE | D83: AGUA | F83: 5 | G83: =+G82+E83-F83 -> 7.1054274e-15
A84: 43496 | B84: POR COBRAR | C84: ENERO | D84: LUZ | E84: 61.6 | G84: =+G83+E84-F84 -> 61.6
D85: AGUA | E85: 5 | G85: =+G84+E85-F85 -> 66.6
D86: ALQUILER | E86: 600 | G86: =+G85+E86-F86 -> 666.6
A87: 43496 | B87: 15888 | C87: ENERO | D87: ALQUILER | F87: 360 | G87: =+G86+E87-F87 -> 306.6
A88: 43554 | B88: B001-0000119 | C88: ENERO | D88: ALQUILER | F88: 165 | G88: =+G87+E88-F88 -> 141.6
A89: 43591 | B89: B001-0000226 | C89: ENERO | D89: LUZ | F89: 61.6 | G89: =+G88+E89-F89 -> 80
A90: 43591 | B90: B001-0000226 | C90: ENERO | D90: AGUA | F90: 5 | G90: =+G89+E90-F90 -> 75
A91: 43591 | B91: B001-0000226 | C91: ENERO | D91: ALQUILER | F91: 75 | G91: =+G90+E91-F91 -> 0
A92: 43524 | B92: POR COBRAR | C92: FEBRERO | D92: LUZ | E92: 65.2 | G92: =+G91+E92-F92 -> 65.2
D93: AGUA | E93: 6.1 | G93: =+G92+E93-F93 -> 71.3
D94: ALQUILER | E94: 600 | G94: =+G93+E94-F94 -> 671.3
A95: 43591 | B95: B001-0000226 | C95: FEBRERO | D95: ALQUILER | F95: 300 | G95: =+G94+E95-F95 -> 371.3
A96: 43594 | B96: B001-0000238 | C96: FEBRERO | D96: ALQUILER | F96: 300 | G96: =+G95+E96-F96 -> 71.3
A97: 43594 | B97: B001-0000238 | C97: FEBRERO | D97: LUZ | F97: 65.2 | G97: =+G96+E97-F97 -> 6.1
A98: 43594 | B98: B001-0000238 | C98: FEBRERO | D98: AGUA | F98: 6.1 | G98: =+G97+E98-F98 -> -4.7961635e-14
A99: 43555 | B99: POR COBRAR | C99: MARZO | D99: LUZ | E99: 60.5 | G99: =+G98+E99-F99 -> 60.5
D100: AGUA | E100: 4.9 | G100: =+G99+E100-F100 -> 65.4
D101: ALQUILER | E101: 600 | G101: =+G100+E101-F101 -> 665.4
A102: 43594 | B102: B001-0000238 | C102: MARZO | D102: ALQUILER | F102: 128.7 | G102: =+G101+E102-F102 -> 536.7
A103: 43671 | B103: B001-0000450 | C103: MARZO | D103: ALQUILER | F103: 471.3 | G103: =+G102+E103-F103 -> 65.4
...

Sheet QUISPE MARISOL
A3: QUISPE CHAVEZ MARISOL
A5: FECHA | B5: DOCUMENTO | C5: PERIODO | D5: CONCEPTO | E5: POR COBRAR | F5: PAGADO | G5: SALDO POR COBRAR
A6: 42736 | B6: SALDO AL 2016 | G6: 701.9
A7: 42737 | B7: 11995 | C7: ACUENTA DEL 2016 | F7: 570 | G7: =+G6+E7-F7 -> 131.9
A8: 42737 | B8: 11996 | C8: ACUENTA DEL 2016 | F8: 25 | G8: =+G7+E8-F8 -> 106.9
A9: 42751 | B9: 12088 | C9: CANCELACION DEL 2016 | F9: 106.9 | G9: =+G8+E9-F9 -> 0
A10: 42766 | B10: POR COBRAR | C10: ENERO | D10: LUZ | E10: 29.8 | G10: =+G9+E10-F10 -> 29.8
D11: AGUA | E11: 2.8 | G11: =+G10+E11-F11 -> 32.6
D12: ALQUILER | E12: 500 | G12: =+G11+E12-F12 -> 532.6
A13: 42800 | B13: 12337 | C13: ENERO | D13: ALQUILER | F13: 500 | G13: =+G12+E13-F13 -> 32.6
A14: 42805 | B14: 12380 | C14: ENERO | D14: LUZ | F14: 29.8 | G14: =+G13+E14-F14 -> 2.8
A15: 42805 | B15: 12380 | C15: ENERO | D15: AGUA | F15: 2.8 | G15: =+G14+E15-F15 -> 2.220446e-14
A16: 42794 | B16: POR COBRAR | C16: FEBRERO | D16: LUZ | E16: 29.8 | G16: =+G15+E16-F16 -> 29.8
D17: AGUA | E17: 2 | G17: =+G16+E17-F17 -> 31.8
D18: ALQUILER | E18: 500 | G18: =+G17+E18-F18 -> 531.8
A19: 42832 | B19: 12511 | C19: FEBRERO | D19: LUZ | F19: 29.8 | G19: =+G18+E19-F19 -> 502
A20: 42832 | B20: 12511 | C20: FEBRERO | D20: AGUA | F20: 2 | G20: =+G19+E20-F20 -> 500
A21: 42857 | B21: 12579 | C21: FEBRERO | D21: ALQUILER | F21: 500 | G21: =+G20+E21-F21 -> 0
A22: 42825 | B22: POR COBRAR | C22: MARZO | D22: LUZ | E22: 37.6 | G22: =+G21+E22-F22 -> 37.6
D23: AGUA | E23: 2 | G23: =+G22+E23-F23 -> 39.6
D24: ALQUILER | E24: 500 | G24: =+G23+E24-F24 -> 539.6
A25: 42870 | B25: 12682 | C25: MARZO | D25: ALQUILER | F25: 500 | G25: =+G24+E25-F25 -> 39.6
A26: 42885 | B26: 12741 | C26: MARZO | D26: LUZ | F26: 37.6 | G26: =+G25+E26-F26 -> 2
A27: 42908 | B27: 12869 | C27: MARZO | D27: AGUA | F27: 2 | G27: =+G26+E27-F27 -> 2.1316282e-14
A28: 42855 | B28: POR COBRAR | C28: ABRIL | D28: LUZ | E28: 38.8 | G28: =+G27+E28-F28 -> 38.8
D29: AGUA | E29: 2 | G29: =+G28+E29-F29 -> 40.8
D30: ALQUILER | E30: 500 | G30: =+G29+E30-F30 -> 540.8
A31: 42908 | B31: 12869 | C31: ABRIL | D31: LUZ | F31: 38.8 | G31: =+G30+E31-F31 -> 502
A32: 42908 | B32: 12870 | C32: ABRIL | D32: AGUA | F32: 2 | G32: =+G31+E32-F32 -> 500
A33: 42927 | B33: 12985 | C33: ABRIL | D33: ALQUILER | F33: 500 | G33: =+G32+E33-F33 -> 0
A34: 42886 | B34: POR COBRAR | C34: MAYO | D34: LUZ | E34: 36.8 | G34: =+G33+E34-F34 -> 36.8
D35: AGUA | E35: 2 | G35: =+G34+E35-F35 -> 38.8
D36: ALQUILER | E36: 500 | G36: =+G35+E36-F36 -> 538.8
A37: 42927 | B37: 12985 | C37: MAYO | D37: LUZ | F37: 36.8 | G37: =+G36+E37-F37 -> 502
A38: 42927 | B38: 12985 | C38: MAYO | D38: AGUA | F38: 2 | G38: =+G37+E38-F38 -> 500
A39: 42959 | B39: 13256 | C39: MAYO | D39: ALQUILER | F39: 500 | G39: =+G38+E39-F39 -> 0
A40: 42916 | B40: POR COBRAR | C40: JUNIO | D40: LUZ | E40: 35.8 | G40: =+G39+E40-F40 -> 35.8
D41: AGUA | E41: 2 | G41: =+G40+E41-F41 -> 37.8
D42: ALQUILER | E42: 500 | G42: =+G41+E42-F42 -> 537.8
A43: 42962 | B43: 13270 | C43: JUNIO | D43: ALQUILER | F43: 500 | G43: =+G42+E43-F43 -> 37.8
A44: 42965 | B44: 13283 | C44: JUNIO | D44: LUZ | F44: 35.8 | G44: =+G43+E44-F44 -> 2
A45: 42965 | B45: 13283 | C45: JUNIO | D45: AGUA | F45: 2 | G45: =+G44+E45-F45 -> -4.2632564e-14
A46: 42947 | B46: POR COBRAR | C46: JULIO | D46: LUZ | E46: 33.4 | G46: =+G45+E46-F46 -> 33.4
D47: AGUA | E47: 2 | G47: =+G46+E47-F47 -> 35.4
D48: ALQUILER | E48: 500 | G48: =+G47+E48-F48 -> 535.4
A49: 42965 | B49: 13283 | C49: JULIO | D49: ALQUILER | F49: 462.2 | G49: =+G48+E49-F49 -> 73.2
