Workbook
Name _Hlk159238530: 'CCENCHO DAVID'!$J$633

Sheet AIRE HECTOR
B3: AIRE MALPARTIDA HECTOR
A5: FECHA | B5: DOCUMENTO | C5: PERIODO | D5: CONCEPTO | E5: POR COBRAR | F5: PAGADO | G5: SALDO POR COBRAR
A6: 42736 | B6: SALDO AL 2016 | G6: 66.7
A7: 42766 | B7: 12184 | C7: A CUENTA 2016 | F7: 66.7 | G7: =+G6+E7-F7 -> 0
A8: 42766 | B8: POR COBRAR | C8: ENERO | D8: LUZ | E8: 66.8 | G8: =+G7+E8-F8 -> 66.8
D9: AGUA | E9: 2.8 | G9: =+G8+E9-F9 -> 69.6
D10: ALQUILER | E10: 450 | G10: =+G9+E10-F10 -> 519.6
A11: 42766 | B11: 12184 | C11: ENERO | D11: ALQUILER | F11: 450 | G11: =+G10+E11-F11 -> 69.6
A12: 42796 | B12: 12321 | C12: ENERO | D12: LUZ | F12: 66.8 | G12: =+G11+E12-F12 -> 2.8
A13: 42796 | B13: 12321 | C13: ENERO | D13: AGUA | F13: 2.8 | G13: =+G12+E13-F13 -> 2.5757174e-14
A14: 42794 | B14: POR COBRAR | C14: FEBRERO | D14: LUZ | E14: 94.8 | G14: =+G13+E14-F14 -> 94.8
D15: AGUA | E15: 2 | G15: =+G14+E15-F15 -> 96.8
D16: ALQUILER | E16: 450 | G16: =+G15+E16-F16 -> 546.8
A17: 42796 | B17: 12320 | C17: FEBRERO | D17: ALQUILER | F17: 450 | G17: =+G16+E17-F17 -> 96.8
A18: 42832 | B18: 12498 | C18: FEBRERO | D18: LUZ | F18: 94.8 | G18: =+G17+E18-F18 -> 2
A19: 42832 | B19: 12498 | C19: FEBRERO | D19: AGUA | F19: 2 | G19: =+G18+E19-F19 -> 7.1054274e-14
A20: 42825 | B20: POR COBRAR | C20: MARZO | D20: LUZ | E20: 69.5 | G20: =+G19+E20-F20 -> 69.5
D21: AGUA | E21: 2 | G21: =+G20+E21-F21 -> 71.5
D22: ALQUILER | E22: 450 | G22: =+G21+E22-F22 -> 521.5
A23: 42832 | B23: 12499 | C23: MARZO | D23: ALQUILER | F23: 450 | G23: =+G22+E23-F23 -> 71.5
A24: 42886 | B24: 12753 | C24: MARZO | D24: LUZ | F24: 69.5 | G24: =+G23+E24-F24 -> 2
A25: 42886 | B25: 12753 | C25: MARZO | D25: AGUA | F25: 2 | G25: =+G24+E25-F25 -> 1.1368684e-13
A26: 42855 | B26: POR COBRAR | C26: ABRIL | D26: LUZ | E26: 43.1 | G26: =+G25+E26-F26 -> 43.1
D27: AGUA | E27: 2 | G27: =+G26+E27-F27 -> 45.1
D28: ALQUILER | E28: 450 | G28: =+G27+E28-F28 -> 495.1
A29: 42886 | B29: 12753 | C29: ABRIL | D29: ALQUILER | F29: 450 | G29: =+G28+E29-F29 -> 45.1
A30: 42886 | B30: 12753 | C30: ABRIL | D30: LUZ | F30: 43.1 | G30: =+G29+E30-F30 -> 2
A31: 42886 | B31: 12753 | C31: ABRIL | D31: AGUA | F31: 2 | G31: =+G30+E31-F31 -> 1.3500312e-13
A32: 42886 | B32: POR COBRAR | C32: MAYO | D32: LUZ | E32: 66.5 | G32: =+G31+E32-F32 -> 66.5
D33: AGUA | E33: 2 | G33: =+G32+E33-F33 -> 68.5
D34: ALQUILER | E34: 450 | G34: =+G33+E34-F34 -> 518.5
A35: 42930 | B35: 13015 | C35: MAYO | D35: ALQUILER | F35: 450 | G35: =+G34+E35-F35 -> 68.5
A36: 42930 | B36: 13015 | C36: MAYO | D36: LUZ | F36: 66.5 | G36: =+G35+E36-F36 -> 2
A37: 42930 | B37: 13015 | C37: MAYO | D37: AGUA | F37: 2 | G37: =+G36+E37-F37 -> 1.1368684e-13
A38: 42916 | B38: POR COBRAR | C38: JUNIO | D38: LUZ | E38: 64.9 | G38: =+G37+E38-F38 -> 64.9
D39: AGUA | E39: 2 | G39: =+G38+E39-F39 -> 66.9
D40: ALQUILER | E40: 450 | G40: =+G39+E40-F40 -> 516.9
A41: 42930 | B41: 13015 | C41: JUNIO | D41: ALQUILER | F41: 450 | G41: =+G40+E41-F41 -> 66.9
A42: 42956 | B42: 13251 | C42: JUNIO | D42: LUZ | F42: 64.9 | G42: =+G41+E42-F42 -> 2
A43: 42956 | B43: 13251 | C43: JUNIO | D43: AGUA | F43: 2 | G43: =+G42+E43-F43 -> 8.5265128e-14
A44: 42947 | B44: POR COBRAR | C44: JULIO | D44: LUZ | E44: 58.9 | G44: =+G43+E44-F44 -> 58.9
D45: AGUA | E45: 2 | G45: =+G44+E45-F45 -> 60.9
D46: ALQUILER | E46: 450 | G46: =+G45+E46-F46 -> 510.9
A47: 42930 | B47: 13015 | C47: JULIO | D47: ALQUILER | F47: 450 | G47: =+G46+E47-F47 -> 60.9
A48: 42971 | B48: 13314 | C48: JULIO | D48: LUZ | F48: 58.9 | G48: =+G47+E48-F48 -> 2
A49: 42971 | B49: 13314 | C49: JULIO | D49: AGUA | F49: 2 | G49: =+G48+E49-F49 -> 9.2370556e-14
A50: 42978 | B50: POR COBRAR | C50: AGOSTO | D50: LUZ | E50: 58.9 | G50: =+G49+E50-F50 -> 58.9
D51: AGUA | E51: 2 | G51: =+G50+E51-F51 -> 60.9
D52: ALQUILER | E52: 450 | G52: =+G51+E52-F52 -> 510.9
A53: 42984 | B53: 13396 | C53: AGOSTO | D53: ALQUILER | F53: 450 | G53: =+G52+E53-F53 -> 60.9
A54: 43011 | B54: 13592 | C54: AGOSTO | D54: LUZ | F54: 58.9 | G54: =+G53+E54-F54 -> 2
A55: 43011 | B55: 13592 | C55: AGOSTO | D55: AGUA | F55: 2 | G55: =+G54+E55-F55 -> 9.2370556e-14
A56: 43008 | B56: POR COBRAR | C56: SEPTIEMBRE | D56: LUZ | E56: 60 | G56: =+G55+E56-F56 -> 60
D57: AGUA | E57: 2 | G57: =+G56+E57-F57 -> 62
D58: ALQUILER | E58: 450 | G58: =+G57+E58-F58 -> 512
A59: 42984 | B59: 13396 | C59: SEPTIEMBRE | D59: ALQUILER | F59: 450 | G59: =+G58+E59-F59 -> 62
A60: 43049 | B60: 13780 | C60: SEPTIEMBRE | D60: LUZ | F60: 56 | G60: =+G59+E60-F60 -> 6
A61: 43049 | B61: 13780 | C61: SEPTIEMBRE | D61: AGUA | F61: 2 | G61: =+G60+E61-F61 -> 4
A62: 43115 | B62: 14073 | C62: SEPTIEMBRE | D62: LUZ | F62: 4 | G62: =+G61+E62-F62 -> 1.1368684e-13
A63: 43039 | B63: POR COBRAR | C63: OCTUBRE | D63: LUZ | E63: 60 | G63: =+G62+E63-F63 -> 60
D64: AGUA | E64: 2 | G64: =+G63+E64-F64 -> 62
D65: ALQUILER | E65: 450 | G65: =+G64+E65-F65 -> 512
A66: 43049 | B66: 13780 | C66: OCTUBRE | D66: ALQUILER | F66: 450 | G66: =+G65+E66-F66 -> 62
A67: 43063 | B67: 13830 | C67: OCTUBRE | D67: LUZ | F67: 59.7 | G67: =+G66+E67-F67 -> 2.3
A68: 43063 | B68: 13830 | C68: OCTUBRE | D68: AGUA | F68: 2 | G68: =+G67+E68-F68 -> 0.3
A69: 43115 | B69: 14073 | C69: OCTUBRE | D69: LUZ | F69: 0.3 | G69: =+G68+E69-F69 -> 1.1085577e-13
A70: 43069 | B70: POR COBRAR | C70: NOVIEMBRE | D70: LUZ | E70: 63.7 | G70: =+G69+E70-F70 -> 63.7
D71: AGUA | E71: 2 | G71: =+G70+E71-F71 -> 65.7
D72: ALQUILER | E72: 450 | G72: =+G71+E72-F72 -> 515.7
A73: 43095 | B73: 13974 | C73: NOVIEMBRE | D73: ALQUILER | F73: 450 | G73: =+G72+E73-F73 -> 65.7
A74: 43115 | B74: 14073 | C74: NOVIEMBRE | D74: LUZ | F74: 63.7 | G74: =+G73+E74-F74 -> 2
A75: 43115 | B75: 14073 | C75: NOVIEMBRE | D75: AGUA | F75: 2 | G75: =+G74+E75-F75 -> 1.563194e-13
A76: 43465 | B76: POR COBRAR | C76: DICIEMBRE | D76: LUZ | E76: 69.3 | G76: =+G75+E76-F76 -> 69.3
D77: AGUA | E77: 2 | G77: =+G76+E77-F77 -> 71.3
D78: ALQUILER | E78: 450 | G78: =+G77+E78-F78 -> 521.3
A79: 43095 | B79: 13974 | C79: DICIEMBRE | D79: ALQUILER | F79: 450 | G79: =+G78+E79-F79 -> 71.3
A80: 43118 | B80: 14108 | C80: DICIEMBRE | D80: LUZ | F80: 69.3 | G80: =+G79+E80-F80 -> 2
A81: 43118 | B81: 14108 | C81: DICIEMBRE | D81: AGUA | F81: 2 | G81: =+G80+E81-F81 -> 1.8474111e-13
A82: 43131 | B82: POR COBRAR | C82: ENERO | D82: LUZ | E82: 61.7 | G82: =+G81+E82-F82 -> 61.7
D83: AGUA | E83: 2 | G83: =+G82+E83-F83 -> 63.7
D84: ALQUILER | E84: 450 | G84: =+G83+E84-F84 -> 513.7
A85: 43153 | B85: 14243 | C85: ENERO | D85: LUZ | F85: 61.7 | G85: =+G84+E85-F85 -> 452
A86: 43153 | B86: 14243 | C86: ENERO | D86: AGUA | F86: 2 | G86: =+G85+E86-F86 -> 450
A87: 43153 | B87: 14243 | C87: ENERO | D87: ALQUILER | F87: 450 | G87: =+G86+E87-F87 -> 0
A88: 43159 | B88: POR COBRAR | C88: FEBRERO | D88: LUZ | E88: 66.5 | G88: =+G87+E88-F88 -> 66.5
D89: AGUA | E89: 2 | G89: =+G88+E89-F89 -> 68.5
D90: ALQUILER | E90: 450 | G90: =+G89+E90-F90 -> 518.5
A91: 43179 | B91: 14376 | C91: FEBRERO | D91: LUZ | F91: 66.5 | G91: =+G90+E91-F91 -> 452
A92: 43179 | B92: 14376 | C92: FEBRERO | D92: AGUA | F92: 2 | G92: =+G91+E92-F92 -> 450
A93: 43216 | B93: 14512 | C93: FEBRERO | D93: ALQUILER | F93: 450 | G93: =+G92+E93-F93 -> 0
A94: 43190 | B94: POR COBRAR | C94: MARZO | D94: LUZ | E94: 63.9 | G94: =+G93+E94-F94 -> 63.9
D95: AGUA | E95: 2 | G95: =+G94+E95-F95 -> 65.9
D96: ALQUILER | E96: 450 | G96: =+G95+E96-F96 -> 515.9
A97: 43216 | B97: 14512 | C97: MARZO | D97: LUZ | F97: 63.9 | G97: =+G96+E97-F97 -> 452
A98: 43216 | B98: 14512 | C98: MARZO | D98: AGUA | F98: 2 | G98: =+G97+E98-F98 -> 450
A99: 43228 | B99: 14580 | C99: MARZO | D99: ALQUILER | F99: 450 | G99: =+G98+E99-F99 -> 0
A100: 43220 | B100: POR COBRAR | C100: ABRIL | D100: LUZ | E100: 66 | G100: =+G99+E100-F100 -> 66
D101: AGUA | E101: 2 | G101: =+G100+E101-F101 -> 68
D102: ALQUILER | E102: 450 | G102: =+G101+E102-F102 -> 518
A103: 43243 | B103: 14667 | C103: ABRIL | D103: LUZ | F103: 66 | G103: =+G102+E103-F103 -> 452
...

Sheet ALARCON MARTHA
B3: ALARCON ESPINOZA MARTHA
A5: FECHA | B5: DOCUMENTO | C5: PERIODO | D5: CONCEPTO | E5: POR COBRAR | F5: PAGADO | G5: SALDO POR COBRAR
A6: 42736 | B6: SALDO AL 2016 | G6: 283.1
A7: 42751 | B7: 12095 | C7: CANCELACION DEL 2016 | F7: 283.1 | G7: =+G6+E7-F7 -> 0
A8: 42766 | B8: POR COBRAR | C8: ENERO | D8: LUZ | E8: 13.5 | G8: =+G7+E8-F8 -> 13.5
D9: AGUA | E9: 2.8 | G9: =+G8+E9-F9 -> 16.3
D10: ALQUILER | E10: 500 | G10: =+G9+E10-F10 -> 516.3
A11: 42766 | B11: 12180 | C11: ENERO | D11: ALQUILER | F11: 250 | G11: =+G10+E11-F11 -> 266.3
A12: 42783 | B12: 12272 | C12: ENERO | D12: ALQUILER | F12: 250 | G12: =+G11+E12-F12 -> 16.3
A13: 42832 | B13: 12500 | C13: ENERO | D13: LUZ | F13: 13.5 | G13: =+G12+E13-F13 -> 2.8
A14: 42832 | B14: 12500 | C14: ENERO | D14: AGUA | F14: 2.8 | G14: =+G13+E14-F14 -> -4.5297099e-14
A15: 42794 | B15: POR COBRAR | C15: FEBRERO | D15: LUZ | E15: 13 | G15: =+G14+E15-F15 -> 13
D16: AGUA | E16: 2 | G16: =+G15+E16-F16 -> 15
D17: ALQUILER | E17: 500 | G17: =+G16+E17-F17 -> 515
A18: 42796 | B18: 12318 | C18: FEBRERO | D18: ALQUILER | F18: 500 | G18: =+G17+E18-F18 -> 15
A19: 42832 | B19: 12500 | C19: FEBRERO | D19: LUZ | F19: 13 | G19: =+G18+E19-F19 -> 2
A20: 42832 | B20: 12500 | C20: FEBRERO | D20: AGUA | F20: 2 | G20: =+G19+E20-F20 -> 0
A21: 42825 | B21: POR COBRAR | C21: MARZO | D21: LUZ | E21: 12 | G21: =+G20+E21-F21 -> 12
D22: AGUA | E22: 2 | G22: =+G21+E22-F22 -> 14
D23: ALQUILER | E23: 500 | G23: =+G22+E23-F23 -> 514
A24: 42831 | B24: 12485 | C24: MARZO | D24: ALQUILER | F24: 500 | G24: =+G23+E24-F24 -> 14
A25: 42847 | B25: 12568 | C25: MARZO | D25: LUZ | F25: 12 | G25: =+G24+E25-F25 -> 2
A26: 42847 | B26: 12568 | C26: MARZO | D26: AGUA | F26: 2 | G26: =+G25+E26-F26 -> 0
A27: 42855 | B27: POR COBRAR | C27: ABRIL | D27: LUZ | E27: 13 | G27: =+G26+E27-F27 -> 13
D28: AGUA | E28: 2 | G28: =+G27+E28-F28 -> 15
D29: ALQUILER | E29: 500 | G29: =+G28+E29-F29 -> 515
A30: 42840 | B30: 12539 | C30: ABRIL | D30: ALQUILER | F30: 500 | G30: =+G29+E30-F30 -> 15
A31: 42887 | B31: 12761 | C31: ABRIL | D31: LUZ | F31: 13 | G31: =+G30+E31-F31 -> 2
A32: 42887 | B32: 12761 | C32: ABRIL | D32: AGUA | F32: 2 | G32: =+G31+E32-F32 -> 0
A33: 42886 | B33: POR COBRAR | C33: MAYO | D33: LUZ | E33: 13 | G33: =+G32+E33-F33 -> 13
D34: AGUA | E34: 2 | G34: =+G33+E34-F34 -> 15
D35: ALQUILER | E35: 500 | G35: =+G34+E35-F35 -> 515
A36: 42870 | B36: 12683 | C36: MAYO | D36: ALQUILER | F36: 500 | G36: =+G35+E36-F36 -> 15
A37: 42947 | B37: 13064 | C37: MAYO | D37: LUZ | F37: 13 | G37: =+G36+E37-F37 -> 2
A38: 42947 | B38: 13064 | C38: MAYO | D38: AGUA | F38: 2 | G38: =+G37+E38-F38 -> 0
A39: 42916 | B39: POR COBRAR | C39: JUNIO | D39: LUZ | E39: 12.5 | G39: =+G38+E39-F39 -> 12.5
D40: AGUA | E40: 2 | G40: =+G39+E40-F40 -> 14.5
D41: ALQUILER | E41: 500 | G41: =+G40+E41-F41 -> 514.5
A42: 42902 | B42: 12837 | C42: JUNIO | D42: ALQUILER | F42: 500 | G42: =+G41+E42-F42 -> 14.5
A43: 42947 | B43: 13064 | C43: JUNIO | D43: LUZ | F43: 12.5 | G43: =+G42+E43-F43 -> 2
A44: 42947 | B44: 13064 | C44: JUNIO | D44: AGUA | F44: 2 | G44: =+G43+E44-F44 -> 0
A45: 42947 | B45: POR COBRAR | D45: LUZ | E45: 13 | G45: =+G44+E45-F45 -> 13
D46: AGUA | E46: 2 | G46: =+G45+E46-F46 -> 15
D47: ALQUILER | E47: 500 | G47: =+G46+E47-F47 -> 515
A48: 42931 | B48: 13020 | C48: JULIO | D48: ALQUILER | F48: 500 | G48: =+G47+E48-F48 -> 15
A49: 43024 | B49: 13634 | C49: JULIO | D49: LUZ | F49: 13 | G49: =+G48+E49-F49 -> 2
A50: 43024 | B50: 13634 | C50: JULIO | D50: AGUA | F50: 2 | G50: =+G49+E50-F50 -> 0
A51: 42978 | B51: POR COBRAR | C51: AGOSTO | D51: LUZ | E51: 13 | G51: =+G50+E51-F51 -> 13
D52: AGUA | E52: 2 | G52: =+G51+E52-F52 -> 15
D53: ALQUILER | E53: 500 | G53: =+G52+E53-F53 -> 515
A54: 42966 | B54: 13262 | C54: AGOSTO | D54: ALQUILER | F54: 500 | G54: =+G53+E54-F54 -> 15
A55: 43024 | B55: 13634 | C55: AGOSTO | D55: LUZ | F55: 13 | G55: =+G54+E55-F55 -> 2
A56: 43024 | B56: 13634 | C56: AGOSTO | D56: AGUA | F56: 2 | G56: =+G55+E56-F56 -> 0
A57: 43008 | B57: POR COBRAR | C57: SEPTIEMBRE | D57: LUZ | E57: 8 | G57: =+G56+E57-F57 -> 8
D58: AGUA | E58: 2 | G58: =+G57+E58-F58 -> 10
D59: ALQUILER | E59: 500 | G59: =+G58+E59-F59 -> 510
A60: 42993 | B60: 13468 | C60: SEPTIEMBRE | D60: ALQUILER | F60: 500 | G60: =+G59+E60-F60 -> 10
A61: 43055 | B61: 13789 | C61: SEPTIEMBRE | D61: LUZ | F61: 8 | G61: =+G60+E61-F61 -> 2
A62: 43055 | B62: 13789 | C62: SEPTIEMBRE | D62: AGUA | F62: 2 | G62: =+G61+E62-F62 -> 0
A63: 43039 | B63: POR COBRAR | C63: OCTUBRE | D63: LUZ | E63: 8 | G63: =+G62+E63-F63 -> 8
D64: AGUA | E64: 2 | G64: =+G63+E64-F64 -> 10
D65: ALQUILER | E65: 500 | G65: =+G64+E65-F65 -> 510
A66: 43024 | B66: 13634 | C66: OCTUBRE | D66: ALQUILER | F66: 500 | G66: =+G65+E66-F66 -> 10
A67: 43115 | B67: 14069 | C67: OCTUBRE | D67: LUZ | F67: 8 | G67: =+G66+E67-F67 -> 2
A68: 43115 | B68: 14069 | C68: OCTUBRE | D68: AGUA | F68: 2 | G68: =+G67+E68-F68 -> 0
A69: 43069 | B69: POR COBRAR | C69: NOVIEMBRE | D69: LUZ | E69: 8.2 | G69: =+G68+E69-F69 -> 8.2
D70: AGUA | E70: 2 | G70: =+G69+E70-F70 -> 10.2
D71: ALQUILER | E71: 500 | G71: =+G70+E71-F71 -> 510.2
A72: 43055 | B72: 13789 | C72: NOVIEMBRE | D72: ALQUILER | F72: 500 | G72: =+G71+E72-F72 -> 10.2
A73: 43084 | B73: 13935 | C73: NOVIEMBRE | D73: LUZ | F73: 8 | G73: =+G72+E73-F73 -> 2.2
A74: 43084 | B74: 13935 | C74: NOVIEMBRE | D74: AGUA | F74: 2 | G74: =+G73+E74-F74 -> 0.2
A75: 43115 | B75: 14069 | C75: NOVIEMBRE | D75: LUZ | F75: 0.2 | G75: =+G74+E75-F75 -> -1.1379786e-14
A76: 43100 | B76: POR COBRAR | C76: DICIEMBRE | D76: LUZ | E76: 8.9 | G76: =+G75+E76-F76 -> 8.9
D77: AGUA | E77: 2 | G77: =+G76+E77-F77 -> 10.9
D78: ALQUILER | E78: 500 | G78: =+G77+E78-F78 -> 510.9
A79: 43084 | B79: 13935 | C79: DICIEMBRE | D79: ALQUILER | F79: 500 | G79: =+G78+E79-F79 -> 10.9
A80: 43118 | B80: 14091 | C80: DICIEMBRE | D80: LUZ | F80: 8.9 | G80: =+G79+E80-F80 -> 2
A81: 43118 | B81: 14091 | C81: DICIEMBRE | D81: AGUA | F81: 2 | G81: =+G80+E81-F81 -> -2.3092639e-14
A82: 43101 | B82: POR COBRAR | C82: ENERO | D82: LUZ | E82: 8 | G82: =+G81+E82-F82 -> 8
D83: AGUA | E83: 2 | G83: =+G82+E83-F83 -> 10
D84: ALQUILER | E84: 500 | G84: =+G83+E84-F84 -> 510
A85: 43115 | B85: 14069 | C85: ENERO | D85: ALQUILER | F85: 500 | G85: =+G84+E85-F85 -> 10
A86: 43256 | B86: 14751 | C86: ENERO | D86: LUZ | F86: 8 | G86: =+G85+E86-F86 -> 2
A87: 43256 | B87: 14751 | C87: ENERO | D87: AGUA | F87: 2 | G87: =+G86+E87-F87 -> 0
A88: 43159 | B88: POR COBRAR | C88: FEBRERO | D88: LUZ | E88: 25.9 | G88: =+G87+E88-F88 -> 25.9
D89: AGUA | E89: 2 | G89: =+G88+E89-F89 -> 27.9
D90: ALQUILER | E90: 500 | G90: =+G89+E90-F90 -> 527.9
A91: 43146 | B91: 14219 | C91: FEBRERO | D91: ALQUILER | F91: 500 | G91: =+G90+E91-F91 -> 27.9
A92: 43256 | B92: 14751 | C92: FEBRERO | D92: LUZ | F92: 25.9 | G92: =+G91+E92-F92 -> 2
A93: 43256 | B93: 14751 | C93: FEBRERO | D93: AGUA | F93: 2 | G93: =+G92+E93-F93 -> -2.1316282e-14
A94: 43190 | B94: POR COBRAR | C94: MARZO | D94: LUZ | E94: 24.8 | G94: =+G93+E94-F94 -> 24.8
D95: AGUA | E95: 2 | G95: =+G94+E95-F95 -> 26.8
D96: ALQUILER | E96: 500 | G96: =+G95+E96-F96 -> 526.8
A97: 43174 | B97: 14831 | C97: MARZO | D97: ALQUILER | F97: 500 | G97: =+G96+E97-F97 -> 26.8
A98: 43256 | B98: 14751 | C98: MARZO | D98: LUZ | F98: 24.8 | G98: =+G97+E98-F98 -> 2
A99: 43256 | B99: 14751 | C99: MARZO | D99: AGUA | F99: 2 | G99: =+G98+E99-F99 -> -4.6185278e-14
A100: 43220 | B100: POR COBRAR | C100: ABRIL | D100: LUZ | E100: 25.7 | G100: =+G99+E100-F100 -> 25.7
D101: AGUA | E101: 2 | G101: =+G100+E101-F101 -> 27.7
D102: ALQUILER | E102: 500 | G102: =+G101+E102-F102 -> 527.7
A103: 43206 | B103: 14485 | C103: ABRIL | D103: ALQUILER | F103: 500 | G103: =+G102+E103-F103 -> 27.7
...

Sheet ALVARO GUSTAVO
B2: ALVARO HUAMANI GUSTAVO
A4: FECHA | B4: DOCUMENTO | C4: PERIODO | D4: CONCEPTO | E4: POR COBRAR | F4: PAGADO | G4: SALDO POR COBRAR
A6: 44804 | B6: POR COBRAR | C6: AGOSTO | D6: ALQUILER | E6: 300 | G6: =G5+E6-F6 -> 300
G7: =G6+E7-F7 -> 300
A8: 45142 | B8: EB01-1112 | C8: AGOSTO | D8: ALQUILER | F8: 300 | G8: =G7+E8-F8 -> 0
G9: =G8+E9-F9 -> 0
D10: LUZ | E10: 21.6 | G10: =G9+E10-F10 -> 21.6
D11: AGUA | E11: 7 | G11: =G10+E11-F11 -> 28.6
A12: 44956 | B12: RII 1360 | C12: AGOSTO | D12: LUZ | F12: 20 | G12: =G11+E12-F12 -> 8.6
A13: 45033 | B13: RII 1507 | C13: AGOSTO | D13: LUZ | F13: 1.6 | G13: =G12+E13-F13 -> 7
A14: 45033 | B14: RII 1507 | C14: AGOSTO | D14: AGUA | F14: 7 | G14: =G13+E14-F14 -> 0
A15: 44834 | B15: POR COBRAR | C15: SETIEMBRE | D15: ALQUILER | E15: 300 | G15: =G14+E15-F15 -> 300
D16: LUZ | E16: 25.5 | G16: =G15+E16-F16 -> 325.5
D17: AGUA | E17: 8.2 | G17: =G16+E17-F17 -> 333.7
A18: 44838 | B18: EB01-1327 | C18: SETIEMBRE | D18: ALQUILER | F18: 300 | G18: =G17+E18-F18 -> 33.7
A19: 45033 | B19: RII 1507 | C19: SETIEMBRE | D19: LUZ | F19: 25.5 | G19: =G18+E19-F19 -> 8.2
A20: 45033 | B20: RII 1507 | C20: SETIEMBRE | D20: AGUA | F20: 8.2 | G20: =G19+E20-F20 -> 0
A21: 44834 | B21: POR COBRAR | C21: OCTUBRE | D21: ALQUILER | E21: 300 | G21: =G20+E21-F21 -> 300
D22: LUZ | E22: 25.4 | G22: =G21+E22-F22 -> 325.4
D23: AGUA | E23: 4.9 | G23: =G22+E23-F23 -> 330.3
A24: 44895 | B24: EB01-1499 | C24: OCTUBRE | D24: ALQUILER | F24: 300 | G24: =G23+E24-F24 -> 30.3
A25: 45033 | B25: RII 1507 | C25: OCTUBRE | D25: LUZ | F25: 25.4 | G25: =G24+E25-F25 -> 4.9
A26: 45033 | B26: RII 1507 | C26: OCTUBRE | D26: AGUA | F26: 4.9 | G26: =G25+E26-F26 -> -4.4408921e-14
A27: 44834 | B27: POR COBRAR | C27: NOVIEMBRE | D27: LUZ | E27: 28.4 | G27: =G26+E27-F27 -> 28.4
D28: AGUA | E28: 6.3 | G28: =G27+E28-F28 -> 34.7
D29: ALQUILER | E29: 300 | G29: =G28+E29-F29 -> 334.7
A30: 44922 | B30: EB01-1589 | C30: NOVIEMBRE | D30: ALQUILER | F30: 300 | G30: =G29+E30-F30 -> 34.7
A31: 45033 | B31: RII 1507 | C31: NOVIEMBRE | D31: LUZ | F31: 28.4 | G31: =G30+E31-F31 -> 6.3
A32: 45033 | B32: RII 1507 | C32: NOVIEMBRE | D32: AGUA | F32: 6.3 | G32: =G31+E32-F32 -> -6.6613381e-14
A33: 44926 | B33: POR COBRAR | C33: DICIEMBRE | D33: LUZ | E33: 32.5 | G33: =G32+E33-F33 -> 32.5
D34: AGUA | E34: 5.7 | G34: =G33+E34-F34 -> 38.2
D35: ALQUILER | E35: 300 | G35: =G34+E35-F35 -> 338.2
A36: 44956 | B36: EB01-1701 | C36: DICIEMBRE | D36: ALQUILER | F36: 300 | G36: =G35+E36-F36 -> 38.2
A37: 45033 | B37: RII 1507 | C37: DICIEMBRE | D37: LUZ | F37: 32.5 | G37: =G36+E37-F37 -> 5.7
A38: 45033 | B38: RII 1507 | C38: DICIEMBRE | D38: AGUA | F38: 5.7 | G38: =G37+E38-F38 -> -6.8389738e-14
A39: 44926 | B39: POR COBRAR | C39: ENERO | D39: LUZ | E39: 35.5 | G39: =G38+E39-F39 -> 35.5
D40: AGUA | E40: 4.8 | G40: =G39+E40-F40 -> 40.3
D41: ALQUILER | E41: 300 | G41: =G40+E41-F41 -> 340.3
A42: 44985 | B42: EB01-1812 | C42: ENERO | D42: ALQUILER | F42: 300 | G42: =G41+E42-F42 -> 40.3
A43: 45033 | B43: RII 1507 | C43: ENERO | D43: LUZ | F43: 35.5 | G43: =G42+E43-F43 -> 4.8
A44: 45033 | B44: RII 1507 | C44: ENERO | D44: AGUA | F44: 4.8 | G44: =G43+E44-F44 -> -4.5297099e-14
A45: 44985 | B45: POR COBRAR | C45: FEBRERO | D45: LUZ | E45: 38.7 | G45: =G44+E45-F45 -> 38.7
D46: AGUA | E46: 1.2 | G46: =G45+E46-F46 -> 39.9
D47: ALQUILER | E47: 300 | G47: =G46+E47-F47 -> 339.9
A48: 45017 | B48: EB01-1978 | C48: FEBRERO | D48: ALQUILER | F48: 300 | G48: =G47+E48-F48 -> 39.9
A49: 45033 | B49: RII 1508 | C49: FEBRERO | D49: LUZ | F49: 38.7 | G49: =G48+E49-F49 -> 1.2
A50: 45033 | B50: RII 1508 | C50: FEBRERO | D50: AGUA | F50: 1.2 | G50: =G49+E50-F50 -> -2.553513e-14
A51: 45016 | B51: POR COBRAR | C51: MARZO | D51: LUZ | E51: 35.6 | G51: =G50+E51-F51 -> 35.6
D52: AGUA | E52: 1.3 | G52: =G51+E52-F52 -> 36.9
D53: ALQUILER | E53: 300 | G53: =G52+E53-F53 -> 336.9
A54: 45063 | B54: EB01-2147 | C54: MARZO | D54: ALQUILER | F54: 163.1 | G54: =G53+E54-F54 -> 173.8
A55: 45063 | B55: RII 1564 | C55: MARZO | D55: LUZ | F55: 35.6 | G55: =G54+E55-F55 -> 138.2
A56: 45063 | B56: RII 1564 | C56: MARZO | D56: AGUA | F56: 1.3 | G56: =G55+E56-F56 -> 136.9
A57: 45076 | B57: EB01-2182 | C57: MARZO | D57: ALQUILER | F57: 136.9 | G57: =G56+E57-F57 -> 0
A58: 45016 | B58: POR COBRAR | C58: ABRIL | D58: LUZ | E58: 37.3 | G58: =G57+E58-F58 -> 37.3
D59: AGUA | E59: 1.5 | G59: =G58+E59-F59 -> 38.8
D60: ALQUILER | E60: 300 | G60: =G59+E60-F60 -> 338.8
A61: 45076 | B61: EB01-2182 | C61: ABRIL | D61: ALQUILER | F61: 63.1 | G61: =G60+E61-F61 -> 275.7
A62: 45122 | B62: EB01-2399 | C62: ABRIL | D62: ALQUILER | F62: 236.9 | G62: =G61+E62-F62 -> 38.8
A63: 45148 | B63: RII 1711 | C63: ABRIL | D63: LUZ | F63: 37.3 | G63: =G62+E63-F63 -> 1.5
A64: 45148 | B64: RII 1711 | C64: ABRIL | D64: AGUA | F64: 1.5 | G64: =G63+E64-F64 -> -1.4210855e-14
A65: 45077 | B65: POR COBRAR | C65: MAYO | D65: LUZ | E65: 34.5 | G65: =G64+E65-F65 -> 34.5
D66: AGUA | E66: 2.1 | G66: =G65+E66-F66 -> 36.6
D67: ALQUILER | E67: 300 | G67: =G66+E67-F67 -> 336.6
D68: TALONARIO MAMÁ | E68: 10 | G68: =G67+E68-F68 -> 346.6
A69: 45115 | B69: EB01-2366 | C69: MAYO | D69: ALQUILER | F69: 300 | G69: =G68+E69-F69 -> 46.6
A70: 45148 | B70: RII 1711 | C70: MAYO | D70: LUZ | F70: 24.3 | G70: =G69+E70-F70 -> 22.3
A71: 45176 | B71: RII 1760 | C71: MAYO | D71: LUZ | F71: 10.2 | G71: =G70+E71-F71 -> 12.1
A72: 45176 | B72: RII 1760 | C72: MAYO | D72: AGUA | F72: 2.1 | G72: =G71+E72-F72 -> 10
A73: 45176 | B73: RII 1760 | C73: MAYO | D73: TALONARIO MAMÁ | F73: 10 | G73: =G72+E73-F73 -> -3.375078e-14
A74: 45107 | B74: POR COBRAR | C74: JUNIO | D74: LUZ | E74: 35.1 | G74: =G73+E74-F74 -> 35.1
D75: AGUA | E75: 2 | G75: =G74+E75-F75 -> 37.1
D76: ALQUILER | E76: 300 | G76: =G75+E76-F76 -> 337.1
A77: 45122 | B77: EB01-2399 | C77: JUNIO | D77: ALQUILER | F77: 163.1 | G77: =G76+E77-F77 -> 174
A78: 45148 | B78: EB01-2514 | C78: JUNIO | D78: ALQUILER | F78: 136.9 | G78: =G77+E78-F78 -> 37.1
A79: 45176 | B79: RII 1760 | C79: JUNIO | D79: LUZ | F79: 35.1 | G79: =G78+E79-F79 -> 2
A80: 45176 | B80: RII 1760 | C80: JUNIO | D80: AGUA | F80: 2 | G80: =G79+E80-F80 -> -3.5527137e-14
A81: 45138 | B81: POR COBRAR | C81: JULIO | D81: LUZ | E81: 33.1 | G81: =G80+E81-F81 -> 33.1
D82: AGUA | E82: 2 | G82: =G81+E82-F82 -> 35.1
D83: ALQUILER | E83: 300 | G83: =G82+E83-F83 -> 335.1 | J83: ALVARO HUAMANI GUSTAVO
A84: 45176 | B84: RII 1760 | C84: JULIO | D84: LUZ | F84: 33.1 | G84: =G83+E84-F84 -> 302 | I84: 2023 | J84: AGOSTO | K84: LUZ | L84: 31.6
A85: 45176 | B85: RII 1760 | C85: JULIO | D85: AGUA | F85: 2 | G85: =G84+E85-F85 -> 300 | K85: AGUA | L85: 2.3
A86: 45176 | B86: EB01-2624 | C86: JULIO | D86: ALQUILER | F86: 300 | G86: =G85+E86-F86 -> 0 | K86: ALQUILER | L86: 44.5
A87: 45169 | B87: POR COBRAR | C87: AGOSTO | D87: LUZ | E87: 31.6 | G87: =G86+E87-F87 -> 31.6 | K87: TALONARIO SANTA ROSA | L87: 10
D88: AGUA | E88: 2.3 | G88: =G87+E88-F88 -> 33.9 | J88: SETIEMBRE | K88: LUZ | L88: 31.5
D89: ALQUILER | E89: 300 | G89: =G88+E89-F89 -> 333.9 | K89: AGUA | L89: 2
D90: TALONARIO SANTA ROSA | E90: 10 | G90: =G89+E90-F90 -> 343.9 | K90: ALQUILER | L90: 300
A91: 45176 | B91: EB01-2624 | C91: AGOSTO | D91: ALQUILER | F91: 5.5 | G91: =G90+E91-F91 -> 338.4 | L91: =SUM(L84:L90) -> 421.9
A92: 45205 | B92: EB01-2754 | C92: AGOSTO | D92: ALQUILER | F92: 250 | G92: =G91+E92-F92 -> 88.4
A93: 45225 | B93: RII 1847 | C93: AGOSTO | D93: LUZ | F93: 31.6 | G93: =G92+E93-F93 -> 56.8
A94: 45225 | B94: RII 1847 | C94: AGOSTO | D94: AGUA | F94: 2.3 | G94: =G93+E94-F94 -> 54.5
A95: 45225 | B95: RII 1847 | C95: AGOSTO | D95: TALONARIO SANTA ROSA | F95: 10 | G95: =G94+E95-F95 -> 44.5
A96: 45225 | B96: EB01-2815 | C96: AGOSTO | D96: ALQUILER | F96: 44.5 | G96: =G95+E96-F96 -> 0
A97: 45199 | B97: POR COBRAR | C97: SETIEMBRE | D97: LUZ | E97: 31.5 | G97: =G96+E97-F97 -> 31.5
D98: AGUA | E98: 2 | G98: =G97+E98-F98 -> 33.5
D99: ALQUILER | E99: 300 | G99: =G98+E99-F99 -> 333.5
A100: 45225 | B100: RII 1847 | C100: SETIEMBRE | D100: LUZ | F100: 31.5 | G100: =G99+E100-F100 -> 302
A101: 45225 | B101: RII 1847 | C101: SETIEMBRE | D101: AGUA | F101: 2 | G101: =G100+E101-F101 -> 300
A102: 45225 | B102: EB01-2815 | C102: SETIEMBRE | D102: ALQUILER | F102: 78.1 | G102: =G101+E102-F102 -> 221.9
A103: 45234 | B103: EB01-2868 | C103: SETIEMBRE | D103: ALQUILER | F103: 150 | G103: =G102+E103-F103 -> 71.9
...

Sheet ALVAREZ EDGAR
B3: ALVAREZ CHIARA EDGAR SALVADOR
A5: FECHA | B5: DOCUMENTO | C5: PERIODO | D5: CONCEPTO | E5: POR COBRAR | F5: PAGADO | G5: SALDO POR COBRAR
A6: 42736 | B6: SALDO AL 2016 | G6: 766.5
A7: 42767 | B7: 12192 | C7: A CUENTA DEL 2016 | F7: 16.5 | G7: =+G6+E7-F7 -> 750
A8: 42859 | B8: 12623 | C8: A CUENTA DEL 2016 | F8: 80 | G8: =+G7+E8-F8 -> 670
A9: 42898 | B9: 12815 | C9: A CUENTA DEL 2016 | F9: 110 | G9: =+G8+E9-F9 -> 560
A10: 42916 | B10: 12897 | C10: A CUENTA DEL 2016 | F10: 70 | G10: =+G9+E10-F10 -> 490
A11: 42947 | B11: 13076 | C11: A CUENTA DEL 2016 | F11: 200 | G11: =+G10+E11-F11 -> 290
A12: 42979 | B12: 13361 | C12: A CUENTA DEL 2016 | F12: 170 | G12: =+G11+E12-F12 -> 120
A13: 43008 | B13: 13559 | C13: A CUENTA DEL 2016 | F13: 90 | G13: =+G12+E13-F13 -> 30
A14: 43039 | B14: 13730 | C14: A CUENTA DEL 2016 | F14: 30 | G14: =+G13+E14-F14 -> 0
A15: 42766 | B15: POR COBRAR | C15: ENERO | D15: LUZ | E15: 13.5 | G15: =+G14+E15-F15 -> 13.5
D16: AGUA | E16: 2.8 | G16: =+G15+E16-F16 -> 16.3
D17: ALQUILER | E17: 300 | G17: =+G16+E17-F17 -> 316.3
A18: 42767 | B18: 12192 | C18: ENERO | D18: ALQUILER | F18: 300 | G18: =+G17+E18-F18 -> 16.3
A19: 42797 | B19: 12324 | C19: ENERO | D19: LUZ | F19: 13.5 | G19: =+G18+E19-F19 -> 2.8
A20: 42797 | B20: 12324 | C20: ENERO | D20: AGUA | F20: 2.8 | G20: =+G19+E20-F20 -> 1.1546319e-14
A21: 42794 | B21: POR COBRAR | C21: FEBRERO | D21: LUZ | E21: 21.8 | G21: =+G20+E21-F21 -> 21.8
D22: AGUA | E22: 2 | G22: =+G21+E22-F22 -> 23.8
D23: ALQUILER | E23: 300 | G23: =+G22+E23-F23 -> 323.8
A24: 42797 | B24: 12324 | C24: FEBRERO | D24: ALQUILER | F24: 300 | G24: =+G23+E24-F24 -> 23.8
A25: 42828 | B25: 12462 | C25: FEBRERO | D25: LUZ | F25: 21.8 | G25: =+G24+E25-F25 -> 2
A26: 42828 | B26: 12462 | C26: FEBRERO | D26: AGUA | F26: 2 | G26: =+G25+E26-F26 -> 1.0658141e-14
A27: 42825 | B27: POR COBRAR | C27: MARZO | D27: LUZ | E27: 20.5 | G27: =+G26+E27-F27 -> 20.5
D28: AGUA | E28: 2 | G28: =+G27+E28-F28 -> 22.5
D29: ALQUILER | E29: 300 | G29: =+G28+E29-F29 -> 322.5
A30: 42828 | B30: 12462 | C30: MARZO | D30: ALQUILER | F30: 300 | G30: =+G29+E30-F30 -> 22.5
A31: 42857 | B31: 12583 | C31: MARZO | D31: LUZ | F31: 20.5 | G31: =+G30+E31-F31 -> 2
A32: 42857 | B32: 12583 | C32: MARZO | D32: AGUA | F32: 2 | G32: =+G31+E32-F32 -> 0
A33: 42855 | B33: POR COBRAR | C33: ABRIL | D33: LUZ | E33: 21.6 | G33: =+G32+E33-F33 -> 21.6
D34: AGUA | E34: 2 | G34: =+G33+E34-F34 -> 23.6
D35: ALQUILER | E35: 300 | G35: =+G34+E35-F35 -> 323.6
A36: 42857 | B36: 12583 | C36: ABRIL | D36: ALQUILER | F36: 300 | G36: =+G35+E36-F36 -> 23.6
A37: 42887 | B37: 12758 | C37: ABRIL | D37: LUZ | F37: 21.6 | G37: =+G36+E37-F37 -> 2
A38: 42887 | B38: 12758 | C38: ABRIL | D38: AGUA | F38: 2 | G38: =+G37+E38-F38 -> 2.1316282e-14
A39: 42886 | B39: POR COBRAR | C39: MAYO | D39: LUZ | E39: 20.9 | G39: =+G38+E39-F39 -> 20.9
D40: AGUA | E40: 2 | G40: =+G39+E40-F40 -> 22.9
D41: ALQUILER | E41: 300 | G41: =+G40+E41-F41 -> 322.9
A42: 42887 | B42: 12758 | C42: MAYO | D42: ALQUILER | F42: 300 | G42: =+G41+E42-F42 -> 22.9
A43: 42919 | B43: 12933 | C43: MAYO | D43: LUZ | F43: 20.9 | G43: =+G42+E43-F43 -> 2
A44: 42919 | B44: 12933 | C44: MAYO | D44: AGUA | F44: 2 | G44: =+G43+E44-F44 -> 3.5527137e-14
A45: 42916 | B45: POR COBRAR | D45: LUZ | E45: 20.3 | G45: =+G44+E45-F45 -> 20.3
D46: AGUA | E46: 2 | G46: =+G45+E46-F46 -> 22.3
D47: ALQUILER | E47: 300 | G47: =+G46+E47-F47 -> 322.3
A48: 42919 | B48: 12933 | C48: JUNIO | D48: ALQUILER | F48: 300 | G48: =+G47+E48-F48 -> 22.3
A49: 42949 | B49: 13208 | C49: JUNIO | D49: LUZ | F49: 20.3 | G49: =+G48+E49-F49 -> 2
A50: 42949 | B50: 13208 | C50: JUNIO | D50: AGUA | F50: 2 | G50: =+G49+E50-F50 -> 1.0658141e-14
A51: 42947 | B51: POR COBRAR | C51: JULIO | D51: LUZ | E51: 19.8 | G51: =+G50+E51-F51 -> 19.8
D52: AGUA | E52: 2 | G52: =+G51+E52-F52 -> 21.8
D53: ALQUILER | E53: 300 | G53: =+G52+E53-F53 -> 321.8
A54: 42949 | B54: 13207 | C54: JULIO | D54: ALQUILER | F54: 300 | G54: =+G53+E54-F54 -> 21.8
A55: 42984 | B55: 13402 | C55: JULIO | D55: LUZ | F55: 19.8 | G55: =+G54+E55-F55 -> 2
A56: 42984 | B56: 13402 | C56: JULIO | D56: AGUA | F56: 2 | G56: =+G55+E56-F56 -> 1.0658141e-14
A57: 42978 | B57: POR COBRAR | C57: AGOSTO | D57: LUZ | E57: 19.8 | G57: =+G56+E57-F57 -> 19.8
D58: AGUA | E58: 2 | G58: =+G57+E58-F58 -> 21.8
D59: ALQUILER | E59: 300 | G59: =+G58+E59-F59 -> 321.8
A60: 42984 | B60: 13402 | C60: AGOSTO | D60: ALQUILER | F60: 300 | G60: =+G59+E60-F60 -> 21.8
A61: 43063 | B61: 13836 | C61: AGOSTO | D61: LUZ | F61: 15.4 | G61: =+G60+E61-F61 -> 6.4
A62: 43063 | B62: 13836 | C62: AGOSTO | D62: AGUA | F62: 2 | G62: =+G61+E62-F62 -> 4.4
A63: 43096 | B63: 13977 | C63: AGOSTO | D63: LUZ | F63: 4.4 | G63: =+G62+E63-F63 -> 1.0658141e-14
A64: 43008 | B64: POR COBRAR | C64: SEPTIEMBRE | D64: LUZ | E64: 15.5 | G64: =+G63+E64-F64 -> 15.5
D65: AGUA | E65: 2 | G65: =+G64+E65-F65 -> 17.5
D66: ALQUILER | E66: 300 | G66: =+G65+E66-F66 -> 317.5
A67: 43015 | B67: 13613 | C67: SEPTIEMBRE | D67: ALQUILER | F67: 300 | G67: =+G66+E67-F67 -> 17.5
A68: 43096 | B68: 13977 | C68: SEPTIEMBRE | D68: LUZ | F68: 15.5 | G68: =+G67+E68-F68 -> 2
A69: 43096 | B69: 13977 | C69: SEPTIEMBRE | D69: AGUA | F69: 2 | G69: =+G68+E69-F69 -> 0
A70: 43039 | B70: POR COBRAR | C70: OCTUBRE | D70: LUZ | E70: 15.4 | G70: =+G69+E70-F70 -> 15.4
D71: AGUA | E71: 2 | G71: =+G70+E71-F71 -> 17.4
D72: ALQUILER | E72: 300 | G72: =+G71+E72-F72 -> 317.4
A73: 43039 | B73: 13730 | C73: OCTUBRE | D73: ALQUILER | F73: 10 | G73: =+G72+E73-F73 -> 307.4
A74: 43073 | B74: 13894 | C74: OCTUBRE | D74: ALQUILER | F74: 290 | G74: =+G73+E74-F74 -> 17.4
A75: 43096 | B75: 13977 | C75: OCTUBRE | D75: LUZ | F75: 15.4 | G75: =+G74+E75-F75 -> 2
A76: 43096 | B76: 13977 | C76: OCTUBRE | D76: AGUA | F76: 2 | G76: =+G75+E76-F76 -> -2.3092639e-14
A77: 43069 | B77: POR COBRAR | C77: NOVIEMBRE | D77: LUZ | E77: 16.4 | G77: =+G76+E77-F77 -> 16.4
D78: AGUA | E78: 2 | G78: =+G77+E78-F78 -> 18.4
D79: ALQUILER | E79: 300 | G79: =+G78+E79-F79 -> 318.4
A80: 43073 | B80: 13894 | C80: NOVIEMBRE | D80: ALQUILER | F80: 10 | G80: =+G79+E80-F80 -> 308.4
A81: 43096 | B81: 13977 | C81: NOVIEMBRE | D81: LUZ | F81: 16.4 | G81: =+G80+E81-F81 -> 292
A82: 43096 | B82: 13977 | C82: NOVIEMBRE | D82: AGUA | F82: 2 | G82: =+G81+E82-F82 -> 290
A83: 43102 | B83: 14029 | C83: NOVIEMBRE | D83: ALQUILER | F83: 290 | G83: =+G82+E83-F83 -> 0
A84: 43100 | B84: POR COBRAR | C84: DICIEMBRE | D84: LUZ | E84: 17.9 | G84: =+G83+E84-F84 -> 17.9
D85: AGUA | E85: 2 | G85: =+G84+E85-F85 -> 19.9
D86: ALQUILER | E86: 300 | G86: =+G85+E86-F86 -> 319.9
A87: 43102 | C87: DICIEMBRE | D87: ALQUILER | F87: 10 | G87: =+G86+E87-F87 -> 309.9
A88: 43118 | B88: 14096 | C88: DICIEMBRE | D88: LUZ | F88: 17.9 | G88: =+G87+E88-F88 -> 292
A89: 43118 | B89: 14096 | C89: DICIEMBRE | D89: AGUA | F89: 2 | G89: =+G88+E89-F89 -> 290
A90: 43138 | B90: 14192 | C90: DICIEMBRE | D90: ALQUILER | F90: 290 | G90: =+G89+E90-F90 -> 0
A91: 43131 | B91: POR COBRAR | C91: ENERO | D91: LUZ | E91: 15.9 | G91: =+G90+E91-F91 -> 15.9
D92: AGUA | E92: 2 | G92: =+G91+E92-F92 -> 17.9
D93: ALQUILER | E93: 300 | G93: =+G92+E93-F93 -> 317.9
A94: 43138 | B94: 14192 | C94: ENERO | D94: ALQUILER | F94: 10 | G94: =+G93+E94-F94 -> 307.9
A95: 43158 | B95: 14252 | C95: ENERO | D95: LUZ | F95: 15.9 | G95: =+G94+E95-F95 -> 292
A96: 43158 | B96: 14252 | C96: ENERO | D96: AGUA | F96: 2 | G96: =+G95+E96-F96 -> 290
A97: 43164 | B97: 14327 | C97: ENERO | D97: ALQUILER | F97: 290 | G97: =+G96+E97-F97 -> 0
A98: 43159 | B98: POR COBRAR | C98: FEBRERO | D98: LUZ | E98: 19.7 | G98: =+G97+E98-F98 -> 19.7
D99: AGUA | E99: 2 | G99: =+G98+E99-F99 -> 21.7
D100: ALQUILER | E100: 300 | G100: =+G99+E100-F100 -> 321.7
A101: 43164 | B101: 14327 | C101: FEBRERO | D101: ALQUILER | F101: 10 | G101: =+G100+E101-F101 -> 311.7
A102: 43199 | B102: 14447 | C102: FEBRERO | D102: ALQUILER | F102: 290 | G102: =+G101+E102-F102 -> 21.7
A103: 43199 | B103: 14447 | C103: FEBRERO | D103: LUZ | F103: 19.7 | G103: =+G102+E103-F103 -> 2
...

Sheet ALVAREZ FLORENCIA
A2: ALVAREZ BERRIO FLORENCIA | I2: DNI | J2: 8877133 | K2: 10 DE CADA MES
A3: FECHA | B3: DOCUMENTO | C3: PERIODO | D3: CONCEPTO | E3: POR COBRAR | F3: PAGADO | G3: SALDO POR COBRAR
A5: 46053 | B5: POR COBRAR | C5: ENERO | D5: LUZ | E5: 14.3 | G5: =+G4+E5-F5 -> 14.3
D6: AGUA | E6: 3 | G6: =+G5+E6-F6 -> 17.3
D7: ALQUILER | E7: 700 | G7: =+G6+E7-F7 -> 717.3
D8: GARANTIA | E8: 1000 | G8: =+G7+E8-F8 -> 1717.3
D9: MULTA X CAPACITACION | E9: 28.3 | G9: =+G8+E9-F9 -> 1745.6
A10: 46032 | B10: RII 3183 | C10: ENERO | D10: GARANTIA | F10: 1000 | G10: =+G9+E10-F10 -> 745.6
A11: 46032 | B11: EB01-6648 | C11: ENERO | D11: ALQUILER | F11: 700 | G11: =+G10+E11-F11 -> 45.6 | I11: ALVAREZ BERRIO FLORENCIA
A12: 46090 | B12: RII 3291 | C12: ENERO | D12: LUZ | F12: 14.3 | G12: =+G11+E12-F12 -> 31.3 | I12: 2026 | J12: ENERO | K12: MULTA X CAPACITACION
A13: 46090 | B13: RII 3291 | C13: ENERO | D13: AGUA | F13: 3 | G13: =+G12+E13-F13 -> 28.3 | J13: FEBRERO | K13: LUZ | L13: 20.2
A14: 46081 | B14: POR COBRAR | C14: FEBRERO | D14: LUZ | E14: 20.2 | G14: =+G13+E14-F14 -> 48.5 | K14: AGUA | L14: 6
D15: AGUA | E15: 6 | G15: =+G14+E15-F15 -> 54.5 | J15: MARZO | K15: LUZ | L15: 19.7
D16: ALQUILER | E16: 700 | G16: =+G15+E16-F16 -> 754.5 | K16: AGUA | L16: 6
A17: 46091 | B17: EB01-7000 | C17: FEBRERO | D17: ALQUILER | F17: 600 | G17: =+G16+E17-F17 -> 154.5 | K17: 100 | L17: =SUM(L12:L16) -> 51.9 | M17: =K17-L17 -> 48.1
A18: 46104 | B18: EB01-7061 | C18: FEBRERO | D18: ALQUILER | F18: 100 | G18: =+G17+E18-F18 -> 54.5
A19: 46140 | B19: RII 3374 | C19: FEBRERO | D19: LUZ | F19: 20.2 | G19: =+G18+E19-F19 -> 34.3
A20: 46140 | B20: RII 3374 | C20: FEBRERO | D20: AGUA | F20: 6 | G20: =+G19+E20-F20 -> 28.3
A21: 46112 | B21: POR COBRAR | C21: MARZO | D21: LUZ | E21: 19.7 | G21: =+G20+E21-F21 -> 48
D22: AGUA | E22: 6 | G22: =+G21+E22-F22 -> 54
D23: ALQUILER | E23: 700 | G23: =+G22+E23-F23 -> 754
A24: 46128 | B24: EB01-7211 | C24: MARZO | D24: ALQUILER | F24: 700 | G24: =+G23+E24-F24 -> 54
A25: 46140 | B25: RII 3374 | C25: MARZO | D25: LUZ | F25: 19.7 | G25: =+G24+E25-F25 -> 34.3
A26: 46140 | B26: RII 3374 | C26: MARZO | D26: AGUA | F26: 6 | G26: =+G25+E26-F26 -> 28.3
A27: 46142 | B27: POR COBRAR | C27: ABRIL | D27: LUZ | G27: =+G26+E27-F27 -> 28.3
D28: AGUA | G28: =+G27+E28-F28 -> 28.3
D29: ALQUILER | E29: 700 | G29: =+G28+E29-F29 -> 728.3
G30: =+G29+E30-F30 -> 728.3
G31: =+G30+E31-F31 -> 728.3
G32: =+G31+E32-F32 -> 728.3
G33: =+G32+E33-F33 -> 728.3
G34: =+G33+E34-F34 -> 728.3
G35: =+G34+E35-F35 -> 728.3
G36: =+G35+E36-F36 -> 728.3
G37: =+G36+E37-F37 -> 728.3
G38: =+G37+E38-F38 -> 728.3
G39: =+G38+E39-F39 -> 728.3
G40: =+G39+E40-F40 -> 728.3
G41: =+G40+E41-F41 -> 728.3
... G107: =+G106+E107-F107 -> 728.3

Sheet ANCHAYA ABEL
B2: ABEL ANCHAYA HUAMAN
A4: FECHA | B4: DOCUMENTO | C4: PERIODO | D4: CONCEPTO | E4: POR COBRAR | F4: PAGADO | G4: SALDO POR COBRAR
A6: 44681 | B6: POR COBRAR | C6: ABRIL | D6: ALQUILER | E6: 700 | G6: =G5+E6-F6 -> 700
D7: GARANTIA | E7: 700 | G7: =G6+E7-F7 -> 1400
A8: 44663 | B8: EB01-690 | C8: MARZO | D8: ALQUILER | F8: 700 | G8: =G7+E8-F8 -> 700
A9: 44663 | B9: EB01-689 | C9: MARZO | D9: GARANTIA | F9: 700 | G9: =G8+E9-F9 -> 0
D10: LUZ | E10: 51.7 | G10: =G9+E10-F10 -> 51.7
D11: AGUA | E11: 2.8 | G11: =G10+E11-F11 -> 54.5
A12: 44764 | B12: RII 1131 | C12: MARZO | D12: LUZ | F12: 51.7 | G12: =G11+E12-F12 -> 2.8
A13: 44764 | B13: RII 1131 | C13: MARZO | D13: AGUA | F13: 2.8 | G13: =G12+E13-F13 -> 0
A14: 44712 | B14: POR COBRAR | C14: MAYO | D14: LUZ | E14: 49.4 | G14: =G13+E14-F14 -> 49.4
D15: AGUA | E15: 9.1 | G15: =G14+E15-F15 -> 58.5
D16: ALQUILER | E16: 700 | G16: =G15+E16-F16 -> 758.5
D17: FUMIGACION | E17: 6 | G17: =G16+E17-F17 -> 764.5
A18: 44697 | B18: EB01-812 | C18: MAYO | D18: ALQUILER | F18: 700 | G18: =G17+E18-F18 -> 64.5
A19: 44764 | B19: RII 1131 | C19: MAYO | D19: LUZ | F19: 49.4 | G19: =G18+E19-F19 -> 15.1
A20: 44764 | B20: RII 1131 | C20: MAYO | D20: AGUA | F20: 9.1 | G20: =G19+E20-F20 -> 6
A21: 45119 | B21: RII 1665 | C21: MAYO | D21: FUMIGACION | F21: 6 | G21: =G20+E21-F21 -> 0
A22: 44742 | B22: POR COBRAR | C22: JUNIO | D22: LUZ | E22: 47.9 | G22: =G21+E22-F22 -> 47.9
D23: AGUA | E23: 6.9 | G23: =G22+E23-F23 -> 54.8
D24: ALQUILER | E24: 700 | G24: =G23+E24-F24 -> 754.8
A25: 44730 | B25: EB01-926 | C25: JUNIO | D25: ALQUILER | F25: 700 | G25: =G24+E25-F25 -> 54.8
A26: 44898 | B26: RII 1305 | C26: JUNIO | D26: LUZ | F26: 47.9 | G26: =G25+E26-F26 -> 6.9
A27: 44898 | B27: RII 1305 | C27: JUNIO | D27: AGUA | F27: 6.9 | G27: =G26+E27-F27 -> -4.4408921e-14
A28: 44773 | B28: POR COBRAR | C28: JULIO | D28: LUZ | E28: 47.6 | G28: =G27+E28-F28 -> 47.6
D29: AGUA | E29: 9.7 | G29: =G28+E29-F29 -> 57.3
D30: ALQUILER | E30: 700 | G30: =G29+E30-F30 -> 757.3
A31: 44767 | B31: EB01-1052 | C31: JULIO | D31: ALQUILER | F31: 700 | G31: =G30+E31-F31 -> 57.3
A32: 44958 | B32: RII 1381 | C32: JULIO | D32: LUZ | F32: 47.6 | G32: =G31+E32-F32 -> 9.7
A33: 44958 | B33: RII 1381 | C33: JULIO | D33: AGUA | F33: 9.7 | G33: =G32+E33-F33 -> -4.6185278e-14
A34: 44804 | B34: POR COBRAR | C34: AGOSTO | D34: LUZ | E34: 47.9 | G34: =G33+E34-F34 -> 47.9
D35: AGUA | E35: 7 | G35: =G34+E35-F35 -> 54.9
D36: ALQUILER | E36: 700 | G36: =G35+E36-F36 -> 754.9
D37: TALONARIO SANTA ROSA | E37: 10 | G37: =G36+E37-F37 -> 764.9
A38: 44804 | B38: EB01-1182 | C38: AGOSTO | D38: ALQUILER | F38: 180 | G38: =G37+E38-F38 -> 584.9
A39: 44958 | B39: RII 1381 | C39: AGOSTO | D39: LUZ | F39: 47.9 | G39: =G38+E39-F39 -> 537
A40: 44958 | B40: RII 1381 | C40: AGOSTO | D40: AGUA | F40: 7 | G40: =G39+E40-F40 -> 530
A41: 45119 | B41: RII 1666 | C41: AGOSTO | D41: TALONARIO SANTA ROSA | F41: 10 | G41: =G40+E41-F41 -> 520
A42: 44039 | B42: EB01-2428 | C42: AGOSTO | D42: ALQUILER | F42: 500 | G42: =G41+E42-F42 -> 20
A43: 45153 | B43: EB01-2533 | C43: AGOSTO | D43: ALQUILER | F43: 19.999 | G43: =G42+E43-F43 -> 0.001
A44: 44804 | B44: POR COBRAR | C44: SETIEMBRE | D44: LUZ | E44: 42.5 | G44: =G43+E44-F44 -> 42.501
D45: AGUA | E45: 8.2 | G45: =G44+E45-F45 -> 50.701
D46: ALQUILER | E46: 700 | G46: =G45+E46-F46 -> 750.701
A47: 44834 | B47: EB01-1288 | C47: SETIEMBRE | D47: ALQUILER | F47: 350 | G47: =G46+E47-F47 -> 400.701
A48: 44839 | B48: EB01-1338 | C48: SETIEMBRE | D48: ALQUILER | F48: 350 | G48: =G47+E48-F48 -> 50.701
A49: 45003 | B49: RII 1439 | C49: SETIEMBRE | D49: LUZ | F49: 42.5 | G49: =G48+E49-F49 -> 8.201
A50: 45003 | B50: RII 1439 | C50: SETIEMBRE | D50: AGUA | F50: 8.2 | G50: =G49+E50-F50 -> 0.001
A51: 44865 | B51: POR COBRAR | C51: OCTUBRE | D51: LUZ | E51: 42.4 | G51: =G50+E51-F51 -> 42.401
D52: AGUA | E52: 4.9 | G52: =G51+E52-F52 -> 47.301
D53: ALQUILER | E53: 700 | G53: =G52+E53-F53 -> 747.301
A54: 44865 | B54: EB01-1393 | C54: OCTUBRE | D54: ALQUILER | F54: 340 | G54: =G53+E54-F54 -> 407.301
A55: 44869 | B55: EB01-1441 | C55: OCTUBRE | D55: ALQUILER | F55: 360 | G55: =G54+E55-F55 -> 47.301
A56: 45003 | B56: RII 1439 | C56: OCTUBRE | D56: LUZ | F56: 42.4 | G56: =G55+E56-F56 -> 4.901
A57: 45003 | B57: RII 1439 | C57: OCTUBRE | D57: AGUA | F57: 4.9 | G57: =G56+E57-F57 -> 0.001
A58: 44895 | B58: POR COBRAR | C58: NOVIEMBRE | D58: LUZ | E58: 47.3 | G58: =G57+E58-F58 -> 47.301
D59: AGUA | E59: 6.3 | G59: =G58+E59-F59 -> 53.601
D60: ALQUILER | E60: 700 | G60: =G59+E60-F60 -> 753.601
A61: 44895 | B61: EB01-1501 | C61: NOVIEMBRE | D61: ALQUILER | F61: 370 | G61: =G60+E61-F61 -> 383.601
A62: 44898 | B62: EB01-1545 | C62: NOVIEMBRE | D62: ALQUILER | F62: 330 | G62: =G61+E62-F62 -> 53.601
A63: 45097 | B63: RII 1625 | C63: NOVIEMBRE | D63: LUZ | F63: 47.3 | G63: =G62+E63-F63 -> 6.301
A64: 45097 | B64: RII 1625 | C64: NOVIEMBRE | D64: AGUA | F64: 6.3 | G64: =G63+E64-F64 -> 0.001
A65: 44926 | B65: POR COBRAR | C65: DICIEMBRE | D65: LUZ | E65: 54.1 | G65: =G64+E65-F65 -> 54.101
D66: AGUA | E66: 5.7 | G66: =G65+E66-F66 -> 59.801
D67: ALQUILER | E67: 700 | G67: =G66+E67-F67 -> 759.801
A68: 44926 | B68: EB01-1601 | C68: DICIEMBRE | D68: ALQUILER | F68: 220 | G68: =G67+E68-F68 -> 539.801
A69: 45097 | B69: RII 1625 | C69: DICIEMBRE | D69: LUZ | F69: 54.1 | G69: =G68+E69-F69 -> 485.701
A70: 45097 | B70: RII 1625 | C70: DICIEMBRE | D70: AGUA | F70: 5.7 | G70: =G69+E70-F70 -> 480.001
A71: 45153 | B71: EB01-2533 | C71: DICIEMBRE | D71: ALQUILER | F71: 479.999 | G71: =G70+E71-F71 -> 0.002
A72: 44957 | B72: POR COBRAR | C72: ENERO | D72: LUZ | E72: 55.1 | G72: =G71+E72-F72 -> 55.102
D73: AGUA | E73: 4.8 | G73: =G72+E73-F73 -> 59.902
D74: ALQUILER | E74: 700 | G74: =G73+E74-F74 -> 759.902
A75: 44957 | B75: EB01-1711 | C75: ENERO | D75: ALQUILER | F75: 360 | G75: =G74+E75-F75 -> 399.902
A76: 45097 | B76: RII 1625 | C76: ENERO | D76: LUZ | F76: 55.1 | G76: =G75+E76-F76 -> 344.802
A77: 45097 | B77: RII 1625 | C77: ENERO | D77: AGUA | F77: 4.8 | G77: =G76+E77-F77 -> 340.002
A78: 45153 | B78: EB01-2533 | C78: ENERO | D78: ALQUILER | F78: 339.999 | G78: =G77+E78-F78 -> 0.003
A79: 44985 | B79: POR COBRAR | C79: FEBRERO | D79: LUZ | E79: 60.1 | G79: =G78+E79-F79 -> 60.103
D80: AGUA | E80: 1.2 | G80: =G79+E80-F80 -> 61.303
D81: ALQUILER | E81: 700 | G81: =G80+E81-F81 -> 761.303
A82: 44985 | B82: EB01-1817 | C82: FEBRERO | D82: ALQUILER | F82: 380 | G82: =G81+E82-F82 -> 381.303
A83: 45104 | B83: RII 1638 | C83: FEBRERO | D83: LUZ | F83: 60.1 | G83: =G82+E83-F83 -> 321.203
A84: 45104 | B84: RII 1638 | C84: FEBRERO | D84: AGUA | F84: 1.2 | G84: =G83+E84-F84 -> 320.003
A85: 45153 | B85: EB01-2533 | C85: FEBRERO | D85: ALQUILER | F85: 159.9999 | G85: =G84+E85-F85 -> 160.0031
A86: 45224 | B86: EB01-2812 | C86: FEBRERO | D86: ALQUILER | F86: 160 | G86: =G85+E86-F86 -> 0.0031
A87: 44985 | B87: POR COBRAR | C87: MARZO | D87: LUZ | E87: 55.3 | G87: =G86+E87-F87 -> 55.3031 | R87: =100*20 -> 2000
D88: AGUA | E88: 1.3 | G88: =G87+E88-F88 -> 56.6031
D89: ALQUILER | E89: 700 | G89: =G88+E89-F89 -> 756.6031
A90: 45016 | B90: EB01-1938 | C90: MARZO | D90: ALQUILER | F90: 660 | G90: =G89+E90-F90 -> 96.6031
A91: 45104 | B91: RII 1638 | C91: MARZO | D91: LUZ | F91: 55.3 | G91: =G90+E91-F91 -> 41.3031
A92: 45104 | B92: RII 1638 | C92: MARZO | D92: AGUA | F92: 1.3 | G92: =G91+E92-F92 -> 40.0031
A93: 45126 | B93: EB01-2410 | C93: MARZO | D93: ALQUILER | F93: 40 | G93: =G92+E93-F93 -> 0.0031
A94: 44985 | B94: POR COBRAR | C94: ABRIL | D94: LUZ | E94: 57.9 | G94: =G93+E94-F94 -> 57.9031
D95: AGUA | E95: 1.5 | G95: =G94+E95-F95 -> 59.4031
D96: ALQUILER | E96: 700 | G96: =G95+E96-F96 -> 759.4031
A97: 45046 | B97: EB01-2060 | C97: ABRIL | D97: ALQUILER | F97: 650 | G97: =G96+E97-F97 -> 109.4031
A98: 45104 | B98: RII 1638 | C98: ABRIL | D98: LUZ | F98: 57.9 | G98: =G97+E98-F98 -> 51.5031
A99: 45104 | B99: RII 1638 | C99: ABRIL | D99: AGUA | F99: 1.5 | G99: =G98+E99-F99 -> 50.0031
A100: 45126 | B100: EB01-2410 | C100: ABRIL | D100: ALQUILER | F100: 50 | G100: =G99+E100-F100 -> 0.0031
A101: 45077 | B101: POR COBRAR | C101: MAYO | D101: LUZ | E101: 53.5 | G101: =G100+E101-F101 -> 53.5031
D102: AGUA | E102: 2.1 | G102: =G101+E102-F102 -> 55.6031
D103: ALQUILER | E103: 700 | G103: =G102+E103-F103 -> 755.6031
...

Sheet ARMESTAR JUANA 
B3: ARMESTAR GODOS JUANA JACKELYNE
A5: FECHA | B5: DOCUMENTO | C5: PERIODO | D5: CONCEPTO | E5: POR COBRAR | F5: PAGADO | G5: SALDO POR COBRAR
G6: =+E6-F6 -> 0
A7: 43285 | B7: POR COBRAR | C7: JULIO | D7: LUZ | E7: 52.6 | G7: =+G6+E7-F7 -> 52.6
D8: AGUA | E8: 5 | G8: =+G7+E8-F8 -> 57.6
D9: ALQUILER | E9: 300 | G9: =+G8+E9-F9 -> 357.6
D10: GARANTIA | E10: 300 | G10: =+G9+E10-F10 -> 657.6
A11: 43285 | B11: 14807 | C11: JULIO | D11: ALQUILER | F11: 300 | G11: =+G10+E11-F11 -> 357.6
A12: 43285 | B12: 14807 | C12: JULIO | D12: GARANTIA | F12: 300 | G12: =+G11+E12-F12 -> 57.6
A13: 43404 | B13: 15428 | C13: JULIO | D13: LUZ | F13: 52.6 | G13: =+G12+E13-F13 -> 5
A14: 43404 | B14: 15428 | C14: JULIO | D14: AGUA | F14: 5 | G14: =+G13+E14-F14 -> 2.1316282e-14
A15: 43343 | B15: POR COBRAR | C15: AGOSTO | D15: LUZ | E15: 67.5 | G15: =+G14+E15-F15 -> 67.5
D16: AGUA | E16: 5 | G16: =+G15+E16-F16 -> 72.5
D17: ALQUILER | E17: 300 | G17: =+G16+E17-F17 -> 372.5
A18: 43314 | B18: 14996 | C18: AGOSTO | D18: ALQUILER | F18: 105 | G18: =+G17+E18-F18 -> 267.5
A19: 43344 | B19: 15114 | C19: AGOSTO | D19: ALQUILER | F19: 130 | G19: =+G18+E19-F19 -> 137.5
A20: 43374 | B20: 15292 | C20: AGOSTO | D20: LUZ | F20: 67.5 | G20: =+G19+E20-F20 -> 70
A21: 43374 | B21: 15292 | C21: AGOSTO | D21: AGUA | F21: 5 | G21: =+G20+E21-F21 -> 65
A22: 43374 | B22: 15292 | C22: AGOSTO | D22: ALQUILER | F22: 65 | G22: =+G21+E22-F22 -> 0
A23: 43373 | B23: POR COBRAR | C23: SETIEMBRE | D23: LUZ | E23: 53.5 | G23: =+G22+E23-F23 -> 53.5
D24: AGUA | E24: 5 | G24: =+G23+E24-F24 -> 58.5
D25: ALQUILER | E25: 300 | G25: =+G24+E25-F25 -> 358.5
A26: 43374 | B26: 15292 | C26: SETIEMBRE | D26: ALQUILER | F26: 72.5 | G26: =+G25+E26-F26 -> 286
A27: 43404 | B27: 15428 | C27: SETIEMBRE | D27: ALQUILER | F27: 152.4 | G27: =+G26+E27-F27 -> 133.6
A28: 43434 | B28: 15528 | C28: SETIEMBRE | D28: ALQUILER | F28: 75.1 | G28: =+G27+E28-F28 -> 58.5
A29: 43434 | B29: 15528 | C29: SETIEMBRE | D29: LUZ | F29: 53.5 | G29: =+G28+E29-F29 -> 5
A30: 43434 | B30: 15528 | C30: SETIEMBRE | D30: AGUA | F30: 5 | G30: =+G29+E30-F30 -> 0
A31: 43404 | B31: POR COBRAR | C31: OCTUBRE | D31: LUZ | E31: 54 | G31: =+G30+E31-F31 -> 54
D32: AGUA | E32: 6 | G32: =+G31+E32-F32 -> 60
D33: ALQUILER | E33: 300 | G33: =+G32+E33-F33 -> 360
A34: 43434 | B34: 15528 | C34: OCTUBRE | D34: ALQUILER | F34: 36.4 | G34: =+G33+E34-F34 -> 323.6
A35: 43830 | B35: 15708 | C35: OCTUBRE | D35: ALQUILER | F35: 150 | G35: =+G34+E35-F35 -> 173.6
A36: 43496 | B36: 15865 | C36: OCTUBRE | D36: LUZ | F36: 54 | G36: =+G35+E36-F36 -> 119.6
A37: 43496 | B37: 15865 | C37: OCTUBRE | D37: AGUA | F37: 6 | G37: =+G36+E37-F37 -> 113.6
A38: 43496 | B38: 15865 | C38: OCTUBRE | D38: ALQUILER | F38: 113.6 | G38: =+G37+E38-F38 -> 0
A39: 43434 | B39: POR COBRAR | C39: NOVIEMBRE | D39: LUZ | E39: 55.4 | G39: =+G38+E39-F39 -> 55.4
D40: AGUA | E40: 6 | G40: =+G39+E40-F40 -> 61.4
D41: ALQUILER | E41: 300 | G41: =+G40+E41-F41 -> 361.4
A42: 43496 | B42: 15865 | C42: NOVIEMBRE | D42: ALQUILER | F42: 106.4 | G42: =+G41+E42-F42 -> 255
A43: 43524 | B43: 15981 | C43: NOVIEMBRE | D43: ALQUILER | F43: 193.9 | G43: =+G42+E43-F43 -> 61.1
A44: 43524 | B44: 15981 | C44: NOVIEMBRE | D44: LUZ | F44: 51.1 | G44: =+G43+E44-F44 -> 10
A45: 43554 | B45: B001-0000120 | D45: LUZ | F45: 4 | G45: =+G44+E45-F45 -> 6
A46: 43554 | B46: B001-0000120 | C46: NOVIEMBRE | D46: AGUA | F46: 6 | G46: =+G45+E46-F46 -> -3.5527137e-14
A47: 43465 | B47: POR COBRAR | C47: DICIEMBRE | D47: LUZ | E47: 59.1 | G47: =+G46+E47-F47 -> 59.1
D48: AGUA | E48: 6 | G48: =+G47+E48-F48 -> 65.1
D49: ALQUILER | E49: 300 | G49: =+G48+E49-F49 -> 365.1
A50: 43554 | B50: B001-0000120 | C50: DICIEMBRE | D50: ALQUILER | F50: 50 | G50: =+G49+E50-F50 -> 315.1
A51: 43585 | B51: B001-0000195 | C51: DICIEMBRE | D51: ALQUILER | F51: 180 | G51: =+G50+E51-F51 -> 135.1
A52: 43591 | B52: B001-0000222 | C52: DICIEMBRE | D52: LUZ | F52: 59.1 | G52: =+G51+E52-F52 -> 76
A53: 43591 | B53: B001-0000222 | C53: DICIEMBRE | D53: AGUA | F53: 6 | G53: =+G52+E53-F53 -> 70
A54: 43591 | B54: B001-0000222 | C54: DICIEMBRE | D54: ALQUILER | F54: 70 | G54: =+G53+E54-F54 -> 0
A55: 43496 | B55: POR COBRAR | C55: ENERO | D55: LUZ | E55: 61.6 | G55: =+G54+E55-F55 -> 61.6
D56: AGUA | E56: 6 | G56: =+G55+E56-F56 -> 67.6
D57: ALQUILER | E57: 300 | G57: =+G56+E57-F57 -> 367.6
A58: 43591 | B58: B001-0000222 | C58: ENERO | D58: LUZ | F58: 61.6 | G58: =+G57+E58-F58 -> 306
A59: 43591 | B59: B001-0000222 | C59: ENERO | D59: AGUA | F59: 6 | G59: =+G58+E59-F59 -> 300
A60: 43591 | B60: B001-0000222 | C60: ENERO | D60: ALQUILER | F60: 297.3 | G60: =+G59+E60-F60 -> 2.7
A61: 43644 | B61: B001-0000401 | C61: ENERO | D61: ALQUILER | F61: 2.7 | G61: =+G60+E61-F61 -> -1.1546319e-14
A62: 43524 | B62: POR COBRAR | C62: FEBRERO | D62: LUZ | E62: 65.1 | G62: =+G61+E62-F62 -> 65.1
D63: AGUA | E63: 7.3 | G63: =+G62+E63-F63 -> 72.4
D64: ALQUILER | E64: 300 | G64: =+G63+E64-F64 -> 372.4
A65: 43616 | B65: B001-0000325 | C65: FEBRERO | D65: ALQUILER | F65: 300 | G65: =+G64+E65-F65 -> 72.4
A66: 43644 | B66: B001-0000401 | C66: FEBRERO | D66: LUZ | F66: 65.1 | G66: =+G65+E66-F66 -> 7.3
A67: 43644 | B67: B001-0000401 | C67: FEBRERO | D67: AGUA | F67: 7.3 | G67: =+G66+E67-F67 -> -1.687539e-14
A68: 43555 | B68: POR COBRAR | C68: MARZO | D68: LUZ | E68: 60.5 | G68: =+G67+E68-F68 -> 60.5
D69: AGUA | E69: 5.8 | G69: =+G68+E69-F69 -> 66.3
D70: ALQUILER | E70: 300 | G70: =+G69+E70-F70 -> 366.3
A71: 43644 | B71: B001-0000401 | C71: MARZO | D71: ALQUILER | F71: 84.9 | G71: =+G70+E71-F71 -> 281.4
A72: 43677 | B72: B001-0000492 | C72: MARZO | D72: ALQUILER | F72: 215.1 | G72: =+G71+E72-F72 -> 66.3
A73: 43677 | B73: B001-0000492 | C73: MARZO | D73: LUZ | F73: 4.9 | G73: =+G72+E73-F73 -> 61.4
A74: 43708 | B74: B001-0000582 | C74: MARZO | D74: LUZ | F74: 55.6 | G74: =+G73+E74-F74 -> 5.8
A75: 43708 | B75: B001-0000582 | C75: MARZO | D75: AGUA | F75: 5.8 | G75: =+G74+E75-F75 -> -1.687539e-14
A76: 43585 | B76: POR COBRAR | C76: ABRIL | D76: LUZ | E76: 61.2 | G76: =+G75+E76-F76 -> 61.2
D77: AGUA | E77: 5.3 | G77: =+G76+E77-F77 -> 66.5
D78: ALQUILER | E78: 300 | G78: =+G77+E78-F78 -> 366.5
A79: 43708 | B79: B001-0000582 | C79: ABRIL | D79: LUZ | F79: 58.6 | G79: =+G78+E79-F79 -> 307.9
A80: 43738 | B80: B001-0000680 | C80: ABRIL | D80: ALQUILER | F80: 120 | G80: =+G79+E80-F80 -> 187.9
A81: 43769 | B81: B001-0000763 | C81: ABRIL | D81: ALQUILER | F81: 120 | G81: =+G80+E81-F81 -> 67.9
A82: 43890 | B82: B001-0001216 | C82: ABRIL | D82: ALQUILER | F82: 10 | G82: =+G81+E82-F82 -> 57.9
A83: 43969 | B83: B001-0001324 | C83: ABRIL | D83: ALQUILER | F83: 50 | G83: =+G82+E83-F83 -> 7.9
A84: 43969 | B84: B001-0001324 | C84: ABRIL | D84: LUZ | F84: 2.6 | G84: =+G83+E84-F84 -> 5.3
A85: 43969 | B85: B001-0001324 | C85: ABRIL | D85: AGUA | F85: 5.3 | G85: =+G84+E85-F85 -> -2.220446e-14
A86: 43616 | B86: POR COBRAR | C86: MAYO | D86: LUZ | E86: 56.4 | G86: =+G85+E86-F86 -> 56.4
D87: AGUA | E87: 6.2 | G87: =+G86+E87-F87 -> 62.6
D88: ALQUILER | E88: 300 | G88: =+G87+E88-F88 -> 362.6
A89: 43616 | B89: B001-0000325 | C89: MAYO | D89: ALQUILER | F89: 300 | G89: =+G88+E89-F89 -> 62.6
A90: 43969 | B90: B001-0001324 | C90: MAYO | D90: LUZ | F90: 56.4 | G90: =+G89+E90-F90 -> 6.2
A91: 43969 | B91: B001-0001324 | C91: MAYO | D91: AGUA | F91: 6.2 | G91: =+G90+E91-F91 -> -3.2862602e-14
A92: 43646 | B92: POR COBRAR | C92: JUNIO | D92: LUZ | E92: 56.3 | G92: =+G91+E92-F92 -> 56.3
D93: AGUA | E93: 5.9 | G93: =+G92+E93-F93 -> 62.2
D94: ALQUILER | E94: 300 | G94: =+G93+E94-F94 -> 362.2
A95: 43644 | B95: B001-0000401 | C95: JUNIO | D95: ALQUILER | F95: 300 | G95: =+G94+E95-F95 -> 62.2
A96: 43969 | B96: B001-0001324 | C96: JUNIO | D96: LUZ | F96: 19.5 | G96: =+G95+E96-F96 -> 42.7
A97: 43985 | B97: B001-00001376 | C97: JUNIO | D97: LUZ | F97: 36.8 | G97: =+G96+E97-F97 -> 5.9
A98: 43985 | B98: B001-00001376 | C98: JUNIO | D98: AGUA | F98: 5.9 | G98: =+G97+E98-F98 -> -6.5725203e-14
A99: 43677 | B99: POR COBRAR | C99: JULIO | D99: LUZ | E99: 56.3 | G99: =+G98+E99-F99 -> 56.3
C100: JULIO | D100: AGUA | E100: 5.7 | G100: =+G99+E100-F100 -> 62
C101: JULIO | D101: ALQUILER | E101: 300 | G101: =+G100+E101-F101 -> 362
A102: 43985 | B102: B001-00001376 | C102: JULIO | D102: LUZ | F102: 56.3 | G102: =+G101+E102-F102 -> 305.7
A103: 43985 | B103: B001-00001376 | C103: JULIO | D103: AGUA | F103: 5.7 | G103: =+G102+E103-F103 -> 300
...

Sheet AYALA MARLENE
B3: AYALA HUASHUAYO MARLENE
A5: FECHA | B5: DOCUMENTO | C5: PERIODO | D5: CONCEPTO | E5: POR COBRAR | F5: PAGADO | G5: SALDO POR COBRAR
A6: 42736 | B6: SALDO AL 2016 | G6: 75.4
A7: 42766 | B7: 12182 | C7: A CUENTA 2016 | F7: 75.4 | G7: =+G6+E7-F7 -> 0
A8: 42766 | B8: POR COBRAR | C8: ENERO | D8: LUZ | E8: 74.5 | G8: =+G7+E8-F8 -> 74.5
D9: AGUA | E9: 2.8 | G9: =+G8+E9-F9 -> 77.3
D10: ALQUILER | E10: 780 | G10: =+G9+E10-F10 -> 857.3
A11: 42766 | B11: 12182 | C11: ENERO | D11: ALQUILER | F11: 780 | G11: =+G10+E11-F11 -> 77.3
A12: 42819 | B12: 12441 | C12: ENERO | D12: LUZ | F12: 74.5 | G12: =+G11+E12-F12 -> 2.8
A13: 42819 | B13: 12441 | C13: ENERO | D13: AGUA | F13: 2.8 | G13: =+G12+E13-F13 -> -4.5297099e-14
A14: 42794 | B14: POR COBRAR | C14: FEBRERO | D14: LUZ | E14: 71.3 | G14: =+G13+E14-F14 -> 71.3
D15: AGUA | E15: 2 | G15: =+G14+E15-F15 -> 73.3
D16: ALQUILER | E16: 780 | G16: =+G15+E16-F16 -> 853.3
A17: 42819 | B17: 12441 | C17: FEBRERO | D17: LUZ | F17: 71.3 | G17: =+G16+E17-F17 -> 782
A18: 42819 | B18: 12441 | C18: FEBRERO | D18: AGUA | F18: 2 | G18: =+G17+E18-F18 -> 780
A19: 42819 | B19: 12442 | C19: FEBRERO | D19: ALQUILER | F19: 780 | G19: =+G18+E19-F19 -> 0
A20: 42825 | B20: POR COBRAR | C20: MARZO | D20: LUZ | E20: 67.7 | G20: =+G19+E20-F20 -> 67.7
D21: AGUA | E21: 2 | G21: =+G20+E21-F21 -> 69.7
D22: ALQUILER | E22: 780 | G22: =+G21+E22-F22 -> 849.7
A23: 42832 | B23: 12514 | C23: MARZO | D23: ALQUILER | F23: 780 | G23: =+G22+E23-F23 -> 69.7
A24: 42884 | B24: 12723 | C24: MARZO | D24: LUZ | F24: 67.7 | G24: =+G23+E24-F24 -> 2
A25: 42884 | B25: 12723 | C25: MARZO | D25: AGUA | F25: 2 | G25: =+G24+E25-F25 -> 4.2632564e-14
A26: 42855 | B26: POR COBRAR | C26: ABRIL | D26: LUZ | E26: 70.1 | G26: =+G25+E26-F26 -> 70.1
D27: AGUA | E27: 2 | G27: =+G26+E27-F27 -> 72.1
D28: ALQUILER | E28: 780 | G28: =+G27+E28-F28 -> 852.1
A29: 42884 | B29: 12723 | C29: ABRIL | D29: LUZ | F29: 70.1 | G29: =+G28+E29-F29 -> 782
A30: 42884 | B30: 12723 | C30: ABRIL | D30: AGUA | F30: 2 | G30: =+G29+E30-F30 -> 780
A31: 42872 | B31: 12687 | C31: ABRIL | D31: ALQUILER | F31: 780 | G31: =+G30+E31-F31 -> 0
A32: 42886 | B32: POR COBRAR | C32: MAYO | D32: LUZ | E32: 58.7 | G32: =+G31+E32-F32 -> 58.7
D33: AGUA | E33: 2 | G33: =+G32+E33-F33 -> 60.7
D34: ALQUILER | E34: 780 | G34: =+G33+E34-F34 -> 840.7
A35: 42905 | B35: 12852 | C35: MAYO | D35: ALQUILER | F35: 780 | G35: =+G34+E35-F35 -> 60.7
A36: 42905 | B36: 12853 | C36: MAYO | D36: LUZ | F36: 58.7 | G36: =+G35+E36-F36 -> 2
A37: 42905 | B37: 12853 | C37: MAYO | D37: AGUA | F37: 2 | G37: =+G36+E37-F37 -> 4.2632564e-14
A38: 42916 | B38: POR COBRAR | C38: JUNIO | D38: LUZ | E38: 57 | G38: =+G37+E38-F38 -> 57
D39: AGUA | E39: 2 | G39: =+G38+E39-F39 -> 59
D40: ALQUILER | E40: 780 | G40: =+G39+E40-F40 -> 839
A41: 42930 | B41: 13014 | C41: JUNIO | D41: ALQUILER | F41: 780 | G41: =+G40+E41-F41 -> 59
A42: 42961 | B42: 13265 | C42: JUNIO | D42: LUZ | F42: 57 | G42: =+G41+E42-F42 -> 2
A43: 42961 | B43: 13265 | C43: JUNIO | D43: AGUA | F43: 2 | G43: =+G42+E43-F43 -> 0
A44: 42947 | B44: POR COBRAR | C44: JULIO | D44: LUZ | E44: 57.7 | G44: =+G43+E44-F44 -> 57.7
D45: AGUA | E45: 2 | G45: =+G44+E45-F45 -> 59.7
D46: ALQUILER | E46: 780 | G46: =+G45+E46-F46 -> 839.7
A47: 42961 | B47: 13265 | C47: JULIO | D47: ALQUILER | F47: 780 | G47: =+G46+E47-F47 -> 59.7
A48: 42985 | B48: 13416 | C48: JULIO | D48: LUZ | F48: 57.7 | G48: =+G47+E48-F48 -> 2
A49: 42985 | B49: 13416 | C49: JULIO | D49: AGUA | F49: 2 | G49: =+G48+E49-F49 -> 4.2632564e-14
A50: 42978 | B50: POR COBRAR | C50: AGOSTO | D50: LUZ | E50: 57.7 | G50: =+G49+E50-F50 -> 57.7
D51: AGUA | E51: 2 | G51: =+G50+E51-F51 -> 59.7
D52: ALQUILER | E52: 780 | G52: =+G51+E52-F52 -> 839.7
A53: 42985 | B53: 13416 | C53: AGOSTO | D53: ALQUILER | F53: 780 | G53: =+G52+E53-F53 -> 59.7
A54: 42998 | B54: 13663 | C54: AGOSTO | D54: LUZ | F54: 57.7 | G54: =+G53+E54-F54 -> 2
A55: 42998 | B55: 13663 | C55: AGOSTO | D55: AGUA | F55: 2 | G55: =+G54+E55-F55 -> 4.2632564e-14
A56: 43008 | B56: POR COBRAR | C56: SEPTIEMBRE | D56: LUZ | E56: 39.5 | G56: =+G55+E56-F56 -> 39.5
D57: AGUA | E57: 2 | G57: =+G56+E57-F57 -> 41.5
D58: ALQUILER | E58: 780 | G58: =+G57+E58-F58 -> 821.5
A59: 42998 | B59: 13663 | C59: SEPTIEMBRE | D59: ALQUILER | F59: 780 | G59: =+G58+E59-F59 -> 41.5
A60: 42998 | B60: 13663 | C60: SEPTIEMBRE | D60: LUZ | F60: 39.5 | G60: =+G59+E60-F60 -> 2
A61: 42998 | B61: 13663 | C61: SEPTIEMBRE | D61: AGUA | F61: 1.3 | G61: =+G60+E61-F61 -> 0.7
A62: 43249 | B62: 14691 | C62: SEPTIEMBRE | D62: LUZ | F62: 0.7 | G62: =+G61+E62-F62 -> 0
A63: 43039 | B63: POR COBRAR | C63: OCTUBRE | D63: LUZ | E63: 39.5 | G63: =+G62+E63-F63 -> 39.5
D64: AGUA | E64: 2 | G64: =+G63+E64-F64 -> 41.5
D65: ALQUILER | E65: 780 | G65: =+G64+E65-F65 -> 821.5
A66: 43039 | B66: 13742 | C66: OCTUBRE | D66: ALQUILER | F66: 380 | G66: =+G65+E66-F66 -> 441.5
A67: 43052 | B67: 13783 | C67: OCTUBRE | D67: ALQUILER | F67: 400 | G67: =+G66+E67-F67 -> 41.5
A68: 43063 | B68: 13833 | C68: OCTUBRE | D68: LUZ | F68: 39.5 | G68: =+G67+E68-F68 -> 2
A69: 43063 | B69: 13833 | C69: OCTUBRE | D69: AGUA | F69: 2 | G69: =+G68+E69-F69 -> 0
A70: 43069 | B70: POR COBRAR | C70: NOVIEMBRE | D70: LUZ | E70: 42.1 | G70: =+G69+E70-F70 -> 42.1
D71: AGUA | E71: 2 | G71: =+G70+E71-F71 -> 44.1
D72: ALQUILER | E72: 780 | G72: =+G71+E72-F72 -> 824.1
A73: 43069 | B73: 13878 | C73: NOVIEMBRE | D73: ALQUILER | F73: 524 | G73: =+G72+E73-F73 -> 300.1
A74: 43097 | B74: 13987 | C74: NOVIEMBRE | D74: ALQUILER | F74: 220.8 | G74: =+G73+E74-F74 -> 79.3
A75: 43099 | B75: 14026 | C75: NOVIEMBRE | D75: ALQUILER | F75: 35.2 | G75: =+G74+E75-F75 -> 44.1
A76: 43249 | B76: 14691 | C76: NOVIEMBRE | D76: LUZ | F76: 42.1 | G76: =+G75+E76-F76 -> 2
A77: 43249 | B77: 14691 | C77: NOVIEMBRE | D77: AGUA | F77: 2 | G77: =+G76+E77-F77 -> 7.1054274e-15
A78: 43100 | B78: POR COBRAR | C78: DICIEMBRE | D78: LUZ | E78: 45.8 | G78: =+G77+E78-F78 -> 45.8
D79: AGUA | E79: 2 | G79: =+G78+E79-F79 -> 47.8
D80: ALQUILER | E80: 780 | G80: =+G79+E80-F80 -> 827.8
A81: 43099 | B81: 14026 | C81: DICIEMBRE | D81: ALQUILER | F81: 780 | G81: =+G80+E81-F81 -> 47.8
A82: 43249 | B82: 14691 | C82: DICIEMBRE | D82: LUZ | F82: 45.8 | G82: =+G81+E82-F82 -> 2
A83: 43249 | B83: 14691 | C83: DICIEMBRE | D83: AGUA | F83: 2 | G83: =+G82+E83-F83 -> -4.2632564e-14
A84: 43101 | B84: POR COBRAR | C84: ENERO | D84: LUZ | E84: 40.8 | G84: =+G83+E84-F84 -> 40.8
D85: AGUA | E85: 2 | G85: =+G84+E85-F85 -> 42.8
D86: ALQUILER | E86: 780 | G86: =+G85+E86-F86 -> 822.8
A87: 43099 | B87: 14026 | C87: ENERO | D87: ALQUILER | F87: 44.8 | G87: =+G86+E87-F87 -> 778
A88: 43136 | B88: 14182 | C88: ENERO | D88: ALQUILER | F88: 735.2 | G88: =+G87+E88-F88 -> 42.8
A89: 43159 | B89: 14274 | C89: ENERO | D89: LUZ | F89: 40.8 | G89: =+G88+E89-F89 -> 2
A90: 43159 | B90: 14274 | C90: ENERO | D90: AGUA | F90: 2 | G90: =+G89+E90-F90 -> -4.2632564e-14
A91: 43159 | B91: POR COBRAR | C91: FEBRERO | D91: LUZ | E91: 62.8 | G91: =+G90+E91-F91 -> 62.8
D92: AGUA | E92: 2 | G92: =+G91+E92-F92 -> 64.8
D93: ALQUILER | E93: 780 | G93: =+G92+E93-F93 -> 844.8
A94: 43181 | B94: 14387 | C94: FEBRERO | D94: LUZ | F94: 62.8 | G94: =+G93+E94-F94 -> 782
A95: 43181 | B95: 14387 | C95: FEBRERO | D95: AGUA | F95: 2 | G95: =+G94+E95-F95 -> 780
A96: 43190 | B96: 14416 | C96: FEBRERO | D96: ALQUILER | F96: 104 | G96: =+G95+E96-F96 -> 676
A97: 43159 | B97: 14291 | C97: FEBRERO | D97: ALQUILER | F97: 676 | G97: =+G96+E97-F97 -> 0
A98: 43190 | B98: PO COBRAR | C98: MARZO | D98: LUZ | E98: 60.3 | G98: =+G97+E98-F98 -> 60.3
D99: AGUA | E99: 2 | G99: =+G98+E99-F99 -> 62.3
D100: ALQUILER | E100: 780 | G100: =+G99+E100-F100 -> 842.3
A101: 31 | B101: 14416 | C101: MARZO | D101: ALQUILER | F101: 652 | G101: =+G100+E101-F101 -> 190.3
A102: 43220 | B102: 14529 | C102: MARZO | D102: ALQUILER | F102: 128 | G102: =+G101+E102-F102 -> 62.3
A103: 43236 | B103: 14607 | C103: MARZO | D103: LUZ | F103: 60.3 | G103: =+G102+E103-F103 -> 2
...

Sheet ARREDONDO GLADYS
B3: ARREDONDO GARCIA GLADYS
A5: FECHA | B5: DOCUMENTO | C5: PERIODO | D5: CONCEPTO | E5: POR COBRAR | F5: PAGADO | G5: SALDO POR COBRAR
A6: 42736 | B6: SALDO AL 2016 | G6: 363.1
A7: 42765 | B7: 12171 | C7: A CUENTA DEL 2016 | F7: 300 | G7: =+G6+E7-F7 -> 63.1
A8: 42767 | B8: 12200 | C8: A CUENTA DEL 2016 | F8: 43.1 | G8: =+G7+E8-F8 -> 20
A9: 43985 | B9: B001-0001371 | C9: A CUENTA DEL 2016 | F9: 20 | G9: =+G8+E9-F9 -> 0
A10: 42766 | B10: POR COBRAR | C10: ENERO | D10: LUZ | E10: 13.5 | G10: =+G9+E10-F10 -> 13.5
D11: AGUA | E11: 2.8 | G11: =+G10+E11-F11 -> 16.3
D12: ALQUILER | E12: 210 | G12: =+G11+E12-F12 -> 226.3
A13: 42859 | B13: 12622 | C13: ENERO | D13: ALQUILER | F13: 180 | G13: =+G12+E13-F13 -> 46.3
A14: 42898 | B14: 12816 | C14: ENERO | D14: ALQUILER | F14: 30 | G14: =+G13+E14-F14 -> 16.3
A15: 43013 | B15: 13607 | C15: ENERO | D15: LUZ | F15: 13.5 | G15: =+G14+E15-F15 -> 2.8
A16: 43013 | B16: 13607 | C16: ENERO | D16: AGUA | F16: 2.8 | G16: =+G15+E16-F16 -> 1.1546319e-14
A17: 42794 | B17: POR COBRAR | C17: FEBRERO | D17: LUZ | E17: 13 | G17: =+G16+E17-F17 -> 13
D18: AGUA | E18: 2 | G18: =+G17+E18-F18 -> 15
D19: ALQUILER | E19: 210 | G19: =+G18+E19-F19 -> 225
A20: 42898 | B20: 12816 | C20: FEBRERO | D20: ALQUILER | F20: 210 | G20: =+G19+E20-F20 -> 15
A21: 43013 | B21: 13607 | C21: FEBRERO | D21: LUZ | F21: 13 | G21: =+G20+E21-F21 -> 2
A22: 43013 | B22: 13607 | C22: FEBRERO | D22: LUZ | F22: 2 | G22: =+G21+E22-F22 -> 0
A23: 42825 | B23: POR COBRAR | C23: MARZO | D23: LUZ | E23: 12 | G23: =+G22+E23-F23 -> 12
D24: AGUA | E24: 2 | G24: =+G23+E24-F24 -> 14
D25: ALQUILER | E25: 210 | G25: =+G24+E25-F25 -> 224
A26: 42898 | B26: 12816 | C26: MARZO | D26: ALQUILER | F26: 30 | G26: =+G25+E26-F26 -> 194
A27: 42916 | B27: 12899 | C27: MARZO | D27: ALQUILER | F27: 180 | G27: =+G26+E27-F27 -> 14
A28: 43013 | B28: 13607 | C28: MARZO | D28: LUZ | F28: 12 | G28: =+G27+E28-F28 -> 2
A29: 43013 | B29: 13607 | C29: MARZO | D29: AGUA | F29: 2 | G29: =+G28+E29-F29 -> 0
A30: 42855 | B30: POR COBRAR | C30: ABRIL | D30: LUZ | E30: 13 | G30: =+G29+E30-F30 -> 13
D31: AGUA | E31: 2 | G31: =+G30+E31-F31 -> 15
D32: ALQUILER | E32: 210 | G32: =+G31+E32-F32 -> 225
A33: 42916 | B33: 12899 | C33: ABRIL | D33: ALQUILER | F33: 210 | G33: =+G32+E33-F33 -> 15
A34: 43013 | B34: 13607 | C34: ABRIL | D34: LUZ | F34: 4.8 | G34: =+G33+E34-F34 -> 10.2
A35: 43008 | B35: 13558 | C35: ABRIL | D35: LUZ | F35: 8.2 | G35: =+G34+E35-F35 -> 2
A36: 43008 | B36: 13558 | C36: ABRIL | D36: AGUA | F36: 2 | G36: =+G35+E36-F36 -> 0
A37: 42886 | B37: POR COBRAR | C37: MAYO | D37: LUZ | E37: 13 | G37: =+G36+E37-F37 -> 13
D38: AGUA | E38: 2 | G38: =+G37+E38-F38 -> 15
D39: ALQUILER | E39: 210 | G39: =+G38+E39-F39 -> 225
A40: 42916 | B40: 12899 | C40: MAYO | D40: ALQUILER | F40: 15 | G40: =+G39+E40-F40 -> 210
A41: 42947 | B41: 13077 | C41: MAYO | D41: ALQUILER | F41: 195 | G41: =+G40+E41-F41 -> 15
A42: 43008 | B42: 13558 | C42: MAYO | D42: LUZ | F42: 13 | G42: =+G41+E42-F42 -> 2
A43: 43008 | B43: 13558 | C43: MAYO | D43: AGUA | F43: 2 | G43: =+G42+E43-F43 -> 0
A44: 42916 | B44: POR COBRAR | C44: JUNIO | D44: LUZ | E44: 13 | G44: =+G43+E44-F44 -> 13
D45: AGUA | E45: 2 | G45: =+G44+E45-F45 -> 15
D46: ALQUILER | E46: 210 | G46: =+G45+E46-F46 -> 225
A47: 42947 | B47: 13077 | C47: JUNIO | D47: ALQUILER | F47: 210 | G47: =+G46+E47-F47 -> 15
A48: 43008 | B48: 13558 | C48: JUNIO | D48: LUZ | F48: 13 | G48: =+G47+E48-F48 -> 2
A49: 43008 | B49: 13558 | C49: JUNIO | D49: AGUA | F49: 2 | G49: =+G48+E49-F49 -> 0
A50: 42947 | B50: POR COBRAR | C50: JULIO | D50: LUZ | E50: 13 | G50: =+G49+E50-F50 -> 13
D51: AGUA | E51: 2 | G51: =+G50+E51-F51 -> 15
D52: ALQUILER | E52: 210 | G52: =+G51+E52-F52 -> 225
A53: 42947 | B53: 13077 | C53: JULIO | D53: ALQUILER | F53: 49 | G53: =+G52+E53-F53 -> 176
A54: 42979 | B54: 13360 | C54: JULIO | D54: ALQUILER | F54: 161 | G54: =+G53+E54-F54 -> 15
A55: 43008 | B55: 13558 | C55: JULIO | D55: LUZ | F55: 13 | G55: =+G54+E55-F55 -> 2
A56: 43008 | B56: 13558 | C56: JULIO | D56: AGUA | F56: 2 | G56: =+G55+E56-F56 -> 0
A57: 42978 | B57: POR COBRAR | C57: AGOSTO | D57: LUZ | E57: 13 | G57: =+G56+E57-F57 -> 13
D58: AGUA | E58: 2 | G58: =+G57+E58-F58 -> 15
D59: ALQUILER | E59: 210 | G59: =+G58+E59-F59 -> 225
A60: 42979 | B60: 13360 | C60: AGOSTO | D60: ALQUILER | F60: 84 | G60: =+G59+E60-F60 -> 141
A61: 43008 | B61: 13558 | C61: AGOSTO | D61: ALQUILER | F61: 126 | G61: =+G60+E61-F61 -> 15
A62: 43008 | B62: 13558 | C62: AGOSTO | D62: LUZ | F62: 13 | G62: =+G61+E62-F62 -> 2
A63: 43008 | B63: 13558 | C63: AGOSTO | D63: AGUA | F63: 2 | G63: =+G62+E63-F63 -> 0
A64: 43008 | B64: POR COBRAR | C64: SEPTIEMBRE | D64: LUZ | E64: 8 | G64: =+G63+E64-F64 -> 8
D65: AGUA | E65: 2 | G65: =+G64+E65-F65 -> 10
D66: ALQUILER | E66: 210 | G66: =+G65+E66-F66 -> 220
A67: 43008 | B67: 13558 | C67: SEPTIEMBRE | D67: LUZ | F67: 2.8 | G67: =+G66+E67-F67 -> 217.2
A68: 43008 | B68: 13558 | C68: SEPTIEMBRE | D68: AGUA | F68: 2 | G68: =+G67+E68-F68 -> 215.2
A69: 43039 | B69: 13729 | C69: SEPTIEMBRE | D69: ALQUILER | F69: 50 | G69: =+G68+E69-F69 -> 165.2
A70: 43059 | B70: 13799 | C70: SEPTIEMBRE | D70: ALQUILER | F70: 50 | G70: =+G69+E70-F70 -> 115.2
A71: 43063 | B71: 13842 | C71: SEPTIEMBRE | D71: LUZ | F71: 5.2 | G71: =+G70+E71-F71 -> 110
A72: 43076 | B72: 13911 | C72: SEPTIEMBRE | D72: ALQUILER | F72: 40 | G72: =+G71+E72-F72 -> 70
A73: 43076 | B73: 13914 | C73: SEPTIEMBRE | D73: ALQUILER | F73: 20 | G73: =+G72+E73-F73 -> 50
A74: 43078 | B74: 13922 | C74: SEPTIEMBRE | D74: ALQUILER | F74: 20 | G74: =+G73+E74-F74 -> 30
A75: 43069 | B75: 13867 | C75: SEPTIEMBRE | D75: ALQUILER | F75: 10 | G75: =+G74+E75-F75 -> 20
A76: 43102 | B76: 14032 | C76: SEPTIEMBRE | D76: ALQUILER | F76: 20 | G76: =+G75+E76-F76 -> 0
A77: 43039 | B77: POR COBRAR | C77: OCTUBRE | D77: LUZ | E77: 8 | G77: =+G76+E77-F77 -> 8
D78: AGUA | E78: 2 | G78: =+G77+E78-F78 -> 10
D79: ALQUILER | E79: 210 | G79: =+G78+E79-F79 -> 220
A80: 43063 | B80: 13842 | C80: OCTUBRE | D80: LUZ | F80: 8 | G80: =+G79+E80-F80 -> 212
A81: 43063 | B81: 13842 | C81: OCTUBRE | D81: AGUA | F81: 2 | G81: =+G80+E81-F81 -> 210
A82: 43102 | B82: 14032 | C82: OCTUBRE | D82: ALQUILER | F82: 210 | G82: =+G81+E82-F82 -> 0
A83: 43069 | B83: POR COBRAR | C83: NOVIEMBRE | D83: LUZ | E83: 8.2 | G83: =+G82+E83-F83 -> 8.2
D84: AGUA | E84: 2 | G84: =+G83+E84-F84 -> 10.2
D85: ALQUILER | E85: 210 | G85: =+G84+E85-F85 -> 220.2
A86: 43063 | B86: 13842 | C86: NOVIEMBRE | D86: LUZ | F86: 2.8 | G86: =+G85+E86-F86 -> 217.4
A87: 43063 | B87: 13842 | C87: NOVIEMBRE | D87: AGUA | F87: 2 | G87: =+G86+E87-F87 -> 215.4
A88: 43102 | C88: NOVIEMBRE | D88: ALQUILER | F88: 70 | G88: =+G87+E88-F88 -> 145.4
A89: 43117 | B89: 14080 | C89: NOVIEMBRE | D89: LUZ | F89: 5.4 | G89: =+G88+E89-F89 -> 140
A90: 43117 | B90: 14080 | C90: NOVIEMBRE | D90: ALQUILER | F90: 140 | G90: =+G89+E90-F90 -> 0
A91: 43069 | B91: POR COBRAR | C91: DICIEMBRE | D91: LUZ | E91: 8.9 | G91: =+G90+E91-F91 -> 8.9
D92: AGUA | E92: 2 | G92: =+G91+E92-F92 -> 10.9
D93: ALQUILER | E93: 210 | G93: =+G92+E93-F93 -> 220.9
A94: 43117 | B94: 14080 | C94: DICIEMBRE | D94: ALQUILER | F94: 210 | G94: =+G93+E94-F94 -> 10.9
A95: 43118 | B95: 14107 | C95: DICIEMBRE | D95: LUZ | F95: 8.9 | G95: =+G94+E95-F95 -> 2
A96: 43118 | B96: 14107 | C96: DICIEMBRE | D96: AGUA | F96: 2 | G96: =+G95+E96-F96 -> 5.3290705e-15
A97: 43131 | B97: POR COBRAR | C97: ENERO | D97: LUZ | E97: 8 | G97: =+G96+E97-F97 -> 8
D98: AGUA | E98: 2 | G98: =+G97+E98-F98 -> 10
D99: ALQUILER | E99: 210 | G99: =+G98+E99-F99 -> 220
A100: 43190 | B100: 14406 | C100: ENERO | D100: ALQUILER | F100: 160 | G100: =+G99+E100-F100 -> 60
A101: 43160 | B101: 14303 | C101: ENERO | D101: LUZ | F101: 8 | G101: =+G100+E101-F101 -> 52
A102: 43160 | B102: 14303 | C102: ENERO | D102: AGUA | F102: 2 | G102: =+G101+E102-F102 -> 50
A103: 43220 | B103: 14538 | C103: ENERO | D103: ALQUILER | F103: 50 | G103: =+G102+E103-F103 -> 0
...

Sheet AVILA ROSA
B3: AVILA CHAVEZ ROSA
A5: FECHA | B5: DOCUMENTO | C5: PERIODO | D5: CONCEPTO | E5: POR COBRAR | F5: PAGADO
G6: 0
A7: 43196 | B7: POR COBRAR | C7: ABRIL | D7: LUZ | G7: =+G6+E7-F7 -> 0
D8: AGUA | G8: =+G7+E8-F8 -> 0
D9: ALQUILER | E9: 210 | G9: =+G8+E9-F9 -> 210
G10: =+G9+E10-F10 -> 210
D11: GUARDIANIA | E11: 60 | G11: =+G10+E11-F11 -> 270
A12: 43196 | B12: 14445 | C12: ABRIL | D12: ALQUILER | F12: 210 | G12: =+G11+E12-F12 -> 60
G13: =+G12+E13-F13 -> 60
A14: 43283 | B14: 14868 | C14: ABRIL | D14: GUARDIANIA | F14: 60 | G14: =+G13+E14-F14 -> 0
A15: 43250 | B15: POR COBRAR | C15: MAYO | D15: ALQUILER | E15: 210 | G15: =+G14+E15-F15 -> 210
D16: GUARDIANIA | E16: 60 | G16: =+G15+E16-F16 -> 270
A17: 43222 | B17: 14547 | C17: MAYO | D17: ALQUILER | F17: 210 | G17: =+G16+E17-F17 -> 60
A18: 43222 | B18: 14547 | C18: MAYO | D18: GUARDIANIA | F18: 60 | G18: =+G17+E18-F18 -> 0
A19: 43281 | B19: POR COBRAR | C19: JUNIO | D19: ALQUILER | E19: 210 | G19: =+G18+E19-F19 -> 210
D20: GUARDIANIA | E20: 60 | G20: =+G19+E20-F20 -> 270
A21: 43251 | B21: 14702 | C21: JUNIO | D21: ALQUILER | F21: 210 | G21: =+G20+E21-F21 -> 60
A22: 43251 | B22: 14702 | C22: JUNIO | D22: GUARDIANIA | F22: 60 | G22: =+G21+E22-F22 -> 0
A23: 43312 | B23: POR COBRAR | C23: JULIO | D23: ALQUILER | E23: 210 | G23: =+G22+E23-F23 -> 210
D24: GUARDIANIA | E24: 60 | G24: =+G23+E24-F24 -> 270
A25: 43283 | B25: 14868 | C25: JULIO | D25: ALQUILER | F25: 210 | G25: =+G24+E25-F25 -> 60
A26: 43283 | B26: 14868 | C26: JULIO | D26: GUARDIANIA | F26: 60 | G26: =+G25+E26-F26 -> 0
A27: 43343 | B27: POR COBRAR | C27: AGOSTO | D27: ALQUILER | E27: 210 | G27: =+G26+E27-F27 -> 210
D28: GUARDIANIA | E28: 60 | G28: =+G27+E28-F28 -> 270
A29: 43314 | B29: 14902 | C29: AGOSTO | D29: ALQUILER | F29: 210 | G29: =+G28+E29-F29 -> 60
A30: 43314 | B30: 14902 | C30: AGOSTO | D30: GUARDIANIA | F30: 60 | G30: =+G29+E30-F30 -> 0
A31: 43373 | B31: POR COBRAR | C31: SEPTIEMBRE | D31: ALQUILER | E31: 210 | G31: =+G30+E31-F31 -> 210
D32: GUARDIANIA | E32: 60 | G32: =+G31+E32-F32 -> 270
A33: 43346 | B33: 15137 | C33: SEPTIEMBRE | D33: ALQUILER | F33: 210 | G33: =+G32+E33-F33 -> 60
A34: 43346 | B34: 15137 | C34: SEPTIEMBRE | D34: GUARDIANIA | F34: 60 | G34: =+G33+E34-F34 -> 0
A35: 43404 | B35: POR COBRAR | C35: OCTUBRE | D35: ALQUILER | E35: 210 | G35: =+G34+E35-F35 -> 210
D36: GUARDIANIA | E36: 60 | G36: =+G35+E36-F36 -> 270
A37: 43374 | B37: 15251 | C37: OCTUBRE | D37: ALQUILER | F37: 210 | G37: =+G36+E37-F37 -> 60
A38: 43374 | B38: 15251 | C38: OCTUBRE | D38: GUARDIANIA | F38: 60 | G38: =+G37+E38-F38 -> 0
A39: 43434 | B39: POR COBRAR | C39: NOVIEMBRE | D39: ALQUILER | E39: 210 | G39: =+G38+E39-F39 -> 210
D40: GUARDIANIA | E40: 60 | G40: =+G39+E40-F40 -> 270
A41: 43404 | B41: 15386 | C41: NOVIEMBRE | D41: ALQUILER | F41: 210 | G41: =+G40+E41-F41 -> 60
A42: 43404 | B42: 15386 | C42: NOVIEMBRE | D42: GUARDIANIA | F42: 60 | G42: =+G41+E42-F42 -> 0
A43: 43465 | B43: POR COBRAR | C43: DICIEMBRE | D43: ALQUILER | E43: 210 | G43: =+G42+E43-F43 -> 210
D44: GUARDIANIA | E44: 60 | G44: =+G43+E44-F44 -> 270
A45: 43434 | B45: 15537 | D45: ALQUILER | F45: 210 | G45: =+G44+E45-F45 -> 60
A46: 43434 | B46: 15537 | C46: DICIEMBRE | D46: GUARDIANIA | F46: 60 | G46: =+G45+E46-F46 -> 0
A47: 43466 | B47: POR COBRAR | C47: ENERO | D47: ALQUILER | E47: 210 | G47: =+G46+E47-F47 -> 210
D48: GUARDIANIA | E48: 60 | G48: =+G47+E48-F48 -> 270
A49: 43830 | B49: 15668 | C49: ENERO | D49: ALQUILER | F49: 210 | G49: =+G48+E49-F49 -> 60
A50: 43830 | B50: 15668 | C50: ENERO | D50: GUARDIANIA | F50: 60 | G50: =+G49+E50-F50 -> 0
A51: 43524 | B51: POR COBRAR | C51: FEBRERO | D51: ALQUILER | E51: 210 | G51: =+G50+E51-F51 -> 210
D52: GUARDIANIA | E52: 60 | G52: =+G51+E52-F52 -> 270
A53: 43496 | B53: 15831 | C53: FEBRERO | D53: ALQUILER | F53: 210 | G53: =+G52+E53-F53 -> 60
A54: 43496 | B54: 15831 | C54: FEBRERO | D54: GUARDIANIA | F54: 60 | G54: =+G53+E54-F54 -> 0
A55: 43555 | B55: POR COBRAR | C55: MARZO | D55: ALQUILER | E55: 210 | G55: =+G54+E55-F55 -> 210
D56: GUARDIANIA | E56: 60 | G56: =+G55+E56-F56 -> 270
A57: 43524 | B57: 15957 | C57: MARZO | D57: ALQUILER | F57: 210 | G57: =+G56+E57-F57 -> 60
A58: 43524 | B58: 15957 | C58: MARZO | D58: GUARDIANIA | F58: 60 | G58: =+G57+E58-F58 -> 0
A59: 43585 | B59: POR COBRAR | C59: ABRIL | D59: ALQUILER | E59: 210 | G59: =+G58+E59-F59 -> 210
D60: GUARDIANIA | E60: 60 | G60: =+G59+E60-F60 -> 270
A61: 43554 | B61: B001-0000022 | C61: ABRIL | D61: ALQUILER | F61: 210 | G61: =+G60+E61-F61 -> 60
A62: 43554 | B62: B001-0000022 | C62: ABRIL | D62: GUARDIANIA | F62: 60 | G62: =+G61+E62-F62 -> 0
A63: 43616 | B63: POR COBRAR | C63: MAYO | D63: ALQUILER | E63: 210 | G63: =+G62+E63-F63 -> 210
D64: GUARDIANIA | E64: 60 | G64: =+G63+E64-F64 -> 270
A65: 43585 | B65: B001-0000167 | C65: MAYO | D65: ALQUILER | F65: 210 | G65: =+G64+E65-F65 -> 60
A66: 43585 | B66: B001-0000167 | C66: MAYO | D66: GUARDIANIA | F66: 60 | G66: =+G65+E66-F66 -> 0
A67: 43646 | B67: POR COBRAR | C67: JUNIO | D67: ALQUILER | E67: 210 | G67: =+G66+E67-F67 -> 210
D68: GUARDIANIA | E68: 60 | G68: =+G67+E68-F68 -> 270
A69: 43616 | B69: B001-0000293 | C69: JUNIO | D69: ALQUILER | F69: 210 | G69: =+G68+E69-F69 -> 60
A70: 43616 | B70: B001-0000293 | C70: JUNIO | D70: GUARDIANIA | F70: 60 | G70: =+G69+E70-F70 -> 0
A71: 43677 | B71: POR COBRAR | C71: JULIO | D71: ALQUILER | E71: 210 | G71: =+G70+E71-F71 -> 210
D72: GUARDIANIA | E72: 60 | G72: =+G71+E72-F72 -> 270
A73: 43644 | B73: B001-0000417 | C73: JULIO | D73: ALQUILER | F73: 210 | G73: =+G72+E73-F73 -> 60
A74: 43644 | B74: B001-0000417 | C74: JULIO | D74: GUARDIANIA | F74: 42 | G74: =+G73+E74-F74 -> 18
A75: 43677 | B75: B001-0000462 | C75: JULIO | D75: GUARDIANIA | F75: 18 | G75: =+G74+E75-F75 -> 0
A76: 43708 | B76: POR COBRAR | C76: AGOSTO | D76: ALQUILER | E76: 210 | G76: =+G75+E76-F76 -> 210
D77: GUARDIANIA | E77: 60 | G77: =+G76+E77-F77 -> 270
A78: 43677 | B78: B001-0000462 | C78: AGOSTO | D78: ALQUILER | F78: 210 | G78: =+G77+E78-F78 -> 60
A79: 43677 | B79: B001-0000462 | C79: AGOSTO | D79: GUARDIANIA | F79: 60 | G79: =+G78+E79-F79 -> 0
A80: 43738 | B80: POR COBRAR | C80: SEPTIEMBRE | D80: ALQUILER | E80: 210 | G80: =+G79+E80-F80 -> 210
D81: GUARDIANIA | E81: 60 | G81: =+G80+E81-F81 -> 270
A82: 43708 | B82: B001-0000551 | C82: SEPTIEMBRE | D82: ALQUILER | F82: 210 | G82: =+G81+E82-F82 -> 60
A83: 43708 | B83: B001-0000551 | C83: SEPTIEMBRE | D83: GUARDIANIA | F83: 60 | G83: =+G82+E83-F83 -> 0
A84: 43769 | B84: POR COBRAR | C84: OCTUBRE | D84: ALQUILER | E84: 210 | G84: =+G83+E84-F84 -> 210
D85: GUARDIANIA | E85: 60 | G85: =+G84+E85-F85 -> 270
A86: 43738 | B86: B001-0000649 | C86: OCTUBRE | D86: ALQUILER | F86: 210 | G86: =+G85+E86-F86 -> 60
A87: 43738 | B87: B001-0000649 | C87: OCTUBRE | D87: GUARDIANIA | F87: 60 | G87: =+G86+E87-F87 -> 0
A88: 43799 | B88: POR COBRAR | C88: NOVIEMBRE | D88: ALQUILER | E88: 210 | G88: =+G87+E88-F88 -> 210
D89: GUARDIANIA | E89: 60 | G89: =+G88+E89-F89 -> 270
A90: 43769 | B90: B001-0000732 | C90: NOVIEMBRE | D90: ALQUILER | F90: 210 | G90: =+G89+E90-F90 -> 60
A91: 43769 | B91: B001-0000732 | C91: NOVIEMBRE | D91: GUARDIANIA | F91: 60 | G91: =+G90+E91-F91 -> 0
A92: 43830 | B92: POR COBRAR | C92: DICIEMBRE | D92: ALQUILER | E92: 210 | G92: =+G91+E92-F92 -> 210
D93: GUARDIANIA | E93: 60 | G93: =+G92+E93-F93 -> 270
A94: 43799 | B94: B001-0000851 | C94: DICIEMBRE | D94: ALQUILER | F94: 210 | G94: =+G93+E94-F94 -> 60
A95: 43799 | B95: B001-0000851 | C95: DICIEMBRE | D95: GUARDIANIA | F95: 60 | G95: =+G94+E95-F95 -> 0
A96: 43861 | B96: POR COBRAR | C96: ENERO | D96: ALQUILER | E96: 210 | G96: =+G95+E96-F96 -> 210
D97: GUARDIANIA | E97: 60 | G97: =+G96+E97-F97 -> 270
A98: 43830 | B98: B001-0000966 | C98: ENERO | D98: ALQUILER | F98: 210 | G98: =+G97+E98-F98 -> 60
A99: 43830 | B99: B001-0000966 | C99: ENERO | D99: GUARDIANIA | F99: 60 | G99: =+G98+E99-F99 -> 0
A100: 43890 | B100: POR COBRAR | C100: FEBRERO | D100: ALQUILER | E100: 210 | G100: =+G99+E100-F100 -> 210
D101: GUARDIANIA | E101: 60 | G101: =+G100+E101-F101 -> 270
A102: 43861 | B102: B001-0001084 | C102: FEBRERO | D102: ALQUILER | F102: 210 | G102: =+G101+E102-F102 -> 60
A103: 43861 | B103: B001-0001084 | C103: FEBRERO | D103: GUARDIANIA | F103: 60 | G103: =+G102+E103-F103 -> 0
...

Sheet AYALA HILARY
B2: AYALA ARIAS HILARY ESPERANZA | I2: COMENZO EN MARZO 2024 | J2: DNI | K2: 70543729
A4: FECHA | B4: DOCUMENTO | C4: PERIODO | D4: CONCEPTO | E4: POR COBRAR | F4: PAGADO | G4: SALDO POR COBRAR
A6: 45382 | B6: POR COBRAR | C6: MARZO | D6: LUZ | E6: 20.6 | G6: =G5+E6-F6 -> 20.6
D7: AGUA | E7: 5 | G7: =G6+E7-F7 -> 25.6
D8: ALQUILER | E8: 350 | G8: =G7+E8-F8 -> 375.6
D9: GARANTIA | E9: 350 | G9: =G8+E9-F9 -> 725.6
A10: 45344 | B10: EB01-3339 | C10: MARZO | D10: GARANTIA | F10: 350 | G10: =G9+E10-F10 -> 375.6
A11: 45387 | B11: EB01-3525 | C11: MARZO | D11: ALQUILER | F11: 350 | G11: =G10+E11-F11 -> 25.6
A12: 45448 | B12: RII 2224 | C12: MARZO | D12: LUZ | F12: 20.6 | G12: =G11+E12-F12 -> 5
A13: 45448 | B13: RII 2224 | C13: MARZO | D13: AGUA | F13: 5 | G13: =G12+E13-F13 -> 2.1316282e-14
A14: 45412 | B14: POR COBRAR | C14: ABRIL | D14: LUZ | E14: 20.5 | G14: =G13+E14-F14 -> 20.5
D15: AGUA | E15: 5 | G15: =G14+E15-F15 -> 25.5
D16: ALQUILER | E16: 350 | G16: =G15+E16-F16 -> 375.5
A17: 45447 | B17: EB01-3786 | C17: ABRIL | D17: ALQUILER | F17: 350 | G17: =G16+E17-F17 -> 25.5
A18: 45448 | B18: RII 2224 | C18: ABRIL | D18: LUZ | F18: 20.5 | G18: =G17+E18-F18 -> 5
A19: 45448 | B19: RII 2224 | C19: ABRIL | D19: AGUA | F19: 5 | G19: =G18+E19-F19 -> 0
A20: 45443 | B20: POR COBRAR | C20: MAYO | D20: LUZ | E20: 18.6 | G20: =G19+E20-F20 -> 18.6
D21: AGUA | E21: 5 | G21: =G20+E21-F21 -> 23.6
D22: ALQUILER | E22: 350 | G22: =G21+E22-F22 -> 373.6
A23: 45475 | B23: EB01-3906 | C23: MAYO | D23: ALQUILER | F23: 350 | G23: =G22+E23-F23 -> 23.6
A24: 45476 | B24: RII 2271 | C24: MAYO | D24: LUZ | F24: 18.6 | G24: =G23+E24-F24 -> 5
A25: 45476 | B25: RII 2271 | C25: MAYO | D25: AGUA | F25: 5 | G25: =G24+E25-F25 -> 2.1316282e-14
A26: 45473 | B26: POR COBRAR | C26: JUNIO | D26: LUZ | E26: 18.1 | G26: =G25+E26-F26 -> 18.1
D27: AGUA | E27: 7 | G27: =G26+E27-F27 -> 25.1
D28: ALQUILER | E28: 350 | G28: =G27+E28-F28 -> 375.1
A29: 45488 | B29: EB01-3964 | C29: JUNIO | D29: ALQUILER | F29: 350 | G29: =G28+E29-F29 -> 25.1
A30: 45499 | B30: RII 2314 | C30: JUNIO | D30: LUZ | F30: 18.1 | G30: =G29+E30-F30 -> 7
A31: 45499 | B31: RII 2314 | C31: JUNIO | D31: AGUA | F31: 7 | G31: =G30+E31-F31 -> 2.1316282e-14
A32: 45504 | B32: POR COBRAR | C32: JULIO | D32: LUZ | E32: 17.8 | G32: =G31+E32-F32 -> 17.8
D33: AGUA | E33: 7 | G33: =G32+E33-F33 -> 24.8
D34: ALQUILER | E34: 350 | G34: =G33+E34-F34 -> 374.8
A35: 45511 | B35: EB01-4072 | C35: JULIO | D35: ALQUILER | F35: 350 | G35: =G34+E35-F35 -> 24.8
A36: 45546 | B36: RII 2401 | C36: JULIO | D36: LUZ | F36: 17.8 | G36: =G35+E36-F36 -> 7
A37: 45546 | B37: RII 2401 | C37: JULIO | D37: AGUA | F37: 7 | G37: =G36+E37-F37 -> 1.0658141e-14
A38: 45535 | B38: POR COBRAR | C38: AGOSTO | D38: LUZ | E38: 17.8 | G38: =G37+E38-F38 -> 17.8
D39: AGUA | E39: 7 | G39: =G38+E39-F39 -> 24.8
D40: ALQUILER | E40: 350 | G40: =G39+E40-F40 -> 374.8
A41: 45546 | B41: EB01-4224 | C41: AGOSTO | D41: ALQUILER | F41: 350 | G41: =G40+E41-F41 -> 24.8
A42: 45735 | B42: RII 2729 | C42: AGOSTO | D42: LUZ | F42: 17.8 | G42: =G41+E42-F42 -> 7
A43: 45735 | B43: RII 2729 | C43: AGOSTO | D43: AGUA | F43: 7 | G43: =G42+E43-F43 -> 1.0658141e-14
A44: 45565 | B44: POR COBRAR | C44: SETIEMBRE | D44: LUZ | E44: 17.9 | G44: =G43+E44-F44 -> 17.9
D45: AGUA | E45: 5 | G45: =G44+E45-F45 -> 22.9
D46: ALQUILER | E46: 350 | G46: =G45+E46-F46 -> 372.9
A47: 45590 | B47: EB01-4417 | C47: SETIEMBRE | D47: ALQUILER | F47: 350 | G47: =G46+E47-F47 -> 22.9
A48: 45735 | B48: RII 2729 | C48: SETIEMBRE | D48: LUZ | F48: 17.9 | G48: =G47+E48-F48 -> 5
A49: 45735 | B49: RII 2729 | C49: SETIEMBRE | D49: AGUA | F49: 5 | G49: =G48+E49-F49 -> 3.5527137e-14
A50: 45596 | B50: POR COBRAR | C50: OCTUBRE | D50: LUZ | E50: 14 | G50: =G49+E50-F50 -> 14
D51: AGUA | E51: 7 | G51: =G50+E51-F51 -> 21
D52: ALQUILER | E52: 350 | G52: =G51+E52-F52 -> 371
A53: 45609 | B53: EB01-4537 | C53: OCTUBRE | D53: ALQUILER | F53: 350 | G53: =G52+E53-F53 -> 21
A54: 45735 | B54: RII 2729 | C54: OCTUBRE | D54: LUZ | F54: 14 | G54: =G53+E54-F54 -> 7
A55: 45735 | B55: RII 2729 | C55: OCTUBRE | D55: AGUA | F55: 7 | G55: =G54+E55-F55 -> 5.6843419e-14
A56: 45626 | B56: POR COBRAR | C56: NOVIEMBRE | D56: LUZ | E56: 16.1 | G56: =G55+E56-F56 -> 16.1
D57: AGUA | E57: 7 | G57: =G56+E57-F57 -> 23.1 | K57: AYALA HILARY
D58: ALQUILER | E58: 350 | G58: =G57+E58-F58 -> 373.1 | I58: 2024 | J58: AGOSTO | K58: LUZ | L58: 17.8
A59: 45664 | B59: EB01-4823 | C59: NOVIEMBRE | D59: ALQUILER | F59: 350 | G59: =G58+E59-F59 -> 23.1 | K59: AGUA | L59: 7
A60: 45686 | B60: RII 2643 | C60: NOVIEMBRE | D60: LUZ | F60: 16.1 | G60: =G59+E60-F60 -> 7
A61: 45686 | B61: RII 2643 | C61: NOVIEMBRE | D61: AGUA | F61: 7 | G61: =G60+E61-F61 -> 7.8159701e-14
A62: 45657 | B62: POR COBRAR | C62: DICIEMBRE | D62: LUZ | E62: 19.7 | G62: =G61+E62-F62 -> 19.7 | J62: SETIEMBRE | K62: LUZ | L62: 17.9
D63: AGUA | E63: 3 | G63: =G62+E63-F63 -> 22.7 | K63: AGUA | L63: 5
D64: ALQUILER | E64: 350 | G64: =G63+E64-F64 -> 372.7 | J64: OCTUBRE | K64: LUZ | L64: 14
A65: 45664 | B65: EB01-4823 | C65: DICIEMBRE | D65: ALQUILER | F65: 350 | G65: =G64+E65-F65 -> 22.7 | K65: AGUA | L65: 7
A66: 45686 | B66: RII 2643 | C66: DICIEMBRE | D66: LUZ | F66: 19.7 | G66: =G65+E66-F66 -> 3 | J66: NOVIEMBRE | K66: LUZ | M66: 16.1
A67: 45686 | B67: RII 2643 | C67: DICIEMBRE | D67: AGUA | F67: 3 | G67: =G66+E67-F67 -> 1.030287e-13 | K67: AGUA | M67: 7
A68: 45688 | B68: POR COBRAR | C68: ENERO | D68: LUZ | E68: 17.5 | G68: =G67+E68-F68 -> 17.5 | J68: DICIEMBRE | K68: LUZ | M68: 19.7
D69: AGUA | E69: 3 | G69: =G68+E69-F69 -> 20.5 | K69: AGUA | M69: 3
D70: ALQUILER | E70: 350 | G70: =G69+E70-F70 -> 370.5 | L70: =SUM(L58:L69) -> 68.7
A71: 45735 | B71: RII 2729 | C71: ENERO | D71: LUZ | F71: 17.5 | G71: =G70+E71-F71 -> 353
A72: 45735 | B72: RII 2729 | C72: ENERO | D72: AGUA | F72: 3 | G72: =G71+E72-F72 -> 350
A73: 45804 | B73: EB01-5525 | C73: ENERO | D73: ALQUILER | F73: 350 | G73: =G72+E73-F73 -> 0
A74: 45716 | B74: POR COBRAR | C74: FEBRERO | D74: LUZ | E74: 16 | G74: =G73+E74-F74 -> 16
D75: AGUA | E75: 3 | G75: =G74+E75-F75 -> 19
D76: ALQUILER | E76: 256.5 | G76: =G75+E76-F76 -> 275.5
D77: GARANTIA DE STAND | E77: 1000 | G77: =G76+E77-F77 -> 1275.5
G78: =G77+E78-F78 -> 1275.5
A79: 45716 | B79: EB01-5106 | C79: FEBRERO | D79: GARANTIA DE STAND | F79: 1000 | G79: =G78+E79-F79 -> 275.5
A80: 45722 | B80: EB01-5170 | C80: FEBRERO | D80: ALQUILER | F80: 500 | G80: =G79+E80-F80 -> -224.5 | I80: NO HAY MONTO
A81: 45804 | B81: RII 2831 | C81: FEBRERO | D81: LUZ | F81: 16 | G81: =G80+E81-F81 -> -240.5
A82: 45804 | B82: RII 2831 | C82: FEBRERO | D82: AGUA | F82: 3 | G82: =G81+E82-F82 -> -243.5
A83: 45804 | B83: EB01-5525 | C83: FEBRERO | D83: ALQUILER | F83: 256.5 | G83: =G82+E83-F83 -> -500
A84: 45747 | B84: POR COBRAR | C84: MARZO | D84: LUZ | E84: 7 | G84: =G83+E84-F84 -> -493
D85: AGUA | E85: 3 | G85: =G84+E85-F85 -> -490
D86: ALQUILER | E86: 150 | G86: =G85+E86-F86 -> -340
A87: 45804 | B87: RII 2831 | C87: MARZO | D87: LUZ | F87: 7 | G87: =G86+E87-F87 -> -347
A88: 45804 | B88: RII 2831 | C88: MARZO | D88: AGUA | F88: 3 | G88: =G87+E88-F88 -> -350
A89: 45804 | B89: EB01-5525 | C89: MARZO | D89: ALQUILER | F89: 150 | G89: =G88+E89-F89 -> -500
A90: 45777 | B90: POR COBRAR | C90: ABRIL | D90: LUZ | E90: 20 | G90: =G89+E90-F90 -> -480
D91: AGUA | E91: 3 | G91: =G90+E91-F91 -> -477
D92: ALQUILER | E92: 500 | G92: =G91+E92-F92 -> 23
A93: 45722 | B93: EB01-5170 | C93: FEBRERO | D93: ALQUILER | F93: 500 | G93: =G92+E93-F93 -> -477
A94: 45804 | B94: RII 2831 | C94: FEBRERO | D94: LUZ | F94: 20 | G94: =G93+E94-F94 -> -497
A95: 45804 | B95: RII 2831 | C95: FEBRERO | D95: AGUA | F95: 3 | G95: =G94+E95-F95 -> -500
A96: 45808 | B96: POR COBRAR | C96: MAYO | D96: LUZ | E96: 20.3 | G96: =G95+E96-F96 -> -479.7
D97: AGUA | E97: 5 | G97: =G96+E97-F97 -> -474.7
D98: ALQUILER | E98: 500 | G98: =G97+E98-F98 -> 25.3
A99: 45826 | B99: RII 2872 | C99: MAYO | D99: LUZ | F99: 20.3 | G99: =G98+E99-F99 -> 5 | J99: AYALA HILARY
A100: 45826 | B100: RII 2872 | C100: MAYO | D100: AGUA | F100: 5 | G100: =G99+E100-F100 -> 1.0658141e-14 | I100: 2025 | J100: JULIO | K100: LUZ | L100: 12
A101: 45833 | B101: EB01-5657 | C101: MAYO | D101: ALQUILER | F101: 500 | G101: =G100+E101-F101 -> -500 | K101: AGUA | L101: 4
A102: 45838 | B102: POR COBRAR | C102: JUNIO | D102: LUZ | E102: 14.2 | G102: =G101+E102-F102 -> -485.8 | L102: =SUM(L100:L101) -> 16
D103: AGUA | E103: 4 | G103: =G102+E103-F103 -> -481.8
...

Sheet AZURZA DAYSI
B2: DAYSI ELIZABETH AZURZA TRIBIÑOS | I2: DNI | J2: 47384400
A4: FECHA | B4: DOCUMENTO | C4: PERIODO | D4: CONCEPTO | E4: POR COBRAR | F4: PAGADO | G4: SALDO POR COBRAR
A5: 42736 | B5: SALDO AL 2016 | G5: 113.1
A6: 42737 | B6: 11992 | C6: ACUENTA DEL 2016 | F6: 42 | G6: =+G5+E6-F6 -> 71.1
A7: 42739 | B7: 12015 | C7: ACUENTA DEL 2016 | F7: 18 | G7: =+G6+E7-F7 -> 53.1
A8: 42748 | B8: 12073 | C8: CANCELACION DEL 2016 | F8: 53.1 | G8: =+G7+E8-F8 -> 0
A9: 42766 | B9: POR COBRAR | C9: ENERO | D9: LUZ | E9: 13.5 | G9: =+G8+E9-F9 -> 13.5
D10: AGUA | E10: 2.7 | G10: =+G9+E10-F10 -> 16.2
D11: ALQUILER | E11: 210 | G11: =+G10+E11-F11 -> 226.2
A12: 42766 | B12: 12177 | C12: ENERO | D12: ALQUILER | F12: 60 | G12: =+G11+E12-F12 -> 166.2
A13: 42760 | B13: 12143 | C13: ENERO | D13: ALQUILER | F13: 14 | G13: =+G12+E13-F13 -> 152.2
A14: 42769 | B14: 12208 | C14: ENERO | D14: ALQUILER | F14: 42 | G14: =+G13+E14-F14 -> 110.2
A15: 42776 | B15: 12247 | C15: ENERO | D15: ALQUILER | F15: 28 | G15: =+G14+E15-F15 -> 82.2
A16: 42780 | B16: 12258 | C16: ENERO | D16: ALQUILER | F16: 28 | G16: =+G15+E16-F16 -> 54.2
A17: 42781 | B17: 12262 | C17: ENERO | D17: ALQUILER | F17: 28 | G17: =+G16+E17-F17 -> 26.2
A18: 42782 | B18: 12266 | C18: ENERO | D18: ALQUILER | F18: 10 | G18: =+G17+E18-F18 -> 16.2
A19: 43314 | B19: 14989 | C19: ENERO | D19: LUZ | F19: 13.5 | G19: =+G18+E19-F19 -> 2.7
A20: 43314 | B20: 14989 | C20: ENERO | D20: AGUA | F20: 2.7 | G20: =+G19+E20-F20 -> -1.1546319e-14
A21: 42794 | B21: POR COBRAR | C21: FEBRERO | D21: LUZ | E21: 13 | G21: =+G20+E21-F21 -> 13
D22: AGUA | E22: 2 | G22: =+G21+E22-F22 -> 15
D23: ALQUILER | E23: 210 | G23: =+G22+E23-F23 -> 225
A24: 42786 | B24: 12280 | C24: FEBRERO | D24: ALQUILER | F24: 28 | G24: =+G23+E24-F24 -> 197
A25: 42790 | B25: 12292 | C25: FEBRERO | D25: ALQUILER | F25: 28 | G25: =+G24+E25-F25 -> 169
A26: 42782 | B26: 12266 | C26: FEBRERO | D26: ALQUILER | F26: 18 | G26: =+G25+E26-F26 -> 151
A27: 42817 | B27: 12427 | C27: FEBRERO | D27: ALQUILER | F27: 28 | G27: =+G26+E27-F27 -> 123
A28: 42821 | B28: 12448 | C28: FEBRERO | D28: ALQUILER | F28: 42 | G28: =+G27+E28-F28 -> 81
A29: 42824 | B29: 12455 | C29: FEBRERO | D29: ALQUILER | F29: 28 | G29: =+G28+E29-F29 -> 53
A30: 42857 | B30: 12581 | C30: FEBRERO | D30: ALQUILER | F30: 7 | G30: =+G29+E30-F30 -> 46
A31: 42858 | B31: 12599 | C31: FEBRERO | D31: ALQUILER | F31: 7 | G31: =+G30+E31-F31 -> 39
A32: 42859 | B32: 12620 | C32: FEBRERO | D32: ALQUILER | F32: 7 | G32: =+G31+E32-F32 -> 32
A33: 42860 | B33: 12636 | C33: FEBRERO | D33: ALQUILER | F33: 7 | G33: =+G32+E33-F33 -> 25
A34: 42861 | B34: 12645 | C34: FEBRERO | D34: ALQUILER | F34: 7 | G34: =+G33+E34-F34 -> 18
A35: 42863 | B35: 12652 | C35: FEBRERO | D35: ALQUILER | F35: 3 | G35: =+G34+E35-F35 -> 15
... A37: 43314 | B37: 14989 | C37: FEBRERO | D37: AGUA | F37: 2 | G37: =+G36+E37-F37 -> 0
A38: 42825 | B38: POR COBRAR | C38: MARZO | D38: LUZ | E38: 12 | G38: =+G37+E38-F38 -> 12
D39: AGUA | E39: 2 | G39: =+G38+E39-F39 -> 14
D40: ALQUILER | E40: 210 | G40: =+G39+E40-F40 -> 224
A41: 42863 | B41: 12652 | C41: MARZO | D41: ALQUILER | F41: 11 | G41: =+G40+E41-F41 -> 213
A42: 42870 | B42: 12679 | C42: MARZO | D42: ALQUILER | F42: 21 | G42: =+G41+E42-F42 -> 192
A43: 42884 | B43: 12717 | C43: MARZO | D43: ALQUILER | F43: 28 | G43: =+G42+E43-F43 -> 164
A44: 42879 | B44: 12705 | D44: ALQUILER | F44: 35 | G44: =+G43+E44-F44 -> 129
A45: 42865 | B45: 12669 | C45: MARZO | D45: ALQUILER | F45: 7 | G45: =+G44+E45-F45 -> 122
A46: 42864 | B46: 12668 | C46: MARZO | D46: ALQUILER | F46: 7 | G46: =+G45+E46-F46 -> 115
A47: 42891 | B47: 12777 | C47: MARZO | D47: ALQUILER | F47: 28 | G47: =+G46+E47-F47 -> 87
A48: 42913 | B48: 12880 | C48: MARZO | D48: ALQUILER | F48: 31 | G48: =+G47+E48-F48 -> 56
A49: 42924 | B49: 12971 | C49: MARZO | D49: ALQUILER | F49: 35 | G49: =+G48+E49-F49 -> 21
A50: 42935 | B50: 13035 | C50: MARZO | D50: ALQUILER | F50: 7 | G50: =+G49+E50-F50 -> 14
A51: 43192 | B51: 14422 | C51: MARZO | D51: LUZ | F51: 8.2 | G51: =+G50+E51-F51 -> 5.8
A52: 43192 | B52: 14422 | C52: MARZO | D52: AGUA | F52: 2 | G52: =+G51+E52-F52 -> 3.8
A53: 43314 | B53: 14989 | C53: MARZO | D53: LUZ | F53: 3.8 | G53: =+G52+E53-F53 -> 0
A54: 42855 | B54: POR COBRAR | C54: ABRIL | D54: LUZ | E54: 13 | G54: =+G53+E54-F54 -> 13
D55: AGUA | E55: 2 | G55: =+G54+E55-F55 -> 15
D56: ALQUILER | E56: 210 | G56: =+G55+E56-F56 -> 225
A57: 42913 | B57: 12880 | C57: ABRIL | D57: ALQUILER | F57: 33 | G57: =+G56+E57-F57 -> 192
A58: 42941 | B58: 13053 | C58: ABRIL | D58: ALQUILER | F58: 100 | G58: =+G57+E58-F58 -> 92
A59: 42947 | B59: 13074 | C59: ABRIL | D59: ALQUILER | F59: 7 | G59: =+G58+E59-F59 -> 85
A60: 42947 | B60: 13092 | C60: ABRIL | D60: ALQUILER | F60: 63 | G60: =+G59+E60-F60 -> 22
A61: 42949 | B61: 13220 | C61: ABRIL | D61: ALQUILER | F61: 7 | G61: =+G60+E61-F61 -> 15
A62: 43314 | B62: 14989 | C62: ABRIL | D62: LUZ | F62: 13 | G62: =+G61+E62-F62 -> 2
A63: 43314 | B63: 14989 | C63: ABRIL | D63: AGUA | F63: 2 | G63: =+G62+E63-F63 -> 0
A64: 42886 | B64: POR COBRAR | C64: MAYO | D64: LUZ | E64: 13 | G64: =+G63+E64-F64 -> 13
D65: AGUA | E65: 2 | G65: =+G64+E65-F65 -> 15
D66: ALQUILER | E66: 210 | G66: =+G65+E66-F66 -> 225
A67: 42947 | B67: 13092 | C67: MAYO | D67: ALQUILER | F67: 48 | G67: =+G66+E67-F67 -> 177
A68: 42961 | B68: 13261 | C68: MAYO | D68: ALQUILER | F68: 7 | G68: =+G67+E68-F68 -> 170
A69: 42963 | B69: 13273 | C69: MAYO | D69: ALQUILER | F69: 14 | G69: =+G68+E69-F69 -> 156
A70: 42964 | B70: 13280 | C70: MAYO | D70: ALQUILER | F70: 7 | G70: =+G69+E70-F70 -> 149
A71: 42965 | B71: 13285 | C71: MAYO | D71: ALQUILER | F71: 7 | G71: =+G70+E71-F71 -> 142
A72: 42969 | B72: 13296 | C72: MAYO | D72: ALQUILER | F72: 7 | G72: =+G71+E72-F72 -> 135
A73: 42970 | B73: 13301 | C73: MAYO | D73: ALQUILER | F73: 7 | G73: =+G72+E73-F73 -> 128
A74: 42972 | B74: 13320 | C74: MAYO | D74: ALQUILER | F74: 7 | G74: =+G73+E74-F74 -> 121
A75: 42972 | B75: 13322 | C75: MAYO | D75: ALQUILER | F75: 7 | G75: =+G74+E75-F75 -> 114
A76: 42973 | B76: 13334 | C76: MAYO | D76: ALQUILER | F76: 7 | G76: =+G75+E76-F76 -> 107
A77: 42975 | B77: 13337 | C77: MAYO | D77: ALQUILER | F77: 7 | G77: =+G76+E77-F77 -> 100
A78: 42975 | B78: 13344 | C78: MAYO | D78: ALQUILER | F78: 7 | G78: =+G77+E78-F78 -> 93
... A88: 43314 | B88: 14989 | C88: MAYO | D88: AGUA | F88: 2 | G88: =+G87+E88-F88 -> 0
A89: 42916 | B89: POR COBRAR | C89: JUNIO | D89: LUZ | E89: 12.5 | G89: =+G88+E89-F89 -> 12.5
D90: AGUA | E90: 2 | G90: =+G89+E90-F90 -> 14.5
D91: ALQUILER | E91: 210 | G91: =+G90+E91-F91 -> 224.5
A92: 42983 | B92: 13392 | C92: JUNIO | D92: ALQUILER | F92: 85 | G92: =+G91+E92-F92 -> 139.5
A93: 42985 | B93: 13415 | C93: JUNIO | D93: ALQUILER | F93: 14 | G93: =+G92+E93-F93 -> 125.5
A94: 42986 | B94: 13428 | C94: JUNIO | D94: ALQUILER | F94: 7 | G94: =+G93+E94-F94 -> 118.5
A95: 42989 | B95: 13446 | C95: JUNIO | D95: ALQUILER | F95: 14 | G95: =+G94+E95-F95 -> 104.5
A96: 42990 | B96: 13453 | C96: JUNIO | D96: ALQUILER | F96: 7 | G96: =+G95+E96-F96 -> 97.5
A97: 42991 | C97: JUNIO | D97: ALQUILER | F97: 7 | G97: =+G96+E97-F97 -> 90.5
A98: 42992 | B98: 13460 | C98: JUNIO | D98: ALQUILER | F98: 7 | G98: =+G97+E98-F98 -> 83.5
A99: 42993 | B99: 13466 | C99: JUNIO | D99: ALQUILER | F99: 7 | G99: =+G98+E99-F99 -> 76.5
A100: 42994 | B100: 13477 | C100: JUNIO | D100: ALQUILER | F100: 7 | G100: =+G99+E100-F100 -> 69.5
A101: 42996 | B101: 13482 | C101: JUNIO | D101: ALQUILER | F101: 7 | G101: =+G100+E101-F101 -> 62.5
A102: 42996 | B102: 13480 | C102: JUNIO | D102: ALQUILER | F102: 7 | G102: =+G101+E102-F102 -> 55.5
A103: 42997 | B103: 13497 | C103: JUNIO | D103: ALQUILER | F103: 7 | G103: =+G102+E103-F103 -> 48.5
A104: 42998 | B104: 13502 | C104: JUNIO | D104: ALQUILER | F104: 7 | G104: =+G103+E104-F104 -> 41.5
A105: 42999 | B105: 13510 | C105: JUNIO | D105: ALQUILER | F105: 7 | G105: =+G104+E105-F105 -> 34.5
A106: 43000 | B106: 13514 | C106: JUNIO | D106: ALQUILER | F106: 7 | G106: =+G105+E106-F106 -> 27.5
A107: 43001 | B107: 13517 | C107: JUNIO | D107: ALQUILER | F107: 7 | G107: =+G106+E107-F107 -> 20.5
A108: 43003 | B108: 13524 | C108: JUNIO | D108: ALQUILER | F108: 6 | G108: =+G107+E108-F108 -> 14.5
A109: 43314 | B109: 14990 | C109: JUNIO | D109: LUZ | F109: 12.5 | G109: =+G108+E109-F109 -> 2
A110: 43314 | B110: 14990 | C110: JUNIO | D110: AGUA | F110: 2 | G110: =+G109+E110-F110 -> 0
A111: 42947 | B111: POR COBRAR | C111: JULIO | D111: LUZ | E111: 13 | G111: =+G110+E111-F111 -> 13
D112: AGUA | E112: 2 | G112: =+G111+E112-F112 -> 15
...

Sheet BENITES ERIKA
E1: SILVIA AZURZA
B3: ERIKA BENITES TRIBIÑOS
A5: FECHA | B5: DOCUMENTO | C5: PERIODO | D5: CONCEPTO | E5: POR COBRAR | F5: PAGADO | G5: SALDO POR COBRAR
A6: 42736 | B6: SALDO AL 2016 | G6: 53.1
A7: 42744 | B7: 12050 | C7: ACUENTA DEL 2016 | F7: 46.2 | G7: =+G6+E7-F7 -> 6.9
A8: 42748 | B8: 12074 | C8: CANCELACION DEL 2016 | F8: 6.9 | G8: =+G7+E8-F8 -> 0
A9: 42766 | B9: POR COBRAR | C9: ENERO | D9: LUZ | E9: 13.5 | G9: =+G8+E9-F9 -> 13.5
D10: AGUA | E10: 2.8 | G10: =+G9+E10-F10 -> 16.3
D11: ALQUILER | E11: 210 | G11: =+G10+E11-F11 -> 226.3
A12: 42744 | B12: 12048 | C12: ENERO | D12: ALQUILER | F12: 42 | G12: =+G11+E12-F12 -> 184.3
A13: 42748 | B13: 12075 | C13: ENERO | D13: ALQUILER | F13: 42 | G13: =+G12+E13-F13 -> 142.3
A14: 42751 | B14: 12089 | C14: ENERO | D14: ALQUILER | F14: 28 | G14: =+G13+E14-F14 -> 114.3
A15: 42753 | B15: 12112 | C15: ENERO | D15: ALQUILER | F15: 28 | G15: =+G14+E15-F15 -> 86.3
A16: 42755 | B16: 12126 | C16: ENERO | D16: ALQUILER | F16: 28 | G16: =+G15+E16-F16 -> 58.3
A17: 42760 | B17: 12142 | C17: ENERO | D17: ALQUILER | F17: 42 | G17: =+G16+E17-F17 -> 16.3
A18: 42993 | B18: 13465 | C18: ENERO | D18: LUZ | F18: 10 | G18: =+G17+E18-F18 -> 6.3
A19: 43167 | B19: 14342 | C19: ENERO | D19: LUZ | F19: 3.5 | G19: =+G18+E19-F19 -> 2.8
A20: 43167 | B20: 14342 | C20: ENERO | D20: AGUA | F20: 2 | G20: =+G19+E20-F20 -> 0.8
A21: 43179 | B21: 14369 | C21: ENERO | D21: AGUA | F21: 0.8 | G21: =+G20+E21-F21 -> 1.1324275e-14
A22: 42794 | B22: POR COBRAR | C22: FEBRERO | D22: LUZ | E22: 13 | G22: =+G21+E22-F22 -> 13
D23: AGUA | E23: 2 | G23: =+G22+E23-F23 -> 15
D24: ALQUILER | E24: 210 | G24: =+G23+E24-F24 -> 225
A25: 43201 | B25: 14456 | C25: FEBRERO | D25: AGUA | F25: 1.3 | G25: =+G24+E25-F25 -> 223.7
A26: 42801 | B26: 12354 | C26: FEBRERO | D26: ALQUILER | F26: 42 | G26: =+G25+E26-F26 -> 181.7
A27: 42776 | B27: 12371 | C27: FEBRERO | D27: ALQUILER | F27: 28 | G27: =+G26+E27-F27 -> 153.7
A28: 42809 | B28: 12404 | C28: FEBRERO | D28: ALQUILER | F28: 42 | G28: =+G27+E28-F28 -> 111.7
A29: 42815 | B29: 12418 | C29: FEBRERO | D29: ALQUILER | F29: 42 | G29: =+G28+E29-F29 -> 69.7
A30: 42857 | B30: 12580 | C30: FEBRERO | D30: ALQUILER | F30: 7 | G30: =+G29+E30-F30 -> 62.7
A31: 42858 | B31: 12598 | C31: FEBRERO | D31: ALQUILER | F31: 7 | G31: =+G30+E31-F31 -> 55.7
A32: 42859 | B32: 12619 | C32: FEBRERO | D32: ALQUILER | F32: 7 | G32: =+G31+E32-F32 -> 48.7
A33: 42860 | B33: 12637 | C33: FEBRERO | D33: ALQUILER | F33: 7 | G33: =+G32+E33-F33 -> 41.7
A34: 42861 | B34: 12646 | C34: FEBRERO | D34: ALQUILER | F34: 7 | G34: =+G33+E34-F34 -> 34.7
A35: 42863 | B35: 12651 | C35: FEBRERO | D35: ALQUILER | F35: 14 | G35: =+G34+E35-F35 -> 20.7
A36: 42864 | B36: 12667 | C36: FEBRERO | D36: ALQUILER | F36: 7 | G36: =+G35+E36-F36 -> 13.7
... A39: 43179 | B39: 14369 | C39: FEBRERO | D39: AGUA | F39: 0.7 | G39: =+G38+E39-F39 -> -1.1324275e-14
A40: 42825 | B40: POR COBRAR | C40: MARZO | D40: LUZ | E40: 12 | G40: =+G39+E40-F40 -> 12
D41: AGUA | E41: 2 | G41: =+G40+E41-F41 -> 14
D42: ALQUILER | E42: 210 | G42: =+G41+E42-F42 -> 224
A43: 43201 | B43: 14456 | C43: MARZO | D43: AGUA | F43: 2 | G43: =+G42+E43-F43 -> 222
A44: 43201 | B44: 14456 | C44: MARZO | D44: LUZ | F44: 7.7 | G44: =+G43+E44-F44 -> 214.3
A45: 42865 | B45: 12670 | D45: ALQUILER | F45: 7 | G45: =+G44+E45-F45 -> 207.3
A46: 42870 | B46: 12680 | C46: MARZO | D46: ALQUILER | F46: 21 | G46: =+G45+E46-F46 -> 186.3
A47: 42879 | B47: 12704 | C47: MARZO | D47: ALQUILER | F47: 35 | G47: =+G46+E47-F47 -> 151.3
A48: 42884 | B48: 12718 | C48: MARZO | D48: ALQUILER | F48: 28 | G48: =+G47+E48-F48 -> 123.3
A49: 42891 | B49: 12776 | C49: MARZO | D49: ALQUILER | F49: 28 | G49: =+G48+E49-F49 -> 95.3
A50: 42913 | B50: 12881 | C50: MARZO | D50: ALQUILER | F50: 64 | G50: =+G49+E50-F50 -> 31.3
A51: 42924 | B51: 12970 | C51: MARZO | D51: ALQUILER | F51: 27 | G51: =+G50+E51-F51 -> 4.3
A52: 43208 | B52: 14493 | C52: MARZO | D52: LUZ | F52: 4.3 | G52: =+G51+E52-F52 -> 1.1546319e-14
A53: 42855 | B53: POR COBRAR | C53: ABRIL | D53: LUZ | E53: 13 | G53: =+G52+E53-F53 -> 13
D54: AGUA | E54: 2 | G54: =+G53+E54-F54 -> 15
D55: ALQUILER | E55: 210 | G55: =+G54+E55-F55 -> 225
A56: 42924 | B56: 12970 | C56: ABRIL | D56: ALQUILER | F56: 8 | G56: =+G55+E56-F56 -> 217
A57: 42935 | B57: 13036 | C57: ABRIL | D57: ALQUILER | F57: 7 | G57: =+G56+E57-F57 -> 210
A58: 42941 | B58: 13054 | C58: ABRIL | D58: ALQUILER | F58: 100 | G58: =+G57+E58-F58 -> 110
A59: 42947 | B59: 13075 | C59: ABRIL | D59: ALQUILER | F59: 7 | G59: =+G58+E59-F59 -> 103
A60: 42956 | B60: 13247 | C60: ABRIL | D60: ALQUILER | F60: 7 | G60: =+G59+E60-F60 -> 96
A61: 42949 | B61: 13219 | C61: ABRIL | D61: ALQUILER | F61: 7 | G61: =+G60+E61-F61 -> 89
A62: 42947 | B62: 13091 | C62: ABRIL | D62: ALQUILER | F62: 74 | G62: =+G61+E62-F62 -> 15
A63: 43208 | B63: 14493 | C63: ABRIL | D63: LUZ | F63: 4.3 | G63: =+G62+E63-F63 -> 10.7
A64: 43236 | B64: 14610 | C64: ABRIL | D64: LUZ | F64: 8.3 | G64: =+G63+E64-F64 -> 2.4
A65: 43256 | B65: 14757 | C65: ABRIL | D65: LUZ | F65: 0.4 | G65: =+G64+E65-F65 -> 2
A66: 43256 | B66: 14757 | C66: ABRIL | D66: AGUA | F66: 2 | G66: =+G65+E66-F66 -> 0
A67: 42886 | B67: POR COBRAR | C67: MAYO | D67: LUZ | E67: 13 | G67: =+G66+E67-F67 -> 13
D68: AGUA | E68: 2 | G68: =+G67+E68-F68 -> 15
D69: ALQUILER | E69: 210 | G69: =+G68+E69-F69 -> 225
A70: 42947 | B70: 13091 | C70: MAYO | D70: ALQUILER | F70: 37 | G70: =+G69+E70-F70 -> 188
A71: 42961 | B71: 13260 | C71: MAYO | D71: ALQUILER | F71: 7 | G71: =+G70+E71-F71 -> 181
A72: 42963 | B72: 13274 | C72: MAYO | D72: ALQUILER | F72: 14 | G72: =+G71+E72-F72 -> 167
A73: 42964 | B73: 13279 | C73: MAYO | D73: ALQUILER | F73: 7 | G73: =+G72+E73-F73 -> 160
A74: 42965 | B74: 13284 | C74: MAYO | D74: ALQUILER | F74: 7 | G74: =+G73+E74-F74 -> 153
A75: 42969 | B75: 13295 | C75: MAYO | D75: ALQUILER | F75: 7 | G75: =+G74+E75-F75 -> 146
A76: 42970 | B76: 13302 | C76: MAYO | D76: ALQUILER | F76: 7 | G76: =+G75+E76-F76 -> 139
A77: 42972 | B77: 13319 | C77: MAYO | D77: ALQUILER | F77: 7 | G77: =+G76+E77-F77 -> 132
A78: 42972 | B78: 13321 | C78: MAYO | D78: ALQUILER | F78: 7 | G78: =+G77+E78-F78 -> 125
A79: 42973 | B79: 13333 | C79: MAYO | D79: ALQUILER | F79: 7 | G79: =+G78+E79-F79 -> 118
A80: 42975 | B80: 13336 | C80: MAYO | D80: ALQUILER | F80: 7 | G80: =+G79+E80-F80 -> 111
A81: 42975 | B81: 13336 | C81: MAYO | D81: ALQUILER | F81: 7 | G81: =+G80+E81-F81 -> 104
... A90: 43256 | B90: 14757 | C90: MAYO | D90: AGUA | F90: 2 | G90: =+G89+E90-F90 -> 0
A91: 42916 | B91: POR COBRAR | C91: JUNIO | D91: LUZ | E91: 13 | G91: =+G90+E91-F91 -> 13
D92: AGUA | E92: 2 | G92: =+G91+E92-F92 -> 15
D93: ALQUILER | E93: 210 | G93: =+G92+E93-F93 -> 225
A94: 42983 | B94: 13392 | C94: JUNIO | D94: ALQUILER | F94: 67 | G94: =+G93+E94-F94 -> 158
A95: 42983 | B95: 13414 | C95: JUNIO | D95: ALQUILER | F95: 14 | G95: =+G94+E95-F95 -> 144
A96: 42986 | B96: 13427 | C96: JUNIO | D96: ALQUILER | F96: 7 | G96: =+G95+E96-F96 -> 137
A97: 42989 | B97: 13445 | C97: JUNIO | D97: ALQUILER | F97: 14 | G97: =+G96+E97-F97 -> 123
A98: 42990 | B98: 13452 | C98: JUNIO | D98: ALQUILER | F98: 7 | G98: =+G97+E98-F98 -> 116
A99: 42991 | B99: 13457 | C99: JUNIO | D99: ALQUILER | F99: 7 | G99: =+G98+E99-F99 -> 109
A100: 42992 | B100: 13459 | C100: JUNIO | D100: ALQUILER | F100: 7 | G100: =+G99+E100-F100 -> 102
A101: 42978 | B101: TARJETA | C101: JUNIO | D101: ALQUILER | F101: 84 | G101: =+G100+E101-F101 -> 18
A102: 42979 | B102: 13362 | C102: JUNIO | D102: ALQUILER | F102: 3 | G102: =+G101+E102-F102 -> 15
A103: 43236 | B103: 14610 | C103: JUNIO | D103: LUZ | F103: 13 | G103: =+G102+E103-F103 -> 2
A104: 43256 | B104: 14757 | C104: JUNIO | D104: LUZ | F104: 2 | G104: =+G103+E104-F104 -> 0
A105: 42947 | B105: POR COBRAR | C105: JULIO | D105: LUZ | E105: 13 | G105: =+G104+E105-F105 -> 13
D106: AGUA | E106: 2 | G106: =+G105+E106-F106 -> 15
D107: ALQUILER | E107: 210 | G107: =+G106+E107-F107 -> 225
A108: 42997 | B108: 13496 | C108: JULIO | D108: ALQUILER | F108: 7 | G108: =+G107+E108-F108 -> 218
A109: 42996 | B109: 13481 | C109: JULIO | D109: ALQUILER | F109: 7 | G109: =+G108+E109-F109 -> 211
A110: 42996 | B110: 13479 | C110: JULIO | D110: ALQUILER | F110: 7 | G110: =+G109+E110-F110 -> 204
A111: 42994 | B111: 13476 | C111: JULIO | D111: ALQUILER | F111: 7 | G111: =+G110+E111-F111 -> 197
A112: 42999 | B112: 13509 | C112: JULIO | D112: ALQUILER | F112: 7 | G112: =+G111+E112-F112 -> 190
...

Sheet BELLIDO ZENAIDA
B3: BELLIDO DE LA TORRE DE CHUQUITAIPE ZENAIDA
A5: FECHA | B5: DOCUMENTO | C5: PERIODO | D5: CONCEPTO | E5: POR COBRAR | F5: PAGADO | G5: SALDO POR COBRAR
A6: 42736 | B6: SALDO AL 2016 | G6: 475.3
A7: 42737 | B7: 11997 | C7: ACUENTA DEL 2016 | F7: 450 | G7: =+G6+E7-F7 -> 25.3
A8: 42754 | B8: 12121 | C8: CANCELACION DEL 2016 | F8: 25.3 | G8: =+G7+E8-F8 -> 0
A9: 42766 | B9: POR COBRAR | C9: ENERO | D9: LUZ | E9: 22.8 | G9: =+G8+E9-F9 -> 22.8
D10: AGUA | E10: 2.8 | G10: =+G9+E10-F10 -> 25.6
D11: ALQUILER | E11: 450 | G11: =+G10+E11-F11 -> 475.6
A12: 42773 | B12: 12223 | C12: ENERO | D12: ALQUILER | F12: 450 | G12: =+G11+E12-F12 -> 25.6
A13: 42797 | B13: 12322 | C13: ENERO | D13: LUZ | F13: 22.8 | G13: =+G12+E13-F13 -> 2.8
A14: 42797 | B14: 12322 | C14: ENERO | D14: AGUA | F14: 2.8 | G14: =+G13+E14-F14 -> 2.220446e-14
A15: 42794 | B15: POR COBRAR | C15: FEBRERO | D15: LUZ | E15: 21.8 | G15: =+G14+E15-F15 -> 21.8
D16: AGUA | E16: 2 | G16: =+G15+E16-F16 -> 23.8
D17: ALQUILER | E17: 450 | G17: =+G16+E17-F17 -> 473.8
A18: 42797 | B18: 12322 | C18: FEBRERO | D18: ALQUILER | F18: 450 | G18: =+G17+E18-F18 -> 23.8
A19: 42829 | B19: 12476 | C19: FEBRERO | D19: LUZ | F19: 21.8 | G19: =+G18+E19-F19 -> 2
A20: 42829 | B20: 12476 | C20: FEBRERO | D20: AGUA | F20: 2 | G20: =+G19+E20-F20 -> 1.0658141e-14
A21: 42825 | B21: POR COBRAR | C21: MARZO | D21: LUZ | E21: 20.5 | G21: =+G20+E21-F21 -> 20.5
D22: AGUA | E22: 2 | G22: =+G21+E22-F22 -> 22.5
D23: ALQUILER | E23: 450 | G23: =+G22+E23-F23 -> 472.5
A24: 42829 | B24: 12476 | C24: MARZO | D24: ALQUILER | F24: 450 | G24: =+G23+E24-F24 -> 22.5
A25: 42857 | B25: 12582 | C25: MARZO | D25: LUZ | F25: 20.5 | G25: =+G24+E25-F25 -> 2
A26: 42857 | B26: 12582 | C26: MARZO | D26: AGUA | F26: 2 | G26: =+G25+E26-F26 -> 0
A27: 42855 | B27: POR COBRAR | C27: ABRIL | D27: LUZ | E27: 21.6 | G27: =+G26+E27-F27 -> 21.6
D28: AGUA | E28: 2 | G28: =+G27+E28-F28 -> 23.6
D29: ALQUILER | E29: 450 | G29: =+G28+E29-F29 -> 473.6
A30: 42857 | B30: 12582 | C30: ABRIL | D30: ALQUILER | F30: 450 | G30: =+G29+E30-F30 -> 23.6
A31: 42888 | B31: 12771 | C31: ABRIL | D31: LUZ | F31: 21.6 | G31: =+G30+E31-F31 -> 2
A32: 42888 | B32: 12771 | C32: ABRIL | D32: AGUA | F32: 2 | G32: =+G31+E32-F32 -> 2.1316282e-14
A33: 42886 | B33: POR COBRAR | C33: MAYO | D33: LUZ | E33: 20.9 | G33: =+G32+E33-F33 -> 20.9
D34: AGUA | E34: 2 | G34: =+G33+E34-F34 -> 22.9
D35: ALQUILER | E35: 450 | G35: =+G34+E35-F35 -> 472.9
A36: 42888 | B36: 12770 | C36: MAYO | D36: ALQUILER | F36: 450 | G36: =+G35+E36-F36 -> 22.9
A37: 42919 | B37: 12934 | C37: MAYO | D37: LUZ | F37: 20.9 | G37: =+G36+E37-F37 -> 2
A38: 42919 | B38: 12934 | C38: MAYO | D38: AGUA | F38: 2 | G38: =+G37+E38-F38 -> 3.5527137e-14
A39: 42916 | B39: POR COBRAR | C39: JUNIO | D39: LUZ | E39: 20.3 | G39: =+G38+E39-F39 -> 20.3
D40: AGUA | E40: 2 | G40: =+G39+E40-F40 -> 22.3
D41: ALQUILER | E41: 450 | G41: =+G40+E41-F41 -> 472.3
A42: 42919 | B42: 12934 | C42: JUNIO | D42: ALQUILER | F42: 450 | G42: =+G41+E42-F42 -> 22.3
A43: 42954 | B43: 13238 | C43: JUNIO | D43: LUZ | F43: 20.3 | G43: =+G42+E43-F43 -> 2
A44: 42954 | B44: 13238 | C44: JUNIO | D44: AGUA | F44: 2 | G44: =+G43+E44-F44 -> 1.0658141e-14
A45: 42947 | B45: POR COBRAR | D45: LUZ | E45: 19.8 | G45: =+G44+E45-F45 -> 19.8
D46: AGUA | E46: 2 | G46: =+G45+E46-F46 -> 21.8
D47: ALQUILER | E47: 450 | G47: =+G46+E47-F47 -> 471.8
A48: 42954 | B48: 13238 | C48: JULIO | D48: ALQUILER | F48: 300 | G48: =+G47+E48-F48 -> 171.8
A49: 42954 | B49: 13239 | C49: JULIO | D49: ALQUILER | F49: 150 | G49: =+G48+E49-F49 -> 21.8
A50: 42971 | B50: 13307 | C50: JULIO | D50: LUZ | F50: 19.8 | G50: =+G49+E50-F50 -> 2
A51: 42971 | B51: 13307 | C51: JULIO | D51: AGUA | F51: 2 | G51: =+G50+E51-F51 -> 1.0658141e-14
A52: 42978 | B52: POR COBRAR | C52: AGOSTO | D52: LUZ | E52: 19.8 | G52: =+G51+E52-F52 -> 19.8
D53: AGUA | E53: 2 | G53: =+G52+E53-F53 -> 21.8
D54: ALQUILER | E54: 450 | G54: =+G53+E54-F54 -> 471.8
A55: 42980 | B55: 13375 | C55: AGOSTO | D55: ALQUILER | F55: 450 | G55: =+G54+E55-F55 -> 21.8
A56: 43010 | B56: 13573 | C56: AGOSTO | D56: LUZ | F56: 19.8 | G56: =+G55+E56-F56 -> 2
A57: 43010 | B57: 13573 | C57: AGOSTO | D57: AGUA | F57: 2 | G57: =+G56+E57-F57 -> 1.0658141e-14
A58: 43008 | B58: POR COBRAR | C58: SEPTIEMBRE | D58: LUZ | E58: 15.5 | G58: =+G57+E58-F58 -> 15.5
D59: AGUA | E59: 2 | G59: =+G58+E59-F59 -> 17.5
D60: ALQUILER | E60: 450 | G60: =+G59+E60-F60 -> 467.5
A61: 42993 | B61: 13471 | C61: SEPTIEMBRE | D61: ALQUILER | F61: 450 | G61: =+G60+E61-F61 -> 17.5
A62: 43043 | B62: 13756 | C62: SEPTIEMBRE | D62: LUZ | F62: 15.5 | G62: =+G61+E62-F62 -> 2
A63: 43043 | B63: 13756 | C63: SEPTIEMBRE | D63: AGUA | F63: 2 | G63: =+G62+E63-F63 -> 0
A64: 43039 | B64: POR COBRAR | C64: OCTUBRE | D64: LUZ | E64: 15.4 | G64: =+G63+E64-F64 -> 15.4
D65: AGUA | E65: 2 | G65: =+G64+E65-F65 -> 17.4
D66: ALQUILER | E66: 450 | G66: =+G65+E66-F66 -> 467.4
A67: 43010 | B67: 13573 | C67: OCTUBRE | D67: ALQUILER | F67: 450 | G67: =+G66+E67-F67 -> 17.4
A68: 43063 | B68: 13829 | C68: OCTUBRE | D68: LUZ | F68: 15.4 | G68: =+G67+E68-F68 -> 2
A69: 43063 | B69: 13829 | C69: OCTUBRE | D69: AGUA | F69: 2 | G69: =+G68+E69-F69 -> -2.3092639e-14
A70: 43069 | B70: POR COBRAR | C70: NOVIEMBRE | D70: LUZ | E70: 16.4 | G70: =+G69+E70-F70 -> 16.4
D71: AGUA | E71: 2 | G71: =+G70+E71-F71 -> 18.4
D72: ALQUILER | E72: 450 | G72: =+G71+E72-F72 -> 468.4
A73: 43043 | B73: 13756 | C73: NOVIEMBRE | D73: ALQUILER | F73: 450 | G73: =+G72+E73-F73 -> 18.4
A74: 43453 | B74: 13958 | C74: NOVIEMBRE | D74: LUZ | F74: 16.4 | G74: =+G73+E74-F74 -> 2
A75: 43453 | B75: 13958 | C75: NOVIEMBRE | D75: AGUA | F75: 2 | G75: =+G74+E75-F75 -> -2.1316282e-14
A76: 43100 | B76: POR COBRAR | C76: DICIEMBRE | D76: LUZ | E76: 17.9 | G76: =+G75+E76-F76 -> 17.9
D77: AGUA | E77: 2 | G77: =+G76+E77-F77 -> 19.9
D78: ALQUILER | E78: 450 | G78: =+G77+E78-F78 -> 469.9
A79: 43074 | B79: 13906 | C79: DICIEMBRE | D79: ALQUILER | F79: 450 | G79: =+G78+E79-F79 -> 19.9
A80: 43118 | B80: 14083 | C80: DICIEMBRE | D80: LUZ | F80: 17.9 | G80: =+G79+E80-F80 -> 2
A81: 43118 | B81: 14083 | C81: DICIEMBRE | D81: AGUA | F81: 2 | G81: =+G80+E81-F81 -> -2.1316282e-14
A82: 43131 | B82: POR COBRAR | C82: ENERO | D82: LUZ | E82: 15.9 | G82: =+G81+E82-F82 -> 15.9
D83: AGUA | E83: 2 | G83: =+G82+E83-F83 -> 17.9
D84: ALQUILER | E84: 450 | G84: =+G83+E84-F84 -> 467.9
A85: 43102 | B85: 14033 | C85: ENERO | D85: ALQUILER | F85: 450 | G85: =+G84+E85-F85 -> 17.9
A86: 43157 | B86: 14249 | C86: ENERO | D86: LUZ | F86: 15.9 | G86: =+G85+E86-F86 -> 2
A87: 43157 | B87: 14249 | C87: ENERO | D87: AGUA | F87: 2 | G87: =+G86+E87-F87 -> -2.3092639e-14
A88: 43159 | B88: POR COBRAR | C88: FEBRERO | D88: LUZ | E88: 19.7 | G88: =+G87+E88-F88 -> 19.7
D89: AGUA | E89: 2 | G89: =+G88+E89-F89 -> 21.7
D90: ALQUILER | E90: 450 | G90: =+G89+E90-F90 -> 471.7
A91: 43181 | B91: 14381 | C91: FEBRERO | D91: LUZ | F91: 19.7 | G91: =+G90+E91-F91 -> 452
A92: 43181 | B92: 14381 | C92: FEBRERO | D92: AGUA | F92: 2 | G92: =+G91+E92-F92 -> 450
A93: 43133 | B93: 14178 | C93: FEBRERO | D93: ALQUILER | F93: 450 | G93: =+G92+E93-F93 -> 0
A94: 43190 | B94: POR COBRAR | C94: MARZO | D94: LUZ | E94: 19 | G94: =+G93+E94-F94 -> 19
D95: AGUA | E95: 2 | G95: =+G94+E95-F95 -> 21
D96: ALQUILER | E96: 450 | G96: =+G95+E96-F96 -> 471
A97: 43161 | B97: 14323 | C97: MARZO | D97: ALQUILER | F97: 450 | G97: =+G96+E97-F97 -> 21
A98: 43208 | B98: 14496 | C98: MARZO | D98: LUZ | F98: 19 | G98: =+G97+E98-F98 -> 2
A99: 43208 | B99: 14496 | C99: MARZO | D99: AGUA | F99: 2 | G99: =+G98+E99-F99 -> 0
A100: 43220 | B100: POR COBRAR | C100: ABRIL | D100: LUZ | E100: 19.6 | G100: =+G99+E100-F100 -> 19.6
D101: AGUA | E101: 2 | G101: =+G100+E101-F101 -> 21.6
D102: ALQUILER | E102: 450 | G102: =+G101+E102-F102 -> 471.6
A103: 43242 | B103: 14633 | C103: ABRIL | D103: LUZ | F103: 19.6 | G103: =+G102+E103-F103 -> 452
...

Sheet BURGA ELMER
A2: BURGA CARRASCO ELMER
A5: FECHA | B5: DOCUMENTO | C5: PERIODO | D5: CONCEPTO | E5: POR COBRAR | F5: PAGADO | G5: SALDO POR COBRAR
G6: 0
A7: 43697 | B7: POR COBRAR | C7: AGOSTO | D7: LUZ | G7: =+G6+E7-F7 -> 0
D8: AGUA | G8: =+G7+E8-F8 -> 0
D9: GARANTIA | E9: 210 | G9: =+G8+E9-F9 -> 210 | I9: TRASPASO AL SR. BURGA CARRASCO ELMER
D10: ALQUILER | E10: 84 | G10: =+G9+E10-F10 -> 294
A11: 43691 | B11: B001-0000537 | C11: AGOSTO | D11: GARANTIA | F11: 210 | G11: =+G10+E11-F11 -> 84
A12: 43999 | B12: B001-0001410 | C12: AGOSTO | D12: ALQUILER | F12: 84 | G12: =+G11+E12-F12 -> 0
A13: 43738 | B13: POR COBRAR | C13: SETIEMBRE | D13: LUZ | E13: 7.7 | G13: =+G12+E13-F13 -> 7.7
D14: AGUA | E14: 6.6 | G14: =+G13+E14-F14 -> 14.3
D15: ALQUILER | E15: 210 | G15: =+G14+E15-F15 -> 224.3
A16: 43738 | B16: B001-0000696 | C16: SETIEMBRE | D16: ALQUILER | F16: 199 | G16: =+G15+E16-F16 -> 25.3
A17: 43894 | B17: B001-0001247 | C17: SETIEMBRE | D17: LUZ | F17: 7.7 | G17: =+G16+E17-F17 -> 17.6
A18: 43894 | B18: B001-0001247 | C18: SETIEMBRE | D18: AGUA | F18: 6.6 | G18: =+G17+E18-F18 -> 11
A19: 43999 | B19: B001-0001410 | C19: SETIEMBRE | D19: ALQUILER | F19: 11 | G19: =+G18+E19-F19 -> 0
A20: 43769 | B20: POR COBRAR | C20: OCTUBRE | D20: LUZ | E20: 7.8 | G20: =+G19+E20-F20 -> 7.8
D21: AGUA | E21: 6.3 | G21: =+G20+E21-F21 -> 14.1
D22: ALQUILER | E22: 210 | G22: =+G21+E22-F22 -> 224.1
A23: 43769 | B23: B001-0000780 | C23: OCTUBRE | D23: ALQUILER | F23: 210 | G23: =+G22+E23-F23 -> 14.1
A24: 43894 | B24: B001-0001247 | C24: OCTUBRE | D24: LUZ | F24: 7.8 | G24: =+G23+E24-F24 -> 6.3
A25: 43894 | B25: B001-0001247 | C25: OCTUBRE | D25: AGUA | F25: 6.3 | G25: =+G24+E25-F25 -> 0
A26: 43799 | B26: POR COBRAR | C26: NOVIEMBRE | D26: LUZ | E26: 8.7 | G26: =+G25+E26-F26 -> 8.7
D27: AGUA | E27: 6.6 | G27: =+G26+E27-F27 -> 15.3
D28: ALQUILER | E28: 210 | G28: =+G27+E28-F28 -> 225.3
A29: 43799 | B29: B001-0000898 | C29: NOVIEMBRE | D29: ALQUILER | F29: 171 | G29: =+G28+E29-F29 -> 54.3
A30: 43999 | B30: B001-0001410 | C30: NOVIEMBRE | D30: ALQUILER | F30: 39 | G30: =+G29+E30-F30 -> 15.3
A31: 43894 | B31: B001-0001247 | C31: NOVIEMBRE | D31: LUZ | F31: 8.7 | G31: =+G30+E31-F31 -> 6.6
A32: 43894 | B32: B001-0001247 | C32: NOVIEMBRE | D32: AGUA | F32: 6.6 | G32: =+G31+E32-F32 -> 1.2434498e-14
A33: 43830 | B33: POR COBRAR | C33: DICIEMBRE | D33: LUZ | E33: 9.1 | G33: =+G32+E33-F33 -> 9.1
D34: AGUA | E34: 6.6 | G34: =+G33+E34-F34 -> 15.7
D35: ALQUILER | E35: 210 | G35: =+G34+E35-F35 -> 225.7
A36: 43830 | B36: B001-0001012 | C36: DICIEMBRE | D36: ALQUILER | F36: 210 | G36: =+G35+E36-F36 -> 15.7
A37: 43894 | B37: B001-0001247 | C37: DICIEMBRE | D37: LUZ | F37: 9.1 | G37: =+G36+E37-F37 -> 6.6
A38: 43894 | B38: B001-0001247 | C38: DICIEMBRE | D38: AGUA | F38: 6.6 | G38: =+G37+E38-F38 -> 1.7763568e-14
A39: 43861 | B39: POR COBRAR | C39: ENERO | D39: LUZ | E39: 11.6 | G39: =+G38+E39-F39 -> 11.6
D40: AGUA | E40: 6.3 | G40: =+G39+E40-F40 -> 17.9
D41: ALQUILER | E41: 210 | G41: =+G40+E41-F41 -> 227.9
A42: 43861 | B42: B001-0001132 | C42: ENERO | D42: ALQUILER | F42: 210 | G42: =+G41+E42-F42 -> 17.9
A43: 43999 | B43: B001-0001410 | C43: ENERO | D43: LUZ | F43: 11.6 | G43: =+G42+E43-F43 -> 6.3
A44: 43999 | B44: B001-0001410 | C44: ENERO | D44: AGUA | F44: 6.3 | G44: =+G43+E44-F44 -> 0
A45: 43890 | B45: POR COBRAR | C45: FEBRERO | D45: LUZ | E45: 12 | G45: =+G44+E45-F45 -> 12
D46: AGUA | E46: 6.7 | G46: =+G45+E46-F46 -> 18.7
D47: ALQUILER | E47: 210 | G47: =+G46+E47-F47 -> 228.7
A48: 43890 | B48: B001-0001233 | C48: FEBRERO | D48: ALQUILER | F48: 180 | G48: =+G47+E48-F48 -> 48.7
A49: 43999 | B49: B001-0001410 | C49: FEBRERO | D49: ALQUILER | F49: 30 | G49: =+G48+E49-F49 -> 18.7
A50: 43999 | B50: B001-0001410 | C50: FEBRERO | D50: LUZ | F50: 12 | G50: =+G49+E50-F50 -> 6.7
A51: 43999 | B51: B001-0001410 | C51: FEBRERO | D51: AGUA | F51: 6.7 | G51: =+G50+E51-F51 -> -1.1546319e-14
A52: 43921 | B52: POR COBRAR | C52: MARZO | D52: LUZ | E52: 12.6 | G52: =+G51+E52-F52 -> 12.6
D53: AGUA | E53: 6.7 | G53: =+G52+E53-F53 -> 19.3
D54: ALQUILER | E54: 210 | G54: =+G53+E54-F54 -> 229.3
A55: 43969 | B55: B001-0001307 | C55: MARZO | D55: ALQUILER | F55: 93 | G55: =+G54+E55-F55 -> 136.3
A56: 43999 | B56: B001-0001410 | C56: MARZO | D56: ALQUILER | F56: 117 | G56: =+G55+E56-F56 -> 19.3
A57: 44154 | B57: RII 000126 | C57: MARZO | D57: LUZ | F57: 12.6 | G57: =+G56+E57-F57 -> 6.7
A58: 44154 | B58: RII 000126 | C58: MARZO | D58: AGUA | F58: 6.7 | G58: =+G57+E58-F58 -> -1.687539e-14
A59: 43951 | B59: POR COBRAR | C59: ABRIL | D59: LUZ | E59: 13.1 | G59: =+G58+E59-F59 -> 13.1
D60: AGUA | E60: 10.8 | G60: =+G59+E60-F60 -> 23.9
D61: ALQUILER | E61: 210 | G61: =+G60+E61-F61 -> 233.9
A62: 43969 | B62: B001-0001307 | C62: ABRIL | D62: ALQUILER | F62: 175 | G62: =+G61+E62-F62 -> 58.9
A63: 43999 | B63: B001-0001410 | C63: ABRIL | D63: ALQUILER | F63: 35 | G63: =+G62+E63-F63 -> 23.9
A64: 44154 | B64: RII 000126 | C64: ABRIL | D64: LUZ | F64: 13.1 | G64: =+G63+E64-F64 -> 10.8
A65: 44154 | B65: RII 000126 | C65: ABRIL | D65: AGUA | F65: 10.8 | G65: =+G64+E65-F65 -> -2.3092639e-14
A66: 43982 | B66: POR COBRAR | C66: MAYO | D66: LUZ | E66: 12.1 | G66: =+G65+E66-F66 -> 12.1
D67: AGUA | E67: 5.8 | G67: =+G66+E67-F67 -> 17.9
D68: ALQUILER | E68: 210 | G68: =+G67+E68-F68 -> 227.9
A69: 43981 | B69: B001-0001361 | C69: MAYO | D69: ALQUILER | F69: 170 | G69: =+G68+E69-F69 -> 57.9
A70: 43999 | B70: B001-0001410 | C70: MAYO | D70: ALQUILER | F70: 40 | G70: =+G69+E70-F70 -> 17.9
A71: 44154 | B71: RII 000126 | C71: MAYO | D71: LUZ | F71: 12.1 | G71: =+G70+E71-F71 -> 5.8
A72: 44154 | B72: RII 000126 | C72: MAYO | D72: AGUA | F72: 5.8 | G72: =+G71+E72-F72 -> -2.220446e-14
A73: 44012 | B73: POR COBRAR | C73: JUNIO | D73: LUZ | E73: 10.7 | G73: =+G72+E73-F73 -> 10.7
D74: AGUA | E74: 2.8 | G74: =+G73+E74-F74 -> 13.5
D75: ALQUILER | E75: 210 | G75: =+G74+E75-F75 -> 223.5
A76: 44104 | B76: B001-0001590 | C76: JUNIO | D76: ALQUILER | F76: 210 | G76: =+G75+E76-F76 -> 13.5
A77: 44154 | B77: RII 000126 | C77: JUNIO | D77: LUZ | F77: 10.7 | G77: =+G76+E77-F77 -> 2.8
A78: 44154 | B78: RII 000126 | C78: JUNIO | D78: AGUA | F78: 2.8 | G78: =+G77+E78-F78 -> -2.7533531e-14
A79: 44043 | B79: POR COBRAR | C79: JULIO | D79: LUZ | E79: 12.8 | G79: =+G78+E79-F79 -> 12.8
D80: AGUA | E80: 9 | G80: =+G79+E80-F80 -> 21.8
D81: ALQUILER | E81: 210 | G81: =+G80+E81-F81 -> 231.8
A82: 44043 | B82: B001-0001489 | C82: JULIO | D82: ALQUILER | F82: 205 | G82: =+G81+E82-F82 -> 26.8
A83: 44154 | B83: RII 000127 | C83: JULIO | D83: LUZ | F83: 12.8 | G83: =+G82+E83-F83 -> 14
A84: 44154 | B84: RII 000127 | C84: JULIO | D84: AGUA | F84: 9 | G84: =+G83+E84-F84 -> 5
A85: 44179 | B85: B001-0001724 | C85: JULIO | D85: ALQUILER | F85: 5 | G85: =+G84+E85-F85 -> -1.7763568e-14
A86: 44074 | B86: POR COBRAR | C86: AGOSTO | D86: LUZ | E86: 13.8 | G86: =+G85+E86-F86 -> 13.8
D87: AGUA | E87: 6.2 | G87: =+G86+E87-F87 -> 20
D88: ALQUILER | E88: 210 | G88: =+G87+E88-F88 -> 230
D89: FISCALIZACION | E89: 15 | G89: =+G88+E89-F89 -> 245
A90: 44074 | B90: B001-1538 | C90: AGOSTO | D90: ALQUILER | F90: 87 | G90: =+G89+E90-F90 -> 158
A91: 44154 | B91: RII 000127 | C91: AGOSTO | D91: LUZ | F91: 13.8 | G91: =+G90+E91-F91 -> 144.2
A92: 44154 | B92: RII 000127 | C92: AGOSTO | D92: AGUA | F92: 6.2 | G92: =+G91+E92-F92 -> 138
A93: 44048 | C93: AGOSTO | D93: FISCALIZACION | F93: 3.5 | G93: =+G92+E93-F93 -> 134.5
A94: 44179 | B94: B001-0001724 | C94: AGOSTO | D94: ALQUILER | F94: 85 | G94: =+G93+E94-F94 -> 49.5
A95: 44216 | B95: RII 000271 | C95: AGOSTO | D95: FISCALIZACION | F95: 11.5 | G95: =+G94+E95-F95 -> 38
A96: 44216 | B96: B001-0001825 | C96: AGOSTO | D96: ALQUILER | F96: 38 | G96: =+G95+E96-F96 -> 0
A97: 44104 | B97: POR COBRAR | C97: SETIEMBRE | D97: LUZ | E97: 14.2 | G97: =+G96+E97-F97 -> 14.2
D98: AGUA | E98: 7.2 | G98: =+G97+E98-F98 -> 21.4
D99: ALQUILER | E99: 210 | G99: =+G98+E99-F99 -> 231.4
D100: FISCALIZACION | E100: 8.5 | G100: =+G99+E100-F100 -> 239.9
A101: 44079 | C101: SETIEMBRE | D101: FISCALIZACION | F101: 1.5 | G101: =+G100+E101-F101 -> 238.4
A102: 44216 | B102: RII 000271 | C102: SETIEMBRE | D102: LUZ | F102: 14.2 | G102: =+G101+E102-F102 -> 224.2
A103: 44216 | B103: RII 000271 | C103: SETIEMBRE | D103: AGUA | F103: 7.2 | G103: =+G102+E103-F103 -> 217
...

Sheet BUSTAMANTE GRACIELA
B3: BUSTAMANTE CHILON GRACIELA
A5: FECHA | B5: DOCUMENTO | C5: PERIODO | D5: CONCEPTO | E5: POR COBRAR | F5: PAGADO | G5: SALDO POR COBRAR
A6: 42736 | B6: SALDO AL 2016 | G6: 116.6
A7: 42802 | B7: 12360 | C7: ACUENTA DEL 2016 | F7: 30 | G7: =+G6+E7-F7 -> 86.6
A8: 42773 | B8: 12224 | C8: ACUENTA DEL 2016 | F8: 30 | G8: =+G7+E8-F8 -> 56.6
A9: 42753 | B9: 12111 | C9: ACUENTA DEL 2016 | F9: 56.6 | G9: =+G8+E9-F9 -> 0
A10: 42766 | B10: POR COBRAR | C10: ENERO | D10: LUZ | E10: 13.5 | G10: =+G9+E10-F10 -> 13.5
D11: AGUA | E11: 21 | G11: =+G10+E11-F11 -> 34.5
D12: ALQUILER | E12: 300 | G12: =+G11+E12-F12 -> 334.5
A13: 42802 | B13: 12360 | C13: ENERO | D13: LUZ | F13: 13.5 | G13: =+G12+E13-F13 -> 321
A14: 42802 | B14: 12360 | C14: ENERO | D14: AGUA | F14: 21 | G14: =+G13+E14-F14 -> 300
A15: 42802 | B15: 12360 | C15: ENERO | D15: ALQUILER | F15: 300 | G15: =+G14+E15-F15 -> 0
A16: 42794 | B16: POR COBRAR | C16: FEBRERO | D16: LUZ | E16: 13 | G16: =+G15+E16-F16 -> 13
D17: AGUA | E17: 15 | G17: =+G16+E17-F17 -> 28
D18: ALQUILER | E18: 300 | G18: =+G17+E18-F18 -> 328
A19: 42802 | B19: 12361 | C19: FEBRERO | D19: ALQUILER | F19: 150 | G19: =+G18+E19-F19 -> 178
A20: 42808 | B20: 12397 | C20: FEBRERO | F20: 150 | G20: =+G19+E20-F20 -> 28
A21: 42845 | B21: 12563 | C21: FEBRERO | D21: LUZ | F21: 13 | G21: =+G20+E21-F21 -> 15
A22: 42845 | B22: 12563 | C22: FEBRERO | D22: AGUA | F22: 15 | G22: =+G21+E22-F22 -> 0
A23: 42825 | B23: POR COBRAR | C23: MARZO | D23: LUZ | E23: 13 | G23: =+G22+E23-F23 -> 13
D24: AGUA | E24: 15 | G24: =+G23+E24-F24 -> 28
D25: ALQUILER | E25: 300 | G25: =+G24+E25-F25 -> 328
A26: 42845 | B26: 12563 | C26: MARZO | D26: ALQUILER | F26: 300 | G26: =+G25+E26-F26 -> 28
A27: 42920 | B27: 12950 | C27: MARZO | D27: LUZ | F27: 13 | G27: =+G26+E27-F27 -> 15
A28: 42920 | B28: 12950 | C28: MARZO | D28: AGUA | F28: 15 | G28: =+G27+E28-F28 -> 0
A29: 42855 | B29: POR COBRAR | C29: ABRIL | D29: LUZ | E29: 13 | G29: =+G28+E29-F29 -> 13
D30: AGUA | E30: 15 | G30: =+G29+E30-F30 -> 28
D31: ALQUILER | E31: 300 | G31: =+G30+E31-F31 -> 328
A32: 42867 | B32: 12676 | C32: ABRIL | D32: ALQUILER | F32: 300 | G32: =+G31+E32-F32 -> 28
A33: 42920 | B33: 12950 | C33: ABRIL | D33: LUZ | F33: 13 | G33: =+G32+E33-F33 -> 15
A34: 42920 | B34: 12950 | C34: ABRIL | D34: AGUA | F34: 15 | G34: =+G33+E34-F34 -> 0
A35: 42886 | B35: POR COBRAR | C35: MAYO | D35: LUZ | E35: 13 | G35: =+G34+E35-F35 -> 13
D36: AGUA | E36: 14.7 | G36: =+G35+E36-F36 -> 27.7
D37: ALQUILER | E37: 300 | G37: =+G36+E37-F37 -> 327.7
A38: 42920 | B38: 12949 | C38: MAYO | D38: ALQUILER | F38: 300 | G38: =+G37+E38-F38 -> 27.7
A39: 43122 | B39: 14117 | C39: MAYO | D39: LUZ | F39: 13 | G39: =+G38+E39-F39 -> 14.7
A40: 43122 | B40: 14117 | C40: MAYO | D40: AGUA | F40: 14.7 | G40: =+G39+E40-F40 -> 0
A41: 42916 | B41: POR COBRAR | C41: JUNIO | D41: LUZ | E41: 12.5 | G41: =+G40+E41-F41 -> 12.5
D42: AGUA | E42: 14.7 | G42: =+G41+E42-F42 -> 27.2
D43: ALQUILER | E43: 300 | G43: =+G42+E43-F43 -> 327.2
A44: 43008 | B44: 13569 | C44: JUNIO | D44: ALQUILER | F44: 160 | G44: =+G43+E44-F44 -> 167.2
A45: 43122 | B45: 14117 | C45: JUNIO | D45: LUZ | F45: 12.5 | G45: =+G44+E45-F45 -> 154.7
A46: 43122 | B46: 14117 | C46: JUNIO | D46: AGUA | F46: 14.7 | G46: =+G45+E46-F46 -> 140
A47: 43122 | B47: 14117 | C47: JUNIO | D47: ALQUILER | F47: 140 | G47: =+G46+E47-F47 -> 0
A48: 42947 | B48: POR COBRAR | C48: JULIO | D48: LUZ | E48: 13 | G48: =+G47+E48-F48 -> 13
D49: AGUA | E49: 14.7 | G49: =+G48+E49-F49 -> 27.7
D50: ALQUILER | E50: 300 | G50: =+G49+E50-F50 -> 327.7
A51: 43098 | B51: 13998 | C51: JULIO | D51: ALQUILER | F51: 300 | G51: =+G50+E51-F51 -> 27.7
A52: 43122 | B52: 14117 | C52: JULIO | D52: LUZ | F52: 13 | G52: =+G51+E52-F52 -> 14.7
A53: 43122 | B53: 14117 | C53: JULIO | D53: AGUA | F53: 14.7 | G53: =+G52+E53-F53 -> 0
A54: 42978 | B54: POR COBRAR | C54: AGOSTO | D54: LUZ | E54: 13 | G54: =+G53+E54-F54 -> 13
D55: AGUA | E55: 14.7 | G55: =+G54+E55-F55 -> 27.7
D56: ALQUILER | E56: 300 | G56: =+G55+E56-F56 -> 327.7
A57: 43122 | B57: 14118 | C57: AGOSTO | D57: LUZ | F57: 13 | G57: =+G56+E57-F57 -> 314.7
A58: 43122 | B58: 14118 | C58: AGOSTO | D58: AGUA | F58: 14.7 | G58: =+G57+E58-F58 -> 300
A59: 43122 | B59: 14118 | C59: AGOSTO | D59: ALQUILER | F59: 300 | G59: =+G58+E59-F59 -> 0
A60: 43008 | B60: POR COBRAR | C60: SEPTIEMBRE | D60: LUZ | E60: 8 | G60: =+G59+E60-F60 -> 8
D61: AGUA | E61: 14.7 | G61: =+G60+E61-F61 -> 22.7
D62: ALQUILER | E62: 300 | G62: =+G61+E62-F62 -> 322.7
A63: 43122 | B63: 14118 | C63: SEPTIEMBRE | D63: ALQUILER | F63: 149.7 | G63: =+G62+E63-F63 -> 173
A64: 43123 | B64: 14129 | C64: SEPTIEMBRE | D64: LUZ | F64: 8 | G64: =+G63+E64-F64 -> 165
A65: 43123 | B65: 14129 | C65: SEPTIEMBRE | D65: AGUA | F65: 14.7 | G65: =+G64+E65-F65 -> 150.3
A66: 43124 | B66: 14138 | C66: SEPTIEMBRE | D66: ALQUILER | F66: 30 | G66: =+G65+E66-F66 -> 120.3
A67: 43129 | B67: 14151 | C67: SEPTIEMBRE | D67: ALQUILER | F67: 90 | G67: =+G66+E67-F67 -> 30.3
A68: 43132 | B68: 14175 | C68: SEPTIEMBRE | D68: ALQUILER | F68: 30.3 | G68: =+G67+E68-F68 -> 0
A69: 43039 | B69: POR COBRAR | C69: OCTUBRE | D69: LUZ | E69: 8 | G69: =+G68+E69-F69 -> 8
D70: AGUA | E70: 14.7 | G70: =+G69+E70-F70 -> 22.7
D71: ALQUILER | E71: 300 | G71: =+G70+E71-F71 -> 322.7
A72: 43039 | B72: 13741 | C72: OCTUBRE | D72: ALQUILER | F72: 180 | G72: =+G71+E72-F72 -> 142.7
A73: 43123 | B73: 14129 | C73: OCTUBRE | D73: LUZ | F73: 7.3 | G73: =+G72+E73-F73 -> 135.4
A74: 43132 | B74: 14175 | C74: OCTUBRE | D74: ALQUILER | F74: 29.7 | G74: =+G73+E74-F74 -> 105.7
A75: 43145 | B75: 14217 | C75: OCTUBRE | D75: LUZ | F75: 0.7 | G75: =+G74+E75-F75 -> 105
A76: 43145 | B76: 14217 | C76: OCTUBRE | D76: AGUA | F76: 14.7 | G76: =+G75+E76-F76 -> 90.3
A77: 43145 | B77: 14217 | C77: OCTUBRE | D77: ALQUILER | F77: 90.3 | G77: =+G76+E77-F77 -> 0
A78: 43069 | B78: POR COBRAR | C78: NOVIEMBRE | D78: LUZ | E78: 8.2 | G78: =+G77+E78-F78 -> 8.2
D79: AGUA | E79: 14.7 | G79: =+G78+E79-F79 -> 22.9
D80: ALQUILER | E80: 300 | G80: =+G79+E80-F80 -> 322.9
A81: 43145 | B81: 14217 | C81: NOVIEMBRE | D81: ALQUILER | F81: 44.3 | G81: =+G80+E81-F81 -> 278.6
A82: 43147 | B82: 14224 | C82: NOVIEMBRE | D82: ALQUILER | F82: 60 | G82: =+G81+E82-F82 -> 218.6
A83: 43151 | B83: 14236 | C83: NOVIEMBRE | D83: ALQUILER | F83: 60 | G83: =+G82+E83-F83 -> 158.6
A84: 43154 | B84: 14244 | C84: NOVIEMBRE | D84: ALQUILER | F84: 90 | G84: =+G83+E84-F84 -> 68.6
A85: 43159 | B85: 14270 | C85: NOVIEMBRE | D85: ALQUILER | F85: 45.7 | G85: =+G84+E85-F85 -> 22.9
A86: 43159 | B86: 14270 | C86: NOVIEMBRE | D86: LUZ | F86: 8.2 | G86: =+G85+E86-F86 -> 14.7
A87: 43159 | B87: 14270 | C87: NOVIEMBRE | D87: AGUA | F87: 6.1 | G87: =+G86+E87-F87 -> 8.6
A88: 43167 | B88: 14344 | C88: NOVIEMBRE | D88: AGUA | F88: 8.6 | G88: =+G87+E88-F88 -> -3.5527137e-14
A89: 43100 | B89: POR COBRAR | C89: DICIEMBRE | D89: LUZ | E89: 8.9 | G89: =+G88+E89-F89 -> 8.9
D90: AGUA | E90: 14.7 | G90: =+G89+E90-F90 -> 23.6
D91: ALQUILER | E91: 300 | G91: =+G90+E91-F91 -> 323.6
A92: 43118 | B92: 14097 | C92: DICIEMBRE | D92: LUZ | F92: 8.9 | G92: =+G91+E92-F92 -> 314.7
A93: 43118 | B93: 14097 | C93: DICIEMBRE | D93: AGUA | F93: 14.7 | G93: =+G92+E93-F93 -> 300
A94: 43167 | B94: 14344 | C94: DICIEMBRE | D94: ALQUILER | F94: 200 | G94: =+G93+E94-F94 -> 100
A95: 43173 | B95: 14360 | C95: DICIEMBRE | D95: LUZ | F95: 100 | G95: =+G94+E95-F95 -> 0
A96: 43131 | B96: POR COBRAR | C96: ENERO | D96: LUZ | E96: 8 | G96: =+G95+E96-F96 -> 8
D97: AGUA | E97: 14.7 | G97: =+G96+E97-F97 -> 22.7
D98: ALQUILER | E98: 300 | G98: =+G97+E98-F98 -> 322.7
A99: 43193 | B99: 14434 | C99: ENERO | D99: ALQUILER | F99: 150 | G99: =+G98+E99-F99 -> 172.7
A100: 43241 | B100: 14627 | C100: ENERO | D100: ALQUILER | F100: 150 | G100: =+G99+E100-F100 -> 22.7
A101: 43241 | B101: 14627 | C101: ENERO | D101: LUZ | F101: 8 | G101: =+G100+E101-F101 -> 14.7
A102: 43241 | B102: 14627 | C102: ENERO | D102: AGUA | F102: 14.7 | G102: =+G101+E102-F102 -> 0
A103: 43159 | B103: POR COBRAR | C103: FEBRERO | D103: LUZ | E103: 9.9 | G103: =+G102+E103-F103 -> 9.9
...

Sheet CAHUANA ALEX
B3: CAHUANA PUCURIMAY ALEX
A5: FECHA | B5: DOCUMENTO | C5: PERIODO | D5: CONCEPTO | E5: POR COBRAR | F5: PAGADO | G5: SALDO POR COBRAR
G6: 0
A7: 44469 | B7: POR COBRAR | C7: SEPTIEMBRE | D7: LUZ | E7: 10.5 | G7: =+G6+E7-F7 -> 10.5
D8: AGUA | E8: 8.1 | G8: =+G7+E8-F8 -> 18.6
D9: GARANTIA | E9: 300 | G9: =+G8+E9-F9 -> 318.6
D10: ALQUILER | E10: 300 | G10: =+G9+E10-F10 -> 618.6
A11: 44445 | B11: EB01-12 | C11: SEPTIEMBRE | D11: GARANTIA | F11: 300 | G11: =+G10+E11-F11 -> 318.6
A12: 44445 | B12: EB01-12 | C12: SEPTIEMBRE | D12: ALQUILER | F12: 300 | G12: =+G11+E12-F12 -> 18.6
A13: 44523 | B13: RII 764 | C13: SEPTIEMBRE | D13: LUZ | F13: 10.5 | G13: =+G12+E13-F13 -> 8.1
A14: 44523 | B14: RII 764 | C14: SEPTIEMBRE | D14: AGUA | F14: 8.1 | G14: =+G13+E14-F14 -> 2.3092639e-14
A15: 44500 | B15: POR COBRAR | C15: OCTUBRE | D15: LUZ | E15: 10.9 | G15: =+G14+E15-F15 -> 10.9
D16: AGUA | E16: 19.1 | G16: =+G15+E16-F16 -> 30
D17: ALQUILER | E17: 300 | G17: =+G16+E17-F17 -> 330
A18: 44523 | B18: EB01-157 | C18: OCTUBRE | D18: ALQUILER | F18: 300 | G18: =+G17+E18-F18 -> 30
A19: 44557 | B19: RII 000874 | C19: OCTUBRE | D19: LUZ | F19: 10.9 | G19: =+G18+E19-F19 -> 19.1
A20: 44557 | B20: RII 000874 | C20: OCTUBRE | D20: AGUA | F20: 19.1 | G20: =+G19+E20-F20 -> 0
A21: 44530 | B21: POR COBRAR | C21: NOVIEMBRE | D21: LUZ | E21: 11.6 | G21: =+G20+E21-F21 -> 11.6
D22: AGUA | E22: 47.1 | G22: =+G21+E22-F22 -> 58.7 | J22: 10.9
D23: ALQUILER | E23: 300 | G23: =+G22+E23-F23 -> 358.7 | J23: 19.1
A24: 44555 | B24: EB01-301 | C24: NOVIEMBRE | D24: ALQUILER | F24: 300 | G24: =+G23+E24-F24 -> 58.7
A25: 44557 | B25: RII 000874 | C25: NOVIEMBRE | D25: LUZ | F25: 11.6 | G25: =+G24+E25-F25 -> 47.1 | J25: 11.6
A26: 44557 | B26: RII 000874 | C26: NOVIEMBRE | D26: AGUA | F26: 47.1 | G26: =+G25+E26-F26 -> 0 | J26: 47.1
A27: 44561 | B27: POR COBRAR | C27: DICIEMBRE | D27: LUZ | E27: 22 | G27: =+G26+E27-F27 -> 22
D28: AGUA | E28: 37.8 | G28: =+G27+E28-F28 -> 59.8
D29: ALQUILER | E29: 300 | G29: =+G28+E29-F29 -> 359.8
A30: 44614 | B30: EB01-502 | C30: DICIEMBRE | D30: ALQUILER | F30: 300 | G30: =+G29+E30-F30 -> 59.8
A31: 44614 | B31: RII 000933 | C31: DICIEMBRE | D31: LUZ | F31: 22 | G31: =+G30+E31-F31 -> 37.8
A32: 44614 | B32: RII 000933 | C32: DICIEMBRE | D32: AGUA | F32: 37.8 | G32: =+G31+E32-F32 -> 0
A33: 44592 | B33: POR COBRAR | C33: ENERO | D33: LUZ | E33: 42.7 | G33: =+G32+E33-F33 -> 42.7
D34: AGUA | E34: 30.4 | G34: =+G33+E34-F34 -> 73.1
D35: ALQUILER | E35: 300 | G35: =+G34+E35-F35 -> 373.1
A36: 44614 | B36: EB01-502 | C36: ENERO | D36: ALQUILER | F36: 300 | G36: =+G35+E36-F36 -> 73.1
A37: 44662 | B37: RII 000999 | C37: ENERO | D37: LUZ | F37: 42.7 | G37: =+G36+E37-F37 -> 30.4
A38: 44662 | B38: RII 000999 | C38: ENERO | D38: AGUA | F38: 30.4 | G38: =+G37+E38-F38 -> 0
A39: 44620 | B39: POR COBRAR | C39: FEBRERO | D39: LUZ | E39: 42 | G39: =+G38+E39-F39 -> 42
D40: AGUA | E40: 24.9 | G40: =+G39+E40-F40 -> 66.9
D41: ALQUILER | E41: 300 | G41: =+G40+E41-F41 -> 366.9
A42: 44614 | B42: EB01-502 | C42: FEBRERO | D42: ALQUILER | F42: 300 | G42: =+G41+E42-F42 -> 66.9
A43: 44662 | B43: RII 000999 | C43: FEBRERO | D43: LUZ | F43: 42 | G43: =+G42+E43-F43 -> 24.9
A44: 44662 | B44: RII 000999 | C44: FEBRERO | D44: AGUA | F44: 24.9 | G44: =+G43+E44-F44 -> 0
A45: 44651 | B45: POR COBRAR | C45: MARZO | D45: LUZ | E45: 42 | G45: =+G44+E45-F45 -> 42
D46: AGUA | E46: 22.4 | G46: =+G45+E46-F46 -> 64.4
D47: ALQUILER | E47: 300 | G47: =+G46+E47-F47 -> 364.4
A48: 44651 | B48: EB01-655 | C48: MARZO | D48: ALQUILER | F48: 270 | G48: =+G47+E48-F48 -> 94.4
A49: 44662 | B49: EB01-679 | C49: MARZO | D49: ALQUILER | F49: 30 | G49: =+G48+E49-F49 -> 64.4
A50: 44681 | B50: RII 1028 | C50: MARZO | D50: LUZ | F50: 30 | G50: =+G49+E50-F50 -> 34.4
A51: 44706 | B51: RII 1052 | C51: MARZO | D51: LUZ | F51: 12 | G51: =+G50+E51-F51 -> 22.4
A52: 44706 | B52: RII 1052 | C52: MARZO | D52: AGUA | F52: 22.4 | G52: =+G51+E52-F52 -> 0
A53: 44681 | B53: POR COBRAR | C53: ABRIL | D53: ALQUILER | E53: 300 | G53: =+G52+E53-F53 -> 300
A54: 44681 | B54: EB01-778 | C54: ABRIL | D54: ALQUILER | F54: 300 | G54: =+G53+E54-F54 -> 0
D55: LUZ | E55: 42.6 | G55: =+G54+E55-F55 -> 42.6
D56: AGUA | E56: 21.2 | G56: =+G55+E56-F56 -> 63.8
A57: 44706 | B57: RII 1052 | C57: ABRIL | D57: LUZ | F57: 42.6 | G57: =+G56+E57-F57 -> 21.2
A58: 44706 | B58: RII 1052 | C58: ABRIL | D58: AGUA | F58: 21.2 | G58: =+G57+E58-F58 -> 0
A59: 44712 | B59: POR COBRAR | C59: MAYO | D59: LUZ | E59: 40.8 | G59: =+G58+E59-F59 -> 40.8
D60: AGUA | E60: 21.2 | G60: =+G59+E60-F60 -> 62
D61: ALQUILER | E61: 300 | G61: =+G60+E61-F61 -> 362
D62: MULTA FISCALIZACION | E62: 160 | G62: =+G61+E62-F62 -> 522
A63: 44712 | B63: EB01-883 | C63: MAYO | D63: ALQUILER | F63: 300 | G63: =+G62+E63-F63 -> 222
A64: 44712 | B64: RII 1071 | C64: MAYO | D64: LUZ | F64: 12 | G64: =+G63+E64-F64 -> 210
A65: 44712 | B65: RII 1071 | C65: MAYO | D65: AGUA | F65: 3 | G65: =+G64+E65-F65 -> 207
A66: 44742 | B66: RII 1096 | C66: MAYO | D66: MULTA FISCALIZACION | F66: 80 | G66: =+G65+E66-F66 -> 127
A67: 44773 | B67: RII 1137 | C67: MAYO | D67: MULTA FISCALIZACION | F67: 80 | G67: =+G66+E67-F67 -> 47
A68: 44773 | B68: RII 1137 | C68: MAYO | D68: LUZ | F68: 20 | G68: =+G67+E68-F68 -> 27
A69: 44804 | B69: RII 1181 | C69: MAYO | D69: LUZ | F69: 8.8 | G69: =+G68+E69-F69 -> 18.2
A70: 44804 | B70: RII 1181 | C70: MAYO | D70: AGUA | F70: 18.2 | G70: =+G69+E70-F70 -> 0
A71: 44742 | B71: POR COBRAR | C71: JUNIO | D71: LUZ | E71: 39.5 | G71: =+G70+E71-F71 -> 39.5
D72: AGUA | E72: 22.7 | G72: =+G71+E72-F72 -> 62.2
D73: ALQUILER | E73: 300 | G73: =+G72+E73-F73 -> 362.2
A74: 44742 | B74: EB01-977 | C74: JUNIO | D74: ALQUILER | F74: 300 | G74: =+G73+E74-F74 -> 62.2
A75: 44804 | B75: RII 1181 | C75: JUNIO | D75: LUZ | F75: 39.5 | G75: =+G74+E75-F75 -> 22.7
A76: 44804 | B76: RII 1181 | C76: JUNIO | D76: AGUA | F76: 22.7 | G76: =+G75+E76-F76 -> 0
A77: 44773 | B77: POR COBRAR | C77: JULIO | D77: LUZ | E77: 39.3 | G77: =+G76+E77-F77 -> 39.3
D78: AGUA | E78: 18.9 | G78: =+G77+E78-F78 -> 58.2
D79: ALQUILER | E79: 300 | G79: =+G78+E79-F79 -> 358.2
A80: 44773 | B80: EB01-1097 | C80: JULIO | D80: ALQUILER | F80: 300 | G80: =+G79+E80-F80 -> 58.2
A81: 44804 | B81: RII 1181 | C81: JULIO | D81: LUZ | F81: 39.3 | G81: =+G80+E81-F81 -> 18.9
A82: 44804 | B82: RII 1181 | C82: JULIO | D82: AGUA | F82: 18.9 | G82: =+G81+E82-F82 -> 0
A83: 44804 | B83: POR COBRAR | C83: AGOSTO | D83: LUZ | E83: 39.5 | G83: =+G82+E83-F83 -> 39.5
D84: AGUA | E84: 15.3 | G84: =+G83+E84-F84 -> 54.8
D85: ALQUILER | E85: 300 | G85: =+G84+E85-F85 -> 354.8
A86: 44804 | B86: EB01-1214 | C86: AGOSTO | D86: ALQUILER | F86: 300 | G86: =+G85+E86-F86 -> 54.8
A87: 44804 | B87: RII 1181 | C87: AGOSTO | D87: LUZ | F87: 2.6 | G87: =+G86+E87-F87 -> 52.2
A88: 44834 | B88: RII 1228 | C88: AGOSTO | D88: LUZ | F88: 36.9 | G88: =+G87+E88-F88 -> 15.3
A89: 44834 | B89: RII 1228 | C89: AGOSTO | D89: AGUA | F89: 13.1 | G89: =+G88+E89-F89 -> 2.2
A90: 44865 | B90: RII 1259 | C90: AGOSTO | D90: AGUA | F90: 2.2 | G90: =+G89+E90-F90 -> 1.1546319e-14
A91: 44834 | B91: POR COBRAR | C91: SEPTIEMBRE | D91: LUZ | E91: 35.1 | G91: =+G90+E91-F91 -> 35.1
D92: AGUA | E92: 15.5 | G92: =+G91+E92-F92 -> 50.6
D93: ALQUILER | E93: 350 | G93: =+G92+E93-F93 -> 400.6
A94: 44834 | B94: EB01-1318 | C94: SEPTIEMBRE | D94: ALQUILER | F94: 350 | G94: =+G93+E94-F94 -> 50.6
A95: 44865 | B95: RII 1259 | C95: SEPTIEMBRE | D95: LUZ | F95: 35.1 | G95: =+G94+E95-F95 -> 15.5
A96: 44865 | B96: RII 1259 | C96: SEPTIEMBRE | D96: AGUA | F96: 15.5 | G96: =+G95+E96-F96 -> 2.1316282e-14
A97: 44865 | B97: POR COBRAR | C97: OCTUBRE | D97: LUZ | E97: 35 | G97: =+G96+E97-F97 -> 35
D98: AGUA | E98: 21.9 | G98: =+G97+E98-F98 -> 56.9
D99: ALQUILER | E99: 350 | G99: =+G98+E99-F99 -> 406.9
A100: 44865 | B100: EB01-1424 | C100: OCTUBRE | D100: ALQUILER | F100: 350 | G100: =+G99+E100-F100 -> 56.9
A101: 44865 | B101: RII 1259 | C101: OCTUBRE | D101: LUZ | F101: 17.2 | G101: =+G100+E101-F101 -> 39.7
A102: 44895 | B102: RII 1299 | C102: OCTUBRE | D102: LUZ | F102: 17.8 | G102: =+G101+E102-F102 -> 21.9
A103: 44895 | B103: RII 1299 | C103: OCTUBRE | D103: AGUA | F103: 21.9 | G103: =+G102+E103-F103 -> 3.1974423e-14
...

Sheet ATO MARIA
D1: MARIA VALERIA ATO ARREDONDO | I1: DNI 76276709
A3: FECHA | B3: DOCUMENTO | C3: PERIODO | D3: CONCEPTO | E3: POR COBRAR | F3: PAGADO | G3: SALDO POR COBRAR
G4: =+E4-F4 -> 0
A5: 45260 | B5: POR COBRAR | C5: NOVIEMBRE | D5: ALQUILER | E5: 1200 | G5: =G4+E5-F5 -> 1200
D6: GARANTIA | G6: =G5+E6-F6 -> 1200
G7: =G6+E7-F7 -> 1200
A8: 45252 | B8: EB01-2921 | C8: NOVIEMBRE | D8: ALQUILER | F8: 1200 | G8: =G7+E8-F8 -> 0
A9: 45291 | B9: POR COBRAR | C9: DICIEMBRE | D9: LUZ | E9: 30.6 | G9: =G8+E9-F9 -> 30.6
D10: AGUA | E10: 5 | G10: =G9+E10-F10 -> 35.6
D11: ALQUILER | E11: 1200 | G11: =G10+E11-F11 -> 1235.6
A12: 45289 | B12: EB01-3087 | C12: DICIEMBRE | D12: ALQUILER | F12: 1200 | G12: =G11+E12-F12 -> 35.6
A13: 45316 | B13: RII 2003 | C13: DICIEMBRE | D13: LUZ | F13: 30.6 | G13: =G12+E13-F13 -> 5
A14: 45316 | B14: RII 2003 | C14: DICIEMBRE | D14: AGUA | F14: 5 | G14: =G13+E14-F14 -> -9.2370556e-14
A15: 45322 | B15: POR COBRAR | C15: ENERO | D15: LUZ | E15: 34.2 | G15: =G14+E15-F15 -> 34.2
D16: AGUA | E16: 8.8 | G16: =G15+E16-F16 -> 43
D17: ALQUILER | E17: 1200 | G17: =G16+E17-F17 -> 1243
A18: 45328 | B18: EB01-3300 | C18: ENERO | D18: ALQUILER | F18: 1200 | G18: =G17+E18-F18 -> 43
A19: 45358 | B19: RII 2082 | C19: ENERO | D19: LUZ | F19: 34.2 | G19: =G18+E19-F19 -> 8.8
A20: 45358 | B20: RII 2082 | C20: ENERO | D20: AGUA | F20: 8.8 | G20: =G19+E20-F20 -> 0
A21: 45351 | B21: POR COBRAR | C21: FEBRERO | D21: LUZ | E21: 35.5 | G21: =G20+E21-F21 -> 35.5
D22: AGUA | E22: 5 | G22: =G21+E22-F22 -> 40.5
D23: ALQUILER | E23: 1200 | G23: =G22+E23-F23 -> 1240.5
A24: 45354 | B24: EB01-3447 | C24: FEBRERO | D24: ALQUILER | F24: 1200 | G24: =G23+E24-F24 -> 40.5 | H24: =+F24 -> 1200 | I24: LEON DIANA
A25: 45414 | B25: RII 2162 | C25: FEBRERO | D25: LUZ | F25: 35.5 | G25: =G24+E25-F25 -> 5
A26: 45414 | B26: RII 2162 | C26: FEBRERO | D26: AGUA | F26: 5 | G26: =G25+E26-F26 -> 0
A27: 45382 | B27: POR COBRAR | C27: MARZO | D27: LUZ | E27: 34.3 | G27: =G26+E27-F27 -> 34.3
D28: AGUA | E28: 5 | G28: =G27+E28-F28 -> 39.3
D29: ALQUILER | E29: 1200 | G29: =G28+E29-F29 -> 1239.3
A30: 45393 | B30: EB01-3554 | C30: MARZO | D30: ALQUILER | F30: 1200 | G30: =G29+E30-F30 -> 39.3
A31: 45414 | B31: RII 2162 | C31: MARZO | D31: LUZ | F31: 34.3 | G31: =G30+E31-F31 -> 5
A32: 45414 | B32: RII 2162 | C32: MARZO | D32: AGUA | F32: 5 | G32: =G31+E32-F32 -> -4.2632564e-14
A33: 45412 | B33: POR COBRAR | C33: ABRIL | D33: LUZ | E33: 34.1 | G33: =G32+E33-F33 -> 34.1
D34: AGUA | E34: 5 | G34: =G33+E34-F34 -> 39.1
D35: ALQUILER | E35: 1200 | G35: =G34+E35-F35 -> 1239.1
A36: 45430 | B36: EB01-3698 | C36: ABRIL | D36: ALQUILER | F36: 1200 | G36: =G35+E36-F36 -> 39.1
A37: 45526 | B37: RII 2361 | C37: ABRIL | D37: LUZ | F37: 34.1 | G37: =G36+E37-F37 -> 5
A38: 45526 | B38: RII 2361 | C38: ABRIL | D38: AGUA | F38: 5 | G38: =G37+E38-F38 -> -9.2370556e-14
A39: 45443 | B39: POR COBRAR | C39: MAYO | D39: LUZ | E39: 31.1 | G39: =G38+E39-F39 -> 31.1
D40: AGUA | E40: 5 | G40: =G39+E40-F40 -> 36.1
D41: ALQUILER | E41: 1200 | G41: =G40+E41-F41 -> 1236.1
A42: 45465 | B42: EB01-3784 | C42: MAYO | D42: ALQUILER | F42: 1200 | G42: =G41+E42-F42 -> 36.1 | H42: =+F42 -> 1200 | I42: HUAMANI JUAREZ ALFONSO GONZALES
A43: 45526 | B43: RII 2361 | C43: MAYO | D43: LUZ | F43: 31.1 | G43: =G42+E43-F43 -> 5
A44: 45526 | B44: RII 2361 | C44: MAYO | D44: AGUA | F44: 5 | G44: =G43+E44-F44 -> -9.2370556e-14
A45: 45473 | B45: POR COBRAR | C45: JUNIO | D45: LUZ | E45: 30.2 | G45: =G44+E45-F45 -> 30.2
D46: AGUA | E46: 7 | G46: =G45+E46-F46 -> 37.2
D47: ALQUILER | E47: 1200 | G47: =G46+E47-F47 -> 1237.2
A48: 45525 | B48: EB01-4120 | C48: JUNIO | D48: ALQUILER | F48: 1200 | G48: =G47+E48-F48 -> 37.2
A49: 45589 | B49: RII 2478 | C49: JUNIO | D49: LUZ | F49: 30.2 | G49: =G48+E49-F49 -> 7 | J49: 76276709
A50: 45589 | B50: RII 2478 | C50: JUNIO | D50: AGUA | F50: 7 | G50: =G49+E50-F50 -> -1.811884e-13
A51: 45504 | B51: POR COBRAR | C51: JULIO | D51: LUZ | E51: 29.6 | G51: =G50+E51-F51 -> 29.6
D52: AGUA | E52: 7 | G52: =G51+E52-F52 -> 36.6
D53: ALQUILER | E53: 1200 | G53: =G52+E53-F53 -> 1236.6
A54: 45589 | B54: RII 2478 | C54: JULIO | D54: LUZ | F54: 29.6 | G54: =G53+E54-F54 -> 1207
A55: 45589 | B55: RII 2478 | C55: JULIO | D55: AGUA | F55: 7 | G55: =G54+E55-F55 -> 1200
A56: 45589 | B56: EB01-4413 | C56: JULIO | D56: ALQUILER | F56: 1200 | G56: =G55+E56-F56 -> 0
A57: 45535 | B57: POR COBRAR | C57: AGOSTO | D57: LUZ | E57: 29.7 | G57: =G56+E57-F57 -> 29.7
D58: AGUA | E58: 7 | G58: =G57+E58-F58 -> 36.7
D59: ALQUILER | E59: 1200 | G59: =G58+E59-F59 -> 1236.7
A60: 45640 | B60: EB01-4691 | C60: AGOSTO | D60: ALQUILER | F60: 1200 | G60: =G59+E60-F60 -> 36.7
A61: 45660 | B61: RII 2598 | C61: AGOSTO | D61: LUZ | F61: 29.7 | G61: =G60+E61-F61 -> 7
A62: 45660 | B62: RII 2598 | C62: AGOSTO | D62: AGUA | F62: 7 | G62: =G61+E62-F62 -> 4.6185278e-14
A63: 45565 | B63: POR COBRAR | C63: SETIEMBRE | D63: LUZ | E63: 29.9 | G63: =G62+E63-F63 -> 29.9
D64: AGUA | E64: 5 | G64: =G63+E64-F64 -> 34.9
D65: ALQUILER | E65: 1200 | G65: =G64+E65-F65 -> 1234.9
A66: 45660 | B66: EB01-4794 | C66: SETIEMBRE | D66: ALQUILER | F66: 1200 | G66: =G65+E66-F66 -> 34.9 | H66: =+F66 -> 1200 | I66: SSHH
A67: 45660 | B67: RII 2598 | C67: SETIEMBRE | D67: LUZ | F67: 29.9 | G67: =G66+E67-F67 -> 5
A68: 45660 | B68: RII 2598 | C68: SETIEMBRE | D68: AGUA | F68: 5 | G68: =G67+E68-F68 -> 9.2370556e-14
A69: 45596 | B69: POR COBRAR | C69: OCTUBRE | D69: LUZ | E69: 25 | G69: =G68+E69-F69 -> 25
D70: AGUA | E70: 7 | G70: =G69+E70-F70 -> 32
D71: ALQUILER | E71: 1100 | G71: =G70+E71-F71 -> 1132
A72: 45693 | B72: RII 2668 | C72: OCTUBRE | D72: LUZ | F72: 25 | G72: =G71+E72-F72 -> 1107
A73: 45693 | B73: RII 2668 | C73: OCTUBRE | D73: AGUA | F73: 7 | G73: =G72+E73-F73 -> 1100
A74: 45693 | B74: EB01-4981 | C74: OCTUBRE | D74: ALQUILER | F74: 502.3 | G74: =G73+E74-F74 -> 597.7
A75: 45705 | B75: EB01-5032 | C75: OCTUBRE | D75: ALQUILER | F75: 597.7 | G75: =G74+E75-F75 -> 0 | H75: =+F75 -> 597.7 | I75: SSHH
A76: 45626 | B76: POR COBRAR | C76: NOVIEMBRE | D76: LUZ | E76: 24.8 | G76: =G75+E76-F76 -> 24.8
D77: AGUA | E77: 7 | G77: =G76+E77-F77 -> 31.8
D78: ALQUILER | E78: 1100 | G78: =G77+E78-F78 -> 1131.8
A79: 45693 | B79: RII 2668 | C79: NOVIEMBRE | D79: LUZ | F79: 24.8 | G79: =G78+E79-F79 -> 1107
A80: 45693 | B80: RII 2668 | C80: NOVIEMBRE | D80: AGUA | F80: 7 | G80: =G79+E80-F80 -> 1100
A81: 45705 | B81: EB01-5032 | C81: NOVIEMBRE | D81: ALQUILER | F81: 402.3 | G81: =G80+E81-F81 -> 697.7 | H81: =+F81 -> 402.3 | I81: SSHH
A82: 45716 | B82: EB01-5145 | C82: NOVIEMBRE | D82: ALQUILER | F82: 390 | G82: =G81+E82-F82 -> 307.7
A83: 45731 | B83: EB01-5211 | C83: NOVIEMBRE | D83: ALQUILER | F83: 307.7 | G83: =G82+E83-F83 -> 0
A84: 45657 | B84: POR COBRAR | C84: DICIEMBRE | D84: LUZ | E84: 20.9 | G84: =G83+E84-F84 -> 20.9
D85: AGUA | E85: 3 | G85: =G84+E85-F85 -> 23.9
D86: ALQUILER | E86: 1100 | G86: =G85+E86-F86 -> 1123.9
A87: 45693 | B87: RII 2668 | C87: DICIEMBRE | D87: LUZ | F87: 20.9 | G87: =G86+E87-F87 -> 1103
A88: 45693 | B88: RII 2668 | C88: DICIEMBRE | D88: AGUA | F88: 3 | G88: =G87+E88-F88 -> 1100
A89: 45238 | B89: EB01-2880 | C89: NOVIEMBRE | D89: GARANTIA | F89: 1100 | G89: =G88+E89-F89 -> 0
A90: 45688 | B90: POR COBRAR | C90: ENERO | D90: LUZ | E90: 18 | G90: =G89+E90-F90 -> 18 | K90: ATO MARIA
D91: AGUA | E91: 3 | G91: =G90+E91-F91 -> 21 | J91: 2024 | K91: NOVIEMBRE | L91: ALQUILER
D92: ALQUILER | E92: 1000 | G92: =G91+E92-F92 -> 1021 | J92: 2025 | K92: ENERO | L92: ALQUILER
A93: 45707 | B93: RII 2689 | C93: ENERO | D93: LUZ | F93: 18 | G93: =G92+E93-F93 -> 1003
A94: 45707 | B94: RII 2689 | C94: ENERO | D94: AGUA | F94: 3 | G94: =G93+E94-F94 -> 1000
A95: 45238 | B95: EB01-2880 | C95: ENERO | D95: GARANTIA | F95: 100 | G95: =G94+E95-F95 -> 900 | K95: FEBRERO | L95: LUZ
A96: 45731 | B96: EB01-5211 | C96: ENERO | D96: ALQUILER | F96: 900 | G96: =G95+E96-F96 -> 0
A97: 45716 | B97: POR COBRAR | C97: FEBRERO | D97: LUZ | E97: 20.9 | G97: =G96+E97-F97 -> 20.9 | L97: AGUA
D98: AGUA | E98: 3 | G98: =G97+E98-F98 -> 23.9 | L98: ALQUILER
D99: ALQUILER | E99: 1000 | G99: =G98+E99-F99 -> 1023.9 | L99: ALQUILER | M99: 400
A100: 45733 | B100: RII 2725 | C100: FEBRERO | D100: LUZ | F100: 20.9 | G100: =G99+E100-F100 -> 1003
A101: 45733 | B101: RII 2725 | C101: FEBRERO | D101: AGUA | F101: 3 | G101: =G100+E101-F101 -> 1000
...

Sheet CLAROS SANTOS
A2: CLAROS TORRES JESUS SANTOS
I3: RUC | J3: 10104498146
A4: FECHA | B4: DOCUMENTO | C4: PERIODO | D4: CONCEPTO | E4: POR COBRAR | F4: PAGADO | G4: SALDO POR COBRAR
G5: 0
A6: 31/06/2025 | B6: POR COBRAR | C6: JUNIO | D6: ALQUILER | E6: 700 | G6: =+G5+E6-F6 -> 700
D7: GARANTIA | E7: 1000 | G7: =+G6+E7-F7 -> 1700
D8: LUZ | E8: 14.3 | G8: =+G7+E8-F8 -> 1714.3
D9: AGUA | E9: 4 | G9: =+G8+E9-F9 -> 1718.3
A10: 45807 | B10: RII 2845 | C10: ABRIL | D10: GARANTIA | F10: 1000 | G10: =+G9+E10-F10 -> 718.3
A11: 45810 | B11: EB01-5583 | C11: ABRIL | D11: ALQUILER | F11: 500 | G11: =+G10+E11-F11 -> 218.3 | H11: =+F11 -> 500 | I11: PARQUEO | K11: JUNIO | L11: LUZ | M11: 14.3
A12: 45810 | B12: EB01-5583 | C12: ABRIL | D12: ALQUILER | F12: 200 | G12: =+G11+E12-F12 -> 18.3 | H12: =+F12 -> 200 | I12: PARQUEO | L12: AGUA | M12: 4
A13: 45939 | B13: RII 3027 | C13: JUNIO | D13: LUZ | F13: 14.3 | G13: =+G12+E13-F13 -> 4
A14: 45939 | B14: RII 3027 | C14: JUNIO | D14: AGUA | F14: 4 | G14: =+G13+E14-F14 -> -4.6185278e-14
A15: 45868 | B15: POR COBRAR | C15: JULIO | D15: LUZ | E15: 18.8 | G15: =+G14+E15-F15 -> 18.8 | K15: JULIO | L15: LUZ | M15: 18.8
D16: AGUA | E16: 4 | G16: =+G15+E16-F16 -> 22.8 | L16: AGUA | M16: 4
D17: ALQUILER | E17: 700 | G17: =+G16+E17-F17 -> 722.8 | L17: ALQUILER | M17: 300 | N17: =SUM(M11:M16) -> 41.1
A18: 45868 | B18: E001-217 | C18: JULIO | D18: ALQUILER | F18: 400 | G18: =+G17+E18-F18 -> 322.8 | M18: =SUM(M11:M17) -> 341.1
A19: 45902 | B19: E001-228 | C19: JULIO | D19: ALQUILER | F19: 160 | G19: =+G18+E19-F19 -> 162.8
A20: 45939 | B20: RII 3027 | C20: JULIO | D20: LUZ | F20: 18.8 | G20: =+G19+E20-F20 -> 144
A21: 45939 | B21: RII 3027 | C21: JULIO | D21: AGUA | F21: 4 | G21: =+G20+E21-F21 -> 140
A22: 45946 | B22: E001-242 | C22: JULIO | D22: ALQUILER | F22: 140 | G22: =+G21+E22-F22 -> 0
A23: 45899 | B23: POR COBRAR | C23: AGOSTO | D23: LUZ | E23: 7 | G23: =+G22+E23-F23 -> 7 | K23: CLAROS SANTOS
D24: AGUA | E24: 6 | G24: =+G23+E24-F24 -> 13 | J24: 2025 | K24: SETIEMBRE | L24: ALQUILER | M24: 140
D25: ALQUILER | E25: 700 | G25: =+G24+E25-F25 -> 713 | K25: OCTUBRE | L25: ALQUILER | M25: 700
A26: 45918 | B26: E001-232 | C26: AGOSTO | D26: ALQUILER | F26: 500 | G26: =+G25+E26-F26 -> 213 | K26: NOVIEMBRE | L26: ALQUILER | M26: 700
A27: 45939 | B27: RII 3027 | C27: AGOSTO | D27: LUZ | F27: 7 | G27: =+G26+E27-F27 -> 206 | M27: =SUM(M24:M26) -> 1540
A28: 45939 | B28: RII 3027 | C28: AGOSTO | D28: AGUA | F28: 6 | G28: =+G27+E28-F28 -> 200
A29: 45946 | B29: E001-242 | C29: AGOSTO | D29: ALQUILER | F29: 160 | G29: =+G28+E29-F29 -> 40
A30: 45946 | B30: E001-243 | C30: AGOSTO | D30: ALQUILER | F30: 40 | G30: =+G29+E30-F30 -> 0
A31: 31/09/2025 | B31: POR COBRAR | C31: SETIEMBRE | D31: LUZ | E31: 25 | G31: =+G30+E31-F31 -> 25 | H31: =SUM(H5:H26) -> 700 | I31: TOTALES
D32: AGUA | E32: 4 | G32: =+G31+E32-F32 -> 29
D33: ALQUILER | E33: 700 | G33: =+G32+E33-F33 -> 729 | K33: OCTUBRE | L33: LUZ | M33: 33.7
A34: 45946 | B34: E001-243 | C34: SETIEMBRE | D34: ALQUILER | F34: 60 | G34: =+G33+E34-F34 -> 669 | L34: AGUA | M34: 6
A35: 45952 | B35: RII 3044 | C35: SETIEMBRE | D35: LUZ | F35: 25 | G35: =+G34+E35-F35 -> 644 | M35: =SUM(M33:M34) -> 39.7
A36: 45952 | B36: RII 3044 | C36: SETIEMBRE | D36: AGUA | F36: 4 | G36: =+G35+E36-F36 -> 640
A37: 45966 | B37: E001-252 | C37: SETIEMBRE | D37: ALQUILER | F37: 500 | G37: =+G36+E37-F37 -> 140
A38: 45994 | B38: E001-267 | C38: SETIEMBRE | D38: ALQUILER | F38: 140 | G38: =+G37+E38-F38 -> 0 | K38: CLAROS SANTOS
A39: 45961 | B39: POR COBRAR | C39: OCTUBRE | D39: LUZ | E39: 33.7 | G39: =+G38+E39-F39 -> 33.7 | J39: 2025 | K39: NOVIEMBRE | L39: LUZ | M39: 24.4
D40: AGUA | E40: 6 | G40: =+G39+E40-F40 -> 39.7 | L40: AGUA | M40: 5
D41: ALQUILER | E41: 700 | G41: =+G40+E41-F41 -> 739.7 | L41: ALQUILER | M41: 500
A42: 45986 | B42: RII 3103 | C42: OCTUBRE | D42: LUZ | F42: 33.7 | G42: =+G41+E42-F42 -> 706 | M42: =SUM(M39:M41) -> 529.4
A43: 45986 | B43: RII3103 | C43: OCTUBRE | D43: AGUA | F43: 6 | G43: =+G42+E43-F43 -> 700
A44: 45994 | B44: E001-268 | C44: OCTUBRE | D44: ALQUILER | F44: 200 | G44: =+G43+E44-F44 -> 500
A45: 46001 | B45: E001-272 | C45: OCTUBRE | D45: ALQUILER | F45: 500 | G45: =+G44+E45-F45 -> 0
A46: 45991 | B46: POR COBRAR | C46: NOVIEMBRE | D46: LUZ | E46: 24.4 | G46: =+G45+E46-F46 -> 24.4
D47: AGUA | E47: 5 | G47: =+G46+E47-F47 -> 29.4
D48: ALQUILER | E48: 700 | G48: =+G47+E48-F48 -> 729.4
A49: 46008 | B49: E001-277 | C49: NOVIEMBRE | D49: ALQUILER | F49: 80 | G49: =+G48+E49-F49 -> 649.4
A50: 46008 | B50: E001-278 | C50: NOVIEMBRE | D50: ALQUILER | F50: 120 | G50: =+G49+E50-F50 -> 529.4
A51: 46020 | B51: RII 3149 | C51: NOVIEMBRE | D51: LUZ | F51: 24.4 | G51: =+G50+E51-F51 -> 505
A52: 46020 | B52: RII 3149 | C52: NOVIEMBRE | D52: AGUA | F52: 5 | G52: =+G51+E52-F52 -> 500
A53: 46020 | B53: E001-284 | C53: NOVIEMBRE | D53: ALQUILER | F53: 200 | G53: =+G52+E53-F53 -> 300
A54: 46020 | B54: E001-285 | C54: NOVIEMBRE | D54: ALQUILER | F54: 100 | G54: =+G53+E54-F54 -> 200
A55: 46027 | B55: E001-292 | C55: NOVIEMBRE | D55: ALQUILER | F55: 200 | G55: =+G54+E55-F55 -> 0
A56: 46022 | B56: POR COBRAR | C56: DICIEMBRE | D56: LUZ | E56: 26.5 | G56: =+G55+E56-F56 -> 26.5
D57: AGUA | E57: 5 | G57: =+G56+E57-F57 -> 31.5
D58: ALQUILER | E58: 700 | G58: =+G57+E58-F58 -> 731.5
A59: 46036 | B59: E001-297 | C59: DICIEMBRE | D59: ALQUILER | F59: 200 | G59: =+G58+E59-F59 -> 531.5
A60: 46043 | B60: E001-305 | C60: DICIEMBRE | D60: ALQUILER | F60: 200 | G60: =+G59+E60-F60 -> 331.5
A61: 46050 | B61: E001-307 | C61: DICIEMBRE | D61: ALQUILER | F61: 120 | G61: =+G60+E61-F61 -> 211.5
A62: 46052 | B62: RII 3221 | C62: DICIEMBRE | D62: LUZ | F62: 26.5 | G62: =+G61+E62-F62 -> 185
A63: 46052 | B63: RII 3221 | C63: DICIEMBRE | D63: AGUA | F63: 5 | G63: =+G62+E63-F63 -> 180
A64: 46052 | B64: E001-308 | C64: DICIEMBRE | D64: ALQUILER | F64: 100 | G64: =+G63+E64-F64 -> 80
A65: 46057 | B65: E001-313 | C65: DICIEMBRE | D65: ALQUILER | F65: 80 | G65: =+G64+E65-F65 -> 0
A66: 46053 | B66: POR COBRAR | C66: ENERO | D66: LUZ | E66: 21.1 | G66: =+G65+E66-F66 -> 21.1
D67: AGUA | E67: 3 | G67: =+G66+E67-F67 -> 24.1
D68: ALQUILER | E68: 700 | G68: =+G67+E68-F68 -> 724.1
A69: 46058 | B69: E001-314 | C69: ENERO | D69: ALQUILER | F69: 150 | G69: =+G68+E69-F69 -> 574.1
A70: 46064 | B70: E001-317 | C70: ENERO | D70: ALQUILER | F70: 100 | G70: =+G69+E70-F70 -> 474.1
A71: 46071 | B71: E001-318 | C71: ENERO | D71: ALQUILER | F71: 100 | G71: =+G70+E71-F71 -> 374.1
A72: 46071 | B72: E001-319 | C72: ENERO | D72: ALQUILER | F72: 50 | G72: =+G71+E72-F72 -> 324.1
A73: 46078 | B73: RII 3269 | C73: ENERO | D73: LUZ | F73: 21.1 | G73: =+G72+E73-F73 -> 303
A74: 46078 | B74: RII 3269 | C74: ENERO | D74: AGUA | F74: 3 | G74: =+G73+E74-F74 -> 300
A75: 46080 | B75: E001-323 | C75: ENERO | D75: ALQUILER | F75: 100 | G75: =+G74+E75-F75 -> 200
A76: 46085 | B76: E001-330 | C76: ENERO | D76: ALQUILER | F76: 100 | G76: =+G75+E76-F76 -> 100
A77: 46085 | B77: E001-331 | C77: ENERO | D77: ALQUILER | F77: 100 | G77: =+G76+E77-F77 -> 0
A78: 46081 | B78: POR COBRAR | C78: FEBRERO | D78: LUZ | E78: 20.1 | G78: =+G77+E78-F78 -> 20.1
D79: AGUA | E79: 6 | G79: =+G78+E79-F79 -> 26.1
D80: ALQUILER | E80: 700 | G80: =+G79+E80-F80 -> 726.1
A81: 46092 | B81: E001-336 | C81: FEBRERO | D81: ALQUILER | F81: 150 | G81: =+G80+E81-F81 -> 576.1
A82: 46099 | B82: E001-346 | C82: FEBRERO | D82: ALQUILER | F82: 150 | G82: =+G81+E82-F82 -> 426.1
A83: 46108 | B83: E001-353 | C83: FEBRERO | D83: ALQUILER | F83: 100 | G83: =+G82+E83-F83 -> 326.1
A84: 46120 | B84: E001-358 | C84: FEBRERO | D84: ALQUILER | F84: 250 | G84: =+G83+E84-F84 -> 76.1
A85: 46127 | B85: E001-365 | C85: FEBRERO | D85: ALQUILER | F85: 50 | G85: =+G84+E85-F85 -> 26.1
A86: 46127 | B86: RII 3345 | C86: FEBRERO | D86: LUZ | F86: 0.1 | G86: =+G85+E86-F86 -> 26 | J86: CLAROS SANTOS
A87: 46127 | B87: RII 3345 | C87: FEBRERO | D87: AGUA | F87: 6 | G87: =+G86+E87-F87 -> 20 | I87: 2026 | J87: MARZO | K87: LUZ | L87: 20.1
A88: 46126 | B88: RII 3346 | C88: FEBRERO | D88: LUZ | F88: 20 | G88: =+G87+E88-F88 -> 0 | K88: AGUA | L88: 6
A89: 46112 | B89: POR COBRAR | C89: MARZO | D89: LUZ | E89: 20.1 | G89: =+G88+E89-F89 -> 20.1 | K89: ALQUILER | L89: 400
D90: AGUA | E90: 6 | G90: =+G89+E90-F90 -> 26.1 | L90: =SUM(L87:L89) -> 426.1
D91: ALQUILER | E91: 700 | G91: =+G90+E91-F91 -> 726.1
A92: 46127 | B92: E001-365 | C92: MARZO | D92: ALQUILER | F92: 150 | G92: =+G91+E92-F92 -> 576.1
A93: 46134 | B93: E001-370 | C93: MARZO | D93: ALQUILER | F93: 150 | G93: =+G92+E93-F93 -> 426.1
A94: 46141 | B94: RII 3379 | C94: MARZO | D94: LUZ | F94: 20.1 | G94: =+G93+E94-F94 -> 406
A95: 46141 | B95: RII 3379 | C95: MARZO | D95: AGUA | F95: 6 | G95: =+G94+E95-F95 -> 400
A96: 46141 | B96: E001-376 | C96: MARZO | D96: ALQUILER | F96: 150 | G96: =+G95+E96-F96 -> 250
A97: 46142 | B97: POR COBRAR | C97: ABRIL | D97: LUZ | G97: =+G96+E97-F97 -> 250
D98: AGUA | G98: =+G97+E98-F98 -> 250
D99: ALQUILER | E99: 700 | G99: =+G98+E99-F99 -> 950
G100: =+G99+E100-F100 -> 950
G101: =+G100+E101-F101 -> 950
...

Sheet CALLIROS FIORELLA
A1: CALLIRGOS GONZALES FIORELLA JAZMIN
A3: FECHA | B3: DOCUMENTO | C3: PERIODO | D3: CONCEPTO | E3: POR COBRAR | F3: PAGADO | G3: SALDO POR COBRAR
G4: 0
A5: 45777 | B5: POR COBRAR | C5: ABRIL | D5: LUZ | E5: 68.2 | G5: =+G4+E5-F5 -> 68.2
D6: AGUA | E6: 3 | G6: =+G5+E6-F6 -> 71.2
D7: ALQUILER | E7: 1000 | G7: =+G6+E7-F7 -> 1071.2
D8: GARANTIA | E8: 1000 | G8: =+G7+E8-F8 -> 2071.2
A9: 45750 | B9: EB01-5313 | C9: ABRIL | D9: ALQUILER | F9: 1000 | G9: =+G8+E9-F9 -> 1071.2
A10: 45750 | B10: EB01-5314 | C10: ABRIL | D10: ALQUILER | F10: 1000 | G10: =+G9+E10-F10 -> 71.2
A11: 45813 | B11: RII 2858 | C11: ABRIL | D11: LUZ | F11: 68.2 | G11: =+G10+E11-F11 -> 3
A12: 45813 | B12: RII 2858 | C12: ABRIL | D12: AGUA | F12: 3 | G12: =+G11+E12-F12 -> -1.8474111e-13
G13: =+G12+E13-F13 -> -1.8474111e-13
G14: =+G13+E14-F14 -> -1.8474111e-13
G15: =+G14+E15-F15 -> -1.8474111e-13
G16: =+G15+E16-F16 -> -1.8474111e-13
G17: =+G16+E17-F17 -> -1.8474111e-13
G18: =+G17+E18-F18 -> -1.8474111e-13
G19: =+G18+E19-F19 -> -1.8474111e-13
G20: =+G19+E20-F20 -> -1.8474111e-13

Sheet CARRASCO MERY
B3: CARRASCO PICHIHUA MERY RUTH
A5: FECHA | B5: DOCUMENTO | C5: PERIODO | D5: CONCEPTO | E5: POR COBRAR | F5: PAGADO | G5: SALDO POR COBRAR
A6: 42736 | B6: SALDO AL 2016 | G6: 738.1
A7: 42746 | B7: 12070 | C7: A CUENTA DEL 2016 | F7: 333.1 | G7: =+G6+E7-F7 -> 405
A8: 42767 | B8: 12193 | C8: A CUENTA DEL 2016 | F8: 25 | G8: =+G7+E8-F8 -> 380
A9: 42766 | B9: 12187 | C9: A CUENTA DEL 2016 | F9: 300 | G9: =+G8+E9-F9 -> 80
A10: 43525 | B10: 17902 | C10: CANCELACION 2016 | F10: 80 | G10: =+G9+E10-F10 -> 0
A11: 42766 | B11: POR COBRAR | C11: ENERO | D11: LUZ | E11: 13.5 | G11: =+G10+E11-F11 -> 13.5
D12: AGUA | E12: 2.8 | G12: =+G11+E12-F12 -> 16.3
D13: ALQUILER | E13: 300 | G13: =+G12+E13-F13 -> 316.3
A14: 42796 | B14: 12315 | C14: ENERO | D14: ALQUILER | F14: 300 | G14: =+G13+E14-F14 -> 16.3
A15: 42796 | B15: 12316 | C15: ENERO | D15: LUZ | F15: 13.5 | G15: =+G14+E15-F15 -> 2.8
A16: 42796 | B16: 12316 | C16: ENERO | D16: AGUA | F16: 2.8 | G16: =+G15+E16-F16 -> 1.1546319e-14
A17: 42794 | B17: POR COBRAR | C17: FEBRERO | D17: LUZ | E17: 13 | G17: =+G16+E17-F17 -> 13
D18: AGUA | E18: 2 | G18: =+G17+E18-F18 -> 15
D19: ALQUILER | E19: 300 | G19: =+G18+E19-F19 -> 315
A20: 42828 | B20: 12468 | C20: FEBRERO | D20: ALQUILER | F20: 300 | G20: =+G19+E20-F20 -> 15
A21: 42828 | B21: 12468 | C21: FEBRERO | D21: LUZ | F21: 13 | G21: =+G20+E21-F21 -> 2
A22: 42828 | B22: 12468 | C22: FEBRERO | D22: AGUA | F22: 2 | G22: =+G21+E22-F22 -> 0
A23: 42825 | B23: POR COBRAR | C23: MARZO | D23: LUZ | E23: 12 | G23: =+G22+E23-F23 -> 12
D24: AGUA | E24: 2 | G24: =+G23+E24-F24 -> 14
D25: ALQUILER | E25: 300 | G25: =+G24+E25-F25 -> 314
A26: 42842 | B26: 12541 | C26: MARZO | D26: ALQUILER | F26: 300 | G26: =+G25+E26-F26 -> 14
A27: 43525 | B27: 17902 | C27: MARZO | D27: LUZ | F27: 12 | G27: =+G26+E27-F27 -> 2
A28: 43525 | B28: 17902 | C28: MARZO | D28: AGUA | F28: 2 | G28: =+G27+E28-F28 -> 0
A29: 42855 | B29: POR COBRAR | C29: ABRIL | D29: LUZ | E29: 13 | G29: =+G28+E29-F29 -> 13
D30: AGUA | E30: 2 | G30: =+G29+E30-F30 -> 15
D31: ALQUILER | E31: 300 | G31: =+G30+E31-F31 -> 315
A32: 42964 | B32: 13276 | C32: ABRIL | D32: ALQUILER | F32: 300 | G32: =+G31+E32-F32 -> 15
A33: 43525 | B33: 17902 | C33: ABRIL | D33: LUZ | F33: 13 | G33: =+G32+E33-F33 -> 2
A34: 43525 | B34: 17902 | C34: ABRIL | D34: AGUA | F34: 2 | G34: =+G33+E34-F34 -> 0
A35: 42886 | B35: POR COBRAR | C35: MAYO | D35: LUZ | E35: 13 | G35: =+G34+E35-F35 -> 13
D36: AGUA | E36: 2 | G36: =+G35+E36-F36 -> 15
D37: ALQUILER | E37: 300 | G37: =+G36+E37-F37 -> 315
A38: 42964 | B38: 13276 | C38: MAYO | D38: ALQUILER | F38: 200 | G38: =+G37+E38-F38 -> 115
A39: 42990 | B39: 13454 | C39: MAYO | D39: ALQUILER | F39: 100 | G39: =+G38+E39-F39 -> 15
A40: 43525 | B40: 17902 | C40: MAYO | D40: LUZ | F40: 13 | G40: =+G39+E40-F40 -> 2
A41: 43525 | B41: 17902 | C41: MAYO | D41: AGUA | F41: 2 | G41: =+G40+E41-F41 -> 0
A42: 42916 | B42: POR COBRAR | C42: JUNIO | D42: LUZ | E42: 13 | G42: =+G41+E42-F42 -> 13
D43: AGUA | E43: 2 | G43: =+G42+E43-F43 -> 15
D44: ALQUILER | E44: 300 | G44: =+G43+E44-F44 -> 315
A45: 42990 | B45: 13454 | D45: ALQUILER | F45: 100 | G45: =+G44+E45-F45 -> 215
A46: 43159 | B46: 14261 | C46: JUNIO | D46: ALQUILER | F46: 200 | G46: =+G45+E46-F46 -> 15
A47: 43525 | B47: 17902 | C47: JUNIO | D47: LUZ | F47: 13 | G47: =+G46+E47-F47 -> 2
A48: 43525 | B48: 17902 | C48: JUNIO | D48: AGUA | F48: 2 | G48: =+G47+E48-F48 -> 0
A49: 42947 | B49: POR COBRAR | C49: JULIO | D49: LUZ | E49: 13 | G49: =+G48+E49-F49 -> 13
D50: AGUA | E50: 2 | G50: =+G49+E50-F50 -> 15
D51: ALQUILER | E51: 300 | G51: =+G50+E51-F51 -> 315
A52: 43162 | B52: 14324 | C52: JUNIO | D52: ALQUILER | F52: 100 | G52: =+G51+E52-F52 -> 215
A53: 43251 | B53: 14708 | C53: JUNIO | D53: ALQUILER | F53: 200 | G53: =+G52+E53-F53 -> 15
A54: 43525 | B54: 17903 | C54: JUNIO | D54: LUZ | F54: 13 | G54: =+G53+E54-F54 -> 2
A55: 43525 | B55: 17903 | C55: JUNIO | D55: AGUA | F55: 2 | G55: =+G54+E55-F55 -> 0
A56: 42978 | B56: POR COBRAR | C56: AGOSTO | D56: LUZ | E56: 13 | G56: =+G55+E56-F56 -> 13
D57: AGUA | E57: 2 | G57: =+G56+E57-F57 -> 15
D58: ALQUILER | E58: 300 | G58: =+G57+E58-F58 -> 315
A59: 43251 | B59: 14708 | C59: AGOSTO | D59: ALQUILER | F59: 100 | G59: =+G58+E59-F59 -> 215
A60: 43298 | B60: 14934 | C60: AGOSTO | D60: ALQUILER | F60: 200 | G60: =+G59+E60-F60 -> 15
A61: 43525 | B61: 17903 | C61: AGOSTO | D61: LUZ | F61: 13 | G61: =+G60+E61-F61 -> 2
A62: 43525 | B62: 17903 | C62: AGOSTO | D62: AGUA | F62: 2 | G62: =+G61+E62-F62 -> 0
A63: 43008 | B63: POR COBRAR | C63: SEPTIEMBRE | D63: LUZ | E63: 8 | G63: =+G62+E63-F63 -> 8
D64: AGUA | E64: 2 | G64: =+G63+E64-F64 -> 10
D65: ALQUILER | E65: 300 | G65: =+G64+E65-F65 -> 310
A66: 43298 | B66: 14934 | C66: SEPTIEMBRE | D66: ALQUILER | F66: 300 | G66: =+G65+E66-F66 -> 10
A67: 43525 | B67: 17903 | C67: SEPTIEMBRE | D67: LUZ | F67: 8 | G67: =+G66+E67-F67 -> 2
A68: 43525 | B68: 17903 | C68: SEPTIEMBRE | D68: AGUA | F68: 2 | G68: =+G67+E68-F68 -> 0
A69: 43039 | B69: POR COBRAR | C69: OCTUBRE | D69: LUZ | E69: 8 | G69: =+G68+E69-F69 -> 8
D70: AGUA | E70: 2 | G70: =+G69+E70-F70 -> 10
D71: ALQUILER | E71: 300 | G71: =+G70+E71-F71 -> 310
A72: 43298 | B72: 14934 | C72: OCTUBRE | D72: ALQUILER | F72: 100 | G72: =+G71+E72-F72 -> 210
A73: 43314 | B73: 15012 | C73: OCTUBRE | D73: ALQUILER | F73: 150 | G73: =+G72+E73-F73 -> 60
A74: 43344 | B74: 15126 | C74: OCTUBRE | D74: ALQUILER | F74: 50 | G74: =+G73+E74-F74 -> 10
A75: 43525 | B75: 17903 | C75: OCTUBRE | D75: LUZ | F75: 8 | G75: =+G74+E75-F75 -> 2
A76: 43525 | B76: 17903 | C76: OCTUBRE | D76: AGUA | F76: 2 | G76: =+G75+E76-F76 -> 0
A77: 43069 | B77: POR COBRAR | C77: NOVIEMBRE | D77: LUZ | E77: 8.2 | G77: =+G76+E77-F77 -> 8.2
D78: AGUA | E78: 2 | G78: =+G77+E78-F78 -> 10.2
D79: ALQUILER | E79: 300 | G79: =+G78+E79-F79 -> 310.2
A80: 43344 | B80: 15126 | C80: NOVIEMBRE | D80: ALQUILER | F80: 120 | G80: =+G79+E80-F80 -> 190.2
A81: 43374 | B81: 15275 | C81: NOVIEMBRE | D81: ALQUILER | F81: 160 | G81: =+G80+E81-F81 -> 30.2
A82: 43406 | B82: 15452 | C82: NOVIEMBRE | D82: ALQUILER | F82: 20 | G82: =+G81+E82-F82 -> 10.2
A83: 43525 | B83: 17904 | C83: NOVIEMBRE | D83: LUZ | F83: 8.2 | G83: =+G82+E83-F83 -> 2
A84: 43525 | B84: 17904 | C84: NOVIEMBRE | D84: AGUA | F84: 2 | G84: =+G83+E84-F84 -> -1.0658141e-14
A85: 43100 | B85: POR COBRAR | C85: DICIEMBRE | D85: LUZ | E85: 8.9 | G85: =+G84+E85-F85 -> 8.9
D86: AGUA | E86: 2 | G86: =+G85+E86-F86 -> 10.9
D87: ALQUILER | E87: 300 | G87: =+G86+E87-F87 -> 310.9
A88: 43406 | B88: 15452 | C88: DICIEMBRE | D88: ALQUILER | F88: 300 | G88: =+G87+E88-F88 -> 10.9
A89: 43525 | B89: 17904 | C89: DICIEMBRE | D89: LUZ | F89: 8.9 | G89: =+G88+E89-F89 -> 2
A90: 43525 | B90: 17904 | C90: DICIEMBRE | D90: AGUA | F90: 2 | G90: =+G89+E90-F90 -> -2.3092639e-14
A91: 43131 | B91: POR COBRAR | C91: ENERO | D91: LUZ | E91: 8 | G91: =+G90+E91-F91 -> 8
D92: AGUA | E92: 2 | G92: =+G91+E92-F92 -> 10
D93: ALQUILER | E93: 300 | G93: =+G92+E93-F93 -> 310
A94: 43159 | B94: 14262 | C94: ENERO | D94: LUZ | F94: 8 | G94: =+G93+E94-F94 -> 302
A95: 43159 | B95: 14262 | C95: ENERO | D95: AGUA | F95: 2 | G95: =+G94+E95-F95 -> 300
A96: 43406 | B96: 15452 | C96: ENERO | D96: ALQUILER | F96: 300 | G96: =+G95+E96-F96 -> 0
A97: 43159 | B97: POR COBRAR | C97: FEBRERO | D97: LUZ | E97: 9.9 | G97: =+G96+E97-F97 -> 9.9
D98: AGUA | E98: 2 | G98: =+G97+E98-F98 -> 11.9
D99: ALQUILER | E99: 300 | G99: =+G98+E99-F99 -> 311.9
A100: 43224 | B100: 14562 | C100: FEBRERO | D100: LUZ | F100: 9.9 | G100: =+G99+E100-F100 -> 302
A101: 43224 | B101: 14562 | C101: FEBRERO | D101: AGUA | F101: 2 | G101: =+G100+E101-F101 -> 300
A102: 43406 | B102: 15452 | C102: FEBRERO | D102: ALQUILER | F102: 280 | G102: =+G101+E102-F102 -> 20
A103: 43404 | B103: 15411 | C103: FEBRERO | D103: ALQUILER | F103: 20 | G103: =+G102+E103-F103 -> 0
...

Sheet CASTRO CONSUELO
B3: CASTRO RODRIGUEZ JANETT CONSUELO
A5: FECHA | B5: DOCUMENTO | C5: PERIODO | D5: CONCEPTO | E5: POR COBRAR | F5: PAGADO | G5: SALDO POR COBRAR
G6: 0
A7: 42766 | B7: POR COBRAR | C7: ENERO | D7: LUZ | E7: 0 | G7: =+G6+E7-F7 -> 0
D8: AGUA | E8: 0 | G8: =+G7+E8-F8 -> 0
D9: ALQUILER | E9: 300 | G9: =+G8+E9-F9 -> 300
D10: GARANTIA | E10: 300 | G10: =+G9+E10-F10 -> 600
A11: 42765 | B11: 12166 | C11: ENERO | D11: GARANTIA | F11: 300 | G11: =+G10+E11-F11 -> 300
A12: 42765 | B12: 12166 | C12: ENERO | D12: ALQUILER | F12: 300 | G12: =+G11+E12-F12 -> 0
A13: 42794 | B13: POR COBRAR | C13: FEBRERO | D13: LUZ | E13: 39.5 | G13: =+G12+E13-F13 -> 39.5
D14: AGUA | E14: 2 | G14: =+G13+E14-F14 -> 41.5
D15: ALQUILER | E15: 0 | G15: =+G14+E15-F15 -> 41.5
A16: 42920 | B16: 12948 | C16: FEBRERO | D16: LUZ | F16: 39.5 | G16: =+G15+E16-F16 -> 2
A17: 42920 | B17: 12948 | C17: FEBRERO | D17: AGUA | F17: 2 | G17: =+G16+E17-F17 -> 0
A18: 42825 | B18: POR COBRAR | C18: MARZO | D18: LUZ | E18: 26.9 | G18: =+G17+E18-F18 -> 26.9
D19: AGUA | E19: 2 | G19: =+G18+E19-F19 -> 28.9
D20: ALQUILER | E20: 300 | G20: =+G19+E20-F20 -> 328.9
A21: 42864 | B21: 12663 | C21: MARZO | D21: ALQUILER | F21: 30 | G21: =+G20+E21-F21 -> 298.9
A22: 42831 | B22: 12490 | C22: MARZO | D22: ALQUILER | F22: 120 | G22: =+G21+E22-F22 -> 178.9
A23: 42892 | B23: 12794 | C23: MARZO | D23: ALQUILER | F23: 150 | G23: =+G22+E23-F23 -> 28.9
A24: 42920 | B24: 12948 | C24: MARZO | D24: LUZ | F24: 26.9 | G24: =+G23+E24-F24 -> 2
A25: 42920 | B25: 12948 | C25: MARZO | D25: AGUA | F25: 2 | G25: =+G24+E25-F25 -> -2.1316282e-14
A26: 42855 | B26: POR COBRAR | C26: ABRIL | D26: LUZ | E26: 28.1 | G26: =+G25+E26-F26 -> 28.1
D27: AGUA | E27: 2 | G27: =+G26+E27-F27 -> 30.1
D28: ALQUILER | E28: 300 | G28: =+G27+E28-F28 -> 330.1
A29: 42908 | B29: 12873 | C29: ABRIL | D29: ALQUILER | F29: 200 | G29: =+G28+E29-F29 -> 130.1
A30: 42920 | B30: 12948 | C30: ABRIL | D30: LUZ | F30: 28.1 | G30: =+G29+E30-F30 -> 102
A31: 42920 | B31: 12948 | C31: ABRIL | D31: AGUA | F31: 2 | G31: =+G30+E31-F31 -> 100
A32: 42958 | B32: 13254 | C32: ABRIL | D32: ALQUILER | F32: 100 | G32: =+G31+E32-F32 -> 0
A33: 42886 | B33: POR COBRAR | C33: MAYO | D33: LUZ | E33: 30.8 | G33: =+G32+E33-F33 -> 30.8
D34: AGUA | E34: 2 | G34: =+G33+E34-F34 -> 32.8
D35: ALQUILER | E35: 300 | G35: =+G34+E35-F35 -> 332.8
A36: 42920 | B36: 12948 | C36: MAYO | D36: LUZ | F36: 30.8 | G36: =+G35+E36-F36 -> 302
A37: 42920 | B37: 12948 | C37: MAYO | D37: AGUA | F37: 2 | G37: =+G36+E37-F37 -> 300
A38: 42958 | B38: 13254 | C38: MAYO | D38: ALQUILER | F38: 300 | G38: =+G37+E38-F38 -> 0
A39: 42916 | B39: POR COBRAR | C39: JUNIO | D39: LUZ | E39: 30.3 | G39: =+G38+E39-F39 -> 30.3
D40: AGUA | E40: 2 | G40: =+G39+E40-F40 -> 32.3
D41: ALQUILER | E41: 300 | G41: =+G40+E41-F41 -> 332.3
A42: 42958 | B42: 13254 | C42: JUNIO | D42: ALQUILER | F42: 300 | G42: =+G41+E42-F42 -> 32.3
A43: 43061 | B43: 13809 | C43: JUNIO | D43: LUZ | F43: 30.3 | G43: =+G42+E43-F43 -> 2
A44: 43061 | B44: 13809 | C44: JUNIO | D44: AGUA | F44: 2 | G44: =+G43+E44-F44 -> 1.0658141e-14
A45: 42947 | B45: POR COBRAR | D45: LUZ | E45: 28.3 | G45: =+G44+E45-F45 -> 28.3
D46: AGUA | E46: 2 | G46: =+G45+E46-F46 -> 30.3
D47: ALQUILER | E47: 300 | G47: =+G46+E47-F47 -> 330.3
A48: 43032 | B48: 13683 | C48: JULIO | D48: ALQUILER | F48: 300 | G48: =+G47+E48-F48 -> 30.3
A49: 43061 | B49: 13809 | C49: JULIO | D49: LUZ | F49: 28.3 | G49: =+G48+E49-F49 -> 2
A50: 43061 | B50: 13809 | C50: JULIO | D50: AGUA | F50: 2 | G50: =+G49+E50-F50 -> 1.0658141e-14
A51: 42978 | B51: POR COBRAR | C51: AGOSTO | D51: LUZ | E51: 28.3 | G51: =+G50+E51-F51 -> 28.3
D52: AGUA | E52: 2 | G52: =+G51+E52-F52 -> 30.3
D53: ALQUILER | E53: 300 | G53: =+G52+E53-F53 -> 330.3
A54: 43061 | B54: 13809 | C54: AGOSTO | D54: AGUA | F54: 2 | G54: =+G53+E54-F54 -> 328.3
A55: 43061 | B55: 13808 | C55: AGOSTO | D55: ALQUILER | F55: 300 | G55: =+G54+E55-F55 -> 28.3
A56: 43087 | B56: 13954 | C56: AGOSTO | D56: LUZ | F56: 28.3 | G56: =+G55+E56-F56 -> 0
A57: 43008 | B57: POR COBRAR | C57: SEPTIEMBRE | D57: LUZ | E57: 25.1 | G57: =+G56+E57-F57 -> 25.1
D58: AGUA | E58: 2 | G58: =+G57+E58-F58 -> 27.1
D59: ALQUILER | E59: 300 | G59: =+G58+E59-F59 -> 327.1
A60: 43061 | B60: 13809 | C60: SEPTIEMBRE | D60: AGUA | F60: 2 | G60: =+G59+E60-F60 -> 325.1
A61: 43061 | B61: 13808 | C61: SEPTIEMBRE | D61: ALQUILER | F61: 300 | G61: =+G60+E61-F61 -> 25.1
A62: 43087 | B62: 13954 | C62: SEPTIEMBRE | D62: LUZ | F62: 25.1 | G62: =+G61+E62-F62 -> 0
A63: 43039 | B63: POR COBRAR | C63: OCTUBRE | D63: LUZ | E63: 25 | G63: =+G62+E63-F63 -> 25
D64: AGUA | E64: 2 | G64: =+G63+E64-F64 -> 27
D65: ALQUILER | E65: 300 | G65: =+G64+E65-F65 -> 327
A66: 43061 | B66: 13809 | C66: OCTUBRE | D66: AGUA | F66: 2 | G66: =+G65+E66-F66 -> 325
A67: 43087 | B67: 13954 | C67: OCTUBRE | D67: LUZ | F67: 6.6 | G67: =+G66+E67-F67 -> 318.4
A68: 43108 | B68: 14056 | C68: OCTUBRE | D68: LUZ | F68: 18.4 | G68: =+G67+E68-F68 -> 300
A69: 43108 | B69: 14057 | C69: OCTUBRE | D69: ALQUILER | F69: 250 | G69: =+G68+E69-F69 -> 50
A70: 43118 | B70: 14081 | C70: OCTUBRE | D70: ALQUILER | F70: 50 | G70: =+G69+E70-F70 -> 0
A71: 43069 | B71: POR COBRAR | C71: NOVIEMBRE | D71: LUZ | E71: 26.7 | G71: =+G70+E71-F71 -> 26.7
D72: AGUA | E72: 2 | G72: =+G71+E72-F72 -> 28.7
D73: ALQUILER | E73: 300 | G73: =+G72+E73-F73 -> 328.7
A74: 43108 | B74: 14056 | C74: NOVIEMBRE | D74: ALQUILER | F74: 300 | G74: =+G73+E74-F74 -> 28.7
A75: 43108 | B75: 14056 | C75: NOVIEMBRE | D75: LUZ | F75: 26.7 | G75: =+G74+E75-F75 -> 2
A76: 43108 | B76: 14056 | C76: NOVIEMBRE | D76: AGUA | F76: 2 | G76: =+G75+E76-F76 -> -1.0658141e-14
A77: 43100 | B77: POR COBRAR | C77: DICIEMBRE | D77: LUZ | E77: 29 | G77: =+G76+E77-F77 -> 29
D78: AGUA | E78: 2 | G78: =+G77+E78-F78 -> 31
D79: ALQUILER | E79: 300 | G79: =+G78+E79-F79 -> 331
A80: 43204 | B80: 14476 | C80: DICIEMBRE | D80: LUZ | F80: 29 | G80: =+G79+E80-F80 -> 302
A81: 43204 | B81: 14476 | C81: DICIEMBRE | D81: AGUA | F81: 2 | G81: =+G80+E81-F81 -> 300
A82: 43118 | B82: 14081 | C82: DICIEMBRE | D82: ALQUILER | F82: 300 | G82: =+G81+E82-F82 -> 0
A83: 43131 | B83: POR COBRAR | C83: ENERO | D83: LUZ | E83: 25.9 | G83: =+G82+E83-F83 -> 25.9
D84: AGUA | E84: 2 | G84: =+G83+E84-F84 -> 27.9
D85: ALQUILER | E85: 300 | G85: =+G84+E85-F85 -> 327.9
A86: 43139 | B86: 14197 | C86: ENERO | D86: ALQUILER | F86: 300 | G86: =+G85+E86-F86 -> 27.9
A87: 43159 | B87: 14267 | C87: ENERO | D87: LUZ | F87: 25.9 | G87: =+G86+E87-F87 -> 2
A88: 43159 | B88: 14267 | C88: ENERO | D88: AGUA | F88: 2 | G88: =+G87+E88-F88 -> -2.1316282e-14
A89: 43159 | B89: POR COBRAR | C89: FEBRERO | D89: LUZ | E89: 32 | G89: =+G88+E89-F89 -> 32
D90: AGUA | E90: 2 | G90: =+G89+E90-F90 -> 34
D91: ALQUILER | E91: 300 | G91: =+G90+E91-F91 -> 334
A92: 43159 | B92: 14267 | C92: FEBRERO | D92: ALQUILER | F92: 300 | G92: =+G91+E92-F92 -> 34
A93: 43252 | B93: 14742 | C93: FEBRERO | D93: LUZ | F93: 32 | G93: =+G92+E93-F93 -> 2
A94: 43252 | B94: 14742 | C94: FEBRERO | D94: AGUA | F94: 2 | G94: =+G93+E94-F94 -> 0
A95: 43190 | B95: POR COBRAR | C95: MARZO | D95: LUZ | E95: 30.8 | G95: =+G94+E95-F95 -> 30.8
D96: AGUA | E96: 2 | G96: =+G95+E96-F96 -> 32.8
D97: ALQUILER | E97: 300 | G97: =+G96+E97-F97 -> 332.8
A98: 43204 | B98: 14476 | C98: MARZO | D98: ALQUILER | F98: 300 | G98: =+G97+E98-F98 -> 32.8
A99: 43234 | B99: 14592 | C99: MARZO | D99: LUZ | F99: 30.8 | G99: =+G98+E99-F99 -> 2
A100: 43252 | B100: 14742 | C100: MARZO | D100: AGUA | F100: 2 | G100: =+G99+E100-F100 -> 1.0658141e-14
A101: 43220 | B101: POR COBRAR | C101: ABRIL | D101: LUZ | E101: 31.8 | G101: =+G100+E101-F101 -> 31.8
D102: AGUA | E102: 2 | G102: =+G101+E102-F102 -> 33.8
D103: ALQUILER | E103: 300 | G103: =+G102+E103-F103 -> 333.8
...

Sheet CASTILLO ASAEL
B3: CASTILLO ZAPATA ASAEL
A5: FECHA | B5: DOCUMENTO | C5: PERIODO | D5: CONCEPTO | E5: POR COBRAR | F5: PAGADO | G5: SALDO POR COBRAR
A6: 42736 | B6: SALDO AL 2016 | G6: 93.4
A7: 42761 | B7: 12149 | C7: CANCELACION DEL 2016 | F7: 93.4 | G7: =+G6+E7-F7 -> 0
A8: 42766 | B8: POR COBRAR | C8: ENERO | D8: LUZ | E8: 94.2 | G8: =+G7+E8-F8 -> 94.2
D9: AGUA | E9: 2.8 | G9: =+G8+E9-F9 -> 97
D10: ALQUILER | E10: 600 | G10: =+G9+E10-F10 -> 697
A11: 42800 | B11: 12346 | C11: ENERO | D11: ALQUILER | F11: 600 | G11: =+G10+E11-F11 -> 97
A12: 42800 | B12: 12346 | C12: ENERO | D12: LUZ | F12: 94.2 | G12: =+G11+E12-F12 -> 2.8
A13: 42800 | B13: 12346 | C13: ENERO | D13: AGUA | F13: 2.8 | G13: =+G12+E13-F13 -> 0
A14: 42794 | B14: POR COBRAR | C14: FEBRERO | D14: LUZ | E14: 115.5 | G14: =+G13+E14-F14 -> 115.5
D15: AGUA | E15: 2 | G15: =+G14+E15-F15 -> 117.5
D16: ALQUILER | E16: 600 | G16: =+G15+E16-F16 -> 717.5
A17: 42824 | B17: 12460 | C17: FEBRERO | D17: ALQUILER | F17: 600 | G17: =+G16+E17-F17 -> 117.5
A18: 42824 | B18: 12460 | C18: FEBRERO | D18: LUZ | F18: 115.5 | G18: =+G17+E18-F18 -> 2
A19: 42824 | B19: 12460 | C19: FEBRERO | D19: AGUA | F19: 2 | G19: =+G18+E19-F19 -> 0
A20: 42825 | B20: POR COBRAR | C20: MARZO | D20: LUZ | E20: 110.3 | G20: =+G19+E20-F20 -> 110.3
D21: AGUA | E21: 2 | G21: =+G20+E21-F21 -> 112.3
D22: ALQUILER | E22: 600 | G22: =+G21+E22-F22 -> 712.3
A23: 42863 | B23: 12650 | C23: MARZO | D23: ALQUILER | F23: 600 | G23: =+G22+E23-F23 -> 112.3
A24: 42864 | B24: 12666 | C24: MARZO | D24: LUZ | F24: 110.3 | G24: =+G23+E24-F24 -> 2
A25: 42864 | B25: 12666 | C25: MARZO | D25: AGUA | F25: 2 | G25: =+G24+E25-F25 -> -4.2632564e-14
A26: 42855 | B26: POR COBRAR | C26: ABRIL | D26: LUZ | E26: 113.1 | G26: =+G25+E26-F26 -> 113.1
D27: AGUA | E27: 2 | G27: =+G26+E27-F27 -> 115.1
D28: ALQUILER | E28: 600 | G28: =+G27+E28-F28 -> 715.1
A29: 42896 | B29: 12809 | C29: ABRIL | D29: ALQUILER | F29: 600 | G29: =+G28+E29-F29 -> 115.1
A30: 42896 | B30: 12809 | C30: ABRIL | D30: LUZ | F30: 113.1 | G30: =+G29+E30-F30 -> 2
A31: 42896 | B31: 12809 | C31: ABRIL | D31: AGUA | F31: 2 | G31: =+G30+E31-F31 -> -8.5265128e-14
A32: 42886 | B32: POR COBRAR | C32: MAYO | D32: LUZ | E32: 106.2 | G32: =+G31+E32-F32 -> 106.2
D33: AGUA | E33: 2 | G33: =+G32+E33-F33 -> 108.2
D34: ALQUILER | E34: 600 | G34: =+G33+E34-F34 -> 708.2
A35: 42921 | B35: 12956 | C35: MAYO | D35: LUZ | F35: 106.2 | G35: =+G34+E35-F35 -> 602
A36: 42921 | B36: 12956 | C36: MAYO | D36: AGUA | F36: 2 | G36: =+G35+E36-F36 -> 600
A37: 42921 | B37: 12956 | C37: MAYO | D37: ALQUILER | F37: 600 | G37: =+G36+E37-F37 -> 0
A38: 42916 | B38: POR COBRAR | C38: JUNIO | D38: LUZ | E38: 103.7 | G38: =+G37+E38-F38 -> 103.7
D39: AGUA | E39: 2 | G39: =+G38+E39-F39 -> 105.7
D40: ALQUILER | E40: 600 | G40: =+G39+E40-F40 -> 705.7
A41: 42936 | B41: 13042 | C41: JUNIO | D41: ALQUILER | F41: 600 | G41: =+G40+E41-F41 -> 105.7
A42: 42936 | B42: 13042 | C42: JUNIO | D42: LUZ | F42: 103.7 | G42: =+G41+E42-F42 -> 2
A43: 42936 | B43: 13042 | C43: JUNIO | D43: AGUA | F43: 2 | G43: =+G42+E43-F43 -> 4.2632564e-14
A44: 42947 | B44: POR COBRAR | C44: JULIO | D44: LUZ | E44: 94.9 | G44: =+G43+E44-F44 -> 94.9
D45: AGUA | E45: 2 | G45: =+G44+E45-F45 -> 96.9
D46: ALQUILER | E46: 600 | G46: =+G45+E46-F46 -> 696.9
A47: 42964 | B47: 13277 | C47: JULIO | D47: ALQUILER | F47: 600 | G47: =+G46+E47-F47 -> 96.9
A48: 42984 | B48: 13395 | C48: JULIO | D48: LUZ | F48: 94.9 | G48: =+G47+E48-F48 -> 2
A49: 42984 | B49: 13395 | C49: JULIO | D49: AGUA | F49: 2 | G49: =+G48+E49-F49 -> 8.5265128e-14
A50: 42978 | B50: POR COBRAR | C50: AGOSTO | D50: LUZ | E50: 94.9 | G50: =+G49+E50-F50 -> 94.9
D51: AGUA | E51: 2 | G51: =+G50+E51-F51 -> 96.9
D52: ALQUILER | E52: 600 | G52: =+G51+E52-F52 -> 696.9
A53: 42987 | B53: 13436 | C53: AGOSTO | D53: ALQUILER | F53: 600 | G53: =+G52+E53-F53 -> 96.9
A54: 43025 | B54: 13639 | C54: AGOSTO | D54: LUZ | F54: 94.9 | G54: =+G53+E54-F54 -> 2
A55: 43025 | B55: 13639 | C55: AGOSTO | D55: AGUA | F55: 2 | G55: =+G54+E55-F55 -> 8.5265128e-14
A56: 43008 | B56: POR COBRAR | C56: SEPTIEMBRE | D56: LUZ | E56: 86.1 | G56: =+G55+E56-F56 -> 86.1
D57: AGUA | E57: 2 | G57: =+G56+E57-F57 -> 88.1
D58: ALQUILER | E58: 600 | G58: =+G57+E58-F58 -> 688.1
A59: 43025 | B59: 13639 | C59: SEPTIEMBRE | D59: ALQUILER | F59: 600 | G59: =+G58+E59-F59 -> 88.1
A60: 43105 | B60: 14049 | C60: SEPTIEMBRE | D60: LUZ | F60: 86.1 | G60: =+G59+E60-F60 -> 2
A61: 43105 | B61: 14049 | C61: SEPTIEMBRE | D61: AGUA | F61: 2 | G61: =+G60+E61-F61 -> 1.4210855e-13
A62: 43039 | B62: POR COBRAR | C62: OCTUBRE | D62: LUZ | E62: 85.6 | G62: =+G61+E62-F62 -> 85.6
D63: AGUA | E63: 2 | G63: =+G62+E63-F63 -> 87.6
D64: ALQUILER | E64: 600 | G64: =+G63+E64-F64 -> 687.6
A65: 43105 | B65: 14049 | C65: OCTUBRE | D65: ALQUILER | F65: 600 | G65: =+G64+E65-F65 -> 87.6
A66: 43105 | B66: 14049 | C66: OCTUBRE | D66: LUZ | F66: 85.6 | G66: =+G65+E66-F66 -> 2
A67: 43105 | B67: 14049 | C67: OCTUBRE | D67: AGUA | F67: 2 | G67: =+G66+E67-F67 -> 1.4210855e-13
A68: 43069 | B68: POR COBRAR | C68: NOVIEMBRE | D68: LUZ | E68: 91.4 | G68: =+G67+E68-F68 -> 91.4
D69: AGUA | E69: 2 | G69: =+G68+E69-F69 -> 93.4
D70: ALQUILER | E70: 600 | G70: =+G69+E70-F70 -> 693.4
A71: 43161 | B71: 14384 | C71: NOVIEMBRE | D71: LUZ | F71: 91.4 | G71: =+G70+E71-F71 -> 602
A72: 43161 | B72: 14384 | C72: NOVIEMBRE | D72: AGUA | F72: 2 | G72: =+G71+E72-F72 -> 600
A73: 43105 | B73: 14049 | C73: NOVIEMBRE | D73: ALQUILER | F73: 600 | G73: =+G72+E73-F73 -> 0
A74: 43100 | B74: POR COBRAR | C74: DICIEMBRE | D74: LUZ | E74: 99.4 | G74: =+G73+E74-F74 -> 99.4
D75: AGUA | E75: 2 | G75: =+G74+E75-F75 -> 101.4
D76: ALQUILER | E76: 600 | G76: =+G75+E76-F76 -> 701.4
A77: 43120 | B77: 14113 | C77: DICIEMBRE | D77: ALQUILER | F77: 600 | G77: =+G76+E77-F77 -> 101.4
A78: 43160 | B78: 14311 | C78: DICIEMBRE | D78: LUZ | F78: 99.4 | G78: =+G77+E78-F78 -> 2
A79: 43160 | B79: 14311 | C79: DICIEMBRE | D79: AGUA | F79: 2 | G79: =+G78+E79-F79 -> -2.8421709e-14
A80: 43131 | B80: POR COBRAR | C80: ENERO | D80: LUZ | E80: 88.5 | G80: =+G79+E80-F80 -> 88.5
D81: AGUA | E81: 2 | G81: =+G80+E81-F81 -> 90.5
D82: ALQUILER | E82: 600 | G82: =+G81+E82-F82 -> 690.5
A83: 43160 | B83: 14311 | C83: ENERO | D83: LUZ | F83: 88.5 | G83: =+G82+E83-F83 -> 602
A84: 43160 | B84: 14311 | C84: ENERO | D84: AGUA | F84: 2 | G84: =+G83+E84-F84 -> 600
A85: 43160 | B85: 14311 | C85: ENERO | D85: ALQUILER | F85: 600 | G85: =+G84+E85-F85 -> 0
A86: 43159 | B86: POR COBRAR | C86: FEBRERO | D86: LUZ | E86: 81.4 | G86: =+G85+E86-F86 -> 81.4
D87: AGUA | E87: 2 | G87: =+G86+E87-F87 -> 83.4
D88: ALQUILER | E88: 600 | G88: =+G87+E88-F88 -> 683.4
A89: 43161 | B89: 14384 | C89: FEBRERO | D89: ALQUILER | F89: 600 | G89: =+G88+E89-F89 -> 83.4
A90: 43161 | B90: 14384 | C90: FEBRERO | D90: LUZ | F90: 81.4 | G90: =+G89+E90-F90 -> 2
A91: 43161 | B91: 14384 | C91: FEBRERO | D91: AGUA | F91: 2 | G91: =+G90+E91-F91 -> -2.8421709e-14
A92: 43190 | B92: POR COBRAR | C92: MARZO | D92: LUZ | E92: 78.7 | G92: =+G91+E92-F92 -> 78.7
D93: AGUA | E93: 2 | G93: =+G92+E93-F93 -> 80.7
D94: ALQUILER | E94: 600 | G94: =+G93+E94-F94 -> 680.7
A95: 43213 | B95: 14505 | C95: MARZO | D95: ALQUILER | F95: 600 | G95: =+G94+E95-F95 -> 80.7
A96: 43213 | B96: 14505 | C96: MARZO | D96: LUZ | F96: 78.7 | G96: =+G95+E96-F96 -> 2
A97: 43213 | B97: 14505 | C97: MARZO | D97: AGUA | F97: 2 | G97: =+G96+E97-F97 -> -7.1054274e-14
A98: 43220 | B98: POR COBRAR | C98: ABRIL | D98: LUZ | E98: 80.8 | G98: =+G97+E98-F98 -> 80.8
D99: AGUA | E99: 2 | G99: =+G98+E99-F99 -> 82.8
D100: ALQUILER | E100: 600 | G100: =+G99+E100-F100 -> 682.8
A101: 43265 | B101: 14798 | C101: ABRIL | D101: LUZ | F101: 80.8 | G101: =+G100+E101-F101 -> 602
A102: 43265 | B102: 14798 | C102: ABRIL | D102: AGUA | F102: 2 | G102: =+G101+E102-F102 -> 600
A103: 43265 | B103: 14798 | C103: ABRIL | D103: ALQUILER | F103: 600 | G103: =+G102+E103-F103 -> 0
...

Sheet CAYO BASILIO
B3: CAYO HUAMANI BASILIO
A5: FECHA | B5: DOCUMENTO | C5: PERIODO | D5: CONCEPTO | E5: POR COBRAR | F5: PAGADO | G5: SALDO POR COBRAR
A6: 42736 | B6: SALDO AL 2016 | G6: 210
A7: 42736 | B7: AGUA RESIDUAL | C7: NOV.2016 | E7: 20 | G7: =+G6+E7-F7 -> 230
A8: 42745 | B8: 12062 | C8: A CUENTA DEL 2016 | F8: 210 | G8: =+G7+E8-F8 -> 20
A9: 42805 | B9: 12378 | C9: A CUENTA DEL 2016 | F9: 10 | G9: =+G8+E9-F9 -> 10
A10: 42836 | B10: 12528 | C10: CANCELACION DEL 2016 | F10: 10 | G10: =+G9+E10-F10 -> 0
A11: 42766 | B11: POR COBRAR | C11: ENERO | D11: LUZ | G11: =+G10+E11-F11 -> 0
D12: AGUA | G12: =+G11+E12-F12 -> 0
D13: ALQUILER | E13: 210 | G13: =+G12+E13-F13 -> 210
A14: 42775 | B14: 12239 | C14: ENERO | D14: ALQUILER | F14: 210 | G14: =+G13+E14-F14 -> 0
A15: 42794 | B15: POR COBRAR | C15: FEBRERO | D15: LUZ | G15: =+G14+E15-F15 -> 0
D16: AGUA | G16: =+G15+E16-F16 -> 0
D17: ALQUILER | E17: 210 | G17: =+G16+E17-F17 -> 210
A18: 42805 | B18: 12378 | C18: FEBRERO | D18: ALQUILER | F18: 210 | G18: =+G17+E18-F18 -> 0
A19: 42825 | B19: POR COBRAR | C19: MARZO | D19: LUZ | G19: =+G18+E19-F19 -> 0
D20: AGUA | G20: =+G19+E20-F20 -> 0
D21: ALQUILER | E21: 210 | G21: =+G20+E21-F21 -> 210
A22: 42836 | B22: 12528 | C22: MARZO | D22: ALQUILER | F22: 210 | G22: =+G21+E22-F22 -> 0
A23: 42855 | B23: POR COBRAR | C23: ABRIL | D23: LUZ | G23: =+G22+E23-F23 -> 0
D24: AGUA | G24: =+G23+E24-F24 -> 0
D25: ALQUILER | E25: 210 | G25: =+G24+E25-F25 -> 210
A26: 42873 | B26: 12689 | C26: ABRIL | D26: ALQUILER | F26: 210 | G26: =+G25+E26-F26 -> 0
A27: 42886 | B27: POR COBRAR | C27: MAYO | D27: LUZ | G27: =+G26+E27-F27 -> 0
D28: AGUA | G28: =+G27+E28-F28 -> 0
D29: ALQUILER | E29: 210 | G29: =+G28+E29-F29 -> 210
A30: 42905 | B30: 12850 | C30: MAYO | D30: ALQUILER | F30: 210 | G30: =+G29+E30-F30 -> 0
A31: 42916 | B31: POR COBRAR | C31: JUNIO | D31: LUZ | G31: =+G30+E31-F31 -> 0
D32: AGUA | G32: =+G31+E32-F32 -> 0
D33: ALQUILER | E33: 210 | G33: =+G32+E33-F33 -> 210
A34: 42931 | B34: 13019 | C34: JUNIO | D34: ALQUILER | F34: 210 | G34: =+G33+E34-F34 -> 0
A35: 42947 | B35: POR COBRAR | C35: JULIO | D35: LUZ | G35: =+G34+E35-F35 -> 0
D36: AGUA | G36: =+G35+E36-F36 -> 0
D37: ALQUILER | E37: 210 | G37: =+G36+E37-F37 -> 210
A38: 42947 | B38: 13067 | C38: JULIO | D38: ALQUILER | F38: 210 | G38: =+G37+E38-F38 -> 0
A39: 42978 | B39: POR COBRAR | C39: AGOSTO | D39: LUZ | G39: =+G38+E39-F39 -> 0
D40: AGUA | G40: =+G39+E40-F40 -> 0
D41: ALQUILER | E41: 210 | G41: =+G40+E41-F41 -> 210
A42: 42978 | B42: 13347 | C42: AGOSTO | D42: ALQUILER | F42: 210 | G42: =+G41+E42-F42 -> 0
A43: 43008 | B43: POR COBRAR | C43: SEPTIEMBRE | D43: LUZ | G43: =+G42+E43-F43 -> 0
D44: AGUA | G44: =+G43+E44-F44 -> 0
D45: ALQUILER | E45: 210 | G45: =+G44+E45-F45 -> 210
A46: 42994 | B46: 13475 | C46: SEPTIEMBRE | D46: ALQUILER | F46: 210 | G46: =+G45+E46-F46 -> 0
A47: 43039 | B47: POR COBRAR | C47: OCTUBRE | D47: LUZ | G47: =+G46+E47-F47 -> 0
D48: AGUA | G48: =+G47+E48-F48 -> 0
D49: ALQUILER | E49: 210 | G49: =+G48+E49-F49 -> 210
A50: 43011 | B50: 13583 | C50: OCTUBRE | D50: ALQUILER | F50: 210 | G50: =+G49+E50-F50 -> 0
A51: 43069 | B51: POR COBRAR | C51: NOVIEMBRE | D51: LUZ | G51: =+G50+E51-F51 -> 0
D52: AGUA | G52: =+G51+E52-F52 -> 0
D53: ALQUILER | E53: 210 | G53: =+G52+E53-F53 -> 210
A54: 43043 | B54: 13757 | C54: NOVIEMBRE | D54: ALQUILER | F54: 210 | G54: =+G53+E54-F54 -> 0
A55: 43100 | B55: POR COBRAR | C55: DICIEMBRE | D55: LUZ | G55: =+G54+E55-F55 -> 0
D56: AGUA | G56: =+G55+E56-F56 -> 0
D57: ALQUILER | E57: 210 | G57: =+G56+E57-F57 -> 210
A58: 43075 | B58: 13909 | C58: DICIEMBRE | D58: ALQUILER | F58: 210 | G58: =+G57+E58-F58 -> 0
A59: 43131 | B59: POR COBRAR | C59: ENERO | D59: LUZ | G59: =+G58+E59-F59 -> 0
D60: AGUA | G60: =+G59+E60-F60 -> 0
D61: ALQUILER | E61: 210 | G61: =+G60+E61-F61 -> 210
A62: 43136 | B62: 14184 | C62: ENERO | D62: ALQUILER | F62: 210 | G62: =+G61+E62-F62 -> 0
A63: 43159 | B63: POR COBRAR | C63: FEBRERO | D63: LUZ | G63: =+G62+E63-F63 -> 0
D64: AGUA | G64: =+G63+E64-F64 -> 0
D65: ALQUILER | E65: 210 | G65: =+G64+E65-F65 -> 210
A66: 43136 | B66: 14183 | C66: FEBRERO | D66: ALQUILER | F66: 210 | G66: =+G65+E66-F66 -> 0
A67: 43190 | B67: POR COBRAR | C67: MARZO | D67: LUZ | G67: =+G66+E67-F67 -> 0
D68: AGUA | G68: =+G67+E68-F68 -> 0
D69: ALQUILER | E69: 210 | G69: =+G68+E69-F69 -> 210
A70: 43172 | B70: 14349 | C70: MARZO | D70: ALQUILER | F70: 210 | G70: =+G69+E70-F70 -> 0
A71: 43220 | B71: POR COBRAR | C71: ABRIL | D71: LUZ | G71: =+G70+E71-F71 -> 0
D72: AGUA | G72: =+G71+E72-F72 -> 0
D73: ALQUILER | E73: 210 | G73: =+G72+E73-F73 -> 210
A74: 43200 | B74: 14452 | C74: ABRIL | D74: ALQUILER | F74: 210 | G74: =+G73+E74-F74 -> 0
A75: 43250 | B75: POR COBRAR | C75: MAYO | D75: LUZ | G75: =+G74+E75-F75 -> 0
D76: AGUA | G76: =+G75+E76-F76 -> 0
D77: ALQUILER | E77: 250 | G77: =+G76+E77-F77 -> 250
A78: 43252 | B78: 14738 | C78: MAYO | D78: ALQUILER | F78: 250 | G78: =+G77+E78-F78 -> 0
A79: 43281 | B79: POR COBRAR | C79: JUNIO | D79: LUZ | G79: =+G78+E79-F79 -> 0
D80: AGUA | G80: =+G79+E80-F80 -> 0
D81: ALQUILER | E81: 250 | G81: =+G80+E81-F81 -> 250
A82: 43287 | B82: 14902 | C82: JUNIO | D82: ALQUILER | F82: 250 | G82: =+G81+E82-F82 -> 0
A83: 43312 | B83: POR COBRAR | C83: JULIO | D83: LUZ | G83: =+G82+E83-F83 -> 0
D84: AGUA | G84: =+G83+E84-F84 -> 0
D85: ALQUILER | E85: 250 | G85: =+G84+E85-F85 -> 250
A86: 43322 | B86: 15033 | C86: JULIO | D86: ALQUILER | F86: 250 | G86: =+G85+E86-F86 -> 0
A87: 43343 | B87: POR COBRAR | C87: AGOSTO | D87: LUZ | G87: =+G86+E87-F87 -> 0
D88: AGUA | G88: =+G87+E88-F88 -> 0
D89: ALQUILER | E89: 250 | G89: =+G88+E89-F89 -> 250
A90: 43349 | B90: 15158 | C90: AGOSTO | D90: ALQUILER | F90: 250 | G90: =+G89+E90-F90 -> 0
A91: 43373 | B91: POR COBRAR | C91: SEPTIEMBRE | D91: LUZ | G91: =+G90+E91-F91 -> 0
D92: AGUA | G92: =+G91+E92-F92 -> 0
D93: ALQUILER | E93: 250 | G93: =+G92+E93-F93 -> 250
A94: 43379 | B94: 15328 | C94: SEPTIEMBRE | D94: ALQUILER | F94: 250 | G94: =+G93+E94-F94 -> 0
A95: 43404 | B95: POR COBRAR | C95: OCTUBRE | D95: LUZ | G95: =+G94+E95-F95 -> 0
D96: AGUA | G96: =+G95+E96-F96 -> 0
D97: ALQUILER | E97: 250 | G97: =+G96+E97-F97 -> 250
A98: 43409 | B98: 15469 | C98: OCTUBRE | D98: ALQUILER | F98: 250 | G98: =+G97+E98-F98 -> 0
A99: 43434 | B99: POR COBRAR | C99: NOVIEMBRE | D99: LUZ | G99: =+G98+E99-F99 -> 0
D100: AGUA | G100: =+G99+E100-F100 -> 0
D101: ALQUILER | E101: 250 | G101: =+G100+E101-F101 -> 250
A102: 43441 | B102: 15605 | C102: NOVIEMBRE | D102: ALQUILER | F102: 250 | G102: =+G101+E102-F102 -> 0
A103: 43465 | B103: POR COBRAR | C103: DICIEMBRE | D103: LUZ | G103: =+G102+E103-F103 -> 0
...

Sheet CCENCHO DAVID
B3: DAVID VICENTE CCENCHO CARRASCO
A5: FECHA | B5: DOCUMENTO | C5: PERIODO | D5: CONCEPTO | E5: POR COBRAR | F5: PAGADO | G5: SALDO POR COBRAR | I5: DNI | J5: 44002664
A6: 42736 | B6: SALDO AL 2016 | G6: 306.6
A7: 42744 | B7: 12055 | C7: A CUENTA DEL 2016 | F7: 210 | G7: =+G6+E7-F7 -> 96.6
A8: 42766 | B8: 12178 | C8: A CUENTA DEL 2016 | F8: 96.6 | G8: =+G7+E8-F8 -> 0
A9: 42766 | B9: POR COBRAR | C9: ENERO | D9: LUZ | E9: 13.5 | G9: =+G8+E9-F9 -> 13.5
D10: AGUA | E10: 2.8 | G10: =+G9+E10-F10 -> 16.3
D11: ALQUILER | E11: 210 | G11: =+G10+E11-F11 -> 226.3
A12: 42766 | B12: 12178 | C12: ENERO | D12: ALQUILER | F12: 210 | G12: =+G11+E12-F12 -> 16.3
A13: 42797 | B13: 12325 | C13: ENERO | D13: LUZ | F13: 13.5 | G13: =+G12+E13-F13 -> 2.8
A14: 42797 | B14: 12325 | C14: ENERO | D14: AGUA | F14: 2.8 | G14: =+G13+E14-F14 -> 1.1546319e-14
A15: 42794 | B15: POR COBRAR | C15: FEBRERO | D15: LUZ | E15: 13 | G15: =+G14+E15-F15 -> 13
D16: AGUA | E16: 2 | G16: =+G15+E16-F16 -> 15
D17: ALQUILER | E17: 210 | G17: =+G16+E17-F17 -> 225
A18: 42797 | B18: 12335 | C18: FEBRERO | D18: ALQUILER | F18: 210 | G18: =+G17+E18-F18 -> 15
A19: 42828 | B19: 12464 | C19: FEBRERO | D19: LUZ | F19: 13 | G19: =+G18+E19-F19 -> 2
A20: 42828 | B20: 12464 | C20: FEBRERO | D20: AGUA | F20: 2 | G20: =+G19+E20-F20 -> 0
A21: 42825 | B21: POR COBRAR | C21: MARZO | D21: LUZ | E21: 12 | G21: =+G20+E21-F21 -> 12
D22: AGUA | E22: 2 | G22: =+G21+E22-F22 -> 14
D23: ALQUILER | E23: 210 | G23: =+G22+E23-F23 -> 224
A24: 42828 | B24: 124640 | C24: MARZO | D24: ALQUILER | F24: 210 | G24: =+G23+E24-F24 -> 14
A25: 42858 | B25: 12608 | C25: MARZO | D25: LUZ | F25: 12 | G25: =+G24+E25-F25 -> 2
A26: 42858 | B26: 12608 | C26: MARZO | D26: AGUA | F26: 2 | G26: =+G25+E26-F26 -> 0
A27: 42855 | B27: POR COBRAR | C27: ABRIL | D27: LUZ | E27: 13 | G27: =+G26+E27-F27 -> 13
D28: AGUA | E28: 2 | G28: =+G27+E28-F28 -> 15
D29: ALQUILER | E29: 210 | G29: =+G28+E29-F29 -> 225
A30: 42858 | B30: 12608 | C30: ABRIL | D30: ALQUILER | F30: 210 | G30: =+G29+E30-F30 -> 15
A31: 42891 | B31: 12784 | C31: ABRIL | D31: LUZ | F31: 13 | G31: =+G30+E31-F31 -> 2
A32: 42891 | B32: 12784 | C32: ABRIL | D32: AGUA | F32: 2 | G32: =+G31+E32-F32 -> 0
A33: 42886 | B33: POR COBRAR | C33: MAYO | D33: LUZ | E33: 13 | G33: =+G32+E33-F33 -> 13
D34: AGUA | E34: 2 | G34: =+G33+E34-F34 -> 15
D35: ALQUILER | E35: 210 | G35: =+G34+E35-F35 -> 225
A36: 42891 | B36: 12784 | C36: MAYO | D36: ALQUILER | F36: 210 | G36: =+G35+E36-F36 -> 15
A37: 42920 | B37: 12952 | C37: MAYO | D37: LUZ | F37: 13 | G37: =+G36+E37-F37 -> 2
A38: 42920 | B38: 12952 | C38: MAYO | D38: AGUA | F38: 2 | G38: =+G37+E38-F38 -> 0
A39: 42916 | B39: POR COBRAR | C39: JUNIO | D39: LUZ | E39: 12.5 | G39: =+G38+E39-F39 -> 12.5
D40: AGUA | E40: 2 | G40: =+G39+E40-F40 -> 14.5
D41: ALQUILER | E41: 210 | G41: =+G40+E41-F41 -> 224.5
A42: 42920 | B42: 12952 | C42: JUNIO | D42: ALQUILER | F42: 210 | G42: =+G41+E42-F42 -> 14.5
A43: 42954 | B43: 13241 | C43: JUNIO | D43: LUZ | F43: 12.5 | G43: =+G42+E43-F43 -> 2
A44: 42954 | B44: 13241 | C44: JUNIO | D44: AGUA | F44: 2 | G44: =+G43+E44-F44 -> 0
A45: 42947 | B45: POR COBRAR | D45: LUZ | E45: 13 | G45: =+G44+E45-F45 -> 13
D46: AGUA | E46: 2 | G46: =+G45+E46-F46 -> 15
D47: ALQUILER | E47: 210 | G47: =+G46+E47-F47 -> 225
A48: 42954 | B48: 13241 | C48: JULIO | D48: ALQUILER | F48: 210 | G48: =+G47+E48-F48 -> 15
A49: 42984 | B49: 13401 | C49: JULIO | D49: LUZ | F49: 13 | G49: =+G48+E49-F49 -> 2
A50: 42984 | B50: 13401 | C50: JULIO | D50: AGUA | F50: 2 | G50: =+G49+E50-F50 -> 0
A51: 42978 | B51: POR COBRAR | C51: AGOSTO | D51: LUZ | E51: 13 | G51: =+G50+E51-F51 -> 13
D52: AGUA | E52: 2 | G52: =+G51+E52-F52 -> 15
D53: ALQUILER | E53: 210 | G53: =+G52+E53-F53 -> 225
A54: 42984 | B54: 13401 | C54: AGOSTO | D54: ALQUILER | F54: 210 | G54: =+G53+E54-F54 -> 15
A55: 43014 | B55: 13610 | C55: AGOSTO | D55: LUZ | F55: 13 | G55: =+G54+E55-F55 -> 2
A56: 43014 | B56: 13610 | C56: AGOSTO | D56: AGUA | F56: 2 | G56: =+G55+E56-F56 -> 0
A57: 43008 | B57: POR COBRAR | C57: SEPTIEMBRE | D57: LUZ | E57: 8 | G57: =+G56+E57-F57 -> 8
D58: AGUA | E58: 2 | G58: =+G57+E58-F58 -> 10
D59: ALQUILER | E59: 210 | G59: =+G58+E59-F59 -> 220
A60: 42989 | B60: 13444 | C60: SEPTIEMBRE | D60: ALQUILER | F60: 210 | G60: =+G59+E60-F60 -> 10
A61: 43426 | B61: 13806 | C61: SEPTIEMBRE | D61: LUZ | F61: 8 | G61: =+G60+E61-F61 -> 2
A62: 43426 | B62: 13806 | C62: SEPTIEMBRE | D62: AGUA | F62: 2 | G62: =+G61+E62-F62 -> 0
A63: 43039 | B63: POR COBRAR | C63: OCTUBRE | D63: LUZ | E63: 8 | G63: =+G62+E63-F63 -> 8
D64: AGUA | E64: 2 | G64: =+G63+E64-F64 -> 10
D65: ALQUILER | E65: 210 | G65: =+G64+E65-F65 -> 220
A66: 43014 | B66: 13610 | C66: OCTUBRE | D66: ALQUILER | F66: 210 | G66: =+G65+E66-F66 -> 10
A67: 43349 | B67: 15165 | C67: OCTUBRE | D67: LUZ | F67: 8 | G67: =+G66+E67-F67 -> 2
A68: 43349 | B68: 15165 | C68: OCTUBRE | D68: AGUA | F68: 2 | G68: =+G67+E68-F68 -> 0
A69: 43069 | B69: POR COBRAR | C69: NOVIEMBRE | D69: LUZ | E69: 8.2 | G69: =+G68+E69-F69 -> 8.2
D70: AGUA | E70: 2 | G70: =+G69+E70-F70 -> 10.2
D71: ALQUILER | E71: 210 | G71: =+G70+E71-F71 -> 220.2
A72: 43061 | B72: 13806 | C72: NOVIEMBRE | D72: ALQUILER | F72: 210 | G72: =+G71+E72-F72 -> 10.2
A73: 43349 | B73: 15165 | C73: NOVIEMBRE | D73: LUZ | F73: 8.2 | G73: =+G72+E73-F73 -> 2
A74: 43349 | B74: 15165 | C74: NOVIEMBRE | D74: AGUA | F74: 2 | G74: =+G73+E74-F74 -> -1.0658141e-14
A75: 43100 | B75: POR COBRAR | C75: DICIEMBRE | D75: LUZ | E75: 8.9 | G75: =+G74+E75-F75 -> 8.9
D76: AGUA | E76: 2 | G76: =+G75+E76-F76 -> 10.9
D77: ALQUILER | E77: 210 | G77: =+G76+E77-F77 -> 220.9
A78: 43124 | B78: 14137 | C78: DICIEMBRE | D78: LUZ | F78: 8.9 | G78: =+G77+E78-F78 -> 212
A79: 43124 | B79: 14137 | C79: DICIEMBRE | D79: AGUA | F79: 2 | G79: =+G78+E79-F79 -> 210
A80: 43129 | B80: 14147 | C80: DICIEMBRE | D80: ALQUILER | F80: 210 | G80: =+G79+E80-F80 -> 0
A81: 43131 | B81: POR COBRAR | C81: ENERO | D81: LUZ | E81: 8 | G81: =+G80+E81-F81 -> 8
D82: AGUA | E82: 2 | G82: =+G81+E82-F82 -> 10
D83: ALQUILER | E83: 210 | G83: =+G82+E83-F83 -> 220
A84: 43129 | B84: 14147 | C84: ENERO | D84: ALQUILER | F84: 210 | G84: =+G83+E84-F84 -> 10
A85: 43161 | B85: 14320 | C85: ENERO | D85: LUZ | F85: 8 | G85: =+G84+E85-F85 -> 2
A86: 43161 | B86: 14320 | C86: ENERO | D86: AGUA | F86: 2 | G86: =+G85+E86-F86 -> 0
A87: 43159 | B87: POR COBRAR | C87: FEBRERO | D87: LUZ | E87: 9.9 | G87: =+G86+E87-F87 -> 9.9
D88: AGUA | E88: 2 | G88: =+G87+E88-F88 -> 11.9
D89: ALQUILER | E89: 210 | G89: =+G88+E89-F89 -> 221.9
A90: 43161 | B90: 14321 | C90: FEBRERO | D90: ALQUILER | F90: 210 | G90: =+G89+E90-F90 -> 11.9
A91: 43192 | B91: 14426 | C91: FEBRERO | D91: LUZ | F91: 9.9 | G91: =+G90+E91-F91 -> 2
A92: 43192 | B92: 14426 | C92: FEBRERO | D92: AGUA | F92: 2 | G92: =+G91+E92-F92 -> 5.3290705e-15
A93: 43190 | B93: POR COBRAR | C93: MARZO | D93: LUZ | E93: 9.5 | G93: =+G92+E93-F93 -> 9.5
D94: AGUA | E94: 2 | G94: =+G93+E94-F94 -> 11.5
D95: ALQUILER | E95: 210 | G95: =+G94+E95-F95 -> 221.5
A96: 43192 | B96: 14426 | C96: MARZO | D96: ALQUILER | F96: 210 | G96: =+G95+E96-F96 -> 11.5
A97: 43227 | B97: 14577 | C97: MARZO | D97: LUZ | F97: 9.5 | G97: =+G96+E97-F97 -> 2
A98: 43227 | B98: 14577 | C98: MARZO | D98: AGUA | F98: 2 | G98: =+G97+E98-F98 -> 0
A99: 43220 | B99: POR COBRAR | C99: ABRIL | D99: LUZ | E99: 9.8 | G99: =+G98+E99-F99 -> 9.8
D100: AGUA | E100: 2 | G100: =+G99+E100-F100 -> 11.8
D101: ALQUILER | E101: 210 | G101: =+G100+E101-F101 -> 221.8
A102: 43227 | B102: 14577 | C102: ABRIL | D102: ALQUILER | F102: 210 | G102: =+G101+E102-F102 -> 11.8
A103: 43243 | B103: 14661 | C103: ABRIL | D103: LUZ | F103: 9.8 | G103: =+G102+E103-F103 -> 2
...

Sheet CERDAN MARIA
B3: CERDAN MUÑOZ MARIA
A5: FECHA | B5: DOCUMENTO | C5: PERIODO | D5: CONCEPTO | E5: POR COBRAR | F5: PAGADO | G5: SALDO POR COBRAR
A6: 42736 | B6: SALDO AL 2016 | G6: 31.9
A7: 42753 | B7: 12116 | C7: CANCELACION DEL 2016 | F7: 31.9 | G7: =+G6+E7-F7 -> 0
A8: 42766 | B8: POR COBRAR | C8: ENERO | D8: LUZ | E8: 29.7 | G8: =+G7+E8-F8 -> 29.7
D9: AGUA | E9: 2.8 | G9: =+G8+E9-F9 -> 32.5
D10: ALQUILER | E10: 210 | G10: =+G9+E10-F10 -> 242.5
A11: 42766 | B11: 12179 | C11: ENERO | D11: ALQUILER | F11: 210 | G11: =+G10+E11-F11 -> 32.5
A12: 42789 | B12: 12291 | C12: ENERO | D12: LUZ | F12: 29.7 | G12: =+G11+E12-F12 -> 2.8
A13: 42789 | B13: 12291 | C13: ENERO | D13: AGUA | F13: 2.8 | G13: =+G12+E13-F13 -> 0
A14: 42794 | B14: POR COBRAR | C14: FEBRERO | D14: LUZ | E14: 28.5 | G14: =+G13+E14-F14 -> 28.5
D15: AGUA | E15: 2 | G15: =+G14+E15-F15 -> 30.5
D16: ALQUILER | E16: 210 | G16: =+G15+E16-F16 -> 240.5
A17: 42794 | B17: 12306 | C17: FEBRERO | D17: ALQUILER | F17: 210 | G17: =+G16+E17-F17 -> 30.5
A18: 42828 | B18: 12470 | C18: FEBRERO | D18: LUZ | F18: 28.5 | G18: =+G17+E18-F18 -> 2
A19: 42828 | B19: 12470 | C19: FEBRERO | D19: AGUA | F19: 2 | G19: =+G18+E19-F19 -> 0
A20: 42825 | B20: POR COBRAR | C20: MARZO | D20: LUZ | E20: 26.9 | G20: =+G19+E20-F20 -> 26.9
D21: AGUA | E21: 2 | G21: =+G20+E21-F21 -> 28.9
D22: ALQUILER | E22: 210 | G22: =+G21+E22-F22 -> 238.9
A23: 42828 | B23: 12470 | C23: MARZO | D23: ALQUILER | F23: 210 | G23: =+G22+E23-F23 -> 28.9
A24: 42859 | B24: 12632 | C24: MARZO | D24: LUZ | F24: 26.9 | G24: =+G23+E24-F24 -> 2
A25: 42859 | B25: 12632 | C25: MARZO | D25: AGUA | F25: 2 | G25: =+G24+E25-F25 -> 7.1054274e-15
A26: 42855 | B26: POR COBRAR | C26: ABRIL | D26: LUZ | E26: 28.1 | G26: =+G25+E26-F26 -> 28.1
D27: AGUA | E27: 2 | G27: =+G26+E27-F27 -> 30.1
D28: ALQUILER | E28: 210 | G28: =+G27+E28-F28 -> 240.1
A29: 42859 | B29: 12632 | C29: ABRIL | D29: ALQUILER | F29: 210 | G29: =+G28+E29-F29 -> 30.1
A30: 42887 | B30: 12760 | C30: ABRIL | D30: LUZ | F30: 28.1 | G30: =+G29+E30-F30 -> 2
A31: 42887 | B31: 12760 | C31: ABRIL | D31: AGUA | F31: 2 | G31: =+G30+E31-F31 -> 2.1316282e-14
A32: 42886 | B32: POR COBRAR | C32: MAYO | D32: LUZ | E32: 26.9 | G32: =+G31+E32-F32 -> 26.9
D33: AGUA | E33: 2 | G33: =+G32+E33-F33 -> 28.9
D34: ALQUILER | E34: 210 | G34: =+G33+E34-F34 -> 238.9
A35: 42916 | B35: 12891 | C35: MAYO | D35: LUZ | F35: 26.9 | G35: =+G34+E35-F35 -> 212
D36: AGUA | F36: 2 | G36: =+G35+E36-F36 -> 210
A37: 42887 | B37: 12760 | C37: MAYO | D37: ALQUILER | F37: 210 | G37: =+G36+E37-F37 -> 0
A38: 42916 | B38: POR COBRAR | C38: JUNIO | D38: LUZ | E38: 26.1 | G38: =+G37+E38-F38 -> 26.1
D39: AGUA | E39: 2 | G39: =+G38+E39-F39 -> 28.1
D40: ALQUILER | E40: 210 | G40: =+G39+E40-F40 -> 238.1
A41: 42916 | B41: 12891 | C41: JUNIO | D41: ALQUILER | F41: 210 | G41: =+G40+E41-F41 -> 28.1
A42: 42948 | B42: 13206 | C42: JUNIO | D42: AGUA | F42: 2 | G42: =+G41+E42-F42 -> 26.1
A43: 42948 | B43: 13206 | C43: JUNIO | D43: LUZ | F43: 26.1 | G43: =+G42+E43-F43 -> 0
A44: 42947 | B44: POR COBRAR | C44: JULIO | D44: LUZ | E44: 24.9 | G44: =+G43+E44-F44 -> 24.9
D45: AGUA | E45: 2 | G45: =+G44+E45-F45 -> 26.9
D46: ALQUILER | E46: 210 | G46: =+G45+E46-F46 -> 236.9
A47: 42948 | B47: 13206 | C47: JULIO | D47: ALQUILER | F47: 210 | G47: =+G46+E47-F47 -> 26.9
A48: 42982 | B48: 13386 | C48: JULIO | D48: LUZ | F48: 24.9 | G48: =+G47+E48-F48 -> 2
A49: 42982 | B49: 13386 | C49: JULIO | D49: AGUA | F49: 2 | G49: =+G48+E49-F49 -> 7.1054274e-15
A50: 42978 | B50: POR COBRAR | C50: AGOSTO | D50: LUZ | E50: 24.9 | G50: =+G49+E50-F50 -> 24.9
D51: AGUA | E51: 2 | G51: =+G50+E51-F51 -> 26.9
D52: ALQUILER | E52: 210 | G52: =+G51+E52-F52 -> 236.9
A53: 42982 | B53: 13386 | C53: AGOSTO | D53: ALQUILER | F53: 210 | G53: =+G52+E53-F53 -> 26.9
A54: 43010 | B54: 13576 | C54: AGOSTO | D54: LUZ | F54: 24.9 | G54: =+G53+E54-F54 -> 2
A55: 43010 | B55: 13576 | C55: AGOSTO | D55: AGUA | F55: 2 | G55: =+G54+E55-F55 -> 7.1054274e-15
A56: 43008 | B56: POR COBRAR | C56: SEPTIEMBRE | D56: LUZ | E56: 21.3 | G56: =+G55+E56-F56 -> 21.3
D57: AGUA | E57: 2 | G57: =+G56+E57-F57 -> 23.3
D58: ALQUILER | E58: 210 | G58: =+G57+E58-F58 -> 233.3
A59: 43010 | B59: 13576 | C59: SEPTIEMBRE | D59: ALQUILER | F59: 210 | G59: =+G58+E59-F59 -> 23.3
A60: 43041 | B60: 13746 | C60: SEPTIEMBRE | D60: LUZ | F60: 21.3 | G60: =+G59+E60-F60 -> 2
A61: 43041 | B61: 13746 | C61: SEPTIEMBRE | D61: AGUA | F61: 2 | G61: =+G60+E61-F61 -> 1.0658141e-14
A62: 43039 | B62: POR COBRAR | C62: OCTUBRE | D62: LUZ | E62: 21.2 | G62: =+G61+E62-F62 -> 21.2
D63: AGUA | E63: 2 | G63: =+G62+E63-F63 -> 23.2
D64: ALQUILER | E64: 210 | G64: =+G63+E64-F64 -> 233.2
A65: 43062 | B65: 13817 | C65: OCTUBRE | D65: LUZ | F65: 21.2 | G65: =+G64+E65-F65 -> 212
A66: 43062 | B66: 13817 | C66: OCTUBRE | D66: AGUA | F66: 2 | G66: =+G65+E66-F66 -> 210
A67: 43041 | B67: 13746 | C67: OCTUBRE | D67: ALQUILER | F67: 210 | G67: =+G66+E67-F67 -> 0
A68: 43069 | B68: POR COBRAR | C68: NOVIEMBRE | D68: LUZ | E68: 22.6 | G68: =+G67+E68-F68 -> 22.6
D69: AGUA | E69: 2 | G69: =+G68+E69-F69 -> 24.6
D70: ALQUILER | E70: 210 | G70: =+G69+E70-F70 -> 234.6
A71: 43073 | B71: 13903 | C71: NOVIEMBRE | D71: ALQUILER | F71: 210 | G71: =+G70+E71-F71 -> 24.6
A72: 43099 | B72: 14000 | C72: NOVIEMBRE | D72: LUZ | F72: 22.6 | G72: =+G71+E72-F72 -> 2
A73: 43099 | B73: 14000 | C73: NOVIEMBRE | D73: AGUA | F73: 2 | G73: =+G72+E73-F73 -> -7.1054274e-15
A74: 43100 | B74: POR COBRAR | C74: DICIEMBRE | D74: LUZ | E74: 24.6 | G74: =+G73+E74-F74 -> 24.6
D75: AGUA | E75: 2 | G75: =+G74+E75-F75 -> 26.6
D76: ALQUILER | E76: 210 | G76: =+G75+E76-F76 -> 236.6
A77: 43099 | B77: 14000 | C77: DICIEMBRE | D77: ALQUILER | F77: 210 | G77: =+G76+E77-F77 -> 26.6
A78: 43118 | B78: 14088 | C78: DICIEMBRE | D78: LUZ | F78: 24.6 | G78: =+G77+E78-F78 -> 2
A79: 43118 | B79: 14088 | C79: DICIEMBRE | D79: AGUA | F79: 2 | G79: =+G78+E79-F79 -> -7.1054274e-15
A80: 43131 | B80: POR COBRAR | C80: ENERO | D80: LUZ | E80: 21.9 | G80: =+G79+E80-F80 -> 21.9
D81: AGUA | E81: 2 | G81: =+G80+E81-F81 -> 23.9
D82: ALQUILER | E82: 210 | G82: =+G81+E82-F82 -> 233.9
A83: 43133 | B83: 14180 | C83: ENERO | D83: ALQUILER | F83: 210 | G83: =+G82+E83-F83 -> 23.9
A84: 43160 | B84: 14309 | C84: ENERO | D84: LUZ | F84: 21.9 | G84: =+G83+E84-F84 -> 2
A85: 43160 | B85: 14309 | C85: ENERO | D85: AGUA | F85: 2 | G85: =+G84+E85-F85 -> -2.1316282e-14
A86: 43159 | B86: POR COBRAR | C86: FEBRERO | D86: LUZ | E86: 27.1 | G86: =+G85+E86-F86 -> 27.1
D87: AGUA | E87: 2 | G87: =+G86+E87-F87 -> 29.1
D88: ALQUILER | E88: 210 | G88: =+G87+E88-F88 -> 239.1
A89: 43195 | B89: 14443 | C89: FEBRERO | D89: LUZ | F89: 27.1 | G89: =+G88+E89-F89 -> 212
A90: 43195 | B90: 14443 | C90: FEBRERO | D90: AGUA | F90: 2 | G90: =+G89+E90-F90 -> 210
A91: 43160 | B91: 14309 | C91: FEBRERO | D91: ALQUILER | F91: 210 | G91: =+G90+E91-F91 -> 0
A92: 43190 | B92: POR COBRAR | C92: MARZO | D92: LUZ | E92: 26 | G92: =+G91+E92-F92 -> 26
D93: AGUA | E93: 2 | G93: =+G92+E93-F93 -> 28
D94: ALQUILER | E94: 210 | G94: =+G93+E94-F94 -> 238
A95: 43195 | B95: 14443 | C95: MARZO | D95: ALQUILER | F95: 210 | G95: =+G94+E95-F95 -> 28
A96: 43222 | B96: 14551 | C96: MARZO | D96: LUZ | F96: 26 | G96: =+G95+E96-F96 -> 2
A97: 43222 | B97: 14551 | C97: MARZO | D97: AGUA | F97: 2 | G97: =+G96+E97-F97 -> 0
A98: 43220 | B98: POR COBRAR | C98: ABRIL | D98: LUZ | E98: 26.9 | G98: =+G97+E98-F98 -> 26.9
D99: AGUA | E99: 2 | G99: =+G98+E99-F99 -> 28.9
D100: ALQUILER | E100: 210 | G100: =+G99+E100-F100 -> 238.9
A101: 43222 | B101: 14551 | C101: ABRIL | D101: ALQUILER | F101: 210 | G101: =+G100+E101-F101 -> 28.9
A102: 43243 | B102: 14656 | C102: ABRIL | D102: LUZ | F102: 26.902 | G102: =+G101+E102-F102 -> 1.998
A103: 43243 | B103: 14656 | C103: ABRIL | D103: AGUA | F103: 2 | G103: =+G102+E103-F103 -> -0.002
...

Sheet CERRON OBDULIA
B3: OBDULIA CERRON GALVAN
A5: FECHA | B5: DOCUMENTO | C5: PERIODO | D5: CONCEPTO | E5: POR COBRAR | F5: PAGADO | G5: SALDO POR COBRAR
A7: 44561 | B7: POR COBRAR | C7: DICIEMBRE | D7: ALQUILER | E7: 300 | G7: =G6+E7-F7 -> 300
A8: 44534 | B8: EB01-248 | C8: DICIEMBRE | D8: ALQUILER | F8: 300 | G8: =G7+E8-F8 -> 0
A9: 44592 | B9: POR COBRAR | C9: ENERO | D9: ALQUILER | E9: 300 | G9: =G8+E9-F9 -> 300
D10: ALQUILER | E10: 130 | G10: =G9+E10-F10 -> 430
A11: 44567 | B11: EB01-360 | C11: ENERO | D11: ALQUILER | F11: 300 | G11: =G10+E11-F11 -> 130
A12: 44576 | B12: EB01-387 | C12: ENERO | D12: ALQUILER | F12: 130 | G12: =G11+E12-F12 -> 0
A13: 44620 | B13: POR COBRAR | C13: FEBRERO | D13: ALQUILER | E13: 300 | G13: =G12+E13-F13 -> 300
A14: 44597 | B14: EB01-467 | C14: FEBRERO | D14: ALQUILER | F14: 300 | G14: =G13+E14-F14 -> 0
A15: 44651 | B15: POR COBRAR | C15: MARZO | D15: ALQUILER | E15: 300 | G15: =G14+E15-F15 -> 300
A16: 44625 | B16: EB01-561 | C16: MARZO | D16: ALQUILER | F16: 300 | G16: =G15+E16-F16 -> 0
A17: 44681 | B17: POR COBRAR | C17: ABRIL | D17: ALQUILER | E17: 300 | G17: =G16+E17-F17 -> 300
A18: 44648 | B18: EB01-610 | C18: ABRIL | D18: ALQUILER | F18: 300 | G18: =G17+E18-F18 -> 0
D19: POR ARREGLO DE BAÑO | E19: 20 | G19: =G18+E19-F19 -> 20
A20: 44648 | B20: EB01-610 | C20: ABRIL | D20: POR ARREGLO DE BAÑO | F20: 20 | G20: =G19+E20-F20 -> 0
A21: 44865 | B21: POR COBRAR | C21: OCTUBRE | D21: ALQUILER | E21: 350 | G21: =G20+E21-F21 -> 350
A22: 44840 | B22: EB01-1341 | C22: OCTUBRE | D22: ALQUILER | F22: 350 | G22: =G21+E22-F22 -> 0
A23: 44865 | B23: POR COBRAR | C23: NOVIEMBRE | D23: ALQUILER | E23: 350 | G23: =G22+E23-F23 -> 350
A24: 44872 | B24: EB01-1445 | C24: NOVIEMBRE | D24: ALQUILER | F24: 350 | G24: =G23+E24-F24 -> 0
A25: 44926 | B25: POR COBRAR | C25: DICIEMBRE | D25: ALQUILER | E25: 350 | G25: =G24+E25-F25 -> 350
A26: 44901 | B26: EB01-1553 | C26: DICIEMBRE | D26: ALQUILER | F26: 350 | G26: =G25+E26-F26 -> 0
A27: 44957 | B27: POR COBRAR | C27: ENERO | D27: ALQUILER | E27: 350 | G27: =G26+E27-F27 -> 350
A28: 44931 | B28: EB01-1649 | C28: ENERO | D28: ALQUILER | F28: 350 | G28: =G27+E28-F28 -> 0
D29: ALQUILER MARTES Y JUEVES POR UN MES | E29: 180
A30: 44950 | B30: EB01-1688 | C30: ENERO | D30: ALQUILER MARTES Y JUEVES POR UN MES | F30: 180
A31: 44958 | B31: POR COBRAR | C31: FEBRERO | D31: ALQUILER | E31: 350 | G31: =G28+E31-F31 -> 350
A32: 44939 | B32: EB01-1668 | C32: FEBRERO | D32: ALQUILER | F32: 350 | G32: =G31+E32-F32 -> 0
A33: 45016 | B33: POR COBRAR | C33: MARZO | D33: ALQUILER | E33: 350 | G33: =G32+E33-F33 -> 350
A34: 44988 | B34: EB01-1853 | C34: MARZO | D34: ALQUILER | F34: 350 | G34: =G33+E34-F34 -> 0
