Workbook

Sheet 01-02-2026
A1: INGRESOS DEL DIA 01-02-2026
A3: INQUILINO | B3: COMPROBANTE | C3: DETALLE | D3: LUZ | E3: AGUA | F3: ALQUILER | G3: ESPACIO | H3: PARQUEO | I3: TICKET | J3: TOTAL
J4: =SUM(D4:I4) -> 0
J5: =SUM(D5:I5) -> 0
J6: =SUM(D6:I6) -> 0
J7: =SUM(D7:I7) -> 0
J8: =SUM(D8:I8) -> 0
J9: =SUM(D9:I9) -> 0
J10: =SUM(D10:I10) -> 0
J11: =SUM(D11:I11) -> 0
J12: =SUM(D12:I12) -> 0
J13: =SUM(D13:I13) -> 0
J14: =SUM(D14:I14) -> 0
J15: =SUM(D15:I15) -> 0
... J21: =SUM(D21:I21) -> 0
A22: TOTAL | D22: =SUM(D4:D21) -> 0 | E22: =SUM(E4:E21) -> 0 | F22: =SUM(F4:F21) -> 0 | G22: =SUM(G4:G21) -> 0 | H22: =SUM(H4:H21) -> 0 | I22: =SUM(I4:I21) -> 0 | J22: =SUM(J4:J21) -> 0
A24: BBVA
A25: INQUILINOS | B25: COMPROBANTE | C25: DETALLE | D25: LUZ | E25: AGUA | F25: ALQUILER | G25: ESPACIO | H25: DEPOSITO | I25: TICKET | J25: TOTAL
J26: =SUM(D26:I26) -> 0
J27: =SUM(D27:I27) -> 0
J28: =SUM(D28:I28) -> 0
J29: =SUM(D29:I29) -> 0 | L29: TOTAL QR | M29: =J30+J38 -> 0
A30: TOTAL | J30: =SUM(J26:J29) -> 0
A32: BBVA
A33: SOCIOS | B33: RECIBO DE SERVICIO | C33: DETALLE | D33: LUZ | E33: AGUA | F33: G. ADM | G33: P. SOCIAL | H33: DEPOSITO | I33: P.S X FALLECIMIENTO | J33: TOTAL
J34: =SUM(D34:I34) -> 0
J35: =SUM(D35:I35) -> 0
J36: =SUM(D36:I36) -> 0
J37: =SUM(D37:I37) -> 0
A38: TOTAL | J38: =SUM(J34:J37) -> 0
A42: SOCIO | B42: RECIBO DE SERVICIO | C42: DETALLE | D42: LUZ | E42: AGUA | F42: G. ADM | G42: P. SOCIAL | H42: P.S X FALLECIMIENTO | I42: DEPOSITO | J42: TOTAL
J43: =SUM(D43:I43) -> 0
J44: =SUM(D44:I44) -> 0
J45: =SUM(D45:I45) -> 0
J46: =SUM(D46:I46) -> 0
J47: =SUM(D47:I47) -> 0
J48: =SUM(D48:I48) -> 0
J49: =SUM(D49:I49) -> 0
J50: =SUM(D50:I50) -> 0
J51: =SUM(D51:I51) -> 0
J52: =SUM(D52:I52) -> 0
J53: =SUM(D53:I53) -> 0
J54: =SUM(D54:I54) -> 0
... J56: =SUM(D56:I56) -> 0
A57: TOTAL | D57: =SUM(D43:D56) -> 0 | E57: =SUM(E43:E56) -> 0 | F57: =SUM(F43:F56) -> 0 | G57: =SUM(G43:G56) -> 0 | H57: =SUM(H43:H56) -> 0 | I57: =SUM(I43:I56) -> 0 | J57: =SUM(J43:J56) -> 0
A60: TOTAL DE INGRESOS | J60: =+J22+J57 -> 0
A63: SRTA. FATIMA SIHUE
A64: COBRANZA SOCIOS
A65: COBRANZA INQUILINOS
A68: SRA. MARIA CUYA ARANGO
A69: COBRANZA DE BAÑO DEL 1ER PISO | J69: 444
A72: COBRANZA DE BAÑO DEL 2DO PISO
A74: TOTAL GENERAL DE INGRESOS | J74: =SUM(J60:J73) -> 444
A76: EGRESOS DEL DIA 01-02-2026
A77: CAJA
A78: RESPONSABLE | B78: COMPROBANTE | C78: DETALLE | J78: TOTAL
A92: TOTAL DE EGRESOS | J92: =SUM(J79:J91) -> 0
A95: RESUMEN
A96: TOTAL GENERAL | B96: =+J74 -> 444
A97: TOTAL DE EGRESOS | B97: =+J92 -> 0
A98: SALDO | B98: =++B96-B97 -> 444

Sheet 02-02-2026
A1: INGRESOS DEL DIA 02-02-2026
A3: INQUILINO | B3: COMPROBANTE | C3: DETALLE | D3: LUZ | E3: AGUA | F3: ALQUILER | G3: LOCAL 2DO PISO | H3: PARQUEO | I3: TICKET | J3: TOTAL
A4: PAÑITOS HUMEDOS | B4: TK 50748 | C4: 46054 | I4: 6 | J4: =SUM(D4:I4) -> 6
A5: JULIA | B5: TK 50749 | C5: 46054 | I5: 6 | J5: =SUM(D5:I5) -> 6
A6: JOSE | B6: TK 50750 | C6: 46054 | I6: 10 | J6: =SUM(D6:I6) -> 10
A7: JOSE | B7: TK 50751 | C7: 46054 | I7: 10 | J7: =SUM(D7:I7) -> 10
A8: ANATOLIA | B8: TK 50752 | C8: 46054 | I8: 10 | J8: =SUM(D8:I8) -> 10
A9: DESARMADORES | B9: TK 50753 | C9: 46054 | I9: 6 | J9: =SUM(D9:I9) -> 6
A10: ALFONSO GONZALO HUAMANI JUAREZ | B10: EB01-6779 | C10: 46054 | G10: 550 | J10: =SUM(D10:I10) -> 550
A11: LA ROSA MARGARITA | B11: EB01-6780 | C11: 46023 | F11: 800 | J11: =SUM(D11:I11) -> 800
A12: VIOLETA RETAMOZO | B12: EB01-6781 | C12: 46113 | G12: 100 | J12: =SUM(D12:I12) -> 100
A13: ZANABRIA LILIA | B13: EB01-6782 | C13: 46023 | F13: 350 | J13: =SUM(D13:I13) -> 350
A14: MAYHUASCA DORIS | B14: EB01-6783 | C14: 46023 | F14: 80 | J14: =SUM(D14:I14) -> 80
A15: CHOQUEHUANCA DERSE | B15: EB01-6784 | C15: 46023 | F15: 350 | J15: =SUM(D15:I15) -> 350
A16: PEÑA ASHLEY | B16: EB01-6785 | C16: 46054 | F16: 1000 | J16: =SUM(D16:I16) -> 1000
A17: ANCHAYA ABEL | B17: EB01-6786 | C17: 45962 | F17: 50 | J17: =SUM(D17:I17) -> 50
A18: PARQUEO | B18: EB01-6787 | C18: 46054 | H18: 56 | J18: =SUM(D18:I18) -> 56
A19: PRUDENCIO TUEROS | B19: EB01-6788 | C19: 46023 | F19: 500 | J19: =SUM(D19:I19) -> 500
A20: PARQUEO | B20: EB01-6790 | C20: 46054 | H20: 55.9 | J20: =SUM(D20:I20) -> 55.9
A21: CHOQUEHUANCA DERSE | B21: RII 3227 | C21: 45992 | D21: 7.7 | E21: 5 | J21: =SUM(D21:I21) -> 12.7
A22: PEÑA ASHLEY | B22: RII 3228 | C22: 45992 | D22: 30.9 | E22: 5 | J22: =SUM(D22:I22) -> 35.9
J23: =SUM(D23:I23) -> 0
J24: =SUM(D24:I24) -> 0
J25: =SUM(D25:I25) -> 0
J26: =SUM(D26:I26) -> 0
J27: =SUM(D27:I27) -> 0
A28: TOTAL | D28: =SUM(D4:D27) -> 38.6 | E28: =SUM(E4:E27) -> 10 | F28: =SUM(F4:F27) -> 3130 | G28: =SUM(G4:G27) -> 650 | H28: =SUM(H4:H27) -> 111.9 | I28: =SUM(I4:I27) -> 48 | J28: =SUM(J4:J27) -> 3988.5
A30: BBVA
A31: INQUILINOS | B31: COMPROBANTE | C31: DETALLE | D31: LUZ | E31: AGUA | F31: ALQUILER | G31: ESPACIO | H31: DEPOSITO | I31: TICKET | J31: TOTAL
A32: ADMINISTRADORA DE SERVICIOS FUNERARIOS SAC | B32: E001-310 | C32: 46054 | G32: 30 | J32: =SUM(D32:I32) -> 30
J33: =SUM(D33:I33) -> 0
J34: =SUM(D34:I34) -> 0
J35: =SUM(D35:I35) -> 0 | L35: TOTAL QR | M35: =J36+J44 -> 1197.6
A36: TOTAL | J36: =SUM(J32:J35) -> 30
A38: BBVA
A39: SOCIOS | B39: RECIBO DE SERVICIO | C39: DETALLE | D39: LUZ | E39: AGUA | F39: G. ADM | G39: P. SOCIAL | H39: DEPOSITO | I39: P.S X FALLECIMIENTO | J39: TOTAL
A40: QUISPE MIGUEL | B40: RI 32446 | C40: 45992 | D40: 618.6 | E40: 14 | J40: =SUM(D40:I40) -> 632.6
A41: NICHO ESTEPHANY | B41: RI 32447 | C41: 45992 | D41: 391.4 | E41: 78.6 | F41: 60 | G41: 5 | J41: =SUM(D41:I41) -> 535
J42: =SUM(D42:I42) -> 0
J43: =SUM(D43:I43) -> 0
A44: TOTAL | J44: =SUM(J40:J43) -> 1167.6
A48: SOCIO | B48: RECIBO DE SERVICIO | C48: DETALLE | D48: LUZ | E48: AGUA | F48: G. ADM | G48: P. SOCIAL | H48: P.S X FALLECIMIENTO | I48: DEPOSITO | J48: TOTAL
A49: DAVILA MARISOL | B49: RI 32448 | C49: 45962 | D49: 50.5 | E49: 6 | J49: =SUM(D49:I49) -> 56.5
C50: 45992 | D50: 51.2 | E50: 6 | J50: =SUM(D50:I50) -> 57.2
A51: QUINTANA GLICERIO | B51: RI 32449 | C51: 45962 | D51: 32.3 | E51: 6 | J51: =SUM(D51:I51) -> 38.3
C52: 45992 | D52: 29.5 | E52: 6 | J52: =SUM(D52:I52) -> 35.5
J53: =SUM(D53:I53) -> 0
J54: =SUM(D54:I54) -> 0
J55: =SUM(D55:I55) -> 0
J56: =SUM(D56:I56) -> 0
J57: =SUM(D57:I57) -> 0
J58: =SUM(D58:I58) -> 0
J59: =SUM(D59:I59) -> 0
J60: =SUM(D60:I60) -> 0
J61: =SUM(D61:I61) -> 0
J62: =SUM(D62:I62) -> 0
A63: TOTAL | D63: =SUM(D49:D62) -> 163.5 | E63: =SUM(E49:E62) -> 24 | F63: =SUM(F49:F62) -> 0 | G63: =SUM(G49:G62) -> 0 | H63: =SUM(H49:H62) -> 0 | I63: =SUM(I49:I62) -> 0 | J63: =SUM(J49:J62) -> 187.5
A66: TOTAL DE INGRESOS | J66: =+J28+J63 -> 4176
A69: SRTA. FATIMA SIHUE
A70: COBRANZA SOCIOS
A71: COBRANZA INQUILINOS
A74: SRA. MARIA CUYA ARANGO
A75: COBRANZA DE BAÑO DEL 1ER PISO | J75: 450
A78: COBRANZA DE BAÑO DEL 2DO PISO
A80: TOTAL GENERAL DE INGRESOS | J80: =SUM(J66:J79) -> 4626
A82: EGRESOS DEL DIA 02-02-2026
A83: CAJA
A84: RESPONSABLE | B84: COMPROBANTE | C84: DETALLE | J84: TOTAL
A85: RAMIREZ HERMELINDA | B85: RC 8525 | C85: REEMPLAZO DE LA SRA DE LOS SSHH DEL DIA 01-02-2026 | J85: 80
A86: MOLERO ROSANA | B86: RC 8526 | C86: LIMPIEZA DE OFICINA Y SSHH DEL SEGUNDO PISO | J86: 70
A87: HERNANDEZ ALDO | B87: RC 8527 | C87: PASAJE PARA FIRMA LAS CONSTANCIAS DE MANIPULACION DE ALIMENTOS | J87: 10
A88: VILLANUEVA TATIHANA | B88: RC 8528 | C88: PASAJE A LA MUNICIPALIDAD PARA DERJAR DOCUMENTACION | J88: 9
A89: HERRERA POMA ADELINO | B89: E001- 39 | C89: ADELANTO DE PAGO PARA LA COMPRA DE MATERIALES PARA EL PINTADO DEL TECHO PARABOLICO | J89: 1000
A90: CAHUANA MATIAS | B90: 516505 | C90: SUELDO DEL MES DE ENERO 2026 | J90: 1638.4
A91: ORMEÑO CARLOS | B91: 517485 | C91: SUELDO DEL MES DE ENERO 2026 | J91: 1001.9
A92: PALOMINO SANTOS | B92: 518252 | C92: SUELDO DEL MES DE ENERO 2026 | J92: 1607.6
A93: POMACANCHARI NICANOR | B93: 519564 | C93: SUELDO DEL MES DE ENERO 2026 | J93: 1441.1
A94: TUEROS PRUDENCIO | B94: 520306 | C94: SUELDO DEL MES DE ENERO 2026 | J94: 989.6
A95: CUYA MARIA | B95: 521071 | C95: SUELDO DEL MES DE ENERO 2026 | J95: 1256.3
A96: HURTADO WILDER | B96: 521881 | C96: SUELDO DEL MES DE ENERO 2026 | J96: 1120.7
A97: VILLANUEVA TATIH | B97: 522741 | C97: SUELDO DEL MES DE ENERO 2026 | J97: 604.7
A98: PANQUIEZ DENIS | B98: 523978 | C98: SUELDO DEL MES DE ENERO 2026 | J98: 506.5
A99: SIHUE FATIMA | B99: 523491 | C99: SUELDO DEL MES DE ENERO 2026 | J99: 934.1
A100: SALDAÑA JESSICA | B100: 974 | C100: 1 SPORADE GRANDE PARA EL CONSEJO DE ADM | J100: 5
A101: SOTO MARIA | B101: RC 8529 | C101: DIETA MES DE ENERO 2026 AL CARGO DE VOCAL TITULAR DEL CONSEJO DE ADM. | J101: 200
A102: VILCHEZ LOURDES | B102: RC 8530 | C102: DIETA MES DE ENERO 2026 AL CARGO DE VOCAL SUPLENTE DEL CONSEJO DE ADM. | J102: 150
A103: LOPEZ NELLY | B103: RC 8531 | C103: DIETA MES DE ENERO 2026 AL CARGO DE GERENTA | J103: 450
A106: TOTAL DE EGRESOS | J106: =SUM(J85:J105) -> 13074.9
A109: RESUMEN
A110: TOTAL GENERAL | B110: =+J80 -> 4626
A111: TOTAL DE EGRESOS | B111: =+J106 -> 13074.9
A112: SALDO | B112: =++B110-B111 -> -8448.9

Sheet 03-02-2026
A1: INGRESOS DEL DIA 03-02-2026
A3: INQUILINO | B3: COMPROBANTE | C3: DETALLE | D3: LUZ | E3: AGUA | F3: ALQUILER | G3: ESPACIO | H3: PARQUEO | I3: TICKET | J3: TOTAL
A4: JOSE | B4: TK 50754 | C4: 46054 | I4: 10 | J4: =SUM(D4:I4) -> 10
A5: FACILTERR S.A.C. | B5: E001-311 | C5: 46054 | G5: 200 | J5: =SUM(D5:I5) -> 200
A6: ESPARTA JULIO | B6: EB01-6792 | C6: 46023 | F6: 350 | J6: =SUM(D6:I6) -> 350
A7: QUISPE MARISOL | B7: EB01-6794 | C7: 45992 | F7: 10 | J7: =SUM(D7:I7) -> 10
B8: EB01-6795 | C8: 46023 | F8: 70 | J8: =SUM(D8:I8) -> 70
A9: PARQUEO | B9: EB01-6797 | C9: 46054 | H9: 61 | J9: =SUM(D9:I9) -> 61
J10: =SUM(D10:I10) -> 0
J11: =SUM(D11:I11) -> 0
A12: ESPARTA JULIO | B12: RII 3230 | C12: 45992 | D12: 44 | E12: 5 | J12: =SUM(D12:I12) -> 49
A13: QUISPE MARISOL | B13: RII 3231 | C13: 45992 | D13: 10 | E13: 5 | J13: =SUM(D13:I13) -> 15
J14: =SUM(D14:I14) -> 0
J15: =SUM(D15:I15) -> 0
J16: =SUM(D16:I16) -> 0
J17: =SUM(D17:I17) -> 0
J18: =SUM(D18:I18) -> 0
J19: =SUM(D19:I19) -> 0
J20: =SUM(D20:I20) -> 0
J21: =SUM(D21:I21) -> 0
A22: TOTAL | D22: =SUM(D4:D21) -> 54 | E22: =SUM(E4:E21) -> 10 | F22: =SUM(F4:F21) -> 430 | G22: =SUM(G4:G21) -> 200 | H22: =SUM(H4:H21) -> 61 | I22: =SUM(I4:I21) -> 10 | J22: =SUM(J4:J21) -> 765
A24: BBVA
A25: INQUILINOS | B25: COMPROBANTE | C25: DETALLE | D25: LUZ | E25: AGUA | F25: ALQUILER | G25: ESPACIO | H25: DEPOSITO | I25: TICKET | J25: TOTAL
A26: HERRERA ROMINA | B26: EB01-6791 | C26: 46023 | F26: 600 | J26: =SUM(D26:I26) -> 600
B27: RII 3229 | C27: 45992 | D27: 31.4 | E27: 5.3 | J27: =SUM(D27:I27) -> 36.7
C28: 46023 | D28: 1.3 | J28: =SUM(D28:I28) -> 1.3
A29: WALTER DAVID MOTA DAMAS | B29: EB01-6793 | C29: 46054 | G29: 30 | J29: =SUM(D29:I29) -> 30
J30: =SUM(D30:I30) -> 0 | L30: TOTAL QR | M30: =J31+J39 -> 668
A31: TOTAL | J31: =SUM(J26:J30) -> 668
A33: BBVA
A34: SOCIOS | B34: RECIBO DE SERVICIO | C34: DETALLE | D34: LUZ | E34: AGUA | F34: G. ADM | G34: P. SOCIAL | H34: DEPOSITO | I34: P.S X FALLECIMIENTO | J34: TOTAL
J35: =SUM(D35:I35) -> 0
J36: =SUM(D36:I36) -> 0
J37: =SUM(D37:I37) -> 0
J38: =SUM(D38:I38) -> 0
A39: TOTAL | J39: =SUM(J35:J38) -> 0
A43: SOCIO | B43: RECIBO DE SERVICIO | C43: DETALLE | D43: LUZ | E43: AGUA | F43: G. ADM | G43: P. SOCIAL | H43: P.S X FALLECIMIENTO | I43: DEPOSITO | J43: TOTAL
A44: YRUPAILLA ISIDRO | B44: RI 32450 | C44: 45992 | F44: 60 | G44: 5 | J44: =SUM(D44:I44) -> 65
C45: 46023 | F45: 60 | G45: 5 | H45: 10 | J45: =SUM(D45:I45) -> 75
A46: MELO MARINA | B46: RI 32451 | C46: 45992 | D46: 621.9 | E46: 24.6 | J46: =SUM(D46:I46) -> 646.5
J47: =SUM(D47:I47) -> 0
J48: =SUM(D48:I48) -> 0
J49: =SUM(D49:I49) -> 0
J50: =SUM(D50:I50) -> 0
J51: =SUM(D51:I51) -> 0
J52: =SUM(D52:I52) -> 0
J53: =SUM(D53:I53) -> 0
J54: =SUM(D54:I54) -> 0
J55: =SUM(D55:I55) -> 0
J56: =SUM(D56:I56) -> 0
J57: =SUM(D57:I57) -> 0
A58: TOTAL | D58: =SUM(D44:D57) -> 621.9 | E58: =SUM(E44:E57) -> 24.6 | F58: =SUM(F44:F57) -> 120 | G58: =SUM(G44:G57) -> 10 | H58: =SUM(H44:H57) -> 10 | I58: =SUM(I44:I57) -> 0 | J58: =SUM(J44:J57) -> 786.5
A61: TOTAL DE INGRESOS | J61: =+J22+J58 -> 1551.5
A64: SRTA. FATIMA SIHUE
A65: COBRANZA SOCIOS
A66: COBRANZA INQUILINOS
A69: SRA. MARIA CUYA ARANGO
A70: COBRANZA DE BAÑO DEL 1ER PISO | J70: 465.5
A73: COBRANZA DE BAÑO DEL 2DO PISO
A75: TOTAL GENERAL DE INGRESOS | J75: =SUM(J61:J74) -> 2017
A77: EGRESOS DEL DIA 03-02-2026
A78: CAJA
A79: RESPONSABLE | B79: COMPROBANTE | C79: DETALLE | J79: TOTAL
A80: JARA ALVAREZ BLANCA ROSA | B80: EB01-49 | C80: EQUIPO + INSTALACION DE INTERNET | J80: 300
A81: TRIGO DE ORO | B81: FA01-00012297 | C81: 1 TORTA GRANDE POR EL ONOMASTICO DE LA PRESIDENTA DEL CONSEJO DE VIGILANCIA | J81: 96
A82: YUCRA JOSUE | B82: RC 8532 | C82: DIETA MES DE ENERO 2026 AL CARGO DE VICEPRESIDENTE DEL CONSEJO DE ADM | J82: 300
A93: TOTAL DE EGRESOS | J93: =SUM(J80:J92) -> 696
A96: RESUMEN
A97: TOTAL GENERAL | B97: =+J75 -> 2017
A98: TOTAL DE EGRESOS | B98: =+J93 -> 696
A99: SALDO | B99: =++B97-B98 -> 1321

Sheet 04-02-2026
A1: INGRESOS DEL DIA 04-02-2026
A3: INQUILINO | B3: COMPROBANTE | C3: DETALLE | D3: LUZ | E3: AGUA | F3: ALQUILER | G3: ESPACIO | H3: PARQUEO | I3: TICKET | J3: TOTAL
A4: JOSE | B4: TK 50755 | C4: 46054 | I4: 10 | J4: =SUM(D4:I4) -> 10
A5: CERVANTES CARLOS | B5: EB01-6798 | C5: 46023 | F5: 500 | J5: =SUM(D5:I5) -> 500
A6: ANCHAYA ABEL | B6: EB01-6801 | C6: 45962 | F6: 50 | J6: =SUM(D6:I6) -> 50
A7: AZURZA DAYSI | B7: EB01-6803 | C7: 46023 | F7: 200 | J7: =SUM(D7:I7) -> 200
A8: BENITES ERIKA | B8: EB01-6805 | C8: 46023 | F8: 100 | J8: =SUM(D8:I8) -> 100
A9: CCENCHO DAVID | B9: EB01-6807 | C9: 46023 | F9: 500 | J9: =SUM(D9:I9) -> 500
A10: CONDORI LIDIA | B10: EB01-6808 | C10: 45992 | F10: 200 | J10: =SUM(D10:I10) -> 200
A11: FLORES DOMINICA | B11: EB01-6811 | C11: 45992 | F11: 100 | J11: =SUM(D11:I11) -> 100
A12: PARQUEO | B12: EB01-6814 | C12: 46054 | H12: 61.5 | J12: =SUM(D12:I12) -> 61.5
J13: =SUM(D13:I13) -> 0
J14: =SUM(D14:I14) -> 0
A15: CERVANTES CARLOS | B15: RII 3232 | C15: 45992 | D15: 10 | E15: 5 | J15: =SUM(D15:I15) -> 15
A16: SATALAYA SEGUNDO | B16: RII 3235 | C16: 45992 | D16: 0.2 | J16: =SUM(D16:I16) -> 0.2
A17: CCENCHO DAVID | B17: RII 3237 | C17: 45992 | D17: 10 | E17: 5 | J17: =SUM(D17:I17) -> 15
A18: DAVILA YESENIA | B18: RII 3238 | C18: 45992 | D18: 10 | E18: 5 | J18: =SUM(D18:I18) -> 15
A19: CONDORI LIDIA | B19: RII 3239 | C19: 45962 | D19: 8.6 | E19: 5 | J19: =SUM(D19:I19) -> 13.6
C20: 45992 | D20: 8.2 | E20: 5 | J20: =SUM(D20:I20) -> 13.2
A21: FLORES DOMINICA | B21: RII 3240 | C21: 45992 | D21: 8.6 | E21: 5 | J21: =SUM(D21:I21) -> 13.6
A22: GOMEZ MARIBEL | B22: RII 3241 | C22: 45931 | D22: 7.2 | E22: 10 | J22: =SUM(D22:I22) -> 17.2
C23: 45962 | D23: 7.3 | E23: 15 | J23: =SUM(D23:I23) -> 22.3
C24: 45992 | D24: 7 | E24: 3.5 | J24: =SUM(D24:I24) -> 10.5
J25: =SUM(D25:I25) -> 0
J26: =SUM(D26:I26) -> 0
A27: TOTAL | D27: =SUM(D4:D26) -> 77.1 | E27: =SUM(E4:E26) -> 58.5 | F27: =SUM(F4:F26) -> 1650 | G27: =SUM(G4:G26) -> 0 | H27: =SUM(H4:H26) -> 61.5 | I27: =SUM(I4:I26) -> 10 | J27: =SUM(J4:J26) -> 1857.1
A29: BBVA
A30: INQUILINOS | B30: COMPROBANTE | C30: DETALLE | D30: LUZ | E30: AGUA | F30: ALQUILER | G30: ESPACIO | H30: DEPOSITO | I30: TICKET | J30: TOTAL
A31: LOVEMARK PUBLICIDAD PROMOCIONAL S.A.C. | B31: E001-312 | C31: 46054 | G31: 30 | J31: =SUM(D31:I31) -> 30
A32: CLAROS SANTOS | B32: E001-313 | C32: 45992 | F32: 80 | J32: =SUM(D32:I32) -> 80
A33: SATALAYA SEGUNDO | B33: EB01-6799 | C33: 45931 | F33: 330 | J33: =SUM(D33:I33) -> 330
C34: 45962 | F34: 70 | J34: =SUM(D34:I34) -> 70
A35: ANCHAYA ABEL | B35: EB01-6800 | C35: 45962 | F35: 50 | J35: =SUM(D35:I35) -> 50
A36: HERNANDEZ LILIBETH | B36: EB01-6802 | C36: 45992 | F36: 200 | J36: =SUM(D36:I36) -> 200
A37: BENITES ERIKA | B37: EB01-6804 | C37: 46023 | F37: 100 | J37: =SUM(D37:I37) -> 100
A38: DAVILA YESENIA | B38: EB01-6806 | C38: 46023 | F38: 500 | J38: =SUM(D38:I38) -> 500
A39: MALLMA LISBETH | B39: EB01-6809 | C39: 45992 | F39: 300 | J39: =SUM(D39:I39) -> 300
A40: MUJICA SANDRA | B40: EB01-6810 | C40: 45992 | F40: 150 | J40: =SUM(D40:I40) -> 150
A41: ENCARNACION GLADYS | B41: EB01-6812 | C41: 46023 | F41: 500 | J41: =SUM(D41:I41) -> 500
A42: HERNANDEZ LILIBETH | B42: RII 3233 | C42: 45992 | D42: 30 | E42: 5 | J42: =SUM(D42:I42) -> 35
A43: HERRERA ORFELITA | B43: RII 3234 | C43: 45992 | D43: 21.9 | E43: 5 | J43: =SUM(D43:I43) -> 26.9
A44: SATALAYA SEGUNDO | B44: RII 3236 | C44: 45992 | D44: 11 | E44: 5 | J44: =SUM(D44:I44) -> 16
A45: ENCARNACION GLADYS | B45: RII 3242 | C45: 45992 | D45: 25 | E45: 5 | J45: =SUM(D45:I45) -> 30
J46: =SUM(D46:I46) -> 0
J47: =SUM(D47:I47) -> 0 | L47: TOTAL QR | M47: =J48+J60 -> 3126.3
A48: TOTAL | J48: =SUM(J31:J47) -> 2417.9
A50: BBVA
A51: SOCIOS | B51: RECIBO DE SERVICIO | C51: DETALLE | D51: LUZ | E51: AGUA | F51: G. ADM | G51: P. SOCIAL | H51: DEPOSITO | I51: P.S X FALLECIMIENTO | J51: TOTAL
A52: RAMOS PEDRO | B52: RI 32459 | C52: 45962 | D52: 24.6 | E52: 109.7 | J52: =SUM(D52:I52) -> 134.3
A53: JUAREZ LEONOR | B53: RI 32461 | C53: 45992 | D53: 115.3 | E53: 117.5 | J53: =SUM(D53:I53) -> 232.8
C54: 46023 | F54: 60 | G54: 5 | J54: =SUM(D54:I54) -> 65
A55: GUTIERREZ ROGER | B55: RI 32462 | C55: 45992 | D55: 81.6 | E55: 119.2 | J55: =SUM(D55:I55) -> 200.8
C56: 46023 | F56: 60 | G56: 5 | J56: =SUM(D56:I56) -> 65
A57: JARA SANTOS | B57: RI 32465 | C57: 45992 | D57: 4.5 | E57: 6 | J57: =SUM(D57:I57) -> 10.5
J58: =SUM(D58:I58) -> 0
J59: =SUM(D59:I59) -> 0
A60: TOTAL | J60: =SUM(J52:J59) -> 708.4
A64: SOCIO | B64: RECIBO DE SERVICIO | C64: DETALLE | D64: LUZ | E64: AGUA | F64: G. ADM | G64: P. SOCIAL | H64: P.S X FALLECIMIENTO | I64: TALONARIO SANTA ROSA | J64: TOTAL
A65: PALOMINO CECILIA | B65: RI 32452 | C65: 45870 | I65: 15 | J65: =SUM(D65:I65) -> 15
C66: 45992 | D66: 308.4 | E66: 68.7 | J66: =SUM(D66:I66) -> 377.1
A67: MEDINA VICENTA | B67: RI 32453 | C67: 45992 | F67: 60 | G67: 5 | J67: =SUM(D67:I67) -> 65
A68: CUYA ALBERTO | B68: RI 32454 | C68: 45901 | F68: 60 | G68: 5 | J68: =SUM(D68:I68) -> 65
A69: BURGA ELIDA | B69: RI 32455 | C69: 45901 | F69: 60 | G69: 5 | J69: =SUM(D69:I69) -> 65
A70: ANULADO | B70: RI 32456 | J70: =SUM(D70:I70) -> 0
A71: LUJAN MARINO | B71: RI 32457 | C71: 45962 | F71: 60 | G71: 5 | J71: =SUM(D71:I71) -> 65
C72: 45992 | F72: 60 | G72: 5 | J72: =SUM(D72:I72) -> 65
C73: 46023 | F73: 60 | G73: 5 | H73: 10 | J73: =SUM(D73:I73) -> 75
A74: RAMOS PEDRO | B74: RI 32458 | C74: 46023 | H74: 10 | J74: =SUM(D74:I74) -> 10
A75: RAMOS PEDRO | B75: RI 32460 | C75: 45962 | E75: 0.4 | J75: =SUM(D75:I75) -> 0.4
C76: 45992 | D76: 23.6 | E76: 86 | F76: 60 | G76: 5 | J76: =SUM(D76:I76) -> 174.6
C77: 46023 | F77: 60 | G77: 5 | J77: =SUM(D77:I77) -> 65
A78: QUISPE ROSA | B78: RI 32463 | C78: 45992 | D78: 393.6 | E78: 11.4 | F78: 20 | G78: 5 | J78: =SUM(D78:I78) -> 430
C79: 46023 | F79: 20 | G79: 5 | H79: 10 | J79: =SUM(D79:I79) -> 35
A80: JARA SANTOS | B80: RI 32464 | C80: 45962 | D80: 12.4 | E80: 6 | J80: =SUM(D80:I80) -> 18.4
C81: 45992 | D81: 11.6 | J81: =SUM(D81:I81) -> 11.6
A82: PACOMPIA GIOVANNI | B82: RI 32466 | C82: 46023 | F82: 60 | G82: 5 | H82: 10 | J82: =SUM(D82:I82) -> 75
A83: CARDEÑA ALEJANDRINA | B83: RI 32467 | C83: 45992 | D83: 5 | E83: 6 | J83: =SUM(D83:I83) -> 11
B84: RI 32468 | C84: 46023 | F84: 60 | G84: 5 | H84: 10 | J84: =SUM(D84:I84) -> 75
A85: ALARCON NANCY | B85: RI 32469 | C85: 45962 | D85: 46.7 | E85: 6 | J85: =SUM(D85:I85) -> 52.7
C86: 45992 | D86: 47.4 | E86: 6 | J86: =SUM(D86:I86) -> 53.4
J87: =SUM(D87:I87) -> 0
J88: =SUM(D88:I88) -> 0
A89: TOTAL | D89: =SUM(D65:D88) -> 848.7 | E89: =SUM(E65:E88) -> 190.5 | F89: =SUM(F65:F88) -> 640 | G89: =SUM(G65:G88) -> 60 | H89: =SUM(H65:H88) -> 50 | I89: =SUM(I65:I88) -> 15 | J89: =SUM(J65:J88) -> 1804.2
A92: TOTAL DE INGRESOS | J92: =+J27+J89 -> 3661.3
A95: SRTA. FATIMA SIHUE
A96: COBRANZA SOCIOS
A97: COBRANZA INQUILINOS
A100: SRA. MARIA CUYA ARANGO
A101: COBRANZA DE BAÑO DEL 1ER PISO | J101: 474
A104: COBRANZA DE BAÑO DEL 2DO PISO
A106: TOTAL GENERAL DE INGRESOS | J106: =SUM(J92:J105) -> 4135.3
A108: EGRESOS DEL DIA 04-02-2026
A109: CAJA
A110: RESPONSABLE | B110: COMPROBANTE | C110: DETALLE | J110: TOTAL
A111: FRANCISCO TORRES | B111: RC 8533 | C111: DIETA MES DE ENERO 2026 AL CARGO DE VOCAL DEL CONSEJO DE VIGILANCIA | J111: 150
A112: SANTILLAN ZOILA | B112: RC 8534 | C112: DIETA MES DE ENERO 2026 AL CARGO DE VICEPRESIDENTE DEL CONSEJO DE VIGILANCIA | J112: 250
A113: GARCIA AQUINO SANTOS | B113: E001-462 | C113: SERVICIO TECNICO Y MANTENIMIENTO DE FOTOCOPIADORA BROTHER Y CAMBIO DE SENDOR DE IMAGEN COLOR | J113: 230
A114: CHOQUE UMPIRE JAMES FIDEL | B114: E001-44 | C114: MEMORIA DE CALCULO DE PLANO EXISTENTE TECHOS PARABOLICOS | J114: 750
A115: CUYA ALBERTO | B115: 8509 | C115: 5 POWER Y 1 PQT DE RITZ PARA LA SESION DE COBRANZA | J115: 15
A124: TOTAL DE EGRESOS | J124: =SUM(J111:J123) -> 1395
...

Sheet 05-02-2026
A1: INGRESOS DEL DIA 05-02-2026
A3: INQUILINO | B3: COMPROBANTE | C3: DETALLE | D3: LUZ | E3: AGUA | F3: ALQUILER | G3: ESPACIO | H3: PARQUEO | I3: TICKET | J3: TOTAL
A4: JOSE | B4: TK 50756 | C4: 46054 | I4: 10 | J4: =SUM(D4:I4) -> 10
A5: GOMEZ MARIBEL | B5: EB01-6815 | C5: 46023 | F5: 600 | J5: =SUM(D5:I5) -> 600
A6: YUPANQUI SAYDA | B6: EB01-6816 | C6: 46023 | F6: 350 | J6: =SUM(D6:I6) -> 350
A7: PARQUEO | B7: EB01-6818 | C7: 46054 | H7: 51 | J7: =SUM(D7:I7) -> 51
A8: CLAROS SANTOS | B8: E001-314 | C8: 46023 | F8: 150 | J8: =SUM(D8:I8) -> 150
J9: =SUM(D9:I9) -> 0
J10: =SUM(D10:I10) -> 0
A11: YAURIMUCHA URSULA | B11: RII 3243 | C11: 45992 | D11: 10 | E11: 5 | J11: =SUM(D11:I11) -> 15
J12: =SUM(D12:I12) -> 0
J13: =SUM(D13:I13) -> 0
J14: =SUM(D14:I14) -> 0
J15: =SUM(D15:I15) -> 0
J16: =SUM(D16:I16) -> 0
J17: =SUM(D17:I17) -> 0
J18: =SUM(D18:I18) -> 0
J19: =SUM(D19:I19) -> 0
J20: =SUM(D20:I20) -> 0
J21: =SUM(D21:I21) -> 0
J22: =SUM(D22:I22) -> 0
A23: TOTAL | D23: =SUM(D4:D22) -> 10 | E23: =SUM(E4:E22) -> 5 | F23: =SUM(F4:F22) -> 1100 | G23: =SUM(G4:G22) -> 0 | H23: =SUM(H4:H22) -> 51 | I23: =SUM(I4:I22) -> 10 | J23: =SUM(J4:J22) -> 1176
A25: BBVA
A26: INQUILINOS | B26: COMPROBANTE | C26: DETALLE | D26: LUZ | E26: AGUA | F26: ALQUILER | G26: TALONARIO SANTA ROSA | H26: DEPOSITO | I26: TICKET | J26: TOTAL
A27: GOMEZ MARIBEL | B27: RII 3244 | C27: 45870 | G27: 15 | J27: =SUM(D27:I27) -> 15
C28: 45992 | E28: 21.1 | J28: =SUM(D28:I28) -> 21.1
J29: =SUM(D29:I29) -> 0
J30: =SUM(D30:I30) -> 0 | L30: TOTAL QR | M30: =J31+J39 -> 36.1
A31: TOTAL | J31: =SUM(J27:J30) -> 36.1
A33: BBVA
A34: SOCIOS | B34: RECIBO DE SERVICIO | C34: DETALLE | D34: LUZ | E34: AGUA | F34: G. ADM | G34: P. SOCIAL | H34: DEPOSITO | I34: P.S X FALLECIMIENTO | J34: TOTAL
J35: =SUM(D35:I35) -> 0
J36: =SUM(D36:I36) -> 0
J37: =SUM(D37:I37) -> 0
J38: =SUM(D38:I38) -> 0
A39: TOTAL | J39: =SUM(J35:J38) -> 0
A43: SOCIO | B43: RECIBO DE SERVICIO | C43: DETALLE | D43: LUZ | E43: AGUA | F43: G. ADM | G43: P. SOCIAL | H43: P.S X FALLECIMIENTO | I43: DEPOSITO | J43: TOTAL
A44: AYALA ELISEO | B44: RI 32470 | C44: 45992 | D44: 21.1 | E44: 6 | J44: =SUM(D44:I44) -> 27.1
C45: 46023 | F45: 60 | G45: 5 | I45: 150 | J45: =SUM(D45:I45) -> 215
A46: AYALA NORMA | B46: RI 32471 | C46: 45992 | D46: 21.1 | E46: 6 | J46: =SUM(D46:I46) -> 27.1
C47: 46023 | F47: 60 | G47: 5 | J47: =SUM(D47:I47) -> 65
A48: HUASHUAYO NORMA | B48: RI 32472 | C48: 45992 | D48: 95.6 | E48: 6 | J48: =SUM(D48:I48) -> 101.6
C49: 46023 | F49: 60 | G49: 5 | I49: 200 | J49: =SUM(D49:I49) -> 265
J50: =SUM(D50:I50) -> 0
J51: =SUM(D51:I51) -> 0
J52: =SUM(D52:I52) -> 0
J53: =SUM(D53:I53) -> 0
J54: =SUM(D54:I54) -> 0
J55: =SUM(D55:I55) -> 0
J56: =SUM(D56:I56) -> 0
J57: =SUM(D57:I57) -> 0
A58: TOTAL | D58: =SUM(D44:D57) -> 137.8 | E58: =SUM(E44:E57) -> 18 | F58: =SUM(F44:F57) -> 180 | G58: =SUM(G44:G57) -> 15 | H58: =SUM(H44:H57) -> 0 | I58: =SUM(I44:I57) -> 350 | J58: =SUM(J44:J57) -> 700.8
A61: TOTAL DE INGRESOS | J61: =+J23+J58 -> 1876.8
A64: SRTA. FATIMA SIHUE
A65: COBRANZA SOCIOS
A66: COBRANZA INQUILINOS
A69: SRA. MARIA CUYA ARANGO
A70: COBRANZA DE BAÑO DEL 1ER PISO | J70: 472
A73: COBRANZA DE BAÑO DEL 2DO PISO
A75: TOTAL GENERAL DE INGRESOS | J75: =SUM(J61:J74) -> 2348.8
A77: EGRESOS DEL DIA 05-02-2026
A78: CAJA
A79: RESPONSABLE | B79: COMPROBANTE | C79: DETALLE | J79: TOTAL
A80: GARCIA AQUINO SANTOS | B80: E001-464 | C80: SERVICIO DE MANTENIMIENTO Y CAMBIO DE 4 SELLOS Y TONER CARTUCHO NEGRO | J80: 340
A81: LOPEZ NELLY | B81: RC 8535 | C81: LONCHE PARA LA SESION DE COBRANZA DEL DIA 04-02-2026 | J81: 15
A82: ANAMPA CLEMENCIA | B82: RC 8536 | C82: DIETA MES DE ENERO 2026 AL CARGO DE VOCAL TITUALR DEL CONSEJO DE ADM | J82: 150
A83: CUYA ALBERTO | B83: 8514 | C83: 1 AGUA SAN MATEO DE 2.5 LT PARA LA SESION DEL CONSEJO DE ADM | J83: 3.5
A92: TOTAL DE EGRESOS | J92: =SUM(J80:J91) -> 508.5
A94: BOVEDA SANTA ROSA
A95: RESPONSABLE | B95: COMPROBANTE | C95: DETALLE | I95: TOTAL
A96: ALARCON ANAMPA BETSY | B96: 930 | C96: ARREGLO FLORAL | I96: 10
A101: TOTAL DE EGRESOS | I101: =SUM(I96:I100) -> 10
A103: RESUMEN
A104: TOTAL GENERAL | B104: =+J75 -> 2348.8
A105: TOTAL DE EGRESOS | B105: =+J92 -> 508.5
A106: SALDO | B106: =++B104-B105 -> 1840.3

Sheet 06-02-2026
A1: INGRESOS DEL DIA 06-02-2026
A3: INQUILINO | B3: COMPROBANTE | C3: DETALLE | D3: LUZ | E3: AGUA | F3: ALQUILER | G3: ESPACIO | H3: PARQUEO | I3: TICKET | J3: TOTAL
A4: JOSE | B4: TK 50757 | C4: 46054 | I4: 10 | J4: =SUM(D4:I4) -> 10
A5: CERRON OBDULIA | B5: EB01-6819 | C5: 46023 | F5: 450 | J5: =SUM(D5:I5) -> 450
A6: SANCHEZ DIANA | B6: EB01-6820 | C6: 46023 | F6: 850 | J6: =SUM(D6:I6) -> 850
A7: WALTER DAVID MOTA DAMAS | B7: EB01-6821 | C7: 46054 | G7: 30 | J7: =SUM(D7:I7) -> 30
A8: LOPEZ HAYDEE | B8: EB01-6822 | C8: 46023 | F8: 500 | J8: =SUM(D8:I8) -> 500
A9: PARQUEO | B9: EB01-6824 | C9: 46054 | H9: 75 | J9: =SUM(D9:I9) -> 75
J10: =SUM(D10:I10) -> 0
J11: =SUM(D11:I11) -> 0
J12: =SUM(D12:I12) -> 0
A13: SANCHEZ DIANA | B13: RII 3245 | C13: 45992 | D13: 15.5 | E13: 5 | J13: =SUM(D13:I13) -> 20.5
A14: LOPEZ HAYDEE | B14: RII 3246 | C14: 45992 | D14: 10 | E14: 5 | J14: =SUM(D14:I14) -> 15
J15: =SUM(D15:I15) -> 0
J16: =SUM(D16:I16) -> 0
J17: =SUM(D17:I17) -> 0
J18: =SUM(D18:I18) -> 0
J19: =SUM(D19:I19) -> 0
J20: =SUM(D20:I20) -> 0
J21: =SUM(D21:I21) -> 0
J22: =SUM(D22:I22) -> 0
A23: TOTAL | D23: =SUM(D4:D22) -> 25.5 | E23: =SUM(E4:E22) -> 10 | F23: =SUM(F4:F22) -> 1800 | G23: =SUM(G4:G22) -> 30 | H23: =SUM(H4:H22) -> 75 | I23: =SUM(I4:I22) -> 10 | J23: =SUM(J4:J22) -> 1950.5
A25: BBVA
A26: INQUILINOS | B26: COMPROBANTE | C26: DETALLE | D26: LUZ | E26: AGUA | F26: ALQUILER | G26: ESPACIO | H26: DEPOSITO | I26: TICKET | J26: TOTAL
J27: =SUM(D27:I27) -> 0
J28: =SUM(D28:I28) -> 0
J29: =SUM(D29:I29) -> 0
J30: =SUM(D30:I30) -> 0 | L30: TOTAL QR | M30: =J31+J39 -> 84.6
A31: TOTAL | J31: =SUM(J27:J30) -> 0
A33: BBVA
A34: SOCIOS | B34: RECIBO DE SERVICIO | C34: DETALLE | D34: LUZ | E34: AGUA | F34: G. ADM | G34: P. SOCIAL | H34: DEPOSITO | I34: P.S X FALLECIMIENTO | J34: TOTAL
A35: CUSI SONIA | B35: RI 32479 | C35: 45962 | D35: 27.9 | E35: 6 | J35: =SUM(D35:I35) -> 33.9
C36: 45992 | D36: 17.7 | E36: 6 | F36: 22 | G36: 5 | J36: =SUM(D36:I36) -> 50.7
J37: =SUM(D37:I37) -> 0
J38: =SUM(D38:I38) -> 0
A39: TOTAL | J39: =SUM(J35:J38) -> 84.6
A43: SOCIO | B43: RECIBO DE SERVICIO | C43: DETALLE | D43: LUZ | E43: AGUA | F43: G. ADM | G43: P. SOCIAL | H43: P.S X FALLECIMIENTO | I43: DEPOSITO | J43: TOTAL
A44: HEREDIA MARIA | B44: RI 32473 | C44: 45992 | D44: 8.3 | E44: 6 | J44: =SUM(D44:I44) -> 14.3
A45: AGUIRRE WILFREDO | B45: RI 32474 | C45: 45992 | D45: 32.1 | E45: 6 | J45: =SUM(D45:I45) -> 38.1
C46: 46023 | I46: 200 | J46: =SUM(D46:I46) -> 200
A47: QUISPE VIDAL | B47: RI 32475 | C47: 45992 | D47: 483.6 | E47: 13.4 | F47: 60 | G47: 5 | J47: =SUM(D47:I47) -> 562
A48: ESTELA ELVIA | B48: RI 32476 | C48: 45992 | D48: 263.6 | E48: 43.2 | F48: 60 | G48: 5 | J48: =SUM(D48:I48) -> 371.8
A49: SEGOVIA VILLAFUERTE | B49: RI 32477 | C49: 46023 | F49: 60 | G49: 5 | H49: 10 | J49: =SUM(D49:I49) -> 75
A50: MARIN BASILISA | B50: RI 32478 | C50: 46023 | D50: 28 | E50: 5 | J50: =SUM(D50:I50) -> 33
J51: =SUM(D51:I51) -> 0
J52: =SUM(D52:I52) -> 0
J53: =SUM(D53:I53) -> 0
J54: =SUM(D54:I54) -> 0
J55: =SUM(D55:I55) -> 0
J56: =SUM(D56:I56) -> 0
J57: =SUM(D57:I57) -> 0
A58: TOTAL | D58: =SUM(D44:D57) -> 815.6 | E58: =SUM(E44:E57) -> 73.6 | F58: =SUM(F44:F57) -> 180 | G58: =SUM(G44:G57) -> 15 | H58: =SUM(H44:H57) -> 10 | I58: =SUM(I44:I57) -> 200 | J58: =SUM(J44:J57) -> 1294.2
A61: TOTAL DE INGRESOS | J61: =+J23+J58 -> 3244.7
A64: SRTA. FATIMA SIHUE
A65: COBRANZA SOCIOS | J65: 1100
A66: COBRANZA INQUILINOS | J66: 2040 | K66: =J65+J66 -> 3140
K67: 100
K68: =K66+K67 -> 3240
A69: SRA. MARIA CUYA ARANGO | M69: 100 | N69: 11 | O69: =N69*M69 -> 1100
A70: COBRANZA DE BAÑO DEL 1ER PISO | J70: 488.5 | M70: 50 | N70: 20 | O70: =N70*M70 -> 1000
M71: 20 | N71: 49 | O71: =N71*M71 -> 980
M72: 10 | N72: 14 | O72: =N72*M72 -> 140
A73: COBRANZA DE BAÑO DEL 2DO PISO | M73: 1 | N73: 20 | O73: =N73*M73 -> 20
O74: =SUM(O69:O73) -> 3240
A75: TOTAL GENERAL DE INGRESOS | J75: =SUM(J61:J74) -> 6873.2
A77: EGRESOS DEL DIA 06-02-2026
A78: CAJA
A79: RESPONSABLE | B79: COMPROBANTE | C79: DETALLE | J79: TOTAL
A80: HUASHUAYO EDUDOSIA | B80: RC 8537 | C80: PREVENCION SOCIAL POR SALUD A LA SOCIA HUASHUAYO EUDOSIA | J80: 400
A81: FERRETERIA Y MATIZADOS EL REY E.I.R.L. | B81: E001 1097 | C81: 1 FOCO LED BOTELLA | J81: 30
A93: TOTAL DE EGRESOS | J93: =SUM(J80:J92) -> 430
A96: RESUMEN
A97: TOTAL GENERAL | B97: =+J75 -> 6873.2
A98: TOTAL DE EGRESOS | B98: =+J93 -> 430
A99: SALDO | B99: =++B97-B98 -> 6443.2

Sheet 07-02-2026
A1: INGRESOS DEL DIA 07-02-2026
A3: INQUILINO | B3: COMPROBANTE | C3: DETALLE | D3: LUZ | E3: AGUA | F3: ALQUILER | G3: LOCAL 2DO PISO | H3: PARQUEO | I3: TICKET | J3: TOTAL
A4: FERREYRA TANIA | B4: E001-315 | C4: 46054 | F4: 350 | J4: =SUM(D4:I4) -> 350
A5: ANATOLIA CHIPANA DE VARGAS | B5: EB01-6825 | C5: 46054 | F5: 140 | J5: =SUM(D5:I5) -> 140
A6: AURORA ISABEL NEYRA CONTRERAS | B6: EB01-6826 | C6: 46054 | G6: 500 | J6: =SUM(D6:I6) -> 500
A7: ROSA | B7: TK 50758 | C7: 46054 | I7: 6 | J7: =SUM(D7:I7) -> 6
A8: JOSE | B8: TK 50759 | C8: 46054 | I8: 10 | J8: =SUM(D8:I8) -> 10
J9: =SUM(D9:I9) -> 0
J10: =SUM(D10:I10) -> 0
J11: =SUM(D11:I11) -> 0
J12: =SUM(D12:I12) -> 0
J13: =SUM(D13:I13) -> 0
J14: =SUM(D14:I14) -> 0
J15: =SUM(D15:I15) -> 0
J16: =SUM(D16:I16) -> 0
J17: =SUM(D17:I17) -> 0
J18: =SUM(D18:I18) -> 0
J19: =SUM(D19:I19) -> 0
J20: =SUM(D20:I20) -> 0
... J22: =SUM(D22:I22) -> 0
A23: TOTAL | D23: =SUM(D4:D22) -> 0 | E23: =SUM(E4:E22) -> 0 | F23: =SUM(F4:F22) -> 490 | G23: =SUM(G4:G22) -> 500 | H23: =SUM(H4:H22) -> 0 | I23: =SUM(I4:I22) -> 16 | J23: =SUM(J4:J22) -> 1006
A25: BBVA
A26: INQUILINOS | B26: COMPROBANTE | C26: DETALLE | D26: LUZ | E26: AGUA | F26: ALQUILER | G26: ESPACIO | H26: DEPOSITO | I26: TICKET | J26: TOTAL
A27: PIZARRO ROMANI RAQUEL SONIA | B27: E001-316 | C27: 46060 | G27: 30 | J27: =SUM(D27:I27) -> 30
J28: =SUM(D28:I28) -> 0
J29: =SUM(D29:I29) -> 0
J30: =SUM(D30:I30) -> 0 | L30: TOTAL QR | M30: =J31+J39 -> 30
A31: TOTAL | J31: =SUM(J27:J30) -> 30
A33: BBVA
A34: SOCIOS | B34: RECIBO DE SERVICIO | C34: DETALLE | D34: LUZ | E34: AGUA | F34: G. ADM | G34: P. SOCIAL | H34: DEPOSITO | I34: P.S X FALLECIMIENTO | J34: TOTAL
J35: =SUM(D35:I35) -> 0
J36: =SUM(D36:I36) -> 0
J37: =SUM(D37:I37) -> 0
J38: =SUM(D38:I38) -> 0
A39: TOTAL | J39: =SUM(J35:J38) -> 0
A43: SOCIO | B43: RECIBO DE SERVICIO | C43: DETALLE | D43: LUZ | E43: AGUA | F43: G. ADM | G43: P. SOCIAL | H43: P.S X FALLECIMIENTO | I43: DEPOSITO | J43: TOTAL
A44: CABALLERO GLADYS | B44: RI 32480 | C44: 46023 | F44: 60 | G44: 5 | J44: =SUM(D44:I44) -> 65
B45: RI 32481 | C45: 46054 | F45: 60 | G45: 5 | J45: =SUM(D45:I45) -> 65
J46: =SUM(D46:I46) -> 0
J47: =SUM(D47:I47) -> 0
J48: =SUM(D48:I48) -> 0
J49: =SUM(D49:I49) -> 0
J50: =SUM(D50:I50) -> 0
J51: =SUM(D51:I51) -> 0
J52: =SUM(D52:I52) -> 0
J53: =SUM(D53:I53) -> 0
J54: =SUM(D54:I54) -> 0
J55: =SUM(D55:I55) -> 0
J56: =SUM(D56:I56) -> 0
J57: =SUM(D57:I57) -> 0
A58: TOTAL | D58: =SUM(D44:D57) -> 0 | E58: =SUM(E44:E57) -> 0 | F58: =SUM(F44:F57) -> 120 | G58: =SUM(G44:G57) -> 10 | H58: =SUM(H44:H57) -> 0 | I58: =SUM(I44:I57) -> 0 | J58: =SUM(J44:J57) -> 130
A61: TOTAL DE INGRESOS | J61: =+J23+J58 -> 1136
A64: SRTA. FATIMA SIHUE
A65: COBRANZA SOCIOS
A66: COBRANZA INQUILINOS
A69: SRA. MARIA CUYA ARANGO
A70: COBRANZA DE BAÑO DEL 1ER PISO | J70: 505.5
A73: COBRANZA DE BAÑO DEL 2DO PISO
A75: TOTAL GENERAL DE INGRESOS | J75: =SUM(J61:J74) -> 1641.5
A77: EGRESOS DEL DIA 07-02-2026
A78: CAJA
A79: RESPONSABLE | B79: COMPROBANTE | C79: DETALLE | J79: TOTAL
A80: TUSE MANUEL | B80: RC 8538 | C80: REEMPLAZO DEL SR NICANOR DEL DIA 29-01 Y 02-02 PARA LA LIMPIEZA DEL MERCADO | J80: 70
A81: TRIGO DE ORO | B81: FA01-00012354 | C81: 1 TORTA GRANDE POR EL ONOMASTICO DE LA SRA LOURDES VILCHEZ DEL CONSEJO DE ADM. | J81: 96
A93: TOTAL DE EGRESOS | J93: =SUM(J80:J92) -> 166
A96: RESUMEN
A97: TOTAL GENERAL | B97: =+J75 -> 1641.5
A98: TOTAL DE EGRESOS | B98: =+J93 -> 166
A99: SALDO | B99: =++B97-B98 -> 1475.5

Sheet 08-02-2026
A1: INGRESOS DEL DIA 08-02-2026
A3: INQUILINO | B3: COMPROBANTE | C3: DETALLE | D3: LUZ | E3: AGUA | F3: ALQUILER | G3: ESPACIO | H3: PARQUEO | I3: TICKET | J3: TOTAL
A4: JOSE | B4: TK 50760 | C4: 46054 | I4: 10 | J4: =SUM(D4:I4) -> 10
A5: JOSE DESARMADORES | B5: TK 50761 | C5: 46054 | I5: 10 | J5: =SUM(D5:I5) -> 10
J6: =SUM(D6:I6) -> 0
J7: =SUM(D7:I7) -> 0
J8: =SUM(D8:I8) -> 0
J9: =SUM(D9:I9) -> 0
J10: =SUM(D10:I10) -> 0
J11: =SUM(D11:I11) -> 0
J12: =SUM(D12:I12) -> 0
J13: =SUM(D13:I13) -> 0
J14: =SUM(D14:I14) -> 0
J15: =SUM(D15:I15) -> 0
J16: =SUM(D16:I16) -> 0
J17: =SUM(D17:I17) -> 0
... J21: =SUM(D21:I21) -> 0
A22: TOTAL | D22: =SUM(D4:D21) -> 0 | E22: =SUM(E4:E21) -> 0 | F22: =SUM(F4:F21) -> 0 | G22: =SUM(G4:G21) -> 0 | H22: =SUM(H4:H21) -> 0 | I22: =SUM(I4:I21) -> 20 | J22: =SUM(J4:J21) -> 20
A24: BBVA
A25: INQUILINOS | B25: COMPROBANTE | C25: DETALLE | D25: LUZ | E25: AGUA | F25: ALQUILER | G25: ESPACIO | H25: DEPOSITO | I25: TICKET | J25: TOTAL
J26: =SUM(D26:I26) -> 0
J27: =SUM(D27:I27) -> 0
J28: =SUM(D28:I28) -> 0
J29: =SUM(D29:I29) -> 0 | L29: TOTAL QR | M29: =J30+J38 -> 0
A30: TOTAL | J30: =SUM(J26:J29) -> 0
A32: BBVA
A33: SOCIOS | B33: RECIBO DE SERVICIO | C33: DETALLE | D33: LUZ | E33: AGUA | F33: G. ADM | G33: P. SOCIAL | H33: DEPOSITO | I33: P.S X FALLECIMIENTO | J33: TOTAL
J34: =SUM(D34:I34) -> 0
J35: =SUM(D35:I35) -> 0
J36: =SUM(D36:I36) -> 0
J37: =SUM(D37:I37) -> 0
A38: TOTAL | J38: =SUM(J34:J37) -> 0
A42: SOCIO | B42: RECIBO DE SERVICIO | C42: DETALLE | D42: LUZ | E42: AGUA | F42: G. ADM | G42: P. SOCIAL | H42: P.S X FALLECIMIENTO | I42: DEPOSITO | J42: TOTAL
J43: =SUM(D43:I43) -> 0
J44: =SUM(D44:I44) -> 0
J45: =SUM(D45:I45) -> 0
J46: =SUM(D46:I46) -> 0
J47: =SUM(D47:I47) -> 0
J48: =SUM(D48:I48) -> 0
J49: =SUM(D49:I49) -> 0
J50: =SUM(D50:I50) -> 0
J51: =SUM(D51:I51) -> 0
J52: =SUM(D52:I52) -> 0
J53: =SUM(D53:I53) -> 0
J54: =SUM(D54:I54) -> 0
... J56: =SUM(D56:I56) -> 0
A57: TOTAL | D57: =SUM(D43:D56) -> 0 | E57: =SUM(E43:E56) -> 0 | F57: =SUM(F43:F56) -> 0 | G57: =SUM(G43:G56) -> 0 | H57: =SUM(H43:H56) -> 0 | I57: =SUM(I43:I56) -> 0 | J57: =SUM(J43:J56) -> 0
A60: TOTAL DE INGRESOS | J60: =+J22+J57 -> 20
A63: SRTA. FATIMA SIHUE
A64: COBRANZA SOCIOS
A65: COBRANZA INQUILINOS
A68: SRA. MARIA CUYA ARANGO
A69: COBRANZA DE BAÑO DEL 1ER PISO | J69: 460
A72: COBRANZA DE BAÑO DEL 2DO PISO
A74: TOTAL GENERAL DE INGRESOS | J74: =SUM(J60:J73) -> 480
A76: EGRESOS DEL DIA 08-02-2026
A77: CAJA
A78: RESPONSABLE | B78: COMPROBANTE | C78: DETALLE | J78: TOTAL
A92: TOTAL DE EGRESOS | J92: =SUM(J79:J91) -> 0
A95: RESUMEN
A96: TOTAL GENERAL | B96: =+J74 -> 480
A97: TOTAL DE EGRESOS | B97: =+J92 -> 0
A98: SALDO | B98: =++B96-B97 -> 480

Sheet 09-02-2026
A1: INGRESOS DEL DIA 09-02-2026
A3: INQUILINO | B3: COMPROBANTE | C3: DETALLE | D3: LUZ | E3: AGUA | F3: ALQUILER | G3: ESPACIO | H3: PARQUEO | I3: TICKET | J3: TOTAL
A4: JOSE | B4: TK 50762 | C4: 46054 | I4: 10 | J4: =SUM(D4:I4) -> 10
A5: VASQUEZ MARGARITA | B5: EB01-6829 | C5: 46054 | G5: 100 | J5: =SUM(D5:I5) -> 100
A6: PARQUEO | B6: EB01-6831 | C6: 46054 | H6: 56 | J6: =SUM(D6:I6) -> 56
A7: PARQUEO | B7: EB01-6833 | C7: 46054 | H7: 54 | J7: =SUM(D7:I7) -> 54
J8: =SUM(D8:I8) -> 0
J9: =SUM(D9:I9) -> 0
J10: =SUM(D10:I10) -> 0
J11: =SUM(D11:I11) -> 0
J12: =SUM(D12:I12) -> 0
J13: =SUM(D13:I13) -> 0
J14: =SUM(D14:I14) -> 0
J15: =SUM(D15:I15) -> 0
J16: =SUM(D16:I16) -> 0
J17: =SUM(D17:I17) -> 0
J18: =SUM(D18:I18) -> 0
J19: =SUM(D19:I19) -> 0
... J22: =SUM(D22:I22) -> 0
A23: TOTAL | D23: =SUM(D4:D22) -> 0 | E23: =SUM(E4:E22) -> 0 | F23: =SUM(F4:F22) -> 0 | G23: =SUM(G4:G22) -> 100 | H23: =SUM(H4:H22) -> 110 | I23: =SUM(I4:I22) -> 10 | J23: =SUM(J4:J22) -> 220
A25: BBVA
A26: INQUILINOS | B26: COMPROBANTE | C26: DETALLE | D26: LUZ | E26: AGUA | F26: ALQUILER | G26: ESPACIO | H26: DEPOSITO | I26: TICKET | J26: TOTAL
A27: MARIBEL GOMEZ MITMA | B27: EB01-6830 | C27: 46054 | G27: 60 | J27: =SUM(D27:I27) -> 60
J28: =SUM(D28:I28) -> 0
J29: =SUM(D29:I29) -> 0
J30: =SUM(D30:I30) -> 0 | L30: TOTAL QR | M30: =J31+J39 -> 60
A31: TOTAL | J31: =SUM(J27:J30) -> 60
A33: BBVA
A34: SOCIOS | B34: RECIBO DE SERVICIO | C34: DETALLE | D34: LUZ | E34: AGUA | F34: G. ADM | G34: P. SOCIAL | H34: DEPOSITO | I34: P.S X FALLECIMIENTO | J34: TOTAL
J35: =SUM(D35:I35) -> 0
J36: =SUM(D36:I36) -> 0
J37: =SUM(D37:I37) -> 0
J38: =SUM(D38:I38) -> 0
A39: TOTAL | J39: =SUM(J35:J38) -> 0
A43: SOCIO | B43: RECIBO DE SERVICIO | C43: DETALLE | D43: LUZ | E43: AGUA | F43: G. ADM | G43: P. SOCIAL | H43: P.S X FALLECIMIENTO | I43: MULTA X CAPACITACION | J43: TOTAL
A44: MAYHUASCA CLUDY | B44: RI 32482 | C44: 45992 | D44: 330.9 | E44: 28 | J44: =SUM(D44:I44) -> 358.9
C45: 45658 | H45: 10 | J45: =SUM(D45:I45) -> 10
A46: URETA EMILIA | B46: RI 32483 | C46: 45992 | D46: 89.9 | E46: 23.4 | J46: =SUM(D46:I46) -> 113.3
A47: ESTRADA OSCAR | B47: RI 32484 | C47: 45992 | D47: 19.2 | E47: 91.7 | J47: =SUM(D47:I47) -> 110.9
C48: 45658 | F48: 56 | G48: 5 | H48: 10 | I48: 28.3 | J48: =SUM(D48:I48) -> 99.3
J49: =SUM(D49:I49) -> 0
J50: =SUM(D50:I50) -> 0
J51: =SUM(D51:I51) -> 0
J52: =SUM(D52:I52) -> 0
J53: =SUM(D53:I53) -> 0
J54: =SUM(D54:I54) -> 0
J55: =SUM(D55:I55) -> 0
J56: =SUM(D56:I56) -> 0
J57: =SUM(D57:I57) -> 0
A58: TOTAL | D58: =SUM(D44:D57) -> 440 | E58: =SUM(E44:E57) -> 143.1 | F58: =SUM(F44:F57) -> 56 | G58: =SUM(G44:G57) -> 5 | H58: =SUM(H44:H57) -> 20 | I58: =SUM(I44:I57) -> 28.3 | J58: =SUM(J44:J57) -> 692.4
A61: TOTAL DE INGRESOS | J61: =+J23+J58 -> 912.4
A64: SRTA. FATIMA SIHUE
A65: COBRANZA SOCIOS
A66: COBRANZA INQUILINOS
A69: SRA. MARIA CUYA ARANGO
A70: COBRANZA DE BAÑO DEL 1ER PISO | J70: 323
A73: COBRANZA DE BAÑO DEL 2DO PISO
A75: TOTAL GENERAL DE INGRESOS | J75: =SUM(J61:J74) -> 1235.4
A77: EGRESOS DEL DIA 09-02-2026
A78: CAJA
A79: RESPONSABLE | B79: COMPROBANTE | C79: DETALLE | J79: TOTAL
A80: CHOQUE UMPIRE JAMES FIDEL | B80: E001-45 | C80: INFORME DE MEMORIA DE CALCULO | J80: 750
A81: ORMEÑO HERNANDEZ CARLOS | B81: 620073 | C81: VACACIONES DEL SR. ORMEÑO | J81: 1651.5
A82: HERMELINDA RAMIREZ | B82: RC 8539 | C82: REEMPLAZO DE LA SRA DE LOS SSHH DEL DIA 08-02-2026 | J82: 80
A83: ROSANNA MOLERO | B83: RC 8540 | C83: LIMPIEZA DE LOS SSHH DEL SEGUNDO PISO Y LA OFICINA | J83: 70
A84: PAREDES FLORES OSCAR | B84: RC 8541 | C84: DIETA MES DE ENERO 2026 AL CARGO DE PRESIDENTE DEL CONSEJO DE ADM | J84: 600
A85: PAZ FRANCO | B85: RC 8542 | C85: 15 PANES CON HUEVO FRITO PARA LA SESION DEL CONSEJO DE ADM | J85: 30
A91: TOTAL DE EGRESOS | J91: =SUM(J80:J90) -> 3181.5
A94: RESUMEN
A95: TOTAL GENERAL | B95: =+J75 -> 1235.4
A96: TOTAL DE EGRESOS | B96: =+J91 -> 3181.5
A97: SALDO | B97: =++B95-B96 -> -1946.1

Sheet 10-02-2026
A1: INGRESOS DEL DIA 10-02-2026
A3: INQUILINO | B3: COMPROBANTE | C3: DETALLE | D3: LUZ | E3: AGUA | F3: ALQUILER | G3: ESPACIO | H3: PARQUEO | I3: TICKET | J3: TOTAL
A4: JOSE | B4: TK 50763 | C4: 46054 | I4: 10 | J4: =SUM(D4:I4) -> 10
A5: MOTA DAVID | B5: EB01-6834 | C5: 46054 | G5: 30 | J5: =SUM(D5:I5) -> 30
A6: CHAMBI SIMONA | B6: EB01-6835 | C6: 46023 | F6: 500 | J6: =SUM(D6:I6) -> 500
A7: BURGA ELMER | B7: EB01-6836 | C7: 46023 | F7: 500 | J7: =SUM(D7:I7) -> 500
A8: QUISPE PATRICIA | B8: EB01-6837 | C8: 46023 | F8: 300 | J8: =SUM(D8:I8) -> 300
A9: CARRASCO MERY | B9: EB01-6840 | C9: 46023 | F9: 220 | J9: =SUM(D9:I9) -> 220
A10: PRADO MILAGROS | B10: EB01-6842 | C10: 46023 | F10: 600 | J10: =SUM(D10:I10) -> 600
A11: PARQUEO | B11: EB01-6844 | C11: 46054 | H11: 68 | J11: =SUM(D11:I11) -> 68
J12: =SUM(D12:I12) -> 0
A13: CHAMBI SIMONA | B13: RII 3247 | C13: 45992 | D13: 10 | E13: 5 | J13: =SUM(D13:I13) -> 15
A14: QUISPE PATRICIA | B14: RII 3248 | C14: 45992 | D14: 10 | E14: 5 | J14: =SUM(D14:I14) -> 15
A15: BUSTAMANTE GRACIELA | B15: RII 3249 | C15: 45992 | D15: 6.5 | E15: 5 | J15: =SUM(D15:I15) -> 11.5
J16: =SUM(D16:I16) -> 0
J17: =SUM(D17:I17) -> 0
J18: =SUM(D18:I18) -> 0
J19: =SUM(D19:I19) -> 0
J20: =SUM(D20:I20) -> 0
J21: =SUM(D21:I21) -> 0
J22: =SUM(D22:I22) -> 0
J23: =SUM(D23:I23) -> 0
A24: TOTAL | D24: =SUM(D4:D23) -> 26.5 | E24: =SUM(E4:E23) -> 15 | F24: =SUM(F4:F23) -> 2120 | G24: =SUM(G4:G23) -> 30 | H24: =SUM(H4:H23) -> 68 | I24: =SUM(I4:I23) -> 10 | J24: =SUM(J4:J23) -> 2269.5
A26: BBVA
A27: INQUILINOS | B27: COMPROBANTE | C27: DETALLE | D27: LUZ | E27: AGUA | F27: ALQUILER | G27: ESPACIO | H27: DEPOSITO | I27: TICKET | J27: TOTAL
A28: QUISPE PATRICIA | B28: EB01-6838 | C28: 46023 | F28: 400 | J28: =SUM(D28:I28) -> 400
A29: BUSTAMANTE GRACIELA | B29: EB01-6839 | C29: 46023 | F29: 500 | J29: =SUM(D29:I29) -> 500
A30: CARRASCO MERY | B30: EB01-6841 | C30: 46023 | F30: 100 | J30: =SUM(D30:I30) -> 100
J31: =SUM(D31:I31) -> 0 | L31: TOTAL QR | M31: =J32+J44 -> 1467.2
A32: TOTAL | J32: =SUM(J28:J31) -> 1000
A34: BBVA
A35: SOCIOS | B35: RECIBO DE SERVICIO | C35: DETALLE | D35: LUZ | E35: AGUA | F35: G. ADM | G35: P. SOCIAL | H35: DEPOSITO | I35: P.S X FALLECIMIENTO | J35: TOTAL
A36: BRAVO ANA | B36: RI 32487 | C36: 45992 | D36: 109.7 | E36: 6 | J36: =SUM(D36:I36) -> 115.7
A37: SANCHEZ LUCIA | B37: RI 32488 | C37: 45962 | D37: 25 | E37: 6 | F37: 60 | G37: 5 | J37: =SUM(D37:I37) -> 96
C38: 45992 | D38: 25.3 | E38: 6 | F38: 60 | G38: 5 | J38: =SUM(D38:I38) -> 96.3
A39: MAYHUASCA ULISES | B39: RI 32489 | C39: 45962 | D39: 38.6 | E39: 6 | J39: =SUM(D39:I39) -> 44.6
C40: 45992 | D40: 33.6 | E40: 6 | J40: =SUM(D40:I40) -> 39.6
C41: 46023 | F41: 60 | G41: 5 | I41: 10 | J41: =SUM(D41:I41) -> 75
J42: =SUM(D42:I42) -> 0
J43: =SUM(D43:I43) -> 0
A44: TOTAL | J44: =SUM(J36:J43) -> 467.2
A48: SOCIO | B48: RECIBO DE SERVICIO | C48: DETALLE | D48: LUZ | E48: AGUA | F48: G. ADM | G48: P. SOCIAL | H48: P.S X FALLECIMIENTO | I48: DEPOSITO | J48: TOTAL
A49: ATANASIO MAXIMILIANA | B49: RI 32485 | C49: 45962 | D49: 44.8 | E49: 6 | J49: =SUM(D49:I49) -> 50.8
C50: 45992 | D50: 27.6 | E50: 6 | J50: =SUM(D50:I50) -> 33.6
A51: ANULADO | B51: RI 32486 | J51: =SUM(D51:I51) -> 0
A52: ROMERO ESTEBAN | B52: RI 32490 | C52: 45992 | D52: 314.8 | E52: 28.6 | J52: =SUM(D52:I52) -> 343.4
J53: =SUM(D53:I53) -> 0
J54: =SUM(D54:I54) -> 0
J55: =SUM(D55:I55) -> 0
J56: =SUM(D56:I56) -> 0
J57: =SUM(D57:I57) -> 0
J58: =SUM(D58:I58) -> 0
J59: =SUM(D59:I59) -> 0
J60: =SUM(D60:I60) -> 0
J61: =SUM(D61:I61) -> 0
J62: =SUM(D62:I62) -> 0
A63: TOTAL | D63: =SUM(D49:D62) -> 387.2 | E63: =SUM(E49:E62) -> 40.6 | F63: =SUM(F49:F62) -> 0 | G63: =SUM(G49:G62) -> 0 | H63: =SUM(H49:H62) -> 0 | I63: =SUM(I49:I62) -> 0 | J63: =SUM(J49:J62) -> 427.8
A66: TOTAL DE INGRESOS | J66: =+J24+J63 -> 2697.3
A69: SRTA. FATIMA SIHUE
A70: COBRANZA SOCIOS
A71: COBRANZA INQUILINOS
A74: SRA. MARIA CUYA ARANGO
A75: COBRANZA DE BAÑO DEL 1ER PISO | J75: 531.5
A78: COBRANZA DE BAÑO DEL 2DO PISO
A80: TOTAL GENERAL DE INGRESOS | J80: =SUM(J66:J79) -> 3228.8
A82: EGRESOS DEL DIA 10-02-2026
A83: CAJA
A84: RESPONSABLE | B84: COMPROBANTE | C84: DETALLE | J84: TOTAL
A85: AFP PRIMA | B85: 5517961663 | C85: PAGO DE AFP PRIMA | J85: 209.4
A86: AFP INTEGRA | B86: 2517960845 | C86: PAGO DE AFP INTEGRA | J86: 468.6
A87: AFP PROFUTURO | B87: 3517962031 | C87: PAGO DE AFP PROFUTURO | J87: 444.6
A88: PALOMINO HELBER | B88: RC 8543 | C88: REEMPLAZO DEL SR WILDER DEL DIA 05-02-2026 TURNO NOCHE | J88: 60
A98: TOTAL DE EGRESOS | J98: =SUM(J85:J97) -> 1182.6
A101: RESUMEN
A102: TOTAL GENERAL | B102: =+J80 -> 3228.8
A103: TOTAL DE EGRESOS | B103: =+J98 -> 1182.6
A104: SALDO | B104: =++B102-B103 -> 2046.2

Sheet 11-02-2026
A1: INGRESOS DEL DIA 11-02-2026
A3: INQUILINO | B3: COMPROBANTE | C3: DETALLE | D3: LUZ | E3: AGUA | F3: ALQUILER | G3: FUMIGACION | H3: PARQUEO | I3: DEPOSITO | J3: TOTAL
A4: QUISPE MARISOL | B4: EB01-6845 | C4: 46023 | F4: 100 | J4: =SUM(D4:I4) -> 100
A5: ANCHAYA ABEL | B5: EB01-6846 | C5: 45962 | F5: 50 | J5: =SUM(D5:I5) -> 50
C6: 45992 | F6: 50 | J6: =SUM(D6:I6) -> 50
A7: SALAZAR MARIA | B7: EB01-6849 | C7: 45962 | F7: 100 | J7: =SUM(D7:I7) -> 100
A8: ARREDONDO GLADYS | B8: EB01-6850 | C8: 46023 | F8: 90 | J8: =SUM(D8:I8) -> 90
A9: PARQUEO | B9: EB01-6852 | C9: 46054 | F9: 72 | J9: =SUM(D9:I9) -> 72
J10: =SUM(D10:I10) -> 0
J11: =SUM(D11:I11) -> 0
J12: =SUM(D12:I12) -> 0
J13: =SUM(D13:I13) -> 0
J14: =SUM(D14:I14) -> 0
J15: =SUM(D15:I15) -> 0
J16: =SUM(D16:I16) -> 0
J17: =SUM(D17:I17) -> 0
A18: CLAROS SANTOS JESUS | B18: E001-317 | C18: 46023 | F18: 100 | J18: =SUM(D18:I18) -> 100
A19: ANCHAYA ABEL | B19: RII 3250 | C19: 45931 | G19: 5 | J19: =SUM(D19:I19) -> 5
A20: SALDAÑA JESSICA | B20: RII 3220 | C20: 46023 | I20: 200 | J20: =SUM(D20:I20) -> 200
J21: =SUM(D21:I21) -> 0
J22: =SUM(D22:I22) -> 0
J23: =SUM(D23:I23) -> 0
J24: =SUM(D24:I24) -> 0
A25: TOTAL | D25: =SUM(D4:D24) -> 0 | E25: =SUM(E4:E24) -> 0 | F25: =SUM(F4:F24) -> 562 | G25: =SUM(G4:G24) -> 5 | H25: =SUM(H4:H24) -> 0 | I25: =SUM(I4:I24) -> 200 | J25: =SUM(J4:J24) -> 767
A27: BBVA
A28: INQUILINOS | B28: COMPROBANTE | C28: DETALLE | D28: LUZ | E28: AGUA | F28: ALQUILER | G28: ESPACIO | H28: DEPOSITO | I28: TICKET | J28: TOTAL
A29: MALLMA LISBETH | B29: RII 3251 | C29: 45962 | D29: 18.4 | E29: 5 | J29: =SUM(D29:I29) -> 23.4
C30: 45992 | D30: 46.1 | E30: 5 | J30: =SUM(D30:I30) -> 51.1
B31: EB01-6847 | C31: 45962 | F31: 19.3 | J31: =SUM(D31:I31) -> 19.3
C32: 45992 | F32: 56.2 | J32: =SUM(D32:I32) -> 56.2
A33: SANDRA MUJICA | B33: EB01-6848 | C33: 45992 | F33: 150 | J33: =SUM(D33:I33) -> 150
A34: ACCO VICTOR | B34: RII 3253 | C34: 45992 | H34: 150 | J34: =SUM(D34:I34) -> 150
C35: 45992 | H35: 150 | J35: =SUM(D35:I35) -> 150
C36: 46023 | H36: 150 | J36: =SUM(D36:I36) -> 150
C37: 46023 | H37: 150 | J37: =SUM(D37:I37) -> 150
J38: =SUM(D38:I38) -> 0
J39: =SUM(D39:I39) -> 0 | L39: TOTAL QR | M39: =J40+J52 -> 1718.4
A40: TOTAL | J40: =SUM(J29:J39) -> 900
A42: BBVA
A43: SOCIOS | B43: RECIBO DE SERVICIO | C43: DETALLE | D43: LUZ | E43: AGUA | F43: G. ADM | G43: P. SOCIAL | H43: DEPOSITO | I43: P.S X FALLECIMIENTO | J43: TOTAL
A44: MORENO FREDY | B44: RI 32495 | C44: 45992 | D44: 49.9 | E44: 6 | F44: 60 | G44: 5 | J44: =SUM(D44:I44) -> 120.9
A45: CERDA CARMEN | B45: RI 32496 | C45: 45962 | D45: 16.5 | E45: 6 | H45: 200 | J45: =SUM(D45:I45) -> 222.5
C46: 45992 | D46: 4 | E46: 6 | F46: 60 | G46: 5 | H46: 200 | J46: =SUM(D46:I46) -> 275
C47: 46023 | H47: 200 | J47: =SUM(D47:I47) -> 200
J48: =SUM(D48:I48) -> 0
J49: =SUM(D49:I49) -> 0
J50: =SUM(D50:I50) -> 0
J51: =SUM(D51:I51) -> 0
A52: TOTAL | J52: =SUM(J44:J51) -> 818.4
A56: SOCIO | B56: RECIBO DE SERVICIO | C56: DETALLE | D56: LUZ | E56: AGUA | F56: G. ADM | G56: P. SOCIAL | H56: P.S X FALLECIMIENTO | I56: DEPOSITO | J56: TOTAL
A57: JARA SANTOS | B57: RI 32491 | C57: 45962 | F57: 60 | G57: 5 | J57: =SUM(D57:I57) -> 65
C58: 45992 | F58: 60 | G58: 5 | J58: =SUM(D58:I58) -> 65
C59: 46023 | F59: 60 | G59: 5 | H59: 10 | J59: =SUM(D59:I59) -> 75
A60: JARA MARIA | B60: RI 32492 | C60: 45962 | D60: 67.9 | E60: 6 | J60: =SUM(D60:I60) -> 73.9
C61: 45992 | D61: 68.9 | E61: 6 | J61: =SUM(D61:I61) -> 74.9
A62: PEREZ EPIFANIA | B62: RI 32493 | C62: 45962 | F62: 60 | G62: 5 | J62: =SUM(D62:I62) -> 65
C63: 45992 | F63: 60 | G63: 5 | J63: =SUM(D63:I63) -> 65
A64: ROMERO EDDNA | B64: RI 32494 | C64: 45962 | D64: 228.5 | E64: 28.9 | F64: 36 | G64: 5 | J64: =SUM(D64:I64) -> 298.4
C65: 45992 | D65: 51.6 | J65: =SUM(D65:I65) -> 51.6
A66: CAJALEON LUIS | B66: RI 32497 | C66: 45962 | D66: 49.3 | E66: 6 | F66: 44.7 | J66: =SUM(D66:I66) -> 100
A67: ANULADO | B67: RI 32498 | J67: =SUM(D67:I67) -> 0
A68: ANULADO | B68: RI 32499 | J68: =SUM(D68:I68) -> 0
A69: QUINTANA GLICERIO | B69: RI 32500 | C69: 45992 | F69: 60 | G69: 5 | J69: =SUM(D69:I69) -> 65
C70: 46023 | F70: 60 | G70: 5 | J70: =SUM(D70:I70) -> 65
A71: CASTRO HORTENCIA | B71: RI 32501 | C71: 45962 | G71: 4.3 | J71: =SUM(D71:I71) -> 4.3
C72: 45992 | D72: 36 | E72: 6 | F72: 53.7 | J72: =SUM(D72:I72) -> 95.7
A73: MAYHUASCA MARILU | B73: RI 32502 | C73: 45992 | D73: 224.6 | E73: 23 | J73: =SUM(D73:I73) -> 247.6
C74: 46023 | H74: 10 | J74: =SUM(D74:I74) -> 10
A75: OQUENDO JESSICA | B75: RI 32503 | C75: 45962 | D75: 77 | E75: 203.9 | J75: =SUM(D75:I75) -> 280.9
C76: 45992 | D76: 76.7 | E76: 191.4 | F76: 8 | G76: 5 | J76: =SUM(D76:I76) -> 281.1
C77: 46023 | H77: 10 | J77: =SUM(D77:I77) -> 10
J78: =SUM(D78:I78) -> 0
J79: =SUM(D79:I79) -> 0
J80: =SUM(D80:I80) -> 0
J81: =SUM(D81:I81) -> 0
J82: =SUM(D82:I82) -> 0
J83: =SUM(D83:I83) -> 0
A84: TOTAL | D84: =SUM(D57:D83) -> 880.5 | E84: =SUM(E57:E83) -> 471.2 | F84: =SUM(F57:F83) -> 562.4 | G84: =SUM(G57:G83) -> 49.3 | H84: =SUM(H57:H83) -> 30 | I84: =SUM(I57:I83) -> 0 | J84: =SUM(J57:J83) -> 1993.4
A87: TOTAL DE INGRESOS | J87: =+J25+J84 -> 2760.4
A90: SRTA. FATIMA SIHUE
A91: COBRANZA SOCIOS
A92: COBRANZA INQUILINOS
A95: SRA. MARIA CUYA ARANGO
A96: COBRANZA DE BAÑO DEL 1ER PISO | J96: 477
A99: COBRANZA DE BAÑO DEL 2DO PISO
A101: TOTAL GENERAL DE INGRESOS | J101: =SUM(J87:J100) -> 3237.4
A103: EGRESOS DEL DIA 11-02-2026
A104: CAJA
A105: RESPONSABLE | B105: COMPROBANTE | C105: DETALLE | J105: TOTAL
A106: LOPEZ NELLY | B106: RC 8544 | C106: LONCHE PARA LA SESION DE COBRANZA DEL DIA 11-02-2026 | J106: 14
A119: TOTAL DE EGRESOS | J119: =SUM(J106:J118) -> 14
A122: RESUMEN
A123: TOTAL GENERAL | B123: =+J101 -> 3237.4
A124: TOTAL DE EGRESOS | B124: =+J119 -> 14
A125: SALDO | B125: =++B123-B124 -> 3223.4

Sheet 12-02-2026
A1: INGRESOS DEL DIA 12-02-2026
A3: INQUILINO | B3: COMPROBANTE | C3: DETALLE | D3: LUZ | E3: AGUA | F3: ALQUILER | G3: ESPACIO | H3: PARQUEO | I3: TICKET | J3: TOTAL
A4: JOSE | B4: TK 50764 | C4: 46054 | I4: 10 | J4: =SUM(D4:I4) -> 10
A5: CAYO BACILIO | B5: EB01-6853 | C5: 46023 | F5: 300 | J5: =SUM(D5:I5) -> 300
A6: SEGUNDO SATALAYA | B6: EB01-6856 | C6: 45962 | F6: 170 | J6: =SUM(D6:I6) -> 170
A7: COLINA SIRLEY | B7: EB01-6857 | C7: 46023 | F7: 1200 | J7: =SUM(D7:I7) -> 1200
A8: PARQUEO | B8: EB01-6859 | C8: 46054 | H8: 46.5 | J8: =SUM(D8:I8) -> 46.5
J9: =SUM(D9:I9) -> 0
J10: =SUM(D10:I10) -> 0
J11: =SUM(D11:I11) -> 0
J12: =SUM(D12:I12) -> 0
J13: =SUM(D13:I13) -> 0
J14: =SUM(D14:I14) -> 0
J15: =SUM(D15:I15) -> 0
J16: =SUM(D16:I16) -> 0
J17: =SUM(D17:I17) -> 0
J18: =SUM(D18:I18) -> 0
J19: =SUM(D19:I19) -> 0
J20: =SUM(D20:I20) -> 0
J21: =SUM(D21:I21) -> 0
A22: TOTAL | D22: =SUM(D4:D21) -> 0 | E22: =SUM(E4:E21) -> 0 | F22: =SUM(F4:F21) -> 1670 | G22: =SUM(G4:G21) -> 0 | H22: =SUM(H4:H21) -> 46.5 | I22: =SUM(I4:I21) -> 10 | J22: =SUM(J4:J21) -> 1726.5
A24: BBVA
A25: INQUILINOS | B25: COMPROBANTE | C25: DETALLE | D25: LUZ | E25: AGUA | F25: ALQUILER | G25: ESPACIO | H25: DEPOSITO | I25: TICKET | J25: TOTAL
A26: CAMARENA GABRIELA | B26: EB01-6854 | C26: 46054 | F26: 60 | J26: =SUM(D26:I26) -> 60
A27: SEGUNDO SATALAYA | B27: EB01-6855 | C27: 45962 | F27: 30 | J27: =SUM(D27:I27) -> 30
J28: =SUM(D28:I28) -> 0
J29: =SUM(D29:I29) -> 0 | L29: TOTAL QR | M29: =J30+J38 -> 90
A30: TOTAL | J30: =SUM(J26:J29) -> 90
A32: BBVA
A33: SOCIOS | B33: RECIBO DE SERVICIO | C33: DETALLE | D33: LUZ | E33: AGUA | F33: G. ADM | G33: P. SOCIAL | H33: DEPOSITO | I33: P.S X FALLECIMIENTO | J33: TOTAL
J34: =SUM(D34:I34) -> 0
J35: =SUM(D35:I35) -> 0
J36: =SUM(D36:I36) -> 0
J37: =SUM(D37:I37) -> 0
A38: TOTAL | J38: =SUM(J34:J37) -> 0
A42: SOCIO | B42: RECIBO DE SERVICIO | C42: DETALLE | D42: LUZ | E42: AGUA | F42: G. ADM | G42: P. SOCIAL | H42: P.S X FALLECIMIENTO | I42: DEPOSITO | J42: TOTAL
A43: CAMPUZANO VICENTA | B43: RI 32504 | C43: 45962 | D43: 17 | E43: 6 | J43: =SUM(D43:I43) -> 23
C44: 45992 | D44: 14.6 | E44: 6 | J44: =SUM(D44:I44) -> 20.6
J45: =SUM(D45:I45) -> 0
J46: =SUM(D46:I46) -> 0
J47: =SUM(D47:I47) -> 0
J48: =SUM(D48:I48) -> 0
J49: =SUM(D49:I49) -> 0
J50: =SUM(D50:I50) -> 0
J51: =SUM(D51:I51) -> 0
J52: =SUM(D52:I52) -> 0
J53: =SUM(D53:I53) -> 0
J54: =SUM(D54:I54) -> 0
J55: =SUM(D55:I55) -> 0
J56: =SUM(D56:I56) -> 0
A57: TOTAL | D57: =SUM(D43:D56) -> 31.6 | E57: =SUM(E43:E56) -> 12 | F57: =SUM(F43:F56) -> 0 | G57: =SUM(G43:G56) -> 0 | H57: =SUM(H43:H56) -> 0 | I57: =SUM(I43:I56) -> 0 | J57: =SUM(J43:J56) -> 43.6
A60: TOTAL DE INGRESOS | J60: =+J22+J57 -> 1770.1
A63: SRTA. FATIMA SIHUE
A64: COBRANZA SOCIOS
A65: COBRANZA INQUILINOS
A68: SRA. MARIA CUYA ARANGO
A69: COBRANZA DE BAÑO DEL 1ER PISO | J69: 455
A72: COBRANZA DE BAÑO DEL 2DO PISO
A74: TOTAL GENERAL DE INGRESOS | J74: =SUM(J60:J73) -> 2225.1
A76: EGRESOS DEL DIA 12-02-2026
A77: CAJA
A78: RESPONSABLE | B78: COMPROBANTE | C78: DETALLE | J78: TOTAL
A79: ZAPATA VICTORIANO | B79: RC 8545 | C79: COMPRA DE CERROJO PARA LA PUERTA DEL BAÑO DE VARONES DEL PRIMER PISO | J79: 5
A80: HERRERA POMA ADELINO | B80: E001-40 | C80: PINTADO DE LOS DADOS Y TORNILLOS EN LA BASE DE LAS VIGAS DE FIERRO | J80: 1000
B81: E001-41 | C81: PINTADO DE LOS DADOS Y TORNILLOS EN LA BASE DE LAS VIGAS DE FIERRO | J81: 500
A82: SALDAÑA JESSICA | B82: 986 | C82: 1 AGUA CIELO DE 2.5 LT PARA LA SESION DEL CONSEJO DE ADM. | J82: 3
A83: INVERSIONES B.L Y CIA SAC | B83: F001-00000227 | C83: 1 GASEOSA INKA DE 1.5 LT PARA LA SESION DEL CONSEJO DE ADM. | J83: 6.5
A92: TOTAL DE EGRESOS | J92: =SUM(J79:J91) -> 1514.5
A95: RESUMEN
A96: TOTAL GENERAL | B96: =+J74 -> 2225.1
A97: TOTAL DE EGRESOS | B97: =+J92 -> 1514.5
A98: SALDO | B98: =++B96-B97 -> 710.6

Sheet 13-02-2026
A1: INGRESOS DEL DIA 13-02-2026
A3: INQUILINO | B3: COMPROBANTE | C3: DETALLE | D3: LUZ | E3: AGUA | F3: ALQUILER | G3: ESPACIO | H3: PARQUEO | I3: TICKET | J3: TOTAL
A4: JOSE | B4: TK 50765 | C4: 46054 | I4: 10 | J4: =SUM(D4:I4) -> 10
A5: ARREDONDO GLADYS | B5: RII 3254 | C5: 45901 | D5: 10 | E5: 4 | J5: =SUM(D5:I5) -> 14
C6: 45931 | D6: 10 | E6: 6 | J6: =SUM(D6:I6) -> 16
C7: 45962 | D7: 10 | E7: 5 | J7: =SUM(D7:I7) -> 15
C8: 45992 | D8: 10 | E8: 5 | J8: =SUM(D8:I8) -> 15
A10: FRANCISCO CONTESOR TORRES ASTO | B10: EB01-6860 | C10: 46054 | G10: 30 | J10: =SUM(D10:I10) -> 30
A11: PARQUEO | B11: EB01-6862 | C11: 46054 | H11: 48 | J11: =SUM(D11:I11) -> 48
J12: =SUM(D12:I12) -> 0
J13: =SUM(D13:I13) -> 0
J14: =SUM(D14:I14) -> 0
J15: =SUM(D15:I15) -> 0
J16: =SUM(D16:I16) -> 0
J17: =SUM(D17:I17) -> 0
J18: =SUM(D18:I18) -> 0
J19: =SUM(D19:I19) -> 0
J20: =SUM(D20:I20) -> 0
J21: =SUM(D21:I21) -> 0
J22: =SUM(D22:I22) -> 0
A23: TOTAL | D23: =SUM(D4:D22) -> 40 | E23: =SUM(E4:E22) -> 20 | F23: =SUM(F4:F22) -> 0 | G23: =SUM(G4:G22) -> 30 | H23: =SUM(H4:H22) -> 48 | I23: =SUM(I4:I22) -> 10 | J23: =SUM(J4:J22) -> 148
A25: BBVA
A26: INQUILINOS | B26: COMPROBANTE | C26: DETALLE | D26: LUZ | E26: AGUA | F26: ALQUILER | G26: ESPACIO | H26: DEPOSITO | I26: TICKET | J26: TOTAL
J27: =SUM(D27:I27) -> 0
J28: =SUM(D28:I28) -> 0
J29: =SUM(D29:I29) -> 0
J30: =SUM(D30:I30) -> 0 | L30: TOTAL QR | M30: =J31+J39 -> 0
A31: TOTAL | J31: =SUM(J27:J30) -> 0
A33: BBVA
A34: SOCIOS | B34: RECIBO DE SERVICIO | C34: DETALLE | D34: LUZ | E34: AGUA | F34: G. ADM | G34: P. SOCIAL | H34: DEPOSITO | I34: P.S X FALLECIMIENTO | J34: TOTAL
J35: =SUM(D35:I35) -> 0
J36: =SUM(D36:I36) -> 0
J37: =SUM(D37:I37) -> 0
J38: =SUM(D38:I38) -> 0
A39: TOTAL | J39: =SUM(J35:J38) -> 0
A43: SOCIO | B43: RECIBO DE SERVICIO | C43: DETALLE | D43: LUZ | E43: AGUA | F43: G. ADM | G43: P. SOCIAL | H43: P.S X FALLECIMIENTO | I43: DEPOSITO | J43: TOTAL
A44: SERMEÑO JAVIER | B44: RI 32505 | C44: 45992 | D44: 299.9 | E44: 15 | J44: =SUM(D44:I44) -> 314.9
A45: CASTRO AQUILA | B45: RI 32506 | C45: 45992 | D45: 45 | E45: 15 | J45: =SUM(D45:I45) -> 60
A46: SALAZAR VICTORIA | B46: RI 32507 | C46: 45992 | D46: 14.6 | E46: 6 | J46: =SUM(D46:I46) -> 20.6
B47: RI 32508 | C47: 46023 | F47: 60 | G47: 5 | J47: =SUM(D47:I47) -> 65
A48: BASTDAS HERMENEGILDO | B48: RI 32509 | C48: 45962 | D48: 26.6 | E48: 8 | J48: =SUM(D48:I48) -> 34.6
C49: 45992 | D49: 23.4 | E49: 8 | J49: =SUM(D49:I49) -> 31.4
C50: 46023 | H50: 10 | J50: =SUM(D50:I50) -> 10
A51: REYES NANCY | B51: RI 32510 | C51: 46023 | F51: 60 | G51: 5 | J51: =SUM(D51:I51) -> 65
A52: VALENCIA VICENTE | B52: RI 32511 | C52: 45992 | D52: 503.3 | E52: 9.2 | J52: =SUM(D52:I52) -> 512.5
J53: =SUM(D53:I53) -> 0
J54: =SUM(D54:I54) -> 0
J55: =SUM(D55:I55) -> 0
J56: =SUM(D56:I56) -> 0
J57: =SUM(D57:I57) -> 0
A58: TOTAL | D58: =SUM(D44:D57) -> 912.8 | E58: =SUM(E44:E57) -> 61.2 | F58: =SUM(F44:F57) -> 120 | G58: =SUM(G44:G57) -> 10 | H58: =SUM(H44:H57) -> 10 | I58: =SUM(I44:I57) -> 0 | J58: =SUM(J44:J57) -> 1114
A61: TOTAL DE INGRESOS | J61: =+J23+J58 -> 1262
A64: SRTA. FATIMA SIHUE
A65: COBRANZA SOCIOS | J65: 1428 | M65: 100 | N65: 23 | O65: =N65*M65 -> 2300
A66: COBRANZA INQUILINOS | J66: 2385 | K66: =J65+J66 -> 3813 | M66: 50 | N66: 15 | O66: =N66*M66 -> 750
K67: 100 | M67: 20 | N67: 34 | O67: =N67*M67 -> 680
K68: =K66+K67 -> 3913 | M68: 10 | N68: 14 | O68: =N68*M68 -> 140
A69: SRA. MARIA CUYA ARANGO | M69: 5 | N69: 3 | O69: =N69*M69 -> 15
A70: COBRANZA DE BAÑO DEL 1ER PISO | J70: 447.5 | M70: 2 | N70: 10 | O70: =N70*M70 -> 20
M71: 1 | N71: 8 | O71: =N71*M71 -> 8
O72: =SUM(O65:O71) -> 3913
A73: COBRANZA DE BAÑO DEL 2DO PISO
A75: TOTAL GENERAL DE INGRESOS | J75: =SUM(J61:J74) -> 5522.5
A77: EGRESOS DEL DIA 13-02-2026
A78: CAJA
A79: RESPONSABLE | B79: COMPROBANTE | C79: DETALLE | J79: TOTAL
A80: MACAVILCA GIAN MARCO | B80: 812 | C80: COPIA DE 06 PLANOS DE LA COOPERATIVA | J80: 66
A81: PAREDES FLORES OSCAR | B81: RC 8546 | C81: PASAJE PARA IR A DEPOSITAR AL BANCO BBVA Y SACAR COPIA DE LOS PLANOS DE LA COOPERATIVA | J81: 12
A93: TOTAL DE EGRESOS | J93: =SUM(J80:J92) -> 78
A96: RESUMEN
A97: TOTAL GENERAL | B97: =+J75 -> 5522.5
A98: TOTAL DE EGRESOS | B98: =+J93 -> 78
A99: SALDO | B99: =++B97-B98 -> 5444.5

Sheet 14-02-2026
A1: INGRESOS DEL DIA 14-02-2026
A3: INQUILINO | B3: COMPROBANTE | C3: DETALLE | D3: LUZ | E3: AGUA | F3: ALQUILER | G3: ESPACIO | H3: PARQUEO | I3: TICKET | J3: TOTAL
A4: JOSE | B4: TK 50766 | C4: 46054 | G4: 10 | J4: =SUM(D4:I4) -> 10
A5: CAMILA | B5: TK 50767 | C5: 46054 | G5: 15 | J5: =SUM(D5:I5) -> 15
A6: QUISPE LISBETH | B6: EB01-6863 | C6: 45992 | F6: 300 | J6: =SUM(D6:I6) -> 300
A7: PIZARRO RAQUEL SONIA | B7: EB01-6864 | C7: 46054 | G7: 30 | J7: =SUM(D7:I7) -> 30
A8: PARQUEO | B8: EB01-6867 | C8: 46054 | H8: 63 | J8: =SUM(D8:I8) -> 63
J9: =SUM(D9:I9) -> 0
J10: =SUM(D10:I10) -> 0
J11: =SUM(D11:I11) -> 0
J12: =SUM(D12:I12) -> 0
J13: =SUM(D13:I13) -> 0
J14: =SUM(D14:I14) -> 0
J15: =SUM(D15:I15) -> 0
J16: =SUM(D16:I16) -> 0
J17: =SUM(D17:I17) -> 0
J18: =SUM(D18:I18) -> 0
J19: =SUM(D19:I19) -> 0
J20: =SUM(D20:I20) -> 0
... J22: =SUM(D22:I22) -> 0
A23: TOTAL | D23: =SUM(D4:D22) -> 0 | E23: =SUM(E4:E22) -> 0 | F23: =SUM(F4:F22) -> 300 | G23: =SUM(G4:G22) -> 55 | H23: =SUM(H4:H22) -> 63 | I23: =SUM(I4:I22) -> 0 | J23: =SUM(J4:J22) -> 418
A25: BBVA
A26: INQUILINOS | B26: COMPROBANTE | C26: DETALLE | D26: LUZ | E26: AGUA | F26: ALQUILER | G26: ESPACIO | H26: DEPOSITO | I26: TICKET | J26: TOTAL
J27: =SUM(D27:I27) -> 0
J28: =SUM(D28:I28) -> 0
J29: =SUM(D29:I29) -> 0
J30: =SUM(D30:I30) -> 0 | L30: TOTAL QR | M30: =J31+J39 -> 0
A31: TOTAL | J31: =SUM(J27:J30) -> 0
A33: BBVA
A34: SOCIOS | B34: RECIBO DE SERVICIO | C34: DETALLE | D34: LUZ | E34: AGUA | F34: G. ADM | G34: P. SOCIAL | H34: DEPOSITO | I34: P.S X FALLECIMIENTO | J34: TOTAL
J35: =SUM(D35:I35) -> 0
J36: =SUM(D36:I36) -> 0
J37: =SUM(D37:I37) -> 0
J38: =SUM(D38:I38) -> 0
A39: TOTAL | J39: =SUM(J35:J38) -> 0
A43: SOCIO | B43: RECIBO DE SERVICIO | C43: DETALLE | D43: LUZ | E43: AGUA | F43: G. ADM | G43: P. SOCIAL | H43: P.S X FALLECIMIENTO | I43: DEPOSITO | J43: TOTAL
J44: =SUM(D44:I44) -> 0
J45: =SUM(D45:I45) -> 0
J46: =SUM(D46:I46) -> 0
J47: =SUM(D47:I47) -> 0
J48: =SUM(D48:I48) -> 0
J49: =SUM(D49:I49) -> 0
J50: =SUM(D50:I50) -> 0
J51: =SUM(D51:I51) -> 0
J52: =SUM(D52:I52) -> 0
J53: =SUM(D53:I53) -> 0
J54: =SUM(D54:I54) -> 0
J55: =SUM(D55:I55) -> 0
... J57: =SUM(D57:I57) -> 0
A58: TOTAL | D58: =SUM(D44:D57) -> 0 | E58: =SUM(E44:E57) -> 0 | F58: =SUM(F44:F57) -> 0 | G58: =SUM(G44:G57) -> 0 | H58: =SUM(H44:H57) -> 0 | I58: =SUM(I44:I57) -> 0 | J58: =SUM(J44:J57) -> 0
A61: TOTAL DE INGRESOS | J61: =+J23+J58 -> 418
A64: SRTA. FATIMA SIHUE
A65: COBRANZA SOCIOS
A66: COBRANZA INQUILINOS
A69: SRA. MARIA CUYA ARANGO
A70: COBRANZA DE BAÑO DEL 1ER PISO | J70: 724.5
A73: COBRANZA DE BAÑO DEL 2DO PISO
A75: TOTAL GENERAL DE INGRESOS | J75: =SUM(J61:J74) -> 1142.5
A77: EGRESOS DEL DIA 14-02-2026
A78: CAJA
A79: RESPONSABLE | B79: COMPROBANTE | C79: DETALLE | J79: TOTAL
A80: MATIAS CAHUANA ACUÑA | B80: 7683 | C80: ADELANTO DE SUELDO MES DE FEBRERO 2026 | J80: 600
A81: PALOMINO SANTOS | B81: 7684 | C81: ADELANTO DE SUELDO MES DE FEBRERO 2026 | J81: 600
A82: POMACANCHARI NICANOR | B82: 7685 | C82: ADELANTO DE SUELDO MES DE FEBRERO 2026 | J82: 600
A83: TUEROS PRUDENCIO | B83: 7687 | C83: ADELANTO DE SUELDO MES DE FEBRERO 2026 | J83: 600
A84: CUYA MARIA | B84: 7688 | C84: ADELANTO DE SUELDO MES DE FEBRERO 2026 | J84: 600
A85: HURTADO WILDER | B85: 2163 | C85: ADELANTO DE SUELDO MES DE FEBRERO 2026 | J85: 450
A86: PARIASCA TATHIANA | B86: 7686 | C86: ADELANTO DE SUELDO MES DE FEBRERO 2026 | J86: 450
A87: SIHUE FATIMA | B87: 7689 | C87: ADELANTO DE SUELDO MES DE FEBRERO 2026 | J87: 600
A88: PANQUIEZ DENIS | B88: 7690 | C88: ADELANTO DE SUELDO MES DE FEBRERO 2026 | J88: 500
A92: TOTAL DE EGRESOS | J92: =SUM(J80:J91) -> 5000
A95: RESUMEN
A96: TOTAL GENERAL | B96: =+J75 -> 1142.5
A97: TOTAL DE EGRESOS | B97: =+J92 -> 5000
A98: SALDO | B98: =++B96-B97 -> -3857.5

Sheet 15-02-2026
A1: INGRESOS DEL DIA 15-02-2026
A3: INQUILINO | B3: COMPROBANTE | C3: DETALLE | D3: LUZ | E3: AGUA | F3: ALQUILER | G3: ESPACIO | H3: PARQUEO | I3: TICKET | J3: TOTAL
J4: =SUM(D4:I4) -> 0
J5: =SUM(D5:I5) -> 0
J6: =SUM(D6:I6) -> 0
J7: =SUM(D7:I7) -> 0
J8: =SUM(D8:I8) -> 0
J9: =SUM(D9:I9) -> 0
J10: =SUM(D10:I10) -> 0
J11: =SUM(D11:I11) -> 0
J12: =SUM(D12:I12) -> 0
J13: =SUM(D13:I13) -> 0
J14: =SUM(D14:I14) -> 0
J15: =SUM(D15:I15) -> 0
... J21: =SUM(D21:I21) -> 0
A22: TOTAL | D22: =SUM(D4:D21) -> 0 | E22: =SUM(E4:E21) -> 0 | F22: =SUM(F4:F21) -> 0 | G22: =SUM(G4:G21) -> 0 | H22: =SUM(H4:H21) -> 0 | I22: =SUM(I4:I21) -> 0 | J22: =SUM(J4:J21) -> 0
A24: BBVA
A25: INQUILINOS | B25: COMPROBANTE | C25: DETALLE | D25: LUZ | E25: AGUA | F25: ALQUILER | G25: ESPACIO | H25: DEPOSITO | I25: TICKET | J25: TOTAL
J26: =SUM(D26:I26) -> 0
J27: =SUM(D27:I27) -> 0
J28: =SUM(D28:I28) -> 0
J29: =SUM(D29:I29) -> 0 | L29: TOTAL QR | M29: =J30+J38 -> 0
A30: TOTAL | J30: =SUM(J26:J29) -> 0
A32: BBVA
A33: SOCIOS | B33: RECIBO DE SERVICIO | C33: DETALLE | D33: LUZ | E33: AGUA | F33: G. ADM | G33: P. SOCIAL | H33: DEPOSITO | I33: P.S X FALLECIMIENTO | J33: TOTAL
J34: =SUM(D34:I34) -> 0
J35: =SUM(D35:I35) -> 0
J36: =SUM(D36:I36) -> 0
J37: =SUM(D37:I37) -> 0
A38: TOTAL | J38: =SUM(J34:J37) -> 0
A42: SOCIO | B42: RECIBO DE SERVICIO | C42: DETALLE | D42: LUZ | E42: AGUA | F42: G. ADM | G42: P. SOCIAL | H42: P.S X FALLECIMIENTO | I42: DEPOSITO | J42: TOTAL
J43: =SUM(D43:I43) -> 0
J44: =SUM(D44:I44) -> 0
J45: =SUM(D45:I45) -> 0
J46: =SUM(D46:I46) -> 0
J47: =SUM(D47:I47) -> 0
J48: =SUM(D48:I48) -> 0
J49: =SUM(D49:I49) -> 0
J50: =SUM(D50:I50) -> 0
J51: =SUM(D51:I51) -> 0
J52: =SUM(D52:I52) -> 0
J53: =SUM(D53:I53) -> 0
J54: =SUM(D54:I54) -> 0
... J56: =SUM(D56:I56) -> 0
A57: TOTAL | D57: =SUM(D43:D56) -> 0 | E57: =SUM(E43:E56) -> 0 | F57: =SUM(F43:F56) -> 0 | G57: =SUM(G43:G56) -> 0 | H57: =SUM(H43:H56) -> 0 | I57: =SUM(I43:I56) -> 0 | J57: =SUM(J43:J56) -> 0
A60: TOTAL DE INGRESOS | J60: =+J22+J57 -> 0
A63: SRTA. FATIMA SIHUE
A64: COBRANZA SOCIOS
A65: COBRANZA INQUILINOS
A68: SRA. MARIA CUYA ARANGO
A69: COBRANZA DE BAÑO DEL 1ER PISO | J69: 216
A72: COBRANZA DE BAÑO DEL 2DO PISO
A74: TOTAL GENERAL DE INGRESOS | J74: =SUM(J60:J73) -> 216
A76: EGRESOS DEL DIA 15-02-2026
A77: CAJA
A78: RESPONSABLE | B78: COMPROBANTE | C78: DETALLE | J78: TOTAL
A92: TOTAL DE EGRESOS | J92: =SUM(J79:J91) -> 0
A95: RESUMEN
A96: TOTAL GENERAL | B96: =+J74 -> 216
A97: TOTAL DE EGRESOS | B97: =+J92 -> 0
A98: SALDO | B98: =++B96-B97 -> 216

Sheet 16-02-2026
A1: INGRESOS DEL DIA 16-02-2026
A3: INQUILINO | B3: COMPROBANTE | C3: DETALLE | D3: LUZ | E3: AGUA | F3: ALQUILER | G3: ESPACIO | H3: PARQUEO | I3: MULTA POR CAPACITACION | J3: TOTAL
A4: CAMARENA GABRIELA | B4: EB01-6869 | C4: 46054 | G4: 60 | J4: =SUM(D4:I4) -> 60
A5: QUISPE MARISOL | B5: EB01-6870 | C5: 46023 | F5: 50 | J5: =SUM(D5:I5) -> 50
A6: PARQUEO | B6: EB01-6872 | C6: 46054 | H6: 51.5 | J6: =SUM(D6:I6) -> 51.5
J7: =SUM(D7:I7) -> 0
J8: =SUM(D8:I8) -> 0
J9: =SUM(D9:I9) -> 0
J10: =SUM(D10:I10) -> 0
J11: =SUM(D11:I11) -> 0
J12: =SUM(D12:I12) -> 0
A13: PRADO MILAGROS | B13: RII 3255 | C13: 46023 | I13: 28.3 | J13: =SUM(D13:I13) -> 28.3
J14: =SUM(D14:I14) -> 0
J15: =SUM(D15:I15) -> 0
J16: =SUM(D16:I16) -> 0
J17: =SUM(D17:I17) -> 0
J18: =SUM(D18:I18) -> 0
J19: =SUM(D19:I19) -> 0
J20: =SUM(D20:I20) -> 0
A21: TOTAL | D21: =SUM(D4:D20) -> 0 | E21: =SUM(E4:E20) -> 0 | F21: =SUM(F4:F20) -> 50 | G21: =SUM(G4:G20) -> 60 | H21: =SUM(H4:H20) -> 51.5 | I21: =SUM(I4:I20) -> 28.3 | J21: =SUM(J4:J20) -> 189.8
A23: BBVA
A24: INQUILINOS | B24: COMPROBANTE | C24: DETALLE | D24: LUZ | E24: AGUA | F24: ALQUILER | G24: ESPACIO | H24: DEPOSITO | I24: TICKET | J24: TOTAL
J25: =SUM(D25:I25) -> 0
J26: =SUM(D26:I26) -> 0
J27: =SUM(D27:I27) -> 0
J28: =SUM(D28:I28) -> 0 | L28: TOTAL QR | M28: =J29+J39 -> 510
A29: TOTAL | J29: =SUM(J25:J28) -> 0
A31: BBVA
A32: SOCIOS | B32: RECIBO DE SERVICIO | C32: DETALLE | D32: LUZ | E32: AGUA | F32: G. ADM | G32: P. SOCIAL | H32: DEPOSITO | I32: P.S X FALLECIMIENTO | J32: TOTAL
A33: HALIRE JOSUE | B33: RI 32513 | C33: 45962 | D33: 24.7 | E33: 7 | H33: 200 | J33: =SUM(D33:I33) -> 231.7
C34: 45992 | D34: 25.8 | E34: 6.1 | H34: 200 | J34: =SUM(D34:I34) -> 231.9
C35: 46023 | D35: 28.4 | E35: 8 | I35: 10 | J35: =SUM(D35:I35) -> 46.4
J38: =SUM(D38:I38) -> 0
A39: TOTAL | J39: =SUM(J33:J38) -> 510
A43: SOCIO | B43: RECIBO DE SERVICIO | C43: DETALLE | D43: LUZ | E43: AGUA | F43: G. ADM | G43: P. SOCIAL | H43: P.S X FALLECIMIENTO | I43: DEPOSITO | J43: TOTAL
A44: RIVERA JUANA | B44: RI 32512 | C44: 45962 | D44: 31.3 | E44: 6 | J44: =SUM(D44:I44) -> 37.3
C45: 45992 | D45: 31.8 | E45: 6 | J45: =SUM(D45:I45) -> 37.8
C46: 46054 | D46: 30.9 | E46: 5 | J46: =SUM(D46:I46) -> 35.9
A47: HALIRE JOSUE | B47: RI 32514 | C47: 46023 | E47: 0.1 | J47: =SUM(D47:I47) -> 0.1
A48: CCOYLLO POLANCO DANIEL | B48: RI 32515 | C48: 46023 | D48: 325.6 | E48: 5 | F48: 60 | G48: 5 | J48: =SUM(D48:I48) -> 395.6
A49: REYES NANCY | B49: RI 32516 | C49: 46023 | D49: 245.7 | E49: 6 | J49: =SUM(D49:I49) -> 251.7
J50: =SUM(D50:I50) -> 0
J51: =SUM(D51:I51) -> 0
J52: =SUM(D52:I52) -> 0
J53: =SUM(D53:I53) -> 0
J54: =SUM(D54:I54) -> 0
J55: =SUM(D55:I55) -> 0
J56: =SUM(D56:I56) -> 0
J57: =SUM(D57:I57) -> 0
A58: TOTAL | D58: =SUM(D47:D57) -> 571.3 | E58: =SUM(E47:E57) -> 11.1 | F58: =SUM(F47:F57) -> 60 | G58: =SUM(G47:G57) -> 5 | H58: =SUM(H47:H57) -> 0 | I58: =SUM(I47:I57) -> 0 | J58: =SUM(J44:J57) -> 758.4
A61: TOTAL DE INGRESOS | J61: =+J21+J58 -> 948.2
A64: SRTA. FATIMA SIHUE
A65: COBRANZA SOCIOS
A66: COBRANZA INQUILINOS
A69: SRA. MARIA CUYA ARANGO
A70: COBRANZA DE BAÑO DEL 1ER PISO | J70: 323
A73: COBRANZA DE BAÑO DEL 2DO PISO
A75: TOTAL GENERAL DE INGRESOS | J75: =SUM(J61:J74) -> 1271.2
A77: EGRESOS DEL DIA 16-02-2026
A78: CAJA
A79: RESPONSABLE | B79: COMPROBANTE | C79: DETALLE | J79: TOTAL
A80: RAMIREZ HERMELINDA | B80: RC 8547 | C80: REEMPLAZO DE LA SRA DE LOS SSHH DEL DIA 15-02-2026 | J80: 80
A90: TOTAL DE EGRESOS | J90: =SUM(J80:J89) -> 80
A93: RESUMEN
A94: TOTAL GENERAL | B94: =+J75 -> 1271.2
A95: TOTAL DE EGRESOS | B95: =+J90 -> 80
A96: SALDO | B96: =++B94-B95 -> 1191.2

Sheet 17-02-2026
A1: INGRESOS DEL DIA 17-02-2026
A3: INQUILINO | B3: COMPROBANTE | C3: DETALLE | D3: LUZ | E3: AGUA | F3: ALQUILER | G3: ESPACIO | H3: PARQUEO | I3: TICKET | J3: TOTAL
A4: JOSE DESARMADORES | B4: TK 50768 | C4: 46054 | I4: 10 | J4: =SUM(D4:I4) -> 10
A5: JOSE | B5: TK 50769 | C5: 46054 | I5: 10 | J5: =SUM(D5:I5) -> 10
A6: JOSE | B6: TK 50770 | C6: 46054 | I6: 10 | J6: =SUM(D6:I6) -> 10
A7: PEÑA TERESA | B7: EB01-6873 | C7: 46023 | F7: 600 | J7: =SUM(D7:I7) -> 600
A8: ALARCON MARTHA | B8: EB01-6874 | C8: 46023 | F8: 550 | J8: =SUM(D8:I8) -> 550
A9: PARQUEO | B9: EB01-6876 | C9: 46054 | H9: 45 | J9: =SUM(D9:I9) -> 45
J10: =SUM(D10:I10) -> 0
J11: =SUM(D11:I11) -> 0
J12: =SUM(D12:I12) -> 0
J13: =SUM(D13:I13) -> 0
A14: PEÑA TERESA | B14: RII 3256 | C14: 45931 | E14: 6 | J14: =SUM(D14:I14) -> 6
C15: 45962 | D15: 10 | E15: 5 | J15: =SUM(D15:I15) -> 15
C16: 45992 | D16: 10 | E16: 5 | J16: =SUM(D16:I16) -> 15
C17: 46023 | D17: 15 | E17: 3 | J17: =SUM(D17:I17) -> 18
A18: ALARCON MARTHA | B18: RII 3257 | C18: 46023 | D18: 36 | E18: 15 | J18: =SUM(D18:I18) -> 51
J19: =SUM(D19:I19) -> 0
J20: =SUM(D20:I20) -> 0
J21: =SUM(D21:I21) -> 0
A22: TOTAL | D22: =SUM(D4:D21) -> 71 | E22: =SUM(E4:E21) -> 34 | F22: =SUM(F4:F21) -> 1150 | G22: =SUM(G4:G21) -> 0 | H22: =SUM(H4:H21) -> 45 | I22: =SUM(I4:I21) -> 30 | J22: =SUM(J4:J21) -> 1330
A24: BBVA
A25: INQUILINOS | B25: COMPROBANTE | C25: DETALLE | D25: LUZ | E25: AGUA | F25: ALQUILER | G25: ESPACIO | H25: DEPOSITO | I25: TICKET | J25: TOTAL
J26: =SUM(D26:I26) -> 0
J27: =SUM(D27:I27) -> 0
J28: =SUM(D28:I28) -> 0
J29: =SUM(D29:I29) -> 0 | L29: TOTAL QR | M29: =J30+J40 -> 462.4
A30: TOTAL | J30: =SUM(J26:J29) -> 0
A32: BBVA
A33: SOCIOS | B33: RECIBO DE SERVICIO | C33: DETALLE | D33: LUZ | E33: AGUA | F33: G. ADM | G33: P. SOCIAL | H33: DEPOSITO | I33: P.S X FALLECIMIENTO | J33: TOTAL
A34: GAVILAN NORMA | B34: RI 32521 | C34: 46023 | D34: 25.7 | E34: 108.4 | J34: =SUM(D34:I34) -> 134.1
A35: CALDERON ESTELA | B35: RI 32523 | C35: 45992 | D35: 89.9 | E35: 6 | F35: 60 | G35: 5 | J35: =SUM(D35:I35) -> 160.9
C36: 46023 | D36: 87.4 | E36: 5 | F36: 60 | G36: 5 | I36: 10 | J36: =SUM(D36:I36) -> 167.4
J39: =SUM(D39:I39) -> 0
A40: TOTAL | J40: =SUM(J34:J39) -> 462.4
A44: SOCIO | B44: RECIBO DE SERVICIO | C44: DETALLE | D44: LUZ | E44: AGUA | F44: G. ADM | G44: P. SOCIAL | H44: P.S X FALLECIMIENTO | I44: DEPOSITO | J44: TOTAL
A45: PAREDES FLORES OSCAR | B45: RI 32517 | C45: 45992 | D45: 150.4 | E45: 6 | J45: =SUM(D45:I45) -> 156.4
A46: ROMERO JAVIER | B46: RI 32518 | C46: 45962 | D46: 60.4 | E46: 6 | J46: =SUM(D46:I46) -> 66.4
C47: 45992 | D47: 61.3 | E47: 6 | J47: =SUM(D47:I47) -> 67.3
C48: 46023 | D48: 59.6 | E48: 5 | J48: =SUM(D48:I48) -> 64.6
A49: SALAS RUTH | B49: RI 32519 | C49: 45962 | D49: 66.5 | E49: 6 | J49: =SUM(D49:I49) -> 72.5
C50: 45992 | D50: 67.5 | E50: 6 | J50: =SUM(D50:I50) -> 73.5
C51: 46023 | D51: 65.6 | E51: 5 | J51: =SUM(D51:I51) -> 70.6
A52: MEDINA HONORATA | B52: RI 32520 | C52: 46023 | D52: 4 | E52: 5 | F52: 60 | G52: 5 | H52: 10 | J52: =SUM(D52:I52) -> 84
A53: SORIA TAPIA EDITH | B53: RI 32522 | C53: 45992 | D53: 32.9 | E53: 6 | F53: 60 | G53: 5 | J53: =SUM(D53:I53) -> 103.9
C54: 46023 | D54: 32 | E54: 5 | F54: 60 | G54: 5 | J54: =SUM(D54:I54) -> 102
J55: =SUM(D55:I55) -> 0
J56: =SUM(D56:I56) -> 0
J57: =SUM(D57:I57) -> 0
J58: =SUM(D58:I58) -> 0
J59: =SUM(D59:I59) -> 0
J60: =SUM(D60:I60) -> 0
A61: TOTAL | D61: =SUM(D45:D60) -> 600.2 | E61: =SUM(E45:E60) -> 56 | F61: =SUM(F45:F60) -> 180 | G61: =SUM(G45:G60) -> 15 | H61: =SUM(H45:H60) -> 10 | I61: =SUM(I45:I60) -> 0 | J61: =SUM(J45:J60) -> 861.2
A64: TOTAL DE INGRESOS | J64: =+J22+J61 -> 2191.2
A67: SRTA. FATIMA SIHUE
A68: COBRANZA SOCIOS
A69: COBRANZA INQUILINOS
A72: SRA. MARIA CUYA ARANGO
A73: COBRANZA DE BAÑO DEL 1ER PISO | J73: 437.5
A76: COBRANZA DE BAÑO DEL 2DO PISO
A78: TOTAL GENERAL DE INGRESOS | J78: =SUM(J64:J77) -> 2628.7
A80: EGRESOS DEL DIA 17-02-2026
A81: CAJA
A82: RESPONSABLE | B82: COMPROBANTE | C82: DETALLE | J82: TOTAL
A83: HUAMAN TACURI JESUS ALBERTO | B83: E001- 15 | C83: MATERIALES PARA SERVICIO DE MONTAJE DE 02 ESTABILIZADORES PARA TRINQUETES DE LOS SSHH DEL PRIMER PISO | J83: 155
A93: TOTAL DE EGRESOS | J93: =SUM(J83:J92) -> 155
A96: RESUMEN
A97: TOTAL GENERAL | B97: =+J78 -> 2628.7
A98: TOTAL DE EGRESOS | B98: =+J93 -> 155
A99: SALDO | B99: =++B97-B98 -> 2473.7

Sheet 18-02-2026
A1: INGRESOS DEL DIA 18-02-2026
A3: INQUILINO | B3: COMPROBANTE | C3: DETALLE | D3: LUZ | E3: AGUA | F3: ALQUILER | G3: ESPACIO | H3: PARQUEO | I3: TICKET | J3: TOTAL
A4: JOSE | B4: TK 50771 | C4: 46054 | I4: 10 | J4: =SUM(D4:I4) -> 10
A5: HERRERA ORFELITA | B5: EB01-6877 | C5: 46023 | F5: 600 | J5: =SUM(D5:I5) -> 600
A6: QUISPE MARISOL | B6: EB01-6878 | C6: 46023 | F6: 100 | J6: =SUM(D6:I6) -> 100
A7: ANCHAYA ABEL | B7: EB01-6880 | C7: 45992 | F7: 150 | J7: =SUM(D7:I7) -> 150
A8: SATALAYA SEGUNDO | B8: EB01-6881 | C8: 45962 | F8: 140 | J8: =SUM(D8:I8) -> 140
A9: MALLMA LISBETH | B9: EB01-6882 | C9: 45992 | F9: 143.8 | J9: =SUM(D9:I9) -> 143.8
C10: 46023 | F10: 6.2 | J10: =SUM(D10:I10) -> 6.2
A11: MUJICA SANDRA | B11: EB01-6883 | C11: 45992 | F11: 32.4 | J11: =SUM(D11:I11) -> 32.4
C12: 46023 | F12: 101 | J12: =SUM(D12:I12) -> 101
A13: AZURZA DAYSI | B13: EB01-6885 | C13: 46023 | F13: 40 | J13: =SUM(D13:I13) -> 40
A14: BENITES ERIKA | B14: EB01-6886 | C14: 46023 | F14: 200 | J14: =SUM(D14:I14) -> 200
A15: ARREDONDO GLADIS | B15: EB01-6887 | C15: 45992 | F15: 100 | J15: =SUM(D15:I15) -> 100
A16: FLORES DOMINICA | B16: EB01-6888 | C16: 46023 | F16: 200 | J16: =SUM(D16:I16) -> 200
A17: CONDORI LIDIA | B17: EB01-6889 | C17: 45992 | F17: 150 | J17: =SUM(D17:I17) -> 150
A18: PARQUEO | B18: EB01-6891 | C18: 46054 | H18: 53 | J18: =SUM(D18:I18) -> 53
J19: =SUM(D19:I19) -> 0
A20: CLAROS SANTOS JESUS | B20: E001-319 | C20: 46023 | F20: 50 | J20: =SUM(D20:I20) -> 50
J21: =SUM(D21:I21) -> 0
J22: =SUM(D22:I22) -> 0
A23: MUJICA SANDRA | B23: RII 3259 | C23: 45992 | D23: 11.6 | E23: 5 | J23: =SUM(D23:I23) -> 16.6
A24: CONDORI LIDIA | B24: RII 3260 | C24: 46023 | D24: 7.6 | E24: 3 | J24: =SUM(D24:I24) -> 10.6
J25: =SUM(D25:I25) -> 0
J26: =SUM(D26:I26) -> 0
J27: =SUM(D27:I27) -> 0
J28: =SUM(D28:I28) -> 0
A29: TOTAL | D29: =SUM(D4:D28) -> 19.2 | E29: =SUM(E4:E28) -> 8 | F29: =SUM(F4:F28) -> 2013.4 | G29: =SUM(G4:G28) -> 0 | H29: =SUM(H4:H28) -> 53 | I29: =SUM(I4:I28) -> 10 | J29: =SUM(J4:J28) -> 2103.6
A31: BBVA
A32: INQUILINOS | B32: COMPROBANTE | C32: DETALLE | D32: LUZ | E32: AGUA | F32: ALQUILER | G32: ESPACIO | H32: DEPOSITO | I32: TICKET | J32: TOTAL
A33: CLAROS SANTOS JESUS | B33: E001-318 | C33: 46023 | F33: 100 | J33: =SUM(D33:I33) -> 100
A34: ASAEL CASTILLO | B34: EB01-6879 | C34: 46023 | F34: 700 | J34: =SUM(D34:I34) -> 700
A35: AZURZA DAYSI | B35: EB01-6884 | C35: 46023 | F35: 160 | J35: =SUM(D35:I35) -> 160
A36: ASAEL CASTILLO | B36: RII 3258 | C36: 45992 | D36: 26.6 | E36: 5 | J36: =SUM(D36:I36) -> 31.6
J37: =SUM(D37:I37) -> 0
J38: =SUM(D38:I38) -> 0 | L38: TOTAL QR | M38: =J39+J50 -> 1592.9
A39: TOTAL | J39: =SUM(J33:J38) -> 991.6
A41: BBVA
A42: SOCIOS | B42: RECIBO DE SERVICIO | C42: DETALLE | D42: LUZ | E42: AGUA | F42: G. ADM | G42: P. SOCIAL | H42: DEPOSITO | I42: P.S X FALLECIMIENTO | J42: TOTAL
A43: ROJAS LIONILA | B43: RI 32527 | C43: 45962 | D43: 68.5 | E43: 6 | J43: =SUM(D43:I43) -> 74.5
C44: 45992 | D44: 69.5 | E44: 6 | J44: =SUM(D44:I44) -> 75.5
C45: 46023 | D45: 50 | J45: =SUM(D45:I45) -> 50
A46: CALLE ALVAREZ MARCO | B46: RI 32534 | C46: 45992 | H46: 200 | J46: =SUM(D46:I46) -> 200
A47: CAHUANA VICENTINA | B47: RI 32536 | C47: 45992 | D47: 54.7 | E47: 136.6 | J47: =SUM(D47:I47) -> 191.3
A48: SORIA TAPIA EDITH | B48: RI 32537 | C48: 46023 | I48: 10 | J48: =SUM(D48:I48) -> 10
J49: =SUM(D49:I49) -> 0
A50: TOTAL | J50: =SUM(J43:J49) -> 601.3
A54: SOCIO | B54: RECIBO DE SERVICIO | C54: DETALLE | D54: LUZ | E54: AGUA | F54: G. ADM | G54: P. SOCIAL | H54: P.S X FALLECIMIENTO | I54: DEPOSITO | J54: TOTAL
A55: PORRAS OLIMPIA | B55: RI 32524 | C55: 45931 | D55: 6.4 | E55: 7 | J55: =SUM(D55:I55) -> 13.4
C56: 45962 | D56: 6.5 | E56: 6 | F56: 60 | G56: 5 | J56: =SUM(D56:I56) -> 77.5
C57: 45992 | D57: 5.8 | E57: 6 | F57: 60 | G57: 5 | J57: =SUM(D57:I57) -> 76.8
B58: RI 32525 | C58: 46023 | D58: 6.3 | E58: 5 | F58: 60 | G58: 5 | H58: 10 | J58: =SUM(D58:I58) -> 86.3
A59: PAREDES DIANA | B59: RI 32526 | C59: 45962 | D59: 66.5 | E59: 6 | J59: =SUM(D59:I59) -> 72.5
C60: 45992 | D60: 67.5 | E60: 6 | J60: =SUM(D60:I60) -> 73.5
A61: ROJAS LIONILA | B61: RI 32528 | C61: 46023 | D61: 17.5 | E61: 5 | J61: =SUM(D61:I61) -> 22.5
A62: SANTILLAN ZOILA | B62: RI 32529 | C62: 45962 | D62: 33.6 | E62: 6 | J62: =SUM(D62:I62) -> 39.6
C63: 45992 | D63: 34.9 | E63: 6 | J63: =SUM(D63:I63) -> 40.9
A64: MEDINA VICENTA | B64: RI 32530 | C64: 45992 | D64: 140.6 | E64: 6 | J64: =SUM(D64:I64) -> 146.6
A65: FALCON HECTOR | B65: RI 32531 | C65: 45962 | D65: 33.3 | E65: 6 | J65: =SUM(D65:I65) -> 39.3
A66: CUYA ALBERTO | B66: RI 32532 | C66: 45962 | D66: 41.1 | E66: 6 | J66: =SUM(D66:I66) -> 47.1
A67: MAYTA MATOS HERMELINDA | B67: RI 32533 | C67: 45992 | E67: 43.9 | F67: 60 | G67: 5 | J67: =SUM(D67:I67) -> 108.9
A68: TELLO EDGAR | B68: RI 32535 | C68: 45962 | E68: 113.2 | J68: =SUM(D68:I68) -> 113.2
C69: 45992 | D69: 47.7 | E69: 218.6 | J69: =SUM(D69:I69) -> 266.3
C70: 45658 | F70: 60 | G70: 5 | J70: =SUM(D70:I70) -> 65
J71: =SUM(D71:I71) -> 0
J72: =SUM(D72:I72) -> 0
J73: =SUM(D73:I73) -> 0
A74: TOTAL | D74: =SUM(D55:D73) -> 507.7 | E74: =SUM(E55:E73) -> 446.7 | F74: =SUM(F55:F73) -> 300 | G74: =SUM(G55:G73) -> 25 | H74: =SUM(H55:H73) -> 10 | I74: =SUM(I55:I73) -> 0 | J74: =SUM(J55:J73) -> 1289.4
A77: TOTAL DE INGRESOS | J77: =+J29+J74 -> 3393
A80: SRTA. FATIMA SIHUE
A81: COBRANZA SOCIOS
A82: COBRANZA INQUILINOS
A85: SRA. MARIA CUYA ARANGO
A86: COBRANZA DE BAÑO DEL 1ER PISO | J86: 429.5
A89: COBRANZA DE BAÑO DEL 2DO PISO
A91: TOTAL GENERAL DE INGRESOS | J91: =SUM(J77:J90) -> 3822.5
A93: EGRESOS DEL DIA 18-02-2026
A94: CAJA
A95: RESPONSABLE | B95: COMPROBANTE | C95: DETALLE | J95: TOTAL
A96: SUNAT | B96: 1173758272 | C96: 5310 SNP-LEY 19990 | J96: 560
A97: SUNAT | B97: 1173758273 | C97: 5210 ESSALUD | J97: 1243
A98: SUNAT | B98: 1173758274 | C98: 3042 RENTA 4 TA. CATEG. RETENCIONES | J98: 325
A99: MACAVILCA GIAN | B99: 965 | C99: IMPRESIÓN DE 6 PLANOS COLOR A1 | J99: 40
A100: DELTRON | B100: F103-01091949 | C100: 3 ESTABILIZADORES PARA LOS SSHH | J100: 161.4
A109: TOTAL DE EGRESOS | J109: =SUM(J96:J108) -> 2329.4
A112: RESUMEN
A113: TOTAL GENERAL | B113: =+J91 -> 3822.5
A114: TOTAL DE EGRESOS | B114: =+J109 -> 2329.4
A115: SALDO | B115: =++B113-B114 -> 1493.1

Sheet 19-02-2026
A1: INGRESOS DEL DIA 19-02-2026
A3: INQUILINO | B3: COMPROBANTE | C3: DETALLE | D3: LUZ | E3: AGUA | F3: ALQUILER | G3: ESPACIO | H3: PARQUEO | I3: TICKET | J3: TOTAL
A4: JOSE | B4: TK 50772 | C4: 46054 | I4: 10 | J4: =SUM(D4:I4) -> 10
A5: AIRE HECTOR | B5: EB01-6892 | C5: 46023 | F5: 300 | J5: =SUM(D5:I5) -> 300
A6: CUNIAS MARIELA | B6: EB01-6893 | C6: 46054 | F6: 50 | J6: =SUM(D6:I6) -> 50
A7: PARQUEO | B7: EB01-6896 | C7: 46054 | H7: 70.3 | J7: =SUM(D7:I7) -> 70.3
J8: =SUM(D8:I8) -> 0
J9: =SUM(D9:I9) -> 0
J10: =SUM(D10:I10) -> 0
A11: AIRE HECTOR | B11: RII 3261 | C11: 45992 | D11: 17 | E11: 12 | J11: =SUM(D11:I11) -> 29
C12: 46023 | D12: 17 | E12: 11 | J12: =SUM(D12:I12) -> 28
A13: CUNIAS MARIELA | B13: RII 3262 | C13: 45901 | D13: 8 | E13: 4 | J13: =SUM(D13:I13) -> 12
C14: 45931 | D14: 6 | E14: 2 | J14: =SUM(D14:I14) -> 8
J15: =SUM(D15:I15) -> 0
J16: =SUM(D16:I16) -> 0
J17: =SUM(D17:I17) -> 0
J18: =SUM(D18:I18) -> 0
J19: =SUM(D19:I19) -> 0
J20: =SUM(D20:I20) -> 0
J21: =SUM(D21:I21) -> 0
A22: TOTAL | D22: =SUM(D4:D21) -> 48 | E22: =SUM(E4:E21) -> 29 | F22: =SUM(F4:F21) -> 350 | G22: =SUM(G4:G21) -> 0 | H22: =SUM(H4:H21) -> 70.3 | I22: =SUM(I4:I21) -> 10 | J22: =SUM(J4:J21) -> 507.3
A24: BBVA
A25: INQUILINOS | B25: COMPROBANTE | C25: DETALLE | D25: LUZ | E25: AGUA | F25: ALQUILER | G25: ESPACIO | H25: DEPOSITO | I25: TICKET | J25: TOTAL
A26: CUNIAS MARIELA | B26: EB01-6894 | C26: 46054 | F26: 450 | J26: =SUM(D26:I26) -> 450
J27: =SUM(D27:I27) -> 0
J28: =SUM(D28:I28) -> 0
J29: =SUM(D29:I29) -> 0 | L29: TOTAL QR | M29: =J30+J38 -> 450
A30: TOTAL | J30: =SUM(J26:J29) -> 450
A32: BBVA
A33: SOCIOS | B33: RECIBO DE SERVICIO | C33: DETALLE | D33: LUZ | E33: AGUA | F33: G. ADM | G33: P. SOCIAL | H33: DEPOSITO | I33: P.S X FALLECIMIENTO | J33: TOTAL
J34: =SUM(D34:I34) -> 0
J35: =SUM(D35:I35) -> 0
J36: =SUM(D36:I36) -> 0
J37: =SUM(D37:I37) -> 0
A38: TOTAL | J38: =SUM(J34:J37) -> 0
A42: SOCIO | B42: RECIBO DE SERVICIO | C42: DETALLE | D42: LUZ | E42: AGUA | F42: G. ADM | G42: P. SOCIAL | H42: P.S X FALLECIMIENTO | I42: DEPOSITO | J42: TOTAL
A43: ANULADO | B43: RI 32538 | J43: =SUM(D43:I43) -> 0
A44: CALLE ALVAREZ MARCO | B44: RI 32539 | C44: 45992 | D44: 10.7 | E44: 6 | J44: =SUM(D44:I44) -> 16.7
B45: RI 32540 | C45: 46023 | D45: 10.7 | E45: 5 | J45: =SUM(D45:I45) -> 15.7
A46: CALLE FIDEL | B46: RI 32541 | C46: 46023 | F46: 60 | G46: 5 | H46: 10 | J46: =SUM(D46:I46) -> 75
J47: =SUM(D47:I47) -> 0
J48: =SUM(D48:I48) -> 0
J49: =SUM(D49:I49) -> 0
J50: =SUM(D50:I50) -> 0
J51: =SUM(D51:I51) -> 0
J52: =SUM(D52:I52) -> 0
J53: =SUM(D53:I53) -> 0
J54: =SUM(D54:I54) -> 0
J55: =SUM(D55:I55) -> 0
J56: =SUM(D56:I56) -> 0
A57: TOTAL | D57: =SUM(D43:D56) -> 21.4 | E57: =SUM(E43:E56) -> 11 | F57: =SUM(F43:F56) -> 60 | G57: =SUM(G43:G56) -> 5 | H57: =SUM(H43:H56) -> 10 | I57: =SUM(I43:I56) -> 0 | J57: =SUM(J43:J56) -> 107.4
A60: TOTAL DE INGRESOS | J60: =+J22+J57 -> 614.7
A63: SRTA. FATIMA SIHUE
A64: COBRANZA SOCIOS
A65: COBRANZA INQUILINOS
A68: SRA. MARIA CUYA ARANGO
A69: COBRANZA DE BAÑO DEL 1ER PISO | J69: 463.5
A72: COBRANZA DE BAÑO DEL 2DO PISO
A74: TOTAL GENERAL DE INGRESOS | J74: =SUM(J60:J73) -> 1078.2
A76: EGRESOS DEL DIA 19-02-2026
A77: CAJA
A78: RESPONSABLE | B78: COMPROBANTE | C78: DETALLE | J78: TOTAL
A79: AGUIRRE WILFREDO | B79: RC 8548 | C79: PREVISION SOCIAL POR SALUD AL SOCIO AGUIRRE WILFREDO | J79: 600
A80: AYALA MARLENE | B80: 7996 | C80: 1 AGUA CIELO DE 2.5 LT PARA LA SESION DEL CONSEJO DE ADM. | J80: 3
A81: TRIGO DE ORO | B81: FA01-00012540 | C81: 1 GASEOSA DE 3LT+ 15 PANES+JAMONADA Y QUESO PARA EL LONCHE DEL CONSEJO DE ADM. | J81: 52.3
A82: SANTOS JARA | B82: 6720 | C82: 1 CAFÉ Y AZUCAR PARA LOS VIGILANTES DEL TURNO NOCHE | J82: 35.7
A90: TOTAL DE EGRESOS | J90: =SUM(J79:J89) -> 691
A93: RESUMEN
A94: TOTAL GENERAL | B94: =+J74 -> 1078.2
A95: TOTAL DE EGRESOS | B95: =+J90 -> 691
A96: SALDO | B96: =++B94-B95 -> 387.2

Sheet 20-02-2026
A1: INGRESOS DEL DIA 20-02-2026
A3: INQUILINO | B3: COMPROBANTE | C3: DETALLE | D3: LUZ | E3: AGUA | F3: ALQUILER | G3: OTROS | H3: PARQUEO | I3: TICKET | J3: TOTAL
A4: JOSE | B4: TK 50773 | C4: 46054 | I4: 10 | J4: =SUM(D4:I4) -> 10
A5: ARREDONDO GLADYS | B5: EB01-6898 | C5: 46023 | F5: 100 | J5: =SUM(D5:I5) -> 100
A6: PARQUEO | B6: EB01-6899 | C6: 46054 | H6: 59 | J6: =SUM(D6:I6) -> 59
A7: PRETEL LUCAS (MAQUINA DE CHICLES) | B7: 10893 | C7: 46054 | G7: 45.2 | J7: =SUM(D7:I7) -> 45.2
J8: =SUM(D8:I8) -> 0
A9: AYALA MARLENE | B9: RI 3263 | C9: 46023 | D9: 117.2 | E9: 3 | J9: =SUM(D9:I9) -> 120.2
J10: =SUM(D10:I10) -> 0
J11: =SUM(D11:I11) -> 0
J12: =SUM(D12:I12) -> 0
J13: =SUM(D13:I13) -> 0
J14: =SUM(D14:I14) -> 0
J15: =SUM(D15:I15) -> 0
J16: =SUM(D16:I16) -> 0
J17: =SUM(D17:I17) -> 0
J18: =SUM(D18:I18) -> 0
J19: =SUM(D19:I19) -> 0
J20: =SUM(D20:I20) -> 0
J21: =SUM(D21:I21) -> 0
A22: TOTAL | D22: =SUM(D4:D21) -> 117.2 | E22: =SUM(E4:E21) -> 3 | F22: =SUM(F4:F21) -> 100 | G22: =SUM(G4:G21) -> 45.2 | H22: =SUM(H4:H21) -> 59 | I22: =SUM(I4:I21) -> 10 | J22: =SUM(J4:J21) -> 334.4
A24: BBVA
A25: INQUILINOS | B25: COMPROBANTE | C25: DETALLE | D25: LUZ | E25: AGUA | F25: ALQUILER | G25: ESPACIO | H25: DEPOSITO | I25: TICKET | J25: TOTAL
A26: SALAZAR MARIA | B26: EB01-6897 | C26: 45962 | F26: 200 | J26: =SUM(D26:I26) -> 200
C27: 45992 | F27: 500 | J27: =SUM(D27:I27) -> 500
C28: 46023 | F28: 500 | J28: =SUM(D28:I28) -> 500
B29: RII 3264 | C29: 46023 | D29: 15.7 | E29: 3 | J29: =SUM(D29:I29) -> 18.7
J30: =SUM(D30:I30) -> 0
J31: =SUM(D31:I31) -> 0 | L31: TOTAL QR | M31: =J32+J40 -> 1294.2
A32: TOTAL | J32: =SUM(J26:J31) -> 1218.7
A34: BBVA
A35: SOCIOS | B35: RECIBO DE SERVICIO | C35: DETALLE | D35: LUZ | E35: AGUA | F35: G. ADM | G35: P. SOCIAL | H35: DEPOSITO | I35: P.S X FALLECIMIENTO | J35: TOTAL
A36: BERNAOLA FLORENCIA | B36: RI 32543 | C36: 45992 | D36: 1.2 | E36: 74.3 | J36: =SUM(D36:I36) -> 75.5
J37: =SUM(D37:I37) -> 0
J38: =SUM(D38:I38) -> 0
J39: =SUM(D39:I39) -> 0
A40: TOTAL | J40: =SUM(J36:J39) -> 75.5
A44: SOCIO | B44: RECIBO DE SERVICIO | C44: DETALLE | D44: LUZ | E44: AGUA | F44: G. ADM | G44: P. SOCIAL | H44: P.S X FALLECIMIENTO | I44: DEPOSITO | J44: TOTAL
A45: CRUZ LUIS | B45: RI 32542 | C45: 46023 | D45: 21.4 | E45: 5 | H45: 10 | J45: =SUM(D45:I45) -> 36.4
A46: CABALLERO GLADYS | B46: RI 32544 | C46: 45992 | D46: 5 | E46: 6 | J46: =SUM(D46:I46) -> 11
C47: 46023 | D47: 5.8 | E47: 5.7 | J47: =SUM(D47:I47) -> 11.5
J48: =SUM(D48:I48) -> 0
J49: =SUM(D49:I49) -> 0
J50: =SUM(D50:I50) -> 0
J51: =SUM(D51:I51) -> 0
J52: =SUM(D52:I52) -> 0
J53: =SUM(D53:I53) -> 0
J54: =SUM(D54:I54) -> 0
J55: =SUM(D55:I55) -> 0
J56: =SUM(D56:I56) -> 0
J57: =SUM(D57:I57) -> 0
J58: =SUM(D58:I58) -> 0
A59: TOTAL | D59: =SUM(D45:D58) -> 32.2 | E59: =SUM(E45:E58) -> 16.7 | F59: =SUM(F45:F58) -> 0 | G59: =SUM(G45:G58) -> 0 | H59: =SUM(H45:H58) -> 10 | I59: =SUM(I45:I58) -> 0 | J59: =SUM(J45:J58) -> 58.9
A62: TOTAL DE INGRESOS | J62: =+J22+J59 -> 393.3
A65: SRTA. FATIMA SIHUE
A66: COBRANZA SOCIOS | J66: 1472
A67: COBRANZA INQUILINOS | J67: 1975
A70: SRA. MARIA CUYA ARANGO
A71: COBRANZA DE BAÑO DEL 1ER PISO | J71: 408.5
A74: COBRANZA DE BAÑO DEL 2DO PISO
A76: TOTAL GENERAL DE INGRESOS | J76: =SUM(J62:J75) -> 4248.8
A78: EGRESOS DEL DIA 20-02-2026
A79: CAJA
A80: RESPONSABLE | B80: COMPROBANTE | C80: DETALLE | J80: TOTAL
A81: ALCAREZ MARIANELA | B81: RC 8549 | C81: PREVISION SOCIAL POR SALUD AL SOCIO ALVAREZ CAMPOS ROLANDO | J81: 400
A82: ACCESOS TECH PERU S.A.C. | B82: E001-963 | C82: REPARACION DEL PULSADOR DE SALIDA DE LOS SSHH DE VARONES DEL PRIMER PISO | J82: 180
A83: CONTINENTAL SAC | B83: F259-00026912 | C83: COMPRA DE UTILES PARA LA OFICINA DE ADMINISTRACION | J83: 578.2
A84: GRAFICA LEON & ASOCIADOS E.I.R.L. | B84: EB01-15 | C84: FABRICACION DE BANNERS PARA LA PLAYA DE ESTACIONAMIENTO | J84: 75
A85: BUSTAMANTE JOSE | B85: RC 8550 | C85: PASAJE PARA REALIZAR LOS BANNERS DE LA PLAYA DE ESTACIONAMIENTO | J85: 5
A86: POMACANCHARI NICANOR | B86: RC8551 | C86: ADELANTO DE SUELDO DEL MES DE FEBRERO 2026 | J86: 100
A94: TOTAL DE EGRESOS | J94: =SUM(J81:J93) -> 1338.2
A97: RESUMEN
A98: TOTAL GENERAL | B98: =+J76 -> 4248.8
A99: TOTAL DE EGRESOS | B99: =+J94 -> 1338.2
A100: SALDO | B100: =++B98-B99 -> 2910.6

Sheet 21-02-2026
A1: INGRESOS DEL DIA 21-02-2026
A3: INQUILINO | B3: COMPROBANTE | C3: DETALLE | D3: LUZ | E3: AGUA | F3: ALQUILER | G3: ESPACIO | H3: PARQUEO | I3: TICKET | J3: TOTAL
A4: JOSE | B4: TK 50774 | C4: 46054 | I4: 10 | J4: =SUM(D4:I4) -> 10
A5: ADMINISTRADORA DE SERVICIOS FUNERARIOS SAC | B5: E001-320 | C5: 46054 | G5: 30 | J5: =SUM(D5:I5) -> 30
J6: =SUM(D6:I6) -> 0
A7: PALOMINO ROSA | B7: EB01-6901 | C7: 46054 | F7: 650 | J7: =SUM(D7:I7) -> 650
J8: =SUM(D8:I8) -> 0
J9: =SUM(D9:I9) -> 0
J10: =SUM(D10:I10) -> 0
J11: =SUM(D11:I11) -> 0
A12: PALOMINO ROSA | B12: RII 3265 | C12: 45992 | D12: 20.1 | E12: 5 | J12: =SUM(D12:I12) -> 25.1
C13: 46023 | D13: 19 | E13: 3 | J13: =SUM(D13:I13) -> 22
J14: =SUM(D14:I14) -> 0
J15: =SUM(D15:I15) -> 0
J16: =SUM(D16:I16) -> 0
J17: =SUM(D17:I17) -> 0
J18: =SUM(D18:I18) -> 0
J19: =SUM(D19:I19) -> 0
J20: =SUM(D20:I20) -> 0
J21: =SUM(D21:I21) -> 0
A22: TOTAL | D22: =SUM(D4:D21) -> 39.1 | E22: =SUM(E4:E21) -> 8 | F22: =SUM(F4:F21) -> 650 | G22: =SUM(G4:G21) -> 30 | H22: =SUM(H4:H21) -> 0 | I22: =SUM(I4:I21) -> 10 | J22: =SUM(J4:J21) -> 737.1
A24: BBVA
A25: INQUILINOS | B25: COMPROBANTE | C25: DETALLE | D25: LUZ | E25: AGUA | F25: ALQUILER | G25: ESPACIO | H25: DEPOSITO | I25: TICKET | J25: TOTAL
J26: =SUM(D26:I26) -> 0
J27: =SUM(D27:I27) -> 0
J28: =SUM(D28:I28) -> 0
J29: =SUM(D29:I29) -> 0 | L29: TOTAL QR | M29: =J30+J38 -> 90.9
A30: TOTAL | J30: =SUM(J26:J29) -> 0
A32: BBVA
A33: SOCIOS | B33: RECIBO DE SERVICIO | C33: DETALLE | D33: LUZ | E33: AGUA | F33: G. ADM | G33: P. SOCIAL | H33: DEPOSITO | I33: P.S X FALLECIMIENTO | J33: TOTAL
A34: SANCHEZ JUDITH | B34: RI 32546 | C34: 46023 | D34: 42.3 | E34: 48.6 | J34: =SUM(D34:I34) -> 90.9
J35: =SUM(D35:I35) -> 0
J36: =SUM(D36:I36) -> 0
J37: =SUM(D37:I37) -> 0
A38: TOTAL | J38: =SUM(J34:J37) -> 90.9
A42: SOCIO | B42: RECIBO DE SERVICIO | C42: DETALLE | D42: LUZ | E42: AGUA | F42: G. ADM | G42: P. SOCIAL | H42: P.S X FALLECIMIENTO | I42: MULTA | J42: TOTAL
A43: ESPEJO ROSA | B43: RI 32545 | C43: 45992 | D43: 102.6 | E43: 6 | F43: 60 | G43: 5 | J43: =SUM(D43:I43) -> 173.6
C44: 46023 | D44: 99.7 | E44: 5 | F44: 60 | G44: 5 | I44: 28.3 | J44: =SUM(D44:I44) -> 198
J45: =SUM(D45:I45) -> 0
J46: =SUM(D46:I46) -> 0
J47: =SUM(D47:I47) -> 0
J48: =SUM(D48:I48) -> 0
J49: =SUM(D49:I49) -> 0
J50: =SUM(D50:I50) -> 0
J51: =SUM(D51:I51) -> 0
J52: =SUM(D52:I52) -> 0
J53: =SUM(D53:I53) -> 0
J54: =SUM(D54:I54) -> 0
J55: =SUM(D55:I55) -> 0
J56: =SUM(D56:I56) -> 0
A57: TOTAL | D57: =SUM(D43:D56) -> 202.3 | E57: =SUM(E43:E56) -> 11 | F57: =SUM(F43:F56) -> 120 | G57: =SUM(G43:G56) -> 10 | H57: =SUM(H43:H56) -> 0 | I57: =SUM(I43:I56) -> 28.3 | J57: =SUM(J43:J56) -> 371.6
A60: TOTAL DE INGRESOS | J60: =+J22+J57 -> 1108.7
A63: SRTA. FATIMA SIHUE
A64: COBRANZA SOCIOS
A65: COBRANZA INQUILINOS
A68: SRA. MARIA CUYA ARANGO
A69: COBRANZA DE BAÑO DEL 1ER PISO | J69: 728.5
A72: COBRANZA DE BAÑO DEL 2DO PISO
A74: TOTAL GENERAL DE INGRESOS | J74: =SUM(J60:J73) -> 1837.2
A76: EGRESOS DEL DIA 21-02-2026
A77: CAJA
A78: RESPONSABLE | B78: COMPROBANTE | C78: DETALLE | J78: TOTAL
A92: TOTAL DE EGRESOS | J92: =SUM(J79:J91) -> 0
A95: RESUMEN
A96: TOTAL GENERAL | B96: =+J74 -> 1837.2
A97: TOTAL DE EGRESOS | B97: =+J92 -> 0
A98: SALDO | B98: =++B96-B97 -> 1837.2

Sheet 22-02-2026
A1: INGRESOS DEL DIA 22-02-2026
A3: INQUILINO | B3: COMPROBANTE | C3: DETALLE | D3: LUZ | E3: AGUA | F3: ALQUILER | G3: ESPACIO | H3: PARQUEO | I3: TICKET | J3: TOTAL
J4: =SUM(D4:I4) -> 0
J5: =SUM(D5:I5) -> 0
J6: =SUM(D6:I6) -> 0
J7: =SUM(D7:I7) -> 0
J8: =SUM(D8:I8) -> 0
J9: =SUM(D9:I9) -> 0
J10: =SUM(D10:I10) -> 0
J11: =SUM(D11:I11) -> 0
J12: =SUM(D12:I12) -> 0
J13: =SUM(D13:I13) -> 0
J14: =SUM(D14:I14) -> 0
J15: =SUM(D15:I15) -> 0
... J21: =SUM(D21:I21) -> 0
A22: TOTAL | D22: =SUM(D4:D21) -> 0 | E22: =SUM(E4:E21) -> 0 | F22: =SUM(F4:F21) -> 0 | G22: =SUM(G4:G21) -> 0 | H22: =SUM(H4:H21) -> 0 | I22: =SUM(I4:I21) -> 0 | J22: =SUM(J4:J21) -> 0
A24: BBVA
A25: INQUILINOS | B25: COMPROBANTE | C25: DETALLE | D25: LUZ | E25: AGUA | F25: ALQUILER | G25: ESPACIO | H25: DEPOSITO | I25: TICKET | J25: TOTAL
J26: =SUM(D26:I26) -> 0
J27: =SUM(D27:I27) -> 0
J28: =SUM(D28:I28) -> 0
J29: =SUM(D29:I29) -> 0 | L29: TOTAL QR | M29: =J30+J38 -> 0
A30: TOTAL | J30: =SUM(J26:J29) -> 0
A32: BBVA
A33: SOCIOS | B33: RECIBO DE SERVICIO | C33: DETALLE | D33: LUZ | E33: AGUA | F33: G. ADM | G33: P. SOCIAL | H33: DEPOSITO | I33: P.S X FALLECIMIENTO | J33: TOTAL
J34: =SUM(D34:I34) -> 0
J35: =SUM(D35:I35) -> 0
J36: =SUM(D36:I36) -> 0
J37: =SUM(D37:I37) -> 0
A38: TOTAL | J38: =SUM(J34:J37) -> 0
A42: SOCIO | B42: RECIBO DE SERVICIO | C42: DETALLE | D42: LUZ | E42: AGUA | F42: G. ADM | G42: P. SOCIAL | H42: P.S X FALLECIMIENTO | I42: DEPOSITO | J42: TOTAL
J43: =SUM(D43:I43) -> 0
J44: =SUM(D44:I44) -> 0
J45: =SUM(D45:I45) -> 0
J46: =SUM(D46:I46) -> 0
J47: =SUM(D47:I47) -> 0
J48: =SUM(D48:I48) -> 0
J49: =SUM(D49:I49) -> 0
J50: =SUM(D50:I50) -> 0
J51: =SUM(D51:I51) -> 0
J52: =SUM(D52:I52) -> 0
J53: =SUM(D53:I53) -> 0
J54: =SUM(D54:I54) -> 0
... J56: =SUM(D56:I56) -> 0
A57: TOTAL | D57: =SUM(D43:D56) -> 0 | E57: =SUM(E43:E56) -> 0 | F57: =SUM(F43:F56) -> 0 | G57: =SUM(G43:G56) -> 0 | H57: =SUM(H43:H56) -> 0 | I57: =SUM(I43:I56) -> 0 | J57: =SUM(J43:J56) -> 0
A60: TOTAL DE INGRESOS | J60: =+J22+J57 -> 0
A63: SRTA. FATIMA SIHUE
A64: COBRANZA SOCIOS
A65: COBRANZA INQUILINOS
A68: SRA. MARIA CUYA ARANGO
A69: COBRANZA DE BAÑO DEL 1ER PISO | J69: 145
A72: COBRANZA DE BAÑO DEL 2DO PISO
A74: TOTAL GENERAL DE INGRESOS | J74: =SUM(J60:J73) -> 145
A76: EGRESOS DEL DIA 22-02-2026
A77: CAJA
A78: RESPONSABLE | B78: COMPROBANTE | C78: DETALLE | J78: TOTAL
A92: TOTAL DE EGRESOS | J92: =SUM(J79:J91) -> 0
A95: RESUMEN
A96: TOTAL GENERAL | B96: =+J74 -> 145
A97: TOTAL DE EGRESOS | B97: =+J92 -> 0
A98: SALDO | B98: =++B96-B97 -> 145

Sheet 23-02-2026
A1: INGRESOS DEL DIA 23-02-2026
A3: INQUILINO | B3: COMPROBANTE | C3: DETALLE | D3: LUZ | E3: AGUA | F3: ALQUILER | G3: ESPACIO | H3: PARQUEO | I3: LOCAL 2DO PISO | J3: TOTAL
A4: SEVEN DAYS CORPORATION S.A.C. | B4: E001-321 | C4: 46054 | G4: 60 | J4: =SUM(D4:I4) -> 60
A5: PARQUEO | B5: EB01-6905 | C5: 46054 | H5: 67 | J5: =SUM(D5:I5) -> 67
A6: CARLOS ROJAS SILVA | B6: EB01-6907 | C6: 46174 | I6: 200 | J6: =SUM(D6:I6) -> 200
A7: LEON RODRIGUEZ ANGIE | B7: EB01-6908 | C7: 46023 | F7: 850 | J7: =SUM(D7:I7) -> 850
A8: PARQUEO | B8: EB01-6910 | C8: 46054 | H8: 54.7 | J8: =SUM(D8:I8) -> 54.7
J9: =SUM(D9:I9) -> 0
J10: =SUM(D10:I10) -> 0
J11: =SUM(D11:I11) -> 0
J12: =SUM(D12:I12) -> 0
J13: =SUM(D13:I13) -> 0
J14: =SUM(D14:I14) -> 0
A15: LEON RODRIGUEZ ANGIE | B15: RII 3267 | C15: 46023 | D15: 13.3 | E15: 3 | J15: =SUM(D15:I15) -> 16.3
J16: =SUM(D16:I16) -> 0
J17: =SUM(D17:I17) -> 0
J18: =SUM(D18:I18) -> 0
J19: =SUM(D19:I19) -> 0
J20: =SUM(D20:I20) -> 0
J21: =SUM(D21:I21) -> 0
A22: TOTAL | D22: =SUM(D5:D21) -> 13.3 | E22: =SUM(E5:E21) -> 3 | F22: =SUM(F5:F21) -> 850 | G22: =SUM(G4:G21) -> 60 | H22: =SUM(H5:H21) -> 121.7 | I22: =SUM(I5:I21) -> 200 | J22: =SUM(J4:J21) -> 1248
A24: BBVA
A25: INQUILINOS | B25: COMPROBANTE | C25: DETALLE | D25: LUZ | E25: AGUA | F25: ALQUILER | G25: ESPACIO | H25: DEPOSITO | I25: TICKET | J25: TOTAL
A26: DAVID CHOQUEHUANCA HUAMAN | B26: EB01-6906 | C26: 46023 | F26: 180 | J26: =SUM(D26:I26) -> 180
B27: RII 3266 | C27: 45839 | D27: 8.2 | E27: 4 | J27: =SUM(D27:I27) -> 12.2
C28: 45962 | D28: 20.4 | E28: 5 | J28: =SUM(D28:I28) -> 25.4
C29: 45992 | D29: 26.6 | E29: 5 | J29: =SUM(D29:I29) -> 31.6
C30: 46023 | D30: 29 | E30: 3 | J30: =SUM(D30:I30) -> 32
J31: =SUM(D31:I31) -> 0
J32: =SUM(D32:I32) -> 0
J33: =SUM(D33:I33) -> 0 | L33: TOTAL QR | M33: =J34+J42 -> 1347.6
A34: TOTAL | J34: =SUM(J26:J33) -> 281.2
A36: BBVA
A37: SOCIOS | B37: RECIBO DE SERVICIO | C37: DETALLE | D37: LUZ | E37: AGUA | F37: G. ADM | G37: P. SOCIAL | H37: DEPOSITO | I37: P.S X FALLECIMIENTO | J37: TOTAL
A38: PALOMINO EUSEBIO | B38: RI 32552 | C38: 46023 | D38: 31.4 | E38: 36.6 | I38: 10 | J38: =SUM(D38:I38) -> 78
A39: FLORES FLORES IRENE | B39: RI 32554 | C39: 46023 | D39: 504.8 | E39: 97.3 | F39: 60 | G39: 5 | I39: 10 | J39: =SUM(D39:I39) -> 677.1
A40: QUISPE DOROTEA | B40: RI 32558 | C40: 45992 | D40: 305.3 | E40: 6 | J40: =SUM(D40:I40) -> 311.3
J41: =SUM(D41:I41) -> 0
A42: TOTAL | J42: =SUM(J38:J41) -> 1066.4
A46: SOCIO | B46: RECIBO DE SERVICIO | C46: DETALLE | D46: LUZ | E46: AGUA | F46: G. ADM | G46: P. SOCIAL | H46: P.S X FALLECIMIENTO | I46: MULTA | J46: TOTAL
A47: TORRES FRANCISCO | B47: RI 32547 | C47: 46023 | D47: 53 | E47: 65 | H47: 10 | J47: =SUM(D47:I47) -> 128
C48: 46054 | F48: 56 | G48: 5 | J48: =SUM(D48:I48) -> 61
A49: CHALLCO NICOLAZA | B49: RI 32548 | C49: 46023 | D49: 823.1 | E49: 28.6 | F49: 60 | G49: 5 | H49: 10 | I49: 28.3 | J49: =SUM(D49:I49) -> 955
A50: SALVATIERRA ALLISON | B50: RI 32549 | C50: 46023 | D50: 77.5 | E50: 201.6 | I50: 28.3 | J50: =SUM(D50:I50) -> 307.4
A51: SALAS JUDITH | B51: RI 32550 | C51: 45992 | D51: 56.2 | E51: 277.5 | J51: =SUM(D51:I51) -> 333.7
C52: 46023 | D52: 54.7 | E52: 221.6 | J52: =SUM(D52:I52) -> 276.3
A53: CCOYLLO ALEXIS | B53: RI 32551 | C53: 45992 | D53: 4.5 | E53: 7 | F53: 60 | G53: 5 | J53: =SUM(D53:I53) -> 76.5
C54: 46023 | D54: 4.1 | E54: 5.3 | H54: 10 | J54: =SUM(D54:I54) -> 19.4
A55: PALOMINO EUSEBIO | B55: RI 32553 | C55: 46023 | D55: 600 | J55: =SUM(D55:I55) -> 600
A56: QUISPE ADRIANA | B56: RI 32555 | C56: 45962 | D56: 564.6 | E56: 54 | J56: =SUM(D56:I56) -> 618.6
C57: 45992 | D57: 426.4 | E57: 54 | J57: =SUM(D57:I57) -> 480.4
C58: 46023 | D58: 688.8 | E58: 42 | H58: 10 | J58: =SUM(D58:I58) -> 740.8
A59: OQUENDO MIGUEL | B59: RI 32556 | C59: 45962 | D59: 5 | E59: 6 | F59: 60 | G59: 5 | J59: =SUM(D59:I59) -> 76
C60: 45992 | D60: 86.3 | E60: 6 | F60: 60 | G60: 5 | J60: =SUM(D60:I60) -> 157.3
C61: 46023 | D61: 666.7 | J61: =SUM(D61:I61) -> 666.7
A62: TORRES NERY | B62: RI 32557 | C62: 45962 | D62: 5.9 | E62: 24.7 | J62: =SUM(D62:I62) -> 30.6
C63: 45992 | D63: 6.9 | E63: 22.9 | J63: =SUM(D63:I63) -> 29.8
C64: 46023 | D64: 5.5 | E64: 30.4 | J64: =SUM(D64:I64) -> 35.9
A65: SALAS JUDITH | B65: RI 32559 | C65: 46023 | H65: 10 | J65: =SUM(D65:I65) -> 10
C66: 46054 | F66: 56 | G66: 5 | J66: =SUM(D66:I66) -> 61
A67: PITTMAN NELLY | B67: RI 32560 | C67: 46023 | D67: 38.3 | E67: 5 | J67: =SUM(D67:I67) -> 43.3
J68: =SUM(D68:I68) -> 0
J69: =SUM(D69:I69) -> 0
A70: TOTAL | D70: =SUM(D47:D69) -> 4167.5 | E70: =SUM(E47:E69) -> 1051.6 | F70: =SUM(F47:F69) -> 352 | G70: =SUM(G47:G69) -> 30 | H70: =SUM(H47:H69) -> 50 | I70: =SUM(I47:I69) -> 56.6 | J70: =SUM(J47:J69) -> 5707.7
A73: TOTAL DE INGRESOS | J73: =+J22+J70 -> 6955.7
A76: SRTA. FATIMA SIHUE
A77: COBRANZA SOCIOS
A78: COBRANZA INQUILINOS
A81: SRA. MARIA CUYA ARANGO
A82: COBRANZA DE BAÑO DEL 1ER PISO | J82: 319
A85: COBRANZA DE BAÑO DEL 2DO PISO
A87: TOTAL GENERAL DE INGRESOS | J87: =SUM(J73:J86) -> 7274.7
A89: EGRESOS DEL DIA 23-02-2026
A90: CAJA
A91: RESPONSABLE | B91: COMPROBANTE | C91: DETALLE | J91: TOTAL
A92: RAMIREZ HERMELINDA | B92: RC 8552 | C92: REEMPLAZO DE LA SRA DE LOS SSHH DEL DIA 22-02-2026 | J92: 80
A105: TOTAL DE EGRESOS | J105: =SUM(J92:J104) -> 80
A108: RESUMEN
A109: TOTAL GENERAL | B109: =+J87 -> 7274.7
A110: TOTAL DE EGRESOS | B110: =+J105 -> 80
A111: SALDO | B111: =++B109-B110 -> 7194.7

Sheet 24-02-2026
A1: INGRESOS DEL DIA 24-02-2026
A3: INQUILINO | B3: COMPROBANTE | C3: DETALLE | D3: LUZ | E3: AGUA | F3: ALQUILER | G3: ESPACIO | H3: PARQUEO | I3: TICKET | J3: TOTAL
A4: JOSE DESARMADORES | B4: TK 50775 | C4: 46054 | I4: 10 | J4: =SUM(D4:I4) -> 10
A5: JOSE | B5: TK 50776 | C5: 46054 | I5: 10 | J5: =SUM(D5:I5) -> 10
A6: PARQUEO | B6: EB01-6912 | C6: 46054 | H6: 55.2 | J6: =SUM(D6:I6) -> 55.2
J7: =SUM(D7:I7) -> 0
J8: =SUM(D8:I8) -> 0
J9: =SUM(D9:I9) -> 0
J10: =SUM(D10:I10) -> 0
J11: =SUM(D11:I11) -> 0
J12: =SUM(D12:I12) -> 0
J13: =SUM(D13:I13) -> 0
J14: =SUM(D14:I14) -> 0
J15: =SUM(D15:I15) -> 0
J16: =SUM(D16:I16) -> 0
J17: =SUM(D17:I17) -> 0
J18: =SUM(D18:I18) -> 0
... J21: =SUM(D21:I21) -> 0
A22: TOTAL | D22: =SUM(D4:D21) -> 0 | E22: =SUM(E4:E21) -> 0 | F22: =SUM(F4:F21) -> 0 | G22: =SUM(G4:G21) -> 0 | H22: =SUM(H4:H21) -> 55.2 | I22: =SUM(I4:I21) -> 20 | J22: =SUM(J4:J21) -> 75.2
A24: BBVA
A25: INQUILINOS | B25: COMPROBANTE | C25: DETALLE | D25: LUZ | E25: AGUA | F25: ALQUILER | G25: ESPACIO | H25: DEPOSITO | I25: TICKET | J25: TOTAL
J26: =SUM(D26:I26) -> 0
J27: =SUM(D27:I27) -> 0
J28: =SUM(D28:I28) -> 0
J29: =SUM(D29:I29) -> 0 | L29: TOTAL QR | M29: =J30+J38 -> 230
A30: TOTAL | J30: =SUM(J26:J29) -> 0
A32: BBVA
A33: SOCIOS | B33: RECIBO DE SERVICIO | C33: DETALLE | D33: LUZ | E33: AGUA | F33: G. ADM | G33: P. SOCIAL | H33: DEPOSITO | I33: P.S X FALLECIMIENTO | J33: TOTAL
A34: ZAPATA ROSANA | B34: RI 32563 | C34: 45992 | D34: 84 | E34: 146 | J34: =SUM(D34:I34) -> 230
J35: =SUM(D35:I35) -> 0
J36: =SUM(D36:I36) -> 0
J37: =SUM(D37:I37) -> 0
A38: TOTAL | J38: =SUM(J34:J37) -> 230
A42: SOCIO | B42: RECIBO DE SERVICIO | C42: DETALLE | D42: LUZ | E42: AGUA | F42: G. ADM | G42: P. SOCIAL | H42: P.S X FALLECIMIENTO | I42: MULTA | J42: TOTAL
A43: DE LA CRUZ JOSE | B43: RI 32561 | C43: 46023 | H43: 10 | J43: =SUM(D43:I43) -> 10
A44: SANCHEZ JUDITH | B44: RI 32562 | C44: 45962 | D44: 53.6 | E44: 11.6 | F44: 60 | G44: 5 | J44: =SUM(D44:I44) -> 130.2
C45: 45992 | D45: 18.5 | E45: 70.1 | F45: 60 | G45: 5 | J45: =SUM(D45:I45) -> 153.6
C46: 46023 | F46: 60 | G46: 5 | H46: 10 | I46: 28.3 | J46: =SUM(D46:I46) -> 103.3
A47: ZAPATA ROSANA | B47: RI 32564 | C47: 45992 | D47: 0.6 | J47: =SUM(D47:I47) -> 0.6
A48: MAYHUASCA CLUDY | B48: RI 32565 | C48: 46023 | D48: 362 | E48: 30 | J48: =SUM(D48:I48) -> 392
A49: SALAS RUTH | B49: RI 32566 | C49: 46023 | H49: 10 | J49: =SUM(D49:I49) -> 10
A50: FLORES FLORES UMBELINA | B50: RI 32567 | C50: 46023 | D50: 221.9 | E50: 98.3 | F50: 56 | G50: 5 | I50: 28.3 | J50: =SUM(D50:I50) -> 409.5
J51: =SUM(D51:I51) -> 0
J52: =SUM(D52:I52) -> 0
J53: =SUM(D53:I53) -> 0
J54: =SUM(D54:I54) -> 0
J55: =SUM(D55:I55) -> 0
J56: =SUM(D56:I56) -> 0
A57: TOTAL | D57: =SUM(D43:D56) -> 656.6 | E57: =SUM(E43:E56) -> 210 | F57: =SUM(F43:F56) -> 236 | G57: =SUM(G43:G56) -> 20 | H57: =SUM(H43:H56) -> 30 | I57: =SUM(I43:I56) -> 56.6 | J57: =SUM(J43:J56) -> 1209.2
A60: TOTAL DE INGRESOS | J60: =+J22+J57 -> 1284.4
A63: SRTA. FATIMA SIHUE
A64: COBRANZA SOCIOS
A65: COBRANZA INQUILINOS
A68: SRA. MARIA CUYA ARANGO
A69: COBRANZA DE BAÑO DEL 1ER PISO | J69: 414
A72: COBRANZA DE BAÑO DEL 2DO PISO
A74: TOTAL GENERAL DE INGRESOS | J74: =SUM(J60:J73) -> 1698.4
A76: EGRESOS DEL DIA 24-02-2026
A77: CAJA
A78: RESPONSABLE | B78: COMPROBANTE | C78: DETALLE | J78: TOTAL
A79: COTRINA MANRIQUE TITO | B79: E001-189 | C79: INSTALACION DE 1 TOMACORRIENTE PARA LA FOTOCOPIADORA DE LA OFICINA DE ADM. | J79: 20
A80: VILLAR RONCAL DIGNA | B80: F001-0003488 | C80: MATERIALES PARA LA INSTALACION DE 1 TOMACORRIENTE PARA LA OFICINA DE ADM | J80: 15.2
A92: TOTAL DE EGRESOS | J92: =SUM(J79:J91) -> 35.2
A95: RESUMEN
A96: TOTAL GENERAL | B96: =+J74 -> 1698.4
A97: TOTAL DE EGRESOS | B97: =+J92 -> 35.2
A98: SALDO | B98: =++B96-B97 -> 1663.2

Sheet 25-02-2026
A1: INGRESOS DEL DIA 25-02-2026
A3: INQUILINO | B3: COMPROBANTE | C3: DETALLE | D3: LUZ | E3: AGUA | F3: ALQUILER | G3: ESPACIO | H3: PARQUEO | I3: TICKET | J3: TOTAL
A4: JOSE | B4: TK 50777 | C4: 46054 | I4: 10 | J4: =SUM(D4:I4) -> 10
A5: LAPAS MARIA | B5: RII 3268 | C5: 45962 | D5: 10 | E5: 5 | J5: =SUM(D5:I5) -> 15
C6: 45992 | D6: 10 | E6: 5 | J6: =SUM(D6:I6) -> 15
C7: 46023 | D7: 15 | E7: 3 | J7: =SUM(D7:I7) -> 18
A8: CLAROS SANTOS JESUS | B8: RII 3269 | C8: 46023 | D8: 21.1 | E8: 3 | J8: =SUM(D8:I8) -> 24.1
A9: CASTRO JANETT | B9: RII 3270 | C9: 46023 | D9: 9 | E9: 3 | J9: =SUM(D9:I9) -> 12
A10: ARREDONDO GLADYS | B10: RII 3271 | C10: 46023 | D10: 15 | E10: 3 | J10: =SUM(D10:I10) -> 18
J11: =SUM(D11:I11) -> 0
J12: =SUM(D12:I12) -> 0
J13: =SUM(D13:I13) -> 0
J14: =SUM(D14:I14) -> 0
A15: HUAMANI MAXIMO | B15: EB01-6913 | C15: 46054 | F15: 400 | J15: =SUM(D15:I15) -> 400
A16: QUISPE MARISOL | B16: EB01-6914 | C16: 46023 | F16: 50 | J16: =SUM(D16:I16) -> 50
A17: ALVAREZ EDGAR | B17: EB01-6915 | C17: 46023 | F17: 300 | J17: =SUM(D17:I17) -> 300
A18: CASTRO JANETT | B18: EB01-6916 | C18: 45992 | F18: 150 | J18: =SUM(D18:I18) -> 150
C19: 46023 | F19: 100 | J19: =SUM(D19:I19) -> 100
A20: ARREDONDO GLADYS | B20: EB01-6917 | C20: 46023 | F20: 100 | J20: =SUM(D20:I20) -> 100
A21: PARQUEO | B21: EB01-6919 | C21: 46054 | H21: 63.5 | J21: =SUM(D21:I21) -> 63.5
J22: =SUM(D22:I22) -> 0
J23: =SUM(D23:I23) -> 0
J24: =SUM(D24:I24) -> 0
J25: =SUM(D25:I25) -> 0
A26: CLAROS SANTOS JESUS | B26: E001-323 | C26: 46023 | F26: 100 | J26: =SUM(D26:I26) -> 100
J27: =SUM(D27:I27) -> 0
J28: =SUM(D28:I28) -> 0
A29: TOTAL | D29: =SUM(D4:D28) -> 80.1 | E29: =SUM(E4:E28) -> 22 | F29: =SUM(F4:F28) -> 1200 | G29: =SUM(G4:G28) -> 0 | H29: =SUM(H4:H28) -> 63.5 | I29: =SUM(I4:I28) -> 10 | J29: =SUM(J4:J28) -> 1375.6
A31: BBVA
A32: INQUILINOS | B32: COMPROBANTE | C32: DETALLE | D32: LUZ | E32: AGUA | F32: ALQUILER | G32: ESPACIO | H32: DEPOSITO | I32: TICKET | J32: TOTAL
A33: VASQUEZ TAFUR SONIA | B33: E001-322 | C33: 46082 | G33: 30 | J33: =SUM(D33:I33) -> 30
J34: =SUM(D34:I34) -> 0
J35: =SUM(D35:I35) -> 0
J36: =SUM(D36:I36) -> 0 | L36: TOTAL QR | M36: =J37+J45 -> 30
A37: TOTAL | J37: =SUM(J33:J36) -> 30
A39: BBVA
A40: SOCIOS | B40: RECIBO DE SERVICIO | C40: DETALLE | D40: LUZ | E40: AGUA | F40: G. ADM | G40: P. SOCIAL | H40: DEPOSITO | I40: P.S X FALLECIMIENTO | J40: TOTAL
J41: =SUM(D41:I41) -> 0
J42: =SUM(D42:I42) -> 0
J43: =SUM(D43:I43) -> 0
J44: =SUM(D44:I44) -> 0
A45: TOTAL | J45: =SUM(J41:J44) -> 0
A49: SOCIO | B49: RECIBO DE SERVICIO | C49: DETALLE | D49: LUZ | E49: AGUA | F49: G. ADM | G49: P. SOCIAL | H49: P.S X FALLECIMIENTO | I49: DEPOSITO | J49: TOTAL
A50: TINTAYA PATRICIA | B50: RI 32568 | C50: 45962 | D50: 46.3 | E50: 6 | J50: =SUM(D50:I50) -> 52.3
C51: 45992 | D51: 47 | E51: 0.7 | J51: =SUM(D51:I51) -> 47.7
A52: ALHUAY JUANA | B52: RI 32569 | C52: 46023 | D52: 28.4 | E52: 33.2 | J52: =SUM(D52:I52) -> 61.6
A53: MEDINA JUAN CARLOS | B53: RI 32570 | C53: 45962 | D53: 9.4 | E53: 6 | J53: =SUM(D53:I53) -> 15.4
C54: 45992 | D54: 8.5 | E54: 6 | J54: =SUM(D54:I54) -> 14.5
C55: 46023 | D55: 8.1 | E55: 5 | F55: 60 | G55: 5 | H55: 10 | J55: =SUM(D55:I55) -> 88.1
J56: =SUM(D56:I56) -> 0
J57: =SUM(D57:I57) -> 0
J58: =SUM(D58:I58) -> 0
J59: =SUM(D59:I59) -> 0
J60: =SUM(D60:I60) -> 0
J61: =SUM(D61:I61) -> 0
J62: =SUM(D62:I62) -> 0
J63: =SUM(D63:I63) -> 0
A64: TOTAL | D64: =SUM(D50:D63) -> 147.7 | E64: =SUM(E50:E63) -> 56.9 | F64: =SUM(F50:F63) -> 60 | G64: =SUM(G50:G63) -> 5 | H64: =SUM(H50:H63) -> 10 | I64: =SUM(I50:I63) -> 0 | J64: =SUM(J50:J63) -> 279.6
A67: TOTAL DE INGRESOS | J67: =+J29+J64 -> 1655.2
A70: SRTA. FATIMA SIHUE
A71: COBRANZA SOCIOS
A72: COBRANZA INQUILINOS
A75: SRA. MARIA CUYA ARANGO
A76: COBRANZA DE BAÑO DEL 1ER PISO | J76: 426
A79: COBRANZA DE BAÑO DEL 2DO PISO
A81: TOTAL GENERAL DE INGRESOS | J81: =SUM(J67:J80) -> 2081.2
A83: EGRESOS DEL DIA 25-02-2026
A84: CAJA
A85: RESPONSABLE | B85: COMPROBANTE | C85: DETALLE | J85: TOTAL
A86: MENDOZA RICHARD | B86: 754 | C86: 1 USB KINGSTON 16 GB PARA EL ABOGADO DE LA COOPERATIVA - CASO DIEGO | J86: 23
A87: HUAMAN TACURI JESUS ALBERTO | B87: E001- 15 | C87: SERVICIO DE MONTAJE Y CONEXION DE 02 TABLEROS Y ESTABILIZADORES DE LOS SSHH DEL PRIMER PISO. | J87: 160
A88: FERRETERIA Y MATIZADOS EL REY E.I.R.L. | B88: E001 1129 | C88: 1 CAÑO JARDIN DE BRONCE PARA LA GRUTA DE LA ENTRADA DE LA COOPERATIVA | J88: 30
A89: DISTRIBUIDORA ROXAL S.A.C. | B89: F002-00004360 | C89: UTILES DE LIMPIEZA PARA LOS SSHH DEL PRIMER PISO | J89: 325
A99: TOTAL DE EGRESOS | J99: =SUM(J86:J98) -> 538
A101: BOVEDA SANTA ROSA
A102: RESPONSABLE | B102: COMPROBANTE | C102: DETALLE | I102: TOTAL
A103: ALARCON ANAMPA BETSY | B103: 934 | C103: ARREGLO FLORAL | I103: 10
B104: 935 | C104: ARREGLO FLORAL | I104: 15
A106: TOTAL DE EGRESOS | I106: =SUM(I103:I105) -> 25
A108: RESUMEN
A109: TOTAL GENERAL | B109: =+J81 -> 2081.2
A110: TOTAL DE EGRESOS | B110: =+J99 -> 538
A111: SALDO | B111: =++B109-B110 -> 1543.2

Sheet 26-02-2026
A1: INGRESOS DEL DIA 26-02-2026
A3: INQUILINO | B3: COMPROBANTE | C3: DETALLE | D3: LUZ | E3: AGUA | F3: ALQUILER | G3: ESPACIO | H3: PARQUEO | I3: TICKET | K3: TOTAL
A4: JOSE | B4: TK 50778 | C4: 46054 | I4: 10 | K4: =SUM(D4:I4) -> 10
A5: PARQUEO | B5: EB01-6920 | C5: 46054 | H5: 62.7 | K5: =SUM(D5:I5) -> 62.7
K6: =SUM(D6:I6) -> 0
K7: =SUM(D7:I7) -> 0
K8: =SUM(D8:I8) -> 0
K9: =SUM(D9:I9) -> 0
K10: =SUM(D10:I10) -> 0
K11: =SUM(D11:I11) -> 0
K12: =SUM(D12:I12) -> 0
K13: =SUM(D13:I13) -> 0
K14: =SUM(D14:I14) -> 0
K15: =SUM(D15:I15) -> 0
K16: =SUM(D16:I16) -> 0
K17: =SUM(D17:I17) -> 0
... K21: =SUM(D21:I21) -> 0
A22: TOTAL | D22: =SUM(D4:D21) -> 0 | E22: =SUM(E4:E21) -> 0 | F22: =SUM(F4:F21) -> 0 | G22: =SUM(G4:G21) -> 0 | H22: =SUM(H4:H21) -> 62.7 | I22: =SUM(I4:I21) -> 10 | K22: =SUM(K4:K21) -> 72.7
A24: BBVA
A25: INQUILINOS | B25: COMPROBANTE | C25: DETALLE | D25: LUZ | E25: AGUA | F25: ALQUILER | G25: ESPACIO | H25: DEPOSITO | I25: TICKET | K25: TOTAL
K26: =SUM(D26:I26) -> 0
K27: =SUM(D27:I27) -> 0
K28: =SUM(D28:I28) -> 0
K29: =SUM(D29:I29) -> 0 | M29: TOTAL QR | N29: =K30+K38 -> 0
A30: TOTAL | K30: =SUM(K26:K29) -> 0
A32: BBVA
A33: SOCIOS | B33: RECIBO DE SERVICIO | C33: DETALLE | D33: LUZ | E33: AGUA | F33: G. ADM | G33: P. SOCIAL | H33: DEPOSITO | I33: P.S X FALLECIMIENTO | K33: TOTAL
K34: =SUM(D34:I34) -> 0
K35: =SUM(D35:I35) -> 0
K36: =SUM(D36:I36) -> 0
K37: =SUM(D37:I37) -> 0
A38: TOTAL | K38: =SUM(K34:K37) -> 0
A42: SOCIO | B42: RECIBO DE SERVICIO | C42: DETALLE | D42: LUZ | E42: AGUA | F42: G. ADM | G42: P. SOCIAL | H42: P.S X FALLECIMIENTO | I42: DEPOSITO | J42: TALONARIO SANTA ROSA | K42: TOTAL
A43: RIVERA JUANA | B43: RI 32571 | C43: 46023 | F43: 60 | G43: 5 | H43: 10 | K43: =SUM(D43:J43) -> 75
C44: 46054 | F44: 56 | G44: 5 | K44: =SUM(D44:J44) -> 61
C45: 46082 | F45: 60 | G45: 5 | K45: =SUM(D45:J45) -> 65
A46: VALLEJOS MARIA | B46: RI 32572 | C46: 46023 | D46: 75.5 | E46: 45 | K46: =SUM(D46:J46) -> 120.5
A47: CALLE FIDEL | B47: RI 32573 | C47: 45992 | D47: 24.2 | E47: 6 | K47: =SUM(D47:J47) -> 30.2
C48: 46023 | D48: 23.5 | E48: 5 | K48: =SUM(D48:J48) -> 28.5
A49: VICENTE JOSE | B49: RI 32574 | C49: 45870 | J49: 15 | K49: =SUM(D49:J49) -> 15
C50: 45962 | D50: 22.3 | E50: 6 | F50: 40 | G50: 5 | I50: 31.7 | K50: =SUM(D50:J50) -> 105
A51: ALHUAY JUANA | B51: RI 32575 | C51: 46023 | H51: 10 | K51: =SUM(D51:J51) -> 10
B52: RI 32576 | C52: 46054 | F52: 56 | G52: 5 | K52: =SUM(D52:J52) -> 61
K53: =SUM(D53:J53) -> 0
K54: =SUM(D54:J54) -> 0
K55: =SUM(D55:J55) -> 0
K56: =SUM(D56:J56) -> 0
A57: TOTAL | D57: =SUM(D43:D56) -> 145.5 | E57: =SUM(E43:E56) -> 62 | F57: =SUM(F43:F56) -> 272 | G57: =SUM(G43:G56) -> 25 | H57: =SUM(H43:H56) -> 20 | I57: =SUM(I43:I56) -> 31.7 | J57: =SUM(J43:J56) -> 15 | K57: =SUM(K43:K56) -> 571.2
A60: TOTAL DE INGRESOS | K60: =+K22+K57 -> 643.9
A63: SRTA. FATIMA SIHUE
A64: COBRANZA SOCIOS
A65: COBRANZA INQUILINOS
A68: SRA. MARIA CUYA ARANGO
A69: COBRANZA DE BAÑO DEL 1ER PISO | K69: 413
A72: COBRANZA DE BAÑO DEL 2DO PISO
A74: TOTAL GENERAL DE INGRESOS | K74: =SUM(K60:K73) -> 1056.9
A76: EGRESOS DEL DIA 26-02-2026
A77: CAJA
A78: RESPONSABLE | B78: COMPROBANTE | C78: DETALLE | K78: TOTAL
A79: PODER JUDICIAL | B79: 8992 | C79: HABILITACION DE NOTIFICACION - CASO DIEGO | K79: 55
A80: PODER JUDICIAL | B80: 9970 | C80: DERECHO DE NOTIFICACION JUDICIAL - CASO DIEGO | K80: 11.4
A81: TUSE MANUEL | B81: RC 8553 | C81: REEMPLAZO DEL SR NICANOR PARA LA LIMPIEZA DEL MERCADO DE LOS DIAS 09/16/23 DE FEB. DEL 2026 | K81: 105
A82: HURTADO WILDER | B82: RC 8554 | C82: DAÑOS AL VEHICULO DE PLACA F3L-210 TOYOTA | K82: 100
A83: CADENA DE COMERCIO PERU S.A.C. OXXO | B83: F349-00000988 | C83: 1 SPORADE DE 1.5 LT PARA LA SESION DEL CONSEJO DE ADM. | K83: 5.5
A84: SALDAÑA JESSICA | B84: 996 | C84: 1 AGUA CIELO DE 2.5 LT PARA LA SESION DEL CONSEJO DE ADM | K84: 3
B85: 997 | C85: 1 RITZ TACO PARA LA SESION DEL CONSEJO DE ADM | K85: 2
A86: TRIGO DE ORO | B86: FA01-00012640 | C86: PAN+JAMON+QUESO PARA LA SESION DEL CONSEJO DE ADM. | K86: 33.3
A87: SOTO MARIA | B87: RC 8555 | C87: PREVISION SOCIAL POR SALUD A LA SOCIA SOTO MARIA | K87: 200
A92: TOTAL DE EGRESOS | K92: =SUM(K79:K91) -> 515.2
A95: RESUMEN
A96: TOTAL GENERAL | B96: =+K74 -> 1056.9
A97: TOTAL DE EGRESOS | B97: =+K92 -> 515.2
A98: SALDO | B98: =++B96-B97 -> 541.7

Sheet 27-02-2026
A1: INGRESOS DEL DIA 27-02-2026
A3: INQUILINO | B3: COMPROBANTE | C3: DETALLE | D3: LUZ | E3: AGUA | F3: ALQUILER | G3: ESPACIO | H3: PARQUEO | I3: TICKET | K3: TOTAL
A4: JOSE | B4: TK 50779 | C4: 46054 | I4: 10 | K4: =SUM(D4:J4) -> 10
A5: SANCHEZ DIANA | B5: EB01-6922 | C5: 46054 | F5: 1000 | K5: =SUM(D5:J5) -> 1000
A6: IDALINA MONTENEGRO BAUTISTA | B6: EB01-6923 | C6: 46023 | F6: 300 | K6: =SUM(D6:J6) -> 300
A7: MARGARITA JUANA GOMERO DULANTO | B7: EB01-6925 | C7: 46054 | F7: 400 | K7: =SUM(D7:J7) -> 400
A8: DURAND BLANCA | B8: EB01-6926 | C8: 46054 | F8: 550 | K8: =SUM(D8:J8) -> 550
A9: PARQUEO | B9: EB01-6928 | C9: 46054 | H9: 62 | K9: =SUM(D9:J9) -> 62
K10: =SUM(D10:J10) -> 0
K11: =SUM(D11:J11) -> 0
K12: =SUM(D12:J12) -> 0
A13: YUPANQUI SAYDA | B13: RII 3273 | C13: 46023 | D13: 100 | K13: =SUM(D13:J13) -> 100
K14: =SUM(D14:J14) -> 0
K15: =SUM(D15:J15) -> 0
K16: =SUM(D16:J16) -> 0
K17: =SUM(D17:J17) -> 0
K18: =SUM(D18:J18) -> 0
K19: =SUM(D19:J19) -> 0
A20: TOTAL | D20: =SUM(D4:D19) -> 100 | E20: =SUM(E4:E19) -> 0 | F20: =SUM(F4:F19) -> 2250 | G20: =SUM(G4:G19) -> 0 | H20: =SUM(H4:H19) -> 62 | I20: =SUM(I4:I19) -> 10 | K20: =SUM(K4:K19) -> 2422
A22: BBVA
A23: INQUILINOS | B23: COMPROBANTE | C23: DETALLE | D23: LUZ | E23: AGUA | F23: ALQUILER | G23: ESPACIO | H23: DEPOSITO | I23: TICKET | K23: TOTAL
A24: MARGARITA JUANA GOMERO DULANTO | B24: EB01-6924 | C24: 46054 | F24: 100 | K24: =SUM(D24:I24) -> 100
B25: RII 3272 | C25: 46023 | D25: 38.2 | E25: 3 | K25: =SUM(D25:I25) -> 41.2
A26: YUPANQUI SAYDA | B26: RII 3274 | C26: 46023 | D26: 127.6 | E26: 3 | K26: =SUM(D26:I26) -> 130.6
K27: =SUM(D27:I27) -> 0 | M27: TOTAL QR | N27: =K28+K36 -> 332.8
A28: TOTAL | K28: =SUM(K24:K27) -> 271.8
A30: BBVA
A31: SOCIOS | B31: RECIBO DE SERVICIO | C31: DETALLE | D31: LUZ | E31: AGUA | F31: G. ADM | G31: P. SOCIAL | H31: DEPOSITO | I31: P.S X FALLECIMIENTO | K31: TOTAL
A32: CERDA CARMEN | B32: RI 32586 | C32: 46054 | F32: 56 | G32: 5 | K32: =SUM(D32:I32) -> 61
K33: =SUM(D33:I33) -> 0
K34: =SUM(D34:I34) -> 0
K35: =SUM(D35:I35) -> 0
A36: TOTAL | K36: =SUM(K32:K35) -> 61
A40: SOCIO | B40: RECIBO DE SERVICIO | C40: DETALLE | D40: LUZ | E40: AGUA | F40: G. ADM | G40: P. SOCIAL | H40: P.S X FALLECIMIENTO | I40: MULTA POR CAPACITACION | J40: DEPOSITO | K40: TOTAL
A41: LUJAN JUAN | B41: RI 32577 | C41: 45992 | D41: 100.7 | E41: 20.9 | K41: =SUM(D41:J41) -> 121.6
C42: 46023 | D42: 96.6 | E42: 22.9 | I42: 28.3 | K42: =SUM(D42:J42) -> 147.8
A43: PAREDES FLORES OSCAR | B43: RI 32578 | C43: 46023 | F43: 60 | G43: 5 | K43: =SUM(D43:J43) -> 65
C44: 46054 | F44: 56 | G44: 5 | K44: =SUM(D44:J44) -> 61
A45: PRADO ZOZIMA | B45: RI 32579 | C45: 46023 | D45: 76.5 | E45: 5 | F45: 60 | G45: 5 | H45: 10 | K45: =SUM(D45:J45) -> 156.5
A46: MARIN HUAMAN MARIA YNES | B46: RI 32580 | C46: 46023 | D46: 76.5 | E46: 5 | F46: 60 | G46: 5 | K46: =SUM(D46:J46) -> 146.5
A47: CHOQUEHUAMANI CEFERINO | B47: RI 32581 | C47: 46023 | F47: 44.3 | G47: 5 | K47: =SUM(D47:J47) -> 49.3
A48: QUISPE LUCIANO | B48: RI 32582 | C48: 46023 | D48: 38.3 | E48: 5 | K48: =SUM(D48:J48) -> 43.3
A49: CARTAGENA BENJAMIN | B49: RI 32583 | C49: 45992 | D49: 11.4 | E49: 25.5 | K49: =SUM(D49:J49) -> 36.9
C50: 46023 | D50: 11.2 | E50: 23.1 | K50: =SUM(D50:J50) -> 34.3
A51: CARTAGENA ALVARO | B51: RI 32584 | C51: 45992 | J51: 200 | K51: =SUM(D51:J51) -> 200
C52: 46023 | J52: 200 | K52: =SUM(D52:J52) -> 200
A53: VILCHEZ LOURDES | B53: RI 32585 | C53: 45992 | D53: 660.3 | E53: 57.1 | J53: 200 | K53: =SUM(D53:J53) -> 917.4
C54: 46023 | D54: 727.2 | E54: 69.3 | J54: 200 | K54: =SUM(D54:J54) -> 996.5
K55: =SUM(D55:J55) -> 0
K56: =SUM(D56:J56) -> 0
K57: =SUM(D57:J57) -> 0
K58: =SUM(D58:J58) -> 0
A59: TOTAL | D59: =SUM(D41:D58) -> 1798.7 | E59: =SUM(E41:E58) -> 233.8 | F59: =SUM(F41:F58) -> 280.3 | G59: =SUM(G41:G58) -> 25 | H59: =SUM(H41:H58) -> 10 | I59: =SUM(I41:I58) -> 28.3 | J59: =SUM(J41:J58) -> 800 | K59: =SUM(K41:K58) -> 3176.1
A62: TOTAL DE INGRESOS | K62: =+K20+K59 -> 5598.1
A65: SRTA. FATIMA SIHUE
A66: COBRANZA SOCIOS | K66: 2069
A67: COBRANZA INQUILINOS | K67: 2650 | L67: =K66+K67 -> 4719
L68: 100
L69: =L67+L68 -> 4819 | M69: 100 | N69: 23 | O69: =N69*M69 -> 2300
A70: SRA. MARIA CUYA ARANGO | M70: 50 | N70: 33 | O70: =N70*M70 -> 1650
A71: COBRANZA DE BAÑO DEL 1ER PISO | K71: 452 | M71: 20 | N71: 38 | O71: =N71*M71 -> 760
M72: 10 | N72: 10 | O72: =N72*M72 -> 100
M73: 5 | N73: 1 | O73: =N73*M73 -> 5
A74: COBRANZA DE BAÑO DEL 2DO PISO | M74: 1 | N74: 3 | O74: =N74*M74 -> 3
M75: 0.5 | N75: 2 | O75: =N75*M75 -> 1
A76: TOTAL GENERAL DE INGRESOS | K76: =SUM(K62:K75) -> 10769.1 | O76: =SUM(O69:O75) -> 4819
A78: EGRESOS DEL DIA 27-02-2026
A79: CAJA
A80: RESPONSABLE | B80: COMPROBANTE | C80: DETALLE | K80: TOTAL
A81: SAAVEDRA LUIS | B81: 14627 | C81: 1 PAR DE PILAS AAA PARA EL TECLADO DE LA SECRETARIA DE LA OFICINA DE ADM | K81: 2.5
B82: 14627 | C82: CARTULINAS Y PLUMONES PARA HACER CARTELES POR INCUMPLIMIENTO DE LOS DEPOSITOS | K82: 11.5
A83: PATRICIO PALOMINO MIGUEL ANGEL | B83: E001-17 | C83: A CUENTA DE 1 MUEBLE PARA LA DOCUMENTACION DE LA OFICINA DE ADM. | K83: 700
A84: CAYRO CARI RUBEN | B84: E001- 200 | C84: ASESORIA LEGAL Y CONSULTORIA DEL MES DE FEBRERO 2026 | K84: 1840
A95: TOTAL DE EGRESOS | K95: =SUM(K81:K94) -> 2554
A98: RESUMEN
A99: TOTAL GENERAL | B99: =+K76 -> 10769.1
A100: TOTAL DE EGRESOS | B100: =+K95 -> 2554
A101: SALDO | B101: =++B99-B100 -> 8215.1

Sheet 28-02-2026
A1: INGRESOS DEL DIA 28-02-2026
A3: INQUILINO | B3: COMPROBANTE | C3: DETALLE | D3: LUZ | E3: AGUA | F3: ALQUILER | G3: ESPACIO | H3: PARQUEO | I3: TICKET | J3: TOTAL
A4: JOSE | B4: TK 50780 | C4: 46054 | I4: 10 | J4: =SUM(D4:I4) -> 10
A5: INVERSIONES MUYA S.A.C. | B5: E001-324 | C5: 46054 | G5: 30 | J5: =SUM(D5:I5) -> 30
J6: =SUM(D6:I6) -> 0
A7: ALVAREZ EDGAR | B7: EB01-6929 | C7: 46023 | F7: 200 | J7: =SUM(D7:I7) -> 200
C8: 46054 | F8: 300 | J8: =SUM(D8:I8) -> 300
J9: =SUM(D9:I9) -> 0
J10: =SUM(D10:I10) -> 0
J11: =SUM(D11:I11) -> 0
J12: =SUM(D12:I12) -> 0
J13: =SUM(D13:I13) -> 0
J14: =SUM(D14:I14) -> 0
J15: =SUM(D15:I15) -> 0
J16: =SUM(D16:I16) -> 0
J17: =SUM(D17:I17) -> 0
J18: =SUM(D18:I18) -> 0
J19: =SUM(D19:I19) -> 0
J20: =SUM(D20:I20) -> 0
J21: =SUM(D21:I21) -> 0
A22: TOTAL | D22: =SUM(D4:D21) -> 0 | E22: =SUM(E4:E21) -> 0 | F22: =SUM(F4:F21) -> 500 | G22: =SUM(G4:G21) -> 30 | H22: =SUM(H4:H21) -> 0 | I22: =SUM(I4:I21) -> 10 | J22: =SUM(J4:J21) -> 540
A24: BBVA
A25: INQUILINOS | B25: COMPROBANTE | C25: DETALLE | D25: LUZ | E25: AGUA | F25: ALQUILER | G25: ESPACIO | H25: DEPOSITO | I25: TICKET | J25: TOTAL
J26: =SUM(D26:I26) -> 0
J27: =SUM(D27:I27) -> 0
J28: =SUM(D28:I28) -> 0
J29: =SUM(D29:I29) -> 0 | L29: TOTAL QR | M29: =J30+J38 -> 0
A30: TOTAL | J30: =SUM(J26:J29) -> 0
A32: BBVA
A33: SOCIOS | B33: RECIBO DE SERVICIO | C33: DETALLE | D33: LUZ | E33: AGUA | F33: G. ADM | G33: P. SOCIAL | H33: DEPOSITO | I33: P.S X FALLECIMIENTO | J33: TOTAL
J34: =SUM(D34:I34) -> 0
J35: =SUM(D35:I35) -> 0
J36: =SUM(D36:I36) -> 0
J37: =SUM(D37:I37) -> 0
A38: TOTAL | J38: =SUM(J34:J37) -> 0
A42: SOCIO | B42: RECIBO DE SERVICIO | C42: DETALLE | D42: LUZ | E42: AGUA | F42: G. ADM | G42: P. SOCIAL | H42: P.S X FALLECIMIENTO | I42: DEPOSITO | J42: TOTAL
A43: BERNAOLA FLORENCIA | B43: RI 32587 | C43: 46054 | F43: 56 | G43: 5 | J43: =SUM(D43:I43) -> 61
A44: CHIRINOS MARIA | B44: RI 32588 | C44: 45992 | D44: 118.7 | E44: 12.9 | J44: =SUM(D44:I44) -> 131.6
J45: =SUM(D45:I45) -> 0
J46: =SUM(D46:I46) -> 0
J47: =SUM(D47:I47) -> 0
J48: =SUM(D48:I48) -> 0
J49: =SUM(D49:I49) -> 0
J50: =SUM(D50:I50) -> 0
J51: =SUM(D51:I51) -> 0
J52: =SUM(D52:I52) -> 0
J53: =SUM(D53:I53) -> 0
J54: =SUM(D54:I54) -> 0
J55: =SUM(D55:I55) -> 0
J56: =SUM(D56:I56) -> 0
A57: TOTAL | D57: =SUM(D43:D56) -> 118.7 | E57: =SUM(E43:E56) -> 12.9 | F57: =SUM(F43:F56) -> 56 | G57: =SUM(G43:G56) -> 5 | H57: =SUM(H43:H56) -> 0 | I57: =SUM(I43:I56) -> 0 | J57: =SUM(J43:J56) -> 192.6
A60: TOTAL DE INGRESOS | J60: =+J22+J57 -> 732.6
A63: SRTA. FATIMA SIHUE
A64: COBRANZA SOCIOS
A65: COBRANZA INQUILINOS
A68: SRA. MARIA CUYA ARANGO
A69: COBRANZA DE BAÑO DEL 1ER PISO | J69: 630
A72: COBRANZA DE BAÑO DEL 2DO PISO
A74: TOTAL GENERAL DE INGRESOS | J74: =SUM(J60:J73) -> 1362.6
A76: EGRESOS DEL DIA 28-02-2026
A77: CAJA
A78: RESPONSABLE | B78: COMPROBANTE | C78: DETALLE | J78: TOTAL
A79: CAMAN HUABLOCHO LLENY SANDYBELL | B79: E001- 546 | C79: ASESORIA CONTABLE DEL MES DE FEBRERO 2026 | J79: 1900
A80: CAHUANA MATIAS | B80: 856246 | C80: SUELDO DEL MES DE FEBRERO 2026 | J80: 820.3
A81: PALOMINO SANTOS | B81: 858668 | C81: SUELDO DEL MES DE FEBRERO 2026 | J81: 1288.7
A82: POMACANCHARI NICANOR | B82: 861204 | C82: SUELDO DEL MES DE FEBRERO 2026 | J82: 1315.1
A83: TUEROS PRUDENCIO | B83: 863347 | C83: SUELDO DEL MES DE FEBRERO 2026 | J83: 1457.4
A84: CUYA MARIA | B84: 890647 | C84: SUELDO DEL MES DE FEBRERO 2026 | J84: 1143.7
A85: HURTADO WILDER | B85: 892094 | C85: SUELDO DEL MES DE FEBRERO 2026 | J85: 962.3
A86: VILLANUEVA TATIH | B86: 893661 | C86: SUELDO DEL MES DE FEBRERO 2026 | J86: 680
A87: SIHUE FATIMA | B87: 894955 | C87: SUELDO DEL MES DE FEBRERO 2026 | J87: 919.5
A88: PANQUIEZ DENIS | B88: 896436 | C88: SUELDO DEL MES DE FEBRERO 2026 | J88: 1108.7
A91: TOTAL DE EGRESOS | J91: =SUM(J79:J90) -> 11595.7
A94: RESUMEN
A95: TOTAL GENERAL | B95: =+J74 -> 1362.6
A96: TOTAL DE EGRESOS | B96: =+J91 -> 11595.7
A97: SALDO | B97: =++B95-B96 -> -10233.1

Sheet ARQUEO RESUMIDO
B2: OFICINA | E2: COBRADOR | H2: 46054
B3: SOCIOS | C3: INQUILINOS | D3: TOTAL | E3: SOCIOS | F3: INQUILINOS | G3: TOTAL | H3: SS.HH | I3: INGRESOS | J3: EGRESOS | K3: SALDO | L3: EGRESOS BOVEDA | M3: CAJA | N3: BOVEDA SANTO ROSA | O3: ACTIVIDAD SANTA ROSA | P3: BOVEDA SR. OSCAR | Q3: DIEGO | R3: DEPOSITO AL BCO | S3: BOVEDA TOTAL | T3: ACUMULADO | U3: DOLARES | W3: PAGO CON QR
A4: SAL. INI. | B4: 2026 | M4: 21744.7 | N4: 1430.1 | O4: 9152.6 | P4: 44358.3 | S4: =SUM(P4+O4+N4) -> 54941 | T4: =+M4+S4 -> 76685.7 | U4: 5266
A5: 46054 | B5: =+'01-02-2026'!J57 -> 0 | C5: =+'01-02-2026'!K57 -> 0 | D5: =B5+C5 -> 0 | H5: =+'01-02-2026'!J69 -> 444 | I5: =SUM(D5+G5+H5) -> 444 | J5: =+'02-02-2026'!J107 -> 0 | K5: =I5-J5 -> 444 | M5: =M4+K5 -> 22188.7 | S5: =SUM(P5+O5+N5)-L5+S4 -> 54941 | T5: =+M5+S5 -> 77129.7 | W5: =+'[1]01-01-2026'!M30 -> 0
A6: 46055 | B6: =+'02-02-2026'!J63 -> 187.5 | C6: =+'02-02-2026'!J28 -> 3988.5 | D6: =B6+C6 -> 4176 | H6: =+'02-02-2026'!J75 -> 450 | I6: =SUM(D6+G6+H6) -> 4626 | J6: =+'02-02-2026'!J106 -> 13074.9 | K6: =I6-J6 -> -8448.9 | M6: =M5+K6 -> 13739.8 | S6: =SUM(P6+O6+N6)-L6+S5 -> 54941 | T6: =+M6+S6 -> 68680.8 | W6: =+'[1]01-01-2026'!M31 -> 0
A7: 46056 | B7: =+'03-02-2026'!J58 -> 786.5 | C7: =+'03-02-2026'!J22 -> 765 | D7: =B7+C7 -> 1551.5 | H7: =+'03-02-2026'!J70 -> 465.5 | I7: =SUM(D7+G7+H7) -> 2017 | J7: =+'03-02-2026'!J93 -> 696 | K7: =I7-J7 -> 1321 | M7: =M6+K7-P7 -> 5060.8 | P7: 10000 | S7: =SUM(P7+O7+N7)-L7+S6 -> 64941 | T7: =+M7+S7 -> 70001.8 | W7: =+'[1]01-01-2026'!M32 -> 0
A8: 46057 | B8: =+'04-02-2026'!J89 -> 1804.2 | C8: =+'04-02-2026'!J27 -> 1857.1 | D8: =B8+C8 -> 3661.3 | H8: =+'04-02-2026'!J101 -> 474 | I8: =SUM(D8+G8+H8) -> 4135.3 | J8: =+'04-02-2026'!J124 -> 1395 | K8: =I8-J8 -> 2740.3 | M8: =M7+K8-P8 -> 3801.1 | P8: 4000 | S8: =SUM(P8+O8+N8)-L8+S7 -> 68941 | T8: =+M8+S8 -> 72742.1 | W8: =+'[1]01-01-2026'!M33 -> 0
A9: 46058 | B9: =+'05-02-2026'!J58 -> 700.8 | C9: =+'05-02-2026'!J23 -> 1176 | D9: =B9+C9 -> 1876.8 | H9: =+'05-02-2026'!J70 -> 472 | I9: =SUM(D9+G9+H9) -> 2348.8 | J9: =+'05-02-2026'!J92 -> 508.5 | K9: =I9-J9 -> 1840.3 | M9: =M8+K9 -> 5641.4 | N9: =110.6-10 -> 100.6 | S9: =SUM(P9+O9+N9)-L9+S8 -> 69041.6 | T9: =+M9+S9 -> 74683 | W9: =+'[1]01-01-2026'!M34 -> 0
A10: 46059 | B10: =+'06-02-2026'!J58 -> 1294.2 | C10: =+'06-02-2026'!J23 -> 1950.5 | D10: =B10+C10 -> 3244.7 | E10: =+'06-02-2026'!J65 -> 1100 | F10: =+'06-02-2026'!J66 -> 2040 | G10: =E10+F10 -> 3140 | H10: =+'06-02-2026'!J70 -> 488.5 | I10: =SUM(D10+G10+H10) -> 6873.2 | J10: =+'06-02-2026'!J93 -> 430 | K10: =I10-J10 -> 6443.2 | M10: =M9+K10 -> 12084.6 | S10: =SUM(P10+O10+N10)-L10+S9 -> 69041.6 | T10: =+M10+S10 -> 81126.2 | W10: =+'[1]01-01-2026'!M35 -> 0
A11: 46060 | B11: =+'07-02-2026'!J58 -> 130 | C11: =+'07-02-2026'!J23 -> 1006 | D11: =B11+C11 -> 1136 | H11: =+'07-02-2026'!J70 -> 505.5 | I11: =SUM(D11+G11+H11) -> 1641.5 | J11: =+'07-02-2026'!J93 -> 166 | K11: =I11-J11 -> 1475.5 | M11: =M10+K11 -> 13560.1 | S11: =SUM(P11+O11+N11)-L11+S10 -> 69041.6 | T11: =+M11+S11 -> 82601.7 | W11: =+'[1]01-01-2026'!M36 -> 0 | Z11: FATIMA
A12: 46061 | B12: =+'07-02-2026'!J60 -> 0 | C12: =+'08-02-2026'!J22 -> 20 | D12: =B12+C12 -> 20 | H12: =+'08-02-2026'!J69 -> 460 | I12: =SUM(D12+G12+H12) -> 480 | J12: =+'08-02-2026'!J95 -> 0 | K12: =I12-J12 -> 480 | M12: =M11+K12 -> 14040.1 | S12: =SUM(P12+O12+N12)-L12+S11 -> 69041.6 | T12: =+M12+S12 -> 83081.7 | W12: =+'[1]01-01-2026'!M37 -> 0 | AA12: 200 | AB12: =Z12*AA12 -> 0
A13: 46062 | B13: =+'09-02-2026'!J58 -> 692.4 | C13: =+'09-02-2026'!J23 -> 220 | D13: =B13+C13 -> 912.4 | H13: =+'09-02-2026'!J70 -> 323 | I13: =SUM(D13+G13+H13) -> 1235.4 | J13: =+'09-02-2026'!J91 -> 3181.5 | K13: =I13-J13 -> -1946.1 | M13: =M12+K13-P13 -> 5094 | P13: 7000 | S13: =SUM(P13+O13+N13)-L13+S12 -> 76041.6 | T13: =+M13+S13 -> 81135.6 | W13: =+'[1]01-01-2026'!M38 -> 0 | AA13: 100 | AB13: =Z13*AA13 -> 0
A14: 46063 | B14: =+'10-02-2026'!J63 -> 427.8 | C14: =+'10-02-2026'!J24 -> 2269.5 | D14: =B14+C14 -> 2697.3 | H14: =+'10-02-2026'!J75 -> 531.5 | I14: =SUM(D14+G14+H14) -> 3228.8 | J14: =+'10-02-2026'!J98 -> 1182.6 | K14: =I14-J14 -> 2046.2 | M14: =M13+K14 -> 7140.2 | S14: =SUM(P14+O14+N14)-L14+S13 -> 76041.6 | T14: =+M14+S14 -> 83181.8 | W14: =+'[1]01-01-2026'!M39 -> 0 | Z14: 55 | AA14: 50 | AB14: =Z14*AA14 -> 2750
A15: 46064 | B15: =+'11-02-2026'!J84 -> 1993.4 | C15: =+'11-02-2026'!J25 -> 767 | D15: =B15+C15 -> 2760.4 | H15: =+'11-02-2026'!J96 -> 477 | I15: =SUM(D15+G15+H15) -> 3237.4 | J15: =+'11-02-2026'!J119 -> 14 | K15: =I15-J15 -> 3223.4 | M15: =M14+K15-P15 -> 7163.6 | P15: 3200 | S15: =SUM(P15+O15+N15)-L15+S14 -> 79241.6 | T15: =+M15+S15 -> 86405.2 | W15: =+'[1]01-01-2026'!M40 -> 0 | Z15: 8 | AA15: 20 | AB15: =Z15*AA15 -> 160
A16: 46065 | B16: =+'12-02-2026'!J57 -> 43.6 | C16: =+'12-02-2026'!J22 -> 1726.5 | D16: =B16+C16 -> 1770.1 | H16: =+'12-02-2026'!J69 -> 455 | I16: =SUM(D16+G16+H16) -> 2225.1 | J16: =+'12-02-2026'!J92 -> 1514.5 | K16: =I16-J16 -> 710.6 | M16: =M15+K16 -> 7874.2 | S16: =SUM(P16+O16+N16)-L16+S15 -> 79241.6 | T16: =+M16+S16 -> 87115.8 | W16: =+'[1]01-01-2026'!M41 -> 0 | Z16: 22 | AA16: 10 | AB16: =Z16*AA16 -> 220
A17: 46066 | B17: =+'13-02-2026'!J58 -> 1114 | C17: =+'13-02-2026'!J23 -> 148 | D17: =B17+C17 -> 1262 | E17: =+'13-02-2026'!J65 -> 1428 | F17: =+'13-02-2026'!J66 -> 2385 | G17: =E17+F17 -> 3813 | H17: =+'13-02-2026'!J70 -> 447.5 | I17: =SUM(D17+G17+H17) -> 5522.5 | J17: =+'13-02-2026'!J93 -> 78 | K17: =I17-J17 -> 5444.5 | M17: =M16+K17 -> 13318.7 | R17: 30000 | S17: =SUM(P17+O17+N17)-L17+S16-R17 -> 49241.6 | T17: =+M17+S17 -> 62560.3 | W17: =+'[1]01-01-2026'!M42 -> 0 | AA17: 1 | AB17: =Z17*AA17 -> 0
A18: 46067 | B18: =+'14-02-2026'!J59 -> 0 | C18: =+'14-02-2026'!J23 -> 418 | D18: =B18+C18 -> 418 | H18: =+'14-02-2026'!J70 -> 724.5 | I18: =SUM(D18+G18+H18) -> 1142.5 | J18: =+'14-02-2026'!J92 -> 5000 | K18: =I18-J18 -> -3857.5 | M18: =M17+K18 -> 9461.2 | S18: =SUM(P18+O18+N18)-L18+S17 -> 49241.6 | T18: =+M18+S18 -> 58702.8 | W18: =+'[1]01-01-2026'!M43 -> 0 | AA18: 1 | AB18: =Z18*AA18 -> 0
A19: 46068 | B19: =+'15-02-2026'!J60 -> 0 | C19: =+'15-02-2026'!J24 -> 0 | D19: =B19+C19 -> 0 | H19: =+'15-02-2026'!J69 -> 216 | I19: =SUM(D19+G19+H19) -> 216 | J19: =+'15-02-2026'!J93 -> 0 | K19: =I19-J19 -> 216 | M19: =M18+K19 -> 9677.2 | S19: =SUM(P19+O19+N19)-L19+S18 -> 49241.6 | T19: =+M19+S19 -> 58918.8 | W19: =+'[1]01-01-2026'!M44 -> 0 | Y19: SENCILLO | Z19: 180 | AA19: 1 | AB19: =Z19*AA19 -> 180
A20: 46069 | B20: =+'16-02-2026'!J58 -> 758.4 | C20: =+'16-02-2026'!J21 -> 189.8 | D20: =B20+C20 -> 948.2 | H20: =+'16-02-2026'!J70 -> 323 | I20: =SUM(D20+G20+H20) -> 1271.2 | J20: =+'16-02-2026'!J90 -> 80 | K20: =I20-J20 -> 1191.2 | M20: =M19+K20-P20 -> 6868.4 | P20: 4000 | S20: =SUM(P20+O20+N20)-L20+S19 -> 53241.6 | T20: =+M20+S20 -> 60110 | W20: =+'[1]01-01-2026'!M45 -> 0 | Y20: MONEDAS DE 50 | Z20: 200 | AA20: 1 | AB20: =Z20*AA20 -> 200
A21: 46070 | B21: =+'17-02-2026'!J61 -> 861.2 | C21: =+'17-02-2026'!J22 -> 1330 | D21: =B21+C21 -> 2191.2 | H21: =+'17-02-2026'!J73 -> 437.5 | I21: =SUM(D21+G21+H21) -> 2628.7 | J21: =+'17-02-2026'!J93 -> 155 | K21: =I21-J21 -> 2473.7 | M21: =M20+K21 -> 9342.1 | S21: =SUM(P21+O21+N21)-L21+S20 -> 53241.6 | T21: =+M21+S21 -> 62583.7 | W21: =+'[1]01-01-2026'!M46 -> 0 | Y21: BAÑO | Z21: 300 | AA21: 1 | AB21: =Z21*AA21 -> 300
A22: 46071 | B22: =+'18-02-2026'!J74 -> 1289.4 | C22: =+'18-02-2026'!J29 -> 2103.6 | D22: =B22+C22 -> 3393 | H22: =+'18-02-2026'!J86 -> 429.5 | I22: =SUM(D22+G22+H22) -> 3822.5 | J22: =+'18-02-2026'!J109 -> 2329.4 | K22: =I22-J22 -> 1493.1 | M22: =M21+K22-P22 -> 5835.2 | P22: 5000 | S22: =SUM(P22+O22+N22)-L22+S21 -> 58241.6 | T22: =+M22+S22 -> 64076.8 | W22: =+'[1]01-01-2026'!M47 -> 0 | Y22: TATIANA | AA22: 1 | AB22: =Z22*AA22 -> 0
A23: 46072 | B23: =+'19-02-2026'!J57 -> 107.4 | C23: =+'19-02-2026'!J22 -> 507.3 | D23: =B23+C23 -> 614.7 | H23: =+'19-02-2026'!J69 -> 463.5 | I23: =SUM(D23+G23+H23) -> 1078.2 | J23: =+'19-02-2026'!J90 -> 691 | K23: =I23-J23 -> 387.2 | M23: =M22+K23 -> 6222.4 | S23: =SUM(P23+O23+N23)-L23+S22 -> 58241.6 | T23: =+M23+S23 -> 64464 | W23: =+'[1]01-01-2026'!M48 -> 0 | AB23: =SUM(AB12:AB22) -> 3810
A24: 46073 | B24: =+'20-02-2026'!J59 -> 58.9 | C24: =+'20-02-2026'!J22 -> 334.4 | D24: =B24+C24 -> 393.3 | E24: =+'20-02-2026'!J66 -> 1472 | F24: =+'20-02-2026'!J67 -> 1975 | G24: =E24+F24 -> 3447 | H24: =+'20-02-2026'!J71 -> 408.5 | I24: =SUM(D24+G24+H24) -> 4248.8 | J24: =+'20-02-2026'!J94 -> 1338.2 | K24: =I24-J24 -> 2910.6 | M24: =M23+K24-P24 -> 6133 | P24: 3000 | S24: =SUM(P24+O24+N24)-L24+S23 -> 61241.6 | T24: =+M24+S24 -> 67374.6 | W24: =+'[1]01-01-2026'!M49 -> 0
A25: 46074 | B25: =+'21-02-2026'!J57 -> 371.6 | C25: =+'21-02-2026'!J22 -> 737.1 | D25: =B25+C25 -> 1108.7 | H25: =+'21-02-2026'!J69 -> 728.5 | I25: =SUM(D25+G25+H25) -> 1837.2 | J25: =+'21-02-2026'!J92 -> 0 | K25: =I25-J25 -> 1837.2 | M25: =M24+K25 -> 7970.2 | S25: =SUM(P25+O25+N25)-L25+S24-R25 -> 61241.6 | T25: =+M25+S25 -> 69211.8 | W25: =+'[1]01-01-2026'!M50 -> 0
A26: 46075 | B26: =+'22-02-2026'!J58 -> 0 | C26: =+'22-02-2026'!J23 -> 0 | D26: =B26+C26 -> 0 | H26: =+'22-02-2026'!J69 -> 145 | I26: =SUM(D26+G26+H26) -> 145 | J26: =+'22-02-2026'!J93 -> 0 | K26: =I26-J26 -> 145 | M26: =M25+K26 -> 8115.2 | S26: =SUM(P26+O26-N26)-L26+S25 -> 61241.6 | T26: =+M26+S26 -> 69356.8 | W26: =+'[1]01-01-2026'!M51 -> 0
A27: 46076 | B27: =+'23-02-2026'!J70 -> 5707.7 | C27: =+'23-02-2026'!J22 -> 1248 | D27: =B27+C27 -> 6955.7 | H27: =+'23-02-2026'!J82 -> 319 | I27: =SUM(D27+G27+H27) -> 7274.7 | J27: =+'23-02-2026'!J105 -> 80 | K27: =I27-J27 -> 7194.7 | M27: =M26+K27-P27 -> 8309.9 | P27: 7000 | S27: =SUM(P27+O27+N27)-L27+S26 -> 68241.6 | T27: =+M27+S27 -> 76551.5 | W27: =+'[1]01-01-2026'!M52 -> 0 | AB27: =M35-AB23 -> 630
A28: 46077 | B28: =+'24-02-2026'!J57 -> 1209.2 | C28: =+'24-02-2026'!J22 -> 75.2 | D28: =B28+C28 -> 1284.4 | H28: =+'24-02-2026'!J69 -> 414 | I28: =SUM(D28+G28+H28) -> 1698.4 | J28: =+'24-02-2026'!J92 -> 35.2 | K28: =I28-J28 -> 1663.2 | M28: =M27+K28 -> 9973.1 | S28: =SUM(P28+O28+N28)-L28+S27 -> 68241.6 | T28: =+M28+S28 -> 78214.7 | W28: =+'[1]01-01-2026'!M53 -> 0
A29: 46078 | B29: =+'25-02-2026'!J64 -> 279.6 | C29: =+'25-02-2026'!J29 -> 1375.6 | D29: =B29+C29 -> 1655.2 | H29: =+'25-02-2026'!J76 -> 426 | I29: =SUM(D29+G29+H29) -> 2081.2 | J29: =+'25-02-2026'!J99 -> 538 | K29: =I29-J29 -> 1543.2 | M29: =M28+K29 -> 11516.3 | N29: =209.2-25 -> 184.2 | S29: =SUM(P29+O29+N29)-L29+S28 -> 68425.8 | T29: =+M29+S29 -> 79942.1 | W29: =+'[1]01-01-2026'!M54 -> 0
A30: 46079 | B30: =+'26-02-2026'!K57 -> 571.2 | C30: =+'26-02-2026'!K22 -> 72.7 | D30: =B30+C30 -> 643.9 | H30: =+'26-02-2026'!K69 -> 413 | I30: =SUM(D30+G30+H30) -> 1056.9 | J30: =+'26-02-2026'!K92 -> 515.2 | K30: =I30-J30 -> 541.7 | M30: =M29+K30 -> 12058 | S30: =SUM(P30+O30+N30)-L30+S29 -> 68425.8 | T30: =+M30+S30 -> 80483.8 | W30: =+'[1]01-01-2026'!M55 -> 0
A31: 46080 | B31: =+'27-02-2026'!K59 -> 3176.1 | C31: =+'27-02-2026'!K20 -> 2422 | D31: =B31+C31 -> 5598.1 | E31: =+'27-02-2026'!K66 -> 2069 | F31: =+'27-02-2026'!K67 -> 2650 | G31: =E31+F31 -> 4719 | H31: =+'27-02-2026'!K71 -> 452 | I31: =SUM(D31+G31+H31) -> 10769.1 | J31: =+'27-02-2026'!K95 -> 2554 | K31: =I31-J31 -> 8215.1 | M31: =M30+K31 -> 20273.1 | S31: =SUM(P31+O31+N31)-L31+S30 -> 68425.8 | T31: =+M31+S31 -> 88698.9 | W31: =+'[1]01-01-2026'!M56 -> 0
A32: 46081 | B32: =+'28-02-2026'!J57 -> 192.6 | C32: =+'28-02-2026'!J22 -> 540 | D32: =B32+C32 -> 732.6 | H32: =+'28-02-2026'!J69 -> 630 | I32: =SUM(D32+G32+H32) -> 1362.6 | J32: =+'28-02-2026'!J91 -> 11595.7 | K32: =I32-J32 -> -10233.1 | M32: =M31+K32-P32 -> 4440 | P32: 5600 | S32: =SUM(P32+O32+N32)-L32+S31 -> 74025.8 | T32: =+M32+S32 -> 78465.8 | W32: =+'[1]01-01-2026'!M57 -> 0 | Y32: NUMERO | Z32: DENOMINACION
D33: =B33+C33 -> 0 | M33: =M32+K33 -> 4440 | S33: =SUM(P33+O33+N33)-L33+S32 -> 74025.8 | T33: =+M33+S33 -> 78465.8 | W33: =+'[1]01-01-2026'!M58 -> 0 | Y33: 11 | Z33: 5 | AA33: =+Y33*Z33 -> 55
D34: =B34+C34 -> 0 | M34: =M33+K34 -> 4440 | S34: =SUM(P34+O34+N34)-L34+S33 -> 74025.8 | T34: =+M34+S34 -> 78465.8 | W34: =+'[1]01-01-2026'!M59 -> 0 | Y34: 6 | Z34: 2 | AA34: =+Y34*Z34 -> 12
D35: =B35+C35 -> 0 | M35: =M34+K35 -> 4440 | S35: =SUM(P35+O35+N35)-L35+S34 -> 74025.8 | T35: =+M35+S35 -> 78465.8 | W35: =+'[1]01-01-2026'!M60 -> 0 | Y35: 35 | Z35: 1 | AA35: =+Y35*Z35 -> 35
B36: =SUM(B5:B35) -> 23757.7 | C36: =SUM(C5:C35) -> 27247.8 | D36: =SUM(D5:D35) -> 51005.5 | E36: =SUM(E5:E35) -> 6069 | F36: =SUM(F5:F35) -> 9050 | G36: =SUM(G5:G35) -> 15119 | H36: =SUM(H5:H35) -> 12523.5 | I36: =SUM(I5:I35) -> 78648 | ... K36: =SUM(K5:K35) -> 31495.3 | M36: =I36+M4-J36 -> 53240 | N36: =N4+N9+N29 -> 1714.9 | O36: =SUM(O4:O35) -> 9152.6 | P36: =SUM(P4:P35) -> 93158.3 | Q36: =SUM(Q4:Q35) -> 0 | R36: =SUM(R4:R35) -> 30000 | U36: =SUM(U4:U35) -> 5266 | W36: =SUM(W5:W35) -> 0 | Y36: 10 | Z36: 0.5 | AA36: =+Y36*Z36 -> 5
Y37: 10 | Z37: 0.2 | AA37: =+Y37*Z37 -> 2
Y38: 60 | Z38: 0.1 | AA38: =+Y38*Z38 -> 6
P39: =P36-R36 -> 63158.3
AA40: =SUM(AA33:AA39) -> 115
M41: =T35-M35 -> 74025.8 | AA41: 65
B42: CCI BBVA | C42: 011 338 000100019602 10 | AA42: =AA40+AA41 -> 180
B43: N DE CUENTA | C43: 0011 0338 0100019602 10
